{
  "type": "Feature",
  "properties": {
    "gn:admin1_code":"4.0",
    "gn:admin2_code":"TTT",
    "gn:admin3_code":"V05",
    "gn:admin4_code":"10014100001.0",
    "gn:asciiname":"Jiajinlin",
    "gn:country_code":"TW",
    "gn:dem":52,
    "gn:feature_class":"P",
    "gn:feature_code":"PPL",
    "gn:name":"Jiajinlin",
    "gn:population":0,
    "gn:timezone":"Asia/Taipei",
    "iso:country":"TW",
    "name:und_x_variant":[
        "Chia-ching-lin",
        "Chia-ching-lin-she",
        "Jiajinlin",
        "Chia-chin-lin"
    ],
    "name:zho_x_preferred":[
        "Chia-chin-lin-ts\u2019un"
    ],
    "name:zho_x_variant":[
        "\u52a0\u6d25\u6797"
    ],
    "wof:name":"Jiajinlin",
    "wof:placetype":"locality"
},
  "geometry": {"coordinates":[120.92306000000001,22.41639],"type":"Point"}
}