{
  "type": "Feature",
  "properties": {
    "gn:admin1_code":"4.0",
    "gn:admin2_code":"CYQ",
    "gn:admin3_code":"Q04",
    "gn:admin4_code":"10010040005.0",
    "gn:asciiname":"Hudi",
    "gn:country_code":"TW",
    "gn:dem":26,
    "gn:feature_class":"P",
    "gn:feature_code":"PPL",
    "gn:name":"Hudi",
    "gn:population":0,
    "gn:timezone":"Asia/Taipei",
    "iso:country":"TW",
    "name:und_x_variant":[
        "Hu-ti"
    ],
    "name:zho_x_preferred":[
        "\u6e56\u5e95"
    ],
    "wof:name":"Hudi",
    "wof:placetype":"locality"
},
  "geometry": {"coordinates":[120.43825,23.59426],"type":"Point"}
}