{
  "type": "Feature",
  "properties": {
    "gn:admin1_code":"04",
    "gn:admin2_code":"TNN",
    "gn:admin3_code":"R03",
    "gn:admin4_code":"67000030012.0",
    "gn:asciiname":"Banqizi",
    "gn:country_code":"TW",
    "gn:dem":415,
    "gn:feature_class":"P",
    "gn:feature_code":"PPL",
    "gn:name":"Banqizi",
    "gn:population":0,
    "gn:timezone":"Asia/Taipei",
    "iso:country":"TW",
    "name:und_x_variant":[
        "Bancizih",
        "Banqizi"
    ],
    "name:zho_x_preferred":[
        "\u534a\u5d0e\u4ed4"
    ],
    "name:zho_x_variant":[
        "Pan-ch\u2019i",
        "Pan-ch\u2019i-tzu"
    ],
    "wof:name":"Banqizi",
    "wof:placetype":"locality"
},
  "geometry": {"coordinates":[120.49306,23.33],"type":"Point"}
}