{
  "type": "Feature",
  "properties": {
    "gn:admin1_code":"4.0",
    "gn:admin2_code":"CYQ",
    "gn:admin3_code":"Q11",
    "gn:admin4_code":"10010110005.0",
    "gn:asciiname":"Zhenping",
    "gn:country_code":"TW",
    "gn:dem":12,
    "gn:feature_class":"P",
    "gn:feature_code":"PPL",
    "gn:name":"Zhenping",
    "gn:population":0,
    "gn:timezone":"Asia/Taipei",
    "iso:country":"TW",
    "name:ceb_x_preferred":[
        "Zhenping"
    ],
    "name:deu_x_preferred":[
        "Zhenping"
    ],
    "name:fra_x_preferred":[
        "Zhenping"
    ],
    "name:kor_x_preferred":[
        "\uc804\ud551\ud604"
    ],
    "name:nor_x_preferred":[
        "Zhenping"
    ],
    "name:rus_x_preferred":[
        "\u0427\u0436\u044d\u043d\u044c\u043f\u0438\u043d"
    ],
    "name:swe_x_preferred":[
        "Zhenping"
    ],
    "name:und_x_variant":[
        "Chen-p\u2019ing"
    ],
    "wof:name":"Zhenping",
    "wof:placetype":"locality"
},
  "geometry": {"coordinates":[120.28333000000001,23.43333],"type":"Point"}
}