{
  "type": "Feature",
  "properties": {
    "gn:admin1_code":"2.0",
    "gn:admin2_code":"KHH",
    "gn:admin3_code":"E33",
    "gn:admin4_code":"64000330007.0",
    "gn:asciiname":"Nanguang",
    "gn:country_code":"TW",
    "gn:dem":333,
    "gn:feature_class":"P",
    "gn:feature_code":"PPL",
    "gn:name":"Nanguang",
    "gn:population":0,
    "gn:timezone":"Asia/Taipei",
    "iso:country":"TW",
    "name:und_x_variant":[
        "Niu-liao",
        "Nan-kuang"
    ],
    "name:zho_x_preferred":[
        "\u5357\u5149"
    ],
    "wof:name":"Nanguang",
    "wof:placetype":"locality"
},
  "geometry": {"coordinates":[120.62056,23.13833],"type":"Point"}
}