{
  "type": "Feature",
  "properties": {
    "gn:admin1_code":"04",
    "gn:admin2_code":"ILA",
    "gn:admin3_code":"G05",
    "gn:admin4_code":"10002070008.0",
    "gn:asciiname":"Dingcukeng",
    "gn:country_code":"TW",
    "gn:dem":175,
    "gn:feature_class":"P",
    "gn:feature_code":"PPL",
    "gn:name":"Dingcukeng",
    "gn:population":0,
    "gn:timezone":"Asia/Taipei",
    "iso:country":"TW",
    "name:zho_x_preferred":[
        "\u9802\u7c97\u5751"
    ],
    "name:zho_x_variant":[
        "Shang-ts\u2019u-k\u2019eng",
        "Ting-ts\u2019u-k\u2019eng"
    ],
    "wof:name":"Dingcukeng",
    "wof:placetype":"locality"
},
  "geometry": {"coordinates":[121.61445000000001,24.69835],"type":"Point"}
}