{
  "type": "Feature",
  "properties": {
    "gn:admin1_code":"4.0",
    "gn:admin2_code":"TAO",
    "gn:admin3_code":"H13",
    "gn:admin4_code":"68000130007.0",
    "gn:asciiname":"Zhongkuihui",
    "gn:country_code":"TW",
    "gn:dem":358,
    "gn:feature_class":"P",
    "gn:feature_code":"PPL",
    "gn:name":"Zhongkuihui",
    "gn:population":0,
    "gn:timezone":"Asia/Taipei",
    "iso:country":"TW",
    "name:und_x_variant":[
        "Jhongkueihuei",
        "Zhongkuihui"
    ],
    "name:zho_x_preferred":[
        "K\u2019uei-hui-she"
    ],
    "name:zho_x_variant":[
        "\u4e2d\u594e\u8f1d",
        "K\u2019uei-hui",
        "Chung-k\u2019uei-hui"
    ],
    "wof:name":"Zhongkuihui",
    "wof:placetype":"locality"
},
  "geometry": {"coordinates":[121.33428000000001,24.79721],"type":"Point"}
}