{
  "type": "Feature",
  "properties": {
    "gn:admin1_code":"3.0",
    "gn:admin2_code":"TPQ",
    "gn:admin3_code":"F10",
    "gn:admin4_code":"65000200007.0",
    "gn:asciiname":"Huliaotan",
    "gn:country_code":"TW",
    "gn:dem":275,
    "gn:feature_class":"P",
    "gn:feature_code":"PPL",
    "gn:name":"Huliaotan",
    "gn:population":0,
    "gn:timezone":"Asia/Taipei",
    "iso:country":"TW",
    "name:zho_x_preferred":[
        "\u864e\u5bee\u6f6d"
    ],
    "name:zho_x_variant":[
        "Hu-liao-t\u2019an"
    ],
    "wof:name":"Huliaotan",
    "wof:placetype":"locality"
},
  "geometry": {"coordinates":[121.74726,24.94523],"type":"Point"}
}