{
  "type": "Feature",
  "properties": {
    "gn:admin1_code":"4.0",
    "gn:admin2_code":"MIA",
    "gn:admin3_code":"K17",
    "gn:admin4_code":"10005170007.0",
    "gn:asciiname":"Wushibi",
    "gn:country_code":"TW",
    "gn:dem":413,
    "gn:feature_class":"P",
    "gn:feature_code":"PPL",
    "gn:name":"Wushibi",
    "gn:population":0,
    "gn:timezone":"Asia/Taipei",
    "iso:country":"TW",
    "name:und_x_variant":[
        "Hei-shih-pi",
        "Wu-shih-pi",
        "\u70cf\u77f3\u58c1",
        "Wushibi",
        "Wushihbi"
    ],
    "name:zho_x_preferred":[
        "\u70cf\u77f3\u58c1"
    ],
    "wof:name":"Wushibi",
    "wof:placetype":"locality"
},
  "geometry": {"coordinates":[120.8883,24.4511],"type":"Point"}
}