{
  "type": "Feature",
  "properties": {
    "iso:country":"TW",
    "name:eng_x_preferred":[
        "Kangryong County"
    ],
    "name:jpn_x_preferred":[
        "\u5eb7\u30ea\u30e7\u30f3\u90e1"
    ],
    "name:kor_x_preferred":[
        "\uac15\ub839\uad70"
    ],
    "name:nan_x_preferred":[
        "Kangry\u014fng K\u016bn"
    ],
    "name:nob_x_preferred":[
        "Kangryong"
    ],
    "name:pol_x_preferred":[
        "Kangny\u014fng"
    ],
    "name:vie_x_preferred":[
        "Kangryong"
    ],
    "name:zho_x_preferred":[
        "\u5eb7\u7fce\u90e1"
    ],
    "qs:name":"\u5bcc\u6c11\u91cc",
    "qs:name_adm0":"\u81fa\u7063",
    "qs:name_adm1":"\u57fa\u9686\u5e02",
    "qs:photos":255,
    "qs:photos_1k":52,
    "qs:photos_9k":1,
    "qs:photos_9r":4,
    "qs:photos_all":255,
    "qs:photos_sr":5,
    "qs:placetype":"Suburb",
    "qs:pop_sr":"0",
    "wd:wordcount":264,
    "wof:name":"\u5bcc\u6c11\u91cc",
    "wof:placetype":"neighbourhood"
},
  "geometry": {"coordinates":[121.71599399999999,25.098307],"type":"Point"}
}