{
  "type": "Feature",
  "properties": {
    "iso:country":"TW",
    "qs:name":"\u5bcc\u6c11\u91cc",
    "qs:name_adm0":"\u81fa\u7063",
    "qs:name_adm1":"\u57fa\u9686\u5e02",
    "qs:photos":255,
    "qs:photos_1k":52,
    "qs:photos_9k":1,
    "qs:photos_9r":4,
    "qs:photos_all":255,
    "qs:photos_sr":5,
    "qs:placetype":"Suburb",
    "qs:pop_sr":"0",
    "wd:wordcount":264,
    "wof:name":"\u5bcc\u6c11\u91cc",
    "wof:placetype":"neighbourhood"
},
  "geometry": {"coordinates":[121.71599399999999,25.098307],"type":"Point"}
}