{
  "type": "Feature",
  "properties": {
    "gn:admin1_code":"4.0",
    "gn:admin2_code":"MIA",
    "gn:admin3_code":"K15",
    "gn:admin4_code":"10005080004.0",
    "gn:asciiname":"Shiliaokeng",
    "gn:country_code":"TW",
    "gn:dem":289,
    "gn:feature_class":"P",
    "gn:feature_code":"PPL",
    "gn:name":"Shiliaokeng",
    "gn:population":0,
    "gn:timezone":"Asia/Taipei",
    "iso:country":"TW",
    "name:und_x_variant":[
        "Shihliaokeng",
        "Shiliaokeng",
        "\u5341\u5bee\u5751"
    ],
    "name:zho_x_preferred":[
        "Shih-liao-k\u2019eng"
    ],
    "name:zho_x_variant":[
        "\u5341\u5bee\u5751"
    ],
    "wof:name":"Shiliaokeng",
    "wof:placetype":"locality"
},
  "geometry": {"coordinates":[120.87990000000001,24.44434],"type":"Point"}
}