{
  "type": "Feature",
  "properties": {
    "gn:admin1_code":"03",
    "gn:admin2_code":"TPQ",
    "gn:admin3_code":"F19",
    "gn:admin4_code":"65000130024.0",
    "gn:asciiname":"Mazutian",
    "gn:country_code":"TW",
    "gn:dem":25,
    "gn:feature_class":"P",
    "gn:feature_code":"PPL",
    "gn:name":"Mazutian",
    "gn:population":0,
    "gn:timezone":"Asia/Taipei",
    "iso:country":"TW",
    "name:zho_x_preferred":[
        "Tsu-t\u2019ien"
    ],
    "name:zho_x_variant":[
        "\u5abd\u7956\u7530",
        "Tsu-t\u2019ien-ts\u2019un",
        "Ma-tsu-t\u2019ien"
    ],
    "wof:name":"Mazutian",
    "wof:placetype":"locality"
},
  "geometry": {"coordinates":[121.41240999999999,24.95495],"type":"Point"}
}