{
  "type": "Feature",
  "properties": {
    "gn:admin1_code":"4.0",
    "gn:admin2_code":"TNN",
    "gn:admin3_code":"R18",
    "gn:admin4_code":"67000180010.0",
    "gn:asciiname":"Liziwei",
    "gn:country_code":"TW",
    "gn:dem":14,
    "gn:feature_class":"P",
    "gn:feature_code":"PPL",
    "gn:name":"Liziwei",
    "gn:population":0,
    "gn:timezone":"Asia/Taipei",
    "iso:country":"TW",
    "name:und_x_variant":[
        "Lizihwei",
        "Li-tzu-wei"
    ],
    "name:zho_x_preferred":[
        "\u7c6c\u4ed4\u5c3e"
    ],
    "wof:name":"Liziwei",
    "wof:placetype":"locality"
},
  "geometry": {"coordinates":[120.30334000000001,23.04791],"type":"Point"}
}