{
  "type": "Feature",
  "properties": {
    "gn:admin1_code":"04",
    "gn:admin2_code":"MIA",
    "gn:admin3_code":"K16",
    "gn:admin4_code":"10005070006.0",
    "gn:asciiname":"Jingshan",
    "gn:country_code":"TW",
    "gn:dem":382,
    "gn:feature_class":"P",
    "gn:feature_code":"PPL",
    "gn:name":"Jingshan",
    "gn:population":0,
    "gn:timezone":"Asia/Taipei",
    "iso:country":"TW",
    "name:ceb_x_preferred":[
        "Jingshan"
    ],
    "name:deu_x_preferred":[
        "Jingshan"
    ],
    "name:nor_x_preferred":[
        "Jingshan"
    ],
    "name:und_x_variant":[
        "Ching-shan"
    ],
    "name:zho_x_preferred":[
        "Ts\u2019ao-liao"
    ],
    "name:zho_x_variant":[
        "\u666f\u5c71"
    ],
    "wof:name":"Jingshan",
    "wof:placetype":"locality"
},
  "geometry": {"coordinates":[120.8723,24.34907],"type":"Point"}
}