{
  "type": "Feature",
  "properties": {
    "iso:country":"TW",
    "name:eng_x_preferred":[
        "Wenchang"
    ],
    "name:eng_x_variant":[
        "Wenchang Village"
    ],
    "name:zho_tw_x_preferred":[
        "\u6587\u660c\u91cc"
    ],
    "qs:name":"\u6587\u660c\u91cc",
    "qs:name_adm0":"\u81fa\u7063",
    "qs:name_adm1":"\u9ad8\u96c4\u5e02",
    "qs:photos":11,
    "qs:photos_1k":2,
    "qs:photos_9k":1,
    "qs:photos_9r":1,
    "qs:photos_all":11,
    "qs:photos_sr":1,
    "qs:placetype":"Suburb",
    "qs:pop_sr":"0",
    "wof:name":"Wenchang",
    "wof:placetype":"neighbourhood"
},
  "geometry": {"coordinates":[120.337028,22.634292],"type":"Point"}
}