{
  "type": "Feature",
  "properties": {
    "gn:admin1_code":"4.0",
    "gn:admin2_code":"HSZ",
    "gn:admin3_code":"J14",
    "gn:admin4_code":"10004120001.0",
    "gn:asciiname":"Xinxing",
    "gn:country_code":"TW",
    "gn:dem":634,
    "gn:feature_class":"P",
    "gn:feature_code":"PPL",
    "gn:name":"Xinxing",
    "gn:population":0,
    "gn:timezone":"Asia/Taipei",
    "iso:country":"TW",
    "name:ceb_x_preferred":[
        "Xinxing"
    ],
    "name:deu_x_preferred":[
        "Xinxing"
    ],
    "name:eus_x_preferred":[
        "Xinxing"
    ],
    "name:fra_x_preferred":[
        "Xinxing"
    ],
    "name:nor_x_preferred":[
        "Xinxing"
    ],
    "name:rus_x_preferred":[
        "\u0421\u0438\u043d\u044c\u0441\u0438\u043d"
    ],
    "name:swe_x_preferred":[
        "Xinxing"
    ],
    "name:und_x_variant":[
        "Sinsing",
        "Xinxing",
        "Hsin-hsing"
    ],
    "name:zho_x_preferred":[
        "\u65b0\u8208"
    ],
    "wof:name":"Xinxing",
    "wof:placetype":"locality"
},
  "geometry": {"coordinates":[121.17972,24.68722],"type":"Point"}
}