{
  "type": "Feature",
  "properties": {
    "gn:admin1_code":"4.0",
    "gn:admin2_code":"TXG",
    "gn:admin3_code":"B11",
    "gn:admin4_code":"66000110026.0",
    "gn:asciiname":"Xiqi",
    "gn:country_code":"TW",
    "gn:dem":18,
    "gn:feature_class":"P",
    "gn:feature_code":"PPL",
    "gn:name":"Xiqi",
    "gn:population":0,
    "gn:timezone":"Asia/Taipei",
    "iso:country":"TW",
    "name:kor_x_preferred":[
        "\ud574\uc81c"
    ],
    "name:und_x_variant":[
        "Sici"
    ],
    "name:zho_x_preferred":[
        "\u897f\u5c90"
    ],
    "name:zho_x_variant":[
        "Ting-hou-ts\u2019o",
        "Ting-hou-ts\u2019o-tzu",
        "Hsi-ch\u2019i"
    ],
    "wof:name":"Xiqi",
    "wof:placetype":"locality"
},
  "geometry": {"coordinates":[120.62833000000001,24.41972],"type":"Point"}
}