{
  "type": "Feature",
  "properties": {
    "iso:country":"TW",
    "qs:name":"\u5927\u5bee\u9109",
    "qs:name_adm0":"\u81fa\u7063",
    "qs:name_adm1":"\u9ad8\u96c4\u5e02",
    "qs:photos":203,
    "qs:photos_1k":41,
    "qs:photos_9k":3,
    "qs:photos_9r":5,
    "qs:photos_all":730,
    "qs:photos_sr":4,
    "qs:placetype":"County",
    "qs:pop_sr":"0",
    "wd:wordcount":114,
    "wof:name":"\u5927\u5bee\u9109",
    "wof:placetype":"county"
},
  "geometry": {"coordinates":[120.412216,22.642056],"type":"Point"}
}