{
  "type": "Feature",
  "properties": {
    "gn:admin1_code":"4.0",
    "gn:admin2_code":"NAN",
    "gn:admin3_code":"M02",
    "gn:admin4_code":"10008020021.0",
    "gn:asciiname":"Kengnei",
    "gn:country_code":"TW",
    "gn:dem":454,
    "gn:feature_class":"P",
    "gn:feature_code":"PPL",
    "gn:name":"Kengnei",
    "gn:population":0,
    "gn:timezone":"Asia/Taipei",
    "iso:country":"TW",
    "name:zho_x_preferred":[
        "\u5751\u5185"
    ],
    "name:zho_x_variant":[
        "K\u2019eng-nei"
    ],
    "wof:name":"Kengnei",
    "wof:placetype":"locality"
},
  "geometry": {"coordinates":[120.91696,23.99538],"type":"Point"}
}