{
  "type": "Feature",
  "properties": {
    "gn:admin1_code":"4.0",
    "gn:admin2_code":"HUA",
    "gn:admin3_code":"U11",
    "gn:admin4_code":"10015110002.0",
    "gn:asciiname":"Sanjianwu",
    "gn:country_code":"TW",
    "gn:dem":189,
    "gn:feature_class":"P",
    "gn:feature_code":"PPL",
    "gn:name":"Sanjianwu",
    "gn:population":0,
    "gn:timezone":"Asia/Taipei",
    "iso:country":"TW",
    "name:und_x_variant":[
        "San-chien-wu"
    ],
    "name:zho_x_preferred":[
        "\u4e09\u9593\u5c4b"
    ],
    "wof:name":"Sanjianwu",
    "wof:placetype":"locality"
},
  "geometry": {"coordinates":[121.62581000000002,24.18242],"type":"Point"}
}