{
  "type": "Feature",
  "properties": {
    "gn:admin1_code":"4.0",
    "gn:admin2_code":"TAO",
    "gn:admin3_code":"H07",
    "gn:admin4_code":"68000070001.0",
    "gn:asciiname":"Zhongkeng",
    "gn:country_code":"TW",
    "gn:dem":191,
    "gn:feature_class":"P",
    "gn:feature_code":"PPL",
    "gn:name":"Zhongkeng",
    "gn:population":0,
    "gn:timezone":"Asia/Taipei",
    "iso:country":"TW",
    "name:und_x_variant":[
        "Jhongkeng"
    ],
    "name:zho_x_preferred":[
        "\u4e2d\u5751"
    ],
    "name:zho_x_variant":[
        "Chung-k\u2019eng"
    ],
    "wof:name":"Zhongkeng",
    "wof:placetype":"locality"
},
  "geometry": {"coordinates":[121.34310000000001,25.02689],"type":"Point"}
}