{
  "type": "Feature",
  "properties": {
    "gn:admin1_code":"4.0",
    "gn:admin2_code":"TNN",
    "gn:admin3_code":"R05",
    "gn:admin4_code":"67000050003.0",
    "gn:asciiname":"Liaozi",
    "gn:country_code":"TW",
    "gn:dem":19,
    "gn:feature_class":"P",
    "gn:feature_code":"PPL",
    "gn:name":"Liaozi",
    "gn:population":0,
    "gn:timezone":"Asia/Taipei",
    "iso:country":"TW",
    "name:und_x_variant":[
        "Liaozih",
        "Liaozi",
        "Liao-tzu"
    ],
    "name:zho_x_preferred":[
        "\u5bee\u5b50"
    ],
    "wof:name":"Liaozi",
    "wof:placetype":"locality"
},
  "geometry": {"coordinates":[120.35250000000001,23.35528],"type":"Point"}
}