{
  "type": "Feature",
  "properties": {
    "gn:admin1_code":"4.0",
    "gn:admin2_code":"HUA",
    "gn:admin3_code":"U03",
    "gn:admin4_code":"10015030011.0",
    "gn:asciiname":"Fuyin",
    "gn:country_code":"TW",
    "gn:dem":110,
    "gn:feature_class":"P",
    "gn:feature_code":"PPL",
    "gn:name":"Fuyin",
    "gn:population":0,
    "gn:timezone":"Asia/Taipei",
    "iso:country":"TW",
    "name:und_x_variant":[
        "Fu-yin"
    ],
    "name:zho_x_preferred":[
        "\u798f\u97f3"
    ],
    "wof:name":"Fuyin",
    "wof:placetype":"locality"
},
  "geometry": {"coordinates":[121.38178000000001,23.43559],"type":"Point"}
}