{
  "type": "Feature",
  "properties": {
    "gn:admin1_code":"3.0",
    "gn:admin2_code":"TPQ",
    "gn:admin3_code":"F07",
    "gn:admin4_code":"65000060026.0",
    "gn:asciiname":"Quchi",
    "gn:country_code":"TW",
    "gn:dem":66,
    "gn:feature_class":"P",
    "gn:feature_code":"PPL",
    "gn:name":"Quchi",
    "gn:population":0,
    "gn:timezone":"Asia/Taipei",
    "iso:country":"TW",
    "name:ara_x_preferred":[
        "\u0642\u0648\u062a\u0634\u064a"
    ],
    "name:fas_x_preferred":[
        "\u0642\u0648\u0686\u06cc"
    ],
    "name:und_x_variant":[
        "Cyuchih",
        "Quchi"
    ],
    "name:zho_x_preferred":[
        "Ch\u2019\u00fc-ch\u2019ih-li"
    ],
    "name:zho_x_variant":[
        "\u5c48\u5c3a",
        "Ch\u2019\u00fc-hs\u00fceh",
        "Ch\u2019\u00fc-ch\u2019ih"
    ],
    "wof:name":"Quchi",
    "wof:placetype":"locality"
},
  "geometry": {"coordinates":[121.54628,24.9231],"type":"Point"}
}