{
  "type": "Feature",
  "properties": {
    "gn:admin1_code":"2.0",
    "gn:admin2_code":"KHH",
    "gn:admin3_code":"E10",
    "gn:admin4_code":"64000100011.0",
    "gn:asciiname":"Zhongzhou",
    "gn:country_code":"TW",
    "gn:dem":7,
    "gn:feature_class":"P",
    "gn:feature_code":"PPL",
    "gn:name":"Zhongzhou",
    "gn:population":0,
    "gn:timezone":"Asia/Taipei",
    "iso:country":"TW",
    "name:und_x_variant":[
        "Chung-chou",
        "\u4e2d\u6d32",
        "Zhongzhou",
        "Jhongjhou"
    ],
    "name:zho_x_preferred":[
        "Ch\u2019ih-t\u2019ou-tzu"
    ],
    "wof:name":"Zhongzhou",
    "wof:placetype":"locality"
},
  "geometry": {"coordinates":[120.29683,22.5761],"type":"Point"}
}