{
  "type": "Feature",
  "properties": {
    "gn:admin1_code":"4.0",
    "gn:admin2_code":"TXG",
    "gn:admin3_code":"B13",
    "gn:admin4_code":"66000130017.0",
    "gn:asciiname":"Gongming",
    "gn:country_code":"TW",
    "gn:dem":214,
    "gn:feature_class":"P",
    "gn:feature_code":"PPL",
    "gn:name":"Gongming",
    "gn:population":0,
    "gn:timezone":"Asia/Taipei",
    "iso:country":"TW",
    "name:und_x_variant":[
        "Kung-kuan",
        "Kung-ming"
    ],
    "name:zho_x_preferred":[
        "\u516c\u660e"
    ],
    "wof:name":"Gongming",
    "wof:placetype":"locality"
},
  "geometry": {"coordinates":[120.60722,24.24556],"type":"Point"}
}