{
  "type": "Feature",
  "properties": {
    "gn:admin1_code":"4.0",
    "gn:admin2_code":"TNN",
    "gn:admin3_code":"R25",
    "gn:admin4_code":"67000250005.0",
    "gn:asciiname":"Xiweizi",
    "gn:country_code":"TW",
    "gn:dem":85,
    "gn:feature_class":"P",
    "gn:feature_code":"PPL",
    "gn:name":"Xiweizi",
    "gn:population":0,
    "gn:timezone":"Asia/Taipei",
    "iso:country":"TW",
    "name:und_x_variant":[
        "Siweizih",
        "Hsi-wei-tzu"
    ],
    "name:zho_x_preferred":[
        "\u6eaa\u5c3e\u4ed4"
    ],
    "wof:name":"Xiweizi",
    "wof:placetype":"locality"
},
  "geometry": {"coordinates":[120.46613000000001,23.02113],"type":"Point"}
}