{
  "type": "Feature",
  "properties": {
    "gn:country":"TW",
    "gn:fcode":"ADMD",
    "gn:pop":0,
    "iso:country":"TW",
    "name:unk_x_variant":[
        "Feng-lin Chen"
    ],
    "name:zho_x_preferred":[
        "\u9cf3\u6797\u93ae"
    ],
    "qs:name":"Fenglin Zhen",
    "qs:photos_9r":0,
    "qs:photos_sr":0,
    "qs:pop_sr":"0",
    "wd:wordcount":229,
    "wof:name":"Fenglin Zhen",
    "wof:placetype":"localadmin",
    "wof:population":0
},
  "geometry": {"coordinates":[121.45,23.73333],"type":"Point"}
}