{
  "type": "Feature",
  "properties": {
    "gn:country":"TW",
    "gn:fcode":"ADMD",
    "gn:population":0,
    "iso:country":"TW",
    "name:ami_x_preferred":[
        "Fenglin"
    ],
    "name:deu_x_preferred":[
        "Fenglin"
    ],
    "name:eng_x_preferred":[
        "Fenglin"
    ],
    "name:hak_x_preferred":[
        "Fung-l\u00ecm-ts\u1e73\u0301n"
    ],
    "name:ita_x_preferred":[
        "Fenglin"
    ],
    "name:jpn_x_preferred":[
        "\u9cf3\u6797\u93ae"
    ],
    "name:kor_x_preferred":[
        "\ud391\ub9b0\uc9c4"
    ],
    "name:lld_x_preferred":[
        "Fenglin"
    ],
    "name:nan_x_preferred":[
        "H\u014dng-l\u00eem-t\u00ecn"
    ],
    "name:pol_x_preferred":[
        "Fenglin"
    ],
    "name:pwn_x_preferred":[
        "Fenglin"
    ],
    "name:rus_x_preferred":[
        "\u0424\u044d\u043d\u043b\u0438\u043d\u044c"
    ],
    "name:szy_x_preferred":[
        "Cingaluan a kenis"
    ],
    "name:tay_x_preferred":[
        "Fenglin"
    ],
    "name:und_x_variant":[
        "Feng-lin Chen"
    ],
    "name:vie_x_preferred":[
        "Ph\u01b0\u1ee3ng L\u00e2m"
    ],
    "name:xsy_x_preferred":[
        "Fenglin"
    ],
    "name:yue_x_preferred":[
        "\u9cf3\u6797\u93ae"
    ],
    "name:zho_x_preferred":[
        "\u9cf3\u6797\u93ae"
    ],
    "qs:name":"Fenglin Zhen",
    "qs:photos_9r":0,
    "qs:photos_sr":0,
    "qs:pop_sr":"0",
    "wd:wordcount":229,
    "wof:name":"Fenglin Zhen",
    "wof:placetype":"localadmin",
    "wof:population":0
},
  "geometry": {"coordinates":[121.45,23.73333],"type":"Point"}
}