{
  "type": "Feature",
  "properties": {
    "gn:admin1_code":"4.0",
    "gn:admin2_code":"HSZ",
    "gn:admin3_code":"J10",
    "gn:admin4_code":"10004070009.0",
    "gn:asciiname":"Shangxinfeng",
    "gn:country_code":"TW",
    "gn:dem":96,
    "gn:feature_class":"P",
    "gn:feature_code":"PPL",
    "gn:name":"Shangxinfeng",
    "gn:population":0,
    "gn:timezone":"Asia/Taipei",
    "iso:country":"TW",
    "name:und_x_variant":[
        "Shangsinfong",
        "Shangxinfeng",
        "Shang-hsin-feng"
    ],
    "name:zho_x_preferred":[
        "\u4e0a\u65b0\u9cf3"
    ],
    "wof:name":"Shangxinfeng",
    "wof:placetype":"locality"
},
  "geometry": {"coordinates":[121.08444,24.76083],"type":"Point"}
}