{
  "type": "Feature",
  "properties": {
    "gn:admin1_code":"4.0",
    "gn:admin2_code":"MIA",
    "gn:admin3_code":"K05",
    "gn:admin4_code":"10005100004.0",
    "gn:asciiname":"Zhuwei",
    "gn:country_code":"TW",
    "gn:dem":214,
    "gn:feature_class":"P",
    "gn:feature_code":"PPL",
    "gn:name":"Zhuwei",
    "gn:population":0,
    "gn:timezone":"Asia/Taipei",
    "iso:country":"TW",
    "name:und_x_variant":[
        "Chu-wei",
        "Zhuwei",
        "Jhuwei"
    ],
    "name:zho_x_preferred":[
        "\u7af9\u570d"
    ],
    "wof:name":"Zhuwei",
    "wof:placetype":"locality"
},
  "geometry": {"coordinates":[120.77838,24.44739],"type":"Point"}
}