{
  "type": "Feature",
  "properties": {
    "gn:admin1_code":"4.0",
    "gn:admin2_code":"TXG",
    "gn:admin3_code":"B19",
    "gn:admin4_code":"66000190009.0",
    "gn:asciiname":"Changqiding",
    "gn:country_code":"TW",
    "gn:dem":524,
    "gn:feature_class":"P",
    "gn:feature_code":"PPL",
    "gn:name":"Changqiding",
    "gn:population":0,
    "gn:timezone":"Asia/Taipei",
    "iso:country":"TW",
    "name:und_x_variant":[
        "Changciding"
    ],
    "name:zho_x_preferred":[
        "\u9577\u5d0e\u9802"
    ],
    "name:zho_x_variant":[
        "Ch\u2019ang-ch\u2019i-ting"
    ],
    "wof:name":"Changqiding",
    "wof:placetype":"locality"
},
  "geometry": {"coordinates":[120.81641999999999,24.20874],"type":"Point"}
}