{
  "type": "Feature",
  "properties": {
    "gn:admin1_code":"4.0",
    "gn:admin2_code":"NAN",
    "gn:admin3_code":"M08",
    "gn:admin4_code":"10008080014.0",
    "gn:asciiname":"Neihuzi",
    "gn:country_code":"TW",
    "gn:dem":215,
    "gn:feature_class":"P",
    "gn:feature_code":"PPL",
    "gn:name":"Neihuzi",
    "gn:population":0,
    "gn:timezone":"Asia/Taipei",
    "iso:country":"TW",
    "name:und_x_variant":[
        "Neihuzih",
        "Nei-hu-tzu"
    ],
    "name:zho_x_preferred":[
        "\u5185\u6e56\u4ed4"
    ],
    "wof:name":"Neihuzi",
    "wof:placetype":"locality"
},
  "geometry": {"coordinates":[120.75709999999999,23.9419],"type":"Point"}
}