{
  "type": "Feature",
  "properties": {
    "gn:admin1_code":"02",
    "gn:admin2_code":"KHH",
    "gn:admin3_code":"E19",
    "gn:admin4_code":"64000190022.0",
    "gn:asciiname":"Yanbu",
    "gn:country_code":"TW",
    "gn:dem":9,
    "gn:feature_class":"P",
    "gn:feature_code":"PPL",
    "gn:name":"Yanbu",
    "gn:population":0,
    "gn:timezone":"Asia/Taipei",
    "iso:country":"TW",
    "name:und_x_variant":[
        "Yen-pu"
    ],
    "name:zho_x_preferred":[
        "\u9e7d\u57d4"
    ],
    "wof:name":"Yanbu",
    "wof:placetype":"locality"
},
  "geometry": {"coordinates":[120.28167000000001,22.76833],"type":"Point"}
}