{
  "type": "Feature",
  "properties": {
    "gn:admin1_code":"02",
    "gn:admin2_code":"KHH",
    "gn:admin3_code":"E19",
    "gn:admin4_code":"64000190022.0",
    "gn:asciiname":"Yanbu",
    "gn:country_code":"TW",
    "gn:dem":9,
    "gn:feature_class":"P",
    "gn:feature_code":"PPL",
    "gn:name":"Yanbu",
    "gn:population":0,
    "gn:timezone":"Asia/Taipei",
    "iso:country":"TW",
    "name:ara_x_preferred":[
        "\u064a\u0646\u0628\u0639"
    ],
    "name:arz_x_preferred":[
        "\u064a\u0646\u0628\u0639"
    ],
    "name:ben_x_preferred":[
        "\u0987\u09af\u09bc\u09be\u09a8\u09ac\u09c1"
    ],
    "name:cat_x_preferred":[
        "Yanbo"
    ],
    "name:dan_x_preferred":[
        "Yanbu"
    ],
    "name:deu_x_preferred":[
        "Yanbu"
    ],
    "name:epo_x_preferred":[
        "Janbu"
    ],
    "name:fas_x_preferred":[
        "\u06cc\u0646\u0628\u0639"
    ],
    "name:fin_x_preferred":[
        "Yanbu"
    ],
    "name:fra_x_preferred":[
        "Yanbu"
    ],
    "name:gle_x_preferred":[
        "Yanbu"
    ],
    "name:heb_x_preferred":[
        "\u05d9\u05e0\u05d1\u05d5\u05e2"
    ],
    "name:hin_x_preferred":[
        "\u092f\u093e\u0902\u092c\u0942"
    ],
    "name:ind_x_preferred":[
        "Yanbu"
    ],
    "name:ita_x_preferred":[
        "Yanbu\u02bf"
    ],
    "name:jpn_x_preferred":[
        "\u30e4\u30f3\u30d6\u30fc"
    ],
    "name:kaz_x_preferred":[
        "\u042f\u043d\u0431\u0443"
    ],
    "name:mal_x_preferred":[
        "\u0d2f\u0d3e\u0d2e\u0d4d\u0d2a\u0d41"
    ],
    "name:nld_x_preferred":[
        "Yanbu"
    ],
    "name:nno_x_preferred":[
        "Yanbu"
    ],
    "name:nor_x_preferred":[
        "Yanbu"
    ],
    "name:pnb_x_preferred":[
        "\u06cc\u0646\u0628\u0639 \u0627\u0644\u0628\u062d\u0631"
    ],
    "name:pol_x_preferred":[
        "Janbu"
    ],
    "name:por_x_preferred":[
        "Iambo"
    ],
    "name:rus_x_preferred":[
        "\u042f\u043d\u0431\u0443-\u044d\u043b\u044c-\u0411\u0430\u0445\u0440"
    ],
    "name:sco_x_preferred":[
        "Yanbu"
    ],
    "name:spa_x_preferred":[
        "Yanbu"
    ],
    "name:sun_x_preferred":[
        "Yanbu"
    ],
    "name:swe_x_preferred":[
        "Yanbu"
    ],
    "name:tgl_x_preferred":[
        "Yanbu"
    ],
    "name:ukr_x_preferred":[
        "\u042f\u043d\u0431\u0443-\u0435\u043b\u044c-\u0411\u0430\u0445\u0440"
    ],
    "name:und_x_variant":[
        "Yen-pu"
    ],
    "name:urd_x_preferred":[
        "\u06cc\u0646\u0628\u0639"
    ],
    "name:vie_x_preferred":[
        "Yanbu"
    ],
    "name:zho_x_preferred":[
        "\u9e7d\u57d4"
    ],
    "wof:name":"Yanbu",
    "wof:placetype":"locality"
},
  "geometry": {"coordinates":[120.28167000000001,22.76833],"type":"Point"}
}