{
  "type": "Feature",
  "properties": {
    "gn:admin1_code":"4.0",
    "gn:admin2_code":"TAO",
    "gn:admin3_code":"H12",
    "gn:admin4_code":"68000120016.0",
    "gn:asciiname":"Zhuocuo",
    "gn:country_code":"TW",
    "gn:dem":109,
    "gn:feature_class":"P",
    "gn:feature_code":"PPL",
    "gn:name":"Zhuocuo",
    "gn:population":0,
    "gn:timezone":"Asia/Taipei",
    "iso:country":"TW",
    "name:und_x_variant":[
        "Cho-wu",
        "Zhuocuo",
        "Jhuocuo"
    ],
    "name:zho_x_preferred":[
        "\u5353\u539d"
    ],
    "name:zho_x_variant":[
        "Cho-ts\u2019o"
    ],
    "wof:name":"Zhuocuo",
    "wof:placetype":"locality"
},
  "geometry": {"coordinates":[121.15389,24.97611],"type":"Point"}
}