{
  "type": "Feature",
  "properties": {
    "gn:admin1_code":"4.0",
    "gn:admin2_code":"NAN",
    "gn:admin3_code":"M10",
    "gn:admin4_code":"10008100008.0",
    "gn:asciiname":"Tangbu",
    "gn:country_code":"TW",
    "gn:dem":233,
    "gn:feature_class":"P",
    "gn:feature_code":"PPL",
    "gn:name":"Tangbu",
    "gn:population":0,
    "gn:timezone":"Asia/Taipei",
    "iso:country":"TW",
    "name:zho_x_preferred":[
        "\u7cd6\u90e8"
    ],
    "name:zho_x_variant":[
        "T\u2019ang-p\u2019ou",
        "T\u2019ang-pu"
    ],
    "wof:name":"Tangbu",
    "wof:placetype":"locality"
},
  "geometry": {"coordinates":[120.81419,24.02401],"type":"Point"}
}