{
  "type": "Feature",
  "properties": {
    "gn:admin1_code":"4.0",
    "gn:admin2_code":"CHA",
    "gn:admin3_code":"N01",
    "gn:admin4_code":"10007010032.0",
    "gn:asciiname":"Kengzinei",
    "gn:country_code":"TW",
    "gn:dem":70,
    "gn:feature_class":"P",
    "gn:feature_code":"PPL",
    "gn:name":"Kengzinei",
    "gn:population":0,
    "gn:timezone":"Asia/Taipei",
    "iso:country":"TW",
    "name:und_x_variant":[
        "T\u2019ao-y\u00fcan-li",
        "Kengzinei",
        "Kengzihnei"
    ],
    "name:zho_x_preferred":[
        "\u5751\u4ed4\u5185"
    ],
    "name:zho_x_variant":[
        "K\u2019eng-tzu-nei"
    ],
    "wof:name":"Kengzinei",
    "wof:placetype":"locality"
},
  "geometry": {"coordinates":[120.56171999999999,24.06546],"type":"Point"}
}