{
  "type": "Feature",
  "properties": {
    "gn:admin1_code":"4.0",
    "gn:admin2_code":"CHA",
    "gn:admin3_code":"N01",
    "gn:admin4_code":"10007010066.0",
    "gn:asciiname":"Shipai",
    "gn:country_code":"TW",
    "gn:dem":62,
    "gn:feature_class":"P",
    "gn:feature_code":"PPL",
    "gn:name":"Shipai",
    "gn:population":0,
    "gn:timezone":"Asia/Taipei",
    "iso:country":"TW",
    "name:und_x_variant":[
        "Shihpai"
    ],
    "name:zho_x_preferred":[
        "\u77f3\u724c"
    ],
    "name:zho_x_variant":[
        "Shih-p\u2019ai"
    ],
    "wof:name":"Shipai",
    "wof:placetype":"locality"
},
  "geometry": {"coordinates":[120.61398,24.05866],"type":"Point"}
}