{
  "type": "Feature",
  "properties": {
    "gn:admin1_code":"4.0",
    "gn:admin2_code":"CHA",
    "gn:admin3_code":"N11",
    "gn:admin4_code":"10007060015.0",
    "gn:asciiname":"Xianian",
    "gn:country_code":"TW",
    "gn:dem":11,
    "gn:feature_class":"P",
    "gn:feature_code":"PPL",
    "gn:name":"Xianian",
    "gn:population":0,
    "gn:timezone":"Asia/Taipei",
    "iso:country":"TW",
    "name:und_x_variant":[
        "Hsia-jan",
        "Xianian",
        "Sianian",
        "Hsia-nien"
    ],
    "name:zho_x_preferred":[
        "Hsia-Jen-Ts\u2019un"
    ],
    "name:zho_x_variant":[
        "Hsia-nien-ts\u2019un",
        "Hsia-jan-ts\u2019un",
        "\u5ec8\u7c98"
    ],
    "wof:name":"Xianian",
    "wof:placetype":"locality"
},
  "geometry": {"coordinates":[120.405,24.02917],"type":"Point"}
}