{
  "type": "Feature",
  "properties": {
    "iso:country":"TW",
    "qs:name":"\u9c32\u9f13\u6751",
    "qs:name_adm0":"\u81fa\u7063",
    "qs:name_adm1":"\u5609\u7fa9\u7e23",
    "qs:photos":179,
    "qs:photos_1k":36,
    "qs:photos_9k":1,
    "qs:photos_9r":4,
    "qs:photos_all":179,
    "qs:photos_sr":4,
    "qs:placetype":"Town",
    "qs:pop_sr":"0",
    "wof:name":"\u9c32\u9f13\u6751",
    "wof:placetype":"locality"
},
  "geometry": {"coordinates":[120.127444,23.508313],"type":"Point"}
}