{
  "type": "Feature",
  "properties": {
    "gn:admin1_code":"3.0",
    "gn:admin2_code":"TPQ",
    "gn:admin3_code":"F02",
    "gn:admin4_code":"65000170010.0",
    "gn:asciiname":"Kengtou",
    "gn:country_code":"TW",
    "gn:dem":207,
    "gn:feature_class":"P",
    "gn:feature_code":"PPL",
    "gn:name":"Kengtou",
    "gn:population":0,
    "gn:timezone":"Asia/Taipei",
    "iso:country":"TW",
    "name:zho_x_preferred":[
        "\u5751\u982d"
    ],
    "name:zho_x_variant":[
        "K\u2019eng-t\u2019ou"
    ],
    "wof:name":"Kengtou",
    "wof:placetype":"locality"
},
  "geometry": {"coordinates":[121.36365000000001,25.08145],"type":"Point"}
}