{
  "type": "Feature",
  "properties": {
    "gn:admin1_code":"04",
    "gn:admin2_code":"MIA",
    "gn:admin3_code":"K17",
    "gn:admin4_code":"10005170003.0",
    "gn:asciiname":"Shitan",
    "gn:country_code":"TW",
    "gn:dem":195,
    "gn:feature_class":"P",
    "gn:feature_code":"PPL",
    "gn:name":"Shitan",
    "gn:population":0,
    "gn:timezone":"Asia/Taipei",
    "iso:country":"TW",
    "name:und_x_variant":[
        "Shihtan",
        "Shitan"
    ],
    "name:zho_x_preferred":[
        "\u7345\u6f6d"
    ],
    "name:zho_x_variant":[
        "Shih-t\u2019an",
        "\u77f3\u6f6d\u9547"
    ],
    "wof:name":"Shitan",
    "wof:placetype":"locality"
},
  "geometry": {"coordinates":[120.92229,24.54137],"type":"Point"}
}