{
  "type": "Feature",
  "properties": {
    "gn:admin1_code":"4.0",
    "gn:admin2_code":"TXG",
    "gn:admin3_code":"B19",
    "gn:admin4_code":"66000190007.0",
    "gn:asciiname":"Xin'ercun",
    "gn:country_code":"TW",
    "gn:dem":476,
    "gn:feature_class":"P",
    "gn:feature_code":"PPL",
    "gn:name":"Xin\u2019ercun",
    "gn:population":0,
    "gn:timezone":"Asia/Taipei",
    "iso:country":"TW",
    "name:und_x_variant":[
        "Hsin-erh"
    ],
    "name:zho_x_preferred":[
        "\u65b0\u4e8c\u6751"
    ],
    "name:zho_x_variant":[
        "Sin\u2019ercun",
        "Xin\u2019ercun",
        "Hsin-erh-ts\u2019un"
    ],
    "wof:name":"Xin'ercun",
    "wof:placetype":"locality"
},
  "geometry": {"coordinates":[120.795,24.2187],"type":"Point"}
}