{
  "type": "Feature",
  "properties": {
    "gn:admin1_code":"4.0",
    "gn:admin2_code":"CHA",
    "gn:admin3_code":"N20",
    "gn:admin4_code":"10007180001.0",
    "gn:asciiname":"Kengnei",
    "gn:country_code":"TW",
    "gn:dem":141,
    "gn:feature_class":"P",
    "gn:feature_code":"PPL",
    "gn:name":"Kengnei",
    "gn:population":0,
    "gn:timezone":"Asia/Taipei",
    "iso:country":"TW",
    "name:zho_x_preferred":[
        "\u5751\u5167"
    ],
    "name:zho_x_variant":[
        "K\u2019eng-nei-ts\u2019un",
        "K\u2019eng-nei"
    ],
    "wof:name":"Kengnei",
    "wof:placetype":"locality"
},
  "geometry": {"coordinates":[120.6144,23.8289],"type":"Point"}
}