{
  "type": "Feature",
  "properties": {
    "gn:admin1_code":"4.0",
    "gn:admin2_code":"MIA",
    "gn:admin3_code":"K16",
    "gn:admin4_code":"10005070003.0",
    "gn:asciiname":"Shuijianxia",
    "gn:country_code":"TW",
    "gn:dem":361,
    "gn:feature_class":"P",
    "gn:feature_code":"PPL",
    "gn:name":"Shuijianxia",
    "gn:population":0,
    "gn:timezone":"Asia/Taipei",
    "iso:country":"TW",
    "name:und_x_variant":[
        "Shui-chien-hsia",
        "\u6c34\u6898\u4e0b",
        "Shueijiansia"
    ],
    "name:zho_x_preferred":[
        "\u6c34\u6898\u4e0b"
    ],
    "wof:name":"Shuijianxia",
    "wof:placetype":"locality"
},
  "geometry": {"coordinates":[120.83844000000001,24.30814],"type":"Point"}
}