{
  "type": "Feature",
  "properties": {
    "gn:admin1_code":"4.0",
    "gn:admin2_code":"CHA",
    "gn:admin3_code":"N15",
    "gn:admin4_code":"10007130010.0",
    "gn:asciiname":"Jiaxi",
    "gn:country_code":"TW",
    "gn:dem":23,
    "gn:feature_class":"P",
    "gn:feature_code":"PPL",
    "gn:name":"Jiaxi",
    "gn:population":0,
    "gn:timezone":"Asia/Taipei",
    "iso:country":"TW",
    "name:und_x_variant":[
        "Chia-yang",
        "Jiaxi",
        "Jiasi",
        "Chia-hsi"
    ],
    "name:zho_x_preferred":[
        "Chia-hsi-ts\u2019un"
    ],
    "name:zho_x_variant":[
        "\u52a0\u932b"
    ],
    "wof:name":"Jiaxi",
    "wof:placetype":"locality"
},
  "geometry": {"coordinates":[120.52589999999999,23.9856],"type":"Point"}
}