{
  "type": "Feature",
  "properties": {
    "gn:admin1_code":"4.0",
    "gn:admin2_code":"HUA",
    "gn:admin3_code":"U06",
    "gn:admin4_code":"10015060014.0",
    "gn:asciiname":"Nankengtou",
    "gn:country_code":"TW",
    "gn:dem":177,
    "gn:feature_class":"P",
    "gn:feature_code":"PPL",
    "gn:name":"Nankengtou",
    "gn:population":0,
    "gn:timezone":"Asia/Taipei",
    "iso:country":"TW",
    "name:zho_x_preferred":[
        "\u5357\u5751\u982d"
    ],
    "name:zho_x_variant":[
        "Nan-k\u2019eng-t\u2019ou"
    ],
    "wof:name":"Nankengtou",
    "wof:placetype":"locality"
},
  "geometry": {"coordinates":[121.53082999999999,23.76361],"type":"Point"}
}