{
  "type": "Feature",
  "properties": {
    "gn:admin1_code":"4.0",
    "gn:admin2_code":"TNN",
    "gn:admin3_code":"R03",
    "gn:admin4_code":"67000030024.0",
    "gn:asciiname":"Ganzhai",
    "gn:country_code":"TW",
    "gn:dem":42,
    "gn:feature_class":"P",
    "gn:feature_code":"PPL",
    "gn:name":"Ganzhai",
    "gn:population":0,
    "gn:timezone":"Asia/Taipei",
    "iso:country":"TW",
    "name:und_x_variant":[
        "Ganjhai",
        "Kan-chai-tzu",
        "Ganzhai",
        "Kan-chai"
    ],
    "name:zho_x_preferred":[
        "\u7518\u5b85"
    ],
    "wof:name":"Ganzhai",
    "wof:placetype":"locality"
},
  "geometry": {"coordinates":[120.43917,23.38083],"type":"Point"}
}