{
  "type": "Feature",
  "properties": {
    "gn:admin1_code":"04",
    "gn:admin2_code":"MIA",
    "gn:admin3_code":"K14",
    "gn:admin4_code":"10005110004.0",
    "gn:asciiname":"Wushezui",
    "gn:country_code":"TW",
    "gn:dem":222,
    "gn:feature_class":"P",
    "gn:feature_code":"PPL",
    "gn:name":"Wushezui",
    "gn:population":0,
    "gn:timezone":"Asia/Taipei",
    "iso:country":"TW",
    "name:und_x_variant":[
        "Wu-she",
        "Wushezuei",
        "Wushezui",
        "Wu-she-tsui"
    ],
    "name:zho_x_preferred":[
        "\u70cf\u86c7\u5634"
    ],
    "wof:name":"Wushezui",
    "wof:placetype":"locality"
},
  "geometry": {"coordinates":[121.01065,24.61559],"type":"Point"}
}