{
  "type": "Feature",
  "properties": {
    "gn:admin1_code":"03",
    "gn:admin2_code":"TPQ",
    "gn:admin3_code":"F22",
    "gn:admin4_code":"65000240007.0",
    "gn:asciiname":"Dongshige",
    "gn:country_code":"TW",
    "gn:dem":290,
    "gn:feature_class":"P",
    "gn:feature_code":"PPL",
    "gn:name":"Dongshige",
    "gn:population":0,
    "gn:timezone":"Asia/Taipei",
    "iso:country":"TW",
    "name:und_x_variant":[
        "Dongshihge",
        "Dongshige",
        "Tung-shih-ko"
    ],
    "name:zho_x_preferred":[
        "\u6771\u52e2\u683c"
    ],
    "wof:name":"Dongshige",
    "wof:placetype":"locality"
},
  "geometry": {"coordinates":[121.73408999999999,25.00109],"type":"Point"}
}