{
  "type": "Feature",
  "properties": {
    "gn:admin1_code":"4.0",
    "gn:admin2_code":"NAN",
    "gn:admin3_code":"M07",
    "gn:admin4_code":"10008070010.0",
    "gn:asciiname":"Wuweilun",
    "gn:country_code":"TW",
    "gn:dem":688,
    "gn:feature_class":"P",
    "gn:feature_code":"PPL",
    "gn:name":"Wuweilun",
    "gn:population":0,
    "gn:timezone":"Asia/Taipei",
    "iso:country":"TW",
    "name:und_x_variant":[
        "Wu-wei-lun"
    ],
    "name:zho_x_preferred":[
        "\u4e94\u5c3e\u5d19"
    ],
    "wof:name":"Wuweilun",
    "wof:placetype":"locality"
},
  "geometry": {"coordinates":[120.78556,23.74528],"type":"Point"}
}