{
  "type": "Feature",
  "properties": {
    "gn:admin1_code":"4.0",
    "gn:admin2_code":"TPE",
    "gn:admin3_code":"A14",
    "gn:admin4_code":"63000100002.0",
    "gn:asciiname":"Fenjihu",
    "gn:country_code":"TW",
    "gn:dem":56,
    "gn:feature_class":"P",
    "gn:feature_code":"PPL",
    "gn:name":"Fenjihu",
    "gn:population":0,
    "gn:timezone":"Asia/Taipei",
    "iso:country":"TW",
    "name:und_x_variant":[
        "Pen-chi-hu",
        "Fenjihu",
        "Fen-chi-hu"
    ],
    "name:zho_x_preferred":[
        "\u7cde\u7b95\u6e56"
    ],
    "wof:name":"Fenjihu",
    "wof:placetype":"locality"
},
  "geometry": {"coordinates":[121.55956999999999,25.09035],"type":"Point"}
}