{
  "type": "Feature",
  "properties": {
    "gn:admin1_code":"4.0",
    "gn:admin2_code":"ILA",
    "gn:admin3_code":"G08",
    "gn:admin4_code":"10002080016.0",
    "gn:asciiname":"Shagang",
    "gn:country_code":"TW",
    "gn:dem":6,
    "gn:feature_class":"P",
    "gn:feature_code":"PPL",
    "gn:name":"Shagang",
    "gn:population":0,
    "gn:timezone":"Asia/Taipei",
    "iso:country":"TW",
    "name:und_x_variant":[
        "Sha-kang"
    ],
    "name:zho_x_preferred":[
        "\u7802\u6e2f"
    ],
    "wof:name":"Shagang",
    "wof:placetype":"locality"
},
  "geometry": {"coordinates":[121.78019999999999,24.6538],"type":"Point"}
}