{
  "type": "Feature",
  "properties": {
    "gn:admin1_code":"4.0",
    "gn:admin2_code":"TAO",
    "gn:admin3_code":"H11",
    "gn:admin4_code":"68000110020.0",
    "gn:asciiname":"Guizhulin",
    "gn:country_code":"TW",
    "gn:dem":24,
    "gn:feature_class":"P",
    "gn:feature_code":"PPL",
    "gn:name":"Guizhulin",
    "gn:population":0,
    "gn:timezone":"Asia/Taipei",
    "iso:country":"TW",
    "name:und_x_variant":[
        "Gueijhulin",
        "Guizhulin",
        "Kuei-chu-lin"
    ],
    "name:zho_x_preferred":[
        "\u6842\u7af9\u6797"
    ],
    "wof:name":"Guizhulin",
    "wof:placetype":"locality"
},
  "geometry": {"coordinates":[121.03361,24.975],"type":"Point"}
}