{
  "type": "Feature",
  "properties": {
    "gn:admin1_code":"01",
    "gn:admin2_code":"KIN",
    "gn:admin3_code":"W02",
    "gn:admin4_code":"9020020001.0",
    "gn:asciiname":"Dongxiao",
    "gn:country_code":"TW",
    "gn:dem":20,
    "gn:feature_class":"P",
    "gn:feature_code":"PPL",
    "gn:name":"Dongxiao",
    "gn:population":0,
    "gn:timezone":"Asia/Taipei",
    "iso:country":"TW",
    "name:und_x_variant":[
        "Tung-hsiao",
        "\u6771\u856d",
        "Dongxiao"
    ],
    "wof:name":"Dongxiao",
    "wof:placetype":"locality"
},
  "geometry": {"coordinates":[118.4233,24.48833],"type":"Point"}
}