{
  "type": "Feature",
  "properties": {
    "gn:admin1_code":"4.0",
    "gn:admin2_code":"TNN",
    "gn:admin3_code":"R18",
    "gn:admin4_code":"67000180020.0",
    "gn:asciiname":"Jiaokengzi",
    "gn:country_code":"TW",
    "gn:dem":64,
    "gn:feature_class":"P",
    "gn:feature_code":"PPL",
    "gn:name":"Jiaokengzi",
    "gn:population":0,
    "gn:timezone":"Asia/Taipei",
    "iso:country":"TW",
    "name:und_x_variant":[
        "Jiaokengzih"
    ],
    "name:zho_x_preferred":[
        "\u7901\u5751\u5b50"
    ],
    "name:zho_x_variant":[
        "Chiao-k\u2019eng-tzu"
    ],
    "wof:name":"Jiaokengzi",
    "wof:placetype":"locality"
},
  "geometry": {"coordinates":[120.35854999999999,23.02991],"type":"Point"}
}