{
  "type": "Feature",
  "properties": {
    "gn:admin1_code":"04",
    "gn:admin2_code":"CHA",
    "gn:admin3_code":"N20",
    "gn:admin4_code":"10007180017.0",
    "gn:asciiname":"Shiwuzhuang",
    "gn:country_code":"TW",
    "gn:dem":65,
    "gn:feature_class":"P",
    "gn:feature_code":"PPL",
    "gn:name":"Shiwuzhuang",
    "gn:population":0,
    "gn:timezone":"Asia/Taipei",
    "iso:country":"TW",
    "name:und_x_variant":[
        "Shihwujhuang",
        "Shih-wu",
        "Shih-wu-chuang"
    ],
    "name:zho_x_preferred":[
        "\u5341\u4e94\u5e84"
    ],
    "wof:name":"Shiwuzhuang",
    "wof:placetype":"locality"
},
  "geometry": {"coordinates":[120.60209999999999,23.82978],"type":"Point"}
}