{
  "type": "Feature",
  "properties": {
    "gn:admin1_code":"3.0",
    "gn:admin2_code":"TPQ",
    "gn:admin3_code":"F15",
    "gn:admin4_code":"65000090016.0",
    "gn:asciiname":"Donglukou",
    "gn:country_code":"TW",
    "gn:dem":189,
    "gn:feature_class":"P",
    "gn:feature_code":"PPL",
    "gn:name":"Donglukou",
    "gn:population":0,
    "gn:timezone":"Asia/Taipei",
    "iso:country":"TW",
    "name:zho_x_preferred":[
        "\u6771\u9e93\u53e3"
    ],
    "name:zho_x_variant":[
        "Tung-lu-k\u2019ou"
    ],
    "wof:name":"Donglukou",
    "wof:placetype":"locality"
},
  "geometry": {"coordinates":[121.42619000000001,24.86209],"type":"Point"}
}