{
  "type": "Feature",
  "properties": {
    "gn:admin1_code":"4.0",
    "gn:admin2_code":"CYQ",
    "gn:admin3_code":"Q04",
    "gn:admin4_code":"10010040012.0",
    "gn:asciiname":"Qijiao",
    "gn:country_code":"TW",
    "gn:dem":109,
    "gn:feature_class":"P",
    "gn:feature_code":"PPL",
    "gn:name":"Qijiao",
    "gn:population":0,
    "gn:timezone":"Asia/Taipei",
    "iso:country":"TW",
    "name:und_x_variant":[
        "Cijiao"
    ],
    "name:zho_x_preferred":[
        "\u5d0e\u811a"
    ],
    "name:zho_x_variant":[
        "Ch\u2019i-chiao"
    ],
    "wof:name":"Qijiao",
    "wof:placetype":"locality"
},
  "geometry": {"coordinates":[120.52833,23.59528],"type":"Point"}
}