{
  "type": "Feature",
  "properties": {
    "gn:admin1_code":"4.0",
    "gn:admin2_code":"YUN",
    "gn:admin3_code":"P09",
    "gn:admin4_code":"10009090005.0",
    "gn:asciiname":"Heping",
    "gn:country_code":"TW",
    "gn:dem":38,
    "gn:feature_class":"P",
    "gn:feature_code":"PPL",
    "gn:name":"Heping",
    "gn:population":0,
    "gn:timezone":"Asia/Taipei",
    "iso:country":"TW",
    "name:zho_x_preferred":[
        "Li-t\u2019ou-ts\u2019o"
    ],
    "name:zho_x_variant":[
        "Ho-ts\u2019o-li",
        "\u548c\u5e73",
        "Ho-ts\u2019o",
        "Ho-p\u2019ing"
    ],
    "wof:name":"Heping",
    "wof:placetype":"locality"
},
  "geometry": {"coordinates":[120.48994,23.77194],"type":"Point"}
}