{
  "type": "Feature",
  "properties": {
    "gn:admin1_code":"4.0",
    "gn:admin2_code":"YUN",
    "gn:admin3_code":"P12",
    "gn:admin4_code":"10009120012.0",
    "gn:asciiname":"Jiuzhuang",
    "gn:country_code":"TW",
    "gn:dem":15,
    "gn:feature_class":"P",
    "gn:feature_code":"PPL",
    "gn:name":"Jiuzhuang",
    "gn:population":0,
    "gn:timezone":"Asia/Taipei",
    "iso:country":"TW",
    "name:und_x_variant":[
        "Jioujhuang",
        "Chiu-chuang"
    ],
    "name:zho_x_preferred":[
        "Chiu-chuang-ts\u2019un"
    ],
    "name:zho_x_variant":[
        "\u820a\u838a"
    ],
    "wof:name":"Jiuzhuang",
    "wof:placetype":"locality"
},
  "geometry": {"coordinates":[120.32935000000001,23.7869],"type":"Point"}
}