{
  "type": "Feature",
  "properties": {
    "gn:admin1_code":"04",
    "gn:admin2_code":"HSZ",
    "gn:admin3_code":"J05",
    "gn:admin4_code":"10004010005.0",
    "gn:asciiname":"Donghaiku",
    "gn:country_code":"TW",
    "gn:dem":48,
    "gn:feature_class":"P",
    "gn:feature_code":"PPL",
    "gn:name":"Donghaiku",
    "gn:population":0,
    "gn:timezone":"Asia/Taipei",
    "iso:country":"TW",
    "name:zho_x_preferred":[
        "\u6771\u6d77\u7a9f"
    ],
    "name:zho_x_variant":[
        "Tung-hai-k\u2019u"
    ],
    "wof:name":"Donghaiku",
    "wof:placetype":"locality"
},
  "geometry": {"coordinates":[121.04083,24.80806],"type":"Point"}
}