{
  "type": "Feature",
  "properties": {
    "gn:admin1_code":"4.0",
    "gn:admin2_code":"TXG",
    "gn:admin3_code":"B26",
    "gn:admin4_code":"66000260016.0",
    "gn:asciiname":"Wai'ankeng",
    "gn:country_code":"TW",
    "gn:dem":204,
    "gn:feature_class":"P",
    "gn:feature_code":"PPL",
    "gn:name":"Wai\u2019ankeng",
    "gn:population":0,
    "gn:timezone":"Asia/Taipei",
    "iso:country":"TW",
    "name:und_x_variant":[
        "\u5916\u6697\u5751",
        "Wai\u2019ankeng",
        "Wai-an-k\u2019eng"
    ],
    "name:zho_x_preferred":[
        "Wai\u2019ankeng"
    ],
    "name:zho_x_variant":[
        "Wai-an-k\u2019eng"
    ],
    "wof:name":"Wai'ankeng",
    "wof:placetype":"locality"
},
  "geometry": {"coordinates":[120.71332,24.03237],"type":"Point"}
}