{
  "type": "Feature",
  "properties": {
    "gn:admin1_code":"04",
    "gn:admin2_code":"TNN",
    "gn:admin3_code":"R28",
    "gn:admin4_code":"67000280012.0",
    "gn:asciiname":"Wudong",
    "gn:country_code":"TW",
    "gn:dem":23,
    "gn:feature_class":"P",
    "gn:feature_code":"PPL",
    "gn:name":"Wudong",
    "gn:population":0,
    "gn:timezone":"Asia/Taipei",
    "iso:country":"TW",
    "name:und_x_variant":[
        "Wu-tung"
    ],
    "name:zho_x_preferred":[
        "Chung-chu-ts\u2019o"
    ],
    "name:zho_x_variant":[
        "Wu-tung-ts\u2019un",
        "\u6b66\u6771"
    ],
    "wof:name":"Wudong",
    "wof:placetype":"locality"
},
  "geometry": {"coordinates":[120.27333,22.91667],"type":"Point"}
}