{
  "type": "Feature",
  "properties": {
    "gn:admin1_code":"4.0",
    "gn:admin2_code":"CHA",
    "gn:admin3_code":"N23",
    "gn:admin4_code":"10007230023.0",
    "gn:asciiname":"Wanggongliao",
    "gn:country_code":"TW",
    "gn:dem":13,
    "gn:feature_class":"P",
    "gn:feature_code":"PPL",
    "gn:name":"Wanggongliao",
    "gn:population":0,
    "gn:timezone":"Asia/Taipei",
    "iso:country":"TW",
    "name:und_x_variant":[
        "Hsia-wang-kung-liao",
        "Wanggongliao",
        "Wang-kung-liao"
    ],
    "name:zho_x_preferred":[
        "\u738b\u529f\u5bee"
    ],
    "name:zho_x_variant":[
        "Chien-p\u2019ing"
    ],
    "wof:name":"Wanggongliao",
    "wof:placetype":"locality"
},
  "geometry": {"coordinates":[120.39892999999999,23.97217],"type":"Point"}
}