{
  "type": "Feature",
  "properties": {
    "gn:admin1_code":"4.0",
    "gn:admin2_code":"TNN",
    "gn:admin3_code":"R21",
    "gn:admin4_code":"67000210014.0",
    "gn:asciiname":"Hailiao",
    "gn:country_code":"TW",
    "gn:dem":10,
    "gn:feature_class":"P",
    "gn:feature_code":"PPL",
    "gn:name":"Hailiao",
    "gn:population":0,
    "gn:timezone":"Asia/Taipei",
    "iso:country":"TW",
    "name:und_x_variant":[
        "Hsin-liao",
        "Hailiao",
        "An-Liao",
        "Hai-liao"
    ],
    "name:zho_x_preferred":[
        "\u6d77\u5bee"
    ],
    "wof:name":"Hailiao",
    "wof:placetype":"locality"
},
  "geometry": {"coordinates":[120.21250000000001,23.09806],"type":"Point"}
}