{
  "type": "Feature",
  "properties": {
    "iso:country":"TW",
    "qs:name":"\u5c07\u5bcc\u6751",
    "qs:name_adm0":"\u81fa\u7063",
    "qs:name_adm1":"\u53f0\u5357\u5e02",
    "qs:photos":4,
    "qs:photos_1k":1,
    "qs:photos_9k":1,
    "qs:photos_9r":1,
    "qs:photos_all":4,
    "qs:photos_sr":1,
    "qs:placetype":"Town",
    "qs:pop_sr":"0",
    "wof:name":"\u5c07\u5bcc\u6751",
    "wof:placetype":"locality"
},
  "geometry": {"coordinates":[120.13678299999999,23.2255065],"type":"Point"}
}