{
  "type": "Feature",
  "properties": {
    "gn:admin1_code":"4.0",
    "gn:admin2_code":"YUN",
    "gn:admin3_code":"P20",
    "gn:admin4_code":"10009200020.0",
    "gn:asciiname":"Buzi",
    "gn:country_code":"TW",
    "gn:dem":5,
    "gn:feature_class":"P",
    "gn:feature_code":"PPL",
    "gn:name":"Buzi",
    "gn:population":0,
    "gn:timezone":"Asia/Taipei",
    "iso:country":"TW",
    "name:und_x_variant":[
        "Buzih",
        "Buzi",
        "Pu-tzu"
    ],
    "name:zho_x_preferred":[
        "\u57d4\u4ed4"
    ],
    "wof:name":"Buzi",
    "wof:placetype":"locality"
},
  "geometry": {"coordinates":[120.22611000000001,23.51611],"type":"Point"}
}