{
  "type": "Feature",
  "properties": {
    "gn:admin1_code":"4.0",
    "gn:admin2_code":"PIF",
    "gn:admin3_code":"T11",
    "gn:admin4_code":"10013110010.0",
    "gn:asciiname":"Jiuliaocun",
    "gn:country_code":"TW",
    "gn:dem":111,
    "gn:feature_class":"P",
    "gn:feature_code":"PPL",
    "gn:name":"Jiuliaocun",
    "gn:population":0,
    "gn:timezone":"Asia/Taipei",
    "iso:country":"TW",
    "name:und_x_variant":[
        "Jiouliaocun",
        "Chiu-liao"
    ],
    "name:zho_x_preferred":[
        "\u820a\u5bee\u6751"
    ],
    "name:zho_x_variant":[
        "Chiu-liao-ts\u2019un"
    ],
    "wof:name":"Jiuliaocun",
    "wof:placetype":"locality"
},
  "geometry": {"coordinates":[120.61138,22.85068],"type":"Point"}
}