{
  "type": "Feature",
  "properties": {
    "gn:admin1_code":"2.0",
    "gn:admin2_code":"KHH",
    "gn:admin3_code":"E22",
    "gn:admin4_code":"64000220001.0",
    "gn:asciiname":"Zhonglubu",
    "gn:country_code":"TW",
    "gn:dem":86,
    "gn:feature_class":"P",
    "gn:feature_code":"PPL",
    "gn:name":"Zhonglubu",
    "gn:population":0,
    "gn:timezone":"Asia/Taipei",
    "iso:country":"TW",
    "name:und_x_variant":[
        "Ta-lu-pu",
        "Chu-ko-liao",
        "Zhonglubu",
        "Jhonglubu",
        "Chung-lu-pu"
    ],
    "name:zho_x_preferred":[
        "\u4e2d\u9e7f\u57d4"
    ],
    "wof:name":"Zhonglubu",
    "wof:placetype":"locality"
},
  "geometry": {"coordinates":[120.42167000000001,22.88722000000001],"type":"Point"}
}