{
  "type": "Feature",
  "properties": {
    "gn:admin1_code":"4.0",
    "gn:admin2_code":"PEN",
    "gn:admin3_code":"X02",
    "gn:admin4_code":"10016020015.0",
    "gn:asciiname":"Xiashe",
    "gn:country_code":"TW",
    "gn:dem":8,
    "gn:feature_class":"P",
    "gn:feature_code":"PPL",
    "gn:name":"Xiashe",
    "gn:population":0,
    "gn:timezone":"Asia/Taipei",
    "iso:country":"TW",
    "name:und_x_variant":[
        "Hsia-she",
        "Xiashe",
        "Siashe"
    ],
    "name:zho_x_preferred":[
        "\u4e0b\u793e"
    ],
    "wof:name":"Xiashe",
    "wof:placetype":"locality"
},
  "geometry": {"coordinates":[119.62177,23.60499],"type":"Point"}
}