{
  "type": "Feature",
  "properties": {
    "gn:admin1_code":"4.0",
    "gn:admin2_code":"TXG",
    "gn:admin3_code":"B29",
    "gn:admin4_code":"66000290003.0",
    "gn:asciiname":"Bo'aiguoxiao",
    "gn:country_code":"TW",
    "gn:dem":667,
    "gn:feature_class":"P",
    "gn:feature_code":"PPL",
    "gn:name":"Bo\u2019aiguoxiao",
    "gn:population":0,
    "gn:timezone":"Asia/Taipei",
    "iso:country":"TW",
    "name:und_x_variant":[
        "Po-ai-kuo-hsiao"
    ],
    "name:zho_x_preferred":[
        "Bo\u2019aiguoxiao"
    ],
    "wof:name":"Bo'aiguoxiao",
    "wof:placetype":"locality"
},
  "geometry": {"coordinates":[120.98056,24.1775],"type":"Point"}
}