{
  "type": "Feature",
  "properties": {
    "gn:admin1_code":"04",
    "gn:admin2_code":"CHA",
    "gn:admin3_code":"N17",
    "gn:admin4_code":"10007150020.0",
    "gn:asciiname":"Pijiao",
    "gn:country_code":"TW",
    "gn:dem":20,
    "gn:feature_class":"P",
    "gn:feature_code":"PPL",
    "gn:name":"Pijiao",
    "gn:population":0,
    "gn:timezone":"Asia/Taipei",
    "iso:country":"TW",
    "name:zho_x_preferred":[
        "P\u2019i-chiao-ts\u2019un"
    ],
    "name:zho_x_variant":[
        "\u57e4\u8173",
        "P\u2019i-chiao"
    ],
    "wof:name":"Pijiao",
    "wof:placetype":"locality"
},
  "geometry": {"coordinates":[120.52394,23.97666],"type":"Point"}
}