{
  "type": "Feature",
  "properties": {
    "gn:admin1_code":"04",
    "gn:admin2_code":"TXG",
    "gn:admin3_code":"B18",
    "gn:admin4_code":"66000180015.0",
    "gn:asciiname":"Datianxin",
    "gn:country_code":"TW",
    "gn:dem":152,
    "gn:feature_class":"P",
    "gn:feature_code":"PPL",
    "gn:name":"Datianxin",
    "gn:population":0,
    "gn:timezone":"Asia/Taipei",
    "iso:country":"TW",
    "name:und_x_variant":[
        "\u5927\u7530\u5fc3",
        "Datianxin",
        "Datiansin",
        "Ta-t\u2019ien-hsin"
    ],
    "name:zho_x_preferred":[
        "Ta-t\u2019ien-hsin"
    ],
    "wof:name":"Datianxin",
    "wof:placetype":"locality"
},
  "geometry": {"coordinates":[120.65696,24.22614],"type":"Point"}
}