{
  "type": "Feature",
  "properties": {
    "gn:admin1_code":"2.0",
    "gn:admin2_code":"KHH",
    "gn:admin3_code":"E21",
    "gn:admin4_code":"64000210001.0",
    "gn:asciiname":"Bailing",
    "gn:country_code":"TW",
    "gn:dem":69,
    "gn:feature_class":"P",
    "gn:feature_code":"PPL",
    "gn:name":"Bailing",
    "gn:population":0,
    "gn:timezone":"Asia/Taipei",
    "iso:country":"TW",
    "name:und_x_variant":[
        "Pai-ling"
    ],
    "name:zho_x_preferred":[
        "\u767e\u5dba"
    ],
    "wof:name":"Bailing",
    "wof:placetype":"locality"
},
  "geometry": {"coordinates":[120.37917,22.80694],"type":"Point"}
}