{
  "type": "Feature",
  "properties": {
    "gn:admin1_code":"4.0",
    "gn:admin2_code":"ILA",
    "gn:admin3_code":"G08",
    "gn:admin4_code":"10002080012.0",
    "gn:asciiname":"Linggongyuan",
    "gn:country_code":"TW",
    "gn:dem":11,
    "gn:feature_class":"P",
    "gn:feature_code":"PPL",
    "gn:name":"Linggongyuan",
    "gn:population":0,
    "gn:timezone":"Asia/Taipei",
    "iso:country":"TW",
    "name:und_x_variant":[
        "Ling-kung-wei"
    ],
    "name:zho_x_preferred":[
        "\u96f6\u5de5\u5712"
    ],
    "name:zho_x_variant":[
        "Ling-kung-y\u00fcan"
    ],
    "wof:name":"Linggongyuan",
    "wof:placetype":"locality"
},
  "geometry": {"coordinates":[121.7621,24.6349],"type":"Point"}
}