{
  "type": "Feature",
  "properties": {
    "iso:country":"TW",
    "name:eng_x_preferred":[
        "Erjie"
    ],
    "name:eng_x_variant":[
        "Erjie Village"
    ],
    "name:zho_tw_x_preferred":[
        "\u4e8c\u7d50\u6751"
    ],
    "qs:name":"\u4e8c\u7d50\u6751",
    "qs:name_adm0":"\u81fa\u7063",
    "qs:name_adm1":"\u5b9c\u862d\u7e23",
    "qs:photos":640,
    "qs:photos_1k":130,
    "qs:photos_9k":3,
    "qs:photos_9r":5,
    "qs:photos_all":640,
    "qs:photos_sr":8,
    "qs:placetype":"Town",
    "qs:pop_sr":"0",
    "wof:name":"Erjie",
    "wof:placetype":"locality"
},
  "geometry": {"coordinates":[121.67735999999999,24.807616],"type":"Point"}
}