{
  "type": "Feature",
  "properties": {
    "gn:admin1_code":"04",
    "gn:admin2_code":"TNN",
    "gn:admin3_code":"R04",
    "gn:admin4_code":"67000040013.0",
    "gn:asciiname":"Mabu",
    "gn:country_code":"TW",
    "gn:dem":60,
    "gn:feature_class":"P",
    "gn:feature_code":"PPL",
    "gn:name":"Mabu",
    "gn:population":0,
    "gn:timezone":"Asia/Taipei",
    "iso:country":"TW",
    "name:ceb_x_preferred":[
        "Mabu"
    ],
    "name:rus_x_preferred":[
        "\u041c\u0430\u0431\u0443"
    ],
    "name:swe_x_preferred":[
        "Mabu"
    ],
    "name:und_x_variant":[
        "Ma-pu"
    ],
    "name:zho_x_preferred":[
        "\u9ebb\u57d4"
    ],
    "wof:name":"Mabu",
    "wof:placetype":"locality"
},
  "geometry": {"coordinates":[120.39028,23.25333],"type":"Point"}
}