{
  "type": "Feature",
  "properties": {
    "gn:admin1_code":"3.0",
    "gn:admin2_code":"TPQ",
    "gn:admin3_code":"F25",
    "gn:admin4_code":"65000270006.0",
    "gn:asciiname":"Fenjihu",
    "gn:country_code":"TW",
    "gn:dem":31,
    "gn:feature_class":"P",
    "gn:feature_code":"PPL",
    "gn:name":"Fenjihu",
    "gn:population":0,
    "gn:timezone":"Asia/Taipei",
    "iso:country":"TW",
    "name:und_x_variant":[
        "Fen-chi-hu"
    ],
    "name:zho_x_preferred":[
        "\u7cde\u7b95\u6e56"
    ],
    "wof:name":"Fenjihu",
    "wof:placetype":"locality"
},
  "geometry": {"coordinates":[121.62067,25.2159],"type":"Point"}
}