{
  "type": "Feature",
  "properties": {
    "gn:admin1_code":"04",
    "gn:admin2_code":"MIA",
    "gn:admin3_code":"K14",
    "gn:admin4_code":"10005110009.0",
    "gn:asciiname":"Egongji",
    "gn:country_code":"TW",
    "gn:dem":546,
    "gn:feature_class":"P",
    "gn:feature_code":"PPL",
    "gn:name":"Egongji",
    "gn:population":0,
    "gn:timezone":"Asia/Taipei",
    "iso:country":"TW",
    "name:und_x_variant":[
        "O-kung-chi"
    ],
    "name:zho_x_preferred":[
        "\u9d5d\u516c\u9afb"
    ],
    "wof:name":"Egongji",
    "wof:placetype":"locality"
},
  "geometry": {"coordinates":[121.05389,24.60611],"type":"Point"}
}