{
  "type": "Feature",
  "properties": {
    "gn:admin1_code":"04",
    "gn:admin2_code":"NAN",
    "gn:admin3_code":"M08",
    "gn:admin4_code":"10008080009.0",
    "gn:asciiname":"Daozhang",
    "gn:country_code":"TW",
    "gn:dem":126,
    "gn:feature_class":"P",
    "gn:feature_code":"PPL",
    "gn:name":"Daozhang",
    "gn:population":0,
    "gn:timezone":"Asia/Taipei",
    "iso:country":"TW",
    "name:und_x_variant":[
        "Daojhang",
        "Daozhang",
        "Tao-chang"
    ],
    "name:zho_x_preferred":[
        "\u5012\u6a1f"
    ],
    "wof:name":"Daozhang",
    "wof:placetype":"locality"
},
  "geometry": {"coordinates":[120.7462,23.8912],"type":"Point"}
}