{
  "type": "Feature",
  "properties": {
    "gn:admin1_code":"4.0",
    "gn:admin2_code":"YUN",
    "gn:admin3_code":"P15",
    "gn:admin4_code":"10009150009.0",
    "gn:asciiname":"Chaocuo",
    "gn:country_code":"TW",
    "gn:dem":15,
    "gn:feature_class":"P",
    "gn:feature_code":"PPL",
    "gn:name":"Chaocuo",
    "gn:population":0,
    "gn:timezone":"Asia/Taipei",
    "iso:country":"TW",
    "name:zho_x_preferred":[
        "Wang-ts\u2019o-liao"
    ],
    "name:zho_x_variant":[
        "\u6f6e\u539d",
        "Ch\u2019ao-yang-ts\u2019o",
        "Ch\u2019ao-ts\u2019o"
    ],
    "wof:name":"Chaocuo",
    "wof:placetype":"locality"
},
  "geometry": {"coordinates":[120.33583,23.71501],"type":"Point"}
}