{
  "type": "Feature",
  "properties": {
    "gn:admin1_code":"03",
    "gn:admin2_code":"TPQ",
    "gn:admin3_code":"F22",
    "gn:admin4_code":"65000240008.0",
    "gn:asciiname":"Wanggukeng",
    "gn:country_code":"TW",
    "gn:dem":233,
    "gn:feature_class":"P",
    "gn:feature_code":"PPL",
    "gn:name":"Wanggukeng",
    "gn:population":0,
    "gn:timezone":"Asia/Taipei",
    "iso:country":"TW",
    "name:zho_x_preferred":[
        "\u671b\u53e4\u5751"
    ],
    "name:zho_x_variant":[
        "Wang-ku-k\u2019eng"
    ],
    "wof:name":"Wanggukeng",
    "wof:placetype":"locality"
},
  "geometry": {"coordinates":[121.75872,25.03758],"type":"Point"}
}