{
  "type": "Feature",
  "properties": {
    "gn:admin1_code":"3.0",
    "gn:admin2_code":"TPQ",
    "gn:admin3_code":"F22",
    "gn:admin4_code":"65000240010.0",
    "gn:asciiname":"Fanzikeng",
    "gn:country_code":"TW",
    "gn:dem":320,
    "gn:feature_class":"P",
    "gn:feature_code":"PPL",
    "gn:name":"Fanzikeng",
    "gn:population":0,
    "gn:timezone":"Asia/Taipei",
    "iso:country":"TW",
    "name:und_x_variant":[
        "Fanzihkeng"
    ],
    "name:zho_x_preferred":[
        "\u756a\u4ed4\u5751"
    ],
    "name:zho_x_variant":[
        "Fan-tzu-k\u2019eng"
    ],
    "wof:name":"Fanzikeng",
    "wof:placetype":"locality"
},
  "geometry": {"coordinates":[121.79470000000001,25.0308],"type":"Point"}
}