{
  "type": "Feature",
  "properties": {
    "gn:admin1_code":"04",
    "gn:admin2_code":"HUA",
    "gn:admin3_code":"U08",
    "gn:admin4_code":"10015080001.0",
    "gn:asciiname":"Baliwan",
    "gn:country_code":"TW",
    "gn:dem":78,
    "gn:feature_class":"P",
    "gn:feature_code":"PPL",
    "gn:name":"Baliwan",
    "gn:population":0,
    "gn:timezone":"Asia/Taipei",
    "iso:country":"TW",
    "name:und_x_variant":[
        "Pa-li-wan"
    ],
    "name:zho_x_preferred":[
        "\u516b\u91cc\u7063"
    ],
    "wof:name":"Baliwan",
    "wof:placetype":"locality"
},
  "geometry": {"coordinates":[121.48617,23.56755],"type":"Point"}
}