{
  "type": "Feature",
  "properties": {
    "gn:admin1_code":"4.0",
    "gn:admin2_code":"CHA",
    "gn:admin3_code":"N13",
    "gn:admin4_code":"10007080001.0",
    "gn:asciiname":"Huatan",
    "gn:country_code":"TW",
    "gn:dem":20,
    "gn:feature_class":"P",
    "gn:feature_code":"PPL",
    "gn:name":"Huatan",
    "gn:population":0,
    "gn:timezone":"Asia/Taipei",
    "iso:country":"TW",
    "name:und_x_variant":[
        "Ch\u2019ieh-tung-chiao",
        "Hua-t\u2019an"
    ],
    "name:zho_x_preferred":[
        "Hua-t\u2019an"
    ],
    "wof:name":"Huatan",
    "wof:placetype":"locality"
},
  "geometry": {"coordinates":[120.53807,24.02718],"type":"Point"}
}