{
  "type": "Feature",
  "properties": {
    "gn:admin1_code":"4.0",
    "gn:admin2_code":"MIA",
    "gn:admin3_code":"K17",
    "gn:admin4_code":"10005170004.0",
    "gn:asciiname":"Shishuikeng",
    "gn:country_code":"TW",
    "gn:dem":305,
    "gn:feature_class":"P",
    "gn:feature_code":"PPL",
    "gn:name":"Shishuikeng",
    "gn:population":0,
    "gn:timezone":"Asia/Taipei",
    "iso:country":"TW",
    "name:und_x_variant":[
        "Shihshueikeng"
    ],
    "name:zho_x_preferred":[
        "\u98df\u6c34\u5751"
    ],
    "name:zho_x_variant":[
        "Shih-shui-k\u2019eng"
    ],
    "wof:name":"Shishuikeng",
    "wof:placetype":"locality"
},
  "geometry": {"coordinates":[120.91995,24.51622],"type":"Point"}
}