{
  "type": "Feature",
  "properties": {
    "gn:admin1_code":"4.0",
    "gn:admin2_code":"TNN",
    "gn:admin3_code":"R30",
    "gn:admin4_code":"67000300001.0",
    "gn:asciiname":"Qiding",
    "gn:country_code":"TW",
    "gn:dem":93,
    "gn:feature_class":"P",
    "gn:feature_code":"PPL",
    "gn:name":"Qiding",
    "gn:population":0,
    "gn:timezone":"Asia/Taipei",
    "iso:country":"TW",
    "name:und_x_variant":[
        "Ciding"
    ],
    "name:zho_x_preferred":[
        "Ting-ch\u2019i"
    ],
    "name:zho_x_variant":[
        "\u5d0e\u9802",
        "Ch\u2019i-ting"
    ],
    "wof:name":"Qiding",
    "wof:placetype":"locality"
},
  "geometry": {"coordinates":[120.36917,22.95806],"type":"Point"}
}