{
  "type": "Feature",
  "properties": {
    "gn:admin1_code":"04",
    "gn:admin2_code":"HSZ",
    "gn:admin3_code":"J10",
    "gn:admin4_code":"10004070011.0",
    "gn:asciiname":"Shangshan",
    "gn:country_code":"TW",
    "gn:dem":101,
    "gn:feature_class":"P",
    "gn:feature_code":"PPL",
    "gn:name":"Shangshan",
    "gn:population":0,
    "gn:timezone":"Asia/Taipei",
    "iso:country":"TW",
    "name:und_x_variant":[
        "Shang-shan"
    ],
    "name:zho_x_preferred":[
        "\u4e0a\u5c71"
    ],
    "wof:name":"Shangshan",
    "wof:placetype":"locality"
},
  "geometry": {"coordinates":[121.075,24.78972000000001],"type":"Point"}
}