{
  "type": "Feature",
  "properties": {
    "gn:admin1_code":"4.0",
    "gn:admin2_code":"TNN",
    "gn:admin3_code":"R06",
    "gn:admin4_code":"67000060014.0",
    "gn:asciiname":"Guocuo",
    "gn:country_code":"TW",
    "gn:dem":120,
    "gn:feature_class":"P",
    "gn:feature_code":"PPL",
    "gn:name":"Guocuo",
    "gn:population":0,
    "gn:timezone":"Asia/Taipei",
    "iso:country":"TW",
    "name:zho_x_preferred":[
        "\u90ed\u539d"
    ],
    "name:zho_x_variant":[
        "Kuo-ts\u2019o"
    ],
    "wof:name":"Guocuo",
    "wof:placetype":"locality"
},
  "geometry": {"coordinates":[120.465,23.27583],"type":"Point"}
}