{
  "type": "Feature",
  "properties": {
    "gn:admin1_code":"4.0",
    "gn:admin2_code":"CYQ",
    "gn:admin3_code":"Q18",
    "gn:admin4_code":"10010170005.0",
    "gn:asciiname":"Maobu",
    "gn:country_code":"TW",
    "gn:dem":302,
    "gn:feature_class":"P",
    "gn:feature_code":"PPL",
    "gn:name":"Maobu",
    "gn:population":0,
    "gn:timezone":"Asia/Taipei",
    "iso:country":"TW",
    "name:und_x_variant":[
        "Mao-pu"
    ],
    "name:zho_x_preferred":[
        "\u8305\u57d4"
    ],
    "wof:name":"Maobu",
    "wof:placetype":"locality"
},
  "geometry": {"coordinates":[120.535,23.24306],"type":"Point"}
}