{
  "type": "Feature",
  "properties": {
    "gn:admin1_code":"4.0",
    "gn:admin2_code":"TAO",
    "gn:admin3_code":"H08",
    "gn:admin4_code":"68000080040.0",
    "gn:asciiname":"Gouhou",
    "gn:country_code":"TW",
    "gn:dem":142,
    "gn:feature_class":"P",
    "gn:feature_code":"PPL",
    "gn:name":"Gouhou",
    "gn:population":0,
    "gn:timezone":"Asia/Taipei",
    "iso:country":"TW",
    "name:und_x_variant":[
        "Kou-hou"
    ],
    "name:zho_x_preferred":[
        "\u6e9d\u5f8c"
    ],
    "wof:name":"Gouhou",
    "wof:placetype":"locality"
},
  "geometry": {"coordinates":[121.28972,24.93484],"type":"Point"}
}