{
  "type": "Feature",
  "properties": {
    "gn:admin1_code":"4.0",
    "gn:admin2_code":"HSZ",
    "gn:admin3_code":"J08",
    "gn:admin4_code":"10004080001.0",
    "gn:asciiname":"Cukeng",
    "gn:country_code":"TW",
    "gn:dem":213,
    "gn:feature_class":"P",
    "gn:feature_code":"PPL",
    "gn:name":"Cukeng",
    "gn:population":0,
    "gn:timezone":"Asia/Taipei",
    "iso:country":"TW",
    "name:zho_x_preferred":[
        "\u7c97\u5751"
    ],
    "name:zho_x_variant":[
        "Ts\u2019u-k\u2019eng"
    ],
    "wof:name":"Cukeng",
    "wof:placetype":"locality"
},
  "geometry": {"coordinates":[121.13889,24.70639],"type":"Point"}
}