{
  "type": "Feature",
  "properties": {
    "gn:admin1_code":"4.0",
    "gn:admin2_code":"PIF",
    "gn:admin3_code":"T03",
    "gn:admin4_code":"10013030020.0",
    "gn:asciiname":"Haiping",
    "gn:country_code":"TW",
    "gn:dem":5,
    "gn:feature_class":"P",
    "gn:feature_code":"PPL",
    "gn:name":"Haiping",
    "gn:population":0,
    "gn:timezone":"Asia/Taipei",
    "iso:country":"TW",
    "name:zho_x_preferred":[
        "\u6d77\u576a"
    ],
    "name:zho_x_variant":[
        "Hai-p\u2019ing"
    ],
    "wof:name":"Haiping",
    "wof:placetype":"locality"
},
  "geometry": {"coordinates":[120.47306,22.48876],"type":"Point"}
}