{
  "type": "Feature",
  "properties": {
    "gn:admin1_code":"04",
    "gn:admin2_code":"YUN",
    "gn:admin3_code":"P03",
    "gn:admin4_code":"10009030024.0",
    "gn:asciiname":"Guoxizi",
    "gn:country_code":"TW",
    "gn:dem":33,
    "gn:feature_class":"P",
    "gn:feature_code":"PPL",
    "gn:name":"Guoxizi",
    "gn:population":0,
    "gn:timezone":"Asia/Taipei",
    "iso:country":"TW",
    "name:und_x_variant":[
        "Ting-hsi-li",
        "Guoxizi",
        "Guosizih",
        "Ting-hsi",
        "Kuo-hsi-tzu"
    ],
    "name:zho_x_preferred":[
        "Ting-ch\u2019i-li"
    ],
    "name:zho_x_variant":[
        "\u904e\u6eaa\u5b50"
    ],
    "wof:name":"Guoxizi",
    "wof:placetype":"locality"
},
  "geometry": {"coordinates":[120.46495,23.72939],"type":"Point"}
}