{
  "type": "Feature",
  "properties": {
    "iso:country":"TW",
    "name:eng_x_preferred":[
        "Neipu"
    ],
    "name:eng_x_variant":[
        "Neipu Township"
    ],
    "name:zho_tw_x_preferred":[
        "\u5167\u57d4\u9109"
    ],
    "qs:name":"\u5167\u57d4\u9109",
    "qs:name_adm0":"\u81fa\u7063",
    "qs:name_adm1":"\u5c4f\u6771\u7e23",
    "qs:photos":189,
    "qs:photos_1k":38,
    "qs:photos_9k":4,
    "qs:photos_9r":6,
    "qs:photos_all":1000,
    "qs:photos_sr":4,
    "qs:placetype":"County",
    "qs:pop_sr":"0",
    "wof:name":"Neipu",
    "wof:placetype":"county"
},
  "geometry": {"coordinates":[120.566604,22.621438],"type":"Point"}
}