{
  "type": "Feature",
  "properties": {
    "gn:admin1_code":"4.0",
    "gn:admin2_code":"TNN",
    "gn:admin3_code":"R15",
    "gn:admin4_code":"67000160001.0",
    "gn:asciiname":"Ch'ang-jung",
    "gn:country_code":"TW",
    "gn:dem":11,
    "gn:feature_class":"P",
    "gn:feature_code":"PPL",
    "gn:name":"Ch'ang-jung",
    "gn:population":0,
    "gn:timezone":"Asia/Taipei",
    "iso:country":"TW",
    "name:und_x_variant":[
        "Changrong",
        "Chu-tzu-chiao"
    ],
    "wof:name":"Ch'ang-jung",
    "wof:placetype":"locality"
},
  "geometry": {"coordinates":[120.15667000000001,23.19389],"type":"Point"}
}