{
  "type": "Feature",
  "properties": {
    "gn:admin1_code":"04",
    "gn:admin2_code":"PIF",
    "gn:admin3_code":"T02",
    "gn:admin4_code":"10013020011.0",
    "gn:asciiname":"Datiedian",
    "gn:country_code":"TW",
    "gn:dem":15,
    "gn:feature_class":"P",
    "gn:feature_code":"PPL",
    "gn:name":"Datiedian",
    "gn:population":0,
    "gn:timezone":"Asia/Taipei",
    "iso:country":"TW",
    "name:und_x_variant":[
        "P\u2019eng-lai-li",
        "Datiedian"
    ],
    "name:zho_x_preferred":[
        "\u6253\u9435\u5e97"
    ],
    "name:zho_x_variant":[
        "P\u2019eng-lai",
        "Ta-t\u2019ieh-tien"
    ],
    "wof:name":"Datiedian",
    "wof:placetype":"locality"
},
  "geometry": {"coordinates":[120.53440999999999,22.55202],"type":"Point"}
}