{
  "type": "Feature",
  "properties": {
    "gn:admin1_code":"3.0",
    "gn:admin2_code":"TPQ",
    "gn:admin3_code":"F03",
    "gn:admin4_code":"65000150018.0",
    "gn:asciiname":"Qiganhu",
    "gn:country_code":"TW",
    "gn:dem":144,
    "gn:feature_class":"P",
    "gn:feature_code":"PPL",
    "gn:name":"Qiganhu",
    "gn:population":0,
    "gn:timezone":"Asia/Taipei",
    "iso:country":"TW",
    "name:und_x_variant":[
        "Ciganhu"
    ],
    "name:zho_x_preferred":[
        "\u65d7\u7aff\u6e56"
    ],
    "name:zho_x_variant":[
        "Ch\u2019i-kan-hu"
    ],
    "wof:name":"Qiganhu",
    "wof:placetype":"locality"
},
  "geometry": {"coordinates":[121.42688,25.10323],"type":"Point"}
}