{
  "type": "Feature",
  "properties": {
    "gn:admin1_code":"4.0",
    "gn:admin2_code":"TNN",
    "gn:admin3_code":"R26",
    "gn:admin4_code":"67000260010.0",
    "gn:asciiname":"Kengzikou",
    "gn:country_code":"TW",
    "gn:dem":128,
    "gn:feature_class":"P",
    "gn:feature_code":"PPL",
    "gn:name":"Kengzikou",
    "gn:population":0,
    "gn:timezone":"Asia/Taipei",
    "iso:country":"TW",
    "name:und_x_variant":[
        "Kengzihkou"
    ],
    "name:zho_x_preferred":[
        "\u5751\u5b50\u53e3"
    ],
    "name:zho_x_variant":[
        "K\u2019eng-tzu-k\u2019ou"
    ],
    "wof:name":"Kengzikou",
    "wof:placetype":"locality"
},
  "geometry": {"coordinates":[120.40389,22.99361],"type":"Point"}
}