{
  "type": "Feature",
  "properties": {
    "gn:admin1_code":"4.0",
    "gn:admin2_code":"CYQ",
    "gn:admin3_code":"Q15",
    "gn:admin4_code":"10010140009.0",
    "gn:asciiname":"Shangxixin",
    "gn:country_code":"TW",
    "gn:dem":86,
    "gn:feature_class":"P",
    "gn:feature_code":"PPL",
    "gn:name":"Shangxixin",
    "gn:population":0,
    "gn:timezone":"Asia/Taipei",
    "iso:country":"TW",
    "name:und_x_variant":[
        "Hsi-hsin",
        "Shangsisin",
        "Shangxixin",
        "Shang-hsi-hsin"
    ],
    "name:zho_x_preferred":[
        "Ch\u2019i-hsin"
    ],
    "name:zho_x_variant":[
        "\u4e0a\u6eaa\u5fc3"
    ],
    "wof:name":"Shangxixin",
    "wof:placetype":"locality"
},
  "geometry": {"coordinates":[120.53111,23.50528],"type":"Point"}
}