{
  "type": "Feature",
  "properties": {
    "gn:admin1_code":"3.0",
    "gn:admin2_code":"TPQ",
    "gn:admin3_code":"F24",
    "gn:admin4_code":"65000260009.0",
    "gn:asciiname":"Daxianglan",
    "gn:country_code":"TW",
    "gn:dem":2,
    "gn:feature_class":"P",
    "gn:feature_code":"PPL",
    "gn:name":"Daxianglan",
    "gn:population":0,
    "gn:timezone":"Asia/Taipei",
    "iso:country":"TW",
    "name:und_x_variant":[
        "Dasianglan",
        "Ta-hsiang-lan"
    ],
    "name:zho_x_preferred":[
        "\u5927\u9999\u862d"
    ],
    "wof:name":"Daxianglan",
    "wof:placetype":"locality"
},
  "geometry": {"coordinates":[121.98453000000001,25.02219],"type":"Point"}
}