{
  "type": "Feature",
  "properties": {
    "gn:admin1_code":"4.0",
    "gn:admin2_code":"TPE",
    "gn:admin3_code":"A11",
    "gn:admin4_code":"63000080036.0",
    "gn:asciiname":"Dakeng",
    "gn:country_code":"TW",
    "gn:dem":90,
    "gn:feature_class":"P",
    "gn:feature_code":"PPL",
    "gn:name":"Dakeng",
    "gn:population":0,
    "gn:timezone":"Asia/Taipei",
    "iso:country":"TW",
    "name:zho_x_preferred":[
        "\u5927\u5751"
    ],
    "name:zho_x_variant":[
        "Ta-k\u2019eng"
    ],
    "wof:name":"Dakeng",
    "wof:placetype":"locality"
},
  "geometry": {"coordinates":[121.58208999999999,24.97651],"type":"Point"}
}