{
  "type": "Feature",
  "properties": {
    "gn:admin1_code":"04",
    "gn:admin2_code":"CHA",
    "gn:admin3_code":"N13",
    "gn:admin4_code":"10007080015.0",
    "gn:asciiname":"Wanzikou",
    "gn:country_code":"TW",
    "gn:dem":25,
    "gn:feature_class":"P",
    "gn:feature_code":"PPL",
    "gn:name":"Wanzikou",
    "gn:population":0,
    "gn:timezone":"Asia/Taipei",
    "iso:country":"TW",
    "name:und_x_variant":[
        "\u7063\u5b50\u53e3",
        "Wanzihkou",
        "Wanzikou",
        "Wan-tzu-k\u2019ou"
    ],
    "name:zho_x_preferred":[
        "Wan-tzu-k\u2019ou"
    ],
    "wof:name":"Wanzikou",
    "wof:placetype":"locality"
},
  "geometry": {"coordinates":[120.56278,24.01876],"type":"Point"}
}