{
  "type": "Feature",
  "properties": {
    "gn:admin1_code":"03",
    "gn:admin2_code":"TPQ",
    "gn:admin3_code":"F17",
    "gn:admin4_code":"65000070022.0",
    "gn:asciiname":"Shitouxi",
    "gn:country_code":"TW",
    "gn:dem":32,
    "gn:feature_class":"P",
    "gn:feature_code":"PPL",
    "gn:name":"Shitouxi",
    "gn:population":0,
    "gn:timezone":"Asia/Taipei",
    "iso:country":"TW",
    "name:und_x_variant":[
        "Shihtousi",
        "Shitouxi"
    ],
    "name:zho_x_preferred":[
        "Shih-t\u2019ou-ch\u2019i"
    ],
    "name:zho_x_variant":[
        "\u77f3\u982d\u6eaa",
        "Shih-t\u2019ou-hsi"
    ],
    "wof:name":"Shitouxi",
    "wof:placetype":"locality"
},
  "geometry": {"coordinates":[121.39619999999999,24.95574],"type":"Point"}
}