{
  "type": "Feature",
  "properties": {
    "gn:admin1_code":"4.0",
    "gn:admin2_code":"CYQ",
    "gn:admin3_code":"Q18",
    "gn:admin4_code":"10010170003.0",
    "gn:asciiname":"Fenshuiling",
    "gn:country_code":"TW",
    "gn:dem":762,
    "gn:feature_class":"P",
    "gn:feature_code":"PPL",
    "gn:name":"Fenshuiling",
    "gn:population":0,
    "gn:timezone":"Asia/Taipei",
    "iso:country":"TW",
    "name:und_x_variant":[
        "Fenshueiling",
        "Feng-shui-ling",
        "Fenshuiling",
        "Fen-shui-ling"
    ],
    "name:zho_x_preferred":[
        "\u5206\u6c34\u5dba"
    ],
    "wof:name":"Fenshuiling",
    "wof:placetype":"locality"
},
  "geometry": {"coordinates":[120.57953000000001,23.35969],"type":"Point"}
}