{
  "type": "Feature",
  "properties": {
    "gn:admin1_code":"4.0",
    "gn:admin2_code":"YUN",
    "gn:admin3_code":"P07",
    "gn:admin4_code":"10009070011.0",
    "gn:asciiname":"Neiguan",
    "gn:country_code":"TW",
    "gn:dem":256,
    "gn:feature_class":"P",
    "gn:feature_code":"PPL",
    "gn:name":"Neiguan",
    "gn:population":0,
    "gn:timezone":"Asia/Taipei",
    "iso:country":"TW",
    "name:und_x_variant":[
        "Nei-kuan"
    ],
    "name:zho_x_preferred":[
        "\u5167\u9928"
    ],
    "wof:name":"Neiguan",
    "wof:placetype":"locality"
},
  "geometry": {"coordinates":[120.58389,23.61361],"type":"Point"}
}