{
  "type": "Feature",
  "properties": {
    "gn:admin1_code":"01",
    "gn:admin2_code":"KIN",
    "gn:admin3_code":"W04",
    "gn:admin4_code":"9020040001.0",
    "gn:asciiname":"Beishan",
    "gn:country_code":"TW",
    "gn:dem":14,
    "gn:feature_class":"P",
    "gn:feature_code":"PPL",
    "gn:name":"Beishan",
    "gn:population":0,
    "gn:timezone":"Asia/Taipei",
    "iso:country":"TW",
    "name:und_x_variant":[
        "Pei-shan"
    ],
    "name:zho_x_preferred":[
        "\u5317\u5c71"
    ],
    "wof:name":"Beishan",
    "wof:placetype":"locality"
},
  "geometry": {"coordinates":[118.31179,24.48047],"type":"Point"}
}