{
  "type": "Feature",
  "properties": {
    "gn:admin1_code":"4.0",
    "gn:admin2_code":"HUA",
    "gn:admin3_code":"U03",
    "gn:admin4_code":"10015030011.0",
    "gn:asciiname":"Wanli",
    "gn:country_code":"TW",
    "gn:dem":159,
    "gn:feature_class":"P",
    "gn:feature_code":"PPL",
    "gn:name":"Wanli",
    "gn:population":0,
    "gn:timezone":"Asia/Taipei",
    "iso:country":"TW",
    "name:und_x_variant":[
        "Wan-li"
    ],
    "name:zho_x_preferred":[
        "\u842c\u9e97"
    ],
    "wof:name":"Wanli",
    "wof:placetype":"locality"
},
  "geometry": {"coordinates":[121.38871,23.42963],"type":"Point"}
}