{
  "type": "Feature",
  "properties": {
    "gn:admin1_code":"4.0",
    "gn:admin2_code":"TNN",
    "gn:admin3_code":"R14",
    "gn:admin4_code":"67000150020.0",
    "gn:asciiname":"Beikanglang",
    "gn:country_code":"TW",
    "gn:dem":8,
    "gn:feature_class":"P",
    "gn:feature_code":"PPL",
    "gn:name":"Beikanglang",
    "gn:population":0,
    "gn:timezone":"Asia/Taipei",
    "iso:country":"TW",
    "name:zho_x_preferred":[
        "Pei-k\u2019ang-lang"
    ],
    "name:zho_x_variant":[
        "K\u2019ang-lang-ts\u2019un",
        "K\u2019ang-hsiang",
        "K\u2019ang-lang",
        "K\u2019ang-hsiang-ts\u2019un",
        "\u5317\u69fa\u6994"
    ],
    "wof:name":"Beikanglang",
    "wof:placetype":"locality"
},
  "geometry": {"coordinates":[120.14417,23.09694],"type":"Point"}
}