{
  "type": "Feature",
  "properties": {
    "gn:admin1_code":"4.0",
    "gn:admin2_code":"TTT",
    "gn:admin3_code":"V10",
    "gn:admin4_code":"10014060010.0",
    "gn:asciiname":"Rishecun",
    "gn:country_code":"TW",
    "gn:dem":225,
    "gn:feature_class":"P",
    "gn:feature_code":"PPL",
    "gn:name":"Rishecun",
    "gn:population":0,
    "gn:timezone":"Asia/Taipei",
    "iso:country":"TW",
    "name:und_x_variant":[
        "Jih-she",
        "Jih-she-ts\u2019un",
        "Rishecun"
    ],
    "wof:name":"Rishecun",
    "wof:placetype":"locality"
},
  "geometry": {"coordinates":[121.18333,23.03333],"type":"Point"}
}