{
  "type": "Feature",
  "properties": {
    "gn:admin1_code":"4.0",
    "gn:admin2_code":"YUN",
    "gn:admin3_code":"P10",
    "gn:admin4_code":"10009100002.0",
    "gn:asciiname":"Chang'an",
    "gn:country_code":"TW",
    "gn:dem":72,
    "gn:feature_class":"P",
    "gn:feature_code":"PPL",
    "gn:name":"Chang\u2019an",
    "gn:population":0,
    "gn:timezone":"Asia/Taipei",
    "iso:country":"TW",
    "name:und_x_variant":[
        "Hsia-wei-liao"
    ],
    "name:zho_x_preferred":[
        "\u9577\u5b89"
    ],
    "name:zho_x_variant":[
        "Chang\u2019an",
        "Ch\u2019ang-an"
    ],
    "wof:name":"Chang'an",
    "wof:placetype":"locality"
},
  "geometry": {"coordinates":[120.60148999999998,23.75792],"type":"Point"}
}