{
  "type": "Feature",
  "properties": {
    "gn:admin1_code":"4.0",
    "gn:admin2_code":"YUN",
    "gn:admin3_code":"P10",
    "gn:admin4_code":"10009100002.0",
    "gn:asciiname":"Chang'an",
    "gn:country_code":"TW",
    "gn:dem":72,
    "gn:feature_class":"P",
    "gn:feature_code":"PPL",
    "gn:name":"Chang\u2019an",
    "gn:population":0,
    "gn:timezone":"Asia/Taipei",
    "iso:country":"TW",
    "name:als_x_preferred":[
        "Chang'an"
    ],
    "name:ara_x_preferred":[
        "\u062a\u0634\u0627\u0646\u063a\u0622\u0646"
    ],
    "name:aze_x_preferred":[
        "\u00c7anqan"
    ],
    "name:bod_x_preferred":[
        "\u0f67\u0fb2\u0f44\u0f0b\u0f68\u0f53\u0f0d"
    ],
    "name:cat_x_preferred":[
        "Chang'an"
    ],
    "name:deu_x_preferred":[
        "Chang\u2019an"
    ],
    "name:epo_x_preferred":[
        "\u0108angano"
    ],
    "name:est_x_preferred":[
        "Chang'an"
    ],
    "name:fas_x_preferred":[
        "\u0686\u0627\u0646\u06af\u200c\u0622\u0646"
    ],
    "name:hin_x_preferred":[
        "\u091a\u093e\u0902\u0917\u0906\u0928"
    ],
    "name:ind_x_preferred":[
        "Chang'an"
    ],
    "name:ita_x_preferred":[
        "Chang'an"
    ],
    "name:kat_x_preferred":[
        "\u10e9\u10d0\u10dc\u10d0\u10dc\u10d8"
    ],
    "name:msa_x_preferred":[
        "Chang'an"
    ],
    "name:nld_x_preferred":[
        "Chang'an"
    ],
    "name:nor_x_preferred":[
        "Chang'an"
    ],
    "name:por_x_preferred":[
        "Changan"
    ],
    "name:rus_x_preferred":[
        "\u0427\u0430\u043d\u044a\u0430\u043d\u044c"
    ],
    "name:sco_x_preferred":[
        "Chang'an"
    ],
    "name:spa_x_preferred":[
        "Chang'an"
    ],
    "name:swe_x_preferred":[
        "Chang\u2019an"
    ],
    "name:tha_x_preferred":[
        "\u0e09\u0e32\u0e07\u0e2d\u0e32\u0e19"
    ],
    "name:tur_x_preferred":[
        "\u00c7angan"
    ],
    "name:ukr_x_preferred":[
        "\u0427\u0430\u043d\u0430\u043d\u044c"
    ],
    "name:und_x_variant":[
        "Hsia-wei-liao"
    ],
    "name:urd_x_preferred":[
        "\u0686\u0627\u0646\u06af \u0622\u0646"
    ],
    "name:vie_x_preferred":[
        "Tr\u01b0\u1eddng An"
    ],
    "name:zho_x_preferred":[
        "\u9577\u5b89"
    ],
    "name:zho_x_variant":[
        "Chang\u2019an",
        "Ch\u2019ang-an"
    ],
    "wof:name":"Chang'an",
    "wof:placetype":"locality"
},
  "geometry": {"coordinates":[120.60148999999998,23.75792],"type":"Point"}
}