{
  "type": "Feature",
  "properties": {
    "gn:admin1_code":"4.0",
    "gn:admin2_code":"TNN",
    "gn:admin3_code":"R06",
    "gn:admin4_code":"67000060009.0",
    "gn:asciiname":"Waidishui",
    "gn:country_code":"TW",
    "gn:dem":134,
    "gn:feature_class":"P",
    "gn:feature_code":"PPL",
    "gn:name":"Waidishui",
    "gn:population":0,
    "gn:timezone":"Asia/Taipei",
    "iso:country":"TW",
    "name:und_x_variant":[
        "Waidishuei",
        "Wai-ti-shui"
    ],
    "name:zho_x_preferred":[
        "\u5916\u6ef4\u6c34"
    ],
    "wof:name":"Waidishui",
    "wof:placetype":"locality"
},
  "geometry": {"coordinates":[120.41639000000001,23.26194],"type":"Point"}
}