{
  "type": "Feature",
  "properties": {
    "gn:admin1_code":"4.0",
    "gn:admin2_code":"TNN",
    "gn:admin3_code":"R11",
    "gn:admin4_code":"67000110001.0",
    "gn:asciiname":"Xincuozi",
    "gn:country_code":"TW",
    "gn:dem":22,
    "gn:feature_class":"P",
    "gn:feature_code":"PPL",
    "gn:name":"Xincuozi",
    "gn:population":0,
    "gn:timezone":"Asia/Taipei",
    "iso:country":"TW",
    "name:und_x_variant":[
        "Liu-fen-li",
        "Xincuozi",
        "Sincuozih",
        "Hsin-li"
    ],
    "name:zho_x_preferred":[
        "\u65b0\u539d\u5b50"
    ],
    "name:zho_x_variant":[
        "Hsin-ts\u2019o-tzu"
    ],
    "wof:name":"Xincuozi",
    "wof:placetype":"locality"
},
  "geometry": {"coordinates":[120.35089000000001,23.14845],"type":"Point"}
}