{
  "type": "Feature",
  "properties": {
    "gn:admin1_code":"02",
    "gn:admin2_code":"KHH",
    "gn:admin3_code":"E02",
    "gn:admin4_code":"64000020034.0",
    "gn:asciiname":"Shaochuantou",
    "gn:country_code":"TW",
    "gn:dem":8,
    "gn:feature_class":"P",
    "gn:feature_code":"PPL",
    "gn:name":"Shaochuantou",
    "gn:population":0,
    "gn:timezone":"Asia/Taipei",
    "iso:country":"TW",
    "name:zho_x_preferred":[
        "\u54e8\u8239\u982d"
    ],
    "name:zho_x_variant":[
        "Shao-ch\u2019uan-t\u2019ou"
    ],
    "wof:name":"Shaochuantou",
    "wof:placetype":"locality"
},
  "geometry": {"coordinates":[120.27194,22.61972],"type":"Point"}
}