{
  "type": "Feature",
  "properties": {
    "gn:admin1_code":"4.0",
    "gn:admin2_code":"CYQ",
    "gn:admin3_code":"Q05",
    "gn:admin4_code":"10010050018.0",
    "gn:asciiname":"Niuchouxi",
    "gn:country_code":"TW",
    "gn:dem":30,
    "gn:feature_class":"P",
    "gn:feature_code":"PPL",
    "gn:name":"Niuchouxi",
    "gn:population":0,
    "gn:timezone":"Asia/Taipei",
    "iso:country":"TW",
    "name:und_x_variant":[
        "Fu-hsing",
        "Niuchouxi",
        "Niouchousi"
    ],
    "name:zho_x_preferred":[
        "Niu-ch\u2019ou-ch\u2019i"
    ],
    "name:zho_x_variant":[
        "\u725b\u7a20\u6eaa",
        "Fu-hsing-ts\u2019un",
        "Niu-ch\u2019ou-hsi"
    ],
    "wof:name":"Niuchouxi",
    "wof:placetype":"locality"
},
  "geometry": {"coordinates":[120.42547999999999,23.51017],"type":"Point"}
}