{
  "type": "Feature",
  "properties": {
    "gn:admin1_code":"4.0",
    "gn:admin2_code":"TNN",
    "gn:admin3_code":"R06",
    "gn:admin4_code":"67000060009.0",
    "gn:asciiname":"Kanxialiao",
    "gn:country_code":"TW",
    "gn:dem":62,
    "gn:feature_class":"P",
    "gn:feature_code":"PPL",
    "gn:name":"Kanxialiao",
    "gn:population":0,
    "gn:timezone":"Asia/Taipei",
    "iso:country":"TW",
    "name:und_x_variant":[
        "Kansialiao"
    ],
    "name:zho_x_preferred":[
        "\u5d01\u4e0b\u5bee"
    ],
    "name:zho_x_variant":[
        "K\u2019an-hsia-liao"
    ],
    "wof:name":"Kanxialiao",
    "wof:placetype":"locality"
},
  "geometry": {"coordinates":[120.40833000000001,23.28],"type":"Point"}
}