{
  "type": "Feature",
  "properties": {
    "gn:admin1_code":"4.0",
    "gn:admin2_code":"ILA",
    "gn:admin3_code":"G07",
    "gn:admin4_code":"10002090009.0",
    "gn:asciiname":"Daqiwei",
    "gn:country_code":"TW",
    "gn:dem":7,
    "gn:feature_class":"P",
    "gn:feature_code":"PPL",
    "gn:name":"Daqiwei",
    "gn:population":0,
    "gn:timezone":"Asia/Taipei",
    "iso:country":"TW",
    "name:und_x_variant":[
        "Daciwei",
        "Daqiwei"
    ],
    "name:zho_x_preferred":[
        "\u5927\u65d7\u5c3e"
    ],
    "name:zho_x_variant":[
        "Ta-ch\u2019i-wei"
    ],
    "wof:name":"Daqiwei",
    "wof:placetype":"locality"
},
  "geometry": {"coordinates":[121.80006000000002,24.69477],"type":"Point"}
}