{
  "type": "Feature",
  "properties": {
    "gn:admin1_code":"2.0",
    "gn:admin2_code":"KHH",
    "gn:admin3_code":"E15",
    "gn:admin4_code":"64000150017.0",
    "gn:asciiname":"Xiankeng",
    "gn:country_code":"TW",
    "gn:dem":71,
    "gn:feature_class":"P",
    "gn:feature_code":"PPL",
    "gn:name":"Xiankeng",
    "gn:population":0,
    "gn:timezone":"Asia/Taipei",
    "iso:country":"TW",
    "name:und_x_variant":[
        "Xiankeng",
        "Siankeng"
    ],
    "name:zho_x_preferred":[
        "Hsien-k\u2019eng"
    ],
    "name:zho_x_variant":[
        "\u4ed9\u5751"
    ],
    "wof:name":"Xiankeng",
    "wof:placetype":"locality"
},
  "geometry": {"coordinates":[120.4375,22.7404],"type":"Point"}
}