{
  "type": "Feature",
  "properties": {
    "gn:admin1_code":"4.0",
    "gn:admin2_code":"TNN",
    "gn:admin3_code":"R07",
    "gn:admin4_code":"67000070014.0",
    "gn:asciiname":"Guanditing",
    "gn:country_code":"TW",
    "gn:dem":11,
    "gn:feature_class":"P",
    "gn:feature_code":"PPL",
    "gn:name":"Guanditing",
    "gn:population":0,
    "gn:timezone":"Asia/Taipei",
    "iso:country":"TW",
    "name:und_x_variant":[
        "Kuan-ti-miao",
        "Guanditing"
    ],
    "name:zho_x_preferred":[
        "Kuan-ti-t\u2019ing"
    ],
    "name:zho_x_variant":[
        "\u95dc\u5e1d\u5ef0"
    ],
    "wof:name":"Guanditing",
    "wof:placetype":"locality"
},
  "geometry": {"coordinates":[120.265,23.18889],"type":"Point"}
}