{
  "type": "Feature",
  "properties": {
    "gn:admin1_code":"4.0",
    "gn:admin2_code":"CYI",
    "gn:admin3_code":"I01",
    "gn:admin4_code":"10020010055.0",
    "gn:asciiname":"Hemu",
    "gn:country_code":"TW",
    "gn:dem":42,
    "gn:feature_class":"P",
    "gn:feature_code":"PPL",
    "gn:name":"Hemu",
    "gn:population":0,
    "gn:timezone":"Asia/Taipei",
    "iso:country":"TW",
    "name:und_x_variant":[
        "Ho-mu"
    ],
    "name:zho_x_preferred":[
        "\u548c\u7766"
    ],
    "wof:name":"Hemu",
    "wof:placetype":"locality"
},
  "geometry": {"coordinates":[120.46250000000001,23.45556],"type":"Point"}
}