{
  "type": "Feature",
  "properties": {
    "gn:admin1_code":"4.0",
    "gn:admin2_code":"PIF",
    "gn:admin3_code":"T01",
    "gn:admin4_code":"10013010071.0",
    "gn:asciiname":"Beiji",
    "gn:country_code":"TW",
    "gn:dem":23,
    "gn:feature_class":"P",
    "gn:feature_code":"PPL",
    "gn:name":"Beiji",
    "gn:population":0,
    "gn:timezone":"Asia/Taipei",
    "iso:country":"TW",
    "name:und_x_variant":[
        "Pei-chi-li",
        "Pei-chi",
        "\u5317\u6a5f",
        "Beiji"
    ],
    "name:zho_x_preferred":[
        "Ch\u2019i-pu-ts\u2019o"
    ],
    "name:zho_x_variant":[
        "Ch\u2019ung-lan",
        "\u5317\u6a5f"
    ],
    "wof:name":"Beiji",
    "wof:placetype":"locality"
},
  "geometry": {"coordinates":[120.46928,22.69269],"type":"Point"}
}