{
  "type": "Feature",
  "properties": {
    "gn:admin1_code":"4.0",
    "gn:admin2_code":"TTT",
    "gn:admin3_code":"V07",
    "gn:admin4_code":"10014070004.0",
    "gn:asciiname":"Niaoxinshi",
    "gn:country_code":"TW",
    "gn:dem":376,
    "gn:feature_class":"P",
    "gn:feature_code":"PPL",
    "gn:name":"Niaoxinshi",
    "gn:population":0,
    "gn:timezone":"Asia/Taipei",
    "iso:country":"TW",
    "name:und_x_variant":[
        "Wu-hsin-shih",
        "Niaoxinshi",
        "Niaosinshih",
        "Niao-hsin-shih"
    ],
    "name:zho_x_preferred":[
        "\u9ce5\u5fc3\u77f3"
    ],
    "wof:name":"Niaoxinshi",
    "wof:placetype":"locality"
},
  "geometry": {"coordinates":[121.21285,22.93355],"type":"Point"}
}