{
  "type": "Feature",
  "properties": {
    "gn:country":"TW",
    "gn:fcode":"ADMD",
    "gn:pop":0,
    "iso:country":"TW",
    "name:eng_x_preferred":[
        "Ji-Xu Xiang"
    ],
    "name:jpn_x_preferred":[
        "\u8fb0\u6e86\u7247"
    ],
    "name:unk_x_variant":[
        "Chi-an Hsiang"
    ],
    "name:zho_x_preferred":[
        "Ji\u2019an Xiang"
    ],
    "name:zho_x_variant":[
        "Ji\u2019an Siang",
        "\u5409\u5b89\u9109"
    ],
    "qs:name":"Ji\u2019an Xiang",
    "qs:photos_9r":0,
    "qs:photos_sr":0,
    "qs:pop_sr":"0",
    "wd:wordcount":196,
    "wof:name":"Ji\u2019an Xiang",
    "wof:placetype":"localadmin",
    "wof:population":0
},
  "geometry": {"coordinates":[121.56667,23.95],"type":"Point"}
}