{
  "type": "Feature",
  "properties": {
    "gn:admin1_code":"4.0",
    "gn:admin2_code":"CHA",
    "gn:admin3_code":"N01",
    "gn:admin4_code":"10007010032.0",
    "gn:asciiname":"Hugang",
    "gn:country_code":"TW",
    "gn:dem":144,
    "gn:feature_class":"P",
    "gn:feature_code":"PPL",
    "gn:name":"Hugang",
    "gn:population":0,
    "gn:timezone":"Asia/Taipei",
    "iso:country":"TW",
    "name:und_x_variant":[
        "Hu-kang"
    ],
    "name:zho_x_preferred":[
        "\u864e\u5d17"
    ],
    "wof:name":"Hugang",
    "wof:placetype":"locality"
},
  "geometry": {"coordinates":[120.5724,24.0586],"type":"Point"}
}