{
  "type": "Feature",
  "properties": {
    "gn:admin1_code":"04",
    "gn:admin2_code":"TTT",
    "gn:admin3_code":"V06",
    "gn:admin4_code":"10014090005.0",
    "gn:asciiname":"Deqili",
    "gn:country_code":"TW",
    "gn:dem":24,
    "gn:feature_class":"P",
    "gn:feature_code":"PPL",
    "gn:name":"Deqili",
    "gn:population":0,
    "gn:timezone":"Asia/Taipei",
    "iso:country":"TW",
    "name:und_x_variant":[
        "Decili",
        "Deqili"
    ],
    "name:zho_x_preferred":[
        "\u5fb7\u5176\u91cc"
    ],
    "name:zho_x_variant":[
        "Te-ch\u2019i-li"
    ],
    "wof:name":"Deqili",
    "wof:placetype":"locality"
},
  "geometry": {"coordinates":[121.00167,22.60444],"type":"Point"}
}