{
  "type": "Feature",
  "properties": {
    "gn:admin1_code":"03",
    "gn:admin2_code":"TPQ",
    "gn:admin3_code":"F02",
    "gn:admin4_code":"65000170001.0",
    "gn:asciiname":"Shuiwei",
    "gn:country_code":"TW",
    "gn:dem":222,
    "gn:feature_class":"P",
    "gn:feature_code":"PPL",
    "gn:name":"Shuiwei",
    "gn:population":0,
    "gn:timezone":"Asia/Taipei",
    "iso:country":"TW",
    "name:und_x_variant":[
        "Shueiwei",
        "Shuiwei",
        "Shui-wei"
    ],
    "name:zho_x_preferred":[
        "\u6c34\u5c3e"
    ],
    "wof:name":"Shuiwei",
    "wof:placetype":"locality"
},
  "geometry": {"coordinates":[121.40593,25.09274],"type":"Point"}
}