{
  "type": "Feature",
  "properties": {
    "gn:admin1_code":"3.0",
    "gn:admin2_code":"TPQ",
    "gn:admin3_code":"F10",
    "gn:admin4_code":"65000200001.0",
    "gn:asciiname":"Shikongzi",
    "gn:country_code":"TW",
    "gn:dem":276,
    "gn:feature_class":"P",
    "gn:feature_code":"PPL",
    "gn:name":"Shikongzi",
    "gn:population":0,
    "gn:timezone":"Asia/Taipei",
    "iso:country":"TW",
    "name:und_x_variant":[
        "Shihkongzih",
        "Shikongzi"
    ],
    "name:zho_x_preferred":[
        "\u77f3\u787f\u5b50"
    ],
    "name:zho_x_variant":[
        "Shih-k\u2019ung-tzu"
    ],
    "wof:name":"Shikongzi",
    "wof:placetype":"locality"
},
  "geometry": {"coordinates":[121.67646999999999,24.93753],"type":"Point"}
}