{
  "type": "Feature",
  "properties": {
    "gn:admin1_code":"4.0",
    "gn:admin2_code":"YUN",
    "gn:admin3_code":"P17",
    "gn:admin4_code":"10009170015.0",
    "gn:asciiname":"Xizhuang",
    "gn:country_code":"TW",
    "gn:dem":12,
    "gn:feature_class":"P",
    "gn:feature_code":"PPL",
    "gn:name":"Xizhuang",
    "gn:population":0,
    "gn:timezone":"Asia/Taipei",
    "iso:country":"TW",
    "name:und_x_variant":[
        "Sijhuang",
        "Hsi-chuang"
    ],
    "name:zho_x_preferred":[
        "\u897f\u838a"
    ],
    "name:zho_x_variant":[
        "Hsi-ts\u2019un"
    ],
    "wof:name":"Xizhuang",
    "wof:placetype":"locality"
},
  "geometry": {"coordinates":[120.30585000000001,23.62171],"type":"Point"}
}