{
  "type": "Feature",
  "properties": {
    "gn:admin1_code":"04",
    "gn:admin2_code":"PIF",
    "gn:admin3_code":"T16",
    "gn:admin4_code":"10013160010.0",
    "gn:asciiname":"Dingying",
    "gn:country_code":"TW",
    "gn:dem":22,
    "gn:feature_class":"P",
    "gn:feature_code":"PPL",
    "gn:name":"Dingying",
    "gn:population":0,
    "gn:timezone":"Asia/Taipei",
    "iso:country":"TW",
    "name:und_x_variant":[
        "\u9802\u71df",
        "Dingying",
        "Ting-ying"
    ],
    "wof:name":"Dingying",
    "wof:placetype":"locality"
},
  "geometry": {"coordinates":[120.61360999999999,22.3875],"type":"Point"}
}