{
  "type": "Feature",
  "properties": {
    "gn:admin1_code":"4.0",
    "gn:admin2_code":"TPE",
    "gn:admin3_code":"A15",
    "gn:admin4_code":"63000110023.0",
    "gn:asciiname":"Fuzhouzi",
    "gn:country_code":"TW",
    "gn:dem":6,
    "gn:feature_class":"P",
    "gn:feature_code":"PPL",
    "gn:name":"Fuzhouzi",
    "gn:population":0,
    "gn:timezone":"Asia/Taipei",
    "iso:country":"TW",
    "name:und_x_variant":[
        "Fujhouzih",
        "Fu-chou-tzu"
    ],
    "name:zho_x_preferred":[
        "\u6d6e\u6d32\u5b50"
    ],
    "wof:name":"Fuzhouzi",
    "wof:placetype":"locality"
},
  "geometry": {"coordinates":[121.49012999999999,25.11042],"type":"Point"}
}