{
  "type": "Feature",
  "properties": {
    "gn:admin1_code":"4.0",
    "gn:admin2_code":"TNN",
    "gn:admin3_code":"R27",
    "gn:admin4_code":"67000270001.0",
    "gn:asciiname":"Liujiazi",
    "gn:country_code":"TW",
    "gn:dem":13,
    "gn:feature_class":"P",
    "gn:feature_code":"PPL",
    "gn:name":"Liujiazi",
    "gn:population":0,
    "gn:timezone":"Asia/Taipei",
    "iso:country":"TW",
    "name:und_x_variant":[
        "Lioujiazih",
        "Liujiazi",
        "Liu-chia-tzu"
    ],
    "name:zho_x_preferred":[
        "\u516d\u7532\u4ed4"
    ],
    "wof:name":"Liujiazi",
    "wof:placetype":"locality"
},
  "geometry": {"coordinates":[120.27110999999999,22.99306],"type":"Point"}
}