{
  "type": "Feature",
  "properties": {
    "gn:admin1_code":"4.0",
    "gn:admin2_code":"YUN",
    "gn:admin3_code":"P01",
    "gn:admin4_code":"10009010016.0",
    "gn:asciiname":"Liaopouzi",
    "gn:country_code":"TW",
    "gn:dem":49,
    "gn:feature_class":"P",
    "gn:feature_code":"PPL",
    "gn:name":"Liaopouzi",
    "gn:population":0,
    "gn:timezone":"Asia/Taipei",
    "iso:country":"TW",
    "name:und_x_variant":[
        "Liaopouzih",
        "Liaopouzi"
    ],
    "name:zho_x_preferred":[
        "\u5ed6\u5ecd\u5b50"
    ],
    "name:zho_x_variant":[
        "Liao-p\u2019ou-tzu"
    ],
    "wof:name":"Liaopouzi",
    "wof:placetype":"locality"
},
  "geometry": {"coordinates":[120.52249999999999,23.67028],"type":"Point"}
}