{
  "type": "Feature",
  "properties": {
    "gn:admin1_code":"04",
    "gn:admin2_code":"ILA",
    "gn:admin3_code":"G04",
    "gn:admin4_code":"10002060011.0",
    "gn:asciiname":"Tuwei",
    "gn:country_code":"TW",
    "gn:dem":7,
    "gn:feature_class":"P",
    "gn:feature_code":"PPL",
    "gn:name":"Tuwei",
    "gn:population":0,
    "gn:timezone":"Asia/Taipei",
    "iso:country":"TW",
    "name:zho_x_preferred":[
        "T\u2019u-wei-ts\u2019un"
    ],
    "name:zho_x_variant":[
        "\u571f\u570d",
        "T\u2019u-wei"
    ],
    "wof:name":"Tuwei",
    "wof:placetype":"locality"
},
  "geometry": {"coordinates":[121.78861000000001,24.77778],"type":"Point"}
}