{
  "type": "Feature",
  "properties": {
    "gn:admin1_code":"4.0",
    "gn:admin2_code":"TXG",
    "gn:admin3_code":"B29",
    "gn:admin4_code":"66000290006.0",
    "gn:asciiname":"Taoshan",
    "gn:country_code":"TW",
    "gn:dem":604,
    "gn:feature_class":"P",
    "gn:feature_code":"PPL",
    "gn:name":"Taoshan",
    "gn:population":0,
    "gn:timezone":"Asia/Taipei",
    "iso:country":"TW",
    "name:und_x_variant":[
        "Taoshan"
    ],
    "name:zho_x_preferred":[
        "Hs\u00fceh-shan-k\u2019eng-she"
    ],
    "name:zho_x_variant":[
        "Hs\u00fceh-shan-k\u2019eng",
        "T\u2019ao-shan",
        "\u6843\u5c71"
    ],
    "wof:name":"Taoshan",
    "wof:placetype":"locality"
},
  "geometry": {"coordinates":[120.9354,24.3382],"type":"Point"}
}