{
  "type": "Feature",
  "properties": {
    "gn:admin1_code":"04",
    "gn:admin2_code":"TNN",
    "gn:admin3_code":"R25",
    "gn:admin4_code":"67000250005.0",
    "gn:asciiname":"Shuiquan",
    "gn:country_code":"TW",
    "gn:dem":489,
    "gn:feature_class":"P",
    "gn:feature_code":"PPL",
    "gn:name":"Shuiquan",
    "gn:population":0,
    "gn:timezone":"Asia/Taipei",
    "iso:country":"TW",
    "name:und_x_variant":[
        "Shui-ch\u2019\u00fcan"
    ],
    "wof:name":"Shuiquan",
    "wof:placetype":"locality"
},
  "geometry": {"coordinates":[120.48333,23.01667],"type":"Point"}
}