{
  "type": "Feature",
  "properties": {
    "iso:country":"TW",
    "qs:name":"\u5317\u5c6f\u91cc",
    "qs:name_adm0":"\u81fa\u7063",
    "qs:name_adm1":"\u53f0\u4e2d\u5e02",
    "qs:photos":65,
    "qs:photos_1k":13,
    "qs:photos_9k":1,
    "qs:photos_9r":2,
    "qs:photos_all":65,
    "qs:photos_sr":2,
    "qs:placetype":"Suburb",
    "qs:pop_sr":"0",
    "wd:wordcount":198,
    "wof:name":"\u5317\u5c6f\u91cc",
    "wof:placetype":"neighbourhood"
},
  "geometry": {"coordinates":[120.690166,24.165571],"type":"Point"}
}