{
  "type": "Feature",
  "properties": {
    "gn:admin1_code":"04",
    "gn:admin2_code":"TXG",
    "gn:admin3_code":"B20",
    "gn:admin4_code":"66000200007.0",
    "gn:asciiname":"Meizi",
    "gn:country_code":"TW",
    "gn:dem":318,
    "gn:feature_class":"P",
    "gn:feature_code":"PPL",
    "gn:name":"Meizi",
    "gn:population":0,
    "gn:timezone":"Asia/Taipei",
    "iso:country":"TW",
    "name:und_x_variant":[
        "Mei-tzu-shu-chiao",
        "Meizih",
        "Meizi",
        "Mei-tzu",
        "\u6885\u5b50"
    ],
    "name:zho_x_preferred":[
        "\u6885\u5b50"
    ],
    "wof:name":"Meizi",
    "wof:placetype":"locality"
},
  "geometry": {"coordinates":[120.80181,24.27005],"type":"Point"}
}