{
  "type": "Feature",
  "properties": {
    "gn:admin1_code":"4.0",
    "gn:admin2_code":"CHA",
    "gn:admin3_code":"N22",
    "gn:admin4_code":"10007220004.0",
    "gn:asciiname":"Xidixiliao",
    "gn:country_code":"TW",
    "gn:dem":20,
    "gn:feature_class":"P",
    "gn:feature_code":"PPL",
    "gn:name":"Xidixiliao",
    "gn:population":0,
    "gn:timezone":"Asia/Taipei",
    "iso:country":"TW",
    "name:und_x_variant":[
        "Hsi-ti-liao",
        "Sidisiliao",
        "Hsi-ti-hsi-liao"
    ],
    "name:zho_x_preferred":[
        "Sha-lung-t\u2019ou"
    ],
    "name:zho_x_variant":[
        "Ch\u2019i-ti-liao",
        "\u6eaa\u5e95\u897f\u5bee"
    ],
    "wof:name":"Xidixiliao",
    "wof:placetype":"locality"
},
  "geometry": {"coordinates":[120.45281,23.91793],"type":"Point"}
}