{
  "type": "Feature",
  "properties": {
    "gn:admin1_code":"4.0",
    "gn:admin2_code":"HUA",
    "gn:admin3_code":"U11",
    "gn:admin4_code":"10015110001.0",
    "gn:asciiname":"Xiaoqingshui",
    "gn:country_code":"TW",
    "gn:dem":301,
    "gn:feature_class":"P",
    "gn:feature_code":"PPL",
    "gn:name":"Xiaoqingshui",
    "gn:population":0,
    "gn:timezone":"Asia/Taipei",
    "iso:country":"TW",
    "name:und_x_variant":[
        "Siaocingshuei"
    ],
    "name:zho_x_preferred":[
        "\u5c0f\u6e05\u6c34"
    ],
    "name:zho_x_variant":[
        "Hsiao-ch\u2019ing-shui"
    ],
    "wof:name":"Xiaoqingshui",
    "wof:placetype":"locality"
},
  "geometry": {"coordinates":[121.67033000000001,24.20981],"type":"Point"}
}