{
  "type": "Feature",
  "properties": {
    "iso:country":"TW",
    "qs:name":"\u897f\u5ddd\u91cc",
    "qs:name_adm0":"\u81fa\u7063",
    "qs:name_adm1":"\u57fa\u9686\u5e02",
    "qs:photos":10,
    "qs:photos_1k":2,
    "qs:photos_9k":1,
    "qs:photos_9r":1,
    "qs:photos_all":10,
    "qs:photos_sr":1,
    "qs:placetype":"Suburb",
    "qs:pop_sr":"0",
    "wof:name":"\u897f\u5ddd\u91cc",
    "wof:placetype":"neighbourhood"
},
  "geometry": {"coordinates":[121.728515,25.137825],"type":"Point"}
}