{
  "type": "Feature",
  "properties": {
    "gn:admin1_code":"4.0",
    "gn:admin2_code":"NAN",
    "gn:admin3_code":"M03",
    "gn:admin4_code":"10008030008.0",
    "gn:asciiname":"Daku",
    "gn:country_code":"TW",
    "gn:dem":100,
    "gn:feature_class":"P",
    "gn:feature_code":"PPL",
    "gn:name":"Daku",
    "gn:population":0,
    "gn:timezone":"Asia/Taipei",
    "iso:country":"TW",
    "name:zho_x_preferred":[
        "\u5927\u5800"
    ],
    "name:zho_x_variant":[
        "Ta-k\u2019u"
    ],
    "wof:name":"Daku",
    "wof:placetype":"locality"
},
  "geometry": {"coordinates":[120.68468,23.99212],"type":"Point"}
}