{
  "type": "Feature",
  "properties": {
    "gn:admin1_code":"4.0",
    "gn:admin2_code":"MIA",
    "gn:admin3_code":"K12",
    "gn:admin4_code":"10005060007.0",
    "gn:asciiname":"Shizitou",
    "gn:country_code":"TW",
    "gn:dem":21,
    "gn:feature_class":"P",
    "gn:feature_code":"PPL",
    "gn:name":"Shizitou",
    "gn:population":0,
    "gn:timezone":"Asia/Taipei",
    "iso:country":"TW",
    "name:und_x_variant":[
        "Shihzihtou",
        "Shizitou"
    ],
    "name:zho_x_preferred":[
        "\u7345\u5b50\u982d"
    ],
    "name:zho_x_variant":[
        "Shih-tzu-t\u2019ou"
    ],
    "wof:name":"Shizitou",
    "wof:placetype":"locality"
},
  "geometry": {"coordinates":[120.83441000000001,24.60144],"type":"Point"}
}