{
  "type": "Feature",
  "properties": {
    "gn:admin1_code":"04",
    "gn:admin2_code":"YUN",
    "gn:admin3_code":"P12",
    "gn:admin4_code":"10009120007.0",
    "gn:asciiname":"Yanyuan",
    "gn:country_code":"TW",
    "gn:dem":16,
    "gn:feature_class":"P",
    "gn:feature_code":"PPL",
    "gn:name":"Yanyuan",
    "gn:population":0,
    "gn:timezone":"Asia/Taipei",
    "iso:country":"TW",
    "name:und_x_variant":[
        "Yanyuan"
    ],
    "name:zho_x_preferred":[
        "A-ch\u2019\u00fcan-ts\u2019un"
    ],
    "name:zho_x_variant":[
        "A-ch\u2019\u00fcan",
        "\u9e7d\u5712",
        "Yen-y\u00fcan",
        "Fan-yen-y\u00fcan"
    ],
    "wof:name":"Yanyuan",
    "wof:placetype":"locality"
},
  "geometry": {"coordinates":[120.33828,23.76268],"type":"Point"}
}