{
  "type": "Feature",
  "properties": {
    "gn:admin1_code":"02",
    "gn:admin2_code":"KHH",
    "gn:admin3_code":"E38",
    "gn:admin4_code":"64000380002.0",
    "gn:asciiname":"Mincyuan",
    "gn:country_code":"TW",
    "gn:dem":559,
    "gn:feature_class":"P",
    "gn:feature_code":"PPL",
    "gn:name":"Mincyuan",
    "gn:population":0,
    "gn:timezone":"Asia/Taipei",
    "iso:country":"TW",
    "name:und_x_variant":[
        "San-min",
        "Pu-la-she",
        "Minquan",
        "Mincyuan",
        "Na-weng Na-weng"
    ],
    "name:zho_x_preferred":[
        "Min-ch\u2019\u00fcan-ts\u2019un"
    ],
    "name:zho_x_variant":[
        "\u6c11\u6b0a",
        "Min-ch\u2019\u00fcan"
    ],
    "wof:name":"Mincyuan",
    "wof:placetype":"locality"
},
  "geometry": {"coordinates":[120.69665999999999,23.2386],"type":"Point"}
}