{
  "type": "Feature",
  "properties": {
    "iso:country":"TW",
    "qs:name":"\u516c\u5fb7\u91cc",
    "qs:name_adm0":"\u81fa\u7063",
    "qs:name_adm1":"\u53f0\u4e2d\u5e02",
    "qs:photos":138,
    "qs:photos_1k":28,
    "qs:photos_9k":1,
    "qs:photos_9r":3,
    "qs:photos_all":138,
    "qs:photos_sr":3,
    "qs:placetype":"Suburb",
    "qs:pop_sr":"0",
    "wd:wordcount":334,
    "wof:name":"\u516c\u5fb7\u91cc",
    "wof:placetype":"neighbourhood"
},
  "geometry": {"coordinates":[120.65600000000001,24.1460955],"type":"Point"}
}