{
  "type": "Feature",
  "properties": {
    "gn:admin1_code":"4.0",
    "gn:admin2_code":"NAN",
    "gn:admin3_code":"M10",
    "gn:admin4_code":"10008100001.0",
    "gn:asciiname":"Zhukeng",
    "gn:country_code":"TW",
    "gn:dem":299,
    "gn:feature_class":"P",
    "gn:feature_code":"PPL",
    "gn:name":"Zhukeng",
    "gn:population":0,
    "gn:timezone":"Asia/Taipei",
    "iso:country":"TW",
    "name:und_x_variant":[
        "Jhukeng"
    ],
    "name:zho_x_preferred":[
        "\u7af9\u5751"
    ],
    "name:zho_x_variant":[
        "Chu-k\u2019eng"
    ],
    "wof:name":"Zhukeng",
    "wof:placetype":"locality"
},
  "geometry": {"coordinates":[120.85526000000002,24.03285],"type":"Point"}
}