{
  "type": "Feature",
  "properties": {
    "gn:admin1_code":"4.0",
    "gn:admin2_code":"ILA",
    "gn:admin3_code":"G12",
    "gn:admin4_code":"10002120005.0",
    "gn:asciiname":"Changshuiyin",
    "gn:country_code":"TW",
    "gn:dem":499,
    "gn:feature_class":"P",
    "gn:feature_code":"PPL",
    "gn:name":"Changshuiyin",
    "gn:population":0,
    "gn:timezone":"Asia/Taipei",
    "iso:country":"TW",
    "name:und_x_variant":[
        "Changshueiyin",
        "Changshuiyin"
    ],
    "name:zho_x_preferred":[
        "\u9577\u6c34\u5f15"
    ],
    "name:zho_x_variant":[
        "Ch\u2019ang-shui-yin"
    ],
    "wof:name":"Changshuiyin",
    "wof:placetype":"locality"
},
  "geometry": {"coordinates":[121.77806,24.39861],"type":"Point"}
}