{
  "type": "Feature",
  "properties": {
    "gn:admin1_code":"03",
    "gn:admin2_code":"TPQ",
    "gn:admin3_code":"F23",
    "gn:admin4_code":"65000250008.0",
    "gn:asciiname":"Waipinglin",
    "gn:country_code":"TW",
    "gn:dem":47,
    "gn:feature_class":"P",
    "gn:feature_code":"PPL",
    "gn:name":"Waipinglin",
    "gn:population":0,
    "gn:timezone":"Asia/Taipei",
    "iso:country":"TW",
    "name:zho_x_preferred":[
        "\u5916\u5e73\u6797"
    ],
    "name:zho_x_variant":[
        "Wai-p\u2019ing-lin"
    ],
    "wof:name":"Waipinglin",
    "wof:placetype":"locality"
},
  "geometry": {"coordinates":[121.84632000000001,25.03521],"type":"Point"}
}