{
  "type": "Feature",
  "properties": {
    "gn:admin1_code":"4.0",
    "gn:admin2_code":"CYQ",
    "gn:admin3_code":"Q15",
    "gn:admin4_code":"10010140013.0",
    "gn:asciiname":"Houshantian",
    "gn:country_code":"TW",
    "gn:dem":422,
    "gn:feature_class":"P",
    "gn:feature_code":"PPL",
    "gn:name":"Houshantian",
    "gn:population":0,
    "gn:timezone":"Asia/Taipei",
    "iso:country":"TW",
    "name:zho_x_preferred":[
        "\u5f8c\u5c71\u7530"
    ],
    "name:zho_x_variant":[
        "Hou-shan-t\u2019ien"
    ],
    "wof:name":"Houshantian",
    "wof:placetype":"locality"
},
  "geometry": {"coordinates":[120.59804,23.49026],"type":"Point"}
}