{
  "type": "Feature",
  "properties": {
    "gn:admin1_code":"04",
    "gn:admin2_code":"TXG",
    "gn:admin3_code":"B08",
    "gn:admin4_code":"66000080021.0",
    "gn:asciiname":"Shangqizhangli",
    "gn:country_code":"TW",
    "gn:dem":140,
    "gn:feature_class":"P",
    "gn:feature_code":"PPL",
    "gn:name":"Shangqizhangli",
    "gn:population":0,
    "gn:timezone":"Asia/Taipei",
    "iso:country":"TW",
    "name:und_x_variant":[
        "\u4e0a\u4e03\u5f35\u7282",
        "Shangcijhangli",
        "T\u2019ung-jung",
        "Shangqizhangli",
        "Shang-ch\u2019i-chang-li"
    ],
    "name:zho_x_preferred":[
        "Shang-ch\u2019i-chang-li"
    ],
    "wof:name":"Shangqizhangli",
    "wof:placetype":"locality"
},
  "geometry": {"coordinates":[120.67898,24.19887],"type":"Point"}
}