{
  "type": "Feature",
  "properties": {
    "gn:admin1_code":"04",
    "gn:admin2_code":"YUN",
    "gn:admin3_code":"P17",
    "gn:admin4_code":"10009170005.0",
    "gn:asciiname":"Dingcuo",
    "gn:country_code":"TW",
    "gn:dem":13,
    "gn:feature_class":"P",
    "gn:feature_code":"PPL",
    "gn:name":"Dingcuo",
    "gn:population":0,
    "gn:timezone":"Asia/Taipei",
    "iso:country":"TW",
    "name:und_x_variant":[
        "Ting-shan-tzu-nei",
        "Dingcuo",
        "Ting-shan-nei"
    ],
    "name:zho_x_preferred":[
        "\u9802\u539d"
    ],
    "name:zho_x_variant":[
        "Ting-ts\u2019o"
    ],
    "wof:name":"Dingcuo",
    "wof:placetype":"locality"
},
  "geometry": {"coordinates":[120.31232,23.68494],"type":"Point"}
}