{
  "type": "Feature",
  "properties": {
    "gn:country":"TW",
    "iso:country":"TW",
    "name:eng_x_preferred":[
        "Dakan"
    ],
    "name:eng_x_variant":[
        "Dakan Village"
    ],
    "name:zho_tw_x_preferred":[
        "\u5927\u5d01\u6751"
    ],
    "qs:name":"\u5927\u5d01\u6751",
    "qs:name_adm0":"\u81fa\u7063",
    "qs:name_adm1":"\u65b0\u5317\u5e02",
    "qs:photos":1761,
    "qs:photos_1k":357,
    "qs:photos_9k":8,
    "qs:photos_9r":8,
    "qs:photos_all":1761,
    "qs:photos_sr":14,
    "qs:placetype":"Town",
    "qs:pop_sr":"0",
    "wof:name":"Dakan",
    "wof:placetype":"locality"
},
  "geometry": {"coordinates":[121.431541,25.161056],"type":"Point"}
}