{
  "type": "Feature",
  "properties": {
    "gn:admin1_code":"4.0",
    "gn:admin2_code":"NAN",
    "gn:admin3_code":"M04",
    "gn:admin4_code":"10008040010.0",
    "gn:asciiname":"Chedianzi",
    "gn:country_code":"TW",
    "gn:dem":160,
    "gn:feature_class":"P",
    "gn:feature_code":"PPL",
    "gn:name":"Chedianzi",
    "gn:population":0,
    "gn:timezone":"Asia/Taipei",
    "iso:country":"TW",
    "name:und_x_variant":[
        "Chedianzih",
        "Chedianzi"
    ],
    "name:zho_x_preferred":[
        "\u8eca\u5e97\u5b50"
    ],
    "name:zho_x_variant":[
        "Ch\u2019e-tien-tzu"
    ],
    "wof:name":"Chedianzi",
    "wof:placetype":"locality"
},
  "geometry": {"coordinates":[120.67083,23.7375],"type":"Point"}
}