{
  "type": "Feature",
  "properties": {
    "gn:admin1_code":"04",
    "gn:admin2_code":"NAN",
    "gn:admin3_code":"M06",
    "gn:admin4_code":"10008060018.0",
    "gn:asciiname":"Songbaikeng",
    "gn:country_code":"TW",
    "gn:dem":404,
    "gn:feature_class":"P",
    "gn:feature_code":"PPL",
    "gn:name":"Songbaikeng",
    "gn:population":0,
    "gn:timezone":"Asia/Taipei",
    "iso:country":"TW",
    "name:und_x_variant":[
        "Sung-pai-ling"
    ],
    "name:zho_x_preferred":[
        "\u677e\u67cf\u5751"
    ],
    "name:zho_x_variant":[
        "Sung-pai-k\u2019eng"
    ],
    "wof:name":"Songbaikeng",
    "wof:placetype":"locality"
},
  "geometry": {"coordinates":[120.63534,23.83602],"type":"Point"}
}