{
  "type": "Feature",
  "properties": {
    "gn:admin1_code":"04",
    "gn:admin2_code":"PIF",
    "gn:admin3_code":"T15",
    "gn:admin4_code":"10013150004.0",
    "gn:asciiname":"Nan'an",
    "gn:country_code":"TW",
    "gn:dem":21,
    "gn:feature_class":"P",
    "gn:feature_code":"PPL",
    "gn:name":"Nan\u2019an",
    "gn:population":0,
    "gn:timezone":"Asia/Taipei",
    "iso:country":"TW",
    "name:und_x_variant":[
        "Nan-an"
    ],
    "name:zho_x_preferred":[
        "\u5357\u5cb8"
    ],
    "name:zho_x_variant":[
        "Nan\u2019an"
    ],
    "wof:name":"Nan'an",
    "wof:placetype":"locality"
},
  "geometry": {"coordinates":[120.55945,22.50095],"type":"Point"}
}