{
  "type": "Feature",
  "properties": {
    "gn:admin1_code":"03",
    "gn:admin2_code":"TPQ",
    "gn:admin3_code":"F08",
    "gn:admin4_code":"65000190011.0",
    "gn:asciiname":"Shizitoukeng",
    "gn:country_code":"TW",
    "gn:dem":195,
    "gn:feature_class":"P",
    "gn:feature_code":"PPL",
    "gn:name":"Shizitoukeng",
    "gn:population":0,
    "gn:timezone":"Asia/Taipei",
    "iso:country":"TW",
    "name:und_x_variant":[
        "Shihzihtoukeng",
        "Shizitoukeng"
    ],
    "name:zho_x_preferred":[
        "Shih-tzu-k\u2019eng-t\u2019ou"
    ],
    "name:zho_x_variant":[
        "\u7345\u5b50\u982d\u5751",
        "Shih-tzu-k\u2019eng",
        "Shih-tzu-t\u2019ou-k\u2019eng"
    ],
    "wof:name":"Shizitoukeng",
    "wof:placetype":"locality"
},
  "geometry": {"coordinates":[121.63983,24.93274],"type":"Point"}
}