{
  "type": "Feature",
  "properties": {
    "gn:admin1_code":"4.0",
    "gn:admin2_code":"YUN",
    "gn:admin3_code":"P03",
    "gn:admin4_code":"10009030006.0",
    "gn:asciiname":"Wujiancuo",
    "gn:country_code":"TW",
    "gn:dem":27,
    "gn:feature_class":"P",
    "gn:feature_code":"PPL",
    "gn:name":"Wujiancuo",
    "gn:population":0,
    "gn:timezone":"Asia/Taipei",
    "iso:country":"TW",
    "name:zho_x_preferred":[
        "\u4e94\u9593\u539d"
    ],
    "name:zho_x_variant":[
        "Wu-chien-ts\u2019o"
    ],
    "wof:name":"Wujiancuo",
    "wof:placetype":"locality"
},
  "geometry": {"coordinates":[120.42949,23.70039],"type":"Point"}
}