{
  "type": "Feature",
  "properties": {
    "gn:admin1_code":"2.0",
    "gn:admin2_code":"KHH",
    "gn:admin3_code":"E22",
    "gn:admin4_code":"64000220009.0",
    "gn:asciiname":"Guting",
    "gn:country_code":"TW",
    "gn:dem":61,
    "gn:feature_class":"P",
    "gn:feature_code":"PPL",
    "gn:name":"Guting",
    "gn:population":0,
    "gn:timezone":"Asia/Taipei",
    "iso:country":"TW",
    "name:zho_x_preferred":[
        "\u53e4\u4ead"
    ],
    "name:zho_x_variant":[
        "Ku-t\u2019ing-k\u2019eng",
        "Ku-t\u2019ing"
    ],
    "wof:name":"Guting",
    "wof:placetype":"locality"
},
  "geometry": {"coordinates":[120.40333,22.89333],"type":"Point"}
}