{
  "type": "Feature",
  "properties": {
    "gn:admin1_code":"4.0",
    "gn:admin2_code":"PIF",
    "gn:admin3_code":"T12",
    "gn:admin4_code":"10013120009.0",
    "gn:asciiname":"Dali",
    "gn:country_code":"TW",
    "gn:dem":64,
    "gn:feature_class":"P",
    "gn:feature_code":"PPL",
    "gn:name":"Dali",
    "gn:population":0,
    "gn:timezone":"Asia/Taipei",
    "iso:country":"TW",
    "name:bul_x_preferred":[
        "\u0414\u0430\u043b\u0438"
    ],
    "name:cat_x_preferred":[
        "Dali"
    ],
    "name:ceb_x_preferred":[
        "Dali"
    ],
    "name:dan_x_preferred":[
        "Dali"
    ],
    "name:deu_x_preferred":[
        "Dali"
    ],
    "name:fin_x_preferred":[
        "Dali"
    ],
    "name:fra_x_preferred":[
        "Dali"
    ],
    "name:heb_x_preferred":[
        "\u05d3\u05d0\u05dc\u05d9"
    ],
    "name:ita_x_preferred":[
        "Dali"
    ],
    "name:kat_x_preferred":[
        "\u10d3\u10d0\u10da\u10d8"
    ],
    "name:lit_x_preferred":[
        "Dali"
    ],
    "name:mlg_x_preferred":[
        "Dali"
    ],
    "name:nld_x_preferred":[
        "Dali"
    ],
    "name:nor_x_preferred":[
        "Dali"
    ],
    "name:pol_x_preferred":[
        "Dali"
    ],
    "name:por_x_preferred":[
        "Dali"
    ],
    "name:rus_x_preferred":[
        "\u0414\u0430\u043b\u0438"
    ],
    "name:spa_x_preferred":[
        "Dali"
    ],
    "name:swe_x_preferred":[
        "Dali"
    ],
    "name:tat_x_preferred":[
        "\u0414\u0430\u043b\u0438"
    ],
    "name:tgl_x_preferred":[
        "Dali"
    ],
    "name:ukr_x_preferred":[
        "\u0414\u0430\u043b\u0456"
    ],
    "name:und_x_variant":[
        "Ta-li"
    ],
    "name:zho_x_preferred":[
        "\u5927\u91cc"
    ],
    "wof:name":"Dali",
    "wof:placetype":"locality"
},
  "geometry": {"coordinates":[120.63536999999999,22.6224],"type":"Point"}
}