{
  "type": "Feature",
  "properties": {
    "gn:admin1_code":"4.0",
    "gn:admin2_code":"PIF",
    "gn:admin3_code":"T12",
    "gn:admin4_code":"10013120009.0",
    "gn:asciiname":"Dali",
    "gn:country_code":"TW",
    "gn:dem":64,
    "gn:feature_class":"P",
    "gn:feature_code":"PPL",
    "gn:name":"Dali",
    "gn:population":0,
    "gn:timezone":"Asia/Taipei",
    "iso:country":"TW",
    "name:und_x_variant":[
        "Ta-li",
        "\u5927\u91cc",
        "Dali"
    ],
    "name:zho_x_preferred":[
        "\u5927\u91cc"
    ],
    "wof:name":"Dali",
    "wof:placetype":"locality"
},
  "geometry": {"coordinates":[120.63536999999999,22.6224],"type":"Point"}
}