{
  "type": "Feature",
  "properties": {
    "gn:admin1_code":"04",
    "gn:admin2_code":"YUN",
    "gn:admin3_code":"P19",
    "gn:admin4_code":"10009190003.0",
    "gn:asciiname":"Dingkouhu",
    "gn:country_code":"TW",
    "gn:dem":5,
    "gn:feature_class":"P",
    "gn:feature_code":"PPL",
    "gn:name":"Dingkouhu",
    "gn:population":0,
    "gn:timezone":"Asia/Taipei",
    "iso:country":"TW",
    "name:zho_x_preferred":[
        "\u9802\u53e3\u6e56"
    ],
    "name:zho_x_variant":[
        "Ting-k\u2019ou-hu"
    ],
    "wof:name":"Dingkouhu",
    "wof:placetype":"locality"
},
  "geometry": {"coordinates":[120.17806000000002,23.60083],"type":"Point"}
}