{
  "type": "Feature",
  "properties": {
    "gn:admin1_code":"4.0",
    "gn:admin2_code":"TAO",
    "gn:admin3_code":"H05",
    "gn:admin4_code":"68000050016.0",
    "gn:asciiname":"Xiahaihu",
    "gn:country_code":"TW",
    "gn:dem":12,
    "gn:feature_class":"P",
    "gn:feature_code":"PPL",
    "gn:name":"Xiahaihu",
    "gn:population":0,
    "gn:timezone":"Asia/Taipei",
    "iso:country":"TW",
    "name:und_x_variant":[
        "Hai-hu",
        "Hsin-hai-hu",
        "Siahaihu",
        "Xiahaihu",
        "Hsia-hai-hu"
    ],
    "name:zho_x_preferred":[
        "\u4e0b\u6d77\u6e56"
    ],
    "wof:name":"Xiahaihu",
    "wof:placetype":"locality"
},
  "geometry": {"coordinates":[121.25238,25.11529],"type":"Point"}
}