{
  "type": "Feature",
  "properties": {
    "gn:admin1_code":"4.0",
    "gn:admin2_code":"YUN",
    "gn:admin3_code":"P13",
    "gn:admin4_code":"10009130007.0",
    "gn:asciiname":"Haiwei",
    "gn:country_code":"TW",
    "gn:dem":4,
    "gn:feature_class":"P",
    "gn:feature_code":"PPL",
    "gn:name":"Haiwei",
    "gn:population":0,
    "gn:timezone":"Asia/Taipei",
    "iso:country":"TW",
    "name:und_x_variant":[
        "Hai-wei",
        "Haiwei",
        "\u6d77\u5c3e"
    ],
    "wof:name":"Haiwei",
    "wof:placetype":"locality"
},
  "geometry": {"coordinates":[120.20999999999999,23.77389],"type":"Point"}
}