{
  "type": "Feature",
  "properties": {
    "gn:admin1_code":"04",
    "gn:admin2_code":"CYQ",
    "gn:admin3_code":"Q16",
    "gn:admin4_code":"10010150012.0",
    "gn:asciiname":"Taiping",
    "gn:country_code":"TW",
    "gn:dem":959,
    "gn:feature_class":"P",
    "gn:feature_code":"PPL",
    "gn:name":"Taiping",
    "gn:population":0,
    "gn:timezone":"Asia/Taipei",
    "iso:country":"TW",
    "name:ceb_x_preferred":[
        "Taiping"
    ],
    "name:deu_x_preferred":[
        "Taiping"
    ],
    "name:fra_x_preferred":[
        "Taiping"
    ],
    "name:ind_x_preferred":[
        "Taiping"
    ],
    "name:msa_x_preferred":[
        "Taiping"
    ],
    "name:nld_x_preferred":[
        "Taiping"
    ],
    "name:rus_x_preferred":[
        "\u0422\u0430\u0439\u043f\u0438\u043d"
    ],
    "name:swe_x_preferred":[
        "Taiping"
    ],
    "name:zho_x_preferred":[
        "\u592a\u5e73"
    ],
    "name:zho_x_variant":[
        "Ta-p\u2019ing",
        "T\u2019ai-p\u2019ing"
    ],
    "wof:name":"Taiping",
    "wof:placetype":"locality"
},
  "geometry": {"coordinates":[120.60417,23.56083],"type":"Point"}
}