{
  "type": "Feature",
  "properties": {
    "gn:admin1_code":"4.0",
    "gn:admin2_code":"ILA",
    "gn:admin3_code":"G07",
    "gn:admin4_code":"10002090010.0",
    "gn:asciiname":"Dabu",
    "gn:country_code":"TW",
    "gn:dem":3,
    "gn:feature_class":"P",
    "gn:feature_code":"PPL",
    "gn:name":"Dabu",
    "gn:population":0,
    "gn:timezone":"Asia/Taipei",
    "iso:country":"TW",
    "name:ceb_x_preferred":[
        "Dabu"
    ],
    "name:deu_x_preferred":[
        "Dabu"
    ],
    "name:fra_x_preferred":[
        "Dabu"
    ],
    "name:ita_x_preferred":[
        "Dabu"
    ],
    "name:und_x_variant":[
        "Hsieh-ho",
        "Ta-pu"
    ],
    "name:zho_x_preferred":[
        "Ch\u2019ing-ti"
    ],
    "name:zho_x_variant":[
        "\u5927\u57d4"
    ],
    "wof:name":"Dabu",
    "wof:placetype":"locality"
},
  "geometry": {"coordinates":[121.81319000000001,24.68055],"type":"Point"}
}