{
  "type": "Feature",
  "properties": {
    "gn:admin1_code":"04",
    "gn:admin2_code":"CYQ",
    "gn:admin3_code":"Q13",
    "gn:admin4_code":"10010120001.0",
    "gn:asciiname":"Wailin",
    "gn:country_code":"TW",
    "gn:dem":30,
    "gn:feature_class":"P",
    "gn:feature_code":"PPL",
    "gn:name":"Wailin",
    "gn:population":0,
    "gn:timezone":"Asia/Taipei",
    "iso:country":"TW",
    "name:und_x_variant":[
        "Wai-lin"
    ],
    "name:zho_x_preferred":[
        "\u5916\u6797"
    ],
    "wof:name":"Wailin",
    "wof:placetype":"locality"
},
  "geometry": {"coordinates":[120.39833,23.42417],"type":"Point"}
}