{
  "type": "Feature",
  "properties": {
    "gn:admin1_code":"3.0",
    "gn:admin2_code":"TPQ",
    "gn:admin3_code":"F30",
    "gn:admin4_code":"65000210006.0",
    "gn:asciiname":"Chencuokeng",
    "gn:country_code":"TW",
    "gn:dem":129,
    "gn:feature_class":"P",
    "gn:feature_code":"PPL",
    "gn:name":"Chencuokeng",
    "gn:population":0,
    "gn:timezone":"Asia/Taipei",
    "iso:country":"TW",
    "name:zho_x_preferred":[
        "\u9673\u539d\u5751"
    ],
    "name:zho_x_variant":[
        "Ch\u2019en-ts\u2019o-k\u2019eng"
    ],
    "wof:name":"Chencuokeng",
    "wof:placetype":"locality"
},
  "geometry": {"coordinates":[121.51767,25.25368],"type":"Point"}
}