{
  "type": "Feature",
  "properties": {
    "gn:admin1_code":"04",
    "gn:admin2_code":"NAN",
    "gn:admin3_code":"M06",
    "gn:admin4_code":"10008060013.0",
    "gn:asciiname":"Dakeng",
    "gn:country_code":"TW",
    "gn:dem":236,
    "gn:feature_class":"P",
    "gn:feature_code":"PPL",
    "gn:name":"Dakeng",
    "gn:population":0,
    "gn:timezone":"Asia/Taipei",
    "iso:country":"TW",
    "name:ceb_x_preferred":[
        "Dakeng"
    ],
    "name:zho_x_preferred":[
        "\u5927\u5751"
    ],
    "name:zho_x_variant":[
        "Ta-k\u2019eng-ch\u2019ien",
        "T\u2019ai-k\u2019ang",
        "Ta-k\u2019eng",
        "\u5927\u5751\u98a8\u666f\u5340"
    ],
    "wof:name":"Dakeng",
    "wof:placetype":"locality"
},
  "geometry": {"coordinates":[120.65706000000002,23.85926],"type":"Point"}
}