{
  "type": "Feature",
  "properties": {
    "gn:admin1_code":"02",
    "gn:admin2_code":"KHH",
    "gn:admin3_code":"E31",
    "gn:admin4_code":"64000310011.0",
    "gn:asciiname":"Pitouxia",
    "gn:country_code":"TW",
    "gn:dem":55,
    "gn:feature_class":"P",
    "gn:feature_code":"PPL",
    "gn:name":"Pitouxia",
    "gn:population":0,
    "gn:timezone":"Asia/Taipei",
    "iso:country":"TW",
    "name:und_x_variant":[
        "Pitousia"
    ],
    "name:zho_x_preferred":[
        "\u57e4\u982d\u4e0b"
    ],
    "name:zho_x_variant":[
        "P\u2019i-t\u2019ou-hsia"
    ],
    "wof:name":"Pitouxia",
    "wof:placetype":"locality"
},
  "geometry": {"coordinates":[120.55098,22.90851],"type":"Point"}
}