{
  "type": "Feature",
  "properties": {
    "gn:admin1_code":"2.0",
    "gn:admin2_code":"KHH",
    "gn:admin3_code":"E31",
    "gn:admin4_code":"64000310006.0",
    "gn:asciiname":"Longbei",
    "gn:country_code":"TW",
    "gn:dem":60,
    "gn:feature_class":"P",
    "gn:feature_code":"PPL",
    "gn:name":"Longbei",
    "gn:population":0,
    "gn:timezone":"Asia/Taipei",
    "iso:country":"TW",
    "name:und_x_variant":[
        "Lung-pei"
    ],
    "name:zho_x_preferred":[
        "\u9f8d\u80cc"
    ],
    "wof:name":"Longbei",
    "wof:placetype":"locality"
},
  "geometry": {"coordinates":[120.56299,22.8796],"type":"Point"}
}