{
  "type": "Feature",
  "properties": {
    "gn:admin1_code":"2.0",
    "gn:admin2_code":"KHH",
    "gn:admin3_code":"E35",
    "gn:admin4_code":"64000350001.0",
    "gn:asciiname":"Pingziding",
    "gn:country_code":"TW",
    "gn:dem":163,
    "gn:feature_class":"P",
    "gn:feature_code":"PPL",
    "gn:name":"Pingziding",
    "gn:population":0,
    "gn:timezone":"Asia/Taipei",
    "iso:country":"TW",
    "name:und_x_variant":[
        "Pingzihding"
    ],
    "name:zho_x_preferred":[
        "\u576a\u5b50\u9802"
    ],
    "name:zho_x_variant":[
        "P\u2019ing-tzu-ting"
    ],
    "wof:name":"Pingziding",
    "wof:placetype":"locality"
},
  "geometry": {"coordinates":[120.51416999999999,23.00222],"type":"Point"}
}