{
  "type": "Feature",
  "properties": {
    "gn:admin1_code":"1.0",
    "gn:admin2_code":"KIN",
    "gn:admin3_code":"W02",
    "gn:admin4_code":"9020020002.0",
    "gn:asciiname":"Xishanqian",
    "gn:country_code":"TW",
    "gn:dem":31,
    "gn:feature_class":"P",
    "gn:feature_code":"PPL",
    "gn:name":"Xishanqian",
    "gn:population":0,
    "gn:timezone":"Asia/Taipei",
    "iso:country":"TW",
    "name:und_x_variant":[
        "\u897f\u5c71\u524d",
        "Xishanqian"
    ],
    "name:zho_x_preferred":[
        "Hsi-shan-ch\u2019ien"
    ],
    "wof:name":"Xishanqian",
    "wof:placetype":"locality"
},
  "geometry": {"coordinates":[118.42753,24.49344],"type":"Point"}
}