{
  "type": "Feature",
  "properties": {
    "gn:admin1_code":"04",
    "gn:admin2_code":"CYQ",
    "gn:admin3_code":"Q17",
    "gn:admin4_code":"10010160004.0",
    "gn:asciiname":"Dingkeng",
    "gn:country_code":"TW",
    "gn:dem":196,
    "gn:feature_class":"P",
    "gn:feature_code":"PPL",
    "gn:name":"Dingkeng",
    "gn:population":0,
    "gn:timezone":"Asia/Taipei",
    "iso:country":"TW",
    "name:zho_x_preferred":[
        "\u9802\u5751"
    ],
    "name:zho_x_variant":[
        "Ting-k\u2019eng"
    ],
    "wof:name":"Dingkeng",
    "wof:placetype":"locality"
},
  "geometry": {"coordinates":[120.54486,23.46475],"type":"Point"}
}