{
  "type": "Feature",
  "properties": {
    "gn:admin1_code":"1.0",
    "gn:admin2_code":"LIE",
    "gn:admin3_code":"Z02",
    "gn:admin4_code":"9007020003.0",
    "gn:asciiname":"Qiaozicun",
    "gn:country_code":"TW",
    "gn:dem":75,
    "gn:feature_class":"P",
    "gn:feature_code":"PPL",
    "gn:name":"Qiaozicun",
    "gn:population":0,
    "gn:timezone":"Asia/Taipei",
    "iso:country":"TW",
    "name:und_x_variant":[
        "Ch\u2019iao-tzu",
        "Ch\u2019iao-tzu-ts\u2019un",
        "Qiaozicun"
    ],
    "wof:name":"Qiaozicun",
    "wof:placetype":"locality"
},
  "geometry": {"coordinates":[119.99417,26.2325],"type":"Point"}
}