{
  "type": "Feature",
  "properties": {
    "gn:admin1_code":"04",
    "gn:admin2_code":"KEE",
    "gn:admin3_code":"C05",
    "gn:admin4_code":"10017050013.0",
    "gn:asciiname":"Niuchougang",
    "gn:country_code":"TW",
    "gn:dem":51,
    "gn:feature_class":"P",
    "gn:feature_code":"PPL",
    "gn:name":"Niuchougang",
    "gn:population":0,
    "gn:timezone":"Asia/Taipei",
    "iso:country":"TW",
    "name:und_x_variant":[
        "Niu-ch\u2019ou-chiang",
        "Niu-ch\u2019ou-kang",
        "Niuchougang"
    ],
    "wof:name":"Niuchougang",
    "wof:placetype":"locality"
},
  "geometry": {"coordinates":[121.73333,25.15],"type":"Point"}
}