{
  "type": "Feature",
  "properties": {
    "gn:admin1_code":"04",
    "gn:admin2_code":"MIA",
    "gn:admin3_code":"K01",
    "gn:admin4_code":"10005010027.0",
    "gn:asciiname":"Dapingding",
    "gn:country_code":"TW",
    "gn:dem":178,
    "gn:feature_class":"P",
    "gn:feature_code":"PPL",
    "gn:name":"Dapingding",
    "gn:population":0,
    "gn:timezone":"Asia/Taipei",
    "iso:country":"TW",
    "name:zho_x_preferred":[
        "\u5927\u576a\u9802"
    ],
    "name:zho_x_variant":[
        "Ta-p\u2019ing-ting"
    ],
    "wof:name":"Dapingding",
    "wof:placetype":"locality"
},
  "geometry": {"coordinates":[120.80316999999999,24.53344],"type":"Point"}
}