{
  "type": "Feature",
  "properties": {
    "gn:admin1_code":"4.0",
    "gn:admin2_code":"TTT",
    "gn:admin3_code":"V12",
    "gn:admin4_code":"10014130004.0",
    "gn:asciiname":"Luanshan",
    "gn:country_code":"TW",
    "gn:dem":191,
    "gn:feature_class":"P",
    "gn:feature_code":"PPL",
    "gn:name":"Luanshan",
    "gn:population":0,
    "gn:timezone":"Asia/Taipei",
    "iso:country":"TW",
    "name:und_x_variant":[
        "Chung-yeh",
        "Luanshan",
        "Luan-shan"
    ],
    "name:zho_x_preferred":[
        "Luan-shan-ts\u2019un"
    ],
    "name:zho_x_variant":[
        "Lan-shan-ts\u2019un",
        "\u9e1e\u5c71"
    ],
    "wof:name":"Luanshan",
    "wof:placetype":"locality"
},
  "geometry": {"coordinates":[121.15234,22.90079],"type":"Point"}
}