{
  "type": "Feature",
  "properties": {
    "gn:admin1_code":"4.0",
    "gn:admin2_code":"TXG",
    "gn:admin3_code":"B10",
    "gn:admin4_code":"66000100020.0",
    "gn:asciiname":"Dawo",
    "gn:country_code":"TW",
    "gn:dem":421,
    "gn:feature_class":"P",
    "gn:feature_code":"PPL",
    "gn:name":"Dawo",
    "gn:population":0,
    "gn:timezone":"Asia/Taipei",
    "iso:country":"TW",
    "name:und_x_variant":[
        "Ta-wo"
    ],
    "name:zho_x_preferred":[
        "\u5927\u7aa9"
    ],
    "wof:name":"Dawo",
    "wof:placetype":"locality"
},
  "geometry": {"coordinates":[120.83060999999999,24.28236],"type":"Point"}
}