{
  "type": "Feature",
  "properties": {
    "gn:admin1_code":"4.0",
    "gn:admin2_code":"CYQ",
    "gn:admin3_code":"Q10",
    "gn:admin4_code":"10010100016.0",
    "gn:asciiname":"Ganziliao",
    "gn:country_code":"TW",
    "gn:dem":7,
    "gn:feature_class":"P",
    "gn:feature_code":"PPL",
    "gn:name":"Ganziliao",
    "gn:population":0,
    "gn:timezone":"Asia/Taipei",
    "iso:country":"TW",
    "name:und_x_variant":[
        "Ganzihliao",
        "Kan-tzu-liao"
    ],
    "name:zho_x_preferred":[
        "\u7aff\u5b50\u5bee"
    ],
    "wof:name":"Ganziliao",
    "wof:placetype":"locality"
},
  "geometry": {"coordinates":[120.18631000000001,23.30629],"type":"Point"}
}