{
  "type": "Feature",
  "properties": {
    "gn:admin1_code":"4.0",
    "gn:admin2_code":"HUA",
    "gn:admin3_code":"U03",
    "gn:admin4_code":"10015030007.0",
    "gn:asciiname":"Chuanzishan",
    "gn:country_code":"TW",
    "gn:dem":145,
    "gn:feature_class":"P",
    "gn:feature_code":"PPL",
    "gn:name":"Chuanzishan",
    "gn:population":0,
    "gn:timezone":"Asia/Taipei",
    "iso:country":"TW",
    "name:und_x_variant":[
        "Chuanzihshan"
    ],
    "name:zho_x_preferred":[
        "\u8239\u4ed4\u5c71"
    ],
    "name:zho_x_variant":[
        "Ch\u2019uan-tzu-shan"
    ],
    "wof:name":"Chuanzishan",
    "wof:placetype":"locality"
},
  "geometry": {"coordinates":[121.32366,23.29381],"type":"Point"}
}