{
  "type": "Feature",
  "properties": {
    "gn:admin1_code":"04",
    "gn:admin2_code":"TNN",
    "gn:admin3_code":"R26",
    "gn:admin4_code":"67000260006.0",
    "gn:asciiname":"Sanjiaotan",
    "gn:country_code":"TW",
    "gn:dem":46,
    "gn:feature_class":"P",
    "gn:feature_code":"PPL",
    "gn:name":"Sanjiaotan",
    "gn:population":0,
    "gn:timezone":"Asia/Taipei",
    "iso:country":"TW",
    "name:und_x_variant":[
        "San-chiao"
    ],
    "name:zho_x_preferred":[
        "\u4e09\u89d2\u6f6d"
    ],
    "name:zho_x_variant":[
        "San-chiao-t\u2019an"
    ],
    "wof:name":"Sanjiaotan",
    "wof:placetype":"locality"
},
  "geometry": {"coordinates":[120.4315,23.04418],"type":"Point"}
}