{
  "type": "Feature",
  "properties": {
    "gn:admin1_code":"04",
    "gn:admin2_code":"HSQ",
    "gn:admin3_code":"O03",
    "gn:admin4_code":"10018030015.0",
    "gn:asciiname":"Dingliao",
    "gn:country_code":"TW",
    "gn:dem":9,
    "gn:feature_class":"P",
    "gn:feature_code":"PPL",
    "gn:name":"Dingliao",
    "gn:population":0,
    "gn:timezone":"Asia/Taipei",
    "iso:country":"TW",
    "name:und_x_variant":[
        "Ting-liao"
    ],
    "name:zho_x_preferred":[
        "\u9802\u5bee"
    ],
    "wof:name":"Dingliao",
    "wof:placetype":"locality"
},
  "geometry": {"coordinates":[120.91500000000001,24.77361],"type":"Point"}
}