{
  "type": "Feature",
  "properties": {
    "gn:admin1_code":"04",
    "gn:admin2_code":"ILA",
    "gn:admin3_code":"G02",
    "gn:admin4_code":"10002040012.0",
    "gn:asciiname":"Toucheng",
    "gn:country_code":"TW",
    "gn:dem":15,
    "gn:feature_class":"P",
    "gn:feature_code":"PPL",
    "gn:name":"Toucheng",
    "gn:population":0,
    "gn:timezone":"Asia/Taipei",
    "iso:country":"TW",
    "name:zho_x_preferred":[
        "T\u2019ou-wei-chuang"
    ],
    "name:zho_x_variant":[
        "T\u2019ou-wei",
        "T\u2019ou-ch\u2019eng"
    ],
    "wof:name":"Toucheng",
    "wof:placetype":"locality"
},
  "geometry": {"coordinates":[121.82277999999999,24.85611],"type":"Point"}
}