{
  "type": "Feature",
  "properties": {
    "gn:admin1_code":"02",
    "gn:admin2_code":"KHH",
    "gn:admin3_code":"E22",
    "gn:admin4_code":"64000220010.0",
    "gn:asciiname":"Pouyang",
    "gn:country_code":"TW",
    "gn:dem":55,
    "gn:feature_class":"P",
    "gn:feature_code":"PPL",
    "gn:name":"Pouyang",
    "gn:population":0,
    "gn:timezone":"Asia/Taipei",
    "iso:country":"TW",
    "name:und_x_variant":[
        "Pu-yang"
    ],
    "name:zho_x_preferred":[
        "\u5ecd\u6d0b"
    ],
    "name:zho_x_variant":[
        "P\u2019ou-yang"
    ],
    "wof:name":"Pouyang",
    "wof:placetype":"locality"
},
  "geometry": {"coordinates":[120.35917000000001,22.83972],"type":"Point"}
}