{
  "type": "Feature",
  "properties": {
    "gn:admin1_code":"4.0",
    "gn:admin2_code":"ILA",
    "gn:admin3_code":"G01",
    "gn:admin4_code":"10002010026.0",
    "gn:asciiname":"Xindian",
    "gn:country_code":"TW",
    "gn:dem":12,
    "gn:feature_class":"P",
    "gn:feature_code":"PPL",
    "gn:name":"Xindian",
    "gn:population":0,
    "gn:timezone":"Asia/Taipei",
    "iso:country":"TW",
    "name:und_x_variant":[
        "Sindian",
        "Xindian",
        "Hsin-tien"
    ],
    "name:zho_x_preferred":[
        "\u65b0\u5e97"
    ],
    "wof:name":"Xindian",
    "wof:placetype":"locality"
},
  "geometry": {"coordinates":[121.7557,24.7686],"type":"Point"}
}