{
  "type": "Feature",
  "properties": {
    "gn:admin1_code":"3.0",
    "gn:admin2_code":"TPQ",
    "gn:admin3_code":"F30",
    "gn:admin4_code":"65000210009.0",
    "gn:asciiname":"Mazhucuo",
    "gn:country_code":"TW",
    "gn:dem":90,
    "gn:feature_class":"P",
    "gn:feature_code":"PPL",
    "gn:name":"Mazhucuo",
    "gn:population":0,
    "gn:timezone":"Asia/Taipei",
    "iso:country":"TW",
    "name:und_x_variant":[
        "Majhucuo"
    ],
    "name:zho_x_preferred":[
        "\u9ebb\u7af9\u539d"
    ],
    "name:zho_x_variant":[
        "Ma-chu-ts\u2019o"
    ],
    "wof:name":"Mazhucuo",
    "wof:placetype":"locality"
},
  "geometry": {"coordinates":[121.48367,25.24404],"type":"Point"}
}