{
  "type": "Feature",
  "properties": {
    "gn:admin1_code":"04",
    "gn:admin2_code":"TTT",
    "gn:admin3_code":"V14",
    "gn:admin4_code":"10014150003.0",
    "gn:asciiname":"Shaojia",
    "gn:country_code":"TW",
    "gn:dem":732,
    "gn:feature_class":"P",
    "gn:feature_code":"PPL",
    "gn:name":"Shaojia",
    "gn:population":0,
    "gn:timezone":"Asia/Taipei",
    "iso:country":"TW",
    "name:und_x_variant":[
        "Shao-chia-she",
        "Shaojia",
        "Shao-chia"
    ],
    "name:zho_x_preferred":[
        "Shao-chia-ts\u2019un"
    ],
    "name:zho_x_variant":[
        "\u7d39\u5bb6"
    ],
    "wof:name":"Shaojia",
    "wof:placetype":"locality"
},
  "geometry": {"coordinates":[120.84417000000001,22.41694],"type":"Point"}
}