{
  "type": "Feature",
  "properties": {
    "gn:admin1_code":"3.0",
    "gn:admin2_code":"TPQ",
    "gn:admin3_code":"F08",
    "gn:admin4_code":"65000190009.0",
    "gn:asciiname":"Erkonggui",
    "gn:country_code":"TW",
    "gn:dem":487,
    "gn:feature_class":"P",
    "gn:feature_code":"PPL",
    "gn:name":"Erkonggui",
    "gn:population":0,
    "gn:timezone":"Asia/Taipei",
    "iso:country":"TW",
    "name:und_x_variant":[
        "Erkongguei",
        "Erkonggui"
    ],
    "name:zho_x_preferred":[
        "\u8033\u7a7a\u9f9c"
    ],
    "name:zho_x_variant":[
        "Erh-k\u2019ung-kuei"
    ],
    "wof:name":"Erkonggui",
    "wof:placetype":"locality"
},
  "geometry": {"coordinates":[121.6964,25.0342],"type":"Point"}
}