{
  "type": "Feature",
  "properties": {
    "gn:admin1_code":"04",
    "gn:admin2_code":"MIA",
    "gn:admin3_code":"K10",
    "gn:admin4_code":"10005050003.0",
    "gn:asciiname":"Douhuanping",
    "gn:country_code":"TW",
    "gn:dem":77,
    "gn:feature_class":"P",
    "gn:feature_code":"PPL",
    "gn:name":"Douhuanping",
    "gn:population":0,
    "gn:timezone":"Asia/Taipei",
    "iso:country":"TW",
    "name:zho_x_preferred":[
        "\u6597\u7165\u576a"
    ],
    "name:zho_x_variant":[
        "Tou-huan-p\u2019ing"
    ],
    "wof:name":"Douhuanping",
    "wof:placetype":"locality"
},
  "geometry": {"coordinates":[120.94428000000001,24.68107],"type":"Point"}
}