{
  "type": "Feature",
  "properties": {
    "iso:country":"TW",
    "name:eng_x_preferred":[
        "Chishui"
    ],
    "name:eng_x_variant":[
        "Chishui Village"
    ],
    "name:zho_tw_x_preferred":[
        "\u8d64\u6c34\u6751"
    ],
    "qs:name":"\u8d64\u6c34\u6751",
    "qs:name_adm0":"\u81fa\u7063",
    "qs:name_adm1":"\u5357\u6295\u7e23",
    "qs:photos":22,
    "qs:photos_1k":4,
    "qs:photos_9k":1,
    "qs:photos_9r":1,
    "qs:photos_all":22,
    "qs:photos_sr":1,
    "qs:placetype":"Town",
    "qs:pop_sr":"0",
    "wof:name":"Chishui",
    "wof:placetype":"locality"
},
  "geometry": {"coordinates":[120.62988199999999,23.869097],"type":"Point"}
}