{
  "type": "Feature",
  "properties": {
    "iso:country":"TW",
    "qs:name":"\u6797\u9756\u91cc",
    "qs:name_adm0":"\u81fa\u7063",
    "qs:name_adm1":"\u9ad8\u96c4\u5e02",
    "qs:photos":55,
    "qs:photos_1k":11,
    "qs:photos_9k":1,
    "qs:photos_9r":2,
    "qs:photos_all":55,
    "qs:photos_sr":2,
    "qs:placetype":"Suburb",
    "qs:pop_sr":"0",
    "wof:name":"\u6797\u9756\u91cc",
    "wof:placetype":"neighbourhood"
},
  "geometry": {"coordinates":[120.326533,22.621816],"type":"Point"}
}