{
  "type": "Feature",
  "properties": {
    "iso:country":"TW",
    "qs:name":"\u6b66\u767b\u6751",
    "qs:name_adm0":"\u81fa\u7063",
    "qs:name_adm1":"\u5357\u6295\u7e23",
    "qs:photos":50,
    "qs:photos_1k":10,
    "qs:photos_9k":1,
    "qs:photos_9r":2,
    "qs:photos_all":50,
    "qs:photos_sr":2,
    "qs:placetype":"Town",
    "qs:pop_sr":"0",
    "wof:name":"\u6b66\u767b\u6751",
    "wof:placetype":"locality"
},
  "geometry": {"coordinates":[120.885465,23.8208775],"type":"Point"}
}