{
  "type": "Feature",
  "properties": {
    "gn:admin1_code":"4.0",
    "gn:admin2_code":"TXG",
    "gn:admin3_code":"B09",
    "gn:admin4_code":"66000090025.0",
    "gn:asciiname":"Xianankeng",
    "gn:country_code":"TW",
    "gn:dem":225,
    "gn:feature_class":"P",
    "gn:feature_code":"PPL",
    "gn:name":"Xianankeng",
    "gn:population":0,
    "gn:timezone":"Asia/Taipei",
    "iso:country":"TW",
    "name:und_x_variant":[
        "\u4e0b\u5357\u5751",
        "Xianankeng",
        "Sianankeng"
    ],
    "name:zho_x_preferred":[
        "Hsia-nan-k\u2019eng"
    ],
    "wof:name":"Xianankeng",
    "wof:placetype":"locality"
},
  "geometry": {"coordinates":[120.72638999999999,24.24427],"type":"Point"}
}