{
  "type": "Feature",
  "properties": {
    "gn:admin1_code":"4.0",
    "gn:admin2_code":"MIA",
    "gn:admin3_code":"K15",
    "gn:admin4_code":"10005080008.0",
    "gn:asciiname":"Shuiliudongkou",
    "gn:country_code":"TW",
    "gn:dem":313,
    "gn:feature_class":"P",
    "gn:feature_code":"PPL",
    "gn:name":"Shuiliudongkou",
    "gn:population":0,
    "gn:timezone":"Asia/Taipei",
    "iso:country":"TW",
    "name:und_x_variant":[
        "Shueilioudongkou",
        "Shuiliudongkou"
    ],
    "name:zho_x_preferred":[
        "\u6c34\u6d41\u6771\u53e3"
    ],
    "name:zho_x_variant":[
        "Shui-liu-tung-k\u2019ou"
    ],
    "wof:name":"Shuiliudongkou",
    "wof:placetype":"locality"
},
  "geometry": {"coordinates":[120.86109999999999,24.37752],"type":"Point"}
}