{
  "type": "Feature",
  "properties": {
    "gn:admin1_code":"4.0",
    "gn:admin2_code":"NAN",
    "gn:admin3_code":"M10",
    "gn:admin4_code":"10008100013.0",
    "gn:asciiname":"Shibafen",
    "gn:country_code":"TW",
    "gn:dem":630,
    "gn:feature_class":"P",
    "gn:feature_code":"PPL",
    "gn:name":"Shibafen",
    "gn:population":0,
    "gn:timezone":"Asia/Taipei",
    "iso:country":"TW",
    "name:und_x_variant":[
        "Shihbafen",
        "Shih-pa-fen"
    ],
    "name:zho_x_preferred":[
        "\u5341\u516b\u4efd"
    ],
    "wof:name":"Shibafen",
    "wof:placetype":"locality"
},
  "geometry": {"coordinates":[120.84027,24.09441],"type":"Point"}
}