{
  "type": "Feature",
  "properties": {
    "gn:admin1_code":"1.0",
    "gn:asciiname":"Laotaoli",
    "gn:country_code":"TW",
    "gn:dem":-9999,
    "gn:feature_class":"P",
    "gn:feature_code":"PPL",
    "gn:name":"Laotaoli",
    "gn:population":0,
    "gn:timezone":"Asia/Taipei",
    "iso:country":"TW",
    "name:und_x_variant":[
        "Lao-t\u2019ao-li"
    ],
    "wof:name":"Laotaoli",
    "wof:placetype":"locality"
},
  "geometry": {"coordinates":[119.93333,25.98333],"type":"Point"}
}