{
  "type": "Feature",
  "properties": {
    "gn:admin1_code":"3.0",
    "gn:admin2_code":"TPQ",
    "gn:admin3_code":"F23",
    "gn:admin4_code":"65000250011.0",
    "gn:asciiname":"Chipilun",
    "gn:country_code":"TW",
    "gn:dem":310,
    "gn:feature_class":"P",
    "gn:feature_code":"PPL",
    "gn:name":"Chipilun",
    "gn:population":0,
    "gn:timezone":"Asia/Taipei",
    "iso:country":"TW",
    "name:und_x_variant":[
        "Chihpilun",
        "Chipilun"
    ],
    "name:zho_x_preferred":[
        "\u8d64\u76ae\u5d19"
    ],
    "name:zho_x_variant":[
        "Ch\u2019ih-p\u2019i-lun"
    ],
    "wof:name":"Chipilun",
    "wof:placetype":"locality"
},
  "geometry": {"coordinates":[121.78977,25.01896],"type":"Point"}
}