{
  "type": "Feature",
  "properties": {
    "gn:admin1_code":"4.0",
    "gn:admin2_code":"CHA",
    "gn:admin3_code":"N16",
    "gn:admin4_code":"10007140013.0",
    "gn:asciiname":"Zhutoujiao",
    "gn:country_code":"TW",
    "gn:dem":15,
    "gn:feature_class":"P",
    "gn:feature_code":"PPL",
    "gn:name":"Zhutoujiao",
    "gn:population":0,
    "gn:timezone":"Asia/Taipei",
    "iso:country":"TW",
    "name:und_x_variant":[
        "Hsin-hsing",
        "Jhutoujiao"
    ],
    "name:zho_x_preferred":[
        "\u7af9\u982d\u89d2"
    ],
    "name:zho_x_variant":[
        "Chu-t\u2019ou-chiao"
    ],
    "wof:name":"Zhutoujiao",
    "wof:placetype":"locality"
},
  "geometry": {"coordinates":[120.45111,24.01694],"type":"Point"}
}