{
  "type": "Feature",
  "properties": {
    "gn:admin1_code":"4.0",
    "gn:asciiname":"Guishanli",
    "gn:country_code":"TW",
    "gn:dem":-9999,
    "gn:feature_class":"P",
    "gn:feature_code":"PPL",
    "gn:name":"Guishanli",
    "gn:population":0,
    "gn:timezone":"Asia/Taipei",
    "iso:country":"TW",
    "name:und_x_variant":[
        "Kuei-shan",
        "Kuei-shan-li",
        "Guishanli"
    ],
    "wof:name":"Guishanli",
    "wof:placetype":"locality"
},
  "geometry": {"coordinates":[121.93333,24.85],"type":"Point"}
}