{
  "type": "Feature",
  "properties": {
    "gn:admin1_code":"3.0",
    "gn:admin2_code":"TPQ",
    "gn:admin3_code":"F24",
    "gn:admin4_code":"65000260007.0",
    "gn:asciiname":"Guogang",
    "gn:country_code":"TW",
    "gn:dem":9,
    "gn:feature_class":"P",
    "gn:feature_code":"PPL",
    "gn:name":"Guogang",
    "gn:population":0,
    "gn:timezone":"Asia/Taipei",
    "iso:country":"TW",
    "name:und_x_variant":[
        "Kuo-kang"
    ],
    "name:zho_x_preferred":[
        "\u904e\u6e2f"
    ],
    "wof:name":"Guogang",
    "wof:placetype":"locality"
},
  "geometry": {"coordinates":[121.92609,25.04845],"type":"Point"}
}