{
  "type": "Feature",
  "properties": {
    "gn:admin1_code":"04",
    "gn:admin2_code":"TPE",
    "gn:admin3_code":"A17",
    "gn:admin4_code":"63000020018.0",
    "gn:asciiname":"Songshan",
    "gn:country_code":"TW",
    "gn:dem":16,
    "gn:feature_class":"P",
    "gn:feature_code":"PPL",
    "gn:name":"Songshan",
    "gn:population":0,
    "gn:timezone":"Asia/Taipei",
    "iso:country":"TW",
    "name:ceb_x_preferred":[
        "Songshan"
    ],
    "name:deu_x_preferred":[
        "Songshan"
    ],
    "name:fra_x_preferred":[
        "Songshan"
    ],
    "name:pol_x_preferred":[
        "Songshan"
    ],
    "name:rus_x_preferred":[
        "\u0421\u0443\u043d\u0448\u0430\u043d\u044c"
    ],
    "name:sco_x_preferred":[
        "Songshan"
    ],
    "name:und_x_variant":[
        "Sung-shan-chuang",
        "Sung-shan-chen",
        "Sung-shan"
    ],
    "name:zho_x_preferred":[
        "\u677e\u5c71"
    ],
    "wof:name":"Songshan",
    "wof:placetype":"locality"
},
  "geometry": {"coordinates":[121.57966999999999,25.04306],"type":"Point"}
}