{
  "type": "Feature",
  "properties": {
    "gn:admin1_code":"04",
    "gn:admin2_code":"MIA",
    "gn:admin3_code":"K04",
    "gn:admin4_code":"10005090010.0",
    "gn:asciiname":"Dangbatu",
    "gn:country_code":"TW",
    "gn:dem":503,
    "gn:feature_class":"P",
    "gn:feature_code":"PPL",
    "gn:name":"Dangbatu",
    "gn:population":0,
    "gn:timezone":"Asia/Taipei",
    "iso:country":"TW",
    "name:und_x_variant":[
        "Tang-pa-tung"
    ],
    "name:zho_x_preferred":[
        "T\u2019ang-pa-tieh"
    ],
    "name:zho_x_variant":[
        "T\u2019ang-pa-tien",
        "Tang-pa-t\u2019u",
        "\u76ea\u628a\u51f8",
        "T\u2019ang-pa-t\u2019u"
    ],
    "wof:name":"Dangbatu",
    "wof:placetype":"locality"
},
  "geometry": {"coordinates":[120.84883000000001,24.45513],"type":"Point"}
}