{
  "type": "Feature",
  "properties": {
    "gn:admin1_code":"04",
    "gn:admin2_code":"ILA",
    "gn:admin3_code":"G11",
    "gn:admin4_code":"10002110004.0",
    "gn:asciiname":"Daxi",
    "gn:country_code":"TW",
    "gn:dem":205,
    "gn:feature_class":"P",
    "gn:feature_code":"PPL",
    "gn:name":"Daxi",
    "gn:population":0,
    "gn:timezone":"Asia/Taipei",
    "iso:country":"TW",
    "name:ceb_x_preferred":[
        "Daxi"
    ],
    "name:deu_x_preferred":[
        "Daxi"
    ],
    "name:swe_x_preferred":[
        "Daxi"
    ],
    "name:und_x_variant":[
        "Dasi",
        "Ta-hsi"
    ],
    "name:zho_x_preferred":[
        "Ta-ch\u2019i"
    ],
    "name:zho_x_variant":[
        "\u5927\u6eaa"
    ],
    "wof:name":"Daxi",
    "wof:placetype":"locality"
},
  "geometry": {"coordinates":[121.60297,24.63211],"type":"Point"}
}