{
  "type": "Feature",
  "properties": {
    "gn:admin1_code":"4.0",
    "gn:admin2_code":"PIF",
    "gn:admin3_code":"T09",
    "gn:admin4_code":"10013090013.0",
    "gn:asciiname":"Xinji",
    "gn:country_code":"TW",
    "gn:dem":36,
    "gn:feature_class":"P",
    "gn:feature_code":"PPL",
    "gn:name":"Xinji",
    "gn:population":0,
    "gn:timezone":"Asia/Taipei",
    "iso:country":"TW",
    "name:ara_x_preferred":[
        "\u0634\u064a\u0646\u062c\u064a"
    ],
    "name:deu_x_preferred":[
        "Xinji"
    ],
    "name:eus_x_preferred":[
        "Xinji"
    ],
    "name:fra_x_preferred":[
        "Xinji"
    ],
    "name:ita_x_preferred":[
        "Xinji"
    ],
    "name:jpn_x_preferred":[
        "\u8f9b\u96c6\u5e02"
    ],
    "name:kik_x_preferred":[
        "Xinji"
    ],
    "name:kor_x_preferred":[
        "\uc2e0\uc9c0\uc2dc"
    ],
    "name:mlg_x_preferred":[
        "Xinji"
    ],
    "name:nor_x_preferred":[
        "Xinji"
    ],
    "name:pam_x_preferred":[
        "Xinji"
    ],
    "name:rus_x_preferred":[
        "\u0421\u0438\u043d\u044c\u0446\u0437\u0438"
    ],
    "name:sco_x_preferred":[
        "Xinji"
    ],
    "name:swe_x_preferred":[
        "Xinji"
    ],
    "name:und_x_variant":[
        "Sinji",
        "Hsin-chi"
    ],
    "name:urd_x_preferred":[
        "\u0634\u0646\u062c\u06cc"
    ],
    "name:vie_x_preferred":[
        "T\u00e2n T\u1eadp"
    ],
    "name:war_x_preferred":[
        "Xinji"
    ],
    "name:zho_x_preferred":[
        "\u65b0\u5409"
    ],
    "name:zho_x_variant":[
        "Hsin-chi-ts\u2019un",
        "\u8f9b\u96c6\u5e02"
    ],
    "wof:name":"Xinji",
    "wof:placetype":"locality"
},
  "geometry": {"coordinates":[120.46972,22.81278],"type":"Point"}
}