{
  "type": "Feature",
  "properties": {
    "gn:admin1_code":"4.0",
    "gn:admin2_code":"PIF",
    "gn:admin3_code":"T09",
    "gn:admin4_code":"10013090013.0",
    "gn:asciiname":"Xinji",
    "gn:country_code":"TW",
    "gn:dem":36,
    "gn:feature_class":"P",
    "gn:feature_code":"PPL",
    "gn:name":"Xinji",
    "gn:population":0,
    "gn:timezone":"Asia/Taipei",
    "iso:country":"TW",
    "name:und_x_variant":[
        "Sinji",
        "Xinji",
        "Hsin-chi"
    ],
    "name:zho_x_preferred":[
        "\u65b0\u5409"
    ],
    "name:zho_x_variant":[
        "Hsin-chi-ts\u2019un"
    ],
    "wof:name":"Xinji",
    "wof:placetype":"locality"
},
  "geometry": {"coordinates":[120.46972,22.81278],"type":"Point"}
}