{
  "type": "Feature",
  "properties": {
    "gn:admin1_code":"04",
    "gn:admin2_code":"CYQ",
    "gn:admin3_code":"Q03",
    "gn:admin4_code":"10010030010.0",
    "gn:asciiname":"Taiyanxintun",
    "gn:country_code":"TW",
    "gn:dem":1,
    "gn:feature_class":"P",
    "gn:feature_code":"PPL",
    "gn:name":"Taiyanxintun",
    "gn:population":0,
    "gn:timezone":"Asia/Taipei",
    "iso:country":"TW",
    "name:und_x_variant":[
        "T\u2019ai-yen-hsin-t\u2019un"
    ],
    "wof:name":"Taiyanxintun",
    "wof:placetype":"locality"
},
  "geometry": {"coordinates":[120.15000000000001,23.33333],"type":"Point"}
}