{
  "type": "Feature",
  "properties": {
    "gn:admin1_code":"04",
    "gn:admin2_code":"CYQ",
    "gn:admin3_code":"Q07",
    "gn:admin4_code":"10010070023.0",
    "gn:asciiname":"Dongcuo",
    "gn:country_code":"TW",
    "gn:dem":13,
    "gn:feature_class":"P",
    "gn:feature_code":"PPL",
    "gn:name":"Dongcuo",
    "gn:population":0,
    "gn:timezone":"Asia/Taipei",
    "iso:country":"TW",
    "name:zho_x_preferred":[
        "\u8463\u539d"
    ],
    "name:zho_x_variant":[
        "Tung-ts\u2019o"
    ],
    "wof:name":"Dongcuo",
    "wof:placetype":"locality"
},
  "geometry": {"coordinates":[120.33676,23.55576],"type":"Point"}
}