{
  "type": "Feature",
  "properties": {
    "gn:admin1_code":"4.0",
    "gn:admin2_code":"ILA",
    "gn:admin3_code":"G05",
    "gn:admin4_code":"10002070008.0",
    "gn:asciiname":"Shigong",
    "gn:country_code":"TW",
    "gn:dem":180,
    "gn:feature_class":"P",
    "gn:feature_code":"PPL",
    "gn:name":"Shigong",
    "gn:population":0,
    "gn:timezone":"Asia/Taipei",
    "iso:country":"TW",
    "name:und_x_variant":[
        "Shiu-kung",
        "Shihgong",
        "Shigong",
        "Shih-kung"
    ],
    "name:zho_x_preferred":[
        "\u77f3\u516c"
    ],
    "wof:name":"Shigong",
    "wof:placetype":"locality"
},
  "geometry": {"coordinates":[121.62860000000001,24.7247],"type":"Point"}
}