{
  "type": "Feature",
  "properties": {
    "gn:admin1_code":"4.0",
    "gn:admin2_code":"TNN",
    "gn:admin3_code":"R07",
    "gn:admin4_code":"67000070013.0",
    "gn:asciiname":"Gouziqian",
    "gn:country_code":"TW",
    "gn:dem":16,
    "gn:feature_class":"P",
    "gn:feature_code":"PPL",
    "gn:name":"Gouziqian",
    "gn:population":0,
    "gn:timezone":"Asia/Taipei",
    "iso:country":"TW",
    "name:und_x_variant":[
        "Gouzihcian",
        "Gouziqian"
    ],
    "name:zho_x_preferred":[
        "\u6e9d\u5b50\u5898"
    ],
    "name:zho_x_variant":[
        "Kou-tzu-ch\u2019ien"
    ],
    "wof:name":"Gouziqian",
    "wof:placetype":"locality"
},
  "geometry": {"coordinates":[120.25957,23.17761],"type":"Point"}
}