{
  "type": "Feature",
  "properties": {
    "gn:admin1_code":"04",
    "gn:admin2_code":"TAO",
    "gn:admin3_code":"H12",
    "gn:admin4_code":"68000120002.0",
    "gn:asciiname":"Baiyu",
    "gn:country_code":"TW",
    "gn:dem":17,
    "gn:feature_class":"P",
    "gn:feature_code":"PPL",
    "gn:name":"Baiyu",
    "gn:population":0,
    "gn:timezone":"Asia/Taipei",
    "iso:country":"TW",
    "name:zho_x_preferred":[
        "Pai-y\u00fc-ts\u2019un"
    ],
    "name:zho_x_variant":[
        "Pai-sha-t\u2019un",
        "\u767d\u7389",
        "Pai-y\u00fc"
    ],
    "wof:name":"Baiyu",
    "wof:placetype":"locality"
},
  "geometry": {"coordinates":[121.08996,25.0456],"type":"Point"}
}