{
  "type": "Feature",
  "properties": {
    "iso:country":"TW",
    "qs:name":"\u6eaa\u5e95\u6751",
    "qs:name_adm0":"\u81fa\u7063",
    "qs:name_adm1":"\u5f70\u5316\u7e23",
    "qs:photos":84,
    "qs:photos_1k":17,
    "qs:photos_9k":1,
    "qs:photos_9r":3,
    "qs:photos_all":84,
    "qs:photos_sr":3,
    "qs:placetype":"Town",
    "qs:pop_sr":"0",
    "wof:name":"\u6eaa\u5e95\u6751",
    "wof:placetype":"locality"
},
  "geometry": {"coordinates":[120.543065,24.19773],"type":"Point"}
}