{
  "type": "Feature",
  "properties": {
    "gn:admin1_code":"4.0",
    "gn:admin2_code":"TNN",
    "gn:admin3_code":"R27",
    "gn:admin4_code":"67000270015.0",
    "gn:asciiname":"Ercenghang",
    "gn:country_code":"TW",
    "gn:dem":12,
    "gn:feature_class":"P",
    "gn:feature_code":"PPL",
    "gn:name":"Ercenghang",
    "gn:population":0,
    "gn:timezone":"Asia/Taipei",
    "iso:country":"TW",
    "name:zho_x_preferred":[
        "\u4e8c\u5c64\u884c"
    ],
    "name:zho_x_variant":[
        "Erh-ts\u2019en-hang",
        "Erh-ts\u2019eng-hang"
    ],
    "wof:name":"Ercenghang",
    "wof:placetype":"locality"
},
  "geometry": {"coordinates":[120.21832999999999,22.91611],"type":"Point"}
}