{
  "type": "Feature",
  "properties": {
    "gn:admin1_code":"2.0",
    "gn:admin2_code":"KHH",
    "gn:admin3_code":"E21",
    "gn:admin4_code":"64000210010.0",
    "gn:asciiname":"Xiwei",
    "gn:country_code":"TW",
    "gn:dem":47,
    "gn:feature_class":"P",
    "gn:feature_code":"PPL",
    "gn:name":"Xiwei",
    "gn:population":0,
    "gn:timezone":"Asia/Taipei",
    "iso:country":"TW",
    "name:ceb_x_preferred":[
        "Xiwei"
    ],
    "name:swe_x_preferred":[
        "Xiwei"
    ],
    "name:und_x_variant":[
        "Siwei",
        "Xiwei",
        "Hsi-wei"
    ],
    "name:zho_x_preferred":[
        "\u6eaa\u5c3e"
    ],
    "wof:name":"Xiwei",
    "wof:placetype":"locality"
},
  "geometry": {"coordinates":[120.39472000000001,22.76972],"type":"Point"}
}