{
  "type": "Feature",
  "properties": {
    "iso:country":"TW",
    "name:eng_x_preferred":[
        "Rende"
    ],
    "name:eng_x_variant":[
        "Rende Village"
    ],
    "name:zho_tw_x_preferred":[
        "\u4ec1\u5fb7\u91cc"
    ],
    "qs:name":"\u4ec1\u5fb7\u91cc",
    "qs:name_adm0":"\u81fa\u7063",
    "qs:name_adm1":"\u65b0\u7af9\u5e02",
    "qs:photos":177,
    "qs:photos_1k":36,
    "qs:photos_9k":1,
    "qs:photos_9r":4,
    "qs:photos_all":177,
    "qs:photos_sr":4,
    "qs:placetype":"Suburb",
    "qs:pop_sr":"0",
    "wof:name":"Rende",
    "wof:placetype":"neighbourhood"
},
  "geometry": {"coordinates":[120.965103,24.807666],"type":"Point"}
}