{
  "type": "Feature",
  "properties": {
    "gn:admin1_code":"4.0",
    "gn:admin2_code":"TPE",
    "gn:admin3_code":"A11",
    "gn:admin4_code":"63000080036.0",
    "gn:asciiname":"Qishan",
    "gn:country_code":"TW",
    "gn:dem":262,
    "gn:feature_class":"P",
    "gn:feature_code":"PPL",
    "gn:name":"Qishan",
    "gn:population":0,
    "gn:timezone":"Asia/Taipei",
    "iso:country":"TW",
    "name:und_x_variant":[
        "Cishan",
        "Qishan"
    ],
    "name:zho_x_preferred":[
        "\u5c90\u5c71"
    ],
    "name:zho_x_variant":[
        "Ch\u2019i-shan"
    ],
    "wof:name":"Qishan",
    "wof:placetype":"locality"
},
  "geometry": {"coordinates":[121.59939,24.97276],"type":"Point"}
}