{
  "type": "Feature",
  "properties": {
    "gn:admin1_code":"4.0",
    "gn:admin2_code":"ILA",
    "gn:admin3_code":"G03",
    "gn:admin4_code":"10002050007.0",
    "gn:asciiname":"Zhouziwei",
    "gn:country_code":"TW",
    "gn:dem":3,
    "gn:feature_class":"P",
    "gn:feature_code":"PPL",
    "gn:name":"Zhouziwei",
    "gn:population":0,
    "gn:timezone":"Asia/Taipei",
    "iso:country":"TW",
    "name:und_x_variant":[
        "Jhouzihwei",
        "Chou-tzu-wei"
    ],
    "name:zho_x_preferred":[
        "\u6d32\u4ed4\u5c3e"
    ],
    "wof:name":"Zhouziwei",
    "wof:placetype":"locality"
},
  "geometry": {"coordinates":[121.78972,24.81028],"type":"Point"}
}