{
  "type": "Feature",
  "properties": {
    "gn:admin1_code":"4.0",
    "gn:admin2_code":"CYQ",
    "gn:admin3_code":"Q15",
    "gn:admin4_code":"10010140009.0",
    "gn:asciiname":"Shuijingtou",
    "gn:country_code":"TW",
    "gn:dem":100,
    "gn:feature_class":"P",
    "gn:feature_code":"PPL",
    "gn:name":"Shuijingtou",
    "gn:population":0,
    "gn:timezone":"Asia/Taipei",
    "iso:country":"TW",
    "name:und_x_variant":[
        "Shueijingtou",
        "Shuijingtou"
    ],
    "name:zho_x_preferred":[
        "\u6c34\u666f\u982d"
    ],
    "name:zho_x_variant":[
        "Shui-ching-t\u2019ou"
    ],
    "wof:name":"Shuijingtou",
    "wof:placetype":"locality"
},
  "geometry": {"coordinates":[120.54056,23.50278],"type":"Point"}
}