{
  "type": "Feature",
  "properties": {
    "gn:admin1_code":"04",
    "gn:admin2_code":"YUN",
    "gn:admin3_code":"P03",
    "gn:admin4_code":"10009030025.0",
    "gn:asciiname":"Shanwei",
    "gn:country_code":"TW",
    "gn:dem":31,
    "gn:feature_class":"P",
    "gn:feature_code":"PPL",
    "gn:name":"Shanwei",
    "gn:population":0,
    "gn:timezone":"Asia/Taipei",
    "iso:country":"TW",
    "name:und_x_variant":[
        "Shan-tzu-wei",
        "Shan-tzu",
        "Shanwei",
        "Shan-wei"
    ],
    "name:zho_x_preferred":[
        "\u6c55\u5c3e"
    ],
    "wof:name":"Shanwei",
    "wof:placetype":"locality"
},
  "geometry": {"coordinates":[120.45459,23.7266],"type":"Point"}
}