{
  "type": "Feature",
  "properties": {
    "gn:admin1_code":"4.0",
    "gn:admin2_code":"PIF",
    "gn:admin3_code":"T31",
    "gn:admin4_code":"10013310004.0",
    "gn:asciiname":"Jiuqijia",
    "gn:country_code":"TW",
    "gn:dem":608,
    "gn:feature_class":"P",
    "gn:feature_code":"PPL",
    "gn:name":"Jiuqijia",
    "gn:population":0,
    "gn:timezone":"Asia/Taipei",
    "iso:country":"TW",
    "name:und_x_variant":[
        "\u820a\u4e03\u4f73",
        "Jiuqijia",
        "Lao-ch\u2019i-chia",
        "Jioucijia"
    ],
    "name:zho_x_preferred":[
        "Chiu-ch\u2019i-chia"
    ],
    "wof:name":"Jiuqijia",
    "wof:placetype":"locality"
},
  "geometry": {"coordinates":[120.71250000000001,22.44778],"type":"Point"}
}