{
  "type": "Feature",
  "properties": {
    "gn:admin1_code":"04",
    "gn:admin2_code":"CYQ",
    "gn:admin3_code":"Q18",
    "gn:admin4_code":"10010170003.0",
    "gn:asciiname":"Buding",
    "gn:country_code":"TW",
    "gn:dem":247,
    "gn:feature_class":"P",
    "gn:feature_code":"PPL",
    "gn:name":"Buding",
    "gn:population":0,
    "gn:timezone":"Asia/Taipei",
    "iso:country":"TW",
    "name:und_x_variant":[
        "Niu-she-pu",
        "Niu-ku-pu",
        "Buding",
        "Pu-ting"
    ],
    "name:zho_x_preferred":[
        "\u57d4\u9802"
    ],
    "wof:name":"Buding",
    "wof:placetype":"locality"
},
  "geometry": {"coordinates":[120.58326,23.31553],"type":"Point"}
}