{
  "type": "Feature",
  "properties": {
    "gn:admin1_code":"04",
    "gn:admin2_code":"ILA",
    "gn:admin3_code":"G02",
    "gn:admin4_code":"10002040014.0",
    "gn:asciiname":"Damayan",
    "gn:country_code":"TW",
    "gn:dem":5,
    "gn:feature_class":"P",
    "gn:feature_code":"PPL",
    "gn:name":"Damayan",
    "gn:population":0,
    "gn:timezone":"Asia/Taipei",
    "iso:country":"TW",
    "name:und_x_variant":[
        "Ta-ma-yen"
    ],
    "name:zho_x_preferred":[
        "\u6253\u99ac\u7159"
    ],
    "wof:name":"Damayan",
    "wof:placetype":"locality"
},
  "geometry": {"coordinates":[121.82389000000001,24.83806],"type":"Point"}
}