{
  "type": "Feature",
  "properties": {
    "gn:admin1_code":"4.0",
    "gn:admin2_code":"ILA",
    "gn:admin3_code":"G05",
    "gn:admin4_code":"10002070016.0",
    "gn:asciiname":"Aijie",
    "gn:country_code":"TW",
    "gn:dem":34,
    "gn:feature_class":"P",
    "gn:feature_code":"PPL",
    "gn:name":"Aijie",
    "gn:population":0,
    "gn:timezone":"Asia/Taipei",
    "iso:country":"TW",
    "name:und_x_variant":[
        "Yai-chieh",
        "Yai-chien",
        "Aijie",
        "Ai-chieh"
    ],
    "name:zho_x_preferred":[
        "\u9698\u754c"
    ],
    "wof:name":"Aijie",
    "wof:placetype":"locality"
},
  "geometry": {"coordinates":[121.68600000000001,24.7496],"type":"Point"}
}