{
  "type": "Feature",
  "properties": {
    "gn:admin1_code":"2.0",
    "gn:admin2_code":"KHH",
    "gn:admin3_code":"E30",
    "gn:admin4_code":"64000300009.0",
    "gn:asciiname":"Fanzikeng",
    "gn:country_code":"TW",
    "gn:dem":129,
    "gn:feature_class":"P",
    "gn:feature_code":"PPL",
    "gn:name":"Fanzikeng",
    "gn:population":0,
    "gn:timezone":"Asia/Taipei",
    "iso:country":"TW",
    "name:und_x_variant":[
        "Fanzihkeng",
        "Fanzikeng"
    ],
    "name:zho_x_preferred":[
        "\u756a\u5b50\u5751"
    ],
    "name:zho_x_variant":[
        "Fan-tzu-k\u2019eng"
    ],
    "wof:name":"Fanzikeng",
    "wof:placetype":"locality"
},
  "geometry": {"coordinates":[120.435,22.80694],"type":"Point"}
}