{
  "type": "Feature",
  "properties": {
    "gn:admin1_code":"4.0",
    "gn:admin2_code":"PIF",
    "gn:admin3_code":"T14",
    "gn:admin4_code":"10013140009.0",
    "gn:asciiname":"Xishizhuang",
    "gn:country_code":"TW",
    "gn:dem":21,
    "gn:feature_class":"P",
    "gn:feature_code":"PPL",
    "gn:name":"Xishizhuang",
    "gn:population":0,
    "gn:timezone":"Asia/Taipei",
    "iso:country":"TW",
    "name:und_x_variant":[
        "Sishihjhuang",
        "Xishizhuang",
        "Hsi-shih-chuang"
    ],
    "name:zho_x_preferred":[
        "\u897f\u52e2\u838a"
    ],
    "wof:name":"Xishizhuang",
    "wof:placetype":"locality"
},
  "geometry": {"coordinates":[120.52484,22.62299],"type":"Point"}
}