{
  "type": "Feature",
  "properties": {
    "iso:country":"TW",
    "qs:name":"\u7063\u4e2d\u91cc",
    "qs:name_adm0":"\u81fa\u7063",
    "qs:name_adm1":"\u9ad8\u96c4\u5e02",
    "qs:photos":41,
    "qs:photos_1k":8,
    "qs:photos_9k":1,
    "qs:photos_9r":2,
    "qs:photos_all":41,
    "qs:photos_sr":2,
    "qs:placetype":"Suburb",
    "qs:pop_sr":"0",
    "wof:name":"\u7063\u4e2d\u91cc",
    "wof:placetype":"neighbourhood"
},
  "geometry": {"coordinates":[120.318583,22.648472],"type":"Point"}
}