{
  "type": "Feature",
  "properties": {
    "gn:admin1_code":"04",
    "gn:admin2_code":"ILA",
    "gn:admin3_code":"G08",
    "gn:admin4_code":"10002080011.0",
    "gn:asciiname":"Shisanfen",
    "gn:country_code":"TW",
    "gn:dem":18,
    "gn:feature_class":"P",
    "gn:feature_code":"PPL",
    "gn:name":"Shisanfen",
    "gn:population":0,
    "gn:timezone":"Asia/Taipei",
    "iso:country":"TW",
    "name:und_x_variant":[
        "Shihsanfen",
        "Shisanfen",
        "Shih-san-fen"
    ],
    "name:zho_x_preferred":[
        "An-p\u2019ing-ts\u2019un"
    ],
    "name:zho_x_variant":[
        "T\u2019ai-ho-ts\u2019un",
        "\u5341\u4e09\u5206"
    ],
    "wof:name":"Shisanfen",
    "wof:placetype":"locality"
},
  "geometry": {"coordinates":[121.76781,24.6264],"type":"Point"}
}