{
  "type": "Feature",
  "properties": {
    "gn:admin1_code":"4.0",
    "gn:admin2_code":"MIA",
    "gn:admin3_code":"K05",
    "gn:admin4_code":"10005100007.0",
    "gn:asciiname":"Qishifen",
    "gn:country_code":"TW",
    "gn:dem":116,
    "gn:feature_class":"P",
    "gn:feature_code":"PPL",
    "gn:name":"Qishifen",
    "gn:population":0,
    "gn:timezone":"Asia/Taipei",
    "iso:country":"TW",
    "name:und_x_variant":[
        "Cishihfen",
        "Qishifen"
    ],
    "name:zho_x_preferred":[
        "\u4e03\u5341\u5206"
    ],
    "name:zho_x_variant":[
        "Ch\u2019i-shih-fen"
    ],
    "wof:name":"Qishifen",
    "wof:placetype":"locality"
},
  "geometry": {"coordinates":[120.80865,24.48505],"type":"Point"}
}