{
  "type": "Feature",
  "properties": {
    "gn:admin1_code":"04",
    "gn:admin2_code":"NAN",
    "gn:admin3_code":"M01",
    "gn:admin4_code":"10008010023.0",
    "gn:asciiname":"Banshan",
    "gn:country_code":"TW",
    "gn:dem":96,
    "gn:feature_class":"P",
    "gn:feature_code":"PPL",
    "gn:name":"Banshan",
    "gn:population":0,
    "gn:timezone":"Asia/Taipei",
    "iso:country":"TW",
    "name:und_x_variant":[
        "Pan-shan"
    ],
    "name:zho_x_preferred":[
        "P\u2019ing-shan-li"
    ],
    "name:zho_x_variant":[
        "P\u2019ing-shan",
        "\u534a\u5c71"
    ],
    "wof:name":"Banshan",
    "wof:placetype":"locality"
},
  "geometry": {"coordinates":[120.6781,23.9222],"type":"Point"}
}