{
  "type": "Feature",
  "properties": {
    "gn:admin1_code":"4.0",
    "gn:admin2_code":"TXG",
    "gn:admin3_code":"B28",
    "gn:admin4_code":"66000280015.0",
    "gn:asciiname":"Zhuzikeng",
    "gn:country_code":"TW",
    "gn:dem":101,
    "gn:feature_class":"P",
    "gn:feature_code":"PPL",
    "gn:name":"Zhuzikeng",
    "gn:population":0,
    "gn:timezone":"Asia/Taipei",
    "iso:country":"TW",
    "name:und_x_variant":[
        "Chien-min-ts\u2019un",
        "Chien-min",
        "\u7af9\u4ed4\u5751",
        "Zhuzikeng",
        "Jhuzihkeng"
    ],
    "name:zho_x_preferred":[
        "Chu-tzu-k\u2019eng"
    ],
    "wof:name":"Zhuzikeng",
    "wof:placetype":"locality"
},
  "geometry": {"coordinates":[120.73108999999999,24.0899],"type":"Point"}
}