{
  "type": "Feature",
  "properties": {
    "gn:admin1_code":"02",
    "gn:admin2_code":"KHH",
    "gn:admin3_code":"E31",
    "gn:admin4_code":"64000310008.0",
    "gn:asciiname":"Dakengli",
    "gn:country_code":"TW",
    "gn:dem":72,
    "gn:feature_class":"P",
    "gn:feature_code":"PPL",
    "gn:name":"Dakengli",
    "gn:population":0,
    "gn:timezone":"Asia/Taipei",
    "iso:country":"TW",
    "name:zho_x_preferred":[
        "\u5927\u5751\u91cc"
    ],
    "name:zho_x_variant":[
        "Ta-k\u2019eng-li"
    ],
    "wof:name":"Dakengli",
    "wof:placetype":"locality"
},
  "geometry": {"coordinates":[120.5801,22.89621],"type":"Point"}
}