{
  "type": "Feature",
  "properties": {
    "gn:admin1_code":"4.0",
    "gn:admin2_code":"HSZ",
    "gn:admin3_code":"J08",
    "gn:admin4_code":"10004080001.0",
    "gn:asciiname":"Zhong'ai",
    "gn:country_code":"TW",
    "gn:dem":268,
    "gn:feature_class":"P",
    "gn:feature_code":"PPL",
    "gn:name":"Zhong\u2019ai",
    "gn:population":0,
    "gn:timezone":"Asia/Taipei",
    "iso:country":"TW",
    "name:und_x_variant":[
        "Chung-ai"
    ],
    "name:zho_x_preferred":[
        "\u4e2d\u9698"
    ],
    "name:zho_x_variant":[
        "Jhong\u2019ai",
        "Zhong\u2019ai"
    ],
    "wof:name":"Zhong'ai",
    "wof:placetype":"locality"
},
  "geometry": {"coordinates":[121.12778,24.70667000000001],"type":"Point"}
}