{
  "type": "Feature",
  "properties": {
    "gn:admin1_code":"4.0",
    "gn:admin2_code":"YUN",
    "gn:admin3_code":"P11",
    "gn:admin4_code":"10009110003.0",
    "gn:asciiname":"Xindian",
    "gn:country_code":"TW",
    "gn:dem":22,
    "gn:feature_class":"P",
    "gn:feature_code":"PPL",
    "gn:name":"Xindian",
    "gn:population":0,
    "gn:timezone":"Asia/Taipei",
    "iso:country":"TW",
    "name:ceb_x_preferred":[
        "Xindian"
    ],
    "name:deu_x_preferred":[
        "Xindian"
    ],
    "name:swe_x_preferred":[
        "Xindian"
    ],
    "name:und_x_variant":[
        "Sindian",
        "Xindian",
        "Hsin-tien"
    ],
    "name:zho_x_preferred":[
        "\u65b0\u5e97"
    ],
    "wof:name":"Xindian",
    "wof:placetype":"locality"
},
  "geometry": {"coordinates":[120.38523000000001,23.76504],"type":"Point"}
}