{
  "type": "Feature",
  "properties": {
    "gn:admin1_code":"04",
    "gn:admin2_code":"HUA",
    "gn:admin3_code":"U04",
    "gn:admin4_code":"10015040003.0",
    "gn:asciiname":"Nansanzhan",
    "gn:country_code":"TW",
    "gn:dem":22,
    "gn:feature_class":"P",
    "gn:feature_code":"PPL",
    "gn:name":"Nansanzhan",
    "gn:population":0,
    "gn:timezone":"Asia/Taipei",
    "iso:country":"TW",
    "name:und_x_variant":[
        "Nansanjhan",
        "Nan-san-chan"
    ],
    "name:zho_x_preferred":[
        "\u5357\u4e09\u68e7"
    ],
    "wof:name":"Nansanzhan",
    "wof:placetype":"locality"
},
  "geometry": {"coordinates":[121.61404,24.09682],"type":"Point"}
}