{
  "type": "Feature",
  "properties": {
    "iso:country":"TW",
    "qs:name":"\u57ce\u5317\u6751",
    "qs:name_adm0":"\u81fa\u7063",
    "qs:name_adm1":"\u6f8e\u6e56\u7e23",
    "qs:photos":170,
    "qs:photos_1k":34,
    "qs:photos_9k":1,
    "qs:photos_9r":4,
    "qs:photos_all":170,
    "qs:photos_sr":4,
    "qs:placetype":"Town",
    "qs:pop_sr":"0",
    "wof:name":"\u57ce\u5317\u6751",
    "wof:placetype":"locality"
},
  "geometry": {"coordinates":[119.61381900000001,23.565403],"type":"Point"}
}