{
  "type": "Feature",
  "properties": {
    "gn:admin1_code":"3.0",
    "gn:admin2_code":"TPQ",
    "gn:admin3_code":"F15",
    "gn:admin4_code":"65000090021.0",
    "gn:asciiname":"Ganzijiao",
    "gn:country_code":"TW",
    "gn:dem":200,
    "gn:feature_class":"P",
    "gn:feature_code":"PPL",
    "gn:name":"Ganzijiao",
    "gn:population":0,
    "gn:timezone":"Asia/Taipei",
    "iso:country":"TW",
    "name:und_x_variant":[
        "Ganzihjiao",
        "Kan-tzu-chiao"
    ],
    "name:zho_x_preferred":[
        "\u67d1\u4ed4\u811a"
    ],
    "wof:name":"Ganzijiao",
    "wof:placetype":"locality"
},
  "geometry": {"coordinates":[121.47280000000001,24.92719],"type":"Point"}
}