{
  "type": "Feature",
  "properties": {
    "gn:admin1_code":"04",
    "gn:admin2_code":"TTT",
    "gn:admin3_code":"V12",
    "gn:admin4_code":"10014130003.0",
    "gn:asciiname":"Taolin",
    "gn:country_code":"TW",
    "gn:dem":882,
    "gn:feature_class":"P",
    "gn:feature_code":"PPL",
    "gn:name":"Taolin",
    "gn:population":0,
    "gn:timezone":"Asia/Taipei",
    "iso:country":"TW",
    "name:zho_x_preferred":[
        "\u6843\u6797"
    ],
    "name:zho_x_variant":[
        "T\u2019ao-lin"
    ],
    "wof:name":"Taolin",
    "wof:placetype":"locality"
},
  "geometry": {"coordinates":[120.93861,22.88611],"type":"Point"}
}