{
  "type": "Feature",
  "properties": {
    "gn:admin1_code":"4.0",
    "gn:admin2_code":"NAN",
    "gn:admin3_code":"M10",
    "gn:admin4_code":"10008100004.0",
    "gn:asciiname":"Wupengkeng",
    "gn:country_code":"TW",
    "gn:dem":490,
    "gn:feature_class":"P",
    "gn:feature_code":"PPL",
    "gn:name":"Wupengkeng",
    "gn:population":0,
    "gn:timezone":"Asia/Taipei",
    "iso:country":"TW",
    "name:zho_x_preferred":[
        "\u4e94\u68da\u5751"
    ],
    "name:zho_x_variant":[
        "Wu-p\u2019eng-k\u2019eng"
    ],
    "wof:name":"Wupengkeng",
    "wof:placetype":"locality"
},
  "geometry": {"coordinates":[120.92053,24.08002],"type":"Point"}
}