{
  "type": "Feature",
  "properties": {
    "iso:country":"TW",
    "qs:name":"\u4ec1\u7fa9\u91cc",
    "qs:name_adm0":"\u81fa\u7063",
    "qs:name_adm1":"\u57fa\u9686\u5e02",
    "qs:photos":169,
    "qs:photos_1k":34,
    "qs:photos_9k":1,
    "qs:photos_9r":4,
    "qs:photos_all":169,
    "qs:photos_sr":4,
    "qs:placetype":"Suburb",
    "qs:pop_sr":"0",
    "wof:name":"\u4ec1\u7fa9\u91cc",
    "wof:placetype":"neighbourhood"
},
  "geometry": {"coordinates":[121.750677,25.133427],"type":"Point"}
}