{
  "type": "Feature",
  "properties": {
    "iso:country":"TW",
    "qs:name":"\u71d5\u5de2\u9109",
    "qs:name_adm0":"\u81fa\u7063",
    "qs:name_adm1":"\u9ad8\u96c4\u5e02",
    "qs:photos":929,
    "qs:photos_1k":188,
    "qs:photos_9k":5,
    "qs:photos_9r":7,
    "qs:photos_all":1034,
    "qs:photos_sr":10,
    "qs:placetype":"County",
    "qs:pop_sr":"0",
    "wd:wordcount":114,
    "wof:name":"\u71d5\u5de2\u9109",
    "wof:placetype":"county"
},
  "geometry": {"coordinates":[120.38887,22.826546],"type":"Point"}
}