{
  "type": "Feature",
  "properties": {
    "iso:country":"TW",
    "name:ces_x_preferred":[
        "Okres Kao-siung"
    ],
    "name:cym_x_preferred":[
        "Sir Kaohsiung"
    ],
    "name:deu_x_preferred":[
        "Landkreis Kaohsiung"
    ],
    "name:eng_x_preferred":[
        "Kaohsiung County"
    ],
    "name:eus_x_preferred":[
        "Kaohsiung konderria"
    ],
    "name:fas_x_preferred":[
        "\u06a9\u0627\u0648\u0633\u06cc\u0627\u0646\u06af"
    ],
    "name:hak_x_preferred":[
        "K\u00f4-hi\u00f9ng-yen"
    ],
    "name:ind_x_preferred":[
        "Kabupaten Kaohsiung"
    ],
    "name:jpn_x_preferred":[
        "\u9ad8\u96c4\u770c"
    ],
    "name:kor_x_preferred":[
        "\uac00\uc624\uc29d\ud604"
    ],
    "name:nan_x_preferred":[
        "Ko-hi\u00f4ng-ko\u0101n"
    ],
    "name:nld_x_preferred":[
        "Kaohsiung"
    ],
    "name:rus_x_preferred":[
        "\u0413\u0430\u043e\u0441\u044e\u043d"
    ],
    "name:vie_x_preferred":[
        "Cao H\u00f9ng"
    ],
    "name:yue_x_preferred":[
        "\u9ad8\u96c4\u7e23"
    ],
    "name:zho_x_preferred":[
        "\u9ad8\u96c4\u7e23"
    ],
    "qs:name":"\u71d5\u5de2\u9109",
    "qs:name_adm0":"\u81fa\u7063",
    "qs:name_adm1":"\u9ad8\u96c4\u5e02",
    "qs:photos":929,
    "qs:photos_1k":188,
    "qs:photos_9k":5,
    "qs:photos_9r":7,
    "qs:photos_all":1034,
    "qs:photos_sr":10,
    "qs:placetype":"County",
    "qs:pop_sr":"0",
    "wd:wordcount":114,
    "wof:name":"\u71d5\u5de2\u9109",
    "wof:placetype":"county"
},
  "geometry": {"coordinates":[120.38887,22.826546],"type":"Point"}
}