{
  "type": "Feature",
  "properties": {
    "iso:country":"TW",
    "qs:name":"\u846b\u6771\u91cc",
    "qs:name_adm0":"\u81fa\u7063",
    "qs:name_adm1":"\u53f0\u5317\u5e02",
    "qs:photos":105,
    "qs:photos_1k":21,
    "qs:photos_9k":1,
    "qs:photos_9r":3,
    "qs:photos_all":105,
    "qs:photos_sr":3,
    "qs:placetype":"Suburb",
    "qs:pop_sr":"0",
    "wof:name":"\u846b\u6771\u91cc",
    "wof:placetype":"neighbourhood"
},
  "geometry": {"coordinates":[121.51007,25.085674],"type":"Point"}
}