{
  "type": "Feature",
  "properties": {
    "gn:admin1_code":"4.0",
    "gn:admin2_code":"NAN",
    "gn:admin3_code":"M01",
    "gn:admin4_code":"10008010020.0",
    "gn:asciiname":"Dingbanling",
    "gn:country_code":"TW",
    "gn:dem":315,
    "gn:feature_class":"P",
    "gn:feature_code":"PPL",
    "gn:name":"Dingbanling",
    "gn:population":0,
    "gn:timezone":"Asia/Taipei",
    "iso:country":"TW",
    "name:und_x_variant":[
        "Ting-pan-ling"
    ],
    "name:zho_x_preferred":[
        "\u9802\u534a\u5dba"
    ],
    "wof:name":"Dingbanling",
    "wof:placetype":"locality"
},
  "geometry": {"coordinates":[120.6533,23.8976],"type":"Point"}
}