{
  "type": "Feature",
  "properties": {
    "gn:admin1_code":"04",
    "gn:admin2_code":"ILA",
    "gn:admin3_code":"G12",
    "gn:admin4_code":"10002120006.0",
    "gn:asciiname":"Biyahaoshe",
    "gn:country_code":"TW",
    "gn:dem":984,
    "gn:feature_class":"P",
    "gn:feature_code":"PPL",
    "gn:name":"Biyahaoshe",
    "gn:population":0,
    "gn:timezone":"Asia/Taipei",
    "iso:country":"TW",
    "name:und_x_variant":[
        "Pi-ya-hao",
        "Pi-ya-hao-she",
        "Biyahaoshe"
    ],
    "wof:name":"Biyahaoshe",
    "wof:placetype":"locality"
},
  "geometry": {"coordinates":[121.53333000000001,24.41667],"type":"Point"}
}