{
  "type": "Feature",
  "properties": {
    "gn:admin1_code":"04",
    "gn:admin2_code":"TAO",
    "gn:admin3_code":"H10",
    "gn:admin4_code":"68000100038.0",
    "gn:asciiname":"Dongshe",
    "gn:country_code":"TW",
    "gn:dem":178,
    "gn:feature_class":"P",
    "gn:feature_code":"PPL",
    "gn:name":"Dongshe",
    "gn:population":0,
    "gn:timezone":"Asia/Taipei",
    "iso:country":"TW",
    "name:und_x_variant":[
        "Tung-she"
    ],
    "name:zho_x_preferred":[
        "Tung-she-ts\u2019un"
    ],
    "name:zho_x_variant":[
        "\u6771\u793e"
    ],
    "wof:name":"Dongshe",
    "wof:placetype":"locality"
},
  "geometry": {"coordinates":[121.24833,24.91583],"type":"Point"}
}