{
  "type": "Feature",
  "properties": {
    "gn:admin1_code":"04",
    "gn:admin2_code":"CHA",
    "gn:admin3_code":"N02",
    "gn:admin4_code":"10007020006.0",
    "gn:asciiname":"Wenshaoliao",
    "gn:country_code":"TW",
    "gn:dem":10,
    "gn:feature_class":"P",
    "gn:feature_code":"PPL",
    "gn:name":"Wenshaoliao",
    "gn:population":0,
    "gn:timezone":"Asia/Taipei",
    "iso:country":"TW",
    "name:und_x_variant":[
        "Wunshaoliao",
        "Wen-shao-liao"
    ],
    "name:zho_x_preferred":[
        "Wen-shao-ts\u2019o"
    ],
    "name:zho_x_variant":[
        "\u6eab\u71d2\u5bee"
    ],
    "wof:name":"Wenshaoliao",
    "wof:placetype":"locality"
},
  "geometry": {"coordinates":[120.45611,24.06306],"type":"Point"}
}