{
  "type": "Feature",
  "properties": {
    "gn:admin1_code":"04",
    "gn:admin2_code":"HSZ",
    "gn:admin3_code":"J08",
    "gn:admin4_code":"10004080002.0",
    "gn:asciiname":"Tianliaokeng",
    "gn:country_code":"TW",
    "gn:dem":167,
    "gn:feature_class":"P",
    "gn:feature_code":"PPL",
    "gn:name":"Tianliaokeng",
    "gn:population":0,
    "gn:timezone":"Asia/Taipei",
    "iso:country":"TW",
    "name:zho_x_preferred":[
        "T\u2019o-tzu"
    ],
    "name:zho_x_variant":[
        "\u7530\u5bee\u5751",
        "T\u2019ien-liao",
        "T\u2019ien-liao-k\u2019eng"
    ],
    "wof:name":"Tianliaokeng",
    "wof:placetype":"locality"
},
  "geometry": {"coordinates":[121.10611000000002,24.705],"type":"Point"}
}