{
  "type": "Feature",
  "properties": {
    "gn:admin1_code":"04",
    "gn:admin2_code":"TPE",
    "gn:admin3_code":"A16",
    "gn:admin4_code":"63000120042.0",
    "gn:asciiname":"Dazhuang",
    "gn:country_code":"TW",
    "gn:dem":570,
    "gn:feature_class":"P",
    "gn:feature_code":"PPL",
    "gn:name":"Dazhuang",
    "gn:population":0,
    "gn:timezone":"Asia/Taipei",
    "iso:country":"TW",
    "name:ceb_x_preferred":[
        "Dazhuang"
    ],
    "name:deu_x_preferred":[
        "Dazhuang"
    ],
    "name:swe_x_preferred":[
        "Dazhuang"
    ],
    "name:und_x_variant":[
        "Dajhuang",
        "Ta-chuang"
    ],
    "name:zho_x_preferred":[
        "\u5927\u5e84"
    ],
    "wof:name":"Dazhuang",
    "wof:placetype":"locality"
},
  "geometry": {"coordinates":[121.5335,25.1659],"type":"Point"}
}