{
  "type": "Feature",
  "properties": {
    "gn:admin1_code":"4.0",
    "gn:admin2_code":"HSZ",
    "gn:admin3_code":"J09",
    "gn:admin4_code":"10004060005.0",
    "gn:asciiname":"Zhonglun",
    "gn:country_code":"TW",
    "gn:dem":27,
    "gn:feature_class":"P",
    "gn:feature_code":"PPL",
    "gn:name":"Zhonglun",
    "gn:population":0,
    "gn:timezone":"Asia/Taipei",
    "iso:country":"TW",
    "name:und_x_variant":[
        "Jhonglun",
        "Chung-lun"
    ],
    "name:zho_x_preferred":[
        "Chung-lun-ts\u2019un"
    ],
    "name:zho_x_variant":[
        "\u4e2d\u5d19"
    ],
    "wof:name":"Zhonglun",
    "wof:placetype":"locality"
},
  "geometry": {"coordinates":[121.00388999999998,24.90361],"type":"Point"}
}