{
  "type": "Feature",
  "properties": {
    "gn:admin1_code":"04",
    "gn:admin2_code":"CYQ",
    "gn:admin3_code":"Q20",
    "gn:admin4_code":"10010180010.0",
    "gn:asciiname":"Shanmei",
    "gn:country_code":"TW",
    "gn:dem":503,
    "gn:feature_class":"P",
    "gn:feature_code":"PPL",
    "gn:name":"Shanmei",
    "gn:population":0,
    "gn:timezone":"Asia/Taipei",
    "iso:country":"TW",
    "name:und_x_variant":[
        "Shan-mei-she",
        "Shanmei",
        "Sha-mei-chi",
        "Shan-mei"
    ],
    "name:zho_x_preferred":[
        "Sa-p\u2019i-chi"
    ],
    "name:zho_x_variant":[
        "Sha-p\u2019i-chi",
        "Shan-mei-ts\u2019un",
        "\u5c71\u7f8e"
    ],
    "wof:name":"Shanmei",
    "wof:placetype":"locality"
},
  "geometry": {"coordinates":[120.66842,23.38257],"type":"Point"}
}