{
  "type": "Feature",
  "properties": {
    "gn:admin1_code":"04",
    "gn:admin2_code":"YUN",
    "gn:admin3_code":"P09",
    "gn:admin4_code":"10009090008.0",
    "gn:asciiname":"Youchezi",
    "gn:country_code":"TW",
    "gn:dem":44,
    "gn:feature_class":"P",
    "gn:feature_code":"PPL",
    "gn:name":"Youchezi",
    "gn:population":0,
    "gn:timezone":"Asia/Taipei",
    "iso:country":"TW",
    "name:und_x_variant":[
        "Youchezih",
        "Youchezi"
    ],
    "name:zho_x_preferred":[
        "\u6cb9\u8eca\u5b50"
    ],
    "name:zho_x_variant":[
        "Yu-ch\u2019e-tzu"
    ],
    "wof:name":"Youchezi",
    "wof:placetype":"locality"
},
  "geometry": {"coordinates":[120.52397000000001,23.74447],"type":"Point"}
}