{
  "type": "Feature",
  "properties": {
    "gn:admin1_code":"4.0",
    "gn:admin2_code":"PIF",
    "gn:admin3_code":"T09",
    "gn:admin4_code":"10013090004.0",
    "gn:asciiname":"Linzi",
    "gn:country_code":"TW",
    "gn:dem":37,
    "gn:feature_class":"P",
    "gn:feature_code":"PPL",
    "gn:name":"Linzi",
    "gn:population":0,
    "gn:timezone":"Asia/Taipei",
    "iso:country":"TW",
    "name:ceb_x_preferred":[
        "Linzi"
    ],
    "name:swe_x_preferred":[
        "Linzi"
    ],
    "name:und_x_variant":[
        "Linzih",
        "Lin-tzu"
    ],
    "name:zho_x_preferred":[
        "\u6797\u5b50"
    ],
    "wof:name":"Linzi",
    "wof:placetype":"locality"
},
  "geometry": {"coordinates":[120.50111,22.76722],"type":"Point"}
}