{
  "type": "Feature",
  "properties": {
    "gn:admin1_code":"04",
    "gn:admin2_code":"PIF",
    "gn:admin3_code":"T33",
    "gn:admin4_code":"10013330001.0",
    "gn:asciiname":"Dingqie",
    "gn:country_code":"TW",
    "gn:dem":264,
    "gn:feature_class":"P",
    "gn:feature_code":"PPL",
    "gn:name":"Dingqie",
    "gn:population":0,
    "gn:timezone":"Asia/Taipei",
    "iso:country":"TW",
    "name:und_x_variant":[
        "Shih-men-ts\u2019un",
        "Ting-chia-chih-lai",
        "Ting-ch\u2019ieh-chih-lai-she",
        "Ting-chia-chih-lai-she",
        "Ting-ch\u2019ieh",
        "Dingqie"
    ],
    "wof:name":"Dingqie",
    "wof:placetype":"locality"
},
  "geometry": {"coordinates":[120.75,22.13333],"type":"Point"}
}