{
  "type": "Feature",
  "properties": {
    "gn:admin1_code":"4.0",
    "gn:admin2_code":"YUN",
    "gn:admin3_code":"P07",
    "gn:admin4_code":"10009070011.0",
    "gn:asciiname":"Zhatian",
    "gn:country_code":"TW",
    "gn:dem":342,
    "gn:feature_class":"P",
    "gn:feature_code":"PPL",
    "gn:name":"Zhatian",
    "gn:population":0,
    "gn:timezone":"Asia/Taipei",
    "iso:country":"TW",
    "name:und_x_variant":[
        "Jhatian",
        "Zhatian"
    ],
    "name:zho_x_preferred":[
        "\u7553\u7530"
    ],
    "name:zho_x_variant":[
        "Cha-t\u2019ien"
    ],
    "wof:name":"Zhatian",
    "wof:placetype":"locality"
},
  "geometry": {"coordinates":[120.59833,23.60806],"type":"Point"}
}