{
  "type": "Feature",
  "properties": {
    "gn:admin1_code":"04",
    "gn:admin2_code":"HUA",
    "gn:admin3_code":"U05",
    "gn:admin4_code":"10015050008.0",
    "gn:asciiname":"Nanhua",
    "gn:country_code":"TW",
    "gn:dem":70,
    "gn:feature_class":"P",
    "gn:feature_code":"PPL",
    "gn:name":"Nanhua",
    "gn:population":0,
    "gn:timezone":"Asia/Taipei",
    "iso:country":"TW",
    "name:deu_x_preferred":[
        "Nanhua"
    ],
    "name:und_x_variant":[
        "Nan-hua"
    ],
    "name:zho_x_preferred":[
        "\u5357\u83ef"
    ],
    "name:zho_x_variant":[
        "Nan-hua-ts\u2019un",
        "Nan-y\u00fcan"
    ],
    "wof:name":"Nanhua",
    "wof:placetype":"locality"
},
  "geometry": {"coordinates":[121.54917,23.95333],"type":"Point"}
}