{
  "type": "Feature",
  "properties": {
    "gn:admin1_code":"4.0",
    "gn:admin2_code":"PIF",
    "gn:admin3_code":"T10",
    "gn:admin4_code":"10013100009.0",
    "gn:asciiname":"Jinlong",
    "gn:country_code":"TW",
    "gn:dem":78,
    "gn:feature_class":"P",
    "gn:feature_code":"PPL",
    "gn:name":"Jinlong",
    "gn:population":0,
    "gn:timezone":"Asia/Taipei",
    "iso:country":"TW",
    "name:und_x_variant":[
        "Chin-lung"
    ],
    "name:zho_x_preferred":[
        "\u9326\u9686"
    ],
    "name:zho_x_variant":[
        "Chin-lung-ts\u2019un"
    ],
    "wof:name":"Jinlong",
    "wof:placetype":"locality"
},
  "geometry": {"coordinates":[120.60061,22.71779],"type":"Point"}
}