{
  "type": "Feature",
  "properties": {
    "gn:country":"TW",
    "gn:fcode":"ADMD",
    "gn:population":0,
    "iso:country":"TW",
    "name:ara_x_preferred":[
        "\u0645\u0642\u0627\u0637\u0639\u0629 \u0634\u064a\u0644\u064a\u0646"
    ],
    "name:deu_x_preferred":[
        "Shilin"
    ],
    "name:eng_x_preferred":[
        "Shilin District"
    ],
    "name:hak_x_preferred":[
        "S\u1e73-l\u00ecm-kh\u00ee"
    ],
    "name:heb_x_preferred":[
        "\u05e9\u05d9\u05dc\u05d9\u05df"
    ],
    "name:hye_x_preferred":[
        "\u0547\u056b\u056c\u056b\u0576"
    ],
    "name:ind_x_preferred":[
        "Distrik Shilin"
    ],
    "name:jpn_x_preferred":[
        "\u58eb\u6797\u533a"
    ],
    "name:kaz_x_preferred":[
        "\u0428\u0438\u043b\u0438\u043d\u044c"
    ],
    "name:kor_x_preferred":[
        "\uc2a4\ub9b0\uad6c"
    ],
    "name:lit_x_preferred":[
        "\u0160ilinas"
    ],
    "name:nan_x_preferred":[
        "S\u016b-l\u00eem-khu"
    ],
    "name:nld_x_preferred":[
        "Shilin District"
    ],
    "name:pol_x_preferred":[
        "Shilin"
    ],
    "name:rus_x_preferred":[
        "\u0428\u0438\u043b\u0438\u043d\u044c"
    ],
    "name:sco_x_preferred":[
        "Shilin Destrict"
    ],
    "name:ukr_x_preferred":[
        "\u0428\u0456\u043b\u0456\u043d\u044c"
    ],
    "name:vie_x_preferred":[
        "S\u1ef9 L\u00e2m"
    ],
    "name:yue_x_preferred":[
        "\u58eb\u6797\u5340"
    ],
    "name:zho_x_preferred":[
        "Shih-lin Ch\u2019\u00fc"
    ],
    "name:zho_x_variant":[
        "\u58eb\u6797\u5340"
    ],
    "qs:name":"Shilin Qu",
    "qs:photos_9r":0,
    "qs:photos_sr":0,
    "qs:pop_sr":"0",
    "wd:wordcount":669,
    "wof:name":"Shilin Qu",
    "wof:placetype":"localadmin",
    "wof:population":0
},
  "geometry": {"coordinates":[121.55,25.13333],"type":"Point"}
}