{
  "type": "Feature",
  "properties": {
    "gn:country":"TW",
    "gn:fcode":"ADMD",
    "gn:pop":0,
    "iso:country":"TW",
    "name:unk_x_variant":[
        "\u58eb\u6797\u5340"
    ],
    "name:zho_x_preferred":[
        "Shih-lin Ch\u2019\u00fc"
    ],
    "name:zho_x_variant":[
        "\u58eb\u6797\u5340"
    ],
    "qs:name":"Shilin Qu",
    "qs:photos_9r":0,
    "qs:photos_sr":0,
    "qs:pop_sr":"0",
    "wd:wordcount":669,
    "wof:name":"Shilin Qu",
    "wof:placetype":"localadmin",
    "wof:population":0
},
  "geometry": {"coordinates":[121.55,25.13333],"type":"Point"}
}