{
  "type": "Feature",
  "properties": {
    "gn:admin1_code":"4.0",
    "gn:admin2_code":"NAN",
    "gn:admin3_code":"M06",
    "gn:admin4_code":"10008060010.0",
    "gn:asciiname":"Tianzidakeng",
    "gn:country_code":"TW",
    "gn:dem":231,
    "gn:feature_class":"P",
    "gn:feature_code":"PPL",
    "gn:name":"Tianzidakeng",
    "gn:population":0,
    "gn:timezone":"Asia/Taipei",
    "iso:country":"TW",
    "name:und_x_variant":[
        "Tianzihdakeng",
        "Tianzidakeng"
    ],
    "name:zho_x_preferred":[
        "\u7530\u4ed4\u5927\u5751"
    ],
    "name:zho_x_variant":[
        "T\u2019ien-tzu-ta-k\u2019eng"
    ],
    "wof:name":"Tianzidakeng",
    "wof:placetype":"locality"
},
  "geometry": {"coordinates":[120.6602,23.8621],"type":"Point"}
}