{
  "type": "Feature",
  "properties": {
    "gn:admin1_code":"04",
    "gn:admin2_code":"CYQ",
    "gn:admin3_code":"Q03",
    "gn:admin4_code":"10010030014.0",
    "gn:asciiname":"Daliao",
    "gn:country_code":"TW",
    "gn:dem":6,
    "gn:feature_class":"P",
    "gn:feature_code":"PPL",
    "gn:name":"Daliao",
    "gn:population":0,
    "gn:timezone":"Asia/Taipei",
    "iso:country":"TW",
    "name:und_x_variant":[
        "Ta-liao"
    ],
    "name:zho_x_preferred":[
        "\u5927\u5bee"
    ],
    "name:zho_x_variant":[
        "Pu-tzu-ts\u2019o"
    ],
    "wof:name":"Daliao",
    "wof:placetype":"locality"
},
  "geometry": {"coordinates":[120.18631999999999,23.37375],"type":"Point"}
}