{
  "type": "Feature",
  "properties": {
    "gn:country":"TW",
    "gn:fcode":"ADMD",
    "gn:pop":0,
    "iso:country":"TW",
    "name:unk_x_variant":[
        "Hsin-kang Hsiang"
    ],
    "name:zho_x_preferred":[
        "\u65b0\u6e2f\u9109"
    ],
    "qs:name":"Xingang Xiang",
    "qs:photos_9r":0,
    "qs:photos_sr":0,
    "qs:pop_sr":"0",
    "wd:wordcount":162,
    "wof:name":"Xingang Xiang",
    "wof:placetype":"localadmin",
    "wof:population":0
},
  "geometry": {"coordinates":[120.34999999999999,23.55],"type":"Point"}
}