{
  "type": "Feature",
  "properties": {
    "gn:country":"TW",
    "gn:fcode":"ADMD",
    "gn:population":0,
    "iso:country":"TW",
    "name:ceb_x_preferred":[
        "Xingang"
    ],
    "name:eng_x_preferred":[
        "Xingang"
    ],
    "name:hak_x_preferred":[
        "S\u00een-k\u00f3ng-hi\u00f4ng"
    ],
    "name:jpn_x_preferred":[
        "\u65b0\u6e2f\u90f7"
    ],
    "name:kor_x_preferred":[
        "\uc2e0\uac15\ud5a5"
    ],
    "name:nan_x_preferred":[
        "Sin-k\u00e1ng-hiong"
    ],
    "name:pol_x_preferred":[
        "Xingang"
    ],
    "name:rus_x_preferred":[
        "\u0421\u0438\u043d\u044c\u0433\u0430\u043d"
    ],
    "name:swe_x_preferred":[
        "Xingang"
    ],
    "name:und_x_variant":[
        "Hsin-kang Hsiang"
    ],
    "name:vie_x_preferred":[
        "T\u00e2n C\u1ea3ng"
    ],
    "name:zho_x_preferred":[
        "\u65b0\u6e2f\u9109"
    ],
    "qs:name":"Xingang Xiang",
    "qs:photos_9r":0,
    "qs:photos_sr":0,
    "qs:pop_sr":"0",
    "wd:wordcount":162,
    "wof:name":"Xingang Xiang",
    "wof:placetype":"localadmin",
    "wof:population":0
},
  "geometry": {"coordinates":[120.34999999999999,23.55],"type":"Point"}
}