{
  "type": "Feature",
  "properties": {
    "gn:admin1_code":"04",
    "gn:admin2_code":"TXG",
    "gn:admin3_code":"B29",
    "gn:admin4_code":"66000290007.0",
    "gn:asciiname":"Pingyanshan",
    "gn:country_code":"TW",
    "gn:dem":2175,
    "gn:feature_class":"P",
    "gn:feature_code":"PPL",
    "gn:name":"Pingyanshan",
    "gn:population":0,
    "gn:timezone":"Asia/Taipei",
    "iso:country":"TW",
    "name:und_x_variant":[
        "P\u2019ing-yen-shan-she",
        "P\u2019ing-yen-shan",
        "Pingyanshan"
    ],
    "wof:name":"Pingyanshan",
    "wof:placetype":"locality"
},
  "geometry": {"coordinates":[121.25,24.25],"type":"Point"}
}