{
  "type": "Feature",
  "properties": {
    "gn:admin1_code":"4.0",
    "gn:admin2_code":"CYQ",
    "gn:admin3_code":"Q07",
    "gn:admin4_code":"10010070023.0",
    "gn:asciiname":"Linzicuo",
    "gn:country_code":"TW",
    "gn:dem":9,
    "gn:feature_class":"P",
    "gn:feature_code":"PPL",
    "gn:name":"Linzicuo",
    "gn:population":0,
    "gn:timezone":"Asia/Taipei",
    "iso:country":"TW",
    "name:und_x_variant":[
        "Linzihcuo",
        "Linzicuo"
    ],
    "name:zho_x_preferred":[
        "\u6797\u5b50\u539d"
    ],
    "name:zho_x_variant":[
        "Lin-tzu-ts\u2019o"
    ],
    "wof:name":"Linzicuo",
    "wof:placetype":"locality"
},
  "geometry": {"coordinates":[120.3237,23.55219],"type":"Point"}
}