{
  "type": "Feature",
  "properties": {
    "gn:admin1_code":"2.0",
    "gn:admin2_code":"KHH",
    "gn:admin3_code":"E21",
    "gn:admin4_code":"64000210006.0",
    "gn:asciiname":"Qianqiuliao",
    "gn:country_code":"TW",
    "gn:dem":153,
    "gn:feature_class":"P",
    "gn:feature_code":"PPL",
    "gn:name":"Qianqiuliao",
    "gn:population":0,
    "gn:timezone":"Asia/Taipei",
    "iso:country":"TW",
    "name:und_x_variant":[
        "Cianciouliao",
        "Qianqiuliao"
    ],
    "name:zho_x_preferred":[
        "\u5343\u79cb\u5bee"
    ],
    "name:zho_x_variant":[
        "P\u2019i-tzu-ti",
        "Ch\u2019ien-ch\u2019iu-liao"
    ],
    "wof:name":"Qianqiuliao",
    "wof:placetype":"locality"
},
  "geometry": {"coordinates":[120.41028,22.80944],"type":"Point"}
}