{
  "type": "Feature",
  "properties": {
    "gn:admin1_code":"4.0",
    "gn:admin2_code":"MIA",
    "gn:admin3_code":"K03",
    "gn:admin4_code":"10005030007.0",
    "gn:asciiname":"Xiaolilin",
    "gn:country_code":"TW",
    "gn:dem":95,
    "gn:feature_class":"P",
    "gn:feature_code":"PPL",
    "gn:name":"Xiaolilin",
    "gn:population":0,
    "gn:timezone":"Asia/Taipei",
    "iso:country":"TW",
    "name:und_x_variant":[
        "Siaolilin",
        "Chiao-li-lin",
        "Hsiao-li-lin"
    ],
    "name:zho_x_preferred":[
        "\u6821\u6817\u6797"
    ],
    "wof:name":"Xiaolilin",
    "wof:placetype":"locality"
},
  "geometry": {"coordinates":[120.72499999999999,24.46778],"type":"Point"}
}