{
  "type": "Feature",
  "properties": {
    "gn:admin1_code":"04",
    "gn:admin2_code":"TXG",
    "gn:admin3_code":"B21",
    "gn:admin4_code":"66000210005.0",
    "gn:asciiname":"Shanjiao",
    "gn:country_code":"TW",
    "gn:dem":123,
    "gn:feature_class":"P",
    "gn:feature_code":"PPL",
    "gn:name":"Shanjiao",
    "gn:population":0,
    "gn:timezone":"Asia/Taipei",
    "iso:country":"TW",
    "name:und_x_variant":[
        "Min-shan",
        "Shanjiao",
        "Shan-chiao"
    ],
    "name:zho_x_preferred":[
        "\u5c71\u811a"
    ],
    "wof:name":"Shanjiao",
    "wof:placetype":"locality"
},
  "geometry": {"coordinates":[120.62944,24.33],"type":"Point"}
}