{
  "type": "Feature",
  "properties": {
    "gn:admin1_code":"4.0",
    "gn:admin2_code":"PEN",
    "gn:admin3_code":"X01",
    "gn:admin4_code":"10016010013.0",
    "gn:asciiname":"Tajian",
    "gn:country_code":"TW",
    "gn:dem":6,
    "gn:feature_class":"P",
    "gn:feature_code":"PPL",
    "gn:name":"Tajian",
    "gn:population":0,
    "gn:timezone":"Asia/Taipei",
    "iso:country":"TW",
    "name:und_x_variant":[
        "Tajian"
    ],
    "name:zho_x_preferred":[
        "T\u2019a-chien"
    ],
    "name:zho_x_variant":[
        "\u5854\u5c16"
    ],
    "wof:name":"Tajian",
    "wof:placetype":"locality"
},
  "geometry": {"coordinates":[119.56708,23.58413],"type":"Point"}
}