{
  "type": "Feature",
  "properties": {
    "gn:admin1_code":"4.0",
    "gn:admin2_code":"ILA",
    "gn:admin3_code":"G10",
    "gn:admin4_code":"10002100001.0",
    "gn:asciiname":"Qingshuihu",
    "gn:country_code":"TW",
    "gn:dem":178,
    "gn:feature_class":"P",
    "gn:feature_code":"PPL",
    "gn:name":"Qingshuihu",
    "gn:population":0,
    "gn:timezone":"Asia/Taipei",
    "iso:country":"TW",
    "name:und_x_variant":[
        "Cingshueihu",
        "Qingshuihu"
    ],
    "name:zho_x_preferred":[
        "\u6e05\u6c34\u6e56"
    ],
    "name:zho_x_variant":[
        "Ch\u2019ing-shui",
        "Ch\u2019ing-shui-hu"
    ],
    "wof:name":"Qingshuihu",
    "wof:placetype":"locality"
},
  "geometry": {"coordinates":[121.59793999999999,24.64308],"type":"Point"}
}