{
  "type": "Feature",
  "properties": {
    "gn:admin1_code":"02",
    "gn:admin2_code":"KHH",
    "gn:admin3_code":"E27",
    "gn:admin4_code":"64000270006.0",
    "gn:asciiname":"Weixin",
    "gn:country_code":"TW",
    "gn:dem":12,
    "gn:feature_class":"P",
    "gn:feature_code":"PPL",
    "gn:name":"Weixin",
    "gn:population":0,
    "gn:timezone":"Asia/Taipei",
    "iso:country":"TW",
    "name:und_x_variant":[
        "Chu-tzu-chiang",
        "Weisin",
        "Chu-tzu-kang",
        "Weixin",
        "Wei-hsin"
    ],
    "name:zho_x_preferred":[
        "Wei-hsin-ts\u2019un"
    ],
    "name:zho_x_variant":[
        "\u7dad\u65b0"
    ],
    "wof:name":"Weixin",
    "wof:placetype":"locality"
},
  "geometry": {"coordinates":[120.2475,22.80667],"type":"Point"}
}