{
  "type": "Feature",
  "properties": {
    "gn:admin1_code":"04",
    "gn:admin2_code":"NAN",
    "gn:admin3_code":"M08",
    "gn:admin4_code":"10008080007.0",
    "gn:asciiname":"Dongshige",
    "gn:country_code":"TW",
    "gn:dem":216,
    "gn:feature_class":"P",
    "gn:feature_code":"PPL",
    "gn:name":"Dongshige",
    "gn:population":0,
    "gn:timezone":"Asia/Taipei",
    "iso:country":"TW",
    "name:und_x_variant":[
        "Tung-shih-chien",
        "Dongshihge",
        "Dongshige",
        "Tung-shih-ko"
    ],
    "name:zho_x_preferred":[
        "\u6771\u52e2\u95a3"
    ],
    "wof:name":"Dongshige",
    "wof:placetype":"locality"
},
  "geometry": {"coordinates":[120.76492,23.89485],"type":"Point"}
}