{
  "type": "Feature",
  "properties": {
    "gn:admin1_code":"4.0",
    "gn:admin2_code":"PEN",
    "gn:admin3_code":"X06",
    "gn:admin4_code":"10016060002.0",
    "gn:asciiname":"Zhongping",
    "gn:country_code":"TW",
    "gn:dem":7,
    "gn:feature_class":"P",
    "gn:feature_code":"PPL",
    "gn:name":"Zhongping",
    "gn:population":0,
    "gn:timezone":"Asia/Taipei",
    "iso:country":"TW",
    "name:und_x_variant":[
        "Chung-p\u2019ing-ts\u2019un",
        "Chung-p\u2019ing",
        "Zhongping"
    ],
    "wof:name":"Zhongping",
    "wof:placetype":"locality"
},
  "geometry": {"coordinates":[119.41667,23.21667],"type":"Point"}
}