{
  "type": "Feature",
  "properties": {
    "gn:admin1_code":"4.0",
    "gn:admin2_code":"TNN",
    "gn:admin3_code":"R27",
    "gn:admin4_code":"67000270006.0",
    "gn:asciiname":"Beibaozi",
    "gn:country_code":"TW",
    "gn:dem":13,
    "gn:feature_class":"P",
    "gn:feature_code":"PPL",
    "gn:name":"Beibaozi",
    "gn:population":0,
    "gn:timezone":"Asia/Taipei",
    "iso:country":"TW",
    "name:und_x_variant":[
        "Beibaozih",
        "Pei-pao-tzu"
    ],
    "name:zho_x_preferred":[
        "\u5317\u4fdd\u4ed4"
    ],
    "wof:name":"Beibaozi",
    "wof:placetype":"locality"
},
  "geometry": {"coordinates":[120.25139,22.95472],"type":"Point"}
}