{
  "type": "Feature",
  "properties": {
    "gn:admin1_code":"4.0",
    "gn:admin2_code":"YUN",
    "gn:admin3_code":"P09",
    "gn:admin4_code":"10009090010.0",
    "gn:asciiname":"Xingbei",
    "gn:country_code":"TW",
    "gn:dem":48,
    "gn:feature_class":"P",
    "gn:feature_code":"PPL",
    "gn:name":"Xingbei",
    "gn:population":0,
    "gn:timezone":"Asia/Taipei",
    "iso:country":"TW",
    "name:und_x_variant":[
        "Singbei",
        "Xingbei",
        "Hsing-pei"
    ],
    "name:zho_x_preferred":[
        "\u8208\u5317"
    ],
    "name:zho_x_variant":[
        "Hung-chu-k\u2019ou"
    ],
    "wof:name":"Xingbei",
    "wof:placetype":"locality"
},
  "geometry": {"coordinates":[120.52067,23.77564],"type":"Point"}
}