{
  "type": "Feature",
  "properties": {
    "gn:admin1_code":"04",
    "gn:admin2_code":"HSZ",
    "gn:admin3_code":"J04",
    "gn:admin4_code":"10004030003.0",
    "gn:asciiname":"Tudigongbu",
    "gn:country_code":"TW",
    "gn:dem":46,
    "gn:feature_class":"P",
    "gn:feature_code":"PPL",
    "gn:name":"Tudigongbu",
    "gn:population":0,
    "gn:timezone":"Asia/Taipei",
    "iso:country":"TW",
    "name:zho_x_preferred":[
        "\u571f\u5730\u516c\u57d4"
    ],
    "name:zho_x_variant":[
        "T\u2019u-ti-pu",
        "T\u2019u-ti-kung-pu"
    ],
    "wof:name":"Tudigongbu",
    "wof:placetype":"locality"
},
  "geometry": {"coordinates":[121.06111,24.825],"type":"Point"}
}