{
  "type": "Feature",
  "properties": {
    "gn:admin1_code":"4.0",
    "gn:admin2_code":"HSQ",
    "gn:admin3_code":"O03",
    "gn:admin4_code":"10018030002.0",
    "gn:asciiname":"Hulinshan",
    "gn:country_code":"TW",
    "gn:dem":16,
    "gn:feature_class":"P",
    "gn:feature_code":"PPL",
    "gn:name":"Hulinshan",
    "gn:population":0,
    "gn:timezone":"Asia/Taipei",
    "iso:country":"TW",
    "name:und_x_variant":[
        "Hu-lin-shan"
    ],
    "name:zho_x_preferred":[
        "\u864e\u6797\u5c71"
    ],
    "wof:name":"Hulinshan",
    "wof:placetype":"locality"
},
  "geometry": {"coordinates":[120.93389000000001,24.80639],"type":"Point"}
}