{
  "type": "Feature",
  "properties": {
    "gn:admin1_code":"4.0",
    "gn:admin2_code":"TAO",
    "gn:admin3_code":"H04",
    "gn:admin4_code":"68000040025.0",
    "gn:asciiname":"Xiasihu",
    "gn:country_code":"TW",
    "gn:dem":120,
    "gn:feature_class":"P",
    "gn:feature_code":"PPL",
    "gn:name":"Xiasihu",
    "gn:population":0,
    "gn:timezone":"Asia/Taipei",
    "iso:country":"TW",
    "name:und_x_variant":[
        "Siasihhu",
        "Xiasihu",
        "Hsia-ssu-hu"
    ],
    "name:zho_x_preferred":[
        "\u4e0b\u56db\u6e56"
    ],
    "wof:name":"Xiasihu",
    "wof:placetype":"locality"
},
  "geometry": {"coordinates":[121.07222,24.91389],"type":"Point"}
}