{
  "type": "Feature",
  "properties": {
    "gn:admin1_code":"2.0",
    "gn:admin2_code":"KHH",
    "gn:admin3_code":"E14",
    "gn:admin4_code":"64000140017.0",
    "gn:asciiname":"Houshengtan",
    "gn:country_code":"TW",
    "gn:dem":25,
    "gn:feature_class":"P",
    "gn:feature_code":"PPL",
    "gn:name":"Houshengtan",
    "gn:population":0,
    "gn:timezone":"Asia/Taipei",
    "iso:country":"TW",
    "name:und_x_variant":[
        "\u5f8c\u8056\u6f6d",
        "Houshengtan"
    ],
    "name:zho_x_preferred":[
        "Hou-sheng-t\u2019an"
    ],
    "name:zho_x_variant":[
        "\u5f8c\u8056\u6f6d"
    ],
    "wof:name":"Houshengtan",
    "wof:placetype":"locality"
},
  "geometry": {"coordinates":[120.38826,22.6082],"type":"Point"}
}