{
  "type": "Feature",
  "properties": {
    "gn:admin1_code":"4.0",
    "gn:admin2_code":"TTT",
    "gn:admin3_code":"V01",
    "gn:admin4_code":"10014010040.0",
    "gn:asciiname":"Fengli",
    "gn:country_code":"TW",
    "gn:dem":21,
    "gn:feature_class":"P",
    "gn:feature_code":"PPL",
    "gn:name":"Fengli",
    "gn:population":0,
    "gn:timezone":"Asia/Taipei",
    "iso:country":"TW",
    "name:und_x_variant":[
        "Fongli",
        "Fengli",
        "Feng-li"
    ],
    "name:zho_x_preferred":[
        "Hs\u00fc-ts\u2019un"
    ],
    "name:zho_x_variant":[
        "Feng-li-ts\u2019un",
        "\u8c50\u91cc"
    ],
    "wof:name":"Fengli",
    "wof:placetype":"locality"
},
  "geometry": {"coordinates":[121.11944,22.73639],"type":"Point"}
}