{
  "type": "Feature",
  "properties": {
    "gn:admin1_code":"02",
    "gn:admin2_code":"KHH",
    "gn:admin3_code":"E21",
    "gn:admin4_code":"64000210004.0",
    "gn:asciiname":"Gunshuiping",
    "gn:country_code":"TW",
    "gn:dem":26,
    "gn:feature_class":"P",
    "gn:feature_code":"PPL",
    "gn:name":"Gunshuiping",
    "gn:population":0,
    "gn:timezone":"Asia/Taipei",
    "iso:country":"TW",
    "name:und_x_variant":[
        "Nuan-feng-shih",
        "Gunshuiping",
        "Gunshueiping"
    ],
    "name:zho_x_preferred":[
        "\u6efe\u6c34\u576a"
    ],
    "name:zho_x_variant":[
        "Nuan-ch\u2019ao-shih",
        "Kun-shui-p\u2019ing"
    ],
    "wof:name":"Gunshuiping",
    "wof:placetype":"locality"
},
  "geometry": {"coordinates":[120.34667,22.77028],"type":"Point"}
}