{
  "type": "Feature",
  "properties": {
    "gn:admin1_code":"4.0",
    "gn:admin2_code":"TTT",
    "gn:admin3_code":"V14",
    "gn:admin4_code":"10014150003.0",
    "gn:asciiname":"Guzilun",
    "gn:country_code":"TW",
    "gn:dem":433,
    "gn:feature_class":"P",
    "gn:feature_code":"PPL",
    "gn:name":"Guzilun",
    "gn:population":0,
    "gn:timezone":"Asia/Taipei",
    "iso:country":"TW",
    "name:und_x_variant":[
        "Guzihlun",
        "Ku-tzu-lun"
    ],
    "name:zho_x_preferred":[
        "\u59d1\u5b50\u5d19"
    ],
    "wof:name":"Guzilun",
    "wof:placetype":"locality"
},
  "geometry": {"coordinates":[120.84056,22.37444],"type":"Point"}
}