{
  "type": "Feature",
  "properties": {
    "gn:admin1_code":"3.0",
    "gn:admin2_code":"TPQ",
    "gn:admin3_code":"F17",
    "gn:admin4_code":"65000070023.0",
    "gn:asciiname":"Nanjingcuo",
    "gn:country_code":"TW",
    "gn:dem":42,
    "gn:feature_class":"P",
    "gn:feature_code":"PPL",
    "gn:name":"Nanjingcuo",
    "gn:population":0,
    "gn:timezone":"Asia/Taipei",
    "iso:country":"TW",
    "name:zho_x_preferred":[
        "\u5357\u9756\u539d"
    ],
    "name:zho_x_variant":[
        "Nan-ching-ts\u2019o"
    ],
    "wof:name":"Nanjingcuo",
    "wof:placetype":"locality"
},
  "geometry": {"coordinates":[121.36794999999999,24.95],"type":"Point"}
}