{
  "type": "Feature",
  "properties": {
    "gn:admin1_code":"04",
    "gn:admin2_code":"TNN",
    "gn:admin3_code":"R03",
    "gn:admin4_code":"67000030012.0",
    "gn:asciiname":"Pingding",
    "gn:country_code":"TW",
    "gn:dem":440,
    "gn:feature_class":"P",
    "gn:feature_code":"PPL",
    "gn:name":"Pingding",
    "gn:population":0,
    "gn:timezone":"Asia/Taipei",
    "iso:country":"TW",
    "name:zho_x_preferred":[
        "\u576a\u9802"
    ],
    "name:zho_x_variant":[
        "P\u2019ing-ting"
    ],
    "wof:name":"Pingding",
    "wof:placetype":"locality"
},
  "geometry": {"coordinates":[120.49889,23.32444],"type":"Point"}
}