{
  "type": "Feature",
  "properties": {
    "gn:admin1_code":"3.0",
    "gn:admin2_code":"TPQ",
    "gn:admin3_code":"F21",
    "gn:admin4_code":"65000120026.0",
    "gn:asciiname":"Jinguashi",
    "gn:country_code":"TW",
    "gn:dem":254,
    "gn:feature_class":"P",
    "gn:feature_code":"PPL",
    "gn:name":"Jinguashi",
    "gn:population":0,
    "gn:timezone":"Asia/Taipei",
    "iso:country":"TW",
    "name:und_x_variant":[
        "Chin-kwa-shih",
        "Jinguashih",
        "Jinguashi",
        "Chin-kua-shih"
    ],
    "name:zho_x_preferred":[
        "\u91d1\u74dc\u77f3"
    ],
    "wof:name":"Jinguashi",
    "wof:placetype":"locality"
},
  "geometry": {"coordinates":[121.85541000000001,25.10946],"type":"Point"}
}