{
  "type": "Feature",
  "properties": {
    "gn:admin1_code":"04",
    "gn:admin2_code":"PIF",
    "gn:admin3_code":"T05",
    "gn:admin4_code":"10013050029.0",
    "gn:asciiname":"Shuixiancun",
    "gn:country_code":"TW",
    "gn:dem":10,
    "gn:feature_class":"P",
    "gn:feature_code":"PPL",
    "gn:name":"Shuixiancun",
    "gn:population":0,
    "gn:timezone":"Asia/Taipei",
    "iso:country":"TW",
    "name:und_x_variant":[
        "Shui-hsien-li",
        "\u6c34\u4ed9\u6751",
        "Shui-hsien",
        "Shui-hsiao",
        "Shuixiancun",
        "Shueisiancun"
    ],
    "name:zho_x_preferred":[
        "Shui-hsien-ts\u2019un"
    ],
    "name:zho_x_variant":[
        "\u6c34\u4ed9\u6751"
    ],
    "wof:name":"Shuixiancun",
    "wof:placetype":"locality"
},
  "geometry": {"coordinates":[120.49151000000001,22.55568],"type":"Point"}
}