{
  "type": "Feature",
  "properties": {
    "gn:admin1_code":"4.0",
    "gn:admin2_code":"TNN",
    "gn:admin3_code":"R05",
    "gn:admin4_code":"67000050020.0",
    "gn:asciiname":"Changduanshu",
    "gn:country_code":"TW",
    "gn:dem":17,
    "gn:feature_class":"P",
    "gn:feature_code":"PPL",
    "gn:name":"Changduanshu",
    "gn:population":0,
    "gn:timezone":"Asia/Taipei",
    "iso:country":"TW",
    "name:zho_x_preferred":[
        "Ting-ch\u2019ang-ts\u2019un"
    ],
    "name:zho_x_variant":[
        "Ting-ch\u2019ang-tuan-shu",
        "\u9577\u77ed\u6a39",
        "Ch\u2019ang-tuan-shu"
    ],
    "wof:name":"Changduanshu",
    "wof:placetype":"locality"
},
  "geometry": {"coordinates":[120.33028,23.36694],"type":"Point"}
}