{
  "type": "Feature",
  "properties": {
    "gn:admin1_code":"3.0",
    "gn:admin2_code":"TPQ",
    "gn:admin3_code":"F25",
    "gn:admin4_code":"65000270012.0",
    "gn:asciiname":"Kanjiaoxia",
    "gn:country_code":"TW",
    "gn:dem":13,
    "gn:feature_class":"P",
    "gn:feature_code":"PPL",
    "gn:name":"Kanjiaoxia",
    "gn:population":0,
    "gn:timezone":"Asia/Taipei",
    "iso:country":"TW",
    "name:und_x_variant":[
        "Kanjiaosia"
    ],
    "name:zho_x_preferred":[
        "\u5d01\u8173\u4e0b"
    ],
    "name:zho_x_variant":[
        "K\u2019an-chiao-hsia"
    ],
    "wof:name":"Kanjiaoxia",
    "wof:placetype":"locality"
},
  "geometry": {"coordinates":[121.62884,25.23809],"type":"Point"}
}