{
  "type": "Feature",
  "properties": {
    "gn:admin1_code":"03",
    "gn:admin2_code":"TPQ",
    "gn:admin3_code":"F03",
    "gn:admin4_code":"65000150007.0",
    "gn:asciiname":"Wugukeng",
    "gn:country_code":"TW",
    "gn:dem":95,
    "gn:feature_class":"P",
    "gn:feature_code":"PPL",
    "gn:name":"Wugukeng",
    "gn:population":0,
    "gn:timezone":"Asia/Taipei",
    "iso:country":"TW",
    "name:und_x_variant":[
        "Wu-ku",
        "Wugukeng"
    ],
    "name:zho_x_preferred":[
        "\u4e94\u80a1\u5751"
    ],
    "name:zho_x_variant":[
        "Wu-ku-k\u2019eng"
    ],
    "wof:name":"Wugukeng",
    "wof:placetype":"locality"
},
  "geometry": {"coordinates":[121.40613999999999,25.1092],"type":"Point"}
}