{
  "type": "Feature",
  "properties": {
    "gn:admin1_code":"4.0",
    "gn:admin2_code":"TTT",
    "gn:admin3_code":"V01",
    "gn:admin4_code":"10014010031.0",
    "gn:asciiname":"Fengnian",
    "gn:country_code":"TW",
    "gn:dem":38,
    "gn:feature_class":"P",
    "gn:feature_code":"PPL",
    "gn:name":"Fengnian",
    "gn:population":0,
    "gn:timezone":"Asia/Taipei",
    "iso:country":"TW",
    "name:und_x_variant":[
        "Fongnian",
        "Fengnian",
        "Feng-nien"
    ],
    "name:zho_x_preferred":[
        "\u8c50\u5e74"
    ],
    "wof:name":"Fengnian",
    "wof:placetype":"locality"
},
  "geometry": {"coordinates":[121.11163999999999,22.77038],"type":"Point"}
}