{
  "type": "Feature",
  "properties": {
    "gn:admin1_code":"4.0",
    "gn:admin2_code":"HSZ",
    "gn:admin3_code":"J08",
    "gn:admin4_code":"10004080003.0",
    "gn:asciiname":"Nanchang",
    "gn:country_code":"TW",
    "gn:dem":312,
    "gn:feature_class":"P",
    "gn:feature_code":"PPL",
    "gn:name":"Nanchang",
    "gn:population":0,
    "gn:timezone":"Asia/Taipei",
    "iso:country":"TW",
    "name:und_x_variant":[
        "Lan-tzu",
        "Nanchang"
    ],
    "name:zho_x_preferred":[
        "Nan-ch\u2019ang-ts\u2019un"
    ],
    "name:zho_x_variant":[
        "\u5357\u660c",
        "Nan-ch\u2019ang"
    ],
    "wof:name":"Nanchang",
    "wof:placetype":"locality"
},
  "geometry": {"coordinates":[121.12694,24.67306],"type":"Point"}
}