{
  "type": "Feature",
  "properties": {
    "gn:admin1_code":"03",
    "gn:admin2_code":"TPQ",
    "gn:admin3_code":"F17",
    "gn:admin4_code":"65000070025.0",
    "gn:asciiname":"Shangshitouxi",
    "gn:country_code":"TW",
    "gn:dem":33,
    "gn:feature_class":"P",
    "gn:feature_code":"PPL",
    "gn:name":"Shangshitouxi",
    "gn:population":0,
    "gn:timezone":"Asia/Taipei",
    "iso:country":"TW",
    "name:und_x_variant":[
        "Shangshihtousi",
        "Shih-hsi",
        "Shangshitouxi"
    ],
    "name:zho_x_preferred":[
        "Hsia-shih-t\u2019ou-ch\u2019i"
    ],
    "name:zho_x_variant":[
        "Shang-shih-t\u2019ou-ch\u2019i",
        "Hsia-shih-t\u2019ou-hsi",
        "\u4e0a\u77f3\u982d\u6eaa",
        "Shang-shih-t\u2019ou-hsi"
    ],
    "wof:name":"Shangshitouxi",
    "wof:placetype":"locality"
},
  "geometry": {"coordinates":[121.39033999999999,24.9581],"type":"Point"}
}