{
  "type": "Feature",
  "properties": {
    "gn:admin1_code":"04",
    "gn:admin2_code":"NAN",
    "gn:admin3_code":"M11",
    "gn:admin4_code":"10008110016.0",
    "gn:asciiname":"Yongxing",
    "gn:country_code":"TW",
    "gn:dem":305,
    "gn:feature_class":"P",
    "gn:feature_code":"PPL",
    "gn:name":"Yongxing",
    "gn:population":0,
    "gn:timezone":"Asia/Taipei",
    "iso:country":"TW",
    "name:ceb_x_preferred":[
        "Yongxing"
    ],
    "name:deu_x_preferred":[
        "Yongxing"
    ],
    "name:gan_x_preferred":[
        "\u6c38\u8208"
    ],
    "name:und_x_variant":[
        "Niu-wen-lu",
        "Yongsing",
        "Yung-hsing"
    ],
    "name:zho_x_preferred":[
        "Yung-hsiang-ts\u2019un"
    ],
    "name:zho_x_variant":[
        "Yung-hsing-ts\u2019un",
        "\u6c38\u8208"
    ],
    "wof:name":"Yongxing",
    "wof:placetype":"locality"
},
  "geometry": {"coordinates":[120.86315999999999,23.78401],"type":"Point"}
}