{
  "type": "Feature",
  "properties": {
    "gn:admin1_code":"04",
    "gn:admin2_code":"MIA",
    "gn:admin3_code":"K04",
    "gn:admin4_code":"10005090004.0",
    "gn:asciiname":"Shangdakeng",
    "gn:country_code":"TW",
    "gn:dem":108,
    "gn:feature_class":"P",
    "gn:feature_code":"PPL",
    "gn:name":"Shangdakeng",
    "gn:population":0,
    "gn:timezone":"Asia/Taipei",
    "iso:country":"TW",
    "name:zho_x_preferred":[
        "\u4e0a\u5927\u5751"
    ],
    "name:zho_x_variant":[
        "Shang-ta-k\u2019eng"
    ],
    "wof:name":"Shangdakeng",
    "wof:placetype":"locality"
},
  "geometry": {"coordinates":[120.83822000000001,24.50487],"type":"Point"}
}