{
  "type": "Feature",
  "properties": {
    "gn:admin1_code":"4.0",
    "gn:admin2_code":"TXG",
    "gn:admin3_code":"B11",
    "gn:admin4_code":"66000110021.0",
    "gn:asciiname":"Liugu",
    "gn:country_code":"TW",
    "gn:dem":114,
    "gn:feature_class":"P",
    "gn:feature_code":"PPL",
    "gn:name":"Liugu",
    "gn:population":0,
    "gn:timezone":"Asia/Taipei",
    "iso:country":"TW",
    "name:und_x_variant":[
        "Liougu",
        "Liu-ku"
    ],
    "name:zho_x_preferred":[
        "\u516d\u80a1"
    ],
    "wof:name":"Liugu",
    "wof:placetype":"locality"
},
  "geometry": {"coordinates":[120.68472,24.365],"type":"Point"}
}