{
  "type": "Feature",
  "properties": {
    "iso:country":"TW",
    "name:unk_x_variant":[
        "\u5e73\u5bee\u91cc"
    ],
    "name:zho_x_preferred":[
        "\u5e73\u5bee\u91cc"
    ],
    "qs:gn_adm0_cc":"TW",
    "qs:gn_local":1678228,
    "qs:local_max":2352,
    "qs:local_sum":26237,
    "qs:localhoods":59,
    "qs:name":"\u5e73\u5bee\u91cc",
    "qs:name_adm0":"\u81fa\u7063",
    "qs:name_adm1":"\u57fa\u9686\u5e02",
    "qs:name_adm2":"\u4e2d\u6b63\u5340",
    "qs:name_local":"\u57fa\u9686\u5e02",
    "qs:photo_max":175,
    "qs:photo_sum":1184,
    "qs:placetype":"Suburb",
    "qs:quad_count":30,
    "qs:woe_adm0":23424971,
    "qs:woe_adm1":22695855,
    "qs:woe_adm2":28752185,
    "qs:woe_lau":0,
    "qs:woe_local":2306188,
    "qs:woe_ver":"7.10.0",
    "wof:lang":[
        "chi"
    ],
    "wof:name":"\u5e73\u5bee\u91cc",
    "wof:placetype":"neighbourhood"
},
  "geometry": {"coordinates":[121.76277399999999,25.158313],"type":"Point"}
}