{
  "type": "Feature",
  "properties": {
    "gn:admin1_code":"4.0",
    "gn:admin2_code":"MIA",
    "gn:admin3_code":"K12",
    "gn:admin4_code":"10005060019.0",
    "gn:asciiname":"Tongxing",
    "gn:country_code":"TW",
    "gn:dem":8,
    "gn:feature_class":"P",
    "gn:feature_code":"PPL",
    "gn:name":"Tongxing",
    "gn:population":0,
    "gn:timezone":"Asia/Taipei",
    "iso:country":"TW",
    "name:und_x_variant":[
        "Wan-kuei-kou",
        "Tongsing"
    ],
    "name:zho_x_preferred":[
        "\u540c\u8208"
    ],
    "name:zho_x_variant":[
        "T\u2019ung-hsing"
    ],
    "wof:name":"Tongxing",
    "wof:placetype":"locality"
},
  "geometry": {"coordinates":[120.76300999999999,24.61016],"type":"Point"}
}