{
  "type": "Feature",
  "properties": {
    "gn:admin1_code":"2.0",
    "gn:admin2_code":"KHH",
    "gn:admin3_code":"E11",
    "gn:admin4_code":"64000110022.0",
    "gn:asciiname":"Zhongpou",
    "gn:country_code":"TW",
    "gn:dem":12,
    "gn:feature_class":"P",
    "gn:feature_code":"PPL",
    "gn:name":"Zhongpou",
    "gn:population":0,
    "gn:timezone":"Asia/Taipei",
    "iso:country":"TW",
    "name:und_x_variant":[
        "\u4e2d\u5ecd",
        "Chung-pu",
        "Jhongpou",
        "Zhongpou"
    ],
    "name:zho_x_preferred":[
        "Chung-p\u2019ou"
    ],
    "name:zho_x_variant":[
        "\u4e2d\u5ecd"
    ],
    "wof:name":"Zhongpou",
    "wof:placetype":"locality"
},
  "geometry": {"coordinates":[120.37316,22.55746],"type":"Point"}
}