{
  "type": "Feature",
  "properties": {
    "gn:admin1_code":"4.0",
    "gn:admin2_code":"TTT",
    "gn:admin3_code":"V08",
    "gn:admin4_code":"10014080006.0",
    "gn:asciiname":"Shimenxiang",
    "gn:country_code":"TW",
    "gn:dem":65,
    "gn:feature_class":"P",
    "gn:feature_code":"PPL",
    "gn:name":"Shimenxiang",
    "gn:population":0,
    "gn:timezone":"Asia/Taipei",
    "iso:country":"TW",
    "name:und_x_variant":[
        "Shihmensiang",
        "Shih-men-hsiang"
    ],
    "name:zho_x_preferred":[
        "\u77f3\u9580\u5df7"
    ],
    "wof:name":"Shimenxiang",
    "wof:placetype":"locality"
},
  "geometry": {"coordinates":[121.40948,23.27183],"type":"Point"}
}