{
  "type": "Feature",
  "properties": {
    "gn:admin1_code":"04",
    "gn:admin2_code":"CHA",
    "gn:admin3_code":"N23",
    "gn:admin4_code":"10007230026.0",
    "gn:asciiname":"Beihanbao",
    "gn:country_code":"TW",
    "gn:dem":6,
    "gn:feature_class":"P",
    "gn:feature_code":"PPL",
    "gn:name":"Beihanbao",
    "gn:population":0,
    "gn:timezone":"Asia/Taipei",
    "iso:country":"TW",
    "name:und_x_variant":[
        "Pei-han-pao"
    ],
    "name:zho_x_preferred":[
        "\u5317\u6f22\u5bf6"
    ],
    "wof:name":"Beihanbao",
    "wof:placetype":"locality"
},
  "geometry": {"coordinates":[120.38222,24.01528],"type":"Point"}
}