{
  "type": "Feature",
  "properties": {
    "gn:admin1_code":"4.0",
    "gn:admin2_code":"PIF",
    "gn:admin3_code":"T21",
    "gn:admin4_code":"10013210010.0",
    "gn:asciiname":"Tianliao",
    "gn:country_code":"TW",
    "gn:dem":7,
    "gn:feature_class":"P",
    "gn:feature_code":"PPL",
    "gn:name":"Tianliao",
    "gn:population":0,
    "gn:timezone":"Asia/Taipei",
    "iso:country":"TW",
    "name:und_x_variant":[
        "Tianliao"
    ],
    "name:zho_x_preferred":[
        "\u7530\u5bee"
    ],
    "name:zho_x_variant":[
        "T\u2019ien-liao"
    ],
    "wof:name":"Tianliao",
    "wof:placetype":"locality"
},
  "geometry": {"coordinates":[120.52778000000001,22.42917000000001],"type":"Point"}
}