{
  "type": "Feature",
  "properties": {
    "gn:admin1_code":"4.0",
    "gn:admin2_code":"TNN",
    "gn:admin3_code":"R13",
    "gn:admin4_code":"67000140002.0",
    "gn:asciiname":"Zhonggang",
    "gn:country_code":"TW",
    "gn:dem":10,
    "gn:feature_class":"P",
    "gn:feature_code":"PPL",
    "gn:name":"Zhonggang",
    "gn:population":0,
    "gn:timezone":"Asia/Taipei",
    "iso:country":"TW",
    "name:und_x_variant":[
        "Chung-kang",
        "Chung-tung",
        "Zhonggang",
        "Chung-chiang",
        "Jhonggang"
    ],
    "name:zho_x_preferred":[
        "Chung-tung-ts\u2019un"
    ],
    "name:zho_x_variant":[
        "\u4e2d\u6e2f"
    ],
    "wof:name":"Zhonggang",
    "wof:placetype":"locality"
},
  "geometry": {"coordinates":[120.19417,23.10889],"type":"Point"}
}