{
  "type": "Feature",
  "properties": {
    "iso:country":"TW",
    "name:eng_x_preferred":[
        "Zhonglin"
    ],
    "name:eng_x_variant":[
        "Zhonglin Village"
    ],
    "name:zho_tw_x_preferred":[
        "\u4e2d\u6797\u6751"
    ],
    "qs:name":"\u4e2d\u6797\u6751",
    "qs:name_adm0":"\u81fa\u7063",
    "qs:name_adm1":"\u5c4f\u6771\u7e23",
    "qs:photos":39,
    "qs:photos_1k":8,
    "qs:photos_9k":1,
    "qs:photos_9r":2,
    "qs:photos_all":39,
    "qs:photos_sr":2,
    "qs:placetype":"Town",
    "qs:pop_sr":"0",
    "wof:name":"Zhonglin",
    "wof:placetype":"locality"
},
  "geometry": {"coordinates":[120.51904399999999,22.436338],"type":"Point"}
}