{
  "type": "Feature",
  "properties": {
    "gn:admin1_code":"04",
    "gn:admin2_code":"CHA",
    "gn:admin3_code":"N24",
    "gn:admin4_code":"10007240010.0",
    "gn:asciiname":"Dabu",
    "gn:country_code":"TW",
    "gn:dem":8,
    "gn:feature_class":"P",
    "gn:feature_code":"PPL",
    "gn:name":"Dabu",
    "gn:population":0,
    "gn:timezone":"Asia/Taipei",
    "iso:country":"TW",
    "name:ceb_x_preferred":[
        "Dabu"
    ],
    "name:deu_x_preferred":[
        "Dabu"
    ],
    "name:fra_x_preferred":[
        "Dabu"
    ],
    "name:ita_x_preferred":[
        "Dabu"
    ],
    "name:und_x_variant":[
        "Ta-pu"
    ],
    "name:zho_x_preferred":[
        "\u5927\u57d4"
    ],
    "wof:name":"Dabu",
    "wof:placetype":"locality"
},
  "geometry": {"coordinates":[120.30096,23.84983],"type":"Point"}
}