{
  "type": "Feature",
  "properties": {
    "gn:country":"TW",
    "iso:country":"TW",
    "qs:name":"\u4e09\u80a1\u6751",
    "qs:name_adm0":"\u81fa\u7063",
    "qs:name_adm1":"\u53f0\u5357\u5e02",
    "qs:photos":496,
    "qs:photos_1k":101,
    "qs:photos_9k":2,
    "qs:photos_9r":5,
    "qs:photos_all":496,
    "qs:photos_sr":7,
    "qs:placetype":"Town",
    "qs:pop_sr":"0",
    "wof:name":"\u4e09\u80a1\u6751",
    "wof:placetype":"locality"
},
  "geometry": {"coordinates":[120.05765100000001,23.124433],"type":"Point"}
}