{
  "type": "Feature",
  "properties": {
    "gn:admin1_code":"4.0",
    "gn:admin2_code":"MIA",
    "gn:admin3_code":"K09",
    "gn:admin4_code":"10005040020.0",
    "gn:asciiname":"Chiqixia",
    "gn:country_code":"TW",
    "gn:dem":60,
    "gn:feature_class":"P",
    "gn:feature_code":"PPL",
    "gn:name":"Chiqixia",
    "gn:population":0,
    "gn:timezone":"Asia/Taipei",
    "iso:country":"TW",
    "name:und_x_variant":[
        "Chihcisia"
    ],
    "name:zho_x_preferred":[
        "\u8d64\u5d0e\u4e0b"
    ],
    "name:zho_x_variant":[
        "Ch\u2019ih-ch\u2019i-hsia"
    ],
    "wof:name":"Chiqixia",
    "wof:placetype":"locality"
},
  "geometry": {"coordinates":[120.92152,24.70412],"type":"Point"}
}