{
  "type": "Feature",
  "properties": {
    "iso:country":"TW",
    "name:eng_x_preferred":[
        "Dunan"
    ],
    "name:eng_x_variant":[
        "Dunan Village"
    ],
    "name:zho_tw_x_preferred":[
        "\u5835\u5357\u91cc"
    ],
    "name:zho_x_preferred":[
        "\u5835\u5357\u91cc"
    ],
    "qs:gn_adm0_cc":"TW",
    "qs:gn_local":1678228,
    "qs:local_max":2352,
    "qs:local_sum":26237,
    "qs:localhoods":59,
    "qs:name":"\u5835\u5357\u91cc",
    "qs:name_adm0":"\u81fa\u7063",
    "qs:name_adm1":"\u57fa\u9686\u5e02",
    "qs:name_adm2":"\u4e03\u5835\u5340",
    "qs:name_local":"\u57fa\u9686\u5e02",
    "qs:photo_max":197,
    "qs:photo_sum":915,
    "qs:placetype":"Suburb",
    "qs:quad_count":33,
    "qs:woe_adm0":23424971,
    "qs:woe_adm1":22695855,
    "qs:woe_adm2":2295810,
    "qs:woe_lau":0,
    "qs:woe_local":2306188,
    "qs:woe_ver":"7.10.0",
    "wof:name":"Dunan",
    "wof:placetype":"neighbourhood"
},
  "geometry": {"coordinates":[121.665487,25.070024],"type":"Point"}
}