{
  "type": "Feature",
  "properties": {
    "gn:admin1_code":"4.0",
    "gn:admin2_code":"NAN",
    "gn:admin3_code":"M10",
    "gn:admin4_code":"10008100008.0",
    "gn:asciiname":"Mianziyuan",
    "gn:country_code":"TW",
    "gn:dem":535,
    "gn:feature_class":"P",
    "gn:feature_code":"PPL",
    "gn:name":"Mianziyuan",
    "gn:population":0,
    "gn:timezone":"Asia/Taipei",
    "iso:country":"TW",
    "name:und_x_variant":[
        "Mianzihyuan"
    ],
    "name:zho_x_preferred":[
        "\u68c9\u5b50\u5712"
    ],
    "name:zho_x_variant":[
        "Mien-tzu-y\u00fcan"
    ],
    "wof:name":"Mianziyuan",
    "wof:placetype":"locality"
},
  "geometry": {"coordinates":[120.81912,24.0535],"type":"Point"}
}