{
  "type": "Feature",
  "properties": {
    "gn:admin1_code":"4.0",
    "gn:admin2_code":"CHA",
    "gn:admin3_code":"N10",
    "gn:admin4_code":"10007050008.0",
    "gn:asciiname":"Dongxibu",
    "gn:country_code":"TW",
    "gn:dem":5,
    "gn:feature_class":"P",
    "gn:feature_code":"PPL",
    "gn:name":"Dongxibu",
    "gn:population":0,
    "gn:timezone":"Asia/Taipei",
    "iso:country":"TW",
    "name:und_x_variant":[
        "Dongsibu",
        "Tung-hsi-pu"
    ],
    "name:zho_x_preferred":[
        "\u6771\u6eaa\u57d4"
    ],
    "wof:name":"Dongxibu",
    "wof:placetype":"locality"
},
  "geometry": {"coordinates":[120.49583,24.17722],"type":"Point"}
}