{
  "type": "Feature",
  "properties": {
    "iso:country":"TW",
    "name:eng_x_preferred":[
        "Zhenhai"
    ],
    "name:eng_x_variant":[
        "Zhenhai Village"
    ],
    "name:zho_tw_x_preferred":[
        "\u93ae\u6d77\u91cc"
    ],
    "qs:name":"\u93ae\u6d77\u91cc",
    "qs:name_adm0":"\u81fa\u7063",
    "qs:name_adm1":"\u9ad8\u96c4\u5e02",
    "qs:photos":88,
    "qs:photos_1k":18,
    "qs:photos_9k":1,
    "qs:photos_9r":3,
    "qs:photos_all":88,
    "qs:photos_sr":3,
    "qs:placetype":"Suburb",
    "qs:pop_sr":"0",
    "wof:name":"Zhenhai",
    "wof:placetype":"neighbourhood"
},
  "geometry": {"coordinates":[120.316159,22.591931],"type":"Point"}
}