{
  "type": "Feature",
  "properties": {
    "gn:admin1_code":"4.0",
    "gn:admin2_code":"NAN",
    "gn:admin3_code":"M12",
    "gn:admin4_code":"10008120014.0",
    "gn:asciiname":"Jiucengkeng",
    "gn:country_code":"TW",
    "gn:dem":791,
    "gn:feature_class":"P",
    "gn:feature_code":"PPL",
    "gn:name":"Jiucengkeng",
    "gn:population":0,
    "gn:timezone":"Asia/Taipei",
    "iso:country":"TW",
    "name:und_x_variant":[
        "Jioucengkeng"
    ],
    "name:zho_x_preferred":[
        "\u4e5d\u5c64\u5751"
    ],
    "name:zho_x_variant":[
        "Chiu-ts\u2019eng-k\u2019eng"
    ],
    "wof:name":"Jiucengkeng",
    "wof:placetype":"locality"
},
  "geometry": {"coordinates":[120.87667,23.68417],"type":"Point"}
}