{
  "type": "Feature",
  "properties": {
    "iso:country":"TW",
    "qs:name":"\u7af9\u6797\u6751",
    "qs:name_adm0":"\u81fa\u7063",
    "qs:name_adm1":"\u5357\u6295\u7e23",
    "qs:photos":151,
    "qs:photos_1k":31,
    "qs:photos_9k":1,
    "qs:photos_9r":4,
    "qs:photos_all":151,
    "qs:photos_sr":4,
    "qs:placetype":"Town",
    "qs:pop_sr":"0",
    "wof:name":"\u7af9\u6797\u6751",
    "wof:placetype":"locality"
},
  "geometry": {"coordinates":[120.747642,23.689647],"type":"Point"}
}