{
  "type": "Feature",
  "properties": {
    "gn:admin1_code":"4.0",
    "gn:admin2_code":"HSZ",
    "gn:admin3_code":"J11",
    "gn:admin4_code":"10004100004.0",
    "gn:asciiname":"Rongshugang",
    "gn:country_code":"TW",
    "gn:dem":56,
    "gn:feature_class":"P",
    "gn:feature_code":"PPL",
    "gn:name":"Rongshugang",
    "gn:population":0,
    "gn:timezone":"Asia/Taipei",
    "iso:country":"TW",
    "name:und_x_variant":[
        "Jung-shu-kang"
    ],
    "name:zho_x_preferred":[
        "\u6995\u6a39\u5d17"
    ],
    "wof:name":"Rongshugang",
    "wof:placetype":"locality"
},
  "geometry": {"coordinates":[120.98027999999999,24.75],"type":"Point"}
}