{
  "type": "Feature",
  "properties": {
    "gn:admin1_code":"4.0",
    "gn:admin2_code":"TTT",
    "gn:admin3_code":"V14",
    "gn:admin4_code":"10014150002.0",
    "gn:asciiname":"Jiakuobucun",
    "gn:country_code":"TW",
    "gn:dem":282,
    "gn:feature_class":"P",
    "gn:feature_code":"PPL",
    "gn:name":"Jiakuobucun",
    "gn:population":0,
    "gn:timezone":"Asia/Taipei",
    "iso:country":"TW",
    "name:und_x_variant":[
        "Chia-k\u2019uo-pu-she",
        "Chia-k\u2019uo-pu-ts\u2019un",
        "Jiakuobucun"
    ],
    "wof:name":"Jiakuobucun",
    "wof:placetype":"locality"
},
  "geometry": {"coordinates":[120.90000000000001,22.45],"type":"Point"}
}