{
  "type": "Feature",
  "properties": {
    "gn:admin1_code":"4.0",
    "gn:admin2_code":"TXG",
    "gn:admin3_code":"B07",
    "gn:admin4_code":"66000070003.0",
    "gn:asciiname":"Fengshujiao",
    "gn:country_code":"TW",
    "gn:dem":45,
    "gn:feature_class":"P",
    "gn:feature_code":"PPL",
    "gn:name":"Fengshujiao",
    "gn:population":0,
    "gn:timezone":"Asia/Taipei",
    "iso:country":"TW",
    "name:und_x_variant":[
        "Hsia-feng-shu-chiao",
        "Feng-shu",
        "Feng-shu-li",
        "Fongshujiao",
        "Fengshujiao",
        "Feng-shu-chiao"
    ],
    "name:zho_x_preferred":[
        "\u6953\u6a39\u811a"
    ],
    "wof:name":"Fengshujiao",
    "wof:placetype":"locality"
},
  "geometry": {"coordinates":[120.63208,24.1184],"type":"Point"}
}