{
  "type": "Feature",
  "properties": {
    "gn:admin1_code":"4.0",
    "gn:admin2_code":"HUA",
    "gn:admin3_code":"U06",
    "gn:admin4_code":"10015060004.0",
    "gn:asciiname":"Fengli",
    "gn:country_code":"TW",
    "gn:dem":54,
    "gn:feature_class":"P",
    "gn:feature_code":"PPL",
    "gn:name":"Fengli",
    "gn:population":0,
    "gn:timezone":"Asia/Taipei",
    "iso:country":"TW",
    "name:und_x_variant":[
        "Sen-pen",
        "Chung-li",
        "Fongli",
        "Fengli",
        "Feng-li"
    ],
    "name:zho_x_preferred":[
        "\u8c50\u88e1"
    ],
    "name:zho_x_variant":[
        "Feng-li-ts\u2019un"
    ],
    "wof:name":"Fengli",
    "wof:placetype":"locality"
},
  "geometry": {"coordinates":[121.50521999999999,23.84334],"type":"Point"}
}