{
  "type": "Feature",
  "properties": {
    "gn:admin1_code":"4.0",
    "gn:admin2_code":"MIA",
    "gn:admin3_code":"K09",
    "gn:admin4_code":"10005040021.0",
    "gn:asciiname":"Qingcao",
    "gn:country_code":"TW",
    "gn:dem":12,
    "gn:feature_class":"P",
    "gn:feature_code":"PPL",
    "gn:name":"Qingcao",
    "gn:population":0,
    "gn:timezone":"Asia/Taipei",
    "iso:country":"TW",
    "name:und_x_variant":[
        "Cingcao"
    ],
    "name:zho_x_preferred":[
        "\u9752\u8349"
    ],
    "name:zho_x_variant":[
        "Ch\u2019ing-ts\u2019ao"
    ],
    "wof:name":"Qingcao",
    "wof:placetype":"locality"
},
  "geometry": {"coordinates":[120.86866999999999,24.7098],"type":"Point"}
}