{
  "type": "Feature",
  "properties": {
    "gn:admin1_code":"04",
    "gn:admin2_code":"CHA",
    "gn:admin3_code":"N07",
    "gn:admin4_code":"10007120020.0",
    "gn:asciiname":"Shizhangli",
    "gn:country_code":"TW",
    "gn:dem":43,
    "gn:feature_class":"P",
    "gn:feature_code":"PPL",
    "gn:name":"Shizhangli",
    "gn:population":0,
    "gn:timezone":"Asia/Taipei",
    "iso:country":"TW",
    "name:und_x_variant":[
        "Shihjhangli",
        "Shizhangli",
        "Shih-chang-li"
    ],
    "name:zho_x_preferred":[
        "\u5341\u5f35\u7282"
    ],
    "wof:name":"Shizhangli",
    "wof:placetype":"locality"
},
  "geometry": {"coordinates":[120.56967,23.86578],"type":"Point"}
}