{
  "type": "Feature",
  "properties": {
    "gn:admin1_code":"04",
    "gn:admin2_code":"TNN",
    "gn:admin3_code":"R05",
    "gn:admin4_code":"67000050012.0",
    "gn:asciiname":"Ding'an",
    "gn:country_code":"TW",
    "gn:dem":23,
    "gn:feature_class":"P",
    "gn:feature_code":"PPL",
    "gn:name":"Ding\u2019an",
    "gn:population":0,
    "gn:timezone":"Asia/Taipei",
    "iso:country":"TW",
    "name:und_x_variant":[
        "Ting-an"
    ],
    "name:zho_x_preferred":[
        "\u9802\u5b89"
    ],
    "name:zho_x_variant":[
        "Ting-an-ts\u2019un",
        "Ding\u2019an"
    ],
    "wof:name":"Ding'an",
    "wof:placetype":"locality"
},
  "geometry": {"coordinates":[120.35083,23.33083],"type":"Point"}
}