{
  "type": "Feature",
  "properties": {
    "gn:admin1_code":"4.0",
    "gn:admin2_code":"CYQ",
    "gn:admin3_code":"Q16",
    "gn:admin4_code":"10010150013.0",
    "gn:asciiname":"Daxiagu",
    "gn:country_code":"TW",
    "gn:dem":567,
    "gn:feature_class":"P",
    "gn:feature_code":"PPL",
    "gn:name":"Daxiagu",
    "gn:population":0,
    "gn:timezone":"Asia/Taipei",
    "iso:country":"TW",
    "name:und_x_variant":[
        "Dasiagu",
        "Ta-hsia-ku"
    ],
    "name:zho_x_preferred":[
        "\u5927\u5cfd\u8c37"
    ],
    "wof:name":"Daxiagu",
    "wof:placetype":"locality"
},
  "geometry": {"coordinates":[120.64361,23.57222],"type":"Point"}
}