{
  "type": "Feature",
  "properties": {
    "gn:admin1_code":"4.0",
    "gn:admin2_code":"TTT",
    "gn:admin3_code":"V08",
    "gn:admin4_code":"10014080006.0",
    "gn:asciiname":"Dazhuangyue",
    "gn:country_code":"TW",
    "gn:dem":847,
    "gn:feature_class":"P",
    "gn:feature_code":"PPL",
    "gn:name":"Dazhuangyue",
    "gn:population":0,
    "gn:timezone":"Asia/Taipei",
    "iso:country":"TW",
    "name:und_x_variant":[
        "Dajhuangyue",
        "Dazhuangyue"
    ],
    "name:zho_x_preferred":[
        "\u5927\u838a\u8d8a"
    ],
    "name:zho_x_variant":[
        "Ta-chuang-y\u00fceh"
    ],
    "wof:name":"Dazhuangyue",
    "wof:placetype":"locality"
},
  "geometry": {"coordinates":[121.3633,23.24591],"type":"Point"}
}