{
  "type": "Feature",
  "properties": {
    "gn:admin1_code":"4.0",
    "gn:admin2_code":"NAN",
    "gn:admin3_code":"M04",
    "gn:admin4_code":"10008040021.0",
    "gn:asciiname":"Quanzhouliao",
    "gn:country_code":"TW",
    "gn:dem":190,
    "gn:feature_class":"P",
    "gn:feature_code":"PPL",
    "gn:name":"Quanzhouliao",
    "gn:population":0,
    "gn:timezone":"Asia/Taipei",
    "iso:country":"TW",
    "name:und_x_variant":[
        "Cyuanjhouliao",
        "Quanzhouliao"
    ],
    "name:zho_x_preferred":[
        "\u6cc9\u5dde\u5bee"
    ],
    "name:zho_x_variant":[
        "Ch\u2019\u00fcan-chou-liao"
    ],
    "wof:name":"Quanzhouliao",
    "wof:placetype":"locality"
},
  "geometry": {"coordinates":[120.66388999999999,23.70139],"type":"Point"}
}