{
  "type": "Feature",
  "properties": {
    "gn:admin1_code":"4.0",
    "gn:admin2_code":"MIA",
    "gn:admin3_code":"K02",
    "gn:admin4_code":"10005020020.0",
    "gn:asciiname":"Shizilukou",
    "gn:country_code":"TW",
    "gn:dem":85,
    "gn:feature_class":"P",
    "gn:feature_code":"PPL",
    "gn:name":"Shizilukou",
    "gn:population":0,
    "gn:timezone":"Asia/Taipei",
    "iso:country":"TW",
    "name:und_x_variant":[
        "Shihzihlukou"
    ],
    "name:zho_x_preferred":[
        "\u5341\u5b57\u8def\u53e3"
    ],
    "name:zho_x_variant":[
        "Shih-tzu-lu-k\u2019ou"
    ],
    "wof:name":"Shizilukou",
    "wof:placetype":"locality"
},
  "geometry": {"coordinates":[120.68944,24.39389],"type":"Point"}
}