{
  "type": "Feature",
  "properties": {
    "gn:admin1_code":"4.0",
    "gn:admin2_code":"TXG",
    "gn:admin3_code":"B25",
    "gn:admin4_code":"66000250009.0",
    "gn:asciiname":"Hucuo",
    "gn:country_code":"TW",
    "gn:dem":12,
    "gn:feature_class":"P",
    "gn:feature_code":"PPL",
    "gn:name":"Hucuo",
    "gn:population":0,
    "gn:timezone":"Asia/Taipei",
    "iso:country":"TW",
    "name:zho_x_preferred":[
        "\u864e\u539d"
    ],
    "name:zho_x_variant":[
        "Hu-ts\u2019o"
    ],
    "wof:name":"Hucuo",
    "wof:placetype":"locality"
},
  "geometry": {"coordinates":[120.51138,24.21516],"type":"Point"}
}