{
  "type": "Feature",
  "properties": {
    "iso:country":"TW",
    "name:eng_x_preferred":[
        "Guangxing"
    ],
    "name:eng_x_variant":[
        "Guangxing Village"
    ],
    "name:zho_tw_x_preferred":[
        "\u5ee3\u8208\u6751"
    ],
    "qs:name":"\u5ee3\u8208\u6751",
    "qs:name_adm0":"\u81fa\u7063",
    "qs:name_adm1":"\u5c4f\u6771\u7e23",
    "qs:photos":9,
    "qs:photos_1k":2,
    "qs:photos_9k":1,
    "qs:photos_9r":1,
    "qs:photos_all":9,
    "qs:photos_sr":1,
    "qs:placetype":"Town",
    "qs:pop_sr":"0",
    "wof:name":"Guangxing",
    "wof:placetype":"locality"
},
  "geometry": {"coordinates":[120.62644899999999,22.743256],"type":"Point"}
}