{
  "type": "Feature",
  "properties": {
    "gn:admin1_code":"4.0",
    "gn:admin2_code":"CYQ",
    "gn:admin3_code":"Q15",
    "gn:admin4_code":"10010140017.0",
    "gn:asciiname":"Jingbuqi",
    "gn:country_code":"TW",
    "gn:dem":195,
    "gn:feature_class":"P",
    "gn:feature_code":"PPL",
    "gn:name":"Jingbuqi",
    "gn:population":0,
    "gn:timezone":"Asia/Taipei",
    "iso:country":"TW",
    "name:und_x_variant":[
        "Jingbuci"
    ],
    "name:zho_x_preferred":[
        "\u83c1\u57d4\u5d0e"
    ],
    "name:zho_x_variant":[
        "Ching-pu-ch\u2019i"
    ],
    "wof:name":"Jingbuqi",
    "wof:placetype":"locality"
},
  "geometry": {"coordinates":[120.57083,23.52028],"type":"Point"}
}