{
  "type": "Feature",
  "properties": {
    "gn:admin1_code":"4.0",
    "gn:admin2_code":"TPE",
    "gn:admin3_code":"A15",
    "gn:admin4_code":"63000110003.0",
    "gn:asciiname":"Linzikou",
    "gn:country_code":"TW",
    "gn:dem":8,
    "gn:feature_class":"P",
    "gn:feature_code":"PPL",
    "gn:name":"Linzikou",
    "gn:population":0,
    "gn:timezone":"Asia/Taipei",
    "iso:country":"TW",
    "name:und_x_variant":[
        "Linzihkou",
        "Linzikou"
    ],
    "name:zho_x_preferred":[
        "\u6797\u5b50\u53e3"
    ],
    "name:zho_x_variant":[
        "Lin-tzu-k\u2019ou"
    ],
    "wof:name":"Linzikou",
    "wof:placetype":"locality"
},
  "geometry": {"coordinates":[121.53234999999999,25.09621],"type":"Point"}
}