{
  "type": "Feature",
  "properties": {
    "gn:admin1_code":"4.0",
    "gn:admin2_code":"TNN",
    "gn:admin3_code":"R30",
    "gn:admin4_code":"67000300007.0",
    "gn:asciiname":"Longchuanwo",
    "gn:country_code":"TW",
    "gn:dem":305,
    "gn:feature_class":"P",
    "gn:feature_code":"PPL",
    "gn:name":"Longchuanwo",
    "gn:population":0,
    "gn:timezone":"Asia/Taipei",
    "iso:country":"TW",
    "name:zho_x_preferred":[
        "\u9f8d\u8239\u7aa9"
    ],
    "name:zho_x_variant":[
        "Lung-ch\u2019uan-wo"
    ],
    "wof:name":"Longchuanwo",
    "wof:placetype":"locality"
},
  "geometry": {"coordinates":[120.43056,22.94889],"type":"Point"}
}