{
  "type": "Feature",
  "properties": {
    "gn:admin1_code":"2.0",
    "gn:admin2_code":"KHH",
    "gn:admin3_code":"E20",
    "gn:admin4_code":"64000200004.0",
    "gn:asciiname":"Shifeng",
    "gn:country_code":"TW",
    "gn:dem":14,
    "gn:feature_class":"P",
    "gn:feature_code":"PPL",
    "gn:name":"Shifeng",
    "gn:population":0,
    "gn:timezone":"Asia/Taipei",
    "iso:country":"TW",
    "name:und_x_variant":[
        "Shihfong",
        "Shih-feng"
    ],
    "name:zho_x_preferred":[
        "\u4ed5\u8c50"
    ],
    "wof:name":"Shifeng",
    "wof:placetype":"locality"
},
  "geometry": {"coordinates":[120.30889000000001,22.75028],"type":"Point"}
}