{
  "type": "Feature",
  "properties": {
    "gn:admin1_code":"02",
    "gn:admin2_code":"KHH",
    "gn:admin3_code":"E18",
    "gn:admin4_code":"64000180001.0",
    "gn:asciiname":"Niaosong",
    "gn:country_code":"TW",
    "gn:dem":17,
    "gn:feature_class":"P",
    "gn:feature_code":"PPL",
    "gn:name":"Niaosong",
    "gn:population":0,
    "gn:timezone":"Asia/Taipei",
    "iso:country":"TW",
    "name:und_x_variant":[
        "Niao-sung",
        "Niao-sung-chuang",
        "Wu-sung",
        "Niaosong"
    ],
    "name:zho_x_preferred":[
        "\u9ce5\u677e"
    ],
    "wof:name":"Niaosong",
    "wof:placetype":"locality"
},
  "geometry": {"coordinates":[120.36194999999999,22.66128],"type":"Point"}
}