{
  "type": "Feature",
  "properties": {
    "gn:admin1_code":"4.0",
    "gn:admin2_code":"CHA",
    "gn:admin3_code":"N03",
    "gn:admin4_code":"10007030002.0",
    "gn:asciiname":"Xiaocuo",
    "gn:country_code":"TW",
    "gn:dem":13,
    "gn:feature_class":"P",
    "gn:feature_code":"PPL",
    "gn:name":"Xiaocuo",
    "gn:population":0,
    "gn:timezone":"Asia/Taipei",
    "iso:country":"TW",
    "name:und_x_variant":[
        "Siaocuo",
        "Xiaocuo"
    ],
    "name:zho_x_preferred":[
        "\u856d\u539d"
    ],
    "name:zho_x_variant":[
        "Shao-ts\u2019o",
        "Hsiao-ts\u2019o"
    ],
    "wof:name":"Xiaocuo",
    "wof:placetype":"locality"
},
  "geometry": {"coordinates":[120.50472000000001,24.105],"type":"Point"}
}