{
  "type": "Feature",
  "properties": {
    "gn:admin1_code":"4.0",
    "gn:admin2_code":"TXG",
    "gn:admin3_code":"B26",
    "gn:admin4_code":"66000260001.0",
    "gn:asciiname":"Beigoukeng",
    "gn:country_code":"TW",
    "gn:dem":230,
    "gn:feature_class":"P",
    "gn:feature_code":"PPL",
    "gn:name":"Beigoukeng",
    "gn:population":0,
    "gn:timezone":"Asia/Taipei",
    "iso:country":"TW",
    "name:und_x_variant":[
        "\u5317\u6e9d\u5751",
        "Beigoukeng"
    ],
    "name:zho_x_preferred":[
        "Pei-kou-k\u2019eng"
    ],
    "wof:name":"Beigoukeng",
    "wof:placetype":"locality"
},
  "geometry": {"coordinates":[120.72833,24.06519],"type":"Point"}
}