{
  "type": "Feature",
  "properties": {
    "gn:admin1_code":"04",
    "gn:admin2_code":"TNN",
    "gn:admin3_code":"R21",
    "gn:admin4_code":"67000210016.0",
    "gn:asciiname":"Youche",
    "gn:country_code":"TW",
    "gn:dem":8,
    "gn:feature_class":"P",
    "gn:feature_code":"PPL",
    "gn:name":"Youche",
    "gn:population":0,
    "gn:timezone":"Asia/Taipei",
    "iso:country":"TW",
    "name:zho_x_preferred":[
        "\u6cb9\u8eca"
    ],
    "name:zho_x_variant":[
        "Yu-ch\u2019e"
    ],
    "wof:name":"Youche",
    "wof:placetype":"locality"
},
  "geometry": {"coordinates":[120.22611000000001,23.10139],"type":"Point"}
}