{
  "type": "Feature",
  "properties": {
    "gn:admin1_code":"01",
    "gn:admin2_code":"KIN",
    "gn:admin3_code":"W05",
    "gn:admin4_code":"9020050001.0",
    "gn:asciiname":"Shaxi",
    "gn:country_code":"TW",
    "gn:dem":8,
    "gn:feature_class":"P",
    "gn:feature_code":"PPL",
    "gn:name":"Shaxi",
    "gn:population":0,
    "gn:timezone":"Asia/Taipei",
    "iso:country":"TW",
    "name:und_x_variant":[
        "Sha-ch\u2019i",
        "\u7802\u6eaa",
        "Sha-hsi",
        "Shaxi"
    ],
    "wof:name":"Shaxi",
    "wof:placetype":"locality"
},
  "geometry": {"coordinates":[118.21890999999999,24.41083],"type":"Point"}
}