{
  "type": "Feature",
  "properties": {
    "gn:admin1_code":"04",
    "gn:asciiname":"Yugang",
    "gn:country_code":"TW",
    "gn:dem":20,
    "gn:feature_class":"P",
    "gn:feature_code":"PPL",
    "gn:name":"Yugang",
    "gn:population":0,
    "gn:timezone":"Asia/Taipei",
    "iso:country":"TW",
    "name:und_x_variant":[
        "Y\u00fc-chiang",
        "Y\u00fc-kang",
        "Yugang"
    ],
    "wof:name":"Yugang",
    "wof:placetype":"locality"
},
  "geometry": {"coordinates":[121.46666999999999,22.66667],"type":"Point"}
}