{
  "type": "Feature",
  "properties": {
    "gn:admin1_code":"4.0",
    "gn:admin2_code":"HSZ",
    "gn:admin3_code":"J11",
    "gn:admin4_code":"10004100004.0",
    "gn:asciiname":"Dongkengkou",
    "gn:country_code":"TW",
    "gn:dem":38,
    "gn:feature_class":"P",
    "gn:feature_code":"PPL",
    "gn:name":"Dongkengkou",
    "gn:population":0,
    "gn:timezone":"Asia/Taipei",
    "iso:country":"TW",
    "name:zho_x_preferred":[
        "\u6771\u5751\u53e3"
    ],
    "name:zho_x_variant":[
        "Tung-k\u2019eng-k\u2019ou"
    ],
    "wof:name":"Dongkengkou",
    "wof:placetype":"locality"
},
  "geometry": {"coordinates":[120.976,24.73748],"type":"Point"}
}