{
  "type": "Feature",
  "properties": {
    "gn:admin1_code":"4.0",
    "gn:admin2_code":"HSZ",
    "gn:admin3_code":"J05",
    "gn:admin4_code":"10004010015.0",
    "gn:asciiname":"Xinzhuanglun",
    "gn:country_code":"TW",
    "gn:dem":7,
    "gn:feature_class":"P",
    "gn:feature_code":"PPL",
    "gn:name":"Xinzhuanglun",
    "gn:population":0,
    "gn:timezone":"Asia/Taipei",
    "iso:country":"TW",
    "name:und_x_variant":[
        "Sinjhuanglun",
        "Xinzhuanglun",
        "Hsin-chuang-lun"
    ],
    "name:zho_x_preferred":[
        "\u65b0\u5e84\u5d19"
    ],
    "wof:name":"Xinzhuanglun",
    "wof:placetype":"locality"
},
  "geometry": {"coordinates":[120.94777999999999,24.84333],"type":"Point"}
}