{
  "type": "Feature",
  "properties": {
    "gn:admin1_code":"04",
    "gn:admin2_code":"TTT",
    "gn:admin3_code":"V06",
    "gn:admin4_code":"10014090003.0",
    "gn:asciiname":"Beikeng",
    "gn:country_code":"TW",
    "gn:dem":71,
    "gn:feature_class":"P",
    "gn:feature_code":"PPL",
    "gn:name":"Beikeng",
    "gn:population":0,
    "gn:timezone":"Asia/Taipei",
    "iso:country":"TW",
    "name:zho_x_preferred":[
        "\u5317\u5751"
    ],
    "name:zho_x_variant":[
        "Pei-k\u2019eng"
    ],
    "wof:name":"Beikeng",
    "wof:placetype":"locality"
},
  "geometry": {"coordinates":[121.02249999999999,22.65556],"type":"Point"}
}