{
  "type": "Feature",
  "properties": {
    "gn:admin1_code":"4.0",
    "gn:admin2_code":"NAN",
    "gn:admin3_code":"M13",
    "gn:admin4_code":"10008130013.0",
    "gn:asciiname":"Gegeyuan",
    "gn:country_code":"TW",
    "gn:dem":1202,
    "gn:feature_class":"P",
    "gn:feature_code":"PPL",
    "gn:name":"Gegeyuan",
    "gn:population":0,
    "gn:timezone":"Asia/Taipei",
    "iso:country":"TW",
    "name:zho_x_preferred":[
        "\u54e5\u54e5\u539f"
    ],
    "name:zho_x_variant":[
        "Ko-ko-y\u00fcan"
    ],
    "wof:name":"Gegeyuan",
    "wof:placetype":"locality"
},
  "geometry": {"coordinates":[121.08306,23.93278],"type":"Point"}
}