{
  "type": "Feature",
  "properties": {
    "gn:admin1_code":"4.0",
    "gn:admin2_code":"TNN",
    "gn:admin3_code":"R26",
    "gn:admin4_code":"67000260007.0",
    "gn:asciiname":"Kekekeng",
    "gn:country_code":"TW",
    "gn:dem":95,
    "gn:feature_class":"P",
    "gn:feature_code":"PPL",
    "gn:name":"Kekekeng",
    "gn:population":0,
    "gn:timezone":"Asia/Taipei",
    "iso:country":"TW",
    "name:zho_x_preferred":[
        "Ho-Ch\u2019ueh-K\u2019eng"
    ],
    "name:zho_x_variant":[
        "Ho-k\u2019o-k\u2019eng",
        "\u86b5\u6bbc\u5751",
        "K\u2019o-k\u2019o-k\u2019eng"
    ],
    "wof:name":"Kekekeng",
    "wof:placetype":"locality"
},
  "geometry": {"coordinates":[120.38491999999999,23.03332],"type":"Point"}
}