{
  "type": "Feature",
  "properties": {
    "gn:admin1_code":"04",
    "gn:admin2_code":"TAO",
    "gn:admin3_code":"H06",
    "gn:admin4_code":"68000060011.0",
    "gn:asciiname":"Bazilin",
    "gn:country_code":"TW",
    "gn:dem":32,
    "gn:feature_class":"P",
    "gn:feature_code":"PPL",
    "gn:name":"Bazilin",
    "gn:population":0,
    "gn:timezone":"Asia/Taipei",
    "iso:country":"TW",
    "name:und_x_variant":[
        "Bazihlin",
        "Bazilin",
        "Pa-tzu-lin"
    ],
    "name:zho_x_preferred":[
        "\u62d4\u5b50\u6797"
    ],
    "wof:name":"Bazilin",
    "wof:placetype":"locality"
},
  "geometry": {"coordinates":[121.26752999999999,25.0745],"type":"Point"}
}