{
  "type": "Feature",
  "properties": {
    "gn:admin1_code":"4.0",
    "gn:admin2_code":"MIA",
    "gn:admin3_code":"K12",
    "gn:admin4_code":"10005060013.0",
    "gn:asciiname":"Baisan",
    "gn:country_code":"TW",
    "gn:dem":39,
    "gn:feature_class":"P",
    "gn:feature_code":"PPL",
    "gn:name":"Baisan",
    "gn:population":0,
    "gn:timezone":"Asia/Taipei",
    "iso:country":"TW",
    "name:und_x_variant":[
        "Pai-san"
    ],
    "name:zho_x_preferred":[
        "\u767e\u4e09"
    ],
    "wof:name":"Baisan",
    "wof:placetype":"locality"
},
  "geometry": {"coordinates":[120.80840000000001,24.64044],"type":"Point"}
}