{
  "type": "Feature",
  "properties": {
    "gn:admin1_code":"4.0",
    "gn:admin2_code":"TXG",
    "gn:admin3_code":"B19",
    "gn:admin4_code":"66000190002.0",
    "gn:asciiname":"Xinsancun",
    "gn:country_code":"TW",
    "gn:dem":490,
    "gn:feature_class":"P",
    "gn:feature_code":"PPL",
    "gn:name":"Xinsancun",
    "gn:population":0,
    "gn:timezone":"Asia/Taipei",
    "iso:country":"TW",
    "name:und_x_variant":[
        "Sinsancun",
        "Xinsancun"
    ],
    "name:zho_x_preferred":[
        "\u65b0\u4e09\u6751"
    ],
    "name:zho_x_variant":[
        "Hsin-san-ts\u2019un"
    ],
    "wof:name":"Xinsancun",
    "wof:placetype":"locality"
},
  "geometry": {"coordinates":[120.8075,24.2218],"type":"Point"}
}