{
  "type": "Feature",
  "properties": {
    "gn:admin1_code":"04",
    "gn:admin2_code":"TNN",
    "gn:admin3_code":"R04",
    "gn:admin4_code":"67000040007.0",
    "gn:asciiname":"Wencuobu",
    "gn:country_code":"TW",
    "gn:dem":15,
    "gn:feature_class":"P",
    "gn:feature_code":"PPL",
    "gn:name":"Wencuobu",
    "gn:population":0,
    "gn:timezone":"Asia/Taipei",
    "iso:country":"TW",
    "name:und_x_variant":[
        "Wuncuobu"
    ],
    "name:zho_x_preferred":[
        "\u6eab\u539d\u5ecd"
    ],
    "name:zho_x_variant":[
        "Wen-ts\u2019o-pu"
    ],
    "wof:name":"Wencuobu",
    "wof:placetype":"locality"
},
  "geometry": {"coordinates":[120.33583,23.27083],"type":"Point"}
}