{
  "type": "Feature",
  "properties": {
    "gn:admin1_code":"4.0",
    "gn:admin2_code":"TAO",
    "gn:admin3_code":"H13",
    "gn:admin4_code":"68000130008.0",
    "gn:asciiname":"Xinxing",
    "gn:country_code":"TW",
    "gn:dem":1157,
    "gn:feature_class":"P",
    "gn:feature_code":"PPL",
    "gn:name":"Xinxing",
    "gn:population":0,
    "gn:timezone":"Asia/Taipei",
    "iso:country":"TW",
    "name:und_x_variant":[
        "Ka-la-ho-she",
        "Ka-la-ho",
        "Sinsing",
        "Xinxing",
        "Hsin-hsing"
    ],
    "name:zho_x_preferred":[
        "K\u2019o-la-ho-she"
    ],
    "name:zho_x_variant":[
        "K\u2019o-la-ho",
        "\u65b0\u8208",
        "K\u2019a-la"
    ],
    "wof:name":"Xinxing",
    "wof:placetype":"locality"
},
  "geometry": {"coordinates":[121.405,24.6375],"type":"Point"}
}