{
  "type": "Feature",
  "properties": {
    "gn:admin1_code":"3.0",
    "gn:admin2_code":"TPQ",
    "gn:admin3_code":"F02",
    "gn:admin4_code":"65000170005.0",
    "gn:asciiname":"Zhonghutou",
    "gn:country_code":"TW",
    "gn:dem":252,
    "gn:feature_class":"P",
    "gn:feature_code":"PPL",
    "gn:name":"Zhonghutou",
    "gn:population":0,
    "gn:timezone":"Asia/Taipei",
    "iso:country":"TW",
    "name:und_x_variant":[
        "Jhonghutou",
        "Zhonghutou"
    ],
    "name:zho_x_preferred":[
        "\u4e2d\u6e56\u982d"
    ],
    "name:zho_x_variant":[
        "Chung-t\u2019ou-hu",
        "Chung-hu-t\u2019ou"
    ],
    "wof:name":"Zhonghutou",
    "wof:placetype":"locality"
},
  "geometry": {"coordinates":[121.38609,25.08368],"type":"Point"}
}