{
  "type": "Feature",
  "properties": {
    "gn:admin1_code":"4.0",
    "gn:admin2_code":"HSZ",
    "gn:admin3_code":"J10",
    "gn:admin4_code":"10004070010.0",
    "gn:asciiname":"Xionglin",
    "gn:country_code":"TW",
    "gn:dem":97,
    "gn:feature_class":"P",
    "gn:feature_code":"PPL",
    "gn:name":"Xionglin",
    "gn:population":0,
    "gn:timezone":"Asia/Taipei",
    "iso:country":"TW",
    "name:hak_x_preferred":[
        "Khi\u00fbng-l\u00ecm-hi\u00f4ng"
    ],
    "name:jpn_x_preferred":[
        "\u30ad\u30e5\u30a6\u6797\u90f7"
    ],
    "name:kor_x_preferred":[
        "\ucda9\ub9b0\ud5a5"
    ],
    "name:und_x_variant":[
        "Shiung-Lin",
        "Xionglin",
        "Syonglin",
        "Hsiung-lin"
    ],
    "name:vie_x_preferred":[
        "Khung L\u00e2m"
    ],
    "name:zho_x_preferred":[
        "Ch\u2019iung-lin"
    ],
    "name:zho_x_variant":[
        "\u828e\u6797",
        "\u828e\u6797\u9109"
    ],
    "wof:name":"Xionglin",
    "wof:placetype":"locality"
},
  "geometry": {"coordinates":[121.07917,24.77528],"type":"Point"}
}