{
  "type": "Feature",
  "properties": {
    "gn:admin1_code":"4.0",
    "gn:admin2_code":"HSZ",
    "gn:admin3_code":"J10",
    "gn:admin4_code":"10004070010.0",
    "gn:asciiname":"Xionglin",
    "gn:country_code":"TW",
    "gn:dem":97,
    "gn:feature_class":"P",
    "gn:feature_code":"PPL",
    "gn:name":"Xionglin",
    "gn:population":0,
    "gn:timezone":"Asia/Taipei",
    "iso:country":"TW",
    "name:und_x_variant":[
        "Shiung-Lin",
        "Xionglin",
        "Syonglin",
        "Hsiung-lin"
    ],
    "name:zho_x_preferred":[
        "Ch\u2019iung-lin"
    ],
    "name:zho_x_variant":[
        "\u828e\u6797"
    ],
    "wof:name":"Xionglin",
    "wof:placetype":"locality"
},
  "geometry": {"coordinates":[121.07917,24.77528],"type":"Point"}
}