{
  "type": "Feature",
  "properties": {
    "gn:admin1_code":"4.0",
    "gn:admin2_code":"TNN",
    "gn:admin3_code":"R24",
    "gn:admin4_code":"67000240002.0",
    "gn:asciiname":"Zhuzise",
    "gn:country_code":"TW",
    "gn:dem":368,
    "gn:feature_class":"P",
    "gn:feature_code":"PPL",
    "gn:name":"Zhuzise",
    "gn:population":0,
    "gn:timezone":"Asia/Taipei",
    "iso:country":"TW",
    "name:und_x_variant":[
        "Jhuzihse",
        "Chu-tzu-se"
    ],
    "name:zho_x_preferred":[
        "\u7af9\u4ed4\u573e"
    ],
    "name:zho_x_variant":[
        "Chu-tzu-p\u2019o"
    ],
    "wof:name":"Zhuzise",
    "wof:placetype":"locality"
},
  "geometry": {"coordinates":[120.54555999999999,23.17889],"type":"Point"}
}