{
  "type": "Feature",
  "properties": {
    "gn:admin1_code":"4.0",
    "gn:admin2_code":"TTT",
    "gn:admin3_code":"V07",
    "gn:admin4_code":"10014070003.0",
    "gn:asciiname":"Jinzun",
    "gn:country_code":"TW",
    "gn:dem":66,
    "gn:feature_class":"P",
    "gn:feature_code":"PPL",
    "gn:name":"Jinzun",
    "gn:population":0,
    "gn:timezone":"Asia/Taipei",
    "iso:country":"TW",
    "name:und_x_variant":[
        "Chin-tsun"
    ],
    "name:zho_x_preferred":[
        "\u91d1\u6a3d"
    ],
    "wof:name":"Jinzun",
    "wof:placetype":"locality"
},
  "geometry": {"coordinates":[121.28972,22.95889],"type":"Point"}
}