{
  "type": "Feature",
  "properties": {
    "iso:country":"TW",
    "label:eng_x_preferred_longname":[
        "Taipei Township"
    ],
    "label:eng_x_preferred_placetype":[
        "township"
    ],
    "name:ces_x_preferred":[
        "Okres Tchaj-pej"
    ],
    "name:cym_x_preferred":[
        "Sir Taipei"
    ],
    "name:eng_x_preferred":[
        "Taipei"
    ],
    "name:epo_x_preferred":[
        "Kantono Tajpeo"
    ],
    "name:jpn_x_preferred":[
        "\u53f0\u5317\u770c"
    ],
    "name:lzh_x_preferred":[
        "\u81fa\u5317\u7e23"
    ],
    "name:rus_x_preferred":[
        "\u0422\u0430\u0439\u0431\u044d\u0439"
    ],
    "name:swe_x_preferred":[
        "Taipeis l\u00e4n"
    ],
    "name:tha_x_preferred":[
        "\u0e40\u0e17\u0e28\u0e21\u0e13\u0e11\u0e25\u0e44\u0e17\u0e40\u0e1b"
    ],
    "name:yue_x_preferred":[
        "\u81fa\u5317\u7e23"
    ],
    "name:zho_x_preferred":[
        "\u81fa\u5317\u7e23"
    ],
    "name:zho_x_variant":[
        "\u6cf0\u5c71\u9109"
    ],
    "qs:name":"\u6cf0\u5c71\u9109",
    "qs:name_adm0":"\u81fa\u7063",
    "qs:name_adm1":"\u65b0\u5317\u5e02",
    "qs:photos":201,
    "qs:photos_1k":41,
    "qs:photos_9k":4,
    "qs:photos_9r":6,
    "qs:photos_all":886,
    "qs:photos_sr":4,
    "qs:placetype":"County",
    "qs:pop_sr":"0",
    "wd:wordcount":161,
    "wof:name":"Taipei",
    "wof:placetype":"county"
},
  "geometry": {"coordinates":[121.453594,25.046705],"type":"Point"}
}