{
  "type": "Feature",
  "properties": {
    "gn:admin1_code":"4.0",
    "gn:admin2_code":"NAN",
    "gn:admin3_code":"M02",
    "gn:admin4_code":"10008020028.0",
    "gn:asciiname":"Shipankeng",
    "gn:country_code":"TW",
    "gn:dem":827,
    "gn:feature_class":"P",
    "gn:feature_code":"PPL",
    "gn:name":"Shipankeng",
    "gn:population":0,
    "gn:timezone":"Asia/Taipei",
    "iso:country":"TW",
    "name:und_x_variant":[
        "Shihpankeng"
    ],
    "name:zho_x_preferred":[
        "\u77f3\u76e4\u5751"
    ],
    "name:zho_x_variant":[
        "Shih-p\u2019an-k\u2019eng"
    ],
    "wof:name":"Shipankeng",
    "wof:placetype":"locality"
},
  "geometry": {"coordinates":[121.02388999999999,23.96194],"type":"Point"}
}