{
  "type": "Feature",
  "properties": {
    "gn:admin1_code":"4.0",
    "gn:admin2_code":"TTT",
    "gn:admin3_code":"V13",
    "gn:admin4_code":"10014120002.0",
    "gn:asciiname":"Xiama",
    "gn:country_code":"TW",
    "gn:dem":742,
    "gn:feature_class":"P",
    "gn:feature_code":"PPL",
    "gn:name":"Xiama",
    "gn:population":0,
    "gn:timezone":"Asia/Taipei",
    "iso:country":"TW",
    "name:und_x_variant":[
        "Siama",
        "Hsia-ma"
    ],
    "name:zho_x_preferred":[
        "\u4e0b\u99ac"
    ],
    "wof:name":"Xiama",
    "wof:placetype":"locality"
},
  "geometry": {"coordinates":[121.06444,23.15528],"type":"Point"}
}