{
  "type": "Feature",
  "properties": {
    "gn:admin1_code":"4.0",
    "gn:admin2_code":"TXG",
    "gn:admin3_code":"B21",
    "gn:admin4_code":"66000210009.0",
    "gn:asciiname":"Xincuozi",
    "gn:country_code":"TW",
    "gn:dem":118,
    "gn:feature_class":"P",
    "gn:feature_code":"PPL",
    "gn:name":"Xincuozi",
    "gn:population":0,
    "gn:timezone":"Asia/Taipei",
    "iso:country":"TW",
    "name:und_x_variant":[
        "Sincuozih"
    ],
    "name:zho_x_preferred":[
        "\u65b0\u539d\u4ed4"
    ],
    "name:zho_x_variant":[
        "Hsin-ts\u2019o-tzu"
    ],
    "wof:name":"Xincuozi",
    "wof:placetype":"locality"
},
  "geometry": {"coordinates":[120.66222,24.35],"type":"Point"}
}