{
  "type": "Feature",
  "properties": {
    "gn:admin1_code":"2.0",
    "gn:admin2_code":"KHH",
    "gn:admin3_code":"E19",
    "gn:admin4_code":"64000190015.0",
    "gn:asciiname":"Shanliao",
    "gn:country_code":"TW",
    "gn:dem":41,
    "gn:feature_class":"P",
    "gn:feature_code":"PPL",
    "gn:name":"Shanliao",
    "gn:population":0,
    "gn:timezone":"Asia/Taipei",
    "iso:country":"TW",
    "name:und_x_variant":[
        "Shan-hsi",
        "Shan-liao"
    ],
    "name:zho_x_preferred":[
        "\u5c71\u5bee"
    ],
    "wof:name":"Shanliao",
    "wof:placetype":"locality"
},
  "geometry": {"coordinates":[120.34111,22.82944],"type":"Point"}
}