{
  "type": "Feature",
  "properties": {
    "gn:admin1_code":"04",
    "gn:admin2_code":"HSZ",
    "gn:admin3_code":"J03",
    "gn:admin4_code":"10004040020.0",
    "gn:asciiname":"Waziku",
    "gn:country_code":"TW",
    "gn:dem":162,
    "gn:feature_class":"P",
    "gn:feature_code":"PPL",
    "gn:name":"Waziku",
    "gn:population":0,
    "gn:timezone":"Asia/Taipei",
    "iso:country":"TW",
    "name:und_x_variant":[
        "Wazihku"
    ],
    "name:zho_x_preferred":[
        "\u86d9\u5b50\u7a9f"
    ],
    "name:zho_x_variant":[
        "Wa-k\u2019u",
        "Wa-tzu-k\u2019u"
    ],
    "wof:name":"Waziku",
    "wof:placetype":"locality"
},
  "geometry": {"coordinates":[121.17333000000001,24.75417],"type":"Point"}
}