{
  "type": "Feature",
  "properties": {
    "gn:admin1_code":"4.0",
    "gn:admin2_code":"PIF",
    "gn:admin3_code":"T17",
    "gn:admin4_code":"10013170004.0",
    "gn:asciiname":"Kan-t'ang-ts'un",
    "gn:cc2":"TW",
    "gn:country_code":"TW",
    "gn:dem":3,
    "gn:feature_class":"P",
    "gn:feature_code":"PPL",
    "gn:name":"Kan-t'ang-ts'un",
    "gn:population":0,
    "gn:timezone":"Asia/Taipei",
    "iso:country":"TW",
    "name:und_x_variant":[
        "Kan-t'ang-li"
    ],
    "wof:name":"Kan-t'ang-ts'un",
    "wof:placetype":"locality"
},
  "geometry": {"coordinates":[120.46666999999999,22.53333],"type":"Point"}
}