{
  "type": "Feature",
  "properties": {
    "gn:admin1_code":"04",
    "gn:admin2_code":"TXG",
    "gn:admin3_code":"B09",
    "gn:admin4_code":"66000090024.0",
    "gn:asciiname":"Dongshi",
    "gn:country_code":"TW",
    "gn:dem":211,
    "gn:feature_class":"P",
    "gn:feature_code":"PPL",
    "gn:name":"Dongshi",
    "gn:population":0,
    "gn:timezone":"Asia/Taipei",
    "iso:country":"TW",
    "name:deu_x_preferred":[
        "Dongshi"
    ],
    "name:kor_x_preferred":[
        "\ub465\uc2a4 \ud5a5"
    ],
    "name:und_x_variant":[
        "Dongshih",
        "Tung-shih"
    ],
    "name:zho_x_preferred":[
        "\u6771\u52e2"
    ],
    "wof:name":"Dongshi",
    "wof:placetype":"locality"
},
  "geometry": {"coordinates":[120.72750000000001,24.2325],"type":"Point"}
}