{
  "type": "Feature",
  "properties": {
    "iso:country":"TW",
    "qs:name":"\u7f85\u6d6e\u6751",
    "qs:name_adm0":"\u81fa\u7063",
    "qs:name_adm1":"\u6843\u5712\u7e23",
    "qs:photos":82,
    "qs:photos_1k":17,
    "qs:photos_9k":1,
    "qs:photos_9r":3,
    "qs:photos_all":82,
    "qs:photos_sr":3,
    "qs:placetype":"Town",
    "qs:pop_sr":"0",
    "wof:name":"\u7f85\u6d6e\u6751",
    "wof:placetype":"locality"
},
  "geometry": {"coordinates":[121.350854,24.75307],"type":"Point"}
}