{
  "type": "Feature",
  "properties": {
    "gn:admin1_code":"4.0",
    "gn:admin2_code":"NAN",
    "gn:admin3_code":"M04",
    "gn:admin4_code":"10008040023.0",
    "gn:asciiname":"Ruizhu",
    "gn:country_code":"TW",
    "gn:dem":215,
    "gn:feature_class":"P",
    "gn:feature_code":"PPL",
    "gn:name":"Ruizhu",
    "gn:population":0,
    "gn:timezone":"Asia/Taipei",
    "iso:country":"TW",
    "name:und_x_variant":[
        "Rueijhu",
        "Ruizhu",
        "Jui-chu"
    ],
    "name:zho_x_preferred":[
        "\u745e\u7af9"
    ],
    "name:zho_x_variant":[
        "Tung-shih-k\u2019eng"
    ],
    "wof:name":"Ruizhu",
    "wof:placetype":"locality"
},
  "geometry": {"coordinates":[120.66500000000001,23.66278],"type":"Point"}
}