{
  "type": "Feature",
  "properties": {
    "gn:admin1_code":"4.0",
    "gn:admin2_code":"TAO",
    "gn:admin3_code":"H10",
    "gn:admin4_code":"68000100013.0",
    "gn:asciiname":"Xinjie",
    "gn:country_code":"TW",
    "gn:dem":170,
    "gn:feature_class":"P",
    "gn:feature_code":"PPL",
    "gn:name":"Xinjie",
    "gn:population":0,
    "gn:timezone":"Asia/Taipei",
    "iso:country":"TW",
    "name:und_x_variant":[
        "Shui-wei",
        "Hsin-chieh",
        "Xinjie"
    ],
    "wof:name":"Xinjie",
    "wof:placetype":"locality"
},
  "geometry": {"coordinates":[121.21666999999999,24.91667],"type":"Point"}
}