{
  "type": "Feature",
  "properties": {
    "gn:admin1_code":"4.0",
    "gn:admin2_code":"TNN",
    "gn:admin3_code":"R11",
    "gn:admin4_code":"67000110007.0",
    "gn:asciiname":"Dashanjiao",
    "gn:country_code":"TW",
    "gn:dem":75,
    "gn:feature_class":"P",
    "gn:feature_code":"PPL",
    "gn:name":"Dashanjiao",
    "gn:population":0,
    "gn:timezone":"Asia/Taipei",
    "iso:country":"TW",
    "name:und_x_variant":[
        "Ta-shan-chiao"
    ],
    "name:zho_x_preferred":[
        "\u5927\u5c71\u8173"
    ],
    "wof:name":"Dashanjiao",
    "wof:placetype":"locality"
},
  "geometry": {"coordinates":[120.38148,23.15516],"type":"Point"}
}