{
  "type": "Feature",
  "properties": {
    "gn:admin1_code":"4.0",
    "gn:admin2_code":"MIA",
    "gn:admin3_code":"K12",
    "gn:admin4_code":"10005060014.0",
    "gn:asciiname":"Xincuo",
    "gn:country_code":"TW",
    "gn:dem":12,
    "gn:feature_class":"P",
    "gn:feature_code":"PPL",
    "gn:name":"Xincuo",
    "gn:population":0,
    "gn:timezone":"Asia/Taipei",
    "iso:country":"TW",
    "name:und_x_variant":[
        "Sincuo",
        "Xincuo"
    ],
    "name:zho_x_preferred":[
        "\u65b0\u539d"
    ],
    "name:zho_x_variant":[
        "Hsin-ts\u2019o"
    ],
    "wof:name":"Xincuo",
    "wof:placetype":"locality"
},
  "geometry": {"coordinates":[120.82271,24.66588],"type":"Point"}
}