{
  "type": "Feature",
  "properties": {
    "iso:country":"TW",
    "qs:name":"\u82f1\u4ec1\u91cc",
    "qs:name_adm0":"\u81fa\u7063",
    "qs:name_adm1":"\u57fa\u9686\u5e02",
    "qs:photos":27,
    "qs:photos_1k":5,
    "qs:photos_9k":1,
    "qs:photos_9r":2,
    "qs:photos_all":27,
    "qs:photos_sr":2,
    "qs:placetype":"Suburb",
    "qs:pop_sr":"0",
    "wof:name":"\u82f1\u4ec1\u91cc",
    "wof:placetype":"neighbourhood"
},
  "geometry": {"coordinates":[121.74490900000001,25.112555],"type":"Point"}
}