{
  "type": "Feature",
  "properties": {
    "gn:admin1_code":"4.0",
    "gn:admin2_code":"CYQ",
    "gn:admin3_code":"Q07",
    "gn:admin4_code":"10010070010.0",
    "gn:asciiname":"Xidiliao",
    "gn:country_code":"TW",
    "gn:dem":17,
    "gn:feature_class":"P",
    "gn:feature_code":"PPL",
    "gn:name":"Xidiliao",
    "gn:population":0,
    "gn:timezone":"Asia/Taipei",
    "iso:country":"TW",
    "name:und_x_variant":[
        "Sidiliao",
        "Xidiliao",
        "Hsi-ti-liao"
    ],
    "name:zho_x_preferred":[
        "\u6eaa\u5e95\u5bee"
    ],
    "wof:name":"Xidiliao",
    "wof:placetype":"locality"
},
  "geometry": {"coordinates":[120.3421,23.58226],"type":"Point"}
}