{
  "type": "Feature",
  "properties": {
    "gn:admin1_code":"04",
    "gn:admin2_code":"HUA",
    "gn:admin3_code":"U11",
    "gn:admin4_code":"10015110005.0",
    "gn:asciiname":"Tongmen",
    "gn:country_code":"TW",
    "gn:dem":171,
    "gn:feature_class":"P",
    "gn:feature_code":"PPL",
    "gn:name":"Tongmen",
    "gn:population":0,
    "gn:timezone":"Asia/Taipei",
    "iso:country":"TW",
    "name:zho_x_preferred":[
        "T\u2019ung-men-ts\u2019un"
    ],
    "name:zho_x_variant":[
        "\u9285\u9580",
        "T\u2019ung-men"
    ],
    "wof:name":"Tongmen",
    "wof:placetype":"locality"
},
  "geometry": {"coordinates":[121.49369,23.96478],"type":"Point"}
}