{
  "type": "Feature",
  "properties": {
    "gn:admin1_code":"04",
    "gn:admin2_code":"TTT",
    "gn:admin3_code":"V16",
    "gn:admin4_code":"10014160004.0",
    "gn:asciiname":"Yeyou",
    "gn:country_code":"TW",
    "gn:dem":18,
    "gn:feature_class":"P",
    "gn:feature_code":"PPL",
    "gn:name":"Yeyou",
    "gn:population":0,
    "gn:timezone":"Asia/Taipei",
    "iso:country":"TW",
    "name:und_x_variant":[
        "Ya-you",
        "Yen-yu",
        "Ya-yu",
        "Yeyou",
        "Yeh-yu"
    ],
    "name:zho_x_preferred":[
        "\u6930\u6cb9"
    ],
    "wof:name":"Yeyou",
    "wof:placetype":"locality"
},
  "geometry": {"coordinates":[121.51278000000001,22.05083],"type":"Point"}
}