{
  "type": "Feature",
  "properties": {
    "gn:admin1_code":"4.0",
    "gn:admin2_code":"NAN",
    "gn:admin3_code":"M05",
    "gn:admin4_code":"10008050010.0",
    "gn:asciiname":"Taipingshan",
    "gn:country_code":"TW",
    "gn:dem":396,
    "gn:feature_class":"P",
    "gn:feature_code":"PPL",
    "gn:name":"Taipingshan",
    "gn:population":0,
    "gn:timezone":"Asia/Taipei",
    "iso:country":"TW",
    "name:zho_x_preferred":[
        "\u592a\u5e73\u5c71"
    ],
    "name:zho_x_variant":[
        "T\u2019ai-p\u2019ing-shan"
    ],
    "wof:name":"Taipingshan",
    "wof:placetype":"locality"
},
  "geometry": {"coordinates":[120.82008,23.83481],"type":"Point"}
}