{
  "type": "Feature",
  "properties": {
    "gn:admin1_code":"4.0",
    "gn:admin2_code":"TAO",
    "gn:admin3_code":"H01",
    "gn:admin4_code":"68000010035.0",
    "gn:asciiname":"Zhonglu",
    "gn:country_code":"TW",
    "gn:dem":99,
    "gn:feature_class":"P",
    "gn:feature_code":"PPL",
    "gn:name":"Zhonglu",
    "gn:population":0,
    "gn:timezone":"Asia/Taipei",
    "iso:country":"TW",
    "name:und_x_variant":[
        "Chung-lu"
    ],
    "wof:name":"Zhonglu",
    "wof:placetype":"locality"
},
  "geometry": {"coordinates":[121.26667,24.98333],"type":"Point"}
}