{
  "type": "Feature",
  "properties": {
    "gn:admin1_code":"4.0",
    "gn:admin2_code":"TAO",
    "gn:admin3_code":"H11",
    "gn:admin4_code":"68000110002.0",
    "gn:asciiname":"Dinghoucuo",
    "gn:country_code":"TW",
    "gn:dem":79,
    "gn:feature_class":"P",
    "gn:feature_code":"PPL",
    "gn:name":"Dinghoucuo",
    "gn:population":0,
    "gn:timezone":"Asia/Taipei",
    "iso:country":"TW",
    "name:zho_x_preferred":[
        "\u9802\u5f8c\u539d"
    ],
    "name:zho_x_variant":[
        "Ting-hou-ts\u2019o"
    ],
    "wof:name":"Dinghoucuo",
    "wof:placetype":"locality"
},
  "geometry": {"coordinates":[121.09833,24.97583],"type":"Point"}
}