{
  "type": "Feature",
  "properties": {
    "gn:admin1_code":"04",
    "gn:admin2_code":"TXG",
    "gn:admin3_code":"B18",
    "gn:admin4_code":"66000180015.0",
    "gn:asciiname":"Shangfengshujiao",
    "gn:country_code":"TW",
    "gn:dem":157,
    "gn:feature_class":"P",
    "gn:feature_code":"PPL",
    "gn:name":"Shangfengshujiao",
    "gn:population":0,
    "gn:timezone":"Asia/Taipei",
    "iso:country":"TW",
    "name:und_x_variant":[
        "Shang-feng",
        "Shang-feng-ts\u2019un",
        "\u4e0a\u6953\u6a39\u811a",
        "Shangfongshujiao",
        "Shangfengshujiao",
        "Shang-feng-shu-chiao"
    ],
    "wof:name":"Shangfengshujiao",
    "wof:placetype":"locality"
},
  "geometry": {"coordinates":[120.65938,24.23225],"type":"Point"}
}