{
  "type": "Feature",
  "properties": {
    "gn:admin1_code":"04",
    "gn:admin2_code":"PIF",
    "gn:admin3_code":"T05",
    "gn:admin4_code":"10013050010.0",
    "gn:asciiname":"Tiancuo",
    "gn:country_code":"TW",
    "gn:dem":13,
    "gn:feature_class":"P",
    "gn:feature_code":"PPL",
    "gn:name":"Tiancuo",
    "gn:population":0,
    "gn:timezone":"Asia/Taipei",
    "iso:country":"TW",
    "name:und_x_variant":[
        "\u7530\u539d",
        "Tiancuo"
    ],
    "name:zho_x_preferred":[
        "T\u2019ien-ts\u2019o-ts\u2019un"
    ],
    "name:zho_x_variant":[
        "T\u2019ien-ts\u2019o",
        "\u7530\u539d"
    ],
    "wof:name":"Tiancuo",
    "wof:placetype":"locality"
},
  "geometry": {"coordinates":[120.46939999999999,22.5897],"type":"Point"}
}