{
  "type": "Feature",
  "properties": {
    "gn:admin1_code":"04",
    "gn:admin2_code":"CHA",
    "gn:admin3_code":"N05",
    "gn:admin4_code":"10007100016.0",
    "gn:asciiname":"Dabucuo",
    "gn:country_code":"TW",
    "gn:dem":23,
    "gn:feature_class":"P",
    "gn:feature_code":"PPL",
    "gn:name":"Dabucuo",
    "gn:population":0,
    "gn:timezone":"Asia/Taipei",
    "iso:country":"TW",
    "name:zho_x_preferred":[
        "\u5927\u57d4\u539d"
    ],
    "name:zho_x_variant":[
        "Ta-pu-ts\u2019o"
    ],
    "wof:name":"Dabucuo",
    "wof:placetype":"locality"
},
  "geometry": {"coordinates":[120.55286,23.97462],"type":"Point"}
}