{
  "type": "Feature",
  "properties": {
    "gn:admin1_code":"4.0",
    "gn:admin2_code":"TNN",
    "gn:admin3_code":"R14",
    "gn:admin4_code":"67000150017.0",
    "gn:asciiname":"Shalunliao",
    "gn:country_code":"TW",
    "gn:dem":2,
    "gn:feature_class":"P",
    "gn:feature_code":"PPL",
    "gn:name":"Shalunliao",
    "gn:population":0,
    "gn:timezone":"Asia/Taipei",
    "iso:country":"TW",
    "name:und_x_variant":[
        "Shan-lun-liao",
        "Sha-lun-liao"
    ],
    "name:zho_x_preferred":[
        "\u6c99\u5d19\u5bee"
    ],
    "wof:name":"Shalunliao",
    "wof:placetype":"locality"
},
  "geometry": {"coordinates":[120.11,23.14722],"type":"Point"}
}