{
  "type": "Feature",
  "properties": {
    "gn:admin1_code":"04",
    "gn:admin2_code":"HSZ",
    "gn:admin3_code":"J14",
    "gn:admin4_code":"10004120006.0",
    "gn:asciiname":"Taiping",
    "gn:country_code":"TW",
    "gn:dem":765,
    "gn:feature_class":"P",
    "gn:feature_code":"PPL",
    "gn:name":"Taiping",
    "gn:population":0,
    "gn:timezone":"Asia/Taipei",
    "iso:country":"TW",
    "name:ceb_x_preferred":[
        "Taiping"
    ],
    "name:deu_x_preferred":[
        "Taiping"
    ],
    "name:fra_x_preferred":[
        "Taiping"
    ],
    "name:ind_x_preferred":[
        "Taiping"
    ],
    "name:msa_x_preferred":[
        "Taiping"
    ],
    "name:nld_x_preferred":[
        "Taiping"
    ],
    "name:rus_x_preferred":[
        "\u0422\u0430\u0439\u043f\u0438\u043d"
    ],
    "name:swe_x_preferred":[
        "Taiping"
    ],
    "name:zho_x_preferred":[
        "\u6cf0\u5e73"
    ],
    "name:zho_x_variant":[
        "Pa-t\u2019o-erh",
        "T\u2019ai-p\u2019ing"
    ],
    "wof:name":"Taiping",
    "wof:placetype":"locality"
},
  "geometry": {"coordinates":[121.33417,24.66972],"type":"Point"}
}