{
  "type": "Feature",
  "properties": {
    "gn:admin1_code":"4.0",
    "gn:admin2_code":"YUN",
    "gn:admin3_code":"P09",
    "gn:admin4_code":"10009090010.0",
    "gn:asciiname":"Xingzhong",
    "gn:country_code":"TW",
    "gn:dem":45,
    "gn:feature_class":"P",
    "gn:feature_code":"PPL",
    "gn:name":"Xingzhong",
    "gn:population":0,
    "gn:timezone":"Asia/Taipei",
    "iso:country":"TW",
    "name:und_x_variant":[
        "Chie-kuei",
        "Singjhong",
        "Xingzhong",
        "Chuang-tzu",
        "Hsing-chung"
    ],
    "name:zho_x_preferred":[
        "\u8208\u4e2d"
    ],
    "wof:name":"Xingzhong",
    "wof:placetype":"locality"
},
  "geometry": {"coordinates":[120.51927999999999,23.76832000000001],"type":"Point"}
}