{
  "type": "Feature",
  "properties": {
    "gn:admin1_code":"4.0",
    "gn:admin2_code":"TTT",
    "gn:admin3_code":"V14",
    "gn:admin4_code":"10014150003.0",
    "gn:asciiname":"Xinhua",
    "gn:country_code":"TW",
    "gn:dem":461,
    "gn:feature_class":"P",
    "gn:feature_code":"PPL",
    "gn:name":"Xinhua",
    "gn:population":0,
    "gn:timezone":"Asia/Taipei",
    "iso:country":"TW",
    "name:und_x_variant":[
        "Sinhua",
        "Hsin-hua"
    ],
    "name:zho_x_preferred":[
        "Hsin-hua-ts\u2019un"
    ],
    "name:zho_x_variant":[
        "\u65b0\u5316"
    ],
    "wof:name":"Xinhua",
    "wof:placetype":"locality"
},
  "geometry": {"coordinates":[120.8575,22.38111],"type":"Point"}
}