{
  "type": "Feature",
  "properties": {
    "gn:admin1_code":"04",
    "gn:admin2_code":"CHA",
    "gn:admin3_code":"N03",
    "gn:admin4_code":"10007030006.0",
    "gn:asciiname":"Sizhangli",
    "gn:country_code":"TW",
    "gn:dem":8,
    "gn:feature_class":"P",
    "gn:feature_code":"PPL",
    "gn:name":"Sizhangli",
    "gn:population":0,
    "gn:timezone":"Asia/Taipei",
    "iso:country":"TW",
    "name:und_x_variant":[
        "Ssu-chang",
        "Sihjhangli",
        "Sizhangli",
        "Ssu-chang-li"
    ],
    "name:zho_x_preferred":[
        "T\u2019ang-chai-ts\u2019o"
    ],
    "name:zho_x_variant":[
        "\u56db\u5f35\u7282"
    ],
    "wof:name":"Sizhangli",
    "wof:placetype":"locality"
},
  "geometry": {"coordinates":[120.48528,24.11472],"type":"Point"}
}