{
  "type": "Feature",
  "properties": {
    "iso:country":"TW",
    "name:eng_x_preferred":[
        "Tamatsukuri District"
    ],
    "name:jpn_x_preferred":[
        "\u7389\u9020\u90e1"
    ],
    "qs:name":"\u5927\u5d0e\u6751",
    "qs:name_adm0":"\u81fa\u7063",
    "qs:name_adm1":"\u65b0\u7af9\u7e23",
    "qs:photos":17,
    "qs:photos_1k":3,
    "qs:photos_9k":1,
    "qs:photos_9r":1,
    "qs:photos_all":17,
    "qs:photos_sr":1,
    "qs:placetype":"Town",
    "qs:pop_sr":"0",
    "wd:wordcount":309,
    "wof:name":"\u5927\u5d0e\u6751",
    "wof:placetype":"locality"
},
  "geometry": {"coordinates":[121.01497000000001,24.75692],"type":"Point"}
}