{
  "type": "Feature",
  "properties": {
    "gn:admin1_code":"3.0",
    "gn:admin2_code":"TPQ",
    "gn:admin3_code":"F22",
    "gn:admin4_code":"65000240005.0",
    "gn:asciiname":"Chaiqiaokeng",
    "gn:country_code":"TW",
    "gn:dem":276,
    "gn:feature_class":"P",
    "gn:feature_code":"PPL",
    "gn:name":"Chaiqiaokeng",
    "gn:population":0,
    "gn:timezone":"Asia/Taipei",
    "iso:country":"TW",
    "name:und_x_variant":[
        "Ch\u2019ai-ch\u2019iao-k\u2019eng"
    ],
    "wof:name":"Chaiqiaokeng",
    "wof:placetype":"locality"
},
  "geometry": {"coordinates":[121.73333,25.03333],"type":"Point"}
}