{
  "type": "Feature",
  "properties": {
    "gn:admin1_code":"04",
    "gn:admin2_code":"HSZ",
    "gn:admin3_code":"J14",
    "gn:admin4_code":"10004120005.0",
    "gn:asciiname":"Zhuwei",
    "gn:country_code":"TW",
    "gn:dem":386,
    "gn:feature_class":"P",
    "gn:feature_code":"PPL",
    "gn:name":"Zhuwei",
    "gn:population":0,
    "gn:timezone":"Asia/Taipei",
    "iso:country":"TW",
    "name:und_x_variant":[
        "Jhuwei",
        "Chu-wei"
    ],
    "name:zho_x_preferred":[
        "\u7af9\u570d"
    ],
    "name:zho_x_variant":[
        "T\u2019ien-ta-na"
    ],
    "wof:name":"Zhuwei",
    "wof:placetype":"locality"
},
  "geometry": {"coordinates":[121.21944000000001,24.68917],"type":"Point"}
}