{
  "type": "Feature",
  "properties": {
    "gn:admin1_code":"04",
    "gn:admin2_code":"HUA",
    "gn:admin3_code":"U07",
    "gn:admin4_code":"10015020006.0",
    "gn:asciiname":"Shanxing",
    "gn:country_code":"TW",
    "gn:dem":97,
    "gn:feature_class":"P",
    "gn:feature_code":"PPL",
    "gn:name":"Shanxing",
    "gn:population":0,
    "gn:timezone":"Asia/Taipei",
    "iso:country":"TW",
    "name:und_x_variant":[
        "Shan-hsing-li",
        "Shansing",
        "Liu-chieh-pi",
        "Shanxing",
        "Shan-hsing"
    ],
    "name:zho_x_preferred":[
        "\u5c71\u8208"
    ],
    "wof:name":"Shanxing",
    "wof:placetype":"locality"
},
  "geometry": {"coordinates":[121.49851,23.72732],"type":"Point"}
}