{
  "type": "Feature",
  "properties": {
    "gn:admin1_code":"2.0",
    "gn:admin2_code":"KHH",
    "gn:admin3_code":"E13",
    "gn:admin4_code":"64000130007.0",
    "gn:asciiname":"Guogou",
    "gn:country_code":"TW",
    "gn:dem":7,
    "gn:feature_class":"P",
    "gn:feature_code":"PPL",
    "gn:name":"Guogou",
    "gn:population":0,
    "gn:timezone":"Asia/Taipei",
    "iso:country":"TW",
    "name:und_x_variant":[
        "Kuo-kou",
        "Kuo-kou-tzu",
        "Guogou"
    ],
    "name:zho_x_preferred":[
        "\u904e\u6e9d"
    ],
    "wof:name":"Guogou",
    "wof:placetype":"locality"
},
  "geometry": {"coordinates":[120.38876,22.50301],"type":"Point"}
}