{
  "type": "Feature",
  "properties": {
    "gn:admin1_code":"4.0",
    "gn:admin2_code":"NAN",
    "gn:admin3_code":"M07",
    "gn:admin4_code":"10008070005.0",
    "gn:asciiname":"Shibagu",
    "gn:country_code":"TW",
    "gn:dem":814,
    "gn:feature_class":"P",
    "gn:feature_code":"PPL",
    "gn:name":"Shibagu",
    "gn:population":0,
    "gn:timezone":"Asia/Taipei",
    "iso:country":"TW",
    "name:und_x_variant":[
        "Shihbagu",
        "Shih-pa-ku"
    ],
    "name:zho_x_preferred":[
        "\u5341\u516b\u80a1"
    ],
    "wof:name":"Shibagu",
    "wof:placetype":"locality"
},
  "geometry": {"coordinates":[120.78749999999999,23.71583],"type":"Point"}
}