{
  "type": "Feature",
  "properties": {
    "gn:admin1_code":"4.0",
    "gn:admin2_code":"ILA",
    "gn:admin3_code":"G09",
    "gn:admin4_code":"10002030002.0",
    "gn:asciiname":"Houhou",
    "gn:country_code":"TW",
    "gn:dem":10,
    "gn:feature_class":"P",
    "gn:feature_code":"PPL",
    "gn:name":"Houhou",
    "gn:population":0,
    "gn:timezone":"Asia/Taipei",
    "iso:country":"TW",
    "name:und_x_variant":[
        "Hou-hou",
        "Houhou"
    ],
    "name:zho_x_preferred":[
        "\u7334\u7334"
    ],
    "wof:name":"Houhou",
    "wof:placetype":"locality"
},
  "geometry": {"coordinates":[121.83231000000001,24.6438],"type":"Point"}
}