{
  "type": "Feature",
  "properties": {
    "gn:admin1_code":"04",
    "gn:admin2_code":"HSZ",
    "gn:admin3_code":"J03",
    "gn:admin4_code":"10004040018.0",
    "gn:asciiname":"Xiananpian",
    "gn:country_code":"TW",
    "gn:dem":85,
    "gn:feature_class":"P",
    "gn:feature_code":"PPL",
    "gn:name":"Xiananpian",
    "gn:population":0,
    "gn:timezone":"Asia/Taipei",
    "iso:country":"TW",
    "name:und_x_variant":[
        "Nan-ho-li",
        "Siananpian",
        "Xiananpian"
    ],
    "name:zho_x_preferred":[
        "\u4e0b\u5357\u7247"
    ],
    "name:zho_x_variant":[
        "Hsia-nan-p\u2019ien"
    ],
    "wof:name":"Xiananpian",
    "wof:placetype":"locality"
},
  "geometry": {"coordinates":[121.11888999999999,24.81167],"type":"Point"}
}