{
  "type": "Feature",
  "properties": {
    "gn:admin1_code":"4.0",
    "gn:admin2_code":"HUA",
    "gn:admin3_code":"U11",
    "gn:admin4_code":"10015110008.0",
    "gn:asciiname":"Jiamin",
    "gn:country_code":"TW",
    "gn:dem":51,
    "gn:feature_class":"P",
    "gn:feature_code":"PPL",
    "gn:name":"Jiamin",
    "gn:population":0,
    "gn:timezone":"Asia/Taipei",
    "iso:country":"TW",
    "name:und_x_variant":[
        "Ta-shan-she",
        "I-pan",
        "Wu-ya-nao",
        "Wu-ya-nao-she",
        "Erh-pan",
        "Jiamin",
        "Chia-min"
    ],
    "name:zho_x_preferred":[
        "Chia-min-ts\u2019un"
    ],
    "name:zho_x_variant":[
        "Ai-k\u2019o-to-sa-she",
        "\u4f73\u6c11"
    ],
    "wof:name":"Jiamin",
    "wof:placetype":"locality"
},
  "geometry": {"coordinates":[121.59753000000001,24.05802000000001],"type":"Point"}
}