{
  "type": "Feature",
  "properties": {
    "gn:admin1_code":"04",
    "gn:admin2_code":"ILA",
    "gn:admin3_code":"G01",
    "gn:admin4_code":"10002010027.0",
    "gn:asciiname":"Shuangjie",
    "gn:country_code":"TW",
    "gn:dem":15,
    "gn:feature_class":"P",
    "gn:feature_code":"PPL",
    "gn:name":"Shuangjie",
    "gn:population":0,
    "gn:timezone":"Asia/Taipei",
    "iso:country":"TW",
    "name:und_x_variant":[
        "Erh-chieh",
        "Shuang-chieh",
        "Shuangjie"
    ],
    "wof:name":"Shuangjie",
    "wof:placetype":"locality"
},
  "geometry": {"coordinates":[121.73333,24.76667],"type":"Point"}
}