{
  "type": "Feature",
  "properties": {
    "gn:admin1_code":"2.0",
    "gn:admin2_code":"KHH",
    "gn:admin3_code":"E30",
    "gn:admin4_code":"64000300011.0",
    "gn:asciiname":"Dawo",
    "gn:country_code":"TW",
    "gn:dem":50,
    "gn:feature_class":"P",
    "gn:feature_code":"PPL",
    "gn:name":"Dawo",
    "gn:population":0,
    "gn:timezone":"Asia/Taipei",
    "iso:country":"TW",
    "name:fra_x_preferred":[
        "Dawo"
    ],
    "name:und_x_variant":[
        "Ta-wo"
    ],
    "name:zho_x_preferred":[
        "\u5927\u7aa9"
    ],
    "wof:name":"Dawo",
    "wof:placetype":"locality"
},
  "geometry": {"coordinates":[120.50167,22.89417000000001],"type":"Point"}
}