{
  "type": "Feature",
  "properties": {
    "gn:admin1_code":"04",
    "gn:admin2_code":"TNN",
    "gn:admin3_code":"R13",
    "gn:admin4_code":"67000140003.0",
    "gn:asciiname":"Bafen",
    "gn:country_code":"TW",
    "gn:dem":11,
    "gn:feature_class":"P",
    "gn:feature_code":"PPL",
    "gn:name":"Bafen",
    "gn:population":0,
    "gn:timezone":"Asia/Taipei",
    "iso:country":"TW",
    "name:und_x_variant":[
        "Pa-fen",
        "Bafen",
        "\u516b\u5206"
    ],
    "name:zho_x_preferred":[
        "\u516b\u5206"
    ],
    "wof:name":"Bafen",
    "wof:placetype":"locality"
},
  "geometry": {"coordinates":[120.21944000000001,23.12833],"type":"Point"}
}