{
  "type": "Feature",
  "properties": {
    "gn:admin1_code":"4.0",
    "gn:admin2_code":"MIA",
    "gn:admin3_code":"K04",
    "gn:admin4_code":"10005090017.0",
    "gn:asciiname":"Xuwuhuofang",
    "gn:country_code":"TW",
    "gn:dem":68,
    "gn:feature_class":"P",
    "gn:feature_code":"PPL",
    "gn:name":"Xuwuhuofang",
    "gn:population":0,
    "gn:timezone":"Asia/Taipei",
    "iso:country":"TW",
    "name:und_x_variant":[
        "Syuwuhuofang"
    ],
    "name:zho_x_preferred":[
        "\u5f90\u5c4b\u4f19\u623f"
    ],
    "name:zho_x_variant":[
        "Tung-hai-t\u2019ang",
        "Hs\u00fc-wu-huo-fang"
    ],
    "wof:name":"Xuwuhuofang",
    "wof:placetype":"locality"
},
  "geometry": {"coordinates":[120.8412,24.53997],"type":"Point"}
}