{
  "type": "Feature",
  "properties": {
    "gn:admin1_code":"4.0",
    "gn:admin2_code":"CHA",
    "gn:admin3_code":"N08",
    "gn:admin4_code":"10007200012.0",
    "gn:asciiname":"Shanliao",
    "gn:country_code":"TW",
    "gn:dem":13,
    "gn:feature_class":"P",
    "gn:feature_code":"PPL",
    "gn:name":"Shanliao",
    "gn:population":0,
    "gn:timezone":"Asia/Taipei",
    "iso:country":"TW",
    "name:und_x_variant":[
        "Shan-liao"
    ],
    "name:zho_x_preferred":[
        "\u5c71\u5bee"
    ],
    "name:zho_x_variant":[
        "Feng-t\u2019ien"
    ],
    "wof:name":"Shanliao",
    "wof:placetype":"locality"
},
  "geometry": {"coordinates":[120.37965,23.90389],"type":"Point"}
}