{
  "type": "Feature",
  "properties": {
    "gn:admin1_code":"2.0",
    "gn:admin2_code":"KHH",
    "gn:admin3_code":"E35",
    "gn:admin4_code":"64000350014.0",
    "gn:asciiname":"Sanwan",
    "gn:country_code":"TW",
    "gn:dem":250,
    "gn:feature_class":"P",
    "gn:feature_code":"PPL",
    "gn:name":"Sanwan",
    "gn:population":0,
    "gn:timezone":"Asia/Taipei",
    "iso:country":"TW",
    "name:und_x_variant":[
        "San-wan"
    ],
    "name:zho_x_preferred":[
        "\u4e09\u7063"
    ],
    "wof:name":"Sanwan",
    "wof:placetype":"locality"
},
  "geometry": {"coordinates":[120.44306,22.97333],"type":"Point"}
}