{
  "type": "Feature",
  "properties": {
    "gn:admin1_code":"2.0",
    "gn:admin2_code":"KHH",
    "gn:admin3_code":"E35",
    "gn:admin4_code":"64000350014.0",
    "gn:asciiname":"Sanwan",
    "gn:country_code":"TW",
    "gn:dem":250,
    "gn:feature_class":"P",
    "gn:feature_code":"PPL",
    "gn:name":"Sanwan",
    "gn:population":0,
    "gn:timezone":"Asia/Taipei",
    "iso:country":"TW",
    "name:fra_x_preferred":[
        "Sanwan"
    ],
    "name:hak_x_preferred":[
        "S\u00e2m-v\u00e2n-hi\u00f4ng"
    ],
    "name:jpn_x_preferred":[
        "\u4e09\u6e7e\u90f7"
    ],
    "name:kor_x_preferred":[
        "\uc2fc\uc644\ud5a5"
    ],
    "name:und_x_variant":[
        "San-wan"
    ],
    "name:vie_x_preferred":[
        "Tam Loan"
    ],
    "name:zho_x_preferred":[
        "\u4e09\u7063"
    ],
    "name:zho_x_variant":[
        "\u4e09\u7063\u9109"
    ],
    "wof:name":"Sanwan",
    "wof:placetype":"locality"
},
  "geometry": {"coordinates":[120.44306,22.97333],"type":"Point"}
}