{
  "type": "Feature",
  "properties": {
    "gn:admin1_code":"04",
    "gn:admin2_code":"TXG",
    "gn:admin3_code":"B24",
    "gn:admin4_code":"66000240010.0",
    "gn:asciiname":"Dadongcun",
    "gn:country_code":"TW",
    "gn:dem":9,
    "gn:feature_class":"P",
    "gn:feature_code":"PPL",
    "gn:name":"Dadongcun",
    "gn:population":0,
    "gn:timezone":"Asia/Taipei",
    "iso:country":"TW",
    "name:und_x_variant":[
        "Ta-tung-ts\u2019un"
    ],
    "wof:name":"Dadongcun",
    "wof:placetype":"locality"
},
  "geometry": {"coordinates":[120.53333000000001,24.15],"type":"Point"}
}