{
  "type": "Feature",
  "properties": {
    "gn:admin1_code":"4.0",
    "gn:admin2_code":"TAO",
    "gn:admin3_code":"H03",
    "gn:admin4_code":"68000020032.0",
    "gn:asciiname":"Chikan",
    "gn:country_code":"TW",
    "gn:dem":80,
    "gn:feature_class":"P",
    "gn:feature_code":"PPL",
    "gn:name":"Chikan",
    "gn:population":0,
    "gn:timezone":"Asia/Taipei",
    "iso:country":"TW",
    "name:ceb_x_preferred":[
        "Chikan"
    ],
    "name:deu_x_preferred":[
        "Chikan"
    ],
    "name:fra_x_preferred":[
        "Chikan"
    ],
    "name:spa_x_preferred":[
        "Chikan"
    ],
    "name:und_x_variant":[
        "Chihkan"
    ],
    "name:zho_x_preferred":[
        "\u8d64\u5d01"
    ],
    "name:zho_x_variant":[
        "Hung-k\u2019an",
        "Ch\u2019ih-k\u2019an"
    ],
    "wof:name":"Chikan",
    "wof:placetype":"locality"
},
  "geometry": {"coordinates":[121.22117,25.01453],"type":"Point"}
}