{
  "type": "Feature",
  "properties": {
    "gn:admin1_code":"4.0",
    "gn:admin2_code":"HSZ",
    "gn:admin3_code":"J03",
    "gn:admin4_code":"10004040013.0",
    "gn:asciiname":"Qianshan",
    "gn:country_code":"TW",
    "gn:dem":450,
    "gn:feature_class":"P",
    "gn:feature_code":"PPL",
    "gn:name":"Qianshan",
    "gn:population":0,
    "gn:timezone":"Asia/Taipei",
    "iso:country":"TW",
    "name:ceb_x_preferred":[
        "Qianshan"
    ],
    "name:deu_x_preferred":[
        "Qianshan"
    ],
    "name:fra_x_preferred":[
        "Qianshan"
    ],
    "name:nor_x_preferred":[
        "Qianshan"
    ],
    "name:rus_x_preferred":[
        "\u0426\u044f\u043d\u044c\u0448\u0430\u043d\u044c"
    ],
    "name:swe_x_preferred":[
        "Qianshan"
    ],
    "name:und_x_variant":[
        "Cianshan"
    ],
    "name:zho_x_preferred":[
        "\u925b\u5c71"
    ],
    "name:zho_x_variant":[
        "Ch\u2019ien-shan"
    ],
    "wof:name":"Qianshan",
    "wof:placetype":"locality"
},
  "geometry": {"coordinates":[121.21056000000002,24.7375],"type":"Point"}
}