{
  "type": "Feature",
  "properties": {
    "gn:admin1_code":"4.0",
    "gn:admin2_code":"TNN",
    "gn:admin3_code":"R14",
    "gn:admin4_code":"67000150021.0",
    "gn:asciiname":"Sanbaierwan",
    "gn:country_code":"TW",
    "gn:dem":5,
    "gn:feature_class":"P",
    "gn:feature_code":"PPL",
    "gn:name":"Sanbaierwan",
    "gn:population":0,
    "gn:timezone":"Asia/Taipei",
    "iso:country":"TW",
    "name:und_x_variant":[
        "San-pai-erh-wan",
        "Sanbaierwan"
    ],
    "name:zho_x_preferred":[
        "\u4e09\u767e\u4e8c\u842c"
    ],
    "wof:name":"Sanbaierwan",
    "wof:placetype":"locality"
},
  "geometry": {"coordinates":[120.12860999999999,23.10083],"type":"Point"}
}