{
  "type": "Feature",
  "properties": {
    "gn:admin1_code":"4.0",
    "gn:admin2_code":"TAO",
    "gn:admin3_code":"H06",
    "gn:admin4_code":"68000060007.0",
    "gn:asciiname":"Rongshukeng",
    "gn:country_code":"TW",
    "gn:dem":52,
    "gn:feature_class":"P",
    "gn:feature_code":"PPL",
    "gn:name":"Rongshukeng",
    "gn:population":0,
    "gn:timezone":"Asia/Taipei",
    "iso:country":"TW",
    "name:zho_x_preferred":[
        "\u6995\u6a39\u5751"
    ],
    "name:zho_x_variant":[
        "Jung-shu-k\u2019eng"
    ],
    "wof:name":"Rongshukeng",
    "wof:placetype":"locality"
},
  "geometry": {"coordinates":[121.23372999999999,25.03452],"type":"Point"}
}