{
  "type": "Feature",
  "properties": {
    "iso:country":"TW",
    "name:cym_x_preferred":[
        "Sir Taoyuan"
    ],
    "name:eng_x_preferred":[
        "Taoyuan County"
    ],
    "name:jpn_x_preferred":[
        "\u6843\u5712\u770c"
    ],
    "name:nan_x_preferred":[
        "Th\u00f4-hn\u0302g-ko\u0101n"
    ],
    "name:rus_x_preferred":[
        "\u0443\u0435\u0437\u0434 \u0422\u0430\u043e\u044e\u0430\u043d\u044c"
    ],
    "name:slv_x_preferred":[
        "Taojuan"
    ],
    "name:zho_x_preferred":[
        "\u6843\u5712\u7e23"
    ],
    "qs:name":"\u694a\u6885\u5e02",
    "qs:name_adm0":"\u81fa\u7063",
    "qs:name_adm1":"\u6843\u5712\u7e23",
    "qs:photos":2937,
    "qs:photos_1k":595,
    "qs:photos_9k":13,
    "qs:photos_9r":11,
    "qs:photos_all":2937,
    "qs:photos_sr":19,
    "qs:placetype":"Town",
    "qs:pop_sr":"0",
    "wd:wordcount":147,
    "wof:name":"\u694a\u6885\u5e02",
    "wof:placetype":"locality"
},
  "geometry": {"coordinates":[121.145973,24.90769],"type":"Point"}
}