{
  "type": "Feature",
  "properties": {
    "gn:admin1_code":"4.0",
    "gn:admin2_code":"HUA",
    "gn:admin3_code":"U02",
    "gn:admin4_code":"10015070009.0",
    "gn:asciiname":"Leiyuan",
    "gn:country_code":"TW",
    "gn:dem":199,
    "gn:feature_class":"P",
    "gn:feature_code":"PPL",
    "gn:name":"Leiyuan",
    "gn:population":0,
    "gn:timezone":"Asia/Taipei",
    "iso:country":"TW",
    "name:zho_x_preferred":[
        "\u5121\u9060"
    ],
    "name:zho_x_variant":[
        "Lei-y\u00fcan"
    ],
    "wof:name":"Leiyuan",
    "wof:placetype":"locality"
},
  "geometry": {"coordinates":[121.40488999999999,23.59298],"type":"Point"}
}