{
  "type": "Feature",
  "properties": {
    "gn:admin1_code":"04",
    "gn:admin2_code":"CYQ",
    "gn:admin3_code":"Q04",
    "gn:admin4_code":"10010040005.0",
    "gn:asciiname":"Xiapitou",
    "gn:country_code":"TW",
    "gn:dem":28,
    "gn:feature_class":"P",
    "gn:feature_code":"PPL",
    "gn:name":"Xiapitou",
    "gn:population":0,
    "gn:timezone":"Asia/Taipei",
    "iso:country":"TW",
    "name:und_x_variant":[
        "Hu-ti",
        "Ming-hua",
        "Siapitou",
        "Xiapitou"
    ],
    "name:zho_x_preferred":[
        "Ming-hua-ts\u2019un"
    ],
    "name:zho_x_variant":[
        "\u4e0b\u57e4\u982d",
        "Hsia-pei-t\u2019ou",
        "Hsia-p\u2019i-t\u2019ou"
    ],
    "wof:name":"Xiapitou",
    "wof:placetype":"locality"
},
  "geometry": {"coordinates":[120.44056999999999,23.6012],"type":"Point"}
}