{
  "type": "Feature",
  "properties": {
    "gn:admin1_code":"4.0",
    "gn:admin2_code":"NAN",
    "gn:admin3_code":"M13",
    "gn:admin4_code":"10008130015.0",
    "gn:asciiname":"Xinzhuang",
    "gn:country_code":"TW",
    "gn:dem":1920,
    "gn:feature_class":"P",
    "gn:feature_code":"PPL",
    "gn:name":"Xinzhuang",
    "gn:population":0,
    "gn:timezone":"Asia/Taipei",
    "iso:country":"TW",
    "name:ceb_x_preferred":[
        "Xinzhuang"
    ],
    "name:deu_x_preferred":[
        "Xinzhuang"
    ],
    "name:und_x_variant":[
        "Sinjhuang",
        "Hsin-chuang"
    ],
    "name:zho_x_preferred":[
        "\u4fe1\u838a"
    ],
    "wof:name":"Xinzhuang",
    "wof:placetype":"locality"
},
  "geometry": {"coordinates":[121.25639,24.24056],"type":"Point"}
}