{
  "type": "Feature",
  "properties": {
    "gn:admin1_code":"4.0",
    "gn:admin2_code":"MIA",
    "gn:admin3_code":"K01",
    "gn:admin4_code":"10005010009.0",
    "gn:asciiname":"Erpingding",
    "gn:country_code":"TW",
    "gn:dem":104,
    "gn:feature_class":"P",
    "gn:feature_code":"PPL",
    "gn:name":"Erpingding",
    "gn:population":0,
    "gn:timezone":"Asia/Taipei",
    "iso:country":"TW",
    "name:zho_x_preferred":[
        "\u4e8c\u576a\u9802"
    ],
    "name:zho_x_variant":[
        "Erh-p\u2019ing-ting"
    ],
    "wof:name":"Erpingding",
    "wof:placetype":"locality"
},
  "geometry": {"coordinates":[120.8111,24.54927],"type":"Point"}
}