{
  "type": "Feature",
  "properties": {
    "iso:country":"TW",
    "qs:name":"\u77f3\u724c\u6751",
    "qs:name_adm0":"\u81fa\u7063",
    "qs:name_adm1":"\u82b1\u84ee\u7e23",
    "qs:photos":112,
    "qs:photos_1k":23,
    "qs:photos_9k":1,
    "qs:photos_9r":3,
    "qs:photos_all":112,
    "qs:photos_sr":3,
    "qs:placetype":"Town",
    "qs:pop_sr":"0",
    "wof:name":"\u77f3\u724c\u6751",
    "wof:placetype":"locality"
},
  "geometry": {"coordinates":[121.272583,23.190231],"type":"Point"}
}