{
  "type": "Feature",
  "properties": {
    "gn:admin1_code":"4.0",
    "gn:admin2_code":"MIA",
    "gn:admin3_code":"K01",
    "gn:admin4_code":"10005010013.0",
    "gn:asciiname":"Shengli",
    "gn:country_code":"TW",
    "gn:dem":56,
    "gn:feature_class":"P",
    "gn:feature_code":"PPL",
    "gn:name":"Shengli",
    "gn:population":0,
    "gn:timezone":"Asia/Taipei",
    "iso:country":"TW",
    "name:und_x_variant":[
        "Sheng-li"
    ],
    "name:zho_x_preferred":[
        "\u52dd\u5229"
    ],
    "wof:name":"Shengli",
    "wof:placetype":"locality"
},
  "geometry": {"coordinates":[120.82590999999999,24.5469],"type":"Point"}
}