{
  "type": "Feature",
  "properties": {
    "gn:admin1_code":"04",
    "gn:admin2_code":"MIA",
    "gn:admin3_code":"K03",
    "gn:admin4_code":"10005030003.0",
    "gn:asciiname":"Xiabeishi",
    "gn:country_code":"TW",
    "gn:dem":19,
    "gn:feature_class":"P",
    "gn:feature_code":"PPL",
    "gn:name":"Xiabeishi",
    "gn:population":0,
    "gn:timezone":"Asia/Taipei",
    "iso:country":"TW",
    "name:und_x_variant":[
        "Pei-shih",
        "Xiabeishi",
        "Siabeishih",
        "Hsia-pei-shih"
    ],
    "name:zho_x_preferred":[
        "\u4e0b\u5317\u52e2"
    ],
    "wof:name":"Xiabeishi",
    "wof:placetype":"locality"
},
  "geometry": {"coordinates":[120.68722,24.48472000000001],"type":"Point"}
}