{
  "type": "Feature",
  "properties": {
    "gn:country":"TW",
    "iso:country":"TW",
    "name:eng_x_preferred":[
        "Renzheng"
    ],
    "name:eng_x_variant":[
        "Renzheng Village"
    ],
    "name:zho_tw_x_preferred":[
        "\u4ec1\u6b63\u91cc"
    ],
    "qs:name":"\u4ec1\u6b63\u91cc",
    "qs:name_adm0":"\u81fa\u7063",
    "qs:name_adm1":"\u57fa\u9686\u5e02",
    "qs:photos":58,
    "qs:photos_1k":12,
    "qs:photos_9k":1,
    "qs:photos_9r":2,
    "qs:photos_all":58,
    "qs:photos_sr":2,
    "qs:placetype":"Suburb",
    "qs:pop_sr":"0",
    "wof:name":"Renzheng",
    "wof:placetype":"neighbourhood"
},
  "geometry": {"coordinates":[121.74136799999999,25.141632],"type":"Point"}
}