{
  "type": "Feature",
  "properties": {
    "gn:admin1_code":"4.0",
    "gn:admin2_code":"ILA",
    "gn:admin3_code":"G05",
    "gn:admin4_code":"10002070012.0",
    "gn:asciiname":"Zhenping",
    "gn:country_code":"TW",
    "gn:dem":26,
    "gn:feature_class":"P",
    "gn:feature_code":"PPL",
    "gn:name":"Zhenping",
    "gn:population":0,
    "gn:timezone":"Asia/Taipei",
    "iso:country":"TW",
    "name:und_x_variant":[
        "Jhenping",
        "Zhenping"
    ],
    "name:zho_x_preferred":[
        "\u93ad\u5e73"
    ],
    "name:zho_x_variant":[
        "Chen-p\u2019ing"
    ],
    "wof:name":"Zhenping",
    "wof:placetype":"locality"
},
  "geometry": {"coordinates":[121.72487,24.76705],"type":"Point"}
}