{
  "type": "Feature",
  "properties": {
    "gn:admin1_code":"4.0",
    "gn:asciiname":"Haiguangxincun",
    "gn:country_code":"TW",
    "gn:dem":-9999,
    "gn:feature_class":"P",
    "gn:feature_code":"PPL",
    "gn:name":"Haiguangxincun",
    "gn:population":0,
    "gn:timezone":"Asia/Taipei",
    "iso:country":"TW",
    "name:und_x_variant":[
        "Hai-kuang-hsin-ts\u2019un"
    ],
    "wof:name":"Haiguangxincun",
    "wof:placetype":"locality"
},
  "geometry": {"coordinates":[119.56667,23.55],"type":"Point"}
}