{
  "type": "Feature",
  "properties": {
    "iso:country":"TW",
    "name:eng_x_preferred":[
        "Dahe"
    ],
    "name:eng_x_variant":[
        "Dahe Village"
    ],
    "name:zho_tw_x_preferred":[
        "\u5927\u6cb3\u6751"
    ],
    "qs:name":"\u5927\u6cb3\u6751",
    "qs:name_adm0":"\u81fa\u7063",
    "qs:name_adm1":"\u82d7\u6817\u7e23",
    "qs:photos":11,
    "qs:photos_1k":2,
    "qs:photos_9k":1,
    "qs:photos_9r":1,
    "qs:photos_all":11,
    "qs:photos_sr":1,
    "qs:placetype":"Town",
    "qs:pop_sr":"0",
    "wof:name":"Dahe",
    "wof:placetype":"locality"
},
  "geometry": {"coordinates":[120.958547,24.608611],"type":"Point"}
}