{
  "type": "Feature",
  "properties": {
    "gn:admin1_code":"4.0",
    "gn:admin2_code":"MIA",
    "gn:admin3_code":"K11",
    "gn:admin4_code":"10005150003.0",
    "gn:asciiname":"Bashichiqiao",
    "gn:country_code":"TW",
    "gn:dem":39,
    "gn:feature_class":"P",
    "gn:feature_code":"PPL",
    "gn:name":"Bashichiqiao",
    "gn:population":0,
    "gn:timezone":"Asia/Taipei",
    "iso:country":"TW",
    "name:und_x_variant":[
        "Bashihchihciao",
        "Bashichiqiao"
    ],
    "name:zho_x_preferred":[
        "\u516b\u5341\u5c3a\u6a4b"
    ],
    "name:zho_x_variant":[
        "Pa-shih-ch\u2019ih-ch\u2019iao"
    ],
    "wof:name":"Bashichiqiao",
    "wof:placetype":"locality"
},
  "geometry": {"coordinates":[120.83669999999999,24.6126],"type":"Point"}
}