{
  "type": "Feature",
  "properties": {
    "gn:admin1_code":"4.0",
    "gn:admin2_code":"CHA",
    "gn:admin3_code":"N26",
    "gn:admin4_code":"10007260006.0",
    "gn:asciiname":"Zhonggu",
    "gn:country_code":"TW",
    "gn:dem":42,
    "gn:feature_class":"P",
    "gn:feature_code":"PPL",
    "gn:name":"Zhonggu",
    "gn:population":0,
    "gn:timezone":"Asia/Taipei",
    "iso:country":"TW",
    "name:und_x_variant":[
        "Jhonggu",
        "Chung-ku"
    ],
    "name:zho_x_preferred":[
        "\u4e2d\u56fa"
    ],
    "wof:name":"Zhonggu",
    "wof:placetype":"locality"
},
  "geometry": {"coordinates":[120.521,23.84012],"type":"Point"}
}