{
  "type": "Feature",
  "properties": {
    "gn:admin1_code":"4.0",
    "gn:admin2_code":"KEE",
    "gn:admin3_code":"C02",
    "gn:admin4_code":"10017020014.0",
    "gn:asciiname":"Xiandonghu",
    "gn:country_code":"TW",
    "gn:dem":65,
    "gn:feature_class":"P",
    "gn:feature_code":"PPL",
    "gn:name":"Xiandonghu",
    "gn:population":0,
    "gn:timezone":"Asia/Taipei",
    "iso:country":"TW",
    "name:und_x_variant":[
        "Siandonghu",
        "Xiandonghu",
        "Hsien-tung-hu-chieh",
        "Hsien-tung-hu"
    ],
    "name:zho_x_preferred":[
        "\u4ed9\u6d1e\u6e56"
    ],
    "wof:name":"Xiandonghu",
    "wof:placetype":"locality"
},
  "geometry": {"coordinates":[121.67993,25.12421],"type":"Point"}
}