{
  "type": "Feature",
  "properties": {
    "iso:country":"TW",
    "qs:name":"\u5de5\u5ee0\u6751",
    "qs:name_adm0":"\u81fa\u7063",
    "qs:name_adm1":"\u5609\u7fa9\u7e23",
    "qs:photos":155,
    "qs:photos_1k":31,
    "qs:photos_9k":1,
    "qs:photos_9r":4,
    "qs:photos_all":155,
    "qs:photos_sr":4,
    "qs:placetype":"Town",
    "qs:pop_sr":"0",
    "wof:name":"\u5de5\u5ee0\u6751",
    "wof:placetype":"locality"
},
  "geometry": {"coordinates":[120.299391,23.47964],"type":"Point"}
}