{
  "type": "Feature",
  "properties": {
    "gn:admin1_code":"4.0",
    "gn:admin2_code":"TAO",
    "gn:admin3_code":"H09",
    "gn:admin4_code":"68000090009.0",
    "gn:asciiname":"Zhuwozi",
    "gn:country_code":"TW",
    "gn:dem":239,
    "gn:feature_class":"P",
    "gn:feature_code":"PPL",
    "gn:name":"Zhuwozi",
    "gn:population":0,
    "gn:timezone":"Asia/Taipei",
    "iso:country":"TW",
    "name:und_x_variant":[
        "Jhuwozih",
        "Zhuwozi",
        "Chu-wo-tzu"
    ],
    "name:zho_x_preferred":[
        "\u7af9\u7aa9\u5b50"
    ],
    "wof:name":"Zhuwozi",
    "wof:placetype":"locality"
},
  "geometry": {"coordinates":[121.20193999999999,24.86139],"type":"Point"}
}