{
  "type": "Feature",
  "properties": {
    "gn:admin1_code":"4.0",
    "gn:admin2_code":"MIA",
    "gn:admin3_code":"K08",
    "gn:admin4_code":"10005120004.0",
    "gn:asciiname":"Dongxingzhuang",
    "gn:country_code":"TW",
    "gn:dem":40,
    "gn:feature_class":"P",
    "gn:feature_code":"PPL",
    "gn:name":"Dongxingzhuang",
    "gn:population":0,
    "gn:timezone":"Asia/Taipei",
    "iso:country":"TW",
    "name:und_x_variant":[
        "Dongsingjhuang",
        "Tung-hsing-chuang"
    ],
    "name:zho_x_preferred":[
        "\u6771\u8208\u838a"
    ],
    "wof:name":"Dongxingzhuang",
    "wof:placetype":"locality"
},
  "geometry": {"coordinates":[120.8518,24.5816],"type":"Point"}
}