{
  "type": "Feature",
  "properties": {
    "iso:country":"TW",
    "name:eng_x_preferred":[
        "Tongde"
    ],
    "name:eng_x_variant":[
        "Tongde Village"
    ],
    "name:zho_tw_x_preferred":[
        "\u540c\u5fb7\u91cc"
    ],
    "qs:name":"\u540c\u5fb7\u91cc",
    "qs:name_adm0":"\u81fa\u7063",
    "qs:name_adm1":"\u9ad8\u96c4\u5e02",
    "qs:photos":193,
    "qs:photos_1k":39,
    "qs:photos_9k":1,
    "qs:photos_9r":4,
    "qs:photos_all":193,
    "qs:photos_sr":4,
    "qs:placetype":"Suburb",
    "qs:pop_sr":"0",
    "wof:name":"Tongde",
    "wof:placetype":"neighbourhood"
},
  "geometry": {"coordinates":[120.31339699999999,22.640722],"type":"Point"}
}