{
  "type": "Feature",
  "properties": {
    "gn:admin1_code":"2.0",
    "gn:admin2_code":"KHH",
    "gn:admin3_code":"E32",
    "gn:admin4_code":"64000320003.0",
    "gn:asciiname":"Zhucuo",
    "gn:country_code":"TW",
    "gn:dem":156,
    "gn:feature_class":"P",
    "gn:feature_code":"PPL",
    "gn:name":"Zhucuo",
    "gn:population":0,
    "gn:timezone":"Asia/Taipei",
    "iso:country":"TW",
    "name:und_x_variant":[
        "Jhucuo"
    ],
    "name:zho_x_preferred":[
        "\u6731\u539d"
    ],
    "name:zho_x_variant":[
        "Chu-ts\u2019o"
    ],
    "wof:name":"Zhucuo",
    "wof:placetype":"locality"
},
  "geometry": {"coordinates":[120.60396,22.8973],"type":"Point"}
}