{
  "type": "Feature",
  "properties": {
    "gn:admin1_code":"3.0",
    "gn:admin2_code":"TPQ",
    "gn:admin3_code":"F02",
    "gn:admin4_code":"65000170011.0",
    "gn:asciiname":"Xialiao",
    "gn:country_code":"TW",
    "gn:dem":10,
    "gn:feature_class":"P",
    "gn:feature_code":"PPL",
    "gn:name":"Xialiao",
    "gn:population":0,
    "gn:timezone":"Asia/Taipei",
    "iso:country":"TW",
    "name:und_x_variant":[
        "Hsia-liao-tzu",
        "Xialiao",
        "Sialiao",
        "Hsia-liao"
    ],
    "name:zho_x_preferred":[
        "\u4e0b\u5bee"
    ],
    "wof:name":"Xialiao",
    "wof:placetype":"locality"
},
  "geometry": {"coordinates":[121.29170999999999,25.11751],"type":"Point"}
}