{
  "type": "Feature",
  "properties": {
    "gn:admin1_code":"4.0",
    "gn:admin2_code":"NAN",
    "gn:admin3_code":"M06",
    "gn:admin4_code":"10008060011.0",
    "gn:asciiname":"Zhuwei",
    "gn:country_code":"TW",
    "gn:dem":240,
    "gn:feature_class":"P",
    "gn:feature_code":"PPL",
    "gn:name":"Zhuwei",
    "gn:population":0,
    "gn:timezone":"Asia/Taipei",
    "iso:country":"TW",
    "name:und_x_variant":[
        "Jhuwei",
        "Zhuwei",
        "Chu-wei"
    ],
    "name:zho_x_preferred":[
        "\u7af9\u570d"
    ],
    "wof:name":"Zhuwei",
    "wof:placetype":"locality"
},
  "geometry": {"coordinates":[120.66146000000001,23.87385],"type":"Point"}
}