{
  "type": "Feature",
  "properties": {
    "gn:admin1_code":"04",
    "gn:admin2_code":"CYQ",
    "gn:admin3_code":"Q08",
    "gn:admin4_code":"10010080003.0",
    "gn:asciiname":"Suantou",
    "gn:country_code":"TW",
    "gn:dem":13,
    "gn:feature_class":"P",
    "gn:feature_code":"PPL",
    "gn:name":"Suantou",
    "gn:population":0,
    "gn:timezone":"Asia/Taipei",
    "iso:country":"TW",
    "name:zho_x_preferred":[
        "\u849c\u982d"
    ],
    "name:zho_x_variant":[
        "Suan-t\u2019ou"
    ],
    "wof:name":"Suantou",
    "wof:placetype":"locality"
},
  "geometry": {"coordinates":[120.29167,23.49056],"type":"Point"}
}