{
  "type": "Feature",
  "properties": {
    "gn:admin1_code":"04",
    "gn:admin2_code":"PIF",
    "gn:admin3_code":"T09",
    "gn:admin4_code":"10013090006.0",
    "gn:asciiname":"Datiedian",
    "gn:country_code":"TW",
    "gn:dem":41,
    "gn:feature_class":"P",
    "gn:feature_code":"PPL",
    "gn:name":"Datiedian",
    "gn:population":0,
    "gn:timezone":"Asia/Taipei",
    "iso:country":"TW",
    "name:zho_x_preferred":[
        "T\u2019ieh-tien-ts\u2019un"
    ],
    "name:zho_x_variant":[
        "\u6253\u9435\u5e97",
        "T\u2019ieh-tien",
        "Ta-t\u2019ieh-tien"
    ],
    "wof:name":"Datiedian",
    "wof:placetype":"locality"
},
  "geometry": {"coordinates":[120.5025,22.77806],"type":"Point"}
}