{
  "type": "Feature",
  "properties": {
    "gn:admin1_code":"3.0",
    "gn:admin2_code":"TPQ",
    "gn:admin3_code":"F07",
    "gn:admin4_code":"65000060024.0",
    "gn:asciiname":"Hushankeng",
    "gn:country_code":"TW",
    "gn:dem":210,
    "gn:feature_class":"P",
    "gn:feature_code":"PPL",
    "gn:name":"Hushankeng",
    "gn:population":0,
    "gn:timezone":"Asia/Taipei",
    "iso:country":"TW",
    "name:zho_x_preferred":[
        "\u6e56\u9583\u5751"
    ],
    "name:zho_x_variant":[
        "Hu-shan-k\u2019eng"
    ],
    "wof:name":"Hushankeng",
    "wof:placetype":"locality"
},
  "geometry": {"coordinates":[121.5712,24.94519],"type":"Point"}
}