{
  "type": "Feature",
  "properties": {
    "gn:admin1_code":"04",
    "gn:admin2_code":"TTT",
    "gn:admin3_code":"V08",
    "gn:admin4_code":"10014080006.0",
    "gn:asciiname":"Nanwushibi",
    "gn:country_code":"TW",
    "gn:dem":16,
    "gn:feature_class":"P",
    "gn:feature_code":"PPL",
    "gn:name":"Nanwushibi",
    "gn:population":0,
    "gn:timezone":"Asia/Taipei",
    "iso:country":"TW",
    "name:und_x_variant":[
        "Wu-shih-pi",
        "Nanwushihbi",
        "Nanwushibi",
        "Nan-wu-shih-pi"
    ],
    "name:zho_x_preferred":[
        "\u5357\u70cf\u77f3\u9f3b"
    ],
    "wof:name":"Nanwushibi",
    "wof:placetype":"locality"
},
  "geometry": {"coordinates":[121.41338,23.23031],"type":"Point"}
}