{
  "type": "Feature",
  "properties": {
    "gn:admin1_code":"4.0",
    "gn:admin2_code":"PIF",
    "gn:admin3_code":"T22",
    "gn:admin4_code":"10013220005.0",
    "gn:asciiname":"Jingzikou",
    "gn:country_code":"TW",
    "gn:dem":19,
    "gn:feature_class":"P",
    "gn:feature_code":"PPL",
    "gn:name":"Jingzikou",
    "gn:population":0,
    "gn:timezone":"Asia/Taipei",
    "iso:country":"TW",
    "name:und_x_variant":[
        "Jingzihkou"
    ],
    "name:zho_x_preferred":[
        "\u4e95\u4ed4\u53e3"
    ],
    "name:zho_x_variant":[
        "Ching-tzu-k\u2019ou"
    ],
    "wof:name":"Jingzikou",
    "wof:placetype":"locality"
},
  "geometry": {"coordinates":[120.36042,22.32322000000001],"type":"Point"}
}