{
  "type": "Feature",
  "properties": {
    "gn:admin1_code":"3.0",
    "gn:admin2_code":"TPQ",
    "gn:admin3_code":"F07",
    "gn:admin4_code":"65000060024.0",
    "gn:asciiname":"Tuqitou",
    "gn:country_code":"TW",
    "gn:dem":202,
    "gn:feature_class":"P",
    "gn:feature_code":"PPL",
    "gn:name":"Tuqitou",
    "gn:population":0,
    "gn:timezone":"Asia/Taipei",
    "iso:country":"TW",
    "name:und_x_variant":[
        "Tucitou"
    ],
    "name:zho_x_preferred":[
        "\u571f\u5d0e\u982d"
    ],
    "name:zho_x_variant":[
        "T\u2019u-ch\u2019i-t\u2019ou"
    ],
    "wof:name":"Tuqitou",
    "wof:placetype":"locality"
},
  "geometry": {"coordinates":[121.57704,24.95261],"type":"Point"}
}