{
  "type": "Feature",
  "properties": {
    "gn:admin1_code":"4.0",
    "gn:admin2_code":"TNN",
    "gn:admin3_code":"R03",
    "gn:admin4_code":"67000030010.0",
    "gn:asciiname":"Liuchongxi",
    "gn:country_code":"TW",
    "gn:dem":87,
    "gn:feature_class":"P",
    "gn:feature_code":"PPL",
    "gn:name":"Liuchongxi",
    "gn:population":0,
    "gn:timezone":"Asia/Taipei",
    "iso:country":"TW",
    "name:und_x_variant":[
        "Liouchongsi"
    ],
    "name:zho_x_preferred":[
        "Liu-ch\u2019ung-ch\u2019i"
    ],
    "name:zho_x_variant":[
        "\u516d\u91cd\u6eaa",
        "Liu-ch\u2019ung-hsi"
    ],
    "wof:name":"Liuchongxi",
    "wof:placetype":"locality"
},
  "geometry": {"coordinates":[120.45944,23.31083],"type":"Point"}
}