{
  "type": "Feature",
  "properties": {
    "gn:admin1_code":"4.0",
    "gn:admin2_code":"CYQ",
    "gn:admin3_code":"Q17",
    "gn:admin4_code":"10010160010.0",
    "gn:asciiname":"Youmaocaolong",
    "gn:country_code":"TW",
    "gn:dem":897,
    "gn:feature_class":"P",
    "gn:feature_code":"PPL",
    "gn:name":"Youmaocaolong",
    "gn:population":0,
    "gn:timezone":"Asia/Taipei",
    "iso:country":"TW",
    "name:zho_x_preferred":[
        "\u6709\u8305\u8349\u9f8d"
    ],
    "name:zho_x_variant":[
        "Yu-mao-ts\u2019ao-lung"
    ],
    "wof:name":"Youmaocaolong",
    "wof:placetype":"locality"
},
  "geometry": {"coordinates":[120.64183,23.40942],"type":"Point"}
}