{
  "type": "Feature",
  "properties": {
    "gn:admin1_code":"4.0",
    "gn:admin2_code":"HSQ",
    "gn:admin3_code":"O03",
    "gn:admin4_code":"10018030014.0",
    "gn:asciiname":"Caona",
    "gn:country_code":"TW",
    "gn:dem":10,
    "gn:feature_class":"P",
    "gn:feature_code":"PPL",
    "gn:name":"Caona",
    "gn:population":0,
    "gn:timezone":"Asia/Taipei",
    "iso:country":"TW",
    "name:zho_x_preferred":[
        "\u8349\u7d0d"
    ],
    "name:zho_x_variant":[
        "Ts\u2019ao-na"
    ],
    "wof:name":"Caona",
    "wof:placetype":"locality"
},
  "geometry": {"coordinates":[120.91639000000001,24.78222],"type":"Point"}
}