{
  "type": "Feature",
  "properties": {
    "gn:admin1_code":"04",
    "gn:admin2_code":"CHA",
    "gn:admin3_code":"N20",
    "gn:admin4_code":"10007180014.0",
    "gn:asciiname":"Yuanquan",
    "gn:country_code":"TW",
    "gn:dem":106,
    "gn:feature_class":"P",
    "gn:feature_code":"PPL",
    "gn:name":"Yuanquan",
    "gn:population":0,
    "gn:timezone":"Asia/Taipei",
    "iso:country":"TW",
    "name:und_x_variant":[
        "Yuancyuan"
    ],
    "name:zho_x_preferred":[
        "Y\u00fcan-ch\u2019\u00fcan-ts\u2019un"
    ],
    "name:zho_x_variant":[
        "\u6e90\u6cc9",
        "Y\u00fcan-ch\u2019\u00fcan"
    ],
    "wof:name":"Yuanquan",
    "wof:placetype":"locality"
},
  "geometry": {"coordinates":[120.64236,23.79879],"type":"Point"}
}