{
  "type": "Feature",
  "properties": {
    "iso:country":"TW",
    "qs:name":"\u6771\u5e73\u91cc",
    "qs:name_adm0":"\u81fa\u7063",
    "qs:name_adm1":"\u5609\u7fa9\u5e02",
    "qs:photos":143,
    "qs:photos_1k":29,
    "qs:photos_9k":1,
    "qs:photos_9r":3,
    "qs:photos_all":143,
    "qs:photos_sr":3,
    "qs:placetype":"Suburb",
    "qs:pop_sr":"0",
    "wof:name":"\u6771\u5e73\u91cc",
    "wof:placetype":"neighbourhood"
},
  "geometry": {"coordinates":[120.45935799999999,23.483705],"type":"Point"}
}