{
  "type": "Feature",
  "properties": {
    "iso:country":"TW",
    "name:eng_x_preferred":[
        "Baode"
    ],
    "name:eng_x_variant":[
        "Baode Village"
    ],
    "name:zho_tw_x_preferred":[
        "\u4fdd\u5fb7\u91cc"
    ],
    "qs:name":"\u4fdd\u5fb7\u91cc",
    "qs:name_adm0":"\u81fa\u7063",
    "qs:name_adm1":"\u53f0\u5317\u5e02",
    "qs:photos":135,
    "qs:photos_1k":27,
    "qs:photos_9k":1,
    "qs:photos_9r":3,
    "qs:photos_all":135,
    "qs:photos_sr":3,
    "qs:placetype":"Suburb",
    "qs:pop_sr":"0",
    "wof:name":"Baode",
    "wof:placetype":"neighbourhood"
},
  "geometry": {"coordinates":[121.496365,25.023784],"type":"Point"}
}