{
  "type": "Feature",
  "properties": {
    "gn:admin1_code":"04",
    "gn:admin2_code":"MIA",
    "gn:admin3_code":"K16",
    "gn:admin4_code":"10005070009.0",
    "gn:asciiname":"Neiwan",
    "gn:country_code":"TW",
    "gn:dem":394,
    "gn:feature_class":"P",
    "gn:feature_code":"PPL",
    "gn:name":"Neiwan",
    "gn:population":0,
    "gn:timezone":"Asia/Taipei",
    "iso:country":"TW",
    "name:und_x_variant":[
        "Hsin-hsing-li",
        "Neiwan",
        "Nei-wan",
        "\u5185\u7063"
    ],
    "name:zho_x_preferred":[
        "\u5185\u7063"
    ],
    "wof:name":"Neiwan",
    "wof:placetype":"locality"
},
  "geometry": {"coordinates":[120.84622,24.29742],"type":"Point"}
}