{
  "type": "Feature",
  "properties": {
    "gn:admin1_code":"4.0",
    "gn:admin2_code":"YUN",
    "gn:admin3_code":"P20",
    "gn:admin4_code":"10009200004.0",
    "gn:asciiname":"Huangcuoliao",
    "gn:country_code":"TW",
    "gn:dem":8,
    "gn:feature_class":"P",
    "gn:feature_code":"PPL",
    "gn:name":"Huangcuoliao",
    "gn:population":0,
    "gn:timezone":"Asia/Taipei",
    "iso:country":"TW",
    "name:zho_x_preferred":[
        "\u9ec3\u539d\u5bee"
    ],
    "name:zho_x_variant":[
        "Huang-ts\u2019o-liao"
    ],
    "wof:name":"Huangcuoliao",
    "wof:placetype":"locality"
},
  "geometry": {"coordinates":[120.25972,23.56694],"type":"Point"}
}