{
  "type": "Feature",
  "properties": {
    "iso:country":"TW",
    "label:eng_x_preferred_longname":[
        "Manzhou Township"
    ],
    "label:eng_x_preferred_placetype":[
        "township"
    ],
    "name:eng_x_preferred":[
        "Manzhou"
    ],
    "name:eng_x_variant":[
        "Manzhou Township"
    ],
    "name:fra_x_preferred":[
        "Manzhou"
    ],
    "name:zho_tw_x_preferred":[
        "\u6eff\u5dde\u9109"
    ],
    "qs:name":"\u6eff\u5dde\u9109",
    "qs:name_adm0":"\u81fa\u7063",
    "qs:name_adm1":"\u5c4f\u6771\u7e23",
    "qs:photos":1337,
    "qs:photos_1k":271,
    "qs:photos_9k":27,
    "qs:photos_9r":14,
    "qs:photos_all":6094,
    "qs:photos_sr":12,
    "qs:placetype":"County",
    "qs:pop_sr":"0",
    "wof:name":"Manzhou",
    "wof:placetype":"county"
},
  "geometry": {"coordinates":[120.848552,21.9274],"type":"Point"}
}