{
  "type": "Feature",
  "properties": {
    "gn:admin1_code":"3.0",
    "gn:admin2_code":"TPQ",
    "gn:admin3_code":"F02",
    "gn:admin4_code":"65000170005.0",
    "gn:asciiname":"Songbaijiao",
    "gn:country_code":"TW",
    "gn:dem":238,
    "gn:feature_class":"P",
    "gn:feature_code":"PPL",
    "gn:name":"Songbaijiao",
    "gn:population":0,
    "gn:timezone":"Asia/Taipei",
    "iso:country":"TW",
    "name:und_x_variant":[
        "Sung-pai-chiao"
    ],
    "name:zho_x_preferred":[
        "\u677e\u67cf\u811a"
    ],
    "wof:name":"Songbaijiao",
    "wof:placetype":"locality"
},
  "geometry": {"coordinates":[121.37656,25.09131],"type":"Point"}
}