{
  "type": "Feature",
  "properties": {
    "gn:admin1_code":"04",
    "gn:admin2_code":"TNN",
    "gn:admin3_code":"R29",
    "gn:admin4_code":"67000290012.0",
    "gn:asciiname":"Shenkeng",
    "gn:country_code":"TW",
    "gn:dem":35,
    "gn:feature_class":"P",
    "gn:feature_code":"PPL",
    "gn:name":"Shenkeng",
    "gn:population":0,
    "gn:timezone":"Asia/Taipei",
    "iso:country":"TW",
    "name:zho_x_preferred":[
        "Shen-k\u2019eng-ts\u2019un"
    ],
    "name:zho_x_variant":[
        "Shen-k\u2019eng-tzu",
        "\u6df1\u5751",
        "Shen-k\u2019eng"
    ],
    "wof:name":"Shenkeng",
    "wof:placetype":"locality"
},
  "geometry": {"coordinates":[120.33417,22.93889],"type":"Point"}
}