{
  "type": "Feature",
  "properties": {
    "gn:admin1_code":"2.0",
    "gn:admin2_code":"KHH",
    "gn:admin3_code":"E17",
    "gn:admin4_code":"64000170010.0",
    "gn:asciiname":"Hougang",
    "gn:country_code":"TW",
    "gn:dem":11,
    "gn:feature_class":"P",
    "gn:feature_code":"PPL",
    "gn:name":"Hougang",
    "gn:population":0,
    "gn:timezone":"Asia/Taipei",
    "iso:country":"TW",
    "name:und_x_variant":[
        "Hou-chiang-tzu",
        "Hou-kang",
        "\u5f8c\u6e2f",
        "Hou-kang-tzu",
        "Hougang"
    ],
    "name:zho_x_preferred":[
        "\u5f8c\u6e2f"
    ],
    "wof:name":"Hougang",
    "wof:placetype":"locality"
},
  "geometry": {"coordinates":[120.3262,22.6808],"type":"Point"}
}