{
  "type": "Feature",
  "properties": {
    "gn:admin1_code":"04",
    "gn:admin2_code":"PIF",
    "gn:admin3_code":"T09",
    "gn:admin4_code":"10013090014.0",
    "gn:asciiname":"Milidu",
    "gn:country_code":"TW",
    "gn:dem":41,
    "gn:feature_class":"P",
    "gn:feature_code":"PPL",
    "gn:name":"Milidu",
    "gn:population":0,
    "gn:timezone":"Asia/Taipei",
    "iso:country":"TW",
    "name:und_x_variant":[
        "Mi-li",
        "Milidu",
        "Mi-li-tu"
    ],
    "name:zho_x_preferred":[
        "Mi-li-ts\u2019un"
    ],
    "name:zho_x_variant":[
        "\u5f4c\u529b\u809a"
    ],
    "wof:name":"Milidu",
    "wof:placetype":"locality"
},
  "geometry": {"coordinates":[120.49111000000001,22.82111],"type":"Point"}
}