{
  "type": "Feature",
  "properties": {
    "gn:admin1_code":"04",
    "gn:admin2_code":"ILA",
    "gn:admin3_code":"G08",
    "gn:admin4_code":"10002080006.0",
    "gn:asciiname":"Neicheng",
    "gn:country_code":"TW",
    "gn:dem":22,
    "gn:feature_class":"P",
    "gn:feature_code":"PPL",
    "gn:name":"Neicheng",
    "gn:population":0,
    "gn:timezone":"Asia/Taipei",
    "iso:country":"TW",
    "name:zho_x_preferred":[
        "\u5167\u57ce"
    ],
    "name:zho_x_variant":[
        "Nei-ch\u2019eng"
    ],
    "wof:name":"Neicheng",
    "wof:placetype":"locality"
},
  "geometry": {"coordinates":[121.80800000000001,24.62076],"type":"Point"}
}