{
  "type": "Feature",
  "properties": {
    "gn:admin1_code":"4.0",
    "gn:admin2_code":"CHA",
    "gn:admin3_code":"N06",
    "gn:admin4_code":"10007110025.0",
    "gn:asciiname":"Xincuoguan",
    "gn:country_code":"TW",
    "gn:dem":21,
    "gn:feature_class":"P",
    "gn:feature_code":"PPL",
    "gn:name":"Xincuoguan",
    "gn:population":0,
    "gn:timezone":"Asia/Taipei",
    "iso:country":"TW",
    "name:und_x_variant":[
        "Sincuoguan"
    ],
    "name:zho_x_preferred":[
        "\u65b0\u539d\u9928"
    ],
    "name:zho_x_variant":[
        "Hsin-ts\u2019o-kuan"
    ],
    "wof:name":"Xincuoguan",
    "wof:placetype":"locality"
},
  "geometry": {"coordinates":[120.4867,23.9245],"type":"Point"}
}