{
  "type": "Feature",
  "properties": {
    "gn:admin1_code":"4.0",
    "gn:admin2_code":"YUN",
    "gn:admin3_code":"P12",
    "gn:admin4_code":"10009120003.0",
    "gn:asciiname":"Xinqiliao",
    "gn:country_code":"TW",
    "gn:dem":20,
    "gn:feature_class":"P",
    "gn:feature_code":"PPL",
    "gn:name":"Xinqiliao",
    "gn:population":0,
    "gn:timezone":"Asia/Taipei",
    "iso:country":"TW",
    "name:und_x_variant":[
        "Sinciliao"
    ],
    "name:zho_x_preferred":[
        "\u65b0\u8d77\u5bee"
    ],
    "name:zho_x_variant":[
        "Hsin-ch\u2019i-liao"
    ],
    "wof:name":"Xinqiliao",
    "wof:placetype":"locality"
},
  "geometry": {"coordinates":[120.35921999999999,23.75991],"type":"Point"}
}