{
  "type": "Feature",
  "properties": {
    "gn:admin1_code":"4.0",
    "gn:admin2_code":"HSZ",
    "gn:admin3_code":"J08",
    "gn:admin4_code":"10004080002.0",
    "gn:asciiname":"Xiawanzi",
    "gn:country_code":"TW",
    "gn:dem":168,
    "gn:feature_class":"P",
    "gn:feature_code":"PPL",
    "gn:name":"Xiawanzi",
    "gn:population":0,
    "gn:timezone":"Asia/Taipei",
    "iso:country":"TW",
    "name:und_x_variant":[
        "Siawanzih",
        "Xiawanzi",
        "Hsia-wan-tzu"
    ],
    "name:zho_x_preferred":[
        "\u4e0b\u7063\u5b50"
    ],
    "wof:name":"Xiawanzi",
    "wof:placetype":"locality"
},
  "geometry": {"coordinates":[121.11,24.71194],"type":"Point"}
}