{
  "type": "Feature",
  "properties": {
    "gn:admin1_code":"4.0",
    "gn:admin2_code":"CHA",
    "gn:admin3_code":"N03",
    "gn:admin4_code":"10007030018.0",
    "gn:asciiname":"Jializhuang",
    "gn:country_code":"TW",
    "gn:dem":17,
    "gn:feature_class":"P",
    "gn:feature_code":"PPL",
    "gn:name":"Jializhuang",
    "gn:population":0,
    "gn:timezone":"Asia/Taipei",
    "iso:country":"TW",
    "name:und_x_variant":[
        "Chia-li",
        "\u5609\u7282\u838a",
        "Jializhuang",
        "Jialijhuang",
        "Chia-li-chuang"
    ],
    "wof:name":"Jializhuang",
    "wof:placetype":"locality"
},
  "geometry": {"coordinates":[120.52177,24.09098],"type":"Point"}
}