{
  "type": "Feature",
  "properties": {
    "gn:admin1_code":"4.0",
    "gn:admin2_code":"HUA",
    "gn:admin3_code":"U11",
    "gn:admin4_code":"10015110002.0",
    "gn:asciiname":"Xinbaiyang",
    "gn:country_code":"TW",
    "gn:dem":1459,
    "gn:feature_class":"P",
    "gn:feature_code":"PPL",
    "gn:name":"Xinbaiyang",
    "gn:population":0,
    "gn:timezone":"Asia/Taipei",
    "iso:country":"TW",
    "name:und_x_variant":[
        "Sinbaiyang",
        "Hsin-pai-yang"
    ],
    "name:zho_x_preferred":[
        "\u65b0\u767d\u694a"
    ],
    "wof:name":"Xinbaiyang",
    "wof:placetype":"locality"
},
  "geometry": {"coordinates":[121.43028,24.19778],"type":"Point"}
}