{
  "type": "Feature",
  "properties": {
    "gn:admin1_code":"04",
    "gn:admin2_code":"CHA",
    "gn:admin3_code":"N15",
    "gn:admin4_code":"10007130003.0",
    "gn:asciiname":"Shuijue",
    "gn:country_code":"TW",
    "gn:dem":21,
    "gn:feature_class":"P",
    "gn:feature_code":"PPL",
    "gn:name":"Shuijue",
    "gn:population":0,
    "gn:timezone":"Asia/Taipei",
    "iso:country":"TW",
    "name:und_x_variant":[
        "Shui-ch\u2019\u00fceh"
    ],
    "wof:name":"Shuijue",
    "wof:placetype":"locality"
},
  "geometry": {"coordinates":[120.55,23.98333],"type":"Point"}
}