{
  "type": "Feature",
  "properties": {
    "gn:admin1_code":"4.0",
    "gn:admin2_code":"TAO",
    "gn:admin3_code":"H10",
    "gn:admin4_code":"68000100027.0",
    "gn:asciiname":"Dakengque",
    "gn:country_code":"TW",
    "gn:dem":175,
    "gn:feature_class":"P",
    "gn:feature_code":"PPL",
    "gn:name":"Dakengque",
    "gn:population":0,
    "gn:timezone":"Asia/Taipei",
    "iso:country":"TW",
    "name:und_x_variant":[
        "Dakengcyue"
    ],
    "name:zho_x_preferred":[
        "\u5927\u5751\u7f3a"
    ],
    "name:zho_x_variant":[
        "Ta-k\u2019eng-ch\u2019\u00fceh"
    ],
    "wof:name":"Dakengque",
    "wof:placetype":"locality"
},
  "geometry": {"coordinates":[121.19222000000001,24.90222],"type":"Point"}
}