{
  "type": "Feature",
  "properties": {
    "gn:admin1_code":"4.0",
    "gn:admin2_code":"TPE",
    "gn:admin3_code":"A10",
    "gn:admin4_code":"63000040013.0",
    "gn:asciiname":"Fanshe",
    "gn:country_code":"TW",
    "gn:dem":37,
    "gn:feature_class":"P",
    "gn:feature_code":"PPL",
    "gn:name":"Fanshe",
    "gn:population":0,
    "gn:timezone":"Asia/Taipei",
    "iso:country":"TW",
    "name:und_x_variant":[
        "Fan-she"
    ],
    "wof:name":"Fanshe",
    "wof:placetype":"locality"
},
  "geometry": {"coordinates":[121.53333000000001,25.08333],"type":"Point"}
}