{
  "type": "Feature",
  "properties": {
    "gn:admin1_code":"4.0",
    "gn:admin2_code":"TTT",
    "gn:admin3_code":"V10",
    "gn:admin4_code":"10014060006.0",
    "gn:asciiname":"Jinyuan",
    "gn:country_code":"TW",
    "gn:dem":276,
    "gn:feature_class":"P",
    "gn:feature_code":"PPL",
    "gn:name":"Jinyuan",
    "gn:population":0,
    "gn:timezone":"Asia/Taipei",
    "iso:country":"TW",
    "name:zho_x_preferred":[
        "Hsin-k\u2019ai-y\u00fcan"
    ],
    "name:zho_x_variant":[
        "Chin-y\u00fcan-ts\u2019un",
        "\u9326\u5712",
        "Chin-y\u00fcan"
    ],
    "wof:name":"Jinyuan",
    "wof:placetype":"locality"
},
  "geometry": {"coordinates":[121.22167,23.10306],"type":"Point"}
}