{
  "type": "Feature",
  "properties": {
    "gn:admin1_code":"04",
    "gn:admin2_code":"PIF",
    "gn:admin3_code":"T32",
    "gn:admin4_code":"10013320007.0",
    "gn:asciiname":"Neishitou",
    "gn:country_code":"TW",
    "gn:dem":637,
    "gn:feature_class":"P",
    "gn:feature_code":"PPL",
    "gn:name":"Neishitou",
    "gn:population":0,
    "gn:timezone":"Asia/Taipei",
    "iso:country":"TW",
    "name:und_x_variant":[
        "Nei-shih-t\u2019ou-she",
        "Nei-shih-ts\u2019un",
        "\u5185\u7345\u982d",
        "Neishihtou",
        "Neishitou",
        "Nei-shih"
    ],
    "name:zho_x_preferred":[
        "Nei-shih-t\u2019ou"
    ],
    "wof:name":"Neishitou",
    "wof:placetype":"locality"
},
  "geometry": {"coordinates":[120.69,22.30472],"type":"Point"}
}