{
  "type": "Feature",
  "properties": {
    "gn:admin1_code":"4.0",
    "gn:admin2_code":"TTT",
    "gn:admin3_code":"V05",
    "gn:admin4_code":"10014100004.0",
    "gn:asciiname":"Mayuan",
    "gn:country_code":"TW",
    "gn:dem":16,
    "gn:feature_class":"P",
    "gn:feature_code":"PPL",
    "gn:name":"Mayuan",
    "gn:population":0,
    "gn:timezone":"Asia/Taipei",
    "iso:country":"TW",
    "name:zho_x_preferred":[
        "\u9ebb\u5712"
    ],
    "name:zho_x_variant":[
        "Ma-y\u00fcan"
    ],
    "wof:name":"Mayuan",
    "wof:placetype":"locality"
},
  "geometry": {"coordinates":[120.88861,22.34417],"type":"Point"}
}