{
  "type": "Feature",
  "properties": {
    "gn:admin1_code":"02",
    "gn:admin2_code":"KHH",
    "gn:admin3_code":"E27",
    "gn:admin4_code":"64000270003.0",
    "gn:asciiname":"Wulintou",
    "gn:country_code":"TW",
    "gn:dem":-1,
    "gn:feature_class":"P",
    "gn:feature_code":"PPL",
    "gn:name":"Wulintou",
    "gn:population":0,
    "gn:timezone":"Asia/Taipei",
    "iso:country":"TW",
    "name:und_x_variant":[
        "Chi-ting",
        "Wulintou"
    ],
    "name:zho_x_preferred":[
        "Chi-ting-ts\u2019un"
    ],
    "name:zho_x_variant":[
        "\u70cf\u6797\u6295",
        "Wu-lin-t\u2019ou"
    ],
    "wof:name":"Wulintou",
    "wof:placetype":"locality"
},
  "geometry": {"coordinates":[120.20305999999999,22.83694],"type":"Point"}
}