{
  "type": "Feature",
  "properties": {
    "gn:admin1_code":"4.0",
    "gn:admin2_code":"TAO",
    "gn:admin3_code":"H03",
    "gn:admin4_code":"68000020049.0",
    "gn:asciiname":"Chaliao",
    "gn:country_code":"TW",
    "gn:dem":74,
    "gn:feature_class":"P",
    "gn:feature_code":"PPL",
    "gn:name":"Chaliao",
    "gn:population":0,
    "gn:timezone":"Asia/Taipei",
    "iso:country":"TW",
    "name:zho_x_preferred":[
        "\u8336\u5bee"
    ],
    "name:zho_x_variant":[
        "Ch\u2019a-liao"
    ],
    "wof:name":"Chaliao",
    "wof:placetype":"locality"
},
  "geometry": {"coordinates":[121.16902,25.01255],"type":"Point"}
}