{
  "type": "Feature",
  "properties": {
    "gn:admin1_code":"04",
    "gn:admin2_code":"HSZ",
    "gn:admin3_code":"J03",
    "gn:admin4_code":"10004040009.0",
    "gn:asciiname":"Shenli",
    "gn:country_code":"TW",
    "gn:dem":218,
    "gn:feature_class":"P",
    "gn:feature_code":"PPL",
    "gn:name":"Shenli",
    "gn:population":0,
    "gn:timezone":"Asia/Taipei",
    "iso:country":"TW",
    "name:und_x_variant":[
        "Shen-li"
    ],
    "name:zho_x_preferred":[
        "\u6df1\u701d"
    ],
    "wof:name":"Shenli",
    "wof:placetype":"locality"
},
  "geometry": {"coordinates":[121.18611,24.77556],"type":"Point"}
}