{
  "type": "Feature",
  "properties": {
    "gn:admin1_code":"04",
    "gn:admin2_code":"HSZ",
    "gn:admin3_code":"J08",
    "gn:admin4_code":"10004080008.0",
    "gn:asciiname":"Nanshakengqiao",
    "gn:country_code":"TW",
    "gn:dem":254,
    "gn:feature_class":"P",
    "gn:feature_code":"PPL",
    "gn:name":"Nanshakengqiao",
    "gn:population":0,
    "gn:timezone":"Asia/Taipei",
    "iso:country":"TW",
    "name:und_x_variant":[
        "Nan-sha-k\u2019eng-ch\u2019iao"
    ],
    "wof:name":"Nanshakengqiao",
    "wof:placetype":"locality"
},
  "geometry": {"coordinates":[121.15000000000001,24.73333],"type":"Point"}
}