{
  "type": "Feature",
  "properties": {
    "gn:admin1_code":"4.0",
    "gn:admin2_code":"YUN",
    "gn:admin3_code":"P07",
    "gn:admin4_code":"10009070012.0",
    "gn:asciiname":"Kanjiao",
    "gn:country_code":"TW",
    "gn:dem":87,
    "gn:feature_class":"P",
    "gn:feature_code":"PPL",
    "gn:name":"Kanjiao",
    "gn:population":0,
    "gn:timezone":"Asia/Taipei",
    "iso:country":"TW",
    "name:zho_x_preferred":[
        "K\u2019an-chiao-ts\u2019un"
    ],
    "name:zho_x_variant":[
        "\u5d01\u811a",
        "K\u2019an-chiao"
    ],
    "wof:name":"Kanjiao",
    "wof:placetype":"locality"
},
  "geometry": {"coordinates":[120.53222,23.60389],"type":"Point"}
}