{
  "type": "Feature",
  "properties": {
    "gn:admin1_code":"04",
    "gn:admin2_code":"CHA",
    "gn:admin3_code":"N02",
    "gn:admin4_code":"10007020022.0",
    "gn:asciiname":"Qipancuo",
    "gn:country_code":"TW",
    "gn:dem":13,
    "gn:feature_class":"P",
    "gn:feature_code":"PPL",
    "gn:name":"Qipancuo",
    "gn:population":0,
    "gn:timezone":"Asia/Taipei",
    "iso:country":"TW",
    "name:und_x_variant":[
        "Cipancuo",
        "Qipancuo"
    ],
    "name:zho_x_preferred":[
        "Kou-ch\u2019ien-she-ch\u2019u"
    ],
    "name:zho_x_variant":[
        "Pei-ma-ts\u2019o",
        "\u68cb\u76e4\u539d",
        "Ch\u2019i-p\u2019an-ts\u2019o"
    ],
    "wof:name":"Qipancuo",
    "wof:placetype":"locality"
},
  "geometry": {"coordinates":[120.47499999999999,24.065],"type":"Point"}
}