{
  "type": "Feature",
  "properties": {
    "gn:admin1_code":"3.0",
    "gn:admin2_code":"TPQ",
    "gn:admin3_code":"F08",
    "gn:admin4_code":"65000190011.0",
    "gn:asciiname":"Gangou",
    "gn:country_code":"TW",
    "gn:dem":216,
    "gn:feature_class":"P",
    "gn:feature_code":"PPL",
    "gn:name":"Gangou",
    "gn:population":0,
    "gn:timezone":"Asia/Taipei",
    "iso:country":"TW",
    "name:und_x_variant":[
        "Kan-kou"
    ],
    "name:zho_x_preferred":[
        "\u4e7e\u6e9d"
    ],
    "name:zho_x_variant":[
        "Kan-kou-ts\u2019un"
    ],
    "wof:name":"Gangou",
    "wof:placetype":"locality"
},
  "geometry": {"coordinates":[121.6276,24.9188],"type":"Point"}
}