{
  "type": "Feature",
  "properties": {
    "gn:admin1_code":"03",
    "gn:admin2_code":"TPQ",
    "gn:admin3_code":"F09",
    "gn:admin4_code":"65000180005.0",
    "gn:asciiname":"Dalunwei",
    "gn:country_code":"TW",
    "gn:dem":418,
    "gn:feature_class":"P",
    "gn:feature_code":"PPL",
    "gn:name":"Dalunwei",
    "gn:population":0,
    "gn:timezone":"Asia/Taipei",
    "iso:country":"TW",
    "name:und_x_variant":[
        "Ta-lun-wei"
    ],
    "name:zho_x_preferred":[
        "\u5927\u5d19\u5c3e"
    ],
    "wof:name":"Dalunwei",
    "wof:placetype":"locality"
},
  "geometry": {"coordinates":[121.61642000000001,24.97482],"type":"Point"}
}