{
  "type": "Feature",
  "properties": {
    "iso:country":"TW",
    "qs:name":"\u5149\u6b66\u91cc",
    "qs:name_adm0":"\u81fa\u7063",
    "qs:name_adm1":"\u53f0\u5357\u5e02",
    "qs:photos":54,
    "qs:photos_1k":11,
    "qs:photos_9k":1,
    "qs:photos_9r":2,
    "qs:photos_all":54,
    "qs:photos_sr":2,
    "qs:placetype":"Suburb",
    "qs:pop_sr":"0",
    "wof:name":"\u5149\u6b66\u91cc",
    "wof:placetype":"neighbourhood"
},
  "geometry": {"coordinates":[120.21542700000001,23.013198],"type":"Point"}
}