{
  "type": "Feature",
  "properties": {
    "gn:admin1_code":"4.0",
    "gn:admin2_code":"CYQ",
    "gn:admin3_code":"Q15",
    "gn:admin4_code":"10010140015.0",
    "gn:asciiname":"Xiaping",
    "gn:country_code":"TW",
    "gn:dem":279,
    "gn:feature_class":"P",
    "gn:feature_code":"PPL",
    "gn:name":"Xiaping",
    "gn:population":0,
    "gn:timezone":"Asia/Taipei",
    "iso:country":"TW",
    "name:und_x_variant":[
        "Siaping",
        "Xiaping"
    ],
    "name:zho_x_preferred":[
        "\u4e0b\u576a"
    ],
    "name:zho_x_variant":[
        "Hsia-p\u2019ing"
    ],
    "wof:name":"Xiaping",
    "wof:placetype":"locality"
},
  "geometry": {"coordinates":[120.57917,23.50139],"type":"Point"}
}