{
  "type": "Feature",
  "properties": {
    "gn:admin1_code":"02",
    "gn:admin2_code":"KHH",
    "gn:admin3_code":"E23",
    "gn:admin4_code":"64000230005.0",
    "gn:asciiname":"Piziwei",
    "gn:country_code":"TW",
    "gn:dem":24,
    "gn:feature_class":"P",
    "gn:feature_code":"PPL",
    "gn:name":"Piziwei",
    "gn:population":0,
    "gn:timezone":"Asia/Taipei",
    "iso:country":"TW",
    "name:und_x_variant":[
        "Pei-tzu-wei",
        "Piziwei",
        "Pizihwei"
    ],
    "name:zho_x_preferred":[
        "\u57e4\u5b50\u5c3e"
    ],
    "name:zho_x_variant":[
        "P\u2019i-tzu-wei"
    ],
    "wof:name":"Piziwei",
    "wof:placetype":"locality"
},
  "geometry": {"coordinates":[120.33333,22.86028],"type":"Point"}
}