{
  "type": "Feature",
  "properties": {
    "gn:admin1_code":"3.0",
    "gn:admin2_code":"TPQ",
    "gn:admin3_code":"F06",
    "gn:admin4_code":"65000160012.0",
    "gn:asciiname":"Tianweizi",
    "gn:country_code":"TW",
    "gn:dem":5,
    "gn:feature_class":"P",
    "gn:feature_code":"PPL",
    "gn:name":"Tianweizi",
    "gn:population":0,
    "gn:timezone":"Asia/Taipei",
    "iso:country":"TW",
    "name:und_x_variant":[
        "Tianweizih"
    ],
    "name:zho_x_preferred":[
        "\u7530\u5c3e\u4ed4"
    ],
    "name:zho_x_variant":[
        "T\u2019ien-wei-tzu"
    ],
    "wof:name":"Tianweizi",
    "wof:placetype":"locality"
},
  "geometry": {"coordinates":[121.43697,25.04468],"type":"Point"}
}