{
  "type": "Feature",
  "properties": {
    "gn:admin1_code":"04",
    "gn:admin2_code":"NAN",
    "gn:admin3_code":"M05",
    "gn:admin4_code":"10008050002.0",
    "gn:asciiname":"Yanshui",
    "gn:country_code":"TW",
    "gn:dem":271,
    "gn:feature_class":"P",
    "gn:feature_code":"PPL",
    "gn:name":"Yanshui",
    "gn:population":0,
    "gn:timezone":"Asia/Taipei",
    "iso:country":"TW",
    "name:und_x_variant":[
        "Yanshuei",
        "Yanshui",
        "Yen-shui"
    ],
    "name:zho_x_preferred":[
        "\u9e7d\u6c34"
    ],
    "wof:name":"Yanshui",
    "wof:placetype":"locality"
},
  "geometry": {"coordinates":[120.77097999999999,23.84183],"type":"Point"}
}