{
  "type": "Feature",
  "properties": {
    "gn:admin1_code":"4.0",
    "gn:admin2_code":"MIA",
    "gn:admin3_code":"K04",
    "gn:admin4_code":"10005090019.0",
    "gn:asciiname":"Ankengzi",
    "gn:country_code":"TW",
    "gn:dem":220,
    "gn:feature_class":"P",
    "gn:feature_code":"PPL",
    "gn:name":"Ankengzi",
    "gn:population":0,
    "gn:timezone":"Asia/Taipei",
    "iso:country":"TW",
    "name:und_x_variant":[
        "Ankengzih",
        "Ankengzi"
    ],
    "name:zho_x_preferred":[
        "\u6697\u5751\u5b50"
    ],
    "name:zho_x_variant":[
        "An-k\u2019eng-tzu"
    ],
    "wof:name":"Ankengzi",
    "wof:placetype":"locality"
},
  "geometry": {"coordinates":[120.87033999999998,24.53036],"type":"Point"}
}