{
  "type": "Feature",
  "properties": {
    "gn:admin1_code":"4.0",
    "gn:admin2_code":"NAN",
    "gn:admin3_code":"M11",
    "gn:admin4_code":"10008110015.0",
    "gn:asciiname":"Shangwan",
    "gn:country_code":"TW",
    "gn:dem":339,
    "gn:feature_class":"P",
    "gn:feature_code":"PPL",
    "gn:name":"Shangwan",
    "gn:population":0,
    "gn:timezone":"Asia/Taipei",
    "iso:country":"TW",
    "name:und_x_variant":[
        "Shang-wan"
    ],
    "name:zho_x_preferred":[
        "\u4e0a\u7063"
    ],
    "wof:name":"Shangwan",
    "wof:placetype":"locality"
},
  "geometry": {"coordinates":[120.89855,23.79006],"type":"Point"}
}