{
  "type": "Feature",
  "properties": {
    "iso:country":"TW",
    "qs:name":"\u4fdd\u5b89\u91cc",
    "qs:name_adm0":"\u81fa\u7063",
    "qs:name_adm1":"\u5609\u7fa9\u5e02",
    "qs:photos":44,
    "qs:photos_1k":9,
    "qs:photos_9k":1,
    "qs:photos_9r":2,
    "qs:photos_all":44,
    "qs:photos_sr":2,
    "qs:placetype":"Suburb",
    "qs:pop_sr":"0",
    "wof:name":"\u4fdd\u5b89\u91cc",
    "wof:placetype":"neighbourhood"
},
  "geometry": {"coordinates":[120.434833,23.491833],"type":"Point"}
}