{
  "type": "Feature",
  "properties": {
    "gn:admin1_code":"4.0",
    "gn:admin2_code":"NAN",
    "gn:admin3_code":"M09",
    "gn:admin4_code":"10008090006.0",
    "gn:asciiname":"Xiamuji",
    "gn:country_code":"TW",
    "gn:dem":649,
    "gn:feature_class":"P",
    "gn:feature_code":"PPL",
    "gn:name":"Xiamuji",
    "gn:population":0,
    "gn:timezone":"Asia/Taipei",
    "iso:country":"TW",
    "name:und_x_variant":[
        "Siamuji",
        "Xiamuji",
        "Hsia-mu-chi"
    ],
    "name:zho_x_preferred":[
        "\u4e0b\u6728\u5c50"
    ],
    "wof:name":"Xiamuji",
    "wof:placetype":"locality"
},
  "geometry": {"coordinates":[120.96034,23.89284],"type":"Point"}
}