{
  "type": "Feature",
  "properties": {
    "gn:admin1_code":"4.0",
    "gn:admin2_code":"PEN",
    "gn:admin3_code":"X02",
    "gn:admin4_code":"10016020007.0",
    "gn:asciiname":"Daohuotou",
    "gn:country_code":"TW",
    "gn:dem":4,
    "gn:feature_class":"P",
    "gn:feature_code":"PPL",
    "gn:name":"Daohuotou",
    "gn:population":0,
    "gn:timezone":"Asia/Taipei",
    "iso:country":"TW",
    "name:und_x_variant":[
        "\u5012\u6d3b\u982d",
        "Daohuotou"
    ],
    "name:zho_x_preferred":[
        "Tao-huo-t\u2019ou"
    ],
    "name:zho_x_variant":[
        "\u5012\u6d3b\u982d"
    ],
    "wof:name":"Daohuotou",
    "wof:placetype":"locality"
},
  "geometry": {"coordinates":[119.63885999999999,23.5988],"type":"Point"}
}