{
  "type": "Feature",
  "properties": {
    "gn:admin1_code":"01",
    "gn:admin2_code":"KIN",
    "gn:admin3_code":"W01",
    "gn:admin4_code":"9020030007.0",
    "gn:asciiname":"Dongshawei",
    "gn:country_code":"TW",
    "gn:dem":18,
    "gn:feature_class":"P",
    "gn:feature_code":"PPL",
    "gn:name":"Dongshawei",
    "gn:population":0,
    "gn:timezone":"Asia/Taipei",
    "iso:country":"TW",
    "name:und_x_variant":[
        "Tung-sha-wei"
    ],
    "name:zho_x_preferred":[
        "\u6771\u6c99\u5c3e"
    ],
    "wof:name":"Dongshawei",
    "wof:placetype":"locality"
},
  "geometry": {"coordinates":[118.44806,24.44667],"type":"Point"}
}