{
  "type": "Feature",
  "properties": {
    "gn:admin1_code":"04",
    "gn:admin2_code":"HSZ",
    "gn:admin3_code":"J03",
    "gn:admin4_code":"10004040015.0",
    "gn:asciiname":"Shigangzi",
    "gn:country_code":"TW",
    "gn:dem":85,
    "gn:feature_class":"P",
    "gn:feature_code":"PPL",
    "gn:name":"Shigangzi",
    "gn:population":0,
    "gn:timezone":"Asia/Taipei",
    "iso:country":"TW",
    "name:und_x_variant":[
        "Shih-kuang",
        "Shihgangzih",
        "Shigangzi",
        "Shih-kang-tzu"
    ],
    "name:zho_x_preferred":[
        "\u77f3\u5ca1\u5b50"
    ],
    "wof:name":"Shigangzi",
    "wof:placetype":"locality"
},
  "geometry": {"coordinates":[121.125,24.81528],"type":"Point"}
}