{
  "type": "Feature",
  "properties": {
    "gn:admin1_code":"4.0",
    "gn:admin2_code":"NAN",
    "gn:admin3_code":"M08",
    "gn:admin4_code":"10008080004.0",
    "gn:asciiname":"Tanliao",
    "gn:country_code":"TW",
    "gn:dem":512,
    "gn:feature_class":"P",
    "gn:feature_code":"PPL",
    "gn:name":"Tanliao",
    "gn:population":0,
    "gn:timezone":"Asia/Taipei",
    "iso:country":"TW",
    "name:zho_x_preferred":[
        "\u70ad\u5bee"
    ],
    "name:zho_x_variant":[
        "T\u2019an-liao"
    ],
    "wof:name":"Tanliao",
    "wof:placetype":"locality"
},
  "geometry": {"coordinates":[120.82229,23.91919],"type":"Point"}
}