{
  "type": "Feature",
  "properties": {
    "gn:admin1_code":"4.0",
    "gn:admin2_code":"MIA",
    "gn:admin3_code":"K13",
    "gn:admin4_code":"10005160007.0",
    "gn:asciiname":"Wuliaowo",
    "gn:country_code":"TW",
    "gn:dem":36,
    "gn:feature_class":"P",
    "gn:feature_code":"PPL",
    "gn:name":"Wuliaowo",
    "gn:population":0,
    "gn:timezone":"Asia/Taipei",
    "iso:country":"TW",
    "name:und_x_variant":[
        "Wu-liao-wo"
    ],
    "name:zho_x_preferred":[
        "\u4e94\u5bee\u7aa9"
    ],
    "wof:name":"Wuliaowo",
    "wof:placetype":"locality"
},
  "geometry": {"coordinates":[120.91262,24.61783],"type":"Point"}
}