{
  "type": "Feature",
  "properties": {
    "iso:country":"TW",
    "name:eng_x_preferred":[
        "Jinhua"
    ],
    "name:eng_x_variant":[
        "Jinhua Village"
    ],
    "name:hun_x_preferred":[
        "Jinhua"
    ],
    "name:zho_tw_x_preferred":[
        "\u9326\u83ef\u91cc"
    ],
    "qs:name":"\u9326\u83ef\u91cc",
    "qs:name_adm0":"\u81fa\u7063",
    "qs:name_adm1":"\u65b0\u7af9\u5e02",
    "qs:photos":693,
    "qs:photos_1k":140,
    "qs:photos_9k":3,
    "qs:photos_9r":5,
    "qs:photos_all":693,
    "qs:photos_sr":8,
    "qs:placetype":"Suburb",
    "qs:pop_sr":"0",
    "wof:name":"Jinhua",
    "wof:placetype":"neighbourhood"
},
  "geometry": {"coordinates":[120.97499999999999,24.809602],"type":"Point"}
}