{
  "type": "Feature",
  "properties": {
    "gn:admin1_code":"4.0",
    "gn:admin2_code":"CHA",
    "gn:admin3_code":"N14",
    "gn:admin4_code":"10007090012.0",
    "gn:asciiname":"Fuxingkeng",
    "gn:country_code":"TW",
    "gn:dem":123,
    "gn:feature_class":"P",
    "gn:feature_code":"PPL",
    "gn:name":"Fuxingkeng",
    "gn:population":0,
    "gn:timezone":"Asia/Taipei",
    "iso:country":"TW",
    "name:und_x_variant":[
        "\u798f\u8208\u5751",
        "Fusingkeng",
        "Fuxingkeng",
        "Fu-hsing-k\u2019eng"
    ],
    "name:zho_x_preferred":[
        "Fu-hsing-k\u2019eng"
    ],
    "wof:name":"Fuxingkeng",
    "wof:placetype":"locality"
},
  "geometry": {"coordinates":[120.6241,23.994],"type":"Point"}
}