{
  "type": "Feature",
  "properties": {
    "gn:admin1_code":"4.0",
    "gn:admin2_code":"MIA",
    "gn:admin3_code":"K11",
    "gn:admin4_code":"10005150009.0",
    "gn:asciiname":"Datan",
    "gn:country_code":"TW",
    "gn:dem":48,
    "gn:feature_class":"P",
    "gn:feature_code":"PPL",
    "gn:name":"Datan",
    "gn:population":0,
    "gn:timezone":"Asia/Taipei",
    "iso:country":"TW",
    "name:deu_x_preferred":[
        "Datan"
    ],
    "name:ita_x_preferred":[
        "Datan"
    ],
    "name:zho_x_preferred":[
        "\u5927\u6f6d"
    ],
    "name:zho_x_variant":[
        "Ta-t\u2019an"
    ],
    "wof:name":"Datan",
    "wof:placetype":"locality"
},
  "geometry": {"coordinates":[120.82586000000001,24.6348],"type":"Point"}
}