{
  "type": "Feature",
  "properties": {
    "gn:admin1_code":"4.0",
    "gn:admin2_code":"MIA",
    "gn:admin3_code":"K09",
    "gn:admin4_code":"10005040022.0",
    "gn:asciiname":"Luchukeng",
    "gn:country_code":"TW",
    "gn:dem":26,
    "gn:feature_class":"P",
    "gn:feature_code":"PPL",
    "gn:name":"Luchukeng",
    "gn:population":0,
    "gn:timezone":"Asia/Taipei",
    "iso:country":"TW",
    "name:zho_x_preferred":[
        "\u9e7f\u53a8\u5751"
    ],
    "name:zho_x_variant":[
        "Lu-ch\u2019u-k\u2019eng"
    ],
    "wof:name":"Luchukeng",
    "wof:placetype":"locality"
},
  "geometry": {"coordinates":[120.90125,24.73322000000001],"type":"Point"}
}