{
  "type": "Feature",
  "properties": {
    "gn:admin1_code":"4.0",
    "gn:admin2_code":"MIA",
    "gn:admin3_code":"K02",
    "gn:admin4_code":"10005020010.0",
    "gn:asciiname":"Maoyu",
    "gn:country_code":"TW",
    "gn:dem":35,
    "gn:feature_class":"P",
    "gn:feature_code":"PPL",
    "gn:name":"Maoyu",
    "gn:population":0,
    "gn:timezone":"Asia/Taipei",
    "iso:country":"TW",
    "name:jpn_x_preferred":[
        "\u307e\u304a\u3086\u3046\u9b54\u738b\u52c7\u8005"
    ],
    "name:tgl_x_preferred":[
        "Maoyu"
    ],
    "name:und_x_variant":[
        "Chung-cheng-li",
        "Mao-meng",
        "Maoyu"
    ],
    "name:zho_x_preferred":[
        "\u8c93\u76c2"
    ],
    "name:zho_x_variant":[
        "Mao-y\u00fc",
        "\u9b54\u738b\u52c7\u8005"
    ],
    "wof:name":"Maoyu",
    "wof:placetype":"locality"
},
  "geometry": {"coordinates":[120.66361000000001,24.43111],"type":"Point"}
}