{
  "type": "Feature",
  "properties": {
    "iso:country":"TW",
    "name:eng_x_preferred":[
        "Caoshan"
    ],
    "name:eng_x_variant":[
        "Caoshan Village"
    ],
    "name:zho_tw_x_preferred":[
        "\u8349\u5c71\u6751"
    ],
    "qs:name":"\u8349\u5c71\u6751",
    "qs:name_adm0":"\u81fa\u7063",
    "qs:name_adm1":"\u53f0\u5357\u5e02",
    "qs:photos":64,
    "qs:photos_1k":13,
    "qs:photos_9k":1,
    "qs:photos_9r":2,
    "qs:photos_all":64,
    "qs:photos_sr":2,
    "qs:placetype":"Town",
    "qs:pop_sr":"0",
    "wof:name":"Caoshan",
    "wof:placetype":"locality"
},
  "geometry": {"coordinates":[120.441175,22.986324],"type":"Point"}
}