{
  "type": "Feature",
  "properties": {
    "iso:country":"TW",
    "qs:name":"\u8349\u5c71\u6751",
    "qs:name_adm0":"\u81fa\u7063",
    "qs:name_adm1":"\u53f0\u5357\u5e02",
    "qs:photos":64,
    "qs:photos_1k":13,
    "qs:photos_9k":1,
    "qs:photos_9r":2,
    "qs:photos_all":64,
    "qs:photos_sr":2,
    "qs:placetype":"Town",
    "qs:pop_sr":"0",
    "wof:name":"\u8349\u5c71\u6751",
    "wof:placetype":"locality"
},
  "geometry": {"coordinates":[120.44117450000002,22.9863245],"type":"Point"}
}