{
  "type": "Feature",
  "properties": {
    "gn:admin1_code":"4.0",
    "gn:admin2_code":"CYQ",
    "gn:admin3_code":"Q04",
    "gn:admin4_code":"10010040021.0",
    "gn:asciiname":"Huzi",
    "gn:country_code":"TW",
    "gn:dem":40,
    "gn:feature_class":"P",
    "gn:feature_code":"PPL",
    "gn:name":"Huzi",
    "gn:population":0,
    "gn:timezone":"Asia/Taipei",
    "iso:country":"TW",
    "name:ita_x_preferred":[
        "Huzi"
    ],
    "name:swa_x_preferred":[
        "Huzi"
    ],
    "name:und_x_variant":[
        "Huzih",
        "Hu-tzu"
    ],
    "name:zho_x_preferred":[
        "\u6e56\u5b50"
    ],
    "wof:name":"Huzi",
    "wof:placetype":"locality"
},
  "geometry": {"coordinates":[120.46829,23.61664],"type":"Point"}
}