{
  "type": "Feature",
  "properties": {
    "gn:admin1_code":"04",
    "gn:admin2_code":"TNN",
    "gn:admin3_code":"R10",
    "gn:admin4_code":"67000100009.0",
    "gn:asciiname":"Wayaozhuang",
    "gn:country_code":"TW",
    "gn:dem":18,
    "gn:feature_class":"P",
    "gn:feature_code":"PPL",
    "gn:name":"Wayaozhuang",
    "gn:population":0,
    "gn:timezone":"Asia/Taipei",
    "iso:country":"TW",
    "name:und_x_variant":[
        "Wayaojhuang",
        "Wayaozhuang",
        "Wa-yao",
        "Wa-yao-chuang"
    ],
    "name:zho_x_preferred":[
        "\u74e6\u78d8\u838a"
    ],
    "wof:name":"Wayaozhuang",
    "wof:placetype":"locality"
},
  "geometry": {"coordinates":[120.30744,23.18521],"type":"Point"}
}