{
  "type": "Feature",
  "properties": {
    "gn:admin1_code":"4.0",
    "gn:admin2_code":"NAN",
    "gn:admin3_code":"M07",
    "gn:admin4_code":"10008070010.0",
    "gn:asciiname":"Xidicheng",
    "gn:country_code":"TW",
    "gn:dem":380,
    "gn:feature_class":"P",
    "gn:feature_code":"PPL",
    "gn:name":"Xidicheng",
    "gn:population":0,
    "gn:timezone":"Asia/Taipei",
    "iso:country":"TW",
    "name:und_x_variant":[
        "Sidicheng",
        "Xidicheng"
    ],
    "name:zho_x_preferred":[
        "\u6eaa\u5e95\u57ce"
    ],
    "name:zho_x_variant":[
        "Hsi-ti-ch\u2019eng"
    ],
    "wof:name":"Xidicheng",
    "wof:placetype":"locality"
},
  "geometry": {"coordinates":[120.78748,23.75842],"type":"Point"}
}