{
  "type": "Feature",
  "properties": {
    "gn:admin1_code":"4.0",
    "gn:admin2_code":"NAN",
    "gn:admin3_code":"M06",
    "gn:admin4_code":"10008060003.0",
    "gn:asciiname":"Nanzibu",
    "gn:country_code":"TW",
    "gn:dem":214,
    "gn:feature_class":"P",
    "gn:feature_code":"PPL",
    "gn:name":"Nanzibu",
    "gn:population":0,
    "gn:timezone":"Asia/Taipei",
    "iso:country":"TW",
    "name:und_x_variant":[
        "Chung-shan",
        "Nanzihbu",
        "Nanzibu",
        "Nan-tzu-pu"
    ],
    "name:zho_x_preferred":[
        "Chung-shan-ts\u2019un"
    ],
    "name:zho_x_variant":[
        "\u6e73\u4ed4\u57d4"
    ],
    "wof:name":"Nanzibu",
    "wof:placetype":"locality"
},
  "geometry": {"coordinates":[120.6806,23.8381],"type":"Point"}
}