{
  "type": "Feature",
  "properties": {
    "gn:admin1_code":"4.0",
    "gn:admin2_code":"ILA",
    "gn:admin3_code":"G04",
    "gn:admin4_code":"10002060004.0",
    "gn:asciiname":"Xiashe",
    "gn:country_code":"TW",
    "gn:dem":2,
    "gn:feature_class":"P",
    "gn:feature_code":"PPL",
    "gn:name":"Xiashe",
    "gn:population":0,
    "gn:timezone":"Asia/Taipei",
    "iso:country":"TW",
    "name:und_x_variant":[
        "Hsia-chuang",
        "Xiashe",
        "Mao-li-wu-han",
        "Siashe",
        "Hsia-she"
    ],
    "name:zho_x_preferred":[
        "\u4e0b\u793e"
    ],
    "wof:name":"Xiashe",
    "wof:placetype":"locality"
},
  "geometry": {"coordinates":[121.81938999999998,24.72241],"type":"Point"}
}