{
  "type": "Feature",
  "properties": {
    "gn:admin1_code":"4.0",
    "gn:admin2_code":"NAN",
    "gn:admin3_code":"M12",
    "gn:admin4_code":"10008120002.0",
    "gn:asciiname":"Wufensuo",
    "gn:country_code":"TW",
    "gn:dem":2433,
    "gn:feature_class":"P",
    "gn:feature_code":"PPL",
    "gn:name":"Wufensuo",
    "gn:population":0,
    "gn:timezone":"Asia/Taipei",
    "iso:country":"TW",
    "name:und_x_variant":[
        "Wu-fen-so"
    ],
    "name:zho_x_preferred":[
        "\u4e94\u5206\u6240"
    ],
    "wof:name":"Wufensuo",
    "wof:placetype":"locality"
},
  "geometry": {"coordinates":[121.12917,23.75389],"type":"Point"}
}