{
  "type": "Feature",
  "properties": {
    "gn:admin1_code":"3.0",
    "gn:admin2_code":"TPQ",
    "gn:admin3_code":"F27",
    "gn:admin4_code":"65000100012.0",
    "gn:asciiname":"Lanweibu",
    "gn:country_code":"TW",
    "gn:dem":38,
    "gn:feature_class":"P",
    "gn:feature_code":"PPL",
    "gn:name":"Lanweibu",
    "gn:population":0,
    "gn:timezone":"Asia/Taipei",
    "iso:country":"TW",
    "name:und_x_variant":[
        "Lan-wei-pu"
    ],
    "name:zho_x_preferred":[
        "\u703e\u5c3e\u57d4"
    ],
    "wof:name":"Lanweibu",
    "wof:placetype":"locality"
},
  "geometry": {"coordinates":[121.44674000000001,25.18244],"type":"Point"}
}