{
  "type": "Feature",
  "properties": {
    "gn:admin1_code":"4.0",
    "gn:admin2_code":"NAN",
    "gn:admin3_code":"M13",
    "gn:admin4_code":"10008130007.0",
    "gn:asciiname":"Meifeng",
    "gn:country_code":"TW",
    "gn:dem":2115,
    "gn:feature_class":"P",
    "gn:feature_code":"PPL",
    "gn:name":"Meifeng",
    "gn:population":0,
    "gn:timezone":"Asia/Taipei",
    "iso:country":"TW",
    "name:und_x_variant":[
        "Meifong",
        "Mei-feng"
    ],
    "name:zho_x_preferred":[
        "\u6885\u5cef"
    ],
    "wof:name":"Meifeng",
    "wof:placetype":"locality"
},
  "geometry": {"coordinates":[121.18138999999999,24.09611],"type":"Point"}
}