{
  "type": "Feature",
  "properties": {
    "gn:admin1_code":"4.0",
    "gn:admin2_code":"YUN",
    "gn:admin3_code":"P10",
    "gn:admin4_code":"10009100010.0",
    "gn:asciiname":"Jinxing",
    "gn:country_code":"TW",
    "gn:dem":68,
    "gn:feature_class":"P",
    "gn:feature_code":"PPL",
    "gn:name":"Jinxing",
    "gn:population":0,
    "gn:timezone":"Asia/Taipei",
    "iso:country":"TW",
    "name:und_x_variant":[
        "Jinsing",
        "Chin-hsing"
    ],
    "name:zho_x_preferred":[
        "Hsia-ts\u2019o-tzu"
    ],
    "name:zho_x_variant":[
        "\u9032\u8208",
        "Hsia-ts\u2019o"
    ],
    "wof:name":"Jinxing",
    "wof:placetype":"locality"
},
  "geometry": {"coordinates":[120.5835,23.7738],"type":"Point"}
}