{
  "type": "Feature",
  "properties": {
    "gn:admin1_code":"4.0",
    "gn:admin2_code":"YUN",
    "gn:admin3_code":"P19",
    "gn:admin4_code":"10009190006.0",
    "gn:asciiname":"Bazijiao",
    "gn:country_code":"TW",
    "gn:dem":4,
    "gn:feature_class":"P",
    "gn:feature_code":"PPL",
    "gn:name":"Bazijiao",
    "gn:population":0,
    "gn:timezone":"Asia/Taipei",
    "iso:country":"TW",
    "name:und_x_variant":[
        "Kuo-chiang",
        "Bazihjiao",
        "Bazijiao",
        "Kuo-kang",
        "Pa-tzu-chiao"
    ],
    "name:zho_x_preferred":[
        "Kuo-chiang-ts\u2019un"
    ],
    "name:zho_x_variant":[
        "Kuo-Kang-Ts\u2019un",
        "\u62d4\u5b50\u8173"
    ],
    "wof:name":"Bazijiao",
    "wof:placetype":"locality"
},
  "geometry": {"coordinates":[120.19138999999998,23.57639],"type":"Point"}
}