{
  "type": "Feature",
  "properties": {
    "gn:admin1_code":"4.0",
    "gn:admin2_code":"YUN",
    "gn:admin3_code":"P15",
    "gn:admin4_code":"10009150005.0",
    "gn:asciiname":"Maming",
    "gn:country_code":"TW",
    "gn:dem":8,
    "gn:feature_class":"P",
    "gn:feature_code":"PPL",
    "gn:name":"Maming",
    "gn:population":0,
    "gn:timezone":"Asia/Taipei",
    "iso:country":"TW",
    "name:und_x_variant":[
        "Ma-ming"
    ],
    "name:zho_x_preferred":[
        "Liu-k\u2019uai-ts\u2019o"
    ],
    "name:zho_x_variant":[
        "Ma-ming-ts\u2019un",
        "Liu-k\u2019uai-liao",
        "\u99ac\u9cf4"
    ],
    "wof:name":"Maming",
    "wof:placetype":"locality"
},
  "geometry": {"coordinates":[120.27588,23.6966],"type":"Point"}
}