{
  "type": "Feature",
  "properties": {
    "gn:admin1_code":"4.0",
    "gn:admin2_code":"TXG",
    "gn:admin3_code":"B18",
    "gn:admin4_code":"66000180003.0",
    "gn:asciiname":"Qingquangang",
    "gn:country_code":"TW",
    "gn:dem":180,
    "gn:feature_class":"P",
    "gn:feature_code":"PPL",
    "gn:name":"Qingquangang",
    "gn:population":0,
    "gn:timezone":"Asia/Taipei",
    "iso:country":"TW",
    "name:und_x_variant":[
        "Cingcyuangang",
        "Qingquangang",
        "Ch\u2019ing-ch\u2019\u00fcan-kang"
    ],
    "name:zho_x_preferred":[
        "Ch\u2019ing-ch\u2019\u00fcan-kang"
    ],
    "wof:name":"Qingquangang",
    "wof:placetype":"locality"
},
  "geometry": {"coordinates":[120.6268,24.23921],"type":"Point"}
}