{
  "type": "Feature",
  "properties": {
    "gn:admin1_code":"4.0",
    "gn:admin2_code":"TNN",
    "gn:admin3_code":"R29",
    "gn:admin4_code":"67000290002.0",
    "gn:asciiname":"Xiangyangcun",
    "gn:country_code":"TW",
    "gn:dem":41,
    "gn:feature_class":"P",
    "gn:feature_code":"PPL",
    "gn:name":"Xiangyangcun",
    "gn:population":0,
    "gn:timezone":"Asia/Taipei",
    "iso:country":"TW",
    "name:und_x_variant":[
        "Hsiang-yang-ts\u2019un"
    ],
    "wof:name":"Xiangyangcun",
    "wof:placetype":"locality"
},
  "geometry": {"coordinates":[120.31667,22.96667],"type":"Point"}
}