{
  "type": "Feature",
  "properties": {
    "gn:admin1_code":"3.0",
    "gn:admin2_code":"TPQ",
    "gn:admin3_code":"F27",
    "gn:admin4_code":"65000100001.0",
    "gn:asciiname":"Lunding",
    "gn:country_code":"TW",
    "gn:dem":124,
    "gn:feature_class":"P",
    "gn:feature_code":"PPL",
    "gn:name":"Lunding",
    "gn:population":0,
    "gn:timezone":"Asia/Taipei",
    "iso:country":"TW",
    "name:und_x_variant":[
        "Lun-ting"
    ],
    "name:zho_x_preferred":[
        "\u5d19\u9802"
    ],
    "wof:name":"Lunding",
    "wof:placetype":"locality"
},
  "geometry": {"coordinates":[121.49169000000001,25.22384],"type":"Point"}
}