{
  "type": "Feature",
  "properties": {
    "iso:country":"TW",
    "name:ara_x_preferred":[
        "\u0632\u0648\u0646\u063a\u0644\u064a"
    ],
    "name:ceb_x_preferred":[
        "Zhongli"
    ],
    "name:deu_x_preferred":[
        "Zhongli"
    ],
    "name:eng_x_preferred":[
        "Zhongli"
    ],
    "name:fra_x_preferred":[
        "Zhongli"
    ],
    "name:hak_x_preferred":[
        "Ch\u00fbng-la\u030dk-s\u1e73"
    ],
    "name:hun_x_preferred":[
        "Csungli"
    ],
    "name:jpn_x_preferred":[
        "\u4e2d\u30ec\u30ad\u533a"
    ],
    "name:kor_x_preferred":[
        "\uc911\ub9ac\uad6c"
    ],
    "name:lit_x_preferred":[
        "D\u017eongli"
    ],
    "name:lzh_x_preferred":[
        "\u4e2d\u58e2\u5340"
    ],
    "name:nan_x_preferred":[
        "Tiong-le\u030dk-khu"
    ],
    "name:nld_x_preferred":[
        "Zhongli"
    ],
    "name:pol_x_preferred":[
        "Zhongli"
    ],
    "name:rus_x_preferred":[
        "\u0427\u0436\u0443\u043d\u043b\u0438"
    ],
    "name:spa_x_preferred":[
        "Zhongli"
    ],
    "name:swe_x_preferred":[
        "Zhongli"
    ],
    "name:vie_x_preferred":[
        "Trung L\u1ecbch"
    ],
    "name:war_x_preferred":[
        "Zhongli"
    ],
    "name:yue_x_preferred":[
        "\u4e2d\u58e2\u5340"
    ],
    "name:zho_x_preferred":[
        "\u4e2d\u58e2\u5340"
    ],
    "qs:name":"\u4e2d\u58e2\u5e02",
    "qs:name_adm0":"\u81fa\u7063",
    "qs:name_adm1":"\u6843\u5712\u7e23",
    "qs:photos":5000,
    "qs:photos_1k":1000,
    "qs:photos_9k":22,
    "qs:photos_9r":14,
    "qs:photos_all":5000,
    "qs:photos_sr":24,
    "qs:placetype":"Town",
    "qs:pop_sr":"0",
    "wd:wordcount":1131,
    "wof:name":"\u4e2d\u58e2\u5e02",
    "wof:placetype":"locality"
},
  "geometry": {"coordinates":[121.217383,24.965111],"type":"Point"}
}