{
  "type": "Feature",
  "properties": {
    "iso:country":"TW",
    "qs:name":"\u4e2d\u58e2\u5e02",
    "qs:name_adm0":"\u81fa\u7063",
    "qs:name_adm1":"\u6843\u5712\u7e23",
    "qs:photos":5000,
    "qs:photos_1k":1000,
    "qs:photos_9k":22,
    "qs:photos_9r":14,
    "qs:photos_all":5000,
    "qs:photos_sr":24,
    "qs:placetype":"Town",
    "qs:pop_sr":"0",
    "wd:wordcount":1131,
    "wof:name":"\u4e2d\u58e2\u5e02",
    "wof:placetype":"locality"
},
  "geometry": {"coordinates":[121.217383,24.965111],"type":"Point"}
}