{
  "type": "Feature",
  "properties": {
    "gn:admin1_code":"4.0",
    "gn:admin2_code":"ILA",
    "gn:admin3_code":"G05",
    "gn:admin4_code":"10002070008.0",
    "gn:asciiname":"Zhonghuacun",
    "gn:country_code":"TW",
    "gn:dem":87,
    "gn:feature_class":"P",
    "gn:feature_code":"PPL",
    "gn:name":"Zhonghuacun",
    "gn:population":0,
    "gn:timezone":"Asia/Taipei",
    "iso:country":"TW",
    "name:und_x_variant":[
        "Jhonghuacun"
    ],
    "name:zho_x_preferred":[
        "\u4e2d\u83ef\u6751"
    ],
    "name:zho_x_variant":[
        "Chung-hua-ts\u2019un"
    ],
    "wof:name":"Zhonghuacun",
    "wof:placetype":"locality"
},
  "geometry": {"coordinates":[121.64711,24.70701],"type":"Point"}
}