{
  "type": "Feature",
  "properties": {
    "gn:admin1_code":"3.0",
    "gn:admin2_code":"TPQ",
    "gn:admin3_code":"F21",
    "gn:admin4_code":"65000120020.0",
    "gn:asciiname":"Jiufen",
    "gn:country_code":"TW",
    "gn:dem":287,
    "gn:feature_class":"P",
    "gn:feature_code":"PPL",
    "gn:name":"Jiufen",
    "gn:population":0,
    "gn:timezone":"Asia/Taipei",
    "iso:country":"TW",
    "name:ara_x_preferred":[
        "\u062c\u064a\u0648\u0641\u064a\u0646"
    ],
    "name:und_x_variant":[
        "Jioufen",
        "Jiufen",
        "Chiu-fen"
    ],
    "name:zho_x_preferred":[
        "\u4e5d\u4efd"
    ],
    "wof:name":"Jiufen",
    "wof:placetype":"locality"
},
  "geometry": {"coordinates":[121.84424,25.10957],"type":"Point"}
}