{
  "type": "Feature",
  "properties": {
    "gn:admin1_code":"4.0",
    "gn:admin2_code":"TNN",
    "gn:admin3_code":"R28",
    "gn:admin4_code":"67000280002.0",
    "gn:asciiname":"Dingguinan",
    "gn:country_code":"TW",
    "gn:dem":25,
    "gn:feature_class":"P",
    "gn:feature_code":"PPL",
    "gn:name":"Dingguinan",
    "gn:population":0,
    "gn:timezone":"Asia/Taipei",
    "iso:country":"TW",
    "name:und_x_variant":[
        "Dinggueinan",
        "Ting-kuei-nan"
    ],
    "name:zho_x_preferred":[
        "\u9802\u6b78\u5357"
    ],
    "wof:name":"Dingguinan",
    "wof:placetype":"locality"
},
  "geometry": {"coordinates":[120.28222,22.95694],"type":"Point"}
}