{
  "type": "Feature",
  "properties": {
    "gn:admin1_code":"04",
    "gn:admin2_code":"TXG",
    "gn:admin3_code":"B19",
    "gn:admin4_code":"66000190008.0",
    "gn:asciiname":"Zhongxingling",
    "gn:country_code":"TW",
    "gn:dem":492,
    "gn:feature_class":"P",
    "gn:feature_code":"PPL",
    "gn:name":"Zhongxingling",
    "gn:population":0,
    "gn:timezone":"Asia/Taipei",
    "iso:country":"TW",
    "name:und_x_variant":[
        "Jhongsingling",
        "Chung-hsing-ling"
    ],
    "name:zho_x_preferred":[
        "Ta-ch\u2019i-chiao"
    ],
    "name:zho_x_variant":[
        "\u4e2d\u8208\u5dba"
    ],
    "wof:name":"Zhongxingling",
    "wof:placetype":"locality"
},
  "geometry": {"coordinates":[120.79062,24.20792],"type":"Point"}
}