{
  "type": "Feature",
  "properties": {
    "gn:admin1_code":"4.0",
    "gn:admin2_code":"ILA",
    "gn:admin3_code":"G02",
    "gn:admin4_code":"10002040017.0",
    "gn:asciiname":"Fudekeng",
    "gn:country_code":"TW",
    "gn:dem":174,
    "gn:feature_class":"P",
    "gn:feature_code":"PPL",
    "gn:name":"Fudekeng",
    "gn:population":0,
    "gn:timezone":"Asia/Taipei",
    "iso:country":"TW",
    "name:zho_x_preferred":[
        "\u798f\u5fb7\u5751"
    ],
    "name:zho_x_variant":[
        "Fu-te-k\u2019eng"
    ],
    "wof:name":"Fudekeng",
    "wof:placetype":"locality"
},
  "geometry": {"coordinates":[121.81,24.88194],"type":"Point"}
}