{
  "type": "Feature",
  "properties": {
    "gn:admin1_code":"04",
    "gn:admin2_code":"TNN",
    "gn:admin3_code":"R19",
    "gn:admin4_code":"67000190003.0",
    "gn:asciiname":"Beizidian",
    "gn:country_code":"TW",
    "gn:dem":20,
    "gn:feature_class":"P",
    "gn:feature_code":"PPL",
    "gn:name":"Beizidian",
    "gn:population":0,
    "gn:timezone":"Asia/Taipei",
    "iso:country":"TW",
    "name:und_x_variant":[
        "Beizihdian",
        "Pei-tzu-tien"
    ],
    "name:zho_x_preferred":[
        "\u5317\u4ed4\u5e97"
    ],
    "wof:name":"Beizidian",
    "wof:placetype":"locality"
},
  "geometry": {"coordinates":[120.31201,23.13668],"type":"Point"}
}