{
  "type": "Feature",
  "properties": {
    "gn:admin1_code":"2.0",
    "gn:admin2_code":"KHH",
    "gn:admin3_code":"E15",
    "gn:admin4_code":"64000150004.0",
    "gn:asciiname":"Hudi",
    "gn:country_code":"TW",
    "gn:dem":42,
    "gn:feature_class":"P",
    "gn:feature_code":"PPL",
    "gn:name":"Hudi",
    "gn:population":0,
    "gn:timezone":"Asia/Taipei",
    "iso:country":"TW",
    "name:fas_x_preferred":[
        "\u0647\u0648\u062f\u06cc"
    ],
    "name:msa_x_preferred":[
        "Hudi"
    ],
    "name:ukr_x_preferred":[
        "\u0413\u0443\u0434\u0456"
    ],
    "name:und_x_variant":[
        "Hu-ti",
        "\u6e56\u5e95",
        "Hudi"
    ],
    "name:zho_x_preferred":[
        "\u6e56\u5e95"
    ],
    "wof:name":"Hudi",
    "wof:placetype":"locality"
},
  "geometry": {"coordinates":[120.41022,22.65909],"type":"Point"}
}