{
  "type": "Feature",
  "properties": {
    "gn:admin1_code":"2.0",
    "gn:admin2_code":"KHH",
    "gn:admin3_code":"E22",
    "gn:admin4_code":"64000220002.0",
    "gn:asciiname":"Waziliao",
    "gn:country_code":"TW",
    "gn:dem":62,
    "gn:feature_class":"P",
    "gn:feature_code":"PPL",
    "gn:name":"Waziliao",
    "gn:population":0,
    "gn:timezone":"Asia/Taipei",
    "iso:country":"TW",
    "name:und_x_variant":[
        "Wazihliao",
        "Wa-tzu-liao"
    ],
    "name:zho_x_preferred":[
        "\u6316\u4ed4\u5bee"
    ],
    "wof:name":"Waziliao",
    "wof:placetype":"locality"
},
  "geometry": {"coordinates":[120.37528,22.84472],"type":"Point"}
}