{
  "type": "Feature",
  "properties": {
    "gn:admin1_code":"1.0",
    "gn:admin2_code":"LIE",
    "gn:asciiname":"Lehuacun",
    "gn:country_code":"TW",
    "gn:dem":61,
    "gn:feature_class":"P",
    "gn:feature_code":"PPL",
    "gn:name":"Lehuacun",
    "gn:population":0,
    "gn:timezone":"Asia/Taipei",
    "iso:country":"TW",
    "name:und_x_variant":[
        "Zhongliucun",
        "Chung-liu-ts\u2019un",
        "Lehuacun",
        "Le-hua-ts\u2019un"
    ],
    "name:zho_x_preferred":[
        "\u6a02\u83ef\u6751"
    ],
    "wof:name":"Lehuacun",
    "wof:placetype":"locality"
},
  "geometry": {"coordinates":[120.48778,26.36907],"type":"Point"}
}