{
  "type": "Feature",
  "properties": {
    "gn:admin1_code":"4.0",
    "gn:admin2_code":"CHA",
    "gn:admin3_code":"N23",
    "gn:admin4_code":"10007230026.0",
    "gn:asciiname":"Hanbaoyuan",
    "gn:country_code":"TW",
    "gn:dem":4,
    "gn:feature_class":"P",
    "gn:feature_code":"PPL",
    "gn:name":"Hanbaoyuan",
    "gn:population":0,
    "gn:timezone":"Asia/Taipei",
    "iso:country":"TW",
    "name:zho_x_preferred":[
        "\u6f22\u5bf6\u5712"
    ],
    "name:zho_x_variant":[
        "Han-pao-y\u00fcan"
    ],
    "wof:name":"Hanbaoyuan",
    "wof:placetype":"locality"
},
  "geometry": {"coordinates":[120.35429999999999,23.9953],"type":"Point"}
}