{
  "type": "Feature",
  "properties": {
    "gn:admin1_code":"4.0",
    "gn:admin2_code":"MIA",
    "gn:admin3_code":"K03",
    "gn:admin4_code":"10005030008.0",
    "gn:asciiname":"Fengshuwozi",
    "gn:country_code":"TW",
    "gn:dem":121,
    "gn:feature_class":"P",
    "gn:feature_code":"PPL",
    "gn:name":"Fengshuwozi",
    "gn:population":0,
    "gn:timezone":"Asia/Taipei",
    "iso:country":"TW",
    "name:und_x_variant":[
        "Fongshuwozih",
        "Fengshuwozi",
        "Feng-shu-wo-tzu"
    ],
    "name:zho_x_preferred":[
        "\u6953\u6a39\u7aa9\u4ed4"
    ],
    "wof:name":"Fengshuwozi",
    "wof:placetype":"locality"
},
  "geometry": {"coordinates":[120.69944,24.46222],"type":"Point"}
}