{
  "type": "Feature",
  "properties": {
    "gn:admin1_code":"4.0",
    "gn:admin2_code":"TNN",
    "gn:admin3_code":"R30",
    "gn:admin4_code":"67000300003.0",
    "gn:asciiname":"Daxikou",
    "gn:country_code":"TW",
    "gn:dem":80,
    "gn:feature_class":"P",
    "gn:feature_code":"PPL",
    "gn:name":"Daxikou",
    "gn:population":0,
    "gn:timezone":"Asia/Taipei",
    "iso:country":"TW",
    "name:und_x_variant":[
        "Dasikou",
        "Daxikou"
    ],
    "name:zho_x_preferred":[
        "\u5927\u6eaa\u53e3"
    ],
    "name:zho_x_variant":[
        "Ta-hsi-k\u2019ou"
    ],
    "wof:name":"Daxikou",
    "wof:placetype":"locality"
},
  "geometry": {"coordinates":[120.36972,22.95083],"type":"Point"}
}