{
  "type": "Feature",
  "properties": {
    "gn:admin1_code":"3.0",
    "gn:admin2_code":"TPQ",
    "gn:admin3_code":"F24",
    "gn:admin4_code":"65000260011.0",
    "gn:asciiname":"Longdong",
    "gn:country_code":"TW",
    "gn:dem":9,
    "gn:feature_class":"P",
    "gn:feature_code":"PPL",
    "gn:name":"Longdong",
    "gn:population":0,
    "gn:timezone":"Asia/Taipei",
    "iso:country":"TW",
    "name:ceb_x_preferred":[
        "Longdong"
    ],
    "name:swe_x_preferred":[
        "Longdong"
    ],
    "name:und_x_variant":[
        "Lao-tung",
        "Longdong",
        "Lung-tung"
    ],
    "name:zho_x_preferred":[
        "\u9f8d\u6d1e"
    ],
    "wof:name":"Longdong",
    "wof:placetype":"locality"
},
  "geometry": {"coordinates":[121.91874,25.1116],"type":"Point"}
}