{
  "type": "Feature",
  "properties": {
    "gn:country":"TW",
    "gn:fcode":"ADM2",
    "gn:pop":0,
    "iso:country":"TW",
    "name:kor_x_preferred":[
        "\uc790\uc774 \uc2dc"
    ],
    "name:unk_x_variant":[
        "Chia-i"
    ],
    "qs:name":"Chiayi",
    "qs:photos_9r":0,
    "qs:photos_sr":0,
    "qs:pop_sr":"0",
    "wd:elevation":69.0,
    "wd:wordcount":1697,
    "wof:name":"Chiayi",
    "wof:placetype":"county",
    "wof:population":0
},
  "geometry": {"coordinates":[120.44526999999999,23.47722],"type":"Point"}
}