{
  "type": "Feature",
  "properties": {
    "gn:admin1_code":"04",
    "gn:admin2_code":"PIF",
    "gn:admin3_code":"T13",
    "gn:admin4_code":"10013130023.0",
    "gn:asciiname":"Beiye",
    "gn:country_code":"TW",
    "gn:dem":147,
    "gn:feature_class":"P",
    "gn:feature_code":"PPL",
    "gn:name":"Beiye",
    "gn:population":0,
    "gn:timezone":"Asia/Taipei",
    "iso:country":"TW",
    "name:und_x_variant":[
        "Pei-yeh-ts\u2019un",
        "Beiye",
        "Pei-yeh"
    ],
    "name:zho_x_preferred":[
        "\u5317\u8449"
    ],
    "wof:name":"Beiye",
    "wof:placetype":"locality"
},
  "geometry": {"coordinates":[120.6467,22.7075],"type":"Point"}
}