{
  "type": "Feature",
  "properties": {
    "gn:admin1_code":"4.0",
    "gn:admin2_code":"TNN",
    "gn:admin3_code":"R30",
    "gn:admin4_code":"67000300006.0",
    "gn:asciiname":"Pangkongzi",
    "gn:country_code":"TW",
    "gn:dem":71,
    "gn:feature_class":"P",
    "gn:feature_code":"PPL",
    "gn:name":"Pangkongzi",
    "gn:population":0,
    "gn:timezone":"Asia/Taipei",
    "iso:country":"TW",
    "name:und_x_variant":[
        "Pangkongzih",
        "Pangkongzi"
    ],
    "name:zho_x_preferred":[
        "\u78c5\u7a7a\u5b50"
    ],
    "name:zho_x_variant":[
        "P\u2019ang-k\u2019ung-tzu"
    ],
    "wof:name":"Pangkongzi",
    "wof:placetype":"locality"
},
  "geometry": {"coordinates":[120.39221999999999,22.94472],"type":"Point"}
}