{
  "type": "Feature",
  "properties": {
    "iso:country":"TW",
    "name:eng_x_preferred":[
        "Jiulu"
    ],
    "name:eng_x_variant":[
        "Jiulu Village"
    ],
    "name:zho_tw_x_preferred":[
        "\u820a\u8def\u6751"
    ],
    "qs:name":"\u820a\u8def\u6751",
    "qs:name_adm0":"\u81fa\u7063",
    "qs:name_adm1":"\u6843\u5712\u7e23",
    "qs:photos":60,
    "qs:photos_1k":12,
    "qs:photos_9k":1,
    "qs:photos_9r":2,
    "qs:photos_all":60,
    "qs:photos_sr":2,
    "qs:placetype":"Town",
    "qs:pop_sr":"0",
    "wof:name":"Jiulu",
    "wof:placetype":"locality"
},
  "geometry": {"coordinates":[121.36545099999999,25.026739],"type":"Point"}
}