{
  "type": "Feature",
  "properties": {
    "gn:admin1_code":"04",
    "gn:admin2_code":"ILA",
    "gn:admin3_code":"G02",
    "gn:admin4_code":"10002040014.0",
    "gn:asciiname":"Sanbaozhu",
    "gn:country_code":"TW",
    "gn:dem":8,
    "gn:feature_class":"P",
    "gn:feature_code":"PPL",
    "gn:name":"Sanbaozhu",
    "gn:population":0,
    "gn:timezone":"Asia/Taipei",
    "iso:country":"TW",
    "name:und_x_variant":[
        "Sanbaojhu",
        "Sanbaozhu",
        "San-pao-chu"
    ],
    "name:zho_x_preferred":[
        "\u4e09\u62b1\u7af9"
    ],
    "wof:name":"Sanbaozhu",
    "wof:placetype":"locality"
},
  "geometry": {"coordinates":[121.82333,24.83333],"type":"Point"}
}