{
  "type": "Feature",
  "properties": {
    "gn:country":"TW",
    "gn:fcode":"ADM2",
    "gn:population":0,
    "iso:country":"TW",
    "label:eng_x_preferred_longname":[
        "Lienchiang Township"
    ],
    "label:eng_x_preferred_placetype":[
        "township"
    ],
    "name:eng_x_preferred":[
        "Lienchiang"
    ],
    "name:fra_x_preferred":[
        "Lienchiang"
    ],
    "name:kor_x_preferred":[
        "\ub844\uc7a5 \ud604"
    ],
    "name:und_x_variant":[
        "Lianjiang Sian"
    ],
    "name:zho_x_preferred":[
        "\u9023\u6c5f\u7e23"
    ],
    "qs:name":"Lienchiang",
    "qs:photos_9r":0,
    "qs:photos_sr":0,
    "qs:pop_sr":"0",
    "wof:name":"Lienchiang",
    "wof:placetype":"county",
    "wof:population":0
},
  "geometry": {"coordinates":[119.95887999999999,26.16416],"type":"Point"}
}