{
  "type": "Feature",
  "properties": {
    "gn:admin1_code":"04",
    "gn:admin2_code":"CYQ",
    "gn:admin3_code":"Q20",
    "gn:admin4_code":"10010180007.0",
    "gn:asciiname":"Dade'an",
    "gn:country_code":"TW",
    "gn:dem":1043,
    "gn:feature_class":"P",
    "gn:feature_code":"PPL",
    "gn:name":"Dade\u2019an",
    "gn:population":0,
    "gn:timezone":"Asia/Taipei",
    "iso:country":"TW",
    "name:und_x_variant":[
        "Ta-pu-te-an-she",
        "Ta-te",
        "Ta-te-an"
    ],
    "name:zho_x_preferred":[
        "\u9054\u5fb7\u5b89"
    ],
    "name:zho_x_variant":[
        "Dade\u2019an"
    ],
    "wof:name":"Dade'an",
    "wof:placetype":"locality"
},
  "geometry": {"coordinates":[120.73996,23.4443],"type":"Point"}
}