{
  "type": "Feature",
  "properties": {
    "gn:admin1_code":"2.0",
    "gn:admin2_code":"KHH",
    "gn:admin3_code":"E32",
    "gn:admin4_code":"64000320010.0",
    "gn:asciiname":"Zhulin",
    "gn:country_code":"TW",
    "gn:dem":686,
    "gn:feature_class":"P",
    "gn:feature_code":"PPL",
    "gn:name":"Zhulin",
    "gn:population":0,
    "gn:timezone":"Asia/Taipei",
    "iso:country":"TW",
    "name:und_x_variant":[
        "Jhulin",
        "Chu-lin"
    ],
    "name:zho_x_preferred":[
        "\u7af9\u6797"
    ],
    "wof:name":"Zhulin",
    "wof:placetype":"locality"
},
  "geometry": {"coordinates":[120.72889000000001,23.11333],"type":"Point"}
}