{
  "type": "Feature",
  "properties": {
    "iso:country":"TW",
    "label:eng_x_preferred_longname":[
        "Taichung Township"
    ],
    "label:eng_x_preferred_placetype":[
        "township"
    ],
    "name:ast_x_preferred":[
        "Condau Taichung"
    ],
    "name:ces_x_preferred":[
        "Okres Tchaj-\u010dung"
    ],
    "name:cym_x_preferred":[
        "Sir Taichung"
    ],
    "name:deu_x_preferred":[
        "Landkreis Taichung"
    ],
    "name:eng_x_preferred":[
        "Taichung"
    ],
    "name:eus_x_preferred":[
        "Taichung konderria"
    ],
    "name:hak_x_preferred":[
        "Th\u00f2i-ch\u00fbng-yen"
    ],
    "name:ind_x_preferred":[
        "Kabupaten Taichung"
    ],
    "name:jpn_x_preferred":[
        "\u53f0\u4e2d\u770c"
    ],
    "name:kor_x_preferred":[
        "\ud0c0\uc774\uc911\ud604"
    ],
    "name:nan_x_preferred":[
        "T\u00e2i-tiong-ko\u0101n"
    ],
    "name:nld_x_preferred":[
        "Taichung"
    ],
    "name:rus_x_preferred":[
        "\u0422\u0430\u0439\u0447\u0436\u0443\u043d"
    ],
    "name:tha_x_preferred":[
        "\u0e44\u0e16\u0e08\u0e07"
    ],
    "name:vie_x_preferred":[
        "\u0110\u00e0i Trung"
    ],
    "name:yue_x_preferred":[
        "\u81fa\u4e2d\u7e23"
    ],
    "name:zho_x_preferred":[
        "\u81fa\u4e2d\u7e23"
    ],
    "name:zho_x_variant":[
        "\u53f0\u4e2d\u7e23",
        "\u77f3\u5ca1\u9109"
    ],
    "qs:name":"\u77f3\u5ca1\u9109",
    "qs:name_adm0":"\u81fa\u7063",
    "qs:name_adm1":"\u53f0\u4e2d\u5e02",
    "qs:photos":401,
    "qs:photos_1k":81,
    "qs:photos_9k":4,
    "qs:photos_9r":6,
    "qs:photos_all":804,
    "qs:photos_sr":6,
    "qs:placetype":"County",
    "qs:pop_sr":"0",
    "wd:wordcount":207,
    "wof:name":"Taichung",
    "wof:placetype":"county"
},
  "geometry": {"coordinates":[120.783691,24.260737],"type":"Point"}
}