{
  "type": "Feature",
  "properties": {
    "gn:admin1_code":"02",
    "gn:admin2_code":"KHH",
    "gn:admin3_code":"E35",
    "gn:admin4_code":"64000350001.0",
    "gn:asciiname":"Guangxing",
    "gn:country_code":"TW",
    "gn:dem":112,
    "gn:feature_class":"P",
    "gn:feature_code":"PPL",
    "gn:name":"Guangxing",
    "gn:population":0,
    "gn:timezone":"Asia/Taipei",
    "iso:country":"TW",
    "name:und_x_variant":[
        "Guangsing",
        "Guangxing",
        "Kuang-hsing"
    ],
    "name:zho_x_preferred":[
        "\u5ee3\u8208"
    ],
    "name:zho_x_variant":[
        "T\u2019ou-she"
    ],
    "wof:name":"Guangxing",
    "wof:placetype":"locality"
},
  "geometry": {"coordinates":[120.50346,23.00029],"type":"Point"}
}