{
  "type": "Feature",
  "properties": {
    "gn:admin1_code":"4.0",
    "gn:admin2_code":"TAO",
    "gn:admin3_code":"H02",
    "gn:admin4_code":"68000030010.0",
    "gn:asciiname":"Shisanfen",
    "gn:country_code":"TW",
    "gn:dem":288,
    "gn:feature_class":"P",
    "gn:feature_code":"PPL",
    "gn:name":"Shisanfen",
    "gn:population":0,
    "gn:timezone":"Asia/Taipei",
    "iso:country":"TW",
    "name:und_x_variant":[
        "Shihsanfen",
        "Shih-san-fen"
    ],
    "name:zho_x_preferred":[
        "\u5341\u4e09\u5206"
    ],
    "wof:name":"Shisanfen",
    "wof:placetype":"locality"
},
  "geometry": {"coordinates":[121.34601000000001,24.85328],"type":"Point"}
}