{
  "type": "Feature",
  "properties": {
    "gn:admin1_code":"4.0",
    "gn:admin2_code":"TXG",
    "gn:admin3_code":"B09",
    "gn:admin4_code":"66000090024.0",
    "gn:asciiname":"Lianzikengkou",
    "gn:country_code":"TW",
    "gn:dem":204,
    "gn:feature_class":"P",
    "gn:feature_code":"PPL",
    "gn:name":"Lianzikengkou",
    "gn:population":0,
    "gn:timezone":"Asia/Taipei",
    "iso:country":"TW",
    "name:und_x_variant":[
        "Lien-ts\u2019un-li",
        "Lien-ts\u2019un",
        "\u942e\u4ed4\u5751\u53e3",
        "Lianzikengkou",
        "Lianzihkengkou",
        "Lien-tzu-k\u2019eng-k\u2019ou"
    ],
    "name:zho_x_preferred":[
        "Lien-tzu-k\u2019eng-k\u2019ou"
    ],
    "wof:name":"Lianzikengkou",
    "wof:placetype":"locality"
},
  "geometry": {"coordinates":[120.72484,24.2297],"type":"Point"}
}