{
  "type": "Feature",
  "properties": {
    "gn:admin1_code":"01",
    "gn:admin2_code":"KIN",
    "gn:admin3_code":"W01",
    "gn:admin4_code":"9020030001.0",
    "gn:asciiname":"Shanwai",
    "gn:country_code":"TW",
    "gn:dem":30,
    "gn:feature_class":"P",
    "gn:feature_code":"PPL",
    "gn:name":"Shanwai",
    "gn:population":0,
    "gn:timezone":"Asia/Taipei",
    "iso:country":"TW",
    "name:und_x_variant":[
        "Shan-wai"
    ],
    "name:zho_x_preferred":[
        "\u5c71\u5916"
    ],
    "wof:name":"Shanwai",
    "wof:placetype":"locality"
},
  "geometry": {"coordinates":[118.41518000000001,24.44203],"type":"Point"}
}