{
  "type": "Feature",
  "properties": {
    "gn:admin1_code":"4.0",
    "gn:admin2_code":"TXG",
    "gn:admin3_code":"B12",
    "gn:admin4_code":"66000120024.0",
    "gn:asciiname":"Dingshuidui",
    "gn:country_code":"TW",
    "gn:dem":60,
    "gn:feature_class":"P",
    "gn:feature_code":"PPL",
    "gn:name":"Dingshuidui",
    "gn:population":0,
    "gn:timezone":"Asia/Taipei",
    "iso:country":"TW",
    "name:und_x_variant":[
        "Dingshueiduei",
        "Dingshuidui",
        "Ting-shui-tui"
    ],
    "name:zho_x_preferred":[
        "\u9802\u6c34\u7893"
    ],
    "wof:name":"Dingshuidui",
    "wof:placetype":"locality"
},
  "geometry": {"coordinates":[120.60056000000002,24.30528],"type":"Point"}
}