{
  "type": "Feature",
  "properties": {
    "gn:admin1_code":"4.0",
    "gn:admin2_code":"TXG",
    "gn:admin3_code":"B10",
    "gn:admin4_code":"66000100011.0",
    "gn:asciiname":"Yunxiandong",
    "gn:country_code":"TW",
    "gn:dem":441,
    "gn:feature_class":"P",
    "gn:feature_code":"PPL",
    "gn:name":"Yunxiandong",
    "gn:population":0,
    "gn:timezone":"Asia/Taipei",
    "iso:country":"TW",
    "name:und_x_variant":[
        "Yunsiandong",
        "Yunxiandong"
    ],
    "name:zho_x_preferred":[
        "\u96f2\u4ed9\u6d1e"
    ],
    "name:zho_x_variant":[
        "Y\u00fcn-hsien-tung-k\u2019ou",
        "Y\u00fcn-hsieh-tung",
        "Y\u00fcn-hsien-tung"
    ],
    "wof:name":"Yunxiandong",
    "wof:placetype":"locality"
},
  "geometry": {"coordinates":[120.86263,24.23789],"type":"Point"}
}