{
  "type": "Feature",
  "properties": {
    "iso:country":"TW",
    "qs:name":"\u5927\u6d77\u6751",
    "qs:name_adm0":"\u81fa\u7063",
    "qs:name_adm1":"\u6843\u5712\u7e23",
    "qs:photos":514,
    "qs:photos_1k":104,
    "qs:photos_9k":2,
    "qs:photos_9r":5,
    "qs:photos_all":514,
    "qs:photos_sr":7,
    "qs:placetype":"Town",
    "qs:pop_sr":"0",
    "wof:name":"\u5927\u6d77\u6751",
    "wof:placetype":"locality"
},
  "geometry": {"coordinates":[121.23069700000001,25.073627],"type":"Point"}
}