{
  "type": "Feature",
  "properties": {
    "gn:admin1_code":"04",
    "gn:admin2_code":"TXG",
    "gn:admin3_code":"B15",
    "gn:admin4_code":"66000150008.0",
    "gn:asciiname":"Dunzijiao",
    "gn:country_code":"TW",
    "gn:dem":214,
    "gn:feature_class":"P",
    "gn:feature_code":"PPL",
    "gn:name":"Dunzijiao",
    "gn:population":0,
    "gn:timezone":"Asia/Taipei",
    "iso:country":"TW",
    "name:und_x_variant":[
        "Dunzihjiao",
        "Dunzijiao",
        "Tun-tzu-chiao"
    ],
    "name:zho_x_preferred":[
        "\u58a9\u5b50\u811a"
    ],
    "name:zho_x_variant":[
        "T\u2019un-tzu-chiao"
    ],
    "wof:name":"Dunzijiao",
    "wof:placetype":"locality"
},
  "geometry": {"coordinates":[120.71389000000001,24.29972],"type":"Point"}
}