{
  "type": "Feature",
  "properties": {
    "gn:admin1_code":"4.0",
    "gn:admin2_code":"TXG",
    "gn:admin3_code":"B29",
    "gn:admin4_code":"66000290003.0",
    "gn:asciiname":"Malun",
    "gn:country_code":"TW",
    "gn:dem":1657,
    "gn:feature_class":"P",
    "gn:feature_code":"PPL",
    "gn:name":"Malun",
    "gn:population":0,
    "gn:timezone":"Asia/Taipei",
    "iso:country":"TW",
    "name:und_x_variant":[
        "Ma-lun-she",
        "Ma-lun",
        "Malun"
    ],
    "wof:name":"Malun",
    "wof:placetype":"locality"
},
  "geometry": {"coordinates":[121.05,24.21667],"type":"Point"}
}