{
  "type": "Feature",
  "properties": {
    "gn:admin1_code":"3.0",
    "gn:admin2_code":"TPQ",
    "gn:admin3_code":"F32",
    "gn:admin4_code":"65000230003.0",
    "gn:asciiname":"Gangzikou",
    "gn:country_code":"TW",
    "gn:dem":10,
    "gn:feature_class":"P",
    "gn:feature_code":"PPL",
    "gn:name":"Gangzikou",
    "gn:population":0,
    "gn:timezone":"Asia/Taipei",
    "iso:country":"TW",
    "name:und_x_variant":[
        "Gangzihkou",
        "Gangzikou"
    ],
    "name:zho_x_preferred":[
        "\u6e2f\u4ed4\u53e3"
    ],
    "name:zho_x_variant":[
        "Kang-tzu-k\u2019ou"
    ],
    "wof:name":"Gangzikou",
    "wof:placetype":"locality"
},
  "geometry": {"coordinates":[121.42843999999999,25.15865],"type":"Point"}
}