{
  "type": "Feature",
  "properties": {
    "gn:admin1_code":"3.0",
    "gn:admin2_code":"TPQ",
    "gn:admin3_code":"F30",
    "gn:admin4_code":"65000210012.0",
    "gn:asciiname":"Guizishan",
    "gn:country_code":"TW",
    "gn:dem":209,
    "gn:feature_class":"P",
    "gn:feature_code":"PPL",
    "gn:name":"Guizishan",
    "gn:population":0,
    "gn:timezone":"Asia/Taipei",
    "iso:country":"TW",
    "name:und_x_variant":[
        "Gueizihshan",
        "Kuei-tzu-shan"
    ],
    "name:zho_x_preferred":[
        "\u9f9c\u5b50\u5c71"
    ],
    "wof:name":"Guizishan",
    "wof:placetype":"locality"
},
  "geometry": {"coordinates":[121.50595,25.21368],"type":"Point"}
}