{
  "type": "Feature",
  "properties": {
    "gn:admin1_code":"4.0",
    "gn:admin2_code":"NAN",
    "gn:admin3_code":"M08",
    "gn:admin4_code":"10008080001.0",
    "gn:asciiname":"Guangxing",
    "gn:country_code":"TW",
    "gn:dem":222,
    "gn:feature_class":"P",
    "gn:feature_code":"PPL",
    "gn:name":"Guangxing",
    "gn:population":0,
    "gn:timezone":"Asia/Taipei",
    "iso:country":"TW",
    "name:und_x_variant":[
        "Guangsing",
        "Guangxing",
        "Kuang-hsing"
    ],
    "name:zho_x_preferred":[
        "\u5ee3\u8208"
    ],
    "wof:name":"Guangxing",
    "wof:placetype":"locality"
},
  "geometry": {"coordinates":[120.78745000000001,23.86437],"type":"Point"}
}