{
  "type": "Feature",
  "properties": {
    "gn:admin1_code":"3.0",
    "gn:admin2_code":"TPQ",
    "gn:admin3_code":"F27",
    "gn:admin4_code":"65000100007.0",
    "gn:asciiname":"Zhuangzilin",
    "gn:country_code":"TW",
    "gn:dem":137,
    "gn:feature_class":"P",
    "gn:feature_code":"PPL",
    "gn:name":"Zhuangzilin",
    "gn:population":0,
    "gn:timezone":"Asia/Taipei",
    "iso:country":"TW",
    "name:und_x_variant":[
        "Jhuangzihlin",
        "Zhuangzilin",
        "Chuang-tzu-lin"
    ],
    "name:zho_x_preferred":[
        "\u6a01\u5b50\u6797"
    ],
    "name:zho_x_variant":[
        "Ch\u2019un-tzu-lin"
    ],
    "wof:name":"Zhuangzilin",
    "wof:placetype":"locality"
},
  "geometry": {"coordinates":[121.48236,25.20353],"type":"Point"}
}