{
  "type": "Feature",
  "properties": {
    "gn:admin1_code":"4.0",
    "gn:admin2_code":"TAO",
    "gn:admin3_code":"H12",
    "gn:admin4_code":"68000120006.0",
    "gn:asciiname":"Liangzuowu",
    "gn:country_code":"TW",
    "gn:dem":29,
    "gn:feature_class":"P",
    "gn:feature_code":"PPL",
    "gn:name":"Liangzuowu",
    "gn:population":0,
    "gn:timezone":"Asia/Taipei",
    "iso:country":"TW",
    "name:und_x_variant":[
        "Erh-chien-wu",
        "Liang-tso-wu"
    ],
    "name:zho_x_preferred":[
        "\u5169\u5ea7\u5c4b"
    ],
    "name:zho_x_variant":[
        "Liang-tso-ts\u2019o"
    ],
    "wof:name":"Liangzuowu",
    "wof:placetype":"locality"
},
  "geometry": {"coordinates":[121.06796,25.01121],"type":"Point"}
}