{
  "type": "Feature",
  "properties": {
    "gn:admin1_code":"4.0",
    "gn:admin2_code":"TNN",
    "gn:admin3_code":"R18",
    "gn:admin4_code":"67000180015.0",
    "gn:asciiname":"Xinhezhuang",
    "gn:country_code":"TW",
    "gn:dem":34,
    "gn:feature_class":"P",
    "gn:feature_code":"PPL",
    "gn:name":"Xinhezhuang",
    "gn:population":0,
    "gn:timezone":"Asia/Taipei",
    "iso:country":"TW",
    "name:und_x_variant":[
        "Hsin-ho",
        "Sinhejhuang",
        "Hsin-chih",
        "Xinhezhuang",
        "Hsin-ho-chuang"
    ],
    "name:zho_x_preferred":[
        "\u65b0\u548c\u838a"
    ],
    "wof:name":"Xinhezhuang",
    "wof:placetype":"locality"
},
  "geometry": {"coordinates":[120.34090999999999,23.01438],"type":"Point"}
}