{
  "type": "Feature",
  "properties": {
    "gn:admin1_code":"4.0",
    "gn:admin2_code":"CYQ",
    "gn:admin3_code":"Q08",
    "gn:admin4_code":"10010080012.0",
    "gn:asciiname":"Liudouwei",
    "gn:country_code":"TW",
    "gn:dem":12,
    "gn:feature_class":"P",
    "gn:feature_code":"PPL",
    "gn:name":"Liudouwei",
    "gn:population":0,
    "gn:timezone":"Asia/Taipei",
    "iso:country":"TW",
    "name:und_x_variant":[
        "Liu-tou",
        "Lioudouwei",
        "Liudouwei",
        "Liu-tou-wei"
    ],
    "name:zho_x_preferred":[
        "Hsin-ts\u2019o"
    ],
    "name:zho_x_variant":[
        "Liu-tou-ts\u2019un",
        "\u516d\u6597\u5c3e"
    ],
    "wof:name":"Liudouwei",
    "wof:placetype":"locality"
},
  "geometry": {"coordinates":[120.29506000000001,23.54238],"type":"Point"}
}