{
  "type": "Feature",
  "properties": {
    "gn:admin1_code":"2.0",
    "gn:admin2_code":"KHH",
    "gn:admin3_code":"E37",
    "gn:admin4_code":"64000370004.0",
    "gn:asciiname":"Gaozhong'ercun",
    "gn:country_code":"TW",
    "gn:dem":554,
    "gn:feature_class":"P",
    "gn:feature_code":"PPL",
    "gn:name":"Gaozhong\u2019ercun",
    "gn:population":0,
    "gn:timezone":"Asia/Taipei",
    "iso:country":"TW",
    "name:zho_x_preferred":[
        "\u9ad8\u4e2d\u4e8c\u6751"
    ],
    "name:zho_x_variant":[
        "Gaozhong\u2019ercun",
        "Gaojhong\u2019ercun",
        "Kao-chung-erh-ts\u2019un"
    ],
    "wof:name":"Gaozhong'ercun",
    "wof:placetype":"locality"
},
  "geometry": {"coordinates":[120.72306,23.13417],"type":"Point"}
}