{
  "type": "Feature",
  "properties": {
    "gn:admin1_code":"04",
    "gn:admin2_code":"TPE",
    "gn:admin3_code":"A11",
    "gn:admin4_code":"63000080034.0",
    "gn:asciiname":"Poneikeng",
    "gn:country_code":"TW",
    "gn:dem":40,
    "gn:feature_class":"P",
    "gn:feature_code":"PPL",
    "gn:name":"Poneikeng",
    "gn:population":0,
    "gn:timezone":"Asia/Taipei",
    "iso:country":"TW",
    "name:zho_x_preferred":[
        "\u5761\u5167\u5751"
    ],
    "name:zho_x_variant":[
        "P\u2019o-nei",
        "Nei-k\u2019ang",
        "P\u2019o-nei-k\u2019eng"
    ],
    "wof:name":"Poneikeng",
    "wof:placetype":"locality"
},
  "geometry": {"coordinates":[121.57746000000002,25.00399],"type":"Point"}
}