{
  "type": "Feature",
  "properties": {
    "iso:country":"TW",
    "name:ara_x_preferred":[
        "\u064a\u0648\u0646\u063a\u062f\u064a\u0646\u063a"
    ],
    "name:ben_x_preferred":[
        "\u0987\u09af\u09bc\u0982\u09a1\u09bf\u0982"
    ],
    "name:ell_x_preferred":[
        "\u0393\u03b9\u03bf\u03bd\u03b3\u03ba\u03bd\u03c4\u03af\u03bd\u03b3\u03ba"
    ],
    "name:eng_x_preferred":[
        "Yongding"
    ],
    "name:eng_x_variant":[
        "Yongding Village"
    ],
    "name:fas_x_preferred":[
        "\u06cc\u0648\u0646\u06af\u062f\u06cc\u0646\u06af"
    ],
    "name:heb_x_preferred":[
        "\u05d9\u05d0\u05e0\u05d2\u05d3\u05d9\u05e0\u05d2"
    ],
    "name:hin_x_preferred":[
        "\u092f\u094b\u0902\u0917\u0921\u093f\u0902\u0917"
    ],
    "name:hun_x_preferred":[
        "Yongding"
    ],
    "name:nld_x_preferred":[
        "Yongding"
    ],
    "name:por_x_preferred":[
        "Yongding"
    ],
    "name:spa_x_preferred":[
        "Yongding"
    ],
    "name:tur_x_preferred":[
        "Yongding"
    ],
    "name:urd_x_preferred":[
        "\u06cc\u0648\u0646\u06af \u0688\u0646\u06af"
    ],
    "name:zho_tw_x_preferred":[
        "\u6c38\u5b9a\u6751"
    ],
    "qs:name":"\u6c38\u5b9a\u6751",
    "qs:name_adm0":"\u81fa\u7063",
    "qs:name_adm1":"\u65b0\u5317\u5e02",
    "qs:photos":88,
    "qs:photos_1k":18,
    "qs:photos_9k":1,
    "qs:photos_9r":3,
    "qs:photos_all":88,
    "qs:photos_sr":3,
    "qs:placetype":"Town",
    "qs:pop_sr":"0",
    "wd:wordcount":257,
    "wof:name":"Yongding",
    "wof:placetype":"locality"
},
  "geometry": {"coordinates":[121.69074999999999,25.010795],"type":"Point"}
}