{
  "type": "Feature",
  "properties": {
    "iso:country":"TW",
    "qs:name":"\u6c38\u5b9a\u6751",
    "qs:name_adm0":"\u81fa\u7063",
    "qs:name_adm1":"\u65b0\u5317\u5e02",
    "qs:photos":88,
    "qs:photos_1k":18,
    "qs:photos_9k":1,
    "qs:photos_9r":3,
    "qs:photos_all":88,
    "qs:photos_sr":3,
    "qs:placetype":"Town",
    "qs:pop_sr":"0",
    "wd:wordcount":257,
    "wof:name":"\u6c38\u5b9a\u6751",
    "wof:placetype":"locality"
},
  "geometry": {"coordinates":[121.69074999999999,25.010795],"type":"Point"}
}