{
  "type": "Feature",
  "properties": {
    "gn:admin1_code":"04",
    "gn:admin2_code":"MIA",
    "gn:admin3_code":"K15",
    "gn:admin4_code":"10005080004.0",
    "gn:asciiname":"Baliaowan",
    "gn:country_code":"TW",
    "gn:dem":248,
    "gn:feature_class":"P",
    "gn:feature_code":"PPL",
    "gn:name":"Baliaowan",
    "gn:population":0,
    "gn:timezone":"Asia/Taipei",
    "iso:country":"TW",
    "name:und_x_variant":[
        "Pa-liao-wan"
    ],
    "name:zho_x_preferred":[
        "\u516b\u5bee\u7063"
    ],
    "wof:name":"Baliaowan",
    "wof:placetype":"locality"
},
  "geometry": {"coordinates":[120.87045999999999,24.43169],"type":"Point"}
}