{
  "type": "Feature",
  "properties": {
    "gn:admin1_code":"4.0",
    "gn:admin2_code":"HSZ",
    "gn:admin3_code":"J13",
    "gn:admin4_code":"10004110003.0",
    "gn:asciiname":"Shijing",
    "gn:country_code":"TW",
    "gn:dem":90,
    "gn:feature_class":"P",
    "gn:feature_code":"PPL",
    "gn:name":"Shijing",
    "gn:population":0,
    "gn:timezone":"Asia/Taipei",
    "iso:country":"TW",
    "name:und_x_variant":[
        "Shihjing",
        "Shih-ching"
    ],
    "name:zho_x_preferred":[
        "\u77f3\u4e95"
    ],
    "wof:name":"Shijing",
    "wof:placetype":"locality"
},
  "geometry": {"coordinates":[121.00291,24.69719],"type":"Point"}
}