{
  "type": "Feature",
  "properties": {
    "gn:admin1_code":"04",
    "gn:admin2_code":"TNN",
    "gn:admin3_code":"R13",
    "gn:admin4_code":"67000140010.0",
    "gn:asciiname":"Dawenliao",
    "gn:country_code":"TW",
    "gn:dem":8,
    "gn:feature_class":"P",
    "gn:feature_code":"PPL",
    "gn:name":"Dawenliao",
    "gn:population":0,
    "gn:timezone":"Asia/Taipei",
    "iso:country":"TW",
    "name:und_x_variant":[
        "Yung-lo",
        "Dawunliao",
        "Ta-wen-liao"
    ],
    "name:zho_x_preferred":[
        "\u5927\u586d\u5bee"
    ],
    "name:zho_x_variant":[
        "Yung-lo-ts\u2019un"
    ],
    "wof:name":"Dawenliao",
    "wof:placetype":"locality"
},
  "geometry": {"coordinates":[120.17833,23.10611],"type":"Point"}
}