{
  "type": "Feature",
  "properties": {
    "gn:admin1_code":"4.0",
    "gn:admin2_code":"CYQ",
    "gn:admin3_code":"Q13",
    "gn:admin4_code":"10010120021.0",
    "gn:asciiname":"Kengziping",
    "gn:country_code":"TW",
    "gn:dem":34,
    "gn:feature_class":"P",
    "gn:feature_code":"PPL",
    "gn:name":"Kengziping",
    "gn:population":0,
    "gn:timezone":"Asia/Taipei",
    "iso:country":"TW",
    "name:und_x_variant":[
        "Kengzihping",
        "Kengziping"
    ],
    "name:zho_x_preferred":[
        "\u5751\u4ed4\u5e73"
    ],
    "name:zho_x_variant":[
        "K\u2019eng-tzu-p\u2019ing"
    ],
    "wof:name":"Kengziping",
    "wof:placetype":"locality"
},
  "geometry": {"coordinates":[120.43694000000001,23.42611],"type":"Point"}
}