{
  "type": "Feature",
  "properties": {
    "gn:admin1_code":"4.0",
    "gn:admin2_code":"YUN",
    "gn:admin3_code":"P18",
    "gn:admin4_code":"10009180007.0",
    "gn:asciiname":"Luonei",
    "gn:country_code":"TW",
    "gn:dem":6,
    "gn:feature_class":"P",
    "gn:feature_code":"PPL",
    "gn:name":"Luonei",
    "gn:population":0,
    "gn:timezone":"Asia/Taipei",
    "iso:country":"TW",
    "name:und_x_variant":[
        "L\u00fceh-nei",
        "Luonei",
        "Lo-nei"
    ],
    "name:zho_x_preferred":[
        "\u54af\u5185"
    ],
    "name:zho_x_variant":[
        "K\u2019o-nei",
        "L\u00fceh-nei"
    ],
    "wof:name":"Luonei",
    "wof:placetype":"locality"
},
  "geometry": {"coordinates":[120.22944,23.62389],"type":"Point"}
}