{
  "type": "Feature",
  "properties": {
    "gn:admin1_code":"4.0",
    "gn:admin2_code":"TNN",
    "gn:admin3_code":"R25",
    "gn:admin4_code":"67000250009.0",
    "gn:asciiname":"Muguakeng",
    "gn:country_code":"TW",
    "gn:dem":358,
    "gn:feature_class":"P",
    "gn:feature_code":"PPL",
    "gn:name":"Muguakeng",
    "gn:population":0,
    "gn:timezone":"Asia/Taipei",
    "iso:country":"TW",
    "name:zho_x_preferred":[
        "Kuei-ts\u2019ang"
    ],
    "name:zho_x_variant":[
        "\u6728\u74dc\u5751",
        "Mu-kua-k\u2019eng"
    ],
    "wof:name":"Muguakeng",
    "wof:placetype":"locality"
},
  "geometry": {"coordinates":[120.61528,23.21917],"type":"Point"}
}