{
  "type": "Feature",
  "properties": {
    "gn:admin1_code":"4.0",
    "gn:admin2_code":"YUN",
    "gn:admin3_code":"P18",
    "gn:admin4_code":"10009180015.0",
    "gn:asciiname":"Sanfang",
    "gn:country_code":"TW",
    "gn:dem":4,
    "gn:feature_class":"P",
    "gn:feature_code":"PPL",
    "gn:name":"Sanfang",
    "gn:population":0,
    "gn:timezone":"Asia/Taipei",
    "iso:country":"TW",
    "name:und_x_variant":[
        "San-fang"
    ],
    "name:zho_x_preferred":[
        "\u4e09\u623f"
    ],
    "wof:name":"Sanfang",
    "wof:placetype":"locality"
},
  "geometry": {"coordinates":[120.16083,23.64167],"type":"Point"}
}