{
  "type": "Feature",
  "properties": {
    "gn:admin1_code":"04",
    "gn:admin2_code":"HSZ",
    "gn:admin3_code":"J14",
    "gn:admin4_code":"10004120001.0",
    "gn:asciiname":"Matai",
    "gn:country_code":"TW",
    "gn:dem":729,
    "gn:feature_class":"P",
    "gn:feature_code":"PPL",
    "gn:name":"Matai",
    "gn:population":0,
    "gn:timezone":"Asia/Taipei",
    "iso:country":"TW",
    "name:ceb_x_preferred":[
        "Matai"
    ],
    "name:deu_x_preferred":[
        "Matai"
    ],
    "name:swe_x_preferred":[
        "Matai"
    ],
    "name:und_x_variant":[
        "Ma-i"
    ],
    "name:zho_x_preferred":[
        "\u99ac\u80ce"
    ],
    "name:zho_x_variant":[
        "Ma-t\u2019ai"
    ],
    "wof:name":"Matai",
    "wof:placetype":"locality"
},
  "geometry": {"coordinates":[121.18444,24.68167],"type":"Point"}
}