{
  "type": "Feature",
  "properties": {
    "gn:admin1_code":"4.0",
    "gn:admin2_code":"MIA",
    "gn:admin3_code":"K07",
    "gn:admin4_code":"10005140003.0",
    "gn:asciiname":"Pitoumian",
    "gn:country_code":"TW",
    "gn:dem":79,
    "gn:feature_class":"P",
    "gn:feature_code":"PPL",
    "gn:name":"Pitoumian",
    "gn:population":0,
    "gn:timezone":"Asia/Taipei",
    "iso:country":"TW",
    "name:zho_x_preferred":[
        "\u57e4\u982d\u9762"
    ],
    "name:zho_x_variant":[
        "P\u2019i-t\u2019ou-mien"
    ],
    "wof:name":"Pitoumian",
    "wof:placetype":"locality"
},
  "geometry": {"coordinates":[120.76778,24.52999],"type":"Point"}
}