{
  "type": "Feature",
  "properties": {
    "gn:admin1_code":"4.0",
    "gn:admin2_code":"HSZ",
    "gn:admin3_code":"J10",
    "gn:admin4_code":"10004070001.0",
    "gn:asciiname":"Shihouzi",
    "gn:country_code":"TW",
    "gn:dem":189,
    "gn:feature_class":"P",
    "gn:feature_code":"PPL",
    "gn:name":"Shihouzi",
    "gn:population":0,
    "gn:timezone":"Asia/Taipei",
    "iso:country":"TW",
    "name:und_x_variant":[
        "Shihhouzih",
        "Shih-hou-tzu"
    ],
    "name:zho_x_preferred":[
        "\u77f3\u543c\u5b50"
    ],
    "wof:name":"Shihouzi",
    "wof:placetype":"locality"
},
  "geometry": {"coordinates":[121.12694,24.73389],"type":"Point"}
}