{
  "type": "Feature",
  "properties": {
    "gn:admin1_code":"04",
    "gn:admin2_code":"ILA",
    "gn:admin3_code":"G11",
    "gn:admin4_code":"10002110006.0",
    "gn:asciiname":"Donglei",
    "gn:country_code":"TW",
    "gn:dem":307,
    "gn:feature_class":"P",
    "gn:feature_code":"PPL",
    "gn:name":"Donglei",
    "gn:population":0,
    "gn:timezone":"Asia/Taipei",
    "iso:country":"TW",
    "name:und_x_variant":[
        "Tung-lei-she",
        "Tung-tieh-she",
        "Donglei",
        "Tung-lei"
    ],
    "name:zho_x_preferred":[
        "\u6771\u58d8"
    ],
    "wof:name":"Donglei",
    "wof:placetype":"locality"
},
  "geometry": {"coordinates":[121.53117,24.60442],"type":"Point"}
}