{
  "type": "Feature",
  "properties": {
    "gn:admin1_code":"04",
    "gn:admin2_code":"CYQ",
    "gn:admin3_code":"Q02",
    "gn:admin4_code":"10010020018.0",
    "gn:asciiname":"Dong'anliao",
    "gn:country_code":"TW",
    "gn:dem":6,
    "gn:feature_class":"P",
    "gn:feature_code":"PPL",
    "gn:name":"Dong\u2019anliao",
    "gn:population":0,
    "gn:timezone":"Asia/Taipei",
    "iso:country":"TW",
    "name:und_x_variant":[
        "Tung-an-liao"
    ],
    "name:zho_x_preferred":[
        "Dong\u2019anliao"
    ],
    "wof:name":"Dong'anliao",
    "wof:placetype":"locality"
},
  "geometry": {"coordinates":[120.25,23.45],"type":"Point"}
}