{
  "type": "Feature",
  "properties": {
    "gn:admin1_code":"4.0",
    "gn:admin2_code":"NAN",
    "gn:admin3_code":"M03",
    "gn:admin4_code":"10008030008.0",
    "gn:asciiname":"Xidizi",
    "gn:country_code":"TW",
    "gn:dem":85,
    "gn:feature_class":"P",
    "gn:feature_code":"PPL",
    "gn:name":"Xidizi",
    "gn:population":0,
    "gn:timezone":"Asia/Taipei",
    "iso:country":"TW",
    "name:und_x_variant":[
        "\u6eaa\u5e95\u5b50",
        "Xidizi",
        "Sidizih",
        "Hsi-ti-tzu"
    ],
    "wof:name":"Xidizi",
    "wof:placetype":"locality"
},
  "geometry": {"coordinates":[120.6763,24.0097],"type":"Point"}
}