{
  "type": "Feature",
  "properties": {
    "gn:admin1_code":"04",
    "gn:admin2_code":"HSZ",
    "gn:admin3_code":"J12",
    "gn:admin4_code":"10004090009.0",
    "gn:asciiname":"Neidaping",
    "gn:country_code":"TW",
    "gn:dem":348,
    "gn:feature_class":"P",
    "gn:feature_code":"PPL",
    "gn:name":"Neidaping",
    "gn:population":0,
    "gn:timezone":"Asia/Taipei",
    "iso:country":"TW",
    "name:zho_x_preferred":[
        "\u5167\u5927\u576a"
    ],
    "name:zho_x_variant":[
        "Nei-ta-p\u2019ing"
    ],
    "wof:name":"Neidaping",
    "wof:placetype":"locality"
},
  "geometry": {"coordinates":[121.06999999999999,24.65139],"type":"Point"}
}