{
  "type": "Feature",
  "properties": {
    "gn:admin1_code":"04",
    "gn:admin2_code":"PIF",
    "gn:admin3_code":"T04",
    "gn:admin4_code":"10013040014.0",
    "gn:asciiname":"Binlangjiao",
    "gn:country_code":"TW",
    "gn:dem":41,
    "gn:feature_class":"P",
    "gn:feature_code":"PPL",
    "gn:name":"Binlangjiao",
    "gn:population":0,
    "gn:timezone":"Asia/Taipei",
    "iso:country":"TW",
    "name:und_x_variant":[
        "Pin-lang-chiao"
    ],
    "name:zho_x_preferred":[
        "\u6ab3\u6994\u811a"
    ],
    "wof:name":"Binlangjiao",
    "wof:placetype":"locality"
},
  "geometry": {"coordinates":[120.73278000000001,21.92222000000001],"type":"Point"}
}