{
  "type": "Feature",
  "properties": {
    "gn:admin1_code":"04",
    "gn:admin2_code":"ILA",
    "gn:admin3_code":"G09",
    "gn:admin4_code":"10002030005.0",
    "gn:asciiname":"Sanmiancheng",
    "gn:country_code":"TW",
    "gn:dem":7,
    "gn:feature_class":"P",
    "gn:feature_code":"PPL",
    "gn:name":"Sanmiancheng",
    "gn:population":0,
    "gn:timezone":"Asia/Taipei",
    "iso:country":"TW",
    "name:zho_x_preferred":[
        "\u4e09\u9762\u57ce"
    ],
    "name:zho_x_variant":[
        "San-mien-ch\u2019eng"
    ],
    "wof:name":"Sanmiancheng",
    "wof:placetype":"locality"
},
  "geometry": {"coordinates":[121.84591,24.61468],"type":"Point"}
}