{
  "type": "Feature",
  "properties": {
    "gn:admin1_code":"1.0",
    "gn:admin2_code":"KIN",
    "gn:admin3_code":"W05",
    "gn:admin4_code":"9020050005.0",
    "gn:asciiname":"Anding",
    "gn:country_code":"TW",
    "gn:dem":54,
    "gn:feature_class":"P",
    "gn:feature_code":"PPL",
    "gn:name":"Anding",
    "gn:population":0,
    "gn:timezone":"Asia/Taipei",
    "iso:country":"TW",
    "name:und_x_variant":[
        "\u5eb5\u9802",
        "An-ting",
        "Anding"
    ],
    "wof:name":"Anding",
    "wof:placetype":"locality"
},
  "geometry": {"coordinates":[118.24951,24.43922],"type":"Point"}
}