{
  "type": "Feature",
  "properties": {
    "iso:country":"TW",
    "name:zho_x_preferred":[
        "\u7887\u548c\u91cc"
    ],
    "qs:gn_adm0_cc":"TW",
    "qs:gn_local":1678228,
    "qs:local_max":2352,
    "qs:local_sum":26237,
    "qs:localhoods":59,
    "qs:name":"\u7887\u548c\u91cc",
    "qs:name_adm0":"\u81fa\u7063",
    "qs:name_adm1":"\u57fa\u9686\u5e02",
    "qs:name_adm2":"\u6696\u6696\u5340",
    "qs:name_local":"\u57fa\u9686\u5e02",
    "qs:photo_max":42,
    "qs:photo_sum":108,
    "qs:placetype":"Suburb",
    "qs:quad_count":12,
    "qs:woe_adm0":23424971,
    "qs:woe_adm1":22695855,
    "qs:woe_adm2":2301634,
    "qs:woe_lau":0,
    "qs:woe_local":2306188,
    "qs:woe_ver":"7.10.0",
    "wof:lang":[
        "chi"
    ],
    "wof:name":"\u7887\u548c\u91cc",
    "wof:placetype":"neighbourhood"
},
  "geometry": {"coordinates":[121.74403100000001,25.099609],"type":"Point"}
}