{
  "type": "Feature",
  "properties": {
    "gn:admin1_code":"4.0",
    "gn:admin2_code":"TNN",
    "gn:admin3_code":"R27",
    "gn:admin4_code":"67000270005.0",
    "gn:asciiname":"Rende",
    "gn:country_code":"TW",
    "gn:dem":11,
    "gn:feature_class":"P",
    "gn:feature_code":"PPL",
    "gn:name":"Rende",
    "gn:population":0,
    "gn:timezone":"Asia/Taipei",
    "iso:country":"TW",
    "name:und_x_variant":[
        "J\u00ean-teh",
        "Rende",
        "Jen-te"
    ],
    "name:zho_x_preferred":[
        "Jen-te-ts\u2019un"
    ],
    "name:zho_x_variant":[
        "\u4ec1\u5fb7",
        "J\u00ean-Teh-Ts\u2019un",
        "J\u00ean-teh"
    ],
    "wof:name":"Rende",
    "wof:placetype":"locality"
},
  "geometry": {"coordinates":[120.25333000000001,22.96972],"type":"Point"}
}