{
  "type": "Feature",
  "properties": {
    "gn:admin1_code":"4.0",
    "gn:admin2_code":"MIA",
    "gn:admin3_code":"K17",
    "gn:admin4_code":"10005170002.0",
    "gn:asciiname":"Liufen",
    "gn:country_code":"TW",
    "gn:dem":206,
    "gn:feature_class":"P",
    "gn:feature_code":"PPL",
    "gn:name":"Liufen",
    "gn:population":0,
    "gn:timezone":"Asia/Taipei",
    "iso:country":"TW",
    "name:und_x_variant":[
        "Lioufen",
        "Liu-fen"
    ],
    "name:zho_x_preferred":[
        "\u516d\u4efd"
    ],
    "wof:name":"Liufen",
    "wof:placetype":"locality"
},
  "geometry": {"coordinates":[120.92767000000001,24.55012],"type":"Point"}
}