{
  "type": "Feature",
  "properties": {
    "iso:country":"TW",
    "name:eng_x_preferred":[
        "Qingye"
    ],
    "name:eng_x_variant":[
        "Qingye Village"
    ],
    "name:zho_tw_x_preferred":[
        "\u9752\u8449\u6751"
    ],
    "qs:name":"\u9752\u8449\u6751",
    "qs:name_adm0":"\u81fa\u7063",
    "qs:name_adm1":"\u5c4f\u6771\u7e23",
    "qs:photos":341,
    "qs:photos_1k":69,
    "qs:photos_9k":2,
    "qs:photos_9r":5,
    "qs:photos_all":341,
    "qs:photos_sr":5,
    "qs:placetype":"Town",
    "qs:pop_sr":"0",
    "wof:name":"Qingye",
    "wof:placetype":"locality"
},
  "geometry": {"coordinates":[120.664389,22.885167],"type":"Point"}
}