{
  "type": "Feature",
  "properties": {
    "gn:admin1_code":"4.0",
    "gn:admin2_code":"CHA",
    "gn:admin3_code":"N01",
    "gn:admin4_code":"10007010070.0",
    "gn:asciiname":"Niuchouhu",
    "gn:country_code":"TW",
    "gn:dem":146,
    "gn:feature_class":"P",
    "gn:feature_code":"PPL",
    "gn:name":"Niuchouhu",
    "gn:population":0,
    "gn:timezone":"Asia/Taipei",
    "iso:country":"TW",
    "name:und_x_variant":[
        "Niouchouhu"
    ],
    "name:zho_x_preferred":[
        "\u725b\u7a20\u6e56"
    ],
    "name:zho_x_variant":[
        "Niu-ch\u2019ou-hu"
    ],
    "wof:name":"Niuchouhu",
    "wof:placetype":"locality"
},
  "geometry": {"coordinates":[120.59276,24.06124],"type":"Point"}
}