{
  "type": "Feature",
  "properties": {
    "gn:admin1_code":"02",
    "gn:admin2_code":"KHH",
    "gn:admin3_code":"E24",
    "gn:admin4_code":"64000240007.0",
    "gn:asciiname":"Yinghou",
    "gn:country_code":"TW",
    "gn:dem":10,
    "gn:feature_class":"P",
    "gn:feature_code":"PPL",
    "gn:name":"Yinghou",
    "gn:population":0,
    "gn:timezone":"Asia/Taipei",
    "iso:country":"TW",
    "name:und_x_variant":[
        "Ying-hou"
    ],
    "name:zho_x_preferred":[
        "\u71df\u5f8c"
    ],
    "wof:name":"Yinghou",
    "wof:placetype":"locality"
},
  "geometry": {"coordinates":[120.27,22.88917],"type":"Point"}
}