{
  "type": "Feature",
  "properties": {
    "gn:admin1_code":"4.0",
    "gn:admin2_code":"HUA",
    "gn:admin3_code":"U11",
    "gn:admin4_code":"10015110002.0",
    "gn:asciiname":"Xipan",
    "gn:country_code":"TW",
    "gn:dem":160,
    "gn:feature_class":"P",
    "gn:feature_code":"PPL",
    "gn:name":"Xipan",
    "gn:population":0,
    "gn:timezone":"Asia/Taipei",
    "iso:country":"TW",
    "name:und_x_variant":[
        "Sipan",
        "Xipan"
    ],
    "name:zho_x_preferred":[
        "\u6eaa\u7554"
    ],
    "name:zho_x_variant":[
        "Ch\u2019i-p\u2019an",
        "Hsi-p\u2019an"
    ],
    "wof:name":"Xipan",
    "wof:placetype":"locality"
},
  "geometry": {"coordinates":[121.58215,24.17978],"type":"Point"}
}