{
  "type": "Feature",
  "properties": {
    "gn:admin1_code":"4.0",
    "gn:admin2_code":"CHA",
    "gn:admin3_code":"N01",
    "gn:admin4_code":"10007010067.0",
    "gn:asciiname":"Tulonggouwan",
    "gn:country_code":"TW",
    "gn:dem":148,
    "gn:feature_class":"P",
    "gn:feature_code":"PPL",
    "gn:name":"Tulonggouwan",
    "gn:population":0,
    "gn:timezone":"Asia/Taipei",
    "iso:country":"TW",
    "name:zho_x_preferred":[
        "\u571f\u9f8d\u6e9d\u7063"
    ],
    "name:zho_x_variant":[
        "T\u2019u-lung-kou-wan"
    ],
    "wof:name":"Tulonggouwan",
    "wof:placetype":"locality"
},
  "geometry": {"coordinates":[120.60054,24.04345],"type":"Point"}
}