{
  "type": "Feature",
  "properties": {
    "gn:admin1_code":"04",
    "gn:admin2_code":"TNN",
    "gn:admin3_code":"R14",
    "gn:admin4_code":"67000150014.0",
    "gn:asciiname":"Shiyifen",
    "gn:country_code":"TW",
    "gn:dem":2,
    "gn:feature_class":"P",
    "gn:feature_code":"PPL",
    "gn:name":"Shiyifen",
    "gn:population":0,
    "gn:timezone":"Asia/Taipei",
    "iso:country":"TW",
    "name:und_x_variant":[
        "Shih-i-fen",
        "Shiyifen",
        "Shihyifen",
        "\u5341\u4e00\u5206"
    ],
    "name:zho_x_preferred":[
        "\u5341\u4e00\u5206"
    ],
    "wof:name":"Shiyifen",
    "wof:placetype":"locality"
},
  "geometry": {"coordinates":[120.13861,23.12222],"type":"Point"}
}