{
  "type": "Feature",
  "properties": {
    "gn:admin1_code":"3.0",
    "gn:admin2_code":"TPQ",
    "gn:admin3_code":"F15",
    "gn:admin4_code":"65000090021.0",
    "gn:asciiname":"Lumutanzi",
    "gn:country_code":"TW",
    "gn:dem":220,
    "gn:feature_class":"P",
    "gn:feature_code":"PPL",
    "gn:name":"Lumutanzi",
    "gn:population":0,
    "gn:timezone":"Asia/Taipei",
    "iso:country":"TW",
    "name:und_x_variant":[
        "Lumutanzih"
    ],
    "name:zho_x_preferred":[
        "\u9e7f\u6bcd\u6f6d\u5b50"
    ],
    "name:zho_x_variant":[
        "Lu-mu-t\u2019an-tzu"
    ],
    "wof:name":"Lumutanzi",
    "wof:placetype":"locality"
},
  "geometry": {"coordinates":[121.46878999999998,24.91747],"type":"Point"}
}