{
  "type": "Feature",
  "properties": {
    "gn:admin1_code":"4.0",
    "gn:admin2_code":"YUN",
    "gn:admin3_code":"P07",
    "gn:admin4_code":"10009070013.0",
    "gn:asciiname":"Shiqiao",
    "gn:country_code":"TW",
    "gn:dem":616,
    "gn:feature_class":"P",
    "gn:feature_code":"PPL",
    "gn:name":"Shiqiao",
    "gn:population":0,
    "gn:timezone":"Asia/Taipei",
    "iso:country":"TW",
    "name:ceb_x_preferred":[
        "Shiqiao"
    ],
    "name:deu_x_preferred":[
        "Shiqiao"
    ],
    "name:swe_x_preferred":[
        "Shiqiao"
    ],
    "name:und_x_variant":[
        "Shihciao",
        "Shiqiao"
    ],
    "name:zho_x_preferred":[
        "\u77f3\u6a4b"
    ],
    "name:zho_x_variant":[
        "Shih-ch\u2019iao"
    ],
    "wof:name":"Shiqiao",
    "wof:placetype":"locality"
},
  "geometry": {"coordinates":[120.6375,23.60917],"type":"Point"}
}