{
  "type": "Feature",
  "properties": {
    "gn:admin1_code":"4.0",
    "gn:admin2_code":"TNN",
    "gn:admin3_code":"R27",
    "gn:admin4_code":"67000270006.0",
    "gn:asciiname":"Gourou",
    "gn:country_code":"TW",
    "gn:dem":17,
    "gn:feature_class":"P",
    "gn:feature_code":"PPL",
    "gn:name":"Gourou",
    "gn:population":0,
    "gn:timezone":"Asia/Taipei",
    "iso:country":"TW",
    "name:und_x_variant":[
        "Kou-jou"
    ],
    "name:zho_x_preferred":[
        "\u72d7\u8089"
    ],
    "wof:name":"Gourou",
    "wof:placetype":"locality"
},
  "geometry": {"coordinates":[120.26806000000001,22.95944],"type":"Point"}
}