{
  "type": "Feature",
  "properties": {
    "iso:country":"TW",
    "qs:name":"\u65b0\u5a01\u6751",
    "qs:name_adm0":"\u81fa\u7063",
    "qs:name_adm1":"\u9ad8\u96c4\u5e02",
    "qs:photos":381,
    "qs:photos_1k":77,
    "qs:photos_9k":2,
    "qs:photos_9r":5,
    "qs:photos_all":381,
    "qs:photos_sr":6,
    "qs:placetype":"Town",
    "qs:pop_sr":"0",
    "wof:name":"\u65b0\u5a01\u6751",
    "wof:placetype":"locality"
},
  "geometry": {"coordinates":[120.621128,22.901519],"type":"Point"}
}