{
  "type": "Feature",
  "properties": {
    "iso:country":"TW",
    "qs:name":"\u5149\u83ef\u6751",
    "qs:name_adm0":"\u81fa\u7063",
    "qs:name_adm1":"\u82b1\u84ee\u7e23",
    "qs:photos":36,
    "qs:photos_1k":7,
    "qs:photos_9k":1,
    "qs:photos_9r":2,
    "qs:photos_all":36,
    "qs:photos_sr":2,
    "qs:placetype":"Town",
    "qs:pop_sr":"0",
    "wof:name":"\u5149\u83ef\u6751",
    "wof:placetype":"locality"
},
  "geometry": {"coordinates":[121.59702249999999,23.916408],"type":"Point"}
}