{
  "type": "Feature",
  "properties": {
    "gn:admin1_code":"3.0",
    "gn:admin2_code":"TPQ",
    "gn:admin3_code":"F06",
    "gn:admin4_code":"65000160002.0",
    "gn:asciiname":"Ganchengsancun",
    "gn:country_code":"TW",
    "gn:dem":49,
    "gn:feature_class":"P",
    "gn:feature_code":"PPL",
    "gn:name":"Ganchengsancun",
    "gn:population":0,
    "gn:timezone":"Asia/Taipei",
    "iso:country":"TW",
    "name:und_x_variant":[
        "Kan-ch\u2019eng-san-ts\u2019un"
    ],
    "wof:name":"Ganchengsancun",
    "wof:placetype":"locality"
},
  "geometry": {"coordinates":[121.41667,25.06667],"type":"Point"}
}