{
  "type": "Feature",
  "properties": {
    "gn:admin1_code":"4.0",
    "gn:admin2_code":"TTT",
    "gn:admin3_code":"V06",
    "gn:admin4_code":"10014090001.0",
    "gn:asciiname":"Qianbancuo",
    "gn:country_code":"TW",
    "gn:dem":391,
    "gn:feature_class":"P",
    "gn:feature_code":"PPL",
    "gn:name":"Qianbancuo",
    "gn:population":0,
    "gn:timezone":"Asia/Taipei",
    "iso:country":"TW",
    "name:und_x_variant":[
        "Cianbancuo",
        "Qianbancuo"
    ],
    "name:zho_x_preferred":[
        "\u925b\u677f\u539d"
    ],
    "name:zho_x_variant":[
        "Ch\u2019ien-pan-ts\u2019o"
    ],
    "wof:name":"Qianbancuo",
    "wof:placetype":"locality"
},
  "geometry": {"coordinates":[121.00055999999999,22.68306],"type":"Point"}
}