{
  "type": "Feature",
  "properties": {
    "gn:admin1_code":"4.0",
    "gn:admin2_code":"HUA",
    "gn:admin3_code":"U01",
    "gn:admin4_code":"10015010045.0",
    "gn:asciiname":"Huadong",
    "gn:country_code":"TW",
    "gn:dem":14,
    "gn:feature_class":"P",
    "gn:feature_code":"PPL",
    "gn:name":"Huadong",
    "gn:population":0,
    "gn:timezone":"Asia/Taipei",
    "iso:country":"TW",
    "name:und_x_variant":[
        "Hua-tung"
    ],
    "name:zho_x_preferred":[
        "\u83ef\u6771"
    ],
    "wof:name":"Huadong",
    "wof:placetype":"locality"
},
  "geometry": {"coordinates":[121.63297,24.00648],"type":"Point"}
}