{
  "type": "Feature",
  "properties": {
    "gn:admin1_code":"04",
    "gn:admin2_code":"TNN",
    "gn:admin3_code":"R17",
    "gn:admin4_code":"67000130010.0",
    "gn:asciiname":"Waliao",
    "gn:country_code":"TW",
    "gn:dem":7,
    "gn:feature_class":"P",
    "gn:feature_code":"PPL",
    "gn:name":"Waliao",
    "gn:population":0,
    "gn:timezone":"Asia/Taipei",
    "iso:country":"TW",
    "name:und_x_variant":[
        "Wa-liao"
    ],
    "name:zho_x_preferred":[
        "\u74e6\u5bee"
    ],
    "wof:name":"Waliao",
    "wof:placetype":"locality"
},
  "geometry": {"coordinates":[120.21306,23.23389],"type":"Point"}
}