{
  "type": "Feature",
  "properties": {
    "gn:admin1_code":"3.0",
    "gn:admin2_code":"TPQ",
    "gn:admin3_code":"F32",
    "gn:admin4_code":"65000230003.0",
    "gn:asciiname":"Ximen",
    "gn:country_code":"TW",
    "gn:dem":23,
    "gn:feature_class":"P",
    "gn:feature_code":"PPL",
    "gn:name":"Ximen",
    "gn:population":0,
    "gn:timezone":"Asia/Taipei",
    "iso:country":"TW",
    "name:und_x_variant":[
        "Simen",
        "Ximen",
        "Hsi-men"
    ],
    "name:zho_x_preferred":[
        "\u897f\u9580"
    ],
    "name:zho_x_variant":[
        "\u897f\u9580\u59d3"
    ],
    "wof:name":"Ximen",
    "wof:placetype":"locality"
},
  "geometry": {"coordinates":[121.42783,25.15741],"type":"Point"}
}