{
  "type": "Feature",
  "properties": {
    "gn:admin1_code":"4.0",
    "gn:admin2_code":"TAO",
    "gn:admin3_code":"H11",
    "gn:admin4_code":"68000110022.0",
    "gn:asciiname":"Youcuo",
    "gn:country_code":"TW",
    "gn:dem":36,
    "gn:feature_class":"P",
    "gn:feature_code":"PPL",
    "gn:name":"Youcuo",
    "gn:population":0,
    "gn:timezone":"Asia/Taipei",
    "iso:country":"TW",
    "name:und_x_variant":[
        "Yu-wu",
        "Youcuo"
    ],
    "name:zho_x_preferred":[
        "\u6e38\u539d"
    ],
    "name:zho_x_variant":[
        "Yu-ts\u2019o"
    ],
    "wof:name":"Youcuo",
    "wof:placetype":"locality"
},
  "geometry": {"coordinates":[121.03583,24.9625],"type":"Point"}
}