{
  "type": "Feature",
  "properties": {
    "gn:admin1_code":"4.0",
    "gn:admin2_code":"CHA",
    "gn:admin3_code":"N11",
    "gn:admin4_code":"10007060021.0",
    "gn:asciiname":"Shewei",
    "gn:country_code":"TW",
    "gn:dem":12,
    "gn:feature_class":"P",
    "gn:feature_code":"PPL",
    "gn:name":"Shewei",
    "gn:population":0,
    "gn:timezone":"Asia/Taipei",
    "iso:country":"TW",
    "name:und_x_variant":[
        "She-wei"
    ],
    "name:zho_x_preferred":[
        "\u793e\u5c3e"
    ],
    "wof:name":"Shewei",
    "wof:placetype":"locality"
},
  "geometry": {"coordinates":[120.44167,24.03083],"type":"Point"}
}