{
  "type": "Feature",
  "properties": {
    "gn:admin1_code":"4.0",
    "gn:admin2_code":"PIF",
    "gn:admin3_code":"T01",
    "gn:admin4_code":"10013010054.0",
    "gn:asciiname":"Qianjin",
    "gn:country_code":"TW",
    "gn:dem":18,
    "gn:feature_class":"P",
    "gn:feature_code":"PPL",
    "gn:name":"Qianjin",
    "gn:population":0,
    "gn:timezone":"Asia/Taipei",
    "iso:country":"TW",
    "name:und_x_variant":[
        "\u524d\u9032",
        "Qianjin",
        "Cianjin"
    ],
    "name:zho_x_preferred":[
        "Ch\u2019ien-chin"
    ],
    "name:zho_x_variant":[
        "Ch\u2019ien-chin-li",
        "\u524d\u9032"
    ],
    "wof:name":"Qianjin",
    "wof:placetype":"locality"
},
  "geometry": {"coordinates":[120.46704,22.65184],"type":"Point"}
}