{
  "type": "Feature",
  "properties": {
    "gn:admin1_code":"4.0",
    "gn:admin2_code":"CYQ",
    "gn:admin3_code":"Q08",
    "gn:admin4_code":"10010080019.0",
    "gn:asciiname":"Xiabuzi",
    "gn:country_code":"TW",
    "gn:dem":7,
    "gn:feature_class":"P",
    "gn:feature_code":"PPL",
    "gn:name":"Xiabuzi",
    "gn:population":0,
    "gn:timezone":"Asia/Taipei",
    "iso:country":"TW",
    "name:und_x_variant":[
        "Hsia-pu-tzu"
    ],
    "wof:name":"Xiabuzi",
    "wof:placetype":"locality"
},
  "geometry": {"coordinates":[120.25,23.48333],"type":"Point"}
}