{
  "type": "Feature",
  "properties": {
    "gn:admin1_code":"4.0",
    "gn:admin2_code":"CYQ",
    "gn:admin3_code":"Q15",
    "gn:admin4_code":"10010140001.0",
    "gn:asciiname":"Jiudian",
    "gn:country_code":"TW",
    "gn:dem":119,
    "gn:feature_class":"P",
    "gn:feature_code":"PPL",
    "gn:name":"Jiudian",
    "gn:population":0,
    "gn:timezone":"Asia/Taipei",
    "iso:country":"TW",
    "name:und_x_variant":[
        "Jioudian",
        "Jiudian",
        "Chiu-tien"
    ],
    "name:zho_x_preferred":[
        "\u9152\u5e97"
    ],
    "wof:name":"Jiudian",
    "wof:placetype":"locality"
},
  "geometry": {"coordinates":[120.54722,23.51944],"type":"Point"}
}