{
  "type": "Feature",
  "properties": {
    "gn:admin1_code":"4.0",
    "gn:admin2_code":"TNN",
    "gn:admin3_code":"R06",
    "gn:admin4_code":"67000060011.0",
    "gn:asciiname":"Dongyuan",
    "gn:country_code":"TW",
    "gn:dem":84,
    "gn:feature_class":"P",
    "gn:feature_code":"PPL",
    "gn:name":"Dongyuan",
    "gn:population":0,
    "gn:timezone":"Asia/Taipei",
    "iso:country":"TW",
    "name:zho_x_preferred":[
        "\u6771\u539f"
    ],
    "name:zho_x_variant":[
        "Ch\u2019ien-ta-pu",
        "Tung-y\u00fcan"
    ],
    "wof:name":"Dongyuan",
    "wof:placetype":"locality"
},
  "geometry": {"coordinates":[120.44499999999999,23.26472],"type":"Point"}
}