{
  "type": "Feature",
  "properties": {
    "gn:admin1_code":"4.0",
    "gn:admin2_code":"NAN",
    "gn:admin3_code":"M05",
    "gn:admin4_code":"10008050011.0",
    "gn:asciiname":"Tuntian",
    "gn:country_code":"TW",
    "gn:dem":242,
    "gn:feature_class":"P",
    "gn:feature_code":"PPL",
    "gn:name":"Tuntian",
    "gn:population":0,
    "gn:timezone":"Asia/Taipei",
    "iso:country":"TW",
    "name:zho_x_preferred":[
        "\u5c6f\u7530"
    ],
    "name:zho_x_variant":[
        "T\u2019un-t\u2019ien"
    ],
    "wof:name":"Tuntian",
    "wof:placetype":"locality"
},
  "geometry": {"coordinates":[120.79333,23.83507],"type":"Point"}
}