{
  "type": "Feature",
  "properties": {
    "gn:admin1_code":"4.0",
    "gn:admin2_code":"HSZ",
    "gn:admin3_code":"J08",
    "gn:admin4_code":"10004080011.0",
    "gn:asciiname":"Shifenliao",
    "gn:country_code":"TW",
    "gn:dem":220,
    "gn:feature_class":"P",
    "gn:feature_code":"PPL",
    "gn:name":"Shifenliao",
    "gn:population":0,
    "gn:timezone":"Asia/Taipei",
    "iso:country":"TW",
    "name:und_x_variant":[
        "Ho-hsing",
        "Shifenliao",
        "Shihfenliao",
        "Shih-fen-liao"
    ],
    "name:zho_x_preferred":[
        "\u5341\u5206\u5bee"
    ],
    "wof:name":"Shifenliao",
    "wof:placetype":"locality"
},
  "geometry": {"coordinates":[121.15443999999999,24.7175],"type":"Point"}
}