{
  "type": "Feature",
  "properties": {
    "gn:admin1_code":"04",
    "gn:admin2_code":"CYQ",
    "gn:admin3_code":"Q16",
    "gn:admin4_code":"10010150015.0",
    "gn:asciiname":"Dibu",
    "gn:country_code":"TW",
    "gn:dem":1235,
    "gn:feature_class":"P",
    "gn:feature_code":"PPL",
    "gn:name":"Dibu",
    "gn:population":0,
    "gn:timezone":"Asia/Taipei",
    "iso:country":"TW",
    "name:und_x_variant":[
        "Ti-pu"
    ],
    "name:zho_x_preferred":[
        "\u5754\u57d4"
    ],
    "wof:name":"Dibu",
    "wof:placetype":"locality"
},
  "geometry": {"coordinates":[120.68167,23.55333],"type":"Point"}
}