{
  "type": "Feature",
  "properties": {
    "gn:admin1_code":"4.0",
    "gn:admin2_code":"PIF",
    "gn:admin3_code":"T31",
    "gn:admin4_code":"10013310006.0",
    "gn:asciiname":"Lili",
    "gn:country_code":"TW",
    "gn:dem":147,
    "gn:feature_class":"P",
    "gn:feature_code":"PPL",
    "gn:name":"Lili",
    "gn:population":0,
    "gn:timezone":"Asia/Taipei",
    "iso:country":"TW",
    "name:und_x_variant":[
        "Li-chi-li-chi-she",
        "Li-li-ts\u2019un",
        "\u529b\u91cc",
        "Y\u00fcan-shan",
        "Lili",
        "Li-li"
    ],
    "wof:name":"Lili",
    "wof:placetype":"locality"
},
  "geometry": {"coordinates":[120.64778,22.43333],"type":"Point"}
}