{
  "type": "Feature",
  "properties": {
    "gn:admin1_code":"02",
    "gn:admin2_code":"KHH",
    "gn:admin3_code":"E17",
    "gn:admin4_code":"64000170005.0",
    "gn:asciiname":"Dakengnei",
    "gn:country_code":"TW",
    "gn:dem":86,
    "gn:feature_class":"P",
    "gn:feature_code":"PPL",
    "gn:name":"Dakengnei",
    "gn:population":0,
    "gn:timezone":"Asia/Taipei",
    "iso:country":"TW",
    "name:und_x_variant":[
        "\u5927\u5751\u5185",
        "Dakengnei"
    ],
    "name:zho_x_preferred":[
        "Ta-k\u2019eng-nei"
    ],
    "name:zho_x_variant":[
        "\u5927\u5751\u5185"
    ],
    "wof:name":"Dakengnei",
    "wof:placetype":"locality"
},
  "geometry": {"coordinates":[120.3909,22.7332],"type":"Point"}
}