{
  "type": "Feature",
  "properties": {
    "iso:country":"TW",
    "qs:name":"\u6fc1\u6c34\u6751",
    "qs:name_adm0":"\u81fa\u7063",
    "qs:name_adm1":"\u5357\u6295\u7e23",
    "qs:photos":57,
    "qs:photos_1k":12,
    "qs:photos_9k":1,
    "qs:photos_9r":2,
    "qs:photos_all":57,
    "qs:photos_sr":2,
    "qs:placetype":"Town",
    "qs:pop_sr":"0",
    "wof:name":"\u6fc1\u6c34\u6751",
    "wof:placetype":"locality"
},
  "geometry": {"coordinates":[120.709666,23.832333],"type":"Point"}
}