{
  "type": "Feature",
  "properties": {
    "gn:admin1_code":"4.0",
    "gn:admin2_code":"NAN",
    "gn:admin3_code":"M13",
    "gn:admin4_code":"10008130015.0",
    "gn:asciiname":"Maliguan",
    "gn:country_code":"TW",
    "gn:dem":1923,
    "gn:feature_class":"P",
    "gn:feature_code":"PPL",
    "gn:name":"Maliguan",
    "gn:population":0,
    "gn:timezone":"Asia/Taipei",
    "iso:country":"TW",
    "name:und_x_variant":[
        "Ma-li-kuan"
    ],
    "name:zho_x_preferred":[
        "\u99ac\u529b\u89c0"
    ],
    "wof:name":"Maliguan",
    "wof:placetype":"locality"
},
  "geometry": {"coordinates":[121.20833,24.18],"type":"Point"}
}