{
  "type": "Feature",
  "properties": {
    "gn:admin1_code":"4.0",
    "gn:admin2_code":"CHA",
    "gn:admin3_code":"N23",
    "gn:admin4_code":"10007230025.0",
    "gn:asciiname":"Guofang",
    "gn:country_code":"TW",
    "gn:dem":7,
    "gn:feature_class":"P",
    "gn:feature_code":"PPL",
    "gn:name":"Guofang",
    "gn:population":0,
    "gn:timezone":"Asia/Taipei",
    "iso:country":"TW",
    "name:und_x_variant":[
        "Hsin-sheng-ts\u2019un",
        "Kuo-kuang-ts\u2019un",
        "Kuo-kuang",
        "Kuo-fang",
        "Guofang"
    ],
    "wof:name":"Guofang",
    "wof:placetype":"locality"
},
  "geometry": {"coordinates":[120.38333,23.98333],"type":"Point"}
}