{
  "type": "Feature",
  "properties": {
    "gn:admin1_code":"02",
    "gn:admin2_code":"KHH",
    "gn:admin3_code":"E23",
    "gn:admin4_code":"64000230010.0",
    "gn:asciiname":"Shanjiao",
    "gn:country_code":"TW",
    "gn:dem":42,
    "gn:feature_class":"P",
    "gn:feature_code":"PPL",
    "gn:name":"Shanjiao",
    "gn:population":0,
    "gn:timezone":"Asia/Taipei",
    "iso:country":"TW",
    "name:und_x_variant":[
        "Shan-chiao"
    ],
    "name:zho_x_preferred":[
        "\u5c71\u8173"
    ],
    "name:zho_x_variant":[
        "Ying-y\u00fcan"
    ],
    "wof:name":"Shanjiao",
    "wof:placetype":"locality"
},
  "geometry": {"coordinates":[120.33499999999999,22.84111],"type":"Point"}
}