{
  "type": "Feature",
  "properties": {
    "gn:admin1_code":"4.0",
    "gn:admin2_code":"TTT",
    "gn:admin3_code":"V14",
    "gn:admin4_code":"10014150003.0",
    "gn:asciiname":"Niaowanxitou",
    "gn:country_code":"TW",
    "gn:dem":337,
    "gn:feature_class":"P",
    "gn:feature_code":"PPL",
    "gn:name":"Niaowanxitou",
    "gn:population":0,
    "gn:timezone":"Asia/Taipei",
    "iso:country":"TW",
    "name:und_x_variant":[
        "Niaowansitou",
        "Niaowanxitou"
    ],
    "name:zho_x_preferred":[
        "\u9ce5\u842c\u6eaa\u982d"
    ],
    "name:zho_x_variant":[
        "Ta-niao-y\u00fcan-t\u2019ou",
        "Ta-niao-hsi-t\u2019ou",
        "Niao-wan-hsi-t\u2019ou"
    ],
    "wof:name":"Niaowanxitou",
    "wof:placetype":"locality"
},
  "geometry": {"coordinates":[120.86499999999999,22.38389],"type":"Point"}
}