{
  "type": "Feature",
  "properties": {
    "gn:admin1_code":"04",
    "gn:admin2_code":"TPE",
    "gn:admin3_code":"A14",
    "gn:admin4_code":"63000100028.0",
    "gn:asciiname":"Xiazhuangzi",
    "gn:country_code":"TW",
    "gn:dem":15,
    "gn:feature_class":"P",
    "gn:feature_code":"PPL",
    "gn:name":"Xiazhuangzi",
    "gn:population":0,
    "gn:timezone":"Asia/Taipei",
    "iso:country":"TW",
    "name:und_x_variant":[
        "Siajhuangzih",
        "Xiazhuangzi",
        "Hsia-chuang-tzu"
    ],
    "name:zho_x_preferred":[
        "\u4e0b\u838a\u5b50"
    ],
    "name:zho_x_variant":[
        "Yang-ch\u2019ou"
    ],
    "wof:name":"Xiazhuangzi",
    "wof:placetype":"locality"
},
  "geometry": {"coordinates":[121.58933,25.06013],"type":"Point"}
}