{
  "type": "Feature",
  "properties": {
    "gn:admin1_code":"4.0",
    "gn:admin2_code":"MIA",
    "gn:admin3_code":"K14",
    "gn:admin4_code":"10005110008.0",
    "gn:asciiname":"Xiashan",
    "gn:country_code":"TW",
    "gn:dem":379,
    "gn:feature_class":"P",
    "gn:feature_code":"PPL",
    "gn:name":"Xiashan",
    "gn:population":0,
    "gn:timezone":"Asia/Taipei",
    "iso:country":"TW",
    "name:und_x_variant":[
        "Siashan",
        "Xiashan",
        "Hsia-shan"
    ],
    "name:zho_x_preferred":[
        "\u4e0b\u5c71"
    ],
    "wof:name":"Xiashan",
    "wof:placetype":"locality"
},
  "geometry": {"coordinates":[120.97602999999999,24.55133],"type":"Point"}
}