{
  "type": "Feature",
  "properties": {
    "gn:admin1_code":"04",
    "gn:admin2_code":"TNN",
    "gn:admin3_code":"R03",
    "gn:admin4_code":"67000030017.0",
    "gn:asciiname":"Beibu",
    "gn:country_code":"TW",
    "gn:dem":27,
    "gn:feature_class":"P",
    "gn:feature_code":"PPL",
    "gn:name":"Beibu",
    "gn:population":0,
    "gn:timezone":"Asia/Taipei",
    "iso:country":"TW",
    "name:und_x_variant":[
        "Pei-pu"
    ],
    "name:zho_x_preferred":[
        "\u5317\u57d4"
    ],
    "wof:name":"Beibu",
    "wof:placetype":"locality"
},
  "geometry": {"coordinates":[120.4075,23.40889],"type":"Point"}
}