{
  "type": "Feature",
  "properties": {
    "gn:admin1_code":"4.0",
    "gn:admin2_code":"MIA",
    "gn:admin3_code":"K17",
    "gn:admin4_code":"10005170002.0",
    "gn:asciiname":"Zhuchonggui",
    "gn:country_code":"TW",
    "gn:dem":192,
    "gn:feature_class":"P",
    "gn:feature_code":"PPL",
    "gn:name":"Zhuchonggui",
    "gn:population":0,
    "gn:timezone":"Asia/Taipei",
    "iso:country":"TW",
    "name:und_x_variant":[
        "Jhuchongguei"
    ],
    "name:zho_x_preferred":[
        "\u7af9\u9283\u6ac3"
    ],
    "name:zho_x_variant":[
        "Chu-ch\u2019ung-kuei"
    ],
    "wof:name":"Zhuchonggui",
    "wof:placetype":"locality"
},
  "geometry": {"coordinates":[120.93035999999999,24.55274],"type":"Point"}
}