{
  "type": "Feature",
  "properties": {
    "gn:admin1_code":"3.0",
    "gn:admin2_code":"TPQ",
    "gn:admin3_code":"F10",
    "gn:admin4_code":"65000200002.0",
    "gn:asciiname":"Xiakengzikou",
    "gn:country_code":"TW",
    "gn:dem":221,
    "gn:feature_class":"P",
    "gn:feature_code":"PPL",
    "gn:name":"Xiakengzikou",
    "gn:population":0,
    "gn:timezone":"Asia/Taipei",
    "iso:country":"TW",
    "name:und_x_variant":[
        "Siakengzihkou"
    ],
    "name:zho_x_preferred":[
        "\u4e0b\u5751\u5b50\u53e3"
    ],
    "name:zho_x_variant":[
        "Hsia-k\u2019eng-tzu-k\u2019ou"
    ],
    "wof:name":"Xiakengzikou",
    "wof:placetype":"locality"
},
  "geometry": {"coordinates":[121.71080000000001,24.94063],"type":"Point"}
}