{
  "type": "Feature",
  "properties": {
    "gn:admin1_code":"04",
    "gn:admin2_code":"PIF",
    "gn:admin3_code":"T22",
    "gn:admin4_code":"10013220002.0",
    "gn:asciiname":"Baishawei",
    "gn:country_code":"TW",
    "gn:dem":12,
    "gn:feature_class":"P",
    "gn:feature_code":"PPL",
    "gn:name":"Baishawei",
    "gn:population":0,
    "gn:timezone":"Asia/Taipei",
    "iso:country":"TW",
    "name:und_x_variant":[
        "Pen-fu",
        "Baishawei",
        "Pai-sha-wei"
    ],
    "name:zho_x_preferred":[
        "Liu-ch\u2019iu"
    ],
    "name:zho_x_variant":[
        "Pen-fu-ts\u2019un",
        "\u767d\u6c99\u5c3e"
    ],
    "wof:name":"Baishawei",
    "wof:placetype":"locality"
},
  "geometry": {"coordinates":[120.38273,22.35187],"type":"Point"}
}