{
  "type": "Feature",
  "properties": {
    "gn:admin1_code":"4.0",
    "gn:admin2_code":"CYQ",
    "gn:admin3_code":"Q04",
    "gn:admin4_code":"10010040013.0",
    "gn:asciiname":"Huijiacuo",
    "gn:country_code":"TW",
    "gn:dem":63,
    "gn:feature_class":"P",
    "gn:feature_code":"PPL",
    "gn:name":"Huijiacuo",
    "gn:population":0,
    "gn:timezone":"Asia/Taipei",
    "iso:country":"TW",
    "name:und_x_variant":[
        "Hueijiacuo"
    ],
    "name:zho_x_preferred":[
        "\u6703\u5bb6\u539d"
    ],
    "name:zho_x_variant":[
        "Hui-chia-ts\u2019o"
    ],
    "wof:name":"Huijiacuo",
    "wof:placetype":"locality"
},
  "geometry": {"coordinates":[120.50422,23.55742],"type":"Point"}
}