{
  "type": "Feature",
  "properties": {
    "gn:admin1_code":"3.0",
    "gn:admin2_code":"TPQ",
    "gn:admin3_code":"F32",
    "gn:admin4_code":"65000230004.0",
    "gn:asciiname":"Gongtian",
    "gn:country_code":"TW",
    "gn:dem":15,
    "gn:feature_class":"P",
    "gn:feature_code":"PPL",
    "gn:name":"Gongtian",
    "gn:population":0,
    "gn:timezone":"Asia/Taipei",
    "iso:country":"TW",
    "name:zho_x_preferred":[
        "\u516c\u7530"
    ],
    "name:zho_x_variant":[
        "Kung-t\u2019ien"
    ],
    "wof:name":"Gongtian",
    "wof:placetype":"locality"
},
  "geometry": {"coordinates":[121.41244,25.15844],"type":"Point"}
}