{
  "type": "Feature",
  "properties": {
    "gn:admin1_code":"04",
    "gn:admin2_code":"TNN",
    "gn:admin3_code":"R25",
    "gn:admin4_code":"67000250008.0",
    "gn:asciiname":"Yanshuikeng",
    "gn:country_code":"TW",
    "gn:dem":115,
    "gn:feature_class":"P",
    "gn:feature_code":"PPL",
    "gn:name":"Yanshuikeng",
    "gn:population":0,
    "gn:timezone":"Asia/Taipei",
    "iso:country":"TW",
    "name:und_x_variant":[
        "Yanshueikeng",
        "Yanshuikeng"
    ],
    "name:zho_x_preferred":[
        "\u9e7d\u6c34\u5751"
    ],
    "name:zho_x_variant":[
        "Yen-shui-k\u2019eng"
    ],
    "wof:name":"Yanshuikeng",
    "wof:placetype":"locality"
},
  "geometry": {"coordinates":[120.52028,23.08361],"type":"Point"}
}