{
  "type": "Feature",
  "properties": {
    "gn:admin1_code":"4.0",
    "gn:admin2_code":"CYQ",
    "gn:admin3_code":"Q03",
    "gn:admin4_code":"10010030017.0",
    "gn:asciiname":"Luliao",
    "gn:country_code":"TW",
    "gn:dem":2,
    "gn:feature_class":"P",
    "gn:feature_code":"PPL",
    "gn:name":"Luliao",
    "gn:population":0,
    "gn:timezone":"Asia/Taipei",
    "iso:country":"TW",
    "name:und_x_variant":[
        "Lu-liao"
    ],
    "name:zho_x_preferred":[
        "\u9e7f\u5bee"
    ],
    "wof:name":"Luliao",
    "wof:placetype":"locality"
},
  "geometry": {"coordinates":[120.18919,23.38991],"type":"Point"}
}