{
  "type": "Feature",
  "properties": {
    "gn:admin1_code":"4.0",
    "gn:admin2_code":"TXG",
    "gn:admin3_code":"B25",
    "gn:admin4_code":"66000250011.0",
    "gn:asciiname":"Longmujing",
    "gn:country_code":"TW",
    "gn:dem":16,
    "gn:feature_class":"P",
    "gn:feature_code":"PPL",
    "gn:name":"Longmujing",
    "gn:population":0,
    "gn:timezone":"Asia/Taipei",
    "iso:country":"TW",
    "name:und_x_variant":[
        "Lung-ching",
        "Lung-ch\u2019\u00fcan-ts\u2019un",
        "Lung-ch\u2019\u00fcan",
        "Longmujing",
        "Lung-mu-ching"
    ],
    "name:zho_x_preferred":[
        "\u9f8d\u76ee\u4e95"
    ],
    "wof:name":"Longmujing",
    "wof:placetype":"locality"
},
  "geometry": {"coordinates":[120.5487,24.19923],"type":"Point"}
}