{
  "type": "Feature",
  "properties": {
    "gn:admin1_code":"4.0",
    "gn:admin2_code":"MIA",
    "gn:admin3_code":"K06",
    "gn:admin4_code":"10005130001.0",
    "gn:asciiname":"Guishan",
    "gn:country_code":"TW",
    "gn:dem":377,
    "gn:feature_class":"P",
    "gn:feature_code":"PPL",
    "gn:name":"Guishan",
    "gn:population":0,
    "gn:timezone":"Asia/Taipei",
    "iso:country":"TW",
    "name:deu_x_preferred":[
        "Guishan"
    ],
    "name:kor_x_preferred":[
        "\uad6c\uc774\uc0b0"
    ],
    "name:und_x_variant":[
        "Kuei-shan"
    ],
    "wof:name":"Guishan",
    "wof:placetype":"locality"
},
  "geometry": {"coordinates":[120.76667,24.41667],"type":"Point"}
}