{
  "type": "Feature",
  "properties": {
    "gn:admin1_code":"4.0",
    "gn:admin2_code":"MIA",
    "gn:admin3_code":"K04",
    "gn:admin4_code":"10005090009.0",
    "gn:asciiname":"Fengzikeng",
    "gn:country_code":"TW",
    "gn:dem":211,
    "gn:feature_class":"P",
    "gn:feature_code":"PPL",
    "gn:name":"Fengzikeng",
    "gn:population":0,
    "gn:timezone":"Asia/Taipei",
    "iso:country":"TW",
    "name:und_x_variant":[
        "Fongzihkeng",
        "Fengzikeng"
    ],
    "name:zho_x_preferred":[
        "\u8702\u5b50\u5751"
    ],
    "name:zho_x_variant":[
        "Feng-tzu-k\u2019eng"
    ],
    "wof:name":"Fengzikeng",
    "wof:placetype":"locality"
},
  "geometry": {"coordinates":[120.83848999999999,24.47905],"type":"Point"}
}