{
  "type": "Feature",
  "properties": {
    "gn:admin1_code":"03",
    "gn:admin2_code":"TPQ",
    "gn:admin3_code":"F25",
    "gn:admin4_code":"65000270006.0",
    "gn:asciiname":"Nanshihu",
    "gn:country_code":"TW",
    "gn:dem":48,
    "gn:feature_class":"P",
    "gn:feature_code":"PPL",
    "gn:name":"Nanshihu",
    "gn:population":0,
    "gn:timezone":"Asia/Taipei",
    "iso:country":"TW",
    "name:und_x_variant":[
        "Nanshihhu",
        "Nanshihu",
        "Nan-shih-hu"
    ],
    "name:zho_x_preferred":[
        "\u5357\u52e2\u6e56"
    ],
    "wof:name":"Nanshihu",
    "wof:placetype":"locality"
},
  "geometry": {"coordinates":[121.61517000000001,25.21664],"type":"Point"}
}