{
  "type": "Feature",
  "properties": {
    "gn:admin1_code":"04",
    "gn:admin2_code":"NAN",
    "gn:admin3_code":"M02",
    "gn:admin4_code":"10008020026.0",
    "gn:asciiname":"Shoucheng",
    "gn:country_code":"TW",
    "gn:dem":481,
    "gn:feature_class":"P",
    "gn:feature_code":"PPL",
    "gn:name":"Shoucheng",
    "gn:population":0,
    "gn:timezone":"Asia/Taipei",
    "iso:country":"TW",
    "name:zho_x_preferred":[
        "Shou-ch\u2019eng-fen"
    ],
    "name:zho_x_variant":[
        "\u5b88\u57ce",
        "Shou-ch\u2019eng"
    ],
    "wof:name":"Shoucheng",
    "wof:placetype":"locality"
},
  "geometry": {"coordinates":[120.9868,23.98743],"type":"Point"}
}