{
  "type": "Feature",
  "properties": {
    "iso:country":"TW",
    "name:eng_x_preferred":[
        "Nan'ao"
    ],
    "name:eng_x_variant":[
        "Nan'ao Village"
    ],
    "name:zho_tw_x_preferred":[
        "\u5357\u6fb3\u6751"
    ],
    "qs:name":"\u5357\u6fb3\u6751",
    "qs:name_adm0":"\u81fa\u7063",
    "qs:name_adm1":"\u5b9c\u862d\u7e23",
    "qs:photos":289,
    "qs:photos_1k":59,
    "qs:photos_9k":1,
    "qs:photos_9r":4,
    "qs:photos_all":289,
    "qs:photos_sr":5,
    "qs:placetype":"Town",
    "qs:pop_sr":"0",
    "wof:name":"Nan'ao",
    "wof:placetype":"locality"
},
  "geometry": {"coordinates":[121.804513,24.466247],"type":"Point"}
}