{
  "type": "Feature",
  "properties": {
    "gn:admin1_code":"4.0",
    "gn:admin2_code":"TNN",
    "gn:admin3_code":"R13",
    "gn:admin4_code":"67000140009.0",
    "gn:asciiname":"Chu-lin",
    "gn:country_code":"TW",
    "gn:dem":8,
    "gn:feature_class":"P",
    "gn:feature_code":"PPL",
    "gn:name":"Chu-lin",
    "gn:population":0,
    "gn:timezone":"Asia/Taipei",
    "iso:country":"TW",
    "name:und_x_variant":[
        "Ta-chu-lin",
        "Chu-lin-ts'un",
        "Dazhulin",
        "Chu-lin",
        "Dajhulin"
    ],
    "wof:name":"Chu-lin",
    "wof:placetype":"locality"
},
  "geometry": {"coordinates":[120.18694000000001,23.1225],"type":"Point"}
}