{
  "type": "Feature",
  "properties": {
    "gn:admin1_code":"4.0",
    "gn:admin2_code":"CHA",
    "gn:admin3_code":"N10",
    "gn:admin4_code":"10007050006.0",
    "gn:asciiname":"Jiangou",
    "gn:country_code":"TW",
    "gn:dem":6,
    "gn:feature_class":"P",
    "gn:feature_code":"PPL",
    "gn:name":"Jiangou",
    "gn:population":0,
    "gn:timezone":"Asia/Taipei",
    "iso:country":"TW",
    "name:und_x_variant":[
        "Chien-kou"
    ],
    "wof:name":"Jiangou",
    "wof:placetype":"locality"
},
  "geometry": {"coordinates":[120.48333,24.15],"type":"Point"}
}