{
  "type": "Feature",
  "properties": {
    "gn:admin1_code":"4.0",
    "gn:admin2_code":"HUA",
    "gn:admin3_code":"U05",
    "gn:admin4_code":"10015050018.0",
    "gn:asciiname":"Guanghuawucun",
    "gn:country_code":"TW",
    "gn:dem":41,
    "gn:feature_class":"P",
    "gn:feature_code":"PPL",
    "gn:name":"Guanghuawucun",
    "gn:population":0,
    "gn:timezone":"Asia/Taipei",
    "iso:country":"TW",
    "name:und_x_variant":[
        "Kuang-hua-wu-lin",
        "\u5149\u83ef\u4e94\u6751"
    ],
    "name:zho_x_preferred":[
        "Kuang-hua-wu-ts\u2019un"
    ],
    "name:zho_x_variant":[
        "\u5149\u83ef\u4e94\u6751"
    ],
    "wof:name":"Guanghuawucun",
    "wof:placetype":"locality"
},
  "geometry": {"coordinates":[121.57277999999999,23.9275],"type":"Point"}
}