{
  "type": "Feature",
  "properties": {
    "gn:admin1_code":"04",
    "gn:admin2_code":"CHA",
    "gn:admin3_code":"N07",
    "gn:admin4_code":"10007120016.0",
    "gn:asciiname":"Dalunwei",
    "gn:country_code":"TW",
    "gn:dem":60,
    "gn:feature_class":"P",
    "gn:feature_code":"PPL",
    "gn:name":"Dalunwei",
    "gn:population":0,
    "gn:timezone":"Asia/Taipei",
    "iso:country":"TW",
    "name:und_x_variant":[
        "Ta-lun-wei"
    ],
    "name:zho_x_preferred":[
        "\u5927\u5d19\u5c3e"
    ],
    "wof:name":"Dalunwei",
    "wof:placetype":"locality"
},
  "geometry": {"coordinates":[120.59399999999999,23.8354],"type":"Point"}
}