{
  "type": "Feature",
  "properties": {
    "gn:admin1_code":"2.0",
    "gn:admin2_code":"KHH",
    "gn:admin3_code":"E31",
    "gn:admin4_code":"64000310008.0",
    "gn:asciiname":"Nankeng",
    "gn:country_code":"TW",
    "gn:dem":90,
    "gn:feature_class":"P",
    "gn:feature_code":"PPL",
    "gn:name":"Nankeng",
    "gn:population":0,
    "gn:timezone":"Asia/Taipei",
    "iso:country":"TW",
    "name:zho_x_preferred":[
        "\u5357\u5751"
    ],
    "name:zho_x_variant":[
        "Nan-k\u2019eng"
    ],
    "wof:name":"Nankeng",
    "wof:placetype":"locality"
},
  "geometry": {"coordinates":[120.58559,22.88296],"type":"Point"}
}