{
  "type": "Feature",
  "properties": {
    "gn:admin1_code":"4.0",
    "gn:admin2_code":"TAO",
    "gn:admin3_code":"H06",
    "gn:admin4_code":"68000060002.0",
    "gn:asciiname":"Xiaxi",
    "gn:country_code":"TW",
    "gn:dem":56,
    "gn:feature_class":"P",
    "gn:feature_code":"PPL",
    "gn:name":"Xiaxi",
    "gn:population":0,
    "gn:timezone":"Asia/Taipei",
    "iso:country":"TW",
    "name:und_x_variant":[
        "Hsia-hsi-tzu",
        "Siasi",
        "Xiaxi",
        "Hsia-hsi"
    ],
    "name:zho_x_preferred":[
        "Hsia-hsia-ch\u2019i"
    ],
    "name:zho_x_variant":[
        "Hsia-ch\u2019i-li",
        "Hsia-ch\u2019i",
        "Hsia-ch\u2019i-tzu",
        "\u6d3d\u6eaa"
    ],
    "wof:name":"Xiaxi",
    "wof:placetype":"locality"
},
  "geometry": {"coordinates":[121.20055000000001,25.02832],"type":"Point"}
}