{
  "type": "Feature",
  "properties": {
    "gn:admin1_code":"4.0",
    "gn:admin2_code":"PIF",
    "gn:admin3_code":"T22",
    "gn:admin4_code":"10013220004.0",
    "gn:asciiname":"Xiapingjiao",
    "gn:country_code":"TW",
    "gn:dem":16,
    "gn:feature_class":"P",
    "gn:feature_code":"PPL",
    "gn:name":"Xiapingjiao",
    "gn:population":0,
    "gn:timezone":"Asia/Taipei",
    "iso:country":"TW",
    "name:und_x_variant":[
        "Siapingjiao",
        "Xiapingjiao"
    ],
    "name:zho_x_preferred":[
        "\u4e0b\u576a\u8173"
    ],
    "name:zho_x_variant":[
        "Hsia-p\u2019ing-chiao"
    ],
    "wof:name":"Xiapingjiao",
    "wof:placetype":"locality"
},
  "geometry": {"coordinates":[120.37085,22.33465],"type":"Point"}
}