{
  "type": "Feature",
  "properties": {
    "gn:admin1_code":"3.0",
    "gn:admin2_code":"TPQ",
    "gn:admin3_code":"F24",
    "gn:admin4_code":"65000260005.0",
    "gn:asciiname":"Shisanxing",
    "gn:country_code":"TW",
    "gn:dem":21,
    "gn:feature_class":"P",
    "gn:feature_code":"PPL",
    "gn:name":"Shisanxing",
    "gn:population":0,
    "gn:timezone":"Asia/Taipei",
    "iso:country":"TW",
    "name:und_x_variant":[
        "Shihsansing",
        "Shisanxing",
        "Shih-san-hsing"
    ],
    "name:zho_x_preferred":[
        "\u5341\u4e09\u59d3"
    ],
    "wof:name":"Shisanxing",
    "wof:placetype":"locality"
},
  "geometry": {"coordinates":[121.9298,25.02657],"type":"Point"}
}