{
  "type": "Feature",
  "properties": {
    "gn:admin1_code":"4.0",
    "gn:admin2_code":"HUA",
    "gn:admin3_code":"U13",
    "gn:admin4_code":"10015130002.0",
    "gn:asciiname":"Gucun",
    "gn:country_code":"TW",
    "gn:dem":194,
    "gn:feature_class":"P",
    "gn:feature_code":"PPL",
    "gn:name":"Gucun",
    "gn:population":0,
    "gn:timezone":"Asia/Taipei",
    "iso:country":"TW",
    "name:zho_x_preferred":[
        "\u53e4\u6751"
    ],
    "name:zho_x_variant":[
        "Ku-ts\u2019un"
    ],
    "wof:name":"Gucun",
    "wof:placetype":"locality"
},
  "geometry": {"coordinates":[121.33232,23.43691],"type":"Point"}
}