{
  "type": "Feature",
  "properties": {
    "gn:admin1_code":"2.0",
    "gn:admin2_code":"KHH",
    "gn:admin3_code":"E22",
    "gn:admin4_code":"64000220010.0",
    "gn:asciiname":"Lunweizi",
    "gn:country_code":"TW",
    "gn:dem":67,
    "gn:feature_class":"P",
    "gn:feature_code":"PPL",
    "gn:name":"Lunweizi",
    "gn:population":0,
    "gn:timezone":"Asia/Taipei",
    "iso:country":"TW",
    "name:und_x_variant":[
        "Lunweizih",
        "Lunweizi",
        "Lun-wei-tzu"
    ],
    "name:zho_x_preferred":[
        "\u5d19\u5c3e\u4ed4"
    ],
    "wof:name":"Lunweizi",
    "wof:placetype":"locality"
},
  "geometry": {"coordinates":[120.39139,22.845],"type":"Point"}
}