{
  "type": "Feature",
  "properties": {
    "gn:admin1_code":"4.0",
    "gn:admin2_code":"NAN",
    "gn:admin3_code":"M08",
    "gn:admin4_code":"10008080003.0",
    "gn:asciiname":"Tailukeng",
    "gn:country_code":"TW",
    "gn:dem":207,
    "gn:feature_class":"P",
    "gn:feature_code":"PPL",
    "gn:name":"Tailukeng",
    "gn:population":0,
    "gn:timezone":"Asia/Taipei",
    "iso:country":"TW",
    "name:zho_x_preferred":[
        "Kua-lu-k\u2019eng"
    ],
    "name:zho_x_variant":[
        "\u80ce\u9e7f\u5751",
        "Chung-lu-k\u2019eng",
        "T\u2019ai-lu-k\u2019eng"
    ],
    "wof:name":"Tailukeng",
    "wof:placetype":"locality"
},
  "geometry": {"coordinates":[120.79082,23.87574],"type":"Point"}
}