{
  "type": "Feature",
  "properties": {
    "gn:admin1_code":"04",
    "gn:admin2_code":"TAO",
    "gn:admin3_code":"H02",
    "gn:admin4_code":"68000030006.0",
    "gn:asciiname":"Niangzikeng",
    "gn:country_code":"TW",
    "gn:dem":131,
    "gn:feature_class":"P",
    "gn:feature_code":"PPL",
    "gn:name":"Niangzikeng",
    "gn:population":0,
    "gn:timezone":"Asia/Taipei",
    "iso:country":"TW",
    "name:und_x_variant":[
        "Niangzihkeng",
        "Niangzikeng"
    ],
    "name:zho_x_preferred":[
        "\u5a18\u5b50\u5751"
    ],
    "name:zho_x_variant":[
        "Niang-tzu-k\u2019eng"
    ],
    "wof:name":"Niangzikeng",
    "wof:placetype":"locality"
},
  "geometry": {"coordinates":[121.3173,24.90182],"type":"Point"}
}