{
  "type": "Feature",
  "properties": {
    "gn:admin1_code":"4.0",
    "gn:admin2_code":"PEN",
    "gn:admin3_code":"X01",
    "gn:admin4_code":"10016010033.0",
    "gn:asciiname":"Hujing",
    "gn:country_code":"TW",
    "gn:dem":11,
    "gn:feature_class":"P",
    "gn:feature_code":"PPL",
    "gn:name":"Hujing",
    "gn:population":0,
    "gn:timezone":"Asia/Taipei",
    "iso:country":"TW",
    "name:und_x_variant":[
        "Hu-ching-li",
        "Hujing",
        "Hu-ching"
    ],
    "name:zho_x_preferred":[
        "\u864e\u4e95"
    ],
    "wof:name":"Hujing",
    "wof:placetype":"locality"
},
  "geometry": {"coordinates":[119.51778,23.48583],"type":"Point"}
}