{
  "type": "Feature",
  "properties": {
    "gn:admin1_code":"04",
    "gn:admin2_code":"PIF",
    "gn:admin3_code":"T33",
    "gn:admin4_code":"10013330003.0",
    "gn:asciiname":"Dongyuan",
    "gn:country_code":"TW",
    "gn:dem":302,
    "gn:feature_class":"P",
    "gn:feature_code":"PPL",
    "gn:name":"Dongyuan",
    "gn:population":0,
    "gn:timezone":"Asia/Taipei",
    "iso:country":"TW",
    "name:ceb_x_preferred":[
        "Dongyuan"
    ],
    "name:deu_x_preferred":[
        "Dongyuan"
    ],
    "name:nor_x_preferred":[
        "Dongyuan"
    ],
    "name:und_x_variant":[
        "Hsin-mu-tan-she",
        "Hsin-mu-tan",
        "Dongyuan"
    ],
    "name:zho_x_preferred":[
        "Tung-y\u00fcan-ts\u2019un"
    ],
    "name:zho_x_variant":[
        "\u6771\u6e90",
        "Tung-y\u00fcan"
    ],
    "wof:name":"Dongyuan",
    "wof:placetype":"locality"
},
  "geometry": {"coordinates":[120.85028,22.20389],"type":"Point"}
}