{
  "type": "Feature",
  "properties": {
    "gn:admin1_code":"4.0",
    "gn:admin2_code":"TNN",
    "gn:admin3_code":"R20",
    "gn:admin4_code":"67000200003.0",
    "gn:asciiname":"Qiaotou",
    "gn:country_code":"TW",
    "gn:dem":4,
    "gn:feature_class":"P",
    "gn:feature_code":"PPL",
    "gn:name":"Qiaotou",
    "gn:population":0,
    "gn:timezone":"Asia/Taipei",
    "iso:country":"TW",
    "name:und_x_variant":[
        "Ciaotou",
        "Qiaotou"
    ],
    "name:zho_x_preferred":[
        "\u6a4b\u982d"
    ],
    "name:zho_x_variant":[
        "Ch\u2019iao-t\u2019ou"
    ],
    "wof:name":"Qiaotou",
    "wof:placetype":"locality"
},
  "geometry": {"coordinates":[120.27755000000001,23.07800000000001],"type":"Point"}
}