{
  "type": "Feature",
  "properties": {
    "gn:admin1_code":"4.0",
    "gn:admin2_code":"CYQ",
    "gn:admin3_code":"Q15",
    "gn:admin4_code":"10010140007.0",
    "gn:asciiname":"Neikeng",
    "gn:country_code":"TW",
    "gn:dem":85,
    "gn:feature_class":"P",
    "gn:feature_code":"PPL",
    "gn:name":"Neikeng",
    "gn:population":0,
    "gn:timezone":"Asia/Taipei",
    "iso:country":"TW",
    "name:zho_x_preferred":[
        "\u5167\u5751"
    ],
    "name:zho_x_variant":[
        "Nei-k\u2019eng"
    ],
    "wof:name":"Neikeng",
    "wof:placetype":"locality"
},
  "geometry": {"coordinates":[120.51667,23.51056],"type":"Point"}
}