{
  "type": "Feature",
  "properties": {
    "gn:admin1_code":"4.0",
    "gn:admin2_code":"HSZ",
    "gn:admin3_code":"J04",
    "gn:admin4_code":"10004030012.0",
    "gn:asciiname":"Xinwawu",
    "gn:country_code":"TW",
    "gn:dem":29,
    "gn:feature_class":"P",
    "gn:feature_code":"PPL",
    "gn:name":"Xinwawu",
    "gn:population":0,
    "gn:timezone":"Asia/Taipei",
    "iso:country":"TW",
    "name:und_x_variant":[
        "Sinwawu",
        "Hsin-wa-wu"
    ],
    "name:zho_x_preferred":[
        "\u65b0\u74e6\u5c4b"
    ],
    "wof:name":"Xinwawu",
    "wof:placetype":"locality"
},
  "geometry": {"coordinates":[121.02778000000001,24.845],"type":"Point"}
}