{
  "type": "Feature",
  "properties": {
    "gn:admin1_code":"04",
    "gn:admin2_code":"NAN",
    "gn:admin3_code":"M12",
    "gn:admin4_code":"10008120012.0",
    "gn:asciiname":"Bankaileisi",
    "gn:country_code":"TW",
    "gn:dem":773,
    "gn:feature_class":"P",
    "gn:feature_code":"PPL",
    "gn:name":"Bankaileisi",
    "gn:population":0,
    "gn:timezone":"Asia/Taipei",
    "iso:country":"TW",
    "name:und_x_variant":[
        "Bankaileisih"
    ],
    "name:zho_x_preferred":[
        "\u73ed\u958b\u96f7\u65af"
    ],
    "name:zho_x_variant":[
        "Pan-k\u2019ai-lai-ssu",
        "Pan-k\u2019ai-lei-ssu"
    ],
    "wof:name":"Bankaileisi",
    "wof:placetype":"locality"
},
  "geometry": {"coordinates":[121.02222,23.77806],"type":"Point"}
}