{
  "type": "Feature",
  "properties": {
    "gn:admin1_code":"4.0",
    "gn:admin2_code":"CYQ",
    "gn:admin3_code":"Q08",
    "gn:admin4_code":"10010080019.0",
    "gn:asciiname":"Xiashuangxi",
    "gn:country_code":"TW",
    "gn:dem":10,
    "gn:feature_class":"P",
    "gn:feature_code":"PPL",
    "gn:name":"Xiashuangxi",
    "gn:population":0,
    "gn:timezone":"Asia/Taipei",
    "iso:country":"TW",
    "name:und_x_variant":[
        "Siashuangsi",
        "Xiashuangxi",
        "Hsia-shuang-hsi"
    ],
    "name:zho_x_preferred":[
        "Hsia-shuang-ch\u2019i"
    ],
    "name:zho_x_variant":[
        "\u4e0b\u96d9\u6eaa"
    ],
    "wof:name":"Xiashuangxi",
    "wof:placetype":"locality"
},
  "geometry": {"coordinates":[120.25360000000001,23.4805],"type":"Point"}
}