{
  "type": "Feature",
  "properties": {
    "gn:admin1_code":"4.0",
    "gn:admin2_code":"TAO",
    "gn:admin3_code":"H13",
    "gn:admin4_code":"68000130008.0",
    "gn:asciiname":"Xuanyuan",
    "gn:country_code":"TW",
    "gn:dem":875,
    "gn:feature_class":"P",
    "gn:feature_code":"PPL",
    "gn:name":"Xuanyuan",
    "gn:population":0,
    "gn:timezone":"Asia/Taipei",
    "iso:country":"TW",
    "name:und_x_variant":[
        "Syuanyuan"
    ],
    "name:zho_x_preferred":[
        "\u8431\u6e90"
    ],
    "name:zho_x_variant":[
        "Hs\u00fcan-y\u00fcan"
    ],
    "wof:name":"Xuanyuan",
    "wof:placetype":"locality"
},
  "geometry": {"coordinates":[121.40694000000001,24.65417],"type":"Point"}
}