{
  "type": "Feature",
  "properties": {
    "gn:admin1_code":"2.0",
    "gn:admin2_code":"KHH",
    "gn:admin3_code":"E04",
    "gn:admin4_code":"64000040001.0",
    "gn:asciiname":"Xiangjiaojiao",
    "gn:country_code":"TW",
    "gn:dem":21,
    "gn:feature_class":"P",
    "gn:feature_code":"PPL",
    "gn:name":"Xiangjiaojiao",
    "gn:population":0,
    "gn:timezone":"Asia/Taipei",
    "iso:country":"TW",
    "name:und_x_variant":[
        "Hsiung-chiao-chiao",
        "Siangjiaojiao",
        "Hsiang-chiao-chiao"
    ],
    "name:zho_x_preferred":[
        "\u9999\u8549\u8173"
    ],
    "wof:name":"Xiangjiaojiao",
    "wof:placetype":"locality"
},
  "geometry": {"coordinates":[120.33056000000001,22.74917],"type":"Point"}
}