{
  "type": "Feature",
  "properties": {
    "iso:country":"TW",
    "name:eng_x_preferred":[
        "Jiaoyuan"
    ],
    "name:eng_x_variant":[
        "Jiaoyuan Village"
    ],
    "name:zho_tw_x_preferred":[
        "\u8549\u5712\u91cc"
    ],
    "qs:name":"\u8549\u5712\u91cc",
    "qs:name_adm0":"\u81fa\u7063",
    "qs:name_adm1":"\u9ad8\u96c4\u5e02",
    "qs:photos":98,
    "qs:photos_1k":20,
    "qs:photos_9k":1,
    "qs:photos_9r":3,
    "qs:photos_all":98,
    "qs:photos_sr":3,
    "qs:placetype":"Suburb",
    "qs:pop_sr":"0",
    "wof:name":"Jiaoyuan",
    "wof:placetype":"neighbourhood"
},
  "geometry": {"coordinates":[120.30449900000001,22.630369],"type":"Point"}
}