{
  "type": "Feature",
  "properties": {
    "gn:admin1_code":"4.0",
    "gn:admin2_code":"TAO",
    "gn:admin3_code":"H09",
    "gn:admin4_code":"68000090017.0",
    "gn:asciiname":"Hechuandi",
    "gn:country_code":"TW",
    "gn:dem":113,
    "gn:feature_class":"P",
    "gn:feature_code":"PPL",
    "gn:name":"Hechuandi",
    "gn:population":0,
    "gn:timezone":"Asia/Taipei",
    "iso:country":"TW",
    "name:zho_x_preferred":[
        "\u6cb3\u5ddd\u5e95"
    ],
    "name:zho_x_variant":[
        "Ho-ch\u2019\u00fcan-ti"
    ],
    "wof:name":"Hechuandi",
    "wof:placetype":"locality"
},
  "geometry": {"coordinates":[121.26143,24.84931],"type":"Point"}
}