{
  "type": "Feature",
  "properties": {
    "gn:admin1_code":"04",
    "gn:admin2_code":"ILA",
    "gn:admin3_code":"G03",
    "gn:admin4_code":"10002050016.0",
    "gn:asciiname":"Longtan",
    "gn:country_code":"TW",
    "gn:dem":30,
    "gn:feature_class":"P",
    "gn:feature_code":"PPL",
    "gn:name":"Longtan",
    "gn:population":0,
    "gn:timezone":"Asia/Taipei",
    "iso:country":"TW",
    "name:ceb_x_preferred":[
        "Longtan"
    ],
    "name:deu_x_preferred":[
        "Longtan"
    ],
    "name:fra_x_preferred":[
        "Longtan"
    ],
    "name:zho_x_preferred":[
        "\u9f8d\u6f6d"
    ],
    "name:zho_x_variant":[
        "Ta-p\u2019o",
        "P\u2019o-k\u2019ou",
        "Lung-t\u2019an"
    ],
    "wof:name":"Longtan",
    "wof:placetype":"locality"
},
  "geometry": {"coordinates":[121.74054,24.78431],"type":"Point"}
}