{
  "type": "Feature",
  "properties": {
    "gn:admin1_code":"2.0",
    "gn:admin2_code":"KHH",
    "gn:admin3_code":"E32",
    "gn:admin4_code":"64000320004.0",
    "gn:asciiname":"Anpingding",
    "gn:country_code":"TW",
    "gn:dem":416,
    "gn:feature_class":"P",
    "gn:feature_code":"PPL",
    "gn:name":"Anpingding",
    "gn:population":0,
    "gn:timezone":"Asia/Taipei",
    "iso:country":"TW",
    "name:und_x_variant":[
        "An-pin-chen",
        "Anpingding"
    ],
    "name:zho_x_preferred":[
        "\u5b89\u5e73\u9802"
    ],
    "name:zho_x_variant":[
        "An-p\u2019ing-ting"
    ],
    "wof:name":"Anpingding",
    "wof:placetype":"locality"
},
  "geometry": {"coordinates":[120.68805999999999,23.06972],"type":"Point"}
}