{
  "type": "Feature",
  "properties": {
    "iso:country":"TW",
    "name:eng_x_preferred":[
        "Dashi"
    ],
    "name:eng_x_variant":[
        "Dashi Village"
    ],
    "name:zho_tw_x_preferred":[
        "\u5927\u77f3\u6751"
    ],
    "qs:name":"\u5927\u77f3\u6751",
    "qs:name_adm0":"\u81fa\u7063",
    "qs:name_adm1":"\u5357\u6295\u7e23",
    "qs:photos":86,
    "qs:photos_1k":17,
    "qs:photos_9k":1,
    "qs:photos_9r":3,
    "qs:photos_all":86,
    "qs:photos_sr":3,
    "qs:placetype":"Town",
    "qs:pop_sr":"0",
    "wof:name":"Dashi",
    "wof:placetype":"locality"
},
  "geometry": {"coordinates":[120.86833,23.980569],"type":"Point"}
}