{
  "type": "Feature",
  "properties": {
    "gn:admin1_code":"04",
    "gn:admin2_code":"ILA",
    "gn:admin3_code":"G04",
    "gn:admin4_code":"10002060011.0",
    "gn:asciiname":"Wujian",
    "gn:country_code":"TW",
    "gn:dem":8,
    "gn:feature_class":"P",
    "gn:feature_code":"PPL",
    "gn:name":"Wujian",
    "gn:population":0,
    "gn:timezone":"Asia/Taipei",
    "iso:country":"TW",
    "name:und_x_variant":[
        "Wu-chien"
    ],
    "name:zho_x_preferred":[
        "\u4e94\u9593"
    ],
    "wof:name":"Wujian",
    "wof:placetype":"locality"
},
  "geometry": {"coordinates":[121.78306000000001,24.77611],"type":"Point"}
}