{
  "type": "Feature",
  "properties": {
    "gn:admin1_code":"03",
    "gn:admin2_code":"TPQ",
    "gn:admin3_code":"F27",
    "gn:admin4_code":"65000100013.0",
    "gn:asciiname":"Zoucuolun",
    "gn:country_code":"TW",
    "gn:dem":130,
    "gn:feature_class":"P",
    "gn:feature_code":"PPL",
    "gn:name":"Zoucuolun",
    "gn:population":0,
    "gn:timezone":"Asia/Taipei",
    "iso:country":"TW",
    "name:zho_x_preferred":[
        "\u9112\u539d\u5d19"
    ],
    "name:zho_x_variant":[
        "Tsou-ts\u2019o-lun"
    ],
    "wof:name":"Zoucuolun",
    "wof:placetype":"locality"
},
  "geometry": {"coordinates":[121.47141000000001,25.19008],"type":"Point"}
}