{
  "type": "Feature",
  "properties": {
    "gn:admin1_code":"4.0",
    "gn:admin2_code":"HUA",
    "gn:admin3_code":"U08",
    "gn:admin4_code":"10015080002.0",
    "gn:asciiname":"Xinzhuang",
    "gn:country_code":"TW",
    "gn:dem":23,
    "gn:feature_class":"P",
    "gn:feature_code":"PPL",
    "gn:name":"Xinzhuang",
    "gn:population":0,
    "gn:timezone":"Asia/Taipei",
    "iso:country":"TW",
    "name:ceb_x_preferred":[
        "Xinzhuang"
    ],
    "name:deu_x_preferred":[
        "Xinzhuang"
    ],
    "name:und_x_variant":[
        "Kung-hsia",
        "Sinjhuang",
        "Hsin-chuang"
    ],
    "name:zho_x_preferred":[
        "\u65b0\u838a"
    ],
    "wof:name":"Xinzhuang",
    "wof:placetype":"locality"
},
  "geometry": {"coordinates":[121.53278,23.64194],"type":"Point"}
}