{
  "type": "Feature",
  "properties": {
    "gn:admin1_code":"1.0",
    "gn:admin2_code":"KIN",
    "gn:admin3_code":"W02",
    "gn:admin4_code":"9020020007.0",
    "gn:asciiname":"Houyupo",
    "gn:country_code":"TW",
    "gn:dem":8,
    "gn:feature_class":"P",
    "gn:feature_code":"PPL",
    "gn:name":"Houyupo",
    "gn:population":0,
    "gn:timezone":"Asia/Taipei",
    "iso:country":"TW",
    "name:und_x_variant":[
        "\u540e\u5dbc\u5761",
        "Houyupo"
    ],
    "name:zho_x_preferred":[
        "Hou-hs\u00fc-p\u2019o"
    ],
    "name:zho_x_variant":[
        "Hou-y\u00fc-p\u2019o"
    ],
    "wof:name":"Houyupo",
    "wof:placetype":"locality"
},
  "geometry": {"coordinates":[118.425,24.52448],"type":"Point"}
}