{
  "type": "Feature",
  "properties": {
    "gn:admin1_code":"04",
    "gn:admin2_code":"HSZ",
    "gn:admin3_code":"J04",
    "gn:admin4_code":"10004030005.0",
    "gn:asciiname":"Sizuowei",
    "gn:country_code":"TW",
    "gn:dem":91,
    "gn:feature_class":"P",
    "gn:feature_code":"PPL",
    "gn:name":"Sizuowei",
    "gn:population":0,
    "gn:timezone":"Asia/Taipei",
    "iso:country":"TW",
    "name:und_x_variant":[
        "Sihzuowei",
        "Sizuowei",
        "Ssu-tso-wei"
    ],
    "name:zho_x_preferred":[
        "\u56db\u5ea7\u5c3e"
    ],
    "wof:name":"Sizuowei",
    "wof:placetype":"locality"
},
  "geometry": {"coordinates":[121.09611,24.8375],"type":"Point"}
}