{
  "type": "Feature",
  "properties": {
    "gn:admin1_code":"4.0",
    "gn:admin2_code":"TTT",
    "gn:admin3_code":"V03",
    "gn:admin4_code":"10014030001.0",
    "gn:asciiname":"Dongming",
    "gn:country_code":"TW",
    "gn:dem":275,
    "gn:feature_class":"P",
    "gn:feature_code":"PPL",
    "gn:name":"Dongming",
    "gn:population":0,
    "gn:timezone":"Asia/Taipei",
    "iso:country":"TW",
    "name:und_x_variant":[
        "Tung-ming"
    ],
    "name:zho_x_preferred":[
        "\u6771\u660e"
    ],
    "wof:name":"Dongming",
    "wof:placetype":"locality"
},
  "geometry": {"coordinates":[121.18472,23.08889],"type":"Point"}
}