{
  "type": "Feature",
  "properties": {
    "gn:admin1_code":"4.0",
    "gn:admin2_code":"PIF",
    "gn:admin3_code":"T13",
    "gn:admin4_code":"10013130007.0",
    "gn:asciiname":"Xigouwei",
    "gn:country_code":"TW",
    "gn:dem":24,
    "gn:feature_class":"P",
    "gn:feature_code":"PPL",
    "gn:name":"Xigouwei",
    "gn:population":0,
    "gn:timezone":"Asia/Taipei",
    "iso:country":"TW",
    "name:und_x_variant":[
        "Sigouwei",
        "Xigouwei",
        "Hsi-kou-wei"
    ],
    "name:zho_x_preferred":[
        "\u897f\u6e9d\u5c3e"
    ],
    "wof:name":"Xigouwei",
    "wof:placetype":"locality"
},
  "geometry": {"coordinates":[120.55166,22.62328],"type":"Point"}
}