{
  "type": "Feature",
  "properties": {
    "gn:admin1_code":"04",
    "gn:admin2_code":"HSZ",
    "gn:admin3_code":"J09",
    "gn:admin4_code":"10004060013.0",
    "gn:asciiname":"Shulinzi",
    "gn:country_code":"TW",
    "gn:dem":9,
    "gn:feature_class":"P",
    "gn:feature_code":"PPL",
    "gn:name":"Shulinzi",
    "gn:population":0,
    "gn:timezone":"Asia/Taipei",
    "iso:country":"TW",
    "name:und_x_variant":[
        "Shulinzih",
        "Shulinzi",
        "Shu-lin-tzu"
    ],
    "name:zho_x_preferred":[
        "Shu-lin-p\u2019o"
    ],
    "name:zho_x_variant":[
        "\u6a39\u6797\u5b50",
        "Chiang-ts\u2019o"
    ],
    "wof:name":"Shulinzi",
    "wof:placetype":"locality"
},
  "geometry": {"coordinates":[120.97111,24.90556],"type":"Point"}
}