{
  "type": "Feature",
  "properties": {
    "gn:admin1_code":"4.0",
    "gn:admin2_code":"ILA",
    "gn:admin3_code":"G09",
    "gn:admin4_code":"10002030007.0",
    "gn:asciiname":"Xinma",
    "gn:country_code":"TW",
    "gn:dem":13,
    "gn:feature_class":"P",
    "gn:feature_code":"PPL",
    "gn:name":"Xinma",
    "gn:population":0,
    "gn:timezone":"Asia/Taipei",
    "iso:country":"TW",
    "name:und_x_variant":[
        "Sinma",
        "Hsin-ma"
    ],
    "name:zho_x_preferred":[
        "\u65b0\u99ac"
    ],
    "wof:name":"Xinma",
    "wof:placetype":"locality"
},
  "geometry": {"coordinates":[121.83376,24.61706],"type":"Point"}
}