{
  "type": "Feature",
  "properties": {
    "iso:country":"TW",
    "qs:name":"\u6e56\u5357\u6751",
    "qs:name_adm0":"\u81fa\u7063",
    "qs:name_adm1":"\u65b0\u5317\u5e02",
    "qs:photos":239,
    "qs:photos_1k":48,
    "qs:photos_9k":1,
    "qs:photos_9r":4,
    "qs:photos_all":239,
    "qs:photos_sr":4,
    "qs:placetype":"Town",
    "qs:pop_sr":"0",
    "wof:name":"\u6e56\u5357\u6751",
    "wof:placetype":"locality"
},
  "geometry": {"coordinates":[121.37621300000001,25.082674],"type":"Point"}
}