{
  "type": "Feature",
  "properties": {
    "gn:admin1_code":"4.0",
    "gn:admin2_code":"TXG",
    "gn:admin3_code":"B29",
    "gn:admin4_code":"66000290003.0",
    "gn:asciiname":"Jiuliangxi",
    "gn:country_code":"TW",
    "gn:dem":1145,
    "gn:feature_class":"P",
    "gn:feature_code":"PPL",
    "gn:name":"Jiuliangxi",
    "gn:population":0,
    "gn:timezone":"Asia/Taipei",
    "iso:country":"TW",
    "name:und_x_variant":[
        "Chiu-liang-hsi-she",
        "Chiu-liang-hsi",
        "Jiuliangxi"
    ],
    "wof:name":"Jiuliangxi",
    "wof:placetype":"locality"
},
  "geometry": {"coordinates":[120.96666999999999,24.18333],"type":"Point"}
}