{
  "type": "Feature",
  "properties": {
    "gn:admin1_code":"3.0",
    "gn:admin2_code":"TPQ",
    "gn:admin3_code":"F07",
    "gn:admin4_code":"65000060028.0",
    "gn:asciiname":"Houliao",
    "gn:country_code":"TW",
    "gn:dem":299,
    "gn:feature_class":"P",
    "gn:feature_code":"PPL",
    "gn:name":"Houliao",
    "gn:population":0,
    "gn:timezone":"Asia/Taipei",
    "iso:country":"TW",
    "name:und_x_variant":[
        "Hou-liao"
    ],
    "name:zho_x_preferred":[
        "\u5f8c\u5bee"
    ],
    "wof:name":"Houliao",
    "wof:placetype":"locality"
},
  "geometry": {"coordinates":[121.53095,24.90703],"type":"Point"}
}