{
  "type": "Feature",
  "properties": {
    "gn:admin1_code":"4.0",
    "gn:admin2_code":"MIA",
    "gn:admin3_code":"K12",
    "gn:admin4_code":"10005060011.0",
    "gn:asciiname":"Xiafuwei",
    "gn:country_code":"TW",
    "gn:dem":18,
    "gn:feature_class":"P",
    "gn:feature_code":"PPL",
    "gn:name":"Xiafuwei",
    "gn:population":0,
    "gn:timezone":"Asia/Taipei",
    "iso:country":"TW",
    "name:und_x_variant":[
        "Hsia-le-wei",
        "Xiafuwei",
        "Hsia-lieh-wei",
        "Siafuwei",
        "Hsia-fu-wei"
    ],
    "name:zho_x_preferred":[
        "\u4e0b\u6d6e\u5c3e"
    ],
    "wof:name":"Xiafuwei",
    "wof:placetype":"locality"
},
  "geometry": {"coordinates":[120.79371,24.62362000000001],"type":"Point"}
}