{
  "type": "Feature",
  "properties": {
    "gn:admin1_code":"4.0",
    "gn:admin2_code":"CHA",
    "gn:admin3_code":"N03",
    "gn:admin4_code":"10007030010.0",
    "gn:asciiname":"Zhengpingzhuang",
    "gn:country_code":"TW",
    "gn:dem":15,
    "gn:feature_class":"P",
    "gn:feature_code":"PPL",
    "gn:name":"Zhengpingzhuang",
    "gn:population":0,
    "gn:timezone":"Asia/Taipei",
    "iso:country":"TW",
    "name:und_x_variant":[
        "Jhengpinjhuang",
        "Zhengpingzhuang"
    ],
    "name:zho_x_preferred":[
        "\u93ae\u5e73\u838a"
    ],
    "name:zho_x_variant":[
        "Cheng-p\u2019ing-chuang"
    ],
    "wof:name":"Zhengpingzhuang",
    "wof:placetype":"locality"
},
  "geometry": {"coordinates":[120.51407,24.08168],"type":"Point"}
}