{
  "type": "Feature",
  "properties": {
    "gn:admin1_code":"4.0",
    "gn:admin2_code":"NAN",
    "gn:admin3_code":"M13",
    "gn:admin4_code":"10008130009.0",
    "gn:asciiname":"Yuanfeng",
    "gn:country_code":"TW",
    "gn:dem":2806,
    "gn:feature_class":"P",
    "gn:feature_code":"PPL",
    "gn:name":"Yuanfeng",
    "gn:population":0,
    "gn:timezone":"Asia/Taipei",
    "iso:country":"TW",
    "name:fra_x_preferred":[
        "Yuanfeng"
    ],
    "name:und_x_variant":[
        "Yuanfong"
    ],
    "name:zho_x_preferred":[
        "\u9cf6\u5cef"
    ],
    "name:zho_x_variant":[
        "Y\u00fcan-feng"
    ],
    "wof:name":"Yuanfeng",
    "wof:placetype":"locality"
},
  "geometry": {"coordinates":[121.24333,24.12111],"type":"Point"}
}