{
  "type": "Feature",
  "properties": {
    "gn:admin1_code":"4.0",
    "gn:admin2_code":"ILA",
    "gn:admin3_code":"G08",
    "gn:admin4_code":"10002080011.0",
    "gn:asciiname":"Taihe",
    "gn:country_code":"TW",
    "gn:dem":9,
    "gn:feature_class":"P",
    "gn:feature_code":"PPL",
    "gn:name":"Taihe",
    "gn:population":0,
    "gn:timezone":"Asia/Taipei",
    "iso:country":"TW",
    "name:zho_x_preferred":[
        "\u592a\u548c"
    ],
    "name:zho_x_variant":[
        "T\u2019ai-ho"
    ],
    "wof:name":"Taihe",
    "wof:placetype":"locality"
},
  "geometry": {"coordinates":[121.77396,24.63279],"type":"Point"}
}