{
  "type": "Feature",
  "properties": {
    "gn:admin1_code":"04",
    "gn:admin2_code":"MIA",
    "gn:admin3_code":"K12",
    "gn:admin4_code":"10005060022.0",
    "gn:asciiname":"Wanwa",
    "gn:country_code":"TW",
    "gn:dem":21,
    "gn:feature_class":"P",
    "gn:feature_code":"PPL",
    "gn:name":"Wanwa",
    "gn:population":0,
    "gn:timezone":"Asia/Taipei",
    "iso:country":"TW",
    "name:und_x_variant":[
        "Wan-wa"
    ],
    "name:zho_x_preferred":[
        "\u7063\u74e6"
    ],
    "name:zho_x_variant":[
        "Hai-k\u2019ou"
    ],
    "wof:name":"Wanwa",
    "wof:placetype":"locality"
},
  "geometry": {"coordinates":[120.73869000000001,24.60445],"type":"Point"}
}