{
  "type": "Feature",
  "properties": {
    "gn:admin1_code":"3.0",
    "gn:admin2_code":"TPQ",
    "gn:admin3_code":"F19",
    "gn:admin4_code":"65000130015.0",
    "gn:asciiname":"Xiaokeng",
    "gn:country_code":"TW",
    "gn:dem":246,
    "gn:feature_class":"P",
    "gn:feature_code":"PPL",
    "gn:name":"Xiaokeng",
    "gn:population":0,
    "gn:timezone":"Asia/Taipei",
    "iso:country":"TW",
    "name:und_x_variant":[
        "Siaokeng"
    ],
    "name:zho_x_preferred":[
        "\u5c0f\u5751"
    ],
    "name:zho_x_variant":[
        "Hsiao-k\u2019eng"
    ],
    "wof:name":"Xiaokeng",
    "wof:placetype":"locality"
},
  "geometry": {"coordinates":[121.46053000000001,24.95031],"type":"Point"}
}