{
  "type": "Feature",
  "properties": {
    "gn:admin1_code":"4.0",
    "gn:admin2_code":"TTT",
    "gn:admin3_code":"V04",
    "gn:admin4_code":"10014040001.0",
    "gn:asciiname":"Heping",
    "gn:country_code":"TW",
    "gn:dem":122,
    "gn:feature_class":"P",
    "gn:feature_code":"PPL",
    "gn:name":"Heping",
    "gn:population":0,
    "gn:timezone":"Asia/Taipei",
    "iso:country":"TW",
    "name:ceb_x_preferred":[
        "Heping"
    ],
    "name:deu_x_preferred":[
        "Heping"
    ],
    "name:eus_x_preferred":[
        "Heping"
    ],
    "name:fra_x_preferred":[
        "Heping"
    ],
    "name:jpn_x_preferred":[
        "\u548c\u5e73\u533a"
    ],
    "name:kor_x_preferred":[
        "\ud5c8\ud551\uad6c"
    ],
    "name:nor_x_preferred":[
        "Heping"
    ],
    "name:sco_x_preferred":[
        "Heping"
    ],
    "name:swe_x_preferred":[
        "Heping"
    ],
    "name:und_x_variant":[
        "Pai-tzu-pai-she",
        "Pai-tzu-pai",
        "Heping"
    ],
    "name:vie_x_preferred":[
        "H\u00f2a B\u00ecnh"
    ],
    "name:zho_x_preferred":[
        "Ho-p\u2019ing-ts\u2019un"
    ],
    "name:zho_x_variant":[
        "Ho-p\u2019ing-ts\u2019un-lo",
        "\u548c\u5e73",
        "Ho-p\u2019ing",
        "\u548c\u5e73\u533a"
    ],
    "wof:name":"Heping",
    "wof:placetype":"locality"
},
  "geometry": {"coordinates":[121.14227,22.88203],"type":"Point"}
}