{
  "type": "Feature",
  "properties": {
    "gn:admin1_code":"04",
    "gn:admin2_code":"TAO",
    "gn:admin3_code":"H12",
    "gn:admin4_code":"68000120015.0",
    "gn:asciiname":"Beipo",
    "gn:country_code":"TW",
    "gn:dem":114,
    "gn:feature_class":"P",
    "gn:feature_code":"PPL",
    "gn:name":"Beipo",
    "gn:population":0,
    "gn:timezone":"Asia/Taipei",
    "iso:country":"TW",
    "name:zho_x_preferred":[
        "\u5317\u5761"
    ],
    "name:zho_x_variant":[
        "Pei-p\u2019o"
    ],
    "wof:name":"Beipo",
    "wof:placetype":"locality"
},
  "geometry": {"coordinates":[121.1525,24.96889],"type":"Point"}
}