{
  "type": "Feature",
  "properties": {
    "gn:admin1_code":"04",
    "gn:admin2_code":"MIA",
    "gn:admin3_code":"K10",
    "gn:admin4_code":"10005050003.0",
    "gn:asciiname":"Sifenzi",
    "gn:country_code":"TW",
    "gn:dem":77,
    "gn:feature_class":"P",
    "gn:feature_code":"PPL",
    "gn:name":"Sifenzi",
    "gn:population":0,
    "gn:timezone":"Asia/Taipei",
    "iso:country":"TW",
    "name:und_x_variant":[
        "Sihfenzih",
        "Ssu-fen-tzu"
    ],
    "name:zho_x_preferred":[
        "\u56db\u5206\u5b50"
    ],
    "wof:name":"Sifenzi",
    "wof:placetype":"locality"
},
  "geometry": {"coordinates":[120.94969,24.68011],"type":"Point"}
}