{
  "type": "Feature",
  "properties": {
    "gn:admin1_code":"4.0",
    "gn:admin2_code":"TXG",
    "gn:admin3_code":"B26",
    "gn:admin4_code":"66000260019.0",
    "gn:asciiname":"Jiugu",
    "gn:country_code":"TW",
    "gn:dem":56,
    "gn:feature_class":"P",
    "gn:feature_code":"PPL",
    "gn:name":"Jiugu",
    "gn:population":0,
    "gn:timezone":"Asia/Taipei",
    "iso:country":"TW",
    "name:und_x_variant":[
        "\u4e5d\u80a1",
        "Jiougu",
        "Jiugu",
        "Chiu-ku"
    ],
    "wof:name":"Jiugu",
    "wof:placetype":"locality"
},
  "geometry": {"coordinates":[120.663,24.042],"type":"Point"}
}