{
  "type": "Feature",
  "properties": {
    "iso:country":"TW",
    "qs:name":"\u69ae\u548c\u6751",
    "qs:name_adm0":"\u81fa\u7063",
    "qs:name_adm1":"\u53f0\u5357\u5e02",
    "qs:photos":9,
    "qs:photos_1k":2,
    "qs:photos_9k":1,
    "qs:photos_9r":1,
    "qs:photos_all":9,
    "qs:photos_sr":1,
    "qs:placetype":"Town",
    "qs:pop_sr":"0",
    "wof:name":"\u69ae\u548c\u6751",
    "wof:placetype":"locality"
},
  "geometry": {"coordinates":[120.3965,23.066],"type":"Point"}
}