{
  "type": "Feature",
  "properties": {
    "gn:admin1_code":"4.0",
    "gn:admin2_code":"CYQ",
    "gn:admin3_code":"Q16",
    "gn:admin4_code":"10010150004.0",
    "gn:asciiname":"Shitoulun",
    "gn:country_code":"TW",
    "gn:dem":143,
    "gn:feature_class":"P",
    "gn:feature_code":"PPL",
    "gn:name":"Shitoulun",
    "gn:population":0,
    "gn:timezone":"Asia/Taipei",
    "iso:country":"TW",
    "name:und_x_variant":[
        "Shihtoulun"
    ],
    "name:zho_x_preferred":[
        "\u7345\u982d\u5d19"
    ],
    "name:zho_x_variant":[
        "Shih-t\u2019ou-lun"
    ],
    "wof:name":"Shitoulun",
    "wof:placetype":"locality"
},
  "geometry": {"coordinates":[120.55194,23.58583],"type":"Point"}
}