{
  "type": "Feature",
  "properties": {
    "gn:admin1_code":"4.0",
    "gn:admin2_code":"TAO",
    "gn:admin3_code":"H02",
    "gn:admin4_code":"68000030014.0",
    "gn:asciiname":"Kantou",
    "gn:country_code":"TW",
    "gn:dem":60,
    "gn:feature_class":"P",
    "gn:feature_code":"PPL",
    "gn:name":"Kantou",
    "gn:population":0,
    "gn:timezone":"Asia/Taipei",
    "iso:country":"TW",
    "name:zho_x_preferred":[
        "K\u2019an-t\u2019ou"
    ],
    "wof:name":"Kantou",
    "wof:placetype":"locality"
},
  "geometry": {"coordinates":[121.32087,24.92817],"type":"Point"}
}