{
  "type": "Feature",
  "properties": {
    "iso:country":"TW",
    "qs:name":"\u540c\u8208\u6751",
    "qs:name_adm0":"\u81fa\u7063",
    "qs:name_adm1":"\u65b0\u5317\u5e02",
    "qs:photos":252,
    "qs:photos_1k":51,
    "qs:photos_9k":1,
    "qs:photos_9r":4,
    "qs:photos_all":252,
    "qs:photos_sr":5,
    "qs:placetype":"Town",
    "qs:pop_sr":"0",
    "wof:name":"\u540c\u8208\u6751",
    "wof:placetype":"locality"
},
  "geometry": {"coordinates":[121.435039,25.056561],"type":"Point"}
}