{
  "type": "Feature",
  "properties": {
    "gn:country":"TW",
    "gn:fcode":"PPL",
    "gn:population":402014,
    "iso:country":"TW",
    "name:ben_x_preferred":[
        "\u09a4\u09be\u09df\u09cb\u0987\u0989\u09df\u09be\u09a8"
    ],
    "name:ell_x_preferred":[
        "\u03a4\u03b1\u03bf\u03b3\u03bf\u03c5\u03ac\u03bd"
    ],
    "name:eng_x_preferred":[
        "Taoyuan"
    ],
    "name:eng_x_variant":[
        "Taoyuan City"
    ],
    "name:fas_x_preferred":[
        "\u062a\u0648\u0626\u0627\u06cc\u0648\u0622\u0646"
    ],
    "name:heb_x_preferred":[
        "\u05d8\u05d0\u05d5\u05d9\u05d5\u05d0\u05df"
    ],
    "name:hin_x_preferred":[
        "\u0924\u093e\u0913\u092f\u0941\u0906\u0928"
    ],
    "name:hun_x_preferred":[
        "Taoyuan"
    ],
    "name:ind_x_preferred":[
        "Taoyuan"
    ],
    "name:rus_x_preferred":[
        "\u0422\u0430\u043e\u044e\u0430\u043d\u044c"
    ],
    "name:tur_x_preferred":[
        "Taoyuan"
    ],
    "name:zho_tw_x_preferred":[
        "\u6843\u5712\u5e02"
    ],
    "qs:name":"\u6843\u5712\u5e02",
    "qs:name_adm0":"\u81fa\u7063",
    "qs:name_adm1":"\u6843\u5712\u7e23",
    "qs:photos":5000,
    "qs:photos_1k":1000,
    "qs:photos_9k":22,
    "qs:photos_9r":14,
    "qs:photos_all":5000,
    "qs:photos_sr":24,
    "qs:placetype":"Town",
    "qs:pop_sr":"10",
    "wof:name":"Taoyuan",
    "wof:placetype":"locality",
    "wof:population":402014
},
  "geometry": {"coordinates":[121.29696,24.99368],"type":"Point"}
}