{
  "type": "Feature",
  "properties": {
    "gn:country":"TW",
    "gn:fcode":"PPL",
    "gn:population":402014,
    "iso:country":"TW",
    "name:eng_x_preferred":[
        "Taoyuan"
    ],
    "name:eng_x_variant":[
        "Taoyuan City"
    ],
    "name:rus_x_preferred":[
        "\u0422\u0430\u043e\u044e\u0430\u043d\u044c"
    ],
    "name:zho_tw_x_preferred":[
        "\u6843\u5712\u5e02"
    ],
    "qs:name":"\u6843\u5712\u5e02",
    "qs:name_adm0":"\u81fa\u7063",
    "qs:name_adm1":"\u6843\u5712\u7e23",
    "qs:photos":5000,
    "qs:photos_1k":1000,
    "qs:photos_9k":22,
    "qs:photos_9r":14,
    "qs:photos_all":5000,
    "qs:photos_sr":24,
    "qs:placetype":"Town",
    "qs:pop_sr":"10",
    "wof:name":"Taoyuan",
    "wof:placetype":"locality",
    "wof:population":402014
},
  "geometry": {"coordinates":[121.29696,24.99368],"type":"Point"}
}