{
  "type": "Feature",
  "properties": {
    "gn:admin1_code":"04",
    "gn:admin2_code":"KEE",
    "gn:admin3_code":"C03",
    "gn:admin4_code":"10017030008.0",
    "gn:asciiname":"Nuannuan",
    "gn:country_code":"TW",
    "gn:dem":43,
    "gn:feature_class":"P",
    "gn:feature_code":"PPL",
    "gn:name":"Nuannuan",
    "gn:population":0,
    "gn:timezone":"Asia/Taipei",
    "iso:country":"TW",
    "name:und_x_variant":[
        "Nuan-nuan"
    ],
    "name:zho_x_preferred":[
        "\u6696\u6696"
    ],
    "wof:name":"Nuannuan",
    "wof:placetype":"locality"
},
  "geometry": {"coordinates":[121.73744000000001,25.1006],"type":"Point"}
}