{
  "type": "Feature",
  "properties": {
    "gn:admin1_code":"2.0",
    "gn:admin2_code":"KHH",
    "gn:admin3_code":"E32",
    "gn:admin4_code":"64000320005.0",
    "gn:asciiname":"Shangzhilai",
    "gn:country_code":"TW",
    "gn:dem":518,
    "gn:feature_class":"P",
    "gn:feature_code":"PPL",
    "gn:name":"Shangzhilai",
    "gn:population":0,
    "gn:timezone":"Asia/Taipei",
    "iso:country":"TW",
    "name:und_x_variant":[
        "Shangjhihlai",
        "Shangzhilai",
        "Shang-chih-lai"
    ],
    "name:zho_x_preferred":[
        "\u4e0a\u76f4\u7028"
    ],
    "wof:name":"Shangzhilai",
    "wof:placetype":"locality"
},
  "geometry": {"coordinates":[120.64610999999999,23.07194],"type":"Point"}
}