{
  "type": "Feature",
  "properties": {
    "iso:country":"TW",
    "qs:name":"\u5d07\u5fb7\u91cc",
    "qs:name_adm0":"\u81fa\u7063",
    "qs:name_adm1":"\u53f0\u4e2d\u5e02",
    "qs:photos":16,
    "qs:photos_1k":3,
    "qs:photos_9k":1,
    "qs:photos_9r":1,
    "qs:photos_all":16,
    "qs:photos_sr":1,
    "qs:placetype":"Suburb",
    "qs:pop_sr":"0",
    "wof:name":"\u5d07\u5fb7\u91cc",
    "wof:placetype":"neighbourhood"
},
  "geometry": {"coordinates":[120.68671000000001,24.165343],"type":"Point"}
}