{
  "type": "Feature",
  "properties": {
    "gn:admin1_code":"4.0",
    "gn:admin2_code":"HSZ",
    "gn:admin3_code":"J08",
    "gn:admin4_code":"10004080007.0",
    "gn:asciiname":"Dong'anbuzhuang",
    "gn:country_code":"TW",
    "gn:dem":259,
    "gn:feature_class":"P",
    "gn:feature_code":"PPL",
    "gn:name":"Dong\u2019anbuzhuang",
    "gn:population":0,
    "gn:timezone":"Asia/Taipei",
    "iso:country":"TW",
    "name:und_x_variant":[
        "Tung-an-pu-chuang"
    ],
    "name:zho_x_preferred":[
        "\u6771\u5b89\u90e8\u838a"
    ],
    "name:zho_x_variant":[
        "Dong\u2019anbujhuang",
        "Dong\u2019anbuzhuang"
    ],
    "wof:name":"Dong'anbuzhuang",
    "wof:placetype":"locality"
},
  "geometry": {"coordinates":[121.17972,24.73167],"type":"Point"}
}