{
  "type": "Feature",
  "properties": {
    "gn:admin1_code":"4.0",
    "gn:admin2_code":"CYQ",
    "gn:admin3_code":"Q14",
    "gn:admin4_code":"10010130011.0",
    "gn:asciiname":"Tianliaozi",
    "gn:country_code":"TW",
    "gn:dem":96,
    "gn:feature_class":"P",
    "gn:feature_code":"PPL",
    "gn:name":"Tianliaozi",
    "gn:population":0,
    "gn:timezone":"Asia/Taipei",
    "iso:country":"TW",
    "name:und_x_variant":[
        "Tianliaozih"
    ],
    "name:zho_x_preferred":[
        "\u7530\u5bee\u4ed4"
    ],
    "name:zho_x_variant":[
        "T\u2019ien-liao-tzu"
    ],
    "wof:name":"Tianliaozi",
    "wof:placetype":"locality"
},
  "geometry": {"coordinates":[120.51466000000001,23.44887],"type":"Point"}
}