{
  "type": "Feature",
  "properties": {
    "gn:admin1_code":"4.0",
    "gn:admin2_code":"TNN",
    "gn:admin3_code":"R03",
    "gn:admin4_code":"67000030010.0",
    "gn:asciiname":"Jiuchong",
    "gn:country_code":"TW",
    "gn:dem":108,
    "gn:feature_class":"P",
    "gn:feature_code":"PPL",
    "gn:name":"Jiuchong",
    "gn:population":0,
    "gn:timezone":"Asia/Taipei",
    "iso:country":"TW",
    "name:und_x_variant":[
        "Jiouchong",
        "Jiuchong"
    ],
    "name:zho_x_preferred":[
        "\u4e5d\u91cd"
    ],
    "name:zho_x_variant":[
        "Chiu-ch\u2019ung"
    ],
    "wof:name":"Jiuchong",
    "wof:placetype":"locality"
},
  "geometry": {"coordinates":[120.47167,23.31167],"type":"Point"}
}