{
  "type": "Feature",
  "properties": {
    "gn:admin1_code":"04",
    "gn:admin2_code":"HSZ",
    "gn:admin3_code":"J14",
    "gn:admin4_code":"10004120003.0",
    "gn:asciiname":"Xinle",
    "gn:country_code":"TW",
    "gn:dem":448,
    "gn:feature_class":"P",
    "gn:feature_code":"PPL",
    "gn:name":"Xinle",
    "gn:population":0,
    "gn:timezone":"Asia/Taipei",
    "iso:country":"TW",
    "name:ceb_x_preferred":[
        "Xinle"
    ],
    "name:deu_x_preferred":[
        "Xinle"
    ],
    "name:rus_x_preferred":[
        "\u0421\u0438\u043d\u044c\u043b\u044d"
    ],
    "name:und_x_variant":[
        "Sinle",
        "Hsin-le"
    ],
    "name:zho_x_preferred":[
        "Shiu-t\u2019ien"
    ],
    "name:zho_x_variant":[
        "\u65b0\u6a02",
        "Shui-t\u2019ien"
    ],
    "wof:name":"Xinle",
    "wof:placetype":"locality"
},
  "geometry": {"coordinates":[121.25082999999999,24.73194],"type":"Point"}
}