{
  "type": "Feature",
  "properties": {
    "gn:admin1_code":"4.0",
    "gn:admin2_code":"NAN",
    "gn:admin3_code":"M11",
    "gn:admin4_code":"10008110011.0",
    "gn:asciiname":"Dijunxiang",
    "gn:country_code":"TW",
    "gn:dem":464,
    "gn:feature_class":"P",
    "gn:feature_code":"PPL",
    "gn:name":"Dijunxiang",
    "gn:population":0,
    "gn:timezone":"Asia/Taipei",
    "iso:country":"TW",
    "name:und_x_variant":[
        "Dijyunsiang",
        "Dijunxiang"
    ],
    "name:zho_x_preferred":[
        "\u5e1d\u541b\u5df7"
    ],
    "name:zho_x_variant":[
        "Ti-ch\u00fcn-hsiang"
    ],
    "wof:name":"Dijunxiang",
    "wof:placetype":"locality"
},
  "geometry": {"coordinates":[120.87048,23.86637],"type":"Point"}
}