{
  "type": "Feature",
  "properties": {
    "gn:admin1_code":"4.0",
    "gn:admin2_code":"HUA",
    "gn:admin3_code":"U10",
    "gn:admin4_code":"10015100011.0",
    "gn:asciiname":"Daqiao",
    "gn:country_code":"TW",
    "gn:dem":287,
    "gn:feature_class":"P",
    "gn:feature_code":"PPL",
    "gn:name":"Daqiao",
    "gn:population":0,
    "gn:timezone":"Asia/Taipei",
    "iso:country":"TW",
    "name:und_x_variant":[
        "Daciao",
        "Daqiao"
    ],
    "name:zho_x_preferred":[
        "\u5927\u6a4b"
    ],
    "name:zho_x_variant":[
        "Ta-ch\u2019iao"
    ],
    "wof:name":"Daqiao",
    "wof:placetype":"locality"
},
  "geometry": {"coordinates":[121.26588999999998,23.14991],"type":"Point"}
}