{
  "type": "Feature",
  "properties": {
    "gn:admin1_code":"4.0",
    "gn:admin2_code":"TAO",
    "gn:admin3_code":"H05",
    "gn:admin4_code":"68000050014.0",
    "gn:asciiname":"Chituqi",
    "gn:country_code":"TW",
    "gn:dem":191,
    "gn:feature_class":"P",
    "gn:feature_code":"PPL",
    "gn:name":"Chituqi",
    "gn:population":0,
    "gn:timezone":"Asia/Taipei",
    "iso:country":"TW",
    "name:und_x_variant":[
        "Chihtuci",
        "Chituqi"
    ],
    "name:zho_x_preferred":[
        "\u8d64\u5857\u5d0e"
    ],
    "name:zho_x_variant":[
        "Ch\u2019ih-t\u2019u-ch\u2019i"
    ],
    "wof:name":"Chituqi",
    "wof:placetype":"locality"
},
  "geometry": {"coordinates":[121.33897,25.06814],"type":"Point"}
}