{
  "type": "Feature",
  "properties": {
    "gn:admin1_code":"4.0",
    "gn:admin2_code":"CYQ",
    "gn:admin3_code":"Q04",
    "gn:admin4_code":"10010040013.0",
    "gn:asciiname":"Baicidong",
    "gn:country_code":"TW",
    "gn:dem":83,
    "gn:feature_class":"P",
    "gn:feature_code":"PPL",
    "gn:name":"Baicidong",
    "gn:population":0,
    "gn:timezone":"Asia/Taipei",
    "iso:country":"TW",
    "name:und_x_variant":[
        "Baicihdong",
        "Pai-lu-tung",
        "Baicidong"
    ],
    "name:zho_x_preferred":[
        "\u767d\u9dbf\u6d1e"
    ],
    "name:zho_x_variant":[
        "Pai-tz\u2019u-tung"
    ],
    "wof:name":"Baicidong",
    "wof:placetype":"locality"
},
  "geometry": {"coordinates":[120.51917,23.57444],"type":"Point"}
}