{
  "type": "Feature",
  "properties": {
    "gn:admin1_code":"4.0",
    "gn:admin2_code":"TTT",
    "gn:admin3_code":"V09",
    "gn:admin4_code":"10014050002.0",
    "gn:asciiname":"Jingfeng",
    "gn:country_code":"TW",
    "gn:dem":238,
    "gn:feature_class":"P",
    "gn:feature_code":"PPL",
    "gn:name":"Jingfeng",
    "gn:population":0,
    "gn:timezone":"Asia/Taipei",
    "iso:country":"TW",
    "name:und_x_variant":[
        "A-hou-liao",
        "A-kou-liao",
        "Jingfeng",
        "Hou-liao",
        "Jingfong",
        "Ching-feng"
    ],
    "name:zho_x_preferred":[
        "\u666f\u8c50"
    ],
    "wof:name":"Jingfeng",
    "wof:placetype":"locality"
},
  "geometry": {"coordinates":[121.14097,22.98927],"type":"Point"}
}