{
  "type": "Feature",
  "properties": {
    "gn:admin1_code":"3.0",
    "gn:admin2_code":"TPQ",
    "gn:admin3_code":"F02",
    "gn:admin4_code":"65000170008.0",
    "gn:asciiname":"Jingzicuo",
    "gn:country_code":"TW",
    "gn:dem":247,
    "gn:feature_class":"P",
    "gn:feature_code":"PPL",
    "gn:name":"Jingzicuo",
    "gn:population":0,
    "gn:timezone":"Asia/Taipei",
    "iso:country":"TW",
    "name:und_x_variant":[
        "Jingzihcuo"
    ],
    "name:zho_x_preferred":[
        "\u4e95\u5b50\u539d"
    ],
    "name:zho_x_variant":[
        "Ching-tzu-ts\u2019o"
    ],
    "wof:name":"Jingzicuo",
    "wof:placetype":"locality"
},
  "geometry": {"coordinates":[121.3516,25.07943],"type":"Point"}
}