{
  "type": "Feature",
  "properties": {
    "gn:admin1_code":"04",
    "gn:admin2_code":"MIA",
    "gn:admin3_code":"K06",
    "gn:admin4_code":"10005130007.0",
    "gn:asciiname":"Shengwangqixia",
    "gn:country_code":"TW",
    "gn:dem":253,
    "gn:feature_class":"P",
    "gn:feature_code":"PPL",
    "gn:name":"Shengwangqixia",
    "gn:population":0,
    "gn:timezone":"Asia/Taipei",
    "iso:country":"TW",
    "name:und_x_variant":[
        "Shengwangcisia"
    ],
    "name:zho_x_preferred":[
        "Sheng-ch\u2019i"
    ],
    "name:zho_x_variant":[
        "\u8056\u738b\u5d0e\u4e0b",
        "Sheng-wang-ch\u2019i-hsia"
    ],
    "wof:name":"Shengwangqixia",
    "wof:placetype":"locality"
},
  "geometry": {"coordinates":[120.75139,24.35556],"type":"Point"}
}