{
  "type": "Feature",
  "properties": {
    "gn:admin1_code":"04",
    "gn:admin2_code":"HSZ",
    "gn:admin3_code":"J15",
    "gn:admin4_code":"10004130002.0",
    "gn:asciiname":"Tianhu",
    "gn:country_code":"TW",
    "gn:dem":894,
    "gn:feature_class":"P",
    "gn:feature_code":"PPL",
    "gn:name":"Tianhu",
    "gn:population":0,
    "gn:timezone":"Asia/Taipei",
    "iso:country":"TW",
    "name:und_x_variant":[
        "Mu-shan",
        "Tianhu"
    ],
    "name:zho_x_preferred":[
        "T\u2019ien-hu-she"
    ],
    "name:zho_x_variant":[
        "\u5929\u6e56",
        "T\u2019ien-hu"
    ],
    "wof:name":"Tianhu",
    "wof:placetype":"locality"
},
  "geometry": {"coordinates":[121.16583,24.65917],"type":"Point"}
}