{
  "type": "Feature",
  "properties": {
    "gn:admin1_code":"4.0",
    "gn:admin2_code":"CYQ",
    "gn:admin3_code":"Q14",
    "gn:admin4_code":"10010130015.0",
    "gn:asciiname":"Zhentouzi",
    "gn:country_code":"TW",
    "gn:dem":170,
    "gn:feature_class":"P",
    "gn:feature_code":"PPL",
    "gn:name":"Zhentouzi",
    "gn:population":0,
    "gn:timezone":"Asia/Taipei",
    "iso:country":"TW",
    "name:und_x_variant":[
        "Jhentouzih",
        "Zhentouzi"
    ],
    "name:zho_x_preferred":[
        "\u5733\u982d\u4ed4"
    ],
    "name:zho_x_variant":[
        "Chen-t\u2019ou-tzu"
    ],
    "wof:name":"Zhentouzi",
    "wof:placetype":"locality"
},
  "geometry": {"coordinates":[120.53755,23.41444],"type":"Point"}
}