{
  "type": "Feature",
  "properties": {
    "gn:admin1_code":"4.0",
    "gn:admin2_code":"TNN",
    "gn:admin3_code":"R25",
    "gn:admin4_code":"67000250008.0",
    "gn:asciiname":"Xiaguilin",
    "gn:country_code":"TW",
    "gn:dem":237,
    "gn:feature_class":"P",
    "gn:feature_code":"PPL",
    "gn:name":"Xiaguilin",
    "gn:population":0,
    "gn:timezone":"Asia/Taipei",
    "iso:country":"TW",
    "name:und_x_variant":[
        "Siagueilin",
        "Hsia-kuei-lin"
    ],
    "name:zho_x_preferred":[
        "\u4e0b\u6b78\u6797"
    ],
    "wof:name":"Xiaguilin",
    "wof:placetype":"locality"
},
  "geometry": {"coordinates":[120.54639,23.07417],"type":"Point"}
}