{
  "type": "Feature",
  "properties": {
    "gn:admin1_code":"3.0",
    "gn:admin2_code":"TPQ",
    "gn:admin3_code":"F27",
    "gn:admin4_code":"65000100009.0",
    "gn:asciiname":"Hazishan",
    "gn:country_code":"TW",
    "gn:dem":46,
    "gn:feature_class":"P",
    "gn:feature_code":"PPL",
    "gn:name":"Hazishan",
    "gn:population":0,
    "gn:timezone":"Asia/Taipei",
    "iso:country":"TW",
    "name:und_x_variant":[
        "Hazihshan",
        "Ha-tzu-shan"
    ],
    "name:zho_x_preferred":[
        "\u86e4\u4ed4\u5c71"
    ],
    "wof:name":"Hazishan",
    "wof:placetype":"locality"
},
  "geometry": {"coordinates":[121.44571999999999,25.19616],"type":"Point"}
}