{
  "type": "Feature",
  "properties": {
    "gn:admin1_code":"3.0",
    "gn:admin2_code":"TPQ",
    "gn:admin3_code":"F26",
    "gn:admin4_code":"65000280004.0",
    "gn:asciiname":"Xiashe",
    "gn:country_code":"TW",
    "gn:dem":11,
    "gn:feature_class":"P",
    "gn:feature_code":"PPL",
    "gn:name":"Xiashe",
    "gn:population":0,
    "gn:timezone":"Asia/Taipei",
    "iso:country":"TW",
    "name:und_x_variant":[
        "Siashe",
        "Xiashe",
        "Hsia-liao",
        "Hsia-she"
    ],
    "name:zho_x_preferred":[
        "\u4e0b\u793e"
    ],
    "wof:name":"Xiashe",
    "wof:placetype":"locality"
},
  "geometry": {"coordinates":[121.6484,25.2169],"type":"Point"}
}