{
  "type": "Feature",
  "properties": {
    "gn:admin1_code":"04",
    "gn:admin2_code":"HUA",
    "gn:admin3_code":"U03",
    "gn:admin4_code":"10015030006.0",
    "gn:asciiname":"Shuiyuan",
    "gn:country_code":"TW",
    "gn:dem":145,
    "gn:feature_class":"P",
    "gn:feature_code":"PPL",
    "gn:name":"Shuiyuan",
    "gn:population":0,
    "gn:timezone":"Asia/Taipei",
    "iso:country":"TW",
    "name:und_x_variant":[
        "Shui-y\u00fcan-li",
        "Shui-yung-li",
        "\u6c34\u6e90",
        "Shuiyuan",
        "Shueiyuan"
    ],
    "name:zho_x_preferred":[
        "Y\u00fcan-ch\u2019eng"
    ],
    "name:zho_x_variant":[
        "Shui-y\u00fcan",
        "\u6c34\u6e90",
        "Shui-y\u00fcan-li"
    ],
    "wof:name":"Shuiyuan",
    "wof:placetype":"locality"
},
  "geometry": {"coordinates":[121.30562,23.33106],"type":"Point"}
}