{
  "type": "Feature",
  "properties": {
    "gn:admin1_code":"4.0",
    "gn:admin2_code":"CYQ",
    "gn:admin3_code":"Q15",
    "gn:admin4_code":"10010140021.0",
    "gn:asciiname":"Xiaweng",
    "gn:country_code":"TW",
    "gn:dem":568,
    "gn:feature_class":"P",
    "gn:feature_code":"PPL",
    "gn:name":"Xiaweng",
    "gn:population":0,
    "gn:timezone":"Asia/Taipei",
    "iso:country":"TW",
    "name:und_x_variant":[
        "Siawong",
        "Hsia-weng"
    ],
    "name:zho_x_preferred":[
        "\u4e0b\u7515"
    ],
    "wof:name":"Xiaweng",
    "wof:placetype":"locality"
},
  "geometry": {"coordinates":[120.59417000000001,23.53694],"type":"Point"}
}