{
  "type": "Feature",
  "properties": {
    "gn:admin1_code":"4.0",
    "gn:admin2_code":"NAN",
    "gn:admin3_code":"M05",
    "gn:admin4_code":"10008050004.0",
    "gn:asciiname":"Xiafengzilin",
    "gn:country_code":"TW",
    "gn:dem":216,
    "gn:feature_class":"P",
    "gn:feature_code":"PPL",
    "gn:name":"Xiafengzilin",
    "gn:population":0,
    "gn:timezone":"Asia/Taipei",
    "iso:country":"TW",
    "name:und_x_variant":[
        "Siafongzihlin",
        "Hsia-feng-lin-tzu",
        "Xiafengzilin",
        "Hsia-feng-tzu-lin"
    ],
    "name:zho_x_preferred":[
        "\u4e0b\u6953\u5b50\u6797"
    ],
    "wof:name":"Xiafengzilin",
    "wof:placetype":"locality"
},
  "geometry": {"coordinates":[120.75122,23.83271],"type":"Point"}
}