{
  "type": "Feature",
  "properties": {
    "gn:admin1_code":"1.0",
    "gn:asciiname":"Kunqiucun",
    "gn:country_code":"TW",
    "gn:dem":-9999,
    "gn:feature_class":"P",
    "gn:feature_code":"PPL",
    "gn:name":"Kunqiucun",
    "gn:population":0,
    "gn:timezone":"Asia/Taipei",
    "iso:country":"TW",
    "name:und_x_variant":[
        "K\u2019un-ch\u2019iu",
        "K\u2019un-ch\u2019iu-ts\u2019un",
        "Kunqiucun"
    ],
    "wof:name":"Kunqiucun",
    "wof:placetype":"locality"
},
  "geometry": {"coordinates":[119.91667,25.98333],"type":"Point"}
}