{
  "type": "Feature",
  "properties": {
    "gn:admin1_code":"3.0",
    "gn:admin2_code":"TPQ",
    "gn:admin3_code":"F11",
    "gn:admin4_code":"65000290001.0",
    "gn:asciiname":"Xiaoliao",
    "gn:country_code":"TW",
    "gn:dem":184,
    "gn:feature_class":"P",
    "gn:feature_code":"PPL",
    "gn:name":"Xiaoliao",
    "gn:population":0,
    "gn:timezone":"Asia/Taipei",
    "iso:country":"TW",
    "name:und_x_variant":[
        "Hsiao-yao",
        "Hsiao-chai",
        "Siaoliao",
        "Hsiao-liao"
    ],
    "name:zho_x_preferred":[
        "\u5c0f\u5bee"
    ],
    "wof:name":"Xiaoliao",
    "wof:placetype":"locality"
},
  "geometry": {"coordinates":[121.54845,24.86536],"type":"Point"}
}