{
  "type": "Feature",
  "properties": {
    "gn:admin1_code":"4.0",
    "gn:admin2_code":"NAN",
    "gn:admin3_code":"M08",
    "gn:admin4_code":"10008080005.0",
    "gn:asciiname":"Shicheng",
    "gn:country_code":"TW",
    "gn:dem":208,
    "gn:feature_class":"P",
    "gn:feature_code":"PPL",
    "gn:name":"Shicheng",
    "gn:population":0,
    "gn:timezone":"Asia/Taipei",
    "iso:country":"TW",
    "name:und_x_variant":[
        "Shihcheng"
    ],
    "name:zho_x_preferred":[
        "\u77f3\u57ce"
    ],
    "name:zho_x_variant":[
        "Shih-ch\u2019eng"
    ],
    "wof:name":"Shicheng",
    "wof:placetype":"locality"
},
  "geometry": {"coordinates":[120.79522,23.88532],"type":"Point"}
}