{
  "type": "Feature",
  "properties": {
    "gn:admin1_code":"4.0",
    "gn:admin2_code":"TXG",
    "gn:admin3_code":"B16",
    "gn:admin4_code":"66000160010.0",
    "gn:asciiname":"Qianliao",
    "gn:country_code":"TW",
    "gn:dem":194,
    "gn:feature_class":"P",
    "gn:feature_code":"PPL",
    "gn:name":"Qianliao",
    "gn:population":0,
    "gn:timezone":"Asia/Taipei",
    "iso:country":"TW",
    "name:und_x_variant":[
        "Cianliao",
        "Qianliao"
    ],
    "name:zho_x_preferred":[
        "\u524d\u5bee"
    ],
    "name:zho_x_variant":[
        "Ch\u2019ien-liao"
    ],
    "wof:name":"Qianliao",
    "wof:placetype":"locality"
},
  "geometry": {"coordinates":[120.70193999999999,24.25861],"type":"Point"}
}