{
  "type": "Feature",
  "properties": {
    "iso:country":"TW",
    "label:eng_x_preferred_longname":[
        "Ji'an Township"
    ],
    "label:eng_x_preferred_placetype":[
        "township"
    ],
    "name:eng_x_preferred":[
        "Ji'an"
    ],
    "name:zho_x_preferred":[
        "\u5409\u5b89\u9109"
    ],
    "qs:name":"\u5409\u5b89\u9109",
    "qs:name_adm0":"\u81fa\u7063",
    "qs:name_adm1":"\u82b1\u84ee\u7e23",
    "qs:photos":2476,
    "qs:photos_1k":502,
    "qs:photos_9k":21,
    "qs:photos_9r":13,
    "qs:photos_all":4638,
    "qs:photos_sr":17,
    "qs:placetype":"County",
    "qs:pop_sr":"0",
    "wof:name":"Ji'an",
    "wof:placetype":"county"
},
  "geometry": {"coordinates":[121.592731,23.94233],"type":"Point"}
}