{
  "type": "Feature",
  "properties": {
    "gn:admin1_code":"4.0",
    "gn:admin2_code":"TNN",
    "gn:admin3_code":"D06",
    "gn:admin4_code":"67000350026.0",
    "gn:asciiname":"Xuejialiao",
    "gn:country_code":"TW",
    "gn:dem":8,
    "gn:feature_class":"P",
    "gn:feature_code":"PPL",
    "gn:name":"Xuejialiao",
    "gn:population":0,
    "gn:timezone":"Asia/Taipei",
    "iso:country":"TW",
    "name:und_x_variant":[
        "Syuejialiao",
        "Xuejialiao"
    ],
    "name:zho_x_preferred":[
        "Hs\u00fceh-chia-liao"
    ],
    "name:zho_x_variant":[
        "\u5b78\u7532\u5bee"
    ],
    "wof:name":"Xuejialiao",
    "wof:placetype":"locality"
},
  "geometry": {"coordinates":[120.14388999999998,23.07917],"type":"Point"}
}