{
  "type": "Feature",
  "properties": {
    "gn:admin1_code":"04",
    "gn:admin2_code":"YUN",
    "gn:admin3_code":"P17",
    "gn:admin4_code":"10009170012.0",
    "gn:asciiname":"Dingliao",
    "gn:country_code":"TW",
    "gn:dem":13,
    "gn:feature_class":"P",
    "gn:feature_code":"PPL",
    "gn:name":"Dingliao",
    "gn:population":0,
    "gn:timezone":"Asia/Taipei",
    "iso:country":"TW",
    "name:und_x_variant":[
        "Ting-liao"
    ],
    "name:zho_x_preferred":[
        "Ting-liao-ts\u2019un"
    ],
    "name:zho_x_variant":[
        "\u9802\u5bee"
    ],
    "wof:name":"Dingliao",
    "wof:placetype":"locality"
},
  "geometry": {"coordinates":[120.33101000000001,23.63042],"type":"Point"}
}