{
  "type": "Feature",
  "properties": {
    "gn:admin1_code":"4.0",
    "gn:admin2_code":"KEE",
    "gn:admin3_code":"C02",
    "gn:admin4_code":"10017020016.0",
    "gn:asciiname":"Zhangkonghu",
    "gn:country_code":"TW",
    "gn:dem":144,
    "gn:feature_class":"P",
    "gn:feature_code":"PPL",
    "gn:name":"Zhangkonghu",
    "gn:population":0,
    "gn:timezone":"Asia/Taipei",
    "iso:country":"TW",
    "name:und_x_variant":[
        "Jhangkonghu",
        "Zhangkonghu"
    ],
    "name:zho_x_preferred":[
        "\u6a1f\u7a7a\u6e56"
    ],
    "name:zho_x_variant":[
        "Chang-k\u2019ung-hu"
    ],
    "wof:name":"Zhangkonghu",
    "wof:placetype":"locality"
},
  "geometry": {"coordinates":[121.65416,25.12628],"type":"Point"}
}