{
  "type": "Feature",
  "properties": {
    "gn:admin1_code":"2.0",
    "gn:admin2_code":"KHH",
    "gn:admin3_code":"E35",
    "gn:admin4_code":"64000350017.0",
    "gn:asciiname":"Zhuweiping",
    "gn:country_code":"TW",
    "gn:dem":106,
    "gn:feature_class":"P",
    "gn:feature_code":"PPL",
    "gn:name":"Zhuweiping",
    "gn:population":0,
    "gn:timezone":"Asia/Taipei",
    "iso:country":"TW",
    "name:und_x_variant":[
        "Jhuweiping",
        "Zhuweiping"
    ],
    "name:zho_x_preferred":[
        "\u7af9\u570d\u576a"
    ],
    "name:zho_x_variant":[
        "Chu-wei-p\u2019ing"
    ],
    "wof:name":"Zhuweiping",
    "wof:placetype":"locality"
},
  "geometry": {"coordinates":[120.42389,22.90139],"type":"Point"}
}