{
  "type": "Feature",
  "properties": {
    "gn:admin1_code":"4.0",
    "gn:admin2_code":"NAN",
    "gn:admin3_code":"M05",
    "gn:admin4_code":"10008050011.0",
    "gn:asciiname":"Beishikeng",
    "gn:country_code":"TW",
    "gn:dem":251,
    "gn:feature_class":"P",
    "gn:feature_code":"PPL",
    "gn:name":"Beishikeng",
    "gn:population":0,
    "gn:timezone":"Asia/Taipei",
    "iso:country":"TW",
    "name:und_x_variant":[
        "Beishihkeng",
        "Kuang-ming"
    ],
    "name:zho_x_preferred":[
        "\u5317\u52e2\u5751"
    ],
    "name:zho_x_variant":[
        "Pei-shih-k\u2019eng"
    ],
    "wof:name":"Beishikeng",
    "wof:placetype":"locality"
},
  "geometry": {"coordinates":[120.79965,23.8404],"type":"Point"}
}