{
  "type": "Feature",
  "properties": {
    "gn:admin1_code":"4.0",
    "gn:admin2_code":"CHA",
    "gn:admin3_code":"N26",
    "gn:admin4_code":"10007260005.0",
    "gn:asciiname":"Xicuo",
    "gn:country_code":"TW",
    "gn:dem":35,
    "gn:feature_class":"P",
    "gn:feature_code":"PPL",
    "gn:name":"Xicuo",
    "gn:population":0,
    "gn:timezone":"Asia/Taipei",
    "iso:country":"TW",
    "name:und_x_variant":[
        "Sicuo",
        "Xicuo"
    ],
    "name:zho_x_preferred":[
        "Ch\u2019i-ts\u2019o-ts\u2019un"
    ],
    "name:zho_x_variant":[
        "Hsi-ts\u2019o-ts\u2019un",
        "\u6eaa\u539d",
        "Hsi-ts\u2019o"
    ],
    "wof:name":"Xicuo",
    "wof:placetype":"locality"
},
  "geometry": {"coordinates":[120.47967,23.84946],"type":"Point"}
}