{
  "type": "Feature",
  "properties": {
    "gn:admin1_code":"4.0",
    "gn:admin2_code":"TXG",
    "gn:admin3_code":"B19",
    "gn:admin4_code":"66000190011.0",
    "gn:asciiname":"Huxing",
    "gn:country_code":"TW",
    "gn:dem":565,
    "gn:feature_class":"P",
    "gn:feature_code":"PPL",
    "gn:name":"Huxing",
    "gn:population":0,
    "gn:timezone":"Asia/Taipei",
    "iso:country":"TW",
    "name:und_x_variant":[
        "Husing",
        "Hu-hsing"
    ],
    "name:zho_x_preferred":[
        "\u6e56\u8208"
    ],
    "wof:name":"Huxing",
    "wof:placetype":"locality"
},
  "geometry": {"coordinates":[120.82453999999998,24.17675],"type":"Point"}
}