{
  "type": "Feature",
  "properties": {
    "gn:admin1_code":"04",
    "gn:admin2_code":"TAO",
    "gn:admin3_code":"H13",
    "gn:admin4_code":"68000130006.0",
    "gn:asciiname":"Wudaonenggan",
    "gn:country_code":"TW",
    "gn:dem":957,
    "gn:feature_class":"P",
    "gn:feature_code":"PPL",
    "gn:name":"Wudaonenggan",
    "gn:population":0,
    "gn:timezone":"Asia/Taipei",
    "iso:country":"TW",
    "name:und_x_variant":[
        "Wu-tao-neng-kan-she",
        "Wudaonenggan",
        "Wu-tao",
        "Wu-tao-neng-kan"
    ],
    "name:zho_x_preferred":[
        "\u6b66\u9053\u80fd\u6562"
    ],
    "name:zho_x_variant":[
        "Pu-t\u2019o-no-k\u2019an"
    ],
    "wof:name":"Wudaonenggan",
    "wof:placetype":"locality"
},
  "geometry": {"coordinates":[121.36028,24.68278],"type":"Point"}
}