{
  "type": "Feature",
  "properties": {
    "iso:country":"TW",
    "qs:name":"\u5c71\u8173\u6751",
    "qs:name_adm0":"\u81fa\u7063",
    "qs:name_adm1":"\u6843\u5712\u7e23",
    "qs:photos":321,
    "qs:photos_1k":65,
    "qs:photos_9k":1,
    "qs:photos_9r":5,
    "qs:photos_all":321,
    "qs:photos_sr":5,
    "qs:placetype":"Town",
    "qs:pop_sr":"0",
    "wof:name":"\u5c71\u8173\u6751",
    "wof:placetype":"locality"
},
  "geometry": {"coordinates":[121.279106,25.087775],"type":"Point"}
}