{
  "type": "Feature",
  "properties": {
    "gn:admin1_code":"04",
    "gn:admin2_code":"HUA",
    "gn:admin3_code":"U10",
    "gn:admin4_code":"10015100008.0",
    "gn:asciiname":"Mingli",
    "gn:country_code":"TW",
    "gn:dem":217,
    "gn:feature_class":"P",
    "gn:feature_code":"PPL",
    "gn:name":"Mingli",
    "gn:population":0,
    "gn:timezone":"Asia/Taipei",
    "iso:country":"TW",
    "name:und_x_variant":[
        "Li-hang",
        "Mingli",
        "Ming-li"
    ],
    "name:zho_x_preferred":[
        "Ming-li-ts\u2019un"
    ],
    "name:zho_x_variant":[
        "\u660e\u91cc"
    ],
    "wof:name":"Mingli",
    "wof:placetype":"locality"
},
  "geometry": {"coordinates":[121.25333000000001,23.20083],"type":"Point"}
}