{
  "type": "Feature",
  "properties": {
    "gn:admin1_code":"4.0",
    "gn:admin2_code":"HSZ",
    "gn:admin3_code":"J04",
    "gn:admin4_code":"10004030011.0",
    "gn:asciiname":"Shangfangliao",
    "gn:country_code":"TW",
    "gn:dem":49,
    "gn:feature_class":"P",
    "gn:feature_code":"PPL",
    "gn:name":"Shangfangliao",
    "gn:population":0,
    "gn:timezone":"Asia/Taipei",
    "iso:country":"TW",
    "name:und_x_variant":[
        "Fang-liao",
        "Shangfangliao",
        "Shang-fang-liao"
    ],
    "name:zho_x_preferred":[
        "\u4e0a\u678b\u5bee"
    ],
    "wof:name":"Shangfangliao",
    "wof:placetype":"locality"
},
  "geometry": {"coordinates":[121.05472,24.83556],"type":"Point"}
}