{
  "type": "Feature",
  "properties": {
    "gn:admin1_code":"04",
    "gn:admin2_code":"TXG",
    "gn:admin3_code":"B27",
    "gn:admin4_code":"66000270034.0",
    "gn:asciiname":"Sancha",
    "gn:country_code":"TW",
    "gn:dem":101,
    "gn:feature_class":"P",
    "gn:feature_code":"PPL",
    "gn:name":"Sancha",
    "gn:population":0,
    "gn:timezone":"Asia/Taipei",
    "iso:country":"TW",
    "name:und_x_variant":[
        "\u4e09\u53c9",
        "Sancha"
    ],
    "name:zho_x_preferred":[
        "San-ch\u2019a"
    ],
    "wof:name":"Sancha",
    "wof:placetype":"locality"
},
  "geometry": {"coordinates":[120.72478,24.13945],"type":"Point"}
}