{
  "type": "Feature",
  "properties": {
    "gn:admin1_code":"4.0",
    "gn:admin2_code":"TNN",
    "gn:admin3_code":"R02",
    "gn:admin4_code":"67000020017.0",
    "gn:asciiname":"Fanziliao",
    "gn:country_code":"TW",
    "gn:dem":4,
    "gn:feature_class":"P",
    "gn:feature_code":"PPL",
    "gn:name":"Fanziliao",
    "gn:population":0,
    "gn:timezone":"Asia/Taipei",
    "iso:country":"TW",
    "name:und_x_variant":[
        "Kao-liao",
        "Fanziliao",
        "Fanzihliao",
        "Fan-tzu-liao"
    ],
    "name:zho_x_preferred":[
        "\u756a\u5b50\u5bee"
    ],
    "wof:name":"Fanziliao",
    "wof:placetype":"locality"
},
  "geometry": {"coordinates":[120.23654999999999,23.30443],"type":"Point"}
}