{
  "type": "Feature",
  "properties": {
    "gn:admin1_code":"4.0",
    "gn:admin2_code":"CYQ",
    "gn:admin3_code":"Q15",
    "gn:admin4_code":"10010140015.0",
    "gn:asciiname":"Dayuan",
    "gn:country_code":"TW",
    "gn:dem":189,
    "gn:feature_class":"P",
    "gn:feature_code":"PPL",
    "gn:name":"Dayuan",
    "gn:population":0,
    "gn:timezone":"Asia/Taipei",
    "iso:country":"TW",
    "name:zho_x_preferred":[
        "\u5927\u5712"
    ],
    "name:zho_x_variant":[
        "Fu-y\u00fcan",
        "Ta-y\u00fcan"
    ],
    "wof:name":"Dayuan",
    "wof:placetype":"locality"
},
  "geometry": {"coordinates":[120.57402999999999,23.48777],"type":"Point"}
}