{
  "type": "Feature",
  "properties": {
    "gn:admin1_code":"4.0",
    "gn:admin2_code":"CYQ",
    "gn:admin3_code":"Q15",
    "gn:admin4_code":"10010140015.0",
    "gn:asciiname":"Dayuan",
    "gn:country_code":"TW",
    "gn:dem":189,
    "gn:feature_class":"P",
    "gn:feature_code":"PPL",
    "gn:name":"Dayuan",
    "gn:population":0,
    "gn:timezone":"Asia/Taipei",
    "iso:country":"TW",
    "name:ces_x_preferred":[
        "Ta-j\u00fcan"
    ],
    "name:deu_x_preferred":[
        "Dayuan"
    ],
    "name:ell_x_preferred":[
        "\u039d\u03c4\u03b1\u03b3\u03b9\u03bf\u03c5\u03ac\u03bd"
    ],
    "name:fas_x_preferred":[
        "\u062f\u0627\u06cc\u0648\u0627\u0646"
    ],
    "name:hye_x_preferred":[
        "\u054f\u0561\u0575\u0575\u0578\u0582\u0561\u0576"
    ],
    "name:ido_x_preferred":[
        "Ta-Yuan"
    ],
    "name:ind_x_preferred":[
        "Dayuan"
    ],
    "name:ita_x_preferred":[
        "Dayuan"
    ],
    "name:kir_x_preferred":[
        "\u0414\u0430\u0431\u0430\u043d \u043c\u0430\u043c\u043b\u0435\u043a\u0435\u0442\u0438"
    ],
    "name:lat_x_preferred":[
        "Taiuani"
    ],
    "name:lit_x_preferred":[
        "Dajuanas"
    ],
    "name:rus_x_preferred":[
        "\u0414\u0430\u0432\u0430\u043d\u044c"
    ],
    "name:ukr_x_preferred":[
        "\u0414\u0430\u044e\u0430\u043d\u044c"
    ],
    "name:uzb_x_preferred":[
        "Davan"
    ],
    "name:vie_x_preferred":[
        "\u0110\u1ea1i Uy\u00ean"
    ],
    "name:zho_x_preferred":[
        "\u5927\u5712"
    ],
    "name:zho_x_variant":[
        "Fu-y\u00fcan",
        "Ta-y\u00fcan"
    ],
    "wof:name":"Dayuan",
    "wof:placetype":"locality"
},
  "geometry": {"coordinates":[120.57402999999999,23.48777],"type":"Point"}
}