{
  "type": "Feature",
  "properties": {
    "gn:admin1_code":"3.0",
    "gn:admin2_code":"TPQ",
    "gn:admin3_code":"F18",
    "gn:admin4_code":"65000030042.0",
    "gn:asciiname":"Piwei",
    "gn:country_code":"TW",
    "gn:dem":20,
    "gn:feature_class":"P",
    "gn:feature_code":"PPL",
    "gn:name":"Piwei",
    "gn:population":0,
    "gn:timezone":"Asia/Taipei",
    "iso:country":"TW",
    "name:zho_x_preferred":[
        "\u57e4\u5c3e"
    ],
    "name:zho_x_variant":[
        "P\u2019i-wei"
    ],
    "wof:name":"Piwei",
    "wof:placetype":"locality"
},
  "geometry": {"coordinates":[121.49983,24.97823],"type":"Point"}
}