{
  "type": "Feature",
  "properties": {
    "gn:admin1_code":"02",
    "gn:admin2_code":"KHH",
    "gn:admin3_code":"E37",
    "gn:admin4_code":"64000370004.0",
    "gn:asciiname":"Mixiao",
    "gn:country_code":"TW",
    "gn:dem":669,
    "gn:feature_class":"P",
    "gn:feature_code":"PPL",
    "gn:name":"Mixiao",
    "gn:population":0,
    "gn:timezone":"Asia/Taipei",
    "iso:country":"TW",
    "name:und_x_variant":[
        "Mi-hsiao-she",
        "Mi-hsiao",
        "Mixiao"
    ],
    "wof:name":"Mixiao",
    "wof:placetype":"locality"
},
  "geometry": {"coordinates":[120.71666999999999,23.13333],"type":"Point"}
}