{
  "type": "Feature",
  "properties": {
    "gn:admin1_code":"4.0",
    "gn:admin2_code":"PEN",
    "gn:admin3_code":"X05",
    "gn:admin4_code":"10016050001.0",
    "gn:asciiname":"Yuzichang",
    "gn:country_code":"TW",
    "gn:dem":5,
    "gn:feature_class":"P",
    "gn:feature_code":"PPL",
    "gn:name":"Yuzichang",
    "gn:population":0,
    "gn:timezone":"Asia/Taipei",
    "iso:country":"TW",
    "name:und_x_variant":[
        "Yuzihchang"
    ],
    "name:zho_x_preferred":[
        "\u9b5a\u4ed4\u5834"
    ],
    "name:zho_x_variant":[
        "Y\u00fc-tzu-ch\u2019ang"
    ],
    "wof:name":"Yuzichang",
    "wof:placetype":"locality"
},
  "geometry": {"coordinates":[119.50806,23.35778],"type":"Point"}
}