{
  "type": "Feature",
  "properties": {
    "gn:admin1_code":"4.0",
    "gn:admin2_code":"MIA",
    "gn:admin3_code":"K14",
    "gn:admin4_code":"10005110005.0",
    "gn:asciiname":"Duchangkou",
    "gn:country_code":"TW",
    "gn:dem":309,
    "gn:feature_class":"P",
    "gn:feature_code":"PPL",
    "gn:name":"Duchangkou",
    "gn:population":0,
    "gn:timezone":"Asia/Taipei",
    "iso:country":"TW",
    "name:zho_x_preferred":[
        "\u90fd\u5834\u53e3"
    ],
    "name:zho_x_variant":[
        "Tu-ch\u2019ang-k\u2019ou"
    ],
    "wof:name":"Duchangkou",
    "wof:placetype":"locality"
},
  "geometry": {"coordinates":[121.0275,24.63167],"type":"Point"}
}