{
  "type": "Feature",
  "properties": {
    "gn:admin1_code":"4.0",
    "gn:admin2_code":"YUN",
    "gn:admin3_code":"P09",
    "gn:admin4_code":"10009090011.0",
    "gn:asciiname":"Yongji",
    "gn:country_code":"TW",
    "gn:dem":46,
    "gn:feature_class":"P",
    "gn:feature_code":"PPL",
    "gn:name":"Yongji",
    "gn:population":0,
    "gn:timezone":"Asia/Taipei",
    "iso:country":"TW",
    "name:und_x_variant":[
        "Yung-chi"
    ],
    "name:zho_x_preferred":[
        "\u6c38\u57fa"
    ],
    "name:zho_x_variant":[
        "T\u2019ieh-ch\u2019i-lu"
    ],
    "wof:name":"Yongji",
    "wof:placetype":"locality"
},
  "geometry": {"coordinates":[120.52611,23.7755],"type":"Point"}
}