{
  "type": "Feature",
  "properties": {
    "gn:admin1_code":"04",
    "gn:admin2_code":"CHA",
    "gn:admin3_code":"N24",
    "gn:admin4_code":"10007240010.0",
    "gn:asciiname":"Sigu",
    "gn:country_code":"TW",
    "gn:dem":8,
    "gn:feature_class":"P",
    "gn:feature_code":"PPL",
    "gn:name":"Sigu",
    "gn:population":0,
    "gn:timezone":"Asia/Taipei",
    "iso:country":"TW",
    "name:und_x_variant":[
        "Kung-kuan",
        "Sigu",
        "Sihgu",
        "Ssu-ku"
    ],
    "name:zho_x_preferred":[
        "Kung-kuan-ts\u2019un"
    ],
    "name:zho_x_variant":[
        "\u56db\u80a1"
    ],
    "wof:name":"Sigu",
    "wof:placetype":"locality"
},
  "geometry": {"coordinates":[120.29964,23.84055],"type":"Point"}
}