{
  "type": "Feature",
  "properties": {
    "gn:admin1_code":"04",
    "gn:admin2_code":"CHA",
    "gn:admin3_code":"N02",
    "gn:admin4_code":"10007020027.0",
    "gn:asciiname":"Caocaicuo",
    "gn:country_code":"TW",
    "gn:dem":6,
    "gn:feature_class":"P",
    "gn:feature_code":"PPL",
    "gn:name":"Caocaicuo",
    "gn:population":0,
    "gn:timezone":"Asia/Taipei",
    "iso:country":"TW",
    "name:und_x_variant":[
        "Ts\u2019ao-ts\u2019ai-ts\u2019o"
    ],
    "wof:name":"Caocaicuo",
    "wof:placetype":"locality"
},
  "geometry": {"coordinates":[120.45,24.08333],"type":"Point"}
}