{
  "type": "Feature",
  "properties": {
    "gn:admin1_code":"04",
    "gn:admin2_code":"TXG",
    "gn:admin3_code":"B28",
    "gn:admin4_code":"66000280001.0",
    "gn:asciiname":"Wayaozi",
    "gn:country_code":"TW",
    "gn:dem":39,
    "gn:feature_class":"P",
    "gn:feature_code":"PPL",
    "gn:name":"Wayaozi",
    "gn:population":0,
    "gn:timezone":"Asia/Taipei",
    "iso:country":"TW",
    "name:und_x_variant":[
        "Wa-yao",
        "\u74e6\u7464\u4ed4",
        "Wayaozih",
        "Wayaozi",
        "Wa-yao-tzu"
    ],
    "wof:name":"Wayaozi",
    "wof:placetype":"locality"
},
  "geometry": {"coordinates":[120.66694,24.09404],"type":"Point"}
}