{
  "type": "Feature",
  "properties": {
    "gn:admin1_code":"3.0",
    "gn:admin2_code":"TPQ",
    "gn:admin3_code":"F31",
    "gn:admin4_code":"65000220007.0",
    "gn:asciiname":"Ergu",
    "gn:country_code":"TW",
    "gn:dem":259,
    "gn:feature_class":"P",
    "gn:feature_code":"PPL",
    "gn:name":"Ergu",
    "gn:population":0,
    "gn:timezone":"Asia/Taipei",
    "iso:country":"TW",
    "name:und_x_variant":[
        "Erh-ku"
    ],
    "name:zho_x_preferred":[
        "\u4e8c\u80a1"
    ],
    "wof:name":"Ergu",
    "wof:placetype":"locality"
},
  "geometry": {"coordinates":[121.58004,25.24415],"type":"Point"}
}