{
  "type": "Feature",
  "properties": {
    "gn:admin1_code":"04",
    "gn:admin2_code":"TTT",
    "gn:admin3_code":"V07",
    "gn:admin4_code":"10014070003.0",
    "gn:asciiname":"Donghe",
    "gn:country":"TW",
    "gn:country_code":"TW",
    "gn:dem":38,
    "gn:feature_class":"P",
    "gn:feature_code":"PPL",
    "gn:name":"Donghe",
    "gn:population":0,
    "gn:timezone":"Asia/Taipei",
    "iso:country":"TW",
    "name:deu_x_preferred":[
        "Donghe"
    ],
    "name:eng_x_preferred":[
        "Donghe"
    ],
    "name:eng_x_variant":[
        "Donghe Village"
    ],
    "name:hak_x_preferred":[
        "T\u00fbng-h\u00f2-hi\u00f4ng"
    ],
    "name:jpn_x_preferred":[
        "\u6771\u6cb3\u90f7"
    ],
    "name:kor_x_preferred":[
        "\ub465\ud5c8\ud5a5"
    ],
    "name:und_x_variant":[
        "Ta-ma",
        "Ta-ma-wu-tu",
        "Tung-ho"
    ],
    "name:vie_x_preferred":[
        "\u0110\u00f4ng H\u00e0"
    ],
    "name:zho_tw_x_preferred":[
        "\u6771\u6cb3\u6751"
    ],
    "name:zho_x_preferred":[
        "Ta-ma-wu-k\u2019u"
    ],
    "name:zho_x_variant":[
        "Tung-ho-ts\u2019un",
        "\u6771\u6cb3",
        "\u6771\u6cb3\u9109"
    ],
    "qs:name":"\u6771\u6cb3\u6751",
    "qs:name_adm0":"\u81fa\u7063",
    "qs:name_adm1":"\u53f0\u6771\u7e23",
    "qs:photos":311,
    "qs:photos_1k":63,
    "qs:photos_9k":1,
    "qs:photos_9r":5,
    "qs:photos_all":311,
    "qs:photos_sr":5,
    "qs:placetype":"Town",
    "qs:pop_sr":"0",
    "wof:name":"Donghe",
    "wof:placetype":"locality"
},
  "geometry": {"coordinates":[121.304419,22.96979],"type":"Point"}
}