{
  "type": "Feature",
  "properties": {
    "gn:admin1_code":"4.0",
    "gn:admin2_code":"TTT",
    "gn:admin3_code":"V15",
    "gn:admin4_code":"10014140004.0",
    "gn:asciiname":"Binmao",
    "gn:country_code":"TW",
    "gn:dem":32,
    "gn:feature_class":"P",
    "gn:feature_code":"PPL",
    "gn:name":"Binmao",
    "gn:population":0,
    "gn:timezone":"Asia/Taipei",
    "iso:country":"TW",
    "name:und_x_variant":[
        "Pin-mao"
    ],
    "name:zho_x_preferred":[
        "\u8cd3\u8302"
    ],
    "wof:name":"Binmao",
    "wof:placetype":"locality"
},
  "geometry": {"coordinates":[120.96111000000001,22.53167],"type":"Point"}
}