{
  "type": "Feature",
  "properties": {
    "gn:admin1_code":"04",
    "gn:admin2_code":"CHA",
    "gn:admin3_code":"N07",
    "gn:admin4_code":"10007120016.0",
    "gn:asciiname":"Sikuaicuo",
    "gn:country_code":"TW",
    "gn:dem":60,
    "gn:feature_class":"P",
    "gn:feature_code":"PPL",
    "gn:name":"Sikuaicuo",
    "gn:population":0,
    "gn:timezone":"Asia/Taipei",
    "iso:country":"TW",
    "name:und_x_variant":[
        "Sihkuaicuo",
        "Sikuaicuo"
    ],
    "name:zho_x_preferred":[
        "\u56db\u584a\u539d"
    ],
    "name:zho_x_variant":[
        "Ssu-k\u2019uai-ts\u2019o"
    ],
    "wof:name":"Sikuaicuo",
    "wof:placetype":"locality"
},
  "geometry": {"coordinates":[120.596,23.83415],"type":"Point"}
}