{
  "type": "Feature",
  "properties": {
    "gn:admin1_code":"4.0",
    "gn:admin2_code":"PIF",
    "gn:admin3_code":"T18",
    "gn:admin4_code":"10013180001.0",
    "gn:asciiname":"Houbi",
    "gn:country_code":"TW",
    "gn:dem":8,
    "gn:feature_class":"P",
    "gn:feature_code":"PPL",
    "gn:name":"Houbi",
    "gn:population":0,
    "gn:timezone":"Asia/Taipei",
    "iso:country":"TW",
    "name:und_x_variant":[
        "Hou-pi",
        "Houbi"
    ],
    "name:zho_x_preferred":[
        "Hou-pi-ts\u2019o"
    ],
    "name:zho_x_variant":[
        "\u5f8c\u58c1"
    ],
    "wof:name":"Houbi",
    "wof:placetype":"locality"
},
  "geometry": {"coordinates":[120.51339,22.52208],"type":"Point"}
}