{
  "type": "Feature",
  "properties": {
    "gn:admin1_code":"04",
    "gn:admin2_code":"TNN",
    "gn:admin3_code":"R12",
    "gn:admin4_code":"67000120016.0",
    "gn:asciiname":"Dongshiliao",
    "gn:country_code":"TW",
    "gn:dem":6,
    "gn:feature_class":"P",
    "gn:feature_code":"PPL",
    "gn:name":"Dongshiliao",
    "gn:population":0,
    "gn:timezone":"Asia/Taipei",
    "iso:country":"TW",
    "name:und_x_variant":[
        "Tung-shih-liao",
        "Dongshiliao",
        "Tung-liao",
        "Dongshihliao"
    ],
    "name:zho_x_preferred":[
        "\u6771\u52e2\u5bee"
    ],
    "wof:name":"Dongshiliao",
    "wof:placetype":"locality"
},
  "geometry": {"coordinates":[120.15806000000001,23.1425],"type":"Point"}
}