{
  "type": "Feature",
  "properties": {
    "gn:admin1_code":"4.0",
    "gn:admin2_code":"TNN",
    "gn:admin3_code":"R15",
    "gn:admin4_code":"67000160017.0",
    "gn:asciiname":"Qingkunshen",
    "gn:country_code":"TW",
    "gn:dem":6,
    "gn:feature_class":"P",
    "gn:feature_code":"PPL",
    "gn:name":"Qingkunshen",
    "gn:population":0,
    "gn:timezone":"Asia/Taipei",
    "iso:country":"TW",
    "name:und_x_variant":[
        "Kunsen",
        "Cingkunshen",
        "Kun-shen",
        "Qingkunshen"
    ],
    "name:zho_x_preferred":[
        "\u9752\u9be4\u9bd3"
    ],
    "name:zho_x_variant":[
        "Kun-pa-ts\u2019un",
        "K\u2019un-pa",
        "Ch\u2019ing-k\u2019un-shen"
    ],
    "wof:name":"Qingkunshen",
    "wof:placetype":"locality"
},
  "geometry": {"coordinates":[120.08861,23.18972],"type":"Point"}
}