{
  "type": "Feature",
  "properties": {
    "gn:admin1_code":"4.0",
    "gn:admin2_code":"TXG",
    "gn:admin3_code":"B08",
    "gn:admin4_code":"66000080015.0",
    "gn:asciiname":"Wayao",
    "gn:country_code":"TW",
    "gn:dem":448,
    "gn:feature_class":"P",
    "gn:feature_code":"PPL",
    "gn:name":"Wayao",
    "gn:population":0,
    "gn:timezone":"Asia/Taipei",
    "iso:country":"TW",
    "name:und_x_variant":[
        "Wa-yao"
    ],
    "name:zho_x_preferred":[
        "\u74e6\u78d8"
    ],
    "wof:name":"Wayao",
    "wof:placetype":"locality"
},
  "geometry": {"coordinates":[120.78546,24.20707],"type":"Point"}
}