{
  "type": "Feature",
  "properties": {
    "gn:admin1_code":"4.0",
    "gn:admin2_code":"TAO",
    "gn:admin3_code":"H08",
    "gn:admin4_code":"68000080013.0",
    "gn:asciiname":"Wufenluxia",
    "gn:country_code":"TW",
    "gn:dem":123,
    "gn:feature_class":"P",
    "gn:feature_code":"PPL",
    "gn:name":"Wufenluxia",
    "gn:population":0,
    "gn:timezone":"Asia/Taipei",
    "iso:country":"TW",
    "name:und_x_variant":[
        "Wufenlusia",
        "Wu-fen-lu-hsia"
    ],
    "name:zho_x_preferred":[
        "\u4e94\u5206\u8def\u4e0b"
    ],
    "wof:name":"Wufenluxia",
    "wof:placetype":"locality"
},
  "geometry": {"coordinates":[121.27086,24.95586],"type":"Point"}
}