{
  "type": "Feature",
  "properties": {
    "gn:admin1_code":"2.0",
    "gn:admin2_code":"KHH",
    "gn:admin3_code":"E21",
    "gn:admin4_code":"64000210007.0",
    "gn:asciiname":"Chegualin",
    "gn:country_code":"TW",
    "gn:dem":87,
    "gn:feature_class":"P",
    "gn:feature_code":"PPL",
    "gn:name":"Chegualin",
    "gn:population":0,
    "gn:timezone":"Asia/Taipei",
    "iso:country":"TW",
    "name:zho_x_preferred":[
        "\u8eca\u74dc\u6797"
    ],
    "name:zho_x_variant":[
        "Ch\u2019e-kua-lin"
    ],
    "wof:name":"Chegualin",
    "wof:placetype":"locality"
},
  "geometry": {"coordinates":[120.39028,22.79694],"type":"Point"}
}