{
  "type": "Feature",
  "properties": {
    "gn:admin1_code":"04",
    "gn:admin2_code":"TAO",
    "gn:admin3_code":"H04",
    "gn:admin4_code":"68000040010.0",
    "gn:asciiname":"Yuemeishanxia",
    "gn:country_code":"TW",
    "gn:dem":189,
    "gn:feature_class":"P",
    "gn:feature_code":"PPL",
    "gn:name":"Yuemeishanxia",
    "gn:population":0,
    "gn:timezone":"Asia/Taipei",
    "iso:country":"TW",
    "name:und_x_variant":[
        "Yuemeishansia"
    ],
    "name:zho_x_preferred":[
        "\u6708\u7709\u5c71\u4e0b"
    ],
    "name:zho_x_variant":[
        "Y\u00fceh-mei",
        "Y\u00fceh-mei-shan-hsia"
    ],
    "wof:name":"Yuemeishanxia",
    "wof:placetype":"locality"
},
  "geometry": {"coordinates":[121.15639,24.91667],"type":"Point"}
}