{
  "type": "Feature",
  "properties": {
    "gn:admin1_code":"4.0",
    "gn:admin2_code":"TNN",
    "gn:admin3_code":"R22",
    "gn:admin4_code":"67000220001.0",
    "gn:asciiname":"Rende",
    "gn:country_code":"TW",
    "gn:dem":13,
    "gn:feature_class":"P",
    "gn:feature_code":"PPL",
    "gn:name":"Rende",
    "gn:population":0,
    "gn:timezone":"Asia/Taipei",
    "iso:country":"TW",
    "name:ara_x_preferred":[
        "\u0631\u064a\u0646\u062f\u064a"
    ],
    "name:azb_x_preferred":[
        "\u0631\u0646\u062f\u0647"
    ],
    "name:bcl_x_preferred":[
        "Rende"
    ],
    "name:bul_x_preferred":[
        "\u0420\u0435\u043d\u0434\u0435"
    ],
    "name:cat_x_preferred":[
        "Rende"
    ],
    "name:ceb_x_preferred":[
        "Rende"
    ],
    "name:deu_x_preferred":[
        "Rende"
    ],
    "name:epo_x_preferred":[
        "Rende"
    ],
    "name:est_x_preferred":[
        "Rende"
    ],
    "name:eus_x_preferred":[
        "Rende"
    ],
    "name:fas_x_preferred":[
        "\u0631\u0646\u062f\u0647"
    ],
    "name:fra_x_preferred":[
        "Rende"
    ],
    "name:hun_x_preferred":[
        "Rende"
    ],
    "name:hye_x_preferred":[
        "\u054c\u0565\u0576\u0564\u0565"
    ],
    "name:ina_x_preferred":[
        "Rende"
    ],
    "name:ita_x_preferred":[
        "Rende"
    ],
    "name:jpn_x_preferred":[
        "\u30ec\u30f3\u30c7"
    ],
    "name:kaz_x_preferred":[
        "\u0420\u0435\u043d\u0434\u0435"
    ],
    "name:lat_x_preferred":[
        "Arintha"
    ],
    "name:lit_x_preferred":[
        "Rend\u0117"
    ],
    "name:lmo_x_preferred":[
        "Rende"
    ],
    "name:msa_x_preferred":[
        "Rende"
    ],
    "name:nap_x_preferred":[
        "Rende"
    ],
    "name:nld_x_preferred":[
        "Rende"
    ],
    "name:nno_x_preferred":[
        "Rende"
    ],
    "name:pms_x_preferred":[
        "Rende"
    ],
    "name:pol_x_preferred":[
        "Rende"
    ],
    "name:por_x_preferred":[
        "Rende"
    ],
    "name:ron_x_preferred":[
        "Rende"
    ],
    "name:rus_x_preferred":[
        "\u0420\u0435\u043d\u0434\u0435"
    ],
    "name:scn_x_preferred":[
        "Renna"
    ],
    "name:spa_x_preferred":[
        "Rende"
    ],
    "name:srp_x_preferred":[
        "\u0420\u0435\u043d\u0434\u0435"
    ],
    "name:tur_x_preferred":[
        "Rende"
    ],
    "name:ukr_x_preferred":[
        "\u0420\u0435\u043d\u0434\u0435"
    ],
    "name:und_x_variant":[
        "Jen-te-ts\u2019un",
        "Jen-te"
    ],
    "name:uzb_x_preferred":[
        "Rende"
    ],
    "name:vol_x_preferred":[
        "Rende"
    ],
    "name:war_x_preferred":[
        "Rende"
    ],
    "wof:name":"Rende",
    "wof:placetype":"locality"
},
  "geometry": {"coordinates":[120.33333,23.11667000000001],"type":"Point"}
}