{
  "type": "Feature",
  "properties": {
    "gn:admin1_code":"4.0",
    "gn:admin2_code":"TNN",
    "gn:admin3_code":"R22",
    "gn:admin4_code":"67000220001.0",
    "gn:asciiname":"Rende",
    "gn:country_code":"TW",
    "gn:dem":13,
    "gn:feature_class":"P",
    "gn:feature_code":"PPL",
    "gn:name":"Rende",
    "gn:population":0,
    "gn:timezone":"Asia/Taipei",
    "iso:country":"TW",
    "name:und_x_variant":[
        "Jen-te-ts\u2019un",
        "Jen-te",
        "Rende"
    ],
    "wof:name":"Rende",
    "wof:placetype":"locality"
},
  "geometry": {"coordinates":[120.33333,23.11667000000001],"type":"Point"}
}