{
  "type": "Feature",
  "properties": {
    "iso:country":"TW",
    "qs:name":"\u5c04\u5bee\u6751",
    "qs:name_adm0":"\u81fa\u7063",
    "qs:name_adm1":"\u5c4f\u6771\u7e23",
    "qs:photos":3767,
    "qs:photos_1k":763,
    "qs:photos_9k":17,
    "qs:photos_9r":12,
    "qs:photos_all":3767,
    "qs:photos_sr":21,
    "qs:placetype":"Town",
    "qs:pop_sr":"0",
    "wof:name":"\u5c04\u5bee\u6751",
    "wof:placetype":"locality"
},
  "geometry": {"coordinates":[120.698397,22.046477],"type":"Point"}
}