{
  "type": "Feature",
  "properties": {
    "gn:admin1_code":"2.0",
    "gn:admin2_code":"KHH",
    "gn:admin3_code":"E25",
    "gn:admin4_code":"64000250008.0",
    "gn:asciiname":"Hunei",
    "gn:country_code":"TW",
    "gn:dem":11,
    "gn:feature_class":"P",
    "gn:feature_code":"PPL",
    "gn:name":"Hunei",
    "gn:population":0,
    "gn:timezone":"Asia/Taipei",
    "iso:country":"TW",
    "name:und_x_variant":[
        "Hu-nei"
    ],
    "name:zho_x_preferred":[
        "Hu-nei-ts\u2019un"
    ],
    "name:zho_x_variant":[
        "\u6e56\u5167"
    ],
    "wof:name":"Hunei",
    "wof:placetype":"locality"
},
  "geometry": {"coordinates":[120.23667,22.88472],"type":"Point"}
}