{
  "type": "Feature",
  "properties": {
    "gn:admin1_code":"4.0",
    "gn:admin2_code":"CYQ",
    "gn:admin3_code":"Q12",
    "gn:admin4_code":"10010010011.0",
    "gn:asciiname":"Xinan",
    "gn:country_code":"TW",
    "gn:dem":16,
    "gn:feature_class":"P",
    "gn:feature_code":"PPL",
    "gn:name":"Xinan",
    "gn:population":0,
    "gn:timezone":"Asia/Taipei",
    "iso:country":"TW",
    "name:und_x_variant":[
        "Sinan",
        "Hsi-nan"
    ],
    "name:zho_x_preferred":[
        "Ch\u2019i-nan"
    ],
    "name:zho_x_variant":[
        "Hsi-nan-ts\u2019un",
        "\u6eaa\u5357"
    ],
    "wof:name":"Xinan",
    "wof:placetype":"locality"
},
  "geometry": {"coordinates":[120.33582,23.50509],"type":"Point"}
}