{
  "type": "Feature",
  "properties": {
    "gn:admin1_code":"4.0",
    "gn:admin2_code":"CYQ",
    "gn:admin3_code":"Q08",
    "gn:admin4_code":"10010080019.0",
    "gn:asciiname":"Zhanfucuo",
    "gn:country_code":"TW",
    "gn:dem":9,
    "gn:feature_class":"P",
    "gn:feature_code":"PPL",
    "gn:name":"Zhanfucuo",
    "gn:population":0,
    "gn:timezone":"Asia/Taipei",
    "iso:country":"TW",
    "name:und_x_variant":[
        "Jhanfucuo",
        "Zhanfucuo"
    ],
    "name:zho_x_preferred":[
        "Chan-ts\u2019o-ts\u2019o"
    ],
    "name:zho_x_variant":[
        "\u5360\u5bcc\u539d",
        "Cheng-i-ts\u2019un",
        "Chan-fu-ts\u2019o"
    ],
    "wof:name":"Zhanfucuo",
    "wof:placetype":"locality"
},
  "geometry": {"coordinates":[120.2547,23.4905],"type":"Point"}
}