{
  "type": "Feature",
  "properties": {
    "gn:admin1_code":"2.0",
    "gn:admin2_code":"KHH",
    "gn:admin3_code":"E32",
    "gn:admin4_code":"64000320006.0",
    "gn:asciiname":"Liugui",
    "gn:country_code":"TW",
    "gn:dem":255,
    "gn:feature_class":"P",
    "gn:feature_code":"PPL",
    "gn:name":"Liugui",
    "gn:population":0,
    "gn:timezone":"Asia/Taipei",
    "iso:country":"TW",
    "name:und_x_variant":[
        "Liouguei",
        "Liu-kuei"
    ],
    "name:zho_x_preferred":[
        "\u516d\u9f9c"
    ],
    "wof:name":"Liugui",
    "wof:placetype":"locality"
},
  "geometry": {"coordinates":[120.63443999999998,22.99861],"type":"Point"}
}