{
  "type": "Feature",
  "properties": {
    "gn:admin1_code":"4.0",
    "gn:admin2_code":"TTT",
    "gn:admin3_code":"V10",
    "gn:admin4_code":"10014060002.0",
    "gn:asciiname":"Zhangzhangba",
    "gn:country_code":"TW",
    "gn:dem":265,
    "gn:feature_class":"P",
    "gn:feature_code":"PPL",
    "gn:name":"Zhangzhangba",
    "gn:population":0,
    "gn:timezone":"Asia/Taipei",
    "iso:country":"TW",
    "name:und_x_variant":[
        "Chang-chang-pa"
    ],
    "wof:name":"Zhangzhangba",
    "wof:placetype":"locality"
},
  "geometry": {"coordinates":[121.23333,23.13333],"type":"Point"}
}