{
  "type": "Feature",
  "properties": {
    "gn:admin1_code":"4.0",
    "gn:admin2_code":"HUA",
    "gn:admin3_code":"U10",
    "gn:admin4_code":"10015100012.0",
    "gn:asciiname":"Choushuigou",
    "gn:country_code":"TW",
    "gn:dem":309,
    "gn:feature_class":"P",
    "gn:feature_code":"PPL",
    "gn:name":"Choushuigou",
    "gn:population":0,
    "gn:timezone":"Asia/Taipei",
    "iso:country":"TW",
    "name:und_x_variant":[
        "Choushueigou"
    ],
    "name:zho_x_preferred":[
        "\u81ed\u6c34\u6e9d"
    ],
    "name:zho_x_variant":[
        "Ch\u2019ou-shui-kou"
    ],
    "wof:name":"Choushuigou",
    "wof:placetype":"locality"
},
  "geometry": {"coordinates":[121.26069,23.13898],"type":"Point"}
}