{
  "type": "Feature",
  "properties": {
    "gn:admin1_code":"2.0",
    "gn:admin2_code":"KHH",
    "gn:admin3_code":"E02",
    "gn:asciiname":"Fu-hsing",
    "gn:cc2":"TW",
    "gn:country_code":"TW",
    "gn:dem":6,
    "gn:feature_class":"P",
    "gn:feature_code":"PPL",
    "gn:name":"Fu-hsing",
    "gn:population":0,
    "gn:timezone":"Asia/Taipei",
    "iso:country":"TW",
    "name:und_x_variant":[
        "P'ing-ho-t'ing",
        "Fu-hsing-li"
    ],
    "wof:name":"Fu-hsing",
    "wof:placetype":"locality"
},
  "geometry": {"coordinates":[120.26667,22.61667000000001],"type":"Point"}
}