{
  "type": "Feature",
  "properties": {
    "gn:admin1_code":"03",
    "gn:admin2_code":"TPQ",
    "gn:admin3_code":"F25",
    "gn:admin4_code":"65000270007.0",
    "gn:asciiname":"Bayan",
    "gn:country_code":"TW",
    "gn:dem":309,
    "gn:feature_class":"P",
    "gn:feature_code":"PPL",
    "gn:name":"Bayan",
    "gn:population":0,
    "gn:timezone":"Asia/Taipei",
    "iso:country":"TW",
    "name:ara_x_preferred":[
        "\u0627\u0644\u0628\u064a\u0627\u0646"
    ],
    "name:aze_x_preferred":[
        "Bayan"
    ],
    "name:cat_x_preferred":[
        "Bayan"
    ],
    "name:ceb_x_preferred":[
        "Bayan"
    ],
    "name:deu_x_preferred":[
        "Bayan"
    ],
    "name:fra_x_preferred":[
        "Bayan"
    ],
    "name:glg_x_preferred":[
        "Baian"
    ],
    "name:ind_x_preferred":[
        "Bayan"
    ],
    "name:ita_x_preferred":[
        "Bayan"
    ],
    "name:jpn_x_preferred":[
        "\u30d0\u30e4\u30f3"
    ],
    "name:kat_x_preferred":[
        "\u10d1\u10d0\u10d8\u10d0\u10dc\u10d8"
    ],
    "name:kaz_x_preferred":[
        "\u0411\u0430\u044f\u043d"
    ],
    "name:mlg_x_preferred":[
        "Bayan"
    ],
    "name:nld_x_preferred":[
        "Bayan"
    ],
    "name:nor_x_preferred":[
        "Bayan"
    ],
    "name:rus_x_preferred":[
        "\u0411\u0430\u044f\u043d"
    ],
    "name:swe_x_preferred":[
        "Bayan"
    ],
    "name:tgl_x_preferred":[
        "Bayan"
    ],
    "name:tur_x_preferred":[
        "Bayan"
    ],
    "name:ukr_x_preferred":[
        "\u0411\u0430\u044f\u043d"
    ],
    "name:und_x_variant":[
        "Pa-yen"
    ],
    "name:zho_x_preferred":[
        "San-ch\u2019ung-chiao"
    ],
    "name:zho_x_variant":[
        "\u516b\u7159"
    ],
    "wof:name":"Bayan",
    "wof:placetype":"locality"
},
  "geometry": {"coordinates":[121.58721,25.19168],"type":"Point"}
}