{
  "type": "Feature",
  "properties": {
    "gn:admin1_code":"03",
    "gn:admin2_code":"TPQ",
    "gn:admin3_code":"F25",
    "gn:admin4_code":"65000270007.0",
    "gn:asciiname":"Bayan",
    "gn:country_code":"TW",
    "gn:dem":309,
    "gn:feature_class":"P",
    "gn:feature_code":"PPL",
    "gn:name":"Bayan",
    "gn:population":0,
    "gn:timezone":"Asia/Taipei",
    "iso:country":"TW",
    "name:und_x_variant":[
        "Pa-yen"
    ],
    "name:zho_x_preferred":[
        "San-ch\u2019ung-chiao"
    ],
    "name:zho_x_variant":[
        "\u516b\u7159"
    ],
    "wof:name":"Bayan",
    "wof:placetype":"locality"
},
  "geometry": {"coordinates":[121.58721,25.19168],"type":"Point"}
}