{
  "type": "Feature",
  "properties": {
    "iso:country":"TW",
    "name:eng_x_preferred":[
        "Ashina District"
    ],
    "name:jpn_x_preferred":[
        "\u82a6\u54c1\u90e1"
    ],
    "name:zho_x_preferred":[
        "\u8606\u54c1\u90e1"
    ],
    "qs:name":"\u5354\u548c\u6751",
    "qs:name_adm0":"\u81fa\u7063",
    "qs:name_adm1":"\u5f70\u5316\u7e23",
    "qs:photos":43,
    "qs:photos_1k":9,
    "qs:photos_9k":1,
    "qs:photos_9r":2,
    "qs:photos_all":43,
    "qs:photos_sr":2,
    "qs:placetype":"Town",
    "qs:pop_sr":"0",
    "wd:wordcount":775,
    "wof:name":"\u5354\u548c\u6751",
    "wof:placetype":"locality"
},
  "geometry": {"coordinates":[120.610957,23.932897],"type":"Point"}
}