{
  "type": "Feature",
  "properties": {
    "gn:admin1_code":"04",
    "gn:admin2_code":"ILA",
    "gn:admin3_code":"G02",
    "gn:admin4_code":"10002040006.0",
    "gn:asciiname":"Wai'ao",
    "gn:country_code":"TW",
    "gn:dem":9,
    "gn:feature_class":"P",
    "gn:feature_code":"PPL",
    "gn:name":"Wai\u2019ao",
    "gn:population":0,
    "gn:timezone":"Asia/Taipei",
    "iso:country":"TW",
    "name:und_x_variant":[
        "Wai-ao-li",
        "Wai-ao"
    ],
    "name:zho_x_preferred":[
        "\u5916\u6fb3"
    ],
    "name:zho_x_variant":[
        "Wai\u2019ao"
    ],
    "wof:name":"Wai'ao",
    "wof:placetype":"locality"
},
  "geometry": {"coordinates":[121.84833,24.88583],"type":"Point"}
}