{
  "type": "Feature",
  "properties": {
    "gn:admin1_code":"4.0",
    "gn:admin2_code":"NAN",
    "gn:admin3_code":"M13",
    "gn:admin4_code":"10008130004.0",
    "gn:asciiname":"Qinglonggu",
    "gn:country_code":"TW",
    "gn:dem":923,
    "gn:feature_class":"P",
    "gn:feature_code":"PPL",
    "gn:name":"Qinglonggu",
    "gn:population":0,
    "gn:timezone":"Asia/Taipei",
    "iso:country":"TW",
    "name:und_x_variant":[
        "Cinglonggu",
        "Qinglonggu"
    ],
    "name:zho_x_preferred":[
        "\u9752\u9f8d\u8c37"
    ],
    "name:zho_x_variant":[
        "Ch\u2019ing-lung-ku"
    ],
    "wof:name":"Qinglonggu",
    "wof:placetype":"locality"
},
  "geometry": {"coordinates":[121.03943999999998,24.07833],"type":"Point"}
}