{
  "type": "Feature",
  "properties": {
    "gn:admin1_code":"4.0",
    "gn:admin2_code":"ILA",
    "gn:admin3_code":"G11",
    "gn:admin4_code":"10002110006.0",
    "gn:asciiname":"Zhinao",
    "gn:country_code":"TW",
    "gn:dem":330,
    "gn:feature_class":"P",
    "gn:feature_code":"PPL",
    "gn:name":"Zhinao",
    "gn:population":0,
    "gn:timezone":"Asia/Taipei",
    "iso:country":"TW",
    "name:und_x_variant":[
        "Jhihnao",
        "Zhinao",
        "Chih-nao"
    ],
    "name:zho_x_preferred":[
        "\u667a\u8166"
    ],
    "wof:name":"Zhinao",
    "wof:placetype":"locality"
},
  "geometry": {"coordinates":[121.51849,24.59074],"type":"Point"}
}