{
  "type": "Feature",
  "properties": {
    "gn:admin1_code":"4.0",
    "gn:admin2_code":"PIF",
    "gn:admin3_code":"T01",
    "gn:admin4_code":"10013010071.0",
    "gn:asciiname":"Chonglan",
    "gn:country_code":"TW",
    "gn:dem":29,
    "gn:feature_class":"P",
    "gn:feature_code":"PPL",
    "gn:name":"Chonglan",
    "gn:population":0,
    "gn:timezone":"Asia/Taipei",
    "iso:country":"TW",
    "name:und_x_variant":[
        "Chonglan"
    ],
    "name:zho_x_preferred":[
        "T\u2019ien-t\u2019ing"
    ],
    "name:zho_x_variant":[
        "Ch\u2019ung-lan-li",
        "Ch\u2019ung-lan",
        "\u5d07\u862d"
    ],
    "wof:name":"Chonglan",
    "wof:placetype":"locality"
},
  "geometry": {"coordinates":[120.48502000000001,22.69255],"type":"Point"}
}