{
  "type": "Feature",
  "properties": {
    "gn:admin1_code":"4.0",
    "gn:admin2_code":"TPE",
    "gn:admin3_code":"A13",
    "gn:admin4_code":"63000090018.0",
    "gn:asciiname":"Jiantou",
    "gn:country_code":"TW",
    "gn:dem":79,
    "gn:feature_class":"P",
    "gn:feature_code":"PPL",
    "gn:name":"Jiantou",
    "gn:population":0,
    "gn:timezone":"Asia/Taipei",
    "iso:country":"TW",
    "name:und_x_variant":[
        "Hou-shan",
        "Jiantou"
    ],
    "name:zho_x_preferred":[
        "\u5c16\u982d"
    ],
    "name:zho_x_variant":[
        "Chien-t\u2019ou"
    ],
    "wof:name":"Jiantou",
    "wof:placetype":"locality"
},
  "geometry": {"coordinates":[121.59553,25.02228],"type":"Point"}
}