{
  "type": "Feature",
  "properties": {
    "gn:admin1_code":"4.0",
    "gn:admin2_code":"HSQ",
    "gn:admin3_code":"O03",
    "gn:admin4_code":"10018030011.0",
    "gn:asciiname":"Dapingding",
    "gn:country_code":"TW",
    "gn:dem":52,
    "gn:feature_class":"P",
    "gn:feature_code":"PPL",
    "gn:name":"Dapingding",
    "gn:population":0,
    "gn:timezone":"Asia/Taipei",
    "iso:country":"TW",
    "name:zho_x_preferred":[
        "\u5927\u576a\u9802"
    ],
    "name:zho_x_variant":[
        "Ta-p\u2019ing-ting"
    ],
    "wof:name":"Dapingding",
    "wof:placetype":"locality"
},
  "geometry": {"coordinates":[120.92889,24.78278],"type":"Point"}
}