{
  "type": "Feature",
  "properties": {
    "gn:admin1_code":"3.0",
    "gn:admin2_code":"TPQ",
    "gn:admin3_code":"F10",
    "gn:admin4_code":"65000200001.0",
    "gn:asciiname":"Renliban",
    "gn:country_code":"TW",
    "gn:dem":184,
    "gn:feature_class":"P",
    "gn:feature_code":"PPL",
    "gn:name":"Renliban",
    "gn:population":0,
    "gn:timezone":"Asia/Taipei",
    "iso:country":"TW",
    "name:und_x_variant":[
        "Jen-li-fan",
        "Renliban",
        "Jen-li-pan"
    ],
    "name:zho_x_preferred":[
        "\u4ec1\u91cc\u5742"
    ],
    "wof:name":"Renliban",
    "wof:placetype":"locality"
},
  "geometry": {"coordinates":[121.6917,24.93318],"type":"Point"}
}