{
  "type": "Feature",
  "properties": {
    "iso:country":"TW",
    "qs:name":"\u4e2d\u8208\u91cc",
    "qs:name_adm0":"\u81fa\u7063",
    "qs:name_adm1":"\u57fa\u9686\u5e02",
    "qs:photos":90,
    "qs:photos_1k":18,
    "qs:photos_9k":1,
    "qs:photos_9r":3,
    "qs:photos_all":90,
    "qs:photos_sr":3,
    "qs:placetype":"Suburb",
    "qs:pop_sr":"0",
    "wd:wordcount":334,
    "wof:name":"\u4e2d\u8208\u91cc",
    "wof:placetype":"neighbourhood"
},
  "geometry": {"coordinates":[121.740145,25.138291],"type":"Point"}
}