{
  "type": "Feature",
  "properties": {
    "iso:country":"TW",
    "qs:name":"\u5e73\u660c\u91cc",
    "qs:name_adm0":"\u81fa\u7063",
    "qs:name_adm1":"\u53f0\u4e2d\u5e02",
    "qs:photos":59,
    "qs:photos_1k":12,
    "qs:photos_9k":1,
    "qs:photos_9r":2,
    "qs:photos_all":59,
    "qs:photos_sr":2,
    "qs:placetype":"Suburb",
    "qs:pop_sr":"0",
    "wd:wordcount":198,
    "wof:name":"\u5e73\u660c\u91cc",
    "wof:placetype":"neighbourhood"
},
  "geometry": {"coordinates":[120.69199999999999,24.169121],"type":"Point"}
}