{
  "type": "Feature",
  "properties": {
    "gn:admin1_code":"4.0",
    "gn:admin2_code":"TAO",
    "gn:admin3_code":"H12",
    "gn:admin4_code":"68000120014.0",
    "gn:asciiname":"Lunping",
    "gn:country_code":"TW",
    "gn:dem":95,
    "gn:feature_class":"P",
    "gn:feature_code":"PPL",
    "gn:name":"Lunping",
    "gn:population":0,
    "gn:timezone":"Asia/Taipei",
    "iso:country":"TW",
    "name:zho_x_preferred":[
        "\u5d19\u576a"
    ],
    "name:zho_x_variant":[
        "Lun-p\u2019ing-ts\u2019un",
        "Lun-p\u2019ing"
    ],
    "wof:name":"Lunping",
    "wof:placetype":"locality"
},
  "geometry": {"coordinates":[121.15795,25.00493],"type":"Point"}
}