{
  "type": "Feature",
  "properties": {
    "gn:admin1_code":"4.0",
    "gn:admin2_code":"TNN",
    "gn:admin3_code":"R07",
    "gn:admin4_code":"67000070028.0",
    "gn:asciiname":"Beibu",
    "gn:country_code":"TW",
    "gn:dem":10,
    "gn:feature_class":"P",
    "gn:feature_code":"PPL",
    "gn:name":"Beibu",
    "gn:population":0,
    "gn:timezone":"Asia/Taipei",
    "iso:country":"TW",
    "name:und_x_variant":[
        "Pei-pu",
        "Pu-ti",
        "Beibu",
        "\u5317\u5ecd"
    ],
    "name:zho_x_preferred":[
        "\u5317\u5ecd"
    ],
    "wof:name":"Beibu",
    "wof:placetype":"locality"
},
  "geometry": {"coordinates":[120.22528,23.16639],"type":"Point"}
}