{
  "type": "Feature",
  "properties": {
    "gn:admin1_code":"3.0",
    "gn:admin2_code":"TPQ",
    "gn:admin3_code":"F24",
    "gn:admin4_code":"65000260006.0",
    "gn:asciiname":"Wazi",
    "gn:country_code":"TW",
    "gn:dem":10,
    "gn:feature_class":"P",
    "gn:feature_code":"PPL",
    "gn:name":"Wazi",
    "gn:population":0,
    "gn:timezone":"Asia/Taipei",
    "iso:country":"TW",
    "name:und_x_variant":[
        "Wazih",
        "Fu-shou",
        "Wazi",
        "Wa-tzu"
    ],
    "name:zho_x_preferred":[
        "\u6316\u5b50"
    ],
    "wof:name":"Wazi",
    "wof:placetype":"locality"
},
  "geometry": {"coordinates":[121.95068999999999,25.02016],"type":"Point"}
}