{
  "type": "Feature",
  "properties": {
    "gn:admin1_code":"4.0",
    "gn:admin2_code":"TNN",
    "gn:admin3_code":"R03",
    "gn:admin4_code":"67000030016.0",
    "gn:asciiname":"Fangzilin",
    "gn:country_code":"TW",
    "gn:dem":33,
    "gn:feature_class":"P",
    "gn:feature_code":"PPL",
    "gn:name":"Fangzilin",
    "gn:population":0,
    "gn:timezone":"Asia/Taipei",
    "iso:country":"TW",
    "name:und_x_variant":[
        "Feng-lin",
        "Fangzihlin",
        "Fang-tzu-lin"
    ],
    "name:zho_x_preferred":[
        "\u678b\u5b50\u6797"
    ],
    "wof:name":"Fangzilin",
    "wof:placetype":"locality"
},
  "geometry": {"coordinates":[120.40472,23.38889],"type":"Point"}
}