{
  "type": "Feature",
  "properties": {
    "gn:country":"TW",
    "gn:fcode":"ADMD",
    "gn:pop":0,
    "iso:country":"TW",
    "name:unk_x_variant":[
        "Lugang Jhen"
    ],
    "name:zho_x_preferred":[
        "\u9e7f\u6e2f\u93ae"
    ],
    "qs:name":"Lugang Zhen",
    "qs:photos_9r":0,
    "qs:photos_sr":0,
    "qs:pop_sr":"0",
    "wd:wordcount":1487,
    "wof:name":"Lugang Zhen",
    "wof:placetype":"localadmin",
    "wof:population":0
},
  "geometry": {"coordinates":[120.45,24.08333],"type":"Point"}
}