{
  "type": "Feature",
  "properties": {
    "gn:admin1_code":"04",
    "gn:admin2_code":"CHA",
    "gn:admin3_code":"N06",
    "gn:admin4_code":"10007110022.0",
    "gn:asciiname":"Dating",
    "gn:country_code":"TW",
    "gn:dem":23,
    "gn:feature_class":"P",
    "gn:feature_code":"PPL",
    "gn:name":"Dating",
    "gn:population":0,
    "gn:timezone":"Asia/Taipei",
    "iso:country":"TW",
    "name:ara_x_preferred":[
        "\u0645\u0648\u0627\u0639\u062f\u0629"
    ],
    "name:ast_x_preferred":[
        "Novialgu"
    ],
    "name:bel_x_preferred":[
        "\u0421\u043f\u0430\u0442\u043a\u0430\u043d\u043d\u0435"
    ],
    "name:ben_x_preferred":[
        "\u09a1\u09c7\u099f\u09bf\u0982"
    ],
    "name:ces_x_preferred":[
        "Rande"
    ],
    "name:chv_x_preferred":[
        "\u041a\u0443\u0440\u043d\u0103\u00e7\u0443"
    ],
    "name:deu_x_preferred":[
        "Stelldichein"
    ],
    "name:epo_x_preferred":[
        "Rendevuado"
    ],
    "name:fas_x_preferred":[
        "\u0642\u0631\u0627\u0631 \u06af\u0630\u0627\u0634\u062a\u0646"
    ],
    "name:fin_x_preferred":[
        "Treffit"
    ],
    "name:fra_x_preferred":[
        "Rendez-vous galant"
    ],
    "name:heb_x_preferred":[
        "\u05d3\u05d9\u05d9\u05d8"
    ],
    "name:ind_x_preferred":[
        "Kencan"
    ],
    "name:ita_x_preferred":[
        "Dating"
    ],
    "name:jpn_x_preferred":[
        "\u30c7\u30fc\u30c8"
    ],
    "name:kor_x_preferred":[
        "\ub370\uc774\ud2b8"
    ],
    "name:msa_x_preferred":[
        "Berpacaran"
    ],
    "name:nld_x_preferred":[
        "Daten"
    ],
    "name:nno_x_preferred":[
        "Stemnem\u00f8te"
    ],
    "name:nor_x_preferred":[
        "Stevnem\u00f8te"
    ],
    "name:pol_x_preferred":[
        "Randka"
    ],
    "name:por_x_preferred":[
        "Namoro"
    ],
    "name:rus_x_preferred":[
        "\u0421\u0432\u0438\u0434\u0430\u043d\u0438\u0435"
    ],
    "name:scn_x_preferred":[
        "Zita"
    ],
    "name:spa_x_preferred":[
        "Cita rom\u00e1ntica"
    ],
    "name:swe_x_preferred":[
        "Dejtning"
    ],
    "name:tam_x_preferred":[
        "\u0b95\u0bb3\u0bb5\u0bb3\u0bbe\u0bb5\u0bb2\u0bcd"
    ],
    "name:tel_x_preferred":[
        "\u0c21\u0c47\u0c1f\u0c3f\u0c02\u0c17\u0c4d"
    ],
    "name:tgl_x_preferred":[
        "Pakikipag-date"
    ],
    "name:tur_x_preferred":[
        "\u00c7\u0131kma"
    ],
    "name:ukr_x_preferred":[
        "\u041f\u043e\u0431\u0430\u0447\u0435\u043d\u043d\u044f"
    ],
    "name:und_x_variant":[
        "Lun-tzu-chiao"
    ],
    "name:yid_x_preferred":[
        "\u05e8\u05d0\u05e0\u05d3\u05e7\u05e2\u05d5\u05d5\u05e2\u05df"
    ],
    "name:zho_x_preferred":[
        "\u5927\u5ead"
    ],
    "name:zho_x_variant":[
        "Ta-t\u2019ing-li",
        "Ta-t\u2019ing"
    ],
    "wof:name":"Dating",
    "wof:placetype":"locality"
},
  "geometry": {"coordinates":[120.49642,23.94752],"type":"Point"}
}