{
  "type": "Feature",
  "properties": {
    "gn:admin1_code":"04",
    "gn:admin2_code":"CHA",
    "gn:admin3_code":"N06",
    "gn:admin4_code":"10007110022.0",
    "gn:asciiname":"Dating",
    "gn:country_code":"TW",
    "gn:dem":23,
    "gn:feature_class":"P",
    "gn:feature_code":"PPL",
    "gn:name":"Dating",
    "gn:population":0,
    "gn:timezone":"Asia/Taipei",
    "iso:country":"TW",
    "name:und_x_variant":[
        "Lun-tzu-chiao"
    ],
    "name:zho_x_preferred":[
        "\u5927\u5ead"
    ],
    "name:zho_x_variant":[
        "Ta-t\u2019ing-li",
        "Ta-t\u2019ing"
    ],
    "wof:name":"Dating",
    "wof:placetype":"locality"
},
  "geometry": {"coordinates":[120.49642,23.94752],"type":"Point"}
}