{
  "type": "Feature",
  "properties": {
    "gn:admin1_code":"4.0",
    "gn:admin2_code":"TNN",
    "gn:admin3_code":"R22",
    "gn:admin4_code":"67000220001.0",
    "gn:asciiname":"Beishizhou",
    "gn:country_code":"TW",
    "gn:dem":21,
    "gn:feature_class":"P",
    "gn:feature_code":"PPL",
    "gn:name":"Beishizhou",
    "gn:population":0,
    "gn:timezone":"Asia/Taipei",
    "iso:country":"TW",
    "name:und_x_variant":[
        "Hsin-chuang",
        "Beishizhou",
        "Beishihjhou",
        "Pei-shih-chou"
    ],
    "name:zho_x_preferred":[
        "\u5317\u52e2\u6d32"
    ],
    "wof:name":"Beishizhou",
    "wof:placetype":"locality"
},
  "geometry": {"coordinates":[120.3398,23.112],"type":"Point"}
}