{
  "type": "Feature",
  "properties": {
    "gn:admin1_code":"1.0",
    "gn:admin2_code":"KIN",
    "gn:admin3_code":"W05",
    "gn:admin4_code":"9020050005.0",
    "gn:asciiname":"Huangcuo",
    "gn:country_code":"TW",
    "gn:dem":20,
    "gn:feature_class":"P",
    "gn:feature_code":"PPL",
    "gn:name":"Huangcuo",
    "gn:population":0,
    "gn:timezone":"Asia/Shanghai",
    "iso:country":"TW",
    "name:und_x_variant":[
        "Huang-ts\u2019o"
    ],
    "name:zho_x_preferred":[
        "\u9ec3\u539d"
    ],
    "wof:name":"Huangcuo",
    "wof:placetype":"locality"
},
  "geometry": {"coordinates":[118.25444,24.44671],"type":"Point"}
}