{
  "type": "Feature",
  "properties": {
    "gn:admin1_code":"4.0",
    "gn:admin2_code":"CYQ",
    "gn:admin3_code":"Q14",
    "gn:admin4_code":"10010130013.0",
    "gn:asciiname":"Houkengzi",
    "gn:country_code":"TW",
    "gn:dem":144,
    "gn:feature_class":"P",
    "gn:feature_code":"PPL",
    "gn:name":"Houkengzi",
    "gn:population":0,
    "gn:timezone":"Asia/Taipei",
    "iso:country":"TW",
    "name:und_x_variant":[
        "Houkengzih"
    ],
    "name:zho_x_preferred":[
        "\u5f8c\u5751\u4ed4"
    ],
    "name:zho_x_variant":[
        "Hou-k\u2019eng-tzu"
    ],
    "wof:name":"Houkengzi",
    "wof:placetype":"locality"
},
  "geometry": {"coordinates":[120.55293,23.4243],"type":"Point"}
}