{
  "type": "Feature",
  "properties": {
    "gn:admin1_code":"4.0",
    "gn:admin2_code":"HSQ",
    "gn:admin3_code":"O03",
    "gn:admin4_code":"10018030012.0",
    "gn:asciiname":"Tuoluoshan",
    "gn:country_code":"TW",
    "gn:dem":17,
    "gn:feature_class":"P",
    "gn:feature_code":"PPL",
    "gn:name":"Tuoluoshan",
    "gn:population":0,
    "gn:timezone":"Asia/Taipei",
    "iso:country":"TW",
    "name:zho_x_preferred":[
        "\u9640\u87ba\u5c71"
    ],
    "name:zho_x_variant":[
        "T\u2019o-lo-shan"
    ],
    "wof:name":"Tuoluoshan",
    "wof:placetype":"locality"
},
  "geometry": {"coordinates":[120.93000000000001,24.78472],"type":"Point"}
}