{
  "type": "Feature",
  "properties": {
    "gn:admin1_code":"04",
    "gn:admin2_code":"CHA",
    "gn:admin3_code":"N01",
    "gn:admin4_code":"10007010060.0",
    "gn:asciiname":"Caigongliao",
    "gn:country_code":"TW",
    "gn:dem":17,
    "gn:feature_class":"P",
    "gn:feature_code":"PPL",
    "gn:name":"Caigongliao",
    "gn:population":0,
    "gn:timezone":"Asia/Taipei",
    "iso:country":"TW",
    "name:und_x_variant":[
        "\u83dc\u516c\u5bee",
        "Caigongliao",
        "Ts\u2019ai-kung-lao",
        "Ts\u2019ai-kung-liao"
    ],
    "name:zho_x_preferred":[
        "Ts\u2019ai-kung-liao"
    ],
    "wof:name":"Caigongliao",
    "wof:placetype":"locality"
},
  "geometry": {"coordinates":[120.55101000000001,24.10778],"type":"Point"}
}