{
  "type": "Feature",
  "properties": {
    "gn:admin1_code":"04",
    "gn:admin2_code":"TNN",
    "gn:admin3_code":"R22",
    "gn:admin4_code":"67000220002.0",
    "gn:asciiname":"Shanshang",
    "gn:country_code":"TW",
    "gn:dem":20,
    "gn:feature_class":"P",
    "gn:feature_code":"PPL",
    "gn:name":"Shanshang",
    "gn:population":0,
    "gn:timezone":"Asia/Taipei",
    "iso:country":"TW",
    "name:und_x_variant":[
        "Shan-shang-chuang",
        "Shanshang",
        "Shan-shang"
    ],
    "name:zho_x_preferred":[
        "\u5c71\u4e0a"
    ],
    "wof:name":"Shanshang",
    "wof:placetype":"locality"
},
  "geometry": {"coordinates":[120.35221,23.10248],"type":"Point"}
}