{
  "type": "Feature",
  "properties": {
    "gn:admin1_code":"04",
    "gn:admin2_code":"CYQ",
    "gn:admin3_code":"Q10",
    "gn:admin4_code":"10010100019.0",
    "gn:asciiname":"Xinzhuang",
    "gn:country_code":"TW",
    "gn:dem":8,
    "gn:feature_class":"P",
    "gn:feature_code":"PPL",
    "gn:name":"Xinzhuang",
    "gn:population":0,
    "gn:timezone":"Asia/Taipei",
    "iso:country":"TW",
    "name:ceb_x_preferred":[
        "Xinzhuang"
    ],
    "name:deu_x_preferred":[
        "Xinzhuang"
    ],
    "name:und_x_variant":[
        "Tung-kuang",
        "Sinjhuang",
        "Hsin-chuang"
    ],
    "name:zho_x_preferred":[
        "\u65b0\u5e84"
    ],
    "wof:name":"Xinzhuang",
    "wof:placetype":"locality"
},
  "geometry": {"coordinates":[120.2444,23.3613],"type":"Point"}
}