{
  "type": "Feature",
  "properties": {
    "gn:admin1_code":"4.0",
    "gn:admin2_code":"TXG",
    "gn:admin3_code":"B19",
    "gn:admin4_code":"66000190005.0",
    "gn:asciiname":"Kengtou",
    "gn:country_code":"TW",
    "gn:dem":382,
    "gn:feature_class":"P",
    "gn:feature_code":"PPL",
    "gn:name":"Kengtou",
    "gn:population":0,
    "gn:timezone":"Asia/Taipei",
    "iso:country":"TW",
    "name:zho_x_preferred":[
        "\u5751\u982d"
    ],
    "name:zho_x_variant":[
        "K\u2019eng-t\u2019ou"
    ],
    "wof:name":"Kengtou",
    "wof:placetype":"locality"
},
  "geometry": {"coordinates":[120.76864,24.23989],"type":"Point"}
}