{
  "type": "Feature",
  "properties": {
    "gn:admin1_code":"4.0",
    "gn:admin2_code":"TNN",
    "gn:admin3_code":"R13",
    "gn:admin4_code":"67000140008.0",
    "gn:asciiname":"Hanxigang",
    "gn:country_code":"TW",
    "gn:dem":8,
    "gn:feature_class":"P",
    "gn:feature_code":"PPL",
    "gn:name":"Hanxigang",
    "gn:population":0,
    "gn:timezone":"Asia/Taipei",
    "iso:country":"TW",
    "name:und_x_variant":[
        "Han-hsi-chiang",
        "Hansigang",
        "Hanxigang",
        "Han-hsi-kang"
    ],
    "name:zho_x_preferred":[
        "\u86b6\u897f\u6e2f"
    ],
    "wof:name":"Hanxigang",
    "wof:placetype":"locality"
},
  "geometry": {"coordinates":[120.17861000000001,23.13167],"type":"Point"}
}