{
  "type": "Feature",
  "properties": {
    "gn:admin1_code":"4.0",
    "gn:admin2_code":"CYQ",
    "gn:admin3_code":"Q15",
    "gn:admin4_code":"10010140015.0",
    "gn:asciiname":"Pingding",
    "gn:country_code":"TW",
    "gn:dem":219,
    "gn:feature_class":"P",
    "gn:feature_code":"PPL",
    "gn:name":"Pingding",
    "gn:population":0,
    "gn:timezone":"Asia/Taipei",
    "iso:country":"TW",
    "name:und_x_variant":[
        "Ping-ting"
    ],
    "name:zho_x_preferred":[
        "\u576a\u9802"
    ],
    "wof:name":"Pingding",
    "wof:placetype":"locality"
},
  "geometry": {"coordinates":[120.56764,23.49659],"type":"Point"}
}