{
  "type": "Feature",
  "properties": {
    "gn:admin1_code":"04",
    "gn:admin2_code":"NAN",
    "gn:admin3_code":"M13",
    "gn:admin4_code":"10008130009.0",
    "gn:asciiname":"Meimu",
    "gn:country_code":"TW",
    "gn:dem":1600,
    "gn:feature_class":"P",
    "gn:feature_code":"PPL",
    "gn:name":"Meimu",
    "gn:population":0,
    "gn:timezone":"Asia/Taipei",
    "iso:country":"TW",
    "name:und_x_variant":[
        "Mei-shui",
        "Meimu",
        "Mei-mu"
    ],
    "name:zho_x_preferred":[
        "\u6885\u6728"
    ],
    "wof:name":"Meimu",
    "wof:placetype":"locality"
},
  "geometry": {"coordinates":[121.15528,24.06],"type":"Point"}
}