{
  "type": "Feature",
  "properties": {
    "gn:admin1_code":"4.0",
    "gn:admin2_code":"HSQ",
    "gn:admin3_code":"O03",
    "gn:admin4_code":"10018030016.0",
    "gn:asciiname":"Haishanjiao",
    "gn:country_code":"TW",
    "gn:dem":13,
    "gn:feature_class":"P",
    "gn:feature_code":"PPL",
    "gn:name":"Haishanjiao",
    "gn:population":0,
    "gn:timezone":"Asia/Taipei",
    "iso:country":"TW",
    "name:und_x_variant":[
        "Hai-shan-chiao"
    ],
    "name:zho_x_preferred":[
        "\u6d77\u5c71\u7a96"
    ],
    "wof:name":"Haishanjiao",
    "wof:placetype":"locality"
},
  "geometry": {"coordinates":[120.90971999999999,24.755],"type":"Point"}
}