{
  "type": "Feature",
  "properties": {
    "gn:admin1_code":"4.0",
    "gn:admin2_code":"TNN",
    "gn:admin3_code":"D02",
    "gn:admin4_code":"67000330016.0",
    "gn:asciiname":"Xishu",
    "gn:country_code":"TW",
    "gn:dem":7,
    "gn:feature_class":"P",
    "gn:feature_code":"PPL",
    "gn:name":"Xishu",
    "gn:population":0,
    "gn:timezone":"Asia/Taipei",
    "iso:country":"TW",
    "name:und_x_variant":[
        "Sishu",
        "Xishu",
        "Hsi-shu"
    ],
    "name:zho_x_preferred":[
        "\u559c\u6a39"
    ],
    "wof:name":"Xishu",
    "wof:placetype":"locality"
},
  "geometry": {"coordinates":[120.17722000000001,22.93972],"type":"Point"}
}