{
  "type": "Feature",
  "properties": {
    "gn:admin1_code":"03",
    "gn:admin2_code":"TPQ",
    "gn:admin3_code":"F25",
    "gn:admin4_code":"65000270004.0",
    "gn:asciiname":"Sheliao",
    "gn:country_code":"TW",
    "gn:dem":11,
    "gn:feature_class":"P",
    "gn:feature_code":"PPL",
    "gn:name":"Sheliao",
    "gn:population":0,
    "gn:timezone":"Asia/Taipei",
    "iso:country":"TW",
    "name:und_x_variant":[
        "She-liao"
    ],
    "name:zho_x_preferred":[
        "\u793e\u5bee"
    ],
    "wof:name":"Sheliao",
    "wof:placetype":"locality"
},
  "geometry": {"coordinates":[121.63919,25.22837],"type":"Point"}
}