{
  "type": "Feature",
  "properties": {
    "gn:admin1_code":"04",
    "gn:admin2_code":"YUN",
    "gn:admin3_code":"P18",
    "gn:admin4_code":"10009180013.0",
    "gn:asciiname":"Santiaolunyugang",
    "gn:country_code":"TW",
    "gn:dem":1,
    "gn:feature_class":"P",
    "gn:feature_code":"PPL",
    "gn:name":"Santiaolunyugang",
    "gn:population":0,
    "gn:timezone":"Asia/Taipei",
    "iso:country":"TW",
    "name:und_x_variant":[
        "San-t\u2019iao-lun-y\u00fc-chiang",
        "San-t\u2019iao-lun-y\u00fc-kang",
        "Santiaolunyugang"
    ],
    "wof:name":"Santiaolunyugang",
    "wof:placetype":"locality"
},
  "geometry": {"coordinates":[120.15000000000001,23.66667],"type":"Point"}
}