{
  "type": "Feature",
  "properties": {
    "gn:admin1_code":"4.0",
    "gn:admin2_code":"MIA",
    "gn:admin3_code":"K10",
    "gn:admin4_code":"10005050016.0",
    "gn:asciiname":"Hecuo",
    "gn:country_code":"TW",
    "gn:dem":26,
    "gn:feature_class":"P",
    "gn:feature_code":"PPL",
    "gn:name":"Hecuo",
    "gn:population":0,
    "gn:timezone":"Asia/Taipei",
    "iso:country":"TW",
    "name:zho_x_preferred":[
        "\u4f55\u539d"
    ],
    "name:zho_x_variant":[
        "Ho-ts\u2019o"
    ],
    "wof:name":"Hecuo",
    "wof:placetype":"locality"
},
  "geometry": {"coordinates":[120.90319,24.70291],"type":"Point"}
}