{
  "type": "Feature",
  "properties": {
    "gn:admin1_code":"4.0",
    "gn:admin2_code":"CHA",
    "gn:admin3_code":"N01",
    "gn:admin4_code":"10007010067.0",
    "gn:asciiname":"Kengliaobu",
    "gn:country_code":"TW",
    "gn:dem":65,
    "gn:feature_class":"P",
    "gn:feature_code":"PPL",
    "gn:name":"Kengliaobu",
    "gn:population":0,
    "gn:timezone":"Asia/Taipei",
    "iso:country":"TW",
    "name:und_x_variant":[
        "K\u2019eng-liao-pu"
    ],
    "name:zho_x_preferred":[
        "\u5751\u5bee\u57d4"
    ],
    "name:zho_x_variant":[
        "K\u2019eng-liao-pu"
    ],
    "wof:name":"Kengliaobu",
    "wof:placetype":"locality"
},
  "geometry": {"coordinates":[120.62015,24.04869],"type":"Point"}
}