{
  "type": "Feature",
  "properties": {
    "gn:admin1_code":"04",
    "gn:admin2_code":"MIA",
    "gn:admin3_code":"K05",
    "gn:admin4_code":"10005100009.0",
    "gn:asciiname":"Pengwu",
    "gn:country_code":"TW",
    "gn:dem":188,
    "gn:feature_class":"P",
    "gn:feature_code":"PPL",
    "gn:name":"Pengwu",
    "gn:population":0,
    "gn:timezone":"Asia/Taipei",
    "iso:country":"TW",
    "name:und_x_variant":[
        "\u5f6d\u5c4b",
        "Pengwu"
    ],
    "name:zho_x_preferred":[
        "P\u2019eng-ts\u2019o"
    ],
    "name:zho_x_variant":[
        "P\u2019eng-wu",
        "\u5f6d\u5c4b"
    ],
    "wof:name":"Pengwu",
    "wof:placetype":"locality"
},
  "geometry": {"coordinates":[120.81238,24.44084],"type":"Point"}
}