{
  "type": "Feature",
  "properties": {
    "gn:admin1_code":"4.0",
    "gn:admin2_code":"KEE",
    "gn:admin3_code":"C06",
    "gn:admin4_code":"10017060022.0",
    "gn:asciiname":"Kekegang",
    "gn:country_code":"TW",
    "gn:dem":88,
    "gn:feature_class":"P",
    "gn:feature_code":"PPL",
    "gn:name":"Kekegang",
    "gn:population":0,
    "gn:timezone":"Asia/Taipei",
    "iso:country":"TW",
    "name:und_x_variant":[
        "Ho-k\u2019o-chiang",
        "K\u2019o-ch\u2019\u00fceh-kang",
        "K\u2019o-k\u2019o-kang",
        "Kekegang"
    ],
    "wof:name":"Kekegang",
    "wof:placetype":"locality"
},
  "geometry": {"coordinates":[121.71666999999999,25.13333],"type":"Point"}
}