{
  "type": "Feature",
  "properties": {
    "gn:admin1_code":"4.0",
    "gn:admin2_code":"TNN",
    "gn:admin3_code":"D06",
    "gn:admin4_code":"67000350004.0",
    "gn:asciiname":"Zhongzhouliao",
    "gn:country_code":"TW",
    "gn:dem":5,
    "gn:feature_class":"P",
    "gn:feature_code":"PPL",
    "gn:name":"Zhongzhouliao",
    "gn:population":0,
    "gn:timezone":"Asia/Taipei",
    "iso:country":"TW",
    "name:und_x_variant":[
        "Chung-chou-liao",
        "Ho-shun",
        "Jhongjhouliao",
        "Zhongzhouliao",
        "\u4e2d\u6d32\u5bee"
    ],
    "name:zho_x_preferred":[
        "\u4e2d\u6d32\u5bee"
    ],
    "wof:name":"Zhongzhouliao",
    "wof:placetype":"locality"
},
  "geometry": {"coordinates":[120.21666999999999,23.06194],"type":"Point"}
}