{
  "type": "Feature",
  "properties": {
    "gn:admin1_code":"4.0",
    "gn:admin2_code":"TXG",
    "gn:admin3_code":"B09",
    "gn:admin4_code":"66000090031.0",
    "gn:asciiname":"Qijiao",
    "gn:country_code":"TW",
    "gn:dem":257,
    "gn:feature_class":"P",
    "gn:feature_code":"PPL",
    "gn:name":"Qijiao",
    "gn:population":0,
    "gn:timezone":"Asia/Taipei",
    "iso:country":"TW",
    "name:und_x_variant":[
        "Cijiao",
        "Qijiao"
    ],
    "name:zho_x_preferred":[
        "\u5d0e\u8173"
    ],
    "name:zho_x_variant":[
        "Ch\u2019i-chiao"
    ],
    "wof:name":"Qijiao",
    "wof:placetype":"locality"
},
  "geometry": {"coordinates":[120.74833,24.26333],"type":"Point"}
}