{
  "type": "Feature",
  "properties": {
    "gn:admin1_code":"2.0",
    "gn:admin2_code":"KHH",
    "gn:admin3_code":"E32",
    "gn:admin4_code":"64000320004.0",
    "gn:asciiname":"Dingxinfa",
    "gn:country_code":"TW",
    "gn:dem":342,
    "gn:feature_class":"P",
    "gn:feature_code":"PPL",
    "gn:name":"Dingxinfa",
    "gn:population":0,
    "gn:timezone":"Asia/Taipei",
    "iso:country":"TW",
    "name:und_x_variant":[
        "Dingsinfa",
        "Ting-hsin-fa"
    ],
    "name:zho_x_preferred":[
        "\u9802\u65b0\u767c"
    ],
    "wof:name":"Dingxinfa",
    "wof:placetype":"locality"
},
  "geometry": {"coordinates":[120.66806,23.04528],"type":"Point"}
}