{
  "type": "Feature",
  "properties": {
    "gn:admin1_code":"4.0",
    "gn:admin2_code":"TAO",
    "gn:admin3_code":"H06",
    "gn:admin4_code":"68000060019.0",
    "gn:asciiname":"Nangang",
    "gn:country_code":"TW",
    "gn:dem":32,
    "gn:feature_class":"P",
    "gn:feature_code":"PPL",
    "gn:name":"Nangang",
    "gn:population":0,
    "gn:timezone":"Asia/Taipei",
    "iso:country":"TW",
    "name:und_x_variant":[
        "Nan-kang"
    ],
    "name:zho_x_preferred":[
        "\u5357\u6e2f"
    ],
    "wof:name":"Nangang",
    "wof:placetype":"locality"
},
  "geometry": {"coordinates":[121.17534999999999,25.06297],"type":"Point"}
}