{
  "type": "Feature",
  "properties": {
    "gn:country":"TW",
    "gn:fcode":"ADMD",
    "gn:pop":0,
    "iso:country":"TW",
    "name:unk_x_variant":[
        "Wu-she"
    ],
    "name:zho_x_preferred":[
        "\u4ec1\u611b\u9109"
    ],
    "name:zho_x_variant":[
        "Ren\u2019ai Xiang",
        "Ren\u2019ai Siang"
    ],
    "qs:name":"Ren\u2019ai Xiang",
    "qs:photos_9r":0,
    "qs:photos_sr":0,
    "qs:pop_sr":"0",
    "wof:name":"Ren\u2019ai Xiang",
    "wof:placetype":"localadmin",
    "wof:population":0
},
  "geometry": {"coordinates":[121.13111000000001,24.02528],"type":"Point"}
}