{
  "type": "Feature",
  "properties": {
    "gn:admin1_code":"4.0",
    "gn:admin2_code":"NAN",
    "gn:admin3_code":"M13",
    "gn:admin4_code":"10008130016.0",
    "gn:asciiname":"Yunhai",
    "gn:country_code":"TW",
    "gn:dem":2286,
    "gn:feature_class":"P",
    "gn:feature_code":"PPL",
    "gn:name":"Yunhai",
    "gn:population":0,
    "gn:timezone":"Asia/Taipei",
    "iso:country":"TW",
    "name:und_x_variant":[
        "Wei-shang",
        "Yunhai"
    ],
    "name:zho_x_preferred":[
        "\u96f2\u6d77"
    ],
    "name:zho_x_variant":[
        "Y\u00fcn-hai"
    ],
    "wof:name":"Yunhai",
    "wof:placetype":"locality"
},
  "geometry": {"coordinates":[121.23721999999999,24.04611],"type":"Point"}
}