{
  "type": "Feature",
  "properties": {
    "gn:admin1_code":"4.0",
    "gn:admin2_code":"CYQ",
    "gn:admin3_code":"Q15",
    "gn:admin4_code":"10010140002.0",
    "gn:asciiname":"Kengzike",
    "gn:country_code":"TW",
    "gn:dem":120,
    "gn:feature_class":"P",
    "gn:feature_code":"PPL",
    "gn:name":"Kengzike",
    "gn:population":0,
    "gn:timezone":"Asia/Taipei",
    "iso:country":"TW",
    "name:und_x_variant":[
        "Kengzihke"
    ],
    "name:zho_x_preferred":[
        "\u5751\u4ed4\u79d1"
    ],
    "name:zho_x_variant":[
        "K\u2019eng-tzu-p\u2019ing",
        "K\u2019eng-tzu-k\u2019o"
    ],
    "wof:name":"Kengzike",
    "wof:placetype":"locality"
},
  "geometry": {"coordinates":[120.55222000000001,23.51556],"type":"Point"}
}