{
  "type": "Feature",
  "properties": {
    "gn:admin1_code":"4.0",
    "gn:admin2_code":"ILA",
    "gn:admin3_code":"G07",
    "gn:admin4_code":"10002090015.0",
    "gn:asciiname":"Liuliu",
    "gn:country_code":"TW",
    "gn:dem":5,
    "gn:feature_class":"P",
    "gn:feature_code":"PPL",
    "gn:name":"Liuliu",
    "gn:population":0,
    "gn:timezone":"Asia/Taipei",
    "iso:country":"TW",
    "name:und_x_variant":[
        "Liouliou",
        "Liu-liu"
    ],
    "name:zho_x_preferred":[
        "\u6d41\u6d41"
    ],
    "wof:name":"Liuliu",
    "wof:placetype":"locality"
},
  "geometry": {"coordinates":[121.8227,24.67406],"type":"Point"}
}