{
  "type": "Feature",
  "properties": {
    "gn:admin1_code":"4.0",
    "gn:admin2_code":"NAN",
    "gn:admin3_code":"M10",
    "gn:admin4_code":"10008100011.0",
    "gn:asciiname":"Xianangang",
    "gn:country_code":"TW",
    "gn:dem":341,
    "gn:feature_class":"P",
    "gn:feature_code":"PPL",
    "gn:name":"Xianangang",
    "gn:population":0,
    "gn:timezone":"Asia/Taipei",
    "iso:country":"TW",
    "name:und_x_variant":[
        "Hsia-nan-chiang",
        "Sianangang",
        "Xianangang",
        "Hsia-nan-kang"
    ],
    "name:zho_x_preferred":[
        "\u4e0b\u5357\u6e2f"
    ],
    "wof:name":"Xianangang",
    "wof:placetype":"locality"
},
  "geometry": {"coordinates":[120.87466000000001,23.97262000000001],"type":"Point"}
}