{
  "type": "Feature",
  "properties": {
    "gn:admin1_code":"03",
    "gn:admin2_code":"TPQ",
    "gn:admin3_code":"F24",
    "gn:admin4_code":"65000260002.0",
    "gn:asciiname":"Neiliao",
    "gn:country_code":"TW",
    "gn:dem":227,
    "gn:feature_class":"P",
    "gn:feature_code":"PPL",
    "gn:name":"Neiliao",
    "gn:population":0,
    "gn:timezone":"Asia/Taipei",
    "iso:country":"TW",
    "name:und_x_variant":[
        "Nei-liao"
    ],
    "name:zho_x_preferred":[
        "\u5167\u5bee"
    ],
    "wof:name":"Neiliao",
    "wof:placetype":"locality"
},
  "geometry": {"coordinates":[121.87860999999999,24.97639],"type":"Point"}
}