{
  "type": "Feature",
  "properties": {
    "gn:admin1_code":"1.0",
    "gn:admin2_code":"KIN",
    "gn:admin3_code":"W04",
    "gn:admin4_code":"9020040002.0",
    "gn:asciiname":"Zhongbao",
    "gn:country_code":"TW",
    "gn:dem":16,
    "gn:feature_class":"P",
    "gn:feature_code":"PPL",
    "gn:name":"Zhongbao",
    "gn:population":0,
    "gn:timezone":"Asia/Taipei",
    "iso:country":"TW",
    "name:und_x_variant":[
        "Chung-pao"
    ],
    "name:zho_x_preferred":[
        "\u4e2d\u5821"
    ],
    "wof:name":"Zhongbao",
    "wof:placetype":"locality"
},
  "geometry": {"coordinates":[118.33750000000001,24.45806],"type":"Point"}
}