{
  "type": "Feature",
  "properties": {
    "gn:admin1_code":"4.0",
    "gn:admin2_code":"NAN",
    "gn:admin3_code":"M08",
    "gn:admin4_code":"10008080010.0",
    "gn:asciiname":"Dagongdong",
    "gn:country_code":"TW",
    "gn:dem":306,
    "gn:feature_class":"P",
    "gn:feature_code":"PPL",
    "gn:name":"Dagongdong",
    "gn:population":0,
    "gn:timezone":"Asia/Taipei",
    "iso:country":"TW",
    "name:und_x_variant":[
        "Ta-kung-tung"
    ],
    "name:zho_x_preferred":[
        "\u5927\u516c\u51cd"
    ],
    "wof:name":"Dagongdong",
    "wof:placetype":"locality"
},
  "geometry": {"coordinates":[120.7295,23.8801],"type":"Point"}
}