{
  "type": "Feature",
  "properties": {
    "gn:admin1_code":"4.0",
    "gn:admin2_code":"HSZ",
    "gn:admin3_code":"J12",
    "gn:admin4_code":"10004090004.0",
    "gn:asciiname":"Heiqiaowo",
    "gn:country_code":"TW",
    "gn:dem":154,
    "gn:feature_class":"P",
    "gn:feature_code":"PPL",
    "gn:name":"Heiqiaowo",
    "gn:population":0,
    "gn:timezone":"Asia/Taipei",
    "iso:country":"TW",
    "name:und_x_variant":[
        "Heiciaowo",
        "Heiqiaowo"
    ],
    "name:zho_x_preferred":[
        "\u9ed1\u6a4b\u7aa9"
    ],
    "name:zho_x_variant":[
        "Hei-ch\u2019iao-wo"
    ],
    "wof:name":"Heiqiaowo",
    "wof:placetype":"locality"
},
  "geometry": {"coordinates":[121.06638999999998,24.71],"type":"Point"}
}