{
  "type": "Feature",
  "properties": {
    "gn:admin1_code":"4.0",
    "gn:admin2_code":"YUN",
    "gn:admin3_code":"P16",
    "gn:admin4_code":"10009160015.0",
    "gn:asciiname":"Haiyuan",
    "gn:country_code":"TW",
    "gn:dem":1,
    "gn:feature_class":"P",
    "gn:feature_code":"PPL",
    "gn:name":"Haiyuan",
    "gn:population":0,
    "gn:timezone":"Asia/Taipei",
    "iso:country":"TW",
    "name:zho_x_preferred":[
        "\u6d77\u5712"
    ],
    "name:zho_x_variant":[
        "Hai-y\u00fcan"
    ],
    "wof:name":"Haiyuan",
    "wof:placetype":"locality"
},
  "geometry": {"coordinates":[120.17444,23.73167],"type":"Point"}
}