{
  "type": "Feature",
  "properties": {
    "gn:admin1_code":"03",
    "gn:admin2_code":"TPQ",
    "gn:admin3_code":"F23",
    "gn:admin4_code":"65000250012.0",
    "gn:asciiname":"Baochengkeng",
    "gn:country_code":"TW",
    "gn:dem":397,
    "gn:feature_class":"P",
    "gn:feature_code":"PPL",
    "gn:name":"Baochengkeng",
    "gn:population":0,
    "gn:timezone":"Asia/Taipei",
    "iso:country":"TW",
    "name:zho_x_preferred":[
        "\u4fdd\u6210\u5751"
    ],
    "name:zho_x_variant":[
        "Pao-sheng-k\u2019eng",
        "Pao-ch\u2019eng-kung",
        "Pao-ch\u2019eng-k\u2019eng"
    ],
    "wof:name":"Baochengkeng",
    "wof:placetype":"locality"
},
  "geometry": {"coordinates":[121.81028000000001,24.97917],"type":"Point"}
}