{
  "type": "Feature",
  "properties": {
    "gn:admin1_code":"4.0",
    "gn:admin2_code":"TAO",
    "gn:admin3_code":"H12",
    "gn:admin4_code":"68000120003.0",
    "gn:asciiname":"Xiaoyi",
    "gn:country_code":"TW",
    "gn:dem":32,
    "gn:feature_class":"P",
    "gn:feature_code":"PPL",
    "gn:name":"Xiaoyi",
    "gn:population":0,
    "gn:timezone":"Asia/Taipei",
    "iso:country":"TW",
    "name:deu_x_preferred":[
        "Xiaoyi"
    ],
    "name:fra_x_preferred":[
        "Xiaoyi"
    ],
    "name:ita_x_preferred":[
        "Xiaoyi"
    ],
    "name:jpn_x_preferred":[
        "\u5b5d\u7fa9\u5e02"
    ],
    "name:kik_x_preferred":[
        "Xiaoyi"
    ],
    "name:kor_x_preferred":[
        "\uc0e4\uc624\uc774\uc2dc"
    ],
    "name:mlg_x_preferred":[
        "Xiaoyi"
    ],
    "name:nld_x_preferred":[
        "Xiaoyi"
    ],
    "name:nor_x_preferred":[
        "Xiaoyi"
    ],
    "name:rus_x_preferred":[
        "\u0421\u044f\u043e\u0438"
    ],
    "name:swe_x_preferred":[
        "Xiaoyi"
    ],
    "name:und_x_variant":[
        "Siaoyi",
        "Hsiao-i"
    ],
    "name:urd_x_preferred":[
        "\u0634\u06cc\u0627\u0648\u06cc\u06cc"
    ],
    "name:vie_x_preferred":[
        "Hi\u1ebfu Ngh\u0129a"
    ],
    "name:zho_x_preferred":[
        "\u5c0f\u5104"
    ],
    "name:zho_x_variant":[
        "\u5b5d\u4e49\u5e02"
    ],
    "wof:name":"Xiaoyi",
    "wof:placetype":"locality"
},
  "geometry": {"coordinates":[121.09893999999998,25.03761],"type":"Point"}
}