{
  "type": "Feature",
  "properties": {
    "gn:admin1_code":"4.0",
    "gn:admin2_code":"TAO",
    "gn:admin3_code":"H12",
    "gn:admin4_code":"68000120003.0",
    "gn:asciiname":"Xiaoyi",
    "gn:country_code":"TW",
    "gn:dem":32,
    "gn:feature_class":"P",
    "gn:feature_code":"PPL",
    "gn:name":"Xiaoyi",
    "gn:population":0,
    "gn:timezone":"Asia/Taipei",
    "iso:country":"TW",
    "name:und_x_variant":[
        "Siaoyi",
        "Hsiao-i"
    ],
    "name:zho_x_preferred":[
        "\u5c0f\u5104"
    ],
    "wof:name":"Xiaoyi",
    "wof:placetype":"locality"
},
  "geometry": {"coordinates":[121.09893999999998,25.03761],"type":"Point"}
}