{
  "type": "Feature",
  "properties": {
    "gn:admin1_code":"4.0",
    "gn:admin2_code":"CYQ",
    "gn:admin3_code":"Q10",
    "gn:admin4_code":"10010100005.0",
    "gn:asciiname":"Chuanfang",
    "gn:country_code":"TW",
    "gn:dem":11,
    "gn:feature_class":"P",
    "gn:feature_code":"PPL",
    "gn:name":"Chuanfang",
    "gn:population":0,
    "gn:timezone":"Asia/Taipei",
    "iso:country":"TW",
    "name:zho_x_preferred":[
        "\u50b3\u82b3"
    ],
    "name:zho_x_variant":[
        "Ch\u2019uan-fang-ts\u2019un",
        "Ch\u2019uan-fang"
    ],
    "wof:name":"Chuanfang",
    "wof:placetype":"locality"
},
  "geometry": {"coordinates":[120.24290000000001,23.3427],"type":"Point"}
}