{
  "type": "Feature",
  "properties": {
    "gn:admin1_code":"4.0",
    "gn:admin2_code":"TAO",
    "gn:admin3_code":"H06",
    "gn:admin4_code":"68000060016.0",
    "gn:asciiname":"Dapingding",
    "gn:country_code":"TW",
    "gn:dem":18,
    "gn:feature_class":"P",
    "gn:feature_code":"PPL",
    "gn:name":"Dapingding",
    "gn:population":0,
    "gn:timezone":"Asia/Taipei",
    "iso:country":"TW",
    "name:zho_x_preferred":[
        "\u5927\u5e73\u9802"
    ],
    "name:zho_x_variant":[
        "Ta-p\u2019ing-ting"
    ],
    "wof:name":"Dapingding",
    "wof:placetype":"locality"
},
  "geometry": {"coordinates":[121.20372,25.09341],"type":"Point"}
}