{
  "type": "Feature",
  "properties": {
    "gn:admin1_code":"4.0",
    "gn:admin2_code":"NAN",
    "gn:admin3_code":"M02",
    "gn:admin4_code":"10008020010.0",
    "gn:asciiname":"Zhongxinwei",
    "gn:country_code":"TW",
    "gn:dem":444,
    "gn:feature_class":"P",
    "gn:feature_code":"PPL",
    "gn:name":"Zhongxinwei",
    "gn:population":0,
    "gn:timezone":"Asia/Taipei",
    "iso:country":"TW",
    "name:und_x_variant":[
        "Jhongsinwei",
        "Chung-hsin-wei"
    ],
    "name:zho_x_preferred":[
        "\u4e2d\u5fc3\u5c3e"
    ],
    "wof:name":"Zhongxinwei",
    "wof:placetype":"locality"
},
  "geometry": {"coordinates":[120.98129,23.95589],"type":"Point"}
}