{
  "type": "Feature",
  "properties": {
    "iso:country":"TW",
    "name:eng_x_preferred":[
        "Dongmen"
    ],
    "name:eng_x_variant":[
        "Dongmen Village"
    ],
    "name:zho_tw_x_preferred":[
        "\u6771\u9580\u91cc"
    ],
    "qs:name":"\u6771\u9580\u91cc",
    "qs:name_adm0":"\u81fa\u7063",
    "qs:name_adm1":"\u53f0\u4e2d\u5e02",
    "qs:photos":36,
    "qs:photos_1k":7,
    "qs:photos_9k":1,
    "qs:photos_9r":2,
    "qs:photos_all":36,
    "qs:photos_sr":2,
    "qs:placetype":"Suburb",
    "qs:pop_sr":"0",
    "wof:name":"Dongmen",
    "wof:placetype":"neighbourhood"
},
  "geometry": {"coordinates":[120.699144,24.127257],"type":"Point"}
}