{
  "type": "Feature",
  "properties": {
    "gn:admin1_code":"4.0",
    "gn:admin2_code":"HUA",
    "gn:admin3_code":"U02",
    "gn:admin4_code":"10015070011.0",
    "gn:asciiname":"Hezishan",
    "gn:country_code":"TW",
    "gn:dem":138,
    "gn:feature_class":"P",
    "gn:feature_code":"PPL",
    "gn:name":"Hezishan",
    "gn:population":0,
    "gn:timezone":"Asia/Taipei",
    "iso:country":"TW",
    "name:und_x_variant":[
        "Hezihshan",
        "Ho-tzu-shan"
    ],
    "name:zho_x_preferred":[
        "\u5408\u4ed4\u5c71"
    ],
    "wof:name":"Hezishan",
    "wof:placetype":"locality"
},
  "geometry": {"coordinates":[121.46847,23.65996],"type":"Point"}
}