{
  "type": "Feature",
  "properties": {
    "gn:admin1_code":"3.0",
    "gn:admin2_code":"TPQ",
    "gn:admin3_code":"F21",
    "gn:admin4_code":"65000120010.0",
    "gn:asciiname":"Fenglaizi",
    "gn:country_code":"TW",
    "gn:dem":41,
    "gn:feature_class":"P",
    "gn:feature_code":"PPL",
    "gn:name":"Fenglaizi",
    "gn:population":0,
    "gn:timezone":"Asia/Taipei",
    "iso:country":"TW",
    "name:und_x_variant":[
        "Feng-tzu-lai",
        "Fonglaizih",
        "Feng-lai-tzu"
    ],
    "name:zho_x_preferred":[
        "\u6953\u7028\u5b50"
    ],
    "wof:name":"Fenglaizi",
    "wof:placetype":"locality"
},
  "geometry": {"coordinates":[121.77358999999998,25.10727],"type":"Point"}
}