{
  "type": "Feature",
  "properties": {
    "gn:admin1_code":"4.0",
    "gn:admin2_code":"HUA",
    "gn:admin3_code":"U11",
    "gn:admin4_code":"10015110002.0",
    "gn:asciiname":"Baduonuofu",
    "gn:country_code":"TW",
    "gn:dem":947,
    "gn:feature_class":"P",
    "gn:feature_code":"PPL",
    "gn:name":"Baduonuofu",
    "gn:population":0,
    "gn:timezone":"Asia/Taipei",
    "iso:country":"TW",
    "name:und_x_variant":[
        "Pa-to-no-fu"
    ],
    "name:zho_x_preferred":[
        "\u5df4\u591a\u8afe\u592b"
    ],
    "wof:name":"Baduonuofu",
    "wof:placetype":"locality"
},
  "geometry": {"coordinates":[121.43722,24.17861],"type":"Point"}
}