{
  "type": "Feature",
  "properties": {
    "gn:admin1_code":"4.0",
    "gn:admin2_code":"TAO",
    "gn:admin3_code":"H11",
    "gn:admin4_code":"68000110007.0",
    "gn:asciiname":"Jiudou",
    "gn:country_code":"TW",
    "gn:dem":105,
    "gn:feature_class":"P",
    "gn:feature_code":"PPL",
    "gn:name":"Jiudou",
    "gn:population":0,
    "gn:timezone":"Asia/Taipei",
    "iso:country":"TW",
    "name:und_x_variant":[
        "Jioudou",
        "Chiu-tou"
    ],
    "name:zho_x_preferred":[
        "\u4e5d\u6597"
    ],
    "wof:name":"Jiudou",
    "wof:placetype":"locality"
},
  "geometry": {"coordinates":[121.12472,24.95528],"type":"Point"}
}