{
  "type": "Feature",
  "properties": {
    "gn:admin1_code":"4.0",
    "gn:admin2_code":"TAO",
    "gn:admin3_code":"H08",
    "gn:admin4_code":"68000080016.0",
    "gn:asciiname":"Chengziding",
    "gn:country_code":"TW",
    "gn:dem":127,
    "gn:feature_class":"P",
    "gn:feature_code":"PPL",
    "gn:name":"Chengziding",
    "gn:population":0,
    "gn:timezone":"Asia/Taipei",
    "iso:country":"TW",
    "name:und_x_variant":[
        "Chengzihding",
        "Chengziding"
    ],
    "name:zho_x_preferred":[
        "\u57ce\u4ed4\u9802"
    ],
    "name:zho_x_variant":[
        "Ch\u2019eng-tzu-ting"
    ],
    "wof:name":"Chengziding",
    "wof:placetype":"locality"
},
  "geometry": {"coordinates":[121.30852,24.94484],"type":"Point"}
}