{
  "type": "Feature",
  "properties": {
    "gn:admin1_code":"4.0",
    "gn:admin2_code":"PEN",
    "gn:admin3_code":"X03",
    "gn:admin4_code":"10016030009.0",
    "gn:asciiname":"Baiguanyin",
    "gn:country_code":"TW",
    "gn:dem":9,
    "gn:feature_class":"P",
    "gn:feature_code":"PPL",
    "gn:name":"Baiguanyin",
    "gn:population":0,
    "gn:timezone":"Asia/Taipei",
    "iso:country":"TW",
    "name:und_x_variant":[
        "Pai-kuan-yin",
        "\u767d\u89c0\u97f3",
        "Baiguanyin"
    ],
    "name:zho_x_preferred":[
        "\u767d\u89c0\u97f3"
    ],
    "wof:name":"Baiguanyin",
    "wof:placetype":"locality"
},
  "geometry": {"coordinates":[119.58148,23.66042],"type":"Point"}
}