{
  "type": "Feature",
  "properties": {
    "gn:admin1_code":"4.0",
    "gn:admin2_code":"NAN",
    "gn:admin3_code":"M07",
    "gn:admin4_code":"10008070005.0",
    "gn:asciiname":"Ercengping",
    "gn:country_code":"TW",
    "gn:dem":1478,
    "gn:feature_class":"P",
    "gn:feature_code":"PPL",
    "gn:name":"Ercengping",
    "gn:population":0,
    "gn:timezone":"Asia/Taipei",
    "iso:country":"TW",
    "name:zho_x_preferred":[
        "\u4e8c\u5c64\u576a"
    ],
    "name:zho_x_variant":[
        "Erh-ts\u2019eng-p\u2019ing"
    ],
    "wof:name":"Ercengping",
    "wof:placetype":"locality"
},
  "geometry": {"coordinates":[120.80444,23.68917],"type":"Point"}
}