{
  "type": "Feature",
  "properties": {
    "gn:admin1_code":"4.0",
    "gn:admin2_code":"MIA",
    "gn:admin3_code":"K15",
    "gn:admin4_code":"10005080009.0",
    "gn:asciiname":"Xiahu",
    "gn:country_code":"TW",
    "gn:dem":475,
    "gn:feature_class":"P",
    "gn:feature_code":"PPL",
    "gn:name":"Xiahu",
    "gn:population":0,
    "gn:timezone":"Asia/Taipei",
    "iso:country":"TW",
    "name:und_x_variant":[
        "Siahu",
        "Hsia-hu"
    ],
    "name:zho_x_preferred":[
        "\u4e0b\u6e56"
    ],
    "wof:name":"Xiahu",
    "wof:placetype":"locality"
},
  "geometry": {"coordinates":[120.88558,24.38037000000001],"type":"Point"}
}