{
  "type": "Feature",
  "properties": {
    "gn:admin1_code":"04",
    "gn:admin2_code":"HSZ",
    "gn:admin3_code":"J10",
    "gn:admin4_code":"10004070012.0",
    "gn:asciiname":"Shuikengkou",
    "gn:country_code":"TW",
    "gn:dem":57,
    "gn:feature_class":"P",
    "gn:feature_code":"PPL",
    "gn:name":"Shuikengkou",
    "gn:population":0,
    "gn:timezone":"Asia/Taipei",
    "iso:country":"TW",
    "name:und_x_variant":[
        "Shueikengkou"
    ],
    "name:zho_x_preferred":[
        "\u6c34\u5751\u53e3"
    ],
    "name:zho_x_variant":[
        "Shui-k\u2019eng-k\u2019ou"
    ],
    "wof:name":"Shuikengkou",
    "wof:placetype":"locality"
},
  "geometry": {"coordinates":[121.05916999999999,24.80917],"type":"Point"}
}