{
  "type": "Feature",
  "properties": {
    "gn:admin1_code":"04",
    "gn:admin2_code":"YUN",
    "gn:admin3_code":"P16",
    "gn:admin4_code":"10009160001.0",
    "gn:asciiname":"Taixi",
    "gn:country_code":"TW",
    "gn:dem":7,
    "gn:feature_class":"P",
    "gn:feature_code":"PPL",
    "gn:name":"Taixi",
    "gn:population":0,
    "gn:timezone":"Asia/Taipei",
    "iso:country":"TW",
    "name:hak_x_preferred":[
        "Th\u00f2i-s\u00ee-hi\u00f4ng"
    ],
    "name:jpn_x_preferred":[
        "\u53f0\u897f\u90f7"
    ],
    "name:kor_x_preferred":[
        "\ud0c0\uc774\uc2dc\ud5a5"
    ],
    "name:und_x_variant":[
        "Taisi"
    ],
    "name:vie_x_preferred":[
        "\u0110\u00e0i T\u00e2y"
    ],
    "name:zho_x_preferred":[
        "Hai-k\u2019ou"
    ],
    "name:zho_x_variant":[
        "\u81fa\u897f",
        "T\u2019ai-hsi",
        "\u81fa\u897f\u9109"
    ],
    "wof:name":"Taixi",
    "wof:placetype":"locality"
},
  "geometry": {"coordinates":[120.19889000000001,23.70111],"type":"Point"}
}