{
  "type": "Feature",
  "properties": {
    "gn:admin1_code":"04",
    "gn:admin2_code":"YUN",
    "gn:admin3_code":"P16",
    "gn:admin4_code":"10009160001.0",
    "gn:asciiname":"Taixi",
    "gn:country_code":"TW",
    "gn:dem":7,
    "gn:feature_class":"P",
    "gn:feature_code":"PPL",
    "gn:name":"Taixi",
    "gn:population":0,
    "gn:timezone":"Asia/Taipei",
    "iso:country":"TW",
    "name:und_x_variant":[
        "Taisi"
    ],
    "name:zho_x_preferred":[
        "Hai-k\u2019ou"
    ],
    "name:zho_x_variant":[
        "\u81fa\u897f",
        "T\u2019ai-hsi"
    ],
    "wof:name":"Taixi",
    "wof:placetype":"locality"
},
  "geometry": {"coordinates":[120.19889000000001,23.70111],"type":"Point"}
}