{
  "type": "Feature",
  "properties": {
    "gn:admin1_code":"04",
    "gn:admin2_code":"TTT",
    "gn:admin3_code":"V04",
    "gn:admin4_code":"10014040003.0",
    "gn:asciiname":"Shanyuan",
    "gn:country_code":"TW",
    "gn:dem":12,
    "gn:feature_class":"P",
    "gn:feature_code":"PPL",
    "gn:name":"Shanyuan",
    "gn:population":0,
    "gn:timezone":"Asia/Taipei",
    "iso:country":"TW",
    "name:und_x_variant":[
        "Sha-yuan",
        "Shanyuan"
    ],
    "name:zho_x_preferred":[
        "\u6749\u539f"
    ],
    "name:zho_x_variant":[
        "Shan-y\u00fcan-ts\u2019un",
        "Shan-y\u00fcan"
    ],
    "wof:name":"Shanyuan",
    "wof:placetype":"locality"
},
  "geometry": {"coordinates":[121.18783999999999,22.83915],"type":"Point"}
}