{
  "type": "Feature",
  "properties": {
    "gn:admin1_code":"04",
    "gn:admin2_code":"TAO",
    "gn:admin3_code":"H03",
    "gn:admin4_code":"68000020027.0",
    "gn:asciiname":"Shenzhenzi",
    "gn:country_code":"TW",
    "gn:dem":99,
    "gn:feature_class":"P",
    "gn:feature_code":"PPL",
    "gn:name":"Shenzhenzi",
    "gn:population":0,
    "gn:timezone":"Asia/Taipei",
    "iso:country":"TW",
    "name:und_x_variant":[
        "Shenjhenzih",
        "Shen-chen-tzu"
    ],
    "name:zho_x_preferred":[
        "Shen-ch\u2019\u00fcan"
    ],
    "name:zho_x_variant":[
        "\u6df1\u5733\u4ed4",
        "Shen-ch\u00fcn-tzu",
        "Shen-ch\u00fcn"
    ],
    "wof:name":"Shenzhenzi",
    "wof:placetype":"locality"
},
  "geometry": {"coordinates":[121.24095,25.00276],"type":"Point"}
}