{
  "type": "Feature",
  "properties": {
    "gn:admin1_code":"4.0",
    "gn:admin2_code":"TAO",
    "gn:admin3_code":"H08",
    "gn:admin4_code":"68000080009.0",
    "gn:asciiname":"Zhuxiang",
    "gn:country_code":"TW",
    "gn:dem":134,
    "gn:feature_class":"P",
    "gn:feature_code":"PPL",
    "gn:name":"Zhuxiang",
    "gn:population":0,
    "gn:timezone":"Asia/Taipei",
    "iso:country":"TW",
    "name:und_x_variant":[
        "Jhusiang",
        "Zhuxiang",
        "Chu-hsiang"
    ],
    "name:zho_x_preferred":[
        "\u7af9\u5df7"
    ],
    "wof:name":"Zhuxiang",
    "wof:placetype":"locality"
},
  "geometry": {"coordinates":[121.27507,24.94223],"type":"Point"}
}