{
  "type": "Feature",
  "properties": {
    "gn:admin1_code":"04",
    "gn:admin2_code":"ILA",
    "gn:admin3_code":"G05",
    "gn:admin4_code":"10002070002.0",
    "gn:asciiname":"Dasanjiu",
    "gn:country_code":"TW",
    "gn:dem":19,
    "gn:feature_class":"P",
    "gn:feature_code":"PPL",
    "gn:name":"Dasanjiu",
    "gn:population":0,
    "gn:timezone":"Asia/Taipei",
    "iso:country":"TW",
    "name:und_x_variant":[
        "Ta-san",
        "Dasanjiou",
        "Dasanjiu",
        "Ta-san-chiu"
    ],
    "name:zho_x_preferred":[
        "\u5927\u4e09\u9b2e"
    ],
    "wof:name":"Dasanjiu",
    "wof:placetype":"locality"
},
  "geometry": {"coordinates":[121.72119000000001,24.73692],"type":"Point"}
}