{
  "type": "Feature",
  "properties": {
    "gn:admin1_code":"4.0",
    "gn:admin2_code":"MIA",
    "gn:admin3_code":"K12",
    "gn:admin4_code":"10005060007.0",
    "gn:asciiname":"Xiaoji",
    "gn:country_code":"TW",
    "gn:dem":29,
    "gn:feature_class":"P",
    "gn:feature_code":"PPL",
    "gn:name":"Xiaoji",
    "gn:population":0,
    "gn:timezone":"Asia/Taipei",
    "iso:country":"TW",
    "name:und_x_variant":[
        "Chiao-i-li",
        "Chiao-chi",
        "Chiao-i-pei",
        "Hsiao-i-pa",
        "Chiao-i",
        "Siaoji",
        "Xiaoji",
        "Hsiao-chi"
    ],
    "name:zho_x_preferred":[
        "Hsiao-chi-ts\u2019un"
    ],
    "name:zho_x_variant":[
        "\u6821\u5bc4"
    ],
    "wof:name":"Xiaoji",
    "wof:placetype":"locality"
},
  "geometry": {"coordinates":[120.82550000000001,24.60908],"type":"Point"}
}