{
  "type": "Feature",
  "properties": {
    "gn:admin1_code":"4.0",
    "gn:admin2_code":"CHA",
    "gn:admin3_code":"N12",
    "gn:admin4_code":"10007070007.0",
    "gn:asciiname":"Daquwei",
    "gn:country_code":"TW",
    "gn:dem":14,
    "gn:feature_class":"P",
    "gn:feature_code":"PPL",
    "gn:name":"Daquwei",
    "gn:population":0,
    "gn:timezone":"Asia/Taipei",
    "iso:country":"TW",
    "name:und_x_variant":[
        "Dacyuwei",
        "Daquwei"
    ],
    "name:zho_x_preferred":[
        "\u5927\u5340\u570d"
    ],
    "name:zho_x_variant":[
        "Ta-ch\u2019\u00fc-wei"
    ],
    "wof:name":"Daquwei",
    "wof:placetype":"locality"
},
  "geometry": {"coordinates":[120.48999999999999,24.05028],"type":"Point"}
}