{
  "type": "Feature",
  "properties": {
    "gn:admin1_code":"3.0",
    "gn:admin2_code":"TPQ",
    "gn:admin3_code":"F06",
    "gn:admin4_code":"65000160002.0",
    "gn:asciiname":"Xinliaokeng",
    "gn:country_code":"TW",
    "gn:dem":82,
    "gn:feature_class":"P",
    "gn:feature_code":"PPL",
    "gn:name":"Xinliaokeng",
    "gn:population":0,
    "gn:timezone":"Asia/Taipei",
    "iso:country":"TW",
    "name:und_x_variant":[
        "Sinliaokeng",
        "Xinliaokeng"
    ],
    "name:zho_x_preferred":[
        "\u65b0\u5bee\u5751"
    ],
    "name:zho_x_variant":[
        "Hsin-liao-k\u2019eng"
    ],
    "wof:name":"Xinliaokeng",
    "wof:placetype":"locality"
},
  "geometry": {"coordinates":[121.41307999999999,25.06754],"type":"Point"}
}