{
  "type": "Feature",
  "properties": {
    "gn:admin1_code":"4.0",
    "gn:admin2_code":"TNN",
    "gn:admin3_code":"R26",
    "gn:admin4_code":"67000260007.0",
    "gn:asciiname":"Shanbao",
    "gn:country_code":"TW",
    "gn:dem":85,
    "gn:feature_class":"P",
    "gn:feature_code":"PPL",
    "gn:name":"Shanbao",
    "gn:population":0,
    "gn:timezone":"Asia/Taipei",
    "iso:country":"TW",
    "name:und_x_variant":[
        "Shan-pao"
    ],
    "name:zho_x_preferred":[
        "\u5c71\u8c79"
    ],
    "wof:name":"Shanbao",
    "wof:placetype":"locality"
},
  "geometry": {"coordinates":[120.39841,23.01997],"type":"Point"}
}