{
  "type": "Feature",
  "properties": {
    "iso:country":"TW",
    "name:eng_x_preferred":[
        "Jiaoxi"
    ],
    "name:eng_x_variant":[
        "Jiaoxi Township"
    ],
    "name:fra_x_preferred":[
        "Jiaoxi"
    ],
    "name:zho_tw_x_preferred":[
        "\u7901\u6eaa\u9109"
    ],
    "qs:name":"\u7901\u6eaa\u9109",
    "qs:name_adm0":"\u81fa\u7063",
    "qs:name_adm1":"\u5b9c\u862d\u7e23",
    "qs:photos":405,
    "qs:photos_1k":82,
    "qs:photos_9k":34,
    "qs:photos_9r":15,
    "qs:photos_all":7631,
    "qs:photos_sr":6,
    "qs:placetype":"County",
    "qs:pop_sr":"0",
    "wof:name":"Jiaoxi",
    "wof:placetype":"county"
},
  "geometry": {"coordinates":[121.755476,24.808395],"type":"Point"}
}