{
  "type": "Feature",
  "properties": {
    "gn:admin1_code":"04",
    "gn:admin2_code":"NAN",
    "gn:admin3_code":"M10",
    "gn:admin4_code":"10008100011.0",
    "gn:asciiname":"Cukengkou",
    "gn:country_code":"TW",
    "gn:dem":382,
    "gn:feature_class":"P",
    "gn:feature_code":"PPL",
    "gn:name":"Cukengkou",
    "gn:population":0,
    "gn:timezone":"Asia/Taipei",
    "iso:country":"TW",
    "name:zho_x_preferred":[
        "\u7c97\u5751\u53e3"
    ],
    "name:zho_x_variant":[
        "Ts\u2019u-k\u2019eng-k\u2019ou"
    ],
    "wof:name":"Cukengkou",
    "wof:placetype":"locality"
},
  "geometry": {"coordinates":[120.87208,23.96708],"type":"Point"}
}