{
  "type": "Feature",
  "properties": {
    "gn:admin1_code":"03",
    "gn:admin2_code":"TPQ",
    "gn:admin3_code":"F27",
    "gn:admin4_code":"65000100013.0",
    "gn:asciiname":"Bailiujia",
    "gn:country_code":"TW",
    "gn:dem":212,
    "gn:feature_class":"P",
    "gn:feature_code":"PPL",
    "gn:name":"Bailiujia",
    "gn:population":0,
    "gn:timezone":"Asia/Taipei",
    "iso:country":"TW",
    "name:und_x_variant":[
        "Pai-liu-ka",
        "Pai-liu-chia",
        "Bailiujia"
    ],
    "wof:name":"Bailiujia",
    "wof:placetype":"locality"
},
  "geometry": {"coordinates":[121.48611,25.18361],"type":"Point"}
}