{
  "type": "Feature",
  "properties": {
    "gn:admin1_code":"4.0",
    "gn:admin2_code":"CYQ",
    "gn:admin3_code":"Q16",
    "gn:admin4_code":"10010150015.0",
    "gn:asciiname":"Ruifeng",
    "gn:country_code":"TW",
    "gn:dem":1106,
    "gn:feature_class":"P",
    "gn:feature_code":"PPL",
    "gn:name":"Ruifeng",
    "gn:population":0,
    "gn:timezone":"Asia/Taipei",
    "iso:country":"TW",
    "name:und_x_variant":[
        "Rueifong",
        "Ruifeng",
        "Jui-feng"
    ],
    "name:zho_x_preferred":[
        "\u745e\u5cf0"
    ],
    "wof:name":"Ruifeng",
    "wof:placetype":"locality"
},
  "geometry": {"coordinates":[120.67194000000001,23.55694],"type":"Point"}
}