{
  "type": "Feature",
  "properties": {
    "iso:country":"TW",
    "name:eng_x_preferred":[
        "Beizhuang"
    ],
    "name:eng_x_variant":[
        "Beizhuang Village"
    ],
    "name:zho_tw_x_preferred":[
        "\u5317\u5e84\u6751"
    ],
    "qs:name":"\u5317\u5e84\u6751",
    "qs:name_adm0":"\u81fa\u7063",
    "qs:name_adm1":"\u53f0\u4e2d\u5e02",
    "qs:photos":14,
    "qs:photos_1k":3,
    "qs:photos_9k":1,
    "qs:photos_9r":1,
    "qs:photos_all":14,
    "qs:photos_sr":1,
    "qs:placetype":"Town",
    "qs:pop_sr":"0",
    "wof:name":"Beizhuang",
    "wof:placetype":"locality"
},
  "geometry": {"coordinates":[120.67016599999999,24.2545],"type":"Point"}
}