{
  "type": "Feature",
  "properties": {
    "gn:admin1_code":"04",
    "gn:admin2_code":"TAO",
    "gn:admin3_code":"H11",
    "gn:admin4_code":"68000110014.0",
    "gn:asciiname":"Dingtianxinzi",
    "gn:country_code":"TW",
    "gn:dem":52,
    "gn:feature_class":"P",
    "gn:feature_code":"PPL",
    "gn:name":"Dingtianxinzi",
    "gn:population":0,
    "gn:timezone":"Asia/Taipei",
    "iso:country":"TW",
    "name:und_x_variant":[
        "Dingtiansinzih",
        "Dingtianxinzi"
    ],
    "name:zho_x_preferred":[
        "\u9802\u7530\u5fc3\u5b50"
    ],
    "name:zho_x_variant":[
        "Ting-hsin-t\u2019ien",
        "Ting-t\u2019ien-hsin-tzu"
    ],
    "wof:name":"Dingtianxinzi",
    "wof:placetype":"locality"
},
  "geometry": {"coordinates":[121.06999999999999,24.98083],"type":"Point"}
}