{
  "type": "Feature",
  "properties": {
    "gn:admin1_code":"4.0",
    "gn:admin2_code":"TNN",
    "gn:admin3_code":"R25",
    "gn:admin4_code":"67000250008.0",
    "gn:asciiname":"Maobu",
    "gn:country_code":"TW",
    "gn:dem":131,
    "gn:feature_class":"P",
    "gn:feature_code":"PPL",
    "gn:name":"Maobu",
    "gn:population":0,
    "gn:timezone":"Asia/Taipei",
    "iso:country":"TW",
    "name:und_x_variant":[
        "Man-pu",
        "Mao-pu"
    ],
    "name:zho_x_preferred":[
        "\u8305\u57d4"
    ],
    "wof:name":"Maobu",
    "wof:placetype":"locality"
},
  "geometry": {"coordinates":[120.52443999999998,23.08361],"type":"Point"}
}