{
  "type": "Feature",
  "properties": {
    "gn:admin1_code":"4.0",
    "gn:admin2_code":"TXG",
    "gn:admin3_code":"B14",
    "gn:admin4_code":"66000140012.0",
    "gn:asciiname":"Huoshaoqiao",
    "gn:country_code":"TW",
    "gn:dem":6,
    "gn:feature_class":"P",
    "gn:feature_code":"PPL",
    "gn:name":"Huoshaoqiao",
    "gn:population":0,
    "gn:timezone":"Asia/Taipei",
    "iso:country":"TW",
    "name:und_x_variant":[
        "Huoshaociao",
        "Huoshaoqiao"
    ],
    "name:zho_x_preferred":[
        "\u706b\u71d2\u6a4b"
    ],
    "name:zho_x_variant":[
        "Huo-shao-ch\u2019iao"
    ],
    "wof:name":"Huoshaoqiao",
    "wof:placetype":"locality"
},
  "geometry": {"coordinates":[120.53682999999999,24.23841],"type":"Point"}
}