{
  "type": "Feature",
  "properties": {
    "gn:admin1_code":"4.0",
    "gn:admin2_code":"YUN",
    "gn:admin3_code":"P02",
    "gn:admin4_code":"10009020014.0",
    "gn:asciiname":"Wen'an",
    "gn:country_code":"TW",
    "gn:dem":35,
    "gn:feature_class":"P",
    "gn:feature_code":"PPL",
    "gn:name":"Wen\u2019an",
    "gn:population":0,
    "gn:timezone":"Asia/Taipei",
    "iso:country":"TW",
    "name:und_x_variant":[
        "Wen-an"
    ],
    "name:zho_x_preferred":[
        "\u6587\u5b89"
    ],
    "name:zho_x_variant":[
        "Wun\u2019an",
        "Wen\u2019an"
    ],
    "wof:name":"Wen'an",
    "wof:placetype":"locality"
},
  "geometry": {"coordinates":[120.48300999999999,23.69035],"type":"Point"}
}