{
  "type": "Feature",
  "properties": {
    "gn:admin1_code":"4.0",
    "gn:admin2_code":"NAN",
    "gn:admin3_code":"M02",
    "gn:admin4_code":"10008020029.0",
    "gn:asciiname":"Sankuaicuo",
    "gn:country_code":"TW",
    "gn:dem":689,
    "gn:feature_class":"P",
    "gn:feature_code":"PPL",
    "gn:name":"Sankuaicuo",
    "gn:population":0,
    "gn:timezone":"Asia/Taipei",
    "iso:country":"TW",
    "name:zho_x_preferred":[
        "\u4e09\u584a\u539d"
    ],
    "name:zho_x_variant":[
        "San-k\u2019uai-ts\u2019o"
    ],
    "wof:name":"Sankuaicuo",
    "wof:placetype":"locality"
},
  "geometry": {"coordinates":[120.92278,24.02713],"type":"Point"}
}