{
  "type": "Feature",
  "properties": {
    "gn:admin1_code":"4.0",
    "gn:admin2_code":"KEE",
    "gn:admin3_code":"C02",
    "gn:admin4_code":"10017020016.0",
    "gn:asciiname":"Qifenliao",
    "gn:country_code":"TW",
    "gn:dem":349,
    "gn:feature_class":"P",
    "gn:feature_code":"PPL",
    "gn:name":"Qifenliao",
    "gn:population":0,
    "gn:timezone":"Asia/Taipei",
    "iso:country":"TW",
    "name:und_x_variant":[
        "Cifenliao"
    ],
    "name:zho_x_preferred":[
        "\u4e03\u5206\u5bee"
    ],
    "name:zho_x_variant":[
        "Ch\u2019i-fen",
        "Ch\u2019i-fen-liao"
    ],
    "wof:name":"Qifenliao",
    "wof:placetype":"locality"
},
  "geometry": {"coordinates":[121.63851,25.13817],"type":"Point"}
}