{
  "type": "Feature",
  "properties": {
    "gn:admin1_code":"3.0",
    "gn:admin2_code":"TPQ",
    "gn:admin3_code":"F27",
    "gn:admin4_code":"65000100003.0",
    "gn:asciiname":"Baliduiwei",
    "gn:country_code":"TW",
    "gn:dem":77,
    "gn:feature_class":"P",
    "gn:feature_code":"PPL",
    "gn:name":"Baliduiwei",
    "gn:population":0,
    "gn:timezone":"Asia/Taipei",
    "iso:country":"TW",
    "name:und_x_variant":[
        "Balidueiwei",
        "Baliduiwei",
        "Pa-li-tui-wei"
    ],
    "name:zho_x_preferred":[
        "\u516b\u91cc\u5806\u5c3e"
    ],
    "wof:name":"Baliduiwei",
    "wof:placetype":"locality"
},
  "geometry": {"coordinates":[121.46368,25.22653],"type":"Point"}
}