{
  "type": "Feature",
  "properties": {
    "iso:country":"TW",
    "name:eng_x_preferred":[
        "Puwei"
    ],
    "name:eng_x_variant":[
        "Puwei Village"
    ],
    "name:zho_tw_x_preferred":[
        "\u57d4\u5c3e\u6751"
    ],
    "qs:name":"\u57d4\u5c3e\u6751",
    "qs:name_adm0":"\u81fa\u7063",
    "qs:name_adm1":"\u65b0\u7af9\u7e23",
    "qs:photos":31,
    "qs:photos_1k":6,
    "qs:photos_9k":1,
    "qs:photos_9r":2,
    "qs:photos_all":31,
    "qs:photos_sr":2,
    "qs:placetype":"Town",
    "qs:pop_sr":"0",
    "wof:name":"Puwei",
    "wof:placetype":"locality"
},
  "geometry": {"coordinates":[121.042722,24.717519],"type":"Point"}
}