{
  "type": "Feature",
  "properties": {
    "gn:admin1_code":"4.0",
    "gn:admin2_code":"TTT",
    "gn:admin3_code":"V03",
    "gn:admin4_code":"10014030007.0",
    "gn:asciiname":"Zhonghe",
    "gn:country_code":"TW",
    "gn:dem":198,
    "gn:feature_class":"P",
    "gn:feature_code":"PPL",
    "gn:name":"Zhonghe",
    "gn:population":0,
    "gn:timezone":"Asia/Taipei",
    "iso:country":"TW",
    "name:und_x_variant":[
        "Jhonghe",
        "Zhonghe",
        "Chung-ho"
    ],
    "name:zho_x_preferred":[
        "\u4e2d\u548c"
    ],
    "wof:name":"Zhonghe",
    "wof:placetype":"locality"
},
  "geometry": {"coordinates":[121.15167,23.01417],"type":"Point"}
}