{
  "type": "Feature",
  "properties": {
    "gn:admin1_code":"4.0",
    "gn:admin2_code":"HSZ",
    "gn:admin3_code":"J13",
    "gn:admin4_code":"10004110005.0",
    "gn:asciiname":"Xiangjiaowo",
    "gn:country_code":"TW",
    "gn:dem":163,
    "gn:feature_class":"P",
    "gn:feature_code":"PPL",
    "gn:name":"Xiangjiaowo",
    "gn:population":0,
    "gn:timezone":"Asia/Taipei",
    "iso:country":"TW",
    "name:und_x_variant":[
        "Siangjiaowo",
        "Xiangjiaowo",
        "Hsiang-chiao-wo"
    ],
    "name:zho_x_preferred":[
        "\u9999\u8549\u7aa9"
    ],
    "wof:name":"Xiangjiaowo",
    "wof:placetype":"locality"
},
  "geometry": {"coordinates":[121.03806000000002,24.66222],"type":"Point"}
}