{
  "type": "Feature",
  "properties": {
    "gn:admin1_code":"4.0",
    "gn:admin2_code":"CHA",
    "gn:admin3_code":"N03",
    "gn:admin4_code":"10007030017.0",
    "gn:asciiname":"Xiaganzitou",
    "gn:country_code":"TW",
    "gn:dem":16,
    "gn:feature_class":"P",
    "gn:feature_code":"PPL",
    "gn:name":"Xiaganzitou",
    "gn:population":0,
    "gn:timezone":"Asia/Taipei",
    "iso:country":"TW",
    "name:und_x_variant":[
        "Xiaganzitou",
        "Siaganzihtou"
    ],
    "name:zho_x_preferred":[
        "\u4e0b\u67d1\u5b50\u982d"
    ],
    "name:zho_x_variant":[
        "Hsia-kan-tzu-t\u2019ou"
    ],
    "wof:name":"Xiaganzitou",
    "wof:placetype":"locality"
},
  "geometry": {"coordinates":[120.51715,24.10424],"type":"Point"}
}