{
  "type": "Feature",
  "properties": {
    "gn:admin1_code":"04",
    "gn:admin2_code":"TNN",
    "gn:admin3_code":"R12",
    "gn:admin4_code":"67000120016.0",
    "gn:asciiname":"Buding",
    "gn:country_code":"TW",
    "gn:dem":3,
    "gn:feature_class":"P",
    "gn:feature_code":"PPL",
    "gn:name":"Buding",
    "gn:population":0,
    "gn:timezone":"Asia/Taipei",
    "iso:country":"TW",
    "name:cat_x_preferred":[
        "Buding"
    ],
    "name:ceb_x_preferred":[
        "Buding"
    ],
    "name:deu_x_preferred":[
        "Buding"
    ],
    "name:eus_x_preferred":[
        "Buding"
    ],
    "name:fas_x_preferred":[
        "\u0628\u0648\u062f\u06cc\u0646\u06af"
    ],
    "name:fra_x_preferred":[
        "Buding"
    ],
    "name:hun_x_preferred":[
        "Buding"
    ],
    "name:ita_x_preferred":[
        "Buding"
    ],
    "name:kaz_x_preferred":[
        "\u0411\u044e\u0434\u0435\u043d"
    ],
    "name:lat_x_preferred":[
        "Buding"
    ],
    "name:ltz_x_preferred":[
        "Buding"
    ],
    "name:msa_x_preferred":[
        "Buding"
    ],
    "name:nld_x_preferred":[
        "Buding"
    ],
    "name:oci_x_preferred":[
        "Buding"
    ],
    "name:pfl_x_preferred":[
        "Buding"
    ],
    "name:pms_x_preferred":[
        "Buding"
    ],
    "name:pol_x_preferred":[
        "Buding"
    ],
    "name:por_x_preferred":[
        "Buding"
    ],
    "name:slk_x_preferred":[
        "Buding"
    ],
    "name:spa_x_preferred":[
        "Buding"
    ],
    "name:srp_x_preferred":[
        "\u0411\u0443\u0434\u0438\u043d\u0433"
    ],
    "name:swe_x_preferred":[
        "Buding"
    ],
    "name:ukr_x_preferred":[
        "\u0411\u044e\u0434\u0435\u043d"
    ],
    "name:und_x_variant":[
        "Pu-ting"
    ],
    "name:uzb_x_preferred":[
        "Buding"
    ],
    "name:vie_x_preferred":[
        "Buding"
    ],
    "name:vol_x_preferred":[
        "Buding"
    ],
    "name:war_x_preferred":[
        "Buding"
    ],
    "name:zho_x_preferred":[
        "\u57d4\u9802"
    ],
    "wof:name":"Buding",
    "wof:placetype":"locality"
},
  "geometry": {"coordinates":[120.15667000000001,23.145],"type":"Point"}
}