{
  "type": "Feature",
  "properties": {
    "gn:admin1_code":"4.0",
    "gn:admin2_code":"PIF",
    "gn:admin3_code":"T16",
    "gn:admin4_code":"10013160013.0",
    "gn:asciiname":"Nanshan",
    "gn:country_code":"TW",
    "gn:dem":92,
    "gn:feature_class":"P",
    "gn:feature_code":"PPL",
    "gn:name":"Nanshan",
    "gn:population":0,
    "gn:timezone":"Asia/Taipei",
    "iso:country":"TW",
    "name:und_x_variant":[
        "\u5357\u5c71",
        "Nanshan",
        "Nan-shan"
    ],
    "name:zho_x_preferred":[
        "\u5357\u5c71"
    ],
    "wof:name":"Nanshan",
    "wof:placetype":"locality"
},
  "geometry": {"coordinates":[120.61499999999999,22.41806],"type":"Point"}
}