{
  "type": "Feature",
  "properties": {
    "gn:admin1_code":"4.0",
    "gn:admin2_code":"NAN",
    "gn:admin3_code":"M08",
    "gn:admin4_code":"10008080009.0",
    "gn:asciiname":"Luliaokeng",
    "gn:country_code":"TW",
    "gn:dem":190,
    "gn:feature_class":"P",
    "gn:feature_code":"PPL",
    "gn:name":"Luliaokeng",
    "gn:population":0,
    "gn:timezone":"Asia/Taipei",
    "iso:country":"TW",
    "name:zho_x_preferred":[
        "\u9e7f\u5bee\u5751"
    ],
    "name:zho_x_variant":[
        "Lu-liao-k\u2019eng"
    ],
    "wof:name":"Luliaokeng",
    "wof:placetype":"locality"
},
  "geometry": {"coordinates":[120.76904999999999,23.90854],"type":"Point"}
}