{
  "type": "Feature",
  "properties": {
    "gn:admin1_code":"04",
    "gn:admin2_code":"PIF",
    "gn:admin3_code":"T21",
    "gn:admin4_code":"10013210004.0",
    "gn:asciiname":"Yuguang",
    "gn:country_code":"TW",
    "gn:dem":15,
    "gn:feature_class":"P",
    "gn:feature_code":"PPL",
    "gn:name":"Yuguang",
    "gn:population":0,
    "gn:timezone":"Asia/Taipei",
    "iso:country":"TW",
    "name:und_x_variant":[
        "Shih-kuang-chien",
        "Y\u00fc-kuang-ts\u2019un",
        "\u7389\u5149",
        "Yuguang"
    ],
    "name:zho_x_preferred":[
        "Y\u00fc-kuang"
    ],
    "wof:name":"Yuguang",
    "wof:placetype":"locality"
},
  "geometry": {"coordinates":[120.56222,22.42722],"type":"Point"}
}