{
  "type": "Feature",
  "properties": {
    "gn:admin1_code":"04",
    "gn:admin2_code":"TNN",
    "gn:admin3_code":"R13",
    "gn:admin4_code":"67000140003.0",
    "gn:asciiname":"Shuangzhangbu",
    "gn:country_code":"TW",
    "gn:dem":11,
    "gn:feature_class":"P",
    "gn:feature_code":"PPL",
    "gn:name":"Shuangzhangbu",
    "gn:population":0,
    "gn:timezone":"Asia/Taipei",
    "iso:country":"TW",
    "name:und_x_variant":[
        "Shuangjhangbu",
        "Shuangzhangbu",
        "Shuang-chang-pu"
    ],
    "name:zho_x_preferred":[
        "\u96d9\u5f35\u5ecd"
    ],
    "wof:name":"Shuangzhangbu",
    "wof:placetype":"locality"
},
  "geometry": {"coordinates":[120.21306,23.12],"type":"Point"}
}