{
  "type": "Feature",
  "properties": {
    "gn:admin1_code":"4.0",
    "gn:admin2_code":"TTT",
    "gn:admin3_code":"V08",
    "gn:admin4_code":"10014080002.0",
    "gn:asciiname":"Xionglun",
    "gn:country_code":"TW",
    "gn:dem":339,
    "gn:feature_class":"P",
    "gn:feature_code":"PPL",
    "gn:name":"Xionglun",
    "gn:population":0,
    "gn:timezone":"Asia/Taipei",
    "iso:country":"TW",
    "name:und_x_variant":[
        "Syonglun",
        "Hsiung-lun"
    ],
    "name:zho_x_preferred":[
        "\u718a\u5d19"
    ],
    "wof:name":"Xionglun",
    "wof:placetype":"locality"
},
  "geometry": {"coordinates":[121.44936,23.36361],"type":"Point"}
}