{
  "type": "Feature",
  "properties": {
    "gn:admin1_code":"04",
    "gn:admin2_code":"TAO",
    "gn:admin3_code":"H06",
    "gn:admin4_code":"68000060015.0",
    "gn:asciiname":"Pojiao",
    "gn:country_code":"TW",
    "gn:dem":19,
    "gn:feature_class":"P",
    "gn:feature_code":"PPL",
    "gn:name":"Pojiao",
    "gn:population":0,
    "gn:timezone":"Asia/Taipei",
    "iso:country":"TW",
    "name:zho_x_preferred":[
        "\u5761\u8173"
    ],
    "name:zho_x_variant":[
        "P\u2019o-chiao"
    ],
    "wof:name":"Pojiao",
    "wof:placetype":"locality"
},
  "geometry": {"coordinates":[121.22307000000001,25.08622],"type":"Point"}
}