{
  "type": "Feature",
  "properties": {
    "gn:admin1_code":"4.0",
    "gn:admin2_code":"MIA",
    "gn:admin3_code":"K01",
    "gn:admin4_code":"10005010006.0",
    "gn:asciiname":"Wuzhiliao",
    "gn:country_code":"TW",
    "gn:dem":57,
    "gn:feature_class":"P",
    "gn:feature_code":"PPL",
    "gn:name":"Wuzhiliao",
    "gn:population":0,
    "gn:timezone":"Asia/Taipei",
    "iso:country":"TW",
    "name:und_x_variant":[
        "Wujhihliao",
        "Wu-chih-liao"
    ],
    "name:zho_x_preferred":[
        "\u4e94\u96bb\u5bee"
    ],
    "wof:name":"Wuzhiliao",
    "wof:placetype":"locality"
},
  "geometry": {"coordinates":[120.82648,24.54848],"type":"Point"}
}