{
  "type": "Feature",
  "properties": {
    "gn:admin1_code":"3.0",
    "gn:admin2_code":"TPQ",
    "gn:admin3_code":"F01",
    "gn:admin4_code":"65000050043.0",
    "gn:asciiname":"Guizikeng",
    "gn:country_code":"TW",
    "gn:dem":65,
    "gn:feature_class":"P",
    "gn:feature_code":"PPL",
    "gn:name":"Guizikeng",
    "gn:population":0,
    "gn:timezone":"Asia/Taipei",
    "iso:country":"TW",
    "name:und_x_variant":[
        "Gueizihkeng",
        "Guizikeng"
    ],
    "name:zho_x_preferred":[
        "\u8cb4\u5b50\u5751"
    ],
    "name:zho_x_variant":[
        "Kuei-tzu-k\u2019eng"
    ],
    "wof:name":"Guizikeng",
    "wof:placetype":"locality"
},
  "geometry": {"coordinates":[121.41303000000001,25.03032],"type":"Point"}
}