{
  "type": "Feature",
  "properties": {
    "gn:admin1_code":"4.0",
    "gn:admin2_code":"CYQ",
    "gn:admin3_code":"Q05",
    "gn:admin4_code":"10010050005.0",
    "gn:asciiname":"Xialiao",
    "gn:country_code":"TW",
    "gn:dem":25,
    "gn:feature_class":"P",
    "gn:feature_code":"PPL",
    "gn:name":"Xialiao",
    "gn:population":0,
    "gn:timezone":"Asia/Taipei",
    "iso:country":"TW",
    "name:und_x_variant":[
        "Sialiao",
        "Hsia-liao"
    ],
    "name:zho_x_preferred":[
        "\u4e0b\u5bee"
    ],
    "wof:name":"Xialiao",
    "wof:placetype":"locality"
},
  "geometry": {"coordinates":[120.42098,23.57063],"type":"Point"}
}