{
  "type": "Feature",
  "properties": {
    "gn:admin1_code":"4.0",
    "gn:admin2_code":"HSQ",
    "gn:admin3_code":"O01",
    "gn:admin4_code":"10018010047.0",
    "gn:asciiname":"Luzikeng",
    "gn:country_code":"TW",
    "gn:dem":148,
    "gn:feature_class":"P",
    "gn:feature_code":"PPL",
    "gn:name":"Luzikeng",
    "gn:population":0,
    "gn:timezone":"Asia/Taipei",
    "iso:country":"TW",
    "name:und_x_variant":[
        "Luzihkeng"
    ],
    "name:zho_x_preferred":[
        "\u9e7f\u4ed4\u5751"
    ],
    "name:zho_x_variant":[
        "Lu-tzu-k\u2019eng"
    ],
    "wof:name":"Luzikeng",
    "wof:placetype":"locality"
},
  "geometry": {"coordinates":[121.01917,24.76167],"type":"Point"}
}