{
  "type": "Feature",
  "properties": {
    "gn:admin1_code":"4.0",
    "gn:admin2_code":"TXG",
    "gn:admin3_code":"B25",
    "gn:admin4_code":"66000250013.0",
    "gn:asciiname":"Xinzhuangzi",
    "gn:country_code":"TW",
    "gn:dem":232,
    "gn:feature_class":"P",
    "gn:feature_code":"PPL",
    "gn:name":"Xinzhuangzi",
    "gn:population":0,
    "gn:timezone":"Asia/Taipei",
    "iso:country":"TW",
    "name:und_x_variant":[
        "Hsin-ts\u2019un",
        "Hsin-chuang-ts\u2019un",
        "Hsin-chuang",
        "Xinzhuangzi",
        "Sinjhuangzih",
        "Hsin-chuang-tzu"
    ],
    "name:zho_x_preferred":[
        "\u65b0\u838a\u5b50"
    ],
    "wof:name":"Xinzhuangzi",
    "wof:placetype":"locality"
},
  "geometry": {"coordinates":[120.5766,24.1824],"type":"Point"}
}