{
  "type": "Feature",
  "properties": {
    "gn:admin1_code":"4.0",
    "gn:admin2_code":"TXG",
    "gn:admin3_code":"B28",
    "gn:admin4_code":"66000280020.0",
    "gn:asciiname":"Xialun",
    "gn:country_code":"TW",
    "gn:dem":44,
    "gn:feature_class":"P",
    "gn:feature_code":"PPL",
    "gn:name":"Xialun",
    "gn:population":0,
    "gn:timezone":"Asia/Taipei",
    "iso:country":"TW",
    "name:und_x_variant":[
        "\u4e0b\u5d19",
        "Sialun",
        "Hsia-chuang",
        "Xialun",
        "Hsia-lun"
    ],
    "wof:name":"Xialun",
    "wof:placetype":"locality"
},
  "geometry": {"coordinates":[120.6841,24.0831],"type":"Point"}
}