{
  "type": "Feature",
  "properties": {
    "iso:country":"TW",
    "qs:name":"\u5927\u7fa9\u6751",
    "qs:name_adm0":"\u81fa\u7063",
    "qs:name_adm1":"\u5b9c\u862d\u7e23",
    "qs:photos":309,
    "qs:photos_1k":63,
    "qs:photos_9k":1,
    "qs:photos_9r":5,
    "qs:photos_all":309,
    "qs:photos_sr":5,
    "qs:placetype":"Town",
    "qs:pop_sr":"0",
    "wof:name":"\u5927\u7fa9\u6751",
    "wof:placetype":"locality"
},
  "geometry": {"coordinates":[121.769778,24.822272],"type":"Point"}
}