{
  "type": "Feature",
  "properties": {
    "gn:admin1_code":"04",
    "gn:admin2_code":"KEE",
    "gn:admin3_code":"C05",
    "gn:admin4_code":"10017050012.0",
    "gn:asciiname":"Jingshui'ao",
    "gn:country_code":"TW",
    "gn:dem":11,
    "gn:feature_class":"P",
    "gn:feature_code":"PPL",
    "gn:name":"Jingshui\u2019ao",
    "gn:population":0,
    "gn:timezone":"Asia/Taipei",
    "iso:country":"TW",
    "name:und_x_variant":[
        "Ching-shui-ao"
    ],
    "name:zho_x_preferred":[
        "\u6c6b\u6c34\u6fb3"
    ],
    "name:zho_x_variant":[
        "Jingshui\u2019ao",
        "Jingshuei\u2019ao",
        "T\u2019an-shui-ao"
    ],
    "wof:name":"Jingshui'ao",
    "wof:placetype":"locality"
},
  "geometry": {"coordinates":[121.72471000000002,25.16378],"type":"Point"}
}