{
  "type": "Feature",
  "properties": {
    "gn:admin1_code":"04",
    "gn:admin2_code":"CYQ",
    "gn:admin3_code":"Q07",
    "gn:admin4_code":"10010070020.0",
    "gn:asciiname":"Tanziqian",
    "gn:country_code":"TW",
    "gn:dem":13,
    "gn:feature_class":"P",
    "gn:feature_code":"PPL",
    "gn:name":"Tanziqian",
    "gn:population":0,
    "gn:timezone":"Asia/Taipei",
    "iso:country":"TW",
    "name:und_x_variant":[
        "Tanzihcian"
    ],
    "name:zho_x_preferred":[
        "\u6f6d\u5b50\u5898"
    ],
    "name:zho_x_variant":[
        "T\u2019an-tzu-ch\u2019ien"
    ],
    "wof:name":"Tanziqian",
    "wof:placetype":"locality"
},
  "geometry": {"coordinates":[120.33528,23.54196],"type":"Point"}
}