{
  "type": "Feature",
  "properties": {
    "gn:admin1_code":"4.0",
    "gn:admin2_code":"HSZ",
    "gn:admin3_code":"J03",
    "gn:admin4_code":"10004040017.0",
    "gn:asciiname":"Chikeliao",
    "gn:country_code":"TW",
    "gn:dem":236,
    "gn:feature_class":"P",
    "gn:feature_code":"PPL",
    "gn:name":"Chikeliao",
    "gn:population":0,
    "gn:timezone":"Asia/Taipei",
    "iso:country":"TW",
    "name:und_x_variant":[
        "Chihkeliao",
        "Chikeliao"
    ],
    "name:zho_x_preferred":[
        "\u8d64\u67ef\u5bee"
    ],
    "name:zho_x_variant":[
        "Ch\u2019ih-k\u2019o-liao"
    ],
    "wof:name":"Chikeliao",
    "wof:placetype":"locality"
},
  "geometry": {"coordinates":[121.11888999999999,24.77333],"type":"Point"}
}