{
  "type": "Feature",
  "properties": {
    "gn:admin1_code":"4.0",
    "gn:admin2_code":"MIA",
    "gn:admin3_code":"K06",
    "gn:admin4_code":"10005130003.0",
    "gn:asciiname":"Shuangliantan",
    "gn:country_code":"TW",
    "gn:dem":300,
    "gn:feature_class":"P",
    "gn:feature_code":"PPL",
    "gn:name":"Shuangliantan",
    "gn:population":0,
    "gn:timezone":"Asia/Taipei",
    "iso:country":"TW",
    "name:und_x_variant":[
        "Hsin-chuang",
        "Hsin-chi",
        "Shuangliantan"
    ],
    "name:zho_x_preferred":[
        "Shuang-t\u2019an-ts\u2019un"
    ],
    "name:zho_x_variant":[
        "\u96d9\u9023\u6f6d",
        "Shuang-t\u2019an",
        "Shuang-lien-t\u2019an"
    ],
    "wof:name":"Shuangliantan",
    "wof:placetype":"locality"
},
  "geometry": {"coordinates":[120.78700000000001,24.41027],"type":"Point"}
}