{
  "type": "Feature",
  "properties": {
    "gn:country":"TW",
    "gn:fcode":"ADMD",
    "gn:pop":0,
    "iso:country":"TW",
    "name:unk_x_variant":[
        "\u5317\u5340"
    ],
    "qs:name":"Bei Qu",
    "qs:photos_9r":0,
    "qs:photos_sr":0,
    "qs:pop_sr":"0",
    "wd:wordcount":88,
    "wof:name":"Bei Qu",
    "wof:placetype":"localadmin",
    "wof:population":0
},
  "geometry": {"coordinates":[120.94934000000001,24.81641],"type":"Point"}
}