{
  "type": "Feature",
  "properties": {
    "gn:admin1_code":"4.0",
    "gn:admin2_code":"NAN",
    "gn:admin3_code":"M03",
    "gn:admin4_code":"10008030021.0",
    "gn:asciiname":"Zhuweizi",
    "gn:country_code":"TW",
    "gn:dem":372,
    "gn:feature_class":"P",
    "gn:feature_code":"PPL",
    "gn:name":"Zhuweizi",
    "gn:population":0,
    "gn:timezone":"Asia/Taipei",
    "iso:country":"TW",
    "name:und_x_variant":[
        "Jhuweizih",
        "Chu-wei-tzu"
    ],
    "name:zho_x_preferred":[
        "\u7af9\u570d\u5b50"
    ],
    "wof:name":"Zhuweizi",
    "wof:placetype":"locality"
},
  "geometry": {"coordinates":[120.7448,23.9677],"type":"Point"}
}