{
  "type": "Feature",
  "properties": {
    "gn:admin1_code":"4.0",
    "gn:admin2_code":"NAN",
    "gn:admin3_code":"M07",
    "gn:admin4_code":"10008070007.0",
    "gn:asciiname":"Shuangxidi",
    "gn:country_code":"TW",
    "gn:dem":319,
    "gn:feature_class":"P",
    "gn:feature_code":"PPL",
    "gn:name":"Shuangxidi",
    "gn:population":0,
    "gn:timezone":"Asia/Taipei",
    "iso:country":"TW",
    "name:und_x_variant":[
        "Shuangsidi",
        "Shuang-hsi-ti"
    ],
    "name:zho_x_preferred":[
        "\u96d9\u6eaa\u5e95"
    ],
    "wof:name":"Shuangxidi",
    "wof:placetype":"locality"
},
  "geometry": {"coordinates":[120.73166999999999,23.74083],"type":"Point"}
}