{
  "type": "Feature",
  "properties": {
    "gn:admin1_code":"4.0",
    "gn:admin2_code":"CHA",
    "gn:admin3_code":"N07",
    "gn:admin4_code":"10007120005.0",
    "gn:asciiname":"Jinmaozhuang",
    "gn:country_code":"TW",
    "gn:dem":94,
    "gn:feature_class":"P",
    "gn:feature_code":"PPL",
    "gn:name":"Jinmaozhuang",
    "gn:population":0,
    "gn:timezone":"Asia/Taipei",
    "iso:country":"TW",
    "name:und_x_variant":[
        "Jinmaojhuang",
        "Jinmaozhuang",
        "Chin-yen",
        "Chin-mao-chuang"
    ],
    "name:zho_x_preferred":[
        "\u9326\u6bdb\u5e84"
    ],
    "wof:name":"Jinmaozhuang",
    "wof:placetype":"locality"
},
  "geometry": {"coordinates":[120.60980000000001,23.8733],"type":"Point"}
}