{
  "type": "Feature",
  "properties": {
    "gn:admin1_code":"04",
    "gn:admin2_code":"TNN",
    "gn:admin3_code":"R15",
    "gn:admin4_code":"67000160008.0",
    "gn:asciiname":"Shezi",
    "gn:country_code":"TW",
    "gn:dem":4,
    "gn:feature_class":"P",
    "gn:feature_code":"PPL",
    "gn:name":"Shezi",
    "gn:population":0,
    "gn:timezone":"Asia/Taipei",
    "iso:country":"TW",
    "name:und_x_variant":[
        "Shezih",
        "She-tzu"
    ],
    "name:zho_x_preferred":[
        "\u793e\u5b50"
    ],
    "wof:name":"Shezi",
    "wof:placetype":"locality"
},
  "geometry": {"coordinates":[120.15611,23.22528],"type":"Point"}
}