{
  "type": "Feature",
  "properties": {
    "gn:admin1_code":"04",
    "gn:admin2_code":"HSZ",
    "gn:admin3_code":"J05",
    "gn:admin4_code":"10004010023.0",
    "gn:asciiname":"Dingxizhou",
    "gn:country_code":"TW",
    "gn:dem":14,
    "gn:feature_class":"P",
    "gn:feature_code":"PPL",
    "gn:name":"Dingxizhou",
    "gn:population":0,
    "gn:timezone":"Asia/Taipei",
    "iso:country":"TW",
    "name:und_x_variant":[
        "Dingsijhou",
        "Dingxizhou",
        "Ting-hsi-chou"
    ],
    "name:zho_x_preferred":[
        "Ting-ch\u2019i-chou"
    ],
    "name:zho_x_variant":[
        "\u9802\u6eaa\u6d32"
    ],
    "wof:name":"Dingxizhou",
    "wof:placetype":"locality"
},
  "geometry": {"coordinates":[120.97472,24.83278],"type":"Point"}
}