{
  "type": "Feature",
  "properties": {
    "iso:country":"TW",
    "qs:name":"\u9727\u9e7f\u6751",
    "qs:name_adm0":"\u81fa\u7063",
    "qs:name_adm1":"\u53f0\u6771\u7e23",
    "qs:photos":41,
    "qs:photos_1k":8,
    "qs:photos_9k":1,
    "qs:photos_9r":2,
    "qs:photos_all":41,
    "qs:photos_sr":2,
    "qs:placetype":"Town",
    "qs:pop_sr":"0",
    "wof:name":"\u9727\u9e7f\u6751",
    "wof:placetype":"locality"
},
  "geometry": {"coordinates":[121.02340599999999,23.187075],"type":"Point"}
}