{
  "type": "Feature",
  "properties": {
    "gn:admin1_code":"3.0",
    "gn:admin2_code":"TPQ",
    "gn:admin3_code":"F02",
    "gn:admin4_code":"65000170012.0",
    "gn:asciiname":"Zhongfu",
    "gn:country_code":"TW",
    "gn:dem":18,
    "gn:feature_class":"P",
    "gn:feature_code":"PPL",
    "gn:name":"Zhongfu",
    "gn:population":0,
    "gn:timezone":"Asia/Taipei",
    "iso:country":"TW",
    "name:und_x_variant":[
        "Jhongfu",
        "Chung-fu"
    ],
    "name:zho_x_preferred":[
        "\u4e2d\u798f"
    ],
    "wof:name":"Zhongfu",
    "wof:placetype":"locality"
},
  "geometry": {"coordinates":[121.32102,25.12079],"type":"Point"}
}