{
  "type": "Feature",
  "properties": {
    "gn:admin1_code":"4.0",
    "gn:admin2_code":"TNN",
    "gn:admin3_code":"R25",
    "gn:admin4_code":"67000250009.0",
    "gn:asciiname":"Shibiliao",
    "gn:country_code":"TW",
    "gn:dem":194,
    "gn:feature_class":"P",
    "gn:feature_code":"PPL",
    "gn:name":"Shibiliao",
    "gn:population":0,
    "gn:timezone":"Asia/Taipei",
    "iso:country":"TW",
    "name:und_x_variant":[
        "Shihbiliao",
        "Shibiliao",
        "Shih-pi-liao"
    ],
    "name:zho_x_preferred":[
        "\u77f3\u58c1\u5bee"
    ],
    "wof:name":"Shibiliao",
    "wof:placetype":"locality"
},
  "geometry": {"coordinates":[120.55889000000001,23.11278],"type":"Point"}
}