{
  "type": "Feature",
  "properties": {
    "gn:admin1_code":"4.0",
    "gn:admin2_code":"MIA",
    "gn:admin3_code":"K13",
    "gn:admin4_code":"10005160006.0",
    "gn:asciiname":"Xi'ai",
    "gn:country_code":"TW",
    "gn:dem":89,
    "gn:feature_class":"P",
    "gn:feature_code":"PPL",
    "gn:name":"Xi\u2019ai",
    "gn:population":0,
    "gn:timezone":"Asia/Taipei",
    "iso:country":"TW",
    "name:und_x_variant":[
        "Hsi-i-tzu",
        "Hsi-yai-tzu",
        "Hsi-ai-tzu",
        "Hsi-ai"
    ],
    "name:zho_x_preferred":[
        "\u932b\u9698"
    ],
    "name:zho_x_variant":[
        "Si\u2019ai",
        "Xi\u2019ai"
    ],
    "wof:name":"Xi'ai",
    "wof:placetype":"locality"
},
  "geometry": {"coordinates":[120.95341000000001,24.62164],"type":"Point"}
}