{
  "type": "Feature",
  "properties": {
    "iso:country":"TW",
    "qs:name":"\u5357\u8208\u6751",
    "qs:name_adm0":"\u81fa\u7063",
    "qs:name_adm1":"\u5b9c\u862d\u7e23",
    "qs:photos":50,
    "qs:photos_1k":10,
    "qs:photos_9k":1,
    "qs:photos_9r":2,
    "qs:photos_all":50,
    "qs:photos_sr":2,
    "qs:placetype":"Town",
    "qs:pop_sr":"0",
    "wof:name":"\u5357\u8208\u6751",
    "wof:placetype":"locality"
},
  "geometry": {"coordinates":[121.792248,24.633383],"type":"Point"}
}