{
  "type": "Feature",
  "properties": {
    "iso:country":"TW",
    "qs:name":"\u5065\u884c\u91cc",
    "qs:name_adm0":"\u81fa\u7063",
    "qs:name_adm1":"\u53f0\u4e2d\u5e02",
    "qs:photos":848,
    "qs:photos_1k":172,
    "qs:photos_9k":4,
    "qs:photos_9r":6,
    "qs:photos_all":848,
    "qs:photos_sr":9,
    "qs:placetype":"Suburb",
    "qs:pop_sr":"0",
    "wof:name":"\u5065\u884c\u91cc",
    "wof:placetype":"neighbourhood"
},
  "geometry": {"coordinates":[120.67059999999999,24.161586],"type":"Point"}
}