{
  "type": "Feature",
  "properties": {
    "gn:admin1_code":"4.0",
    "gn:admin2_code":"TAO",
    "gn:admin3_code":"H13",
    "gn:admin4_code":"68000130010.0",
    "gn:asciiname":"Li'an",
    "gn:country_code":"TW",
    "gn:dem":670,
    "gn:feature_class":"P",
    "gn:feature_code":"PPL",
    "gn:name":"Li\u2019an",
    "gn:population":0,
    "gn:timezone":"Asia/Taipei",
    "iso:country":"TW",
    "name:und_x_variant":[
        "Li-an"
    ],
    "name:zho_x_preferred":[
        "\u91cc\u5b89"
    ],
    "name:zho_x_variant":[
        "Li\u2019an"
    ],
    "wof:name":"Li'an",
    "wof:placetype":"locality"
},
  "geometry": {"coordinates":[121.35417,24.72667],"type":"Point"}
}