{
  "type": "Feature",
  "properties": {
    "gn:admin1_code":"04",
    "gn:admin2_code":"YUN",
    "gn:admin3_code":"P07",
    "gn:admin4_code":"10009070004.0",
    "gn:asciiname":"Banliaobu",
    "gn:country_code":"TW",
    "gn:dem":319,
    "gn:feature_class":"P",
    "gn:feature_code":"PPL",
    "gn:name":"Banliaobu",
    "gn:population":0,
    "gn:timezone":"Asia/Taipei",
    "iso:country":"TW",
    "name:und_x_variant":[
        "Fang-liao-pu",
        "Banliaobu",
        "Pan-liao-pu"
    ],
    "name:zho_x_preferred":[
        "\u677f\u5bee\u57d4"
    ],
    "wof:name":"Banliaobu",
    "wof:placetype":"locality"
},
  "geometry": {"coordinates":[120.61333,23.62917],"type":"Point"}
}