{
  "type": "Feature",
  "properties": {
    "iso:country":"TW",
    "name:eng_x_preferred":[
        "Guohui"
    ],
    "name:eng_x_variant":[
        "Guohui Village"
    ],
    "name:zho_tw_x_preferred":[
        "\u679c\u60e0\u91cc"
    ],
    "qs:name":"\u679c\u60e0\u91cc",
    "qs:name_adm0":"\u81fa\u7063",
    "qs:name_adm1":"\u9ad8\u96c4\u5e02",
    "qs:photos":99,
    "qs:photos_1k":20,
    "qs:photos_9k":1,
    "qs:photos_9r":3,
    "qs:photos_all":99,
    "qs:photos_sr":3,
    "qs:placetype":"Suburb",
    "qs:pop_sr":"0",
    "wof:name":"Guohui",
    "wof:placetype":"neighbourhood"
},
  "geometry": {"coordinates":[120.287976,22.670077],"type":"Point"}
}