{
  "type": "Feature",
  "properties": {
    "gn:admin1_code":"01",
    "gn:admin2_code":"KIN",
    "gn:admin3_code":"W04",
    "gn:admin4_code":"9020040004.0",
    "gn:asciiname":"Puhou",
    "gn:country_code":"TW",
    "gn:dem":32,
    "gn:feature_class":"P",
    "gn:feature_code":"PPL",
    "gn:name":"Puhou",
    "gn:population":0,
    "gn:timezone":"Asia/Taipei",
    "iso:country":"TW",
    "name:und_x_variant":[
        "Buhou",
        "Pu-hou",
        "Puhou"
    ],
    "name:zho_x_preferred":[
        "\u57d4\u5f8c"
    ],
    "wof:name":"Puhou",
    "wof:placetype":"locality"
},
  "geometry": {"coordinates":[118.31674,24.44408],"type":"Point"}
}