{
  "type": "Feature",
  "properties": {
    "gn:admin1_code":"04",
    "gn:admin2_code":"MIA",
    "gn:admin3_code":"K02",
    "gn:admin4_code":"10005020019.0",
    "gn:asciiname":"Weiliao",
    "gn:country_code":"TW",
    "gn:dem":68,
    "gn:feature_class":"P",
    "gn:feature_code":"PPL",
    "gn:name":"Weiliao",
    "gn:population":0,
    "gn:timezone":"Asia/Taipei",
    "iso:country":"TW",
    "name:und_x_variant":[
        "Wei-liao"
    ],
    "wof:name":"Weiliao",
    "wof:placetype":"locality"
},
  "geometry": {"coordinates":[120.67610999999999,24.40167000000001],"type":"Point"}
}