{
  "type": "Feature",
  "properties": {
    "gn:admin1_code":"02",
    "gn:admin2_code":"KHH",
    "gn:admin3_code":"E31",
    "gn:admin4_code":"64000310004.0",
    "gn:asciiname":"Wuzhiliao",
    "gn:country_code":"TW",
    "gn:dem":56,
    "gn:feature_class":"P",
    "gn:feature_code":"PPL",
    "gn:name":"Wuzhiliao",
    "gn:population":0,
    "gn:timezone":"Asia/Taipei",
    "iso:country":"TW",
    "name:und_x_variant":[
        "Wujhihliao",
        "Wu-chih-liao"
    ],
    "name:zho_x_preferred":[
        "\u4e94\u96bb\u5bee"
    ],
    "wof:name":"Wuzhiliao",
    "wof:placetype":"locality"
},
  "geometry": {"coordinates":[120.54939,22.87283],"type":"Point"}
}