{
  "type": "Feature",
  "properties": {
    "gn:country":"TW",
    "gn:fcode":"ADMD",
    "gn:pop":0,
    "iso:country":"TW",
    "name:unk_x_variant":[
        "Mei-shan"
    ],
    "name:zho_x_preferred":[
        "\u6885\u5c71\u9109"
    ],
    "qs:name":"Meishan Xiang",
    "qs:photos_9r":0,
    "qs:photos_sr":0,
    "qs:pop_sr":"0",
    "wd:wordcount":151,
    "wof:name":"Meishan Xiang",
    "wof:placetype":"localadmin",
    "wof:population":0
},
  "geometry": {"coordinates":[120.63333,23.55],"type":"Point"}
}