{
  "type": "Feature",
  "properties": {
    "gn:country":"TW",
    "gn:fcode":"ADMD",
    "gn:pop":0,
    "iso:country":"TW",
    "name:eng_x_preferred":[
        "Meishan"
    ],
    "name:fra_x_preferred":[
        "Meishan"
    ],
    "name:hak_x_preferred":[
        "M\u00f2i-s\u00e2n-hi\u00f4ng"
    ],
    "name:jpn_x_preferred":[
        "\u6885\u5c71\u90f7"
    ],
    "name:kor_x_preferred":[
        "\uba54\uc774\uc0b0\ud5a5"
    ],
    "name:nan_x_preferred":[
        "B\u00f4e-san-hiong"
    ],
    "name:pol_x_preferred":[
        "Meishan"
    ],
    "name:rus_x_preferred":[
        "\u041c\u044d\u0439\u0448\u0430\u043d\u044c"
    ],
    "name:unk_x_variant":[
        "Mei-shan"
    ],
    "name:vie_x_preferred":[
        "Mai S\u01a1n"
    ],
    "name:zho_x_preferred":[
        "\u6885\u5c71\u9109"
    ],
    "qs:name":"Meishan Xiang",
    "qs:photos_9r":0,
    "qs:photos_sr":0,
    "qs:pop_sr":"0",
    "wd:wordcount":151,
    "wof:name":"Meishan Xiang",
    "wof:placetype":"localadmin",
    "wof:population":0
},
  "geometry": {"coordinates":[120.63333,23.55],"type":"Point"}
}