{
  "type": "Feature",
  "properties": {
    "iso:country":"TW",
    "qs:name":"\u897f\u5bcc\u6751",
    "qs:name_adm0":"\u81fa\u7063",
    "qs:name_adm1":"\u82b1\u84ee\u7e23",
    "qs:photos":3,
    "qs:photos_1k":1,
    "qs:photos_9k":1,
    "qs:photos_9r":1,
    "qs:photos_all":3,
    "qs:photos_sr":1,
    "qs:placetype":"Town",
    "qs:pop_sr":"0",
    "wof:name":"\u897f\u5bcc\u6751",
    "wof:placetype":"locality"
},
  "geometry": {"coordinates":[121.441253,23.640832],"type":"Point"}
}