{
  "type": "Feature",
  "properties": {
    "gn:admin1_code":"4.0",
    "gn:admin2_code":"NAN",
    "gn:admin3_code":"M06",
    "gn:admin4_code":"10008060015.0",
    "gn:asciiname":"Chishui",
    "gn:country_code":"TW",
    "gn:dem":321,
    "gn:feature_class":"P",
    "gn:feature_code":"PPL",
    "gn:name":"Chishui",
    "gn:population":0,
    "gn:timezone":"Asia/Taipei",
    "iso:country":"TW",
    "name:deu_x_preferred":[
        "Chishui"
    ],
    "name:nor_x_preferred":[
        "Chishui"
    ],
    "name:pam_x_preferred":[
        "Chishui"
    ],
    "name:und_x_variant":[
        "Chihshuei"
    ],
    "name:zho_x_preferred":[
        "\u8d64\u6c34"
    ],
    "name:zho_x_variant":[
        "Ch\u2019ih-shui"
    ],
    "wof:name":"Chishui",
    "wof:placetype":"locality"
},
  "geometry": {"coordinates":[120.63158,23.85988],"type":"Point"}
}