{
  "type": "Feature",
  "properties": {
    "gn:admin1_code":"4.0",
    "gn:admin2_code":"HSZ",
    "gn:admin3_code":"J13",
    "gn:admin4_code":"10004110005.0",
    "gn:asciiname":"Shuziwu",
    "gn:country_code":"TW",
    "gn:dem":107,
    "gn:feature_class":"P",
    "gn:feature_code":"PPL",
    "gn:name":"Shuziwu",
    "gn:population":0,
    "gn:timezone":"Asia/Taipei",
    "iso:country":"TW",
    "name:und_x_variant":[
        "Shuzihwu",
        "Shuziwu",
        "Shu-tzu-wu"
    ],
    "name:zho_x_preferred":[
        "\u6a39\u5b50\u5c4b"
    ],
    "wof:name":"Shuziwu",
    "wof:placetype":"locality"
},
  "geometry": {"coordinates":[121.01333,24.66972],"type":"Point"}
}