{
  "type": "Feature",
  "properties": {
    "gn:admin1_code":"03",
    "gn:admin2_code":"TPQ",
    "gn:admin3_code":"F24",
    "gn:admin4_code":"65000260011.0",
    "gn:asciiname":"Nanshikeng",
    "gn:country_code":"TW",
    "gn:dem":94,
    "gn:feature_class":"P",
    "gn:feature_code":"PPL",
    "gn:name":"Nanshikeng",
    "gn:population":0,
    "gn:timezone":"Asia/Taipei",
    "iso:country":"TW",
    "name:und_x_variant":[
        "Nanshihkeng"
    ],
    "name:zho_x_preferred":[
        "\u5357\u52e2\u5751"
    ],
    "name:zho_x_variant":[
        "Nan-shih-k\u2019eng"
    ],
    "wof:name":"Nanshikeng",
    "wof:placetype":"locality"
},
  "geometry": {"coordinates":[121.90600000000001,25.0861],"type":"Point"}
}