{
  "type": "Feature",
  "properties": {
    "iso:country":"TW",
    "qs:name":"\u678b\u5bee\u9109",
    "qs:name_adm0":"\u81fa\u7063",
    "qs:name_adm1":"\u5c4f\u6771\u7e23",
    "qs:photos":14,
    "qs:photos_1k":3,
    "qs:photos_9k":1,
    "qs:photos_9r":4,
    "qs:photos_all":265,
    "qs:photos_sr":1,
    "qs:placetype":"County",
    "qs:pop_sr":"0",
    "wof:name":"\u678b\u5bee\u9109",
    "wof:placetype":"county"
},
  "geometry": {"coordinates":[120.5952485,22.3680725],"type":"Point"}
}