{
  "type": "Feature",
  "properties": {
    "iso:country":"TW",
    "label:eng_x_preferred_longname":[
        "Fangliao Township"
    ],
    "label:eng_x_preferred_placetype":[
        "township"
    ],
    "name:eng_x_preferred":[
        "Fangliao"
    ],
    "name:eng_x_variant":[
        "Fangliao Township"
    ],
    "name:fra_x_preferred":[
        "Fangliao"
    ],
    "name:zho_tw_x_preferred":[
        "\u678b\u5bee\u9109"
    ],
    "qs:name":"\u678b\u5bee\u9109",
    "qs:name_adm0":"\u81fa\u7063",
    "qs:name_adm1":"\u5c4f\u6771\u7e23",
    "qs:photos":14,
    "qs:photos_1k":3,
    "qs:photos_9k":1,
    "qs:photos_9r":4,
    "qs:photos_all":265,
    "qs:photos_sr":1,
    "qs:placetype":"County",
    "qs:pop_sr":"0",
    "wof:name":"Fangliao",
    "wof:placetype":"county"
},
  "geometry": {"coordinates":[120.595248,22.368073],"type":"Point"}
}