{
  "type": "Feature",
  "properties": {
    "gn:admin1_code":"3.0",
    "gn:admin2_code":"TPQ",
    "gn:admin3_code":"F32",
    "gn:admin4_code":"65000230008.0",
    "gn:asciiname":"Qiding",
    "gn:country_code":"TW",
    "gn:dem":257,
    "gn:feature_class":"P",
    "gn:feature_code":"PPL",
    "gn:name":"Qiding",
    "gn:population":0,
    "gn:timezone":"Asia/Taipei",
    "iso:country":"TW",
    "name:und_x_variant":[
        "Ciding"
    ],
    "name:zho_x_preferred":[
        "\u5d0e\u9802"
    ],
    "name:zho_x_variant":[
        "Ch\u2019i-ting"
    ],
    "wof:name":"Qiding",
    "wof:placetype":"locality"
},
  "geometry": {"coordinates":[121.41328,25.12425],"type":"Point"}
}