{
  "type": "Feature",
  "properties": {
    "gn:admin1_code":"4.0",
    "gn:admin2_code":"HSZ",
    "gn:admin3_code":"J14",
    "gn:admin4_code":"10004120005.0",
    "gn:asciiname":"Shekou",
    "gn:country_code":"TW",
    "gn:dem":722,
    "gn:feature_class":"P",
    "gn:feature_code":"PPL",
    "gn:name":"Shekou",
    "gn:population":0,
    "gn:timezone":"Asia/Taipei",
    "iso:country":"TW",
    "name:fra_x_preferred":[
        "Shekou"
    ],
    "name:nor_x_preferred":[
        "Shekou"
    ],
    "name:swe_x_preferred":[
        "Shekou"
    ],
    "name:zho_x_preferred":[
        "\u793e\u53e3"
    ],
    "name:zho_x_variant":[
        "She-k\u2019ou",
        "\u86c7\u53e3\u5de5\u4e1a\u533a"
    ],
    "wof:name":"Shekou",
    "wof:placetype":"locality"
},
  "geometry": {"coordinates":[121.25360999999999,24.68778],"type":"Point"}
}