{
  "type": "Feature",
  "properties": {
    "gn:admin1_code":"04",
    "gn:admin2_code":"CYQ",
    "gn:admin3_code":"Q15",
    "gn:admin4_code":"10010140020.0",
    "gn:asciiname":"Mulueliao",
    "gn:country_code":"TW",
    "gn:dem":429,
    "gn:feature_class":"P",
    "gn:feature_code":"PPL",
    "gn:name":"Mul\u00fcliao",
    "gn:population":0,
    "gn:timezone":"Asia/Taipei",
    "iso:country":"TW",
    "name:und_x_variant":[
        "Mulyuliao",
        "Mu-li-liao",
        "Mu-chi-liao"
    ],
    "name:zho_x_preferred":[
        "\u6728\u5c65\u5bee"
    ],
    "name:zho_x_variant":[
        "Mul\u00fcliao",
        "Mu-l\u00fc-liao"
    ],
    "wof:name":"Mulueliao",
    "wof:placetype":"locality"
},
  "geometry": {"coordinates":[120.58444,23.53694],"type":"Point"}
}