{
  "type": "Feature",
  "properties": {
    "gn:admin1_code":"02",
    "gn:admin2_code":"KHH",
    "gn:admin3_code":"E17",
    "gn:admin4_code":"64000170009.0",
    "gn:asciiname":"Bagualiao",
    "gn:country_code":"TW",
    "gn:dem":14,
    "gn:feature_class":"P",
    "gn:feature_code":"PPL",
    "gn:name":"Bagualiao",
    "gn:population":0,
    "gn:timezone":"Asia/Taipei",
    "iso:country":"TW",
    "name:und_x_variant":[
        "Pa-kua-liao",
        "Pa-kua",
        "Bagualiao"
    ],
    "name:zho_x_preferred":[
        "Pa-kua-ts\u2019un"
    ],
    "name:zho_x_variant":[
        "Pei-Kua-Ts\u2019un",
        "\u516b\u5366\u5bee"
    ],
    "wof:name":"Bagualiao",
    "wof:placetype":"locality"
},
  "geometry": {"coordinates":[120.33750000000001,22.68852],"type":"Point"}
}