{
  "type": "Feature",
  "properties": {
    "gn:admin1_code":"4.0",
    "gn:admin2_code":"NAN",
    "gn:admin3_code":"M08",
    "gn:admin4_code":"10008080006.0",
    "gn:asciiname":"Zhongliao",
    "gn:country_code":"TW",
    "gn:dem":170,
    "gn:feature_class":"P",
    "gn:feature_code":"PPL",
    "gn:name":"Zhongliao",
    "gn:population":0,
    "gn:timezone":"Asia/Taipei",
    "iso:country":"TW",
    "name:deu_x_preferred":[
        "Zhongliao"
    ],
    "name:hak_x_preferred":[
        "Ch\u00fbng-li\u00e0u-hi\u00f4ng"
    ],
    "name:jpn_x_preferred":[
        "\u4e2d\u5bee\u90f7"
    ],
    "name:kor_x_preferred":[
        "\uc911\ub7b4\uc624\ud5a5"
    ],
    "name:pol_x_preferred":[
        "Zhongliao"
    ],
    "name:und_x_variant":[
        "Jhongliao",
        "Chung-liao"
    ],
    "name:vie_x_preferred":[
        "Trung Li\u00eau"
    ],
    "name:zho_x_preferred":[
        "Chung-liao-she-ch\u2019\u00fc"
    ],
    "name:zho_x_variant":[
        "Chung-liao-ts\u2019un",
        "\u4e2d\u5bee",
        "Hsiang-ch\u2019in-liao",
        "\u4e2d\u5bee\u9109"
    ],
    "wof:name":"Zhongliao",
    "wof:placetype":"locality"
},
  "geometry": {"coordinates":[120.76546,23.87958],"type":"Point"}
}