{
  "type": "Feature",
  "properties": {
    "iso:country":"TW",
    "name:eng_x_preferred":[
        "Linde"
    ],
    "name:eng_x_variant":[
        "Linde Village"
    ],
    "name:zho_tw_x_preferred":[
        "\u6797\u5fb7\u91cc"
    ],
    "qs:name":"\u6797\u5fb7\u91cc",
    "qs:name_adm0":"\u81fa\u7063",
    "qs:name_adm1":"\u9ad8\u96c4\u5e02",
    "qs:photos":218,
    "qs:photos_1k":44,
    "qs:photos_9k":1,
    "qs:photos_9r":4,
    "qs:photos_all":218,
    "qs:photos_sr":4,
    "qs:placetype":"Suburb",
    "qs:pop_sr":"0",
    "wof:name":"Linde",
    "wof:placetype":"neighbourhood"
},
  "geometry": {"coordinates":[120.321664,22.623094],"type":"Point"}
}