{
  "type": "Feature",
  "properties": {
    "gn:admin1_code":"4.0",
    "gn:admin2_code":"TNN",
    "gn:admin3_code":"R30",
    "gn:admin4_code":"67000300001.0",
    "gn:asciiname":"Guoling",
    "gn:country_code":"TW",
    "gn:dem":97,
    "gn:feature_class":"P",
    "gn:feature_code":"PPL",
    "gn:name":"Guoling",
    "gn:population":0,
    "gn:timezone":"Asia/Taipei",
    "iso:country":"TW",
    "name:und_x_variant":[
        "Kuo-ling"
    ],
    "name:zho_x_preferred":[
        "\u904e\u5dba"
    ],
    "wof:name":"Guoling",
    "wof:placetype":"locality"
},
  "geometry": {"coordinates":[120.39333000000001,22.96944],"type":"Point"}
}