{
  "type": "Feature",
  "properties": {
    "gn:admin1_code":"04",
    "gn:admin2_code":"TPE",
    "gn:admin3_code":"A14",
    "gn:admin4_code":"63000100010.0",
    "gn:asciiname":"Neihu",
    "gn:country_code":"TW",
    "gn:dem":18,
    "gn:feature_class":"P",
    "gn:feature_code":"PPL",
    "gn:name":"Neihu",
    "gn:population":0,
    "gn:timezone":"Asia/Taipei",
    "iso:country":"TW",
    "name:eng_x_preferred":[
        "Neihu District"
    ],
    "name:fra_x_preferred":[
        "District de Neihu"
    ],
    "name:hak_x_preferred":[
        "Nui-f\u00f9-kh\u00ee"
    ],
    "name:ind_x_preferred":[
        "Distrik Neihu"
    ],
    "name:ita_x_preferred":[
        "Distretto di Neihu"
    ],
    "name:jpn_x_preferred":[
        "\u5185\u6e56\u533a"
    ],
    "name:kor_x_preferred":[
        "\ub124\uc774\ud6c4 \uad6c"
    ],
    "name:lzh_x_preferred":[
        "\u5167\u6e56\u5340"
    ],
    "name:nan_x_preferred":[
        "L\u0101i-\u00f4\u0358-khu"
    ],
    "name:rus_x_preferred":[
        "\u041d\u044d\u0439\u0445\u0443"
    ],
    "name:und_x_variant":[
        "Nei-hu"
    ],
    "name:vie_x_preferred":[
        "N\u1ed9i H\u1ed3"
    ],
    "name:zho_x_preferred":[
        "\u5167\u6e56"
    ],
    "name:zho_x_variant":[
        "\u5167\u6e56\u5340"
    ],
    "wof:name":"Neihu",
    "wof:placetype":"locality"
},
  "geometry": {"coordinates":[121.58808999999999,25.0815],"type":"Point"}
}