{
  "type": "Feature",
  "properties": {
    "gn:admin1_code":"04",
    "gn:admin2_code":"CHA",
    "gn:admin3_code":"N11",
    "gn:admin4_code":"10007060004.0",
    "gn:asciiname":"Waibu",
    "gn:country_code":"TW",
    "gn:dem":12,
    "gn:feature_class":"P",
    "gn:feature_code":"PPL",
    "gn:name":"Waibu",
    "gn:population":0,
    "gn:timezone":"Asia/Taipei",
    "iso:country":"TW",
    "name:und_x_variant":[
        "Wai-pu"
    ],
    "name:zho_x_preferred":[
        "\u5916\u57d4"
    ],
    "name:zho_x_variant":[
        "Wai-pu-ts\u2019un"
    ],
    "wof:name":"Waibu",
    "wof:placetype":"locality"
},
  "geometry": {"coordinates":[120.47472,24.03028],"type":"Point"}
}