{
  "type": "Feature",
  "properties": {
    "gn:admin1_code":"3.0",
    "gn:admin2_code":"TPQ",
    "gn:admin3_code":"F02",
    "gn:admin4_code":"65000170011.0",
    "gn:asciiname":"Jialin",
    "gn:country_code":"TW",
    "gn:dem":36,
    "gn:feature_class":"P",
    "gn:feature_code":"PPL",
    "gn:name":"Jialin",
    "gn:population":0,
    "gn:timezone":"Asia/Taipei",
    "iso:country":"TW",
    "name:und_x_variant":[
        "Chia-lin"
    ],
    "name:zho_x_preferred":[
        "\u4f73\u6797"
    ],
    "wof:name":"Jialin",
    "wof:placetype":"locality"
},
  "geometry": {"coordinates":[121.30892,25.10889],"type":"Point"}
}