{
  "type": "Feature",
  "properties": {
    "gn:admin1_code":"4.0",
    "gn:admin2_code":"CYQ",
    "gn:admin3_code":"Q16",
    "gn:admin4_code":"10010150015.0",
    "gn:asciiname":"Daoliao",
    "gn:country_code":"TW",
    "gn:dem":423,
    "gn:feature_class":"P",
    "gn:feature_code":"PPL",
    "gn:name":"Daoliao",
    "gn:population":0,
    "gn:timezone":"Asia/Taipei",
    "iso:country":"TW",
    "name:und_x_variant":[
        "Tao-liao"
    ],
    "name:zho_x_preferred":[
        "\u7a3b\u5bee"
    ],
    "wof:name":"Daoliao",
    "wof:placetype":"locality"
},
  "geometry": {"coordinates":[120.64306000000001,23.56611],"type":"Point"}
}