{
  "type": "Feature",
  "properties": {
    "gn:admin1_code":"4.0",
    "gn:admin2_code":"TAO",
    "gn:admin3_code":"H06",
    "gn:admin4_code":"68000060018.0",
    "gn:asciiname":"Xucuogang",
    "gn:country_code":"TW",
    "gn:dem":2,
    "gn:feature_class":"P",
    "gn:feature_code":"PPL",
    "gn:name":"Xucuogang",
    "gn:population":0,
    "gn:timezone":"Asia/Taipei",
    "iso:country":"TW",
    "name:und_x_variant":[
        "Syucuogang",
        "Xucuogang"
    ],
    "name:zho_x_preferred":[
        "Hs\u00fc-ts\u2019o-chiang"
    ],
    "name:zho_x_variant":[
        "Hs\u00fc-ts\u2019o",
        "Hs\u00fc-Ts\u2019o-Ts\u2019un",
        "\u8a31\u539d\u6e2f",
        "Hs\u00fc-ts\u2019o-kang"
    ],
    "wof:name":"Xucuogang",
    "wof:placetype":"locality"
},
  "geometry": {"coordinates":[121.17373000000001,25.0851],"type":"Point"}
}