{
  "type": "Feature",
  "properties": {
    "gn:admin1_code":"04",
    "gn:admin2_code":"HUA",
    "gn:admin3_code":"U03",
    "gn:admin4_code":"10015030014.0",
    "gn:asciiname":"Sanmin",
    "gn:country_code":"TW",
    "gn:dem":92,
    "gn:feature_class":"P",
    "gn:feature_code":"PPL",
    "gn:name":"Sanmin",
    "gn:population":0,
    "gn:timezone":"Asia/Taipei",
    "iso:country":"TW",
    "name:und_x_variant":[
        "San-min-li",
        "San-li",
        "San-min",
        "Sanmin"
    ],
    "name:zho_x_preferred":[
        "San-li-ts\u2019un"
    ],
    "name:zho_x_variant":[
        "\u4e09\u6c11"
    ],
    "wof:name":"Sanmin",
    "wof:placetype":"locality"
},
  "geometry": {"coordinates":[121.34798000000001,23.42903],"type":"Point"}
}