{
  "type": "Feature",
  "properties": {
    "gn:admin1_code":"03",
    "gn:admin2_code":"TPQ",
    "gn:admin3_code":"F10",
    "gn:admin4_code":"65000200007.0",
    "gn:asciiname":"Dinghe",
    "gn:country_code":"TW",
    "gn:dem":603,
    "gn:feature_class":"P",
    "gn:feature_code":"PPL",
    "gn:name":"Dinghe",
    "gn:population":0,
    "gn:timezone":"Asia/Taipei",
    "iso:country":"TW",
    "name:und_x_variant":[
        "Ting-ho"
    ],
    "name:zho_x_preferred":[
        "\u9802\u6cb3"
    ],
    "wof:name":"Dinghe",
    "wof:placetype":"locality"
},
  "geometry": {"coordinates":[121.77972,24.93528],"type":"Point"}
}