{
  "type": "Feature",
  "properties": {
    "gn:admin1_code":"03",
    "gn:admin2_code":"TPQ",
    "gn:admin3_code":"F27",
    "gn:admin4_code":"65000100012.0",
    "gn:asciiname":"Shanzibian",
    "gn:country_code":"TW",
    "gn:dem":131,
    "gn:feature_class":"P",
    "gn:feature_code":"PPL",
    "gn:name":"Shanzibian",
    "gn:population":0,
    "gn:timezone":"Asia/Taipei",
    "iso:country":"TW",
    "name:und_x_variant":[
        "Shan-tzu-pien"
    ],
    "wof:name":"Shanzibian",
    "wof:placetype":"locality"
},
  "geometry": {"coordinates":[121.46666999999999,25.18333],"type":"Point"}
}