{
  "type": "Feature",
  "properties": {
    "gn:admin1_code":"4.0",
    "gn:admin2_code":"TXG",
    "gn:admin3_code":"B12",
    "gn:admin4_code":"66000120021.0",
    "gn:asciiname":"Xidi",
    "gn:country_code":"TW",
    "gn:dem":15,
    "gn:feature_class":"P",
    "gn:feature_code":"PPL",
    "gn:name":"Xidi",
    "gn:population":0,
    "gn:timezone":"Asia/Taipei",
    "iso:country":"TW",
    "name:und_x_variant":[
        "Sidi",
        "Hsi-ti"
    ],
    "name:zho_x_preferred":[
        "\u6eaa\u5e95"
    ],
    "wof:name":"Xidi",
    "wof:placetype":"locality"
},
  "geometry": {"coordinates":[120.56583000000001,24.3225],"type":"Point"}
}