{
  "type": "Feature",
  "properties": {
    "gn:admin1_code":"02",
    "gn:admin2_code":"KHH",
    "gn:admin3_code":"E35",
    "gn:admin4_code":"64000350005.0",
    "gn:asciiname":"Toubankeng",
    "gn:country_code":"TW",
    "gn:dem":126,
    "gn:feature_class":"P",
    "gn:feature_code":"PPL",
    "gn:name":"Toubankeng",
    "gn:population":0,
    "gn:timezone":"Asia/Taipei",
    "iso:country":"TW",
    "name:zho_x_preferred":[
        "\u982d\u677f\u5751"
    ],
    "name:zho_x_variant":[
        "T\u2019ou-pan-k\u2019eng"
    ],
    "wof:name":"Toubankeng",
    "wof:placetype":"locality"
},
  "geometry": {"coordinates":[120.51721999999999,22.98139],"type":"Point"}
}