{
  "type": "Feature",
  "properties": {
    "gn:admin1_code":"4.0",
    "gn:admin2_code":"PIF",
    "gn:admin3_code":"T03",
    "gn:admin4_code":"10013030016.0",
    "gn:asciiname":"Xinzhu",
    "gn:country_code":"TW",
    "gn:dem":3,
    "gn:feature_class":"P",
    "gn:feature_code":"PPL",
    "gn:name":"Xinzhu",
    "gn:population":0,
    "gn:timezone":"Asia/Taipei",
    "iso:country":"TW",
    "name:und_x_variant":[
        "Sinjhu",
        "Xinzhu",
        "Hsin-chu"
    ],
    "name:zho_x_preferred":[
        "\u65b0\u7af9"
    ],
    "wof:name":"Xinzhu",
    "wof:placetype":"locality"
},
  "geometry": {"coordinates":[120.47335,22.46205],"type":"Point"}
}