{
  "type": "Feature",
  "properties": {
    "gn:admin1_code":"01",
    "gn:admin2_code":"KIN",
    "gn:admin3_code":"W03",
    "gn:admin4_code":"9020010007.0",
    "gn:asciiname":"Oucuo",
    "gn:country_code":"TW",
    "gn:dem":26,
    "gn:feature_class":"P",
    "gn:feature_code":"PPL",
    "gn:name":"Oucuo",
    "gn:population":0,
    "gn:timezone":"Asia/Taipei",
    "iso:country":"TW",
    "name:und_x_variant":[
        "Os-ts\u2019o",
        "Ou-ts\u2019o",
        "Oucuo"
    ],
    "name:zho_x_preferred":[
        "\u6b50\u539d"
    ],
    "wof:name":"Oucuo",
    "wof:placetype":"locality"
},
  "geometry": {"coordinates":[118.33237,24.40807],"type":"Point"}
}