{
  "type": "Feature",
  "properties": {
    "gn:admin1_code":"04",
    "gn:admin2_code":"MIA",
    "gn:admin3_code":"K02",
    "gn:admin4_code":"10005020014.0",
    "gn:asciiname":"Shanjiao",
    "gn:country_code":"TW",
    "gn:dem":62,
    "gn:feature_class":"P",
    "gn:feature_code":"PPL",
    "gn:name":"Shanjiao",
    "gn:population":0,
    "gn:timezone":"Asia/Taipei",
    "iso:country":"TW",
    "name:und_x_variant":[
        "Shan-chiao"
    ],
    "name:zho_x_preferred":[
        "\u5c71\u811a"
    ],
    "wof:name":"Shanjiao",
    "wof:placetype":"locality"
},
  "geometry": {"coordinates":[120.68611,24.41639],"type":"Point"}
}