{
  "type": "Feature",
  "properties": {
    "gn:admin1_code":"3.0",
    "gn:admin2_code":"TPQ",
    "gn:admin3_code":"F17",
    "gn:admin4_code":"65000070036.0",
    "gn:asciiname":"Taigaokeng",
    "gn:country_code":"TW",
    "gn:dem":171,
    "gn:feature_class":"P",
    "gn:feature_code":"PPL",
    "gn:name":"Taigaokeng",
    "gn:population":0,
    "gn:timezone":"Asia/Taipei",
    "iso:country":"TW",
    "name:zho_x_preferred":[
        "\u592a\u9ad8\u5751"
    ],
    "name:zho_x_variant":[
        "T\u2019ai-kao-k\u2019eng"
    ],
    "wof:name":"Taigaokeng",
    "wof:placetype":"locality"
},
  "geometry": {"coordinates":[121.39081000000002,24.98146],"type":"Point"}
}