{
  "type": "Feature",
  "properties": {
    "gn:admin1_code":"4.0",
    "gn:admin2_code":"TXG",
    "gn:admin3_code":"B21",
    "gn:admin4_code":"66000210010.0",
    "gn:asciiname":"Zhonglu",
    "gn:country_code":"TW",
    "gn:dem":163,
    "gn:feature_class":"P",
    "gn:feature_code":"PPL",
    "gn:name":"Zhonglu",
    "gn:population":0,
    "gn:timezone":"Asia/Taipei",
    "iso:country":"TW",
    "name:fas_x_preferred":[
        "\u0698\u0648\u0646\u06af\u0644\u0648"
    ],
    "name:und_x_variant":[
        "Jhonglu",
        "Zhonglu",
        "Chung-lu"
    ],
    "name:zho_x_preferred":[
        "\u4e2d\u8def"
    ],
    "name:zho_x_variant":[
        "\u5fe0\u8def\u9547"
    ],
    "wof:name":"Zhonglu",
    "wof:placetype":"locality"
},
  "geometry": {"coordinates":[120.715,24.34],"type":"Point"}
}