{
  "type": "Feature",
  "properties": {
    "gn:admin1_code":"03",
    "gn:admin2_code":"TPQ",
    "gn:admin3_code":"F10",
    "gn:admin4_code":"65000200004.0",
    "gn:asciiname":"Shanlin",
    "gn:country_code":"TW",
    "gn:dem":484,
    "gn:feature_class":"P",
    "gn:feature_code":"PPL",
    "gn:name":"Shanlin",
    "gn:population":0,
    "gn:timezone":"Asia/Taipei",
    "iso:country":"TW",
    "name:fra_x_preferred":[
        "Shanlin"
    ],
    "name:spa_x_preferred":[
        "Shanlin"
    ],
    "name:und_x_variant":[
        "Shan-lin"
    ],
    "name:zho_x_preferred":[
        "\u5c71\u6797"
    ],
    "wof:name":"Shanlin",
    "wof:placetype":"locality"
},
  "geometry": {"coordinates":[121.765,24.87167],"type":"Point"}
}