{
  "type": "Feature",
  "properties": {
    "gn:admin1_code":"04",
    "gn:admin2_code":"TTT",
    "gn:admin3_code":"V08",
    "gn:admin4_code":"10014080005.0",
    "gn:asciiname":"Nanzhuhu",
    "gn:country_code":"TW",
    "gn:dem":41,
    "gn:feature_class":"P",
    "gn:feature_code":"PPL",
    "gn:name":"Nanzhuhu",
    "gn:population":0,
    "gn:timezone":"Asia/Taipei",
    "iso:country":"TW",
    "name:und_x_variant":[
        "Nanjhuhu",
        "Nan-chu-hu"
    ],
    "name:zho_x_preferred":[
        "\u5357\u7af9\u6e56"
    ],
    "wof:name":"Nanzhuhu",
    "wof:placetype":"locality"
},
  "geometry": {"coordinates":[121.42225999999999,23.27524],"type":"Point"}
}