{
  "type": "Feature",
  "properties": {
    "gn:admin1_code":"3.0",
    "gn:admin2_code":"TPQ",
    "gn:admin3_code":"F26",
    "gn:admin4_code":"65000280006.0",
    "gn:asciiname":"Mazhujiao",
    "gn:country_code":"TW",
    "gn:dem":153,
    "gn:feature_class":"P",
    "gn:feature_code":"PPL",
    "gn:name":"Mazhujiao",
    "gn:population":0,
    "gn:timezone":"Asia/Taipei",
    "iso:country":"TW",
    "name:und_x_variant":[
        "Majhujiao",
        "Mazhujiao",
        "Ma-chu-chiao"
    ],
    "name:zho_x_preferred":[
        "\u8534\u7af9\u811a"
    ],
    "wof:name":"Mazhujiao",
    "wof:placetype":"locality"
},
  "geometry": {"coordinates":[121.6414,25.18693],"type":"Point"}
}