{
  "type": "Feature",
  "properties": {
    "gn:admin1_code":"4.0",
    "gn:admin2_code":"TXG",
    "gn:admin3_code":"B19",
    "gn:admin4_code":"66000190013.0",
    "gn:asciiname":"Ergui",
    "gn:country_code":"TW",
    "gn:dem":693,
    "gn:feature_class":"P",
    "gn:feature_code":"PPL",
    "gn:name":"Ergui",
    "gn:population":0,
    "gn:timezone":"Asia/Taipei",
    "iso:country":"TW",
    "name:und_x_variant":[
        "Erguei",
        "Erh-kuei"
    ],
    "name:zho_x_preferred":[
        "\u4e8c\u6ac3"
    ],
    "wof:name":"Ergui",
    "wof:placetype":"locality"
},
  "geometry": {"coordinates":[120.87885,24.13236],"type":"Point"}
}