{
  "type": "Feature",
  "properties": {
    "gn:admin1_code":"4.0",
    "gn:admin2_code":"ILA",
    "gn:admin3_code":"G07",
    "gn:admin4_code":"10002090010.0",
    "gn:asciiname":"Qingzidi",
    "gn:country_code":"TW",
    "gn:dem":2,
    "gn:feature_class":"P",
    "gn:feature_code":"PPL",
    "gn:name":"Qingzidi",
    "gn:population":0,
    "gn:timezone":"Asia/Taipei",
    "iso:country":"TW",
    "name:und_x_variant":[
        "Cingzihdi",
        "Qingzidi"
    ],
    "name:zho_x_preferred":[
        "\u9752\u4ed4\u5730"
    ],
    "name:zho_x_variant":[
        "Ch\u2019ing-tzu-ti"
    ],
    "wof:name":"Qingzidi",
    "wof:placetype":"locality"
},
  "geometry": {"coordinates":[121.8182,24.6717],"type":"Point"}
}