{
  "type": "Feature",
  "properties": {
    "gn:admin1_code":"02",
    "gn:admin2_code":"KHH",
    "gn:admin3_code":"E30",
    "gn:admin4_code":"64000300005.0",
    "gn:asciiname":"Yuantan",
    "gn:country_code":"TW",
    "gn:dem":70,
    "gn:feature_class":"P",
    "gn:feature_code":"PPL",
    "gn:name":"Yuantan",
    "gn:population":0,
    "gn:timezone":"Asia/Taipei",
    "iso:country":"TW",
    "name:zho_x_preferred":[
        "\u5713\u6f6d"
    ],
    "name:zho_x_variant":[
        "Y\u00fcan-t\u2019an"
    ],
    "wof:name":"Yuantan",
    "wof:placetype":"locality"
},
  "geometry": {"coordinates":[120.50278,22.92833],"type":"Point"}
}