{
  "type": "Feature",
  "properties": {
    "gn:admin1_code":"4.0",
    "gn:admin2_code":"CHA",
    "gn:admin3_code":"N01",
    "gn:admin4_code":"10007010067.0",
    "gn:asciiname":"Fanzitian",
    "gn:country_code":"TW",
    "gn:dem":48,
    "gn:feature_class":"P",
    "gn:feature_code":"PPL",
    "gn:name":"Fanzitian",
    "gn:population":0,
    "gn:timezone":"Asia/Taipei",
    "iso:country":"TW",
    "name:und_x_variant":[
        "Fanzihtian",
        "Fanzitian"
    ],
    "name:zho_x_preferred":[
        "\u756a\u5b50\u7530"
    ],
    "name:zho_x_variant":[
        "Fan-tzu-t\u2019ien"
    ],
    "wof:name":"Fanzitian",
    "wof:placetype":"locality"
},
  "geometry": {"coordinates":[120.6194,24.0586],"type":"Point"}
}