{
  "type": "Feature",
  "properties": {
    "gn:admin1_code":"4.0",
    "gn:admin2_code":"TXG",
    "gn:admin3_code":"B12",
    "gn:admin4_code":"66000120028.0",
    "gn:asciiname":"Xinjiedianzi",
    "gn:country_code":"TW",
    "gn:dem":15,
    "gn:feature_class":"P",
    "gn:feature_code":"PPL",
    "gn:name":"Xinjiedianzi",
    "gn:population":0,
    "gn:timezone":"Asia/Taipei",
    "iso:country":"TW",
    "name:und_x_variant":[
        "Sinjiedianzih",
        "Hsin-chieh-tien-tzu"
    ],
    "name:zho_x_preferred":[
        "\u65b0\u8857\u5e97\u4ed4"
    ],
    "wof:name":"Xinjiedianzi",
    "wof:placetype":"locality"
},
  "geometry": {"coordinates":[120.58056000000001,24.27917],"type":"Point"}
}