{
  "type": "Feature",
  "properties": {
    "gn:admin1_code":"04",
    "gn:admin2_code":"TXG",
    "gn:admin3_code":"B09",
    "gn:admin4_code":"66000090036.0",
    "gn:asciiname":"Pozikou",
    "gn:country_code":"TW",
    "gn:dem":239,
    "gn:feature_class":"P",
    "gn:feature_code":"PPL",
    "gn:name":"Pozikou",
    "gn:population":0,
    "gn:timezone":"Asia/Taipei",
    "iso:country":"TW",
    "name:und_x_variant":[
        "Pozihkou"
    ],
    "name:zho_x_preferred":[
        "\u6734\u5b50\u53e3"
    ],
    "name:zho_x_variant":[
        "Pu-tzu-k\u2019ou",
        "P\u2019o-tzu-k\u2019ou"
    ],
    "wof:name":"Pozikou",
    "wof:placetype":"locality"
},
  "geometry": {"coordinates":[120.74361,24.27556],"type":"Point"}
}