{
  "type": "Feature",
  "properties": {
    "gn:admin1_code":"4.0",
    "gn:admin2_code":"TNN",
    "gn:admin3_code":"R24",
    "gn:admin4_code":"67000240003.0",
    "gn:asciiname":"Pizinei",
    "gn:country_code":"TW",
    "gn:dem":279,
    "gn:feature_class":"P",
    "gn:feature_code":"PPL",
    "gn:name":"Pizinei",
    "gn:population":0,
    "gn:timezone":"Asia/Taipei",
    "iso:country":"TW",
    "name:und_x_variant":[
        "Pizihnei",
        "Pizinei"
    ],
    "name:zho_x_preferred":[
        "\u57e4\u4ed4\u5167"
    ],
    "name:zho_x_variant":[
        "P\u2019i-tzu-nei"
    ],
    "wof:name":"Pizinei",
    "wof:placetype":"locality"
},
  "geometry": {"coordinates":[120.52278,23.19556],"type":"Point"}
}