{
  "type": "Feature",
  "properties": {
    "gn:admin1_code":"4.0",
    "gn:admin2_code":"MIA",
    "gn:admin3_code":"K18",
    "gn:admin4_code":"10005180007.0",
    "gn:asciiname":"Da'an",
    "gn:country_code":"TW",
    "gn:dem":731,
    "gn:feature_class":"P",
    "gn:feature_code":"PPL",
    "gn:name":"Da\u2019an",
    "gn:population":0,
    "gn:timezone":"Asia/Taipei",
    "iso:country":"TW",
    "name:und_x_variant":[
        "Lu-peng-she",
        "Ta-an",
        "\u5927\u5b89"
    ],
    "name:zho_x_preferred":[
        "Da\u2019an"
    ],
    "name:zho_x_variant":[
        "\u5927\u5b89"
    ],
    "wof:name":"Da'an",
    "wof:placetype":"locality"
},
  "geometry": {"coordinates":[120.96827999999999,24.37154],"type":"Point"}
}