{
  "type": "Feature",
  "properties": {
    "gn:admin1_code":"4.0",
    "gn:admin2_code":"TNN",
    "gn:admin3_code":"R21",
    "gn:admin4_code":"67000210011.0",
    "gn:asciiname":"Liukuailiao",
    "gn:country_code":"TW",
    "gn:dem":7,
    "gn:feature_class":"P",
    "gn:feature_code":"PPL",
    "gn:name":"Liukuailiao",
    "gn:population":0,
    "gn:timezone":"Asia/Taipei",
    "iso:country":"TW",
    "name:und_x_variant":[
        "Lioukuailiao",
        "Liu-chia",
        "Liukuailiao"
    ],
    "name:zho_x_preferred":[
        "\u516d\u584a\u5bee"
    ],
    "name:zho_x_variant":[
        "Liu-chia-ts\u2019un",
        "Liu-k\u2019uai-liao"
    ],
    "wof:name":"Liukuailiao",
    "wof:placetype":"locality"
},
  "geometry": {"coordinates":[120.22139,23.08028],"type":"Point"}
}