{
  "type": "Feature",
  "properties": {
    "gn:admin1_code":"4.0",
    "gn:admin2_code":"PIF",
    "gn:admin3_code":"T02",
    "gn:admin4_code":"10013020002.0",
    "gn:asciiname":"Chaozhou",
    "gn:country_code":"TW",
    "gn:dem":16,
    "gn:feature_class":"P",
    "gn:feature_code":"PPL",
    "gn:name":"Chaozhou",
    "gn:population":0,
    "gn:timezone":"Asia/Taipei",
    "iso:country":"TW",
    "name:bul_x_preferred":[
        "\u0427\u0430\u043e\u0434\u0436\u043e\u0443"
    ],
    "name:deu_x_preferred":[
        "Chaozhou"
    ],
    "name:eng_x_preferred":[
        "Chaozhou"
    ],
    "name:eng_x_variant":[
        "Chaozhou Township"
    ],
    "name:hak_x_preferred":[
        "Tsh\u00e8u-ch\u00fb-ts\u1e73\u0301n"
    ],
    "name:heb_x_preferred":[
        "\u05e6'\u05d0\u05d5\u05d6'\u05d5"
    ],
    "name:hun_x_preferred":[
        "Chaozhou"
    ],
    "name:jpn_x_preferred":[
        "\u6f6e\u5dde\u93ae"
    ],
    "name:kor_x_preferred":[
        "\ucc28\uc624\uc800\uc6b0\uc9c4"
    ],
    "name:und_x_variant":[
        "Ch\u2019ao-chou-chang",
        "Chaojhou"
    ],
    "name:vie_x_preferred":[
        "Tri\u1ec1u Ch\u00e2u"
    ],
    "name:zho_tw_x_preferred":[
        "\u6f6e\u5dde\u93ae"
    ],
    "name:zho_x_preferred":[
        "\u6f6e\u6d32"
    ],
    "name:zho_x_variant":[
        "Ch\u2019ao-chou",
        "\u6f6e\u5dde\u93ae"
    ],
    "qs:name":"\u6f6e\u5dde\u93ae",
    "qs:name_adm0":"\u81fa\u7063",
    "qs:name_adm1":"\u5c4f\u6771\u7e23",
    "qs:photos":1313,
    "qs:photos_1k":266,
    "qs:photos_9k":6,
    "qs:photos_9r":7,
    "qs:photos_all":1313,
    "qs:photos_sr":12,
    "qs:placetype":"Town",
    "qs:pop_sr":"0",
    "wof:name":"Chaozhou",
    "wof:placetype":"locality"
},
  "geometry": {"coordinates":[120.540181,22.550373],"type":"Point"}
}