{
  "type": "Feature",
  "properties": {
    "iso:country":"TW",
    "qs:name":"\u6f6e\u5dde\u93ae",
    "qs:name_adm0":"\u81fa\u7063",
    "qs:name_adm1":"\u5c4f\u6771\u7e23",
    "qs:photos":1313,
    "qs:photos_1k":266,
    "qs:photos_9k":6,
    "qs:photos_9r":7,
    "qs:photos_all":1313,
    "qs:photos_sr":12,
    "qs:placetype":"Town",
    "qs:pop_sr":"0",
    "wof:name":"\u6f6e\u5dde\u93ae",
    "wof:placetype":"locality"
},
  "geometry": {"coordinates":[120.540181,22.550373],"type":"Point"}
}