{
  "type": "Feature",
  "properties": {
    "gn:admin1_code":"4.0",
    "gn:admin2_code":"NAN",
    "gn:admin3_code":"M08",
    "gn:admin4_code":"10008080005.0",
    "gn:asciiname":"Daping",
    "gn:country_code":"TW",
    "gn:dem":471,
    "gn:feature_class":"P",
    "gn:feature_code":"PPL",
    "gn:name":"Daping",
    "gn:population":0,
    "gn:timezone":"Asia/Taipei",
    "iso:country":"TW",
    "name:ceb_x_preferred":[
        "Daping"
    ],
    "name:deu_x_preferred":[
        "Daping"
    ],
    "name:swe_x_preferred":[
        "Daping"
    ],
    "name:zho_x_preferred":[
        "\u5927\u576a"
    ],
    "name:zho_x_variant":[
        "Ta-p\u2019ing"
    ],
    "wof:name":"Daping",
    "wof:placetype":"locality"
},
  "geometry": {"coordinates":[120.82080999999999,23.88743],"type":"Point"}
}