{
  "type": "Feature",
  "properties": {
    "iso:country":"TW",
    "qs:name":"\u8c50\u6797\u6751",
    "qs:name_adm0":"\u81fa\u7063",
    "qs:name_adm1":"\u82d7\u6817\u7e23",
    "qs:photos":10,
    "qs:photos_1k":2,
    "qs:photos_9k":1,
    "qs:photos_9r":1,
    "qs:photos_all":10,
    "qs:photos_sr":1,
    "qs:placetype":"Town",
    "qs:pop_sr":"0",
    "wof:name":"\u8c50\u6797\u6751",
    "wof:placetype":"locality"
},
  "geometry": {"coordinates":[120.9025,24.49784],"type":"Point"}
}