{
  "type": "Feature",
  "properties": {
    "iso:country":"TW",
    "name:eng_x_preferred":[
        "Gaoping"
    ],
    "name:eng_x_variant":[
        "Gaoping Village"
    ],
    "name:zho_tw_x_preferred":[
        "\u9ad8\u5e73\u6751"
    ],
    "qs:name":"\u9ad8\u5e73\u6751",
    "qs:name_adm0":"\u81fa\u7063",
    "qs:name_adm1":"\u6843\u5712\u7e23",
    "qs:photos":33,
    "qs:photos_1k":7,
    "qs:photos_9k":1,
    "qs:photos_9r":2,
    "qs:photos_all":33,
    "qs:photos_sr":2,
    "qs:placetype":"Town",
    "qs:pop_sr":"0",
    "wof:name":"Gaoping",
    "wof:placetype":"locality"
},
  "geometry": {"coordinates":[121.22348700000001,24.799591],"type":"Point"}
}