{
  "type": "Feature",
  "properties": {
    "iso:country":"TW",
    "qs:name":"\u897f\u5eb7\u91cc",
    "qs:name_adm0":"\u81fa\u7063",
    "qs:name_adm1":"\u57fa\u9686\u5e02",
    "qs:photos":54,
    "qs:photos_1k":11,
    "qs:photos_9k":1,
    "qs:photos_9r":2,
    "qs:photos_all":54,
    "qs:photos_sr":2,
    "qs:placetype":"Suburb",
    "qs:pop_sr":"0",
    "wof:name":"\u897f\u5eb7\u91cc",
    "wof:placetype":"neighbourhood"
},
  "geometry": {"coordinates":[121.729888,25.142798],"type":"Point"}
}