{
  "type": "Feature",
  "properties": {
    "gn:admin1_code":"03",
    "gn:admin2_code":"TPQ",
    "gn:admin3_code":"F08",
    "gn:admin4_code":"65000190004.0",
    "gn:asciiname":"Sheshezi",
    "gn:country_code":"TW",
    "gn:dem":250,
    "gn:feature_class":"P",
    "gn:feature_code":"PPL",
    "gn:name":"Sheshezi",
    "gn:population":0,
    "gn:timezone":"Asia/Taipei",
    "iso:country":"TW",
    "name:und_x_variant":[
        "Sheshezih",
        "Sheshezi",
        "She-she-tzu"
    ],
    "name:zho_x_preferred":[
        "\u86c7\u820c\u5b50"
    ],
    "wof:name":"Sheshezi",
    "wof:placetype":"locality"
},
  "geometry": {"coordinates":[121.66160000000001,24.9698],"type":"Point"}
}