{
  "type": "Feature",
  "properties": {
    "gn:admin1_code":"2.0",
    "gn:admin2_code":"KHH",
    "gn:admin3_code":"E35",
    "gn:admin4_code":"64000350002.0",
    "gn:asciiname":"Goushikeng",
    "gn:country_code":"TW",
    "gn:dem":158,
    "gn:feature_class":"P",
    "gn:feature_code":"PPL",
    "gn:name":"Goushikeng",
    "gn:population":0,
    "gn:timezone":"Asia/Taipei",
    "iso:country":"TW",
    "name:und_x_variant":[
        "Goushihkeng"
    ],
    "name:zho_x_preferred":[
        "\u72d7\u5c4e\u5751"
    ],
    "name:zho_x_variant":[
        "Kou-shih-k\u2019eng"
    ],
    "wof:name":"Goushikeng",
    "wof:placetype":"locality"
},
  "geometry": {"coordinates":[120.52139,23.00528],"type":"Point"}
}