{
  "type": "Feature",
  "properties": {
    "gn:admin1_code":"4.0",
    "gn:admin2_code":"TTT",
    "gn:admin3_code":"V04",
    "gn:admin4_code":"10014040011.0",
    "gn:asciiname":"Lijiacun",
    "gn:country_code":"TW",
    "gn:dem":123,
    "gn:feature_class":"P",
    "gn:feature_code":"PPL",
    "gn:name":"Lijiacun",
    "gn:population":0,
    "gn:timezone":"Asia/Taipei",
    "iso:country":"TW",
    "name:und_x_variant":[
        "L\u00fc-chia",
        "Li-chia",
        "Lijiacun"
    ],
    "name:zho_x_preferred":[
        "\u5229\u5609\u6751"
    ],
    "name:zho_x_variant":[
        "Li-chia-ts\u2019un",
        "L\u00fc-chia"
    ],
    "wof:name":"Lijiacun",
    "wof:placetype":"locality"
},
  "geometry": {"coordinates":[121.06328000000001,22.77533],"type":"Point"}
}