{
  "type": "Feature",
  "properties": {
    "gn:admin1_code":"4.0",
    "gn:admin2_code":"MIA",
    "gn:admin3_code":"K05",
    "gn:admin4_code":"10005100010.0",
    "gn:asciiname":"Huangsiliao",
    "gn:country_code":"TW",
    "gn:dem":589,
    "gn:feature_class":"P",
    "gn:feature_code":"PPL",
    "gn:name":"Huangsiliao",
    "gn:population":0,
    "gn:timezone":"Asia/Taipei",
    "iso:country":"TW",
    "name:und_x_variant":[
        "Huang-ssu-liao",
        "\u9ec3\u56db\u5bee",
        "Huangsihliao"
    ],
    "name:zho_x_preferred":[
        "\u9ec3\u56db\u5bee"
    ],
    "wof:name":"Huangsiliao",
    "wof:placetype":"locality"
},
  "geometry": {"coordinates":[120.83316000000001,24.40237],"type":"Point"}
}