{
  "type": "Feature",
  "properties": {
    "gn:admin1_code":"4.0",
    "gn:admin2_code":"TXG",
    "gn:admin3_code":"B24",
    "gn:admin4_code":"66000240006.0",
    "gn:asciiname":"Kanzijiao",
    "gn:country_code":"TW",
    "gn:dem":24,
    "gn:feature_class":"P",
    "gn:feature_code":"PPL",
    "gn:name":"Kanzijiao",
    "gn:population":0,
    "gn:timezone":"Asia/Taipei",
    "iso:country":"TW",
    "name:und_x_variant":[
        "Ch\u2019ien-tzu-chiao",
        "Kanzihjiao",
        "Kanzijiao"
    ],
    "name:zho_x_preferred":[
        "\u5d01\u5b50\u811a"
    ],
    "name:zho_x_variant":[
        "K\u2019an-tzu-chiao"
    ],
    "wof:name":"Kanzijiao",
    "wof:placetype":"locality"
},
  "geometry": {"coordinates":[120.55085,24.14097000000001],"type":"Point"}
}