{
  "type": "Feature",
  "properties": {
    "gn:admin1_code":"4.0",
    "gn:admin2_code":"TXG",
    "gn:admin3_code":"B12",
    "gn:admin4_code":"66000120014.0",
    "gn:asciiname":"Zhuziliao",
    "gn:country_code":"TW",
    "gn:dem":6,
    "gn:feature_class":"P",
    "gn:feature_code":"PPL",
    "gn:name":"Zhuziliao",
    "gn:population":0,
    "gn:timezone":"Asia/Taipei",
    "iso:country":"TW",
    "name:und_x_variant":[
        "Chu-ya-liao",
        "Zhuziliao",
        "Jhuzihliao",
        "Chu-tzu-liao"
    ],
    "name:zho_x_preferred":[
        "\u7af9\u4ed4\u5bee"
    ],
    "wof:name":"Zhuziliao",
    "wof:placetype":"locality"
},
  "geometry": {"coordinates":[120.55083,24.28139],"type":"Point"}
}