{
  "type": "Feature",
  "properties": {
    "gn:admin1_code":"4.0",
    "gn:admin2_code":"MIA",
    "gn:admin3_code":"K17",
    "gn:admin4_code":"10005170005.0",
    "gn:asciiname":"Lengquan",
    "gn:country_code":"TW",
    "gn:dem":476,
    "gn:feature_class":"P",
    "gn:feature_code":"PPL",
    "gn:name":"Lengquan",
    "gn:population":0,
    "gn:timezone":"Asia/Taipei",
    "iso:country":"TW",
    "name:und_x_variant":[
        "Lengquan",
        "Lengcyuan"
    ],
    "name:zho_x_preferred":[
        "Leng-ch\u2019\u00fcan"
    ],
    "name:zho_x_variant":[
        "\u51b7\u6cc9"
    ],
    "wof:name":"Lengquan",
    "wof:placetype":"locality"
},
  "geometry": {"coordinates":[120.91423,24.47943],"type":"Point"}
}