{
  "type": "Feature",
  "properties": {
    "gn:admin1_code":"4.0",
    "gn:admin2_code":"YUN",
    "gn:admin3_code":"P05",
    "gn:admin4_code":"10009050009.0",
    "gn:asciiname":"Xiakanding",
    "gn:country_code":"TW",
    "gn:dem":19,
    "gn:feature_class":"P",
    "gn:feature_code":"PPL",
    "gn:name":"Xiakanding",
    "gn:population":0,
    "gn:timezone":"Asia/Taipei",
    "iso:country":"TW",
    "name:und_x_variant":[
        "Siakanding",
        "Xiakanding"
    ],
    "name:zho_x_preferred":[
        "\u4e0b\u5d01\u9802"
    ],
    "name:zho_x_variant":[
        "Hsia-k\u2019an-ting"
    ],
    "wof:name":"Xiakanding",
    "wof:placetype":"locality"
},
  "geometry": {"coordinates":[120.37567,23.69274],"type":"Point"}
}