{
  "type": "Feature",
  "properties": {
    "gn:admin1_code":"4.0",
    "gn:admin2_code":"MIA",
    "gn:admin3_code":"K13",
    "gn:admin4_code":"10005160007.0",
    "gn:asciiname":"Daoshikeng",
    "gn:country_code":"TW",
    "gn:dem":52,
    "gn:feature_class":"P",
    "gn:feature_code":"PPL",
    "gn:name":"Daoshikeng",
    "gn:population":0,
    "gn:timezone":"Asia/Taipei",
    "iso:country":"TW",
    "name:und_x_variant":[
        "Daoshihkeng",
        "Daoshikeng"
    ],
    "name:zho_x_preferred":[
        "\u5200\u77f3\u5751"
    ],
    "name:zho_x_variant":[
        "Tao-shih-k\u2019eng"
    ],
    "wof:name":"Daoshikeng",
    "wof:placetype":"locality"
},
  "geometry": {"coordinates":[120.92534999999999,24.61548],"type":"Point"}
}