{
  "type": "Feature",
  "properties": {
    "gn:admin1_code":"04",
    "gn:admin2_code":"NAN",
    "gn:admin3_code":"M04",
    "gn:admin4_code":"10008040011.0",
    "gn:asciiname":"Tenghu",
    "gn:country_code":"TW",
    "gn:dem":169,
    "gn:feature_class":"P",
    "gn:feature_code":"PPL",
    "gn:name":"Tenghu",
    "gn:population":0,
    "gn:timezone":"Asia/Taipei",
    "iso:country":"TW",
    "name:zho_x_preferred":[
        "\u85e4\u6e56"
    ],
    "name:zho_x_variant":[
        "T\u2019eng-hu"
    ],
    "wof:name":"Tenghu",
    "wof:placetype":"locality"
},
  "geometry": {"coordinates":[120.715,23.7788],"type":"Point"}
}