{
  "type": "Feature",
  "properties": {
    "gn:admin1_code":"03",
    "gn:admin2_code":"TPQ",
    "gn:admin3_code":"F02",
    "gn:admin4_code":"65000170017.0",
    "gn:asciiname":"Yuankuzi",
    "gn:country_code":"TW",
    "gn:dem":249,
    "gn:feature_class":"P",
    "gn:feature_code":"PPL",
    "gn:name":"Yuankuzi",
    "gn:population":0,
    "gn:timezone":"Asia/Taipei",
    "iso:country":"TW",
    "name:und_x_variant":[
        "Yuankuzih",
        "Yuankuzi"
    ],
    "name:zho_x_preferred":[
        "Chia-k\u2019u-tzu"
    ],
    "name:zho_x_variant":[
        "\u5713\u5800\u4ed4",
        "Y\u00fcan-k\u2019u-tzu"
    ],
    "wof:name":"Yuankuzi",
    "wof:placetype":"locality"
},
  "geometry": {"coordinates":[121.37322,25.06652],"type":"Point"}
}