{
  "type": "Feature",
  "properties": {
    "gn:admin1_code":"04",
    "gn:admin2_code":"CYQ",
    "gn:admin3_code":"Q04",
    "gn:admin4_code":"10010040011.0",
    "gn:asciiname":"Dabumei",
    "gn:country_code":"TW",
    "gn:dem":60,
    "gn:feature_class":"P",
    "gn:feature_code":"PPL",
    "gn:name":"Dabumei",
    "gn:population":0,
    "gn:timezone":"Asia/Taipei",
    "iso:country":"TW",
    "name:und_x_variant":[
        "Ta-pu-wei",
        "Dabumei",
        "Ta-pu-mei"
    ],
    "name:zho_x_preferred":[
        "\u5927\u57d4\u7f8e"
    ],
    "wof:name":"Dabumei",
    "wof:placetype":"locality"
},
  "geometry": {"coordinates":[120.50552999999999,23.60005],"type":"Point"}
}