{
  "type": "Feature",
  "properties": {
    "gn:admin1_code":"4.0",
    "gn:admin2_code":"HUA",
    "gn:admin3_code":"U11",
    "gn:admin4_code":"10015110002.0",
    "gn:asciiname":"Hongdoupo",
    "gn:country_code":"TW",
    "gn:dem":2790,
    "gn:feature_class":"P",
    "gn:feature_code":"PPL",
    "gn:name":"Hongdoupo",
    "gn:population":0,
    "gn:timezone":"Asia/Taipei",
    "iso:country":"TW",
    "name:zho_x_preferred":[
        "\u7d05\u8c46\u5761"
    ],
    "name:zho_x_variant":[
        "Hung-tou-p\u2019o"
    ],
    "wof:name":"Hongdoupo",
    "wof:placetype":"locality"
},
  "geometry": {"coordinates":[121.30056,24.17417],"type":"Point"}
}