{
  "type": "Feature",
  "properties": {
    "gn:admin1_code":"04",
    "gn:admin2_code":"PIF",
    "gn:admin3_code":"T12",
    "gn:admin4_code":"10013120007.0",
    "gn:asciiname":"Dalin",
    "gn:country_code":"TW",
    "gn:dem":26,
    "gn:feature_class":"P",
    "gn:feature_code":"PPL",
    "gn:name":"Dalin",
    "gn:population":0,
    "gn:timezone":"Asia/Taipei",
    "iso:country":"TW",
    "name:deu_x_preferred":[
        "Dalin"
    ],
    "name:fra_x_preferred":[
        "Dalin"
    ],
    "name:pol_x_preferred":[
        "Dalin"
    ],
    "name:und_x_variant":[
        "Ta-lin",
        "\u5927\u6797",
        "Dalin"
    ],
    "name:zho_x_preferred":[
        "\u5927\u6797"
    ],
    "wof:name":"Dalin",
    "wof:placetype":"locality"
},
  "geometry": {"coordinates":[120.6014,22.58626],"type":"Point"}
}