{
  "type": "Feature",
  "properties": {
    "gn:admin1_code":"04",
    "gn:admin2_code":"CHA",
    "gn:admin3_code":"N05",
    "gn:admin4_code":"10007100028.0",
    "gn:asciiname":"Shuiyuandi",
    "gn:country_code":"TW",
    "gn:dem":59,
    "gn:feature_class":"P",
    "gn:feature_code":"PPL",
    "gn:name":"Shuiyuandi",
    "gn:population":0,
    "gn:timezone":"Asia/Taipei",
    "iso:country":"TW",
    "name:und_x_variant":[
        "Shueiyuandi",
        "Shuiyuandi"
    ],
    "name:zho_x_preferred":[
        "\u6c34\u6e90\u5730"
    ],
    "name:zho_x_variant":[
        "Shui-y\u00fcan-ti"
    ],
    "wof:name":"Shuiyuandi",
    "wof:placetype":"locality"
},
  "geometry": {"coordinates":[120.60521,23.94887],"type":"Point"}
}