{
  "type": "Feature",
  "properties": {
    "gn:admin1_code":"4.0",
    "gn:admin2_code":"TNN",
    "gn:admin3_code":"R26",
    "gn:admin4_code":"67000260007.0",
    "gn:asciiname":"Hongshuikeng",
    "gn:country_code":"TW",
    "gn:dem":122,
    "gn:feature_class":"P",
    "gn:feature_code":"PPL",
    "gn:name":"Hongshuikeng",
    "gn:population":0,
    "gn:timezone":"Asia/Taipei",
    "iso:country":"TW",
    "name:und_x_variant":[
        "Hongshueikeng"
    ],
    "name:zho_x_preferred":[
        "\u7d05\u6c34\u5751"
    ],
    "name:zho_x_variant":[
        "Hung-shui-k\u2019eng"
    ],
    "wof:name":"Hongshuikeng",
    "wof:placetype":"locality"
},
  "geometry": {"coordinates":[120.37961,23.02818],"type":"Point"}
}