{
  "type": "Feature",
  "properties": {
    "gn:admin1_code":"4.0",
    "gn:admin2_code":"CHA",
    "gn:admin3_code":"N23",
    "gn:admin4_code":"10007230020.0",
    "gn:asciiname":"Tulonggou",
    "gn:country_code":"TW",
    "gn:dem":3,
    "gn:feature_class":"P",
    "gn:feature_code":"PPL",
    "gn:name":"Tulonggou",
    "gn:population":0,
    "gn:timezone":"Asia/Taipei",
    "iso:country":"TW",
    "name:zho_x_preferred":[
        "\u571f\u58e0\u6e9d"
    ],
    "name:zho_x_variant":[
        "T\u2019u-lung-kou"
    ],
    "wof:name":"Tulonggou",
    "wof:placetype":"locality"
},
  "geometry": {"coordinates":[120.35396,23.98215],"type":"Point"}
}