{
  "type": "Feature",
  "properties": {
    "gn:admin1_code":"4.0",
    "gn:admin2_code":"CHA",
    "gn:admin3_code":"N03",
    "gn:admin4_code":"10007030010.0",
    "gn:asciiname":"Zhenpingzhuang",
    "gn:country_code":"TW",
    "gn:dem":15,
    "gn:feature_class":"P",
    "gn:feature_code":"PPL",
    "gn:name":"Zhenpingzhuang",
    "gn:population":0,
    "gn:timezone":"Asia/Taipei",
    "iso:country":"TW",
    "name:und_x_variant":[
        "Kung-t\u2019so",
        "Chen-p\u2019ing-li",
        "Kang-tso",
        "Chen-p\u2019ing-chuang",
        "Zhenpingzhuang"
    ],
    "wof:name":"Zhenpingzhuang",
    "wof:placetype":"locality"
},
  "geometry": {"coordinates":[120.50833,24.08222],"type":"Point"}
}