{
  "type": "Feature",
  "properties": {
    "gn:admin1_code":"4.0",
    "gn:admin2_code":"CHA",
    "gn:admin3_code":"N02",
    "gn:admin4_code":"10007020024.0",
    "gn:asciiname":"Kanqiao",
    "gn:country_code":"TW",
    "gn:dem":11,
    "gn:feature_class":"P",
    "gn:feature_code":"PPL",
    "gn:name":"Kanqiao",
    "gn:population":0,
    "gn:timezone":"Asia/Taipei",
    "iso:country":"TW",
    "name:und_x_variant":[
        "Kanciao"
    ],
    "name:zho_x_preferred":[
        "\u582a\u6a4b"
    ],
    "name:zho_x_variant":[
        "Chen-ch\u2019iao",
        "K\u2019an-ch\u2019iao"
    ],
    "wof:name":"Kanqiao",
    "wof:placetype":"locality"
},
  "geometry": {"coordinates":[120.47528,24.10111],"type":"Point"}
}