{
  "type": "Feature",
  "properties": {
    "iso:country":"TW",
    "qs:name":"\u82b1\u5712\u6751",
    "qs:name_adm0":"\u81fa\u7063",
    "qs:name_adm1":"\u65b0\u7af9\u7e23",
    "qs:photos":371,
    "qs:photos_1k":75,
    "qs:photos_9k":2,
    "qs:photos_9r":5,
    "qs:photos_all":371,
    "qs:photos_sr":6,
    "qs:placetype":"Town",
    "qs:pop_sr":"0",
    "wof:name":"\u82b1\u5712\u6751",
    "wof:placetype":"locality"
},
  "geometry": {"coordinates":[121.152935,24.650761],"type":"Point"}
}