{
  "type": "Feature",
  "properties": {
    "gn:admin1_code":"4.0",
    "gn:admin2_code":"NAN",
    "gn:admin3_code":"M03",
    "gn:admin4_code":"10008030010.0",
    "gn:asciiname":"Guogou",
    "gn:country_code":"TW",
    "gn:dem":85,
    "gn:feature_class":"P",
    "gn:feature_code":"PPL",
    "gn:name":"Guogou",
    "gn:population":0,
    "gn:timezone":"Asia/Taipei",
    "iso:country":"TW",
    "name:und_x_variant":[
        "Kuo-kou"
    ],
    "name:zho_x_preferred":[
        "\u904e\u6e9d"
    ],
    "wof:name":"Guogou",
    "wof:placetype":"locality"
},
  "geometry": {"coordinates":[120.65989999999999,23.9573],"type":"Point"}
}