{
  "type": "Feature",
  "properties": {
    "gn:admin1_code":"4.0",
    "gn:admin2_code":"TNN",
    "gn:admin3_code":"R01",
    "gn:admin4_code":"67000010010.0",
    "gn:asciiname":"Maoshe",
    "gn:country_code":"TW",
    "gn:dem":17,
    "gn:feature_class":"P",
    "gn:feature_code":"PPL",
    "gn:name":"Maoshe",
    "gn:population":0,
    "gn:timezone":"Asia/Taipei",
    "iso:country":"TW",
    "name:und_x_variant":[
        "Mao-she"
    ],
    "name:zho_x_preferred":[
        "\u536f\u820d"
    ],
    "wof:name":"Maoshe",
    "wof:placetype":"locality"
},
  "geometry": {"coordinates":[120.33028,23.32167],"type":"Point"}
}