{
  "type": "Feature",
  "properties": {
    "gn:admin1_code":"4.0",
    "gn:admin2_code":"TAO",
    "gn:admin3_code":"H13",
    "gn:admin4_code":"68000130008.0",
    "gn:asciiname":"Shangbaling",
    "gn:country_code":"TW",
    "gn:dem":1192,
    "gn:feature_class":"P",
    "gn:feature_code":"PPL",
    "gn:name":"Shangbaling",
    "gn:population":0,
    "gn:timezone":"Asia/Taipei",
    "iso:country":"TW",
    "name:und_x_variant":[
        "Shang-pa-ling"
    ],
    "name:zho_x_preferred":[
        "\u4e0a\u5df4\u9675"
    ],
    "wof:name":"Shangbaling",
    "wof:placetype":"locality"
},
  "geometry": {"coordinates":[121.39639,24.685],"type":"Point"}
}