{
  "type": "Feature",
  "properties": {
    "iso:country":"TW",
    "qs:name":"\u96d9\u6e56\u6751",
    "qs:name_adm0":"\u81fa\u7063",
    "qs:name_adm1":"\u82d7\u6817\u7e23",
    "qs:photos":993,
    "qs:photos_1k":201,
    "qs:photos_9k":4,
    "qs:photos_9r":6,
    "qs:photos_all":993,
    "qs:photos_sr":10,
    "qs:placetype":"Town",
    "qs:pop_sr":"0",
    "wof:name":"\u96d9\u6e56\u6751",
    "wof:placetype":"locality"
},
  "geometry": {"coordinates":[120.742424,24.441068],"type":"Point"}
}