{
  "type": "Feature",
  "properties": {
    "gn:admin1_code":"4.0",
    "gn:admin2_code":"HUA",
    "gn:admin3_code":"U10",
    "gn:admin4_code":"10015100006.0",
    "gn:asciiname":"Qingkeng",
    "gn:country_code":"TW",
    "gn:dem":264,
    "gn:feature_class":"P",
    "gn:feature_code":"PPL",
    "gn:name":"Qingkeng",
    "gn:population":0,
    "gn:timezone":"Asia/Taipei",
    "iso:country":"TW",
    "name:und_x_variant":[
        "Cingkeng"
    ],
    "name:zho_x_preferred":[
        "\u6e05\u5751"
    ],
    "name:zho_x_variant":[
        "Ch\u2019ing-k\u2019eng"
    ],
    "wof:name":"Qingkeng",
    "wof:placetype":"locality"
},
  "geometry": {"coordinates":[121.28942000000001,23.2044],"type":"Point"}
}