{
  "type": "Feature",
  "properties": {
    "gn:admin1_code":"04",
    "gn:admin2_code":"YUN",
    "gn:admin3_code":"P08",
    "gn:admin4_code":"10009080008.0",
    "gn:asciiname":"Pitou",
    "gn:country_code":"TW",
    "gn:dem":27,
    "gn:feature_class":"P",
    "gn:feature_code":"PPL",
    "gn:name":"Pitou",
    "gn:population":0,
    "gn:timezone":"Asia/Taipei",
    "iso:country":"TW",
    "name:und_x_variant":[
        "San-cheih",
        "Pitou",
        "San-chieh"
    ],
    "name:zho_x_preferred":[
        "San-chieh-ts\u2019un"
    ],
    "name:zho_x_variant":[
        "\u57e4\u982d",
        "P\u2019i-t\u2019an",
        "P\u2019i-t\u2019ou"
    ],
    "wof:name":"Pitou",
    "wof:placetype":"locality"
},
  "geometry": {"coordinates":[120.43675,23.66163],"type":"Point"}
}