{
  "type": "Feature",
  "properties": {
    "gn:admin1_code":"04",
    "gn:admin2_code":"HSZ",
    "gn:admin3_code":"J06",
    "gn:admin4_code":"10004050017.0",
    "gn:asciiname":"Boluocun",
    "gn:country_code":"TW",
    "gn:dem":82,
    "gn:feature_class":"P",
    "gn:feature_code":"PPL",
    "gn:name":"Boluocun",
    "gn:population":0,
    "gn:timezone":"Asia/Taipei",
    "iso:country":"TW",
    "name:zho_x_preferred":[
        "Po-lo-ts\u2019un"
    ],
    "name:zho_x_variant":[
        "\u6ce2\u7f85\u6751",
        "Peng-p\u2019o-ch\u2019\u00fceh",
        "P\u2019o-lo-ts\u2019un"
    ],
    "wof:name":"Boluocun",
    "wof:placetype":"locality"
},
  "geometry": {"coordinates":[121.03722,24.88528],"type":"Point"}
}