{
  "type": "Feature",
  "properties": {
    "gn:admin1_code":"04",
    "gn:admin2_code":"TNN",
    "gn:admin3_code":"D02",
    "gn:admin4_code":"67000330023.0",
    "gn:asciiname":"Tongpanqian",
    "gn:country_code":"TW",
    "gn:dem":26,
    "gn:feature_class":"P",
    "gn:feature_code":"PPL",
    "gn:name":"Tongpanqian",
    "gn:population":0,
    "gn:timezone":"Asia/Taipei",
    "iso:country":"TW",
    "name:und_x_variant":[
        "Tongpancian",
        "Tongpanqian"
    ],
    "name:zho_x_preferred":[
        "\u6876\u76e4\u6dfa"
    ],
    "name:zho_x_variant":[
        "T\u2019ung-p\u2019an-ch\u2019ien"
    ],
    "wof:name":"Tongpanqian",
    "wof:placetype":"locality"
},
  "geometry": {"coordinates":[120.21361,22.95417],"type":"Point"}
}