{
  "type": "Feature",
  "properties": {
    "gn:admin1_code":"4.0",
    "gn:admin2_code":"CYQ",
    "gn:admin3_code":"Q09",
    "gn:admin4_code":"10010090014.0",
    "gn:asciiname":"Niaosongcun",
    "gn:country_code":"TW",
    "gn:dem":5,
    "gn:feature_class":"P",
    "gn:feature_code":"PPL",
    "gn:name":"Niaosongcun",
    "gn:population":0,
    "gn:timezone":"Asia/Taipei",
    "iso:country":"TW",
    "name:und_x_variant":[
        "Hsia-niao-sung"
    ],
    "name:zho_x_preferred":[
        "\u8526\u677e\u6751"
    ],
    "name:zho_x_variant":[
        "Hsia-niao-ts\u2019un",
        "Niao-sung-ts\u2019un"
    ],
    "wof:name":"Niaosongcun",
    "wof:placetype":"locality"
},
  "geometry": {"coordinates":[120.21715,23.47152],"type":"Point"}
}