{
  "type": "Feature",
  "properties": {
    "iso:country":"TW",
    "qs:name":"\u4e2d\u5c6f\u6751",
    "qs:name_adm0":"\u81fa\u7063",
    "qs:name_adm1":"\u6f8e\u6e56\u7e23",
    "qs:photos":255,
    "qs:photos_1k":52,
    "qs:photos_9k":1,
    "qs:photos_9r":4,
    "qs:photos_all":255,
    "qs:photos_sr":5,
    "qs:placetype":"Town",
    "qs:pop_sr":"0",
    "wof:name":"\u4e2d\u5c6f\u6751",
    "wof:placetype":"locality"
},
  "geometry": {"coordinates":[119.605875,23.619912],"type":"Point"}
}