{
  "type": "Feature",
  "properties": {
    "gn:admin1_code":"4.0",
    "gn:admin2_code":"ILA",
    "gn:admin3_code":"G09",
    "gn:admin4_code":"10002030026.0",
    "gn:asciiname":"Chaoyang",
    "gn:country_code":"TW",
    "gn:dem":98,
    "gn:feature_class":"P",
    "gn:feature_code":"PPL",
    "gn:name":"Chaoyang",
    "gn:population":0,
    "gn:timezone":"Asia/Taipei",
    "iso:country":"TW",
    "name:ceb_x_preferred":[
        "Chaoyang"
    ],
    "name:ces_x_preferred":[
        "\u010cchao-jang"
    ],
    "name:deu_x_preferred":[
        "Chaoyang"
    ],
    "name:eus_x_preferred":[
        "Chaoyang"
    ],
    "name:fra_x_preferred":[
        "Chaoyang"
    ],
    "name:mlg_x_preferred":[
        "Chaoyang"
    ],
    "name:nld_x_preferred":[
        "Chaoyang"
    ],
    "name:nor_x_preferred":[
        "Chaoyang"
    ],
    "name:pol_x_preferred":[
        "Chaoyang"
    ],
    "name:rus_x_preferred":[
        "\u0427\u0430\u043e\u044f\u043d"
    ],
    "name:spa_x_preferred":[
        "Chaoyang"
    ],
    "name:swe_x_preferred":[
        "Chaoyang"
    ],
    "name:tur_x_preferred":[
        "Chaoyang"
    ],
    "name:und_x_variant":[
        "T\u2019ui-su",
        "Ch\u2019ao-yang-li",
        "Lang-su",
        "Ch\u2019ao-yang"
    ],
    "wof:name":"Chaoyang",
    "wof:placetype":"locality"
},
  "geometry": {"coordinates":[121.81667,24.46667],"type":"Point"}
}