{
  "type": "Feature",
  "properties": {
    "gn:admin1_code":"04",
    "gn:admin2_code":"PIF",
    "gn:admin3_code":"T02",
    "gn:admin4_code":"10013020019.0",
    "gn:asciiname":"Sanliao",
    "gn:country_code":"TW",
    "gn:dem":24,
    "gn:feature_class":"P",
    "gn:feature_code":"PPL",
    "gn:name":"Sanliao",
    "gn:population":0,
    "gn:timezone":"Asia/Taipei",
    "iso:country":"TW",
    "name:und_x_variant":[
        "San-chia-ts\u2019un",
        "San-chia-chih",
        "San-chia",
        "Sanliao",
        "San-liao"
    ],
    "name:zho_x_preferred":[
        "\u4e09\u5bee"
    ],
    "name:zho_x_variant":[
        "San-chia-ch\u2019un"
    ],
    "wof:name":"Sanliao",
    "wof:placetype":"locality"
},
  "geometry": {"coordinates":[120.56218,22.55179],"type":"Point"}
}