{
  "type": "Feature",
  "properties": {
    "gn:admin1_code":"04",
    "gn:admin2_code":"CHA",
    "gn:admin3_code":"N11",
    "gn:admin4_code":"10007060003.0",
    "gn:asciiname":"Tianyangcun",
    "gn:country_code":"TW",
    "gn:dem":12,
    "gn:feature_class":"P",
    "gn:feature_code":"PPL",
    "gn:name":"Tianyangcun",
    "gn:population":0,
    "gn:timezone":"Asia/Taipei",
    "iso:country":"TW",
    "name:und_x_variant":[
        "Wai-chuang",
        "Tianyangcun"
    ],
    "name:zho_x_preferred":[
        "T\u2019ien-yang-tzu"
    ],
    "name:zho_x_variant":[
        "\u7530\u6d0b\u6751",
        "T\u2019ien-yang-ts\u2019un"
    ],
    "wof:name":"Tianyangcun",
    "wof:placetype":"locality"
},
  "geometry": {"coordinates":[120.47528,24.03861],"type":"Point"}
}