{
  "type": "Feature",
  "properties": {
    "gn:admin1_code":"3.0",
    "gn:admin2_code":"TPQ",
    "gn:admin3_code":"F27",
    "gn:admin4_code":"65000100003.0",
    "gn:asciiname":"Houzhouzi",
    "gn:country_code":"TW",
    "gn:dem":34,
    "gn:feature_class":"P",
    "gn:feature_code":"PPL",
    "gn:name":"Houzhouzi",
    "gn:population":0,
    "gn:timezone":"Asia/Taipei",
    "iso:country":"TW",
    "name:und_x_variant":[
        "Houjhouzih",
        "Houzhouzi",
        "Hou-chou-tzu"
    ],
    "name:zho_x_preferred":[
        "\u5f8c\u6d32\u5b50"
    ],
    "wof:name":"Houzhouzi",
    "wof:placetype":"locality"
},
  "geometry": {"coordinates":[121.44773000000001,25.2253],"type":"Point"}
}