{
  "type": "Feature",
  "properties": {
    "gn:admin1_code":"3.0",
    "gn:admin2_code":"TPQ",
    "gn:admin3_code":"F21",
    "gn:admin4_code":"65000120013.0",
    "gn:asciiname":"Kengzi",
    "gn:country_code":"TW",
    "gn:dem":96,
    "gn:feature_class":"P",
    "gn:feature_code":"PPL",
    "gn:name":"Kengzi",
    "gn:population":0,
    "gn:timezone":"Asia/Taipei",
    "iso:country":"TW",
    "name:und_x_variant":[
        "Kengzih"
    ],
    "name:zho_x_preferred":[
        "K\u2019eng-tzu-nei"
    ],
    "name:zho_x_variant":[
        "\u5751\u5b50",
        "K\u2019ang-nei",
        "K\u2019eng-tzu"
    ],
    "wof:name":"Kengzi",
    "wof:placetype":"locality"
},
  "geometry": {"coordinates":[121.79648,25.10123],"type":"Point"}
}