{
  "type": "Feature",
  "properties": {
    "gn:admin1_code":"4.0",
    "gn:admin2_code":"NAN",
    "gn:admin3_code":"M04",
    "gn:admin4_code":"10008040019.0",
    "gn:asciiname":"Lengshuikeng",
    "gn:country_code":"TW",
    "gn:dem":819,
    "gn:feature_class":"P",
    "gn:feature_code":"PPL",
    "gn:name":"Lengshuikeng",
    "gn:population":0,
    "gn:timezone":"Asia/Taipei",
    "iso:country":"TW",
    "name:und_x_variant":[
        "Lengshueikeng"
    ],
    "name:zho_x_preferred":[
        "\u51b7\u6c34\u5751"
    ],
    "name:zho_x_variant":[
        "Leng-shui-k\u2019eng"
    ],
    "wof:name":"Lengshuikeng",
    "wof:placetype":"locality"
},
  "geometry": {"coordinates":[120.71693999999999,23.66056],"type":"Point"}
}