{
  "type": "Feature",
  "properties": {
    "gn:admin1_code":"4.0",
    "gn:admin2_code":"PIF",
    "gn:admin3_code":"T07",
    "gn:admin4_code":"10013070001.0",
    "gn:asciiname":"Laotianwei",
    "gn:country_code":"TW",
    "gn:dem":31,
    "gn:feature_class":"P",
    "gn:feature_code":"PPL",
    "gn:name":"Laotianwei",
    "gn:population":0,
    "gn:timezone":"Asia/Taipei",
    "iso:country":"TW",
    "name:zho_x_preferred":[
        "\u8001\u7530\u5c3e"
    ],
    "name:zho_x_variant":[
        "Lao-t\u2019ien-wei"
    ],
    "wof:name":"Laotianwei",
    "wof:placetype":"locality"
},
  "geometry": {"coordinates":[120.5342,22.6549],"type":"Point"}
}