{
  "type": "Feature",
  "properties": {
    "gn:admin1_code":"04",
    "gn:admin2_code":"NAN",
    "gn:admin3_code":"M04",
    "gn:admin4_code":"10008040022.0",
    "gn:asciiname":"Muguatan",
    "gn:country_code":"TW",
    "gn:dem":207,
    "gn:feature_class":"P",
    "gn:feature_code":"PPL",
    "gn:name":"Muguatan",
    "gn:population":0,
    "gn:timezone":"Asia/Taipei",
    "iso:country":"TW",
    "name:zho_x_preferred":[
        "\u6728\u74dc\u6f6d"
    ],
    "name:zho_x_variant":[
        "Mu-kua-t\u2019an"
    ],
    "wof:name":"Muguatan",
    "wof:placetype":"locality"
},
  "geometry": {"coordinates":[120.65611,23.67611],"type":"Point"}
}