{
  "type": "Feature",
  "properties": {
    "gn:admin1_code":"4.0",
    "gn:admin2_code":"TNN",
    "gn:admin3_code":"R10",
    "gn:admin4_code":"67000100012.0",
    "gn:asciiname":"Xinpi",
    "gn:country_code":"TW",
    "gn:dem":39,
    "gn:feature_class":"P",
    "gn:feature_code":"PPL",
    "gn:name":"Xinpi",
    "gn:population":0,
    "gn:timezone":"Asia/Taipei",
    "iso:country":"TW",
    "name:und_x_variant":[
        "Sinpi",
        "Xinpi"
    ],
    "name:zho_x_preferred":[
        "\u65b0\u57e4"
    ],
    "name:zho_x_variant":[
        "Hsin-p\u2019i"
    ],
    "wof:name":"Xinpi",
    "wof:placetype":"locality"
},
  "geometry": {"coordinates":[120.35811,23.16008],"type":"Point"}
}