{
  "type": "Feature",
  "properties": {
    "gn:admin1_code":"4.0",
    "gn:admin2_code":"CYQ",
    "gn:admin3_code":"Q20",
    "gn:admin4_code":"10010180002.0",
    "gn:asciiname":"Zhaoping",
    "gn:country_code":"TW",
    "gn:dem":2297,
    "gn:feature_class":"P",
    "gn:feature_code":"PPL",
    "gn:name":"Zhaoping",
    "gn:population":0,
    "gn:timezone":"Asia/Taipei",
    "iso:country":"TW",
    "name:und_x_variant":[
        "Jhaoping",
        "Zhaoping"
    ],
    "name:zho_x_preferred":[
        "\u6cbc\u5e73"
    ],
    "name:zho_x_variant":[
        "Chao-p\u2019ing"
    ],
    "wof:name":"Zhaoping",
    "wof:placetype":"locality"
},
  "geometry": {"coordinates":[120.81278,23.51278],"type":"Point"}
}