{
  "type": "Feature",
  "properties": {
    "gn:admin1_code":"4.0",
    "gn:admin2_code":"HUA",
    "gn:admin3_code":"U10",
    "gn:admin4_code":"10015100010.0",
    "gn:asciiname":"Fuxing",
    "gn:country_code":"TW",
    "gn:dem":266,
    "gn:feature_class":"P",
    "gn:feature_code":"PPL",
    "gn:name":"Fuxing",
    "gn:population":0,
    "gn:timezone":"Asia/Taipei",
    "iso:country":"TW",
    "name:ceb_x_preferred":[
        "Fuxing"
    ],
    "name:deu_x_preferred":[
        "Fuxing"
    ],
    "name:fra_x_preferred":[
        "Fuxing"
    ],
    "name:jpn_x_preferred":[
        "\u5fa9\u8208"
    ],
    "name:nor_x_preferred":[
        "Fuxing"
    ],
    "name:und_x_variant":[
        "Fusing",
        "Fuxing",
        "Fu-hsing"
    ],
    "name:vie_x_preferred":[
        "Ph\u1ee5c H\u01b0ng"
    ],
    "name:zho_x_preferred":[
        "\u5fa9\u8208"
    ],
    "name:zho_x_variant":[
        "T\u2019u-ti-kung"
    ],
    "wof:name":"Fuxing",
    "wof:placetype":"locality"
},
  "geometry": {"coordinates":[121.26681000000001,23.16173],"type":"Point"}
}