{
  "type": "Feature",
  "properties": {
    "gn:admin1_code":"04",
    "gn:admin2_code":"CHA",
    "gn:admin3_code":"N03",
    "gn:admin4_code":"10007030026.0",
    "gn:asciiname":"Tianxinzi",
    "gn:country_code":"TW",
    "gn:dem":10,
    "gn:feature_class":"P",
    "gn:feature_code":"PPL",
    "gn:name":"Tianxinzi",
    "gn:population":0,
    "gn:timezone":"Asia/Taipei",
    "iso:country":"TW",
    "name:und_x_variant":[
        "Tiansinzih"
    ],
    "name:zho_x_preferred":[
        "T\u2019ien-hsin-li"
    ],
    "name:zho_x_variant":[
        "\u7530\u5fc3\u4ed4",
        "T\u2019ien-hsin-tzu"
    ],
    "wof:name":"Tianxinzi",
    "wof:placetype":"locality"
},
  "geometry": {"coordinates":[120.50833,24.13028],"type":"Point"}
}