{
  "type": "Feature",
  "properties": {
    "gn:admin1_code":"4.0",
    "gn:admin2_code":"CHA",
    "gn:admin3_code":"N10",
    "gn:admin4_code":"10007050002.0",
    "gn:asciiname":"Keliao",
    "gn:country_code":"TW",
    "gn:dem":7,
    "gn:feature_class":"P",
    "gn:feature_code":"PPL",
    "gn:name":"Keliao",
    "gn:population":0,
    "gn:timezone":"Asia/Taipei",
    "iso:country":"TW",
    "name:und_x_variant":[
        "Ho-liao",
        "Keliao"
    ],
    "name:zho_x_preferred":[
        "K\u2019o-liao-ts\u2019un"
    ],
    "name:zho_x_variant":[
        "Ho-liao-ts\u2019un",
        "\u86b5\u5bee",
        "K\u2019o-liao"
    ],
    "wof:name":"Keliao",
    "wof:placetype":"locality"
},
  "geometry": {"coordinates":[120.46083,24.14806],"type":"Point"}
}