{
  "type": "Feature",
  "properties": {
    "gn:admin1_code":"04",
    "gn:admin2_code":"ILA",
    "gn:admin3_code":"G05",
    "gn:admin4_code":"10002070006.0",
    "gn:asciiname":"Shangshengou",
    "gn:country_code":"TW",
    "gn:dem":51,
    "gn:feature_class":"P",
    "gn:feature_code":"PPL",
    "gn:name":"Shangshengou",
    "gn:population":0,
    "gn:timezone":"Asia/Taipei",
    "iso:country":"TW",
    "name:und_x_variant":[
        "Shang-shen-kou"
    ],
    "name:zho_x_preferred":[
        "\u4e0a\u6df1\u6e9d"
    ],
    "wof:name":"Shangshengou",
    "wof:placetype":"locality"
},
  "geometry": {"coordinates":[121.68377,24.70903],"type":"Point"}
}