{
  "type": "Feature",
  "properties": {
    "gn:admin1_code":"3.0",
    "gn:admin2_code":"TPQ",
    "gn:admin3_code":"F17",
    "gn:admin4_code":"65000070024.0",
    "gn:asciiname":"Nanyuan",
    "gn:country_code":"TW",
    "gn:dem":35,
    "gn:feature_class":"P",
    "gn:feature_code":"PPL",
    "gn:name":"Nanyuan",
    "gn:population":0,
    "gn:timezone":"Asia/Taipei",
    "iso:country":"TW",
    "name:ceb_x_preferred":[
        "Nanyuan"
    ],
    "name:swe_x_preferred":[
        "Nanyuan"
    ],
    "name:zho_x_preferred":[
        "\u5357\u5712"
    ],
    "name:zho_x_variant":[
        "Nan-y\u00fcan",
        "\u5357\u82d1"
    ],
    "wof:name":"Nanyuan",
    "wof:placetype":"locality"
},
  "geometry": {"coordinates":[121.38536999999999,24.94748],"type":"Point"}
}