{
  "type": "Feature",
  "properties": {
    "gn:admin1_code":"04",
    "gn:admin2_code":"PIF",
    "gn:admin3_code":"T06",
    "gn:admin4_code":"10013060002.0",
    "gn:asciiname":"Sanzuowu",
    "gn:country_code":"TW",
    "gn:dem":33,
    "gn:feature_class":"P",
    "gn:feature_code":"PPL",
    "gn:name":"Sanzuowu",
    "gn:population":0,
    "gn:timezone":"Asia/Taipei",
    "iso:country":"TW",
    "name:und_x_variant":[
        "San-tso-wu",
        "Sanzuowu"
    ],
    "name:zho_x_preferred":[
        "San-tso-ts\u2019o"
    ],
    "name:zho_x_variant":[
        "\u4e09\u5ea7\u5c4b"
    ],
    "wof:name":"Sanzuowu",
    "wof:placetype":"locality"
},
  "geometry": {"coordinates":[120.51988,22.68171],"type":"Point"}
}