{
  "type": "Feature",
  "properties": {
    "gn:admin1_code":"3.0",
    "gn:admin2_code":"TPQ",
    "gn:admin3_code":"F31",
    "gn:admin4_code":"65000220003.0",
    "gn:asciiname":"Laomei",
    "gn:country_code":"TW",
    "gn:dem":8,
    "gn:feature_class":"P",
    "gn:feature_code":"PPL",
    "gn:name":"Laomei",
    "gn:population":0,
    "gn:timezone":"Asia/Taipei",
    "iso:country":"TW",
    "name:und_x_variant":[
        "Kung-ti",
        "Laomei",
        "Lao-mei"
    ],
    "name:zho_x_preferred":[
        "Lao-mei-ts\u2019un"
    ],
    "name:zho_x_variant":[
        "\u8001\u6885"
    ],
    "wof:name":"Laomei",
    "wof:placetype":"locality"
},
  "geometry": {"coordinates":[121.54568999999999,25.28984],"type":"Point"}
}