{
  "type": "Feature",
  "properties": {
    "gn:admin1_code":"4.0",
    "gn:admin2_code":"HUA",
    "gn:admin3_code":"U12",
    "gn:admin4_code":"10015120004.0",
    "gn:asciiname":"Gaodeng",
    "gn:country_code":"TW",
    "gn:dem":2508,
    "gn:feature_class":"P",
    "gn:feature_code":"PPL",
    "gn:name":"Gaodeng",
    "gn:population":0,
    "gn:timezone":"Asia/Taipei",
    "iso:country":"TW",
    "name:und_x_variant":[
        "Kao-teng"
    ],
    "name:zho_x_preferred":[
        "\u9ad8\u767b"
    ],
    "wof:name":"Gaodeng",
    "wof:placetype":"locality"
},
  "geometry": {"coordinates":[121.26134999999999,23.73702],"type":"Point"}
}