{
  "type": "Feature",
  "properties": {
    "gn:admin1_code":"4.0",
    "gn:admin2_code":"NAN",
    "gn:admin3_code":"M11",
    "gn:admin4_code":"10008110018.0",
    "gn:asciiname":"Xinglong",
    "gn:country_code":"TW",
    "gn:dem":330,
    "gn:feature_class":"P",
    "gn:feature_code":"PPL",
    "gn:name":"Xinglong",
    "gn:population":0,
    "gn:timezone":"Asia/Taipei",
    "iso:country":"TW",
    "name:und_x_variant":[
        "Singlong",
        "Xinglong",
        "Hsing-lung"
    ],
    "name:zho_x_preferred":[
        "\u8208\u9686"
    ],
    "wof:name":"Xinglong",
    "wof:placetype":"locality"
},
  "geometry": {"coordinates":[120.86154999999999,23.77737],"type":"Point"}
}