{
  "type": "Feature",
  "properties": {
    "gn:admin1_code":"4.0",
    "gn:admin2_code":"NAN",
    "gn:admin3_code":"M10",
    "gn:admin4_code":"10008100008.0",
    "gn:asciiname":"Ganfeng",
    "gn:country_code":"TW",
    "gn:dem":255,
    "gn:feature_class":"P",
    "gn:feature_code":"PPL",
    "gn:name":"Ganfeng",
    "gn:population":0,
    "gn:timezone":"Asia/Taipei",
    "iso:country":"TW",
    "name:und_x_variant":[
        "Ganfong",
        "Kan-feng"
    ],
    "name:zho_x_preferred":[
        "\u4e7e\u5cf0"
    ],
    "wof:name":"Ganfeng",
    "wof:placetype":"locality"
},
  "geometry": {"coordinates":[120.82662999999999,24.02875],"type":"Point"}
}