{
  "type": "Feature",
  "properties": {
    "gn:admin1_code":"03",
    "gn:admin2_code":"TPQ",
    "gn:admin3_code":"F22",
    "gn:admin4_code":"65000240004.0",
    "gn:asciiname":"Shisunjian",
    "gn:country_code":"TW",
    "gn:dem":240,
    "gn:feature_class":"P",
    "gn:feature_code":"PPL",
    "gn:name":"Shisunjian",
    "gn:population":0,
    "gn:timezone":"Asia/Taipei",
    "iso:country":"TW",
    "name:und_x_variant":[
        "Shisunjian",
        "Shihsunjian",
        "Shih-sun-chien"
    ],
    "name:zho_x_preferred":[
        "\u77f3\u7b0b\u5c16"
    ],
    "name:zho_x_variant":[
        "Shih-Hs\u00fcn-Chien"
    ],
    "wof:name":"Shisunjian",
    "wof:placetype":"locality"
},
  "geometry": {"coordinates":[121.73049,25.0266],"type":"Point"}
}