{
  "type": "Feature",
  "properties": {
    "gn:admin1_code":"4.0",
    "gn:admin2_code":"ILA",
    "gn:admin3_code":"G08",
    "gn:admin4_code":"10002080024.0",
    "gn:asciiname":"Xiaopi",
    "gn:country_code":"TW",
    "gn:dem":103,
    "gn:feature_class":"P",
    "gn:feature_code":"PPL",
    "gn:name":"Xiaopi",
    "gn:population":0,
    "gn:timezone":"Asia/Taipei",
    "iso:country":"TW",
    "name:und_x_variant":[
        "Siaopi"
    ],
    "name:zho_x_preferred":[
        "\u5c0f\u57e4"
    ],
    "name:zho_x_variant":[
        "Hsiao-p\u2019o",
        "Hsiao-p\u2019i"
    ],
    "wof:name":"Xiaopi",
    "wof:placetype":"locality"
},
  "geometry": {"coordinates":[121.71187999999999,24.63231],"type":"Point"}
}