{
  "type": "Feature",
  "properties": {
    "gn:admin1_code":"04",
    "gn:admin2_code":"YUN",
    "gn:admin3_code":"P07",
    "gn:admin4_code":"10009070010.0",
    "gn:asciiname":"Bantianhu",
    "gn:country_code":"TW",
    "gn:dem":161,
    "gn:feature_class":"P",
    "gn:feature_code":"PPL",
    "gn:name":"Bantianhu",
    "gn:population":0,
    "gn:timezone":"Asia/Taipei",
    "iso:country":"TW",
    "name:und_x_variant":[
        "Pan-t\u2019ien-hu"
    ],
    "wof:name":"Bantianhu",
    "wof:placetype":"locality"
},
  "geometry": {"coordinates":[120.56667,23.61667000000001],"type":"Point"}
}