{
  "type": "Feature",
  "properties": {
    "gn:admin1_code":"3.0",
    "gn:admin2_code":"TPQ",
    "gn:admin3_code":"F28",
    "gn:admin4_code":"65000110017.0",
    "gn:asciiname":"Sanxiushan",
    "gn:country_code":"TW",
    "gn:dem":37,
    "gn:feature_class":"P",
    "gn:feature_code":"PPL",
    "gn:name":"Sanxiushan",
    "gn:population":0,
    "gn:timezone":"Asia/Taipei",
    "iso:country":"TW",
    "name:und_x_variant":[
        "Sansioushan",
        "Sanxiushan",
        "San-hsiu-shan"
    ],
    "name:zho_x_preferred":[
        "\u4e09\u79c0\u5c71"
    ],
    "wof:name":"Sanxiushan",
    "wof:placetype":"locality"
},
  "geometry": {"coordinates":[121.6335,25.09702],"type":"Point"}
}