{
  "type": "Feature",
  "properties": {
    "gn:admin1_code":"4.0",
    "gn:admin2_code":"HSQ",
    "gn:admin3_code":"O03",
    "gn:admin4_code":"10018030013.0",
    "gn:asciiname":"Gongkou",
    "gn:country_code":"TW",
    "gn:dem":10,
    "gn:feature_class":"P",
    "gn:feature_code":"PPL",
    "gn:name":"Gongkou",
    "gn:population":0,
    "gn:timezone":"Asia/Taipei",
    "iso:country":"TW",
    "name:zho_x_preferred":[
        "\u5bae\u53e3"
    ],
    "name:zho_x_variant":[
        "Kung-k\u2019ou"
    ],
    "wof:name":"Gongkou",
    "wof:placetype":"locality"
},
  "geometry": {"coordinates":[120.9225,24.79361],"type":"Point"}
}