{
  "type": "Feature",
  "properties": {
    "gn:admin1_code":"4.0",
    "gn:admin2_code":"TXG",
    "gn:admin3_code":"B10",
    "gn:admin4_code":"66000100024.0",
    "gn:asciiname":"Dingbu",
    "gn:country_code":"TW",
    "gn:dem":300,
    "gn:feature_class":"P",
    "gn:feature_code":"PPL",
    "gn:name":"Dingbu",
    "gn:population":0,
    "gn:timezone":"Asia/Taipei",
    "iso:country":"TW",
    "name:und_x_variant":[
        "Ting-pu",
        "Dingbu"
    ],
    "name:zho_x_preferred":[
        "\u9802\u57d4"
    ],
    "wof:name":"Dingbu",
    "wof:placetype":"locality"
},
  "geometry": {"coordinates":[120.76663000000001,24.28543],"type":"Point"}
}