{
  "type": "Feature",
  "properties": {
    "gn:admin1_code":"04",
    "gn:admin2_code":"TTT",
    "gn:admin3_code":"V01",
    "gn:admin4_code":"10014010042.0",
    "gn:asciiname":"Tianliao",
    "gn:country_code":"TW",
    "gn:dem":57,
    "gn:feature_class":"P",
    "gn:feature_code":"PPL",
    "gn:name":"Tianliao",
    "gn:population":0,
    "gn:timezone":"Asia/Taipei",
    "iso:country":"TW",
    "name:und_x_variant":[
        "T\u2019ien-liao"
    ],
    "wof:name":"Tianliao",
    "wof:placetype":"locality"
},
  "geometry": {"coordinates":[121.05,22.71667],"type":"Point"}
}