{
  "type": "Feature",
  "properties": {
    "gn:admin1_code":"3.0",
    "gn:admin2_code":"TPQ",
    "gn:admin3_code":"F19",
    "gn:admin4_code":"65000130015.0",
    "gn:asciiname":"Huotankeng",
    "gn:country_code":"TW",
    "gn:dem":257,
    "gn:feature_class":"P",
    "gn:feature_code":"PPL",
    "gn:name":"Huotankeng",
    "gn:population":0,
    "gn:timezone":"Asia/Taipei",
    "iso:country":"TW",
    "name:zho_x_preferred":[
        "\u706b\u70ad\u5751"
    ],
    "name:zho_x_variant":[
        "Huo-t\u2019an-k\u2019eng"
    ],
    "wof:name":"Huotankeng",
    "wof:placetype":"locality"
},
  "geometry": {"coordinates":[121.46326999999999,24.95243],"type":"Point"}
}