{
  "type": "Feature",
  "properties": {
    "gn:admin1_code":"04",
    "gn:admin2_code":"TNN",
    "gn:admin3_code":"R25",
    "gn:admin4_code":"67000250006.0",
    "gn:asciiname":"Jingpuliao",
    "gn:country_code":"TW",
    "gn:dem":64,
    "gn:feature_class":"P",
    "gn:feature_code":"PPL",
    "gn:name":"Jingpuliao",
    "gn:population":0,
    "gn:timezone":"Asia/Taipei",
    "iso:country":"TW",
    "name:und_x_variant":[
        "P\u2019u-liao",
        "Ching-p\u2019u-liao"
    ],
    "name:zho_x_preferred":[
        "\u83c1\u57d4\u5bee"
    ],
    "wof:name":"Jingpuliao",
    "wof:placetype":"locality"
},
  "geometry": {"coordinates":[120.44999,23.03998],"type":"Point"}
}