{
  "type": "Feature",
  "properties": {
    "gn:admin1_code":"4.0",
    "gn:admin2_code":"PEN",
    "gn:admin3_code":"X06",
    "gn:admin4_code":"10016060002.0",
    "gn:asciiname":"Xihucun",
    "gn:country_code":"TW",
    "gn:dem":7,
    "gn:feature_class":"P",
    "gn:feature_code":"PPL",
    "gn:name":"Xihucun",
    "gn:population":0,
    "gn:timezone":"Asia/Taipei",
    "iso:country":"TW",
    "name:und_x_variant":[
        "Hsi-hu-ts\u2019un"
    ],
    "wof:name":"Xihucun",
    "wof:placetype":"locality"
},
  "geometry": {"coordinates":[119.41667,23.21667],"type":"Point"}
}