{
  "type": "Feature",
  "properties": {
    "gn:admin1_code":"4.0",
    "gn:admin2_code":"CHA",
    "gn:admin3_code":"N15",
    "gn:admin4_code":"10007130015.0",
    "gn:asciiname":"Beibiantiantou",
    "gn:country_code":"TW",
    "gn:dem":28,
    "gn:feature_class":"P",
    "gn:feature_code":"PPL",
    "gn:name":"Beibiantiantou",
    "gn:population":0,
    "gn:timezone":"Asia/Taipei",
    "iso:country":"TW",
    "name:zho_x_preferred":[
        "\u5317\u908a\u7530\u982d"
    ],
    "name:zho_x_variant":[
        "Pei-pien-t\u2019ien-t\u2019ou"
    ],
    "wof:name":"Beibiantiantou",
    "wof:placetype":"locality"
},
  "geometry": {"coordinates":[120.5779,23.9826],"type":"Point"}
}