{
  "type": "Feature",
  "properties": {
    "gn:admin1_code":"4.0",
    "gn:admin2_code":"ILA",
    "gn:admin3_code":"G05",
    "gn:admin4_code":"10002070016.0",
    "gn:asciiname":"Jiuxionglin",
    "gn:country_code":"TW",
    "gn:dem":306,
    "gn:feature_class":"P",
    "gn:feature_code":"PPL",
    "gn:name":"Jiuxionglin",
    "gn:population":0,
    "gn:timezone":"Asia/Taipei",
    "iso:country":"TW",
    "name:und_x_variant":[
        "Jiousyonglin",
        "Chiu-hsiung-lin"
    ],
    "name:zho_x_preferred":[
        "\u4e5d\u828e\u6797"
    ],
    "wof:name":"Jiuxionglin",
    "wof:placetype":"locality"
},
  "geometry": {"coordinates":[121.64713999999999,24.75243],"type":"Point"}
}