{
  "type": "Feature",
  "properties": {
    "gn:admin1_code":"2.0",
    "gn:admin2_code":"KHH",
    "gn:admin3_code":"E35",
    "gn:admin4_code":"64000350007.0",
    "gn:asciiname":"Sankandian",
    "gn:country_code":"TW",
    "gn:dem":77,
    "gn:feature_class":"P",
    "gn:feature_code":"PPL",
    "gn:name":"Sankandian",
    "gn:population":0,
    "gn:timezone":"Asia/Taipei",
    "iso:country":"TW",
    "name:zho_x_preferred":[
        "\u4e09\u5d01\u5e97"
    ],
    "name:zho_x_variant":[
        "San-k\u2019an-tien"
    ],
    "wof:name":"Sankandian",
    "wof:placetype":"locality"
},
  "geometry": {"coordinates":[120.46444,22.94861],"type":"Point"}
}