{
  "type": "Feature",
  "properties": {
    "gn:admin1_code":"4.0",
    "gn:admin2_code":"CHA",
    "gn:admin3_code":"N26",
    "gn:admin4_code":"10007260010.0",
    "gn:asciiname":"Chaoyang",
    "gn:country_code":"TW",
    "gn:dem":43,
    "gn:feature_class":"P",
    "gn:feature_code":"PPL",
    "gn:name":"Chaoyang",
    "gn:population":0,
    "gn:timezone":"Asia/Taipei",
    "iso:country":"TW",
    "name:ceb_x_preferred":[
        "Chaoyang"
    ],
    "name:ces_x_preferred":[
        "\u010cchao-jang"
    ],
    "name:deu_x_preferred":[
        "Chaoyang"
    ],
    "name:eus_x_preferred":[
        "Chaoyang"
    ],
    "name:fra_x_preferred":[
        "Chaoyang"
    ],
    "name:mlg_x_preferred":[
        "Chaoyang"
    ],
    "name:nld_x_preferred":[
        "Chaoyang"
    ],
    "name:nor_x_preferred":[
        "Chaoyang"
    ],
    "name:pol_x_preferred":[
        "Chaoyang"
    ],
    "name:rus_x_preferred":[
        "\u0427\u0430\u043e\u044f\u043d"
    ],
    "name:spa_x_preferred":[
        "Chaoyang"
    ],
    "name:swe_x_preferred":[
        "Chaoyang"
    ],
    "name:tur_x_preferred":[
        "Chaoyang"
    ],
    "name:zho_x_preferred":[
        "Hu-yang-ts\u2019o"
    ],
    "name:zho_x_variant":[
        "Chang-ts\u2019o",
        "Ch\u2019ao-yang-ts\u2019o",
        "Ch\u2019ao-yang-ts\u2019un",
        "\u6f6e\u6d0b",
        "Ch\u2019ao-yang"
    ],
    "wof:name":"Chaoyang",
    "wof:placetype":"locality"
},
  "geometry": {"coordinates":[120.51721999999999,23.81292],"type":"Point"}
}