{
  "type": "Feature",
  "properties": {
    "gn:admin1_code":"04",
    "gn:admin2_code":"TTT",
    "gn:admin3_code":"V08",
    "gn:admin4_code":"10014080006.0",
    "gn:asciiname":"Baisang'an",
    "gn:country_code":"TW",
    "gn:dem":17,
    "gn:feature_class":"P",
    "gn:feature_code":"PPL",
    "gn:name":"Baisang\u2019an",
    "gn:population":0,
    "gn:timezone":"Asia/Taipei",
    "iso:country":"TW",
    "name:und_x_variant":[
        "Pai-sang-an",
        "Pa-sang-an"
    ],
    "name:zho_x_preferred":[
        "Baisang\u2019an"
    ],
    "name:zho_x_variant":[
        "\u767d\u6851\u5b89"
    ],
    "wof:name":"Baisang'an",
    "wof:placetype":"locality"
},
  "geometry": {"coordinates":[121.41785,23.25317],"type":"Point"}
}