{
  "type": "Feature",
  "properties": {
    "gn:admin1_code":"4.0",
    "gn:admin2_code":"TTT",
    "gn:admin3_code":"V03",
    "gn:admin4_code":"10014030006.0",
    "gn:asciiname":"Guangxing",
    "gn:country_code":"TW",
    "gn:dem":239,
    "gn:feature_class":"P",
    "gn:feature_code":"PPL",
    "gn:name":"Guangxing",
    "gn:population":0,
    "gn:timezone":"Asia/Taipei",
    "iso:country":"TW",
    "name:und_x_variant":[
        "Guangsing",
        "Guangxing",
        "Kuang-hsing"
    ],
    "name:zho_x_preferred":[
        "\u5ee3\u8208"
    ],
    "wof:name":"Guangxing",
    "wof:placetype":"locality"
},
  "geometry": {"coordinates":[121.17722000000001,22.99972],"type":"Point"}
}