{
  "type": "Feature",
  "properties": {
    "gn:admin1_code":"4.0",
    "gn:admin2_code":"CHA",
    "gn:admin3_code":"N20",
    "gn:admin4_code":"10007180010.0",
    "gn:asciiname":"Liuzikeng",
    "gn:country_code":"TW",
    "gn:dem":106,
    "gn:feature_class":"P",
    "gn:feature_code":"PPL",
    "gn:name":"Liuzikeng",
    "gn:population":0,
    "gn:timezone":"Asia/Taipei",
    "iso:country":"TW",
    "name:und_x_variant":[
        "Liouzihkeng"
    ],
    "name:zho_x_preferred":[
        "\u67f3\u4ed4\u5751"
    ],
    "name:zho_x_variant":[
        "Liu-tzu-k\u2019eng"
    ],
    "wof:name":"Liuzikeng",
    "wof:placetype":"locality"
},
  "geometry": {"coordinates":[120.63128,23.80802000000001],"type":"Point"}
}