{
  "type": "Feature",
  "properties": {
    "iso:country":"TW",
    "name:eng_x_preferred":[
        "Baoshan"
    ],
    "name:eng_x_variant":[
        "Baoshan Township"
    ],
    "name:fra_x_preferred":[
        "Baoshan"
    ],
    "name:heb_x_preferred":[
        "\u05d1\u05d0\u05d5\u05e9\u05d0\u05df"
    ],
    "name:hun_x_preferred":[
        "Paosan"
    ],
    "name:por_x_preferred":[
        "Baoshan"
    ],
    "name:zho_tw_x_preferred":[
        "\u5bf6\u5c71\u9109"
    ],
    "qs:name":"\u5bf6\u5c71\u9109",
    "qs:name_adm0":"\u81fa\u7063",
    "qs:name_adm1":"\u65b0\u7af9\u7e23",
    "qs:photos":7,
    "qs:photos_1k":1,
    "qs:photos_9k":1,
    "qs:photos_9r":2,
    "qs:photos_all":42,
    "qs:photos_sr":1,
    "qs:placetype":"County",
    "qs:pop_sr":"0",
    "wof:name":"Baoshan",
    "wof:placetype":"county"
},
  "geometry": {"coordinates":[120.982089,24.723697],"type":"Point"}
}