{
  "type": "Feature",
  "properties": {
    "iso:country":"TW",
    "qs:name":"\u5167\u7063\u6751",
    "qs:name_adm0":"\u81fa\u7063",
    "qs:name_adm1":"\u82d7\u6817\u7e23",
    "qs:photos":216,
    "qs:photos_1k":44,
    "qs:photos_9k":1,
    "qs:photos_9r":4,
    "qs:photos_all":216,
    "qs:photos_sr":4,
    "qs:placetype":"Town",
    "qs:pop_sr":"0",
    "wof:name":"\u5167\u7063\u6751",
    "wof:placetype":"locality"
},
  "geometry": {"coordinates":[120.949172,24.665309],"type":"Point"}
}