{
  "type": "Feature",
  "properties": {
    "gn:admin1_code":"2.0",
    "gn:admin2_code":"KHH",
    "gn:admin3_code":"E34",
    "gn:admin4_code":"64000340001.0",
    "gn:asciiname":"Fenjihu",
    "gn:country_code":"TW",
    "gn:dem":176,
    "gn:feature_class":"P",
    "gn:feature_code":"PPL",
    "gn:name":"Fenjihu",
    "gn:population":0,
    "gn:timezone":"Asia/Taipei",
    "iso:country":"TW",
    "name:und_x_variant":[
        "Fan-chi-hu",
        "Fenjihu",
        "Fen-chi-hu"
    ],
    "name:zho_x_preferred":[
        "\u7cde\u7b95\u6e56"
    ],
    "wof:name":"Fenjihu",
    "wof:placetype":"locality"
},
  "geometry": {"coordinates":[120.56056,23.00111],"type":"Point"}
}