{
  "type": "Feature",
  "properties": {
    "iso:country":"TW",
    "qs:name":"\u4ec1\u653f\u91cc",
    "qs:name_adm0":"\u81fa\u7063",
    "qs:name_adm1":"\u9ad8\u96c4\u5e02",
    "qs:photos":333,
    "qs:photos_1k":67,
    "qs:photos_9k":1,
    "qs:photos_9r":5,
    "qs:photos_all":333,
    "qs:photos_sr":5,
    "qs:placetype":"Suburb",
    "qs:pop_sr":"0",
    "wof:name":"\u4ec1\u653f\u91cc",
    "wof:placetype":"neighbourhood"
},
  "geometry": {"coordinates":[120.304236,22.619418],"type":"Point"}
}