{
  "type": "Feature",
  "properties": {
    "gn:admin1_code":"2.0",
    "gn:admin2_code":"KHH",
    "gn:admin3_code":"E22",
    "gn:admin4_code":"64000220004.0",
    "gn:asciiname":"Kunshan",
    "gn:country_code":"TW",
    "gn:dem":154,
    "gn:feature_class":"P",
    "gn:feature_code":"PPL",
    "gn:name":"Kunshan",
    "gn:population":0,
    "gn:timezone":"Asia/Taipei",
    "iso:country":"TW",
    "name:ceb_x_preferred":[
        "Kunshan"
    ],
    "name:ces_x_preferred":[
        "Kchun-\u0161an"
    ],
    "name:deu_x_preferred":[
        "Kunshan"
    ],
    "name:est_x_preferred":[
        "Kunshan"
    ],
    "name:fra_x_preferred":[
        "Kunshan"
    ],
    "name:ita_x_preferred":[
        "Kunshan"
    ],
    "name:jpn_x_preferred":[
        "\u5d11\u5c71\u5e02"
    ],
    "name:kik_x_preferred":[
        "Kunshan"
    ],
    "name:kor_x_preferred":[
        "\ucfe4\uc0b0\uc2dc"
    ],
    "name:lit_x_preferred":[
        "Kun\u0161anas"
    ],
    "name:mlg_x_preferred":[
        "Kunshan"
    ],
    "name:nor_x_preferred":[
        "Kunshan"
    ],
    "name:pol_x_preferred":[
        "Kunshan"
    ],
    "name:rus_x_preferred":[
        "\u041a\u0443\u043d\u044c\u0448\u0430\u043d\u044c"
    ],
    "name:spa_x_preferred":[
        "Kunshan"
    ],
    "name:swe_x_preferred":[
        "Kunshan"
    ],
    "name:tgl_x_preferred":[
        "Kunshan"
    ],
    "name:tur_x_preferred":[
        "Kunshan"
    ],
    "name:ukr_x_preferred":[
        "\u041a\u0443\u043d\u044c\u0448\u0430\u043d\u044c"
    ],
    "name:urd_x_preferred":[
        "\u06a9\u0648\u0646\u0634\u0627\u0646"
    ],
    "name:vie_x_preferred":[
        "C\u00f4n S\u01a1n"
    ],
    "name:war_x_preferred":[
        "Kunshan"
    ],
    "name:zho_x_preferred":[
        "\u5d11\u5c71"
    ],
    "name:zho_x_variant":[
        "K\u2019un-shan",
        "\u6606\u5c71\u5e02"
    ],
    "wof:name":"Kunshan",
    "wof:placetype":"locality"
},
  "geometry": {"coordinates":[120.43944,22.84306],"type":"Point"}
}