{
  "type": "Feature",
  "properties": {
    "gn:admin1_code":"2.0",
    "gn:admin2_code":"KHH",
    "gn:admin3_code":"E22",
    "gn:admin4_code":"64000220004.0",
    "gn:asciiname":"Kunshan",
    "gn:country_code":"TW",
    "gn:dem":154,
    "gn:feature_class":"P",
    "gn:feature_code":"PPL",
    "gn:name":"Kunshan",
    "gn:population":0,
    "gn:timezone":"Asia/Taipei",
    "iso:country":"TW",
    "name:zho_x_preferred":[
        "\u5d11\u5c71"
    ],
    "name:zho_x_variant":[
        "K\u2019un-shan"
    ],
    "wof:name":"Kunshan",
    "wof:placetype":"locality"
},
  "geometry": {"coordinates":[120.43944,22.84306],"type":"Point"}
}