{
  "type": "Feature",
  "properties": {
    "gn:admin1_code":"4.0",
    "gn:admin2_code":"CYQ",
    "gn:admin3_code":"Q03",
    "gn:admin4_code":"10010030008.0",
    "gn:asciiname":"Xincuozi",
    "gn:country_code":"TW",
    "gn:dem":2,
    "gn:feature_class":"P",
    "gn:feature_code":"PPL",
    "gn:name":"Xincuozi",
    "gn:population":0,
    "gn:timezone":"Asia/Taipei",
    "iso:country":"TW",
    "name:und_x_variant":[
        "Lung-chiang",
        "Sincuozih",
        "Xincuozi"
    ],
    "name:zho_x_preferred":[
        "Hsin-ts\u2019o-ts\u2019un"
    ],
    "name:zho_x_variant":[
        "\u65b0\u539d\u4ed4",
        "Hsin-ts\u2019o",
        "Hsin-ts\u2019o-tzu"
    ],
    "wof:name":"Xincuozi",
    "wof:placetype":"locality"
},
  "geometry": {"coordinates":[120.17023,23.3846],"type":"Point"}
}