{
  "type": "Feature",
  "properties": {
    "iso:country":"TW",
    "name:eng_x_preferred":[
        "Neicheng"
    ],
    "name:eng_x_variant":[
        "Neicheng Village"
    ],
    "name:zho_tw_x_preferred":[
        "\u5167\u57ce\u6751"
    ],
    "qs:name":"\u5167\u57ce\u6751",
    "qs:name_adm0":"\u81fa\u7063",
    "qs:name_adm1":"\u5357\u6295\u7e23",
    "qs:photos":5,
    "qs:photos_1k":1,
    "qs:photos_9k":1,
    "qs:photos_9r":1,
    "qs:photos_all":5,
    "qs:photos_sr":1,
    "qs:placetype":"Town",
    "qs:pop_sr":"0",
    "wof:name":"Neicheng",
    "wof:placetype":"locality"
},
  "geometry": {"coordinates":[120.81186599999999,23.94001],"type":"Point"}
}