{
  "type": "Feature",
  "properties": {
    "gn:admin1_code":"04",
    "gn:admin2_code":"NAN",
    "gn:admin3_code":"M09",
    "gn:admin4_code":"10008090003.0",
    "gn:asciiname":"Tianluowu",
    "gn:country_code":"TW",
    "gn:dem":665,
    "gn:feature_class":"P",
    "gn:feature_code":"PPL",
    "gn:name":"Tianluowu",
    "gn:population":0,
    "gn:timezone":"Asia/Taipei",
    "iso:country":"TW",
    "name:zho_x_preferred":[
        "T\u2019ien-io-wu"
    ],
    "name:zho_x_variant":[
        "\u7530\u87ba\u6c5a",
        "T\u2019ien-lo-wu"
    ],
    "wof:name":"Tianluowu",
    "wof:placetype":"locality"
},
  "geometry": {"coordinates":[120.91624,23.89438],"type":"Point"}
}