{
  "type": "Feature",
  "properties": {
    "gn:admin1_code":"4.0",
    "gn:admin2_code":"TNN",
    "gn:admin3_code":"R04",
    "gn:admin4_code":"67000040010.0",
    "gn:asciiname":"Danong",
    "gn:country_code":"TW",
    "gn:dem":20,
    "gn:feature_class":"P",
    "gn:feature_code":"PPL",
    "gn:name":"Danong",
    "gn:population":0,
    "gn:timezone":"Asia/Taipei",
    "iso:country":"TW",
    "name:und_x_variant":[
        "Ta-nung"
    ],
    "name:zho_x_preferred":[
        "\u5927\u8fb2"
    ],
    "wof:name":"Danong",
    "wof:placetype":"locality"
},
  "geometry": {"coordinates":[120.34833,23.28556],"type":"Point"}
}