{
  "type": "Feature",
  "properties": {
    "gn:admin1_code":"04",
    "gn:admin2_code":"TXG",
    "gn:admin3_code":"B08",
    "gn:admin4_code":"66000080014.0",
    "gn:asciiname":"Sanguicheng",
    "gn:country_code":"TW",
    "gn:dem":221,
    "gn:feature_class":"P",
    "gn:feature_code":"PPL",
    "gn:name":"Sanguicheng",
    "gn:population":0,
    "gn:timezone":"Asia/Taipei",
    "iso:country":"TW",
    "name:und_x_variant":[
        "\u4e09\u8cb4\u57ce",
        "Sangueicheng",
        "Sanguicheng",
        "San-kuei-ch\u2019eng"
    ],
    "name:zho_x_preferred":[
        "San-kuei-ch\u2019eng"
    ],
    "wof:name":"Sanguicheng",
    "wof:placetype":"locality"
},
  "geometry": {"coordinates":[120.74816,24.19474],"type":"Point"}
}