{
  "type": "Feature",
  "properties": {
    "gn:admin1_code":"4.0",
    "gn:admin2_code":"PIF",
    "gn:admin3_code":"T24",
    "gn:admin4_code":"10013240007.0",
    "gn:asciiname":"Jiupeng",
    "gn:country_code":"TW",
    "gn:dem":30,
    "gn:feature_class":"P",
    "gn:feature_code":"PPL",
    "gn:name":"Jiupeng",
    "gn:population":0,
    "gn:timezone":"Asia/Taipei",
    "iso:country":"TW",
    "name:und_x_variant":[
        "Chiu-cha",
        "Pa-yao-wan",
        "Jioupeng",
        "Jiupeng"
    ],
    "name:zho_x_preferred":[
        "Chiu-p\u2019eng-ts\u2019un"
    ],
    "name:zho_x_variant":[
        "Chiu-cha-ts\u2019un",
        "Chiu-p\u2019ing-ts\u2019un",
        "\u4e5d\u68da",
        "Chiu-p\u2019eng"
    ],
    "wof:name":"Jiupeng",
    "wof:placetype":"locality"
},
  "geometry": {"coordinates":[120.87444000000001,22.10944],"type":"Point"}
}