{
  "type": "Feature",
  "properties": {
    "gn:admin1_code":"4.0",
    "gn:admin2_code":"YUN",
    "gn:admin3_code":"P05",
    "gn:admin4_code":"10009050006.0",
    "gn:asciiname":"Xingxin",
    "gn:country_code":"TW",
    "gn:dem":19,
    "gn:feature_class":"P",
    "gn:feature_code":"PPL",
    "gn:name":"Xingxin",
    "gn:population":0,
    "gn:timezone":"Asia/Taipei",
    "iso:country":"TW",
    "name:und_x_variant":[
        "Nei-hsing",
        "Hsing-hsin-li",
        "Nei-hsing-li",
        "Hsin-hsing",
        "Xingxin",
        "Singsin",
        "Hsing-hsin"
    ],
    "name:zho_x_preferred":[
        "\u8208\u65b0"
    ],
    "wof:name":"Xingxin",
    "wof:placetype":"locality"
},
  "geometry": {"coordinates":[120.37354999999999,23.66566],"type":"Point"}
}