{
  "type": "Feature",
  "properties": {
    "iso:country":"TW",
    "name:ara_x_preferred":[
        "\u0628\u0648\u0632\u064a"
    ],
    "name:chi_x_preferred":[
        "\u6734\u5b50\u5e02"
    ],
    "name:eng_x_preferred":[
        "Puzi"
    ],
    "name:fre_x_preferred":[
        "Puzi"
    ],
    "name:ger_x_preferred":[
        "Puzih"
    ],
    "name:hak_x_preferred":[
        "Ph\u00fa-ch\u1e73\u0301-s\u1e73"
    ],
    "name:jpn_x_preferred":[
        "\u6734\u5b50\u5e02"
    ],
    "name:kor_x_preferred":[
        "\ud478\ucbd4 \uc2dc"
    ],
    "name:lit_x_preferred":[
        "Pudzi"
    ],
    "name:nan_x_preferred":[
        "Phoh-ch\u00fa-chh\u012b"
    ],
    "name:per_x_preferred":[
        "\u067e\u0648\u0632\u06cc"
    ],
    "name:pol_x_preferred":[
        "Pozi"
    ],
    "name:por_x_preferred":[
        "Puzi"
    ],
    "name:rus_x_preferred":[
        "\u041f\u0443\u0446\u0437\u044b"
    ],
    "name:vie_x_preferred":[
        "Ph\u00e1c T\u1eed"
    ],
    "ne:ADM0CAP":0.0,
    "ne:ADM0NAME":"Taiwan",
    "ne:ADM0_A3":"TWN",
    "ne:ADM1NAME":"Chiayi",
    "ne:ADMIN1_COD":0,
    "ne:CAPALT":0,
    "ne:CHANGED":0,
    "ne:CHECKME":0,
    "ne:COMPARE":0,
    "ne:DIFFASCII":0,
    "ne:DIFFNOTE":"Added",
    "ne:ELEVATION":0.0,
    "ne:FEATURECLA":"Populated place",
    "ne:GEONAMEID":1670367,
    "ne:GEONAMESNO":"GeoNames match general.",
    "ne:GN_POP":0,
    "ne:GTOPO30":0.0,
    "ne:ISO_A2":"TW",
    "ne:LABELRANK":8,
    "ne:LATITUDE":23.461111,
    "ne:LONGITUDE":120.241944,
    "ne:LS_MATCH":0,
    "ne:LS_NAME":"Puzi",
    "ne:MAX_AREAKM":0.0,
    "ne:MAX_AREAMI":0.0,
    "ne:MAX_BBXMAX":0.0,
    "ne:MAX_BBXMIN":0.0,
    "ne:MAX_BBYMAX":0.0,
    "ne:MAX_BBYMIN":0.0,
    "ne:MAX_NATSCA":0.0,
    "ne:MAX_PERKM":0.0,
    "ne:MAX_PERMI":0.0,
    "ne:MAX_POP10":0,
    "ne:MAX_POP20":0,
    "ne:MAX_POP300":0,
    "ne:MAX_POP310":0,
    "ne:MAX_POP50":0,
    "ne:MEAN_BBXC":0.0,
    "ne:MEAN_BBYC":0.0,
    "ne:MEGACITY":0,
    "ne:MIN_AREAKM":0.0,
    "ne:MIN_AREAMI":0.0,
    "ne:MIN_BBXMAX":0.0,
    "ne:MIN_BBXMIN":0.0,
    "ne:MIN_BBYMAX":0.0,
    "ne:MIN_BBYMIN":0.0,
    "ne:MIN_PERKM":0.0,
    "ne:MIN_PERMI":0.0,
    "ne:NAME":"Puzi",
    "ne:NAMEASCII":"Puzi",
    "ne:NAMEDIFF":0,
    "ne:NATSCALE":10,
    "ne:POP1950":0,
    "ne:POP1955":0,
    "ne:POP1960":0,
    "ne:POP1965":0,
    "ne:POP1970":0,
    "ne:POP1975":0,
    "ne:POP1980":0,
    "ne:POP1985":0,
    "ne:POP1990":0,
    "ne:POP1995":0,
    "ne:POP2000":0,
    "ne:POP2005":0,
    "ne:POP2010":0,
    "ne:POP2015":0,
    "ne:POP2020":0,
    "ne:POP2025":0,
    "ne:POP2050":0,
    "ne:POP_MAX":50000,
    "ne:POP_MIN":44084,
    "ne:POP_OTHER":0,
    "ne:RANK_MAX":7,
    "ne:RANK_MIN":7,
    "ne:SCALERANK":8,
    "ne:SOV0NAME":"Taiwan",
    "ne:SOV_A3":"TWN",
    "ne:UN_FID":0,
    "ne:UN_LAT":0.0,
    "ne:UN_LONG":0.0,
    "ne:WORLDCITY":0,
    "ne:min_zoom":7.0,
    "wof:name":"Puzi",
    "wof:placetype":"locality"
},
  "geometry": {"coordinates":[120.241944444444,23.4611111111111],"type":"Point"}
}