{
  "type": "Feature",
  "properties": {
    "iso:country":"TW",
    "name:eng_x_preferred":[
        "Yuying"
    ],
    "name:eng_x_variant":[
        "Yuying Village"
    ],
    "name:zho_tw_x_preferred":[
        "\u80b2\u82f1\u91cc"
    ],
    "qs:name":"\u80b2\u82f1\u91cc",
    "qs:name_adm0":"\u81fa\u7063",
    "qs:name_adm1":"\u65b0\u7af9\u5e02",
    "qs:photos":36,
    "qs:photos_1k":7,
    "qs:photos_9k":1,
    "qs:photos_9r":2,
    "qs:photos_all":36,
    "qs:photos_sr":2,
    "qs:placetype":"Suburb",
    "qs:pop_sr":"0",
    "wof:name":"Yuying",
    "wof:placetype":"neighbourhood"
},
  "geometry": {"coordinates":[120.960035,24.798053],"type":"Point"}
}