{
  "type": "Feature",
  "properties": {
    "gn:admin1_code":"4.0",
    "gn:admin2_code":"YUN",
    "gn:admin3_code":"P11",
    "gn:admin4_code":"10009110006.0",
    "gn:asciiname":"Dingtianwei",
    "gn:country_code":"TW",
    "gn:dem":26,
    "gn:feature_class":"P",
    "gn:feature_code":"PPL",
    "gn:name":"Dingtianwei",
    "gn:population":0,
    "gn:timezone":"Asia/Taipei",
    "iso:country":"TW",
    "name:und_x_variant":[
        "Ting-chuang"
    ],
    "name:zho_x_preferred":[
        "\u9802\u7530\u5c3e"
    ],
    "name:zho_x_variant":[
        "Ting-t\u2019ien-wei"
    ],
    "wof:name":"Dingtianwei",
    "wof:placetype":"locality"
},
  "geometry": {"coordinates":[120.42094,23.76114],"type":"Point"}
}