{
  "type": "Feature",
  "properties": {
    "iso:country":"TW",
    "name:eng_x_preferred":[
        "Wunan"
    ],
    "name:eng_x_variant":[
        "Wunan Village"
    ],
    "name:zho_tw_x_preferred":[
        "\u68a7\u5357\u6751"
    ],
    "qs:name":"\u68a7\u5357\u6751",
    "qs:name_adm0":"\u81fa\u7063",
    "qs:name_adm1":"\u96f2\u6797\u7e23",
    "qs:photos":16,
    "qs:photos_1k":3,
    "qs:photos_9k":1,
    "qs:photos_9r":1,
    "qs:photos_all":16,
    "qs:photos_sr":1,
    "qs:placetype":"Town",
    "qs:pop_sr":"0",
    "wof:name":"Wunan",
    "wof:placetype":"locality"
},
  "geometry": {"coordinates":[120.173164,23.546527],"type":"Point"}
}