{
  "type": "Feature",
  "properties": {
    "gn:admin1_code":"4.0",
    "gn:admin2_code":"TAO",
    "gn:admin3_code":"H06",
    "gn:admin4_code":"68000060013.0",
    "gn:asciiname":"Guotian",
    "gn:country_code":"TW",
    "gn:dem":8,
    "gn:feature_class":"P",
    "gn:feature_code":"PPL",
    "gn:name":"Guotian",
    "gn:population":0,
    "gn:timezone":"Asia/Taipei",
    "iso:country":"TW",
    "name:zho_x_preferred":[
        "\u904e\u7530"
    ],
    "name:zho_x_variant":[
        "Kuo-t\u2019ien"
    ],
    "wof:name":"Guotian",
    "wof:placetype":"locality"
},
  "geometry": {"coordinates":[121.24633,25.10626],"type":"Point"}
}