{
  "type": "Feature",
  "properties": {
    "gn:admin1_code":"3.0",
    "gn:admin2_code":"TPQ",
    "gn:admin3_code":"F31",
    "gn:admin4_code":"65000220002.0",
    "gn:asciiname":"Dengtaikou",
    "gn:country_code":"TW",
    "gn:dem":34,
    "gn:feature_class":"P",
    "gn:feature_code":"PPL",
    "gn:name":"Dengtaikou",
    "gn:population":0,
    "gn:timezone":"Asia/Taipei",
    "iso:country":"TW",
    "name:zho_x_preferred":[
        "\u71c8\u81fa\u53e3"
    ],
    "name:zho_x_variant":[
        "Teng-t\u2019ai-k\u2019ou"
    ],
    "wof:name":"Dengtaikou",
    "wof:placetype":"locality"
},
  "geometry": {"coordinates":[121.54058999999999,25.28816],"type":"Point"}
}