{
  "type": "Feature",
  "properties": {
    "gn:admin1_code":"04",
    "gn:admin2_code":"HSZ",
    "gn:admin3_code":"J02",
    "gn:admin4_code":"10004020004.0",
    "gn:asciiname":"Yuandongzi",
    "gn:country_code":"TW",
    "gn:dem":188,
    "gn:feature_class":"P",
    "gn:feature_code":"PPL",
    "gn:name":"Yuandongzi",
    "gn:population":0,
    "gn:timezone":"Asia/Taipei",
    "iso:country":"TW",
    "name:und_x_variant":[
        "Yuandongzih",
        "Yuandongzi"
    ],
    "name:zho_x_preferred":[
        "\u54e1\u5d20\u5b50"
    ],
    "name:zho_x_variant":[
        "Y\u00fcan-tung-tzu"
    ],
    "wof:name":"Yuandongzi",
    "wof:placetype":"locality"
},
  "geometry": {"coordinates":[121.09778,24.71],"type":"Point"}
}