{
  "type": "Feature",
  "properties": {
    "gn:admin1_code":"4.0",
    "gn:admin2_code":"YUN",
    "gn:admin3_code":"P13",
    "gn:admin4_code":"10009130004.0",
    "gn:asciiname":"Xiaoren",
    "gn:country_code":"TW",
    "gn:dem":8,
    "gn:feature_class":"P",
    "gn:feature_code":"PPL",
    "gn:name":"Xiaoren",
    "gn:population":0,
    "gn:timezone":"Asia/Taipei",
    "iso:country":"TW",
    "name:und_x_variant":[
        "Siaoren",
        "Xiaoren",
        "Hsiao-jen"
    ],
    "name:zho_x_preferred":[
        "\u9704\u4ec1"
    ],
    "wof:name":"Xiaoren",
    "wof:placetype":"locality"
},
  "geometry": {"coordinates":[120.27997999999999,23.75233],"type":"Point"}
}