{
  "type": "Feature",
  "properties": {
    "gn:country":"TW",
    "iso:country":"TW",
    "qs:name":"\u8449\u6751",
    "qs:name_adm0":"\u81fa\u7063",
    "qs:name_adm1":"\u6f8e\u6e56\u7e23",
    "qs:photos":947,
    "qs:photos_1k":192,
    "qs:photos_9k":4,
    "qs:photos_9r":6,
    "qs:photos_all":947,
    "qs:photos_sr":10,
    "qs:placetype":"Town",
    "qs:pop_sr":"0",
    "wof:name":"\u8449\u6751",
    "wof:placetype":"locality"
},
  "geometry": {"coordinates":[119.681061,23.579166],"type":"Point"}
}