{
  "type": "Feature",
  "properties": {
    "gn:admin1_code":"04",
    "gn:admin2_code":"TNN",
    "gn:admin3_code":"R14",
    "gn:admin4_code":"67000150002.0",
    "gn:asciiname":"Dingtancun",
    "gn:country_code":"TW",
    "gn:dem":5,
    "gn:feature_class":"P",
    "gn:feature_code":"PPL",
    "gn:name":"Dingtancun",
    "gn:population":0,
    "gn:timezone":"Asia/Taipei",
    "iso:country":"TW",
    "name:zho_x_preferred":[
        "\u9802\u6f6d\u6751"
    ],
    "name:zho_x_variant":[
        "Ting-t\u2019an",
        "T\u2019ai-t\u2019an-ts\u2019un",
        "Hou-chiang-ta-t\u2019an-liao",
        "Ta-t\u2019an-liao",
        "T\u2019ai-t\u2019an",
        "Ting-t\u2019an-ts\u2019un"
    ],
    "wof:name":"Dingtancun",
    "wof:placetype":"locality"
},
  "geometry": {"coordinates":[120.13056,23.19222],"type":"Point"}
}