{
  "type": "Feature",
  "properties": {
    "gn:admin1_code":"4.0",
    "gn:admin2_code":"TNN",
    "gn:admin3_code":"D06",
    "gn:admin4_code":"67000350038.0",
    "gn:asciiname":"Nan'anshun",
    "gn:country_code":"TW",
    "gn:dem":6,
    "gn:feature_class":"P",
    "gn:feature_code":"PPL",
    "gn:name":"Nan\u2019anshun",
    "gn:population":0,
    "gn:timezone":"Asia/Taipei",
    "iso:country":"TW",
    "name:und_x_variant":[
        "Nan-an-shun",
        "\u5357\u5b89\u9806"
    ],
    "name:zho_x_preferred":[
        "Nan\u2019anshun"
    ],
    "name:zho_x_variant":[
        "\u5357\u5b89\u9806"
    ],
    "wof:name":"Nan'anshun",
    "wof:placetype":"locality"
},
  "geometry": {"coordinates":[120.21250000000001,23.02667000000001],"type":"Point"}
}