{
  "type": "Feature",
  "properties": {
    "gn:admin1_code":"04",
    "gn:admin2_code":"PIF",
    "gn:admin3_code":"T30",
    "gn:admin4_code":"10013300003.0",
    "gn:asciiname":"Danlin",
    "gn:country_code":"TW",
    "gn:dem":150,
    "gn:feature_class":"P",
    "gn:feature_code":"PPL",
    "gn:name":"Danlin",
    "gn:population":0,
    "gn:timezone":"Asia/Taipei",
    "iso:country":"TW",
    "name:und_x_variant":[
        "Tan-lin",
        "Danlin",
        "Tan-na-hsiu"
    ],
    "name:zho_x_preferred":[
        "T\u2019a-na-hsiu"
    ],
    "name:zho_x_variant":[
        "T\u2019a-na-hsiu-she",
        "Tan-lin-ts\u2019un",
        "\u4e39\u6797"
    ],
    "wof:name":"Danlin",
    "wof:placetype":"locality"
},
  "geometry": {"coordinates":[120.63554999999999,22.51627],"type":"Point"}
}