{
  "type": "Feature",
  "properties": {
    "gn:admin1_code":"4.0",
    "gn:admin2_code":"TAO",
    "gn:admin3_code":"H06",
    "gn:admin4_code":"68000060004.0",
    "gn:asciiname":"Jiucuozi",
    "gn:country_code":"TW",
    "gn:dem":45,
    "gn:feature_class":"P",
    "gn:feature_code":"PPL",
    "gn:name":"Jiucuozi",
    "gn:population":0,
    "gn:timezone":"Asia/Taipei",
    "iso:country":"TW",
    "name:und_x_variant":[
        "Jioucuozih",
        "Jiucuozi",
        "Chiu-wu-tzu"
    ],
    "name:zho_x_preferred":[
        "\u820a\u539d\u4ed4"
    ],
    "name:zho_x_variant":[
        "Chiu-ts\u2019o-tzu"
    ],
    "wof:name":"Jiucuozi",
    "wof:placetype":"locality"
},
  "geometry": {"coordinates":[121.17505,25.04441],"type":"Point"}
}