{
  "type": "Feature",
  "properties": {
    "gn:admin1_code":"04",
    "gn:admin2_code":"CYQ",
    "gn:admin3_code":"Q06",
    "gn:admin4_code":"10010060004.0",
    "gn:asciiname":"Youcuo",
    "gn:country_code":"TW",
    "gn:dem":19,
    "gn:feature_class":"P",
    "gn:feature_code":"PPL",
    "gn:name":"Youcuo",
    "gn:population":0,
    "gn:timezone":"Asia/Taipei",
    "iso:country":"TW",
    "name:und_x_variant":[
        "Yu-tung"
    ],
    "name:zho_x_preferred":[
        "Yu-tung-ts\u2019un"
    ],
    "name:zho_x_variant":[
        "\u6e38\u539d",
        "Yu-ts\u2019o"
    ],
    "wof:name":"Youcuo",
    "wof:placetype":"locality"
},
  "geometry": {"coordinates":[120.40513,23.61769],"type":"Point"}
}