{
  "type": "Feature",
  "properties": {
    "gn:admin1_code":"03",
    "gn:admin2_code":"TPQ",
    "gn:admin3_code":"F03",
    "gn:admin4_code":"65000150004.0",
    "gn:asciiname":"Bengshan",
    "gn:country_code":"TW",
    "gn:dem":269,
    "gn:feature_class":"P",
    "gn:feature_code":"PPL",
    "gn:name":"Bengshan",
    "gn:population":0,
    "gn:timezone":"Asia/Taipei",
    "iso:country":"TW",
    "name:und_x_variant":[
        "Peng-shan"
    ],
    "name:zho_x_preferred":[
        "\u5d29\u5c71"
    ],
    "wof:name":"Bengshan",
    "wof:placetype":"locality"
},
  "geometry": {"coordinates":[121.41946000000002,25.12592],"type":"Point"}
}