{
  "type": "Feature",
  "properties": {
    "gn:admin1_code":"04",
    "gn:admin2_code":"MIA",
    "gn:admin3_code":"K18",
    "gn:admin4_code":"10005180002.0",
    "gn:asciiname":"Nantianwo",
    "gn:country_code":"TW",
    "gn:dem":653,
    "gn:feature_class":"P",
    "gn:feature_code":"PPL",
    "gn:name":"Nantianwo",
    "gn:population":0,
    "gn:timezone":"Asia/Taipei",
    "iso:country":"TW",
    "name:und_x_variant":[
        "Nan-ta-wo",
        "Nantianwo"
    ],
    "name:zho_x_preferred":[
        "Nan-t\u2019ien-wo"
    ],
    "name:zho_x_variant":[
        "\u5357\u5929\u7aa9"
    ],
    "wof:name":"Nantianwo",
    "wof:placetype":"locality"
},
  "geometry": {"coordinates":[120.96966,24.46022],"type":"Point"}
}