{
  "type": "Feature",
  "properties": {
    "gn:country":"TW",
    "gn:fcode":"PPL",
    "gn:pop":16597,
    "iso:country":"TW",
    "name:deu_x_preferred":[
        "Yujing"
    ],
    "name:eng_x_preferred":[
        "Yujing District"
    ],
    "name:hak_x_preferred":[
        "Ngiu\u030dk-tsi\u00e1ng-hi\u00f4ng"
    ],
    "name:jpn_x_preferred":[
        "\u7389\u4e95\u533a"
    ],
    "name:kor_x_preferred":[
        "\uc704\uc9d5\uad6c"
    ],
    "name:nan_x_preferred":[
        "Gio\u030dk-ch\u00e9\u207f-khu"
    ],
    "name:unk_x_variant":[
        "Y\u00fc-ching-chuang"
    ],
    "name:vie_x_preferred":[
        "Ng\u1ecdc T\u0129nh"
    ],
    "name:yue_x_preferred":[
        "\u7389\u4e95\u5340"
    ],
    "name:zho_x_preferred":[
        "Y\u00fc-ching-ts\u2019un"
    ],
    "name:zho_x_variant":[
        "\u7389\u4e95",
        "Y\u00fc-ching",
        "Y\u00fc-ching-chuang",
        "\u7389\u4e95\u5340"
    ],
    "qs:name":"Yujing",
    "qs:photos_9r":0,
    "qs:photos_sr":0,
    "qs:pop_sr":"6",
    "wd:wordcount":394,
    "wof:name":"Yujing",
    "wof:placetype":"locality",
    "wof:population":16597
},
  "geometry": {"coordinates":[120.46138000000001,23.12493],"type":"Point"}
}