{
  "type": "Feature",
  "properties": {
    "gn:country":"TW",
    "gn:fcode":"PPL",
    "gn:pop":16597,
    "iso:country":"TW",
    "name:unk_x_variant":[
        "Y\u00fc-ching-chuang"
    ],
    "name:zho_x_preferred":[
        "Y\u00fc-ching-ts\u2019un"
    ],
    "name:zho_x_variant":[
        "\u7389\u4e95",
        "Y\u00fc-ching",
        "Y\u00fc-ching-chuang"
    ],
    "qs:name":"Yujing",
    "qs:photos_9r":0,
    "qs:photos_sr":0,
    "qs:pop_sr":"6",
    "wd:wordcount":394,
    "wof:name":"Yujing",
    "wof:placetype":"locality",
    "wof:population":16597
},
  "geometry": {"coordinates":[120.46138000000001,23.12493],"type":"Point"}
}