{
  "type": "Feature",
  "properties": {
    "gn:admin1_code":"4.0",
    "gn:admin2_code":"CYQ",
    "gn:admin3_code":"Q16",
    "gn:admin4_code":"10010150017.0",
    "gn:asciiname":"Sheqianhu",
    "gn:country_code":"TW",
    "gn:dem":705,
    "gn:feature_class":"P",
    "gn:feature_code":"PPL",
    "gn:name":"Sheqianhu",
    "gn:population":0,
    "gn:timezone":"Asia/Taipei",
    "iso:country":"TW",
    "name:und_x_variant":[
        "Shecianhu",
        "Sheqianhu"
    ],
    "name:zho_x_preferred":[
        "\u793e\u524d\u6e56"
    ],
    "name:zho_x_variant":[
        "She-ch\u2019ien-hu"
    ],
    "wof:name":"Sheqianhu",
    "wof:placetype":"locality"
},
  "geometry": {"coordinates":[120.72278,23.55639],"type":"Point"}
}