{
  "type": "Feature",
  "properties": {
    "gn:admin1_code":"4.0",
    "gn:admin2_code":"TTT",
    "gn:admin3_code":"V09",
    "gn:admin4_code":"10014050004.0",
    "gn:asciiname":"Gaotai",
    "gn:country_code":"TW",
    "gn:dem":310,
    "gn:feature_class":"P",
    "gn:feature_code":"PPL",
    "gn:name":"Gaotai",
    "gn:population":0,
    "gn:timezone":"Asia/Taipei",
    "iso:country":"TW",
    "name:zho_x_preferred":[
        "\u9ad8\u81fa"
    ],
    "name:zho_x_variant":[
        "Kao-t\u2019ai"
    ],
    "wof:name":"Gaotai",
    "wof:placetype":"locality"
},
  "geometry": {"coordinates":[121.12644,22.9257],"type":"Point"}
}