{
  "type": "Feature",
  "properties": {
    "gn:admin1_code":"04",
    "gn:admin2_code":"TNN",
    "gn:admin3_code":"R27",
    "gn:admin4_code":"67000270008.0",
    "gn:asciiname":"Shanglunzi",
    "gn:country_code":"TW",
    "gn:dem":11,
    "gn:feature_class":"P",
    "gn:feature_code":"PPL",
    "gn:name":"Shanglunzi",
    "gn:population":0,
    "gn:timezone":"Asia/Taipei",
    "iso:country":"TW",
    "name:und_x_variant":[
        "Shanglunzih",
        "Shang-lun",
        "Shanglunzi",
        "Shang-lun-tzu"
    ],
    "name:zho_x_preferred":[
        "Shang-lun-ts\u2019un"
    ],
    "name:zho_x_variant":[
        "\u4e0a\u5d19\u4ed4"
    ],
    "wof:name":"Shanglunzi",
    "wof:placetype":"locality"
},
  "geometry": {"coordinates":[120.25778,22.94333],"type":"Point"}
}