{
  "type": "Feature",
  "properties": {
    "gn:admin1_code":"04",
    "gn:admin2_code":"TNN",
    "gn:admin3_code":"R01",
    "gn:admin4_code":"67000010010.0",
    "gn:asciiname":"Tuku",
    "gn:country_code":"TW",
    "gn:dem":22,
    "gn:feature_class":"P",
    "gn:feature_code":"PPL",
    "gn:name":"Tuku",
    "gn:population":0,
    "gn:timezone":"Asia/Taipei",
    "iso:country":"TW",
    "name:zho_x_preferred":[
        "\u571f\u5eab"
    ],
    "name:zho_x_variant":[
        "T\u2019u-k\u2019u"
    ],
    "wof:name":"Tuku",
    "wof:placetype":"locality"
},
  "geometry": {"coordinates":[120.34667,23.32056],"type":"Point"}
}