{
  "type": "Feature",
  "properties": {
    "gn:admin1_code":"03",
    "gn:admin2_code":"TPQ",
    "gn:admin3_code":"F01",
    "gn:admin4_code":"65000050023.0",
    "gn:asciiname":"Siyuan",
    "gn:country_code":"TW",
    "gn:dem":18,
    "gn:feature_class":"P",
    "gn:feature_code":"PPL",
    "gn:name":"Siyuan",
    "gn:population":0,
    "gn:timezone":"Asia/Taipei",
    "iso:country":"TW",
    "name:und_x_variant":[
        "Hsiao-t\u2019ien-hsin-tzu",
        "Ssu-y\u00fcan",
        "Siyuan"
    ],
    "wof:name":"Siyuan",
    "wof:placetype":"locality"
},
  "geometry": {"coordinates":[121.45,25.05],"type":"Point"}
}