{
  "type": "Feature",
  "properties": {
    "gn:admin1_code":"04",
    "gn:admin2_code":"TXG",
    "gn:admin3_code":"B18",
    "gn:admin4_code":"66000180003.0",
    "gn:asciiname":"Buziqian",
    "gn:country_code":"TW",
    "gn:dem":181,
    "gn:feature_class":"P",
    "gn:feature_code":"PPL",
    "gn:name":"Buziqian",
    "gn:population":0,
    "gn:timezone":"Asia/Taipei",
    "iso:country":"TW",
    "name:und_x_variant":[
        "Buzihcian"
    ],
    "name:zho_x_preferred":[
        "\u57d4\u5b50\u5898"
    ],
    "name:zho_x_variant":[
        "Pu-tzu-ch\u2019ien"
    ],
    "wof:name":"Buziqian",
    "wof:placetype":"locality"
},
  "geometry": {"coordinates":[120.63500000000001,24.24333],"type":"Point"}
}