{
  "type": "Feature",
  "properties": {
    "gn:admin1_code":"4.0",
    "gn:admin2_code":"NAN",
    "gn:admin3_code":"M07",
    "gn:admin4_code":"10008070011.0",
    "gn:asciiname":"Hongyintuku",
    "gn:country_code":"TW",
    "gn:dem":969,
    "gn:feature_class":"P",
    "gn:feature_code":"PPL",
    "gn:name":"Hongyintuku",
    "gn:population":0,
    "gn:timezone":"Asia/Taipei",
    "iso:country":"TW",
    "name:zho_x_preferred":[
        "\u7d05\u9280\u571f\u5800"
    ],
    "name:zho_x_variant":[
        "Hung-yin-t\u2019u-k\u2019u"
    ],
    "wof:name":"Hongyintuku",
    "wof:placetype":"locality"
},
  "geometry": {"coordinates":[120.81072,23.77158],"type":"Point"}
}