{
  "type": "Feature",
  "properties": {
    "gn:admin1_code":"4.0",
    "gn:admin2_code":"MIA",
    "gn:admin3_code":"K09",
    "gn:admin4_code":"10005040004.0",
    "gn:asciiname":"Sanjiaodian",
    "gn:country_code":"TW",
    "gn:dem":13,
    "gn:feature_class":"P",
    "gn:feature_code":"PPL",
    "gn:name":"Sanjiaodian",
    "gn:population":0,
    "gn:timezone":"Asia/Taipei",
    "iso:country":"TW",
    "name:und_x_variant":[
        "San-chiao-tien"
    ],
    "name:zho_x_preferred":[
        "\u4e09\u89d2\u5e97"
    ],
    "wof:name":"Sanjiaodian",
    "wof:placetype":"locality"
},
  "geometry": {"coordinates":[120.88294999999999,24.685],"type":"Point"}
}