{
  "type": "Feature",
  "properties": {
    "gn:admin1_code":"3.0",
    "gn:admin2_code":"TPQ",
    "gn:admin3_code":"F25",
    "gn:admin4_code":"65000270012.0",
    "gn:asciiname":"Jianshanzi",
    "gn:country_code":"TW",
    "gn:dem":45,
    "gn:feature_class":"P",
    "gn:feature_code":"PPL",
    "gn:name":"Jianshanzi",
    "gn:population":0,
    "gn:timezone":"Asia/Taipei",
    "iso:country":"TW",
    "name:und_x_variant":[
        "Jianshanzih",
        "Jianshanzi",
        "Chien-shan-tzu"
    ],
    "name:zho_x_preferred":[
        "\u5c16\u5c71\u5b50"
    ],
    "wof:name":"Jianshanzi",
    "wof:placetype":"locality"
},
  "geometry": {"coordinates":[121.63333,25.25005],"type":"Point"}
}