{
  "type": "Feature",
  "properties": {
    "gn:admin1_code":"04",
    "gn:admin2_code":"YUN",
    "gn:admin3_code":"P16",
    "gn:admin4_code":"10009160015.0",
    "gn:asciiname":"Wacuo",
    "gn:country_code":"TW",
    "gn:dem":6,
    "gn:feature_class":"P",
    "gn:feature_code":"PPL",
    "gn:name":"Wacuo",
    "gn:population":0,
    "gn:timezone":"Asia/Taipei",
    "iso:country":"TW",
    "name:und_x_variant":[
        "Wu-chiang",
        "Wu-kang",
        "Wacuo"
    ],
    "name:zho_x_preferred":[
        "Wu-chiang-ts\u2019un"
    ],
    "name:zho_x_variant":[
        "\u74e6\u539d",
        "Wa-ts\u2019o"
    ],
    "wof:name":"Wacuo",
    "wof:placetype":"locality"
},
  "geometry": {"coordinates":[120.20889,23.71472],"type":"Point"}
}