{
  "type": "Feature",
  "properties": {
    "gn:admin1_code":"4.0",
    "gn:admin2_code":"CYQ",
    "gn:admin3_code":"Q14",
    "gn:admin4_code":"10010130017.0",
    "gn:asciiname":"Bengshan",
    "gn:country_code":"TW",
    "gn:dem":150,
    "gn:feature_class":"P",
    "gn:feature_code":"PPL",
    "gn:name":"Bengshan",
    "gn:population":0,
    "gn:timezone":"Asia/Taipei",
    "iso:country":"TW",
    "name:und_x_variant":[
        "Peng-shan"
    ],
    "name:zho_x_preferred":[
        "\u5d29\u5c71"
    ],
    "wof:name":"Bengshan",
    "wof:placetype":"locality"
},
  "geometry": {"coordinates":[120.54040999999999,23.39561],"type":"Point"}
}