{
  "type": "Feature",
  "properties": {
    "gn:admin1_code":"4.0",
    "gn:admin2_code":"MIA",
    "gn:admin3_code":"K15",
    "gn:admin4_code":"10005080012.0",
    "gn:asciiname":"Dachongku",
    "gn:country_code":"TW",
    "gn:dem":351,
    "gn:feature_class":"P",
    "gn:feature_code":"PPL",
    "gn:name":"Dachongku",
    "gn:population":0,
    "gn:timezone":"Asia/Taipei",
    "iso:country":"TW",
    "name:zho_x_preferred":[
        "\u5927\u9283\u5eab"
    ],
    "name:zho_x_variant":[
        "Ta-ch\u2019ung-k\u2019u"
    ],
    "wof:name":"Dachongku",
    "wof:placetype":"locality"
},
  "geometry": {"coordinates":[120.83710000000001,24.35684],"type":"Point"}
}