{
  "type": "Feature",
  "properties": {
    "gn:admin1_code":"4.0",
    "gn:admin2_code":"TAO",
    "gn:admin3_code":"H12",
    "gn:admin4_code":"68000120022.0",
    "gn:asciiname":"Haihudi",
    "gn:country_code":"TW",
    "gn:dem":8,
    "gn:feature_class":"P",
    "gn:feature_code":"PPL",
    "gn:name":"Haihudi",
    "gn:population":0,
    "gn:timezone":"Asia/Taipei",
    "iso:country":"TW",
    "name:und_x_variant":[
        "Hai-hu-ti"
    ],
    "name:zho_x_preferred":[
        "\u6d77\u6e56\u5e95"
    ],
    "wof:name":"Haihudi",
    "wof:placetype":"locality"
},
  "geometry": {"coordinates":[121.12024,25.0695],"type":"Point"}
}