{
  "type": "Feature",
  "properties": {
    "gn:admin1_code":"04",
    "gn:admin2_code":"CHA",
    "gn:admin3_code":"N05",
    "gn:admin4_code":"10007100024.0",
    "gn:asciiname":"Wannian",
    "gn:country_code":"TW",
    "gn:dem":34,
    "gn:feature_class":"P",
    "gn:feature_code":"PPL",
    "gn:name":"Wannian",
    "gn:population":0,
    "gn:timezone":"Asia/Taipei",
    "iso:country":"TW",
    "name:und_x_variant":[
        "Wan-nien"
    ],
    "name:zho_x_preferred":[
        "\u842c\u5e74"
    ],
    "wof:name":"Wannian",
    "wof:placetype":"locality"
},
  "geometry": {"coordinates":[120.58226999999999,23.94693],"type":"Point"}
}