{
  "type": "Feature",
  "properties": {
    "gn:admin1_code":"4.0",
    "gn:admin2_code":"TPE",
    "gn:admin3_code":"A15",
    "gn:admin4_code":"63000110048.0",
    "gn:asciiname":"Shuiwei",
    "gn:country_code":"TW",
    "gn:dem":390,
    "gn:feature_class":"P",
    "gn:feature_code":"PPL",
    "gn:name":"Shuiwei",
    "gn:population":0,
    "gn:timezone":"Asia/Taipei",
    "iso:country":"TW",
    "name:und_x_variant":[
        "Shueiwei",
        "Shui-wei"
    ],
    "name:zho_x_preferred":[
        "\u6c34\u5c3e"
    ],
    "wof:name":"Shuiwei",
    "wof:placetype":"locality"
},
  "geometry": {"coordinates":[121.57441,25.12873],"type":"Point"}
}