{
  "type": "Feature",
  "properties": {
    "gn:admin1_code":"4.0",
    "gn:admin2_code":"YUN",
    "gn:admin3_code":"P12",
    "gn:admin4_code":"10009120013.0",
    "gn:asciiname":"Tiandizi",
    "gn:country_code":"TW",
    "gn:dem":13,
    "gn:feature_class":"P",
    "gn:feature_code":"PPL",
    "gn:name":"Tiandizi",
    "gn:population":0,
    "gn:timezone":"Asia/Taipei",
    "iso:country":"TW",
    "name:und_x_variant":[
        "Hsin-kung-kuan",
        "Tiandizi",
        "Tiandizih",
        "Hsin-sheng"
    ],
    "name:zho_x_preferred":[
        "\u7530\u5e95\u4ed4"
    ],
    "name:zho_x_variant":[
        "T\u2019ien-ti-tzu"
    ],
    "wof:name":"Tiandizi",
    "wof:placetype":"locality"
},
  "geometry": {"coordinates":[120.35138000000001,23.79651],"type":"Point"}
}