{
  "type": "Feature",
  "properties": {
    "gn:admin1_code":"02",
    "gn:admin2_code":"KHH",
    "gn:admin3_code":"E19",
    "gn:admin4_code":"64000190026.0",
    "gn:asciiname":"Shamaoshi",
    "gn:country_code":"TW",
    "gn:dem":9,
    "gn:feature_class":"P",
    "gn:feature_code":"PPL",
    "gn:name":"Shamaoshi",
    "gn:population":0,
    "gn:timezone":"Asia/Taipei",
    "iso:country":"TW",
    "name:und_x_variant":[
        "Sha-mao-shih"
    ],
    "wof:name":"Shamaoshi",
    "wof:placetype":"locality"
},
  "geometry": {"coordinates":[120.31667,22.81667],"type":"Point"}
}