{
  "type": "Feature",
  "properties": {
    "gn:admin1_code":"4.0",
    "gn:admin2_code":"ILA",
    "gn:admin3_code":"G04",
    "gn:admin4_code":"10002060003.0",
    "gn:asciiname":"Funanxing",
    "gn:country_code":"TW",
    "gn:dem":4,
    "gn:feature_class":"P",
    "gn:feature_code":"PPL",
    "gn:name":"Funanxing",
    "gn:population":0,
    "gn:timezone":"Asia/Taipei",
    "iso:country":"TW",
    "name:und_x_variant":[
        "Fu-nan-hsing",
        "Funanxing"
    ],
    "name:zho_x_preferred":[
        "\u526f\u5357\u8208"
    ],
    "wof:name":"Funanxing",
    "wof:placetype":"locality"
},
  "geometry": {"coordinates":[121.7953,24.7207],"type":"Point"}
}