{
  "type": "Feature",
  "properties": {
    "gn:admin1_code":"4.0",
    "gn:admin2_code":"CHA",
    "gn:admin3_code":"N23",
    "gn:admin4_code":"10007230023.0",
    "gn:asciiname":"Dingwanggongliao",
    "gn:country_code":"TW",
    "gn:dem":11,
    "gn:feature_class":"P",
    "gn:feature_code":"PPL",
    "gn:name":"Dingwanggongliao",
    "gn:population":0,
    "gn:timezone":"Asia/Taipei",
    "iso:country":"TW",
    "name:und_x_variant":[
        "Ting-wang-kung-liao"
    ],
    "name:zho_x_preferred":[
        "\u9802\u738b\u529f\u5bee"
    ],
    "wof:name":"Dingwanggongliao",
    "wof:placetype":"locality"
},
  "geometry": {"coordinates":[120.38927,23.97689],"type":"Point"}
}