{
  "type": "Feature",
  "properties": {
    "gn:admin1_code":"4.0",
    "gn:admin2_code":"TAO",
    "gn:admin3_code":"H02",
    "gn:admin4_code":"68000030012.0",
    "gn:asciiname":"Dongneizha",
    "gn:country_code":"TW",
    "gn:dem":143,
    "gn:feature_class":"P",
    "gn:feature_code":"PPL",
    "gn:name":"Dongneizha",
    "gn:population":0,
    "gn:timezone":"Asia/Taipei",
    "iso:country":"TW",
    "name:und_x_variant":[
        "Dongneijha",
        "Dongneizha",
        "Tung-nei-cha"
    ],
    "name:zho_x_preferred":[
        "\u6771\u5167\u67f5"
    ],
    "wof:name":"Dongneizha",
    "wof:placetype":"locality"
},
  "geometry": {"coordinates":[121.28413999999999,24.85896],"type":"Point"}
}