{
  "type": "Feature",
  "properties": {
    "gn:admin1_code":"4.0",
    "gn:admin2_code":"CHA",
    "gn:admin3_code":"N26",
    "gn:admin4_code":"10007260018.0",
    "gn:asciiname":"Datong",
    "gn:country_code":"TW",
    "gn:dem":60,
    "gn:feature_class":"P",
    "gn:feature_code":"PPL",
    "gn:name":"Datong",
    "gn:population":0,
    "gn:timezone":"Asia/Taipei",
    "iso:country":"TW",
    "name:zho_x_preferred":[
        "\u5927\u540c"
    ],
    "name:zho_x_variant":[
        "Ta-t\u2019ung"
    ],
    "wof:name":"Datong",
    "wof:placetype":"locality"
},
  "geometry": {"coordinates":[120.57726,23.81915],"type":"Point"}
}