{
  "type": "Feature",
  "properties": {
    "gn:admin1_code":"04",
    "gn:admin2_code":"ILA",
    "gn:admin3_code":"G11",
    "gn:admin4_code":"10002110007.0",
    "gn:asciiname":"Renze",
    "gn:country_code":"TW",
    "gn:dem":640,
    "gn:feature_class":"P",
    "gn:feature_code":"PPL",
    "gn:name":"Renze",
    "gn:population":0,
    "gn:timezone":"Asia/Taipei",
    "iso:country":"TW",
    "name:und_x_variant":[
        "Shao-shui",
        "Jen-tse"
    ],
    "name:zho_x_preferred":[
        "\u4ec1\u6fa4"
    ],
    "wof:name":"Renze",
    "wof:placetype":"locality"
},
  "geometry": {"coordinates":[121.50444,24.54361],"type":"Point"}
}