{
  "type": "Feature",
  "properties": {
    "gn:admin1_code":"02",
    "gn:admin2_code":"KHH",
    "gn:admin3_code":"E22",
    "gn:admin4_code":"64000220004.0",
    "gn:asciiname":"Dapingding",
    "gn:country_code":"TW",
    "gn:dem":92,
    "gn:feature_class":"P",
    "gn:feature_code":"PPL",
    "gn:name":"Dapingding",
    "gn:population":0,
    "gn:timezone":"Asia/Taipei",
    "iso:country":"TW",
    "name:zho_x_preferred":[
        "\u5927\u576a\u9802"
    ],
    "name:zho_x_variant":[
        "Ta-p\u2019ing-ting"
    ],
    "wof:name":"Dapingding",
    "wof:placetype":"locality"
},
  "geometry": {"coordinates":[120.42083,22.84306],"type":"Point"}
}