{
  "type": "Feature",
  "properties": {
    "gn:admin1_code":"4.0",
    "gn:admin2_code":"TAO",
    "gn:admin3_code":"H03",
    "gn:admin4_code":"68000020022.0",
    "gn:asciiname":"Caoxilun",
    "gn:country_code":"TW",
    "gn:dem":63,
    "gn:feature_class":"P",
    "gn:feature_code":"PPL",
    "gn:name":"Caoxilun",
    "gn:population":0,
    "gn:timezone":"Asia/Taipei",
    "iso:country":"TW",
    "name:und_x_variant":[
        "Caosilun"
    ],
    "name:zho_x_preferred":[
        "\u8349\u84c6\u5d19"
    ],
    "name:zho_x_variant":[
        "Ts\u2019ao-hsi-lun"
    ],
    "wof:name":"Caoxilun",
    "wof:placetype":"locality"
},
  "geometry": {"coordinates":[121.19726,25.02374],"type":"Point"}
}