{
  "type": "Feature",
  "properties": {
    "gn:admin1_code":"4.0",
    "gn:admin2_code":"TAO",
    "gn:admin3_code":"H09",
    "gn:admin4_code":"68000090016.0",
    "gn:asciiname":"Fanziwo",
    "gn:country_code":"TW",
    "gn:dem":278,
    "gn:feature_class":"P",
    "gn:feature_code":"PPL",
    "gn:name":"Fanziwo",
    "gn:population":0,
    "gn:timezone":"Asia/Taipei",
    "iso:country":"TW",
    "name:und_x_variant":[
        "Fanzihwo",
        "Fan-wu",
        "Fanziwo",
        "Fan-tzu-wo"
    ],
    "name:zho_x_preferred":[
        "\u756a\u5b50\u7aa9"
    ],
    "wof:name":"Fanziwo",
    "wof:placetype":"locality"
},
  "geometry": {"coordinates":[121.17778,24.85556],"type":"Point"}
}