{
  "type": "Feature",
  "properties": {
    "gn:admin1_code":"04",
    "gn:admin2_code":"NAN",
    "gn:admin3_code":"M01",
    "gn:admin4_code":"10008010034.0",
    "gn:asciiname":"Shanjiao",
    "gn:country_code":"TW",
    "gn:dem":109,
    "gn:feature_class":"P",
    "gn:feature_code":"PPL",
    "gn:name":"Shanjiao",
    "gn:population":0,
    "gn:timezone":"Asia/Taipei",
    "iso:country":"TW",
    "name:und_x_variant":[
        "Shan-chiao"
    ],
    "name:zho_x_preferred":[
        "\u5c71\u811a"
    ],
    "wof:name":"Shanjiao",
    "wof:placetype":"locality"
},
  "geometry": {"coordinates":[120.68595999999999,23.96114],"type":"Point"}
}