{
  "type": "Feature",
  "properties": {
    "gn:admin1_code":"4.0",
    "gn:admin2_code":"PEN",
    "gn:admin3_code":"X02",
    "gn:admin4_code":"10016020003.0",
    "gn:asciiname":"Qingluo",
    "gn:country_code":"TW",
    "gn:dem":9,
    "gn:feature_class":"P",
    "gn:feature_code":"PPL",
    "gn:name":"Qingluo",
    "gn:population":0,
    "gn:timezone":"Asia/Taipei",
    "iso:country":"TW",
    "name:und_x_variant":[
        "Cingluo",
        "Qingluo"
    ],
    "name:zho_x_preferred":[
        "Ch\u2019ing-lo-she"
    ],
    "name:zho_x_variant":[
        "Ch\u2019ing-tieh",
        "Ch\u2019ing-lo-ts\u2019un",
        "\u9751\u87ba",
        "Ch\u2019ing-lo"
    ],
    "wof:name":"Qingluo",
    "wof:placetype":"locality"
},
  "geometry": {"coordinates":[119.64951000000001,23.59945],"type":"Point"}
}