{
  "type": "Feature",
  "properties": {
    "gn:admin1_code":"2.0",
    "gn:admin2_code":"KHH",
    "gn:admin3_code":"E30",
    "gn:admin4_code":"64000300016.0",
    "gn:asciiname":"Hechang",
    "gn:country_code":"TW",
    "gn:dem":58,
    "gn:feature_class":"P",
    "gn:feature_code":"PPL",
    "gn:name":"Hechang",
    "gn:population":0,
    "gn:timezone":"Asia/Taipei",
    "iso:country":"TW",
    "name:zho_x_preferred":[
        "\u548c\u660c"
    ],
    "name:zho_x_variant":[
        "Ho-ch\u2019ang"
    ],
    "wof:name":"Hechang",
    "wof:placetype":"locality"
},
  "geometry": {"coordinates":[120.47028,22.86389],"type":"Point"}
}