{
  "type": "Feature",
  "properties": {
    "gn:admin1_code":"4.0",
    "gn:admin2_code":"HSZ",
    "gn:admin3_code":"J03",
    "gn:admin4_code":"10004040005.0",
    "gn:asciiname":"Niulanhe",
    "gn:country_code":"TW",
    "gn:dem":221,
    "gn:feature_class":"P",
    "gn:feature_code":"PPL",
    "gn:name":"Niulanhe",
    "gn:population":0,
    "gn:timezone":"Asia/Taipei",
    "iso:country":"TW",
    "name:und_x_variant":[
        "Nioulanhe",
        "Niu-lan-ho"
    ],
    "name:zho_x_preferred":[
        "\u725b\u6b04\u6cb3"
    ],
    "wof:name":"Niulanhe",
    "wof:placetype":"locality"
},
  "geometry": {"coordinates":[121.19333,24.80556],"type":"Point"}
}