{
  "type": "Feature",
  "properties": {
    "iso:country":"TW",
    "name:eng_x_preferred":[
        "Houcun"
    ],
    "name:eng_x_variant":[
        "Houcun Village"
    ],
    "name:zho_tw_x_preferred":[
        "\u5f8c\u6751\u6751"
    ],
    "qs:name":"\u5f8c\u6751\u6751",
    "qs:name_adm0":"\u81fa\u7063",
    "qs:name_adm1":"\u5c4f\u6771\u7e23",
    "qs:photos":31,
    "qs:photos_1k":6,
    "qs:photos_9k":1,
    "qs:photos_9r":2,
    "qs:photos_all":31,
    "qs:photos_sr":2,
    "qs:placetype":"Town",
    "qs:pop_sr":"0",
    "wof:name":"Houcun",
    "wof:placetype":"locality"
},
  "geometry": {"coordinates":[120.4585,22.571167],"type":"Point"}
}