{
  "type": "Feature",
  "properties": {
    "gn:admin1_code":"4.0",
    "gn:admin2_code":"YUN",
    "gn:admin3_code":"P18",
    "gn:admin4_code":"10009180020.0",
    "gn:asciiname":"Feidong",
    "gn:country_code":"TW",
    "gn:dem":5,
    "gn:feature_class":"P",
    "gn:feature_code":"PPL",
    "gn:name":"Feidong",
    "gn:population":0,
    "gn:timezone":"Asia/Taipei",
    "iso:country":"TW",
    "name:und_x_variant":[
        "Fei-tung"
    ],
    "name:zho_x_preferred":[
        "\u98db\u6771"
    ],
    "name:zho_x_variant":[
        "Fei-tung-ts\u2019un"
    ],
    "wof:name":"Feidong",
    "wof:placetype":"locality"
},
  "geometry": {"coordinates":[120.18472,23.645],"type":"Point"}
}