{
  "type": "Feature",
  "properties": {
    "gn:admin1_code":"4.0",
    "gn:admin2_code":"TAO",
    "gn:admin3_code":"H11",
    "gn:admin4_code":"68000110009.0",
    "gn:asciiname":"Shangzhuangzi",
    "gn:country_code":"TW",
    "gn:dem":64,
    "gn:feature_class":"P",
    "gn:feature_code":"PPL",
    "gn:name":"Shangzhuangzi",
    "gn:population":0,
    "gn:timezone":"Asia/Taipei",
    "iso:country":"TW",
    "name:und_x_variant":[
        "Shangjhuangzih",
        "Shang-chuang-tzu"
    ],
    "name:zho_x_preferred":[
        "\u4e0a\u5e84\u5b50"
    ],
    "wof:name":"Shangzhuangzi",
    "wof:placetype":"locality"
},
  "geometry": {"coordinates":[121.08583,24.97083],"type":"Point"}
}