{
  "type": "Feature",
  "properties": {
    "gn:admin1_code":"4.0",
    "gn:admin2_code":"MIA",
    "gn:admin3_code":"K03",
    "gn:admin4_code":"10005030011.0",
    "gn:asciiname":"Zoucuo",
    "gn:country_code":"TW",
    "gn:dem":101,
    "gn:feature_class":"P",
    "gn:feature_code":"PPL",
    "gn:name":"Zoucuo",
    "gn:population":0,
    "gn:timezone":"Asia/Taipei",
    "iso:country":"TW",
    "name:zho_x_preferred":[
        "\u9112\u539d"
    ],
    "name:zho_x_variant":[
        "Tsou-ts\u2019o"
    ],
    "wof:name":"Zoucuo",
    "wof:placetype":"locality"
},
  "geometry": {"coordinates":[120.69667,24.45139],"type":"Point"}
}