{
  "type": "Feature",
  "properties": {
    "gn:admin1_code":"4.0",
    "gn:admin2_code":"HUA",
    "gn:admin3_code":"U09",
    "gn:admin4_code":"10015090006.0",
    "gn:asciiname":"Maliyun",
    "gn:country_code":"TW",
    "gn:dem":148,
    "gn:feature_class":"P",
    "gn:feature_code":"PPL",
    "gn:name":"Maliyun",
    "gn:population":0,
    "gn:timezone":"Asia/Taipei",
    "iso:country":"TW",
    "name:und_x_variant":[
        "Wu-hao",
        "\u99ac\u7acb\u96f2",
        "Ma-li-wen",
        "Maliyun",
        "Wu-ho"
    ],
    "name:zho_x_preferred":[
        "Ma-li-y\u00fcn"
    ],
    "name:zho_x_variant":[
        "\u99ac\u7acb\u96f2"
    ],
    "wof:name":"Maliyun",
    "wof:placetype":"locality"
},
  "geometry": {"coordinates":[121.34992,23.47274],"type":"Point"}
}