{
  "type": "Feature",
  "properties": {
    "gn:admin1_code":"04",
    "gn:admin2_code":"TAO",
    "gn:admin3_code":"H03",
    "gn:admin4_code":"68000020049.0",
    "gn:asciiname":"Shandong",
    "gn:country_code":"TW",
    "gn:dem":70,
    "gn:feature_class":"P",
    "gn:feature_code":"PPL",
    "gn:name":"Shandong",
    "gn:population":0,
    "gn:timezone":"Asia/Taipei",
    "iso:country":"TW",
    "name:und_x_variant":[
        "Shan-tung-li",
        "Shandong",
        "Shan-tung"
    ],
    "name:zho_x_preferred":[
        "\u5c71\u6771"
    ],
    "wof:name":"Shandong",
    "wof:placetype":"locality"
},
  "geometry": {"coordinates":[121.17416,25.01769],"type":"Point"}
}