{
  "type": "Feature",
  "properties": {
    "gn:admin1_code":"4.0",
    "gn:admin2_code":"TNN",
    "gn:admin3_code":"D06",
    "gn:admin4_code":"67000350032.0",
    "gn:asciiname":"Wendi",
    "gn:country_code":"TW",
    "gn:dem":8,
    "gn:feature_class":"P",
    "gn:feature_code":"PPL",
    "gn:name":"Wendi",
    "gn:population":0,
    "gn:timezone":"Asia/Taipei",
    "iso:country":"TW",
    "name:deu_x_preferred":[
        "Wendi"
    ],
    "name:fra_x_preferred":[
        "Wendi"
    ],
    "name:ita_x_preferred":[
        "Wendi"
    ],
    "name:pol_x_preferred":[
        "Wendi"
    ],
    "name:und_x_variant":[
        "Wen-ti",
        "Wei-ti",
        "Wundi"
    ],
    "name:zho_x_preferred":[
        "\u586d\u5e95"
    ],
    "wof:name":"Wendi",
    "wof:placetype":"locality"
},
  "geometry": {"coordinates":[120.11667,23.07444],"type":"Point"}
}