{
  "type": "Feature",
  "properties": {
    "gn:admin1_code":"3.0",
    "gn:admin2_code":"TPQ",
    "gn:admin3_code":"F21",
    "gn:admin4_code":"65000120013.0",
    "gn:asciiname":"Bafenliaoding",
    "gn:country_code":"TW",
    "gn:dem":356,
    "gn:feature_class":"P",
    "gn:feature_code":"PPL",
    "gn:name":"Bafenliaoding",
    "gn:population":0,
    "gn:timezone":"Asia/Taipei",
    "iso:country":"TW",
    "name:und_x_variant":[
        "Pa-fen-liao-ting"
    ],
    "name:zho_x_preferred":[
        "\u516b\u5206\u5bee\u9802"
    ],
    "wof:name":"Bafenliaoding",
    "wof:placetype":"locality"
},
  "geometry": {"coordinates":[121.79470999999999,25.08291],"type":"Point"}
}