{
  "type": "Feature",
  "properties": {
    "gn:admin1_code":"4.0",
    "gn:admin2_code":"HUA",
    "gn:admin3_code":"U05",
    "gn:admin4_code":"10015050017.0",
    "gn:asciiname":"Fuxingdongcun",
    "gn:country_code":"TW",
    "gn:dem":29,
    "gn:feature_class":"P",
    "gn:feature_code":"PPL",
    "gn:name":"Fuxingdongcun",
    "gn:population":0,
    "gn:timezone":"Asia/Taipei",
    "iso:country":"TW",
    "name:und_x_variant":[
        "Fusingdongcun",
        "Fuxingdongcun"
    ],
    "name:zho_x_preferred":[
        "\u5fa9\u8208\u6771\u6751"
    ],
    "name:zho_x_variant":[
        "Fu-hsing-tung-ts\u2019un"
    ],
    "wof:name":"Fuxingdongcun",
    "wof:placetype":"locality"
},
  "geometry": {"coordinates":[121.58333,23.95639],"type":"Point"}
}