{
  "type": "Feature",
  "properties": {
    "gn:admin1_code":"4.0",
    "gn:admin2_code":"HUA",
    "gn:admin3_code":"U06",
    "gn:admin4_code":"10015060010.0",
    "gn:asciiname":"Wuquan",
    "gn:country_code":"TW",
    "gn:dem":31,
    "gn:feature_class":"P",
    "gn:feature_code":"PPL",
    "gn:name":"Wuquan",
    "gn:population":0,
    "gn:timezone":"Asia/Taipei",
    "iso:country":"TW",
    "name:und_x_variant":[
        "Wucyuan"
    ],
    "name:zho_x_preferred":[
        "\u5433\u5168"
    ],
    "name:zho_x_variant":[
        "Wu-ch\u2019\u00fcan-ch\u2019eng",
        "Wu-ch\u2019\u00fcan"
    ],
    "wof:name":"Wuquan",
    "wof:placetype":"locality"
},
  "geometry": {"coordinates":[121.55056,23.88833],"type":"Point"}
}