{
  "type": "Feature",
  "properties": {
    "gn:admin1_code":"4.0",
    "gn:admin2_code":"PEN",
    "gn:admin3_code":"X04",
    "gn:admin4_code":"10016040004.0",
    "gn:asciiname":"Wandi",
    "gn:country_code":"TW",
    "gn:dem":28,
    "gn:feature_class":"P",
    "gn:feature_code":"PPL",
    "gn:name":"Wandi",
    "gn:population":0,
    "gn:timezone":"Asia/Taipei",
    "iso:country":"TW",
    "name:ceb_x_preferred":[
        "Wandi"
    ],
    "name:swe_x_preferred":[
        "Wandi"
    ],
    "name:und_x_variant":[
        "Wan-ti"
    ],
    "name:zho_x_preferred":[
        "\u7063\u5e95"
    ],
    "wof:name":"Wandi",
    "wof:placetype":"locality"
},
  "geometry": {"coordinates":[119.51454,23.62554],"type":"Point"}
}