{
  "type": "Feature",
  "properties": {
    "gn:admin1_code":"04",
    "gn:admin2_code":"HSZ",
    "gn:admin3_code":"J12",
    "gn:admin4_code":"10004090004.0",
    "gn:asciiname":"Mabushupai",
    "gn:country_code":"TW",
    "gn:dem":147,
    "gn:feature_class":"P",
    "gn:feature_code":"PPL",
    "gn:name":"Mabushupai",
    "gn:population":0,
    "gn:timezone":"Asia/Taipei",
    "iso:country":"TW",
    "name:zho_x_preferred":[
        "Ma-pu-shu-t\u2019ao"
    ],
    "name:zho_x_variant":[
        "\u9ebb\u5e03\u6a39\u6392",
        "Shui-ts\u2019un",
        "Ma-pu-shu-p\u2019ai"
    ],
    "wof:name":"Mabushupai",
    "wof:placetype":"locality"
},
  "geometry": {"coordinates":[121.06778,24.70861],"type":"Point"}
}