{
  "type": "Feature",
  "properties": {
    "gn:admin1_code":"3.0",
    "gn:admin2_code":"TPQ",
    "gn:admin3_code":"F24",
    "gn:admin4_code":"65000260005.0",
    "gn:asciiname":"Jiushe",
    "gn:country_code":"TW",
    "gn:dem":17,
    "gn:feature_class":"P",
    "gn:feature_code":"PPL",
    "gn:name":"Jiushe",
    "gn:population":0,
    "gn:timezone":"Asia/Taipei",
    "iso:country":"TW",
    "name:und_x_variant":[
        "Chui-she",
        "She-li",
        "Lung-men",
        "Jiushe",
        "Jioushe",
        "Lung-men-chieh",
        "Chiu-she"
    ],
    "name:zho_x_preferred":[
        "Lung-men-ts\u2019un"
    ],
    "name:zho_x_variant":[
        "\u820a\u793e"
    ],
    "wof:name":"Jiushe",
    "wof:placetype":"locality"
},
  "geometry": {"coordinates":[121.93267,25.02616],"type":"Point"}
}