{
  "type": "Feature",
  "properties": {
    "gn:admin1_code":"4.0",
    "gn:admin2_code":"PIF",
    "gn:admin3_code":"T31",
    "gn:admin4_code":"10013310006.0",
    "gn:asciiname":"Jiulili",
    "gn:country_code":"TW",
    "gn:dem":995,
    "gn:feature_class":"P",
    "gn:feature_code":"PPL",
    "gn:name":"Jiulili",
    "gn:population":0,
    "gn:timezone":"Asia/Taipei",
    "iso:country":"TW",
    "name:und_x_variant":[
        "\u820a\u529b\u91cc",
        "Jiulili",
        "Jioulili",
        "Chiu-li-li"
    ],
    "wof:name":"Jiulili",
    "wof:placetype":"locality"
},
  "geometry": {"coordinates":[120.68805999999999,22.41194],"type":"Point"}
}