{
  "type": "Feature",
  "properties": {
    "gn:admin1_code":"4.0",
    "gn:admin2_code":"ILA",
    "gn:admin3_code":"G12",
    "gn:admin4_code":"10002120001.0",
    "gn:asciiname":"Gamin",
    "gn:country_code":"TW",
    "gn:dem":774,
    "gn:feature_class":"P",
    "gn:feature_code":"PPL",
    "gn:name":"Gamin",
    "gn:population":0,
    "gn:timezone":"Asia/Taipei",
    "iso:country":"TW",
    "name:por_x_preferred":[
        "Gamin"
    ],
    "name:rus_x_preferred":[
        "Gamin"
    ],
    "name:und_x_variant":[
        "Ka-min"
    ],
    "name:zho_x_preferred":[
        "\u560e\u6c11"
    ],
    "wof:name":"Gamin",
    "wof:placetype":"locality"
},
  "geometry": {"coordinates":[121.78547,24.51715],"type":"Point"}
}