{
  "type": "Feature",
  "properties": {
    "gn:admin1_code":"4.0",
    "gn:admin2_code":"TNN",
    "gn:admin3_code":"R26",
    "gn:admin4_code":"67000260008.0",
    "gn:asciiname":"Lizikeng",
    "gn:country_code":"TW",
    "gn:dem":77,
    "gn:feature_class":"P",
    "gn:feature_code":"PPL",
    "gn:name":"Lizikeng",
    "gn:population":0,
    "gn:timezone":"Asia/Taipei",
    "iso:country":"TW",
    "name:und_x_variant":[
        "Lizihkeng",
        "Lizikeng"
    ],
    "name:zho_x_preferred":[
        "\u72f8\u5b50\u5751"
    ],
    "name:zho_x_variant":[
        "Li-tzu-k\u2019eng"
    ],
    "wof:name":"Lizikeng",
    "wof:placetype":"locality"
},
  "geometry": {"coordinates":[120.40859,23.00354],"type":"Point"}
}