{
  "type": "Feature",
  "properties": {
    "gn:admin1_code":"04",
    "gn:admin2_code":"NAN",
    "gn:admin3_code":"M08",
    "gn:admin4_code":"10008080017.0",
    "gn:asciiname":"Daqiuyuan",
    "gn:country_code":"TW",
    "gn:dem":191,
    "gn:feature_class":"P",
    "gn:feature_code":"PPL",
    "gn:name":"Daqiuyuan",
    "gn:population":0,
    "gn:timezone":"Asia/Taipei",
    "iso:country":"TW",
    "name:und_x_variant":[
        "Daciouyuan",
        "Daqiuyuan"
    ],
    "name:zho_x_preferred":[
        "\u5927\u4e18\u5712"
    ],
    "name:zho_x_variant":[
        "Ta-ch\u2019iu-y\u00fcan"
    ],
    "wof:name":"Daqiuyuan",
    "wof:placetype":"locality"
},
  "geometry": {"coordinates":[120.7521,23.9317],"type":"Point"}
}