{
  "type": "Feature",
  "properties": {
    "gn:admin1_code":"4.0",
    "gn:admin2_code":"TXG",
    "gn:admin3_code":"B27",
    "gn:admin4_code":"66000270019.0",
    "gn:asciiname":"Ganxikou",
    "gn:country_code":"TW",
    "gn:dem":289,
    "gn:feature_class":"P",
    "gn:feature_code":"PPL",
    "gn:name":"Ganxikou",
    "gn:population":0,
    "gn:timezone":"Asia/Taipei",
    "iso:country":"TW",
    "name:und_x_variant":[
        "Gansikou"
    ],
    "name:zho_x_preferred":[
        "Kan-ch\u2019i\u2019ou"
    ],
    "name:zho_x_variant":[
        "\u4e7e\u6eaa\u53e3",
        "Kan-hsi-k\u2019ou"
    ],
    "wof:name":"Ganxikou",
    "wof:placetype":"locality"
},
  "geometry": {"coordinates":[120.77844,24.08425],"type":"Point"}
}