{
  "type": "Feature",
  "properties": {
    "iso:country":"TW",
    "qs:name":"\u58fd\u5fb7\u91cc",
    "qs:name_adm0":"\u81fa\u7063",
    "qs:name_adm1":"\u53f0\u5317\u5e02",
    "qs:photos":48,
    "qs:photos_1k":10,
    "qs:photos_9k":1,
    "qs:photos_9r":2,
    "qs:photos_all":48,
    "qs:photos_sr":2,
    "qs:placetype":"Suburb",
    "qs:pop_sr":"0",
    "wof:name":"\u58fd\u5fb7\u91cc",
    "wof:placetype":"neighbourhood"
},
  "geometry": {"coordinates":[121.50036900000001,25.021353],"type":"Point"}
}