{
  "type": "Feature",
  "properties": {
    "gn:admin1_code":"04",
    "gn:admin2_code":"HSZ",
    "gn:admin3_code":"J02",
    "gn:admin4_code":"10004020001.0",
    "gn:asciiname":"Shangping",
    "gn:country_code":"TW",
    "gn:dem":257,
    "gn:feature_class":"P",
    "gn:feature_code":"PPL",
    "gn:name":"Shangping",
    "gn:population":0,
    "gn:timezone":"Asia/Taipei",
    "iso:country":"TW",
    "name:zho_x_preferred":[
        "\u4e0a\u576a"
    ],
    "name:zho_x_variant":[
        "Shang-p\u2019ing"
    ],
    "wof:name":"Shangping",
    "wof:placetype":"locality"
},
  "geometry": {"coordinates":[121.12056,24.66333],"type":"Point"}
}