{
  "type": "Feature",
  "properties": {
    "gn:admin1_code":"4.0",
    "gn:admin2_code":"TXG",
    "gn:admin3_code":"B25",
    "gn:admin4_code":"66000250008.0",
    "gn:asciiname":"Sande",
    "gn:country_code":"TW",
    "gn:dem":7,
    "gn:feature_class":"P",
    "gn:feature_code":"PPL",
    "gn:name":"Sande",
    "gn:population":0,
    "gn:timezone":"Asia/Taipei",
    "iso:country":"TW",
    "name:ceb_x_preferred":[
        "Sande"
    ],
    "name:dan_x_preferred":[
        "Sande"
    ],
    "name:deu_x_preferred":[
        "Sande"
    ],
    "name:epo_x_preferred":[
        "Sande"
    ],
    "name:est_x_preferred":[
        "Sande"
    ],
    "name:eus_x_preferred":[
        "Sande"
    ],
    "name:fin_x_preferred":[
        "Sande"
    ],
    "name:fra_x_preferred":[
        "Sande"
    ],
    "name:glg_x_preferred":[
        "Sande"
    ],
    "name:hrv_x_preferred":[
        "Sande"
    ],
    "name:ita_x_preferred":[
        "Sande"
    ],
    "name:lim_x_preferred":[
        "Sande"
    ],
    "name:nld_x_preferred":[
        "Sande"
    ],
    "name:nno_x_preferred":[
        "Sande"
    ],
    "name:nor_x_preferred":[
        "Sande"
    ],
    "name:pol_x_preferred":[
        "Sande"
    ],
    "name:por_x_preferred":[
        "Sande"
    ],
    "name:ron_x_preferred":[
        "Sande"
    ],
    "name:rus_x_preferred":[
        "\u0421\u0430\u043d\u0434\u0435"
    ],
    "name:sme_x_preferred":[
        "Sande"
    ],
    "name:swe_x_preferred":[
        "Sande"
    ],
    "name:und_x_variant":[
        "San-te"
    ],
    "name:zho_x_preferred":[
        "\u4e09\u5fb7"
    ],
    "wof:name":"Sande",
    "wof:placetype":"locality"
},
  "geometry": {"coordinates":[120.52366000000001,24.20607],"type":"Point"}
}