{
  "type": "Feature",
  "properties": {
    "gn:admin1_code":"4.0",
    "gn:admin2_code":"TNN",
    "gn:admin3_code":"R30",
    "gn:admin4_code":"67000300007.0",
    "gn:asciiname":"Wujian",
    "gn:country_code":"TW",
    "gn:dem":161,
    "gn:feature_class":"P",
    "gn:feature_code":"PPL",
    "gn:name":"Wujian",
    "gn:population":0,
    "gn:timezone":"Asia/Taipei",
    "iso:country":"TW",
    "name:und_x_variant":[
        "Wu-chien"
    ],
    "name:zho_x_preferred":[
        "\u4e94\u9593"
    ],
    "wof:name":"Wujian",
    "wof:placetype":"locality"
},
  "geometry": {"coordinates":[120.42361,22.94472],"type":"Point"}
}