{
  "type": "Feature",
  "properties": {
    "gn:admin1_code":"04",
    "gn:admin2_code":"TXG",
    "gn:admin3_code":"B27",
    "gn:admin4_code":"66000270014.0",
    "gn:asciiname":"Dabao",
    "gn:country_code":"TW",
    "gn:dem":296,
    "gn:feature_class":"P",
    "gn:feature_code":"PPL",
    "gn:name":"Dabao",
    "gn:population":0,
    "gn:timezone":"Asia/Taipei",
    "iso:country":"TW",
    "name:und_x_variant":[
        "Ta-pao-nung-ch\u2019ang",
        "Ta-pao",
        "Dabao"
    ],
    "wof:name":"Dabao",
    "wof:placetype":"locality"
},
  "geometry": {"coordinates":[120.76667,24.15],"type":"Point"}
}