{
  "type": "Feature",
  "properties": {
    "gn:admin1_code":"4.0",
    "gn:admin2_code":"HSZ",
    "gn:admin3_code":"J04",
    "gn:admin4_code":"10004030003.0",
    "gn:asciiname":"Litoushan",
    "gn:country_code":"TW",
    "gn:dem":57,
    "gn:feature_class":"P",
    "gn:feature_code":"PPL",
    "gn:name":"Litoushan",
    "gn:population":0,
    "gn:timezone":"Asia/Taipei",
    "iso:country":"TW",
    "name:zho_x_preferred":[
        "\u7281\u982d\u5c71"
    ],
    "name:zho_x_variant":[
        "Li-t\u2019ou-shan"
    ],
    "wof:name":"Litoushan",
    "wof:placetype":"locality"
},
  "geometry": {"coordinates":[121.04000000000001,24.82833],"type":"Point"}
}