{
  "type": "Feature",
  "properties": {
    "gn:admin1_code":"3.0",
    "gn:admin2_code":"TPQ",
    "gn:admin3_code":"F15",
    "gn:admin4_code":"65000090022.0",
    "gn:asciiname":"Dingsancengping",
    "gn:country_code":"TW",
    "gn:dem":391,
    "gn:feature_class":"P",
    "gn:feature_code":"PPL",
    "gn:name":"Dingsancengping",
    "gn:population":0,
    "gn:timezone":"Asia/Taipei",
    "iso:country":"TW",
    "name:zho_x_preferred":[
        "\u9802\u4e09\u5c64\u576a"
    ],
    "name:zho_x_variant":[
        "Ting-san-ts\u2019eng-p\u2019ing"
    ],
    "wof:name":"Dingsancengping",
    "wof:placetype":"locality"
},
  "geometry": {"coordinates":[121.44759999999999,24.90662],"type":"Point"}
}