{
  "type": "Feature",
  "properties": {
    "gn:admin1_code":"4.0",
    "gn:admin2_code":"CYQ",
    "gn:admin3_code":"Q04",
    "gn:admin4_code":"10010040012.0",
    "gn:asciiname":"Xinqitou",
    "gn:country_code":"TW",
    "gn:dem":88,
    "gn:feature_class":"P",
    "gn:feature_code":"PPL",
    "gn:name":"Xinqitou",
    "gn:population":0,
    "gn:timezone":"Asia/Taipei",
    "iso:country":"TW",
    "name:und_x_variant":[
        "Sincitou"
    ],
    "name:zho_x_preferred":[
        "\u65b0\u5d0e\u982d"
    ],
    "name:zho_x_variant":[
        "Hsin-ch\u2019i-t\u2019ou"
    ],
    "wof:name":"Xinqitou",
    "wof:placetype":"locality"
},
  "geometry": {"coordinates":[120.52972,23.59778],"type":"Point"}
}