{
  "type": "Feature",
  "properties": {
    "gn:admin1_code":"04",
    "gn:admin2_code":"NAN",
    "gn:admin3_code":"M13",
    "gn:admin4_code":"10008130009.0",
    "gn:asciiname":"Youshi",
    "gn:country_code":"TW",
    "gn:dem":1736,
    "gn:feature_class":"P",
    "gn:feature_code":"PPL",
    "gn:name":"Youshi",
    "gn:population":0,
    "gn:timezone":"Asia/Taipei",
    "iso:country":"TW",
    "name:und_x_variant":[
        "Y\u00fcang-wang",
        "Youshi",
        "Youshih",
        "Yu-shih"
    ],
    "name:zho_x_preferred":[
        "\u5e7c\u7345"
    ],
    "name:zho_x_variant":[
        "Y\u00fcang-wang"
    ],
    "wof:name":"Youshi",
    "wof:placetype":"locality"
},
  "geometry": {"coordinates":[121.15611,24.04778],"type":"Point"}
}