{
  "type": "Feature",
  "properties": {
    "gn:admin1_code":"4.0",
    "gn:admin2_code":"TPE",
    "gn:admin3_code":"A14",
    "gn:admin4_code":"63000100030.0",
    "gn:asciiname":"Fenliao",
    "gn:country_code":"TW",
    "gn:dem":2,
    "gn:feature_class":"P",
    "gn:feature_code":"PPL",
    "gn:name":"Fenliao",
    "gn:population":0,
    "gn:timezone":"Asia/Taipei",
    "iso:country":"TW",
    "name:und_x_variant":[
        "Fen-liao"
    ],
    "name:zho_x_preferred":[
        "\u7c89\u5bee"
    ],
    "wof:name":"Fenliao",
    "wof:placetype":"locality"
},
  "geometry": {"coordinates":[121.5741,25.06862000000001],"type":"Point"}
}