{
  "type": "Feature",
  "properties": {
    "iso:country":"TW",
    "qs:name":"\u7709\u5c71\u6751",
    "qs:name_adm0":"\u81fa\u7063",
    "qs:name_adm1":"\u53f0\u4e2d\u5e02",
    "qs:photos":59,
    "qs:photos_1k":12,
    "qs:photos_9k":1,
    "qs:photos_9r":2,
    "qs:photos_all":59,
    "qs:photos_sr":2,
    "qs:placetype":"Town",
    "qs:pop_sr":"0",
    "wof:name":"\u7709\u5c71\u6751",
    "wof:placetype":"locality"
},
  "geometry": {"coordinates":[120.694198,24.3221],"type":"Point"}
}