{
  "type": "Feature",
  "properties": {
    "gn:admin1_code":"4.0",
    "gn:admin2_code":"TXG",
    "gn:admin3_code":"B18",
    "gn:admin4_code":"66000180004.0",
    "gn:asciiname":"Shanghengshan",
    "gn:country_code":"TW",
    "gn:dem":141,
    "gn:feature_class":"P",
    "gn:feature_code":"PPL",
    "gn:name":"Shanghengshan",
    "gn:population":0,
    "gn:timezone":"Asia/Taipei",
    "iso:country":"TW",
    "name:und_x_variant":[
        "Heng-shan",
        "Heng-shan-ts\u2019un",
        "\u4e0a\u6a6b\u5c71",
        "Shanghengshan",
        "Shang-heng-shan"
    ],
    "wof:name":"Shanghengshan",
    "wof:placetype":"locality"
},
  "geometry": {"coordinates":[120.63162,24.21985],"type":"Point"}
}