{
  "type": "Feature",
  "properties": {
    "gn:admin1_code":"04",
    "gn:admin2_code":"TNN",
    "gn:admin3_code":"R20",
    "gn:admin4_code":"67000200008.0",
    "gn:asciiname":"Dashe",
    "gn:country_code":"TW",
    "gn:dem":20,
    "gn:feature_class":"P",
    "gn:feature_code":"PPL",
    "gn:name":"Dashe",
    "gn:population":0,
    "gn:timezone":"Asia/Taipei",
    "iso:country":"TW",
    "name:und_x_variant":[
        "Ta-she"
    ],
    "name:zho_x_preferred":[
        "\u5927\u793e"
    ],
    "wof:name":"Dashe",
    "wof:placetype":"locality"
},
  "geometry": {"coordinates":[120.3181,23.09],"type":"Point"}
}