{
  "type": "Feature",
  "properties": {
    "gn:admin1_code":"4.0",
    "gn:admin2_code":"YUN",
    "gn:admin3_code":"P10",
    "gn:admin4_code":"10009100005.0",
    "gn:asciiname":"Zhongxing",
    "gn:country_code":"TW",
    "gn:dem":94,
    "gn:feature_class":"P",
    "gn:feature_code":"PPL",
    "gn:name":"Zhongxing",
    "gn:population":0,
    "gn:timezone":"Asia/Taipei",
    "iso:country":"TW",
    "name:ceb_x_preferred":[
        "Zhongxing"
    ],
    "name:deu_x_preferred":[
        "Zhongxing"
    ],
    "name:pol_x_preferred":[
        "Zhongxing"
    ],
    "name:swe_x_preferred":[
        "Zhongxing"
    ],
    "name:und_x_variant":[
        "Jhongsing",
        "Chung-hsing"
    ],
    "name:zho_x_preferred":[
        "\u4e2d\u8208"
    ],
    "wof:name":"Zhongxing",
    "wof:placetype":"locality"
},
  "geometry": {"coordinates":[120.61187,23.74858],"type":"Point"}
}