{
  "type": "Feature",
  "properties": {
    "gn:admin1_code":"04",
    "gn:admin2_code":"CYQ",
    "gn:admin3_code":"Q16",
    "gn:admin4_code":"10010150016.0",
    "gn:asciiname":"Ruili",
    "gn:country_code":"TW",
    "gn:dem":1044,
    "gn:feature_class":"P",
    "gn:feature_code":"PPL",
    "gn:name":"Ruili",
    "gn:population":0,
    "gn:timezone":"Asia/Taipei",
    "iso:country":"TW",
    "name:ara_x_preferred":[
        "\u0631\u0648\u064a\u0644\u064a"
    ],
    "name:deu_x_preferred":[
        "Ruili"
    ],
    "name:fra_x_preferred":[
        "Ruili"
    ],
    "name:ita_x_preferred":[
        "Ruili"
    ],
    "name:jpn_x_preferred":[
        "\u745e\u9e97\u5e02"
    ],
    "name:kik_x_preferred":[
        "Ruili"
    ],
    "name:kor_x_preferred":[
        "\ub8e8\uc774\ub9ac\uc2dc"
    ],
    "name:mya_x_preferred":[
        "\u101b\u103d\u103e\u1031\u101c\u102e"
    ],
    "name:nld_x_preferred":[
        "Ruili"
    ],
    "name:nor_x_preferred":[
        "Ruili"
    ],
    "name:spa_x_preferred":[
        "Ruili"
    ],
    "name:swe_x_preferred":[
        "Ruili"
    ],
    "name:und_x_variant":[
        "Yu-yeh-lin",
        "Rueili",
        "Jui-li"
    ],
    "name:urd_x_preferred":[
        "\u0631\u0648\u0626\u0644\u06cc"
    ],
    "name:vie_x_preferred":[
        "Th\u1ee5y L\u1ec7"
    ],
    "name:zho_x_preferred":[
        "\u745e\u91cc"
    ],
    "name:zho_x_variant":[
        "\u745e\u4e3d\u5e02"
    ],
    "wof:name":"Ruili",
    "wof:placetype":"locality"
},
  "geometry": {"coordinates":[120.66889,23.53944],"type":"Point"}
}