{
  "type": "Feature",
  "properties": {
    "gn:admin1_code":"04",
    "gn:admin2_code":"CYQ",
    "gn:admin3_code":"Q16",
    "gn:admin4_code":"10010150016.0",
    "gn:asciiname":"Ruili",
    "gn:country_code":"TW",
    "gn:dem":1044,
    "gn:feature_class":"P",
    "gn:feature_code":"PPL",
    "gn:name":"Ruili",
    "gn:population":0,
    "gn:timezone":"Asia/Taipei",
    "iso:country":"TW",
    "name:und_x_variant":[
        "Yu-yeh-lin",
        "Rueili",
        "Jui-li"
    ],
    "name:zho_x_preferred":[
        "\u745e\u91cc"
    ],
    "wof:name":"Ruili",
    "wof:placetype":"locality"
},
  "geometry": {"coordinates":[120.66889,23.53944],"type":"Point"}
}