{
  "type": "Feature",
  "properties": {
    "gn:admin1_code":"4.0",
    "gn:admin2_code":"TNN",
    "gn:admin3_code":"R06",
    "gn:admin4_code":"67000060009.0",
    "gn:asciiname":"Guizikong",
    "gn:country_code":"TW",
    "gn:dem":38,
    "gn:feature_class":"P",
    "gn:feature_code":"PPL",
    "gn:name":"Guizikong",
    "gn:population":0,
    "gn:timezone":"Asia/Taipei",
    "iso:country":"TW",
    "name:und_x_variant":[
        "Gueizihkong",
        "Guizikong"
    ],
    "name:zho_x_preferred":[
        "\u9b3c\u5b50\u7a7a"
    ],
    "name:zho_x_variant":[
        "Hs\u00fc-kuang",
        "Kuei-tzu-k\u2019ung"
    ],
    "wof:name":"Guizikong",
    "wof:placetype":"locality"
},
  "geometry": {"coordinates":[120.41139,23.27361],"type":"Point"}
}