{
  "type": "Feature",
  "properties": {
    "gn:admin1_code":"04",
    "gn:admin2_code":"TNN",
    "gn:admin3_code":"R08",
    "gn:admin4_code":"67000080014.0",
    "gn:asciiname":"Shiliujia",
    "gn:country_code":"TW",
    "gn:dem":8,
    "gn:feature_class":"P",
    "gn:feature_code":"PPL",
    "gn:name":"Shiliujia",
    "gn:population":0,
    "gn:timezone":"Asia/Taipei",
    "iso:country":"TW",
    "name:und_x_variant":[
        "Chia-chung",
        "Shihlioujia",
        "Shiliujia",
        "Shih-liu-chia"
    ],
    "name:zho_x_preferred":[
        "Chia-chung-ts\u2019un"
    ],
    "name:zho_x_variant":[
        "\u5341\u516d\u7532"
    ],
    "wof:name":"Shiliujia",
    "wof:placetype":"locality"
},
  "geometry": {"coordinates":[120.27417,23.25111],"type":"Point"}
}