{
  "type": "Feature",
  "properties": {
    "gn:admin1_code":"3.0",
    "gn:admin2_code":"TPQ",
    "gn:admin3_code":"F02",
    "gn:admin4_code":"65000170005.0",
    "gn:asciiname":"Jingbu",
    "gn:country_code":"TW",
    "gn:dem":232,
    "gn:feature_class":"P",
    "gn:feature_code":"PPL",
    "gn:name":"Jingbu",
    "gn:population":0,
    "gn:timezone":"Asia/Taipei",
    "iso:country":"TW",
    "name:und_x_variant":[
        "Ching-pu"
    ],
    "name:zho_x_preferred":[
        "Ching-hu-ts\u2019un"
    ],
    "name:zho_x_variant":[
        "\u83c1\u57d4",
        "Ch\u2019ing-hu"
    ],
    "wof:name":"Jingbu",
    "wof:placetype":"locality"
},
  "geometry": {"coordinates":[121.37791,25.09657],"type":"Point"}
}