{
  "type": "Feature",
  "properties": {
    "gn:admin1_code":"4.0",
    "gn:admin2_code":"TAO",
    "gn:admin3_code":"H09",
    "gn:admin4_code":"68000090015.0",
    "gn:asciiname":"Shiyuan",
    "gn:country_code":"TW",
    "gn:dem":242,
    "gn:feature_class":"P",
    "gn:feature_code":"PPL",
    "gn:name":"Shiyuan",
    "gn:population":0,
    "gn:timezone":"Asia/Taipei",
    "iso:country":"TW",
    "name:fra_x_preferred":[
        "Shiyuan"
    ],
    "name:und_x_variant":[
        "Shihyuan"
    ],
    "name:zho_x_preferred":[
        "\u77f3\u5712"
    ],
    "name:zho_x_variant":[
        "Shih-y\u00fcan"
    ],
    "wof:name":"Shiyuan",
    "wof:placetype":"locality"
},
  "geometry": {"coordinates":[121.24333,24.83667],"type":"Point"}
}