{
  "type": "Feature",
  "properties": {
    "iso:country":"TW",
    "qs:name":"\u5927\u9d6c\u6751",
    "qs:name_adm0":"\u81fa\u7063",
    "qs:name_adm1":"\u65b0\u5317\u5e02",
    "qs:photos":123,
    "qs:photos_1k":25,
    "qs:photos_9k":1,
    "qs:photos_9r":3,
    "qs:photos_all":123,
    "qs:photos_sr":3,
    "qs:placetype":"Town",
    "qs:pop_sr":"0",
    "wof:name":"\u5927\u9d6c\u6751",
    "wof:placetype":"locality"
},
  "geometry": {"coordinates":[121.64868800000001,25.210611],"type":"Point"}
}