{
  "type": "Feature",
  "properties": {
    "gn:admin1_code":"04",
    "gn:admin2_code":"TNN",
    "gn:admin3_code":"D06",
    "gn:admin4_code":"67000350036.0",
    "gn:asciiname":"Sicao",
    "gn:country_code":"TW",
    "gn:dem":1,
    "gn:feature_class":"P",
    "gn:feature_code":"PPL",
    "gn:name":"Sicao",
    "gn:population":0,
    "gn:timezone":"Asia/Taipei",
    "iso:country":"TW",
    "name:und_x_variant":[
        "Sihcao"
    ],
    "name:zho_x_preferred":[
        "\u56db\u8349"
    ],
    "name:zho_x_variant":[
        "Ssu-ts\u2019ao-hu",
        "Ssu-ts\u2019ao"
    ],
    "wof:name":"Sicao",
    "wof:placetype":"locality"
},
  "geometry": {"coordinates":[120.13167,23.01694],"type":"Point"}
}