{
  "type": "Feature",
  "properties": {
    "gn:admin1_code":"4.0",
    "gn:admin2_code":"HSZ",
    "gn:admin3_code":"J11",
    "gn:admin4_code":"10004100001.0",
    "gn:asciiname":"Huludu",
    "gn:country_code":"TW",
    "gn:dem":48,
    "gn:feature_class":"P",
    "gn:feature_code":"PPL",
    "gn:name":"Huludu",
    "gn:population":0,
    "gn:timezone":"Asia/Taipei",
    "iso:country":"TW",
    "name:und_x_variant":[
        "Hu-lu-tu"
    ],
    "name:zho_x_preferred":[
        "\u846b\u8606\u809a"
    ],
    "wof:name":"Huludu",
    "wof:placetype":"locality"
},
  "geometry": {"coordinates":[120.99722,24.76528],"type":"Point"}
}