{
  "type": "Feature",
  "properties": {
    "gn:admin1_code":"04",
    "gn:admin2_code":"TNN",
    "gn:admin3_code":"R06",
    "gn:admin4_code":"67000060011.0",
    "gn:asciiname":"Zilongting",
    "gn:country_code":"TW",
    "gn:dem":129,
    "gn:feature_class":"P",
    "gn:feature_code":"PPL",
    "gn:name":"Zilongting",
    "gn:population":0,
    "gn:timezone":"Asia/Taipei",
    "iso:country":"TW",
    "name:und_x_variant":[
        "Zihlongting",
        "Zilongting"
    ],
    "name:zho_x_preferred":[
        "\u5b50\u9f8d\u5ef0"
    ],
    "name:zho_x_variant":[
        "Tzu-lung-t\u2019ing"
    ],
    "wof:name":"Zilongting",
    "wof:placetype":"locality"
},
  "geometry": {"coordinates":[120.45722000000001,23.2825],"type":"Point"}
}