{
  "type": "Feature",
  "properties": {
    "iso:country":"TW",
    "name:eng_x_preferred":[
        "Nanshan"
    ],
    "name:eng_x_variant":[
        "Nanshan Village"
    ],
    "name:zho_tw_x_preferred":[
        "\u5357\u5c71\u6751"
    ],
    "qs:name":"\u5357\u5c71\u6751",
    "qs:name_adm0":"\u81fa\u7063",
    "qs:name_adm1":"\u65b0\u5317\u5e02",
    "qs:photos":103,
    "qs:photos_1k":21,
    "qs:photos_9k":1,
    "qs:photos_9r":3,
    "qs:photos_all":103,
    "qs:photos_sr":3,
    "qs:placetype":"Town",
    "qs:pop_sr":"0",
    "wof:name":"Nanshan",
    "wof:placetype":"locality"
},
  "geometry": {"coordinates":[121.795377,25.050146],"type":"Point"}
}