{
  "type": "Feature",
  "properties": {
    "gn:admin1_code":"04",
    "gn:admin2_code":"MIA",
    "gn:admin3_code":"K13",
    "gn:admin4_code":"10005160006.0",
    "gn:asciiname":"Dahedi",
    "gn:country_code":"TW",
    "gn:dem":72,
    "gn:feature_class":"P",
    "gn:feature_code":"PPL",
    "gn:name":"Dahedi",
    "gn:population":0,
    "gn:timezone":"Asia/Taipei",
    "iso:country":"TW",
    "name:und_x_variant":[
        "Shih-wu-fen",
        "Dahedi",
        "Ta-ho-ti"
    ],
    "name:zho_x_preferred":[
        "\u5927\u6cb3\u5e95"
    ],
    "wof:name":"Dahedi",
    "wof:placetype":"locality"
},
  "geometry": {"coordinates":[120.94506,24.61743],"type":"Point"}
}