{
  "type": "Feature",
  "properties": {
    "gn:admin1_code":"04",
    "gn:admin2_code":"YUN",
    "gn:admin3_code":"P20",
    "gn:admin4_code":"10009200004.0",
    "gn:asciiname":"Wangcuoliao",
    "gn:country_code":"TW",
    "gn:dem":7,
    "gn:feature_class":"P",
    "gn:feature_code":"PPL",
    "gn:name":"Wangcuoliao",
    "gn:population":0,
    "gn:timezone":"Asia/Taipei",
    "iso:country":"TW",
    "name:zho_x_preferred":[
        "Wang-ts\u2019o"
    ],
    "name:zho_x_variant":[
        "\u738b\u539d\u5bee",
        "Wang-ts\u2019o-liao"
    ],
    "wof:name":"Wangcuoliao",
    "wof:placetype":"locality"
},
  "geometry": {"coordinates":[120.26000000000001,23.57028],"type":"Point"}
}