{
  "type": "Feature",
  "properties": {
    "gn:admin1_code":"03",
    "gn:admin2_code":"TPQ",
    "gn:admin3_code":"F27",
    "gn:admin4_code":"65000100033.0",
    "gn:asciiname":"Shalun",
    "gn:country_code":"TW",
    "gn:dem":13,
    "gn:feature_class":"P",
    "gn:feature_code":"PPL",
    "gn:name":"Shalun",
    "gn:population":0,
    "gn:timezone":"Asia/Taipei",
    "iso:country":"TW",
    "name:und_x_variant":[
        "Sha-lun-tzu",
        "Sha-lun-li",
        "Shalun",
        "Sha-lun"
    ],
    "name:zho_x_preferred":[
        "\u6c99\u5d19"
    ],
    "wof:name":"Shalun",
    "wof:placetype":"locality"
},
  "geometry": {"coordinates":[121.42131000000001,25.18557],"type":"Point"}
}