{
  "type": "Feature",
  "properties": {
    "gn:admin1_code":"4.0",
    "gn:admin2_code":"NAN",
    "gn:admin3_code":"M11",
    "gn:admin4_code":"10008110015.0",
    "gn:asciiname":"Xiatangpou",
    "gn:country_code":"TW",
    "gn:dem":366,
    "gn:feature_class":"P",
    "gn:feature_code":"PPL",
    "gn:name":"Xiatangpou",
    "gn:population":0,
    "gn:timezone":"Asia/Taipei",
    "iso:country":"TW",
    "name:und_x_variant":[
        "Siatangpou",
        "Xiatangpou"
    ],
    "name:zho_x_preferred":[
        "\u4e0b\u5858\u5ecd"
    ],
    "name:zho_x_variant":[
        "Hsia-t\u2019ang-p\u2019u",
        "Hsia-t\u2019ang-p\u2019ou"
    ],
    "wof:name":"Xiatangpou",
    "wof:placetype":"locality"
},
  "geometry": {"coordinates":[120.92743,23.79501],"type":"Point"}
}