{
  "type": "Feature",
  "properties": {
    "gn:admin1_code":"4.0",
    "gn:admin2_code":"NAN",
    "gn:admin3_code":"M04",
    "gn:admin4_code":"10008040026.0",
    "gn:asciiname":"Shizilin",
    "gn:country_code":"TW",
    "gn:dem":325,
    "gn:feature_class":"P",
    "gn:feature_code":"PPL",
    "gn:name":"Shizilin",
    "gn:population":0,
    "gn:timezone":"Asia/Taipei",
    "iso:country":"TW",
    "name:und_x_variant":[
        "Shihzihlin",
        "Shizilin",
        "Shih-tzu-lin"
    ],
    "name:zho_x_preferred":[
        "\u67ff\u5b50\u6797"
    ],
    "wof:name":"Shizilin",
    "wof:placetype":"locality"
},
  "geometry": {"coordinates":[120.70028000000001,23.72167],"type":"Point"}
}