{
  "type": "Feature",
  "properties": {
    "gn:admin1_code":"1.0",
    "gn:admin2_code":"KIN",
    "gn:asciiname":"Xiaxing",
    "gn:country_code":"TW",
    "gn:dem":39,
    "gn:feature_class":"P",
    "gn:feature_code":"PPL",
    "gn:name":"Xiaxing",
    "gn:population":0,
    "gn:timezone":"Asia/Taipei",
    "iso:country":"TW",
    "name:und_x_variant":[
        "Hsia-hsing"
    ],
    "name:zho_x_preferred":[
        "\u590f\u8208"
    ],
    "wof:name":"Xiaxing",
    "wof:placetype":"locality"
},
  "geometry": {"coordinates":[118.39897000000001,24.44038],"type":"Point"}
}