{
  "type": "Feature",
  "properties": {
    "gn:admin1_code":"3.0",
    "gn:admin2_code":"TPQ",
    "gn:admin3_code":"F15",
    "gn:admin4_code":"65000090026.0",
    "gn:asciiname":"Erjiu",
    "gn:country_code":"TW",
    "gn:dem":87,
    "gn:feature_class":"P",
    "gn:feature_code":"PPL",
    "gn:name":"Erjiu",
    "gn:population":0,
    "gn:timezone":"Asia/Taipei",
    "iso:country":"TW",
    "name:und_x_variant":[
        "Erjiou",
        "Erjiu",
        "Erh-chiu"
    ],
    "name:zho_x_preferred":[
        "\u4e8c\u9b2e"
    ],
    "wof:name":"Erjiu",
    "wof:placetype":"locality"
},
  "geometry": {"coordinates":[121.35414,24.9039],"type":"Point"}
}