{
  "type": "Feature",
  "properties": {
    "gn:admin1_code":"4.0",
    "gn:admin2_code":"YUN",
    "gn:admin3_code":"P02",
    "gn:admin4_code":"10009020008.0",
    "gn:asciiname":"Qingbu",
    "gn:country_code":"TW",
    "gn:dem":44,
    "gn:feature_class":"P",
    "gn:feature_code":"PPL",
    "gn:name":"Qingbu",
    "gn:population":0,
    "gn:timezone":"Asia/Taipei",
    "iso:country":"TW",
    "name:und_x_variant":[
        "Cingbu",
        "Qingbu"
    ],
    "name:zho_x_preferred":[
        "\u9752\u57d4"
    ],
    "name:zho_x_variant":[
        "Ch\u2019ing-pu"
    ],
    "wof:name":"Qingbu",
    "wof:placetype":"locality"
},
  "geometry": {"coordinates":[120.49353000000001,23.63688],"type":"Point"}
}