{
  "type": "Feature",
  "properties": {
    "gn:admin1_code":"04",
    "gn:admin2_code":"MIA",
    "gn:admin3_code":"K02",
    "gn:admin4_code":"10005020019.0",
    "gn:asciiname":"Sheling",
    "gn:country_code":"TW",
    "gn:dem":68,
    "gn:feature_class":"P",
    "gn:feature_code":"PPL",
    "gn:name":"Sheling",
    "gn:population":0,
    "gn:timezone":"Asia/Taipei",
    "iso:country":"TW",
    "name:und_x_variant":[
        "She-ling-li",
        "Sheling",
        "She-ling"
    ],
    "name:zho_x_preferred":[
        "\u793e\u82d3"
    ],
    "wof:name":"Sheling",
    "wof:placetype":"locality"
},
  "geometry": {"coordinates":[120.67583,24.40139],"type":"Point"}
}