{
  "type": "Feature",
  "properties": {
    "gn:admin1_code":"4.0",
    "gn:admin2_code":"CHA",
    "gn:admin3_code":"N12",
    "gn:admin4_code":"10007070004.0",
    "gn:asciiname":"Anshang",
    "gn:country_code":"TW",
    "gn:dem":19,
    "gn:feature_class":"P",
    "gn:feature_code":"PPL",
    "gn:name":"Anshang",
    "gn:population":0,
    "gn:timezone":"Asia/Taipei",
    "iso:country":"TW",
    "name:und_x_variant":[
        "An-shang"
    ],
    "name:zho_x_preferred":[
        "\u5cb8\u4e0a"
    ],
    "wof:name":"Anshang",
    "wof:placetype":"locality"
},
  "geometry": {"coordinates":[120.5273,24.0137],"type":"Point"}
}