{
  "type": "Feature",
  "properties": {
    "gn:admin1_code":"4.0",
    "gn:admin2_code":"TPE",
    "gn:admin3_code":"A14",
    "gn:admin4_code":"63000100015.0",
    "gn:asciiname":"Tupijiao",
    "gn:country_code":"TW",
    "gn:dem":213,
    "gn:feature_class":"P",
    "gn:feature_code":"PPL",
    "gn:name":"Tupijiao",
    "gn:population":0,
    "gn:timezone":"Asia/Taipei",
    "iso:country":"TW",
    "name:zho_x_preferred":[
        "\u571f\u57e4\u811a"
    ],
    "name:zho_x_variant":[
        "T\u2019u-p\u2019i-chiao"
    ],
    "wof:name":"Tupijiao",
    "wof:placetype":"locality"
},
  "geometry": {"coordinates":[121.59035,25.10083],"type":"Point"}
}