{
  "type": "Feature",
  "properties": {
    "gn:admin1_code":"04",
    "gn:admin2_code":"YUN",
    "gn:admin3_code":"P02",
    "gn:admin4_code":"10009020018.0",
    "gn:asciiname":"Pima",
    "gn:country_code":"TW",
    "gn:dem":29,
    "gn:feature_class":"P",
    "gn:feature_code":"PPL",
    "gn:name":"Pima",
    "gn:population":0,
    "gn:timezone":"Asia/Taipei",
    "iso:country":"TW",
    "name:zho_x_preferred":[
        "\u57e4\u9ebb"
    ],
    "name:zho_x_variant":[
        "P\u2019i-ma"
    ],
    "wof:name":"Pima",
    "wof:placetype":"locality"
},
  "geometry": {"coordinates":[120.44956000000001,23.68381],"type":"Point"}
}