{
  "type": "Feature",
  "properties": {
    "gn:admin1_code":"4.0",
    "gn:admin2_code":"TNN",
    "gn:admin3_code":"R06",
    "gn:admin4_code":"67000060002.0",
    "gn:asciiname":"Beima",
    "gn:country_code":"TW",
    "gn:dem":27,
    "gn:feature_class":"P",
    "gn:feature_code":"PPL",
    "gn:name":"Beima",
    "gn:population":0,
    "gn:timezone":"Asia/Taipei",
    "iso:country":"TW",
    "name:und_x_variant":[
        "Fan-she",
        "Beima",
        "Pei-ma"
    ],
    "name:zho_x_preferred":[
        "Fan-she-ts\u2019un"
    ],
    "name:zho_x_variant":[
        "\u5317\u99ac"
    ],
    "wof:name":"Beima",
    "wof:placetype":"locality"
},
  "geometry": {"coordinates":[120.40056,23.30889],"type":"Point"}
}