{
  "type": "Feature",
  "properties": {
    "gn:admin1_code":"02",
    "gn:admin2_code":"KHH",
    "gn:admin3_code":"E32",
    "gn:admin4_code":"64000320010.0",
    "gn:asciiname":"Baolai",
    "gn:country_code":"TW",
    "gn:dem":408,
    "gn:feature_class":"P",
    "gn:feature_code":"PPL",
    "gn:name":"Baolai",
    "gn:population":0,
    "gn:timezone":"Asia/Taipei",
    "iso:country":"TW",
    "name:und_x_variant":[
        "Pao-lai"
    ],
    "name:zho_x_preferred":[
        "\u5bf6\u4f86"
    ],
    "wof:name":"Baolai",
    "wof:placetype":"locality"
},
  "geometry": {"coordinates":[120.69972,23.10833],"type":"Point"}
}