{
  "type": "Feature",
  "properties": {
    "gn:admin1_code":"4.0",
    "gn:admin2_code":"TTT",
    "gn:admin3_code":"V09",
    "gn:admin4_code":"10014050007.0",
    "gn:asciiname":"Mabei",
    "gn:country_code":"TW",
    "gn:dem":273,
    "gn:feature_class":"P",
    "gn:feature_code":"PPL",
    "gn:name":"Mabei",
    "gn:population":0,
    "gn:timezone":"Asia/Taipei",
    "iso:country":"TW",
    "name:und_x_variant":[
        "Ma-pei"
    ],
    "name:zho_x_preferred":[
        "\u99ac\u80cc"
    ],
    "wof:name":"Mabei",
    "wof:placetype":"locality"
},
  "geometry": {"coordinates":[121.11615999999999,22.91967],"type":"Point"}
}