{
  "type": "Feature",
  "properties": {
    "gn:admin1_code":"2.0",
    "gn:admin2_code":"KHH",
    "gn:admin3_code":"E37",
    "gn:admin4_code":"64000370003.0",
    "gn:asciiname":"Xiabaolai",
    "gn:country_code":"TW",
    "gn:dem":385,
    "gn:feature_class":"P",
    "gn:feature_code":"PPL",
    "gn:name":"Xiabaolai",
    "gn:population":0,
    "gn:timezone":"Asia/Taipei",
    "iso:country":"TW",
    "name:und_x_variant":[
        "Siabaolai",
        "Xiabaolai",
        "Hsia-pao-lai"
    ],
    "name:zho_x_preferred":[
        "\u4e0b\u5bf6\u4f86"
    ],
    "wof:name":"Xiabaolai",
    "wof:placetype":"locality"
},
  "geometry": {"coordinates":[120.69028,23.09917],"type":"Point"}
}