{
  "type": "Feature",
  "properties": {
    "gn:admin1_code":"4.0",
    "gn:admin2_code":"HUA",
    "gn:admin3_code":"U10",
    "gn:admin4_code":"10015100006.0",
    "gn:asciiname":"Nihuoshan",
    "gn:country_code":"TW",
    "gn:dem":347,
    "gn:feature_class":"P",
    "gn:feature_code":"PPL",
    "gn:name":"Nihuoshan",
    "gn:population":0,
    "gn:timezone":"Asia/Taipei",
    "iso:country":"TW",
    "name:und_x_variant":[
        "Ni-huo-shan"
    ],
    "name:zho_x_preferred":[
        "\u6ce5\u706b\u5c71"
    ],
    "wof:name":"Nihuoshan",
    "wof:placetype":"locality"
},
  "geometry": {"coordinates":[121.28733,23.18856],"type":"Point"}
}