{
  "type": "Feature",
  "properties": {
    "iso:country":"TW",
    "qs:name":"\u54e1\u6797\u6751",
    "qs:name_adm0":"\u81fa\u7063",
    "qs:name_adm1":"\u53f0\u4e2d\u5e02",
    "qs:photos":128,
    "qs:photos_1k":26,
    "qs:photos_9k":1,
    "qs:photos_9r":3,
    "qs:photos_all":128,
    "qs:photos_sr":3,
    "qs:placetype":"Town",
    "qs:pop_sr":"0",
    "wof:name":"\u54e1\u6797\u6751",
    "wof:placetype":"locality"
},
  "geometry": {"coordinates":[120.6491285,24.240526],"type":"Point"}
}