{
  "type": "Feature",
  "properties": {
    "gn:admin1_code":"4.0",
    "gn:admin2_code":"NAN",
    "gn:admin3_code":"M09",
    "gn:admin4_code":"10008090013.0",
    "gn:asciiname":"Dehuashe",
    "gn:country_code":"TW",
    "gn:dem":754,
    "gn:feature_class":"P",
    "gn:feature_code":"PPL",
    "gn:name":"Dehuashe",
    "gn:population":0,
    "gn:timezone":"Asia/Taipei",
    "iso:country":"TW",
    "name:und_x_variant":[
        "Pu-chi",
        "Hua-fan-she",
        "Hua-fan",
        "Dehuashe",
        "Te-hua-she"
    ],
    "name:zho_x_preferred":[
        "Te-hua-ts\u2019un"
    ],
    "name:zho_x_variant":[
        "\u5fb7\u5316\u793e"
    ],
    "wof:name":"Dehuashe",
    "wof:placetype":"locality"
},
  "geometry": {"coordinates":[120.93033,23.84813],"type":"Point"}
}