{
  "type": "Feature",
  "properties": {
    "gn:admin1_code":"4.0",
    "gn:admin2_code":"CYQ",
    "gn:admin3_code":"Q16",
    "gn:admin4_code":"10010150010.0",
    "gn:asciiname":"Hougoupu",
    "gn:country_code":"TW",
    "gn:dem":111,
    "gn:feature_class":"P",
    "gn:feature_code":"PPL",
    "gn:name":"Hougoupu",
    "gn:population":0,
    "gn:timezone":"Asia/Taipei",
    "iso:country":"TW",
    "name:zho_x_preferred":[
        "\u5f8c\u6e9d\u6d66"
    ],
    "name:zho_x_variant":[
        "Hou-kou-p\u2019u"
    ],
    "wof:name":"Hougoupu",
    "wof:placetype":"locality"
},
  "geometry": {"coordinates":[120.53749999999999,23.55861],"type":"Point"}
}