{
  "type": "Feature",
  "properties": {
    "gn:admin1_code":"4.0",
    "gn:admin2_code":"TXG",
    "gn:admin3_code":"B18",
    "gn:admin4_code":"66000180002.0",
    "gn:asciiname":"Shangyuanlin",
    "gn:country_code":"TW",
    "gn:dem":168,
    "gn:feature_class":"P",
    "gn:feature_code":"PPL",
    "gn:name":"Shangyuanlin",
    "gn:population":0,
    "gn:timezone":"Asia/Taipei",
    "iso:country":"TW",
    "name:zho_x_preferred":[
        "Chuang-ch\u2019ien-ts\u2019un"
    ],
    "name:zho_x_variant":[
        "Chuang-ch\u2019ien",
        "\u4e0a\u54e1\u6797",
        "Shang-y\u00fcan-lin"
    ],
    "wof:name":"Shangyuanlin",
    "wof:placetype":"locality"
},
  "geometry": {"coordinates":[120.65443999999999,24.24917],"type":"Point"}
}