{
  "type": "Feature",
  "properties": {
    "iso:country":"TW",
    "qs:name":"\u8356\u6fc3\u6751",
    "qs:name_adm0":"\u81fa\u7063",
    "qs:name_adm1":"\u9ad8\u96c4\u5e02",
    "qs:photos":74,
    "qs:photos_1k":15,
    "qs:photos_9k":1,
    "qs:photos_9r":2,
    "qs:photos_all":74,
    "qs:photos_sr":2,
    "qs:placetype":"Town",
    "qs:pop_sr":"0",
    "wof:name":"\u8356\u6fc3\u6751",
    "wof:placetype":"locality"
},
  "geometry": {"coordinates":[120.661113,23.041832],"type":"Point"}
}