{
  "type": "Feature",
  "properties": {
    "gn:admin1_code":"4.0",
    "gn:admin2_code":"TXG",
    "gn:admin3_code":"B14",
    "gn:admin4_code":"66000140012.0",
    "gn:asciiname":"Tianzhongyang",
    "gn:country_code":"TW",
    "gn:dem":4,
    "gn:feature_class":"P",
    "gn:feature_code":"PPL",
    "gn:name":"Tianzhongyang",
    "gn:population":0,
    "gn:timezone":"Asia/Taipei",
    "iso:country":"TW",
    "name:und_x_variant":[
        "Tianjhongyang",
        "T\u2019ien-chung-yang"
    ],
    "name:zho_x_preferred":[
        "\u7530\u4e2d\u592e"
    ],
    "name:zho_x_variant":[
        "T\u2019ien-chung-yang"
    ],
    "wof:name":"Tianzhongyang",
    "wof:placetype":"locality"
},
  "geometry": {"coordinates":[120.53926,24.2366],"type":"Point"}
}