{
  "type": "Feature",
  "properties": {
    "gn:admin1_code":"2.0",
    "gn:admin2_code":"KHH",
    "gn:admin3_code":"E36",
    "gn:admin4_code":"64000360003.0",
    "gn:asciiname":"Maolin Xiang",
    "gn:country_code":"TW",
    "gn:dem":1451,
    "gn:feature_class":"P",
    "gn:feature_code":"PPL",
    "gn:name":"Maolin Xiang",
    "gn:population":0,
    "gn:timezone":"Asia/Taipei",
    "iso:country":"TW",
    "name:und_x_variant":[
        "Mao-lin Hsiang"
    ],
    "wof:name":"Maolin Xiang",
    "wof:placetype":"locality"
},
  "geometry": {"coordinates":[120.75,22.91667],"type":"Point"}
}