{
  "type": "Feature",
  "properties": {
    "gn:admin1_code":"4.0",
    "gn:admin2_code":"CHA",
    "gn:admin3_code":"N08",
    "gn:admin4_code":"10007200010.0",
    "gn:asciiname":"Dingfanshe",
    "gn:country_code":"TW",
    "gn:dem":16,
    "gn:feature_class":"P",
    "gn:feature_code":"PPL",
    "gn:name":"Dingfanshe",
    "gn:population":0,
    "gn:timezone":"Asia/Taipei",
    "iso:country":"TW",
    "name:und_x_variant":[
        "Ting-fan-chuang",
        "Ting-fan-she"
    ],
    "name:zho_x_preferred":[
        "\u9802\u756a\u793e"
    ],
    "wof:name":"Dingfanshe",
    "wof:placetype":"locality"
},
  "geometry": {"coordinates":[120.3754,23.88748],"type":"Point"}
}