{
  "type": "Feature",
  "properties": {
    "gn:admin1_code":"4.0",
    "gn:admin2_code":"PIF",
    "gn:admin3_code":"T12",
    "gn:admin4_code":"10013120005.0",
    "gn:asciiname":"Liutangqi",
    "gn:country_code":"TW",
    "gn:dem":20,
    "gn:feature_class":"P",
    "gn:feature_code":"PPL",
    "gn:name":"Liutangqi",
    "gn:population":0,
    "gn:timezone":"Asia/Taipei",
    "iso:country":"TW",
    "name:und_x_variant":[
        "Liu-kung-ts\u2019un",
        "Lin-huang-ts\u2019un",
        "Liu-huang-ts\u2019un",
        "Lioutangci",
        "Liutangqi"
    ],
    "name:zho_x_preferred":[
        "\u786b\u5858\u5d0e"
    ],
    "name:zho_x_variant":[
        "Liu-t\u2019ang-ch\u2019i"
    ],
    "wof:name":"Liutangqi",
    "wof:placetype":"locality"
},
  "geometry": {"coordinates":[120.57261,22.58297],"type":"Point"}
}