{
  "type": "Feature",
  "properties": {
    "iso:country":"TW",
    "name:eng_x_preferred":[
        "Jilong"
    ],
    "name:eng_x_variant":[
        "Jilong City"
    ],
    "name:zho_tw_x_preferred":[
        "\u57fa\u9686\u5e02"
    ],
    "qs:name":"\u57fa\u9686\u5e02",
    "qs:name_adm0":"\u81fa\u7063",
    "qs:name_adm1":"\u57fa\u9686\u5e02",
    "qs:photos":623,
    "qs:photos_1k":126,
    "qs:photos_9k":121,
    "qs:photos_9r":22,
    "qs:photos_all":27314,
    "qs:photos_sr":8,
    "qs:placetype":"Town",
    "qs:pop_sr":"0",
    "wof:name":"Jilong",
    "wof:placetype":"locality"
},
  "geometry": {"coordinates":[121.732978,25.134095],"type":"Point"}
}