{
  "type": "Feature",
  "properties": {
    "gn:admin1_code":"04",
    "gn:admin2_code":"YUN",
    "gn:admin3_code":"P11",
    "gn:admin4_code":"10009110003.0",
    "gn:asciiname":"Daniunan",
    "gn:country_code":"TW",
    "gn:dem":25,
    "gn:feature_class":"P",
    "gn:feature_code":"PPL",
    "gn:name":"Daniunan",
    "gn:population":0,
    "gn:timezone":"Asia/Taipei",
    "iso:country":"TW",
    "name:und_x_variant":[
        "Daniounan",
        "Ta-niu-nan"
    ],
    "name:zho_x_preferred":[
        "\u6253\u725b\u6e73"
    ],
    "wof:name":"Daniunan",
    "wof:placetype":"locality"
},
  "geometry": {"coordinates":[120.39870999999999,23.76341],"type":"Point"}
}