{
  "type": "Feature",
  "properties": {
    "iso:country":"TW",
    "name:eng_x_preferred":[
        "Liuyi"
    ],
    "name:eng_x_variant":[
        "Liuyi Village"
    ],
    "name:zho_tw_x_preferred":[
        "\u516d\u85dd\u91cc"
    ],
    "qs:name":"\u516d\u85dd\u91cc",
    "qs:name_adm0":"\u81fa\u7063",
    "qs:name_adm1":"\u53f0\u5317\u5e02",
    "qs:photos":191,
    "qs:photos_1k":39,
    "qs:photos_9k":1,
    "qs:photos_9r":4,
    "qs:photos_all":191,
    "qs:photos_sr":4,
    "qs:placetype":"Suburb",
    "qs:pop_sr":"0",
    "wof:name":"Liuyi",
    "wof:placetype":"neighbourhood"
},
  "geometry": {"coordinates":[121.57062999999999,25.043095],"type":"Point"}
}