{
  "type": "Feature",
  "properties": {
    "gn:admin1_code":"4.0",
    "gn:admin2_code":"CHA",
    "gn:admin3_code":"N13",
    "gn:admin4_code":"10007080015.0",
    "gn:asciiname":"Bagu",
    "gn:country_code":"TW",
    "gn:dem":112,
    "gn:feature_class":"P",
    "gn:feature_code":"PPL",
    "gn:name":"Bagu",
    "gn:population":0,
    "gn:timezone":"Asia/Taipei",
    "iso:country":"TW",
    "name:und_x_variant":[
        "Pa-ku"
    ],
    "name:zho_x_preferred":[
        "\u516b\u80a1"
    ],
    "wof:name":"Bagu",
    "wof:placetype":"locality"
},
  "geometry": {"coordinates":[120.5853,24.03109],"type":"Point"}
}