{
  "type": "Feature",
  "properties": {
    "iso:country":"TW",
    "name:eng_x_preferred":[
        "Sanjia"
    ],
    "name:eng_x_variant":[
        "Sanjia Village"
    ],
    "name:zho_tw_x_preferred":[
        "\u4e09\u7532\u6751"
    ],
    "qs:name":"\u4e09\u7532\u6751",
    "qs:name_adm0":"\u81fa\u7063",
    "qs:name_adm1":"\u53f0\u5357\u5e02",
    "qs:photos":41,
    "qs:photos_1k":8,
    "qs:photos_9k":1,
    "qs:photos_9r":2,
    "qs:photos_all":41,
    "qs:photos_sr":2,
    "qs:placetype":"Town",
    "qs:pop_sr":"0",
    "wof:name":"Sanjia",
    "wof:placetype":"locality"
},
  "geometry": {"coordinates":[120.243763,22.926833],"type":"Point"}
}