{
  "type": "Feature",
  "properties": {
    "gn:admin1_code":"4.0",
    "gn:admin2_code":"TPE",
    "gn:admin3_code":"A15",
    "gn:admin4_code":"63000110047.0",
    "gn:asciiname":"Xiaqigu",
    "gn:country_code":"TW",
    "gn:dem":438,
    "gn:feature_class":"P",
    "gn:feature_code":"PPL",
    "gn:name":"Xiaqigu",
    "gn:population":0,
    "gn:timezone":"Asia/Taipei",
    "iso:country":"TW",
    "name:und_x_variant":[
        "Siacigu"
    ],
    "name:zho_x_preferred":[
        "\u4e0b\u4e03\u80a1"
    ],
    "name:zho_x_variant":[
        "Hsia-ch\u2019i-ku"
    ],
    "wof:name":"Xiaqigu",
    "wof:placetype":"locality"
},
  "geometry": {"coordinates":[121.57632,25.18252],"type":"Point"}
}