{
  "type": "Feature",
  "properties": {
    "gn:admin1_code":"4.0",
    "gn:admin2_code":"TAO",
    "gn:admin3_code":"H08",
    "gn:admin4_code":"68000080045.0",
    "gn:asciiname":"Yingqu",
    "gn:country_code":"TW",
    "gn:dem":175,
    "gn:feature_class":"P",
    "gn:feature_code":"PPL",
    "gn:name":"Yingqu",
    "gn:population":0,
    "gn:timezone":"Asia/Taipei",
    "iso:country":"TW",
    "name:und_x_variant":[
        "Yingcyu",
        "Yingqu"
    ],
    "name:zho_x_preferred":[
        "\u71df\u5340"
    ],
    "name:zho_x_variant":[
        "Ying-ch\u00fc"
    ],
    "wof:name":"Yingqu",
    "wof:placetype":"locality"
},
  "geometry": {"coordinates":[121.25611000000001,24.92417],"type":"Point"}
}