{
  "type": "Feature",
  "properties": {
    "gn:admin1_code":"4.0",
    "gn:admin2_code":"YUN",
    "gn:admin3_code":"P11",
    "gn:admin4_code":"10009110014.0",
    "gn:asciiname":"Xinxing",
    "gn:country_code":"TW",
    "gn:dem":18,
    "gn:feature_class":"P",
    "gn:feature_code":"PPL",
    "gn:name":"Xinxing",
    "gn:population":0,
    "gn:timezone":"Asia/Taipei",
    "iso:country":"TW",
    "name:ceb_x_preferred":[
        "Xinxing"
    ],
    "name:deu_x_preferred":[
        "Xinxing"
    ],
    "name:eus_x_preferred":[
        "Xinxing"
    ],
    "name:fra_x_preferred":[
        "Xinxing"
    ],
    "name:nor_x_preferred":[
        "Xinxing"
    ],
    "name:rus_x_preferred":[
        "\u0421\u0438\u043d\u044c\u0441\u0438\u043d"
    ],
    "name:swe_x_preferred":[
        "Xinxing"
    ],
    "name:und_x_variant":[
        "Sinsing",
        "Hsin-hsing"
    ],
    "name:zho_x_preferred":[
        "\u65b0\u8208"
    ],
    "wof:name":"Xinxing",
    "wof:placetype":"locality"
},
  "geometry": {"coordinates":[120.36669999999999,23.8116],"type":"Point"}
}