{
  "type": "Feature",
  "properties": {
    "gn:admin1_code":"04",
    "gn:admin2_code":"HSQ",
    "gn:admin3_code":"O02",
    "gn:admin4_code":"10018020026.0",
    "gn:asciiname":"Baguacuo",
    "gn:country_code":"TW",
    "gn:dem":10,
    "gn:feature_class":"P",
    "gn:feature_code":"PPL",
    "gn:name":"Baguacuo",
    "gn:population":0,
    "gn:timezone":"Asia/Taipei",
    "iso:country":"TW",
    "name:und_x_variant":[
        "Pa-kua-ts\u2019o"
    ],
    "wof:name":"Baguacuo",
    "wof:placetype":"locality"
},
  "geometry": {"coordinates":[120.95,24.83333],"type":"Point"}
}