{
  "type": "Feature",
  "properties": {
    "gn:admin1_code":"4.0",
    "gn:admin2_code":"NAN",
    "gn:admin3_code":"M10",
    "gn:admin4_code":"10008100009.0",
    "gn:asciiname":"Zhumaoya",
    "gn:country_code":"TW",
    "gn:dem":328,
    "gn:feature_class":"P",
    "gn:feature_code":"PPL",
    "gn:name":"Zhumaoya",
    "gn:population":0,
    "gn:timezone":"Asia/Taipei",
    "iso:country":"TW",
    "name:und_x_variant":[
        "Jhumaoya",
        "Zhumaoya",
        "Chu-mao-ya"
    ],
    "name:zho_x_preferred":[
        "Ts\u2019ao-y\u00fc-t\u2019an"
    ],
    "name:zho_x_variant":[
        "\u4e3b\u6bdb\u7259"
    ],
    "wof:name":"Zhumaoya",
    "wof:placetype":"locality"
},
  "geometry": {"coordinates":[120.85008999999999,24.01367],"type":"Point"}
}