{
  "type": "Feature",
  "properties": {
    "gn:admin1_code":"4.0",
    "gn:admin2_code":"TXG",
    "gn:admin3_code":"B27",
    "gn:admin4_code":"66000270014.0",
    "gn:asciiname":"Zuoliaokeng",
    "gn:country_code":"TW",
    "gn:dem":291,
    "gn:feature_class":"P",
    "gn:feature_code":"PPL",
    "gn:name":"Zuoliaokeng",
    "gn:population":0,
    "gn:timezone":"Asia/Taipei",
    "iso:country":"TW",
    "name:zho_x_preferred":[
        "\u4f5c\u6599\u5751"
    ],
    "name:zho_x_variant":[
        "Tso-liao-k\u2019eng"
    ],
    "wof:name":"Zuoliaokeng",
    "wof:placetype":"locality"
},
  "geometry": {"coordinates":[120.7702,24.1548],"type":"Point"}
}