{
  "type": "Feature",
  "properties": {
    "gn:admin1_code":"04",
    "gn:admin2_code":"CYQ",
    "gn:admin3_code":"Q04",
    "gn:admin4_code":"10010040004.0",
    "gn:asciiname":"Dalin",
    "gn:country_code":"TW",
    "gn:dem":35,
    "gn:feature_class":"P",
    "gn:feature_code":"PPL",
    "gn:name":"Dalin",
    "gn:population":0,
    "gn:timezone":"Asia/Taipei",
    "iso:country":"TW",
    "name:und_x_variant":[
        "Ta-lin-chuang",
        "Dalin",
        "Ta-lin"
    ],
    "name:zho_x_preferred":[
        "\u5927\u6797"
    ],
    "name:zho_x_variant":[
        "Ta-p\u2019u-lin"
    ],
    "wof:name":"Dalin",
    "wof:placetype":"locality"
},
  "geometry": {"coordinates":[120.45782,23.60395],"type":"Point"}
}