{
  "type": "Feature",
  "properties": {
    "gn:admin1_code":"04",
    "gn:admin2_code":"CYQ",
    "gn:admin3_code":"Q04",
    "gn:admin4_code":"10010040004.0",
    "gn:asciiname":"Dalin",
    "gn:country_code":"TW",
    "gn:dem":35,
    "gn:feature_class":"P",
    "gn:feature_code":"PPL",
    "gn:name":"Dalin",
    "gn:population":0,
    "gn:timezone":"Asia/Taipei",
    "iso:country":"TW",
    "name:hak_x_preferred":[
        "Thai-l\u00ecm-ch\u1e73\u0301n"
    ],
    "name:jpn_x_preferred":[
        "\u5927\u6797\u93ae"
    ],
    "name:kor_x_preferred":[
        "\ub2e4\ub9b0\uc9c4"
    ],
    "name:pol_x_preferred":[
        "Dalin"
    ],
    "name:und_x_variant":[
        "Ta-lin-chuang",
        "Dalin",
        "Ta-lin"
    ],
    "name:vie_x_preferred":[
        "\u0110\u1ea1i L\u00e2m"
    ],
    "name:zho_x_preferred":[
        "\u5927\u6797"
    ],
    "name:zho_x_variant":[
        "Ta-p\u2019u-lin",
        "\u5927\u6797\u93ae"
    ],
    "wof:name":"Dalin",
    "wof:placetype":"locality"
},
  "geometry": {"coordinates":[120.45782,23.60395],"type":"Point"}
}