{
  "type": "Feature",
  "properties": {
    "gn:admin1_code":"3.0",
    "gn:admin2_code":"TPQ",
    "gn:admin3_code":"F15",
    "gn:admin4_code":"65000090010.0",
    "gn:asciiname":"Zhuizitou",
    "gn:country_code":"TW",
    "gn:dem":95,
    "gn:feature_class":"P",
    "gn:feature_code":"PPL",
    "gn:name":"Zhuizitou",
    "gn:population":0,
    "gn:timezone":"Asia/Taipei",
    "iso:country":"TW",
    "name:und_x_variant":[
        "Jhueizihtou",
        "Zhuizitou"
    ],
    "name:zho_x_preferred":[
        "\u9310\u5b50\u982d"
    ],
    "name:zho_x_variant":[
        "Tsui-tzu-t\u2019ou",
        "Chui-tzu-t\u2019ou"
    ],
    "wof:name":"Zhuizitou",
    "wof:placetype":"locality"
},
  "geometry": {"coordinates":[121.36466,24.8972],"type":"Point"}
}