{
  "type": "Feature",
  "properties": {
    "gn:admin1_code":"4.0",
    "gn:admin2_code":"CYQ",
    "gn:admin3_code":"Q15",
    "gn:admin4_code":"10010140024.0",
    "gn:asciiname":"Pingyuan",
    "gn:country_code":"TW",
    "gn:dem":927,
    "gn:feature_class":"P",
    "gn:feature_code":"PPL",
    "gn:name":"Pingyuan",
    "gn:population":0,
    "gn:timezone":"Asia/Taipei",
    "iso:country":"TW",
    "name:ceb_x_preferred":[
        "Pingyuan"
    ],
    "name:deu_x_preferred":[
        "Pingyuan"
    ],
    "name:fra_x_preferred":[
        "Pingyuan"
    ],
    "name:kor_x_preferred":[
        "\ud551\uc704\uc548\ud604"
    ],
    "name:nor_x_preferred":[
        "Pingyuan"
    ],
    "name:pol_x_preferred":[
        "Pingyuan"
    ],
    "name:rus_x_preferred":[
        "\u041f\u0438\u043d\u044a\u044e\u0430\u043d\u044c"
    ],
    "name:swe_x_preferred":[
        "Pingyuan"
    ],
    "name:zho_x_preferred":[
        "\u5e73\u5712"
    ],
    "name:zho_x_variant":[
        "P\u2019ing-y\u00fcan"
    ],
    "wof:name":"Pingyuan",
    "wof:placetype":"locality"
},
  "geometry": {"coordinates":[120.67269,23.47918],"type":"Point"}
}