{
  "type": "Feature",
  "properties": {
    "iso:country":"TW",
    "name:eng_x_preferred":[
        "Mili"
    ],
    "name:eng_x_variant":[
        "Mili Village"
    ],
    "name:zho_tw_x_preferred":[
        "\u5bc6\u91cc"
    ],
    "name:zho_tw_x_variant":[
        "\u7030\u529b\u6751"
    ],
    "qs:name":"\u7030\u529b\u6751",
    "qs:name_adm0":"\u81fa\u7063",
    "qs:name_adm1":"\u5c4f\u6771\u7e23",
    "qs:photos":46,
    "qs:photos_1k":9,
    "qs:photos_9k":1,
    "qs:photos_9r":2,
    "qs:photos_all":46,
    "qs:photos_sr":2,
    "qs:placetype":"Town",
    "qs:pop_sr":"0",
    "wof:name":"Mili",
    "wof:placetype":"locality"
},
  "geometry": {"coordinates":[120.422962,22.817654],"type":"Point"}
}