{
  "type": "Feature",
  "properties": {
    "gn:admin1_code":"3.0",
    "gn:admin2_code":"TPQ",
    "gn:admin3_code":"F17",
    "gn:admin4_code":"65000070036.0",
    "gn:asciiname":"Shanjia",
    "gn:country_code":"TW",
    "gn:dem":33,
    "gn:feature_class":"P",
    "gn:feature_code":"PPL",
    "gn:name":"Shanjia",
    "gn:population":0,
    "gn:timezone":"Asia/Taipei",
    "iso:country":"TW",
    "name:und_x_variant":[
        "Shan-chia"
    ],
    "name:zho_x_preferred":[
        "\u5c71\u4f73"
    ],
    "wof:name":"Shanjia",
    "wof:placetype":"locality"
},
  "geometry": {"coordinates":[121.39343999999998,24.97211],"type":"Point"}
}