{
  "type": "Feature",
  "properties": {
    "gn:admin1_code":"03",
    "gn:admin2_code":"TPQ",
    "gn:admin3_code":"F27",
    "gn:admin4_code":"65000100012.0",
    "gn:asciiname":"Tianxinzi",
    "gn:country_code":"TW",
    "gn:dem":56,
    "gn:feature_class":"P",
    "gn:feature_code":"PPL",
    "gn:name":"Tianxinzi",
    "gn:population":0,
    "gn:timezone":"Asia/Taipei",
    "iso:country":"TW",
    "name:und_x_variant":[
        "T\u2019ien-hsin-tzu (4)",
        "T\u2019ien-hsin-tzu",
        "Tianxinzi"
    ],
    "wof:name":"Tianxinzi",
    "wof:placetype":"locality"
},
  "geometry": {"coordinates":[121.45,25.18333],"type":"Point"}
}