{
  "type": "Feature",
  "properties": {
    "gn:admin1_code":"4.0",
    "gn:admin2_code":"TTT",
    "gn:admin3_code":"V10",
    "gn:admin4_code":"10014060007.0",
    "gn:asciiname":"Xinxing",
    "gn:country_code":"TW",
    "gn:dem":280,
    "gn:feature_class":"P",
    "gn:feature_code":"PPL",
    "gn:name":"Xinxing",
    "gn:population":0,
    "gn:timezone":"Asia/Taipei",
    "iso:country":"TW",
    "name:und_x_variant":[
        "Sinsing",
        "Hsin-hsing"
    ],
    "name:zho_x_preferred":[
        "Hsin-hsing-ts\u2019un"
    ],
    "name:zho_x_variant":[
        "\u65b0\u8208"
    ],
    "wof:name":"Xinxing",
    "wof:placetype":"locality"
},
  "geometry": {"coordinates":[121.2075,23.10667],"type":"Point"}
}