{
  "type": "Feature",
  "properties": {
    "gn:admin1_code":"4.0",
    "gn:admin2_code":"TAO",
    "gn:admin3_code":"H02",
    "gn:admin4_code":"68000030022.0",
    "gn:asciiname":"Fanziliao",
    "gn:country_code":"TW",
    "gn:dem":213,
    "gn:feature_class":"P",
    "gn:feature_code":"PPL",
    "gn:name":"Fanziliao",
    "gn:population":0,
    "gn:timezone":"Asia/Taipei",
    "iso:country":"TW",
    "name:und_x_variant":[
        "Fanzihliao",
        "Fanziliao",
        "Fan-tzu-liao"
    ],
    "name:zho_x_preferred":[
        "\u756a\u5b50\u5bee"
    ],
    "name:zho_x_variant":[
        "Jui-y\u00fcan"
    ],
    "wof:name":"Fanziliao",
    "wof:placetype":"locality"
},
  "geometry": {"coordinates":[121.2525,24.86778],"type":"Point"}
}