{
  "type": "Feature",
  "properties": {
    "gn:admin1_code":"3.0",
    "gn:admin2_code":"TPQ",
    "gn:admin3_code":"F23",
    "gn:admin4_code":"65000250004.0",
    "gn:asciiname":"Dachayuan",
    "gn:country_code":"TW",
    "gn:dem":217,
    "gn:feature_class":"P",
    "gn:feature_code":"PPL",
    "gn:name":"Dachayuan",
    "gn:population":0,
    "gn:timezone":"Asia/Taipei",
    "iso:country":"TW",
    "name:zho_x_preferred":[
        "\u5927\u8336\u5712"
    ],
    "name:zho_x_variant":[
        "Ta-ch\u2019a-y\u00fcan"
    ],
    "wof:name":"Dachayuan",
    "wof:placetype":"locality"
},
  "geometry": {"coordinates":[121.86274,25.00108],"type":"Point"}
}