{
  "type": "Feature",
  "properties": {
    "gn:admin1_code":"04",
    "gn:admin2_code":"HUA",
    "gn:admin3_code":"U10",
    "gn:admin4_code":"10015100007.0",
    "gn:asciiname":"Shipai",
    "gn:country_code":"TW",
    "gn:dem":221,
    "gn:feature_class":"P",
    "gn:feature_code":"PPL",
    "gn:name":"Shipai",
    "gn:population":0,
    "gn:timezone":"Asia/Taipei",
    "iso:country":"TW",
    "name:und_x_variant":[
        "Shihpai"
    ],
    "name:zho_x_preferred":[
        "Shih-p\u2019ai-ts\u2019un"
    ],
    "name:zho_x_variant":[
        "\u77f3\u724c",
        "Shih-p\u2019ai"
    ],
    "wof:name":"Shipai",
    "wof:placetype":"locality"
},
  "geometry": {"coordinates":[121.26447,23.19287000000001],"type":"Point"}
}