{
  "type": "Feature",
  "properties": {
    "gn:admin1_code":"04",
    "gn:admin2_code":"YUN",
    "gn:admin3_code":"P06",
    "gn:admin4_code":"10009060020.0",
    "gn:asciiname":"Yanzhushe",
    "gn:country_code":"TW",
    "gn:dem":11,
    "gn:feature_class":"P",
    "gn:feature_code":"PPL",
    "gn:name":"Yanzhushe",
    "gn:population":0,
    "gn:timezone":"Asia/Taipei",
    "iso:country":"TW",
    "name:und_x_variant":[
        "Yen-chu",
        "Yanjhushe",
        "Yanzhushe",
        "Yen-chu-she"
    ],
    "name:zho_x_preferred":[
        "\u5944\u732a\u793e"
    ],
    "wof:name":"Yanzhushe",
    "wof:placetype":"locality"
},
  "geometry": {"coordinates":[120.2945,23.6028],"type":"Point"}
}