{
  "type": "Feature",
  "properties": {
    "gn:admin1_code":"4.0",
    "gn:admin2_code":"ILA",
    "gn:admin3_code":"G03",
    "gn:admin4_code":"10002050018.0",
    "gn:asciiname":"Cizilun",
    "gn:country_code":"TW",
    "gn:dem":49,
    "gn:feature_class":"P",
    "gn:feature_code":"PPL",
    "gn:name":"Cizilun",
    "gn:population":0,
    "gn:timezone":"Asia/Taipei",
    "iso:country":"TW",
    "name:und_x_variant":[
        "Cihzihlun",
        "Cizilun"
    ],
    "name:zho_x_preferred":[
        "\u523a\u5b50\u5d19"
    ],
    "name:zho_x_variant":[
        "Tz\u2019u-tzu-lun"
    ],
    "wof:name":"Cizilun",
    "wof:placetype":"locality"
},
  "geometry": {"coordinates":[121.7239,24.78588],"type":"Point"}
}