{
  "type": "Feature",
  "properties": {
    "gn:admin1_code":"04",
    "gn:admin2_code":"HSZ",
    "gn:admin3_code":"J06",
    "gn:admin4_code":"10004050006.0",
    "gn:asciiname":"Desheng",
    "gn:country_code":"TW",
    "gn:dem":59,
    "gn:feature_class":"P",
    "gn:feature_code":"PPL",
    "gn:name":"Desheng",
    "gn:population":0,
    "gn:timezone":"Asia/Taipei",
    "iso:country":"TW",
    "name:und_x_variant":[
        "Te-sheng"
    ],
    "name:zho_x_preferred":[
        "\u5fb7\u76db"
    ],
    "wof:name":"Desheng",
    "wof:placetype":"locality"
},
  "geometry": {"coordinates":[121.03082999999999,24.90611],"type":"Point"}
}