{
  "type": "Feature",
  "properties": {
    "iso:country":"TW",
    "name:eng_x_preferred":[
        "Mingfeng"
    ],
    "name:eng_x_variant":[
        "Mingfeng Village"
    ],
    "name:zho_tw_x_preferred":[
        "\u9cf4\u9cf3\u6751"
    ],
    "qs:name":"\u9cf4\u9cf3\u6751",
    "qs:name_adm0":"\u81fa\u7063",
    "qs:name_adm1":"\u82d7\u6817\u7e23",
    "qs:photos":83,
    "qs:photos_1k":17,
    "qs:photos_9k":1,
    "qs:photos_9r":3,
    "qs:photos_all":83,
    "qs:photos_sr":3,
    "qs:placetype":"Town",
    "qs:pop_sr":"0",
    "wof:name":"Mingfeng",
    "wof:placetype":"locality"
},
  "geometry": {"coordinates":[120.906194,24.547638],"type":"Point"}
}