{
  "type": "Feature",
  "properties": {
    "gn:admin1_code":"04",
    "gn:admin2_code":"MIA",
    "gn:admin3_code":"K13",
    "gn:admin4_code":"10005160005.0",
    "gn:asciiname":"Dabeibu",
    "gn:country_code":"TW",
    "gn:dem":225,
    "gn:feature_class":"P",
    "gn:feature_code":"PPL",
    "gn:name":"Dabeibu",
    "gn:population":0,
    "gn:timezone":"Asia/Taipei",
    "iso:country":"TW",
    "name:und_x_variant":[
        "Ta-pei-pu"
    ],
    "name:zho_x_preferred":[
        "Tu-p\u2019ei-pu"
    ],
    "name:zho_x_variant":[
        "\u5927\u5317\u57d4"
    ],
    "wof:name":"Dabeibu",
    "wof:placetype":"locality"
},
  "geometry": {"coordinates":[120.9815,24.64555],"type":"Point"}
}