{
  "type": "Feature",
  "properties": {
    "gn:admin1_code":"04",
    "gn:admin2_code":"CYQ",
    "gn:admin3_code":"Q12",
    "gn:admin4_code":"10010010008.0",
    "gn:asciiname":"Dongshiliao",
    "gn:country_code":"TW",
    "gn:dem":15,
    "gn:feature_class":"P",
    "gn:feature_code":"PPL",
    "gn:name":"Dongshiliao",
    "gn:population":0,
    "gn:timezone":"Asia/Taipei",
    "iso:country":"TW",
    "name:und_x_variant":[
        "Tung-shih-li",
        "Tung-shih",
        "Dongshiliao",
        "Dongshihliao",
        "Tung-shih-liao"
    ],
    "name:zho_x_preferred":[
        "\u6771\u52e2\u5bee"
    ],
    "wof:name":"Dongshiliao",
    "wof:placetype":"locality"
},
  "geometry": {"coordinates":[120.30583,23.46639],"type":"Point"}
}