{
  "type": "Feature",
  "properties": {
    "gn:admin1_code":"4.0",
    "gn:admin2_code":"PIF",
    "gn:admin3_code":"T18",
    "gn:admin4_code":"10013180007.0",
    "gn:asciiname":"Xialiao",
    "gn:country_code":"TW",
    "gn:dem":3,
    "gn:feature_class":"P",
    "gn:feature_code":"PPL",
    "gn:name":"Xialiao",
    "gn:population":0,
    "gn:timezone":"Asia/Taipei",
    "iso:country":"TW",
    "name:und_x_variant":[
        "Hsia-liao",
        "Sialiao"
    ],
    "name:zho_x_preferred":[
        "\u4e0b\u5bee"
    ],
    "wof:name":"Xialiao",
    "wof:placetype":"locality"
},
  "geometry": {"coordinates":[120.4883,22.5011],"type":"Point"}
}