{
  "type": "Feature",
  "properties": {
    "gn:admin1_code":"02",
    "gn:admin2_code":"KHH",
    "gn:admin3_code":"E31",
    "gn:admin4_code":"64000310015.0",
    "gn:asciiname":"Qingshui",
    "gn:country_code":"TW",
    "gn:dem":45,
    "gn:feature_class":"P",
    "gn:feature_code":"PPL",
    "gn:name":"Qingshui",
    "gn:population":0,
    "gn:timezone":"Asia/Taipei",
    "iso:country":"TW",
    "name:ceb_x_preferred":[
        "Qingshui"
    ],
    "name:deu_x_preferred":[
        "Qingshui"
    ],
    "name:und_x_variant":[
        "Cingshuei"
    ],
    "name:zho_x_preferred":[
        "Shang-ch\u2019ing-shui-chiang"
    ],
    "name:zho_x_variant":[
        "\u6e05\u6c34",
        "Shang-ch\u2019ing-shui-kang",
        "Ch\u2019ing-shui"
    ],
    "wof:name":"Qingshui",
    "wof:placetype":"locality"
},
  "geometry": {"coordinates":[120.52248,22.86894],"type":"Point"}
}