{
  "type": "Feature",
  "properties": {
    "gn:admin1_code":"04",
    "gn:admin2_code":"PIF",
    "gn:admin3_code":"T13",
    "gn:admin4_code":"10013130008.0",
    "gn:asciiname":"Shangzhutoujiao",
    "gn:country_code":"TW",
    "gn:dem":21,
    "gn:feature_class":"P",
    "gn:feature_code":"PPL",
    "gn:name":"Shangzhutoujiao",
    "gn:population":0,
    "gn:timezone":"Asia/Taipei",
    "iso:country":"TW",
    "name:und_x_variant":[
        "\u4e0a\u7af9\u982d\u89d2",
        "Shangzhutoujiao",
        "Shangjhutoujiao"
    ],
    "name:zho_x_preferred":[
        "Shang-chu-t\u2019ou-chiao"
    ],
    "name:zho_x_variant":[
        "\u4e0a\u7af9\u982d\u89d2"
    ],
    "wof:name":"Shangzhutoujiao",
    "wof:placetype":"locality"
},
  "geometry": {"coordinates":[120.53719,22.62155],"type":"Point"}
}