{
  "type": "Feature",
  "properties": {
    "iso:country":"TW",
    "name:eng_x_preferred":[
        "Xinjian"
    ],
    "name:eng_x_variant":[
        "Xinjian Village"
    ],
    "name:zho_tw_x_preferred":[
        "\u65b0\u5efa\u91cc"
    ],
    "qs:name":"\u65b0\u5efa\u91cc",
    "qs:name_adm0":"\u81fa\u7063",
    "qs:name_adm1":"\u57fa\u9686\u5e02",
    "qs:photos":19,
    "qs:photos_1k":4,
    "qs:photos_9k":1,
    "qs:photos_9r":1,
    "qs:photos_all":19,
    "qs:photos_sr":1,
    "qs:placetype":"Suburb",
    "qs:pop_sr":"0",
    "wof:name":"Xinjian",
    "wof:placetype":"neighbourhood"
},
  "geometry": {"coordinates":[121.737613,25.130286],"type":"Point"}
}