{
  "type": "Feature",
  "properties": {
    "gn:admin1_code":"4.0",
    "gn:admin2_code":"ILA",
    "gn:admin3_code":"G10",
    "gn:admin4_code":"10002100006.0",
    "gn:asciiname":"Ganzikeng",
    "gn:country_code":"TW",
    "gn:dem":193,
    "gn:feature_class":"P",
    "gn:feature_code":"PPL",
    "gn:name":"Ganzikeng",
    "gn:population":0,
    "gn:timezone":"Asia/Taipei",
    "iso:country":"TW",
    "name:und_x_variant":[
        "Ganzihkeng",
        "Ganzikeng"
    ],
    "name:zho_x_preferred":[
        "\u67d1\u4ed4\u5751"
    ],
    "name:zho_x_variant":[
        "Kan-tzu-k\u2019eng"
    ],
    "wof:name":"Ganzikeng",
    "wof:placetype":"locality"
},
  "geometry": {"coordinates":[121.64852,24.64809],"type":"Point"}
}