{
  "type": "Feature",
  "properties": {
    "gn:admin1_code":"4.0",
    "gn:admin2_code":"PIF",
    "gn:admin3_code":"T23",
    "gn:admin4_code":"10013230004.0",
    "gn:asciiname":"Dagedong",
    "gn:country_code":"TW",
    "gn:dem":21,
    "gn:feature_class":"P",
    "gn:feature_code":"PPL",
    "gn:name":"Dagedong",
    "gn:population":0,
    "gn:timezone":"Asia/Taipei",
    "iso:country":"TW",
    "name:und_x_variant":[
        "Ta-ko-tung"
    ],
    "name:zho_x_preferred":[
        "\u5927\u54e5\u6d1e"
    ],
    "wof:name":"Dagedong",
    "wof:placetype":"locality"
},
  "geometry": {"coordinates":[120.71389000000001,22.11556],"type":"Point"}
}