{
  "type": "Feature",
  "properties": {
    "gn:admin1_code":"4.0",
    "gn:admin2_code":"TXG",
    "gn:admin3_code":"B18",
    "gn:admin4_code":"66000180007.0",
    "gn:asciiname":"Magangcuo",
    "gn:country_code":"TW",
    "gn:dem":143,
    "gn:feature_class":"P",
    "gn:feature_code":"PPL",
    "gn:name":"Magangcuo",
    "gn:population":0,
    "gn:timezone":"Asia/Taipei",
    "iso:country":"TW",
    "name:und_x_variant":[
        "San-ho",
        "San-ho-ts\u2019un",
        "\u99ac\u5ca1\u539d",
        "Magangcuo"
    ],
    "name:zho_x_preferred":[
        "Ma-kang-ts\u2019o"
    ],
    "wof:name":"Magangcuo",
    "wof:placetype":"locality"
},
  "geometry": {"coordinates":[120.66638,24.21519],"type":"Point"}
}