{
  "type": "Feature",
  "properties": {
    "gn:admin1_code":"3.0",
    "gn:admin2_code":"TPQ",
    "gn:admin3_code":"F15",
    "gn:admin4_code":"65000090016.0",
    "gn:asciiname":"Donglu",
    "gn:country_code":"TW",
    "gn:dem":452,
    "gn:feature_class":"P",
    "gn:feature_code":"PPL",
    "gn:name":"Donglu",
    "gn:population":0,
    "gn:timezone":"Asia/Taipei",
    "iso:country":"TW",
    "name:und_x_variant":[
        "Tung-lu"
    ],
    "name:zho_x_preferred":[
        "\u6771\u9e93"
    ],
    "wof:name":"Donglu",
    "wof:placetype":"locality"
},
  "geometry": {"coordinates":[121.42877,24.85605],"type":"Point"}
}