{
  "type": "Feature",
  "properties": {
    "gn:admin1_code":"4.0",
    "gn:admin2_code":"ILA",
    "gn:admin3_code":"G04",
    "gn:admin4_code":"10002060002.0",
    "gn:asciiname":"Jiadonglin",
    "gn:country_code":"TW",
    "gn:dem":3,
    "gn:feature_class":"P",
    "gn:feature_code":"PPL",
    "gn:name":"Jiadonglin",
    "gn:population":0,
    "gn:timezone":"Asia/Taipei",
    "iso:country":"TW",
    "name:und_x_variant":[
        "Chia-tung-lin"
    ],
    "name:zho_x_preferred":[
        "\u52a0\u51ac\u6797"
    ],
    "name:zho_x_variant":[
        "Ch\u2019ieh-tung-lin"
    ],
    "wof:name":"Jiadonglin",
    "wof:placetype":"locality"
},
  "geometry": {"coordinates":[121.78476999999999,24.72551],"type":"Point"}
}