{
  "type": "Feature",
  "properties": {
    "gn:admin1_code":"04",
    "gn:admin2_code":"ILA",
    "gn:admin3_code":"G08",
    "gn:admin4_code":"10002080001.0",
    "gn:asciiname":"Toudu",
    "gn:country_code":"TW",
    "gn:dem":4,
    "gn:feature_class":"P",
    "gn:feature_code":"PPL",
    "gn:name":"Toudu",
    "gn:population":0,
    "gn:timezone":"Asia/Taipei",
    "iso:country":"TW",
    "name:zho_x_preferred":[
        "\u982d\u5835"
    ],
    "name:zho_x_variant":[
        "T\u2019ou-tu"
    ],
    "wof:name":"Toudu",
    "wof:placetype":"locality"
},
  "geometry": {"coordinates":[121.79898,24.65179],"type":"Point"}
}