{
  "type": "Feature",
  "properties": {
    "gn:admin1_code":"04",
    "gn:admin2_code":"CYQ",
    "gn:admin3_code":"Q03",
    "gn:admin4_code":"10010030016.0",
    "gn:asciiname":"Caipuli",
    "gn:country_code":"TW",
    "gn:dem":5,
    "gn:feature_class":"P",
    "gn:feature_code":"PPL",
    "gn:name":"Caipuli",
    "gn:population":0,
    "gn:timezone":"Asia/Taipei",
    "iso:country":"TW",
    "name:zho_x_preferred":[
        "Ts\u2019ai-pu-pu"
    ],
    "name:zho_x_variant":[
        "Ts\u2019ai-p\u2019u-ts\u2019un",
        "\u83dc\u92ea\u91cc",
        "Ts\u2019ai-pu-p\u2019ou",
        "Ts\u2019ai-p\u2019u",
        "Ts\u2019ai-p\u2019u-li"
    ],
    "wof:name":"Caipuli",
    "wof:placetype":"locality"
},
  "geometry": {"coordinates":[120.21644000000001,23.38689],"type":"Point"}
}