{
  "type": "Feature",
  "properties": {
    "gn:admin1_code":"4.0",
    "gn:admin2_code":"HUA",
    "gn:admin3_code":"U13",
    "gn:admin4_code":"10015130005.0",
    "gn:asciiname":"Sanxing",
    "gn:country_code":"TW",
    "gn:dem":804,
    "gn:feature_class":"P",
    "gn:feature_code":"PPL",
    "gn:name":"Sanxing",
    "gn:population":0,
    "gn:timezone":"Asia/Taipei",
    "iso:country":"TW",
    "name:und_x_variant":[
        "Sansing",
        "San-hsing"
    ],
    "name:zho_x_preferred":[
        "\u4e09\u8208"
    ],
    "wof:name":"Sanxing",
    "wof:placetype":"locality"
},
  "geometry": {"coordinates":[121.18277999999999,23.26056],"type":"Point"}
}