{
  "type": "Feature",
  "properties": {
    "gn:admin1_code":"4.0",
    "gn:admin2_code":"TNN",
    "gn:admin3_code":"R10",
    "gn:admin4_code":"67000100005.0",
    "gn:asciiname":"Zhonglun",
    "gn:country_code":"TW",
    "gn:dem":88,
    "gn:feature_class":"P",
    "gn:feature_code":"PPL",
    "gn:name":"Zhonglun",
    "gn:population":0,
    "gn:timezone":"Asia/Taipei",
    "iso:country":"TW",
    "name:und_x_variant":[
        "Jhonglun",
        "Zhonglun",
        "Chung-lun"
    ],
    "name:zho_x_preferred":[
        "\u4e2d\u5d19"
    ],
    "wof:name":"Zhonglun",
    "wof:placetype":"locality"
},
  "geometry": {"coordinates":[120.42028999999999,23.19568],"type":"Point"}
}