{
  "type": "Feature",
  "properties": {
    "gn:admin1_code":"04",
    "gn:admin2_code":"TAO",
    "gn:admin3_code":"H04",
    "gn:admin4_code":"68000040006.0",
    "gn:asciiname":"Bengpoxia",
    "gn:country_code":"TW",
    "gn:dem":181,
    "gn:feature_class":"P",
    "gn:feature_code":"PPL",
    "gn:name":"Bengpoxia",
    "gn:population":0,
    "gn:timezone":"Asia/Taipei",
    "iso:country":"TW",
    "name:und_x_variant":[
        "Bengposia"
    ],
    "name:zho_x_preferred":[
        "\u5d29\u5761\u4e0b"
    ],
    "name:zho_x_variant":[
        "Peng-p\u2019o-hsia"
    ],
    "wof:name":"Bengpoxia",
    "wof:placetype":"locality"
},
  "geometry": {"coordinates":[121.11278,24.89472],"type":"Point"}
}