{
  "type": "Feature",
  "properties": {
    "iso:country":"TW",
    "label:eng_x_preferred_longname":[
        "Fuxing Township"
    ],
    "label:eng_x_preferred_placetype":[
        "township"
    ],
    "name:ami_x_preferred":[
        "Fuxing"
    ],
    "name:deu_x_preferred":[
        "Fuxing"
    ],
    "name:eng_x_preferred":[
        "Fuxing"
    ],
    "name:hak_x_preferred":[
        "Fu\u030dk-h\u00een-hi\u00f4ng"
    ],
    "name:jpn_x_preferred":[
        "\u5fa9\u8208\u533a"
    ],
    "name:kor_x_preferred":[
        "\ud478\uc2f1 \ud5a5"
    ],
    "name:lit_x_preferred":[
        "Fusingas"
    ],
    "name:nan_x_preferred":[
        "Ho\u030dk-heng-khu"
    ],
    "name:pwn_x_preferred":[
        "Fuxing"
    ],
    "name:szy_x_preferred":[
        "Fuxing"
    ],
    "name:tay_x_preferred":[
        "Hosing Ku"
    ],
    "name:trv_x_preferred":[
        "Fuxing"
    ],
    "name:vie_x_preferred":[
        "Ph\u00fac H\u01b0ng"
    ],
    "name:xsy_x_preferred":[
        "Fuxing"
    ],
    "name:yue_x_preferred":[
        "\u5fa9\u8208\u5340"
    ],
    "name:zho_x_preferred":[
        "\u5fa9\u8208\u5340"
    ],
    "name:zho_x_variant":[
        "\u5fa9\u8208\u9109"
    ],
    "qs:name":"\u5fa9\u8208\u9109",
    "qs:name_adm0":"\u81fa\u7063",
    "qs:name_adm1":"\u6843\u5712\u7e23",
    "qs:photos":1960,
    "qs:photos_1k":397,
    "qs:photos_9k":9,
    "qs:photos_9r":9,
    "qs:photos_all":1960,
    "qs:photos_sr":15,
    "qs:placetype":"County",
    "qs:pop_sr":"0",
    "wd:wordcount":480,
    "wof:name":"Fuxing",
    "wof:placetype":"county"
},
  "geometry": {"coordinates":[121.376609,24.680089],"type":"Point"}
}