{
  "type": "Feature",
  "properties": {
    "iso:country":"TW",
    "qs:name":"\u5fa9\u8208\u9109",
    "qs:name_adm0":"\u81fa\u7063",
    "qs:name_adm1":"\u6843\u5712\u7e23",
    "qs:photos":1960,
    "qs:photos_1k":397,
    "qs:photos_9k":9,
    "qs:photos_9r":9,
    "qs:photos_all":1960,
    "qs:photos_sr":15,
    "qs:placetype":"County",
    "qs:pop_sr":"0",
    "wd:wordcount":480,
    "wof:name":"\u5fa9\u8208\u9109",
    "wof:placetype":"county"
},
  "geometry": {"coordinates":[121.376609,24.680089],"type":"Point"}
}