{
  "type": "Feature",
  "properties": {
    "gn:admin1_code":"3.0",
    "gn:admin2_code":"TPQ",
    "gn:admin3_code":"F15",
    "gn:admin4_code":"65000090016.0",
    "gn:asciiname":"Axikeng",
    "gn:country_code":"TW",
    "gn:dem":367,
    "gn:feature_class":"P",
    "gn:feature_code":"PPL",
    "gn:name":"Axikeng",
    "gn:population":0,
    "gn:timezone":"Asia/Taipei",
    "iso:country":"TW",
    "name:und_x_variant":[
        "Asikeng"
    ],
    "name:zho_x_preferred":[
        "\u963f\u7fd2\u5751"
    ],
    "name:zho_x_variant":[
        "A-hsi-k\u2019eng"
    ],
    "wof:name":"Axikeng",
    "wof:placetype":"locality"
},
  "geometry": {"coordinates":[121.41659,24.85966],"type":"Point"}
}