{
  "type": "Feature",
  "properties": {
    "gn:admin1_code":"04",
    "gn:admin2_code":"TAO",
    "gn:admin3_code":"H01",
    "gn:admin4_code":"68000010017.0",
    "gn:asciiname":"Buzi",
    "gn:country_code":"TW",
    "gn:dem":91,
    "gn:feature_class":"P",
    "gn:feature_code":"PPL",
    "gn:name":"Buzi",
    "gn:population":0,
    "gn:timezone":"Asia/Taipei",
    "iso:country":"TW",
    "name:und_x_variant":[
        "Chung-pu",
        "Buzih",
        "Buzi",
        "Pu-tzu"
    ],
    "name:zho_x_preferred":[
        "\u57d4\u5b50"
    ],
    "wof:name":"Buzi",
    "wof:placetype":"locality"
},
  "geometry": {"coordinates":[121.29165999999999,25.00800000000001],"type":"Point"}
}