{
  "type": "Feature",
  "properties": {
    "gn:admin1_code":"3.0",
    "gn:admin2_code":"TPQ",
    "gn:admin3_code":"F02",
    "gn:admin4_code":"65000170010.0",
    "gn:asciiname":"Tudigongcuo",
    "gn:country_code":"TW",
    "gn:dem":144,
    "gn:feature_class":"P",
    "gn:feature_code":"PPL",
    "gn:name":"Tudigongcuo",
    "gn:population":0,
    "gn:timezone":"Asia/Taipei",
    "iso:country":"TW",
    "name:zho_x_preferred":[
        "\u571f\u5730\u516c\u539d"
    ],
    "name:zho_x_variant":[
        "T\u2019u-ti-kung-ts\u2019o"
    ],
    "wof:name":"Tudigongcuo",
    "wof:placetype":"locality"
},
  "geometry": {"coordinates":[121.3522,25.09513],"type":"Point"}
}