{
  "type": "Feature",
  "properties": {
    "gn:admin1_code":"03",
    "gn:admin2_code":"TPQ",
    "gn:admin3_code":"F23",
    "gn:admin4_code":"65000250008.0",
    "gn:asciiname":"Buwei",
    "gn:country_code":"TW",
    "gn:dem":57,
    "gn:feature_class":"P",
    "gn:feature_code":"PPL",
    "gn:name":"Buwei",
    "gn:population":0,
    "gn:timezone":"Asia/Taipei",
    "iso:country":"TW",
    "name:und_x_variant":[
        "Pu-wei"
    ],
    "name:zho_x_preferred":[
        "\u57d4\u5c3e"
    ],
    "wof:name":"Buwei",
    "wof:placetype":"locality"
},
  "geometry": {"coordinates":[121.8558,25.03794],"type":"Point"}
}