{
  "type": "Feature",
  "properties": {
    "gn:admin1_code":"4.0",
    "gn:admin2_code":"TTT",
    "gn:admin3_code":"V07",
    "gn:admin4_code":"10014070004.0",
    "gn:asciiname":"Qikuaicuo",
    "gn:country_code":"TW",
    "gn:dem":244,
    "gn:feature_class":"P",
    "gn:feature_code":"PPL",
    "gn:name":"Qikuaicuo",
    "gn:population":0,
    "gn:timezone":"Asia/Taipei",
    "iso:country":"TW",
    "name:und_x_variant":[
        "Cikuaicuo",
        "Qikuaicuo"
    ],
    "name:zho_x_preferred":[
        "Wa-k\u2019o-ya-chi"
    ],
    "name:zho_x_variant":[
        "Chi-ya-k\u2019o-wa",
        "\u4e03\u584a\u539d",
        "Ch\u2019i-k\u2019uai-ts\u2019o"
    ],
    "wof:name":"Qikuaicuo",
    "wof:placetype":"locality"
},
  "geometry": {"coordinates":[121.21732,22.94326],"type":"Point"}
}