{
  "type": "Feature",
  "properties": {
    "gn:admin1_code":"4.0",
    "gn:admin2_code":"MIA",
    "gn:admin3_code":"K16",
    "gn:admin4_code":"10005070010.0",
    "gn:asciiname":"Tangpou",
    "gn:country_code":"TW",
    "gn:dem":314,
    "gn:feature_class":"P",
    "gn:feature_code":"PPL",
    "gn:name":"Tangpou",
    "gn:population":0,
    "gn:timezone":"Asia/Taipei",
    "iso:country":"TW",
    "name:zho_x_preferred":[
        "\u7cd6\u5ecd"
    ],
    "name:zho_x_variant":[
        "T\u2019ang-p\u2019u",
        "T\u2019ang-p\u2019ou"
    ],
    "wof:name":"Tangpou",
    "wof:placetype":"locality"
},
  "geometry": {"coordinates":[120.81656,24.32506],"type":"Point"}
}