{
  "type": "Feature",
  "properties": {
    "gn:admin1_code":"4.0",
    "gn:admin2_code":"HSZ",
    "gn:admin3_code":"J13",
    "gn:admin4_code":"10004110001.0",
    "gn:asciiname":"Yinying",
    "gn:country_code":"TW",
    "gn:dem":136,
    "gn:feature_class":"P",
    "gn:feature_code":"PPL",
    "gn:name":"Yinying",
    "gn:population":0,
    "gn:timezone":"Asia/Taipei",
    "iso:country":"TW",
    "name:und_x_variant":[
        "Yin-ying"
    ],
    "name:zho_x_preferred":[
        "\u9670\u5f71"
    ],
    "wof:name":"Yinying",
    "wof:placetype":"locality"
},
  "geometry": {"coordinates":[121.03194000000001,24.68028],"type":"Point"}
}