{
  "type": "Feature",
  "properties": {
    "iso:country":"TW",
    "name:eng_x_preferred":[
        "Yuanlin"
    ],
    "name:eng_x_variant":[
        "Yuanlin Township"
    ],
    "name:zho_tw_x_preferred":[
        "\u54e1\u6797\u93ae"
    ],
    "qs:name":"\u54e1\u6797\u93ae",
    "qs:name_adm0":"\u81fa\u7063",
    "qs:name_adm1":"\u5f70\u5316\u7e23",
    "qs:photos":5000,
    "qs:photos_1k":1000,
    "qs:photos_9k":22,
    "qs:photos_9r":14,
    "qs:photos_all":5000,
    "qs:photos_sr":24,
    "qs:placetype":"Town",
    "qs:pop_sr":"0",
    "wof:name":"Yuanlin",
    "wof:placetype":"locality"
},
  "geometry": {"coordinates":[120.575363,23.954861],"type":"Point"}
}