{
  "type": "Feature",
  "properties": {
    "gn:admin1_code":"04",
    "gn:admin2_code":"CHA",
    "gn:admin3_code":"N10",
    "gn:admin4_code":"10007050008.0",
    "gn:asciiname":"Dingxibu",
    "gn:country_code":"TW",
    "gn:dem":4,
    "gn:feature_class":"P",
    "gn:feature_code":"PPL",
    "gn:name":"Dingxibu",
    "gn:population":0,
    "gn:timezone":"Asia/Taipei",
    "iso:country":"TW",
    "name:und_x_variant":[
        "Dingsibu",
        "Dingxibu",
        "Ting-hsi-pu"
    ],
    "name:zho_x_preferred":[
        "Ch\u2019\u00fcan-hsing"
    ],
    "name:zho_x_variant":[
        "Ting-ch\u2019i-pu",
        "Ch\u2019\u00fcan-hsing-ts\u2019un",
        "\u9802\u6eaa\u57d4"
    ],
    "wof:name":"Dingxibu",
    "wof:placetype":"locality"
},
  "geometry": {"coordinates":[120.49056000000002,24.17833],"type":"Point"}
}