{
  "type": "Feature",
  "properties": {
    "gn:admin1_code":"4.0",
    "gn:admin2_code":"CHA",
    "gn:admin3_code":"N03",
    "gn:admin4_code":"10007030029.0",
    "gn:asciiname":"Jiabaotan",
    "gn:country_code":"TW",
    "gn:dem":14,
    "gn:feature_class":"P",
    "gn:feature_code":"PPL",
    "gn:name":"Jiabaotan",
    "gn:population":0,
    "gn:timezone":"Asia/Taipei",
    "iso:country":"TW",
    "name:und_x_variant":[
        "Chia-pao-li",
        "Jiabaotan",
        "Chia-pao"
    ],
    "name:zho_x_preferred":[
        "\u5609\u5bf6\u6f6d"
    ],
    "name:zho_x_variant":[
        "Chia-pao-t\u2019an"
    ],
    "wof:name":"Jiabaotan",
    "wof:placetype":"locality"
},
  "geometry": {"coordinates":[120.51389,24.13],"type":"Point"}
}