{
  "type": "Feature",
  "properties": {
    "gn:admin1_code":"4.0",
    "gn:admin2_code":"HSZ",
    "gn:admin3_code":"J06",
    "gn:admin4_code":"10004050005.0",
    "gn:asciiname":"Wucuo",
    "gn:country_code":"TW",
    "gn:dem":97,
    "gn:feature_class":"P",
    "gn:feature_code":"PPL",
    "gn:name":"Wucuo",
    "gn:population":0,
    "gn:timezone":"Asia/Taipei",
    "iso:country":"TW",
    "name:und_x_variant":[
        "Wu-wu",
        "Wucuo"
    ],
    "name:zho_x_preferred":[
        "\u5433\u539d"
    ],
    "name:zho_x_variant":[
        "Wu-ts\u2019o"
    ],
    "wof:name":"Wucuo",
    "wof:placetype":"locality"
},
  "geometry": {"coordinates":[121.05889000000001,24.90194],"type":"Point"}
}