{
  "type": "Feature",
  "properties": {
    "gn:admin1_code":"04",
    "gn:admin2_code":"NAN",
    "gn:admin3_code":"M01",
    "gn:admin4_code":"10008010008.0",
    "gn:asciiname":"Shibazhang",
    "gn:country_code":"TW",
    "gn:dem":96,
    "gn:feature_class":"P",
    "gn:feature_code":"PPL",
    "gn:name":"Shibazhang",
    "gn:population":0,
    "gn:timezone":"Asia/Taipei",
    "iso:country":"TW",
    "name:und_x_variant":[
        "Shih-pa-chang"
    ],
    "wof:name":"Shibazhang",
    "wof:placetype":"locality"
},
  "geometry": {"coordinates":[120.68333,23.91667],"type":"Point"}
}