{
  "type": "Feature",
  "properties": {
    "gn:admin1_code":"4.0",
    "gn:admin2_code":"HSZ",
    "gn:admin3_code":"J12",
    "gn:admin4_code":"10004090004.0",
    "gn:asciiname":"Zhuangkou",
    "gn:country_code":"TW",
    "gn:dem":162,
    "gn:feature_class":"P",
    "gn:feature_code":"PPL",
    "gn:name":"Zhuangkou",
    "gn:population":0,
    "gn:timezone":"Asia/Taipei",
    "iso:country":"TW",
    "name:und_x_variant":[
        "Jhuangkou",
        "Zhuangkou"
    ],
    "name:zho_x_preferred":[
        "\u5e84\u53e3"
    ],
    "name:zho_x_variant":[
        "Chuang-k\u2019ou"
    ],
    "wof:name":"Zhuangkou",
    "wof:placetype":"locality"
},
  "geometry": {"coordinates":[121.07083,24.71],"type":"Point"}
}