{
  "type": "Feature",
  "properties": {
    "gn:admin1_code":"4.0",
    "gn:admin2_code":"TNN",
    "gn:admin3_code":"R29",
    "gn:admin4_code":"67000290014.0",
    "gn:asciiname":"Wanqi",
    "gn:country_code":"TW",
    "gn:dem":39,
    "gn:feature_class":"P",
    "gn:feature_code":"PPL",
    "gn:name":"Wanqi",
    "gn:population":0,
    "gn:timezone":"Asia/Taipei",
    "iso:country":"TW",
    "name:und_x_variant":[
        "Wanci",
        "Wanqi"
    ],
    "name:zho_x_preferred":[
        "\u7063\u5d0e"
    ],
    "name:zho_x_variant":[
        "Wan-ch\u2019i"
    ],
    "wof:name":"Wanqi",
    "wof:placetype":"locality"
},
  "geometry": {"coordinates":[120.36306,22.90333],"type":"Point"}
}