{
  "type": "Feature",
  "properties": {
    "gn:admin1_code":"04",
    "gn:admin2_code":"TXG",
    "gn:admin3_code":"B23",
    "gn:admin4_code":"66000230010.0",
    "gn:asciiname":"Wuguang",
    "gn:country_code":"TW",
    "gn:dem":33,
    "gn:feature_class":"P",
    "gn:feature_code":"PPL",
    "gn:name":"Wuguang",
    "gn:population":0,
    "gn:timezone":"Asia/Taipei",
    "iso:country":"TW",
    "name:und_x_variant":[
        "Wu-kuang-ts\u2019un",
        "\u4e94\u5149",
        "Wuguang",
        "Wu-kuang"
    ],
    "wof:name":"Wuguang",
    "wof:placetype":"locality"
},
  "geometry": {"coordinates":[120.646,24.09386],"type":"Point"}
}