{
  "type": "Feature",
  "properties": {
    "gn:admin1_code":"04",
    "gn:admin2_code":"MIA",
    "gn:admin3_code":"K14",
    "gn:admin4_code":"10005110008.0",
    "gn:asciiname":"Shenshe",
    "gn:country_code":"TW",
    "gn:dem":587,
    "gn:feature_class":"P",
    "gn:feature_code":"PPL",
    "gn:name":"Shenshe",
    "gn:population":0,
    "gn:timezone":"Asia/Taipei",
    "iso:country":"TW",
    "name:und_x_variant":[
        "Shen-she"
    ],
    "name:zho_x_preferred":[
        "\u795e\u793e"
    ],
    "wof:name":"Shenshe",
    "wof:placetype":"locality"
},
  "geometry": {"coordinates":[120.96760999999999,24.53385],"type":"Point"}
}