{
  "type": "Feature",
  "properties": {
    "gn:admin1_code":"4.0",
    "gn:admin2_code":"CYQ",
    "gn:admin3_code":"Q10",
    "gn:admin4_code":"10010100008.0",
    "gn:asciiname":"Qikuaicuo",
    "gn:country_code":"TW",
    "gn:dem":12,
    "gn:feature_class":"P",
    "gn:feature_code":"PPL",
    "gn:name":"Qikuaicuo",
    "gn:population":0,
    "gn:timezone":"Asia/Taipei",
    "iso:country":"TW",
    "name:und_x_variant":[
        "Cikuaicuo",
        "Qikuaicuo"
    ],
    "name:zho_x_preferred":[
        "\u4e03\u584a\u539d"
    ],
    "name:zho_x_variant":[
        "Ch\u2019i-k\u2019uai-ts\u2019o"
    ],
    "wof:name":"Qikuaicuo",
    "wof:placetype":"locality"
},
  "geometry": {"coordinates":[120.27861,23.36417],"type":"Point"}
}