{
  "type": "Feature",
  "properties": {
    "gn:admin1_code":"3.0",
    "gn:admin2_code":"TPQ",
    "gn:admin3_code":"F16",
    "gn:admin4_code":"65000080012.0",
    "gn:asciiname":"Erjiajiu",
    "gn:country_code":"TW",
    "gn:dem":62,
    "gn:feature_class":"P",
    "gn:feature_code":"PPL",
    "gn:name":"Erjiajiu",
    "gn:population":0,
    "gn:timezone":"Asia/Taipei",
    "iso:country":"TW",
    "name:und_x_variant":[
        "Erjiajiou",
        "Erh-chia-li",
        "Erjiajiu",
        "Erh-chia-chiu"
    ],
    "name:zho_x_preferred":[
        "\u4e8c\u7532\u4e5d"
    ],
    "wof:name":"Erjiajiu",
    "wof:placetype":"locality"
},
  "geometry": {"coordinates":[121.33731,24.93522],"type":"Point"}
}