{
  "type": "Feature",
  "properties": {
    "gn:admin1_code":"04",
    "gn:admin2_code":"TAO",
    "gn:admin3_code":"H06",
    "gn:admin4_code":"68000060015.0",
    "gn:asciiname":"Buding",
    "gn:country_code":"TW",
    "gn:dem":15,
    "gn:feature_class":"P",
    "gn:feature_code":"PPL",
    "gn:name":"Buding",
    "gn:population":0,
    "gn:timezone":"Asia/Taipei",
    "iso:country":"TW",
    "name:und_x_variant":[
        "Pu-shang",
        "Pu-ting"
    ],
    "name:zho_x_preferred":[
        "\u57d4\u9802"
    ],
    "wof:name":"Buding",
    "wof:placetype":"locality"
},
  "geometry": {"coordinates":[121.21510000000001,25.0835],"type":"Point"}
}