{
  "type": "Feature",
  "properties": {
    "gn:admin1_code":"4.0",
    "gn:admin2_code":"NAN",
    "gn:admin3_code":"M02",
    "gn:admin4_code":"10008020023.0",
    "gn:asciiname":"Tieguiwei",
    "gn:country_code":"TW",
    "gn:dem":605,
    "gn:feature_class":"P",
    "gn:feature_code":"PPL",
    "gn:name":"Tieguiwei",
    "gn:population":0,
    "gn:timezone":"Asia/Taipei",
    "iso:country":"TW",
    "name:und_x_variant":[
        "Tiegueiwei",
        "Tieguiwei"
    ],
    "name:zho_x_preferred":[
        "\u9435\u8ecc\u5c3e"
    ],
    "name:zho_x_variant":[
        "T\u2019ieh-kuei-wei"
    ],
    "wof:name":"Tieguiwei",
    "wof:placetype":"locality"
},
  "geometry": {"coordinates":[120.94723,24.04151],"type":"Point"}
}