{
  "type": "Feature",
  "properties": {
    "gn:admin1_code":"4.0",
    "gn:admin2_code":"NAN",
    "gn:admin3_code":"M12",
    "gn:admin4_code":"10008120006.0",
    "gn:asciiname":"Chufengling",
    "gn:country_code":"TW",
    "gn:dem":2024,
    "gn:feature_class":"P",
    "gn:feature_code":"PPL",
    "gn:name":"Chufengling",
    "gn:population":0,
    "gn:timezone":"Asia/Taipei",
    "iso:country":"TW",
    "name:und_x_variant":[
        "Chufongling",
        "Chufengling"
    ],
    "name:zho_x_preferred":[
        "\u521d\u9022\u5dba"
    ],
    "name:zho_x_variant":[
        "Ch\u2019u-feng-ling"
    ],
    "wof:name":"Chufengling",
    "wof:placetype":"locality"
},
  "geometry": {"coordinates":[120.82666999999999,23.62611],"type":"Point"}
}