{
  "type": "Feature",
  "properties": {
    "iso:country":"TW",
    "qs:name":"\u7fe0\u83ef\u6751",
    "qs:name_adm0":"\u81fa\u7063",
    "qs:name_adm1":"\u5357\u6295\u7e23",
    "qs:photos":2079,
    "qs:photos_1k":421,
    "qs:photos_9k":9,
    "qs:photos_9r":9,
    "qs:photos_all":2079,
    "qs:photos_sr":16,
    "qs:placetype":"Town",
    "qs:pop_sr":"0",
    "wof:name":"\u7fe0\u83ef\u6751",
    "wof:placetype":"locality"
},
  "geometry": {"coordinates":[121.231899,24.199843],"type":"Point"}
}