{
  "type": "Feature",
  "properties": {
    "gn:admin1_code":"4.0",
    "gn:admin2_code":"YUN",
    "gn:admin3_code":"P02",
    "gn:admin4_code":"10009020020.0",
    "gn:asciiname":"Gangqian",
    "gn:country_code":"TW",
    "gn:dem":27,
    "gn:feature_class":"P",
    "gn:feature_code":"PPL",
    "gn:name":"Gangqian",
    "gn:population":0,
    "gn:timezone":"Asia/Taipei",
    "iso:country":"TW",
    "name:und_x_variant":[
        "Gangcian",
        "Gangqian"
    ],
    "name:zho_x_preferred":[
        "Chiang-ch\u2019ien"
    ],
    "name:zho_x_variant":[
        "\u6e2f\u5898",
        "Kang-ch\u2019ien"
    ],
    "wof:name":"Gangqian",
    "wof:placetype":"locality"
},
  "geometry": {"coordinates":[120.43835,23.67305],"type":"Point"}
}