{
  "type": "Feature",
  "properties": {
    "iso:country":"TW",
    "qs:name":"\u4e09\u5149\u6751",
    "qs:name_adm0":"\u81fa\u7063",
    "qs:name_adm1":"\u6843\u5712\u7e23",
    "qs:photos":441,
    "qs:photos_1k":89,
    "qs:photos_9k":2,
    "qs:photos_9r":5,
    "qs:photos_all":441,
    "qs:photos_sr":6,
    "qs:placetype":"Town",
    "qs:pop_sr":"0",
    "wof:name":"\u4e09\u5149\u6751",
    "wof:placetype":"locality"
},
  "geometry": {"coordinates":[121.38482,24.679368],"type":"Point"}
}