{
  "type": "Feature",
  "properties": {
    "gn:admin1_code":"4.0",
    "gn:admin2_code":"TXG",
    "gn:admin3_code":"B23",
    "gn:admin4_code":"66000230006.0",
    "gn:asciiname":"Jiuzhangli",
    "gn:country_code":"TW",
    "gn:dem":43,
    "gn:feature_class":"P",
    "gn:feature_code":"PPL",
    "gn:name":"Jiuzhangli",
    "gn:population":0,
    "gn:timezone":"Asia/Taipei",
    "iso:country":"TW",
    "name:und_x_variant":[
        "Chiu-huai",
        "Chiu-te-ts\u2019un",
        "Chiu-huai-ts\u2019un",
        "\u4e5d\u5f35\u7282",
        "Jioujhangli",
        "Jiuzhangli",
        "Chiu-chang-li"
    ],
    "wof:name":"Jiuzhangli",
    "wof:placetype":"locality"
},
  "geometry": {"coordinates":[120.63986,24.10884],"type":"Point"}
}