{
  "type": "Feature",
  "properties": {
    "gn:admin1_code":"1.0",
    "gn:admin2_code":"KIN",
    "gn:admin3_code":"W02",
    "gn:admin4_code":"9020020008.0",
    "gn:asciiname":"Yingshan",
    "gn:country_code":"TW",
    "gn:dem":8,
    "gn:feature_class":"P",
    "gn:feature_code":"PPL",
    "gn:name":"Yingshan",
    "gn:population":0,
    "gn:timezone":"Asia/Taipei",
    "iso:country":"TW",
    "name:und_x_variant":[
        "Ying-shan",
        "\u71df\u5c71",
        "Yingshan"
    ],
    "wof:name":"Yingshan",
    "wof:placetype":"locality"
},
  "geometry": {"coordinates":[118.39621,24.49053],"type":"Point"}
}