{
  "type": "Feature",
  "properties": {
    "gn:admin1_code":"4.0",
    "gn:admin2_code":"TAO",
    "gn:admin3_code":"H05",
    "gn:admin4_code":"68000050030.0",
    "gn:asciiname":"Hedi",
    "gn:country_code":"TW",
    "gn:dem":59,
    "gn:feature_class":"P",
    "gn:feature_code":"PPL",
    "gn:name":"Hedi",
    "gn:population":0,
    "gn:timezone":"Asia/Taipei",
    "iso:country":"TW",
    "name:und_x_variant":[
        "Ho-ti"
    ],
    "name:zho_x_preferred":[
        "\u6cb3\u5e95"
    ],
    "wof:name":"Hedi",
    "wof:placetype":"locality"
},
  "geometry": {"coordinates":[121.28487,25.0424],"type":"Point"}
}