{
  "type": "Feature",
  "properties": {
    "gn:admin1_code":"04",
    "gn:admin2_code":"CHA",
    "gn:admin3_code":"N03",
    "gn:admin4_code":"10007030015.0",
    "gn:asciiname":"Xiashanliao",
    "gn:country_code":"TW",
    "gn:dem":12,
    "gn:feature_class":"P",
    "gn:feature_code":"PPL",
    "gn:name":"Xiashanliao",
    "gn:population":0,
    "gn:timezone":"Asia/Taipei",
    "iso:country":"TW",
    "name:und_x_variant":[
        "Shan-li",
        "Xiashanliao",
        "Siashanliao",
        "Shan-liao",
        "Hsia-shan-liao"
    ],
    "name:zho_x_preferred":[
        "\u4e0b\u5c71\u5bee"
    ],
    "wof:name":"Xiashanliao",
    "wof:placetype":"locality"
},
  "geometry": {"coordinates":[120.49806,24.10556],"type":"Point"}
}