{
  "type": "Feature",
  "properties": {
    "gn:admin1_code":"3.0",
    "gn:admin2_code":"TPQ",
    "gn:admin3_code":"F25",
    "gn:admin4_code":"65000270008.0",
    "gn:asciiname":"Kuishanhu",
    "gn:country_code":"TW",
    "gn:dem":197,
    "gn:feature_class":"P",
    "gn:feature_code":"PPL",
    "gn:name":"Kuishanhu",
    "gn:population":0,
    "gn:timezone":"Asia/Taipei",
    "iso:country":"TW",
    "name:und_x_variant":[
        "Kueishanhu",
        "Kuishanhu"
    ],
    "name:zho_x_preferred":[
        "\u8475\u6247\u6e56"
    ],
    "name:zho_x_variant":[
        "K\u2019uei-shan-hu"
    ],
    "wof:name":"Kuishanhu",
    "wof:placetype":"locality"
},
  "geometry": {"coordinates":[121.59573,25.22913],"type":"Point"}
}