{
  "type": "Feature",
  "properties": {
    "gn:admin1_code":"04",
    "gn:admin2_code":"ILA",
    "gn:admin3_code":"G03",
    "gn:admin4_code":"10002050013.0",
    "gn:asciiname":"Wunuan",
    "gn:country_code":"TW",
    "gn:dem":6,
    "gn:feature_class":"P",
    "gn:feature_code":"PPL",
    "gn:name":"Wunuan",
    "gn:population":0,
    "gn:timezone":"Asia/Taipei",
    "iso:country":"TW",
    "name:und_x_variant":[
        "Wu-nuan"
    ],
    "name:zho_x_preferred":[
        "\u6b66\u6696"
    ],
    "wof:name":"Wunuan",
    "wof:placetype":"locality"
},
  "geometry": {"coordinates":[121.77583,24.78944],"type":"Point"}
}