{
  "type": "Feature",
  "properties": {
    "iso:country":"TW",
    "qs:name":"\u4e2d\u6c55\u6751",
    "qs:name_adm0":"\u81fa\u7063",
    "qs:name_adm1":"\u9ad8\u96c4\u5e02",
    "qs:photos":8,
    "qs:photos_1k":2,
    "qs:photos_9k":1,
    "qs:photos_9r":1,
    "qs:photos_all":8,
    "qs:photos_sr":1,
    "qs:placetype":"Town",
    "qs:pop_sr":"0",
    "wof:name":"\u4e2d\u6c55\u6751",
    "wof:placetype":"locality"
},
  "geometry": {"coordinates":[120.406143,22.4866635],"type":"Point"}
}