{
  "type": "Feature",
  "properties": {
    "gn:country":"TW",
    "iso:country":"TW",
    "name:eng_x_preferred":[
        "Wanshou"
    ],
    "name:eng_x_variant":[
        "Wanshou Village"
    ],
    "name:zho_tw_x_preferred":[
        "\u842c\u58fd\u6751"
    ],
    "qs:name":"\u842c\u58fd\u6751",
    "qs:name_adm0":"\u81fa\u7063",
    "qs:name_adm1":"\u65b0\u5317\u5e02",
    "qs:photos":470,
    "qs:photos_1k":95,
    "qs:photos_9k":2,
    "qs:photos_9r":5,
    "qs:photos_all":470,
    "qs:photos_sr":7,
    "qs:placetype":"Town",
    "qs:pop_sr":"0",
    "wof:name":"Wanshou",
    "wof:placetype":"locality"
},
  "geometry": {"coordinates":[121.63427299999999,25.240727],"type":"Point"}
}