{
  "type": "Feature",
  "properties": {
    "iso:country":"TW",
    "name:deu_x_preferred":[
        "Luzhou"
    ],
    "name:eng_x_preferred":[
        "Luzhou District"
    ],
    "name:fra_x_preferred":[
        "Luzhou"
    ],
    "name:hak_x_preferred":[
        "L\u00f9-ch\u00fb-kh\u00ee"
    ],
    "name:hye_x_preferred":[
        "\u053c\u0578\u0582\u056a\u0578\u0578\u0582"
    ],
    "name:jpn_x_preferred":[
        "\u8606\u6d32\u533a"
    ],
    "name:kor_x_preferred":[
        "\ub8e8\uc800\uc6b0\uad6c"
    ],
    "name:lit_x_preferred":[
        "Lud\u017eou"
    ],
    "name:nan_x_preferred":[
        "L\u00f4\u0358-chiu-khu"
    ],
    "name:pol_x_preferred":[
        "Luzhou"
    ],
    "name:ukr_x_preferred":[
        "\u041b\u0443\u0447\u0436\u043e\u0443"
    ],
    "name:vie_x_preferred":[
        "L\u00f4 Ch\u00e2u"
    ],
    "name:war_x_preferred":[
        "Luzhou"
    ],
    "name:zho_x_preferred":[
        "\u958b\u5e73\u91cc"
    ],
    "name:zho_x_variant":[
        "\u8606\u6d32\u5340"
    ],
    "qs:name":"\u8606\u6d32\u5e02",
    "qs:name_adm0":"\u81fa\u7063",
    "qs:name_adm1":"\u65b0\u5317\u5e02",
    "qs:photos":2061,
    "qs:photos_1k":418,
    "qs:photos_9k":9,
    "qs:photos_9r":9,
    "qs:photos_all":2061,
    "qs:photos_sr":16,
    "qs:placetype":"Town",
    "qs:pop_sr":"0",
    "wd:wordcount":181,
    "wof:name":"\u8606\u6d32\u5e02",
    "wof:placetype":"locality"
},
  "geometry": {"coordinates":[121.4699,25.081653],"type":"Point"}
}