{
  "type": "Feature",
  "properties": {
    "iso:country":"TW",
    "qs:name":"\u8606\u6d32\u5e02",
    "qs:name_adm0":"\u81fa\u7063",
    "qs:name_adm1":"\u65b0\u5317\u5e02",
    "qs:photos":2061,
    "qs:photos_1k":418,
    "qs:photos_9k":9,
    "qs:photos_9r":9,
    "qs:photos_all":2061,
    "qs:photos_sr":16,
    "qs:placetype":"Town",
    "qs:pop_sr":"0",
    "wd:wordcount":181,
    "wof:name":"\u8606\u6d32\u5e02",
    "wof:placetype":"locality"
},
  "geometry": {"coordinates":[121.4699,25.081653],"type":"Point"}
}