{
  "type": "Feature",
  "properties": {
    "gn:admin1_code":"4.0",
    "gn:admin2_code":"NAN",
    "gn:admin3_code":"M12",
    "gn:admin4_code":"10008120007.0",
    "gn:asciiname":"Bishi",
    "gn:country_code":"TW",
    "gn:dem":660,
    "gn:feature_class":"P",
    "gn:feature_code":"PPL",
    "gn:name":"Bishi",
    "gn:population":0,
    "gn:timezone":"Asia/Taipei",
    "iso:country":"TW",
    "name:und_x_variant":[
        "Bishih",
        "Bishi",
        "Pi-shih"
    ],
    "name:zho_x_preferred":[
        "\u7b46\u77f3"
    ],
    "wof:name":"Bishi",
    "wof:placetype":"locality"
},
  "geometry": {"coordinates":[120.88361,23.64278],"type":"Point"}
}