{
  "type": "Feature",
  "properties": {
    "gn:admin1_code":"4.0",
    "gn:admin2_code":"MIA",
    "gn:admin3_code":"K18",
    "gn:admin4_code":"10005180002.0",
    "gn:asciiname":"Naoliaozhuang",
    "gn:country_code":"TW",
    "gn:dem":835,
    "gn:feature_class":"P",
    "gn:feature_code":"PPL",
    "gn:name":"Naoliaozhuang",
    "gn:population":0,
    "gn:timezone":"Asia/Taipei",
    "iso:country":"TW",
    "name:und_x_variant":[
        "Nao-hao-chuang",
        "Nao-liao-chuang",
        "Naoliaojhuang",
        "Naoliaozhuang"
    ],
    "name:zho_x_preferred":[
        "\u8166\u5bee\u838a"
    ],
    "wof:name":"Naoliaozhuang",
    "wof:placetype":"locality"
},
  "geometry": {"coordinates":[120.94398,24.45314],"type":"Point"}
}