{
  "type": "Feature",
  "properties": {
    "gn:admin1_code":"3.0",
    "gn:admin2_code":"TPQ",
    "gn:admin3_code":"F32",
    "gn:admin4_code":"65000230009.0",
    "gn:asciiname":"Jiushe",
    "gn:country_code":"TW",
    "gn:dem":34,
    "gn:feature_class":"P",
    "gn:feature_code":"PPL",
    "gn:name":"Jiushe",
    "gn:population":0,
    "gn:timezone":"Asia/Taipei",
    "iso:country":"TW",
    "name:und_x_variant":[
        "Jioushe",
        "Jiushe",
        "Chiu-she"
    ],
    "name:zho_x_preferred":[
        "\u820a\u793e"
    ],
    "wof:name":"Jiushe",
    "wof:placetype":"locality"
},
  "geometry": {"coordinates":[121.38903000000001,25.12815],"type":"Point"}
}