{
  "type": "Feature",
  "properties": {
    "gn:admin1_code":"03",
    "gn:admin2_code":"TPQ",
    "gn:admin3_code":"F23",
    "gn:admin4_code":"65000250006.0",
    "gn:asciiname":"Dingping",
    "gn:country_code":"TW",
    "gn:dem":75,
    "gn:feature_class":"P",
    "gn:feature_code":"PPL",
    "gn:name":"Dingping",
    "gn:population":0,
    "gn:timezone":"Asia/Taipei",
    "iso:country":"TW",
    "name:zho_x_preferred":[
        "\u9802\u576a"
    ],
    "name:zho_x_variant":[
        "Ting-p\u2019ing"
    ],
    "wof:name":"Dingping",
    "wof:placetype":"locality"
},
  "geometry": {"coordinates":[121.86192,25.04435],"type":"Point"}
}