{
  "type": "Feature",
  "properties": {
    "gn:admin1_code":"04",
    "gn:admin2_code":"MIA",
    "gn:admin3_code":"K07",
    "gn:admin4_code":"10005140005.0",
    "gn:asciiname":"Beikeng",
    "gn:country_code":"TW",
    "gn:dem":99,
    "gn:feature_class":"P",
    "gn:feature_code":"PPL",
    "gn:name":"Beikeng",
    "gn:population":0,
    "gn:timezone":"Asia/Taipei",
    "iso:country":"TW",
    "name:und_x_variant":[
        "Hsin-min",
        "Pei-k\u2019eng",
        "Beikeng"
    ],
    "wof:name":"Beikeng",
    "wof:placetype":"locality"
},
  "geometry": {"coordinates":[120.78333000000001,24.55],"type":"Point"}
}