{
  "type": "Feature",
  "properties": {
    "gn:admin1_code":"04",
    "gn:admin2_code":"CYQ",
    "gn:admin3_code":"Q08",
    "gn:admin4_code":"10010080001.0",
    "gn:asciiname":"Niubu",
    "gn:country_code":"TW",
    "gn:dem":11,
    "gn:feature_class":"P",
    "gn:feature_code":"PPL",
    "gn:name":"Niubu",
    "gn:population":0,
    "gn:timezone":"Asia/Taipei",
    "iso:country":"TW",
    "name:und_x_variant":[
        "Nioubu",
        "Niu-pu"
    ],
    "name:zho_x_preferred":[
        "\u725b\u57d4"
    ],
    "wof:name":"Niubu",
    "wof:placetype":"locality"
},
  "geometry": {"coordinates":[120.28943999999998,23.49583],"type":"Point"}
}