{
  "type": "Feature",
  "properties": {
    "gn:admin1_code":"4.0",
    "gn:admin2_code":"CYQ",
    "gn:admin3_code":"Q08",
    "gn:admin4_code":"10010080019.0",
    "gn:asciiname":"Houpoziqiao",
    "gn:country_code":"TW",
    "gn:dem":8,
    "gn:feature_class":"P",
    "gn:feature_code":"PPL",
    "gn:name":"Houpoziqiao",
    "gn:population":0,
    "gn:timezone":"Asia/Taipei",
    "iso:country":"TW",
    "name:und_x_variant":[
        "Houpozihciao",
        "Houpoziqiao"
    ],
    "name:zho_x_preferred":[
        "\u5f8c\u6734\u5b50\u6a4b"
    ],
    "name:zho_x_variant":[
        "Hou-p\u2019o-tzu-chiao",
        "Hou-p\u2019u-tzu-chiao",
        "Hou-p\u2019o-tzu-ch\u2019iao"
    ],
    "wof:name":"Houpoziqiao",
    "wof:placetype":"locality"
},
  "geometry": {"coordinates":[120.26656,23.51263],"type":"Point"}
}