{
  "type": "Feature",
  "properties": {
    "gn:admin1_code":"2.0",
    "gn:admin2_code":"KHH",
    "gn:admin3_code":"E21",
    "gn:admin4_code":"64000210003.0",
    "gn:asciiname":"Fangnan",
    "gn:country_code":"TW",
    "gn:dem":33,
    "gn:feature_class":"P",
    "gn:feature_code":"PPL",
    "gn:name":"Fangnan",
    "gn:population":0,
    "gn:timezone":"Asia/Taipei",
    "iso:country":"TW",
    "name:und_x_variant":[
        "Fang-nan-ts\u2019un",
        "Fang-nan",
        "Fangnan"
    ],
    "wof:name":"Fangnan",
    "wof:placetype":"locality"
},
  "geometry": {"coordinates":[120.34999999999999,22.78333],"type":"Point"}
}