{
  "type": "Feature",
  "properties": {
    "gn:admin1_code":"04",
    "gn:admin2_code":"TAO",
    "gn:admin3_code":"H12",
    "gn:admin4_code":"68000120011.0",
    "gn:asciiname":"Shuzijiao",
    "gn:country_code":"TW",
    "gn:dem":73,
    "gn:feature_class":"P",
    "gn:feature_code":"PPL",
    "gn:name":"Shuzijiao",
    "gn:population":0,
    "gn:timezone":"Asia/Taipei",
    "iso:country":"TW",
    "name:und_x_variant":[
        "Shuzihjiao",
        "Shuzijiao",
        "Shu-tzu-chiao"
    ],
    "name:zho_x_preferred":[
        "\u6a39\u4ed4\u811a"
    ],
    "wof:name":"Shuzijiao",
    "wof:placetype":"locality"
},
  "geometry": {"coordinates":[121.11225,24.99365],"type":"Point"}
}