{
  "type": "Feature",
  "properties": {
    "gn:admin1_code":"04",
    "gn:admin2_code":"PIF",
    "gn:admin3_code":"T22",
    "gn:admin4_code":"10013220007.0",
    "gn:asciiname":"Wansong",
    "gn:country_code":"TW",
    "gn:dem":39,
    "gn:feature_class":"P",
    "gn:feature_code":"PPL",
    "gn:name":"Wansong",
    "gn:population":0,
    "gn:timezone":"Asia/Taipei",
    "iso:country":"TW",
    "name:und_x_variant":[
        "Wan-sun",
        "Wan-sung-ts\u2019un",
        "Wan-sung",
        "Wansong"
    ],
    "wof:name":"Wansong",
    "wof:placetype":"locality"
},
  "geometry": {"coordinates":[120.36503,22.33958],"type":"Point"}
}