{
  "type": "Feature",
  "properties": {
    "gn:admin1_code":"04",
    "gn:admin2_code":"YUN",
    "gn:admin3_code":"P04",
    "gn:admin4_code":"10009040015.0",
    "gn:asciiname":"Buxin",
    "gn:country_code":"TW",
    "gn:dem":29,
    "gn:feature_class":"P",
    "gn:feature_code":"PPL",
    "gn:name":"Buxin",
    "gn:population":0,
    "gn:timezone":"Asia/Taipei",
    "iso:country":"TW",
    "name:und_x_variant":[
        "Busin",
        "Pu-hsin"
    ],
    "name:zho_x_preferred":[
        "\u57d4\u5fc3"
    ],
    "wof:name":"Buxin",
    "wof:placetype":"locality"
},
  "geometry": {"coordinates":[120.44076,23.79995],"type":"Point"}
}