{
  "type": "Feature",
  "properties": {
    "iso:country":"TW",
    "qs:name":"\u5149\u83ef\u6751",
    "qs:name_adm0":"\u81fa\u7063",
    "qs:name_adm1":"\u5609\u7fa9\u7e23",
    "qs:photos":77,
    "qs:photos_1k":16,
    "qs:photos_9k":1,
    "qs:photos_9r":3,
    "qs:photos_all":77,
    "qs:photos_sr":3,
    "qs:placetype":"Town",
    "qs:pop_sr":"0",
    "wof:name":"\u5149\u83ef\u6751",
    "wof:placetype":"locality"
},
  "geometry": {"coordinates":[120.66819700000001,23.473953],"type":"Point"}
}