{
  "type": "Feature",
  "properties": {
    "gn:admin1_code":"4.0",
    "gn:admin2_code":"HUA",
    "gn:admin3_code":"U02",
    "gn:admin4_code":"10015070003.0",
    "gn:asciiname":"Yuanbu",
    "gn:country_code":"TW",
    "gn:dem":118,
    "gn:feature_class":"P",
    "gn:feature_code":"PPL",
    "gn:name":"Yuanbu",
    "gn:population":0,
    "gn:timezone":"Asia/Taipei",
    "iso:country":"TW",
    "name:zho_x_preferred":[
        "\u5712\u57d4"
    ],
    "name:zho_x_variant":[
        "Y\u00fcan-pu"
    ],
    "wof:name":"Yuanbu",
    "wof:placetype":"locality"
},
  "geometry": {"coordinates":[121.43957,23.67549],"type":"Point"}
}