{
  "type": "Feature",
  "properties": {
    "gn:admin1_code":"2.0",
    "gn:admin2_code":"KHH",
    "gn:admin3_code":"E30",
    "gn:admin4_code":"64000300004.0",
    "gn:asciiname":"Pizidi",
    "gn:country_code":"TW",
    "gn:dem":64,
    "gn:feature_class":"P",
    "gn:feature_code":"PPL",
    "gn:name":"Pizidi",
    "gn:population":0,
    "gn:timezone":"Asia/Taipei",
    "iso:country":"TW",
    "name:und_x_variant":[
        "Pizihdi",
        "Pizidi"
    ],
    "name:zho_x_preferred":[
        "\u57e4\u5b50\u5e95"
    ],
    "name:zho_x_variant":[
        "P\u2019i-tzu-ti"
    ],
    "wof:name":"Pizidi",
    "wof:placetype":"locality"
},
  "geometry": {"coordinates":[120.4975,22.91833],"type":"Point"}
}