{
  "type": "Feature",
  "properties": {
    "gn:admin1_code":"3.0",
    "gn:admin2_code":"TPQ",
    "gn:admin3_code":"F07",
    "gn:admin4_code":"65000060056.0",
    "gn:asciiname":"Danankeng",
    "gn:country_code":"TW",
    "gn:dem":22,
    "gn:feature_class":"P",
    "gn:feature_code":"PPL",
    "gn:name":"Danankeng",
    "gn:population":0,
    "gn:timezone":"Asia/Taipei",
    "iso:country":"TW",
    "name:zho_x_preferred":[
        "\u5927\u6e73\u5751"
    ],
    "name:zho_x_variant":[
        "Ta-nan-k\u2019eng"
    ],
    "wof:name":"Danankeng",
    "wof:placetype":"locality"
},
  "geometry": {"coordinates":[121.51358999999999,24.97526],"type":"Point"}
}