{
  "type": "Feature",
  "properties": {
    "gn:admin1_code":"4.0",
    "gn:admin2_code":"YUN",
    "gn:admin3_code":"P07",
    "gn:admin4_code":"10009070008.0",
    "gn:asciiname":"Dingkexi",
    "gn:country_code":"TW",
    "gn:dem":559,
    "gn:feature_class":"P",
    "gn:feature_code":"PPL",
    "gn:name":"Dingkexi",
    "gn:population":0,
    "gn:timezone":"Asia/Taipei",
    "iso:country":"TW",
    "name:und_x_variant":[
        "Dingkesi"
    ],
    "name:zho_x_preferred":[
        "\u9802\u79d1\u6eaa"
    ],
    "name:zho_x_variant":[
        "Ting-k\u2019o-chiao",
        "Ting-k\u2019o-hsi"
    ],
    "wof:name":"Dingkexi",
    "wof:placetype":"locality"
},
  "geometry": {"coordinates":[120.59889,23.58861],"type":"Point"}
}