{
  "type": "Feature",
  "properties": {
    "gn:admin1_code":"04",
    "gn:admin2_code":"CHA",
    "gn:admin3_code":"N02",
    "gn:admin4_code":"10007020027.0",
    "gn:asciiname":"Shicuoliao",
    "gn:country_code":"TW",
    "gn:dem":9,
    "gn:feature_class":"P",
    "gn:feature_code":"PPL",
    "gn:name":"Shicuoliao",
    "gn:population":0,
    "gn:timezone":"Asia/Taipei",
    "iso:country":"TW",
    "name:und_x_variant":[
        "Shihcuoliao"
    ],
    "name:zho_x_preferred":[
        "\u65bd\u539d\u5bee"
    ],
    "name:zho_x_variant":[
        "Shih-ts\u2019o-liao"
    ],
    "wof:name":"Shicuoliao",
    "wof:placetype":"locality"
},
  "geometry": {"coordinates":[120.45528,24.07083],"type":"Point"}
}