{
  "type": "Feature",
  "properties": {
    "gn:admin1_code":"4.0",
    "gn:admin2_code":"TXG",
    "gn:admin3_code":"B10",
    "gn:admin4_code":"66000100022.0",
    "gn:asciiname":"Hengkeng",
    "gn:country_code":"TW",
    "gn:dem":416,
    "gn:feature_class":"P",
    "gn:feature_code":"PPL",
    "gn:name":"Hengkeng",
    "gn:population":0,
    "gn:timezone":"Asia/Taipei",
    "iso:country":"TW",
    "name:und_x_variant":[
        "Hengkeng"
    ],
    "name:zho_x_preferred":[
        "Heng-k\u2019eng"
    ],
    "name:zho_x_variant":[
        "\u6a6b\u5751"
    ],
    "wof:name":"Hengkeng",
    "wof:placetype":"locality"
},
  "geometry": {"coordinates":[120.80612000000001,24.2925],"type":"Point"}
}