{
  "type": "Feature",
  "properties": {
    "gn:admin1_code":"04",
    "gn:admin2_code":"MIA",
    "gn:admin3_code":"K06",
    "gn:admin4_code":"10005130001.0",
    "gn:asciiname":"Bagu",
    "gn:country_code":"TW",
    "gn:dem":294,
    "gn:feature_class":"P",
    "gn:feature_code":"PPL",
    "gn:name":"Bagu",
    "gn:population":0,
    "gn:timezone":"Asia/Taipei",
    "iso:country":"TW",
    "name:und_x_variant":[
        "Pa-ku"
    ],
    "name:zho_x_preferred":[
        "\u516b\u80a1"
    ],
    "wof:name":"Bagu",
    "wof:placetype":"locality"
},
  "geometry": {"coordinates":[120.76802000000001,24.40816],"type":"Point"}
}