{
  "type": "Feature",
  "properties": {
    "gn:admin1_code":"4.0",
    "gn:admin2_code":"MIA",
    "gn:admin3_code":"K01",
    "gn:admin4_code":"10005010007.0",
    "gn:asciiname":"Buwei",
    "gn:country_code":"TW",
    "gn:dem":51,
    "gn:feature_class":"P",
    "gn:feature_code":"PPL",
    "gn:name":"Buwei",
    "gn:population":0,
    "gn:timezone":"Asia/Taipei",
    "iso:country":"TW",
    "name:und_x_variant":[
        "Pu-wei"
    ],
    "name:zho_x_preferred":[
        "\u57d4\u5c3e"
    ],
    "wof:name":"Buwei",
    "wof:placetype":"locality"
},
  "geometry": {"coordinates":[120.82834,24.5546],"type":"Point"}
}