{
  "type": "Feature",
  "properties": {
    "gn:admin1_code":"04",
    "gn:admin2_code":"HUA",
    "gn:admin3_code":"U04",
    "gn:admin4_code":"10015040002.0",
    "gn:asciiname":"Beisanzhan",
    "gn:country_code":"TW",
    "gn:dem":17,
    "gn:feature_class":"P",
    "gn:feature_code":"PPL",
    "gn:name":"Beisanzhan",
    "gn:population":0,
    "gn:timezone":"Asia/Taipei",
    "iso:country":"TW",
    "name:und_x_variant":[
        "Beisanjhan",
        "Beisanzhan",
        "Pei-san-chan"
    ],
    "name:zho_x_preferred":[
        "\u5317\u4e09\u68e7"
    ],
    "wof:name":"Beisanzhan",
    "wof:placetype":"locality"
},
  "geometry": {"coordinates":[121.62041000000001,24.10531],"type":"Point"}
}