{
  "type": "Feature",
  "properties": {
    "gn:admin1_code":"03",
    "gn:admin2_code":"TPQ",
    "gn:admin3_code":"F08",
    "gn:admin4_code":"65000190011.0",
    "gn:asciiname":"Shuidiliao",
    "gn:country_code":"TW",
    "gn:dem":466,
    "gn:feature_class":"P",
    "gn:feature_code":"PPL",
    "gn:name":"Shuidiliao",
    "gn:population":0,
    "gn:timezone":"Asia/Taipei",
    "iso:country":"TW",
    "name:und_x_variant":[
        "Shueidiliao",
        "Shui-ti",
        "Shuidiliao",
        "Shui-ti-liao"
    ],
    "name:zho_x_preferred":[
        "Shui-ti-ts\u2019un"
    ],
    "name:zho_x_variant":[
        "\u6c34\u5e95\u5bee"
    ],
    "wof:name":"Shuidiliao",
    "wof:placetype":"locality"
},
  "geometry": {"coordinates":[121.6647,24.9459],"type":"Point"}
}