{
  "type": "Feature",
  "properties": {
    "gn:admin1_code":"03",
    "gn:admin2_code":"TPQ",
    "gn:admin3_code":"F32",
    "gn:admin4_code":"65000230003.0",
    "gn:asciiname":"Dakuhu",
    "gn:country_code":"TW",
    "gn:dem":108,
    "gn:feature_class":"P",
    "gn:feature_code":"PPL",
    "gn:name":"Dakuhu",
    "gn:population":0,
    "gn:timezone":"Asia/Taipei",
    "iso:country":"TW",
    "name:zho_x_preferred":[
        "\u5927\u5800\u6e56"
    ],
    "name:zho_x_variant":[
        "Ta-k\u2019u-hu"
    ],
    "wof:name":"Dakuhu",
    "wof:placetype":"locality"
},
  "geometry": {"coordinates":[121.42397,25.14989],"type":"Point"}
}