{
  "type": "Feature",
  "properties": {
    "iso:country":"TW",
    "name:eng_x_preferred":[
        "Hushan"
    ],
    "name:eng_x_variant":[
        "Hushan Village"
    ],
    "name:zho_tw_x_preferred":[
        "\u6e56\u5c71\u6751"
    ],
    "qs:name":"\u6e56\u5c71\u6751",
    "qs:name_adm0":"\u81fa\u7063",
    "qs:name_adm1":"\u53f0\u5357\u5e02",
    "qs:photos":78,
    "qs:photos_1k":16,
    "qs:photos_9k":1,
    "qs:photos_9r":3,
    "qs:photos_all":78,
    "qs:photos_sr":3,
    "qs:placetype":"Town",
    "qs:pop_sr":"0",
    "wof:name":"Hushan",
    "wof:placetype":"locality"
},
  "geometry": {"coordinates":[120.351963,23.211373],"type":"Point"}
}