{
  "type": "Feature",
  "properties": {
    "gn:admin1_code":"04",
    "gn:admin2_code":"CYQ",
    "gn:admin3_code":"Q06",
    "gn:admin4_code":"10010060008.0",
    "gn:asciiname":"Tianshe",
    "gn:country_code":"TW",
    "gn:dem":18,
    "gn:feature_class":"P",
    "gn:feature_code":"PPL",
    "gn:name":"Tianshe",
    "gn:population":0,
    "gn:timezone":"Asia/Taipei",
    "iso:country":"TW",
    "name:zho_x_preferred":[
        "T\u2019ien-ao"
    ],
    "name:zho_x_variant":[
        "\u5929\u8d66",
        "T\u2019ien-she"
    ],
    "wof:name":"Tianshe",
    "wof:placetype":"locality"
},
  "geometry": {"coordinates":[120.37512,23.58578],"type":"Point"}
}