{
  "type": "Feature",
  "properties": {
    "gn:admin1_code":"4.0",
    "gn:admin2_code":"YUN",
    "gn:admin3_code":"P19",
    "gn:admin4_code":"10009190017.0",
    "gn:asciiname":"Zhonggangzi",
    "gn:country_code":"TW",
    "gn:dem":2,
    "gn:feature_class":"P",
    "gn:feature_code":"PPL",
    "gn:name":"Zhonggangzi",
    "gn:population":0,
    "gn:timezone":"Asia/Taipei",
    "iso:country":"TW",
    "name:und_x_variant":[
        "Jhonggangzih",
        "Zhonggangzi",
        "Chung-kang-tzu"
    ],
    "name:zho_x_preferred":[
        "\u4e2d\u6e2f\u4ed4"
    ],
    "wof:name":"Zhonggangzi",
    "wof:placetype":"locality"
},
  "geometry": {"coordinates":[120.18194,23.51806],"type":"Point"}
}