{
  "type": "Feature",
  "properties": {
    "gn:admin1_code":"3.0",
    "gn:admin2_code":"TPQ",
    "gn:admin3_code":"F22",
    "gn:admin4_code":"65000240009.0",
    "gn:asciiname":"Erxiekeng",
    "gn:country_code":"TW",
    "gn:dem":231,
    "gn:feature_class":"P",
    "gn:feature_code":"PPL",
    "gn:name":"Erxiekeng",
    "gn:population":0,
    "gn:timezone":"Asia/Taipei",
    "iso:country":"TW",
    "name:und_x_variant":[
        "Ersiekeng"
    ],
    "name:zho_x_preferred":[
        "\u4e8c\u659c\u5751"
    ],
    "name:zho_x_variant":[
        "Erh-hsieh-k\u2019eng"
    ],
    "wof:name":"Erxiekeng",
    "wof:placetype":"locality"
},
  "geometry": {"coordinates":[121.7801,25.03],"type":"Point"}
}