{
  "type": "Feature",
  "properties": {
    "gn:admin1_code":"4.0",
    "gn:admin2_code":"HSZ",
    "gn:admin3_code":"J05",
    "gn:admin4_code":"10004010018.0",
    "gn:asciiname":"Kanzijiao",
    "gn:country_code":"TW",
    "gn:dem":7,
    "gn:feature_class":"P",
    "gn:feature_code":"PPL",
    "gn:name":"Kanzijiao",
    "gn:population":0,
    "gn:timezone":"Asia/Taipei",
    "iso:country":"TW",
    "name:und_x_variant":[
        "Kanzihjiao"
    ],
    "name:zho_x_preferred":[
        "\u5d01\u5b50\u811a"
    ],
    "name:zho_x_variant":[
        "K\u2019an-tzu-chiao"
    ],
    "wof:name":"Kanzijiao",
    "wof:placetype":"locality"
},
  "geometry": {"coordinates":[120.94833,24.86056],"type":"Point"}
}