{
  "type": "Feature",
  "properties": {
    "gn:admin1_code":"4.0",
    "gn:admin2_code":"PIF",
    "gn:admin3_code":"T18",
    "gn:admin4_code":"10013180008.0",
    "gn:asciiname":"Zhuweizi",
    "gn:country_code":"TW",
    "gn:dem":5,
    "gn:feature_class":"P",
    "gn:feature_code":"PPL",
    "gn:name":"Zhuweizi",
    "gn:population":0,
    "gn:timezone":"Asia/Taipei",
    "iso:country":"TW",
    "name:und_x_variant":[
        "Chu-wei-tzu",
        "\u7af9\u570d\u5b50",
        "Jhuweizih",
        "Zhuweizi"
    ],
    "name:zho_x_preferred":[
        "Kang-tung-ts\u2019un"
    ],
    "name:zho_x_variant":[
        "\u7af9\u570d\u5b50"
    ],
    "wof:name":"Zhuweizi",
    "wof:placetype":"locality"
},
  "geometry": {"coordinates":[120.47512,22.50258],"type":"Point"}
}