{
  "type": "Feature",
  "properties": {
    "gn:admin1_code":"3.0",
    "gn:admin2_code":"TPQ",
    "gn:admin3_code":"F30",
    "gn:admin4_code":"65000210008.0",
    "gn:asciiname":"Fanpolin",
    "gn:country_code":"TW",
    "gn:dem":84,
    "gn:feature_class":"P",
    "gn:feature_code":"PPL",
    "gn:name":"Fanpolin",
    "gn:population":0,
    "gn:timezone":"Asia/Taipei",
    "iso:country":"TW",
    "name:und_x_variant":[
        "Fan-tzu-lin",
        "Fanpolin"
    ],
    "name:zho_x_preferred":[
        "\u756a\u5a46\u6797"
    ],
    "name:zho_x_variant":[
        "Fan-p\u2019o-lin"
    ],
    "wof:name":"Fanpolin",
    "wof:placetype":"locality"
},
  "geometry": {"coordinates":[121.49476,25.24002],"type":"Point"}
}