{
  "type": "Feature",
  "properties": {
    "gn:admin1_code":"04",
    "gn:admin2_code":"YUN",
    "gn:admin3_code":"P09",
    "gn:admin4_code":"10009090013.0",
    "gn:asciiname":"Hunei",
    "gn:country_code":"TW",
    "gn:dem":60,
    "gn:feature_class":"P",
    "gn:feature_code":"PPL",
    "gn:name":"Hunei",
    "gn:population":0,
    "gn:timezone":"Asia/Taipei",
    "iso:country":"TW",
    "name:und_x_variant":[
        "Hu-tzu-nei",
        "Wu-hua",
        "Hunei",
        "Hu-nei"
    ],
    "name:zho_x_preferred":[
        "\u6e56\u5167"
    ],
    "wof:name":"Hunei",
    "wof:placetype":"locality"
},
  "geometry": {"coordinates":[120.563,23.7783],"type":"Point"}
}