{
  "type": "Feature",
  "properties": {
    "gn:admin1_code":"04",
    "gn:admin2_code":"MIA",
    "gn:admin3_code":"K03",
    "gn:admin4_code":"10005030014.0",
    "gn:asciiname":"Neihu",
    "gn:country_code":"TW",
    "gn:dem":31,
    "gn:feature_class":"P",
    "gn:feature_code":"PPL",
    "gn:name":"Neihu",
    "gn:population":0,
    "gn:timezone":"Asia/Taipei",
    "iso:country":"TW",
    "name:und_x_variant":[
        "Nei-hu"
    ],
    "name:zho_x_preferred":[
        "\u5167\u6e56"
    ],
    "wof:name":"Neihu",
    "wof:placetype":"locality"
},
  "geometry": {"coordinates":[120.71099,24.49958],"type":"Point"}
}