{
  "type": "Feature",
  "properties": {
    "gn:admin1_code":"04",
    "gn:admin2_code":"CYQ",
    "gn:admin3_code":"Q10",
    "gn:admin4_code":"10010100009.0",
    "gn:asciiname":"Pizitou",
    "gn:country_code":"TW",
    "gn:dem":8,
    "gn:feature_class":"P",
    "gn:feature_code":"PPL",
    "gn:name":"Pizitou",
    "gn:population":0,
    "gn:timezone":"Asia/Taipei",
    "iso:country":"TW",
    "name:und_x_variant":[
        "Pizihtou"
    ],
    "name:zho_x_preferred":[
        "\u57e4\u5b50\u982d"
    ],
    "name:zho_x_variant":[
        "P\u2019i-ch\u2019ien-ts\u2019un",
        "P\u2019i-tzu-t\u2019ou"
    ],
    "wof:name":"Pizitou",
    "wof:placetype":"locality"
},
  "geometry": {"coordinates":[120.22405000000001,23.34542],"type":"Point"}
}