{
  "type": "Feature",
  "properties": {
    "iso:country":"TW",
    "name:eng_x_preferred":[
        "Dapu"
    ],
    "name:eng_x_variant":[
        "Dapu Village"
    ],
    "name:zho_tw_x_preferred":[
        "\u5927\u57d4\u6751"
    ],
    "qs:name":"\u5927\u57d4\u6751",
    "qs:name_adm0":"\u81fa\u7063",
    "qs:name_adm1":"\u53f0\u6771\u7e23",
    "qs:photos":10,
    "qs:photos_1k":2,
    "qs:photos_9k":1,
    "qs:photos_9r":1,
    "qs:photos_all":10,
    "qs:photos_sr":1,
    "qs:placetype":"Town",
    "qs:pop_sr":"0",
    "wof:name":"Dapu",
    "wof:placetype":"locality"
},
  "geometry": {"coordinates":[121.193832,23.128704],"type":"Point"}
}