{
  "type": "Feature",
  "properties": {
    "gn:admin1_code":"3.0",
    "gn:admin2_code":"TPQ",
    "gn:admin3_code":"F07",
    "gn:admin4_code":"65000060017.0",
    "gn:asciiname":"Datiekeng",
    "gn:country_code":"TW",
    "gn:dem":84,
    "gn:feature_class":"P",
    "gn:feature_code":"PPL",
    "gn:name":"Datiekeng",
    "gn:population":0,
    "gn:timezone":"Asia/Taipei",
    "iso:country":"TW",
    "name:zho_x_preferred":[
        "\u6253\u9435\u5751"
    ],
    "name:zho_x_variant":[
        "Ta-t\u2019ieh-k\u2019eng"
    ],
    "wof:name":"Datiekeng",
    "wof:placetype":"locality"
},
  "geometry": {"coordinates":[121.50526000000001,24.96301],"type":"Point"}
}