{
  "type": "Feature",
  "properties": {
    "gn:admin1_code":"4.0",
    "gn:admin2_code":"CYQ",
    "gn:admin3_code":"Q15",
    "gn:admin4_code":"10010140013.0",
    "gn:asciiname":"Daoziliao",
    "gn:country_code":"TW",
    "gn:dem":528,
    "gn:feature_class":"P",
    "gn:feature_code":"PPL",
    "gn:name":"Daoziliao",
    "gn:population":0,
    "gn:timezone":"Asia/Taipei",
    "iso:country":"TW",
    "name:und_x_variant":[
        "Daozihliao",
        "Daoziliao",
        "Tao-tzu-liao"
    ],
    "name:zho_x_preferred":[
        "\u7a3b\u4ed4\u5bee"
    ],
    "wof:name":"Daoziliao",
    "wof:placetype":"locality"
},
  "geometry": {"coordinates":[120.60115999999999,23.49305],"type":"Point"}
}