{
  "type": "Feature",
  "properties": {
    "gn:admin1_code":"4.0",
    "gn:admin2_code":"TTT",
    "gn:admin3_code":"V06",
    "gn:admin4_code":"10014090004.0",
    "gn:asciiname":"Senchuan",
    "gn:country_code":"TW",
    "gn:dem":776,
    "gn:feature_class":"P",
    "gn:feature_code":"PPL",
    "gn:name":"Senchuan",
    "gn:population":0,
    "gn:timezone":"Asia/Taipei",
    "iso:country":"TW",
    "name:und_x_variant":[
        "Sen-shan"
    ],
    "name:zho_x_preferred":[
        "\u68ee\u5ddd"
    ],
    "name:zho_x_variant":[
        "Sen-ch\u2019uan"
    ],
    "wof:name":"Senchuan",
    "wof:placetype":"locality"
},
  "geometry": {"coordinates":[120.99333,22.6625],"type":"Point"}
}