{
  "type": "Feature",
  "properties": {
    "gn:admin1_code":"4.0",
    "gn:admin2_code":"CHA",
    "gn:admin3_code":"N22",
    "gn:admin4_code":"10007220001.0",
    "gn:asciiname":"Qihao",
    "gn:country_code":"TW",
    "gn:dem":26,
    "gn:feature_class":"P",
    "gn:feature_code":"PPL",
    "gn:name":"Qihao",
    "gn:population":0,
    "gn:timezone":"Asia/Taipei",
    "iso:country":"TW",
    "name:und_x_variant":[
        "Cihao",
        "Qihao"
    ],
    "name:zho_x_preferred":[
        "\u4e03\u865f"
    ],
    "name:zho_x_variant":[
        "Ch\u2019i-hao"
    ],
    "wof:name":"Qihao",
    "wof:placetype":"locality"
},
  "geometry": {"coordinates":[120.49093000000001,23.89432],"type":"Point"}
}