{
  "type": "Feature",
  "properties": {
    "gn:admin1_code":"4.0",
    "gn:admin2_code":"CHA",
    "gn:admin3_code":"N15",
    "gn:admin4_code":"10007130012.0",
    "gn:asciiname":"Daqiaotou",
    "gn:country_code":"TW",
    "gn:dem":22,
    "gn:feature_class":"P",
    "gn:feature_code":"PPL",
    "gn:name":"Daqiaotou",
    "gn:population":0,
    "gn:timezone":"Asia/Taipei",
    "iso:country":"TW",
    "name:und_x_variant":[
        "Daciaotou",
        "Daqiaotou"
    ],
    "name:zho_x_preferred":[
        "\u5927\u6a4b\u982d"
    ],
    "name:zho_x_variant":[
        "Ta-ch\u2019iao-t\u2019ou"
    ],
    "wof:name":"Daqiaotou",
    "wof:placetype":"locality"
},
  "geometry": {"coordinates":[120.55629999999999,24.0006],"type":"Point"}
}