{
  "type": "Feature",
  "properties": {
    "gn:admin1_code":"04",
    "gn:admin2_code":"MIA",
    "gn:admin3_code":"K07",
    "gn:admin4_code":"10005140008.0",
    "gn:asciiname":"Dawo",
    "gn:country_code":"TW",
    "gn:dem":83,
    "gn:feature_class":"P",
    "gn:feature_code":"PPL",
    "gn:name":"Dawo",
    "gn:population":0,
    "gn:timezone":"Asia/Taipei",
    "iso:country":"TW",
    "name:und_x_variant":[
        "Ta-wo"
    ],
    "name:zho_x_preferred":[
        "\u5927\u7aa9"
    ],
    "wof:name":"Dawo",
    "wof:placetype":"locality"
},
  "geometry": {"coordinates":[120.77016999999999,24.57196],"type":"Point"}
}