{
  "type": "Feature",
  "properties": {
    "gn:admin1_code":"04",
    "gn:admin2_code":"MIA",
    "gn:admin3_code":"K15",
    "gn:admin4_code":"10005080001.0",
    "gn:asciiname":"Dahu",
    "gn:country_code":"TW",
    "gn:dem":283,
    "gn:feature_class":"P",
    "gn:feature_code":"PPL",
    "gn:name":"Dahu",
    "gn:population":0,
    "gn:timezone":"Asia/Taipei",
    "iso:country":"TW",
    "name:hak_x_preferred":[
        "Thai-f\u00f9-hi\u00f4ng"
    ],
    "name:jpn_x_preferred":[
        "\u5927\u6e56\u90f7"
    ],
    "name:kor_x_preferred":[
        "\ub2e4\ud6c4\ud5a5"
    ],
    "name:und_x_variant":[
        "Ta-hu-chuang",
        "Dahu",
        "Ma-ao",
        "Ta-hu"
    ],
    "name:vie_x_preferred":[
        "\u0110\u1ea1i H\u1ed3"
    ],
    "name:zho_x_preferred":[
        "\u5927\u6e56"
    ],
    "name:zho_x_variant":[
        "\u5927\u6e56\u9109"
    ],
    "wof:name":"Dahu",
    "wof:placetype":"locality"
},
  "geometry": {"coordinates":[120.86756,24.42364],"type":"Point"}
}