{
  "type": "Feature",
  "properties": {
    "gn:admin1_code":"01",
    "gn:admin2_code":"KIN",
    "gn:admin3_code":"W02",
    "gn:admin4_code":"9020020001.0",
    "gn:asciiname":"Shamei",
    "gn:country_code":"TW",
    "gn:dem":13,
    "gn:feature_class":"P",
    "gn:feature_code":"PPL",
    "gn:name":"Shamei",
    "gn:population":0,
    "gn:timezone":"Asia/Taipei",
    "iso:country":"TW",
    "name:und_x_variant":[
        "Sha-mei",
        "\u6c99\u7f8e",
        "Chin-sha",
        "Shamei"
    ],
    "wof:name":"Shamei",
    "wof:placetype":"locality"
},
  "geometry": {"coordinates":[118.41292,24.49171],"type":"Point"}
}