{
  "type": "Feature",
  "properties": {
    "gn:admin1_code":"04",
    "gn:admin2_code":"PIF",
    "gn:admin3_code":"T05",
    "gn:admin4_code":"10013050008.0",
    "gn:asciiname":"Dingxinzhuangzi",
    "gn:country_code":"TW",
    "gn:dem":17,
    "gn:feature_class":"P",
    "gn:feature_code":"PPL",
    "gn:name":"Dingxinzhuangzi",
    "gn:population":0,
    "gn:timezone":"Asia/Taipei",
    "iso:country":"TW",
    "name:und_x_variant":[
        "Ting-hsin-chuang-tzu",
        "Ting-hdis-chung-tzu",
        "Dingxinzhuangzi",
        "Dingsinjhuangzih"
    ],
    "name:zho_x_preferred":[
        "\u9802\u65b0\u838a\u4ed4"
    ],
    "wof:name":"Dingxinzhuangzi",
    "wof:placetype":"locality"
},
  "geometry": {"coordinates":[120.50171,22.61674],"type":"Point"}
}