{
  "type": "Feature",
  "properties": {
    "gn:admin1_code":"4.0",
    "gn:admin2_code":"CYQ",
    "gn:admin3_code":"Q18",
    "gn:admin4_code":"10010170005.0",
    "gn:asciiname":"Sanchongxibu",
    "gn:country_code":"TW",
    "gn:dem":453,
    "gn:feature_class":"P",
    "gn:feature_code":"PPL",
    "gn:name":"Sanchongxibu",
    "gn:population":0,
    "gn:timezone":"Asia/Taipei",
    "iso:country":"TW",
    "name:und_x_variant":[
        "Sanchongsibu",
        "Sanchongxibu"
    ],
    "name:zho_x_preferred":[
        "\u4e09\u91cd\u6eaa\u57d4"
    ],
    "name:zho_x_variant":[
        "San-ch\u2019ung-hsi-pu"
    ],
    "wof:name":"Sanchongxibu",
    "wof:placetype":"locality"
},
  "geometry": {"coordinates":[120.58356000000001,23.26003],"type":"Point"}
}