{
  "type": "Feature",
  "properties": {
    "gn:admin1_code":"04",
    "gn:admin2_code":"NAN",
    "gn:admin3_code":"M13",
    "gn:admin4_code":"10008130009.0",
    "gn:asciiname":"Bihu",
    "gn:country_code":"TW",
    "gn:dem":1189,
    "gn:feature_class":"P",
    "gn:feature_code":"PPL",
    "gn:name":"Bihu",
    "gn:population":0,
    "gn:timezone":"Asia/Taipei",
    "iso:country":"TW",
    "name:asm_x_preferred":[
        "\u09ac\u09bf\u09b9\u09c1"
    ],
    "name:ben_x_preferred":[
        "\u09ac\u09bf\u09b9\u09c1"
    ],
    "name:bih_x_preferred":[
        "\u092c\u093f\u0939\u0942"
    ],
    "name:bpy_x_preferred":[
        "\u09ac\u09bf\u09b9\u09c1"
    ],
    "name:fin_x_preferred":[
        "Bihu"
    ],
    "name:fra_x_preferred":[
        "Bihu"
    ],
    "name:hin_x_preferred":[
        "\u092c\u093f\u0939\u0941 \u0924\u094d\u092f\u094b\u0939\u093e\u0930"
    ],
    "name:kan_x_preferred":[
        "\u0cac\u0cbf\u0cb9\u0cc1"
    ],
    "name:mal_x_preferred":[
        "\u0d2c\u0d3f\u0d39\u0d41"
    ],
    "name:mar_x_preferred":[
        "\u092c\u093f\u0939\u0942"
    ],
    "name:nno_x_preferred":[
        "Bihu"
    ],
    "name:ori_x_preferred":[
        "\u0b2c\u0b3f\u0b39\u0b41 \u0b2a\u0b30\u0b4d\u0b2c"
    ],
    "name:sat_x_preferred":[
        "\u1c75\u1c64\u1c66\u1c69"
    ],
    "name:tam_x_preferred":[
        "\u0baa\u0bbf\u0bb9\u0bc1"
    ],
    "name:tel_x_preferred":[
        "\u0c2c\u0c3f\u0c39\u0c42 \u0c28\u0c43\u0c24\u0c4d\u0c2f\u0c02"
    ],
    "name:und_x_variant":[
        "Pi-hu"
    ],
    "name:zho_x_preferred":[
        "\u78a7\u6e56"
    ],
    "wof:name":"Bihu",
    "wof:placetype":"locality"
},
  "geometry": {"coordinates":[121.13583,24.02528],"type":"Point"}
}