{
  "type": "Feature",
  "properties": {
    "gn:admin1_code":"04",
    "gn:admin2_code":"NAN",
    "gn:admin3_code":"M13",
    "gn:admin4_code":"10008130009.0",
    "gn:asciiname":"Bihu",
    "gn:country_code":"TW",
    "gn:dem":1189,
    "gn:feature_class":"P",
    "gn:feature_code":"PPL",
    "gn:name":"Bihu",
    "gn:population":0,
    "gn:timezone":"Asia/Taipei",
    "iso:country":"TW",
    "name:und_x_variant":[
        "Pi-hu"
    ],
    "name:zho_x_preferred":[
        "\u78a7\u6e56"
    ],
    "wof:name":"Bihu",
    "wof:placetype":"locality"
},
  "geometry": {"coordinates":[121.13583,24.02528],"type":"Point"}
}