{
  "type": "Feature",
  "properties": {
    "gn:admin1_code":"2.0",
    "gn:admin2_code":"KHH",
    "gn:admin3_code":"E34",
    "gn:admin4_code":"64000340007.0",
    "gn:asciiname":"Zhuwei",
    "gn:country_code":"TW",
    "gn:dem":89,
    "gn:feature_class":"P",
    "gn:feature_code":"PPL",
    "gn:name":"Zhuwei",
    "gn:population":0,
    "gn:timezone":"Asia/Taipei",
    "iso:country":"TW",
    "name:und_x_variant":[
        "Jhuwei",
        "Chu-wei"
    ],
    "name:zho_x_preferred":[
        "\u7af9\u570d"
    ],
    "wof:name":"Zhuwei",
    "wof:placetype":"locality"
},
  "geometry": {"coordinates":[120.53438,22.9401],"type":"Point"}
}