{
  "type": "Feature",
  "properties": {
    "gn:admin1_code":"4.0",
    "gn:admin2_code":"HSZ",
    "gn:admin3_code":"J09",
    "gn:admin4_code":"10004060004.0",
    "gn:asciiname":"Licuo",
    "gn:country_code":"TW",
    "gn:dem":17,
    "gn:feature_class":"P",
    "gn:feature_code":"PPL",
    "gn:name":"Licuo",
    "gn:population":0,
    "gn:timezone":"Asia/Taipei",
    "iso:country":"TW",
    "name:zho_x_preferred":[
        "\u674e\u539d"
    ],
    "name:zho_x_variant":[
        "Li-ts\u2019o"
    ],
    "wof:name":"Licuo",
    "wof:placetype":"locality"
},
  "geometry": {"coordinates":[120.98444000000001,24.92472],"type":"Point"}
}