{
  "type": "Feature",
  "properties": {
    "gn:admin1_code":"4.0",
    "gn:admin2_code":"TXG",
    "gn:admin3_code":"B15",
    "gn:admin4_code":"66000150001.0",
    "gn:asciiname":"Machang",
    "gn:country_code":"TW",
    "gn:dem":271,
    "gn:feature_class":"P",
    "gn:feature_code":"PPL",
    "gn:name":"Machang",
    "gn:population":0,
    "gn:timezone":"Asia/Taipei",
    "iso:country":"TW",
    "name:ceb_x_preferred":[
        "Machang"
    ],
    "name:deu_x_preferred":[
        "Machang"
    ],
    "name:nld_x_preferred":[
        "Machang"
    ],
    "name:nor_x_preferred":[
        "Machang"
    ],
    "name:swe_x_preferred":[
        "Machang"
    ],
    "name:vie_x_preferred":[
        "Machang"
    ],
    "name:zho_x_preferred":[
        "\u99ac\u5834"
    ],
    "name:zho_x_variant":[
        "Ma-ch\u2019ang",
        "\u9a6c\u5382\u9547"
    ],
    "wof:name":"Machang",
    "wof:placetype":"locality"
},
  "geometry": {"coordinates":[120.7375,24.30222],"type":"Point"}
}