{
  "type": "Feature",
  "properties": {
    "gn:admin1_code":"04",
    "gn:admin2_code":"TPE",
    "gn:admin3_code":"A15",
    "gn:admin4_code":"63000110036.0",
    "gn:asciiname":"Yuchouhu",
    "gn:country_code":"TW",
    "gn:dem":20,
    "gn:feature_class":"P",
    "gn:feature_code":"PPL",
    "gn:name":"Yuchouhu",
    "gn:population":0,
    "gn:timezone":"Asia/Taipei",
    "iso:country":"TW",
    "name:und_x_variant":[
        "Y\u00fc-ch\u2019ou-hu"
    ],
    "wof:name":"Yuchouhu",
    "wof:placetype":"locality"
},
  "geometry": {"coordinates":[121.53333000000001,25.11667000000001],"type":"Point"}
}