{
  "type": "Feature",
  "properties": {
    "gn:admin1_code":"04",
    "gn:admin2_code":"TTT",
    "gn:admin3_code":"V07",
    "gn:admin4_code":"10014070007.0",
    "gn:asciiname":"Najie",
    "gn:country_code":"TW",
    "gn:dem":378,
    "gn:feature_class":"P",
    "gn:feature_code":"PPL",
    "gn:name":"Najie",
    "gn:population":0,
    "gn:timezone":"Asia/Taipei",
    "iso:country":"TW",
    "name:und_x_variant":[
        "Na-chieh"
    ],
    "name:zho_x_preferred":[
        "Ch\u2019\u00fcn-chieh"
    ],
    "name:zho_x_variant":[
        "\u90a3\u754c"
    ],
    "wof:name":"Najie",
    "wof:placetype":"locality"
},
  "geometry": {"coordinates":[121.19007000000001,22.87955],"type":"Point"}
}