{
  "type": "Feature",
  "properties": {
    "gn:admin1_code":"4.0",
    "gn:admin2_code":"TNN",
    "gn:admin3_code":"R16",
    "gn:admin4_code":"67000170009.0",
    "gn:asciiname":"Huiyaogang",
    "gn:country_code":"TW",
    "gn:dem":5,
    "gn:feature_class":"P",
    "gn:feature_code":"PPL",
    "gn:name":"Huiyaogang",
    "gn:population":0,
    "gn:timezone":"Asia/Taipei",
    "iso:country":"TW",
    "name:und_x_variant":[
        "Hueiyaogang",
        "Hui-yao-kang"
    ],
    "name:zho_x_preferred":[
        "\u7070\u78d8\u6e2f"
    ],
    "wof:name":"Huiyaogang",
    "wof:placetype":"locality"
},
  "geometry": {"coordinates":[120.13854000000001,23.26296],"type":"Point"}
}