{
  "type": "Feature",
  "properties": {
    "gn:admin1_code":"4.0",
    "gn:admin2_code":"HSZ",
    "gn:admin3_code":"J11",
    "gn:admin4_code":"10004100004.0",
    "gn:asciiname":"Ganziqi",
    "gn:country_code":"TW",
    "gn:dem":42,
    "gn:feature_class":"P",
    "gn:feature_code":"PPL",
    "gn:name":"Ganziqi",
    "gn:population":0,
    "gn:timezone":"Asia/Taipei",
    "iso:country":"TW",
    "name:und_x_variant":[
        "Ganzihci"
    ],
    "name:zho_x_preferred":[
        "\u67d1\u5b50\u5d0e"
    ],
    "name:zho_x_variant":[
        "Kan-tzu-ch\u2019i"
    ],
    "wof:name":"Ganziqi",
    "wof:placetype":"locality"
},
  "geometry": {"coordinates":[120.98023000000001,24.72374],"type":"Point"}
}