{
  "type": "Feature",
  "properties": {
    "gn:admin1_code":"4.0",
    "gn:admin2_code":"TXG",
    "gn:admin3_code":"B28",
    "gn:admin4_code":"66000280011.0",
    "gn:asciiname":"Shijiujia",
    "gn:country_code":"TW",
    "gn:dem":69,
    "gn:feature_class":"P",
    "gn:feature_code":"PPL",
    "gn:name":"Shijiujia",
    "gn:population":0,
    "gn:timezone":"Asia/Taipei",
    "iso:country":"TW",
    "name:und_x_variant":[
        "\u5341\u4e5d\u7532",
        "Shijiujia",
        "Shihjioujia",
        "Shih-chiu-chia"
    ],
    "wof:name":"Shijiujia",
    "wof:placetype":"locality"
},
  "geometry": {"coordinates":[120.70731000000001,24.1109],"type":"Point"}
}