{
  "type": "Feature",
  "properties": {
    "gn:admin1_code":"04",
    "gn:admin2_code":"CHA",
    "gn:admin3_code":"N16",
    "gn:admin4_code":"10007140013.0",
    "gn:asciiname":"Dayou",
    "gn:country_code":"TW",
    "gn:dem":15,
    "gn:feature_class":"P",
    "gn:feature_code":"PPL",
    "gn:name":"Dayou",
    "gn:population":0,
    "gn:timezone":"Asia/Taipei",
    "iso:country":"TW",
    "name:und_x_variant":[
        "Ta-yu"
    ],
    "name:zho_x_preferred":[
        "Ta-yu-ts\u2019un"
    ],
    "name:zho_x_variant":[
        "\u5927\u6709"
    ],
    "wof:name":"Dayou",
    "wof:placetype":"locality"
},
  "geometry": {"coordinates":[120.45332999999999,24.015],"type":"Point"}
}