{
  "type": "Feature",
  "properties": {
    "iso:country":"TW",
    "qs:name":"\u9e9f\u8dbe\u6751",
    "qs:name_adm0":"\u81fa\u7063",
    "qs:name_adm1":"\u5c4f\u6771\u7e23",
    "qs:photos":2,
    "qs:photos_1k":1,
    "qs:photos_9k":1,
    "qs:photos_9r":1,
    "qs:photos_all":2,
    "qs:photos_sr":1,
    "qs:placetype":"Town",
    "qs:pop_sr":"0",
    "wof:name":"\u9e9f\u8dbe\u6751",
    "wof:placetype":"locality"
},
  "geometry": {"coordinates":[120.519149,22.655604],"type":"Point"}
}