{
  "type": "Feature",
  "properties": {
    "gn:admin1_code":"2.0",
    "gn:admin2_code":"KHH",
    "gn:admin3_code":"E21",
    "gn:admin4_code":"64000210001.0",
    "gn:asciiname":"Jialing",
    "gn:country_code":"TW",
    "gn:dem":64,
    "gn:feature_class":"P",
    "gn:feature_code":"PPL",
    "gn:name":"Jialing",
    "gn:population":0,
    "gn:timezone":"Asia/Taipei",
    "iso:country":"TW",
    "name:ceb_x_preferred":[
        "Jialing"
    ],
    "name:deu_x_preferred":[
        "Jialing"
    ],
    "name:fra_x_preferred":[
        "Jialing"
    ],
    "name:nor_x_preferred":[
        "Jialing"
    ],
    "name:und_x_variant":[
        "Chia-ling"
    ],
    "name:zho_x_preferred":[
        "\u5609\u5dba"
    ],
    "wof:name":"Jialing",
    "wof:placetype":"locality"
},
  "geometry": {"coordinates":[120.36833,22.81389],"type":"Point"}
}