{
  "type": "Feature",
  "properties": {
    "gn:admin1_code":"04",
    "gn:admin2_code":"PIF",
    "gn:admin3_code":"T32",
    "gn:admin4_code":"10013320006.0",
    "gn:asciiname":"Caijiata",
    "gn:country_code":"TW",
    "gn:dem":448,
    "gn:feature_class":"P",
    "gn:feature_code":"PPL",
    "gn:name":"Caijiata",
    "gn:population":0,
    "gn:timezone":"Asia/Taipei",
    "iso:country":"TW",
    "name:und_x_variant":[
        "Ts\u2019ai-chia-t\u2019a"
    ],
    "wof:name":"Caijiata",
    "wof:placetype":"locality"
},
  "geometry": {"coordinates":[120.68333,22.25],"type":"Point"}
}