{
  "type": "Feature",
  "properties": {
    "gn:admin1_code":"4.0",
    "gn:admin2_code":"YUN",
    "gn:admin3_code":"P17",
    "gn:admin4_code":"10009170011.0",
    "gn:asciiname":"Zhuoyuncuo",
    "gn:country_code":"TW",
    "gn:dem":16,
    "gn:feature_class":"P",
    "gn:feature_code":"PPL",
    "gn:name":"Zhuoyuncuo",
    "gn:population":0,
    "gn:timezone":"Asia/Taipei",
    "iso:country":"TW",
    "name:und_x_variant":[
        "Jhuoyuncuo"
    ],
    "name:zho_x_preferred":[
        "Cho-y\u00fcn-ts\u2019un"
    ],
    "name:zho_x_variant":[
        "\u5353\u904b\u539d",
        "Cho-y\u00fcn",
        "Che-yun-te\u2019o",
        "Cho-y\u00fcn-ts\u2019o"
    ],
    "wof:name":"Zhuoyuncuo",
    "wof:placetype":"locality"
},
  "geometry": {"coordinates":[120.35054,23.64382],"type":"Point"}
}