{
  "type": "Feature",
  "properties": {
    "iso:country":"TW",
    "qs:name":"\u6e56\u5167\u9109",
    "qs:name_adm0":"\u81fa\u7063",
    "qs:name_adm1":"\u9ad8\u96c4\u5e02",
    "qs:photos":46,
    "qs:photos_1k":9,
    "qs:photos_9k":1,
    "qs:photos_9r":2,
    "qs:photos_all":46,
    "qs:photos_sr":2,
    "qs:placetype":"County",
    "qs:pop_sr":"0",
    "wd:wordcount":114,
    "wof:name":"\u6e56\u5167\u9109",
    "wof:placetype":"county"
},
  "geometry": {"coordinates":[120.20596500000001,22.909384],"type":"Point"}
}