{
  "type": "Feature",
  "properties": {
    "gn:country":"TW",
    "iso:country":"TW",
    "label:eng_x_preferred_longname":[
        "Baisha Township"
    ],
    "label:eng_x_preferred_placetype":[
        "township"
    ],
    "name:eng_x_preferred":[
        "Baisha"
    ],
    "name:eng_x_variant":[
        "Baisha Township"
    ],
    "name:fra_x_preferred":[
        "Baisha"
    ],
    "name:zho_tw_x_preferred":[
        "\u767d\u6c99\u9109"
    ],
    "qs:name":"\u767d\u6c99\u9109",
    "qs:name_adm0":"\u81fa\u7063",
    "qs:name_adm1":"\u6f8e\u6e56\u7e23",
    "qs:photos":1648,
    "qs:photos_1k":334,
    "qs:photos_9k":17,
    "qs:photos_9r":12,
    "qs:photos_all":3853,
    "qs:photos_sr":13,
    "qs:placetype":"County",
    "qs:pop_sr":"0",
    "wof:name":"Baisha",
    "wof:placetype":"county"
},
  "geometry": {"coordinates":[119.591159,23.712517],"type":"Point"}
}