{
  "type": "Feature",
  "properties": {
    "gn:admin1_code":"04",
    "gn:admin2_code":"MIA",
    "gn:admin3_code":"K03",
    "gn:admin4_code":"10005030013.0",
    "gn:asciiname":"Wulipai",
    "gn:country_code":"TW",
    "gn:dem":10,
    "gn:feature_class":"P",
    "gn:feature_code":"PPL",
    "gn:name":"Wulipai",
    "gn:population":0,
    "gn:timezone":"Asia/Taipei",
    "iso:country":"TW",
    "name:und_x_variant":[
        "Wen-ming",
        "Fan-tzu-liao",
        "Wulipai"
    ],
    "name:zho_x_preferred":[
        "\u4e94\u91cc\u724c"
    ],
    "name:zho_x_variant":[
        "Wu-li-p\u2019ai"
    ],
    "wof:name":"Wulipai",
    "wof:placetype":"locality"
},
  "geometry": {"coordinates":[120.66528,24.47889],"type":"Point"}
}