{
  "type": "Feature",
  "properties": {
    "gn:admin1_code":"4.0",
    "gn:admin2_code":"TXG",
    "gn:admin3_code":"B27",
    "gn:admin4_code":"66000270014.0",
    "gn:asciiname":"Zhongkeng",
    "gn:country_code":"TW",
    "gn:dem":221,
    "gn:feature_class":"P",
    "gn:feature_code":"PPL",
    "gn:name":"Zhongkeng",
    "gn:population":0,
    "gn:timezone":"Asia/Taipei",
    "iso:country":"TW",
    "name:und_x_variant":[
        "Jhongkeng",
        "Zhongkeng"
    ],
    "name:zho_x_preferred":[
        "\u4e2d\u5751"
    ],
    "name:zho_x_variant":[
        "Chung-k\u2019eng"
    ],
    "wof:name":"Zhongkeng",
    "wof:placetype":"locality"
},
  "geometry": {"coordinates":[120.77521000000002,24.12668],"type":"Point"}
}