{
  "type": "Feature",
  "properties": {
    "gn:admin1_code":"4.0",
    "gn:admin2_code":"TAO",
    "gn:admin3_code":"H12",
    "gn:admin4_code":"68000120001.0",
    "gn:asciiname":"Guanyin",
    "gn:country_code":"TW",
    "gn:dem":26,
    "gn:feature_class":"P",
    "gn:feature_code":"PPL",
    "gn:name":"Guanyin",
    "gn:population":0,
    "gn:timezone":"Asia/Taipei",
    "iso:country":"TW",
    "name:und_x_variant":[
        "Kuangyin",
        "Shih-kuan-yin",
        "Guanyin",
        "Kuan-yin"
    ],
    "name:zho_x_preferred":[
        "Kuan-yin-ts\u2019un"
    ],
    "name:zho_x_variant":[
        "\u89c0\u97f3"
    ],
    "wof:name":"Guanyin",
    "wof:placetype":"locality"
},
  "geometry": {"coordinates":[121.08147,25.03644],"type":"Point"}
}