{
  "type": "Feature",
  "properties": {
    "gn:admin1_code":"4.0",
    "gn:admin2_code":"TNN",
    "gn:admin3_code":"R31",
    "gn:admin4_code":"67000310004.0",
    "gn:asciiname":"Buzi",
    "gn:country_code":"TW",
    "gn:dem":19,
    "gn:feature_class":"P",
    "gn:feature_code":"PPL",
    "gn:name":"Buzi",
    "gn:population":0,
    "gn:timezone":"Asia/Taipei",
    "iso:country":"TW",
    "name:nld_x_preferred":[
        "Buzi"
    ],
    "name:und_x_variant":[
        "Pu-tzu",
        "Buzih"
    ],
    "name:zho_x_preferred":[
        "\u57d4\u5b50"
    ],
    "wof:name":"Buzi",
    "wof:placetype":"locality"
},
  "geometry": {"coordinates":[120.25306,23.03278],"type":"Point"}
}