{
  "type": "Feature",
  "properties": {
    "gn:admin1_code":"4.0",
    "gn:admin2_code":"ILA",
    "gn:admin3_code":"G10",
    "gn:admin4_code":"10002100012.0",
    "gn:asciiname":"Fenglin",
    "gn:country_code":"TW",
    "gn:dem":91,
    "gn:feature_class":"P",
    "gn:feature_code":"PPL",
    "gn:name":"Fenglin",
    "gn:population":0,
    "gn:timezone":"Asia/Taipei",
    "iso:country":"TW",
    "name:ceb_x_preferred":[
        "Fenglin"
    ],
    "name:deu_x_preferred":[
        "Fenglin"
    ],
    "name:swe_x_preferred":[
        "Fenglin"
    ],
    "name:und_x_variant":[
        "Fonglin",
        "Feng-lin"
    ],
    "name:zho_x_preferred":[
        "\u6953\u6797"
    ],
    "wof:name":"Fenglin",
    "wof:placetype":"locality"
},
  "geometry": {"coordinates":[121.65308,24.68011],"type":"Point"}
}