{
  "type": "Feature",
  "properties": {
    "gn:admin1_code":"4.0",
    "gn:admin2_code":"MIA",
    "gn:admin3_code":"K07",
    "gn:admin4_code":"10005140003.0",
    "gn:asciiname":"Shanghukeng",
    "gn:country_code":"TW",
    "gn:dem":112,
    "gn:feature_class":"P",
    "gn:feature_code":"PPL",
    "gn:name":"Shanghukeng",
    "gn:population":0,
    "gn:timezone":"Asia/Taipei",
    "iso:country":"TW",
    "name:zho_x_preferred":[
        "\u4e0a\u6e56\u5751"
    ],
    "name:zho_x_variant":[
        "Shang-hu-k\u2019eng"
    ],
    "wof:name":"Shanghukeng",
    "wof:placetype":"locality"
},
  "geometry": {"coordinates":[120.7814,24.52446],"type":"Point"}
}