{
  "type": "Feature",
  "properties": {
    "iso:country":"TW",
    "qs:name":"\u65b0\u548c\u91cc",
    "qs:name_adm0":"\u81fa\u7063",
    "qs:name_adm1":"\u53f0\u5317\u5e02",
    "qs:photos":211,
    "qs:photos_1k":43,
    "qs:photos_9k":1,
    "qs:photos_9r":4,
    "qs:photos_all":211,
    "qs:photos_sr":4,
    "qs:placetype":"Suburb",
    "qs:pop_sr":"0",
    "wof:name":"\u65b0\u548c\u91cc",
    "wof:placetype":"neighbourhood"
},
  "geometry": {"coordinates":[121.505656,25.026],"type":"Point"}
}