{
  "type": "Feature",
  "properties": {
    "gn:admin1_code":"4.0",
    "gn:admin2_code":"CHA",
    "gn:admin3_code":"N07",
    "gn:admin4_code":"10007120001.0",
    "gn:asciiname":"Houzhuang",
    "gn:country_code":"TW",
    "gn:dem":57,
    "gn:feature_class":"P",
    "gn:feature_code":"PPL",
    "gn:name":"Houzhuang",
    "gn:population":0,
    "gn:timezone":"Asia/Taipei",
    "iso:country":"TW",
    "name:und_x_variant":[
        "Houjhuang",
        "Hou-chuang"
    ],
    "name:zho_x_preferred":[
        "\u5f8c\u5e84"
    ],
    "wof:name":"Houzhuang",
    "wof:placetype":"locality"
},
  "geometry": {"coordinates":[120.5996,23.845],"type":"Point"}
}