{
  "type": "Feature",
  "properties": {
    "gn:admin1_code":"4.0",
    "gn:admin2_code":"TAO",
    "gn:admin3_code":"H13",
    "gn:admin4_code":"68000130005.0",
    "gn:asciiname":"Sanjiaogu",
    "gn:country_code":"TW",
    "gn:dem":263,
    "gn:feature_class":"P",
    "gn:feature_code":"PPL",
    "gn:name":"Sanjiaogu",
    "gn:population":0,
    "gn:timezone":"Asia/Taipei",
    "iso:country":"TW",
    "name:und_x_variant":[
        "San-chiao-ku"
    ],
    "name:zho_x_preferred":[
        "\u4e09\u89d2\u8c37"
    ],
    "wof:name":"Sanjiaogu",
    "wof:placetype":"locality"
},
  "geometry": {"coordinates":[121.26718,24.80307],"type":"Point"}
}