{
  "type": "Feature",
  "properties": {
    "gn:admin1_code":"4.0",
    "gn:admin2_code":"YUN",
    "gn:admin3_code":"P08",
    "gn:admin4_code":"10009080003.0",
    "gn:asciiname":"Qianliao",
    "gn:country_code":"TW",
    "gn:dem":22,
    "gn:feature_class":"P",
    "gn:feature_code":"PPL",
    "gn:name":"Qianliao",
    "gn:population":0,
    "gn:timezone":"Asia/Taipei",
    "iso:country":"TW",
    "name:und_x_variant":[
        "Hsin-chieh-liao",
        "Qianliao",
        "Cianliao"
    ],
    "name:zho_x_preferred":[
        "\u524d\u5bee"
    ],
    "name:zho_x_variant":[
        "Ch\u2019ien-liao"
    ],
    "wof:name":"Qianliao",
    "wof:placetype":"locality"
},
  "geometry": {"coordinates":[120.4166,23.6261],"type":"Point"}
}