{
  "type": "Feature",
  "properties": {
    "gn:admin1_code":"03",
    "gn:admin2_code":"TPQ",
    "gn:admin3_code":"F23",
    "gn:admin4_code":"65000250012.0",
    "gn:asciiname":"Wushan",
    "gn:country_code":"TW",
    "gn:dem":478,
    "gn:feature_class":"P",
    "gn:feature_code":"PPL",
    "gn:name":"Wushan",
    "gn:population":0,
    "gn:timezone":"Asia/Taipei",
    "iso:country":"TW",
    "name:ceb_x_preferred":[
        "Wushan"
    ],
    "name:deu_x_preferred":[
        "Wushan"
    ],
    "name:fra_x_preferred":[
        "Wushan"
    ],
    "name:kor_x_preferred":[
        "\uc6b0\uc0b0\ud604"
    ],
    "name:nor_x_preferred":[
        "Wushan"
    ],
    "name:swe_x_preferred":[
        "Wushan"
    ],
    "name:und_x_variant":[
        "Wu-shan"
    ],
    "name:zho_x_preferred":[
        "\u70cf\u5c71"
    ],
    "wof:name":"Wushan",
    "wof:placetype":"locality"
},
  "geometry": {"coordinates":[121.82861,24.94444],"type":"Point"}
}