{
  "type": "Feature",
  "properties": {
    "gn:admin1_code":"04",
    "gn:admin2_code":"TAO",
    "gn:admin3_code":"H13",
    "gn:admin4_code":"68000130006.0",
    "gn:asciiname":"Yeheng",
    "gn:country_code":"TW",
    "gn:dem":673,
    "gn:feature_class":"P",
    "gn:feature_code":"PPL",
    "gn:name":"Yeheng",
    "gn:population":0,
    "gn:timezone":"Asia/Taipei",
    "iso:country":"TW",
    "name:und_x_variant":[
        "Heng-yeh",
        "Yeh-hsiang-she",
        "Yeheng",
        "Yeh-heng"
    ],
    "name:zho_x_preferred":[
        "\u723a\u4ea8"
    ],
    "wof:name":"Yeheng",
    "wof:placetype":"locality"
},
  "geometry": {"coordinates":[121.37472,24.67],"type":"Point"}
}