{
  "type": "Feature",
  "properties": {
    "gn:admin1_code":"2.0",
    "gn:admin2_code":"KHH",
    "gn:admin3_code":"E22",
    "gn:admin4_code":"64000220007.0",
    "gn:asciiname":"Xinluzi",
    "gn:country_code":"TW",
    "gn:dem":33,
    "gn:feature_class":"P",
    "gn:feature_code":"PPL",
    "gn:name":"Xinluzi",
    "gn:population":0,
    "gn:timezone":"Asia/Taipei",
    "iso:country":"TW",
    "name:und_x_variant":[
        "Sinluzih",
        "Hsin-lu-tzu"
    ],
    "name:zho_x_preferred":[
        "\u65b0\u8def\u5b50"
    ],
    "wof:name":"Xinluzi",
    "wof:placetype":"locality"
},
  "geometry": {"coordinates":[120.35805999999999,22.88833],"type":"Point"}
}