{
  "type": "Feature",
  "properties": {
    "gn:admin1_code":"4.0",
    "gn:admin2_code":"ILA",
    "gn:admin3_code":"G11",
    "gn:admin4_code":"10002110009.0",
    "gn:asciiname":"Pinanxiang",
    "gn:country_code":"TW",
    "gn:dem":1154,
    "gn:feature_class":"P",
    "gn:feature_code":"PPL",
    "gn:name":"Pinanxiang",
    "gn:population":0,
    "gn:timezone":"Asia/Taipei",
    "iso:country":"TW",
    "name:und_x_variant":[
        "Pinansiang",
        "Shang-pu-lo"
    ],
    "name:zho_x_preferred":[
        "\u57e4\u5357\u5df7"
    ],
    "name:zho_x_variant":[
        "P\u2019i-nan-hsiang"
    ],
    "wof:name":"Pinanxiang",
    "wof:placetype":"locality"
},
  "geometry": {"coordinates":[121.37888999999998,24.43944],"type":"Point"}
}