{
  "type": "Feature",
  "properties": {
    "gn:admin1_code":"04",
    "gn:admin2_code":"TPE",
    "gn:admin3_code":"A14",
    "gn:admin4_code":"63000100025.0",
    "gn:asciiname":"Daqiutian",
    "gn:country_code":"TW",
    "gn:dem":333,
    "gn:feature_class":"P",
    "gn:feature_code":"PPL",
    "gn:name":"Daqiutian",
    "gn:population":0,
    "gn:timezone":"Asia/Taipei",
    "iso:country":"TW",
    "name:und_x_variant":[
        "Dacioutian",
        "Daqiutian"
    ],
    "name:zho_x_preferred":[
        "\u5927\u90b1\u7530"
    ],
    "name:zho_x_variant":[
        "Ta-ch\u2019iu-t\u2019ien"
    ],
    "wof:name":"Daqiutian",
    "wof:placetype":"locality"
},
  "geometry": {"coordinates":[121.60124,25.10336],"type":"Point"}
}