{
  "type": "Feature",
  "properties": {
    "gn:admin1_code":"4.0",
    "gn:admin2_code":"NAN",
    "gn:admin3_code":"M04",
    "gn:admin4_code":"10008040020.0",
    "gn:asciiname":"Wentian",
    "gn:country_code":"TW",
    "gn:dem":447,
    "gn:feature_class":"P",
    "gn:feature_code":"PPL",
    "gn:name":"Wentian",
    "gn:population":0,
    "gn:timezone":"Asia/Taipei",
    "iso:country":"TW",
    "name:und_x_variant":[
        "Wuntian"
    ],
    "name:zho_x_preferred":[
        "\u6587\u7530"
    ],
    "name:zho_x_variant":[
        "Wen-t\u2019ien",
        "\u6587\u7530\u9547"
    ],
    "wof:name":"Wentian",
    "wof:placetype":"locality"
},
  "geometry": {"coordinates":[120.68832999999999,23.70417],"type":"Point"}
}