{
  "type": "Feature",
  "properties": {
    "iso:country":"TW",
    "qs:name":"\u9686\u8208\u6751",
    "qs:name_adm0":"\u81fa\u7063",
    "qs:name_adm1":"\u5609\u7fa9\u7e23",
    "qs:photos":12,
    "qs:photos_1k":2,
    "qs:photos_9k":1,
    "qs:photos_9r":1,
    "qs:photos_all":12,
    "qs:photos_sr":1,
    "qs:placetype":"Town",
    "qs:pop_sr":"0",
    "wof:name":"\u9686\u8208\u6751",
    "wof:placetype":"locality"
},
  "geometry": {"coordinates":[120.5294105,23.4416895],"type":"Point"}
}