{
  "type": "Feature",
  "properties": {
    "gn:admin1_code":"4.0",
    "gn:admin2_code":"CYQ",
    "gn:admin3_code":"Q11",
    "gn:admin4_code":"10010110005.0",
    "gn:asciiname":"Haifeng",
    "gn:country_code":"TW",
    "gn:dem":14,
    "gn:feature_class":"P",
    "gn:feature_code":"PPL",
    "gn:name":"Haifeng",
    "gn:population":0,
    "gn:timezone":"Asia/Taipei",
    "iso:country":"TW",
    "name:und_x_variant":[
        "Haifong",
        "Hai-feng"
    ],
    "name:zho_x_preferred":[
        "\u6d77\u8c50"
    ],
    "wof:name":"Haifeng",
    "wof:placetype":"locality"
},
  "geometry": {"coordinates":[120.28778,23.41639],"type":"Point"}
}