{
  "type": "Feature",
  "properties": {
    "gn:admin1_code":"4.0",
    "gn:admin2_code":"NAN",
    "gn:admin3_code":"M09",
    "gn:admin4_code":"10008090009.0",
    "gn:asciiname":"Wuchengkou",
    "gn:country_code":"TW",
    "gn:dem":572,
    "gn:feature_class":"P",
    "gn:feature_code":"PPL",
    "gn:name":"Wuchengkou",
    "gn:population":0,
    "gn:timezone":"Asia/Taipei",
    "iso:country":"TW",
    "name:zho_x_preferred":[
        "\u4e94\u57ce\u53e3"
    ],
    "name:zho_x_variant":[
        "Wu-ch\u2019eng-k\u2019ou"
    ],
    "wof:name":"Wuchengkou",
    "wof:placetype":"locality"
},
  "geometry": {"coordinates":[120.89069000000001,23.88412000000001],"type":"Point"}
}