{
  "type": "Feature",
  "properties": {
    "gn:admin1_code":"04",
    "gn:asciiname":"Weng-yuan-ts'un",
    "gn:country_code":"TW",
    "gn:dem":10,
    "gn:feature_class":"P",
    "gn:feature_code":"PPL",
    "gn:name":"Weng-y\u00fcan-ts'un",
    "gn:population":0,
    "gn:timezone":"Asia/Taipei",
    "iso:country":"TW",
    "wof:name":"Weng-yuan-ts'un",
    "wof:placetype":"locality"
},
  "geometry": {"coordinates":[120.40000000000001,22.61667000000001],"type":"Point"}
}