{
  "type": "Feature",
  "properties": {
    "gn:admin1_code":"4.0",
    "gn:admin2_code":"CHA",
    "gn:admin3_code":"N01",
    "gn:admin4_code":"10007010066.0",
    "gn:asciiname":"Yinhangshan",
    "gn:country_code":"TW",
    "gn:dem":220,
    "gn:feature_class":"P",
    "gn:feature_code":"PPL",
    "gn:name":"Yinhangshan",
    "gn:population":0,
    "gn:timezone":"Asia/Taipei",
    "iso:country":"TW",
    "name:und_x_variant":[
        "Yinhangshan",
        "Yin-hang-shan"
    ],
    "name:zho_x_preferred":[
        "\u9280\u884c\u5c71"
    ],
    "wof:name":"Yinhangshan",
    "wof:placetype":"locality"
},
  "geometry": {"coordinates":[120.58781,24.05287],"type":"Point"}
}