{
  "type": "Feature",
  "properties": {
    "iso:country":"TW",
    "qs:name":"\u828e\u6797\u9109",
    "qs:name_adm0":"\u81fa\u7063",
    "qs:name_adm1":"\u65b0\u7af9\u7e23",
    "qs:photos":16,
    "qs:photos_1k":3,
    "qs:photos_9k":1,
    "qs:photos_9r":3,
    "qs:photos_all":143,
    "qs:photos_sr":1,
    "qs:placetype":"County",
    "qs:pop_sr":"0",
    "wof:name":"\u828e\u6797\u9109",
    "wof:placetype":"county"
},
  "geometry": {"coordinates":[121.087732,24.7645165],"type":"Point"}
}