{
  "type": "Feature",
  "properties": {
    "gn:admin1_code":"4.0",
    "gn:admin2_code":"NAN",
    "gn:admin3_code":"M02",
    "gn:admin4_code":"10008020008.0",
    "gn:asciiname":"Hengjicheng",
    "gn:country_code":"TW",
    "gn:dem":429,
    "gn:feature_class":"P",
    "gn:feature_code":"PPL",
    "gn:name":"Hengjicheng",
    "gn:population":0,
    "gn:timezone":"Asia/Taipei",
    "iso:country":"TW",
    "name:zho_x_preferred":[
        "\u6052\u5409\u57ce"
    ],
    "name:zho_x_variant":[
        "Heng-chi-ch\u2019eng"
    ],
    "wof:name":"Hengjicheng",
    "wof:placetype":"locality"
},
  "geometry": {"coordinates":[120.95005999999999,23.9727],"type":"Point"}
}