{
  "type": "Feature",
  "properties": {
    "gn:admin1_code":"4.0",
    "gn:admin2_code":"MIA",
    "gn:admin3_code":"K15",
    "gn:admin4_code":"10005080004.0",
    "gn:asciiname":"Qiliaodong",
    "gn:country_code":"TW",
    "gn:dem":330,
    "gn:feature_class":"P",
    "gn:feature_code":"PPL",
    "gn:name":"Qiliaodong",
    "gn:population":0,
    "gn:timezone":"Asia/Taipei",
    "iso:country":"TW",
    "name:und_x_variant":[
        "Ciliaodong",
        "Qiliaodong"
    ],
    "name:zho_x_preferred":[
        "\u4e03\u5bee\u5d20"
    ],
    "name:zho_x_variant":[
        "Ch\u2019i-liao-tung"
    ],
    "wof:name":"Qiliaodong",
    "wof:placetype":"locality"
},
  "geometry": {"coordinates":[120.87716,24.43244],"type":"Point"}
}