{
  "type": "Feature",
  "properties": {
    "iso:country":"TW",
    "qs:name":"\u592a\u5e73\u6751",
    "qs:name_adm0":"\u81fa\u7063",
    "qs:name_adm1":"\u5b9c\u862d\u7e23",
    "qs:photos":286,
    "qs:photos_1k":58,
    "qs:photos_9k":1,
    "qs:photos_9r":4,
    "qs:photos_all":286,
    "qs:photos_sr":5,
    "qs:placetype":"Town",
    "qs:pop_sr":"0",
    "wof:name":"\u592a\u5e73\u6751",
    "wof:placetype":"locality"
},
  "geometry": {"coordinates":[121.536254,24.525359],"type":"Point"}
}