{
  "type": "Feature",
  "properties": {
    "iso:country":"TW",
    "qs:name":"\u6c11\u65cf\u6751",
    "qs:name_adm0":"\u81fa\u7063",
    "qs:name_adm1":"\u9ad8\u96c4\u5e02",
    "qs:photos":69,
    "qs:photos_1k":14,
    "qs:photos_9k":1,
    "qs:photos_9r":2,
    "qs:photos_all":69,
    "qs:photos_sr":2,
    "qs:placetype":"Town",
    "qs:pop_sr":"0",
    "wd:wordcount":392,
    "wof:name":"\u6c11\u65cf\u6751",
    "wof:placetype":"locality"
},
  "geometry": {"coordinates":[120.677604,23.208139],"type":"Point"}
}