{
  "type": "Feature",
  "properties": {
    "iso:country":"TW",
    "name:ara_x_preferred":[
        "\u0642\u0631\u064a\u0629 \u0635\u064a\u0646\u064a\u0629"
    ],
    "name:bak_x_preferred":[
        "\u04a0\u044b\u0442\u0430\u0439 \u0430\u0443\u044b\u043b\u044b"
    ],
    "name:dan_x_preferred":[
        "kinesisk landsby"
    ],
    "name:fas_x_preferred":[
        "\u0631\u0648\u0633\u062a\u0627"
    ],
    "name:fin_x_preferred":[
        "kyl\u00e4 Kiinassa"
    ],
    "name:fra_x_preferred":[
        "village chinois"
    ],
    "name:hye_x_preferred":[
        "\u0563\u0575\u0578\u0582\u0572 \u0549\u053a\u0540-\u0578\u0582\u0574"
    ],
    "name:jpn_x_preferred":[
        "\u4e2d\u56fd\u306e\u6751\u7d1a\u884c\u653f\u533a\u753b"
    ],
    "name:oci_x_preferred":[
        "vilatge chin\u00e9s"
    ],
    "name:rus_x_preferred":[
        "\u0434\u0435\u0440\u0435\u0432\u043d\u044f \u041a\u041d\u0420"
    ],
    "name:tel_x_preferred":[
        "\u0c1a\u0c48\u0c28\u0c3e \u0c17\u0c4d\u0c30\u0c3e\u0c2e\u0c02"
    ],
    "name:uig_x_preferred":[
        "\u0643\u06d5\u0646\u062a"
    ],
    "name:zho_x_preferred":[
        "\u884c\u653f\u6751"
    ],
    "qs:name":"\u6c11\u65cf\u6751",
    "qs:name_adm0":"\u81fa\u7063",
    "qs:name_adm1":"\u9ad8\u96c4\u5e02",
    "qs:photos":69,
    "qs:photos_1k":14,
    "qs:photos_9k":1,
    "qs:photos_9r":2,
    "qs:photos_all":69,
    "qs:photos_sr":2,
    "qs:placetype":"Town",
    "qs:pop_sr":"0",
    "wd:wordcount":392,
    "wof:name":"\u6c11\u65cf\u6751",
    "wof:placetype":"locality"
},
  "geometry": {"coordinates":[120.677604,23.208139],"type":"Point"}
}