{
  "type": "Feature",
  "properties": {
    "gn:admin1_code":"4.0",
    "gn:admin2_code":"TXG",
    "gn:admin3_code":"B14",
    "gn:admin4_code":"66000140012.0",
    "gn:asciiname":"Zhurenli",
    "gn:country_code":"TW",
    "gn:dem":5,
    "gn:feature_class":"P",
    "gn:feature_code":"PPL",
    "gn:name":"Zhurenli",
    "gn:population":0,
    "gn:timezone":"Asia/Taipei",
    "iso:country":"TW",
    "name:und_x_variant":[
        "Chu-jen-li"
    ],
    "wof:name":"Zhurenli",
    "wof:placetype":"locality"
},
  "geometry": {"coordinates":[120.55,24.23333],"type":"Point"}
}