{
  "type": "Feature",
  "properties": {
    "gn:admin1_code":"01",
    "gn:admin2_code":"KIN",
    "gn:admin3_code":"W02",
    "gn:admin4_code":"9020020002.0",
    "gn:asciiname":"Shanhou",
    "gn:country_code":"TW",
    "gn:dem":17,
    "gn:feature_class":"P",
    "gn:feature_code":"PPL",
    "gn:name":"Shanhou",
    "gn:population":0,
    "gn:timezone":"Asia/Taipei",
    "iso:country":"TW",
    "name:und_x_variant":[
        "Shan-hou",
        "\u5c71\u540e",
        "Shanhou"
    ],
    "wof:name":"Shanhou",
    "wof:placetype":"locality"
},
  "geometry": {"coordinates":[118.44096999999999,24.50471],"type":"Point"}
}