{
  "type": "Feature",
  "properties": {
    "gn:admin1_code":"4.0",
    "gn:admin2_code":"YUN",
    "gn:admin3_code":"P12",
    "gn:admin4_code":"10009120004.0",
    "gn:asciiname":"Gangzibei",
    "gn:country_code":"TW",
    "gn:dem":16,
    "gn:feature_class":"P",
    "gn:feature_code":"PPL",
    "gn:name":"Gangzibei",
    "gn:population":0,
    "gn:timezone":"Asia/Taipei",
    "iso:country":"TW",
    "name:und_x_variant":[
        "Kang-pei",
        "Gangzibei",
        "Gangzihbei",
        "Kang-tzu-pei"
    ],
    "name:zho_x_preferred":[
        "\u5d17\u5b50\u80cc"
    ],
    "wof:name":"Gangzibei",
    "wof:placetype":"locality"
},
  "geometry": {"coordinates":[120.35890000000001,23.75374],"type":"Point"}
}