{
  "type": "Feature",
  "properties": {
    "gn:admin1_code":"3.0",
    "gn:admin2_code":"TPQ",
    "gn:admin3_code":"F23",
    "gn:admin4_code":"65000250011.0",
    "gn:asciiname":"Xiakengkou",
    "gn:country_code":"TW",
    "gn:dem":164,
    "gn:feature_class":"P",
    "gn:feature_code":"PPL",
    "gn:name":"Xiakengkou",
    "gn:population":0,
    "gn:timezone":"Asia/Taipei",
    "iso:country":"TW",
    "name:und_x_variant":[
        "Siakengkou"
    ],
    "name:zho_x_preferred":[
        "Hsian-k\u2019eng"
    ],
    "name:zho_x_variant":[
        "\u4e0b\u5751\u53e3",
        "Hsia-k\u2019eng",
        "Hsia-k\u2019eng-k\u2019ou"
    ],
    "wof:name":"Xiakengkou",
    "wof:placetype":"locality"
},
  "geometry": {"coordinates":[121.79563,25.00691],"type":"Point"}
}