{
  "type": "Feature",
  "properties": {
    "gn:admin1_code":"04",
    "gn:admin2_code":"TTT",
    "gn:admin3_code":"V07",
    "gn:admin4_code":"10014070001.0",
    "gn:asciiname":"Beiyuan",
    "gn:country_code":"TW",
    "gn:dem":155,
    "gn:feature_class":"P",
    "gn:feature_code":"PPL",
    "gn:name":"Beiyuan",
    "gn:population":0,
    "gn:timezone":"Asia/Taipei",
    "iso:country":"TW",
    "name:ceb_x_preferred":[
        "Beiyuan"
    ],
    "name:swe_x_preferred":[
        "Beiyuan"
    ],
    "name:zho_x_preferred":[
        "Pei-y\u00fcan-ts\u2019un"
    ],
    "name:zho_x_variant":[
        "\u5317\u6e90",
        "Pei-y\u00fcan",
        "Hua-k\u2019u"
    ],
    "wof:name":"Beiyuan",
    "wof:placetype":"locality"
},
  "geometry": {"coordinates":[121.28655999999999,23.01998],"type":"Point"}
}