{
  "type": "Feature",
  "properties": {
    "gn:admin1_code":"4.0",
    "gn:admin2_code":"KEE",
    "gn:admin3_code":"C02",
    "gn:admin4_code":"10017020014.0",
    "gn:asciiname":"Liyukeng",
    "gn:country_code":"TW",
    "gn:dem":67,
    "gn:feature_class":"P",
    "gn:feature_code":"PPL",
    "gn:name":"Liyukeng",
    "gn:population":0,
    "gn:timezone":"Asia/Taipei",
    "iso:country":"TW",
    "name:zho_x_preferred":[
        "\u9bc9\u9b5a\u5751"
    ],
    "name:zho_x_variant":[
        "Li-y\u00fc-k\u2019eng"
    ],
    "wof:name":"Liyukeng",
    "wof:placetype":"locality"
},
  "geometry": {"coordinates":[121.67883999999999,25.12289],"type":"Point"}
}