{
  "type": "Feature",
  "properties": {
    "gn:admin1_code":"04",
    "gn:admin2_code":"NAN",
    "gn:admin3_code":"M09",
    "gn:admin4_code":"10008090011.0",
    "gn:asciiname":"Neiwazi",
    "gn:country_code":"TW",
    "gn:dem":655,
    "gn:feature_class":"P",
    "gn:feature_code":"PPL",
    "gn:name":"Neiwazi",
    "gn:population":0,
    "gn:timezone":"Asia/Taipei",
    "iso:country":"TW",
    "name:und_x_variant":[
        "Neiwazih",
        "Nei-wa-tzu"
    ],
    "name:zho_x_preferred":[
        "\u5185\u51f9\u4ed4"
    ],
    "name:zho_x_variant":[
        "Nei-t\u2019a-tzu"
    ],
    "wof:name":"Neiwazi",
    "wof:placetype":"locality"
},
  "geometry": {"coordinates":[120.90331999999999,23.82047],"type":"Point"}
}