{
  "type": "Feature",
  "properties": {
    "gn:admin1_code":"3.0",
    "gn:admin2_code":"TPQ",
    "gn:admin3_code":"F08",
    "gn:admin4_code":"65000190011.0",
    "gn:asciiname":"Ganjiaofang",
    "gn:country_code":"TW",
    "gn:dem":299,
    "gn:feature_class":"P",
    "gn:feature_code":"PPL",
    "gn:name":"Ganjiaofang",
    "gn:population":0,
    "gn:timezone":"Asia/Taipei",
    "iso:country":"TW",
    "name:und_x_variant":[
        "Kan-chiao-fang"
    ],
    "name:zho_x_preferred":[
        "\u67d1\u811a\u574a"
    ],
    "name:zho_x_variant":[
        "Kan-chiao-k\u2019eng"
    ],
    "wof:name":"Ganjiaofang",
    "wof:placetype":"locality"
},
  "geometry": {"coordinates":[121.65895,24.93866],"type":"Point"}
}