{
  "type": "Feature",
  "properties": {
    "gn:admin1_code":"04",
    "gn:admin2_code":"TAO",
    "gn:admin3_code":"H07",
    "gn:admin4_code":"68000070001.0",
    "gn:asciiname":"Dingshe",
    "gn:country_code":"TW",
    "gn:dem":146,
    "gn:feature_class":"P",
    "gn:feature_code":"PPL",
    "gn:name":"Dingshe",
    "gn:population":0,
    "gn:timezone":"Asia/Taipei",
    "iso:country":"TW",
    "name:und_x_variant":[
        "She-chang",
        "Dingshe",
        "She-chuang",
        "Ting-she"
    ],
    "name:zho_x_preferred":[
        "\u9802\u793e"
    ],
    "wof:name":"Dingshe",
    "wof:placetype":"locality"
},
  "geometry": {"coordinates":[121.34169,25.00804],"type":"Point"}
}