{
  "type": "Feature",
  "properties": {
    "gn:admin1_code":"4.0",
    "gn:admin2_code":"CHA",
    "gn:admin3_code":"N20",
    "gn:admin4_code":"10007180012.0",
    "gn:asciiname":"Nanxiuren",
    "gn:country_code":"TW",
    "gn:dem":98,
    "gn:feature_class":"P",
    "gn:feature_code":"PPL",
    "gn:name":"Nanxiuren",
    "gn:population":0,
    "gn:timezone":"Asia/Taipei",
    "iso:country":"TW",
    "name:und_x_variant":[
        "Fan-tzu-liao",
        "Nansiouren",
        "Nanxiuren",
        "Hsiu-jen",
        "Nan-hsiu-jen"
    ],
    "name:zho_x_preferred":[
        "\u5357\u4fee\u4ec1"
    ],
    "wof:name":"Nanxiuren",
    "wof:placetype":"locality"
},
  "geometry": {"coordinates":[120.6318,23.7993],"type":"Point"}
}