{
  "type": "Feature",
  "properties": {
    "gn:admin1_code":"4.0",
    "gn:admin2_code":"HSZ",
    "gn:admin3_code":"J04",
    "gn:admin4_code":"10004030018.0",
    "gn:asciiname":"Qixia",
    "gn:country_code":"TW",
    "gn:dem":237,
    "gn:feature_class":"P",
    "gn:feature_code":"PPL",
    "gn:name":"Qixia",
    "gn:population":0,
    "gn:timezone":"Asia/Taipei",
    "iso:country":"TW",
    "name:ceb_x_preferred":[
        "Qixia"
    ],
    "name:deu_x_preferred":[
        "Qixia"
    ],
    "name:fra_x_preferred":[
        "Qixia"
    ],
    "name:nor_x_preferred":[
        "Qixia"
    ],
    "name:rus_x_preferred":[
        "\u0426\u0438\u0441\u044f"
    ],
    "name:und_x_variant":[
        "Ch\u2019i-hsia"
    ],
    "wof:name":"Qixia",
    "wof:placetype":"locality"
},
  "geometry": {"coordinates":[121.13333,24.85],"type":"Point"}
}