{
  "type": "Feature",
  "properties": {
    "gn:admin1_code":"4.0",
    "gn:admin2_code":"YUN",
    "gn:admin3_code":"P05",
    "gn:admin4_code":"10009050017.0",
    "gn:asciiname":"Xidi",
    "gn:country_code":"TW",
    "gn:dem":16,
    "gn:feature_class":"P",
    "gn:feature_code":"PPL",
    "gn:name":"Xidi",
    "gn:population":0,
    "gn:timezone":"Asia/Taipei",
    "iso:country":"TW",
    "name:und_x_variant":[
        "Sidi",
        "Xidi",
        "Hsi-ti"
    ],
    "name:zho_x_preferred":[
        "\u6eaa\u5e95"
    ],
    "wof:name":"Xidi",
    "wof:placetype":"locality"
},
  "geometry": {"coordinates":[120.34469,23.74439],"type":"Point"}
}