{
  "type": "Feature",
  "properties": {
    "iso:country":"TW",
    "name:eng_x_preferred":[
        "Baifu"
    ],
    "name:eng_x_variant":[
        "Baifu Village"
    ],
    "name:zho_tw_x_preferred":[
        "\u767e\u798f\u91cc"
    ],
    "qs:name":"\u767e\u798f\u91cc",
    "qs:name_adm0":"\u81fa\u7063",
    "qs:name_adm1":"\u57fa\u9686\u5e02",
    "qs:photos":32,
    "qs:photos_1k":6,
    "qs:photos_9k":1,
    "qs:photos_9r":2,
    "qs:photos_all":32,
    "qs:photos_sr":2,
    "qs:placetype":"Suburb",
    "qs:pop_sr":"0",
    "wof:name":"Baifu",
    "wof:placetype":"neighbourhood"
},
  "geometry": {"coordinates":[121.694011,25.088016],"type":"Point"}
}