{
  "type": "Feature",
  "properties": {
    "iso:country":"TW",
    "qs:name":"\u5e73\u7530\u91cc",
    "qs:name_adm0":"\u81fa\u7063",
    "qs:name_adm1":"\u53f0\u4e2d\u5e02",
    "qs:photos":19,
    "qs:photos_1k":4,
    "qs:photos_9k":1,
    "qs:photos_9r":1,
    "qs:photos_all":19,
    "qs:photos_sr":1,
    "qs:placetype":"Suburb",
    "qs:pop_sr":"0",
    "wd:wordcount":198,
    "wof:name":"\u5e73\u7530\u91cc",
    "wof:placetype":"neighbourhood"
},
  "geometry": {"coordinates":[120.692924,24.171813],"type":"Point"}
}