{
  "type": "Feature",
  "properties": {
    "gn:admin1_code":"04",
    "gn:admin2_code":"NAN",
    "gn:admin3_code":"M13",
    "gn:admin4_code":"10008130004.0",
    "gn:asciiname":"Neifengzilin",
    "gn:country_code":"TW",
    "gn:dem":627,
    "gn:feature_class":"P",
    "gn:feature_code":"PPL",
    "gn:name":"Neifengzilin",
    "gn:population":0,
    "gn:timezone":"Asia/Taipei",
    "iso:country":"TW",
    "name:und_x_variant":[
        "Neifongzihlin",
        "Nei-feng-tzu-lin"
    ],
    "name:zho_x_preferred":[
        "\u5167\u6953\u4ed4\u6797"
    ],
    "wof:name":"Neifengzilin",
    "wof:placetype":"locality"
},
  "geometry": {"coordinates":[121.05222000000001,24.00306],"type":"Point"}
}