{
  "type": "Feature",
  "properties": {
    "gn:admin1_code":"4.0",
    "gn:admin2_code":"ILA",
    "gn:admin3_code":"G03",
    "gn:admin4_code":"10002050011.0",
    "gn:asciiname":"Linwei",
    "gn:country_code":"TW",
    "gn:dem":25,
    "gn:feature_class":"P",
    "gn:feature_code":"PPL",
    "gn:name":"Linwei",
    "gn:population":0,
    "gn:timezone":"Asia/Taipei",
    "iso:country":"TW",
    "name:und_x_variant":[
        "Lin-wei"
    ],
    "name:zho_x_preferred":[
        "\u6797\u5c3e"
    ],
    "wof:name":"Linwei",
    "wof:placetype":"locality"
},
  "geometry": {"coordinates":[121.75075,24.81295],"type":"Point"}
}