{
  "type": "Feature",
  "properties": {
    "gn:admin1_code":"03",
    "gn:admin2_code":"TPQ",
    "gn:admin3_code":"F15",
    "gn:admin4_code":"65000090016.0",
    "gn:asciiname":"Shuangxi",
    "gn:country_code":"TW",
    "gn:dem":246,
    "gn:feature_class":"P",
    "gn:feature_code":"PPL",
    "gn:name":"Shuangxi",
    "gn:population":0,
    "gn:timezone":"Asia/Taipei",
    "iso:country":"TW",
    "name:ceb_x_preferred":[
        "Shuangxi"
    ],
    "name:deu_x_preferred":[
        "Shuangxi"
    ],
    "name:swe_x_preferred":[
        "Shuangxi"
    ],
    "name:und_x_variant":[
        "Shuangsi",
        "Shuang-hsi"
    ],
    "name:zho_x_preferred":[
        "Shuang-ch\u2019i"
    ],
    "name:zho_x_variant":[
        "\u96d9\u6eaa"
    ],
    "wof:name":"Shuangxi",
    "wof:placetype":"locality"
},
  "geometry": {"coordinates":[121.43738,24.85298],"type":"Point"}
}