{
  "type": "Feature",
  "properties": {
    "gn:admin1_code":"4.0",
    "gn:admin2_code":"TAO",
    "gn:admin3_code":"H02",
    "gn:admin4_code":"68000030007.0",
    "gn:asciiname":"Sancengqiding",
    "gn:country_code":"TW",
    "gn:dem":207,
    "gn:feature_class":"P",
    "gn:feature_code":"PPL",
    "gn:name":"Sancengqiding",
    "gn:population":0,
    "gn:timezone":"Asia/Taipei",
    "iso:country":"TW",
    "name:und_x_variant":[
        "Sancengciding"
    ],
    "name:zho_x_preferred":[
        "\u4e09\u5c64\u5d0e\u9802"
    ],
    "name:zho_x_variant":[
        "San-ts\u2019eng-ch\u2019i-ting"
    ],
    "wof:name":"Sancengqiding",
    "wof:placetype":"locality"
},
  "geometry": {"coordinates":[121.29725999999999,24.86569],"type":"Point"}
}