{
  "type": "Feature",
  "properties": {
    "gn:admin1_code":"4.0",
    "gn:admin2_code":"NAN",
    "gn:admin3_code":"M11",
    "gn:admin4_code":"10008110017.0",
    "gn:asciiname":"Shiya",
    "gn:country_code":"TW",
    "gn:dem":741,
    "gn:feature_class":"P",
    "gn:feature_code":"PPL",
    "gn:name":"Shiya",
    "gn:population":0,
    "gn:timezone":"Asia/Taipei",
    "iso:country":"TW",
    "name:und_x_variant":[
        "Shihya",
        "Shiya",
        "Shih-ya"
    ],
    "name:zho_x_preferred":[
        "\u77f3\u7259"
    ],
    "wof:name":"Shiya",
    "wof:placetype":"locality"
},
  "geometry": {"coordinates":[120.81871,23.78089],"type":"Point"}
}