{
  "type": "Feature",
  "properties": {
    "gn:admin1_code":"4.0",
    "gn:admin2_code":"PEN",
    "gn:admin3_code":"X02",
    "gn:admin4_code":"10016020021.0",
    "gn:asciiname":"Longmen",
    "gn:country_code":"TW",
    "gn:dem":9,
    "gn:feature_class":"P",
    "gn:feature_code":"PPL",
    "gn:name":"Longmen",
    "gn:population":0,
    "gn:timezone":"Asia/Taipei",
    "iso:country":"TW",
    "name:ceb_x_preferred":[
        "Longmen"
    ],
    "name:deu_x_preferred":[
        "Longmen"
    ],
    "name:fra_x_preferred":[
        "Longmen"
    ],
    "name:mlg_x_preferred":[
        "Longmen"
    ],
    "name:nor_x_preferred":[
        "Longmen"
    ],
    "name:pol_x_preferred":[
        "Longmen"
    ],
    "name:und_x_variant":[
        "Liang-wen-chiang",
        "Liang-wen-kang",
        "Lung-men"
    ],
    "name:vie_x_preferred":[
        "Long M\u00f4n"
    ],
    "name:zho_x_preferred":[
        "Lung-men-ts\u2019un"
    ],
    "name:zho_x_variant":[
        "\u9f8d\u9580"
    ],
    "wof:name":"Longmen",
    "wof:placetype":"locality"
},
  "geometry": {"coordinates":[119.67331,23.56356],"type":"Point"}
}