{
  "type": "Feature",
  "properties": {
    "iso:country":"TW",
    "qs:name":"\u4e0a\u56db\u6751",
    "qs:name_adm0":"\u81fa\u7063",
    "qs:name_adm1":"\u5b9c\u862d\u7e23",
    "qs:photos":55,
    "qs:photos_1k":11,
    "qs:photos_9k":1,
    "qs:photos_9r":2,
    "qs:photos_all":55,
    "qs:photos_sr":2,
    "qs:placetype":"Town",
    "qs:pop_sr":"0",
    "wof:name":"\u4e0a\u56db\u6751",
    "wof:placetype":"locality"
},
  "geometry": {"coordinates":[121.76720299999999,24.697743],"type":"Point"}
}