{
  "type": "Feature",
  "properties": {
    "gn:admin1_code":"4.0",
    "gn:admin2_code":"HSZ",
    "gn:admin3_code":"J11",
    "gn:admin4_code":"10004100009.0",
    "gn:asciiname":"Wuhua",
    "gn:country_code":"TW",
    "gn:dem":157,
    "gn:feature_class":"P",
    "gn:feature_code":"PPL",
    "gn:name":"Wuhua",
    "gn:population":0,
    "gn:timezone":"Asia/Taipei",
    "iso:country":"TW",
    "name:und_x_variant":[
        "Wu-hua"
    ],
    "name:zho_x_preferred":[
        "\u4e94\u5316"
    ],
    "wof:name":"Wuhua",
    "wof:placetype":"locality"
},
  "geometry": {"coordinates":[121.00682999999999,24.71882],"type":"Point"}
}