{
  "type": "Feature",
  "properties": {
    "gn:admin1_code":"4.0",
    "gn:admin2_code":"MIA",
    "gn:admin3_code":"K05",
    "gn:admin4_code":"10005100001.0",
    "gn:asciiname":"Jinxing",
    "gn:country_code":"TW",
    "gn:dem":158,
    "gn:feature_class":"P",
    "gn:feature_code":"PPL",
    "gn:name":"Jinxing",
    "gn:population":0,
    "gn:timezone":"Asia/Taipei",
    "iso:country":"TW",
    "name:und_x_variant":[
        "Jinsing",
        "Chin-hsing"
    ],
    "name:zho_x_preferred":[
        "\u9326\u8208"
    ],
    "wof:name":"Jinxing",
    "wof:placetype":"locality"
},
  "geometry": {"coordinates":[120.78937000000001,24.4928],"type":"Point"}
}