{
  "type": "Feature",
  "properties": {
    "gn:admin1_code":"4.0",
    "gn:admin2_code":"CYQ",
    "gn:admin3_code":"Q18",
    "gn:admin4_code":"10010170005.0",
    "gn:asciiname":"Qilaizi",
    "gn:country_code":"TW",
    "gn:dem":264,
    "gn:feature_class":"P",
    "gn:feature_code":"PPL",
    "gn:name":"Qilaizi",
    "gn:population":0,
    "gn:timezone":"Asia/Taipei",
    "iso:country":"TW",
    "name:und_x_variant":[
        "Cilaizih",
        "Qilaizi"
    ],
    "name:zho_x_preferred":[
        "\u4e03\u7028\u5b50"
    ],
    "name:zho_x_variant":[
        "Ch\u2019i-lai-tzu"
    ],
    "wof:name":"Qilaizi",
    "wof:placetype":"locality"
},
  "geometry": {"coordinates":[120.5609,23.26314],"type":"Point"}
}