{
  "type": "Feature",
  "properties": {
    "gn:admin1_code":"4.0",
    "gn:admin2_code":"HSQ",
    "gn:admin3_code":"O03",
    "gn:admin4_code":"10018030012.0",
    "gn:asciiname":"Zhucuoyuan",
    "gn:country_code":"TW",
    "gn:dem":13,
    "gn:feature_class":"P",
    "gn:feature_code":"PPL",
    "gn:name":"Zhucuoyuan",
    "gn:population":0,
    "gn:timezone":"Asia/Taipei",
    "iso:country":"TW",
    "name:und_x_variant":[
        "Jhucuoyuan",
        "Zhucuoyuan"
    ],
    "name:zho_x_preferred":[
        "\u4e3b\u539d\u5712"
    ],
    "name:zho_x_variant":[
        "Chu-ts\u2019o-y\u00fcan"
    ],
    "wof:name":"Zhucuoyuan",
    "wof:placetype":"locality"
},
  "geometry": {"coordinates":[120.92638999999998,24.7925],"type":"Point"}
}