{
  "type": "Feature",
  "properties": {
    "gn:admin1_code":"2.0",
    "gn:admin2_code":"KHH",
    "gn:admin3_code":"E30",
    "gn:admin4_code":"64000300018.0",
    "gn:asciiname":"Doudengkeng",
    "gn:country_code":"TW",
    "gn:dem":88,
    "gn:feature_class":"P",
    "gn:feature_code":"PPL",
    "gn:name":"Doudengkeng",
    "gn:population":0,
    "gn:timezone":"Asia/Taipei",
    "iso:country":"TW",
    "name:zho_x_preferred":[
        "\u6597\u767b\u5751"
    ],
    "name:zho_x_variant":[
        "Tou-teng-k\u2019eng"
    ],
    "wof:name":"Doudengkeng",
    "wof:placetype":"locality"
},
  "geometry": {"coordinates":[120.45694,22.85861],"type":"Point"}
}