{
  "type": "Feature",
  "properties": {
    "gn:admin1_code":"4.0",
    "gn:admin2_code":"TAO",
    "gn:admin3_code":"H04",
    "gn:admin4_code":"68000040037.0",
    "gn:asciiname":"Dabogong",
    "gn:country_code":"TW",
    "gn:dem":166,
    "gn:feature_class":"P",
    "gn:feature_code":"PPL",
    "gn:name":"Dabogong",
    "gn:population":0,
    "gn:timezone":"Asia/Taipei",
    "iso:country":"TW",
    "name:und_x_variant":[
        "Ta-po-kung"
    ],
    "name:zho_x_preferred":[
        "\u5927\u4f2f\u516c"
    ],
    "wof:name":"Dabogong",
    "wof:placetype":"locality"
},
  "geometry": {"coordinates":[121.15833000000001,24.93278],"type":"Point"}
}