{
  "type": "Feature",
  "properties": {
    "gn:admin1_code":"4.0",
    "gn:admin2_code":"YUN",
    "gn:admin3_code":"P11",
    "gn:admin4_code":"10009110002.0",
    "gn:asciiname":"Xiazhuangzi",
    "gn:country_code":"TW",
    "gn:dem":24,
    "gn:feature_class":"P",
    "gn:feature_code":"PPL",
    "gn:name":"Xiazhuangzi",
    "gn:population":0,
    "gn:timezone":"Asia/Taipei",
    "iso:country":"TW",
    "name:und_x_variant":[
        "Hsia-chuang",
        "Xiazhuangzi",
        "Siajhuangzih",
        "Hsia-chuang-tzu"
    ],
    "name:zho_x_preferred":[
        "\u4e0b\u838a\u5b50"
    ],
    "wof:name":"Xiazhuangzi",
    "wof:placetype":"locality"
},
  "geometry": {"coordinates":[120.40464,23.76999],"type":"Point"}
}