{
  "type": "Feature",
  "properties": {
    "gn:admin1_code":"4.0",
    "gn:admin2_code":"TNN",
    "gn:admin3_code":"R10",
    "gn:admin4_code":"67000100005.0",
    "gn:asciiname":"Dajing",
    "gn:country_code":"TW",
    "gn:dem":98,
    "gn:feature_class":"P",
    "gn:feature_code":"PPL",
    "gn:name":"Dajing",
    "gn:population":0,
    "gn:timezone":"Asia/Taipei",
    "iso:country":"TW",
    "name:und_x_variant":[
        "Ta-ching"
    ],
    "name:zho_x_preferred":[
        "\u5927\u4e95"
    ],
    "wof:name":"Dajing",
    "wof:placetype":"locality"
},
  "geometry": {"coordinates":[120.39892999999999,23.18021],"type":"Point"}
}