{
  "type": "Feature",
  "properties": {
    "iso:country":"TW",
    "name:eng_x_preferred":[
        "Meihe"
    ],
    "name:eng_x_variant":[
        "Meihe Village"
    ],
    "name:zho_tw_x_preferred":[
        "\u7f8e\u548c\u6751"
    ],
    "qs:name":"\u7f8e\u548c\u6751",
    "qs:name_adm0":"\u81fa\u7063",
    "qs:name_adm1":"\u5c4f\u6771\u7e23",
    "qs:photos":1,
    "qs:photos_1k":1,
    "qs:photos_9k":1,
    "qs:photos_9r":1,
    "qs:photos_all":1,
    "qs:photos_sr":1,
    "qs:placetype":"Town",
    "qs:pop_sr":"0",
    "wof:name":"Meihe",
    "wof:placetype":"locality"
},
  "geometry": {"coordinates":[120.558983,22.593441],"type":"Point"}
}