{
  "type": "Feature",
  "properties": {
    "gn:admin1_code":"4.0",
    "gn:admin2_code":"TPE",
    "gn:admin3_code":"A16",
    "gn:admin4_code":"63000120008.0",
    "gn:asciiname":"Lanya",
    "gn:country_code":"TW",
    "gn:dem":16,
    "gn:feature_class":"P",
    "gn:feature_code":"PPL",
    "gn:name":"Lanya",
    "gn:population":0,
    "gn:timezone":"Asia/Taipei",
    "iso:country":"TW",
    "name:und_x_variant":[
        "Lan-ya-li",
        "Lan-ya",
        "Lanya"
    ],
    "wof:name":"Lanya",
    "wof:placetype":"locality"
},
  "geometry": {"coordinates":[121.51667,25.11667000000001],"type":"Point"}
}