{
  "type": "Feature",
  "properties": {
    "iso:country":"TW",
    "qs:name":"\u9806\u8208\u91cc",
    "qs:name_adm0":"\u81fa\u7063",
    "qs:name_adm1":"\u53f0\u5317\u5e02",
    "qs:photos":166,
    "qs:photos_1k":34,
    "qs:photos_9k":1,
    "qs:photos_9r":4,
    "qs:photos_all":166,
    "qs:photos_sr":4,
    "qs:placetype":"Suburb",
    "qs:pop_sr":"0",
    "wof:name":"\u9806\u8208\u91cc",
    "wof:placetype":"neighbourhood"
},
  "geometry": {"coordinates":[121.5635,24.983333],"type":"Point"}
}