{
  "type": "Feature",
  "properties": {
    "gn:admin1_code":"4.0",
    "gn:admin2_code":"CHA",
    "gn:admin3_code":"N01",
    "gn:admin4_code":"10007010053.0",
    "gn:asciiname":"Xiangshanzhuang",
    "gn:country_code":"TW",
    "gn:dem":41,
    "gn:feature_class":"P",
    "gn:feature_code":"PPL",
    "gn:name":"Xiangshanzhuang",
    "gn:population":0,
    "gn:timezone":"Asia/Taipei",
    "iso:country":"TW",
    "name:und_x_variant":[
        "Fan-she-k\u2019ou",
        "Hsiang-shan",
        "Hsiang-shan-li",
        "Siangshanjhuang",
        "Xiangshanzhuang",
        "Hsiang-shan-chuang"
    ],
    "name:zho_x_preferred":[
        "\u9999\u5c71\u838a"
    ],
    "wof:name":"Xiangshanzhuang",
    "wof:placetype":"locality"
},
  "geometry": {"coordinates":[120.59021,24.08172],"type":"Point"}
}