{
  "type": "Feature",
  "properties": {
    "gn:admin1_code":"4.0",
    "gn:admin2_code":"TAO",
    "gn:admin3_code":"H11",
    "gn:admin4_code":"68000110003.0",
    "gn:asciiname":"Hewu",
    "gn:country_code":"TW",
    "gn:dem":60,
    "gn:feature_class":"P",
    "gn:feature_code":"PPL",
    "gn:name":"Hewu",
    "gn:population":0,
    "gn:timezone":"Asia/Taipei",
    "iso:country":"TW",
    "name:und_x_variant":[
        "Ho-wu"
    ],
    "name:zho_x_preferred":[
        "\u4f55\u5c4b"
    ],
    "wof:name":"Hewu",
    "wof:placetype":"locality"
},
  "geometry": {"coordinates":[121.0825,24.98444],"type":"Point"}
}