{
  "type": "Feature",
  "properties": {
    "gn:admin1_code":"04",
    "gn:admin2_code":"TXG",
    "gn:admin3_code":"B16",
    "gn:admin4_code":"66000160008.0",
    "gn:asciiname":"Wangliao",
    "gn:country_code":"TW",
    "gn:dem":193,
    "gn:feature_class":"P",
    "gn:feature_code":"PPL",
    "gn:name":"Wangliao",
    "gn:population":0,
    "gn:timezone":"Asia/Taipei",
    "iso:country":"TW",
    "name:und_x_variant":[
        "Wang-liao"
    ],
    "name:zho_x_preferred":[
        "\u671b\u5bee"
    ],
    "wof:name":"Wangliao",
    "wof:placetype":"locality"
},
  "geometry": {"coordinates":[120.69306,24.24917],"type":"Point"}
}