{
  "type": "Feature",
  "properties": {
    "gn:admin1_code":"4.0",
    "gn:admin2_code":"TNN",
    "gn:admin3_code":"R24",
    "gn:admin4_code":"67000240005.0",
    "gn:asciiname":"Dalin",
    "gn:country_code":"TW",
    "gn:dem":86,
    "gn:feature_class":"P",
    "gn:feature_code":"PPL",
    "gn:name":"Dalin",
    "gn:population":0,
    "gn:timezone":"Asia/Taipei",
    "iso:country":"TW",
    "name:und_x_variant":[
        "Ta-lin"
    ],
    "name:zho_x_preferred":[
        "\u5927\u6797"
    ],
    "wof:name":"Dalin",
    "wof:placetype":"locality"
},
  "geometry": {"coordinates":[120.4838,23.15359],"type":"Point"}
}