{
  "type": "Feature",
  "properties": {
    "gn:admin1_code":"4.0",
    "gn:admin2_code":"NAN",
    "gn:admin3_code":"M09",
    "gn:admin4_code":"10008090012.0",
    "gn:asciiname":"Chonggui",
    "gn:country_code":"TW",
    "gn:dem":615,
    "gn:feature_class":"P",
    "gn:feature_code":"PPL",
    "gn:name":"Chonggui",
    "gn:population":0,
    "gn:timezone":"Asia/Taipei",
    "iso:country":"TW",
    "name:und_x_variant":[
        "Chongguei"
    ],
    "name:zho_x_preferred":[
        "\u9283\u6ac3"
    ],
    "name:zho_x_variant":[
        "Ch\u2019ung-kuei"
    ],
    "wof:name":"Chonggui",
    "wof:placetype":"locality"
},
  "geometry": {"coordinates":[120.88222,23.81852],"type":"Point"}
}