{
  "type": "Feature",
  "properties": {
    "gn:admin1_code":"04",
    "gn:admin2_code":"NAN",
    "gn:admin3_code":"M06",
    "gn:admin4_code":"10008060022.0",
    "gn:asciiname":"Xinguangcun",
    "gn:country_code":"TW",
    "gn:dem":200,
    "gn:feature_class":"P",
    "gn:feature_code":"PPL",
    "gn:name":"Xinguangcun",
    "gn:population":0,
    "gn:timezone":"Asia/Taipei",
    "iso:country":"TW",
    "name:und_x_variant":[
        "Singuangcun",
        "Xinguangcun",
        "San-kuang"
    ],
    "name:zho_x_preferred":[
        "San-kuang-ts\u2019un"
    ],
    "name:zho_x_variant":[
        "San-kung-ts\u2019un",
        "\u65b0\u5149\u6751",
        "Hsin-kuang-ts\u2019un"
    ],
    "wof:name":"Xinguangcun",
    "wof:placetype":"locality"
},
  "geometry": {"coordinates":[120.67645,23.85612],"type":"Point"}
}