{
  "type": "Feature",
  "properties": {
    "gn:admin1_code":"4.0",
    "gn:admin2_code":"MIA",
    "gn:admin3_code":"K06",
    "gn:admin4_code":"10005130005.0",
    "gn:asciiname":"Liudong",
    "gn:country_code":"TW",
    "gn:dem":376,
    "gn:feature_class":"P",
    "gn:feature_code":"PPL",
    "gn:name":"Liudong",
    "gn:population":0,
    "gn:timezone":"Asia/Taipei",
    "iso:country":"TW",
    "name:und_x_variant":[
        "Liu-tung-k\u2019eng",
        "Liu-tung",
        "Liudong"
    ],
    "wof:name":"Liudong",
    "wof:placetype":"locality"
},
  "geometry": {"coordinates":[120.75,24.38333],"type":"Point"}
}