{
  "type": "Feature",
  "properties": {
    "gn:admin1_code":"4.0",
    "gn:admin2_code":"PIF",
    "gn:admin3_code":"T03",
    "gn:admin4_code":"10013030016.0",
    "gn:asciiname":"Chuantou",
    "gn:country_code":"TW",
    "gn:dem":5,
    "gn:feature_class":"P",
    "gn:feature_code":"PPL",
    "gn:name":"Chuantou",
    "gn:population":0,
    "gn:timezone":"Asia/Taipei",
    "iso:country":"TW",
    "name:zho_x_preferred":[
        "\u8239\u982d"
    ],
    "name:zho_x_variant":[
        "Ch\u2019uan-tzu-t\u2019ou",
        "Ch\u2019uan-t\u2019ou"
    ],
    "wof:name":"Chuantou",
    "wof:placetype":"locality"
},
  "geometry": {"coordinates":[120.46836,22.46391],"type":"Point"}
}