{
  "type": "Feature",
  "properties": {
    "gn:admin1_code":"2.0",
    "gn:admin2_code":"KHH",
    "gn:admin3_code":"E22",
    "gn:admin4_code":"64000220002.0",
    "gn:asciiname":"Qiongzibu",
    "gn:country_code":"TW",
    "gn:dem":40,
    "gn:feature_class":"P",
    "gn:feature_code":"PPL",
    "gn:name":"Qiongzibu",
    "gn:population":0,
    "gn:timezone":"Asia/Taipei",
    "iso:country":"TW",
    "name:und_x_variant":[
        "Cyongzihbu"
    ],
    "name:zho_x_preferred":[
        "\u74ca\u4ed4\u57d4"
    ],
    "name:zho_x_variant":[
        "Ch\u2019ien-tzu-pu",
        "Ch\u2019iung-tzu-pu"
    ],
    "wof:name":"Qiongzibu",
    "wof:placetype":"locality"
},
  "geometry": {"coordinates":[120.37027999999999,22.865],"type":"Point"}
}