{
  "type": "Feature",
  "properties": {
    "gn:admin1_code":"4.0",
    "gn:admin2_code":"YUN",
    "gn:admin3_code":"P10",
    "gn:admin4_code":"10009100008.0",
    "gn:asciiname":"Ruihe",
    "gn:country_code":"TW",
    "gn:dem":72,
    "gn:feature_class":"P",
    "gn:feature_code":"PPL",
    "gn:name":"Ruihe",
    "gn:population":0,
    "gn:timezone":"Asia/Taipei",
    "iso:country":"TW",
    "name:und_x_variant":[
        "Rueihe",
        "Ruihe",
        "Jui-ho"
    ],
    "name:zho_x_preferred":[
        "\u745e\u548c"
    ],
    "wof:name":"Ruihe",
    "wof:placetype":"locality"
},
  "geometry": {"coordinates":[120.59068000000001,23.77037],"type":"Point"}
}