{
  "type": "Feature",
  "properties": {
    "gn:admin1_code":"4.0",
    "gn:admin2_code":"TXG",
    "gn:admin3_code":"B19",
    "gn:admin4_code":"66000190013.0",
    "gn:asciiname":"Mazhukeng",
    "gn:country_code":"TW",
    "gn:dem":527,
    "gn:feature_class":"P",
    "gn:feature_code":"PPL",
    "gn:name":"Mazhukeng",
    "gn:population":0,
    "gn:timezone":"Asia/Taipei",
    "iso:country":"TW",
    "name:und_x_variant":[
        "Majhukeng"
    ],
    "name:zho_x_preferred":[
        "\u9ebb\u7af9\u5751"
    ],
    "name:zho_x_variant":[
        "Ma-chu-k\u2019eng"
    ],
    "wof:name":"Mazhukeng",
    "wof:placetype":"locality"
},
  "geometry": {"coordinates":[120.86346,24.15555],"type":"Point"}
}