{
  "type": "Feature",
  "properties": {
    "gn:admin1_code":"4.0",
    "gn:admin2_code":"NAN",
    "gn:admin3_code":"M13",
    "gn:admin4_code":"10008130009.0",
    "gn:asciiname":"Gaolengdi",
    "gn:country_code":"TW",
    "gn:dem":1071,
    "gn:feature_class":"P",
    "gn:feature_code":"PPL",
    "gn:name":"Gaolengdi",
    "gn:population":0,
    "gn:timezone":"Asia/Taipei",
    "iso:country":"TW",
    "name:und_x_variant":[
        "Pa-lan-she",
        "Kao-leng-ti",
        "Gaolengdi"
    ],
    "wof:name":"Gaolengdi",
    "wof:placetype":"locality"
},
  "geometry": {"coordinates":[121.11667,24.01667],"type":"Point"}
}