{
  "type": "Feature",
  "properties": {
    "gn:admin1_code":"1.0",
    "gn:admin2_code":"KIN",
    "gn:admin3_code":"W03",
    "gn:admin4_code":"9020010007.0",
    "gn:asciiname":"Xiaoximen",
    "gn:country_code":"TW",
    "gn:dem":31,
    "gn:feature_class":"P",
    "gn:feature_code":"PPL",
    "gn:name":"Xiaoximen",
    "gn:population":0,
    "gn:timezone":"Asia/Taipei",
    "iso:country":"TW",
    "name:und_x_variant":[
        "Hsiao-hsi-men"
    ],
    "name:zho_x_preferred":[
        "\u5c0f\u897f\u9580"
    ],
    "wof:name":"Xiaoximen",
    "wof:placetype":"locality"
},
  "geometry": {"coordinates":[118.32883,24.41168],"type":"Point"}
}