{
  "type": "Feature",
  "properties": {
    "gn:admin1_code":"04",
    "gn:admin2_code":"CYQ",
    "gn:admin3_code":"Q16",
    "gn:admin4_code":"10010150009.0",
    "gn:asciiname":"Dapiantian",
    "gn:country_code":"TW",
    "gn:dem":152,
    "gn:feature_class":"P",
    "gn:feature_code":"PPL",
    "gn:name":"Dapiantian",
    "gn:population":0,
    "gn:timezone":"Asia/Taipei",
    "iso:country":"TW",
    "name:zho_x_preferred":[
        "\u5927\u7247\u7530"
    ],
    "name:zho_x_variant":[
        "Ta-p\u2019ien-t\u2019ien"
    ],
    "wof:name":"Dapiantian",
    "wof:placetype":"locality"
},
  "geometry": {"coordinates":[120.55833,23.5525],"type":"Point"}
}