{
  "type": "Feature",
  "properties": {
    "iso:country":"TW",
    "name:eng_x_preferred":[
        "Ruili"
    ],
    "name:eng_x_variant":[
        "Ruili Village"
    ],
    "name:zho_tw_x_preferred":[
        "\u745e\u91cc\u6751"
    ],
    "qs:name":"\u745e\u91cc\u6751",
    "qs:name_adm0":"\u81fa\u7063",
    "qs:name_adm1":"\u5609\u7fa9\u7e23",
    "qs:photos":91,
    "qs:photos_1k":18,
    "qs:photos_9k":1,
    "qs:photos_9r":3,
    "qs:photos_all":91,
    "qs:photos_sr":3,
    "qs:placetype":"Town",
    "qs:pop_sr":"0",
    "wof:name":"Ruili",
    "wof:placetype":"locality"
},
  "geometry": {"coordinates":[120.694677,23.504775],"type":"Point"}
}