{
  "type": "Feature",
  "properties": {
    "gn:admin1_code":"4.0",
    "gn:admin2_code":"TXG",
    "gn:admin3_code":"B16",
    "gn:admin4_code":"66000160002.0",
    "gn:asciiname":"Zhuangqian",
    "gn:country_code":"TW",
    "gn:dem":170,
    "gn:feature_class":"P",
    "gn:feature_code":"PPL",
    "gn:name":"Zhuangqian",
    "gn:population":0,
    "gn:timezone":"Asia/Taipei",
    "iso:country":"TW",
    "name:und_x_variant":[
        "Jhuangcian",
        "Zhuangqian"
    ],
    "name:zho_x_preferred":[
        "\u5e84\u524d"
    ],
    "name:zho_x_variant":[
        "Chuang-ch\u2019ien"
    ],
    "wof:name":"Zhuangqian",
    "wof:placetype":"locality"
},
  "geometry": {"coordinates":[120.65416999999999,24.25222],"type":"Point"}
}