{
  "type": "Feature",
  "properties": {
    "gn:admin1_code":"4.0",
    "gn:admin2_code":"MIA",
    "gn:admin3_code":"K17",
    "gn:admin4_code":"10005170003.0",
    "gn:asciiname":"Sanfen",
    "gn:country_code":"TW",
    "gn:dem":258,
    "gn:feature_class":"P",
    "gn:feature_code":"PPL",
    "gn:name":"Sanfen",
    "gn:population":0,
    "gn:timezone":"Asia/Taipei",
    "iso:country":"TW",
    "name:und_x_variant":[
        "San-fen"
    ],
    "name:zho_x_preferred":[
        "\u4e09\u4efd"
    ],
    "wof:name":"Sanfen",
    "wof:placetype":"locality"
},
  "geometry": {"coordinates":[120.92941999999999,24.53083],"type":"Point"}
}