{
  "type": "Feature",
  "properties": {
    "gn:admin1_code":"4.0",
    "gn:admin2_code":"TNN",
    "gn:admin3_code":"R25",
    "gn:admin4_code":"67000250002.0",
    "gn:asciiname":"Qiaozinei",
    "gn:country_code":"TW",
    "gn:dem":134,
    "gn:feature_class":"P",
    "gn:feature_code":"PPL",
    "gn:name":"Qiaozinei",
    "gn:population":0,
    "gn:timezone":"Asia/Taipei",
    "iso:country":"TW",
    "name:und_x_variant":[
        "Ciaozihnei",
        "Qiaozinei"
    ],
    "name:zho_x_preferred":[
        "\u6a4b\u4ed4\u5167"
    ],
    "name:zho_x_variant":[
        "Ch\u2019iao-tzu-nei"
    ],
    "wof:name":"Qiaozinei",
    "wof:placetype":"locality"
},
  "geometry": {"coordinates":[120.48992,23.05039],"type":"Point"}
}