{
  "type": "Feature",
  "properties": {
    "gn:admin1_code":"4.0",
    "gn:admin2_code":"NAN",
    "gn:admin3_code":"M08",
    "gn:admin4_code":"10008080005.0",
    "gn:asciiname":"Xiaomao",
    "gn:country_code":"TW",
    "gn:dem":214,
    "gn:feature_class":"P",
    "gn:feature_code":"PPL",
    "gn:name":"Xiaomao",
    "gn:population":0,
    "gn:timezone":"Asia/Taipei",
    "iso:country":"TW",
    "name:und_x_variant":[
        "Siaomao",
        "Xiaomao",
        "Hsiao-mao"
    ],
    "name:zho_x_preferred":[
        "Fu-hsing-ts\u2019un"
    ],
    "name:zho_x_variant":[
        "\u54ee\u732b"
    ],
    "wof:name":"Xiaomao",
    "wof:placetype":"locality"
},
  "geometry": {"coordinates":[120.79472,23.88039],"type":"Point"}
}