{
  "type": "Feature",
  "properties": {
    "gn:admin1_code":"04",
    "gn:admin2_code":"CHA",
    "gn:admin3_code":"N08",
    "gn:admin4_code":"10007200013.0",
    "gn:asciiname":"Wanggongliao",
    "gn:country_code":"TW",
    "gn:dem":13,
    "gn:feature_class":"P",
    "gn:feature_code":"PPL",
    "gn:name":"Wanggongliao",
    "gn:population":0,
    "gn:timezone":"Asia/Taipei",
    "iso:country":"TW",
    "name:und_x_variant":[
        "Ting-lun-li",
        "Wanggongliao",
        "Ting-lun",
        "Wang-kung-liao"
    ],
    "name:zho_x_preferred":[
        "\u738b\u529f\u5bee"
    ],
    "wof:name":"Wanggongliao",
    "wof:placetype":"locality"
},
  "geometry": {"coordinates":[120.38021000000001,23.9231],"type":"Point"}
}