{
  "type": "Feature",
  "properties": {
    "gn:admin1_code":"04",
    "gn:admin2_code":"TPE",
    "gn:admin3_code":"A16",
    "gn:admin4_code":"63000120035.0",
    "gn:asciiname":"Beizitou",
    "gn:country_code":"TW",
    "gn:dem":243,
    "gn:feature_class":"P",
    "gn:feature_code":"PPL",
    "gn:name":"Beizitou",
    "gn:population":0,
    "gn:timezone":"Asia/Taipei",
    "iso:country":"TW",
    "name:und_x_variant":[
        "Pei-tzu-t\u2019ou"
    ],
    "wof:name":"Beizitou",
    "wof:placetype":"locality"
},
  "geometry": {"coordinates":[121.48333,25.15],"type":"Point"}
}