{
  "type": "Feature",
  "properties": {
    "gn:admin1_code":"2.0",
    "gn:admin2_code":"KHH",
    "gn:admin3_code":"E14",
    "gn:admin4_code":"64000140012.0",
    "gn:asciiname":"Xincuo",
    "gn:country_code":"TW",
    "gn:dem":16,
    "gn:feature_class":"P",
    "gn:feature_code":"PPL",
    "gn:name":"Xincuo",
    "gn:population":0,
    "gn:timezone":"Asia/Taipei",
    "iso:country":"TW",
    "name:und_x_variant":[
        "Xincuo",
        "Sincuo"
    ],
    "name:zho_x_preferred":[
        "Hsin-ts\u2019o"
    ],
    "name:zho_x_variant":[
        "Hsin-ts\u2019o-ts\u2019un",
        "\u65b0\u539d"
    ],
    "wof:name":"Xincuo",
    "wof:placetype":"locality"
},
  "geometry": {"coordinates":[120.40900000000001,22.5617],"type":"Point"}
}