{
  "type": "Feature",
  "properties": {
    "gn:admin1_code":"4.0",
    "gn:admin2_code":"TAO",
    "gn:admin3_code":"H11",
    "gn:admin4_code":"68000110022.0",
    "gn:asciiname":"Dapo",
    "gn:country_code":"TW",
    "gn:dem":40,
    "gn:feature_class":"P",
    "gn:feature_code":"PPL",
    "gn:name":"Dapo",
    "gn:population":0,
    "gn:timezone":"Asia/Taipei",
    "iso:country":"TW",
    "name:zho_x_preferred":[
        "San-chiao-k\u2019u"
    ],
    "name:zho_x_variant":[
        "\u5927\u5761",
        "Kuang-p\u2019o",
        "Ta-p\u2019o"
    ],
    "wof:name":"Dapo",
    "wof:placetype":"locality"
},
  "geometry": {"coordinates":[121.03943999999998,24.96],"type":"Point"}
}