{
  "type": "Feature",
  "properties": {
    "gn:admin1_code":"4.0",
    "gn:admin2_code":"HUA",
    "gn:admin3_code":"U10",
    "gn:admin4_code":"10015100011.0",
    "gn:asciiname":"Fengnan",
    "gn:country_code":"TW",
    "gn:dem":295,
    "gn:feature_class":"P",
    "gn:feature_code":"PPL",
    "gn:name":"Fengnan",
    "gn:population":0,
    "gn:timezone":"Asia/Taipei",
    "iso:country":"TW",
    "name:und_x_variant":[
        "Pieh-hsi",
        "Fongnan",
        "Fengnan",
        "Hsin-fu",
        "Feng-nan"
    ],
    "name:zho_x_preferred":[
        "\u8c50\u5357"
    ],
    "wof:name":"Fengnan",
    "wof:placetype":"locality"
},
  "geometry": {"coordinates":[121.26851000000001,23.14364],"type":"Point"}
}