{
  "type": "Feature",
  "properties": {
    "gn:admin1_code":"4.0",
    "gn:admin2_code":"TNN",
    "gn:admin3_code":"R17",
    "gn:admin4_code":"67000130010.0",
    "gn:asciiname":"Dingshanliao",
    "gn:country_code":"TW",
    "gn:dem":5,
    "gn:feature_class":"P",
    "gn:feature_code":"PPL",
    "gn:name":"Dingshanliao",
    "gn:population":0,
    "gn:timezone":"Asia/Taipei",
    "iso:country":"TW",
    "name:und_x_variant":[
        "Ting-shan-liao",
        "Dingshanliao",
        "\u9802\u5c71\u5bee"
    ],
    "name:zho_x_preferred":[
        "\u9802\u5c71\u5bee"
    ],
    "wof:name":"Dingshanliao",
    "wof:placetype":"locality"
},
  "geometry": {"coordinates":[120.19556,23.23972],"type":"Point"}
}