{
  "type": "Feature",
  "properties": {
    "gn:admin1_code":"4.0",
    "gn:admin2_code":"HSZ",
    "gn:admin3_code":"J08",
    "gn:admin4_code":"10004080010.0",
    "gn:asciiname":"Dadu",
    "gn:country_code":"TW",
    "gn:dem":178,
    "gn:feature_class":"P",
    "gn:feature_code":"PPL",
    "gn:name":"Dadu",
    "gn:population":0,
    "gn:timezone":"Asia/Taipei",
    "iso:country":"TW",
    "name:und_x_variant":[
        "Hsin-hsing",
        "Dadu",
        "Ta-tu"
    ],
    "name:zho_x_preferred":[
        "\u5927\u809a"
    ],
    "wof:name":"Dadu",
    "wof:placetype":"locality"
},
  "geometry": {"coordinates":[121.13443999999998,24.72556],"type":"Point"}
}