{
  "type": "Feature",
  "properties": {
    "gn:admin1_code":"4.0",
    "gn:admin2_code":"HSZ",
    "gn:admin3_code":"J08",
    "gn:admin4_code":"10004080010.0",
    "gn:asciiname":"Dadu",
    "gn:country_code":"TW",
    "gn:dem":178,
    "gn:feature_class":"P",
    "gn:feature_code":"PPL",
    "gn:name":"Dadu",
    "gn:population":0,
    "gn:timezone":"Asia/Taipei",
    "iso:country":"TW",
    "name:ara_x_preferred":[
        "\u062f\u0627\u062f\u0648"
    ],
    "name:ben_x_preferred":[
        "\u09a1\u09be\u09a6\u09c1"
    ],
    "name:ceb_x_preferred":[
        "Dadu"
    ],
    "name:ces_x_preferred":[
        "Ta-tu"
    ],
    "name:deu_x_preferred":[
        "Dadu"
    ],
    "name:ell_x_preferred":[
        "\u039c\u03c0\u03b1\u03c4\u03bf\u03cd"
    ],
    "name:fra_x_preferred":[
        "Dadu"
    ],
    "name:heb_x_preferred":[
        "\u05d3\u05d0\u05d3\u05d5"
    ],
    "name:hin_x_preferred":[
        "\u0926\u093e\u0926\u0942"
    ],
    "name:hun_x_preferred":[
        "Dadu"
    ],
    "name:ind_x_preferred":[
        "Dadu"
    ],
    "name:nld_x_preferred":[
        "Dadu"
    ],
    "name:nor_x_preferred":[
        "Dadu"
    ],
    "name:por_x_preferred":[
        "Dadu"
    ],
    "name:scn_x_preferred":[
        "Dadu"
    ],
    "name:swe_x_preferred":[
        "Dadu"
    ],
    "name:und_x_variant":[
        "Hsin-hsing"
    ],
    "name:urd_x_preferred":[
        "\u062f\u0627\u062f\u0648"
    ],
    "name:zho_x_preferred":[
        "\u5927\u809a"
    ],
    "wof:name":"Dadu",
    "wof:placetype":"locality"
},
  "geometry": {"coordinates":[121.13444,24.72556],"type":"Point"}
}