{
  "type": "Feature",
  "properties": {
    "iso:country":"TW",
    "name:eng_x_preferred":[
        "Riyue"
    ],
    "name:eng_x_variant":[
        "Riyue Village"
    ],
    "name:zho_tw_x_preferred":[
        "\u65e5\u6708\u6751"
    ],
    "qs:name":"\u65e5\u6708\u6751",
    "qs:name_adm0":"\u81fa\u7063",
    "qs:name_adm1":"\u5357\u6295\u7e23",
    "qs:photos":1870,
    "qs:photos_1k":379,
    "qs:photos_9k":8,
    "qs:photos_9r":9,
    "qs:photos_all":1870,
    "qs:photos_sr":15,
    "qs:placetype":"Town",
    "qs:pop_sr":"0",
    "wof:name":"Riyue",
    "wof:placetype":"locality"
},
  "geometry": {"coordinates":[120.93000000000001,23.849255],"type":"Point"}
}