{
  "type": "Feature",
  "properties": {
    "iso:country":"TW",
    "name:eng_x_preferred":[
        "Rongquan"
    ],
    "name:eng_x_variant":[
        "Rongquan Village"
    ],
    "name:zho_tw_x_preferred":[
        "\u69ae\u6cc9\u6751"
    ],
    "qs:name":"\u69ae\u6cc9\u6751",
    "qs:name_adm0":"\u81fa\u7063",
    "qs:name_adm1":"\u53f0\u4e2d\u5e02",
    "qs:photos":113,
    "qs:photos_1k":23,
    "qs:photos_9k":1,
    "qs:photos_9r":3,
    "qs:photos_all":113,
    "qs:photos_sr":3,
    "qs:placetype":"Town",
    "qs:pop_sr":"0",
    "wof:name":"Rongquan",
    "wof:placetype":"locality"
},
  "geometry": {"coordinates":[120.592203,24.115734],"type":"Point"}
}