{
  "type": "Feature",
  "properties": {
    "gn:admin1_code":"1.0",
    "gn:admin2_code":"KIN",
    "gn:admin3_code":"W01",
    "gn:admin4_code":"9020030007.0",
    "gn:asciiname":"Xibian",
    "gn:country_code":"TW",
    "gn:dem":17,
    "gn:feature_class":"P",
    "gn:feature_code":"PPL",
    "gn:name":"Xibian",
    "gn:population":0,
    "gn:timezone":"Asia/Taipei",
    "iso:country":"TW",
    "name:und_x_variant":[
        "Ch\u2019i-pien",
        "Hsi-pien",
        "Xibian"
    ],
    "name:zho_x_preferred":[
        "\u6eaa\u908a"
    ],
    "wof:name":"Xibian",
    "wof:placetype":"locality"
},
  "geometry": {"coordinates":[118.46003,24.44052000000001],"type":"Point"}
}