{
  "type": "Feature",
  "properties": {
    "gn:admin1_code":"04",
    "gn:admin2_code":"NAN",
    "gn:admin3_code":"M06",
    "gn:admin4_code":"10008060022.0",
    "gn:asciiname":"Shizilu",
    "gn:country_code":"TW",
    "gn:dem":228,
    "gn:feature_class":"P",
    "gn:feature_code":"PPL",
    "gn:name":"Shizilu",
    "gn:population":0,
    "gn:timezone":"Asia/Taipei",
    "iso:country":"TW",
    "name:und_x_variant":[
        "Shihzihlu",
        "Shizilu",
        "Shih-tzu-lu"
    ],
    "name:zho_x_preferred":[
        "\u5341\u5b57\u8def"
    ],
    "wof:name":"Shizilu",
    "wof:placetype":"locality"
},
  "geometry": {"coordinates":[120.66885000000001,23.8499],"type":"Point"}
}