{
  "type": "Feature",
  "properties": {
    "gn:admin1_code":"4.0",
    "gn:admin2_code":"MIA",
    "gn:admin3_code":"K11",
    "gn:admin4_code":"10005150009.0",
    "gn:asciiname":"Zhepou",
    "gn:country_code":"TW",
    "gn:dem":35,
    "gn:feature_class":"P",
    "gn:feature_code":"PPL",
    "gn:name":"Zhepou",
    "gn:population":0,
    "gn:timezone":"Asia/Taipei",
    "iso:country":"TW",
    "name:und_x_variant":[
        "Jhepou",
        "Zhepou"
    ],
    "name:zho_x_preferred":[
        "\u8517\u5ecd"
    ],
    "name:zho_x_variant":[
        "Che-p\u2019ou"
    ],
    "wof:name":"Zhepou",
    "wof:placetype":"locality"
},
  "geometry": {"coordinates":[120.83351,24.63443],"type":"Point"}
}