{
  "type": "Feature",
  "properties": {
    "gn:admin1_code":"4.0",
    "gn:admin2_code":"CHA",
    "gn:admin3_code":"N25",
    "gn:admin4_code":"10007250008.0",
    "gn:asciiname":"Xinjizhuang",
    "gn:country_code":"TW",
    "gn:dem":25,
    "gn:feature_class":"P",
    "gn:feature_code":"PPL",
    "gn:name":"Xinjizhuang",
    "gn:population":0,
    "gn:timezone":"Asia/Taipei",
    "iso:country":"TW",
    "name:und_x_variant":[
        "Sinjijhuang",
        "Xinjizhuang",
        "Hsin-chi-chuang"
    ],
    "name:zho_x_preferred":[
        "\u65b0\u5409\u838a"
    ],
    "wof:name":"Xinjizhuang",
    "wof:placetype":"locality"
},
  "geometry": {"coordinates":[120.4247,23.8518],"type":"Point"}
}