{
  "type": "Feature",
  "properties": {
    "gn:admin1_code":"03",
    "gn:admin2_code":"TPQ",
    "gn:admin3_code":"F24",
    "gn:admin4_code":"65000260003.0",
    "gn:asciiname":"Tianliaoyang",
    "gn:country_code":"TW",
    "gn:dem":27,
    "gn:feature_class":"P",
    "gn:feature_code":"PPL",
    "gn:name":"Tianliaoyang",
    "gn:population":0,
    "gn:timezone":"Asia/Taipei",
    "iso:country":"TW",
    "name:zho_x_preferred":[
        "\u7530\u5bee\u6d0b"
    ],
    "name:zho_x_variant":[
        "T\u2019ien-liao-yang"
    ],
    "wof:name":"Tianliaoyang",
    "wof:placetype":"locality"
},
  "geometry": {"coordinates":[121.92802,25.01824],"type":"Point"}
}