{
  "type": "Feature",
  "properties": {
    "iso:country":"TW",
    "qs:name":"\u6e56\u5149\u6751",
    "qs:name_adm0":"\u81fa\u7063",
    "qs:name_adm1":"\u65b0\u7af9\u7e23",
    "qs:photos":131,
    "qs:photos_1k":27,
    "qs:photos_9k":1,
    "qs:photos_9r":3,
    "qs:photos_all":131,
    "qs:photos_sr":3,
    "qs:placetype":"Town",
    "qs:pop_sr":"0",
    "wof:name":"\u6e56\u5149\u6751",
    "wof:placetype":"locality"
},
  "geometry": {"coordinates":[120.993694,24.671533],"type":"Point"}
}