{
  "type": "Feature",
  "properties": {
    "gn:admin1_code":"04",
    "gn:admin2_code":"TNN",
    "gn:admin3_code":"R19",
    "gn:admin4_code":"67000190013.0",
    "gn:asciiname":"Dongshizhai",
    "gn:country_code":"TW",
    "gn:dem":18,
    "gn:feature_class":"P",
    "gn:feature_code":"PPL",
    "gn:name":"Dongshizhai",
    "gn:population":0,
    "gn:timezone":"Asia/Taipei",
    "iso:country":"TW",
    "name:und_x_variant":[
        "Tung-shih",
        "Dongshizhai",
        "Dongshihjhai",
        "Tung-shih-chai"
    ],
    "name:zho_x_preferred":[
        "\u6771\u52e2\u5b85"
    ],
    "wof:name":"Dongshizhai",
    "wof:placetype":"locality"
},
  "geometry": {"coordinates":[120.29469,23.14993],"type":"Point"}
}