{
  "type": "Feature",
  "properties": {
    "gn:admin1_code":"02",
    "gn:admin2_code":"KHH",
    "gn:admin3_code":"E15",
    "gn:admin4_code":"64000150007.0",
    "gn:asciiname":"Dazhuangshanding",
    "gn:country_code":"TW",
    "gn:dem":70,
    "gn:feature_class":"P",
    "gn:feature_code":"PPL",
    "gn:name":"Dazhuangshanding",
    "gn:population":0,
    "gn:timezone":"Asia/Taipei",
    "iso:country":"TW",
    "name:und_x_variant":[
        "Ta-chuang-shan-ting",
        "Ta-chuang-shan",
        "Dajhuangshanding",
        "Dazhuangshanding"
    ],
    "name:zho_x_preferred":[
        "\u5927\u5e84\u5c71\u9802"
    ],
    "wof:name":"Dazhuangshanding",
    "wof:placetype":"locality"
},
  "geometry": {"coordinates":[120.42572,22.70087],"type":"Point"}
}