{
  "type": "Feature",
  "properties": {
    "gn:admin1_code":"4.0",
    "gn:admin2_code":"MIA",
    "gn:admin3_code":"K05",
    "gn:admin4_code":"10005100004.0",
    "gn:asciiname":"Beicha",
    "gn:country_code":"TW",
    "gn:dem":188,
    "gn:feature_class":"P",
    "gn:feature_code":"PPL",
    "gn:name":"Beicha",
    "gn:population":0,
    "gn:timezone":"Asia/Taipei",
    "iso:country":"TW",
    "name:zho_x_preferred":[
        "\u5317\u53c9"
    ],
    "name:zho_x_variant":[
        "Pei-ch\u2019a"
    ],
    "wof:name":"Beicha",
    "wof:placetype":"locality"
},
  "geometry": {"coordinates":[120.7885,24.4708],"type":"Point"}
}