{
  "type": "Feature",
  "properties": {
    "gn:admin1_code":"4.0",
    "gn:admin2_code":"TXG",
    "gn:admin3_code":"B26",
    "gn:admin4_code":"66000260001.0",
    "gn:asciiname":"Ankeng",
    "gn:country_code":"TW",
    "gn:dem":114,
    "gn:feature_class":"P",
    "gn:feature_code":"PPL",
    "gn:name":"Ankeng",
    "gn:population":0,
    "gn:timezone":"Asia/Taipei",
    "iso:country":"TW",
    "name:und_x_variant":[
        "\u6697\u5751",
        "Ankeng",
        "An-k\u2019eng"
    ],
    "name:zho_x_preferred":[
        "An-k\u2019eng"
    ],
    "wof:name":"Ankeng",
    "wof:placetype":"locality"
},
  "geometry": {"coordinates":[120.7325,24.0705],"type":"Point"}
}