{
  "type": "Feature",
  "properties": {
    "gn:admin1_code":"02",
    "gn:admin2_code":"KHH",
    "gn:admin3_code":"E10",
    "gn:admin4_code":"64000100009.0",
    "gn:asciiname":"Dashantou",
    "gn:country_code":"TW",
    "gn:dem":2,
    "gn:feature_class":"P",
    "gn:feature_code":"PPL",
    "gn:name":"Dashantou",
    "gn:population":0,
    "gn:timezone":"Asia/Taipei",
    "iso:country":"TW",
    "name:und_x_variant":[
        "Shang-chu-li",
        "\u5927\u6c55\u982d",
        "Shang-chu",
        "Dashantou"
    ],
    "name:zho_x_preferred":[
        "Ta-shan-t\u2019ou"
    ],
    "wof:name":"Dashantou",
    "wof:placetype":"locality"
},
  "geometry": {"coordinates":[120.28979,22.58617000000001],"type":"Point"}
}