{
  "type": "Feature",
  "properties": {
    "gn:admin1_code":"04",
    "gn:admin2_code":"CYQ",
    "gn:admin3_code":"Q11",
    "gn:admin4_code":"10010110007.0",
    "gn:asciiname":"Shicuoliao",
    "gn:country_code":"TW",
    "gn:dem":16,
    "gn:feature_class":"P",
    "gn:feature_code":"PPL",
    "gn:name":"Shicuoliao",
    "gn:population":0,
    "gn:timezone":"Asia/Taipei",
    "iso:country":"TW",
    "name:und_x_variant":[
        "Shih-chia-chai",
        "Shihcuoliao",
        "Shicuoliao"
    ],
    "name:zho_x_preferred":[
        "Shih-ts\u2019o-chai"
    ],
    "name:zho_x_variant":[
        "\u65bd\u539d\u5bee",
        "Shih-ts\u2019o-liao"
    ],
    "wof:name":"Shicuoliao",
    "wof:placetype":"locality"
},
  "geometry": {"coordinates":[120.31278,23.39139],"type":"Point"}
}