{
  "type": "Feature",
  "properties": {
    "gn:admin1_code":"4.0",
    "gn:admin2_code":"TTT",
    "gn:admin3_code":"V07",
    "gn:admin4_code":"10014070003.0",
    "gn:asciiname":"Nandonghe",
    "gn:country_code":"TW",
    "gn:dem":25,
    "gn:feature_class":"P",
    "gn:feature_code":"PPL",
    "gn:name":"Nandonghe",
    "gn:population":0,
    "gn:timezone":"Asia/Taipei",
    "iso:country":"TW",
    "name:und_x_variant":[
        "Nan-tung-ho"
    ],
    "name:zho_x_preferred":[
        "\u5357\u6771\u6cb3"
    ],
    "wof:name":"Nandonghe",
    "wof:placetype":"locality"
},
  "geometry": {"coordinates":[121.30028,22.96417000000001],"type":"Point"}
}