{
  "type": "Feature",
  "properties": {
    "gn:admin1_code":"04",
    "gn:admin2_code":"CHA",
    "gn:admin3_code":"N21",
    "gn:admin4_code":"10007210004.0",
    "gn:asciiname":"Molizhuang",
    "gn:country_code":"TW",
    "gn:dem":41,
    "gn:feature_class":"P",
    "gn:feature_code":"PPL",
    "gn:name":"Molizhuang",
    "gn:population":0,
    "gn:timezone":"Asia/Taipei",
    "iso:country":"TW",
    "name:und_x_variant":[
        "Mu-hs\u00fcan-chuang",
        "Molijhuang",
        "Mu-i-chuang",
        "Molizhuang",
        "Mo-li-chuang"
    ],
    "name:zho_x_preferred":[
        "\u8309\u8389\u838a"
    ],
    "name:zho_x_variant":[
        "Mu-hs\u00fcan-chuang"
    ],
    "wof:name":"Molizhuang",
    "wof:placetype":"locality"
},
  "geometry": {"coordinates":[120.55352000000001,23.88383],"type":"Point"}
}