{
  "type": "Feature",
  "properties": {
    "gn:admin1_code":"4.0",
    "gn:admin2_code":"ILA",
    "gn:admin3_code":"G06",
    "gn:admin4_code":"10002020024.0",
    "gn:asciiname":"Qingshuigou",
    "gn:country_code":"TW",
    "gn:dem":10,
    "gn:feature_class":"P",
    "gn:feature_code":"PPL",
    "gn:name":"Qingshuigou",
    "gn:population":0,
    "gn:timezone":"Asia/Taipei",
    "iso:country":"TW",
    "name:und_x_variant":[
        "Jen-ai-li",
        "Cingshueigou",
        "Qingshuigou"
    ],
    "name:zho_x_preferred":[
        "\u6e05\u6c34\u6e9d"
    ],
    "name:zho_x_variant":[
        "Ch\u2019ing-shui-kou"
    ],
    "wof:name":"Qingshuigou",
    "wof:placetype":"locality"
},
  "geometry": {"coordinates":[121.7606,24.69369],"type":"Point"}
}