{
  "type": "Feature",
  "properties": {
    "gn:admin1_code":"4.0",
    "gn:admin2_code":"HUA",
    "gn:admin3_code":"U02",
    "gn:admin4_code":"10015070008.0",
    "gn:asciiname":"Atajie",
    "gn:country_code":"TW",
    "gn:dem":158,
    "gn:feature_class":"P",
    "gn:feature_code":"PPL",
    "gn:name":"Atajie",
    "gn:population":0,
    "gn:timezone":"Asia/Taipei",
    "iso:country":"TW",
    "name:zho_x_preferred":[
        "O-k\u2019o-k\u2019ai"
    ],
    "name:zho_x_variant":[
        "\u963f\u4ed6\u968e",
        "Ho-t\u2019a-chieh",
        "A-t\u2019a-chieh"
    ],
    "wof:name":"Atajie",
    "wof:placetype":"locality"
},
  "geometry": {"coordinates":[121.39677,23.6323],"type":"Point"}
}