{
  "type": "Feature",
  "properties": {
    "gn:admin1_code":"4.0",
    "gn:admin2_code":"MIA",
    "gn:admin3_code":"K16",
    "gn:admin4_code":"10005070001.0",
    "gn:asciiname":"Zhuolan",
    "gn:country_code":"TW",
    "gn:dem":343,
    "gn:feature_class":"P",
    "gn:feature_code":"PPL",
    "gn:name":"Zhuolan",
    "gn:population":0,
    "gn:timezone":"Asia/Taipei",
    "iso:country":"TW",
    "name:und_x_variant":[
        "Cho-lan-chen",
        "Cho-lan-chuang",
        "Chao-lan",
        "Cho-lan",
        "Jhuolan",
        "Zhuolan"
    ],
    "name:zho_x_preferred":[
        "\u5353\u862d"
    ],
    "wof:name":"Zhuolan",
    "wof:placetype":"locality"
},
  "geometry": {"coordinates":[120.82787999999999,24.3113],"type":"Point"}
}