{
  "type": "Feature",
  "properties": {
    "gn:admin1_code":"4.0",
    "gn:admin2_code":"HSQ",
    "gn:admin3_code":"O03",
    "gn:admin4_code":"10018030009.0",
    "gn:asciiname":"Buqiangwei",
    "gn:country_code":"TW",
    "gn:dem":26,
    "gn:feature_class":"P",
    "gn:feature_code":"PPL",
    "gn:name":"Buqiangwei",
    "gn:population":0,
    "gn:timezone":"Asia/Taipei",
    "iso:country":"TW",
    "name:und_x_variant":[
        "Buciangwei"
    ],
    "name:zho_x_preferred":[
        "\u57d4\u7f8c\u570d"
    ],
    "name:zho_x_variant":[
        "Pu-ch\u2019iang-y\u00fcan",
        "Pu-ch\u2019iang-wei"
    ],
    "wof:name":"Buqiangwei",
    "wof:placetype":"locality"
},
  "geometry": {"coordinates":[120.95361,24.79778],"type":"Point"}
}