{
  "type": "Feature",
  "properties": {
    "gn:admin1_code":"03",
    "gn:admin2_code":"TPQ",
    "gn:admin3_code":"F24",
    "gn:admin4_code":"65000260009.0",
    "gn:asciiname":"Yinggeshi",
    "gn:country_code":"TW",
    "gn:dem":45,
    "gn:feature_class":"P",
    "gn:feature_code":"PPL",
    "gn:name":"Yinggeshi",
    "gn:population":0,
    "gn:timezone":"Asia/Taipei",
    "iso:country":"TW",
    "name:und_x_variant":[
        "Yinggeshih",
        "Ying-ko-shih"
    ],
    "name:zho_x_preferred":[
        "\u9daf\u6b4c\u77f3"
    ],
    "name:zho_x_variant":[
        "Y\u00fcan-ko-shih"
    ],
    "wof:name":"Yinggeshi",
    "wof:placetype":"locality"
},
  "geometry": {"coordinates":[121.97583,24.99222],"type":"Point"}
}