{
  "type": "Feature",
  "properties": {
    "gn:admin1_code":"4.0",
    "gn:admin2_code":"TTT",
    "gn:admin3_code":"V09",
    "gn:admin4_code":"10014050005.0",
    "gn:asciiname":"Houhu",
    "gn:country_code":"TW",
    "gn:dem":153,
    "gn:feature_class":"P",
    "gn:feature_code":"PPL",
    "gn:name":"Houhu",
    "gn:population":0,
    "gn:timezone":"Asia/Taipei",
    "iso:country":"TW",
    "name:und_x_variant":[
        "Hou-hu"
    ],
    "name:zho_x_preferred":[
        "\u540e\u6e56"
    ],
    "wof:name":"Houhu",
    "wof:placetype":"locality"
},
  "geometry": {"coordinates":[121.17234000000001,22.9483],"type":"Point"}
}