{
  "type": "Feature",
  "properties": {
    "gn:admin1_code":"3.0",
    "gn:admin2_code":"TPQ",
    "gn:admin3_code":"F09",
    "gn:admin4_code":"65000180004.0",
    "gn:asciiname":"Xiangtianhu",
    "gn:country_code":"TW",
    "gn:dem":206,
    "gn:feature_class":"P",
    "gn:feature_code":"PPL",
    "gn:name":"Xiangtianhu",
    "gn:population":0,
    "gn:timezone":"Asia/Taipei",
    "iso:country":"TW",
    "name:und_x_variant":[
        "Siangtianhu",
        "Xiangtianhu"
    ],
    "name:zho_x_preferred":[
        "\u5411\u5929\u6e56"
    ],
    "name:zho_x_variant":[
        "Hsiang-t\u2019ien-hu"
    ],
    "wof:name":"Xiangtianhu",
    "wof:placetype":"locality"
},
  "geometry": {"coordinates":[121.62387,24.99098],"type":"Point"}
}