{
  "type": "Feature",
  "properties": {
    "iso:country":"TW",
    "qs:name":"\u8ca2\u5bee\u9109",
    "qs:name_adm0":"\u81fa\u7063",
    "qs:name_adm1":"\u65b0\u5317\u5e02",
    "qs:photos":595,
    "qs:photos_1k":121,
    "qs:photos_9k":69,
    "qs:photos_9r":19,
    "qs:photos_all":15601,
    "qs:photos_sr":8,
    "qs:placetype":"County",
    "qs:pop_sr":"0",
    "wd:wordcount":161,
    "wof:name":"\u8ca2\u5bee\u9109",
    "wof:placetype":"county"
},
  "geometry": {"coordinates":[121.910133,25.110082],"type":"Point"}
}