{
  "type": "Feature",
  "properties": {
    "gn:country":"TW",
    "gn:fcode":"ADMD",
    "gn:pop":0,
    "iso:country":"TW",
    "name:unk_x_variant":[
        "Hou-lung Chen"
    ],
    "name:zho_x_preferred":[
        "\u5f8c\u9f8d\u93ae"
    ],
    "qs:name":"Houlong Zhen",
    "qs:photos_9r":0,
    "qs:photos_sr":0,
    "qs:pop_sr":"0",
    "wof:name":"Houlong Zhen",
    "wof:placetype":"localadmin",
    "wof:population":0
},
  "geometry": {"coordinates":[120.76667,24.61667],"type":"Point"}
}