{
  "type": "Feature",
  "properties": {
    "gn:admin1_code":"4.0",
    "gn:admin2_code":"PIF",
    "gn:admin3_code":"T01",
    "gn:admin4_code":"10013010051.0",
    "gn:asciiname":"Zhuanziyao",
    "gn:country_code":"TW",
    "gn:dem":15,
    "gn:feature_class":"P",
    "gn:feature_code":"PPL",
    "gn:name":"Zhuanziyao",
    "gn:population":0,
    "gn:timezone":"Asia/Taipei",
    "iso:country":"TW",
    "name:und_x_variant":[
        "Chuan-tzu-yao",
        "Jhuanzihyao"
    ],
    "name:zho_x_preferred":[
        "\u78da\u5b50\u78d8"
    ],
    "wof:name":"Zhuanziyao",
    "wof:placetype":"locality"
},
  "geometry": {"coordinates":[120.45569,22.63034],"type":"Point"}
}