{
  "type": "Feature",
  "properties": {
    "gn:admin1_code":"04",
    "gn:admin2_code":"TTT",
    "gn:admin3_code":"V06",
    "gn:admin4_code":"10014090003.0",
    "gn:asciiname":"Xinji",
    "gn:country_code":"TW",
    "gn:dem":135,
    "gn:feature_class":"P",
    "gn:feature_code":"PPL",
    "gn:name":"Xinji",
    "gn:population":0,
    "gn:timezone":"Asia/Taipei",
    "iso:country":"TW",
    "name:und_x_variant":[
        "Sinji",
        "Wen-tzu-shuai",
        "Wen-tzu-pang",
        "Wen-tzu-chiao",
        "Xinji",
        "Hsin-chi"
    ],
    "name:zho_x_preferred":[
        "Hsin-chi-ts\u2019un"
    ],
    "name:zho_x_variant":[
        "\u65b0\u5409",
        "T\u2019ai-ma-li-hsiang"
    ],
    "wof:name":"Xinji",
    "wof:placetype":"locality"
},
  "geometry": {"coordinates":[121.01443999999999,22.64056],"type":"Point"}
}