{
  "type": "Feature",
  "properties": {
    "gn:admin1_code":"4.0",
    "gn:admin2_code":"TXG",
    "gn:admin3_code":"B22",
    "gn:admin4_code":"66000220003.0",
    "gn:asciiname":"Zhongzhuang",
    "gn:country_code":"TW",
    "gn:dem":15,
    "gn:feature_class":"P",
    "gn:feature_code":"PPL",
    "gn:name":"Zhongzhuang",
    "gn:population":0,
    "gn:timezone":"Asia/Taipei",
    "iso:country":"TW",
    "name:und_x_variant":[
        "Ting-chuang-tzu",
        "Ting-chuang",
        "Zhongzhuang",
        "Jhongjhuang",
        "Chung-chuang"
    ],
    "name:zho_x_preferred":[
        "Chung-chuang-ts\u2019un"
    ],
    "name:zho_x_variant":[
        "\u4e2d\u5e84"
    ],
    "wof:name":"Zhongzhuang",
    "wof:placetype":"locality"
},
  "geometry": {"coordinates":[120.58472,24.35139],"type":"Point"}
}