{
  "type": "Feature",
  "properties": {
    "gn:admin1_code":"4.0",
    "gn:admin2_code":"MIA",
    "gn:admin3_code":"K05",
    "gn:admin4_code":"10005100005.0",
    "gn:asciiname":"Qiedonglang",
    "gn:country_code":"TW",
    "gn:dem":326,
    "gn:feature_class":"P",
    "gn:feature_code":"PPL",
    "gn:name":"Qiedonglang",
    "gn:population":0,
    "gn:timezone":"Asia/Taipei",
    "iso:country":"TW",
    "name:und_x_variant":[
        "Ciedonglang",
        "Qiedonglang"
    ],
    "name:zho_x_preferred":[
        "\u8304\u51ac\u5d00"
    ],
    "name:zho_x_variant":[
        "Ch\u2019ieh-tung-lang"
    ],
    "wof:name":"Qiedonglang",
    "wof:placetype":"locality"
},
  "geometry": {"coordinates":[120.7659,24.45300000000001],"type":"Point"}
}