{
  "type": "Feature",
  "properties": {
    "iso:country":"TW",
    "name:ara_x_preferred":[
        "\u0645\u062d\u0627\u0641\u0638\u0629 \u0633\u0627\u0646\u063a\u0648\u0648\u0646"
    ],
    "name:ceb_x_preferred":[
        "Sangw\u014fn-gun"
    ],
    "name:cym_x_preferred":[
        "Sir Sangwon"
    ],
    "name:eng_x_preferred":[
        "Sangwon County"
    ],
    "name:jpn_x_preferred":[
        "\u7965\u539f\u90e1"
    ],
    "name:kor_x_preferred":[
        "\uc0c1\uc6d0\uad70"
    ],
    "name:nan_x_preferred":[
        "Sangw\u014fn K\u016bn"
    ],
    "name:nob_x_preferred":[
        "Sangwon"
    ],
    "name:pol_x_preferred":[
        "Sang'w\u014fn"
    ],
    "name:por_x_preferred":[
        "Sangw\u014fn-gun"
    ],
    "name:swe_x_preferred":[
        "Sangw\u014fn-gun"
    ],
    "name:vie_x_preferred":[
        "Sangwon"
    ],
    "name:zho_x_preferred":[
        "\u7965\u539f\u90e1"
    ],
    "qs:name":"\u5927\u540c\u91cc",
    "qs:name_adm0":"\u81fa\u7063",
    "qs:name_adm1":"\u53f0\u4e2d\u5e02",
    "qs:photos":52,
    "qs:photos_1k":11,
    "qs:photos_9k":1,
    "qs:photos_9r":2,
    "qs:photos_all":52,
    "qs:photos_sr":2,
    "qs:placetype":"Suburb",
    "qs:pop_sr":"0",
    "wd:wordcount":155,
    "wof:name":"\u5927\u540c\u91cc",
    "wof:placetype":"neighbourhood"
},
  "geometry": {"coordinates":[120.65275099999999,24.143531],"type":"Point"}
}