{
  "type": "Feature",
  "properties": {
    "gn:admin1_code":"4.0",
    "gn:admin2_code":"TNN",
    "gn:admin3_code":"D01",
    "gn:admin4_code":"67000320026.0",
    "gn:asciiname":"Zhugaocuo",
    "gn:country_code":"TW",
    "gn:dem":29,
    "gn:feature_class":"P",
    "gn:feature_code":"PPL",
    "gn:name":"Zhugaocuo",
    "gn:population":0,
    "gn:timezone":"Asia/Taipei",
    "iso:country":"TW",
    "name:und_x_variant":[
        "Chu-kuo-li",
        "Chu-hao-li",
        "Chu-kao-li",
        "Zhugaocuo",
        "Jhugaocuo",
        "Chu-kao"
    ],
    "name:zho_x_preferred":[
        "\u7af9\u7bd9\u539d"
    ],
    "name:zho_x_variant":[
        "Chu-kao-ts\u2019o"
    ],
    "wof:name":"Zhugaocuo",
    "wof:placetype":"locality"
},
  "geometry": {"coordinates":[120.235,22.96694],"type":"Point"}
}