{
  "type": "Feature",
  "properties": {
    "iso:country":"TW",
    "qs:name":"\u7af9\u7530\u6751",
    "qs:name_adm0":"\u81fa\u7063",
    "qs:name_adm1":"\u82b1\u84ee\u7e23",
    "qs:photos":223,
    "qs:photos_1k":45,
    "qs:photos_9k":1,
    "qs:photos_9r":4,
    "qs:photos_all":223,
    "qs:photos_sr":4,
    "qs:placetype":"Town",
    "qs:pop_sr":"0",
    "wof:name":"\u7af9\u7530\u6751",
    "wof:placetype":"locality"
},
  "geometry": {"coordinates":[121.29589799999999,23.215064],"type":"Point"}
}