{
  "type": "Feature",
  "properties": {
    "gn:admin1_code":"4.0",
    "gn:admin2_code":"CHA",
    "gn:admin3_code":"N19",
    "gn:admin4_code":"10007170013.0",
    "gn:asciiname":"Lunya",
    "gn:country_code":"TW",
    "gn:dem":47,
    "gn:feature_class":"P",
    "gn:feature_code":"PPL",
    "gn:name":"Lunya",
    "gn:population":0,
    "gn:timezone":"Asia/Taipei",
    "iso:country":"TW",
    "name:und_x_variant":[
        "Lun-ya"
    ],
    "name:zho_x_preferred":[
        "Lun-ya-ts\u2019un"
    ],
    "name:zho_x_variant":[
        "\u5d19\u96c5"
    ],
    "wof:name":"Lunya",
    "wof:placetype":"locality"
},
  "geometry": {"coordinates":[120.5882,23.8909],"type":"Point"}
}