{
  "type": "Feature",
  "properties": {
    "iso:country":"TW",
    "name:eng_x_preferred":[
        "Xingguang"
    ],
    "name:eng_x_variant":[
        "Xingguang Village"
    ],
    "name:zho_tw_x_preferred":[
        "\u8208\u5149\u91cc"
    ],
    "qs:name":"\u8208\u5149\u91cc",
    "qs:name_adm0":"\u81fa\u7063",
    "qs:name_adm1":"\u53f0\u5317\u5e02",
    "qs:photos":366,
    "qs:photos_1k":74,
    "qs:photos_9k":2,
    "qs:photos_9r":5,
    "qs:photos_all":366,
    "qs:photos_sr":6,
    "qs:placetype":"Suburb",
    "qs:pop_sr":"0",
    "wof:name":"Xingguang",
    "wof:placetype":"neighbourhood"
},
  "geometry": {"coordinates":[121.55814100000001,24.999123],"type":"Point"}
}