{
  "type": "Feature",
  "properties": {
    "gn:admin1_code":"3.0",
    "gn:admin2_code":"TPQ",
    "gn:admin3_code":"F03",
    "gn:admin4_code":"65000150004.0",
    "gn:asciiname":"Guanyinkeng",
    "gn:country_code":"TW",
    "gn:dem":95,
    "gn:feature_class":"P",
    "gn:feature_code":"PPL",
    "gn:name":"Guanyinkeng",
    "gn:population":0,
    "gn:timezone":"Asia/Taipei",
    "iso:country":"TW",
    "name:und_x_variant":[
        "Kuan-yin",
        "Guanyinkeng"
    ],
    "name:zho_x_preferred":[
        "Chung-k\u2019eng"
    ],
    "name:zho_x_variant":[
        "\u89c0\u97f3\u5751",
        "Kuan-yin-k\u2019eng"
    ],
    "wof:name":"Guanyinkeng",
    "wof:placetype":"locality"
},
  "geometry": {"coordinates":[121.43214,25.11692],"type":"Point"}
}