{
  "type": "Feature",
  "properties": {
    "gn:admin1_code":"04",
    "gn:admin2_code":"TNN",
    "gn:admin3_code":"R14",
    "gn:admin4_code":"67000150021.0",
    "gn:asciiname":"Yongji",
    "gn:country_code":"TW",
    "gn:dem":7,
    "gn:feature_class":"P",
    "gn:feature_code":"PPL",
    "gn:name":"Yongji",
    "gn:population":0,
    "gn:timezone":"Asia/Taipei",
    "iso:country":"TW",
    "name:deu_x_preferred":[
        "Yongji"
    ],
    "name:fra_x_preferred":[
        "Yongji"
    ],
    "name:nor_x_preferred":[
        "Yongji"
    ],
    "name:rus_x_preferred":[
        "\u042e\u043d\u0446\u0437\u0438"
    ],
    "name:swe_x_preferred":[
        "Yongji"
    ],
    "name:und_x_variant":[
        "Yung-chi",
        "Kung-ti-wei"
    ],
    "name:zho_x_preferred":[
        "Yung-chi-ts\u2019un"
    ],
    "name:zho_x_variant":[
        "\u6c38\u5409"
    ],
    "wof:name":"Yongji",
    "wof:placetype":"locality"
},
  "geometry": {"coordinates":[120.12917,23.09333],"type":"Point"}
}