{
  "type": "Feature",
  "properties": {
    "gn:admin1_code":"3.0",
    "gn:admin2_code":"TPQ",
    "gn:admin3_code":"F31",
    "gn:admin4_code":"65000220001.0",
    "gn:asciiname":"Linshanbi",
    "gn:country_code":"TW",
    "gn:dem":17,
    "gn:feature_class":"P",
    "gn:feature_code":"PPL",
    "gn:name":"Linshanbi",
    "gn:population":0,
    "gn:timezone":"Asia/Taipei",
    "iso:country":"TW",
    "name:und_x_variant":[
        "Lin-shan-pi"
    ],
    "name:zho_x_preferred":[
        "\u9e9f\u5c71\u9f3b"
    ],
    "wof:name":"Linshanbi",
    "wof:placetype":"locality"
},
  "geometry": {"coordinates":[121.5111,25.28826],"type":"Point"}
}