{
  "type": "Feature",
  "properties": {
    "gn:admin1_code":"04",
    "gn:admin2_code":"TNN",
    "gn:admin3_code":"R27",
    "gn:admin4_code":"67000270012.0",
    "gn:asciiname":"Shisanjia",
    "gn:country_code":"TW",
    "gn:dem":18,
    "gn:feature_class":"P",
    "gn:feature_code":"PPL",
    "gn:name":"Shisanjia",
    "gn:population":0,
    "gn:timezone":"Asia/Taipei",
    "iso:country":"TW",
    "name:und_x_variant":[
        "Shihsanjia",
        "Shih-san-chia"
    ],
    "name:zho_x_preferred":[
        "\u5341\u4e09\u7532"
    ],
    "wof:name":"Shisanjia",
    "wof:placetype":"locality"
},
  "geometry": {"coordinates":[120.22194,22.94389],"type":"Point"}
}