{
  "type": "Feature",
  "properties": {
    "gn:admin1_code":"4.0",
    "gn:admin2_code":"HUA",
    "gn:admin3_code":"U05",
    "gn:admin4_code":"10015050010.0",
    "gn:asciiname":"Fuxing",
    "gn:country_code":"TW",
    "gn:dem":56,
    "gn:feature_class":"P",
    "gn:feature_code":"PPL",
    "gn:name":"Fuxing",
    "gn:population":0,
    "gn:timezone":"Asia/Taipei",
    "iso:country":"TW",
    "name:und_x_variant":[
        "Fusing",
        "Fu-hsing"
    ],
    "name:zho_x_preferred":[
        "\u5fa9\u8208"
    ],
    "wof:name":"Fuxing",
    "wof:placetype":"locality"
},
  "geometry": {"coordinates":[121.56222,23.9425],"type":"Point"}
}