{
  "type": "Feature",
  "properties": {
    "gn:admin1_code":"4.0",
    "gn:admin2_code":"NAN",
    "gn:admin3_code":"M06",
    "gn:admin4_code":"10008060014.0",
    "gn:asciiname":"Chulinhu",
    "gn:country_code":"TW",
    "gn:dem":275,
    "gn:feature_class":"P",
    "gn:feature_code":"PPL",
    "gn:name":"Chulinhu",
    "gn:population":0,
    "gn:timezone":"Asia/Taipei",
    "iso:country":"TW",
    "name:und_x_variant":[
        "Lin-hu",
        "Chulinhu"
    ],
    "name:zho_x_preferred":[
        "Ch\u2019u-lin-hu-tzu"
    ],
    "name:zho_x_variant":[
        "\u51fa\u6797\u864e",
        "Ch\u2019u-lin-hu"
    ],
    "wof:name":"Chulinhu",
    "wof:placetype":"locality"
},
  "geometry": {"coordinates":[120.65182,23.85172],"type":"Point"}
}