{
  "type": "Feature",
  "properties": {
    "iso:country":"TW",
    "qs:name":"\u65b0\u5e02\u9109",
    "qs:name_adm0":"\u81fa\u7063",
    "qs:name_adm1":"\u53f0\u5357\u5e02",
    "qs:photos":8073,
    "qs:photos_1k":1000,
    "qs:photos_9k":36,
    "qs:photos_9r":15,
    "qs:photos_all":8215,
    "qs:photos_sr":25,
    "qs:placetype":"County",
    "qs:pop_sr":"0",
    "wd:wordcount":136,
    "wof:name":"\u65b0\u5e02\u9109",
    "wof:placetype":"county"
},
  "geometry": {"coordinates":[120.27510100000001,23.084192],"type":"Point"}
}