{
  "type": "Feature",
  "properties": {
    "gn:country":"TW",
    "gn:fcode":"ADMD",
    "gn:population":0,
    "iso:country":"TW",
    "name:eng_x_preferred":[
        "Wandan"
    ],
    "name:hak_x_preferred":[
        "Van-t\u00e2n-hi\u00f4ng"
    ],
    "name:jpn_x_preferred":[
        "\u4e07\u4e39\u90f7"
    ],
    "name:kor_x_preferred":[
        "\uc644\ub2e8\ud5a5"
    ],
    "name:nan_x_preferred":[
        "B\u0101n-tan-hiong"
    ],
    "name:und_x_variant":[
        "Wan-tan Hsiang"
    ],
    "name:vie_x_preferred":[
        "V\u1ea1n \u0110an"
    ],
    "name:zho_x_preferred":[
        "\u842c\u4e39\u9109"
    ],
    "qs:name":"Wandan Xiang",
    "qs:photos_9r":0,
    "qs:photos_sr":0,
    "qs:pop_sr":"0",
    "wd:wordcount":301,
    "wof:name":"Wandan Xiang",
    "wof:placetype":"localadmin",
    "wof:population":0
},
  "geometry": {"coordinates":[120.46666999999999,22.58333],"type":"Point"}
}