{
  "type": "Feature",
  "properties": {
    "gn:country":"TW",
    "gn:fcode":"ADMD",
    "gn:pop":0,
    "iso:country":"TW",
    "name:unk_x_variant":[
        "Wan-tan Hsiang"
    ],
    "name:zho_x_preferred":[
        "\u842c\u4e39\u9109"
    ],
    "qs:name":"Wandan Xiang",
    "qs:photos_9r":0,
    "qs:photos_sr":0,
    "qs:pop_sr":"0",
    "wd:wordcount":301,
    "wof:name":"Wandan Xiang",
    "wof:placetype":"localadmin",
    "wof:population":0
},
  "geometry": {"coordinates":[120.46666999999999,22.58333],"type":"Point"}
}