{
  "type": "Feature",
  "properties": {
    "gn:admin1_code":"4.0",
    "gn:admin2_code":"TNN",
    "gn:admin3_code":"R26",
    "gn:admin4_code":"67000260009.0",
    "gn:asciiname":"Hongmaoliao",
    "gn:country_code":"TW",
    "gn:dem":80,
    "gn:feature_class":"P",
    "gn:feature_code":"PPL",
    "gn:name":"Hongmaoliao",
    "gn:population":0,
    "gn:timezone":"Asia/Taipei",
    "iso:country":"TW",
    "name:und_x_variant":[
        "Hung-mao-liao"
    ],
    "name:zho_x_preferred":[
        "\u7d05\u6bdb\u5bee"
    ],
    "wof:name":"Hongmaoliao",
    "wof:placetype":"locality"
},
  "geometry": {"coordinates":[120.43778,22.99556],"type":"Point"}
}