{
  "type": "Feature",
  "properties": {
    "gn:admin1_code":"04",
    "gn:admin2_code":"HUA",
    "gn:admin3_code":"U08",
    "gn:admin4_code":"10015080004.0",
    "gn:asciiname":"Dagangkou",
    "gn:country_code":"TW",
    "gn:dem":13,
    "gn:feature_class":"P",
    "gn:feature_code":"PPL",
    "gn:name":"Dagangkou",
    "gn:population":0,
    "gn:timezone":"Asia/Taipei",
    "iso:country":"TW",
    "name:und_x_variant":[
        "Dagangkou"
    ],
    "name:zho_x_preferred":[
        "Ta-chiang-k\u2019ou"
    ],
    "name:zho_x_variant":[
        "\u5927\u6e2f\u56d7",
        "Ta-kang-k\u2019ou"
    ],
    "wof:name":"Dagangkou",
    "wof:placetype":"locality"
},
  "geometry": {"coordinates":[121.49748,23.46936],"type":"Point"}
}