{
  "type": "Feature",
  "properties": {
    "gn:admin1_code":"2.0",
    "gn:admin2_code":"KHH",
    "gn:admin3_code":"E30",
    "gn:admin4_code":"64000300016.0",
    "gn:asciiname":"Santaoshan",
    "gn:country_code":"TW",
    "gn:dem":56,
    "gn:feature_class":"P",
    "gn:feature_code":"PPL",
    "gn:name":"Santaoshan",
    "gn:population":0,
    "gn:timezone":"Asia/Taipei",
    "iso:country":"TW",
    "name:zho_x_preferred":[
        "\u4e09\u6843\u5c71"
    ],
    "name:zho_x_variant":[
        "Ch\u2019iu-liang-shan",
        "San-t\u2019ao-shan"
    ],
    "wof:name":"Santaoshan",
    "wof:placetype":"locality"
},
  "geometry": {"coordinates":[120.47611000000001,22.87917],"type":"Point"}
}