{
  "type": "Feature",
  "properties": {
    "gn:admin1_code":"2.0",
    "gn:admin2_code":"KHH",
    "gn:admin3_code":"E31",
    "gn:admin4_code":"64000310017.0",
    "gn:asciiname":"Siwei",
    "gn:country_code":"TW",
    "gn:dem":50,
    "gn:feature_class":"P",
    "gn:feature_code":"PPL",
    "gn:name":"Siwei",
    "gn:population":0,
    "gn:timezone":"Asia/Taipei",
    "iso:country":"TW",
    "name:und_x_variant":[
        "Sihwei",
        "Ssu-chih-wei",
        "Siwei",
        "Ssu-chih-wu",
        "Ssu-wei"
    ],
    "name:zho_x_preferred":[
        "\u56db\u7dad"
    ],
    "wof:name":"Siwei",
    "wof:placetype":"locality"
},
  "geometry": {"coordinates":[120.52638,22.84777],"type":"Point"}
}