{
  "type": "Feature",
  "properties": {
    "gn:admin1_code":"3.0",
    "gn:admin2_code":"TPQ",
    "gn:admin3_code":"F07",
    "gn:admin4_code":"65000060028.0",
    "gn:asciiname":"Xiaokeng",
    "gn:country_code":"TW",
    "gn:dem":311,
    "gn:feature_class":"P",
    "gn:feature_code":"PPL",
    "gn:name":"Xiaokeng",
    "gn:population":0,
    "gn:timezone":"Asia/Taipei",
    "iso:country":"TW",
    "name:und_x_variant":[
        "Siaokeng",
        "Xiaokeng"
    ],
    "name:zho_x_preferred":[
        "Hsiao-ts\u2019u-k\u2019eng"
    ],
    "name:zho_x_variant":[
        "\u5c0f\u5751",
        "Hsi-k\u2019eng",
        "Hsiao-k\u2019eng"
    ],
    "wof:name":"Xiaokeng",
    "wof:placetype":"locality"
},
  "geometry": {"coordinates":[121.52701,24.9101],"type":"Point"}
}