{
  "type": "Feature",
  "properties": {
    "gn:admin1_code":"04",
    "gn:admin2_code":"MIA",
    "gn:admin3_code":"K03",
    "gn:admin4_code":"10005030022.0",
    "gn:asciiname":"Baishatun",
    "gn:country_code":"TW",
    "gn:dem":10,
    "gn:feature_class":"P",
    "gn:feature_code":"PPL",
    "gn:name":"Baishatun",
    "gn:population":0,
    "gn:timezone":"Asia/Taipei",
    "iso:country":"TW",
    "name:zho_x_preferred":[
        "\u767d\u6c99\u5c6f"
    ],
    "name:zho_x_variant":[
        "Pai-sha-t\u2019un"
    ],
    "wof:name":"Baishatun",
    "wof:placetype":"locality"
},
  "geometry": {"coordinates":[120.71057999999999,24.57071],"type":"Point"}
}