{
  "type": "Feature",
  "properties": {
    "gn:admin1_code":"4.0",
    "gn:admin2_code":"YUN",
    "gn:admin3_code":"P17",
    "gn:admin4_code":"10009170016.0",
    "gn:asciiname":"Luliao",
    "gn:country_code":"TW",
    "gn:dem":19,
    "gn:feature_class":"P",
    "gn:feature_code":"PPL",
    "gn:name":"Luliao",
    "gn:population":0,
    "gn:timezone":"Asia/Taipei",
    "iso:country":"TW",
    "name:und_x_variant":[
        "Lu-nan",
        "Luliao",
        "Lu-liao"
    ],
    "name:zho_x_preferred":[
        "Lu-nan-ts\u2019un"
    ],
    "name:zho_x_variant":[
        "\u9e7f\u5bee"
    ],
    "wof:name":"Luliao",
    "wof:placetype":"locality"
},
  "geometry": {"coordinates":[120.3736,23.64438],"type":"Point"}
}