{
  "type": "Feature",
  "properties": {
    "gn:admin1_code":"3.0",
    "gn:admin2_code":"TPQ",
    "gn:admin3_code":"F23",
    "gn:admin4_code":"65000250008.0",
    "gn:asciiname":"Mazhukeng",
    "gn:country_code":"TW",
    "gn:dem":75,
    "gn:feature_class":"P",
    "gn:feature_code":"PPL",
    "gn:name":"Mazhukeng",
    "gn:population":0,
    "gn:timezone":"Asia/Taipei",
    "iso:country":"TW",
    "name:und_x_variant":[
        "Majhukeng",
        "Mazhukeng"
    ],
    "name:zho_x_preferred":[
        "\u9ebb\u7af9\u5751"
    ],
    "name:zho_x_variant":[
        "Ma-chu-k\u2019eng"
    ],
    "wof:name":"Mazhukeng",
    "wof:placetype":"locality"
},
  "geometry": {"coordinates":[121.85250000000001,25.0306],"type":"Point"}
}