{
  "type": "Feature",
  "properties": {
    "gn:admin1_code":"4.0",
    "gn:admin2_code":"ILA",
    "gn:admin3_code":"G12",
    "gn:admin4_code":"10002120007.0",
    "gn:asciiname":"Aohua",
    "gn:country_code":"TW",
    "gn:dem":59,
    "gn:feature_class":"P",
    "gn:feature_code":"PPL",
    "gn:name":"Aohua",
    "gn:population":0,
    "gn:timezone":"Asia/Taipei",
    "iso:country":"TW",
    "name:und_x_variant":[
        "Ta-cho-shui",
        "Aohua",
        "Ao-hua"
    ],
    "name:zho_x_preferred":[
        "Ao-hua-ts\u2019un"
    ],
    "name:zho_x_variant":[
        "\u6fb3\u82b1"
    ],
    "wof:name":"Aohua",
    "wof:placetype":"locality"
},
  "geometry": {"coordinates":[121.74312999999999,24.33218],"type":"Point"}
}