{
  "type": "Feature",
  "properties": {
    "gn:admin1_code":"4.0",
    "gn:admin2_code":"TAO",
    "gn:admin3_code":"H05",
    "gn:admin4_code":"68000050012.0",
    "gn:asciiname":"Weifan",
    "gn:country_code":"TW",
    "gn:dem":36,
    "gn:feature_class":"P",
    "gn:feature_code":"PPL",
    "gn:name":"Weifan",
    "gn:population":0,
    "gn:timezone":"Asia/Taipei",
    "iso:country":"TW",
    "name:und_x_variant":[
        "Wei-fan"
    ],
    "name:zho_x_preferred":[
        "\u5c3e\u8543"
    ],
    "wof:name":"Weifan",
    "wof:placetype":"locality"
},
  "geometry": {"coordinates":[121.27851,25.08887],"type":"Point"}
}