{
  "type": "Feature",
  "properties": {
    "gn:admin1_code":"4.0",
    "gn:admin2_code":"TNN",
    "gn:admin3_code":"R19",
    "gn:admin4_code":"67000190019.0",
    "gn:asciiname":"Wulingzi",
    "gn:country_code":"TW",
    "gn:dem":21,
    "gn:feature_class":"P",
    "gn:feature_code":"PPL",
    "gn:name":"Wulingzi",
    "gn:population":0,
    "gn:timezone":"Asia/Taipei",
    "iso:country":"TW",
    "name:und_x_variant":[
        "Wulingzih",
        "Wulingzi",
        "Wu-ling-tzu"
    ],
    "name:zho_x_preferred":[
        "\u4e94\u9234\u4ed4"
    ],
    "wof:name":"Wulingzi",
    "wof:placetype":"locality"
},
  "geometry": {"coordinates":[120.33786000000001,23.13681],"type":"Point"}
}