{
  "type": "Feature",
  "properties": {
    "gn:admin1_code":"02",
    "gn:admin2_code":"KHH",
    "gn:admin3_code":"E22",
    "gn:admin4_code":"64000220009.0",
    "gn:asciiname":"Shishanlun",
    "gn:country_code":"TW",
    "gn:dem":63,
    "gn:feature_class":"P",
    "gn:feature_code":"PPL",
    "gn:name":"Shishanlun",
    "gn:population":0,
    "gn:timezone":"Asia/Taipei",
    "iso:country":"TW",
    "name:und_x_variant":[
        "Shihshanlun",
        "Shih-shan-tzu",
        "Shih-shan-lun"
    ],
    "name:zho_x_preferred":[
        "\u77f3\u5c71\u5d19"
    ],
    "wof:name":"Shishanlun",
    "wof:placetype":"locality"
},
  "geometry": {"coordinates":[120.41806,22.89889],"type":"Point"}
}