{
  "type": "Feature",
  "properties": {
    "gn:admin1_code":"4.0",
    "gn:admin2_code":"MIA",
    "gn:admin3_code":"K10",
    "gn:admin4_code":"10005050019.0",
    "gn:asciiname":"Liushuitan",
    "gn:country_code":"TW",
    "gn:dem":11,
    "gn:feature_class":"P",
    "gn:feature_code":"PPL",
    "gn:name":"Liushuitan",
    "gn:population":0,
    "gn:timezone":"Asia/Taipei",
    "iso:country":"TW",
    "name:und_x_variant":[
        "Lioushueitan",
        "Liushuitan"
    ],
    "name:zho_x_preferred":[
        "\u6d41\u6c34\u6f6d"
    ],
    "name:zho_x_variant":[
        "Liu-shui-t\u2019an"
    ],
    "wof:name":"Liushuitan",
    "wof:placetype":"locality"
},
  "geometry": {"coordinates":[120.88070999999999,24.67338],"type":"Point"}
}