{
  "type": "Feature",
  "properties": {
    "gn:admin1_code":"4.0",
    "gn:admin2_code":"TNN",
    "gn:admin3_code":"R27",
    "gn:admin4_code":"67000270004.0",
    "gn:asciiname":"Kanjiao",
    "gn:country_code":"TW",
    "gn:dem":10,
    "gn:feature_class":"P",
    "gn:feature_code":"PPL",
    "gn:name":"Kanjiao",
    "gn:population":0,
    "gn:timezone":"Asia/Taipei",
    "iso:country":"TW",
    "name:zho_x_preferred":[
        "\u5d01\u8173"
    ],
    "name:zho_x_variant":[
        "K\u2019an-chiao"
    ],
    "wof:name":"Kanjiao",
    "wof:placetype":"locality"
},
  "geometry": {"coordinates":[120.24666999999999,22.9725],"type":"Point"}
}