{
  "type": "Feature",
  "properties": {
    "gn:admin1_code":"4.0",
    "gn:admin2_code":"HSZ",
    "gn:admin3_code":"J04",
    "gn:admin4_code":"10004030006.0",
    "gn:asciiname":"Xiazhangshulin",
    "gn:country_code":"TW",
    "gn:dem":107,
    "gn:feature_class":"P",
    "gn:feature_code":"PPL",
    "gn:name":"Xiazhangshulin",
    "gn:population":0,
    "gn:timezone":"Asia/Taipei",
    "iso:country":"TW",
    "name:und_x_variant":[
        "Siajhangshulin",
        "Chang-shu-lin",
        "Hsia-chang-shu-lin"
    ],
    "name:zho_x_preferred":[
        "\u4e0b\u6a1f\u6a39\u6797"
    ],
    "wof:name":"Xiazhangshulin",
    "wof:placetype":"locality"
},
  "geometry": {"coordinates":[121.07611,24.835],"type":"Point"}
}