{
  "type": "Feature",
  "properties": {
    "gn:admin1_code":"4.0",
    "gn:admin2_code":"CHA",
    "gn:admin3_code":"N03",
    "gn:admin4_code":"10007030010.0",
    "gn:asciiname":"Gongcuo",
    "gn:country_code":"TW",
    "gn:dem":13,
    "gn:feature_class":"P",
    "gn:feature_code":"PPL",
    "gn:name":"Gongcuo",
    "gn:population":0,
    "gn:timezone":"Asia/Taipei",
    "iso:country":"TW",
    "name:zho_x_preferred":[
        "\u516c\u539d"
    ],
    "name:zho_x_variant":[
        "Kung-ts\u2019o"
    ],
    "wof:name":"Gongcuo",
    "wof:placetype":"locality"
},
  "geometry": {"coordinates":[120.49917000000001,24.08111],"type":"Point"}
}