{
  "type": "Feature",
  "properties": {
    "gn:admin1_code":"4.0",
    "gn:admin2_code":"CHA",
    "gn:admin3_code":"N06",
    "gn:admin4_code":"10007110014.0",
    "gn:asciiname":"Dingsankuaicuo",
    "gn:country_code":"TW",
    "gn:dem":24,
    "gn:feature_class":"P",
    "gn:feature_code":"PPL",
    "gn:name":"Dingsankuaicuo",
    "gn:population":0,
    "gn:timezone":"Asia/Taipei",
    "iso:country":"TW",
    "name:zho_x_preferred":[
        "\u9802\u4e09\u584a\u539d"
    ],
    "name:zho_x_variant":[
        "Li-ts\u2019o",
        "Ting-san-k\u2019uai-ts\u2019o"
    ],
    "wof:name":"Dingsankuaicuo",
    "wof:placetype":"locality"
},
  "geometry": {"coordinates":[120.49764,23.9712],"type":"Point"}
}