{
  "type": "Feature",
  "properties": {
    "gn:admin1_code":"4.0",
    "gn:admin2_code":"TAO",
    "gn:admin3_code":"H02",
    "gn:admin4_code":"68000030007.0",
    "gn:asciiname":"Buxinzi",
    "gn:country_code":"TW",
    "gn:dem":208,
    "gn:feature_class":"P",
    "gn:feature_code":"PPL",
    "gn:name":"Buxinzi",
    "gn:population":0,
    "gn:timezone":"Asia/Taipei",
    "iso:country":"TW",
    "name:und_x_variant":[
        "Businzih",
        "Pu-hsin-tzu"
    ],
    "name:zho_x_preferred":[
        "\u57d4\u5fc3\u4ed4"
    ],
    "wof:name":"Buxinzi",
    "wof:placetype":"locality"
},
  "geometry": {"coordinates":[121.29346,24.86541],"type":"Point"}
}