{
  "type": "Feature",
  "properties": {
    "gn:admin1_code":"04",
    "gn:admin2_code":"MIA",
    "gn:admin3_code":"K07",
    "gn:admin4_code":"10005140007.0",
    "gn:asciiname":"Dongsanhu",
    "gn:country_code":"TW",
    "gn:dem":51,
    "gn:feature_class":"P",
    "gn:feature_code":"PPL",
    "gn:name":"Dongsanhu",
    "gn:population":0,
    "gn:timezone":"Asia/Taipei",
    "iso:country":"TW",
    "name:und_x_variant":[
        "Tung-san-hu"
    ],
    "name:zho_x_preferred":[
        "Tung-san-hu-p\u2019ai"
    ],
    "name:zho_x_variant":[
        "Tung-shan-hu-p\u2019ai",
        "\u6771\u4e09\u6e56"
    ],
    "wof:name":"Dongsanhu",
    "wof:placetype":"locality"
},
  "geometry": {"coordinates":[120.75226000000001,24.54754],"type":"Point"}
}