{
  "type": "Feature",
  "properties": {
    "gn:admin1_code":"4.0",
    "gn:admin2_code":"NAN",
    "gn:admin3_code":"M10",
    "gn:admin4_code":"10008100008.0",
    "gn:asciiname":"Zhongxixiang",
    "gn:country_code":"TW",
    "gn:dem":309,
    "gn:feature_class":"P",
    "gn:feature_code":"PPL",
    "gn:name":"Zhongxixiang",
    "gn:population":0,
    "gn:timezone":"Asia/Taipei",
    "iso:country":"TW",
    "name:und_x_variant":[
        "Jhongsisiang",
        "Chung-hsi-hsiang"
    ],
    "name:zho_x_preferred":[
        "\u4e2d\u897f\u5df7"
    ],
    "wof:name":"Zhongxixiang",
    "wof:placetype":"locality"
},
  "geometry": {"coordinates":[120.80764000000001,24.04186],"type":"Point"}
}