{
  "type": "Feature",
  "properties": {
    "gn:admin1_code":"4.0",
    "gn:admin2_code":"CYQ",
    "gn:admin3_code":"Q18",
    "gn:admin4_code":"10010170005.0",
    "gn:asciiname":"Daowanlong",
    "gn:country_code":"TW",
    "gn:dem":341,
    "gn:feature_class":"P",
    "gn:feature_code":"PPL",
    "gn:name":"Daowanlong",
    "gn:population":0,
    "gn:timezone":"Asia/Taipei",
    "iso:country":"TW",
    "name:und_x_variant":[
        "Tao-wan-lung"
    ],
    "name:zho_x_preferred":[
        "\u5012\u5f4e\u9f8d"
    ],
    "wof:name":"Daowanlong",
    "wof:placetype":"locality"
},
  "geometry": {"coordinates":[120.56926,23.26045],"type":"Point"}
}