{
  "type": "Feature",
  "properties": {
    "gn:admin1_code":"4.0",
    "gn:admin2_code":"TAO",
    "gn:admin3_code":"H09",
    "gn:admin4_code":"68000090012.0",
    "gn:asciiname":"Liugangliao",
    "gn:country_code":"TW",
    "gn:dem":301,
    "gn:feature_class":"P",
    "gn:feature_code":"PPL",
    "gn:name":"Liugangliao",
    "gn:population":0,
    "gn:timezone":"Asia/Taipei",
    "iso:country":"TW",
    "name:und_x_variant":[
        "Liougangliao",
        "Liugangliao",
        "Liu-kang-liao"
    ],
    "name:zho_x_preferred":[
        "\u516d\u69d3\u5bee"
    ],
    "wof:name":"Liugangliao",
    "wof:placetype":"locality"
},
  "geometry": {"coordinates":[121.18805999999999,24.83944],"type":"Point"}
}