{
  "type": "Feature",
  "properties": {
    "gn:admin1_code":"4.0",
    "gn:admin2_code":"TTT",
    "gn:admin3_code":"V01",
    "gn:admin4_code":"10014010001.0",
    "gn:asciiname":"Jialulan",
    "gn:country_code":"TW",
    "gn:dem":48,
    "gn:feature_class":"P",
    "gn:feature_code":"PPL",
    "gn:name":"Jialulan",
    "gn:population":0,
    "gn:timezone":"Asia/Taipei",
    "iso:country":"TW",
    "name:und_x_variant":[
        "Chia-lu-lan-fan-she",
        "Jialulan",
        "Chia-lu-lan"
    ],
    "name:zho_x_preferred":[
        "\u52a0\u8def\u862d"
    ],
    "name:zho_x_variant":[
        "Chia-lu-lan-ts\u2019un"
    ],
    "wof:name":"Jialulan",
    "wof:placetype":"locality"
},
  "geometry": {"coordinates":[121.18770000000001,22.8109],"type":"Point"}
}