{
  "type": "Feature",
  "properties": {
    "gn:admin1_code":"3.0",
    "gn:admin2_code":"TPQ",
    "gn:admin3_code":"F26",
    "gn:admin4_code":"65000280006.0",
    "gn:asciiname":"Laoliaohu",
    "gn:country_code":"TW",
    "gn:dem":444,
    "gn:feature_class":"P",
    "gn:feature_code":"PPL",
    "gn:name":"Laoliaohu",
    "gn:population":0,
    "gn:timezone":"Asia/Taipei",
    "iso:country":"TW",
    "name:und_x_variant":[
        "Lao-liao-hu",
        "Laoliaohu"
    ],
    "name:zho_x_preferred":[
        "\u8001\u5bee\u6e56"
    ],
    "wof:name":"Laoliaohu",
    "wof:placetype":"locality"
},
  "geometry": {"coordinates":[121.62506,25.17455],"type":"Point"}
}