{
  "type": "Feature",
  "properties": {
    "gn:admin1_code":"4.0",
    "gn:admin2_code":"TPE",
    "gn:admin3_code":"A16",
    "gn:admin4_code":"63000120018.0",
    "gn:asciiname":"Zhongbaxian",
    "gn:country_code":"TW",
    "gn:dem":5,
    "gn:feature_class":"P",
    "gn:feature_code":"PPL",
    "gn:name":"Zhongbaxian",
    "gn:population":0,
    "gn:timezone":"Asia/Taipei",
    "iso:country":"TW",
    "name:und_x_variant":[
        "Jhongbasian",
        "Chung-pa-hsien"
    ],
    "name:zho_x_preferred":[
        "\u4e2d\u516b\u4ed9"
    ],
    "wof:name":"Zhongbaxian",
    "wof:placetype":"locality"
},
  "geometry": {"coordinates":[121.4961,25.1155],"type":"Point"}
}