{
  "type": "Feature",
  "properties": {
    "gn:admin1_code":"4.0",
    "gn:admin2_code":"HUA",
    "gn:admin3_code":"U06",
    "gn:admin4_code":"10015060009.0",
    "gn:asciiname":"Ganlin",
    "gn:country_code":"TW",
    "gn:dem":125,
    "gn:feature_class":"P",
    "gn:feature_code":"PPL",
    "gn:name":"Ganlin",
    "gn:population":0,
    "gn:timezone":"Asia/Taipei",
    "iso:country":"TW",
    "name:und_x_variant":[
        "Kan-lin"
    ],
    "name:zho_x_preferred":[
        "\u67d1\u6797"
    ],
    "wof:name":"Ganlin",
    "wof:placetype":"locality"
},
  "geometry": {"coordinates":[121.50712,23.91021],"type":"Point"}
}