{
  "type": "Feature",
  "properties": {
    "gn:admin1_code":"4.0",
    "gn:admin2_code":"PIF",
    "gn:admin3_code":"T27",
    "gn:admin4_code":"10013270001.0",
    "gn:asciiname":"Shenshan",
    "gn:country_code":"TW",
    "gn:dem":540,
    "gn:feature_class":"P",
    "gn:feature_code":"PPL",
    "gn:name":"Shenshan",
    "gn:population":0,
    "gn:timezone":"Asia/Taipei",
    "iso:country":"TW",
    "name:und_x_variant":[
        "Hua-jung-she",
        "Hua-jung",
        "Shenshan",
        "Shen-shan"
    ],
    "name:zho_x_preferred":[
        "Wu-t\u2019ai-ts\u2019un"
    ],
    "name:zho_x_variant":[
        "\u795e\u5c71",
        "Hsia-wu-t\u2019ai"
    ],
    "wof:name":"Shenshan",
    "wof:placetype":"locality"
},
  "geometry": {"coordinates":[120.7226,22.7513],"type":"Point"}
}