{
  "type": "Feature",
  "properties": {
    "gn:admin1_code":"04",
    "gn:admin2_code":"CYQ",
    "gn:admin3_code":"Q15",
    "gn:admin4_code":"10010140015.0",
    "gn:asciiname":"Tangxialiao",
    "gn:country_code":"TW",
    "gn:dem":154,
    "gn:feature_class":"P",
    "gn:feature_code":"PPL",
    "gn:name":"Tangxialiao",
    "gn:population":0,
    "gn:timezone":"Asia/Taipei",
    "iso:country":"TW",
    "name:und_x_variant":[
        "Tangsialiao"
    ],
    "name:zho_x_preferred":[
        "\u5858\u4e0b\u5bee"
    ],
    "name:zho_x_variant":[
        "T\u2019ang-hsia",
        "T\u2019ang-hsia-liao"
    ],
    "wof:name":"Tangxialiao",
    "wof:placetype":"locality"
},
  "geometry": {"coordinates":[120.56999999999999,23.49306],"type":"Point"}
}