{
  "type": "Feature",
  "properties": {
    "gn:admin1_code":"04",
    "gn:admin2_code":"NAN",
    "gn:admin3_code":"M03",
    "gn:admin4_code":"10008030009.0",
    "gn:asciiname":"Yuemeicuo",
    "gn:country_code":"TW",
    "gn:dem":80,
    "gn:feature_class":"P",
    "gn:feature_code":"PPL",
    "gn:name":"Yuemeicuo",
    "gn:population":0,
    "gn:timezone":"Asia/Taipei",
    "iso:country":"TW",
    "name:und_x_variant":[
        "Yuemeicuo"
    ],
    "name:zho_x_preferred":[
        "\u6708\u7709\u539d"
    ],
    "name:zho_x_variant":[
        "Y\u00fceh-mei",
        "Y\u00fceh-mei-ts\u2019o",
        "Y\u00fceh-mei-li"
    ],
    "wof:name":"Yuemeicuo",
    "wof:placetype":"locality"
},
  "geometry": {"coordinates":[120.65191000000002,23.971],"type":"Point"}
}