{
  "type": "Feature",
  "properties": {
    "gn:admin1_code":"03",
    "gn:admin2_code":"TPQ",
    "gn:admin3_code":"F07",
    "gn:admin4_code":"65000060023.0",
    "gn:asciiname":"Meiziliao",
    "gn:country_code":"TW",
    "gn:dem":131,
    "gn:feature_class":"P",
    "gn:feature_code":"PPL",
    "gn:name":"Meiziliao",
    "gn:population":0,
    "gn:timezone":"Asia/Taipei",
    "iso:country":"TW",
    "name:und_x_variant":[
        "Meizihliao",
        "Meiziliao",
        "Mei-tzu-liao"
    ],
    "name:zho_x_preferred":[
        "\u6963\u5b50\u5bee"
    ],
    "wof:name":"Meiziliao",
    "wof:placetype":"locality"
},
  "geometry": {"coordinates":[121.57097,24.95884],"type":"Point"}
}