{
  "type": "Feature",
  "properties": {
    "gn:admin1_code":"03",
    "gn:admin2_code":"TPQ",
    "gn:admin3_code":"F09",
    "gn:admin4_code":"65000180004.0",
    "gn:asciiname":"Wangjunliao",
    "gn:country_code":"TW",
    "gn:dem":175,
    "gn:feature_class":"P",
    "gn:feature_code":"PPL",
    "gn:name":"Wangjunliao",
    "gn:population":0,
    "gn:timezone":"Asia/Taipei",
    "iso:country":"TW",
    "name:und_x_variant":[
        "Wangjyunliao"
    ],
    "name:zho_x_preferred":[
        "\u738b\u8ecd\u5bee"
    ],
    "name:zho_x_variant":[
        "Wang-ch\u00fcn-liao"
    ],
    "wof:name":"Wangjunliao",
    "wof:placetype":"locality"
},
  "geometry": {"coordinates":[121.62085,24.98408],"type":"Point"}
}