{
  "type": "Feature",
  "properties": {
    "gn:admin1_code":"4.0",
    "gn:admin2_code":"HSZ",
    "gn:admin3_code":"J11",
    "gn:admin4_code":"10004100001.0",
    "gn:asciiname":"Baoshan",
    "gn:country_code":"TW",
    "gn:dem":57,
    "gn:feature_class":"P",
    "gn:feature_code":"PPL",
    "gn:name":"Baoshan",
    "gn:population":0,
    "gn:timezone":"Asia/Taipei",
    "iso:country":"TW",
    "name:und_x_variant":[
        "Pao-shan"
    ],
    "name:zho_x_preferred":[
        "\u5bf6\u5c71"
    ],
    "wof:name":"Baoshan",
    "wof:placetype":"locality"
},
  "geometry": {"coordinates":[120.99056000000002,24.76444],"type":"Point"}
}