{
  "type": "Feature",
  "properties": {
    "iso:country":"TW",
    "qs:name":"\u5357\u5bee\u6751",
    "qs:name_adm0":"\u81fa\u7063",
    "qs:name_adm1":"\u53f0\u6771\u7e23",
    "qs:photos":1049,
    "qs:photos_1k":213,
    "qs:photos_9k":5,
    "qs:photos_9r":7,
    "qs:photos_all":1049,
    "qs:photos_sr":11,
    "qs:placetype":"Town",
    "qs:pop_sr":"0",
    "wof:name":"\u5357\u5bee\u6751",
    "wof:placetype":"locality"
},
  "geometry": {"coordinates":[121.481323,22.652828],"type":"Point"}
}