{
  "type": "Feature",
  "properties": {
    "iso:country":"TW",
    "qs:name":"\u6c38\u548c\u6751",
    "qs:name_adm0":"\u81fa\u7063",
    "qs:name_adm1":"\u82d7\u6817\u7e23",
    "qs:photos":74,
    "qs:photos_1k":15,
    "qs:photos_9k":1,
    "qs:photos_9r":2,
    "qs:photos_all":74,
    "qs:photos_sr":2,
    "qs:placetype":"Town",
    "qs:pop_sr":"0",
    "wof:name":"\u6c38\u548c\u6751",
    "wof:placetype":"locality"
},
  "geometry": {"coordinates":[120.9249825,24.6567745],"type":"Point"}
}