{
  "type": "Feature",
  "properties": {
    "gn:admin1_code":"04",
    "gn:admin2_code":"ILA",
    "gn:admin3_code":"G05",
    "gn:admin4_code":"10002070008.0",
    "gn:asciiname":"Zailian",
    "gn:country_code":"TW",
    "gn:dem":64,
    "gn:feature_class":"P",
    "gn:feature_code":"PPL",
    "gn:name":"Zailian",
    "gn:population":0,
    "gn:timezone":"Asia/Taipei",
    "iso:country":"TW",
    "name:und_x_variant":[
        "Tsai-lien"
    ],
    "name:zho_x_preferred":[
        "\u518d\u9023"
    ],
    "wof:name":"Zailian",
    "wof:placetype":"locality"
},
  "geometry": {"coordinates":[121.66467,24.71137],"type":"Point"}
}