{
  "type": "Feature",
  "properties": {
    "gn:admin1_code":"4.0",
    "gn:admin2_code":"YUN",
    "gn:admin3_code":"P10",
    "gn:admin4_code":"10009100008.0",
    "gn:asciiname":"Dingwutuzi",
    "gn:country_code":"TW",
    "gn:dem":77,
    "gn:feature_class":"P",
    "gn:feature_code":"PPL",
    "gn:name":"Dingwutuzi",
    "gn:population":0,
    "gn:timezone":"Asia/Taipei",
    "iso:country":"TW",
    "name:und_x_variant":[
        "Dingwutuzih",
        "Dingwutuzi"
    ],
    "name:zho_x_preferred":[
        "\u9802\u70cf\u5857\u4ed4"
    ],
    "name:zho_x_variant":[
        "Ting-wu-t\u2019u-tzu"
    ],
    "wof:name":"Dingwutuzi",
    "wof:placetype":"locality"
},
  "geometry": {"coordinates":[120.59885,23.76965],"type":"Point"}
}