{
  "type": "Feature",
  "properties": {
    "gn:admin1_code":"4.0",
    "gn:admin2_code":"YUN",
    "gn:admin3_code":"P02",
    "gn:admin4_code":"10009020016.0",
    "gn:asciiname":"Erchonggou",
    "gn:country_code":"TW",
    "gn:dem":33,
    "gn:feature_class":"P",
    "gn:feature_code":"PPL",
    "gn:name":"Erchonggou",
    "gn:population":0,
    "gn:timezone":"Asia/Taipei",
    "iso:country":"TW",
    "name:zho_x_preferred":[
        "Erh-ch\u2019ung-ch\u2019i"
    ],
    "name:zho_x_variant":[
        "Feng-t\u2019ien-ts\u2019un",
        "Erh-ch\u2019ung-hsi",
        "\u4e8c\u91cd\u6e9d",
        "Feng-t\u2019ien",
        "Erh-ch\u2019ung-kou"
    ],
    "wof:name":"Erchonggou",
    "wof:placetype":"locality"
},
  "geometry": {"coordinates":[120.46460999999999,23.66712],"type":"Point"}
}