{
  "type": "Feature",
  "properties": {
    "gn:admin1_code":"4.0",
    "gn:admin2_code":"CYQ",
    "gn:admin3_code":"Q13",
    "gn:admin4_code":"10010120022.0",
    "gn:asciiname":"Lutenghu",
    "gn:country_code":"TW",
    "gn:dem":111,
    "gn:feature_class":"P",
    "gn:feature_code":"PPL",
    "gn:name":"Lutenghu",
    "gn:population":0,
    "gn:timezone":"Asia/Taipei",
    "iso:country":"TW",
    "name:zho_x_preferred":[
        "\u8606\u7c50\u6e56"
    ],
    "name:zho_x_variant":[
        "Lu-t\u2019eng-hu"
    ],
    "wof:name":"Lutenghu",
    "wof:placetype":"locality"
},
  "geometry": {"coordinates":[120.4825,23.39361],"type":"Point"}
}