{
  "type": "Feature",
  "properties": {
    "gn:admin1_code":"4.0",
    "gn:admin2_code":"MIA",
    "gn:admin3_code":"K03",
    "gn:admin4_code":"10005030015.0",
    "gn:asciiname":"Hongluqi",
    "gn:country_code":"TW",
    "gn:dem":109,
    "gn:feature_class":"P",
    "gn:feature_code":"PPL",
    "gn:name":"Hongluqi",
    "gn:population":0,
    "gn:timezone":"Asia/Taipei",
    "iso:country":"TW",
    "name:und_x_variant":[
        "Hongluci"
    ],
    "name:zho_x_preferred":[
        "\u70d8\u7210\u5d0e"
    ],
    "name:zho_x_variant":[
        "Hung-lu-ch\u2019i"
    ],
    "wof:name":"Hongluqi",
    "wof:placetype":"locality"
},
  "geometry": {"coordinates":[120.74056000000002,24.48611],"type":"Point"}
}