{
  "type": "Feature",
  "properties": {
    "gn:admin1_code":"4.0",
    "gn:admin2_code":"YUN",
    "gn:admin3_code":"P17",
    "gn:admin4_code":"10009170012.0",
    "gn:asciiname":"Zhongkengzi",
    "gn:country_code":"TW",
    "gn:dem":15,
    "gn:feature_class":"P",
    "gn:feature_code":"PPL",
    "gn:name":"Zhongkengzi",
    "gn:population":0,
    "gn:timezone":"Asia/Taipei",
    "iso:country":"TW",
    "name:und_x_variant":[
        "Chung-hang-tzu",
        "Zhongkengzi",
        "Jhongkengzih"
    ],
    "name:zho_x_preferred":[
        "Chung-k\u2019eng"
    ],
    "name:zho_x_variant":[
        "\u4e2d\u5751\u5b50",
        "Chung-k\u2019eng-tzu"
    ],
    "wof:name":"Zhongkengzi",
    "wof:placetype":"locality"
},
  "geometry": {"coordinates":[120.32841000000001,23.63774],"type":"Point"}
}