{
  "type": "Feature",
  "properties": {
    "gn:admin1_code":"04",
    "gn:admin2_code":"NAN",
    "gn:admin3_code":"M12",
    "gn:admin4_code":"10008120001.0",
    "gn:asciiname":"Tongge",
    "gn:country_code":"TW",
    "gn:dem":783,
    "gn:feature_class":"P",
    "gn:feature_code":"PPL",
    "gn:name":"Tongge",
    "gn:population":0,
    "gn:timezone":"Asia/Taipei",
    "iso:country":"TW",
    "name:und_x_variant":[
        "Pu-t\u2019ung-k\u2019uo-she",
        "Pu-t\u2019ung-ko-she",
        "T\u2019ung-ko",
        "Tongge"
    ],
    "wof:name":"Tongge",
    "wof:placetype":"locality"
},
  "geometry": {"coordinates":[120.91667,23.73333],"type":"Point"}
}