{
  "type": "Feature",
  "properties": {
    "gn:admin1_code":"4.0",
    "gn:admin2_code":"PIF",
    "gn:admin3_code":"T30",
    "gn:admin4_code":"10013300001.0",
    "gn:asciiname":"Neishe",
    "gn:country_code":"TW",
    "gn:dem":212,
    "gn:feature_class":"P",
    "gn:feature_code":"PPL",
    "gn:name":"Neishe",
    "gn:population":0,
    "gn:timezone":"Asia/Taipei",
    "iso:country":"TW",
    "name:und_x_variant":[
        "Nei-she"
    ],
    "name:zho_x_preferred":[
        "\u5185\u793e"
    ],
    "wof:name":"Neishe",
    "wof:placetype":"locality"
},
  "geometry": {"coordinates":[120.6833,22.5266],"type":"Point"}
}