{
  "type": "Feature",
  "properties": {
    "gn:admin1_code":"4.0",
    "gn:admin2_code":"YUN",
    "gn:admin3_code":"P11",
    "gn:admin4_code":"10009110009.0",
    "gn:asciiname":"Yizhuang",
    "gn:country_code":"TW",
    "gn:dem":26,
    "gn:feature_class":"P",
    "gn:feature_code":"PPL",
    "gn:name":"Yizhuang",
    "gn:population":0,
    "gn:timezone":"Asia/Taipei",
    "iso:country":"TW",
    "name:und_x_variant":[
        "Hsin-chuang-tzu",
        "Yijhuang",
        "Yizhuang",
        "Yi-chuang",
        "I-chuang"
    ],
    "name:zho_x_preferred":[
        "I-chuang-ts\u2019un"
    ],
    "name:zho_x_variant":[
        "\u7fa9\u5e84"
    ],
    "wof:name":"Yizhuang",
    "wof:placetype":"locality"
},
  "geometry": {"coordinates":[120.42054,23.81812],"type":"Point"}
}