{
  "type": "Feature",
  "properties": {
    "iso:country":"TW",
    "qs:name":"\u798f\u58fd\u91cc",
    "qs:name_adm0":"\u81fa\u7063",
    "qs:name_adm1":"\u9ad8\u96c4\u5e02",
    "qs:photos":21,
    "qs:photos_1k":4,
    "qs:photos_9k":1,
    "qs:photos_9r":1,
    "qs:photos_all":21,
    "qs:photos_sr":1,
    "qs:placetype":"Suburb",
    "qs:pop_sr":"0",
    "wof:name":"\u798f\u58fd\u91cc",
    "wof:placetype":"neighbourhood"
},
  "geometry": {"coordinates":[120.327883,22.62758],"type":"Point"}
}