{
  "type": "Feature",
  "properties": {
    "gn:admin1_code":"4.0",
    "gn:admin2_code":"CYQ",
    "gn:admin3_code":"Q16",
    "gn:admin4_code":"10010150006.0",
    "gn:asciiname":"Jiuxiongkeng",
    "gn:country_code":"TW",
    "gn:dem":211,
    "gn:feature_class":"P",
    "gn:feature_code":"PPL",
    "gn:name":"Jiuxiongkeng",
    "gn:population":0,
    "gn:timezone":"Asia/Taipei",
    "iso:country":"TW",
    "name:und_x_variant":[
        "Jiousyongkeng"
    ],
    "name:zho_x_preferred":[
        "\u4e5d\u828e\u5751"
    ],
    "name:zho_x_variant":[
        "Chiu-hsiung-k\u2019eng"
    ],
    "wof:name":"Jiuxiongkeng",
    "wof:placetype":"locality"
},
  "geometry": {"coordinates":[120.56083,23.56778],"type":"Point"}
}