{
  "type": "Feature",
  "properties": {
    "gn:admin1_code":"4.0",
    "gn:admin2_code":"MIA",
    "gn:admin3_code":"K17",
    "gn:admin4_code":"10005170007.0",
    "gn:asciiname":"Lixiangping",
    "gn:country_code":"TW",
    "gn:dem":246,
    "gn:feature_class":"P",
    "gn:feature_code":"PPL",
    "gn:name":"Lixiangping",
    "gn:population":0,
    "gn:timezone":"Asia/Taipei",
    "iso:country":"TW",
    "name:und_x_variant":[
        "Lisiangping"
    ],
    "name:zho_x_preferred":[
        "\u7281\u7965\u576a"
    ],
    "name:zho_x_variant":[
        "Li-hsiang-p\u2019ing"
    ],
    "wof:name":"Lixiangping",
    "wof:placetype":"locality"
},
  "geometry": {"coordinates":[120.88402000000001,24.46169],"type":"Point"}
}