{
  "type": "Feature",
  "properties": {
    "gn:admin1_code":"4.0",
    "gn:admin2_code":"NAN",
    "gn:admin3_code":"M02",
    "gn:admin4_code":"10008020022.0",
    "gn:asciiname":"Dazhuang",
    "gn:country_code":"TW",
    "gn:dem":476,
    "gn:feature_class":"P",
    "gn:feature_code":"PPL",
    "gn:name":"Dazhuang",
    "gn:population":0,
    "gn:timezone":"Asia/Taipei",
    "iso:country":"TW",
    "name:und_x_variant":[
        "Dajhuang",
        "Dazhuang",
        "Ta-chuang"
    ],
    "name:zho_x_preferred":[
        "\u5927\u838a"
    ],
    "wof:name":"Dazhuang",
    "wof:placetype":"locality"
},
  "geometry": {"coordinates":[120.93463,24.00384],"type":"Point"}
}