{
  "type": "Feature",
  "properties": {
    "gn:admin1_code":"4.0",
    "gn:admin2_code":"TTT",
    "gn:admin3_code":"V04",
    "gn:admin4_code":"10014040006.0",
    "gn:asciiname":"Wujiapo",
    "gn:country_code":"TW",
    "gn:dem":369,
    "gn:feature_class":"P",
    "gn:feature_code":"PPL",
    "gn:name":"Wujiapo",
    "gn:population":0,
    "gn:timezone":"Asia/Taipei",
    "iso:country":"TW",
    "name:zho_x_preferred":[
        "\u4e94\u5bb6\u5761"
    ],
    "name:zho_x_variant":[
        "Wu-chia-p\u2019o"
    ],
    "wof:name":"Wujiapo",
    "wof:placetype":"locality"
},
  "geometry": {"coordinates":[121.08072,22.85839],"type":"Point"}
}