{
  "type": "Feature",
  "properties": {
    "gn:admin1_code":"04",
    "gn:admin2_code":"MIA",
    "gn:admin3_code":"K04",
    "gn:admin4_code":"10005090010.0",
    "gn:asciiname":"Nanliao",
    "gn:country_code":"TW",
    "gn:dem":236,
    "gn:feature_class":"P",
    "gn:feature_code":"PPL",
    "gn:name":"Nanliao",
    "gn:population":0,
    "gn:timezone":"Asia/Taipei",
    "iso:country":"TW",
    "name:und_x_variant":[
        "Nan-liao",
        "Nanliao"
    ],
    "name:zho_x_preferred":[
        "\u5357\u5bee"
    ],
    "wof:name":"Nanliao",
    "wof:placetype":"locality"
},
  "geometry": {"coordinates":[120.87205,24.46267000000001],"type":"Point"}
}