{
  "type": "Feature",
  "properties": {
    "gn:admin1_code":"4.0",
    "gn:admin2_code":"TNN",
    "gn:admin3_code":"R27",
    "gn:admin4_code":"67000270003.0",
    "gn:asciiname":"Yijia",
    "gn:country_code":"TW",
    "gn:dem":10,
    "gn:feature_class":"P",
    "gn:feature_code":"PPL",
    "gn:name":"Yijia",
    "gn:population":0,
    "gn:timezone":"Asia/Taipei",
    "iso:country":"TW",
    "name:und_x_variant":[
        "I-chia"
    ],
    "name:zho_x_preferred":[
        "\u4e00\u7532"
    ],
    "wof:name":"Yijia",
    "wof:placetype":"locality"
},
  "geometry": {"coordinates":[120.25556,22.97667],"type":"Point"}
}