{
  "type": "Feature",
  "properties": {
    "gn:admin1_code":"4.0",
    "gn:admin2_code":"TAO",
    "gn:admin3_code":"H02",
    "gn:admin4_code":"68000030013.0",
    "gn:asciiname":"Gongguan",
    "gn:country_code":"TW",
    "gn:dem":94,
    "gn:feature_class":"P",
    "gn:feature_code":"PPL",
    "gn:name":"Gongguan",
    "gn:population":0,
    "gn:timezone":"Asia/Taipei",
    "iso:country":"TW",
    "name:deu_x_preferred":[
        "Gongguan"
    ],
    "name:und_x_variant":[
        "Kung-kuan"
    ],
    "name:zho_x_preferred":[
        "\u516c\u9928"
    ],
    "wof:name":"Gongguan",
    "wof:placetype":"locality"
},
  "geometry": {"coordinates":[121.30146000000001,24.91925],"type":"Point"}
}