{
  "type": "Feature",
  "properties": {
    "gn:admin1_code":"4.0",
    "gn:admin2_code":"TXG",
    "gn:admin3_code":"B27",
    "gn:admin4_code":"66000270014.0",
    "gn:asciiname":"Xiaoneixian",
    "gn:country_code":"TW",
    "gn:dem":389,
    "gn:feature_class":"P",
    "gn:feature_code":"PPL",
    "gn:name":"Xiaoneixian",
    "gn:population":0,
    "gn:timezone":"Asia/Taipei",
    "iso:country":"TW",
    "name:und_x_variant":[
        "Siaoneisian",
        "Hsiao-nei-hsien"
    ],
    "name:zho_x_preferred":[
        "\u5c0f\u5185\u96aa"
    ],
    "wof:name":"Xiaoneixian",
    "wof:placetype":"locality"
},
  "geometry": {"coordinates":[120.79737,24.13689],"type":"Point"}
}