{
  "type": "Feature",
  "properties": {
    "gn:admin1_code":"4.0",
    "gn:admin2_code":"TPE",
    "gn:admin3_code":"A16",
    "gn:admin4_code":"63000120018.0",
    "gn:asciiname":"Tudigongba",
    "gn:country_code":"TW",
    "gn:dem":5,
    "gn:feature_class":"P",
    "gn:feature_code":"PPL",
    "gn:name":"Tudigongba",
    "gn:population":0,
    "gn:timezone":"Asia/Taipei",
    "iso:country":"TW",
    "name:zho_x_preferred":[
        "\u571f\u5730\u516c\u58e9"
    ],
    "name:zho_x_variant":[
        "T\u2019u-ti-kung-pa"
    ],
    "wof:name":"Tudigongba",
    "wof:placetype":"locality"
},
  "geometry": {"coordinates":[121.49695,25.1226],"type":"Point"}
}