{
  "type": "Feature",
  "properties": {
    "gn:admin1_code":"4.0",
    "gn:admin2_code":"NAN",
    "gn:admin3_code":"M11",
    "gn:admin4_code":"10008110009.0",
    "gn:asciiname":"Zhongzhuangzi",
    "gn:country_code":"TW",
    "gn:dem":652,
    "gn:feature_class":"P",
    "gn:feature_code":"PPL",
    "gn:name":"Zhongzhuangzi",
    "gn:population":0,
    "gn:timezone":"Asia/Taipei",
    "iso:country":"TW",
    "name:und_x_variant":[
        "Jhongjhuangzih",
        "Zhongzhuangzi",
        "Chung-zhuang-tzu"
    ],
    "name:zho_x_preferred":[
        "\u4e2d\u838a\u4ed4"
    ],
    "wof:name":"Zhongzhuangzi",
    "wof:placetype":"locality"
},
  "geometry": {"coordinates":[120.88197,23.80126],"type":"Point"}
}