{
  "type": "Feature",
  "properties": {
    "gn:admin1_code":"4.0",
    "gn:admin2_code":"ILA",
    "gn:admin3_code":"G07",
    "gn:admin4_code":"10002090011.0",
    "gn:asciiname":"Xiaxiaowei",
    "gn:country_code":"TW",
    "gn:dem":5,
    "gn:feature_class":"P",
    "gn:feature_code":"PPL",
    "gn:name":"Xiaxiaowei",
    "gn:population":0,
    "gn:timezone":"Asia/Taipei",
    "iso:country":"TW",
    "name:und_x_variant":[
        "Siasiaowei",
        "Xiaxiaowei",
        "Hsia-hsiao-wei"
    ],
    "name:zho_x_preferred":[
        "\u4e0b\u5b5d\u5a01"
    ],
    "wof:name":"Xiaxiaowei",
    "wof:placetype":"locality"
},
  "geometry": {"coordinates":[121.8155,24.6911],"type":"Point"}
}