{
  "type": "Feature",
  "properties": {
    "gn:admin1_code":"4.0",
    "gn:admin2_code":"TAO",
    "gn:admin3_code":"H11",
    "gn:admin4_code":"68000110023.0",
    "gn:asciiname":"Lyuwu",
    "gn:country_code":"TW",
    "gn:dem":63,
    "gn:feature_class":"P",
    "gn:feature_code":"PPL",
    "gn:name":"Lyuwu",
    "gn:population":0,
    "gn:timezone":"Asia/Taipei",
    "iso:country":"TW",
    "name:zho_x_preferred":[
        "\u5442\u5c4b"
    ],
    "name:zho_x_variant":[
        "L\u00fcwu",
        "L\u00fc-wu"
    ],
    "wof:name":"Lyuwu",
    "wof:placetype":"locality"
},
  "geometry": {"coordinates":[121.06471999999999,24.9475],"type":"Point"}
}