{
  "type": "Feature",
  "properties": {
    "gn:admin1_code":"03",
    "gn:admin2_code":"TPQ",
    "gn:admin3_code":"F19",
    "gn:admin4_code":"65000130022.0",
    "gn:asciiname":"Peishepo",
    "gn:country_code":"TW",
    "gn:dem":5,
    "gn:feature_class":"P",
    "gn:feature_code":"PPL",
    "gn:name":"Peishepo",
    "gn:population":0,
    "gn:timezone":"Asia/Taipei",
    "iso:country":"TW",
    "name:und_x_variant":[
        "P\u2019ei-she-p\u2019o"
    ],
    "wof:name":"Peishepo",
    "wof:placetype":"locality"
},
  "geometry": {"coordinates":[121.41667,24.96667],"type":"Point"}
}