{
  "type": "Feature",
  "properties": {
    "gn:admin1_code":"04",
    "gn:admin2_code":"YUN",
    "gn:admin3_code":"P01",
    "gn:admin4_code":"10009010016.0",
    "gn:asciiname":"Wacuozi",
    "gn:country_code":"TW",
    "gn:dem":47,
    "gn:feature_class":"P",
    "gn:feature_code":"PPL",
    "gn:name":"Wacuozi",
    "gn:population":0,
    "gn:timezone":"Asia/Taipei",
    "iso:country":"TW",
    "name:und_x_variant":[
        "Wacuozih",
        "Wacuozi"
    ],
    "name:zho_x_preferred":[
        "\u74e6\u539d\u5b50"
    ],
    "name:zho_x_variant":[
        "Wa-ts\u2019o-tzu"
    ],
    "wof:name":"Wacuozi",
    "wof:placetype":"locality"
},
  "geometry": {"coordinates":[120.51555999999999,23.66944],"type":"Point"}
}