{
  "type": "Feature",
  "properties": {
    "gn:admin1_code":"02",
    "gn:admin2_code":"KHH",
    "gn:admin3_code":"E22",
    "gn:admin4_code":"64000220003.0",
    "gn:asciiname":"Caitang",
    "gn:country_code":"TW",
    "gn:dem":54,
    "gn:feature_class":"P",
    "gn:feature_code":"PPL",
    "gn:name":"Caitang",
    "gn:population":0,
    "gn:timezone":"Asia/Taipei",
    "iso:country":"TW",
    "name:zho_x_preferred":[
        "\u83dc\u5802"
    ],
    "name:zho_x_variant":[
        "Ts\u2019ai-t\u2019ang"
    ],
    "wof:name":"Caitang",
    "wof:placetype":"locality"
},
  "geometry": {"coordinates":[120.40111,22.84889],"type":"Point"}
}