{
  "type": "Feature",
  "properties": {
    "gn:admin1_code":"4.0",
    "gn:admin2_code":"TXG",
    "gn:admin3_code":"B11",
    "gn:admin4_code":"66000110024.0",
    "gn:asciiname":"Huweiliao",
    "gn:country_code":"TW",
    "gn:dem":33,
    "gn:feature_class":"P",
    "gn:feature_code":"PPL",
    "gn:name":"Huweiliao",
    "gn:population":0,
    "gn:timezone":"Asia/Taipei",
    "iso:country":"TW",
    "name:und_x_variant":[
        "Hu-wei-liao"
    ],
    "name:zho_x_preferred":[
        "\u864e\u5c3e\u5bee"
    ],
    "wof:name":"Huweiliao",
    "wof:placetype":"locality"
},
  "geometry": {"coordinates":[120.64388999999998,24.41333],"type":"Point"}
}