{
  "type": "Feature",
  "properties": {
    "gn:admin1_code":"4.0",
    "gn:admin2_code":"TNN",
    "gn:admin3_code":"R29",
    "gn:admin4_code":"67000290014.0",
    "gn:asciiname":"Taxi",
    "gn:country_code":"TW",
    "gn:dem":34,
    "gn:feature_class":"P",
    "gn:feature_code":"PPL",
    "gn:name":"Taxi",
    "gn:population":0,
    "gn:timezone":"Asia/Taipei",
    "iso:country":"TW",
    "name:und_x_variant":[
        "Tasi",
        "Fan-hsi",
        "Cha-hsi",
        "Taxi"
    ],
    "name:zho_x_preferred":[
        "Fan-ch\u2019i"
    ],
    "name:zho_x_variant":[
        "\u6c93\u6eaa",
        "T\u2019a-hsi"
    ],
    "wof:name":"Taxi",
    "wof:placetype":"locality"
},
  "geometry": {"coordinates":[120.35583,22.8975],"type":"Point"}
}