{
  "type": "Feature",
  "properties": {
    "gn:admin1_code":"3.0",
    "gn:admin2_code":"TPQ",
    "gn:admin3_code":"F17",
    "gn:admin4_code":"65000070026.0",
    "gn:asciiname":"Lincuo",
    "gn:country_code":"TW",
    "gn:dem":35,
    "gn:feature_class":"P",
    "gn:feature_code":"PPL",
    "gn:name":"Lincuo",
    "gn:population":0,
    "gn:timezone":"Asia/Taipei",
    "iso:country":"TW",
    "name:zho_x_preferred":[
        "\u6797\u539d"
    ],
    "name:zho_x_variant":[
        "Lin-ts\u2019o"
    ],
    "wof:name":"Lincuo",
    "wof:placetype":"locality"
},
  "geometry": {"coordinates":[121.38587,24.95427],"type":"Point"}
}