{
  "type": "Feature",
  "properties": {
    "gn:admin1_code":"4.0",
    "gn:admin2_code":"CYQ",
    "gn:admin3_code":"Q06",
    "gn:admin4_code":"10010060012.0",
    "gn:asciiname":"Xiayuanlin",
    "gn:country_code":"TW",
    "gn:dem":29,
    "gn:feature_class":"P",
    "gn:feature_code":"PPL",
    "gn:name":"Xiayuanlin",
    "gn:population":0,
    "gn:timezone":"Asia/Taipei",
    "iso:country":"TW",
    "name:und_x_variant":[
        "Siayuanlin",
        "Xiayuanlin"
    ],
    "name:zho_x_preferred":[
        "\u4e0b\u54e1\u6797"
    ],
    "name:zho_x_variant":[
        "Hsia-y\u00fcan-lin"
    ],
    "wof:name":"Xiayuanlin",
    "wof:placetype":"locality"
},
  "geometry": {"coordinates":[120.44403,23.59288],"type":"Point"}
}