{
  "type": "Feature",
  "properties": {
    "gn:admin1_code":"4.0",
    "gn:admin2_code":"TNN",
    "gn:admin3_code":"R25",
    "gn:admin4_code":"67000250002.0",
    "gn:asciiname":"Jingmian",
    "gn:country_code":"TW",
    "gn:dem":177,
    "gn:feature_class":"P",
    "gn:feature_code":"PPL",
    "gn:name":"Jingmian",
    "gn:population":0,
    "gn:timezone":"Asia/Taipei",
    "iso:country":"TW",
    "name:und_x_variant":[
        "Ching-mein",
        "Ching-mien"
    ],
    "name:zho_x_preferred":[
        "\u93e1\u9762"
    ],
    "wof:name":"Jingmian",
    "wof:placetype":"locality"
},
  "geometry": {"coordinates":[120.49961999999999,23.05829],"type":"Point"}
}