{
  "type": "Feature",
  "properties": {
    "gn:admin1_code":"04",
    "gn:admin2_code":"NAN",
    "gn:admin3_code":"M12",
    "gn:admin4_code":"10008120008.0",
    "gn:asciiname":"Ziqiang",
    "gn:country_code":"TW",
    "gn:dem":1410,
    "gn:feature_class":"P",
    "gn:feature_code":"PPL",
    "gn:name":"Ziqiang",
    "gn:population":0,
    "gn:timezone":"Asia/Taipei",
    "iso:country":"TW",
    "name:und_x_variant":[
        "Tzu-ch\u2019iang-ts\u2019un",
        "Tzu-ch\u2019iang",
        "Ziqiang"
    ],
    "wof:name":"Ziqiang",
    "wof:placetype":"locality"
},
  "geometry": {"coordinates":[120.86667,23.58333],"type":"Point"}
}