{
  "type": "Feature",
  "properties": {
    "gn:admin1_code":"4.0",
    "gn:admin2_code":"NAN",
    "gn:admin3_code":"M13",
    "gn:admin4_code":"10008130009.0",
    "gn:asciiname":"Kenanguan",
    "gn:country_code":"TW",
    "gn:dem":3156,
    "gn:feature_class":"P",
    "gn:feature_code":"PPL",
    "gn:name":"Kenanguan",
    "gn:population":0,
    "gn:timezone":"Asia/Taipei",
    "iso:country":"TW",
    "name:zho_x_preferred":[
        "\u514b\u96e3\u95dc"
    ],
    "name:zho_x_variant":[
        "K\u2019o-nan-kuan"
    ],
    "wof:name":"Kenanguan",
    "wof:placetype":"locality"
},
  "geometry": {"coordinates":[121.28028,24.15222],"type":"Point"}
}