{
  "type": "Feature",
  "properties": {
    "gn:admin1_code":"4.0",
    "gn:admin2_code":"TTT",
    "gn:admin3_code":"V10",
    "gn:admin4_code":"10014060010.0",
    "gn:asciiname":"Jiawen",
    "gn:country_code":"TW",
    "gn:dem":311,
    "gn:feature_class":"P",
    "gn:feature_code":"PPL",
    "gn:name":"Jiawen",
    "gn:population":0,
    "gn:timezone":"Asia/Taipei",
    "iso:country":"TW",
    "name:und_x_variant":[
        "Jiawun",
        "Jiawen",
        "Chia-wen"
    ],
    "name:zho_x_preferred":[
        "\u5609\u6587"
    ],
    "wof:name":"Jiawen",
    "wof:placetype":"locality"
},
  "geometry": {"coordinates":[121.18861,23.03472],"type":"Point"}
}