{
  "type": "Feature",
  "properties": {
    "gn:admin1_code":"01",
    "gn:admin2_code":"KIN",
    "gn:admin3_code":"W02",
    "gn:admin4_code":"9020020002.0",
    "gn:asciiname":"Bishan",
    "gn:country_code":"TW",
    "gn:dem":29,
    "gn:feature_class":"P",
    "gn:feature_code":"PPL",
    "gn:name":"Bishan",
    "gn:population":0,
    "gn:timezone":"Asia/Taipei",
    "iso:country":"TW",
    "name:ceb_x_preferred":[
        "Bishan"
    ],
    "name:nld_x_preferred":[
        "Bishan"
    ],
    "name:nor_x_preferred":[
        "Bishan"
    ],
    "name:und_x_variant":[
        "Pi-shan",
        "\u78a7\u5c71",
        "Bishan"
    ],
    "wof:name":"Bishan",
    "wof:placetype":"locality"
},
  "geometry": {"coordinates":[118.44414,24.48496],"type":"Point"}
}