{
  "type": "Feature",
  "properties": {
    "gn:admin1_code":"4.0",
    "gn:admin2_code":"TXG",
    "gn:admin3_code":"B27",
    "gn:admin4_code":"66000270014.0",
    "gn:asciiname":"Ganliaokeng",
    "gn:country_code":"TW",
    "gn:dem":603,
    "gn:feature_class":"P",
    "gn:feature_code":"PPL",
    "gn:name":"Ganliaokeng",
    "gn:population":0,
    "gn:timezone":"Asia/Taipei",
    "iso:country":"TW",
    "name:zho_x_preferred":[
        "\u713f\u5bee\u5751"
    ],
    "name:zho_x_variant":[
        "Keng-liao-k\u2019eng",
        "Kan-liao-k\u2019eng"
    ],
    "wof:name":"Ganliaokeng",
    "wof:placetype":"locality"
},
  "geometry": {"coordinates":[120.81068999999999,24.13782],"type":"Point"}
}