{
  "type": "Feature",
  "properties": {
    "gn:admin1_code":"04",
    "gn:admin2_code":"TPE",
    "gn:admin3_code":"A15",
    "gn:admin4_code":"63000110003.0",
    "gn:asciiname":"Shanzijiao",
    "gn:country_code":"TW",
    "gn:dem":14,
    "gn:feature_class":"P",
    "gn:feature_code":"PPL",
    "gn:name":"Shanzijiao",
    "gn:population":0,
    "gn:timezone":"Asia/Taipei",
    "iso:country":"TW",
    "name:und_x_variant":[
        "Shanzihjiao",
        "Shanzijiao",
        "Shan-tzu-chiao"
    ],
    "name:zho_x_preferred":[
        "\u5c71\u5b50\u811a"
    ],
    "wof:name":"Shanzijiao",
    "wof:placetype":"locality"
},
  "geometry": {"coordinates":[121.52759,25.08712],"type":"Point"}
}