{
  "type": "Feature",
  "properties": {
    "iso:country":"TW",
    "qs:name":"\u6cb9\u8eca\u6751",
    "qs:name_adm0":"\u81fa\u7063",
    "qs:name_adm1":"\u5f70\u5316\u7e23",
    "qs:photos":19,
    "qs:photos_1k":4,
    "qs:photos_9k":1,
    "qs:photos_9r":1,
    "qs:photos_all":19,
    "qs:photos_sr":1,
    "qs:placetype":"Town",
    "qs:pop_sr":"0",
    "wof:name":"\u6cb9\u8eca\u6751",
    "wof:placetype":"locality"
},
  "geometry": {"coordinates":[120.54199199999999,23.965862],"type":"Point"}
}