{
  "type": "Feature",
  "properties": {
    "gn:admin1_code":"04",
    "gn:admin2_code":"TNN",
    "gn:admin3_code":"R03",
    "gn:admin4_code":"67000030024.0",
    "gn:asciiname":"Pijiao",
    "gn:country_code":"TW",
    "gn:dem":40,
    "gn:feature_class":"P",
    "gn:feature_code":"PPL",
    "gn:name":"Pijiao",
    "gn:population":0,
    "gn:timezone":"Asia/Taipei",
    "iso:country":"TW",
    "name:zho_x_preferred":[
        "\u57e4\u89d2"
    ],
    "name:zho_x_variant":[
        "P\u2019i-chiao"
    ],
    "wof:name":"Pijiao",
    "wof:placetype":"locality"
},
  "geometry": {"coordinates":[120.43611,23.385],"type":"Point"}
}