{
  "type": "Feature",
  "properties": {
    "iso:country":"TW",
    "name:eng_x_preferred":[
        "Rizhong"
    ],
    "name:eng_x_variant":[
        "Rizhong Village"
    ],
    "name:zho_tw_x_preferred":[
        "\u65e5\u4e2d\u91cc"
    ],
    "qs:name":"\u65e5\u4e2d\u91cc",
    "qs:name_adm0":"\u81fa\u7063",
    "qs:name_adm1":"\u9ad8\u96c4\u5e02",
    "qs:photos":22,
    "qs:photos_1k":4,
    "qs:photos_9k":1,
    "qs:photos_9r":1,
    "qs:photos_all":22,
    "qs:photos_sr":1,
    "qs:placetype":"Suburb",
    "qs:pop_sr":"0",
    "wof:name":"Rizhong",
    "wof:placetype":"neighbourhood"
},
  "geometry": {"coordinates":[120.309684,22.616803],"type":"Point"}
}