{
  "type": "Feature",
  "properties": {
    "gn:admin1_code":"3.0",
    "gn:admin2_code":"TPQ",
    "gn:admin3_code":"F15",
    "gn:admin4_code":"65000090019.0",
    "gn:asciiname":"Pinglin",
    "gn:country_code":"TW",
    "gn:dem":46,
    "gn:feature_class":"P",
    "gn:feature_code":"PPL",
    "gn:name":"Pinglin",
    "gn:population":0,
    "gn:timezone":"Asia/Taipei",
    "iso:country":"TW",
    "name:zho_x_preferred":[
        "\u576a\u6797"
    ],
    "name:zho_x_variant":[
        "P\u2019ing-lin"
    ],
    "wof:name":"Pinglin",
    "wof:placetype":"locality"
},
  "geometry": {"coordinates":[121.40885,24.93252],"type":"Point"}
}