{
  "type": "Feature",
  "properties": {
    "gn:admin1_code":"04",
    "gn:admin2_code":"PEN",
    "gn:admin3_code":"X05",
    "gn:admin4_code":"10016050004.0",
    "gn:asciiname":"Shui'an",
    "gn:country_code":"TW",
    "gn:dem":12,
    "gn:feature_class":"P",
    "gn:feature_code":"PPL",
    "gn:name":"Shui\u2019an",
    "gn:population":0,
    "gn:timezone":"Asia/Taipei",
    "iso:country":"TW",
    "name:und_x_variant":[
        "Shui-an-hsiang",
        "Shui-an"
    ],
    "name:zho_x_preferred":[
        "\u6c34\u57b5"
    ],
    "name:zho_x_variant":[
        "Shui\u2019an",
        "Shuei\u2019an",
        "Shui-an-ts\u2019un"
    ],
    "wof:name":"Shui'an",
    "wof:placetype":"locality"
},
  "geometry": {"coordinates":[119.49917000000001,23.3875],"type":"Point"}
}