{
  "type": "Feature",
  "properties": {
    "gn:admin1_code":"4.0",
    "gn:admin2_code":"TXG",
    "gn:admin3_code":"B21",
    "gn:admin4_code":"66000210002.0",
    "gn:asciiname":"Fengliyuan",
    "gn:country_code":"TW",
    "gn:dem":223,
    "gn:feature_class":"P",
    "gn:feature_code":"PPL",
    "gn:name":"Fengliyuan",
    "gn:population":0,
    "gn:timezone":"Asia/Taipei",
    "iso:country":"TW",
    "name:und_x_variant":[
        "Fongliyuan",
        "Fengliyuan"
    ],
    "name:zho_x_preferred":[
        "\u9cf3\u68a8\u5712"
    ],
    "name:zho_x_variant":[
        "Feng-li-y\u00fcan"
    ],
    "wof:name":"Fengliyuan",
    "wof:placetype":"locality"
},
  "geometry": {"coordinates":[120.67972,24.32333],"type":"Point"}
}