{
  "type": "Feature",
  "properties": {
    "gn:admin1_code":"04",
    "gn:admin2_code":"TNN",
    "gn:admin3_code":"R09",
    "gn:admin4_code":"67000090012.0",
    "gn:asciiname":"Daqiuyuan",
    "gn:country_code":"TW",
    "gn:dem":78,
    "gn:feature_class":"P",
    "gn:feature_code":"PPL",
    "gn:name":"Daqiuyuan",
    "gn:population":0,
    "gn:timezone":"Asia/Taipei",
    "iso:country":"TW",
    "name:und_x_variant":[
        "Daciouyuan",
        "Daqiuyuan"
    ],
    "name:zho_x_preferred":[
        "Ta-ch\u2019iu-ts\u2019un"
    ],
    "name:zho_x_variant":[
        "\u5927\u4e18\u5712",
        "Ta-ch\u2019iu",
        "Ta-ch\u2019iu-y\u00fcan",
        "Ta-ch\u2019iu-yuan"
    ],
    "wof:name":"Daqiuyuan",
    "wof:placetype":"locality"
},
  "geometry": {"coordinates":[120.4379,23.2201],"type":"Point"}
}