{
  "type": "Feature",
  "properties": {
    "gn:admin1_code":"04",
    "gn:admin2_code":"TNN",
    "gn:admin3_code":"R06",
    "gn:admin4_code":"67000060004.0",
    "gn:asciiname":"Muzha",
    "gn:country_code":"TW",
    "gn:dem":28,
    "gn:feature_class":"P",
    "gn:feature_code":"PPL",
    "gn:name":"Muzha",
    "gn:population":0,
    "gn:timezone":"Asia/Taipei",
    "iso:country":"TW",
    "name:und_x_variant":[
        "Mujha",
        "Mu-cha"
    ],
    "name:zho_x_preferred":[
        "\u6728\u67f5"
    ],
    "wof:name":"Muzha",
    "wof:placetype":"locality"
},
  "geometry": {"coordinates":[120.38943999999999,23.31917],"type":"Point"}
}