{
  "type": "Feature",
  "properties": {
    "gn:admin1_code":"04",
    "gn:admin2_code":"TPE",
    "gn:admin3_code":"A14",
    "gn:admin4_code":"63000100025.0",
    "gn:asciiname":"Neigou",
    "gn:country_code":"TW",
    "gn:dem":26,
    "gn:feature_class":"P",
    "gn:feature_code":"PPL",
    "gn:name":"Neigou",
    "gn:population":0,
    "gn:timezone":"Asia/Taipei",
    "iso:country":"TW",
    "name:und_x_variant":[
        "Nei-kou"
    ],
    "name:zho_x_preferred":[
        "\u5167\u6e9d"
    ],
    "wof:name":"Neigou",
    "wof:placetype":"locality"
},
  "geometry": {"coordinates":[121.62554,25.08653],"type":"Point"}
}