{
  "type": "Feature",
  "properties": {
    "gn:admin1_code":"4.0",
    "gn:admin2_code":"MIA",
    "gn:admin3_code":"K16",
    "gn:admin4_code":"10005070011.0",
    "gn:asciiname":"Xiazhongxin",
    "gn:country_code":"TW",
    "gn:dem":343,
    "gn:feature_class":"P",
    "gn:feature_code":"PPL",
    "gn:name":"Xiazhongxin",
    "gn:population":0,
    "gn:timezone":"Asia/Taipei",
    "iso:country":"TW",
    "name:und_x_variant":[
        "Siajhongsin",
        "Xiazhongxin",
        "Hsia-chung-hsin"
    ],
    "name:zho_x_preferred":[
        "\u4e0b\u4e2d\u5fc3"
    ],
    "wof:name":"Xiazhongxin",
    "wof:placetype":"locality"
},
  "geometry": {"coordinates":[120.84197,24.34482],"type":"Point"}
}