{
  "type": "Feature",
  "properties": {
    "gn:admin1_code":"4.0",
    "gn:admin2_code":"TTT",
    "gn:admin3_code":"V13",
    "gn:admin4_code":"10014120004.0",
    "gn:asciiname":"Chulai",
    "gn:country_code":"TW",
    "gn:dem":353,
    "gn:feature_class":"P",
    "gn:feature_code":"PPL",
    "gn:name":"Chulai",
    "gn:population":0,
    "gn:timezone":"Asia/Taipei",
    "iso:country":"TW",
    "name:zho_x_preferred":[
        "Ch\u2019u-lai-she"
    ],
    "name:zho_x_variant":[
        "\u521d\u4f86",
        "Ch\u2019u-lai"
    ],
    "wof:name":"Chulai",
    "wof:placetype":"locality"
},
  "geometry": {"coordinates":[121.16777999999999,23.1175],"type":"Point"}
}