{
  "type": "Feature",
  "properties": {
    "gn:admin1_code":"04",
    "gn:admin2_code":"TPE",
    "gn:admin3_code":"A13",
    "gn:admin4_code":"63000090017.0",
    "gn:asciiname":"Nangangzi",
    "gn:country_code":"TW",
    "gn:dem":14,
    "gn:feature_class":"P",
    "gn:feature_code":"PPL",
    "gn:name":"Nangangzi",
    "gn:population":0,
    "gn:timezone":"Asia/Taipei",
    "iso:country":"TW",
    "name:und_x_variant":[
        "Nan-chiang-tzu",
        "Nangangzi",
        "Nangangzih",
        "Nan-kang-tzu"
    ],
    "name:zho_x_preferred":[
        "\u5357\u6e2f\u5b50"
    ],
    "wof:name":"Nangangzi",
    "wof:placetype":"locality"
},
  "geometry": {"coordinates":[121.61602000000001,25.04472],"type":"Point"}
}