{
  "type": "Feature",
  "properties": {
    "gn:admin1_code":"02",
    "gn:admin2_code":"KHH",
    "gn:admin3_code":"E22",
    "gn:admin4_code":"64000220003.0",
    "gn:asciiname":"Daqiding",
    "gn:country_code":"TW",
    "gn:dem":66,
    "gn:feature_class":"P",
    "gn:feature_code":"PPL",
    "gn:name":"Daqiding",
    "gn:population":0,
    "gn:timezone":"Asia/Taipei",
    "iso:country":"TW",
    "name:und_x_variant":[
        "Daciding",
        "Daqiding"
    ],
    "name:zho_x_preferred":[
        "\u5927\u5d0e\u9802"
    ],
    "name:zho_x_variant":[
        "Ta-ch\u2019i-t\u2019ou",
        "Ta-ch\u2019i-ting"
    ],
    "wof:name":"Daqiding",
    "wof:placetype":"locality"
},
  "geometry": {"coordinates":[120.39167,22.85028],"type":"Point"}
}