{
  "type": "Feature",
  "properties": {
    "gn:admin1_code":"2.0",
    "gn:admin2_code":"KHH",
    "gn:admin3_code":"E34",
    "gn:admin4_code":"64000340002.0",
    "gn:asciiname":"Tianziding",
    "gn:country_code":"TW",
    "gn:dem":517,
    "gn:feature_class":"P",
    "gn:feature_code":"PPL",
    "gn:name":"Tianziding",
    "gn:population":0,
    "gn:timezone":"Asia/Taipei",
    "iso:country":"TW",
    "name:und_x_variant":[
        "Tianzihding"
    ],
    "name:zho_x_preferred":[
        "\u7530\u4ed4\u9802"
    ],
    "name:zho_x_variant":[
        "T\u2019ien-tzu-ting"
    ],
    "wof:name":"Tianziding",
    "wof:placetype":"locality"
},
  "geometry": {"coordinates":[120.51443999999999,23.03194],"type":"Point"}
}