{
  "type": "Feature",
  "properties": {
    "gn:admin1_code":"04",
    "gn:admin2_code":"TXG",
    "gn:admin3_code":"B24",
    "gn:admin4_code":"66000240004.0",
    "gn:asciiname":"Duchuantou",
    "gn:country_code":"TW",
    "gn:dem":26,
    "gn:feature_class":"P",
    "gn:feature_code":"PPL",
    "gn:name":"Duchuantou",
    "gn:population":0,
    "gn:timezone":"Asia/Taipei",
    "iso:country":"TW",
    "name:und_x_variant":[
        "Tu-ch\u2019uan-t\u2019ou",
        "\u6e21\u8239\u982d",
        "Duchuantou"
    ],
    "name:zho_x_preferred":[
        "Tu-ch\u2019uan-t\u2019ou"
    ],
    "wof:name":"Duchuantou",
    "wof:placetype":"locality"
},
  "geometry": {"coordinates":[120.55249999999999,24.12028],"type":"Point"}
}