{
  "type": "Feature",
  "properties": {
    "gn:admin1_code":"04",
    "gn:admin2_code":"TNN",
    "gn:admin3_code":"R25",
    "gn:admin4_code":"67000250007.0",
    "gn:asciiname":"Nanliao",
    "gn:country_code":"TW",
    "gn:dem":94,
    "gn:feature_class":"P",
    "gn:feature_code":"PPL",
    "gn:name":"Nanliao",
    "gn:population":0,
    "gn:timezone":"Asia/Taipei",
    "iso:country":"TW",
    "name:und_x_variant":[
        "Nan-liao"
    ],
    "name:zho_x_preferred":[
        "\u5357\u5bee"
    ],
    "wof:name":"Nanliao",
    "wof:placetype":"locality"
},
  "geometry": {"coordinates":[120.49047,23.07343],"type":"Point"}
}