{
  "type": "Feature",
  "properties": {
    "gn:admin1_code":"03",
    "gn:admin2_code":"TPQ",
    "gn:admin3_code":"F09",
    "gn:admin4_code":"65000180007.0",
    "gn:asciiname":"Kengwaigu",
    "gn:country_code":"TW",
    "gn:dem":54,
    "gn:feature_class":"P",
    "gn:feature_code":"PPL",
    "gn:name":"Kengwaigu",
    "gn:population":0,
    "gn:timezone":"Asia/Taipei",
    "iso:country":"TW",
    "name:zho_x_preferred":[
        "\u5751\u5916\u80a1"
    ],
    "name:zho_x_variant":[
        "Ta-k\u2019eng-wai-ku",
        "K\u2019eng-wai-ku"
    ],
    "wof:name":"Kengwaigu",
    "wof:placetype":"locality"
},
  "geometry": {"coordinates":[121.60202,25.00814],"type":"Point"}
}