{
  "type": "Feature",
  "properties": {
    "gn:admin1_code":"2.0",
    "gn:admin2_code":"KHH",
    "gn:admin3_code":"E31",
    "gn:admin4_code":"64000310011.0",
    "gn:asciiname":"Niujiaowan",
    "gn:country_code":"TW",
    "gn:dem":53,
    "gn:feature_class":"P",
    "gn:feature_code":"PPL",
    "gn:name":"Niujiaowan",
    "gn:population":0,
    "gn:timezone":"Asia/Taipei",
    "iso:country":"TW",
    "name:und_x_variant":[
        "Nioujiaowan",
        "Niujiaowan",
        "Niu-chiao-wan"
    ],
    "name:zho_x_preferred":[
        "\u725b\u89d2\u7063"
    ],
    "wof:name":"Niujiaowan",
    "wof:placetype":"locality"
},
  "geometry": {"coordinates":[120.53545,22.90911],"type":"Point"}
}