{
  "type": "Feature",
  "properties": {
    "gn:admin1_code":"4.0",
    "gn:admin2_code":"YUN",
    "gn:admin3_code":"P04",
    "gn:admin4_code":"10009040023.0",
    "gn:asciiname":"Xiananzi",
    "gn:country_code":"TW",
    "gn:dem":27,
    "gn:feature_class":"P",
    "gn:feature_code":"PPL",
    "gn:name":"Xiananzi",
    "gn:population":0,
    "gn:timezone":"Asia/Taipei",
    "iso:country":"TW",
    "name:und_x_variant":[
        "Siananzih",
        "Hsia-nan",
        "Hsia-nan-tzu"
    ],
    "name:zho_x_preferred":[
        "\u4e0b\u6e73\u4ed4"
    ],
    "wof:name":"Xiananzi",
    "wof:placetype":"locality"
},
  "geometry": {"coordinates":[120.43411999999999,23.76263],"type":"Point"}
}