{
  "type": "Feature",
  "properties": {
    "gn:admin1_code":"2.0",
    "gn:admin2_code":"KHH",
    "gn:admin3_code":"E32",
    "gn:admin4_code":"64000320005.0",
    "gn:asciiname":"Xiazhilai",
    "gn:country_code":"TW",
    "gn:dem":485,
    "gn:feature_class":"P",
    "gn:feature_code":"PPL",
    "gn:name":"Xiazhilai",
    "gn:population":0,
    "gn:timezone":"Asia/Taipei",
    "iso:country":"TW",
    "name:und_x_variant":[
        "Siajhihlai",
        "Xiazhilai",
        "Hsia-chih-lai"
    ],
    "name:zho_x_preferred":[
        "\u4e0b\u76f4\u7028"
    ],
    "wof:name":"Xiazhilai",
    "wof:placetype":"locality"
},
  "geometry": {"coordinates":[120.65028,23.07222],"type":"Point"}
}