{
  "type": "Feature",
  "properties": {
    "gn:admin1_code":"04",
    "gn:admin2_code":"YUN",
    "gn:admin3_code":"P11",
    "gn:admin4_code":"10009110014.0",
    "gn:asciiname":"Dazhuang",
    "gn:country_code":"TW",
    "gn:dem":19,
    "gn:feature_class":"P",
    "gn:feature_code":"PPL",
    "gn:name":"Dazhuang",
    "gn:population":0,
    "gn:timezone":"Asia/Taipei",
    "iso:country":"TW",
    "name:und_x_variant":[
        "Dajhuang",
        "Dazhuang",
        "Ta-chuang"
    ],
    "name:zho_x_preferred":[
        "\u5927\u838a"
    ],
    "wof:name":"Dazhuang",
    "wof:placetype":"locality"
},
  "geometry": {"coordinates":[120.37627999999999,23.80471],"type":"Point"}
}