{
  "type": "Feature",
  "properties": {
    "gn:admin1_code":"4.0",
    "gn:admin2_code":"TXG",
    "gn:admin3_code":"B19",
    "gn:admin4_code":"66000190009.0",
    "gn:asciiname":"Shuihankeng",
    "gn:country_code":"TW",
    "gn:dem":514,
    "gn:feature_class":"P",
    "gn:feature_code":"PPL",
    "gn:name":"Shuihankeng",
    "gn:population":0,
    "gn:timezone":"Asia/Taipei",
    "iso:country":"TW",
    "name:und_x_variant":[
        "Shueihankeng"
    ],
    "name:zho_x_preferred":[
        "\u6c34\u6db5\u5751"
    ],
    "name:zho_x_variant":[
        "Shui-han-k\u2019eng"
    ],
    "wof:name":"Shuihankeng",
    "wof:placetype":"locality"
},
  "geometry": {"coordinates":[120.81932,24.16564],"type":"Point"}
}