{
  "type": "Feature",
  "properties": {
    "gn:admin1_code":"4.0",
    "gn:admin2_code":"YUN",
    "gn:admin3_code":"P20",
    "gn:admin4_code":"10009200021.0",
    "gn:asciiname":"Qiongbu",
    "gn:country_code":"TW",
    "gn:dem":5,
    "gn:feature_class":"P",
    "gn:feature_code":"PPL",
    "gn:name":"Qiongbu",
    "gn:population":0,
    "gn:timezone":"Asia/Taipei",
    "iso:country":"TW",
    "name:und_x_variant":[
        "Ting-chiu-tzu-pu",
        "Qiongbu",
        "Cyongbu"
    ],
    "name:zho_x_preferred":[
        "\u74ca\u57d4"
    ],
    "name:zho_x_variant":[
        "Ch\u2019iung-pu"
    ],
    "wof:name":"Qiongbu",
    "wof:placetype":"locality"
},
  "geometry": {"coordinates":[120.20944,23.51472],"type":"Point"}
}