{
  "type": "Feature",
  "properties": {
    "gn:admin1_code":"4.0",
    "gn:admin2_code":"TNN",
    "gn:admin3_code":"R15",
    "gn:admin4_code":"67000160003.0",
    "gn:asciiname":"Xihe",
    "gn:country_code":"TW",
    "gn:dem":7,
    "gn:feature_class":"P",
    "gn:feature_code":"PPL",
    "gn:name":"Xihe",
    "gn:population":0,
    "gn:timezone":"Asia/Taipei",
    "iso:country":"TW",
    "name:ceb_x_preferred":[
        "Xihe"
    ],
    "name:deu_x_preferred":[
        "Xihe"
    ],
    "name:fra_x_preferred":[
        "Xihe"
    ],
    "name:nor_x_preferred":[
        "Xihe"
    ],
    "name:swe_x_preferred":[
        "Xihe"
    ],
    "name:und_x_variant":[
        "Hsi-chia",
        "Sihe",
        "Hsi-ho"
    ],
    "name:zho_x_preferred":[
        "\u897f\u548c"
    ],
    "name:zho_x_variant":[
        "Hsi-ho-ts\u2019un"
    ],
    "wof:name":"Xihe",
    "wof:placetype":"locality"
},
  "geometry": {"coordinates":[120.15278000000001,23.19639],"type":"Point"}
}