{
  "type": "Feature",
  "properties": {
    "gn:admin1_code":"4.0",
    "gn:admin2_code":"CHA",
    "gn:admin3_code":"N10",
    "gn:admin4_code":"10007050006.0",
    "gn:asciiname":"Dinglin",
    "gn:country_code":"TW",
    "gn:dem":6,
    "gn:feature_class":"P",
    "gn:feature_code":"PPL",
    "gn:name":"Dinglin",
    "gn:population":0,
    "gn:timezone":"Asia/Taipei",
    "iso:country":"TW",
    "name:und_x_variant":[
        "Ting-lin"
    ],
    "name:zho_x_preferred":[
        "\u9802\u6797"
    ],
    "wof:name":"Dinglin",
    "wof:placetype":"locality"
},
  "geometry": {"coordinates":[120.47722,24.14972],"type":"Point"}
}