{
  "type": "Feature",
  "properties": {
    "gn:admin1_code":"4.0",
    "gn:admin2_code":"PIF",
    "gn:admin3_code":"T11",
    "gn:admin4_code":"10013110011.0",
    "gn:asciiname":"Yixingzhuang",
    "gn:country_code":"TW",
    "gn:dem":132,
    "gn:feature_class":"P",
    "gn:feature_code":"PPL",
    "gn:name":"Yixingzhuang",
    "gn:population":0,
    "gn:timezone":"Asia/Taipei",
    "iso:country":"TW",
    "name:und_x_variant":[
        "Yisingjhuang",
        "I-hsing-chuang"
    ],
    "name:zho_x_preferred":[
        "\u7fa9\u8208\u838a"
    ],
    "wof:name":"Yixingzhuang",
    "wof:placetype":"locality"
},
  "geometry": {"coordinates":[120.64024999999999,22.86703],"type":"Point"}
}