{
  "type": "Feature",
  "properties": {
    "gn:admin1_code":"4.0",
    "gn:admin2_code":"PEN",
    "gn:admin3_code":"X01",
    "gn:admin4_code":"10016010024.0",
    "gn:asciiname":"Xiaogua",
    "gn:country_code":"TW",
    "gn:dem":11,
    "gn:feature_class":"P",
    "gn:feature_code":"PPL",
    "gn:name":"Xiaogua",
    "gn:population":0,
    "gn:timezone":"Asia/Taipei",
    "iso:country":"TW",
    "name:und_x_variant":[
        "Siaogua",
        "Hsiao-kua"
    ],
    "name:zho_x_preferred":[
        "\u856d\u74dc"
    ],
    "wof:name":"Xiaogua",
    "wof:placetype":"locality"
},
  "geometry": {"coordinates":[119.63256,23.54856],"type":"Point"}
}