{
  "type": "Feature",
  "properties": {
    "gn:admin1_code":"4.0",
    "gn:admin2_code":"CYI",
    "gn:admin3_code":"I01",
    "gn:admin4_code":"10020010001.0",
    "gn:asciiname":"Houcuo",
    "gn:country_code":"TW",
    "gn:dem":32,
    "gn:feature_class":"P",
    "gn:feature_code":"PPL",
    "gn:name":"Houcuo",
    "gn:population":0,
    "gn:timezone":"Asia/Taipei",
    "iso:country":"TW",
    "name:zho_x_preferred":[
        "\u5f8c\u539d"
    ],
    "name:zho_x_variant":[
        "Hou-ts\u2019o"
    ],
    "wof:name":"Houcuo",
    "wof:placetype":"locality"
},
  "geometry": {"coordinates":[120.43997,23.50917],"type":"Point"}
}