{
  "type": "Feature",
  "properties": {
    "gn:admin1_code":"4.0",
    "gn:admin2_code":"TNN",
    "gn:admin3_code":"R06",
    "gn:admin4_code":"67000060015.0",
    "gn:asciiname":"Shuijing",
    "gn:country_code":"TW",
    "gn:dem":154,
    "gn:feature_class":"P",
    "gn:feature_code":"PPL",
    "gn:name":"Shuijing",
    "gn:population":0,
    "gn:timezone":"Asia/Taipei",
    "iso:country":"TW",
    "name:und_x_variant":[
        "Shueijing",
        "Shuijing",
        "Shui-ching"
    ],
    "name:zho_x_preferred":[
        "\u6c34\u4e95"
    ],
    "wof:name":"Shuijing",
    "wof:placetype":"locality"
},
  "geometry": {"coordinates":[120.47083000000001,23.28583],"type":"Point"}
}