{
  "type": "Feature",
  "properties": {
    "gn:admin1_code":"4.0",
    "gn:admin2_code":"TTT",
    "gn:admin3_code":"V10",
    "gn:admin4_code":"10014060010.0",
    "gn:asciiname":"Dashuihu",
    "gn:country_code":"TW",
    "gn:dem":275,
    "gn:feature_class":"P",
    "gn:feature_code":"PPL",
    "gn:name":"Dashuihu",
    "gn:population":0,
    "gn:timezone":"Asia/Taipei",
    "iso:country":"TW",
    "name:und_x_variant":[
        "Dashueihu",
        "Dashuihu",
        "Ta-shui-hu"
    ],
    "name:zho_x_preferred":[
        "\u5927\u6c34\u6e56"
    ],
    "wof:name":"Dashuihu",
    "wof:placetype":"locality"
},
  "geometry": {"coordinates":[121.19083000000001,23.0425],"type":"Point"}
}