{
  "type": "Feature",
  "properties": {
    "gn:admin1_code":"4.0",
    "gn:admin2_code":"CHA",
    "gn:admin3_code":"N02",
    "gn:admin4_code":"10007020026.0",
    "gn:asciiname":"Nanqiao",
    "gn:country_code":"TW",
    "gn:dem":9,
    "gn:feature_class":"P",
    "gn:feature_code":"PPL",
    "gn:name":"Nanqiao",
    "gn:population":0,
    "gn:timezone":"Asia/Taipei",
    "iso:country":"TW",
    "name:und_x_variant":[
        "Nanciao"
    ],
    "name:zho_x_preferred":[
        "\u5357\u6a4b"
    ],
    "name:zho_x_variant":[
        "Nan-ch\u2019iao"
    ],
    "wof:name":"Nanqiao",
    "wof:placetype":"locality"
},
  "geometry": {"coordinates":[120.44389,24.07],"type":"Point"}
}