{
  "type": "Feature",
  "properties": {
    "iso:country":"TW",
    "name:eng_x_preferred":[
        "Dajie"
    ],
    "name:eng_x_variant":[
        "Dajie Village"
    ],
    "name:zho_tw_x_preferred":[
        "\u5927\u8857\u91cc"
    ],
    "qs:name":"\u5927\u8857\u91cc",
    "qs:name_adm0":"\u81fa\u7063",
    "qs:name_adm1":"\u5609\u7fa9\u5e02",
    "qs:photos":14,
    "qs:photos_1k":3,
    "qs:photos_9k":1,
    "qs:photos_9r":1,
    "qs:photos_all":14,
    "qs:photos_sr":1,
    "qs:placetype":"Suburb",
    "qs:pop_sr":"0",
    "wof:name":"Dajie",
    "wof:placetype":"neighbourhood"
},
  "geometry": {"coordinates":[120.4532,23.479926],"type":"Point"}
}