{
  "type": "Feature",
  "properties": {
    "iso:country":"TW",
    "qs:name":"\u5927\u8857\u91cc",
    "qs:name_adm0":"\u81fa\u7063",
    "qs:name_adm1":"\u5609\u7fa9\u5e02",
    "qs:photos":14,
    "qs:photos_1k":3,
    "qs:photos_9k":1,
    "qs:photos_9r":1,
    "qs:photos_all":14,
    "qs:photos_sr":1,
    "qs:placetype":"Suburb",
    "qs:pop_sr":"0",
    "wof:name":"\u5927\u8857\u91cc",
    "wof:placetype":"neighbourhood"
},
  "geometry": {"coordinates":[120.45320049999999,23.4799255],"type":"Point"}
}