{
  "type": "Feature",
  "properties": {
    "gn:admin1_code":"4.0",
    "gn:admin2_code":"TNN",
    "gn:admin3_code":"R26",
    "gn:admin4_code":"67000260007.0",
    "gn:asciiname":"Erkengzi",
    "gn:country_code":"TW",
    "gn:dem":94,
    "gn:feature_class":"P",
    "gn:feature_code":"PPL",
    "gn:name":"Erkengzi",
    "gn:population":0,
    "gn:timezone":"Asia/Taipei",
    "iso:country":"TW",
    "name:und_x_variant":[
        "Erkengzih",
        "Erkengzi"
    ],
    "name:zho_x_preferred":[
        "\u4e8c\u5751\u4ed4"
    ],
    "name:zho_x_variant":[
        "Erh-k\u2019eng-tzu"
    ],
    "wof:name":"Erkengzi",
    "wof:placetype":"locality"
},
  "geometry": {"coordinates":[120.37916,23.0443],"type":"Point"}
}