{
  "type": "Feature",
  "properties": {
    "gn:admin1_code":"4.0",
    "gn:admin2_code":"TTT",
    "gn:admin3_code":"V01",
    "gn:admin4_code":"10014010003.0",
    "gn:asciiname":"Yanwan",
    "gn:country_code":"TW",
    "gn:dem":59,
    "gn:feature_class":"P",
    "gn:feature_code":"PPL",
    "gn:name":"Yanwan",
    "gn:population":0,
    "gn:timezone":"Asia/Taipei",
    "iso:country":"TW",
    "name:und_x_variant":[
        "Yung-ho",
        "Hsia-yen-wan",
        "Yen-wan"
    ],
    "name:zho_x_preferred":[
        "\u5ca9\u7063"
    ],
    "wof:name":"Yanwan",
    "wof:placetype":"locality"
},
  "geometry": {"coordinates":[121.12554,22.80693],"type":"Point"}
}