{
  "type": "Feature",
  "properties": {
    "gn:admin1_code":"04",
    "gn:admin2_code":"CYQ",
    "gn:admin3_code":"Q16",
    "gn:admin4_code":"10010150015.0",
    "gn:asciiname":"Daojiaoshan",
    "gn:country_code":"TW",
    "gn:dem":603,
    "gn:feature_class":"P",
    "gn:feature_code":"PPL",
    "gn:name":"Daojiaoshan",
    "gn:population":0,
    "gn:timezone":"Asia/Taipei",
    "iso:country":"TW",
    "name:und_x_variant":[
        "Tao-chiao-shan"
    ],
    "name:zho_x_preferred":[
        "\u5230\u4ea4\u5c71"
    ],
    "wof:name":"Daojiaoshan",
    "wof:placetype":"locality"
},
  "geometry": {"coordinates":[120.66611,23.57444],"type":"Point"}
}