{
  "type": "Feature",
  "properties": {
    "gn:admin1_code":"04",
    "gn:admin2_code":"NAN",
    "gn:admin3_code":"M04",
    "gn:admin4_code":"10008040016.0",
    "gn:asciiname":"Bafenzi",
    "gn:country_code":"TW",
    "gn:dem":202,
    "gn:feature_class":"P",
    "gn:feature_code":"PPL",
    "gn:name":"Bafenzi",
    "gn:population":0,
    "gn:timezone":"Asia/Taipei",
    "iso:country":"TW",
    "name:und_x_variant":[
        "Bafenzih",
        "Pa-fen-tzu"
    ],
    "name:zho_x_preferred":[
        "\u516b\u5206\u5b50"
    ],
    "wof:name":"Bafenzi",
    "wof:placetype":"locality"
},
  "geometry": {"coordinates":[120.72436999999999,23.80562],"type":"Point"}
}