{
  "type": "Feature",
  "properties": {
    "gn:admin1_code":"3.0",
    "gn:admin2_code":"TPQ",
    "gn:admin3_code":"F27",
    "gn:admin4_code":"65000100001.0",
    "gn:asciiname":"Zhonghe",
    "gn:country_code":"TW",
    "gn:dem":101,
    "gn:feature_class":"P",
    "gn:feature_code":"PPL",
    "gn:name":"Zhonghe",
    "gn:population":0,
    "gn:timezone":"Asia/Taipei",
    "iso:country":"TW",
    "name:und_x_variant":[
        "Jhonghe",
        "Chung-ho"
    ],
    "name:zho_x_preferred":[
        "\u4e2d\u548c"
    ],
    "wof:name":"Zhonghe",
    "wof:placetype":"locality"
},
  "geometry": {"coordinates":[121.48622,25.23036],"type":"Point"}
}