{
  "type": "Feature",
  "properties": {
    "gn:admin1_code":"4.0",
    "gn:admin2_code":"TPE",
    "gn:admin3_code":"A14",
    "gn:admin4_code":"63000100030.0",
    "gn:asciiname":"Gangqian",
    "gn:country_code":"TW",
    "gn:dem":5,
    "gn:feature_class":"P",
    "gn:feature_code":"PPL",
    "gn:name":"Gangqian",
    "gn:population":0,
    "gn:timezone":"Asia/Taipei",
    "iso:country":"TW",
    "name:und_x_variant":[
        "Gangcian",
        "Gangqian"
    ],
    "name:zho_x_preferred":[
        "Chaing-ch\u2019ien"
    ],
    "name:zho_x_variant":[
        "Chiang-ch\u2019ien-ts\u2019un",
        "Kang-ch\u2019ien-ts\u2019un",
        "Chiang-ch\u2019ien",
        "\u6e2f\u5898",
        "Kang-ch\u2019ien"
    ],
    "wof:name":"Gangqian",
    "wof:placetype":"locality"
},
  "geometry": {"coordinates":[121.57391,25.07169],"type":"Point"}
}