{
  "type": "Feature",
  "properties": {
    "gn:admin1_code":"4.0",
    "gn:admin2_code":"HUA",
    "gn:admin3_code":"U09",
    "gn:admin4_code":"10015090008.0",
    "gn:asciiname":"Jiangjunmao",
    "gn:country_code":"TW",
    "gn:dem":77,
    "gn:feature_class":"P",
    "gn:feature_code":"PPL",
    "gn:name":"Jiangjunmao",
    "gn:population":0,
    "gn:timezone":"Asia/Taipei",
    "iso:country":"TW",
    "name:und_x_variant":[
        "Jiangjyunmao"
    ],
    "name:zho_x_preferred":[
        "\u5c07\u8ecd\u5e3d"
    ],
    "name:zho_x_variant":[
        "Chiang-ch\u00fcn-mao"
    ],
    "wof:name":"Jiangjunmao",
    "wof:placetype":"locality"
},
  "geometry": {"coordinates":[121.43558,23.5006],"type":"Point"}
}