{
  "type": "Feature",
  "properties": {
    "gn:admin1_code":"4.0",
    "gn:admin2_code":"HUA",
    "gn:admin3_code":"U05",
    "gn:admin4_code":"10015050014.0",
    "gn:asciiname":"Huaren",
    "gn:country_code":"TW",
    "gn:dem":26,
    "gn:feature_class":"P",
    "gn:feature_code":"PPL",
    "gn:name":"Huaren",
    "gn:population":0,
    "gn:timezone":"Asia/Taipei",
    "iso:country":"TW",
    "name:und_x_variant":[
        "Li-lou",
        "Ch\u2019uan-chin",
        "Jen-hua",
        "Hua-jen",
        "Huaren"
    ],
    "wof:name":"Huaren",
    "wof:placetype":"locality"
},
  "geometry": {"coordinates":[121.58333,23.96667],"type":"Point"}
}