{
  "type": "Feature",
  "properties": {
    "gn:admin1_code":"4.0",
    "gn:admin2_code":"TNN",
    "gn:admin3_code":"R03",
    "gn:admin4_code":"67000030021.0",
    "gn:asciiname":"Xizhou",
    "gn:country_code":"TW",
    "gn:dem":44,
    "gn:feature_class":"P",
    "gn:feature_code":"PPL",
    "gn:name":"Xizhou",
    "gn:population":0,
    "gn:timezone":"Asia/Taipei",
    "iso:country":"TW",
    "name:und_x_variant":[
        "Sijhou",
        "Hsi-chou"
    ],
    "name:zho_x_preferred":[
        "Ch\u2019i-chou"
    ],
    "name:zho_x_variant":[
        "\u6eaa\u6d32"
    ],
    "wof:name":"Xizhou",
    "wof:placetype":"locality"
},
  "geometry": {"coordinates":[120.4425,23.35889],"type":"Point"}
}