{
  "type": "Feature",
  "properties": {
    "gn:admin1_code":"4.0",
    "gn:admin2_code":"ILA",
    "gn:admin3_code":"G07",
    "gn:admin4_code":"10002090002.0",
    "gn:asciiname":"Erjie",
    "gn:country_code":"TW",
    "gn:dem":10,
    "gn:feature_class":"P",
    "gn:feature_code":"PPL",
    "gn:name":"Erjie",
    "gn:population":0,
    "gn:timezone":"Asia/Taipei",
    "iso:country":"TW",
    "name:und_x_variant":[
        "Erh-chieh"
    ],
    "name:zho_x_preferred":[
        "\u4e8c\u7d50"
    ],
    "wof:name":"Erjie",
    "wof:placetype":"locality"
},
  "geometry": {"coordinates":[121.76939,24.70537],"type":"Point"}
}