{
  "type": "Feature",
  "properties": {
    "gn:admin1_code":"4.0",
    "gn:admin2_code":"TAO",
    "gn:admin3_code":"H04",
    "gn:admin4_code":"68000040021.0",
    "gn:asciiname":"Xiayinyingwo",
    "gn:country_code":"TW",
    "gn:dem":78,
    "gn:feature_class":"P",
    "gn:feature_code":"PPL",
    "gn:name":"Xiayinyingwo",
    "gn:population":0,
    "gn:timezone":"Asia/Taipei",
    "iso:country":"TW",
    "name:und_x_variant":[
        "Feng-yeh",
        "Xiayinyingwo",
        "Siayinyingwo",
        "Hsia-yin-ying-wo"
    ],
    "name:zho_x_preferred":[
        "\u4e0b\u9670\u5f71\u7aa9"
    ],
    "wof:name":"Xiayinyingwo",
    "wof:placetype":"locality"
},
  "geometry": {"coordinates":[121.08444,24.94778],"type":"Point"}
}