{
  "type": "Feature",
  "properties": {
    "gn:admin1_code":"4.0",
    "gn:admin2_code":"CYQ",
    "gn:admin3_code":"Q20",
    "gn:admin4_code":"10010180004.0",
    "gn:asciiname":"Yimuzhishe",
    "gn:country_code":"TW",
    "gn:dem":1111,
    "gn:feature_class":"P",
    "gn:feature_code":"PPL",
    "gn:name":"Yimuzhishe",
    "gn:population":0,
    "gn:timezone":"Asia/Taipei",
    "iso:country":"TW",
    "name:und_x_variant":[
        "I-mu-chih-she"
    ],
    "wof:name":"Yimuzhishe",
    "wof:placetype":"locality"
},
  "geometry": {"coordinates":[120.73333,23.51667],"type":"Point"}
}