{
  "type": "Feature",
  "properties": {
    "gn:admin1_code":"03",
    "gn:admin2_code":"TPQ",
    "gn:admin3_code":"F07",
    "gn:admin4_code":"65000060014.0",
    "gn:asciiname":"Shisifen",
    "gn:country_code":"TW",
    "gn:dem":21,
    "gn:feature_class":"P",
    "gn:feature_code":"PPL",
    "gn:name":"Shisifen",
    "gn:population":0,
    "gn:timezone":"Asia/Taipei",
    "iso:country":"TW",
    "name:und_x_variant":[
        "Shih-ssu-fen-lu",
        "Shihsihfen",
        "Shih-ssu-fen"
    ],
    "name:zho_x_preferred":[
        "\u5341\u56db\u4efd"
    ],
    "wof:name":"Shisifen",
    "wof:placetype":"locality"
},
  "geometry": {"coordinates":[121.51831,24.97021],"type":"Point"}
}