{
  "type": "Feature",
  "properties": {
    "gn:admin1_code":"04",
    "gn:admin2_code":"TNN",
    "gn:admin3_code":"R09",
    "gn:admin4_code":"67000090012.0",
    "gn:asciiname":"Beishikeng",
    "gn:country_code":"TW",
    "gn:dem":77,
    "gn:feature_class":"P",
    "gn:feature_code":"PPL",
    "gn:name":"Beishikeng",
    "gn:population":0,
    "gn:timezone":"Asia/Taipei",
    "iso:country":"TW",
    "name:und_x_variant":[
        "Beishihkeng",
        "Beishikeng"
    ],
    "name:zho_x_preferred":[
        "\u5317\u52e2\u5751"
    ],
    "name:zho_x_variant":[
        "Pei-shih-k\u2019eng"
    ],
    "wof:name":"Beishikeng",
    "wof:placetype":"locality"
},
  "geometry": {"coordinates":[120.42737,23.23164],"type":"Point"}
}