{
  "type": "Feature",
  "properties": {
    "gn:admin1_code":"4.0",
    "gn:admin2_code":"HUA",
    "gn:admin3_code":"U13",
    "gn:admin4_code":"10015130005.0",
    "gn:asciiname":"Qingshui",
    "gn:country_code":"TW",
    "gn:dem":225,
    "gn:feature_class":"P",
    "gn:feature_code":"PPL",
    "gn:name":"Qingshui",
    "gn:population":0,
    "gn:timezone":"Asia/Taipei",
    "iso:country":"TW",
    "name:ceb_x_preferred":[
        "Qingshui"
    ],
    "name:deu_x_preferred":[
        "Qingshui"
    ],
    "name:und_x_variant":[
        "Cingshuei"
    ],
    "name:zho_x_preferred":[
        "Ch\u2019ing-shui"
    ],
    "name:zho_x_variant":[
        "Cho-ch\u2019ing-ts\u2019un-pa-lin",
        "\u6e05\u6c34"
    ],
    "wof:name":"Qingshui",
    "wof:placetype":"locality"
},
  "geometry": {"coordinates":[121.26223,23.27441],"type":"Point"}
}