{
  "type": "Feature",
  "properties": {
    "gn:admin1_code":"4.0",
    "gn:admin2_code":"CYQ",
    "gn:admin3_code":"Q12",
    "gn:admin4_code":"10010010012.0",
    "gn:asciiname":"Changfuqiao",
    "gn:country_code":"TW",
    "gn:dem":19,
    "gn:feature_class":"P",
    "gn:feature_code":"PPL",
    "gn:name":"Changfuqiao",
    "gn:population":0,
    "gn:timezone":"Asia/Taipei",
    "iso:country":"TW",
    "name:und_x_variant":[
        "Ch\u2019ang-fu-ch\u2019iao"
    ],
    "wof:name":"Changfuqiao",
    "wof:placetype":"locality"
},
  "geometry": {"coordinates":[120.36667,23.46667],"type":"Point"}
}