{
  "type": "Feature",
  "properties": {
    "gn:admin1_code":"4.0",
    "gn:admin2_code":"TAO",
    "gn:admin3_code":"H10",
    "gn:admin4_code":"68000100032.0",
    "gn:asciiname":"Ailiaoding",
    "gn:country_code":"TW",
    "gn:dem":199,
    "gn:feature_class":"P",
    "gn:feature_code":"PPL",
    "gn:name":"Ailiaoding",
    "gn:population":0,
    "gn:timezone":"Asia/Taipei",
    "iso:country":"TW",
    "name:und_x_variant":[
        "Yai-liao-ting",
        "Ailiaoding",
        "Ai-liao-ting"
    ],
    "name:zho_x_preferred":[
        "\u9698\u5bee\u9802"
    ],
    "wof:name":"Ailiaoding",
    "wof:placetype":"locality"
},
  "geometry": {"coordinates":[121.22667,24.89722],"type":"Point"}
}