{
  "type": "Feature",
  "properties": {
    "gn:admin1_code":"4.0",
    "gn:admin2_code":"TAO",
    "gn:admin3_code":"H04",
    "gn:admin4_code":"68000040037.0",
    "gn:asciiname":"Xigaoshanding",
    "gn:country_code":"TW",
    "gn:dem":151,
    "gn:feature_class":"P",
    "gn:feature_code":"PPL",
    "gn:name":"Xigaoshanding",
    "gn:population":0,
    "gn:timezone":"Asia/Taipei",
    "iso:country":"TW",
    "name:und_x_variant":[
        "Kao-shan-ting",
        "Sigaoshanding",
        "Xigaoshanding",
        "Hsi-kao-shan-ting"
    ],
    "name:zho_x_preferred":[
        "\u897f\u9ad8\u5c71\u9802"
    ],
    "wof:name":"Xigaoshanding",
    "wof:placetype":"locality"
},
  "geometry": {"coordinates":[121.15694000000001,24.93778],"type":"Point"}
}