{
  "type": "Feature",
  "properties": {
    "gn:admin1_code":"4.0",
    "gn:admin2_code":"HUA",
    "gn:admin3_code":"U03",
    "gn:admin4_code":"10015030011.0",
    "gn:asciiname":"Chikeping",
    "gn:country_code":"TW",
    "gn:dem":844,
    "gn:feature_class":"P",
    "gn:feature_code":"PPL",
    "gn:name":"Chikeping",
    "gn:population":0,
    "gn:timezone":"Asia/Taipei",
    "iso:country":"TW",
    "name:und_x_variant":[
        "Chihkeping",
        "Chikeping"
    ],
    "name:zho_x_preferred":[
        "\u8d64\u79d1\u576a"
    ],
    "name:zho_x_variant":[
        "Ch\u2019ih-k\u2019o-p\u2019ing"
    ],
    "wof:name":"Chikeping",
    "wof:placetype":"locality"
},
  "geometry": {"coordinates":[121.39426,23.39739],"type":"Point"}
}