{
  "type": "Feature",
  "properties": {
    "gn:admin1_code":"1.0",
    "gn:admin2_code":"LIE",
    "gn:admin3_code":"Z01",
    "gn:admin4_code":"9007010002.0",
    "gn:asciiname":"Fuxingcun",
    "gn:country_code":"TW",
    "gn:dem":44,
    "gn:feature_class":"P",
    "gn:feature_code":"PPL",
    "gn:name":"Fuxingcun",
    "gn:population":0,
    "gn:timezone":"Asia/Taipei",
    "iso:country":"TW",
    "name:und_x_variant":[
        "Niu-chiao",
        "Fu-hsing-ts\u2019un",
        "Fuxingcun"
    ],
    "wof:name":"Fuxingcun",
    "wof:placetype":"locality"
},
  "geometry": {"coordinates":[119.95,26.16667],"type":"Point"}
}