{
  "type": "Feature",
  "properties": {
    "gn:admin1_code":"02",
    "gn:admin2_code":"KHH",
    "gn:admin3_code":"E22",
    "gn:admin4_code":"64000220005.0",
    "gn:asciiname":"Nanshihu",
    "gn:country_code":"TW",
    "gn:dem":115,
    "gn:feature_class":"P",
    "gn:feature_code":"PPL",
    "gn:name":"Nanshihu",
    "gn:population":0,
    "gn:timezone":"Asia/Taipei",
    "iso:country":"TW",
    "name:und_x_variant":[
        "Nanshihhu",
        "Nan-shih-hu"
    ],
    "name:zho_x_preferred":[
        "\u5357\u52e2\u6e56"
    ],
    "wof:name":"Nanshihu",
    "wof:placetype":"locality"
},
  "geometry": {"coordinates":[120.41388999999999,22.82111],"type":"Point"}
}