{
  "type": "Feature",
  "properties": {
    "gn:admin1_code":"4.0",
    "gn:admin2_code":"MIA",
    "gn:admin3_code":"K09",
    "gn:admin4_code":"10005040015.0",
    "gn:asciiname":"Xiajiezi",
    "gn:country_code":"TW",
    "gn:dem":8,
    "gn:feature_class":"P",
    "gn:feature_code":"PPL",
    "gn:name":"Xiajiezi",
    "gn:population":0,
    "gn:timezone":"Asia/Taipei",
    "iso:country":"TW",
    "name:und_x_variant":[
        "Siajiezih",
        "Xiajiezi",
        "Hsia-chieh-tzu"
    ],
    "name:zho_x_preferred":[
        "\u4e0b\u8857\u4ed4"
    ],
    "wof:name":"Xiajiezi",
    "wof:placetype":"locality"
},
  "geometry": {"coordinates":[120.86776999999999,24.67975],"type":"Point"}
}