{
  "type": "Feature",
  "properties": {
    "gn:admin1_code":"03",
    "gn:admin2_code":"TPQ",
    "gn:admin3_code":"F26",
    "gn:admin4_code":"65000280006.0",
    "gn:asciiname":"Buzi",
    "gn:country_code":"TW",
    "gn:dem":212,
    "gn:feature_class":"P",
    "gn:feature_code":"PPL",
    "gn:name":"Buzi",
    "gn:population":0,
    "gn:timezone":"Asia/Taipei",
    "iso:country":"TW",
    "name:und_x_variant":[
        "Pu-tzu-ting",
        "Pu-tzu",
        "Buzi"
    ],
    "wof:name":"Buzi",
    "wof:placetype":"locality"
},
  "geometry": {"coordinates":[121.65000000000001,25.18333],"type":"Point"}
}