{
  "type": "Feature",
  "properties": {
    "gn:admin1_code":"2.0",
    "gn:admin2_code":"KHH",
    "gn:admin3_code":"E31",
    "gn:admin4_code":"64000310008.0",
    "gn:asciiname":"Beishangtang",
    "gn:country_code":"TW",
    "gn:dem":73,
    "gn:feature_class":"P",
    "gn:feature_code":"PPL",
    "gn:name":"Beishangtang",
    "gn:population":0,
    "gn:timezone":"Asia/Taipei",
    "iso:country":"TW",
    "name:zho_x_preferred":[
        "\u5317\u4e0a\u5858"
    ],
    "name:zho_x_variant":[
        "Pei-shang-t\u2019ang"
    ],
    "wof:name":"Beishangtang",
    "wof:placetype":"locality"
},
  "geometry": {"coordinates":[120.5812,22.9005],"type":"Point"}
}