{
  "type": "Feature",
  "properties": {
    "gn:admin1_code":"4.0",
    "gn:admin2_code":"TAO",
    "gn:admin3_code":"H07",
    "gn:admin4_code":"68000070018.0",
    "gn:asciiname":"Dongjiulukeng",
    "gn:country_code":"TW",
    "gn:dem":162,
    "gn:feature_class":"P",
    "gn:feature_code":"PPL",
    "gn:name":"Dongjiulukeng",
    "gn:population":0,
    "gn:timezone":"Asia/Taipei",
    "iso:country":"TW",
    "name:und_x_variant":[
        "Chiu-lu",
        "Dongjioulukeng"
    ],
    "name:zho_x_preferred":[
        "Chiu-lu-k\u2019eng"
    ],
    "name:zho_x_variant":[
        "Chiu-lu-ts\u2019un",
        "\u6771\u820a\u8def\u5751",
        "Tung-chiu-lu-k\u2019eng"
    ],
    "wof:name":"Dongjiulukeng",
    "wof:placetype":"locality"
},
  "geometry": {"coordinates":[121.3609,25.01142],"type":"Point"}
}