{
  "type": "Feature",
  "properties": {
    "gn:admin1_code":"04",
    "gn:admin2_code":"HSZ",
    "gn:admin3_code":"J14",
    "gn:admin4_code":"10004120005.0",
    "gn:asciiname":"Daoxia",
    "gn:country_code":"TW",
    "gn:dem":907,
    "gn:feature_class":"P",
    "gn:feature_code":"PPL",
    "gn:name":"Daoxia",
    "gn:population":0,
    "gn:timezone":"Asia/Taipei",
    "iso:country":"TW",
    "name:und_x_variant":[
        "Daosia",
        "Daoxia",
        "Tao-hsia"
    ],
    "name:zho_x_preferred":[
        "\u9053\u4e0b"
    ],
    "wof:name":"Daoxia",
    "wof:placetype":"locality"
},
  "geometry": {"coordinates":[121.26667,24.67083],"type":"Point"}
}