{
  "type": "Feature",
  "properties": {
    "gn:admin1_code":"4.0",
    "gn:admin2_code":"PIF",
    "gn:admin3_code":"T32",
    "gn:admin4_code":"10013320001.0",
    "gn:asciiname":"Fenglin",
    "gn:country_code":"TW",
    "gn:dem":54,
    "gn:feature_class":"P",
    "gn:feature_code":"PPL",
    "gn:name":"Fenglin",
    "gn:population":0,
    "gn:timezone":"Asia/Taipei",
    "iso:country":"TW",
    "name:und_x_variant":[
        "Shih-tzu",
        "Fonglin",
        "Fenglin",
        "Feng-lin"
    ],
    "name:zho_x_preferred":[
        "Feng-lin-ts\u2019un"
    ],
    "name:zho_x_variant":[
        "\u6953\u6797"
    ],
    "wof:name":"Fenglin",
    "wof:placetype":"locality"
},
  "geometry": {"coordinates":[120.7075,22.19972000000001],"type":"Point"}
}