{
  "type": "Feature",
  "properties": {
    "gn:admin1_code":"4.0",
    "gn:admin2_code":"CYQ",
    "gn:admin3_code":"Q15",
    "gn:admin4_code":"10010140008.0",
    "gn:asciiname":"Shimayuan",
    "gn:country_code":"TW",
    "gn:dem":75,
    "gn:feature_class":"P",
    "gn:feature_code":"PPL",
    "gn:name":"Shimayuan",
    "gn:population":0,
    "gn:timezone":"Asia/Taipei",
    "iso:country":"TW",
    "name:und_x_variant":[
        "Shihmayuan",
        "Shimayuan"
    ],
    "name:zho_x_preferred":[
        "\u77f3\u9ebb\u5712"
    ],
    "name:zho_x_variant":[
        "Shih-ma-y\u00fcan"
    ],
    "wof:name":"Shimayuan",
    "wof:placetype":"locality"
},
  "geometry": {"coordinates":[120.50946999999999,23.48599],"type":"Point"}
}