{
  "type": "Feature",
  "properties": {
    "gn:admin1_code":"04",
    "gn:admin2_code":"TPE",
    "gn:admin3_code":"A13",
    "gn:admin4_code":"63000090018.0",
    "gn:asciiname":"Dalingtou",
    "gn:country_code":"TW",
    "gn:dem":264,
    "gn:feature_class":"P",
    "gn:feature_code":"PPL",
    "gn:name":"Dalingtou",
    "gn:population":0,
    "gn:timezone":"Asia/Taipei",
    "iso:country":"TW",
    "name:zho_x_preferred":[
        "\u5927\u5dba\u982d"
    ],
    "name:zho_x_variant":[
        "Ta-ling-t\u2019ou"
    ],
    "wof:name":"Dalingtou",
    "wof:placetype":"locality"
},
  "geometry": {"coordinates":[121.58963,25.02647],"type":"Point"}
}