{
  "type": "Feature",
  "properties": {
    "gn:admin1_code":"3.0",
    "gn:admin2_code":"TPQ",
    "gn:admin3_code":"F15",
    "gn:admin4_code":"65000090015.0",
    "gn:asciiname":"Liangting",
    "gn:country_code":"TW",
    "gn:dem":522,
    "gn:feature_class":"P",
    "gn:feature_code":"PPL",
    "gn:name":"Liangting",
    "gn:population":0,
    "gn:timezone":"Asia/Taipei",
    "iso:country":"TW",
    "name:zho_x_preferred":[
        "\u6dbc\u4ead"
    ],
    "name:zho_x_variant":[
        "Liang-t\u2019ing"
    ],
    "wof:name":"Liangting",
    "wof:placetype":"locality"
},
  "geometry": {"coordinates":[121.41939000000001,24.88598],"type":"Point"}
}