{
  "type": "Feature",
  "properties": {
    "gn:admin1_code":"4.0",
    "gn:admin2_code":"TAO",
    "gn:admin3_code":"H09",
    "gn:admin4_code":"68000090026.0",
    "gn:asciiname":"Shanghua",
    "gn:country_code":"TW",
    "gn:dem":239,
    "gn:feature_class":"P",
    "gn:feature_code":"PPL",
    "gn:name":"Shanghua",
    "gn:population":0,
    "gn:timezone":"Asia/Taipei",
    "iso:country":"TW",
    "name:und_x_variant":[
        "Shang-hua"
    ],
    "name:zho_x_preferred":[
        "\u4e0a\u83ef"
    ],
    "wof:name":"Shanghua",
    "wof:placetype":"locality"
},
  "geometry": {"coordinates":[121.2225,24.85222000000001],"type":"Point"}
}