{
  "type": "Feature",
  "properties": {
    "gn:admin1_code":"4.0",
    "gn:admin2_code":"TPE",
    "gn:admin3_code":"A16",
    "gn:admin4_code":"63000120018.0",
    "gn:asciiname":"Xiabaxian",
    "gn:country_code":"TW",
    "gn:dem":4,
    "gn:feature_class":"P",
    "gn:feature_code":"PPL",
    "gn:name":"Xiabaxian",
    "gn:population":0,
    "gn:timezone":"Asia/Taipei",
    "iso:country":"TW",
    "name:und_x_variant":[
        "Siabasian",
        "Hsia-pa-hsien"
    ],
    "name:zho_x_preferred":[
        "\u4e0b\u516b\u4ed9"
    ],
    "wof:name":"Xiabaxian",
    "wof:placetype":"locality"
},
  "geometry": {"coordinates":[121.48399999999999,25.1153],"type":"Point"}
}