{
  "type": "Feature",
  "properties": {
    "gn:admin1_code":"4.0",
    "gn:admin2_code":"CHA",
    "gn:admin3_code":"N18",
    "gn:admin4_code":"10007160011.0",
    "gn:asciiname":"Fuzhen",
    "gn:country_code":"TW",
    "gn:dem":34,
    "gn:feature_class":"P",
    "gn:feature_code":"PPL",
    "gn:name":"Fuzhen",
    "gn:population":0,
    "gn:timezone":"Asia/Taipei",
    "iso:country":"TW",
    "name:und_x_variant":[
        "Fujhen",
        "Fuzhen",
        "Fu-chen"
    ],
    "name:zho_x_preferred":[
        "\u6d6e\u5733"
    ],
    "name:zho_x_variant":[
        "Fu-ch\u00fcn"
    ],
    "wof:name":"Fuzhen",
    "wof:placetype":"locality"
},
  "geometry": {"coordinates":[120.56131000000001,23.91516],"type":"Point"}
}