{
  "type": "Feature",
  "properties": {
    "iso:country":"TW",
    "name:eng_x_preferred":[
        "West District"
    ],
    "name:ita_x_preferred":[
        "Distretto Occidentale"
    ],
    "name:jpn_x_preferred":[
        "\u897f\u533a"
    ],
    "name:kor_x_preferred":[
        "\uc2dc \uad6c"
    ],
    "name:nan_x_preferred":[
        "Se-khu"
    ],
    "name:pol_x_preferred":[
        "Xi"
    ],
    "name:vie_x_preferred":[
        "Qu\u1eadn T\u00e2y"
    ],
    "name:zho_x_preferred":[
        "\u9130\u6c5f\u91cc"
    ],
    "name:zho_x_variant":[
        "\u897f\u5340"
    ],
    "qs:name":"\u5229\u6c11\u91cc",
    "qs:name_adm0":"\u81fa\u7063",
    "qs:name_adm1":"\u53f0\u4e2d\u5e02",
    "qs:photos":361,
    "qs:photos_1k":73,
    "qs:photos_9k":2,
    "qs:photos_9r":5,
    "qs:photos_all":361,
    "qs:photos_sr":6,
    "qs:placetype":"Suburb",
    "qs:pop_sr":"0",
    "wd:wordcount":334,
    "wof:name":"\u5229\u6c11\u91cc",
    "wof:placetype":"neighbourhood"
},
  "geometry": {"coordinates":[120.674171,24.13435],"type":"Point"}
}