{
  "type": "Feature",
  "properties": {
    "gn:admin1_code":"4.0",
    "gn:admin2_code":"HSZ",
    "gn:admin3_code":"J05",
    "gn:admin4_code":"10004010006.0",
    "gn:asciiname":"Dongxing",
    "gn:country_code":"TW",
    "gn:dem":58,
    "gn:feature_class":"P",
    "gn:feature_code":"PPL",
    "gn:name":"Dongxing",
    "gn:population":0,
    "gn:timezone":"Asia/Taipei",
    "iso:country":"TW",
    "name:und_x_variant":[
        "Dongsing",
        "Dongxing",
        "Tung-hsing"
    ],
    "name:zho_x_preferred":[
        "\u6771\u8208"
    ],
    "wof:name":"Dongxing",
    "wof:placetype":"locality"
},
  "geometry": {"coordinates":[121.05056,24.80361],"type":"Point"}
}