{
  "type": "Feature",
  "properties": {
    "gn:admin1_code":"4.0",
    "gn:admin2_code":"HSZ",
    "gn:admin3_code":"J05",
    "gn:admin4_code":"10004010006.0",
    "gn:asciiname":"Dongxing",
    "gn:country_code":"TW",
    "gn:dem":58,
    "gn:feature_class":"P",
    "gn:feature_code":"PPL",
    "gn:name":"Dongxing",
    "gn:population":0,
    "gn:timezone":"Asia/Taipei",
    "iso:country":"TW",
    "name:ceb_x_preferred":[
        "Dongxing"
    ],
    "name:deu_x_preferred":[
        "Dongxing"
    ],
    "name:fra_x_preferred":[
        "Dongxing"
    ],
    "name:mlg_x_preferred":[
        "Dongxing"
    ],
    "name:nor_x_preferred":[
        "Dongxing"
    ],
    "name:pnb_x_preferred":[
        "\u0688\u0648\u0646\u06af\u0634\u06cc\u0646\u06af"
    ],
    "name:rus_x_preferred":[
        "\u0414\u0443\u043d\u0441\u0438\u043d"
    ],
    "name:swe_x_preferred":[
        "Dongxing"
    ],
    "name:und_x_variant":[
        "Dongsing",
        "Tung-hsing"
    ],
    "name:vie_x_preferred":[
        "\u0110\u00f4ng H\u01b0ng"
    ],
    "name:zho_x_preferred":[
        "\u6771\u8208"
    ],
    "wof:name":"Dongxing",
    "wof:placetype":"locality"
},
  "geometry": {"coordinates":[121.05056,24.80361],"type":"Point"}
}