{
  "type": "Feature",
  "properties": {
    "gn:admin1_code":"4.0",
    "gn:admin2_code":"PIF",
    "gn:admin3_code":"T23",
    "gn:admin4_code":"10013230002.0",
    "gn:asciiname":"Fu'ancun",
    "gn:country_code":"TW",
    "gn:dem":1,
    "gn:feature_class":"P",
    "gn:feature_code":"PPL",
    "gn:name":"Fu\u2019ancun",
    "gn:population":0,
    "gn:timezone":"Asia/Taipei",
    "iso:country":"TW",
    "name:und_x_variant":[
        "Fu-an"
    ],
    "name:zho_x_preferred":[
        "\u798f\u5b89\u6751"
    ],
    "name:zho_x_variant":[
        "Fu\u2019ancun",
        "Fu-an-ts\u2019un"
    ],
    "wof:name":"Fu'ancun",
    "wof:placetype":"locality"
},
  "geometry": {"coordinates":[120.70694,22.06944],"type":"Point"}
}