{
  "type": "Feature",
  "properties": {
    "gn:admin1_code":"4.0",
    "gn:admin2_code":"TNN",
    "gn:admin3_code":"R21",
    "gn:admin4_code":"67000210003.0",
    "gn:asciiname":"Anding",
    "gn:country_code":"TW",
    "gn:dem":10,
    "gn:feature_class":"P",
    "gn:feature_code":"PPL",
    "gn:name":"Anding",
    "gn:population":0,
    "gn:timezone":"Asia/Taipei",
    "iso:country":"TW",
    "name:ceb_x_preferred":[
        "Anding"
    ],
    "name:deu_x_preferred":[
        "Anding"
    ],
    "name:fra_x_preferred":[
        "Anding"
    ],
    "name:nor_x_preferred":[
        "Anding"
    ],
    "name:und_x_variant":[
        "An-ting"
    ],
    "name:zho_x_preferred":[
        "\u5b89\u5b9a"
    ],
    "wof:name":"Anding",
    "wof:placetype":"locality"
},
  "geometry": {"coordinates":[120.23667,23.11972],"type":"Point"}
}