{
  "type": "Feature",
  "properties": {
    "gn:admin1_code":"3.0",
    "gn:admin2_code":"TPQ",
    "gn:admin3_code":"F10",
    "gn:admin4_code":"65000200004.0",
    "gn:asciiname":"Shangshicao",
    "gn:country_code":"TW",
    "gn:dem":501,
    "gn:feature_class":"P",
    "gn:feature_code":"PPL",
    "gn:name":"Shangshicao",
    "gn:population":0,
    "gn:timezone":"Asia/Taipei",
    "iso:country":"TW",
    "name:und_x_variant":[
        "Shangshihcao"
    ],
    "name:zho_x_preferred":[
        "\u4e0a\u77f3\u66f9"
    ],
    "name:zho_x_variant":[
        "Shang-shih-ts\u2019ao"
    ],
    "wof:name":"Shangshicao",
    "wof:placetype":"locality"
},
  "geometry": {"coordinates":[121.75033000000001,24.88554],"type":"Point"}
}