{
  "type": "Feature",
  "properties": {
    "gn:admin1_code":"04",
    "gn:admin2_code":"HUA",
    "gn:admin3_code":"U02",
    "gn:admin4_code":"10015070013.0",
    "gn:asciiname":"Nanfu",
    "gn:country_code":"TW",
    "gn:dem":136,
    "gn:feature_class":"P",
    "gn:feature_code":"PPL",
    "gn:name":"Nanfu",
    "gn:population":0,
    "gn:timezone":"Asia/Taipei",
    "iso:country":"TW",
    "name:und_x_variant":[
        "Sha-lao",
        "Nanfu",
        "Nan-fu"
    ],
    "name:zho_x_preferred":[
        "Nan-fu-ts\u2019un"
    ],
    "name:zho_x_variant":[
        "\u5357\u5bcc"
    ],
    "wof:name":"Nanfu",
    "wof:placetype":"locality"
},
  "geometry": {"coordinates":[121.45222,23.64177],"type":"Point"}
}