{
  "type": "Feature",
  "properties": {
    "gn:admin1_code":"4.0",
    "gn:admin2_code":"TNN",
    "gn:admin3_code":"R15",
    "gn:admin4_code":"67000160004.0",
    "gn:asciiname":"Zhongjia",
    "gn:country_code":"TW",
    "gn:dem":6,
    "gn:feature_class":"P",
    "gn:feature_code":"PPL",
    "gn:name":"Zhongjia",
    "gn:population":0,
    "gn:timezone":"Asia/Taipei",
    "iso:country":"TW",
    "name:und_x_variant":[
        "Jhongjia",
        "Zhongjia",
        "Chung-chia"
    ],
    "name:zho_x_preferred":[
        "\u4e2d\u7532"
    ],
    "wof:name":"Zhongjia",
    "wof:placetype":"locality"
},
  "geometry": {"coordinates":[120.15778,23.20333],"type":"Point"}
}