{
  "type": "Feature",
  "properties": {
    "gn:admin1_code":"1.0",
    "gn:admin2_code":"KIN",
    "gn:admin3_code":"W01",
    "gn:admin4_code":"9020030008.0",
    "gn:asciiname":"Xipu",
    "gn:country_code":"TW",
    "gn:dem":9,
    "gn:feature_class":"P",
    "gn:feature_code":"PPL",
    "gn:name":"Xipu",
    "gn:population":0,
    "gn:timezone":"Asia/Taipei",
    "iso:country":"TW",
    "name:und_x_variant":[
        "Xibu",
        "Hsi-pu",
        "Xipu"
    ],
    "name:zho_x_preferred":[
        "\u897f\u57d4"
    ],
    "wof:name":"Xipu",
    "wof:placetype":"locality"
},
  "geometry": {"coordinates":[118.44754,24.43153],"type":"Point"}
}