{
  "type": "Feature",
  "properties": {
    "gn:admin1_code":"03",
    "gn:admin2_code":"TPQ",
    "gn:admin3_code":"F26",
    "gn:admin4_code":"65000280005.0",
    "gn:asciiname":"Yuantanzi",
    "gn:country_code":"TW",
    "gn:dem":63,
    "gn:feature_class":"P",
    "gn:feature_code":"PPL",
    "gn:name":"Yuantanzi",
    "gn:population":0,
    "gn:timezone":"Asia/Taipei",
    "iso:country":"TW",
    "name:und_x_variant":[
        "Yuantanzih",
        "Yuantanzi"
    ],
    "name:zho_x_preferred":[
        "\u54e1\u6f6d\u5b50"
    ],
    "name:zho_x_variant":[
        "Y\u00fcan-t\u2019an-tzu"
    ],
    "wof:name":"Yuantanzi",
    "wof:placetype":"locality"
},
  "geometry": {"coordinates":[121.64364999999999,25.19532],"type":"Point"}
}