{
  "type": "Feature",
  "properties": {
    "iso:country":"TW",
    "qs:name":"\u9022\u798f\u91cc",
    "qs:name_adm0":"\u81fa\u7063",
    "qs:name_adm1":"\u53f0\u4e2d\u5e02",
    "qs:photos":78,
    "qs:photos_1k":16,
    "qs:photos_9k":1,
    "qs:photos_9r":3,
    "qs:photos_all":78,
    "qs:photos_sr":3,
    "qs:placetype":"Suburb",
    "qs:pop_sr":"0",
    "wof:name":"\u9022\u798f\u91cc",
    "wof:placetype":"neighbourhood"
},
  "geometry": {"coordinates":[120.64975800000001,24.174875],"type":"Point"}
}