{
  "type": "Feature",
  "properties": {
    "gn:admin1_code":"04",
    "gn:admin2_code":"HSZ",
    "gn:admin3_code":"J10",
    "gn:admin4_code":"10004070001.0",
    "gn:asciiname":"Shaotanwo",
    "gn:country_code":"TW",
    "gn:dem":194,
    "gn:feature_class":"P",
    "gn:feature_code":"PPL",
    "gn:name":"Shaotanwo",
    "gn:population":0,
    "gn:timezone":"Asia/Taipei",
    "iso:country":"TW",
    "name:zho_x_preferred":[
        "\u71d2\u70ad\u7aa9"
    ],
    "name:zho_x_variant":[
        "Shao-t\u2019an-wo"
    ],
    "wof:name":"Shaotanwo",
    "wof:placetype":"locality"
},
  "geometry": {"coordinates":[121.11694,24.74111],"type":"Point"}
}