{
  "type": "Feature",
  "properties": {
    "gn:admin1_code":"04",
    "gn:admin2_code":"MIA",
    "gn:admin3_code":"K13",
    "gn:admin4_code":"10005160008.0",
    "gn:asciiname":"Shangshuangkeng",
    "gn:country_code":"TW",
    "gn:dem":110,
    "gn:feature_class":"P",
    "gn:feature_code":"PPL",
    "gn:name":"Shangshuangkeng",
    "gn:population":0,
    "gn:timezone":"Asia/Taipei",
    "iso:country":"TW",
    "name:zho_x_preferred":[
        "Shang-shuang-k\u2019eng"
    ],
    "wof:name":"Shangshuangkeng",
    "wof:placetype":"locality"
},
  "geometry": {"coordinates":[120.91838,24.63829],"type":"Point"}
}