{
  "type": "Feature",
  "properties": {
    "gn:admin1_code":"4.0",
    "gn:admin2_code":"HSZ",
    "gn:admin3_code":"J05",
    "gn:admin4_code":"10004010027.0",
    "gn:asciiname":"Luchang",
    "gn:country_code":"TW",
    "gn:dem":45,
    "gn:feature_class":"P",
    "gn:feature_code":"PPL",
    "gn:name":"Luchang",
    "gn:population":0,
    "gn:timezone":"Asia/Taipei",
    "iso:country":"TW",
    "name:zho_x_preferred":[
        "\u9e7f\u5834"
    ],
    "name:zho_x_variant":[
        "Lu-ch\u2019ang"
    ],
    "wof:name":"Luchang",
    "wof:placetype":"locality"
},
  "geometry": {"coordinates":[121.03139,24.82167],"type":"Point"}
}