{
  "type": "Feature",
  "properties": {
    "gn:admin1_code":"4.0",
    "gn:admin2_code":"HUA",
    "gn:admin3_code":"U02",
    "gn:admin4_code":"10015070004.0",
    "gn:asciiname":"Xianlezhuang",
    "gn:country_code":"TW",
    "gn:dem":339,
    "gn:feature_class":"P",
    "gn:feature_code":"PPL",
    "gn:name":"Xianlezhuang",
    "gn:population":0,
    "gn:timezone":"Asia/Taipei",
    "iso:country":"TW",
    "name:und_x_variant":[
        "Sianlejhuang",
        "Hsien-le-chuang"
    ],
    "name:zho_x_preferred":[
        "\u4ed9\u6a02\u838a"
    ],
    "wof:name":"Xianlezhuang",
    "wof:placetype":"locality"
},
  "geometry": {"coordinates":[121.39274,23.67578],"type":"Point"}
}