{
  "type": "Feature",
  "properties": {
    "gn:admin1_code":"4.0",
    "gn:admin2_code":"MIA",
    "gn:admin3_code":"K05",
    "gn:admin4_code":"10005100008.0",
    "gn:asciiname":"Shikeng",
    "gn:country_code":"TW",
    "gn:dem":155,
    "gn:feature_class":"P",
    "gn:feature_code":"PPL",
    "gn:name":"Shikeng",
    "gn:population":0,
    "gn:timezone":"Asia/Taipei",
    "iso:country":"TW",
    "name:und_x_variant":[
        "Shihkeng",
        "Shikeng"
    ],
    "name:zho_x_preferred":[
        "\u77f3\u5751"
    ],
    "name:zho_x_variant":[
        "Shih-k\u2019eng"
    ],
    "wof:name":"Shikeng",
    "wof:placetype":"locality"
},
  "geometry": {"coordinates":[120.80835999999999,24.4596],"type":"Point"}
}