{
  "type": "Feature",
  "properties": {
    "gn:admin1_code":"04",
    "gn:admin2_code":"PIF",
    "gn:admin3_code":"T30",
    "gn:admin4_code":"10013300006.0",
    "gn:asciiname":"Wangjia",
    "gn:country_code":"TW",
    "gn:dem":56,
    "gn:feature_class":"P",
    "gn:feature_code":"PPL",
    "gn:name":"Wangjia",
    "gn:population":0,
    "gn:timezone":"Asia/Taipei",
    "iso:country":"TW",
    "name:und_x_variant":[
        "Wang-chia-ts\u2019un",
        "\u671b\u5609",
        "Wangjia",
        "Meng-k\u2019a-li",
        "Wang-chia"
    ],
    "wof:name":"Wangjia",
    "wof:placetype":"locality"
},
  "geometry": {"coordinates":[120.61944,22.46472],"type":"Point"}
}