{
  "type": "Feature",
  "properties": {
    "gn:admin1_code":"4.0",
    "gn:admin2_code":"TAO",
    "gn:admin3_code":"H13",
    "gn:admin4_code":"68000130010.0",
    "gn:asciiname":"Gaoyi",
    "gn:country_code":"TW",
    "gn:dem":701,
    "gn:feature_class":"P",
    "gn:feature_code":"PPL",
    "gn:name":"Gaoyi",
    "gn:population":0,
    "gn:timezone":"Asia/Taipei",
    "iso:country":"TW",
    "name:und_x_variant":[
        "Kao-i-lan-she",
        "Kao-i-lan",
        "Gaoyi",
        "Kao-i"
    ],
    "name:zho_x_preferred":[
        "Ch\u2019ia-i-lan"
    ],
    "name:zho_x_variant":[
        "\u9ad8\u7fa9"
    ],
    "wof:name":"Gaoyi",
    "wof:placetype":"locality"
},
  "geometry": {"coordinates":[121.35944000000001,24.71167],"type":"Point"}
}