{
  "type": "Feature",
  "properties": {
    "iso:country":"TW",
    "name:eng_x_preferred":[
        "Yuanchang"
    ],
    "name:eng_x_variant":[
        "Yuanchang Township"
    ],
    "name:zho_tw_x_preferred":[
        "\u5143\u9577\u9109"
    ],
    "qs:name":"\u5143\u9577\u9109",
    "qs:name_adm0":"\u81fa\u7063",
    "qs:name_adm1":"\u96f2\u6797\u7e23",
    "qs:photos":27,
    "qs:photos_1k":5,
    "qs:photos_9k":1,
    "qs:photos_9r":2,
    "qs:photos_all":30,
    "qs:photos_sr":2,
    "qs:placetype":"County",
    "qs:pop_sr":"0",
    "wof:name":"Yuanchang",
    "wof:placetype":"county"
},
  "geometry": {"coordinates":[120.311965,23.652229],"type":"Point"}
}