{
  "type": "Feature",
  "properties": {
    "gn:admin1_code":"4.0",
    "gn:admin2_code":"MIA",
    "gn:admin3_code":"K12",
    "gn:admin4_code":"10005060019.0",
    "gn:asciiname":"Gongsiliao",
    "gn:country_code":"TW",
    "gn:dem":8,
    "gn:feature_class":"P",
    "gn:feature_code":"PPL",
    "gn:name":"Gongsiliao",
    "gn:population":0,
    "gn:timezone":"Asia/Taipei",
    "iso:country":"TW",
    "name:und_x_variant":[
        "Gongsihliao",
        "Kung-ssu-liao-chuang",
        "Kung-ssu-liao"
    ],
    "name:zho_x_preferred":[
        "\u516c\u53f8\u5bee"
    ],
    "wof:name":"Gongsiliao",
    "wof:placetype":"locality"
},
  "geometry": {"coordinates":[120.75743,24.61257],"type":"Point"}
}