{
  "type": "Feature",
  "properties": {
    "gn:admin1_code":"04",
    "gn:admin2_code":"TXG",
    "gn:admin3_code":"B22",
    "gn:admin4_code":"66000220007.0",
    "gn:asciiname":"Antianzhuang",
    "gn:country_code":"TW",
    "gn:dem":10,
    "gn:feature_class":"P",
    "gn:feature_code":"PPL",
    "gn:name":"Antianzhuang",
    "gn:population":0,
    "gn:timezone":"Asia/Taipei",
    "iso:country":"TW",
    "name:und_x_variant":[
        "Ting-an",
        "Antianzhuang",
        "Antianjhuang"
    ],
    "name:zho_x_preferred":[
        "T\u2019ien-hsin-tzu"
    ],
    "name:zho_x_variant":[
        "Ting-an-ts\u2019un",
        "\u5b89\u7530\u838a",
        "An-t\u2019ien-chuang"
    ],
    "wof:name":"Antianzhuang",
    "wof:placetype":"locality"
},
  "geometry": {"coordinates":[120.60083,24.39278],"type":"Point"}
}