{
  "type": "Feature",
  "properties": {
    "gn:admin1_code":"4.0",
    "gn:admin2_code":"TNN",
    "gn:admin3_code":"R25",
    "gn:admin4_code":"67000250003.0",
    "gn:asciiname":"Zhutouqi",
    "gn:country_code":"TW",
    "gn:dem":68,
    "gn:feature_class":"P",
    "gn:feature_code":"PPL",
    "gn:name":"Zhutouqi",
    "gn:population":0,
    "gn:timezone":"Asia/Taipei",
    "iso:country":"TW",
    "name:und_x_variant":[
        "Jhutouci",
        "Zhutouqi"
    ],
    "name:zho_x_preferred":[
        "\u7af9\u982d\u5d0e"
    ],
    "name:zho_x_variant":[
        "Y\u00fc-y\u00fcan",
        "Chu-t\u2019ou-ch\u2019i"
    ],
    "wof:name":"Zhutouqi",
    "wof:placetype":"locality"
},
  "geometry": {"coordinates":[120.45023999999999,23.05111],"type":"Point"}
}