{
  "type": "Feature",
  "properties": {
    "gn:admin1_code":"4.0",
    "gn:admin2_code":"MIA",
    "gn:admin3_code":"K14",
    "gn:admin4_code":"10005110001.0",
    "gn:asciiname":"Wushewo",
    "gn:country_code":"TW",
    "gn:dem":344,
    "gn:feature_class":"P",
    "gn:feature_code":"PPL",
    "gn:name":"Wushewo",
    "gn:population":0,
    "gn:timezone":"Asia/Taipei",
    "iso:country":"TW",
    "name:und_x_variant":[
        "Wu-she-wo"
    ],
    "name:zho_x_preferred":[
        "\u70cf\u86c7\u7aa9"
    ],
    "wof:name":"Wushewo",
    "wof:placetype":"locality"
},
  "geometry": {"coordinates":[121.01139000000001,24.60556],"type":"Point"}
}