{
  "type": "Feature",
  "properties": {
    "gn:admin1_code":"4.0",
    "gn:admin2_code":"HSQ",
    "gn:admin3_code":"O03",
    "gn:admin4_code":"10018030021.0",
    "gn:asciiname":"Dingcuo",
    "gn:country_code":"TW",
    "gn:dem":9,
    "gn:feature_class":"P",
    "gn:feature_code":"PPL",
    "gn:name":"Dingcuo",
    "gn:population":0,
    "gn:timezone":"Asia/Taipei",
    "iso:country":"TW",
    "name:zho_x_preferred":[
        "\u9802\u539d"
    ],
    "name:zho_x_variant":[
        "Ting-ts\u2019o"
    ],
    "wof:name":"Dingcuo",
    "wof:placetype":"locality"
},
  "geometry": {"coordinates":[120.91437999999999,24.7426],"type":"Point"}
}