{
  "type": "Feature",
  "properties": {
    "gn:admin1_code":"4.0",
    "gn:admin2_code":"TXG",
    "gn:admin3_code":"B08",
    "gn:admin4_code":"66000080014.0",
    "gn:asciiname":"Qingshuikou",
    "gn:country_code":"TW",
    "gn:dem":195,
    "gn:feature_class":"P",
    "gn:feature_code":"PPL",
    "gn:name":"Qingshuikou",
    "gn:population":0,
    "gn:timezone":"Asia/Taipei",
    "iso:country":"TW",
    "name:und_x_variant":[
        "\u6e05\u6c34\u53e3",
        "Qingshuikou",
        "Cingshueikou"
    ],
    "name:zho_x_preferred":[
        "Ch\u2019ing-shui-k\u2019ou"
    ],
    "wof:name":"Qingshuikou",
    "wof:placetype":"locality"
},
  "geometry": {"coordinates":[120.7443,24.1877],"type":"Point"}
}