{
  "type": "Feature",
  "properties": {
    "gn:admin1_code":"4.0",
    "gn:admin2_code":"TAO",
    "gn:admin3_code":"H08",
    "gn:admin4_code":"68000080047.0",
    "gn:asciiname":"Kanjiao",
    "gn:country_code":"TW",
    "gn:dem":117,
    "gn:feature_class":"P",
    "gn:feature_code":"PPL",
    "gn:name":"Kanjiao",
    "gn:population":0,
    "gn:timezone":"Asia/Taipei",
    "iso:country":"TW",
    "name:zho_x_preferred":[
        "\u5d01\u811a"
    ],
    "name:zho_x_variant":[
        "Hsia-k\u2019an",
        "K\u2019an-chiao"
    ],
    "wof:name":"Kanjiao",
    "wof:placetype":"locality"
},
  "geometry": {"coordinates":[121.26555999999999,24.96917],"type":"Point"}
}