{
  "type": "Feature",
  "properties": {
    "gn:admin1_code":"2.0",
    "gn:admin2_code":"KHH",
    "gn:admin3_code":"E37",
    "gn:admin4_code":"64000370001.0",
    "gn:asciiname":"Liuzuotun",
    "gn:country_code":"TW",
    "gn:dem":1773,
    "gn:feature_class":"P",
    "gn:feature_code":"PPL",
    "gn:name":"Liuzuotun",
    "gn:population":0,
    "gn:timezone":"Asia/Taipei",
    "iso:country":"TW",
    "name:und_x_variant":[
        "Liu-tso-t\u2019un"
    ],
    "wof:name":"Liuzuotun",
    "wof:placetype":"locality"
},
  "geometry": {"coordinates":[120.80472,23.15139],"type":"Point"}
}