{
  "type": "Feature",
  "properties": {
    "gn:country":"TW",
    "gn:fcode":"ADMD",
    "gn:population":0,
    "iso:country":"TW",
    "name:cat_x_preferred":[
        "Neihu"
    ],
    "name:ceb_x_preferred":[
        "Neihu Qu"
    ],
    "name:deu_x_preferred":[
        "Neihu"
    ],
    "name:eng_x_preferred":[
        "Neihu District"
    ],
    "name:hak_x_preferred":[
        "Nui-f\u00f9-kh\u00ee"
    ],
    "name:hye_x_preferred":[
        "\u0546\u0565\u0575\u0570\u0578\u0582"
    ],
    "name:ind_x_preferred":[
        "Distrik Neihu"
    ],
    "name:jpn_x_preferred":[
        "\u5185\u6e56\u533a"
    ],
    "name:kor_x_preferred":[
        "\ub124\uc774\ud6c4\uad6c"
    ],
    "name:lit_x_preferred":[
        "Neihu"
    ],
    "name:lzh_x_preferred":[
        "\u5167\u6e56\u5340"
    ],
    "name:nan_x_preferred":[
        "L\u0101i-\u00f4\u0358-khu"
    ],
    "name:nld_x_preferred":[
        "Neihu District"
    ],
    "name:pol_x_preferred":[
        "Neihu"
    ],
    "name:rus_x_preferred":[
        "\u041d\u044d\u0439\u0445\u0443"
    ],
    "name:ukr_x_preferred":[
        "\u041d\u0435\u0439\u0445\u0443"
    ],
    "name:vie_x_preferred":[
        "N\u1ed9i H\u1ed3"
    ],
    "name:yue_x_preferred":[
        "\u5167\u6e56\u5340"
    ],
    "name:zho_x_preferred":[
        "Nei-hu Ch\u2019\u00fc"
    ],
    "name:zho_x_variant":[
        "\u5167\u6e56\u5340"
    ],
    "qs:name":"Neihu Qu",
    "qs:photos_9r":0,
    "qs:photos_sr":0,
    "qs:pop_sr":"0",
    "wd:wordcount":534,
    "wof:name":"Neihu Qu",
    "wof:placetype":"localadmin",
    "wof:population":0
},
  "geometry": {"coordinates":[121.58333,25.08333],"type":"Point"}
}