{
  "type": "Feature",
  "properties": {
    "gn:country":"TW",
    "gn:fcode":"ADMD",
    "gn:pop":0,
    "iso:country":"TW",
    "name:unk_x_variant":[
        "\u5167\u6e56\u5340"
    ],
    "name:zho_x_preferred":[
        "Nei-hu Ch\u2019\u00fc"
    ],
    "name:zho_x_variant":[
        "\u5167\u6e56\u5340"
    ],
    "qs:name":"Neihu Qu",
    "qs:photos_9r":0,
    "qs:photos_sr":0,
    "qs:pop_sr":"0",
    "wd:wordcount":534,
    "wof:name":"Neihu Qu",
    "wof:placetype":"localadmin",
    "wof:population":0
},
  "geometry": {"coordinates":[121.58333,25.08333],"type":"Point"}
}