{
  "type": "Feature",
  "properties": {
    "gn:admin1_code":"4.0",
    "gn:admin2_code":"TAO",
    "gn:admin3_code":"H03",
    "gn:admin4_code":"68000020043.0",
    "gn:asciiname":"Guoling",
    "gn:country_code":"TW",
    "gn:dem":135,
    "gn:feature_class":"P",
    "gn:feature_code":"PPL",
    "gn:name":"Guoling",
    "gn:population":0,
    "gn:timezone":"Asia/Taipei",
    "iso:country":"TW",
    "name:und_x_variant":[
        "Kuo-ling"
    ],
    "name:zho_x_preferred":[
        "\u904e\u5dba"
    ],
    "wof:name":"Guoling",
    "wof:placetype":"locality"
},
  "geometry": {"coordinates":[121.17667,24.96],"type":"Point"}
}