{
  "type": "Feature",
  "properties": {
    "gn:admin1_code":"4.0",
    "gn:admin2_code":"TNN",
    "gn:admin3_code":"R11",
    "gn:admin4_code":"67000110008.0",
    "gn:asciiname":"Koulin",
    "gn:country_code":"TW",
    "gn:dem":61,
    "gn:feature_class":"P",
    "gn:feature_code":"PPL",
    "gn:name":"Koulin",
    "gn:population":0,
    "gn:timezone":"Asia/Taipei",
    "iso:country":"TW",
    "name:zho_x_preferred":[
        "\u53e3\u6797"
    ],
    "name:zho_x_variant":[
        "K\u2019ou-lin"
    ],
    "wof:name":"Koulin",
    "wof:placetype":"locality"
},
  "geometry": {"coordinates":[120.42122999999999,23.14081],"type":"Point"}
}