{
  "type": "Feature",
  "properties": {
    "gn:admin1_code":"03",
    "gn:admin2_code":"TPQ",
    "gn:admin3_code":"F30",
    "gn:admin4_code":"65000210005.0",
    "gn:asciiname":"Butoukeng",
    "gn:country_code":"TW",
    "gn:dem":130,
    "gn:feature_class":"P",
    "gn:feature_code":"PPL",
    "gn:name":"Butoukeng",
    "gn:population":0,
    "gn:timezone":"Asia/Taipei",
    "iso:country":"TW",
    "name:zho_x_preferred":[
        "Pu-t\u2019ou-wei"
    ],
    "name:zho_x_variant":[
        "\u57d4\u982d\u5751",
        "Pu-t\u2019ou-k\u2019eng"
    ],
    "wof:name":"Butoukeng",
    "wof:placetype":"locality"
},
  "geometry": {"coordinates":[121.51554,25.24653],"type":"Point"}
}