{
  "type": "Feature",
  "properties": {
    "gn:admin1_code":"4.0",
    "gn:admin2_code":"CHA",
    "gn:admin3_code":"N23",
    "gn:admin4_code":"10007230024.0",
    "gn:asciiname":"Lunjiao",
    "gn:country_code":"TW",
    "gn:dem":8,
    "gn:feature_class":"P",
    "gn:feature_code":"PPL",
    "gn:name":"Lunjiao",
    "gn:population":0,
    "gn:timezone":"Asia/Taipei",
    "iso:country":"TW",
    "name:und_x_variant":[
        "Ta-lun-chiao",
        "Lunjiao",
        "Lun-chiao"
    ],
    "name:zho_x_preferred":[
        "Lun-chiao-ts\u2019un"
    ],
    "name:zho_x_variant":[
        "\u5d19\u8173"
    ],
    "wof:name":"Lunjiao",
    "wof:placetype":"locality"
},
  "geometry": {"coordinates":[120.3634,23.96961],"type":"Point"}
}