{
  "type": "Feature",
  "properties": {
    "gn:admin1_code":"2.0",
    "gn:admin2_code":"KHH",
    "gn:admin3_code":"E22",
    "gn:admin4_code":"64000220010.0",
    "gn:asciiname":"Caitangliao",
    "gn:country_code":"TW",
    "gn:dem":50,
    "gn:feature_class":"P",
    "gn:feature_code":"PPL",
    "gn:name":"Caitangliao",
    "gn:population":0,
    "gn:timezone":"Asia/Taipei",
    "iso:country":"TW",
    "name:zho_x_preferred":[
        "\u83dc\u5802\u5bee"
    ],
    "name:zho_x_variant":[
        "Ts\u2019ai-t\u2019ang-liao"
    ],
    "wof:name":"Caitangliao",
    "wof:placetype":"locality"
},
  "geometry": {"coordinates":[120.34944,22.82972],"type":"Point"}
}