{
  "type": "Feature",
  "properties": {
    "gn:admin1_code":"4.0",
    "gn:admin2_code":"HUA",
    "gn:admin3_code":"U10",
    "gn:admin4_code":"10015100006.0",
    "gn:asciiname":"Zhuyuanxia",
    "gn:country_code":"TW",
    "gn:dem":371,
    "gn:feature_class":"P",
    "gn:feature_code":"PPL",
    "gn:name":"Zhuyuanxia",
    "gn:population":0,
    "gn:timezone":"Asia/Taipei",
    "iso:country":"TW",
    "name:und_x_variant":[
        "Jhuyuansia"
    ],
    "name:zho_x_preferred":[
        "\u7af9\u5712\u4e0b"
    ],
    "name:zho_x_variant":[
        "Chu-y\u00fcan-hsia"
    ],
    "wof:name":"Zhuyuanxia",
    "wof:placetype":"locality"
},
  "geometry": {"coordinates":[121.29378,23.19918],"type":"Point"}
}