{
  "type": "Feature",
  "properties": {
    "gn:admin1_code":"4.0",
    "gn:admin2_code":"ILA",
    "gn:admin3_code":"G02",
    "gn:admin4_code":"10002040006.0",
    "gn:asciiname":"Xiao'ao",
    "gn:country_code":"TW",
    "gn:dem":11,
    "gn:feature_class":"P",
    "gn:feature_code":"PPL",
    "gn:name":"Xiao\u2019ao",
    "gn:population":0,
    "gn:timezone":"Asia/Taipei",
    "iso:country":"TW",
    "name:und_x_variant":[
        "Chiang-ao",
        "Kang-ao",
        "Hsiao-ao"
    ],
    "name:zho_x_preferred":[
        "\u5c0f\u6fb3"
    ],
    "name:zho_x_variant":[
        "Xiao\u2019ao",
        "Siao\u2019ao"
    ],
    "wof:name":"Xiao'ao",
    "wof:placetype":"locality"
},
  "geometry": {"coordinates":[121.84889,24.88917],"type":"Point"}
}