{
  "type": "Feature",
  "properties": {
    "gn:admin1_code":"04",
    "gn:admin2_code":"TXG",
    "gn:admin3_code":"B13",
    "gn:admin4_code":"66000130005.0",
    "gn:asciiname":"Shalu",
    "gn:country_code":"TW",
    "gn:dem":17,
    "gn:feature_class":"P",
    "gn:feature_code":"PPL",
    "gn:name":"Shalu",
    "gn:population":0,
    "gn:timezone":"Asia/Taipei",
    "iso:country":"TW",
    "name:deu_x_preferred":[
        "Shalu"
    ],
    "name:nld_x_preferred":[
        "Shalu"
    ],
    "name:und_x_variant":[
        "Sha-lu-chuang",
        "Sha-lu-li",
        "Sha-lu"
    ],
    "name:zho_x_preferred":[
        "\u6c99\u9e7f"
    ],
    "wof:name":"Shalu",
    "wof:placetype":"locality"
},
  "geometry": {"coordinates":[120.5598,24.2359],"type":"Point"}
}