{
  "type": "Feature",
  "properties": {
    "gn:admin1_code":"04",
    "gn:admin2_code":"TNN",
    "gn:admin3_code":"R25",
    "gn:admin4_code":"67000250007.0",
    "gn:asciiname":"Beiliao",
    "gn:country_code":"TW",
    "gn:dem":86,
    "gn:feature_class":"P",
    "gn:feature_code":"PPL",
    "gn:name":"Beiliao",
    "gn:population":0,
    "gn:timezone":"Asia/Taipei",
    "iso:country":"TW",
    "name:und_x_variant":[
        "Pei-liao"
    ],
    "name:zho_x_preferred":[
        "\u5317\u5bee"
    ],
    "wof:name":"Beiliao",
    "wof:placetype":"locality"
},
  "geometry": {"coordinates":[120.49078,23.079],"type":"Point"}
}