{
  "type": "Feature",
  "properties": {
    "gn:admin1_code":"04",
    "gn:admin2_code":"NAN",
    "gn:admin3_code":"M02",
    "gn:admin4_code":"10008020015.0",
    "gn:asciiname":"Taomikengqiao",
    "gn:country_code":"TW",
    "gn:dem":626,
    "gn:feature_class":"P",
    "gn:feature_code":"PPL",
    "gn:name":"Taomikengqiao",
    "gn:population":0,
    "gn:timezone":"Asia/Taipei",
    "iso:country":"TW",
    "name:und_x_variant":[
        "T\u2019ao-mi-k\u2019eng-ch\u2019iao"
    ],
    "wof:name":"Taomikengqiao",
    "wof:placetype":"locality"
},
  "geometry": {"coordinates":[120.91667,23.95],"type":"Point"}
}