{
  "type": "Feature",
  "properties": {
    "gn:admin1_code":"3.0",
    "gn:admin2_code":"TPQ",
    "gn:admin3_code":"F32",
    "gn:admin4_code":"65000230010.0",
    "gn:asciiname":"Dakengkou",
    "gn:country_code":"TW",
    "gn:dem":21,
    "gn:feature_class":"P",
    "gn:feature_code":"PPL",
    "gn:name":"Dakengkou",
    "gn:population":0,
    "gn:timezone":"Asia/Taipei",
    "iso:country":"TW",
    "name:zho_x_preferred":[
        "\u5927\u5751\u53e3"
    ],
    "name:zho_x_variant":[
        "Ta-k\u2019eng-k\u2019ou"
    ],
    "wof:name":"Dakengkou",
    "wof:placetype":"locality"
},
  "geometry": {"coordinates":[121.39387000000001,25.13802],"type":"Point"}
}