{
  "type": "Feature",
  "properties": {
    "gn:admin1_code":"4.0",
    "gn:admin2_code":"TTT",
    "gn:admin3_code":"V13",
    "gn:admin4_code":"10014120006.0",
    "gn:asciiname":"Jiale",
    "gn:country_code":"TW",
    "gn:dem":332,
    "gn:feature_class":"P",
    "gn:feature_code":"PPL",
    "gn:name":"Jiale",
    "gn:population":0,
    "gn:timezone":"Asia/Taipei",
    "iso:country":"TW",
    "name:und_x_variant":[
        "Chia-na-lu-she",
        "Chia-na-tien-she",
        "Jiale",
        "Chia-le"
    ],
    "name:zho_x_preferred":[
        "\u52a0\u6a02"
    ],
    "wof:name":"Jiale",
    "wof:placetype":"locality"
},
  "geometry": {"coordinates":[121.13056,23.00833],"type":"Point"}
}