{
  "type": "Feature",
  "properties": {
    "gn:admin1_code":"4.0",
    "gn:admin2_code":"TXG",
    "gn:admin3_code":"B26",
    "gn:admin4_code":"66000260016.0",
    "gn:asciiname":"Fenggu",
    "gn:country_code":"TW",
    "gn:dem":148,
    "gn:feature_class":"P",
    "gn:feature_code":"PPL",
    "gn:name":"Fenggu",
    "gn:population":0,
    "gn:timezone":"Asia/Taipei",
    "iso:country":"TW",
    "name:und_x_variant":[
        "Feng-ku-ts\u2019un",
        "\u5cf0\u8c37",
        "Fonggu",
        "Fenggu",
        "Feng-ku"
    ],
    "wof:name":"Fenggu",
    "wof:placetype":"locality"
},
  "geometry": {"coordinates":[120.72216,24.03598],"type":"Point"}
}