{
  "type": "Feature",
  "properties": {
    "gn:admin1_code":"4.0",
    "gn:admin2_code":"TNN",
    "gn:admin3_code":"R07",
    "gn:admin4_code":"67000070016.0",
    "gn:asciiname":"Lingzilin",
    "gn:country_code":"TW",
    "gn:dem":4,
    "gn:feature_class":"P",
    "gn:feature_code":"PPL",
    "gn:name":"Lingzilin",
    "gn:population":0,
    "gn:timezone":"Asia/Taipei",
    "iso:country":"TW",
    "name:und_x_variant":[
        "Ling-tzu-lin",
        "Liang-lin",
        "Lin-tzu-ling",
        "Lingzilin",
        "Lingzihlin",
        "\u82d3\u5b50\u6797"
    ],
    "name:zho_x_preferred":[
        "\u82d3\u5b50\u6797"
    ],
    "wof:name":"Lingzilin",
    "wof:placetype":"locality"
},
  "geometry": {"coordinates":[120.23361,23.18444],"type":"Point"}
}