{
  "type": "Feature",
  "properties": {
    "gn:admin1_code":"4.0",
    "gn:admin2_code":"MIA",
    "gn:admin3_code":"K08",
    "gn:admin4_code":"10005120007.0",
    "gn:asciiname":"Yuanyangdao",
    "gn:country_code":"TW",
    "gn:dem":81,
    "gn:feature_class":"P",
    "gn:feature_code":"PPL",
    "gn:name":"Yuanyangdao",
    "gn:population":0,
    "gn:timezone":"Asia/Taipei",
    "iso:country":"TW",
    "name:zho_x_preferred":[
        "\u9d1b\u9d26\u5cf6"
    ],
    "name:zho_x_variant":[
        "Y\u00fcan-yang-tao"
    ],
    "wof:name":"Yuanyangdao",
    "wof:placetype":"locality"
},
  "geometry": {"coordinates":[120.89309,24.58407],"type":"Point"}
}