{
  "type": "Feature",
  "properties": {
    "iso:country":"TW",
    "name:eng_x_preferred":[
        "Zhongming"
    ],
    "name:eng_x_variant":[
        "Zhongming Village"
    ],
    "name:zho_tw_x_preferred":[
        "\u4e2d\u660e\u6751"
    ],
    "qs:name":"\u4e2d\u660e\u6751",
    "qs:name_adm0":"\u81fa\u7063",
    "qs:name_adm1":"\u5357\u6295\u7e23",
    "qs:photos":259,
    "qs:photos_1k":52,
    "qs:photos_9k":1,
    "qs:photos_9r":4,
    "qs:photos_all":259,
    "qs:photos_sr":5,
    "qs:placetype":"Town",
    "qs:pop_sr":"0",
    "wof:name":"Zhongming",
    "wof:placetype":"locality"
},
  "geometry": {"coordinates":[120.916042,23.875219],"type":"Point"}
}