{
  "type": "Feature",
  "properties": {
    "gn:admin1_code":"3.0",
    "gn:admin2_code":"TPQ",
    "gn:admin3_code":"F27",
    "gn:admin4_code":"65000100016.0",
    "gn:asciiname":"Xiaopingding",
    "gn:country_code":"TW",
    "gn:dem":255,
    "gn:feature_class":"P",
    "gn:feature_code":"PPL",
    "gn:name":"Xiaopingding",
    "gn:population":0,
    "gn:timezone":"Asia/Taipei",
    "iso:country":"TW",
    "name:und_x_variant":[
        "Siaopingding"
    ],
    "name:zho_x_preferred":[
        "\u5c0f\u576a\u9802"
    ],
    "name:zho_x_variant":[
        "Hsiao-p\u2019ing-ting"
    ],
    "wof:name":"Xiaopingding",
    "wof:placetype":"locality"
},
  "geometry": {"coordinates":[121.4845,25.15783],"type":"Point"}
}