{
  "type": "Feature",
  "properties": {
    "gn:admin1_code":"4.0",
    "gn:admin2_code":"NAN",
    "gn:admin3_code":"M03",
    "gn:admin4_code":"10008030015.0",
    "gn:asciiname":"Guoxizi",
    "gn:country_code":"TW",
    "gn:dem":79,
    "gn:feature_class":"P",
    "gn:feature_code":"PPL",
    "gn:name":"Guoxizi",
    "gn:population":0,
    "gn:timezone":"Asia/Taipei",
    "iso:country":"TW",
    "name:und_x_variant":[
        "Guosizih",
        "Kuo-hsi-tzu"
    ],
    "name:zho_x_preferred":[
        "\u904e\u6eaa\u4ed4"
    ],
    "wof:name":"Guoxizi",
    "wof:placetype":"locality"
},
  "geometry": {"coordinates":[120.66039000000001,23.99428],"type":"Point"}
}