{
  "type": "Feature",
  "properties": {
    "gn:admin1_code":"04",
    "gn:admin2_code":"YUN",
    "gn:admin3_code":"P08",
    "gn:admin4_code":"10009080005.0",
    "gn:asciiname":"Luzhuxiang",
    "gn:country_code":"TW",
    "gn:dem":31,
    "gn:feature_class":"P",
    "gn:feature_code":"PPL",
    "gn:name":"Luzhuxiang",
    "gn:population":0,
    "gn:timezone":"Asia/Taipei",
    "iso:country":"TW",
    "name:und_x_variant":[
        "Shang-i",
        "Lujhusiang",
        "Lu-chu-hsiang"
    ],
    "name:zho_x_preferred":[
        "Shang-i-ts\u2019un"
    ],
    "name:zho_x_variant":[
        "\u8606\u7af9\u5df7"
    ],
    "wof:name":"Luzhuxiang",
    "wof:placetype":"locality"
},
  "geometry": {"coordinates":[120.44728000000001,23.63875],"type":"Point"}
}