{
  "type": "Feature",
  "properties": {
    "gn:admin1_code":"04",
    "gn:admin2_code":"CYQ",
    "gn:admin3_code":"Q02",
    "gn:admin4_code":"10010020023.0",
    "gn:asciiname":"Zhuzijiao",
    "gn:country_code":"TW",
    "gn:dem":10,
    "gn:feature_class":"P",
    "gn:feature_code":"PPL",
    "gn:name":"Zhuzijiao",
    "gn:population":0,
    "gn:timezone":"Asia/Taipei",
    "iso:country":"TW",
    "name:und_x_variant":[
        "Wu-chu-tzu-chiao",
        "Te-chia-li",
        "Jhuzihjiao",
        "Te-chia",
        "Zhuzijiao",
        "Chu-tzu-chiao"
    ],
    "name:zho_x_preferred":[
        "Ch\u2019en-chu-tzu-chiao"
    ],
    "name:zho_x_variant":[
        "\u7af9\u5b50\u8173"
    ],
    "wof:name":"Zhuzijiao",
    "wof:placetype":"locality"
},
  "geometry": {"coordinates":[120.2466,23.4249],"type":"Point"}
}