{
  "type": "Feature",
  "properties": {
    "gn:admin1_code":"4.0",
    "gn:admin2_code":"NAN",
    "gn:admin3_code":"M06",
    "gn:admin4_code":"10008060015.0",
    "gn:asciiname":"Jingzitou",
    "gn:country_code":"TW",
    "gn:dem":322,
    "gn:feature_class":"P",
    "gn:feature_code":"PPL",
    "gn:name":"Jingzitou",
    "gn:population":0,
    "gn:timezone":"Asia/Taipei",
    "iso:country":"TW",
    "name:und_x_variant":[
        "Jingzihtou"
    ],
    "name:zho_x_preferred":[
        "\u4e95\u4ed4\u982d"
    ],
    "name:zho_x_variant":[
        "Ching-tzu-t\u2019ou"
    ],
    "wof:name":"Jingzitou",
    "wof:placetype":"locality"
},
  "geometry": {"coordinates":[120.6262,23.85942],"type":"Point"}
}