{
  "type": "Feature",
  "properties": {
    "gn:admin1_code":"4.0",
    "gn:admin2_code":"TAO",
    "gn:admin3_code":"H05",
    "gn:admin4_code":"68000050016.0",
    "gn:asciiname":"Zhonghaihu",
    "gn:country_code":"TW",
    "gn:dem":12,
    "gn:feature_class":"P",
    "gn:feature_code":"PPL",
    "gn:name":"Zhonghaihu",
    "gn:population":0,
    "gn:timezone":"Asia/Taipei",
    "iso:country":"TW",
    "name:und_x_variant":[
        "Hai-hu",
        "Zhonghaihu",
        "Jhonghaihu",
        "Chung-hai-hu"
    ],
    "name:zho_x_preferred":[
        "\u4e2d\u6d77\u6e56"
    ],
    "wof:name":"Zhonghaihu",
    "wof:placetype":"locality"
},
  "geometry": {"coordinates":[121.25483,25.11138],"type":"Point"}
}