{
  "type": "Feature",
  "properties": {
    "gn:admin1_code":"4.0",
    "gn:admin2_code":"TXG",
    "gn:admin3_code":"B27",
    "gn:admin4_code":"66000270014.0",
    "gn:asciiname":"Dongnankeng",
    "gn:country_code":"TW",
    "gn:dem":352,
    "gn:feature_class":"P",
    "gn:feature_code":"PPL",
    "gn:name":"Dongnankeng",
    "gn:population":0,
    "gn:timezone":"Asia/Taipei",
    "iso:country":"TW",
    "name:zho_x_preferred":[
        "\u6771\u5357\u5751"
    ],
    "name:zho_x_variant":[
        "Tung-nan-k\u2019eng"
    ],
    "wof:name":"Dongnankeng",
    "wof:placetype":"locality"
},
  "geometry": {"coordinates":[120.78100999999999,24.15701],"type":"Point"}
}