{
  "type": "Feature",
  "properties": {
    "gn:admin1_code":"3.0",
    "gn:admin2_code":"TPQ",
    "gn:admin3_code":"F25",
    "gn:admin4_code":"65000270014.0",
    "gn:asciiname":"Fenshui",
    "gn:country_code":"TW",
    "gn:dem":87,
    "gn:feature_class":"P",
    "gn:feature_code":"PPL",
    "gn:name":"Fenshui",
    "gn:population":0,
    "gn:timezone":"Asia/Taipei",
    "iso:country":"TW",
    "name:und_x_variant":[
        "Fenshuei",
        "Fen-shui"
    ],
    "name:zho_x_preferred":[
        "P\u2019en-shui"
    ],
    "name:zho_x_variant":[
        "\u6fc6\u6c34"
    ],
    "wof:name":"Fenshui",
    "wof:placetype":"locality"
},
  "geometry": {"coordinates":[121.62215999999999,25.26829],"type":"Point"}
}