{
  "type": "Feature",
  "properties": {
    "gn:admin1_code":"3.0",
    "gn:admin2_code":"TPQ",
    "gn:admin3_code":"F30",
    "gn:admin4_code":"65000210007.0",
    "gn:asciiname":"Hengshan",
    "gn:country_code":"TW",
    "gn:dem":167,
    "gn:feature_class":"P",
    "gn:feature_code":"PPL",
    "gn:name":"Hengshan",
    "gn:population":0,
    "gn:timezone":"Asia/Taipei",
    "iso:country":"TW",
    "name:ceb_x_preferred":[
        "Hengshan"
    ],
    "name:deu_x_preferred":[
        "Hengshan"
    ],
    "name:fra_x_preferred":[
        "Hengshan"
    ],
    "name:nor_x_preferred":[
        "Hengshan"
    ],
    "name:pol_x_preferred":[
        "Heng Shan"
    ],
    "name:rus_x_preferred":[
        "\u0425\u044d\u043d\u0448\u0430\u043d\u044c"
    ],
    "name:swe_x_preferred":[
        "Hengshan"
    ],
    "name:und_x_variant":[
        "San-chih-chuang",
        "Hengshan",
        "Heng-shan"
    ],
    "name:zho_x_preferred":[
        "Heng-shan-ts\u2019un"
    ],
    "name:zho_x_variant":[
        "\u6a2a\u5c71"
    ],
    "wof:name":"Hengshan",
    "wof:placetype":"locality"
},
  "geometry": {"coordinates":[121.52991000000002,25.25888],"type":"Point"}
}