{
  "type": "Feature",
  "properties": {
    "gn:admin1_code":"04",
    "gn:admin2_code":"TXG",
    "gn:admin3_code":"B27",
    "gn:admin4_code":"66000270015.0",
    "gn:asciiname":"Neizhujiao",
    "gn:country_code":"TW",
    "gn:dem":360,
    "gn:feature_class":"P",
    "gn:feature_code":"PPL",
    "gn:name":"Neizhujiao",
    "gn:population":0,
    "gn:timezone":"Asia/Taipei",
    "iso:country":"TW",
    "name:und_x_variant":[
        "Neijhujiao",
        "Nei-chu-chiao"
    ],
    "name:zho_x_preferred":[
        "\u5167\u7af9\u8173"
    ],
    "wof:name":"Neizhujiao",
    "wof:placetype":"locality"
},
  "geometry": {"coordinates":[120.80032,24.10271],"type":"Point"}
}