{
  "type": "Feature",
  "properties": {
    "gn:admin1_code":"2.0",
    "gn:admin2_code":"KHH",
    "gn:admin3_code":"E22",
    "gn:admin4_code":"64000220001.0",
    "gn:asciiname":"Dalubu",
    "gn:country_code":"TW",
    "gn:dem":120,
    "gn:feature_class":"P",
    "gn:feature_code":"PPL",
    "gn:name":"Dalubu",
    "gn:population":0,
    "gn:timezone":"Asia/Taipei",
    "iso:country":"TW",
    "name:und_x_variant":[
        "Ta-lu-pu"
    ],
    "name:zho_x_preferred":[
        "\u6253\u9e7f\u57d4"
    ],
    "wof:name":"Dalubu",
    "wof:placetype":"locality"
},
  "geometry": {"coordinates":[120.43971999999999,22.88306],"type":"Point"}
}