{
  "type": "Feature",
  "properties": {
    "gn:admin1_code":"04",
    "gn:admin2_code":"MIA",
    "gn:admin3_code":"K11",
    "gn:admin4_code":"10005150006.0",
    "gn:asciiname":"Sanbailiukeng",
    "gn:country_code":"TW",
    "gn:dem":47,
    "gn:feature_class":"P",
    "gn:feature_code":"PPL",
    "gn:name":"Sanbailiukeng",
    "gn:population":0,
    "gn:timezone":"Asia/Taipei",
    "iso:country":"TW",
    "name:und_x_variant":[
        "Sanbailioukeng",
        "Pai-lu"
    ],
    "name:zho_x_preferred":[
        "San-pia-liu-k\u2019an"
    ],
    "name:zho_x_variant":[
        "\u4e09\u767e\u516d\u5751",
        "San-pai-liu-k\u2019eng"
    ],
    "wof:name":"Sanbailiukeng",
    "wof:placetype":"locality"
},
  "geometry": {"coordinates":[120.90624,24.60502],"type":"Point"}
}