{
  "type": "Feature",
  "properties": {
    "gn:admin1_code":"4.0",
    "gn:admin2_code":"TXG",
    "gn:admin3_code":"B14",
    "gn:admin4_code":"66000140009.0",
    "gn:asciiname":"Chencuozhuang",
    "gn:country_code":"TW",
    "gn:dem":11,
    "gn:feature_class":"P",
    "gn:feature_code":"PPL",
    "gn:name":"Chencuozhuang",
    "gn:population":0,
    "gn:timezone":"Asia/Taipei",
    "iso:country":"TW",
    "name:und_x_variant":[
        "Chencuojhuang",
        "Chencuozhuang"
    ],
    "name:zho_x_preferred":[
        "Ch\u2019en-ts\u2019o"
    ],
    "name:zho_x_variant":[
        "\u9673\u539d\u838a",
        "Ch\u2019en-ts\u2019o-chuang"
    ],
    "wof:name":"Chencuozhuang",
    "wof:placetype":"locality"
},
  "geometry": {"coordinates":[120.54083,24.25278],"type":"Point"}
}