{
  "type": "Feature",
  "properties": {
    "gn:admin1_code":"04",
    "gn:admin2_code":"TAO",
    "gn:admin3_code":"H11",
    "gn:admin4_code":"68000110017.0",
    "gn:asciiname":"Benzigang",
    "gn:country_code":"TW",
    "gn:dem":13,
    "gn:feature_class":"P",
    "gn:feature_code":"PPL",
    "gn:name":"Benzigang",
    "gn:population":0,
    "gn:timezone":"Asia/Taipei",
    "iso:country":"TW",
    "name:und_x_variant":[
        "Pen-tzu-chiang",
        "Benzihgang",
        "Benzigang",
        "Pen-tzu-kang"
    ],
    "name:zho_x_preferred":[
        "\u7b28\u4ed4\u6e2f"
    ],
    "wof:name":"Benzigang",
    "wof:placetype":"locality"
},
  "geometry": {"coordinates":[121.02388999999999,24.97806],"type":"Point"}
}