{
  "type": "Feature",
  "properties": {
    "gn:admin1_code":"4.0",
    "gn:admin2_code":"TNN",
    "gn:admin3_code":"R03",
    "gn:admin4_code":"67000030024.0",
    "gn:asciiname":"Kanding",
    "gn:country_code":"TW",
    "gn:dem":50,
    "gn:feature_class":"P",
    "gn:feature_code":"PPL",
    "gn:name":"Kanding",
    "gn:population":0,
    "gn:timezone":"Asia/Taipei",
    "iso:country":"TW",
    "name:hak_x_preferred":[
        "Kham-t\u00e1ng-hi\u00f4ng"
    ],
    "name:jpn_x_preferred":[
        "\u30ab\u30f3\u9802\u90f7"
    ],
    "name:kor_x_preferred":[
        "\uce78\ub529\ud5a5"
    ],
    "name:und_x_variant":[
        "Kan-chai-tzu",
        "Kan-chai-li",
        "Kan-chai",
        "Kanding"
    ],
    "name:vie_x_preferred":[
        "Kh\u00e1m \u0110\u00ednh"
    ],
    "name:zho_x_preferred":[
        "\u5d01\u9802"
    ],
    "name:zho_x_variant":[
        "K\u2019an-ting",
        "\u5d01\u9802\u9109"
    ],
    "wof:name":"Kanding",
    "wof:placetype":"locality"
},
  "geometry": {"coordinates":[120.44,23.385],"type":"Point"}
}