{
  "type": "Feature",
  "properties": {
    "gn:admin1_code":"4.0",
    "gn:admin2_code":"MIA",
    "gn:admin3_code":"K04",
    "gn:admin4_code":"10005090011.0",
    "gn:asciiname":"Xinbeiliao",
    "gn:country_code":"TW",
    "gn:dem":430,
    "gn:feature_class":"P",
    "gn:feature_code":"PPL",
    "gn:name":"Xinbeiliao",
    "gn:population":0,
    "gn:timezone":"Asia/Taipei",
    "iso:country":"TW",
    "name:und_x_variant":[
        "Hsin-pei-liao",
        "Sinbeiliao",
        "Xinbeiliao"
    ],
    "name:zho_x_preferred":[
        "\u65b0\u5317\u5bee"
    ],
    "wof:name":"Xinbeiliao",
    "wof:placetype":"locality"
},
  "geometry": {"coordinates":[120.86575999999999,24.47906],"type":"Point"}
}