{
  "type": "Feature",
  "properties": {
    "gn:admin1_code":"4.0",
    "gn:admin2_code":"CYQ",
    "gn:admin3_code":"Q14",
    "gn:admin4_code":"10010130016.0",
    "gn:asciiname":"Sucuo",
    "gn:country_code":"TW",
    "gn:dem":89,
    "gn:feature_class":"P",
    "gn:feature_code":"PPL",
    "gn:name":"Sucuo",
    "gn:population":0,
    "gn:timezone":"Asia/Taipei",
    "iso:country":"TW",
    "name:zho_x_preferred":[
        "\u8607\u539d"
    ],
    "name:zho_x_variant":[
        "Su-ts\u2019o"
    ],
    "wof:name":"Sucuo",
    "wof:placetype":"locality"
},
  "geometry": {"coordinates":[120.50472000000001,23.41194],"type":"Point"}
}