{
  "type": "Feature",
  "properties": {
    "gn:admin1_code":"4.0",
    "gn:admin2_code":"CYQ",
    "gn:admin3_code":"Q07",
    "gn:admin4_code":"10010070019.0",
    "gn:asciiname":"Xinjiezhuangzi",
    "gn:country_code":"TW",
    "gn:dem":13,
    "gn:feature_class":"P",
    "gn:feature_code":"PPL",
    "gn:name":"Xinjiezhuangzi",
    "gn:population":0,
    "gn:timezone":"Asia/Taipei",
    "iso:country":"TW",
    "name:und_x_variant":[
        "Sinjiejhuangzih",
        "Hsin-chieh-chuang-tzu"
    ],
    "name:zho_x_preferred":[
        "\u65b0\u7d50\u838a\u5b50"
    ],
    "wof:name":"Xinjiezhuangzi",
    "wof:placetype":"locality"
},
  "geometry": {"coordinates":[120.30631,23.5187],"type":"Point"}
}