{
  "type": "Feature",
  "properties": {
    "gn:admin1_code":"04",
    "gn:admin2_code":"TNN",
    "gn:admin3_code":"R17",
    "gn:admin4_code":"67000130004.0",
    "gn:asciiname":"Ergangzi",
    "gn:country_code":"TW",
    "gn:dem":7,
    "gn:feature_class":"P",
    "gn:feature_code":"PPL",
    "gn:name":"Ergangzi",
    "gn:population":0,
    "gn:timezone":"Asia/Taipei",
    "iso:country":"TW",
    "name:und_x_variant":[
        "San-tzu-chiang",
        "Erh-chiang-tzu",
        "San-tzu-kang",
        "San-tzu-chuang",
        "Ergangzih",
        "Ergangzi",
        "Erh-tzu-kang",
        "Erh-kang-tzu"
    ],
    "name:zho_x_preferred":[
        "\u4e8c\u6e2f\u4ed4"
    ],
    "wof:name":"Ergangzi",
    "wof:placetype":"locality"
},
  "geometry": {"coordinates":[120.19141999999999,23.26396],"type":"Point"}
}