{
  "type": "Feature",
  "properties": {
    "gn:admin1_code":"4.0",
    "gn:admin2_code":"TXG",
    "gn:admin3_code":"B23",
    "gn:admin4_code":"66000230016.0",
    "gn:asciiname":"Xiweiliao",
    "gn:country_code":"TW",
    "gn:dem":40,
    "gn:feature_class":"P",
    "gn:feature_code":"PPL",
    "gn:name":"Xiweiliao",
    "gn:population":0,
    "gn:timezone":"Asia/Taipei",
    "iso:country":"TW",
    "name:und_x_variant":[
        "Ch\u2019i-wei-ts\u2019un",
        "Hsi-wei-ts\u2019un",
        "Ch\u2019i-wei-liao",
        "Siweiliao",
        "Xiweiliao",
        "Hsi-wei-liao"
    ],
    "name:zho_x_preferred":[
        "\u6eaa\u5c3e\u5bee"
    ],
    "wof:name":"Xiweiliao",
    "wof:placetype":"locality"
},
  "geometry": {"coordinates":[120.6285,24.0543],"type":"Point"}
}