{
  "type": "Feature",
  "properties": {
    "gn:admin1_code":"4.0",
    "gn:admin2_code":"TNN",
    "gn:admin3_code":"R03",
    "gn:admin4_code":"67000030006.0",
    "gn:asciiname":"Zhuangzi",
    "gn:country_code":"TW",
    "gn:dem":41,
    "gn:feature_class":"P",
    "gn:feature_code":"PPL",
    "gn:name":"Zhuangzi",
    "gn:population":0,
    "gn:timezone":"Asia/Taipei",
    "iso:country":"TW",
    "name:oci_x_preferred":[
        "Zhuangzi"
    ],
    "name:pol_x_preferred":[
        "Zhuangzi"
    ],
    "name:ukr_x_preferred":[
        "\u0427\u0436\u0443\u0430\u043d-\u0446\u0437\u0438"
    ],
    "name:und_x_variant":[
        "Jhuangzih",
        "Chuang-tzu"
    ],
    "name:zho_x_preferred":[
        "\u838a\u5b50"
    ],
    "wof:name":"Zhuangzi",
    "wof:placetype":"locality"
},
  "geometry": {"coordinates":[120.42306000000001,23.34583],"type":"Point"}
}