{
  "type": "Feature",
  "properties": {
    "gn:admin1_code":"3.0",
    "gn:admin2_code":"TPQ",
    "gn:admin3_code":"F24",
    "gn:admin4_code":"65000260003.0",
    "gn:asciiname":"Zhuweizi",
    "gn:country_code":"TW",
    "gn:dem":185,
    "gn:feature_class":"P",
    "gn:feature_code":"PPL",
    "gn:name":"Zhuweizi",
    "gn:population":0,
    "gn:timezone":"Asia/Taipei",
    "iso:country":"TW",
    "name:und_x_variant":[
        "Jhuweizih",
        "Chu-wei-tzu"
    ],
    "name:zho_x_preferred":[
        "\u7af9\u570d\u4ed4"
    ],
    "wof:name":"Zhuweizi",
    "wof:placetype":"locality"
},
  "geometry": {"coordinates":[121.93628,25.00151],"type":"Point"}
}