{
  "type": "Feature",
  "properties": {
    "gn:admin1_code":"4.0",
    "gn:admin2_code":"HSZ",
    "gn:admin3_code":"J06",
    "gn:admin4_code":"10004050020.0",
    "gn:asciiname":"Zhugaowu",
    "gn:country_code":"TW",
    "gn:dem":99,
    "gn:feature_class":"P",
    "gn:feature_code":"PPL",
    "gn:name":"Zhugaowu",
    "gn:population":0,
    "gn:timezone":"Asia/Taipei",
    "iso:country":"TW",
    "name:und_x_variant":[
        "Jhugaowu",
        "Zhugaowu",
        "Chu-kao-wu"
    ],
    "name:zho_x_preferred":[
        "\u7af9\u9ad8\u5c4b"
    ],
    "wof:name":"Zhugaowu",
    "wof:placetype":"locality"
},
  "geometry": {"coordinates":[121.02388999999999,24.86194],"type":"Point"}
}