{
  "type": "Feature",
  "properties": {
    "gn:admin1_code":"4.0",
    "gn:admin2_code":"HSZ",
    "gn:admin3_code":"J13",
    "gn:admin4_code":"10004110001.0",
    "gn:asciiname":"Xi'emei",
    "gn:country_code":"TW",
    "gn:dem":95,
    "gn:feature_class":"P",
    "gn:feature_code":"PPL",
    "gn:name":"Xi\u2019emei",
    "gn:population":0,
    "gn:timezone":"Asia/Taipei",
    "iso:country":"TW",
    "name:und_x_variant":[
        "Hsi-o-mei"
    ],
    "name:zho_x_preferred":[
        "\u897f\u5ce8\u7709"
    ],
    "name:zho_x_variant":[
        "Xi\u2019emei",
        "Si\u2019emei"
    ],
    "wof:name":"Xi'emei",
    "wof:placetype":"locality"
},
  "geometry": {"coordinates":[121.01778,24.69111],"type":"Point"}
}