{
  "type": "Feature",
  "properties": {
    "gn:admin1_code":"4.0",
    "gn:admin2_code":"TXG",
    "gn:admin3_code":"B29",
    "gn:admin4_code":"66000290003.0",
    "gn:asciiname":"Guguan",
    "gn:country_code":"TW",
    "gn:dem":738,
    "gn:feature_class":"P",
    "gn:feature_code":"PPL",
    "gn:name":"Guguan",
    "gn:population":0,
    "gn:timezone":"Asia/Taipei",
    "iso:country":"TW",
    "name:ces_x_preferred":[
        "Guguan"
    ],
    "name:cha_x_preferred":[
        "Guguan"
    ],
    "name:deu_x_preferred":[
        "Guguan"
    ],
    "name:est_x_preferred":[
        "Guguan"
    ],
    "name:fas_x_preferred":[
        "\u06af\u0648\u06af\u0648\u0627\u0646"
    ],
    "name:fin_x_preferred":[
        "Guguan"
    ],
    "name:fra_x_preferred":[
        "Guguan"
    ],
    "name:glg_x_preferred":[
        "Guguan"
    ],
    "name:ita_x_preferred":[
        "Guguan"
    ],
    "name:jpn_x_preferred":[
        "\u30b0\u30b0\u30a2\u30f3\u5cf6"
    ],
    "name:nld_x_preferred":[
        "Guguan"
    ],
    "name:pol_x_preferred":[
        "Guguan"
    ],
    "name:por_x_preferred":[
        "Guguan"
    ],
    "name:rus_x_preferred":[
        "\u0413\u0443\u0433\u0443\u0430\u043d"
    ],
    "name:slk_x_preferred":[
        "Guguan"
    ],
    "name:spa_x_preferred":[
        "Guguan"
    ],
    "name:swe_x_preferred":[
        "Guguan"
    ],
    "name:und_x_variant":[
        "Ku-kuan"
    ],
    "name:urd_x_preferred":[
        "\u06af\u0648\u06af\u0648\u0627\u0646"
    ],
    "name:zho_x_preferred":[
        "\u8c37\u95dc"
    ],
    "wof:name":"Guguan",
    "wof:placetype":"locality"
},
  "geometry": {"coordinates":[121.00715,24.20334],"type":"Point"}
}