{
  "type": "Feature",
  "properties": {
    "gn:admin1_code":"4.0",
    "gn:admin2_code":"TXG",
    "gn:admin3_code":"B29",
    "gn:admin4_code":"66000290003.0",
    "gn:asciiname":"Guguan",
    "gn:country_code":"TW",
    "gn:dem":738,
    "gn:feature_class":"P",
    "gn:feature_code":"PPL",
    "gn:name":"Guguan",
    "gn:population":0,
    "gn:timezone":"Asia/Taipei",
    "iso:country":"TW",
    "name:und_x_variant":[
        "Ku-kuan"
    ],
    "name:zho_x_preferred":[
        "\u8c37\u95dc"
    ],
    "wof:name":"Guguan",
    "wof:placetype":"locality"
},
  "geometry": {"coordinates":[121.00715,24.20334],"type":"Point"}
}