{
  "type": "Feature",
  "properties": {
    "gn:admin1_code":"4.0",
    "gn:admin2_code":"ILA",
    "gn:admin3_code":"G08",
    "gn:admin4_code":"10002080014.0",
    "gn:asciiname":"Tanliaokeng",
    "gn:country_code":"TW",
    "gn:dem":32,
    "gn:feature_class":"P",
    "gn:feature_code":"PPL",
    "gn:name":"Tanliaokeng",
    "gn:population":0,
    "gn:timezone":"Asia/Taipei",
    "iso:country":"TW",
    "name:zho_x_preferred":[
        "\u70ad\u5bee\u5751"
    ],
    "name:zho_x_variant":[
        "T\u2019an-liao-k\u2019eng"
    ],
    "wof:name":"Tanliaokeng",
    "wof:placetype":"locality"
},
  "geometry": {"coordinates":[121.75147,24.63071],"type":"Point"}
}