{
  "type": "Feature",
  "properties": {
    "gn:admin1_code":"03",
    "gn:admin2_code":"TPQ",
    "gn:admin3_code":"F26",
    "gn:admin4_code":"65000280001.0",
    "gn:asciiname":"Wanli",
    "gn:country_code":"TW",
    "gn:dem":14,
    "gn:feature_class":"P",
    "gn:feature_code":"PPL",
    "gn:name":"Wanli",
    "gn:population":0,
    "gn:timezone":"Asia/Taipei",
    "iso:country":"TW",
    "name:und_x_variant":[
        "Wan-li"
    ],
    "name:zho_x_preferred":[
        "Ma-su-chiang-k\u2019ou"
    ],
    "name:zho_x_variant":[
        "Wan-li-ts\u2019un",
        "Ma-lien-chiang-k\u2019ou",
        "\u842c\u91cc"
    ],
    "wof:name":"Wanli",
    "wof:placetype":"locality"
},
  "geometry": {"coordinates":[121.68959,25.17933],"type":"Point"}
}