{
  "type": "Feature",
  "properties": {
    "gn:admin1_code":"4.0",
    "gn:admin2_code":"CHA",
    "gn:admin3_code":"N08",
    "gn:admin4_code":"10007200024.0",
    "gn:asciiname":"Qiaozitou",
    "gn:country_code":"TW",
    "gn:dem":20,
    "gn:feature_class":"P",
    "gn:feature_code":"PPL",
    "gn:name":"Qiaozitou",
    "gn:population":0,
    "gn:timezone":"Asia/Taipei",
    "iso:country":"TW",
    "name:und_x_variant":[
        "Ciaozihtou"
    ],
    "name:zho_x_preferred":[
        "\u6a4b\u5b50\u982d"
    ],
    "name:zho_x_variant":[
        "Ch\u2019iao-tzu-t\u2019ou"
    ],
    "wof:name":"Qiaozitou",
    "wof:placetype":"locality"
},
  "geometry": {"coordinates":[120.4342,23.8966],"type":"Point"}
}