{
  "type": "Feature",
  "properties": {
    "gn:admin1_code":"2.0",
    "gn:admin2_code":"KHH",
    "gn:admin3_code":"E38",
    "gn:admin4_code":"64000380003.0",
    "gn:asciiname":"Honghuazi",
    "gn:country_code":"TW",
    "gn:dem":663,
    "gn:feature_class":"P",
    "gn:feature_code":"PPL",
    "gn:name":"Honghuazi",
    "gn:population":0,
    "gn:timezone":"Asia/Taipei",
    "iso:country":"TW",
    "name:und_x_variant":[
        "An-wan-na-she",
        "Honghuazi",
        "An-wa-na",
        "Honghuazih",
        "Hung-hua-tzu"
    ],
    "name:zho_x_preferred":[
        "\u7d05\u82b1\u5b50"
    ],
    "wof:name":"Honghuazi",
    "wof:placetype":"locality"
},
  "geometry": {"coordinates":[120.67889,23.20583],"type":"Point"}
}