{
  "type": "Feature",
  "properties": {
    "gn:admin1_code":"4.0",
    "gn:admin2_code":"MIA",
    "gn:admin3_code":"K03",
    "gn:admin4_code":"10005030014.0",
    "gn:asciiname":"Hanpizi",
    "gn:country_code":"TW",
    "gn:dem":41,
    "gn:feature_class":"P",
    "gn:feature_code":"PPL",
    "gn:name":"Hanpizi",
    "gn:population":0,
    "gn:timezone":"Asia/Taipei",
    "iso:country":"TW",
    "name:und_x_variant":[
        "Hanpizih",
        "Hanpizi"
    ],
    "name:zho_x_preferred":[
        "\u65f1\u57e4\u4ed4"
    ],
    "name:zho_x_variant":[
        "Han-p\u2019i-tzu"
    ],
    "wof:name":"Hanpizi",
    "wof:placetype":"locality"
},
  "geometry": {"coordinates":[120.71333,24.49194],"type":"Point"}
}