{
  "type": "Feature",
  "properties": {
    "gn:admin1_code":"4.0",
    "gn:admin2_code":"MIA",
    "gn:admin3_code":"K04",
    "gn:admin4_code":"10005090012.0",
    "gn:asciiname":"Yaocuo",
    "gn:country_code":"TW",
    "gn:dem":70,
    "gn:feature_class":"P",
    "gn:feature_code":"PPL",
    "gn:name":"Yaocuo",
    "gn:population":0,
    "gn:timezone":"Asia/Taipei",
    "iso:country":"TW",
    "name:und_x_variant":[
        "Shui-wei",
        "Hsi-mei",
        "Yeh-wu",
        "Yaocuo"
    ],
    "name:zho_x_preferred":[
        "Yeh-ts\u2019o"
    ],
    "name:zho_x_variant":[
        "\u85e5\u539d",
        "Yao-ts\u2019o"
    ],
    "wof:name":"Yaocuo",
    "wof:placetype":"locality"
},
  "geometry": {"coordinates":[120.81726999999999,24.52462],"type":"Point"}
}