{
  "type": "Feature",
  "properties": {
    "gn:admin1_code":"4.0",
    "gn:admin2_code":"CHA",
    "gn:admin3_code":"N11",
    "gn:admin4_code":"10007060013.0",
    "gn:asciiname":"Sanhe",
    "gn:country_code":"TW",
    "gn:dem":12,
    "gn:feature_class":"P",
    "gn:feature_code":"PPL",
    "gn:name":"Sanhe",
    "gn:population":0,
    "gn:timezone":"Asia/Taipei",
    "iso:country":"TW",
    "name:und_x_variant":[
        "Chu-wei-tzu",
        "Sanhe",
        "San-ho"
    ],
    "name:zho_x_preferred":[
        "San-ho-ts\u2019un"
    ],
    "name:zho_x_variant":[
        "\u4e09\u548c"
    ],
    "wof:name":"Sanhe",
    "wof:placetype":"locality"
},
  "geometry": {"coordinates":[120.40971999999999,24.00833],"type":"Point"}
}