{
  "type": "Feature",
  "properties": {
    "gn:admin1_code":"03",
    "gn:admin2_code":"TPQ",
    "gn:admin3_code":"F07",
    "gn:admin4_code":"65000060017.0",
    "gn:asciiname":"Damaobu",
    "gn:country_code":"TW",
    "gn:dem":32,
    "gn:feature_class":"P",
    "gn:feature_code":"PPL",
    "gn:name":"Damaobu",
    "gn:population":0,
    "gn:timezone":"Asia/Taipei",
    "iso:country":"TW",
    "name:und_x_variant":[
        "Ta-mao-pu"
    ],
    "name:zho_x_preferred":[
        "\u5927\u8305\u57d4"
    ],
    "wof:name":"Damaobu",
    "wof:placetype":"locality"
},
  "geometry": {"coordinates":[121.49728,24.95479],"type":"Point"}
}