{
  "type": "Feature",
  "properties": {
    "gn:admin1_code":"04",
    "gn:admin2_code":"CHA",
    "gn:admin3_code":"N22",
    "gn:admin4_code":"10007220005.0",
    "gn:asciiname":"Cuozi",
    "gn:country_code":"TW",
    "gn:dem":21,
    "gn:feature_class":"P",
    "gn:feature_code":"PPL",
    "gn:name":"Cuozi",
    "gn:population":0,
    "gn:timezone":"Asia/Taipei",
    "iso:country":"TW",
    "name:und_x_variant":[
        "Cuozih"
    ],
    "name:zho_x_preferred":[
        "\u539d\u5b50"
    ],
    "name:zho_x_variant":[
        "Ts\u2019o-tzu"
    ],
    "wof:name":"Cuozi",
    "wof:placetype":"locality"
},
  "geometry": {"coordinates":[120.44998,23.90802],"type":"Point"}
}