{
  "type": "Feature",
  "properties": {
    "gn:admin1_code":"4.0",
    "gn:admin2_code":"TAO",
    "gn:admin3_code":"H05",
    "gn:admin4_code":"68000050023.0",
    "gn:asciiname":"Xishibu",
    "gn:country_code":"TW",
    "gn:dem":52,
    "gn:feature_class":"P",
    "gn:feature_code":"PPL",
    "gn:name":"Xishibu",
    "gn:population":0,
    "gn:timezone":"Asia/Taipei",
    "iso:country":"TW",
    "name:und_x_variant":[
        "Sishihbu",
        "Hsi-shih-pu"
    ],
    "name:zho_x_preferred":[
        "\u897f\u52e2\u57d4"
    ],
    "wof:name":"Xishibu",
    "wof:placetype":"locality"
},
  "geometry": {"coordinates":[121.24048000000001,25.04332],"type":"Point"}
}