{
  "type": "Feature",
  "properties": {
    "gn:admin1_code":"4.0",
    "gn:admin2_code":"TAO",
    "gn:admin3_code":"H03",
    "gn:admin4_code":"68000020049.0",
    "gn:asciiname":"Liangwu",
    "gn:country_code":"TW",
    "gn:dem":88,
    "gn:feature_class":"P",
    "gn:feature_code":"PPL",
    "gn:name":"Liangwu",
    "gn:population":0,
    "gn:timezone":"Asia/Taipei",
    "iso:country":"TW",
    "name:und_x_variant":[
        "Liang-wu"
    ],
    "name:zho_x_preferred":[
        "\u6881\u5c4b"
    ],
    "wof:name":"Liangwu",
    "wof:placetype":"locality"
},
  "geometry": {"coordinates":[121.17055999999999,24.99611],"type":"Point"}
}