{
  "type": "Feature",
  "properties": {
    "gn:country":"TW",
    "iso:country":"TW",
    "qs:name":"\u6e2f\u53e3\u6751",
    "qs:name_adm0":"\u81fa\u7063",
    "qs:name_adm1":"\u82b1\u84ee\u7e23",
    "qs:photos":676,
    "qs:photos_1k":137,
    "qs:photos_9k":3,
    "qs:photos_9r":5,
    "qs:photos_all":676,
    "qs:photos_sr":8,
    "qs:placetype":"Town",
    "qs:pop_sr":"0",
    "wd:wordcount":167,
    "wof:name":"\u6e2f\u53e3\u6751",
    "wof:placetype":"locality"
},
  "geometry": {"coordinates":[121.508402,23.491272],"type":"Point"}
}