{
  "type": "Feature",
  "properties": {
    "gn:admin1_code":"04",
    "gn:admin2_code":"MIA",
    "gn:admin3_code":"K03",
    "gn:admin4_code":"10005030014.0",
    "gn:asciiname":"Sanzhangxun",
    "gn:country_code":"TW",
    "gn:dem":46,
    "gn:feature_class":"P",
    "gn:feature_code":"PPL",
    "gn:name":"Sanzhangxun",
    "gn:population":0,
    "gn:timezone":"Asia/Taipei",
    "iso:country":"TW",
    "name:und_x_variant":[
        "Sanjhangsyun",
        "Sanzhangxun",
        "San-chang"
    ],
    "name:zho_x_preferred":[
        "\u4e09\u5f35\u85b0"
    ],
    "name:zho_x_variant":[
        "San-chang-hs\u00fcn"
    ],
    "wof:name":"Sanzhangxun",
    "wof:placetype":"locality"
},
  "geometry": {"coordinates":[120.71593,24.50626],"type":"Point"}
}