{
  "type": "Feature",
  "properties": {
    "gn:admin1_code":"4.0",
    "gn:admin2_code":"CHA",
    "gn:admin3_code":"N13",
    "gn:admin4_code":"10007080002.0",
    "gn:asciiname":"Fanzitun",
    "gn:country_code":"TW",
    "gn:dem":24,
    "gn:feature_class":"P",
    "gn:feature_code":"PPL",
    "gn:name":"Fanzitun",
    "gn:population":0,
    "gn:timezone":"Asia/Taipei",
    "iso:country":"TW",
    "name:und_x_variant":[
        "Fanzihtun",
        "Fan-tzu-t\u2019un"
    ],
    "name:zho_x_preferred":[
        "\u756a\u4ed4\u5c6f"
    ],
    "name:zho_x_variant":[
        "Fan-tzu-t\u2019un"
    ],
    "wof:name":"Fanzitun",
    "wof:placetype":"locality"
},
  "geometry": {"coordinates":[120.54566,24.01788],"type":"Point"}
}