{
  "type": "Feature",
  "properties": {
    "gn:admin1_code":"04",
    "gn:admin2_code":"CHA",
    "gn:admin3_code":"N16",
    "gn:admin4_code":"10007140012.0",
    "gn:asciiname":"Buxinzi",
    "gn:country_code":"TW",
    "gn:dem":15,
    "gn:feature_class":"P",
    "gn:feature_code":"PPL",
    "gn:name":"Buxinzi",
    "gn:population":0,
    "gn:timezone":"Asia/Taipei",
    "iso:country":"TW",
    "name:und_x_variant":[
        "Businzih",
        "Buxinzi",
        "Pu-hsin-tzu"
    ],
    "name:zho_x_preferred":[
        "\u57d4\u5fc3\u4ed4"
    ],
    "wof:name":"Buxinzi",
    "wof:placetype":"locality"
},
  "geometry": {"coordinates":[120.45111,24.00583],"type":"Point"}
}