{
  "type": "Feature",
  "properties": {
    "gn:admin1_code":"02",
    "gn:admin2_code":"KHH",
    "gn:admin3_code":"E14",
    "gn:admin4_code":"64000140002.0",
    "gn:asciiname":"Tianliao",
    "gn:country_code":"TW",
    "gn:dem":16,
    "gn:feature_class":"P",
    "gn:feature_code":"PPL",
    "gn:name":"Tianliao",
    "gn:population":0,
    "gn:timezone":"Asia/Taipei",
    "iso:country":"TW",
    "name:und_x_variant":[
        "Tianliao"
    ],
    "name:zho_x_preferred":[
        "T\u2019ien-liao"
    ],
    "name:zho_x_variant":[
        "\u7530\u5bee"
    ],
    "wof:name":"Tianliao",
    "wof:placetype":"locality"
},
  "geometry": {"coordinates":[120.3937,22.58975],"type":"Point"}
}