{
  "type": "Feature",
  "properties": {
    "gn:admin1_code":"4.0",
    "gn:admin2_code":"PIF",
    "gn:admin3_code":"T23",
    "gn:admin4_code":"10013230007.0",
    "gn:asciiname":"Maolanyi",
    "gn:country_code":"TW",
    "gn:dem":22,
    "gn:feature_class":"P",
    "gn:feature_code":"PPL",
    "gn:name":"Maolanyi",
    "gn:population":0,
    "gn:timezone":"Asia/Taipei",
    "iso:country":"TW",
    "name:und_x_variant":[
        "Mao-lan-i"
    ],
    "name:zho_x_preferred":[
        "\u8c93\u85cd\u9038"
    ],
    "wof:name":"Maolanyi",
    "wof:placetype":"locality"
},
  "geometry": {"coordinates":[120.73860999999999,22.0525],"type":"Point"}
}