{
  "type": "Feature",
  "properties": {
    "gn:admin1_code":"04",
    "gn:admin2_code":"HSZ",
    "gn:admin3_code":"J04",
    "gn:admin4_code":"10004030016.0",
    "gn:asciiname":"Shimen",
    "gn:country_code":"TW",
    "gn:dem":165,
    "gn:feature_class":"P",
    "gn:feature_code":"PPL",
    "gn:name":"Shimen",
    "gn:population":0,
    "gn:timezone":"Asia/Taipei",
    "iso:country":"TW",
    "name:ceb_x_preferred":[
        "Shimen"
    ],
    "name:deu_x_preferred":[
        "Shimen"
    ],
    "name:nor_x_preferred":[
        "Shimen"
    ],
    "name:und_x_variant":[
        "Shihmen",
        "Shih-men"
    ],
    "name:zho_x_preferred":[
        "\u77f3\u9580"
    ],
    "wof:name":"Shimen",
    "wof:placetype":"locality"
},
  "geometry": {"coordinates":[121.11917,24.86167],"type":"Point"}
}