{
  "type": "Feature",
  "properties": {
    "gn:admin1_code":"4.0",
    "gn:admin2_code":"ILA",
    "gn:admin3_code":"G11",
    "gn:admin4_code":"10002110010.0",
    "gn:asciiname":"Liumao'an",
    "gn:country_code":"TW",
    "gn:dem":582,
    "gn:feature_class":"P",
    "gn:feature_code":"PPL",
    "gn:name":"Liumao\u2019an",
    "gn:population":0,
    "gn:timezone":"Asia/Taipei",
    "iso:country":"TW",
    "name:und_x_variant":[
        "Liu-mao-an-she",
        "Mao-an",
        "Liu-mao-an"
    ],
    "name:zho_x_preferred":[
        "\u7559\u8302\u5b89"
    ],
    "name:zho_x_variant":[
        "Lioumao\u2019an",
        "Liumao\u2019an"
    ],
    "wof:name":"Liumao'an",
    "wof:placetype":"locality"
},
  "geometry": {"coordinates":[121.45083,24.53278],"type":"Point"}
}