{
  "type": "Feature",
  "properties": {
    "gn:admin1_code":"3.0",
    "gn:admin2_code":"TPQ",
    "gn:admin3_code":"F27",
    "gn:admin4_code":"65000100004.0",
    "gn:asciiname":"Qianzhouzi",
    "gn:country_code":"TW",
    "gn:dem":13,
    "gn:feature_class":"P",
    "gn:feature_code":"PPL",
    "gn:name":"Qianzhouzi",
    "gn:population":0,
    "gn:timezone":"Asia/Taipei",
    "iso:country":"TW",
    "name:und_x_variant":[
        "Cianjhouzih",
        "Qianzhouzi"
    ],
    "name:zho_x_preferred":[
        "\u524d\u6d32\u5b50"
    ],
    "name:zho_x_variant":[
        "Ch\u2019ien-chou-tzu"
    ],
    "wof:name":"Qianzhouzi",
    "wof:placetype":"locality"
},
  "geometry": {"coordinates":[121.44266,25.22219],"type":"Point"}
}