{
  "type": "Feature",
  "properties": {
    "gn:admin1_code":"4.0",
    "gn:admin2_code":"PIF",
    "gn:admin3_code":"T17",
    "gn:admin4_code":"10013170001.0",
    "gn:asciiname":"Xiawayao",
    "gn:country_code":"TW",
    "gn:dem":6,
    "gn:feature_class":"P",
    "gn:feature_code":"PPL",
    "gn:name":"Xiawayao",
    "gn:population":0,
    "gn:timezone":"Asia/Taipei",
    "iso:country":"TW",
    "name:und_x_variant":[
        "Hsia-wa-yao",
        "Xiawayao",
        "Siawayao"
    ],
    "name:zho_x_preferred":[
        "\u4e0b\u74e6\u78d8"
    ],
    "wof:name":"Xiawayao",
    "wof:placetype":"locality"
},
  "geometry": {"coordinates":[120.47333999999999,22.54658],"type":"Point"}
}