{
  "type": "Feature",
  "properties": {
    "gn:admin1_code":"4.0",
    "gn:admin2_code":"NAN",
    "gn:admin3_code":"M04",
    "gn:admin4_code":"10008040010.0",
    "gn:asciiname":"Kezikeng",
    "gn:country_code":"TW",
    "gn:dem":138,
    "gn:feature_class":"P",
    "gn:feature_code":"PPL",
    "gn:name":"Kezikeng",
    "gn:population":0,
    "gn:timezone":"Asia/Taipei",
    "iso:country":"TW",
    "name:und_x_variant":[
        "Kezihkeng",
        "Kezikeng"
    ],
    "name:zho_x_preferred":[
        "\u67ef\u5b50\u5751"
    ],
    "name:zho_x_variant":[
        "Hsia-k\u2019an",
        "K\u2019o-tzu-k\u2019eng"
    ],
    "wof:name":"Kezikeng",
    "wof:placetype":"locality"
},
  "geometry": {"coordinates":[120.66417,23.74333],"type":"Point"}
}