{
  "type": "Feature",
  "properties": {
    "gn:admin1_code":"04",
    "gn:admin2_code":"TAO",
    "gn:admin3_code":"H03",
    "gn:admin4_code":"68000020043.0",
    "gn:asciiname":"Shipo",
    "gn:country_code":"TW",
    "gn:dem":116,
    "gn:feature_class":"P",
    "gn:feature_code":"PPL",
    "gn:name":"Shipo",
    "gn:population":0,
    "gn:timezone":"Asia/Taipei",
    "iso:country":"TW",
    "name:und_x_variant":[
        "Shihpo",
        "Shipo"
    ],
    "name:zho_x_preferred":[
        "\u77f3\u7834"
    ],
    "name:zho_x_variant":[
        "Shih-p\u2019o"
    ],
    "wof:name":"Shipo",
    "wof:placetype":"locality"
},
  "geometry": {"coordinates":[121.16639000000001,24.97778],"type":"Point"}
}