{
  "type": "Feature",
  "properties": {
    "gn:admin1_code":"4.0",
    "gn:admin2_code":"TNN",
    "gn:admin3_code":"R30",
    "gn:admin4_code":"67000300005.0",
    "gn:asciiname":"Xialiaozi",
    "gn:country_code":"TW",
    "gn:dem":64,
    "gn:feature_class":"P",
    "gn:feature_code":"PPL",
    "gn:name":"Xialiaozi",
    "gn:population":0,
    "gn:timezone":"Asia/Taipei",
    "iso:country":"TW",
    "name:und_x_variant":[
        "Sialiaozih",
        "Hsia-liao-tzu"
    ],
    "name:zho_x_preferred":[
        "\u4e0b\u5bee\u4ed4"
    ],
    "wof:name":"Xialiaozi",
    "wof:placetype":"locality"
},
  "geometry": {"coordinates":[120.41556,22.92139],"type":"Point"}
}