{
  "type": "Feature",
  "properties": {
    "gn:admin1_code":"02",
    "gn:admin2_code":"KHH",
    "gn:admin3_code":"E15",
    "gn:admin4_code":"64000150015.0",
    "gn:asciiname":"Sanjiaoliao",
    "gn:country_code":"TW",
    "gn:dem":29,
    "gn:feature_class":"P",
    "gn:feature_code":"PPL",
    "gn:name":"Sanjiaoliao",
    "gn:population":0,
    "gn:timezone":"Asia/Taipei",
    "iso:country":"TW",
    "name:und_x_variant":[
        "San-chiao-liao",
        "\u4e09\u8173\u5bee",
        "Sanjiaoliao"
    ],
    "name:zho_x_preferred":[
        "\u4e09\u8173\u5bee"
    ],
    "wof:name":"Sanjiaoliao",
    "wof:placetype":"locality"
},
  "geometry": {"coordinates":[120.43846000000001,22.71771],"type":"Point"}
}