{
  "type": "Feature",
  "properties": {
    "gn:admin1_code":"4.0",
    "gn:admin2_code":"NAN",
    "gn:admin3_code":"M02",
    "gn:admin4_code":"10008020015.0",
    "gn:asciiname":"Dingcaonan",
    "gn:country_code":"TW",
    "gn:dem":574,
    "gn:feature_class":"P",
    "gn:feature_code":"PPL",
    "gn:name":"Dingcaonan",
    "gn:population":0,
    "gn:timezone":"Asia/Taipei",
    "iso:country":"TW",
    "name:zho_x_preferred":[
        "\u9802\u8349\u6e73"
    ],
    "name:zho_x_variant":[
        "Ting-ts\u2019ao-nan"
    ],
    "wof:name":"Dingcaonan",
    "wof:placetype":"locality"
},
  "geometry": {"coordinates":[120.90767,23.93919],"type":"Point"}
}