{
  "type": "Feature",
  "properties": {
    "gn:admin1_code":"4.0",
    "gn:admin2_code":"TAO",
    "gn:admin3_code":"H11",
    "gn:admin4_code":"68000110023.0",
    "gn:asciiname":"Zhuangcuo",
    "gn:country_code":"TW",
    "gn:dem":41,
    "gn:feature_class":"P",
    "gn:feature_code":"PPL",
    "gn:name":"Zhuangcuo",
    "gn:population":0,
    "gn:timezone":"Asia/Taipei",
    "iso:country":"TW",
    "name:und_x_variant":[
        "Jhuangcuo"
    ],
    "name:zho_x_preferred":[
        "\u838a\u539d"
    ],
    "name:zho_x_variant":[
        "Chuang-ts\u2019o"
    ],
    "wof:name":"Zhuangcuo",
    "wof:placetype":"locality"
},
  "geometry": {"coordinates":[121.03610999999999,24.94889],"type":"Point"}
}