{
  "type": "Feature",
  "properties": {
    "gn:admin1_code":"2.0",
    "gn:admin2_code":"KHH",
    "gn:admin3_code":"E14",
    "gn:admin4_code":"64000140015.0",
    "gn:asciiname":"Liyu Shan",
    "gn:country_code":"TW",
    "gn:dem":5,
    "gn:feature_class":"P",
    "gn:feature_code":"PPL",
    "gn:name":"Liyu Shan",
    "gn:population":0,
    "gn:timezone":"Asia/Taipei",
    "iso:country":"TW",
    "name:und_x_variant":[
        "Li-y\u00fc Shan"
    ],
    "wof:name":"Liyu Shan",
    "wof:placetype":"locality"
},
  "geometry": {"coordinates":[120.43333,22.55],"type":"Point"}
}