{
  "type": "Feature",
  "properties": {
    "gn:admin1_code":"04",
    "gn:admin2_code":"HSZ",
    "gn:admin3_code":"J14",
    "gn:admin4_code":"10004120005.0",
    "gn:asciiname":"Bilin",
    "gn:country_code":"TW",
    "gn:dem":589,
    "gn:feature_class":"P",
    "gn:feature_code":"PPL",
    "gn:name":"Bilin",
    "gn:population":0,
    "gn:timezone":"Asia/Taipei",
    "iso:country":"TW",
    "name:ceb_x_preferred":[
        "Bilin"
    ],
    "name:deu_x_preferred":[
        "Bilin"
    ],
    "name:srp_x_preferred":[
        "Bilin"
    ],
    "name:swe_x_preferred":[
        "Bilin"
    ],
    "name:und_x_variant":[
        "Pi-lin"
    ],
    "name:zho_x_preferred":[
        "\u6bd4\u9e9f"
    ],
    "wof:name":"Bilin",
    "wof:placetype":"locality"
},
  "geometry": {"coordinates":[121.22638999999999,24.69639],"type":"Point"}
}