{
  "type": "Feature",
  "properties": {
    "gn:admin1_code":"4.0",
    "gn:admin2_code":"TXG",
    "gn:admin3_code":"B22",
    "gn:admin4_code":"66000220011.0",
    "gn:asciiname":"Yangliuzhuang",
    "gn:country_code":"TW",
    "gn:dem":15,
    "gn:feature_class":"P",
    "gn:feature_code":"PPL",
    "gn:name":"Yangliuzhuang",
    "gn:population":0,
    "gn:timezone":"Asia/Taipei",
    "iso:country":"TW",
    "name:und_x_variant":[
        "Shui-liu-chuang",
        "Yanglioujhuang",
        "Yangliuzhuang",
        "Yang-liu-chuang"
    ],
    "name:zho_x_preferred":[
        "\u694a\u67f3\u5e84"
    ],
    "wof:name":"Yangliuzhuang",
    "wof:placetype":"locality"
},
  "geometry": {"coordinates":[120.60278,24.37583],"type":"Point"}
}