{
  "type": "Feature",
  "properties": {
    "gn:admin1_code":"04",
    "gn:admin2_code":"TNN",
    "gn:admin3_code":"R06",
    "gn:admin4_code":"67000060013.0",
    "gn:asciiname":"Gezibu",
    "gn:country_code":"TW",
    "gn:dem":121,
    "gn:feature_class":"P",
    "gn:feature_code":"PPL",
    "gn:name":"Gezibu",
    "gn:population":0,
    "gn:timezone":"Asia/Taipei",
    "iso:country":"TW",
    "name:und_x_variant":[
        "Gezihbu",
        "Ko-tzu-pu"
    ],
    "name:zho_x_preferred":[
        "\u683c\u5b50\u57d4"
    ],
    "name:zho_x_variant":[
        "Y\u00fc-tzu-pu"
    ],
    "wof:name":"Gezibu",
    "wof:placetype":"locality"
},
  "geometry": {"coordinates":[120.46861,23.2675],"type":"Point"}
}