{
  "type": "Feature",
  "properties": {
    "gn:admin1_code":"4.0",
    "gn:admin2_code":"PIF",
    "gn:admin3_code":"T08",
    "gn:admin4_code":"10013080010.0",
    "gn:asciiname":"Dongning",
    "gn:country_code":"TW",
    "gn:dem":34,
    "gn:feature_class":"P",
    "gn:feature_code":"PPL",
    "gn:name":"Dongning",
    "gn:population":0,
    "gn:timezone":"Asia/Taipei",
    "iso:country":"TW",
    "name:und_x_variant":[
        "Tung-ning",
        "\u6771\u5be7",
        "Dongning"
    ],
    "name:zho_x_preferred":[
        "Ch\u2019e-ning-ts\u2019un"
    ],
    "name:zho_x_variant":[
        "Tung-ning-ts\u2019un",
        "Ch\u2019e-ning-li",
        "Ch\u2019e-Neng-Li",
        "Ch\u2019e-ning",
        "\u6771\u5be7"
    ],
    "wof:name":"Dongning",
    "wof:placetype":"locality"
},
  "geometry": {"coordinates":[120.49733999999999,22.73554],"type":"Point"}
}