{
  "type": "Feature",
  "properties": {
    "gn:admin1_code":"4.0",
    "gn:admin2_code":"NAN",
    "gn:admin3_code":"M13",
    "gn:admin4_code":"10008130016.0",
    "gn:asciiname":"Weishang",
    "gn:country_code":"TW",
    "gn:dem":2319,
    "gn:feature_class":"P",
    "gn:feature_code":"PPL",
    "gn:name":"Weishang",
    "gn:population":0,
    "gn:timezone":"Asia/Taipei",
    "iso:country":"TW",
    "name:und_x_variant":[
        "Wei-shang"
    ],
    "name:zho_x_preferred":[
        "\u5c3e\u4e0a"
    ],
    "wof:name":"Weishang",
    "wof:placetype":"locality"
},
  "geometry": {"coordinates":[121.22667,24.04972],"type":"Point"}
}