{
  "type": "Feature",
  "properties": {
    "gn:admin1_code":"04",
    "gn:admin2_code":"NAN",
    "gn:admin3_code":"M07",
    "gn:admin4_code":"10008070003.0",
    "gn:asciiname":"Dongding",
    "gn:country_code":"TW",
    "gn:dem":723,
    "gn:feature_class":"P",
    "gn:feature_code":"PPL",
    "gn:name":"Dongding",
    "gn:population":0,
    "gn:timezone":"Asia/Taipei",
    "iso:country":"TW",
    "name:und_x_variant":[
        "Tung-ting"
    ],
    "name:zho_x_preferred":[
        "\u51cd\u9802"
    ],
    "wof:name":"Dongding",
    "wof:placetype":"locality"
},
  "geometry": {"coordinates":[120.76904999999999,23.74971],"type":"Point"}
}