{
  "type": "Feature",
  "properties": {
    "gn:admin1_code":"4.0",
    "gn:admin2_code":"NAN",
    "gn:admin3_code":"M03",
    "gn:admin4_code":"10008030015.0",
    "gn:asciiname":"Xiabuzi",
    "gn:country_code":"TW",
    "gn:dem":69,
    "gn:feature_class":"P",
    "gn:feature_code":"PPL",
    "gn:name":"Xiabuzi",
    "gn:population":0,
    "gn:timezone":"Asia/Taipei",
    "iso:country":"TW",
    "name:und_x_variant":[
        "\u4e0b\u57d4\u5b50",
        "Xiabuzi",
        "Siabuzih",
        "Hsia-pu-tzu"
    ],
    "wof:name":"Xiabuzi",
    "wof:placetype":"locality"
},
  "geometry": {"coordinates":[120.64866000000001,24.0019],"type":"Point"}
}