{
  "type": "Feature",
  "properties": {
    "iso:country":"TW",
    "qs:name":"\u864e\u5c3e\u93ae",
    "qs:name_adm0":"\u81fa\u7063",
    "qs:name_adm1":"\u96f2\u6797\u7e23",
    "qs:photos":2269,
    "qs:photos_1k":460,
    "qs:photos_9k":10,
    "qs:photos_9r":9,
    "qs:photos_all":2269,
    "qs:photos_sr":17,
    "qs:placetype":"Town",
    "qs:pop_sr":"0",
    "wof:name":"\u864e\u5c3e\u93ae",
    "wof:placetype":"locality"
},
  "geometry": {"coordinates":[120.434944,23.711102],"type":"Point"}
}