{
  "type": "Feature",
  "properties": {
    "gn:admin1_code":"4.0",
    "gn:admin2_code":"MIA",
    "gn:admin3_code":"K11",
    "gn:admin4_code":"10005150006.0",
    "gn:asciiname":"Erliaokeng",
    "gn:country_code":"TW",
    "gn:dem":81,
    "gn:feature_class":"P",
    "gn:feature_code":"PPL",
    "gn:name":"Erliaokeng",
    "gn:population":0,
    "gn:timezone":"Asia/Taipei",
    "iso:country":"TW",
    "name:zho_x_preferred":[
        "\u4e8c\u5bee\u5751"
    ],
    "name:zho_x_variant":[
        "Erh-liao-k\u2019eng"
    ],
    "wof:name":"Erliaokeng",
    "wof:placetype":"locality"
},
  "geometry": {"coordinates":[120.93195,24.60539],"type":"Point"}
}