{
  "type": "Feature",
  "properties": {
    "gn:admin1_code":"4.0",
    "gn:admin2_code":"NAN",
    "gn:admin3_code":"M10",
    "gn:admin4_code":"10008100002.0",
    "gn:asciiname":"Yanding",
    "gn:country_code":"TW",
    "gn:dem":595,
    "gn:feature_class":"P",
    "gn:feature_code":"PPL",
    "gn:name":"Yanding",
    "gn:population":0,
    "gn:timezone":"Asia/Taipei",
    "iso:country":"TW",
    "name:und_x_variant":[
        "Yen-ting"
    ],
    "name:zho_x_preferred":[
        "\u5ca9\u9802"
    ],
    "wof:name":"Yanding",
    "wof:placetype":"locality"
},
  "geometry": {"coordinates":[120.87869000000001,24.03336],"type":"Point"}
}