{
  "type": "Feature",
  "properties": {
    "gn:admin1_code":"4.0",
    "gn:admin2_code":"TAO",
    "gn:admin3_code":"H09",
    "gn:admin4_code":"68000090018.0",
    "gn:asciiname":"Beiyuan",
    "gn:country_code":"TW",
    "gn:dem":161,
    "gn:feature_class":"P",
    "gn:feature_code":"PPL",
    "gn:name":"Beiyuan",
    "gn:population":0,
    "gn:timezone":"Asia/Taipei",
    "iso:country":"TW",
    "name:ceb_x_preferred":[
        "Beiyuan"
    ],
    "name:swe_x_preferred":[
        "Beiyuan"
    ],
    "name:zho_x_preferred":[
        "\u5317\u82d1"
    ],
    "name:zho_x_variant":[
        "Pei-y\u00fcan"
    ],
    "wof:name":"Beiyuan",
    "wof:placetype":"locality"
},
  "geometry": {"coordinates":[121.24417,24.82028],"type":"Point"}
}