{
  "type": "Feature",
  "properties": {
    "iso:country":"TW",
    "name:cat_x_preferred":[
        "Beitun"
    ],
    "name:eng_x_preferred":[
        "Beitun District"
    ],
    "name:epo_x_preferred":[
        "\u54e1\u6797\u6751"
    ],
    "name:fra_x_preferred":[
        "Beitun"
    ],
    "name:jpn_x_preferred":[
        "\u5317\u5c6f\u533a"
    ],
    "name:kor_x_preferred":[
        "\ubca0\uc774\ud230\uad6c"
    ],
    "name:nan_x_preferred":[
        "Pak-t\u016bn-khu"
    ],
    "name:pol_x_preferred":[
        "Beitun"
    ],
    "name:rus_x_preferred":[
        "\u0411\u044d\u0439\u0442\u0443\u043d\u044c"
    ],
    "name:tha_x_preferred":[
        "\u0e40\u0e02\u0e15\u0e40\u0e1b\u0e48\u0e22\u0e4c\u0e16\u0e38\u0e19"
    ],
    "name:vie_x_preferred":[
        "B\u1eafc \u0110\u1ed3n"
    ],
    "name:yue_x_preferred":[
        "\u5317\u5c6f\u5340"
    ],
    "name:zho_x_preferred":[
        "\u5317\u5c6f\u5340"
    ],
    "qs:name":"\u6c34\u6e73\u91cc",
    "qs:name_adm0":"\u81fa\u7063",
    "qs:name_adm1":"\u53f0\u4e2d\u5e02",
    "qs:photos":36,
    "qs:photos_1k":7,
    "qs:photos_9k":1,
    "qs:photos_9r":2,
    "qs:photos_all":36,
    "qs:photos_sr":2,
    "qs:placetype":"Suburb",
    "qs:pop_sr":"0",
    "wd:wordcount":198,
    "wof:name":"\u6c34\u6e73\u91cc",
    "wof:placetype":"neighbourhood"
},
  "geometry": {"coordinates":[120.67571599999999,24.175905],"type":"Point"}
}