{
  "type": "Feature",
  "properties": {
    "iso:country":"TW",
    "name:eng_x_preferred":[
        "Fangyuan"
    ],
    "name:eng_x_variant":[
        "Fangyuan Village"
    ],
    "name:zho_tw_x_preferred":[
        "\u82b3\u82d1\u6751"
    ],
    "qs:name":"\u82b3\u82d1\u6751",
    "qs:name_adm0":"\u81fa\u7063",
    "qs:name_adm1":"\u5f70\u5316\u7e23",
    "qs:photos":72,
    "qs:photos_1k":15,
    "qs:photos_9k":1,
    "qs:photos_9r":2,
    "qs:photos_all":72,
    "qs:photos_sr":2,
    "qs:placetype":"Town",
    "qs:pop_sr":"0",
    "wof:name":"Fangyuan",
    "wof:placetype":"locality"
},
  "geometry": {"coordinates":[120.31639800000001,23.929264],"type":"Point"}
}