{
  "type": "Feature",
  "properties": {
    "gn:admin1_code":"4.0",
    "gn:admin2_code":"TXG",
    "gn:admin3_code":"B22",
    "gn:admin4_code":"66000220009.0",
    "gn:asciiname":"Yangzhuzhuang",
    "gn:country_code":"TW",
    "gn:dem":32,
    "gn:feature_class":"P",
    "gn:feature_code":"PPL",
    "gn:name":"Yangzhuzhuang",
    "gn:population":0,
    "gn:timezone":"Asia/Taipei",
    "iso:country":"TW",
    "name:und_x_variant":[
        "Yangjhujhuang",
        "Yangzhuzhuang",
        "Yang-chu-chuang"
    ],
    "name:zho_x_preferred":[
        "\u694a\u4f4f\u5e84"
    ],
    "name:zho_x_variant":[
        "Shan-liao-t\u2019ou"
    ],
    "wof:name":"Yangzhuzhuang",
    "wof:placetype":"locality"
},
  "geometry": {"coordinates":[120.61806,24.37778],"type":"Point"}
}