{
  "type": "Feature",
  "properties": {
    "gn:admin1_code":"04",
    "gn:admin2_code":"CHA",
    "gn:admin3_code":"N05",
    "gn:admin4_code":"10007100030.0",
    "gn:asciiname":"Dalunkeng",
    "gn:country_code":"TW",
    "gn:dem":251,
    "gn:feature_class":"P",
    "gn:feature_code":"PPL",
    "gn:name":"Dalunkeng",
    "gn:population":0,
    "gn:timezone":"Asia/Taipei",
    "iso:country":"TW",
    "name:zho_x_preferred":[
        "\u5927\u5d19\u5751"
    ],
    "name:zho_x_variant":[
        "Ta-lun-k\u2019eng"
    ],
    "wof:name":"Dalunkeng",
    "wof:placetype":"locality"
},
  "geometry": {"coordinates":[120.62282999999999,23.95817000000001],"type":"Point"}
}