{
  "type": "Feature",
  "properties": {
    "iso:country":"TW",
    "qs:name":"\u5e73\u8208\u91cc",
    "qs:name_adm0":"\u81fa\u7063",
    "qs:name_adm1":"\u53f0\u4e2d\u5e02",
    "qs:photos":94,
    "qs:photos_1k":19,
    "qs:photos_9k":1,
    "qs:photos_9r":3,
    "qs:photos_all":94,
    "qs:photos_sr":3,
    "qs:placetype":"Suburb",
    "qs:pop_sr":"0",
    "wd:wordcount":198,
    "wof:name":"\u5e73\u8208\u91cc",
    "wof:placetype":"neighbourhood"
},
  "geometry": {"coordinates":[120.697883,24.175611],"type":"Point"}
}