{
  "type": "Feature",
  "properties": {
    "gn:admin1_code":"4.0",
    "gn:admin2_code":"TXG",
    "gn:admin3_code":"B15",
    "gn:admin4_code":"66000150014.0",
    "gn:asciiname":"Wujialiu",
    "gn:country_code":"TW",
    "gn:dem":191,
    "gn:feature_class":"P",
    "gn:feature_code":"PPL",
    "gn:name":"Wujialiu",
    "gn:population":0,
    "gn:timezone":"Asia/Taipei",
    "iso:country":"TW",
    "name:und_x_variant":[
        "Wujialiou",
        "Wu-chia-liu"
    ],
    "name:zho_x_preferred":[
        "\u4e94\u7532\u516d"
    ],
    "wof:name":"Wujialiu",
    "wof:placetype":"locality"
},
  "geometry": {"coordinates":[120.69222000000001,24.30778],"type":"Point"}
}