{
  "type": "Feature",
  "properties": {
    "gn:admin1_code":"04",
    "gn:admin2_code":"TNN",
    "gn:admin3_code":"R19",
    "gn:admin4_code":"67000190010.0",
    "gn:asciiname":"Bai'erjia",
    "gn:country_code":"TW",
    "gn:dem":13,
    "gn:feature_class":"P",
    "gn:feature_code":"PPL",
    "gn:name":"Bai\u2019erjia",
    "gn:population":0,
    "gn:timezone":"Asia/Taipei",
    "iso:country":"TW",
    "name:und_x_variant":[
        "Pai-erh-chia"
    ],
    "name:zho_x_preferred":[
        "\u767e\u4e8c\u7532"
    ],
    "name:zho_x_variant":[
        "Bai\u2019erjia"
    ],
    "wof:name":"Bai'erjia",
    "wof:placetype":"locality"
},
  "geometry": {"coordinates":[120.27011,23.13907],"type":"Point"}
}