{
  "type": "Feature",
  "properties": {
    "gn:admin1_code":"04",
    "gn:admin2_code":"CYQ",
    "gn:admin3_code":"Q14",
    "gn:admin4_code":"10010130014.0",
    "gn:asciiname":"Tengliaozi",
    "gn:country_code":"TW",
    "gn:dem":344,
    "gn:feature_class":"P",
    "gn:feature_code":"PPL",
    "gn:name":"Tengliaozi",
    "gn:population":0,
    "gn:timezone":"Asia/Taipei",
    "iso:country":"TW",
    "name:und_x_variant":[
        "Tengliaozih",
        "Tengliaozi"
    ],
    "name:zho_x_preferred":[
        "\u7c50\u5bee\u4ed4"
    ],
    "name:zho_x_variant":[
        "T\u2019eng-liao-tzu"
    ],
    "wof:name":"Tengliaozi",
    "wof:placetype":"locality"
},
  "geometry": {"coordinates":[120.57537000000001,23.39837],"type":"Point"}
}