{
  "type": "Feature",
  "properties": {
    "gn:admin1_code":"4.0",
    "gn:admin2_code":"TAO",
    "gn:admin3_code":"H10",
    "gn:admin4_code":"68000100015.0",
    "gn:asciiname":"Lanbei",
    "gn:country_code":"TW",
    "gn:dem":204,
    "gn:feature_class":"P",
    "gn:feature_code":"PPL",
    "gn:name":"Lanbei",
    "gn:population":0,
    "gn:timezone":"Asia/Taipei",
    "iso:country":"TW",
    "name:und_x_variant":[
        "Nan-pei",
        "Lanbei",
        "Lan-pei"
    ],
    "name:zho_x_preferred":[
        "\u6feb\u80cc"
    ],
    "wof:name":"Lanbei",
    "wof:placetype":"locality"
},
  "geometry": {"coordinates":[121.21722,24.89361],"type":"Point"}
}