{
  "type": "Feature",
  "properties": {
    "gn:admin1_code":"04",
    "gn:admin2_code":"CHA",
    "gn:admin3_code":"N03",
    "gn:admin4_code":"10007030027.0",
    "gn:asciiname":"Bao'anlin",
    "gn:country_code":"TW",
    "gn:dem":13,
    "gn:feature_class":"P",
    "gn:feature_code":"PPL",
    "gn:name":"Bao\u2019anlin",
    "gn:population":0,
    "gn:timezone":"Asia/Taipei",
    "iso:country":"TW",
    "name:und_x_variant":[
        "Pao-an-lin"
    ],
    "name:zho_x_preferred":[
        "Bao\u2019anlin"
    ],
    "wof:name":"Bao'anlin",
    "wof:placetype":"locality"
},
  "geometry": {"coordinates":[120.51361,24.15056],"type":"Point"}
}