{
  "type": "Feature",
  "properties": {
    "gn:admin1_code":"04",
    "gn:admin2_code":"TTT",
    "gn:admin3_code":"V11",
    "gn:admin4_code":"10014110001.0",
    "gn:asciiname":"Youzihu",
    "gn:country_code":"TW",
    "gn:dem":9,
    "gn:feature_class":"P",
    "gn:feature_code":"PPL",
    "gn:name":"Youzihu",
    "gn:population":0,
    "gn:timezone":"Asia/Taipei",
    "iso:country":"TW",
    "name:und_x_variant":[
        "Youzihhu",
        "Yu-tzu-hu"
    ],
    "name:zho_x_preferred":[
        "\u67da\u5b50\u6e56"
    ],
    "wof:name":"Youzihu",
    "wof:placetype":"locality"
},
  "geometry": {"coordinates":[121.50888999999999,22.66611],"type":"Point"}
}