{
  "type": "Feature",
  "properties": {
    "gn:admin1_code":"4.0",
    "gn:admin2_code":"PIF",
    "gn:admin3_code":"T26",
    "gn:admin4_code":"10013260008.0",
    "gn:asciiname":"Dashuichong",
    "gn:country_code":"TW",
    "gn:dem":94,
    "gn:feature_class":"P",
    "gn:feature_code":"PPL",
    "gn:name":"Dashuichong",
    "gn:population":0,
    "gn:timezone":"Asia/Taipei",
    "iso:country":"TW",
    "name:und_x_variant":[
        "Dashueichong",
        "Dashuichong"
    ],
    "name:zho_x_preferred":[
        "\u5927\u6c34\u6c96"
    ],
    "name:zho_x_variant":[
        "Ta-shui-ch\u2019ung"
    ],
    "wof:name":"Dashuichong",
    "wof:placetype":"locality"
},
  "geometry": {"coordinates":[120.63061999999999,22.79238],"type":"Point"}
}