{
  "type": "Feature",
  "properties": {
    "gn:admin1_code":"03",
    "gn:admin2_code":"TPQ",
    "gn:admin3_code":"F17",
    "gn:admin4_code":"65000070025.0",
    "gn:asciiname":"Sankuaicuo",
    "gn:country_code":"TW",
    "gn:dem":31,
    "gn:feature_class":"P",
    "gn:feature_code":"PPL",
    "gn:name":"Sankuaicuo",
    "gn:population":0,
    "gn:timezone":"Asia/Taipei",
    "iso:country":"TW",
    "name:zho_x_preferred":[
        "\u4e09\u584a\u539d"
    ],
    "name:zho_x_variant":[
        "San-k\u2019uai-ts\u2019o"
    ],
    "wof:name":"Sankuaicuo",
    "wof:placetype":"locality"
},
  "geometry": {"coordinates":[121.39973999999999,24.96328],"type":"Point"}
}