{
  "type": "Feature",
  "properties": {
    "gn:admin1_code":"03",
    "gn:admin2_code":"TPQ",
    "gn:admin3_code":"F21",
    "gn:admin4_code":"65000120007.0",
    "gn:asciiname":"Sanzhaozikeng",
    "gn:country_code":"TW",
    "gn:dem":62,
    "gn:feature_class":"P",
    "gn:feature_code":"PPL",
    "gn:name":"Sanzhaozikeng",
    "gn:population":0,
    "gn:timezone":"Asia/Taipei",
    "iso:country":"TW",
    "name:und_x_variant":[
        "Sanjhaozihkeng",
        "Sanzhaozikeng"
    ],
    "name:zho_x_preferred":[
        "San-Chua-Tz\u016d-K\u2019eng"
    ],
    "name:zho_x_variant":[
        "\u4e09\u722a\u5b50\u5751",
        "San-chao-tzu-k\u2019eng"
    ],
    "wof:name":"Sanzhaozikeng",
    "wof:placetype":"locality"
},
  "geometry": {"coordinates":[121.81215,25.10677],"type":"Point"}
}