{
  "type": "Feature",
  "properties": {
    "gn:admin1_code":"03",
    "gn:admin2_code":"TPQ",
    "gn:admin3_code":"F09",
    "gn:admin4_code":"65000180002.0",
    "gn:asciiname":"Wanshunliao",
    "gn:country_code":"TW",
    "gn:dem":36,
    "gn:feature_class":"P",
    "gn:feature_code":"PPL",
    "gn:name":"Wanshunliao",
    "gn:population":0,
    "gn:timezone":"Asia/Taipei",
    "iso:country":"TW",
    "name:und_x_variant":[
        "Wan-shun-liao"
    ],
    "name:zho_x_preferred":[
        "\u842c\u9806\u5bee"
    ],
    "wof:name":"Wanshunliao",
    "wof:placetype":"locality"
},
  "geometry": {"coordinates":[121.60702000000001,25.00095],"type":"Point"}
}