{
  "type": "Feature",
  "properties": {
    "gn:admin1_code":"4.0",
    "gn:admin2_code":"TNN",
    "gn:admin3_code":"R01",
    "gn:admin4_code":"67000010024.0",
    "gn:asciiname":"Xiucai",
    "gn:country_code":"TW",
    "gn:dem":11,
    "gn:feature_class":"P",
    "gn:feature_code":"PPL",
    "gn:name":"Xiucai",
    "gn:population":0,
    "gn:timezone":"Asia/Taipei",
    "iso:country":"TW",
    "name:und_x_variant":[
        "Sioucai",
        "Xiucai"
    ],
    "name:zho_x_preferred":[
        "\u79c0\u624d"
    ],
    "name:zho_x_variant":[
        "Hsiu-ts\u2019ai"
    ],
    "wof:name":"Xiucai",
    "wof:placetype":"locality"
},
  "geometry": {"coordinates":[120.26434999999999,23.2653],"type":"Point"}
}