{
  "type": "Feature",
  "properties": {
    "iso:country":"TW",
    "qs:name":"\u9752\u5e74\u91cc",
    "qs:name_adm0":"\u81fa\u7063",
    "qs:name_adm1":"\u53f0\u5357\u5e02",
    "qs:photos":331,
    "qs:photos_1k":67,
    "qs:photos_9k":1,
    "qs:photos_9r":5,
    "qs:photos_all":331,
    "qs:photos_sr":5,
    "qs:placetype":"Suburb",
    "qs:pop_sr":"0",
    "wof:name":"\u9752\u5e74\u91cc",
    "wof:placetype":"neighbourhood"
},
  "geometry": {"coordinates":[120.209902,22.992846],"type":"Point"}
}