{
  "type": "Feature",
  "properties": {
    "gn:admin1_code":"04",
    "gn:admin2_code":"NAN",
    "gn:admin3_code":"M12",
    "gn:admin4_code":"10008120002.0",
    "gn:asciiname":"Dilicun",
    "gn:country_code":"TW",
    "gn:dem":402,
    "gn:feature_class":"P",
    "gn:feature_code":"PPL",
    "gn:name":"Dilicun",
    "gn:population":0,
    "gn:timezone":"Asia/Taipei",
    "iso:country":"TW",
    "name:und_x_variant":[
        "Ti-li"
    ],
    "name:zho_x_preferred":[
        "\u5730\u5229\u6751"
    ],
    "name:zho_x_variant":[
        "T\u2019a-ma-lo-wan-she",
        "Ti-li-ts\u2019un"
    ],
    "wof:name":"Dilicun",
    "wof:placetype":"locality"
},
  "geometry": {"coordinates":[120.94450000000001,23.79439],"type":"Point"}
}