{
  "type": "Feature",
  "properties": {
    "gn:admin1_code":"04",
    "gn:admin2_code":"TPE",
    "gn:admin3_code":"A11",
    "gn:admin4_code":"63000080036.0",
    "gn:asciiname":"Paozilin",
    "gn:country_code":"TW",
    "gn:dem":36,
    "gn:feature_class":"P",
    "gn:feature_code":"PPL",
    "gn:name":"Paozilin",
    "gn:population":0,
    "gn:timezone":"Asia/Taipei",
    "iso:country":"TW",
    "name:und_x_variant":[
        "Paozihlin"
    ],
    "name:zho_x_preferred":[
        "\u70ae\u5b50\u6797"
    ],
    "name:zho_x_variant":[
        "P\u2019ao-tzu-lin"
    ],
    "wof:name":"Paozilin",
    "wof:placetype":"locality"
},
  "geometry": {"coordinates":[121.5784,24.9839],"type":"Point"}
}