{
  "type": "Feature",
  "properties": {
    "gn:admin1_code":"03",
    "gn:admin2_code":"TPQ",
    "gn:admin3_code":"F17",
    "gn:admin4_code":"65000070018.0",
    "gn:asciiname":"Shanzijiao",
    "gn:country_code":"TW",
    "gn:dem":62,
    "gn:feature_class":"P",
    "gn:feature_code":"PPL",
    "gn:name":"Shanzijiao",
    "gn:population":0,
    "gn:timezone":"Asia/Taipei",
    "iso:country":"TW",
    "name:und_x_variant":[
        "Shan-tzu-chiao"
    ],
    "wof:name":"Shanzijiao",
    "wof:placetype":"locality"
},
  "geometry": {"coordinates":[121.40000000000001,24.98333],"type":"Point"}
}