{
  "type": "Feature",
  "properties": {
    "gn:admin1_code":"4.0",
    "gn:admin2_code":"HSZ",
    "gn:admin3_code":"J08",
    "gn:admin4_code":"10004080005.0",
    "gn:asciiname":"Dashulong",
    "gn:country_code":"TW",
    "gn:dem":417,
    "gn:feature_class":"P",
    "gn:feature_code":"PPL",
    "gn:name":"Dashulong",
    "gn:population":0,
    "gn:timezone":"Asia/Taipei",
    "iso:country":"TW",
    "name:und_x_variant":[
        "Ta-shan-pei",
        "Feng-hsiang",
        "Dashulong",
        "Ta-shu-lung"
    ],
    "name:zho_x_preferred":[
        "\u5927\u6a39\u9f8d"
    ],
    "wof:name":"Dashulong",
    "wof:placetype":"locality"
},
  "geometry": {"coordinates":[121.15083,24.69],"type":"Point"}
}