{
  "type": "Feature",
  "properties": {
    "gn:admin1_code":"03",
    "gn:admin2_code":"TPQ",
    "gn:admin3_code":"F03",
    "gn:admin4_code":"65000150004.0",
    "gn:asciiname":"Neiyan",
    "gn:country_code":"TW",
    "gn:dem":238,
    "gn:feature_class":"P",
    "gn:feature_code":"PPL",
    "gn:name":"Neiyan",
    "gn:population":0,
    "gn:timezone":"Asia/Taipei",
    "iso:country":"TW",
    "name:und_x_variant":[
        "Nei-yen"
    ],
    "name:zho_x_preferred":[
        "\u5185\u5dd6"
    ],
    "wof:name":"Neiyan",
    "wof:placetype":"locality"
},
  "geometry": {"coordinates":[121.42489999999999,25.12542],"type":"Point"}
}