{
  "type": "Feature",
  "properties": {
    "gn:admin1_code":"4.0",
    "gn:admin2_code":"MIA",
    "gn:admin3_code":"K11",
    "gn:admin4_code":"10005150001.0",
    "gn:asciiname":"Shuziwo",
    "gn:country_code":"TW",
    "gn:dem":26,
    "gn:feature_class":"P",
    "gn:feature_code":"PPL",
    "gn:name":"Shuziwo",
    "gn:population":0,
    "gn:timezone":"Asia/Taipei",
    "iso:country":"TW",
    "name:und_x_variant":[
        "Shuzihwo",
        "Shu-tzu-wo"
    ],
    "name:zho_x_preferred":[
        "\u6a39\u5b50\u7aa9"
    ],
    "wof:name":"Shuziwo",
    "wof:placetype":"locality"
},
  "geometry": {"coordinates":[120.87052,24.64029],"type":"Point"}
}