{
  "type": "Feature",
  "properties": {
    "gn:admin1_code":"04",
    "gn:admin2_code":"CHA",
    "gn:admin3_code":"N15",
    "gn:admin4_code":"10007130007.0",
    "gn:asciiname":"Dahu",
    "gn:country_code":"TW",
    "gn:dem":26,
    "gn:feature_class":"P",
    "gn:feature_code":"PPL",
    "gn:name":"Dahu",
    "gn:population":0,
    "gn:timezone":"Asia/Taipei",
    "iso:country":"TW",
    "name:deu_x_preferred":[
        "Dahu"
    ],
    "name:fra_x_preferred":[
        "Dahu"
    ],
    "name:frp_x_preferred":[
        "Dahu"
    ],
    "name:heb_x_preferred":[
        "Dahu"
    ],
    "name:ita_x_preferred":[
        "Dahu"
    ],
    "name:lmo_x_preferred":[
        "Da\u00f9"
    ],
    "name:mkd_x_preferred":[
        "\u0414\u0430\u0445\u0443"
    ],
    "name:nld_x_preferred":[
        "Dahu"
    ],
    "name:por_x_preferred":[
        "Dahu"
    ],
    "name:rus_x_preferred":[
        "\u0414\u0430\u0445\u0443"
    ],
    "name:spa_x_preferred":[
        "Dahu"
    ],
    "name:srp_x_preferred":[
        "\u0414\u0430\u0445\u0443"
    ],
    "name:und_x_variant":[
        "Ta-hu"
    ],
    "name:zho_x_preferred":[
        "\u5927\u6e56"
    ],
    "wof:name":"Dahu",
    "wof:placetype":"locality"
},
  "geometry": {"coordinates":[120.5752,23.9801],"type":"Point"}
}