{
  "type": "Feature",
  "properties": {
    "iso:country":"TW",
    "name:eng_x_preferred":[
        "Yingshi"
    ],
    "name:eng_x_variant":[
        "Yingshi Village"
    ],
    "name:zho_tw_x_preferred":[
        "\u82f1\u58eb\u6751"
    ],
    "qs:name":"\u82f1\u58eb\u6751",
    "qs:name_adm0":"\u81fa\u7063",
    "qs:name_adm1":"\u5b9c\u862d\u7e23",
    "qs:photos":315,
    "qs:photos_1k":64,
    "qs:photos_9k":1,
    "qs:photos_9r":5,
    "qs:photos_all":315,
    "qs:photos_sr":5,
    "qs:placetype":"Town",
    "qs:pop_sr":"0",
    "wof:name":"Yingshi",
    "wof:placetype":"locality"
},
  "geometry": {"coordinates":[121.481916,24.640672],"type":"Point"}
}