{
  "type": "Feature",
  "properties": {
    "gn:admin1_code":"04",
    "gn:admin2_code":"CHA",
    "gn:admin3_code":"N01",
    "gn:admin4_code":"10007010069.0",
    "gn:asciiname":"Tianzhongzhuang",
    "gn:country_code":"TW",
    "gn:dem":29,
    "gn:feature_class":"P",
    "gn:feature_code":"PPL",
    "gn:name":"Tianzhongzhuang",
    "gn:population":0,
    "gn:timezone":"Asia/Taipei",
    "iso:country":"TW",
    "name:und_x_variant":[
        "Ta-t\u2019ing",
        "\u7530\u4e2d\u838a",
        "Tianzhongzhuang",
        "Tianjhongjhuang",
        "T\u2019ien-chung-chuang"
    ],
    "name:zho_x_preferred":[
        "T\u2019ien-chung-chuang"
    ],
    "wof:name":"Tianzhongzhuang",
    "wof:placetype":"locality"
},
  "geometry": {"coordinates":[120.60939999999999,24.08991],"type":"Point"}
}