{
  "type": "Feature",
  "properties": {
    "gn:admin1_code":"04",
    "gn:admin2_code":"NAN",
    "gn:admin3_code":"M10",
    "gn:admin4_code":"10008100003.0",
    "gn:asciiname":"Daqi",
    "gn:country_code":"TW",
    "gn:dem":279,
    "gn:feature_class":"P",
    "gn:feature_code":"PPL",
    "gn:name":"Daqi",
    "gn:population":0,
    "gn:timezone":"Asia/Taipei",
    "iso:country":"TW",
    "name:und_x_variant":[
        "Daci",
        "Daqi"
    ],
    "name:zho_x_preferred":[
        "Ta-ch\u2019i-wei"
    ],
    "name:zho_x_variant":[
        "\u5927\u65d7",
        "Ta-ch\u2019i"
    ],
    "wof:name":"Daqi",
    "wof:placetype":"locality"
},
  "geometry": {"coordinates":[120.86431,24.04812],"type":"Point"}
}