{
  "type": "Feature",
  "properties": {
    "gn:admin1_code":"4.0",
    "gn:admin2_code":"HSZ",
    "gn:admin3_code":"J10",
    "gn:admin4_code":"10004070002.0",
    "gn:asciiname":"Laochating",
    "gn:country_code":"TW",
    "gn:dem":263,
    "gn:feature_class":"P",
    "gn:feature_code":"PPL",
    "gn:name":"Laochating",
    "gn:population":0,
    "gn:timezone":"Asia/Taipei",
    "iso:country":"TW",
    "name:zho_x_preferred":[
        "\u8001\u8336\u4ead"
    ],
    "name:zho_x_variant":[
        "Lao-ch\u2019a-t\u2019ing"
    ],
    "wof:name":"Laochating",
    "wof:placetype":"locality"
},
  "geometry": {"coordinates":[121.14694,24.75361],"type":"Point"}
}