{
  "type": "Feature",
  "properties": {
    "gn:admin1_code":"1.0",
    "gn:admin2_code":"KIN",
    "gn:admin3_code":"W03",
    "gn:admin4_code":"9020010006.0",
    "gn:asciiname":"Xiecuo",
    "gn:country_code":"TW",
    "gn:dem":5,
    "gn:feature_class":"P",
    "gn:feature_code":"PPL",
    "gn:name":"Xiecuo",
    "gn:population":0,
    "gn:timezone":"Asia/Taipei",
    "iso:country":"TW",
    "name:und_x_variant":[
        "Hsieh-ts\u2019o"
    ],
    "name:zho_x_preferred":[
        "\u8b1d\u539d"
    ],
    "wof:name":"Xiecuo",
    "wof:placetype":"locality"
},
  "geometry": {"coordinates":[118.29510999999999,24.41132],"type":"Point"}
}