{
  "type": "Feature",
  "properties": {
    "gn:admin1_code":"4.0",
    "gn:admin2_code":"CHA",
    "gn:admin3_code":"N08",
    "gn:admin4_code":"10007200026.0",
    "gn:asciiname":"Wuhu",
    "gn:country_code":"TW",
    "gn:dem":23,
    "gn:feature_class":"P",
    "gn:feature_code":"PPL",
    "gn:name":"Wuhu",
    "gn:population":0,
    "gn:timezone":"Asia/Taipei",
    "iso:country":"TW",
    "name:und_x_variant":[
        "Wu-hu"
    ],
    "name:zho_x_preferred":[
        "\u4e94\u6236"
    ],
    "wof:name":"Wuhu",
    "wof:placetype":"locality"
},
  "geometry": {"coordinates":[120.44399,23.88023],"type":"Point"}
}