{
  "type": "Feature",
  "properties": {
    "iso:country":"TW",
    "qs:name":"\u79c0\u6c34\u9109",
    "qs:name_adm0":"\u81fa\u7063",
    "qs:name_adm1":"\u5f70\u5316\u7e23",
    "qs:photos":408,
    "qs:photos_1k":83,
    "qs:photos_9k":2,
    "qs:photos_9r":5,
    "qs:photos_all":540,
    "qs:photos_sr":6,
    "qs:placetype":"County",
    "qs:pop_sr":"0",
    "wof:name":"\u79c0\u6c34\u9109",
    "wof:placetype":"county"
},
  "geometry": {"coordinates":[120.51433299999999,24.03157],"type":"Point"}
}