{
  "type": "Feature",
  "properties": {
    "gn:admin1_code":"4.0",
    "gn:admin2_code":"HSZ",
    "gn:admin3_code":"J03",
    "gn:admin4_code":"10004040007.0",
    "gn:asciiname":"Duchuantou",
    "gn:country_code":"TW",
    "gn:dem":162,
    "gn:feature_class":"P",
    "gn:feature_code":"PPL",
    "gn:name":"Duchuantou",
    "gn:population":0,
    "gn:timezone":"Asia/Taipei",
    "iso:country":"TW",
    "name:zho_x_preferred":[
        "\u6e21\u8239\u982d"
    ],
    "name:zho_x_variant":[
        "Tu-ch\u2019uan-t\u2019ou"
    ],
    "wof:name":"Duchuantou",
    "wof:placetype":"locality"
},
  "geometry": {"coordinates":[121.17444,24.78083],"type":"Point"}
}