{
  "type": "Feature",
  "properties": {
    "gn:admin1_code":"2.0",
    "gn:admin2_code":"KHH",
    "gn:admin3_code":"E30",
    "gn:admin4_code":"64000300005.0",
    "gn:asciiname":"Xinsanjiaozi",
    "gn:country_code":"TW",
    "gn:dem":78,
    "gn:feature_class":"P",
    "gn:feature_code":"PPL",
    "gn:name":"Xinsanjiaozi",
    "gn:population":0,
    "gn:timezone":"Asia/Taipei",
    "iso:country":"TW",
    "name:und_x_variant":[
        "Hsin-san-chiao",
        "Xinsanjiaozi",
        "Sinsanjiaozih",
        "Chung-cheng",
        "Hsin-san-chiao-tzu"
    ],
    "name:zho_x_preferred":[
        "\u65b0\u4e09\u89d2\u5b50"
    ],
    "wof:name":"Xinsanjiaozi",
    "wof:placetype":"locality"
},
  "geometry": {"coordinates":[120.50417,22.93278],"type":"Point"}
}