{
  "type": "Feature",
  "properties": {
    "gn:admin1_code":"03",
    "gn:admin2_code":"TPQ",
    "gn:admin3_code":"F22",
    "gn:admin4_code":"65000240012.0",
    "gn:asciiname":"Shijiehou",
    "gn:country_code":"TW",
    "gn:dem":479,
    "gn:feature_class":"P",
    "gn:feature_code":"PPL",
    "gn:name":"Shijiehou",
    "gn:population":0,
    "gn:timezone":"Asia/Taipei",
    "iso:country":"TW",
    "name:und_x_variant":[
        "Shihjiehou",
        "Shijiehou",
        "Shih-chieh",
        "Shih-chieh-hou"
    ],
    "name:zho_x_preferred":[
        "\u77f3\u78a3\u5f8c"
    ],
    "wof:name":"Shijiehou",
    "wof:placetype":"locality"
},
  "geometry": {"coordinates":[121.78789999999999,25.07058],"type":"Point"}
}