{
  "type": "Feature",
  "properties": {
    "gn:admin1_code":"4.0",
    "gn:admin2_code":"CHA",
    "gn:admin3_code":"N22",
    "gn:admin4_code":"10007220012.0",
    "gn:asciiname":"Xinzhuang",
    "gn:country_code":"TW",
    "gn:dem":33,
    "gn:feature_class":"P",
    "gn:feature_code":"PPL",
    "gn:name":"Xinzhuang",
    "gn:population":0,
    "gn:timezone":"Asia/Taipei",
    "iso:country":"TW",
    "name:und_x_variant":[
        "Hsin-chuang-tzu",
        "Sinjhuang",
        "Xinzhuang",
        "Hsin-chuang"
    ],
    "name:zho_x_preferred":[
        "Hsin-chuang-ts\u2019un"
    ],
    "name:zho_x_variant":[
        "\u65b0\u838a"
    ],
    "wof:name":"Xinzhuang",
    "wof:placetype":"locality"
},
  "geometry": {"coordinates":[120.48336999999999,23.85994],"type":"Point"}
}