{
  "type": "Feature",
  "properties": {
    "gn:admin1_code":"04",
    "gn:admin2_code":"TNN",
    "gn:admin3_code":"D06",
    "gn:admin4_code":"67000350043.0",
    "gn:asciiname":"Caohuliao",
    "gn:country_code":"TW",
    "gn:dem":7,
    "gn:feature_class":"P",
    "gn:feature_code":"PPL",
    "gn:name":"Caohuliao",
    "gn:population":0,
    "gn:timezone":"Asia/Taipei",
    "iso:country":"TW",
    "name:zho_x_preferred":[
        "Ts\u2019ao-hu-liao"
    ],
    "name:zho_x_variant":[
        "\u8349\u6e56\u5bee"
    ],
    "wof:name":"Caohuliao",
    "wof:placetype":"locality"
},
  "geometry": {"coordinates":[120.19722,23.04306],"type":"Point"}
}