{
  "type": "Feature",
  "properties": {
    "gn:admin1_code":"4.0",
    "gn:admin2_code":"CYQ",
    "gn:admin3_code":"Q18",
    "gn:admin4_code":"10010170005.0",
    "gn:asciiname":"Zuzhou",
    "gn:country_code":"TW",
    "gn:dem":287,
    "gn:feature_class":"P",
    "gn:feature_code":"PPL",
    "gn:name":"Zuzhou",
    "gn:population":0,
    "gn:timezone":"Asia/Taipei",
    "iso:country":"TW",
    "name:und_x_variant":[
        "Zujhou",
        "Tsu-chou"
    ],
    "name:zho_x_preferred":[
        "\u7d44\u5dde"
    ],
    "wof:name":"Zuzhou",
    "wof:placetype":"locality"
},
  "geometry": {"coordinates":[120.57104,23.25214],"type":"Point"}
}