{
  "type": "Feature",
  "properties": {
    "iso:country":"TW",
    "qs:name":"\u820a\u5bee\u6751",
    "qs:name_adm0":"\u81fa\u7063",
    "qs:name_adm1":"\u5c4f\u6771\u7e23",
    "qs:photos":149,
    "qs:photos_1k":30,
    "qs:photos_9k":1,
    "qs:photos_9r":3,
    "qs:photos_all":149,
    "qs:photos_sr":3,
    "qs:placetype":"Town",
    "qs:pop_sr":"0",
    "wof:name":"\u820a\u5bee\u6751",
    "wof:placetype":"locality"
},
  "geometry": {"coordinates":[120.61572200000001,22.888738],"type":"Point"}
}