{
  "type": "Feature",
  "properties": {
    "gn:admin1_code":"4.0",
    "gn:admin2_code":"TNN",
    "gn:admin3_code":"R11",
    "gn:admin4_code":"67000110007.0",
    "gn:asciiname":"Dapingding",
    "gn:country_code":"TW",
    "gn:dem":80,
    "gn:feature_class":"P",
    "gn:feature_code":"PPL",
    "gn:name":"Dapingding",
    "gn:population":0,
    "gn:timezone":"Asia/Taipei",
    "iso:country":"TW",
    "name:zho_x_preferred":[
        "\u5927\u576a\u9876"
    ],
    "name:zho_x_variant":[
        "T\u2019a-p\u2019ing-ting"
    ],
    "wof:name":"Dapingding",
    "wof:placetype":"locality"
},
  "geometry": {"coordinates":[120.39151,23.1554],"type":"Point"}
}