{
  "type": "Feature",
  "properties": {
    "gn:admin1_code":"3.0",
    "gn:admin2_code":"TPQ",
    "gn:admin3_code":"F03",
    "gn:admin4_code":"65000150002.0",
    "gn:asciiname":"Zhuhua",
    "gn:country_code":"TW",
    "gn:dem":1,
    "gn:feature_class":"P",
    "gn:feature_code":"PPL",
    "gn:name":"Zhuhua",
    "gn:population":0,
    "gn:timezone":"Asia/Taipei",
    "iso:country":"TW",
    "name:und_x_variant":[
        "Chu-hua-ts\u2019un",
        "Chu-hua",
        "Zhuhua"
    ],
    "wof:name":"Zhuhua",
    "wof:placetype":"locality"
},
  "geometry": {"coordinates":[121.45,25.08333],"type":"Point"}
}