{
  "type": "Feature",
  "properties": {
    "iso:country":"TW",
    "name:eng_x_preferred":[
        "Weiqian"
    ],
    "name:eng_x_variant":[
        "Weiqian Village"
    ],
    "name:zho_tw_x_preferred":[
        "\u5c3e\u5879\u6751"
    ],
    "qs:name":"\u5c3e\u5879\u6751",
    "qs:name_adm0":"\u81fa\u7063",
    "qs:name_adm1":"\u5b9c\u862d\u7e23",
    "qs:photos":192,
    "qs:photos_1k":39,
    "qs:photos_9k":1,
    "qs:photos_9r":4,
    "qs:photos_all":192,
    "qs:photos_sr":4,
    "qs:placetype":"Town",
    "qs:pop_sr":"0",
    "wof:name":"Weiqian",
    "wof:placetype":"locality"
},
  "geometry": {"coordinates":[121.749493,24.702846],"type":"Point"}
}