{
  "type": "Feature",
  "properties": {
    "gn:admin1_code":"4.0",
    "gn:admin2_code":"PIF",
    "gn:admin3_code":"T04",
    "gn:admin4_code":"10013040007.0",
    "gn:asciiname":"Houbihu",
    "gn:country_code":"TW",
    "gn:dem":9,
    "gn:feature_class":"P",
    "gn:feature_code":"PPL",
    "gn:name":"Houbihu",
    "gn:population":0,
    "gn:timezone":"Asia/Taipei",
    "iso:country":"TW",
    "name:und_x_variant":[
        "Hou-pi-hu"
    ],
    "name:zho_x_preferred":[
        "\u5f8c\u58c1\u6e56"
    ],
    "wof:name":"Houbihu",
    "wof:placetype":"locality"
},
  "geometry": {"coordinates":[120.71722,22.04333],"type":"Point"}
}