{
  "type": "Feature",
  "properties": {
    "gn:admin1_code":"4.0",
    "gn:admin2_code":"CYQ",
    "gn:admin3_code":"Q02",
    "gn:admin4_code":"10010020022.0",
    "gn:asciiname":"Kanhou",
    "gn:country_code":"TW",
    "gn:dem":5,
    "gn:feature_class":"P",
    "gn:feature_code":"PPL",
    "gn:name":"Kanhou",
    "gn:population":0,
    "gn:timezone":"Asia/Taipei",
    "iso:country":"TW",
    "name:zho_x_preferred":[
        "K\u2019an-hou-li"
    ],
    "name:zho_x_variant":[
        "\u5d01\u5f8c",
        "K\u2019an-hou"
    ],
    "wof:name":"Kanhou",
    "wof:placetype":"locality"
},
  "geometry": {"coordinates":[120.22835000000001,23.44631],"type":"Point"}
}