{
  "type": "Feature",
  "properties": {
    "gn:admin1_code":"2.0",
    "gn:admin2_code":"KHH",
    "gn:admin3_code":"E32",
    "gn:admin4_code":"64000320002.0",
    "gn:asciiname":"Xinwei",
    "gn:country_code":"TW",
    "gn:dem":158,
    "gn:feature_class":"P",
    "gn:feature_code":"PPL",
    "gn:name":"Xinwei",
    "gn:population":0,
    "gn:timezone":"Asia/Taipei",
    "iso:country":"TW",
    "name:und_x_variant":[
        "Sinwei",
        "Hsin-wei"
    ],
    "name:zho_x_preferred":[
        "\u65b0\u5a01"
    ],
    "wof:name":"Xinwei",
    "wof:placetype":"locality"
},
  "geometry": {"coordinates":[120.62984,22.90264],"type":"Point"}
}