{
  "type": "Feature",
  "properties": {
    "gn:admin1_code":"4.0",
    "gn:admin2_code":"HUA",
    "gn:admin3_code":"U08",
    "gn:admin4_code":"10015080001.0",
    "gn:asciiname":"Yongfeng",
    "gn:country_code":"TW",
    "gn:dem":40,
    "gn:feature_class":"P",
    "gn:feature_code":"PPL",
    "gn:name":"Yongfeng",
    "gn:population":0,
    "gn:timezone":"Asia/Taipei",
    "iso:country":"TW",
    "name:ceb_x_preferred":[
        "Yongfeng"
    ],
    "name:deu_x_preferred":[
        "Yongfeng"
    ],
    "name:und_x_variant":[
        "Yongfong",
        "Yung-feng"
    ],
    "name:zho_x_preferred":[
        "\u6c38\u8c50"
    ],
    "name:zho_x_variant":[
        "Shen-ch\u2019iao"
    ],
    "wof:name":"Yongfeng",
    "wof:placetype":"locality"
},
  "geometry": {"coordinates":[121.52861,23.605],"type":"Point"}
}