{
  "type": "Feature",
  "properties": {
    "gn:admin1_code":"4.0",
    "gn:admin2_code":"NAN",
    "gn:admin3_code":"M03",
    "gn:admin4_code":"10008030022.0",
    "gn:asciiname":"Waigengliao",
    "gn:country_code":"TW",
    "gn:dem":539,
    "gn:feature_class":"P",
    "gn:feature_code":"PPL",
    "gn:name":"Waigengliao",
    "gn:population":0,
    "gn:timezone":"Asia/Taipei",
    "iso:country":"TW",
    "name:und_x_variant":[
        "Wai-keng-liao"
    ],
    "name:zho_x_preferred":[
        "\u5916\u6929\u5bee"
    ],
    "wof:name":"Waigengliao",
    "wof:placetype":"locality"
},
  "geometry": {"coordinates":[120.82205,23.98803],"type":"Point"}
}