{
  "type": "Feature",
  "properties": {
    "gn:admin1_code":"3.0",
    "gn:admin2_code":"TPQ",
    "gn:admin3_code":"F15",
    "gn:admin4_code":"65000090017.0",
    "gn:asciiname":"Hengxi",
    "gn:country_code":"TW",
    "gn:dem":35,
    "gn:feature_class":"P",
    "gn:feature_code":"PPL",
    "gn:name":"Hengxi",
    "gn:population":0,
    "gn:timezone":"Asia/Taipei",
    "iso:country":"TW",
    "name:und_x_variant":[
        "Hengsi",
        "Heng-hsi"
    ],
    "name:zho_x_preferred":[
        "Heng-ch\u2019i"
    ],
    "name:zho_x_variant":[
        "\u6a6b\u6eaa"
    ],
    "wof:name":"Hengxi",
    "wof:placetype":"locality"
},
  "geometry": {"coordinates":[121.39558,24.93716],"type":"Point"}
}