{
  "type": "Feature",
  "properties": {
    "gn:admin1_code":"4.0",
    "gn:admin2_code":"TNN",
    "gn:admin3_code":"R11",
    "gn:admin4_code":"67000110007.0",
    "gn:asciiname":"Zhuzhaizi",
    "gn:country_code":"TW",
    "gn:dem":75,
    "gn:feature_class":"P",
    "gn:feature_code":"PPL",
    "gn:name":"Zhuzhaizi",
    "gn:population":0,
    "gn:timezone":"Asia/Taipei",
    "iso:country":"TW",
    "name:und_x_variant":[
        "Jhujhaizih",
        "Zhuzhaizi",
        "Chu-chai-tzu"
    ],
    "name:zho_x_preferred":[
        "\u7af9\u5b85\u5b50"
    ],
    "wof:name":"Zhuzhaizi",
    "wof:placetype":"locality"
},
  "geometry": {"coordinates":[120.39482,23.15731],"type":"Point"}
}