{
  "type": "Feature",
  "properties": {
    "gn:admin1_code":"04",
    "gn:admin2_code":"CHA",
    "gn:admin3_code":"N20",
    "gn:admin4_code":"10007180002.0",
    "gn:asciiname":"Haifengliao",
    "gn:country_code":"TW",
    "gn:dem":85,
    "gn:feature_class":"P",
    "gn:feature_code":"PPL",
    "gn:name":"Haifengliao",
    "gn:population":0,
    "gn:timezone":"Asia/Taipei",
    "iso:country":"TW",
    "name:und_x_variant":[
        "Haifongliao",
        "Ta-feng",
        "Haifengliao",
        "Hai-feng-liao"
    ],
    "name:zho_x_preferred":[
        "Ta-feng-ts\u2019un"
    ],
    "name:zho_x_variant":[
        "\u6d77\u8c50\u5bee",
        "Pa-le-k\u2019eng"
    ],
    "wof:name":"Haifengliao",
    "wof:placetype":"locality"
},
  "geometry": {"coordinates":[120.61707,23.81828],"type":"Point"}
}