{
  "type": "Feature",
  "properties": {
    "gn:admin1_code":"4.0",
    "gn:admin2_code":"NAN",
    "gn:admin3_code":"M02",
    "gn:admin4_code":"10008020015.0",
    "gn:asciiname":"Zhiliaokeng",
    "gn:country_code":"TW",
    "gn:dem":480,
    "gn:feature_class":"P",
    "gn:feature_code":"PPL",
    "gn:name":"Zhiliaokeng",
    "gn:population":0,
    "gn:timezone":"Asia/Taipei",
    "iso:country":"TW",
    "name:und_x_variant":[
        "Jhihliaokeng"
    ],
    "name:zho_x_preferred":[
        "\u7d19\u5bee\u5751"
    ],
    "name:zho_x_variant":[
        "Chih-liao-k\u2019eng"
    ],
    "wof:name":"Zhiliaokeng",
    "wof:placetype":"locality"
},
  "geometry": {"coordinates":[120.93304000000001,23.94178],"type":"Point"}
}