{
  "type": "Feature",
  "properties": {
    "iso:country":"TW",
    "qs:name":"\u9ebb\u8c46\u93ae",
    "qs:name_adm0":"\u81fa\u7063",
    "qs:name_adm1":"\u53f0\u5357\u5e02",
    "qs:photos":2068,
    "qs:photos_1k":419,
    "qs:photos_9k":9,
    "qs:photos_9r":9,
    "qs:photos_all":2068,
    "qs:photos_sr":16,
    "qs:placetype":"Town",
    "qs:pop_sr":"0",
    "wd:wordcount":136,
    "wof:name":"\u9ebb\u8c46\u93ae",
    "wof:placetype":"locality"
},
  "geometry": {"coordinates":[120.241928,23.1896],"type":"Point"}
}