{
  "type": "Feature",
  "properties": {
    "iso:country":"TW",
    "name:ces_x_preferred":[
        "Okres Tchaj-nan"
    ],
    "name:cym_x_preferred":[
        "Sir Tainan"
    ],
    "name:deu_x_preferred":[
        "Landkreis Tainan"
    ],
    "name:eng_x_preferred":[
        "Tainan County"
    ],
    "name:eus_x_preferred":[
        "Tainan konderria"
    ],
    "name:hak_x_preferred":[
        "Th\u00f2i-n\u00e0m-yen"
    ],
    "name:ind_x_preferred":[
        "Kabupaten Tainan"
    ],
    "name:jpn_x_preferred":[
        "\u53f0\u5357\u770c"
    ],
    "name:kor_x_preferred":[
        "\ud0c0\uc774\ub09c\ud604"
    ],
    "name:lzh_x_preferred":[
        "\u81fa\u5357\u7e23"
    ],
    "name:nan_x_preferred":[
        "T\u00e2i-l\u00e2m-ko\u0101n"
    ],
    "name:nld_x_preferred":[
        "Tainan"
    ],
    "name:por_x_preferred":[
        "Tainan"
    ],
    "name:rus_x_preferred":[
        "\u0443\u0435\u0437\u0434 \u0422\u0430\u0439\u043d\u0430\u043d\u044c"
    ],
    "name:tha_x_preferred":[
        "\u0e44\u0e16\u0e2b\u0e19\u0e32\u0e19"
    ],
    "name:vie_x_preferred":[
        "\u0110\u00e0i Nam"
    ],
    "name:yue_x_preferred":[
        "\u81fa\u5357\u7e23"
    ],
    "name:zho_x_preferred":[
        "\u81fa\u5357\u7e23"
    ],
    "qs:name":"\u9ebb\u8c46\u93ae",
    "qs:name_adm0":"\u81fa\u7063",
    "qs:name_adm1":"\u53f0\u5357\u5e02",
    "qs:photos":2068,
    "qs:photos_1k":419,
    "qs:photos_9k":9,
    "qs:photos_9r":9,
    "qs:photos_all":2068,
    "qs:photos_sr":16,
    "qs:placetype":"Town",
    "qs:pop_sr":"0",
    "wd:wordcount":136,
    "wof:name":"\u9ebb\u8c46\u93ae",
    "wof:placetype":"locality"
},
  "geometry": {"coordinates":[120.241928,23.1896],"type":"Point"}
}