{
  "type": "Feature",
  "properties": {
    "gn:admin1_code":"4.0",
    "gn:admin2_code":"TXG",
    "gn:admin3_code":"B10",
    "gn:admin4_code":"66000100024.0",
    "gn:asciiname":"Xiazhuang",
    "gn:country_code":"TW",
    "gn:dem":251,
    "gn:feature_class":"P",
    "gn:feature_code":"PPL",
    "gn:name":"Xiazhuang",
    "gn:population":0,
    "gn:timezone":"Asia/Taipei",
    "iso:country":"TW",
    "name:deu_x_preferred":[
        "Xiazhuang"
    ],
    "name:und_x_variant":[
        "Siajhuang",
        "Xiazhuang",
        "Hsia-chuang"
    ],
    "name:zho_x_preferred":[
        "\u4e0b\u838a"
    ],
    "wof:name":"Xiazhuang",
    "wof:placetype":"locality"
},
  "geometry": {"coordinates":[120.75556,24.28278],"type":"Point"}
}