{
  "type": "Feature",
  "properties": {
    "gn:admin1_code":"2.0",
    "gn:admin2_code":"KHH",
    "gn:admin3_code":"E31",
    "gn:admin4_code":"64000310001.0",
    "gn:asciiname":"Quanshuiwo",
    "gn:country_code":"TW",
    "gn:dem":43,
    "gn:feature_class":"P",
    "gn:feature_code":"PPL",
    "gn:name":"Quanshuiwo",
    "gn:population":0,
    "gn:timezone":"Asia/Taipei",
    "iso:country":"TW",
    "name:und_x_variant":[
        "Cyuanshueiwo",
        "Quanshuiwo"
    ],
    "name:zho_x_preferred":[
        "\u6cc9\u6c34\u7aa9"
    ],
    "name:zho_x_variant":[
        "Ch\u2019\u00fcan-shui-wo"
    ],
    "wof:name":"Quanshuiwo",
    "wof:placetype":"locality"
},
  "geometry": {"coordinates":[120.51049999999999,22.89851],"type":"Point"}
}