{
  "type": "Feature",
  "properties": {
    "gn:admin1_code":"4.0",
    "gn:admin2_code":"NAN",
    "gn:admin3_code":"M01",
    "gn:admin4_code":"10008010023.0",
    "gn:asciiname":"Pingshan",
    "gn:country_code":"TW",
    "gn:dem":96,
    "gn:feature_class":"P",
    "gn:feature_code":"PPL",
    "gn:name":"Pingshan",
    "gn:population":0,
    "gn:timezone":"Asia/Taipei",
    "iso:country":"TW",
    "name:ceb_x_preferred":[
        "Pingshan"
    ],
    "name:deu_x_preferred":[
        "Pingshan"
    ],
    "name:fra_x_preferred":[
        "Pingshan"
    ],
    "name:mlg_x_preferred":[
        "Pingshan"
    ],
    "name:nor_x_preferred":[
        "Pingshan"
    ],
    "name:rus_x_preferred":[
        "\u041f\u0438\u043d\u0448\u0430\u043d\u044c"
    ],
    "name:swe_x_preferred":[
        "Pingshan"
    ],
    "name:zho_x_preferred":[
        "\u5e73\u5c71"
    ],
    "name:zho_x_variant":[
        "P\u2019ing-shan"
    ],
    "wof:name":"Pingshan",
    "wof:placetype":"locality"
},
  "geometry": {"coordinates":[120.67624000000001,23.92547],"type":"Point"}
}