{
  "type": "Feature",
  "properties": {
    "gn:admin1_code":"3.0",
    "gn:admin2_code":"TPQ",
    "gn:admin3_code":"F24",
    "gn:admin4_code":"65000260001.0",
    "gn:asciiname":"Changtai",
    "gn:country_code":"TW",
    "gn:dem":43,
    "gn:feature_class":"P",
    "gn:feature_code":"PPL",
    "gn:name":"Changtai",
    "gn:population":0,
    "gn:timezone":"Asia/Taipei",
    "iso:country":"TW",
    "name:zho_x_preferred":[
        "\u9577\u6cf0"
    ],
    "name:zho_x_variant":[
        "Ch\u2019ang-t\u2019ai"
    ],
    "wof:name":"Changtai",
    "wof:placetype":"locality"
},
  "geometry": {"coordinates":[121.89037,25.02088],"type":"Point"}
}