{
  "type": "Feature",
  "properties": {
    "gn:admin1_code":"4.0",
    "gn:admin2_code":"CYQ",
    "gn:admin3_code":"Q15",
    "gn:admin4_code":"10010140024.0",
    "gn:asciiname":"Guoxi",
    "gn:country_code":"TW",
    "gn:dem":1069,
    "gn:feature_class":"P",
    "gn:feature_code":"PPL",
    "gn:name":"Guoxi",
    "gn:population":0,
    "gn:timezone":"Asia/Taipei",
    "iso:country":"TW",
    "name:und_x_variant":[
        "Guosi",
        "Kuo-hsi"
    ],
    "name:zho_x_preferred":[
        "\u904e\u6eaa"
    ],
    "wof:name":"Guoxi",
    "wof:placetype":"locality"
},
  "geometry": {"coordinates":[120.68235,23.47537],"type":"Point"}
}