{
  "type": "Feature",
  "properties": {
    "gn:admin1_code":"2.0",
    "gn:admin2_code":"KHH",
    "gn:admin3_code":"E15",
    "gn:admin4_code":"64000150012.0",
    "gn:asciiname":"Chishanhu",
    "gn:country_code":"TW",
    "gn:dem":139,
    "gn:feature_class":"P",
    "gn:feature_code":"PPL",
    "gn:name":"Chishanhu",
    "gn:population":0,
    "gn:timezone":"Asia/Taipei",
    "iso:country":"TW",
    "name:und_x_variant":[
        "\u8d64\u5c71\u6e56",
        "Chihshanhu",
        "Chishanhu"
    ],
    "name:zho_x_preferred":[
        "Ch\u2019ih-shan-hu"
    ],
    "name:zho_x_variant":[
        "\u8d64\u5c71\u6e56"
    ],
    "wof:name":"Chishanhu",
    "wof:placetype":"locality"
},
  "geometry": {"coordinates":[120.39525,22.69008],"type":"Point"}
}