{
  "type": "Feature",
  "properties": {
    "iso:country":"TW",
    "name:deu_x_preferred":[
        "Xinwu"
    ],
    "name:eng_x_preferred":[
        "Sinwu"
    ],
    "name:hak_x_preferred":[
        "S\u00een-vuk-hi\u00f4ng"
    ],
    "name:jpn_x_preferred":[
        "\u65b0\u5c4b\u533a"
    ],
    "name:kor_x_preferred":[
        "\uc2e0\uc6b0\uad6c"
    ],
    "name:lit_x_preferred":[
        "Sinvu"
    ],
    "name:nan_x_preferred":[
        "Sin-ok-khu"
    ],
    "name:pol_x_preferred":[
        "Xinwu"
    ],
    "name:vie_x_preferred":[
        "T\u00e2n \u1ed0c"
    ],
    "name:zho_x_preferred":[
        "\u65b0\u5c4b\u5340"
    ],
    "qs:name":"\u65b0\u5c4b\u9109",
    "qs:name_adm0":"\u81fa\u7063",
    "qs:name_adm1":"\u6843\u5712\u7e23",
    "qs:photos":807,
    "qs:photos_1k":164,
    "qs:photos_9k":4,
    "qs:photos_9r":6,
    "qs:photos_all":807,
    "qs:photos_sr":9,
    "qs:placetype":"County",
    "qs:pop_sr":"0",
    "wd:wordcount":310,
    "wof:name":"\u65b0\u5c4b\u9109",
    "wof:placetype":"county"
},
  "geometry": {"coordinates":[121.02014699999999,24.988144],"type":"Point"}
}