{
  "type": "Feature",
  "properties": {
    "gn:admin1_code":"3.0",
    "gn:admin2_code":"TPQ",
    "gn:admin3_code":"F11",
    "gn:admin4_code":"65000290002.0",
    "gn:asciiname":"Honghe",
    "gn:country_code":"TW",
    "gn:dem":104,
    "gn:feature_class":"P",
    "gn:feature_code":"PPL",
    "gn:name":"Honghe",
    "gn:population":0,
    "gn:timezone":"Asia/Taipei",
    "iso:country":"TW",
    "name:und_x_variant":[
        "Chia-chiu-liao",
        "Hung-ho"
    ],
    "name:zho_x_preferred":[
        "\u7d05\u6cb3"
    ],
    "wof:name":"Honghe",
    "wof:placetype":"locality"
},
  "geometry": {"coordinates":[121.54011,24.88411],"type":"Point"}
}