{
  "type": "Feature",
  "properties": {
    "gn:admin1_code":"4.0",
    "gn:admin2_code":"CHA",
    "gn:admin3_code":"N03",
    "gn:admin4_code":"10007030028.0",
    "gn:asciiname":"Dongxidi",
    "gn:country_code":"TW",
    "gn:dem":10,
    "gn:feature_class":"P",
    "gn:feature_code":"PPL",
    "gn:name":"Dongxidi",
    "gn:population":0,
    "gn:timezone":"Asia/Taipei",
    "iso:country":"TW",
    "name:und_x_variant":[
        "Dongsidi",
        "Dongxidi",
        "Tung-hsi-ti"
    ],
    "name:zho_x_preferred":[
        "\u6771\u6eaa\u5e95"
    ],
    "wof:name":"Dongxidi",
    "wof:placetype":"locality"
},
  "geometry": {"coordinates":[120.51125,24.15512],"type":"Point"}
}