{
  "type": "Feature",
  "properties": {
    "gn:admin1_code":"03",
    "gn:admin2_code":"TPQ",
    "gn:admin3_code":"F23",
    "gn:admin4_code":"65000250012.0",
    "gn:asciiname":"Poziliao",
    "gn:country_code":"TW",
    "gn:dem":447,
    "gn:feature_class":"P",
    "gn:feature_code":"PPL",
    "gn:name":"Poziliao",
    "gn:population":0,
    "gn:timezone":"Asia/Taipei",
    "iso:country":"TW",
    "name:und_x_variant":[
        "Pozihliao",
        "Poziliao"
    ],
    "name:zho_x_preferred":[
        "\u7834\u5b50\u5bee"
    ],
    "name:zho_x_variant":[
        "P\u2019o-tzu-liao"
    ],
    "wof:name":"Poziliao",
    "wof:placetype":"locality"
},
  "geometry": {"coordinates":[121.84389,24.98611],"type":"Point"}
}