{
  "type": "Feature",
  "properties": {
    "gn:admin1_code":"4.0",
    "gn:admin2_code":"ILA",
    "gn:admin3_code":"G07",
    "gn:admin4_code":"10002090001.0",
    "gn:asciiname":"Xingzhangdi",
    "gn:country_code":"TW",
    "gn:dem":9,
    "gn:feature_class":"P",
    "gn:feature_code":"PPL",
    "gn:name":"Xingzhangdi",
    "gn:population":0,
    "gn:timezone":"Asia/Taipei",
    "iso:country":"TW",
    "name:und_x_variant":[
        "Singjhangdi",
        "Xingzhangdi",
        "Hsing-chang-ti"
    ],
    "name:zho_x_preferred":[
        "\u59d3\u5f35\u5e95"
    ],
    "wof:name":"Xingzhangdi",
    "wof:placetype":"locality"
},
  "geometry": {"coordinates":[121.77579,24.70435],"type":"Point"}
}