{
  "type": "Feature",
  "properties": {
    "gn:admin1_code":"4.0",
    "gn:admin2_code":"NAN",
    "gn:admin3_code":"M08",
    "gn:admin4_code":"10008080015.0",
    "gn:asciiname":"Zhucong",
    "gn:country_code":"TW",
    "gn:dem":160,
    "gn:feature_class":"P",
    "gn:feature_code":"PPL",
    "gn:name":"Zhucong",
    "gn:population":0,
    "gn:timezone":"Asia/Taipei",
    "iso:country":"TW",
    "name:und_x_variant":[
        "Jhucong",
        "Zhucong"
    ],
    "name:zho_x_preferred":[
        "\u7af9\u6b09"
    ],
    "name:zho_x_variant":[
        "Chu-ts\u2019ung"
    ],
    "wof:name":"Zhucong",
    "wof:placetype":"locality"
},
  "geometry": {"coordinates":[120.7343,23.9233],"type":"Point"}
}