{
  "type": "Feature",
  "properties": {
    "gn:admin1_code":"4.0",
    "gn:admin2_code":"ILA",
    "gn:admin3_code":"G07",
    "gn:admin4_code":"10002090001.0",
    "gn:asciiname":"Xidicheng",
    "gn:country_code":"TW",
    "gn:dem":9,
    "gn:feature_class":"P",
    "gn:feature_code":"PPL",
    "gn:name":"Xidicheng",
    "gn:population":0,
    "gn:timezone":"Asia/Taipei",
    "iso:country":"TW",
    "name:und_x_variant":[
        "Sidicheng",
        "Xidicheng"
    ],
    "name:zho_x_preferred":[
        "Ch\u2019i-ti-ch\u2019eng"
    ],
    "name:zho_x_variant":[
        "\u6eaa\u5e95\u57ce",
        "Hsi-ti-ch\u2019eng"
    ],
    "wof:name":"Xidicheng",
    "wof:placetype":"locality"
},
  "geometry": {"coordinates":[121.77607,24.71007],"type":"Point"}
}