{
  "type": "Feature",
  "properties": {
    "gn:admin1_code":"4.0",
    "gn:admin2_code":"TTT",
    "gn:admin3_code":"V11",
    "gn:admin4_code":"10014110002.0",
    "gn:asciiname":"Zhongliao",
    "gn:country_code":"TW",
    "gn:dem":13,
    "gn:feature_class":"P",
    "gn:feature_code":"PPL",
    "gn:name":"Zhongliao",
    "gn:population":0,
    "gn:timezone":"Asia/Taipei",
    "iso:country":"TW",
    "name:deu_x_preferred":[
        "Zhongliao"
    ],
    "name:hak_x_preferred":[
        "Ch\u00fbng-li\u00e0u-hi\u00f4ng"
    ],
    "name:jpn_x_preferred":[
        "\u4e2d\u5bee\u90f7"
    ],
    "name:kor_x_preferred":[
        "\uc911\ub7b4\uc624\ud5a5"
    ],
    "name:pol_x_preferred":[
        "Zhongliao"
    ],
    "name:und_x_variant":[
        "Shan-tzu-chiao",
        "Zhongliao",
        "Jhongliao",
        "Chung-liao"
    ],
    "name:vie_x_preferred":[
        "Trung Li\u00eau"
    ],
    "name:zho_x_preferred":[
        "\u4e2d\u5bee"
    ],
    "name:zho_x_variant":[
        "\u4e2d\u5bee\u9109"
    ],
    "wof:name":"Zhongliao",
    "wof:placetype":"locality"
},
  "geometry": {"coordinates":[121.47194,22.67417],"type":"Point"}
}