{
  "type": "Feature",
  "properties": {
    "gn:admin1_code":"4.0",
    "gn:admin2_code":"TTT",
    "gn:admin3_code":"V11",
    "gn:admin4_code":"10014110002.0",
    "gn:asciiname":"Zhongliao",
    "gn:country_code":"TW",
    "gn:dem":13,
    "gn:feature_class":"P",
    "gn:feature_code":"PPL",
    "gn:name":"Zhongliao",
    "gn:population":0,
    "gn:timezone":"Asia/Taipei",
    "iso:country":"TW",
    "name:und_x_variant":[
        "Shan-tzu-chiao",
        "Zhongliao",
        "Jhongliao",
        "Chung-liao"
    ],
    "name:zho_x_preferred":[
        "\u4e2d\u5bee"
    ],
    "wof:name":"Zhongliao",
    "wof:placetype":"locality"
},
  "geometry": {"coordinates":[121.47194,22.67417],"type":"Point"}
}