{
  "type": "Feature",
  "properties": {
    "gn:admin1_code":"4.0",
    "gn:admin2_code":"NAN",
    "gn:admin3_code":"M03",
    "gn:admin4_code":"10008030022.0",
    "gn:asciiname":"Shutengyan",
    "gn:country_code":"TW",
    "gn:dem":461,
    "gn:feature_class":"P",
    "gn:feature_code":"PPL",
    "gn:name":"Shutengyan",
    "gn:population":0,
    "gn:timezone":"Asia/Taipei",
    "iso:country":"TW",
    "name:zho_x_preferred":[
        "\u6a39\u85e4\u5ca9"
    ],
    "name:zho_x_variant":[
        "Shu-t\u2019eng-yen"
    ],
    "wof:name":"Shutengyan",
    "wof:placetype":"locality"
},
  "geometry": {"coordinates":[120.80682,23.98102],"type":"Point"}
}