{
  "type": "Feature",
  "properties": {
    "gn:admin1_code":"4.0",
    "gn:admin2_code":"MIA",
    "gn:admin3_code":"K18",
    "gn:admin4_code":"10005180006.0",
    "gn:asciiname":"Tai-an Township",
    "gn:country_code":"TW",
    "gn:dem":988,
    "gn:feature_class":"P",
    "gn:feature_code":"PPL",
    "gn:name":"Tai-an Township",
    "gn:population":0,
    "gn:timezone":"Asia/Taipei",
    "iso:country":"TW",
    "wof:name":"Tai-an Township",
    "wof:placetype":"locality"
},
  "geometry": {"coordinates":[121.03122999999999,24.3915],"type":"Point"}
}