{
  "type": "Feature",
  "properties": {
    "gn:admin1_code":"4.0",
    "gn:admin2_code":"MIA",
    "gn:admin3_code":"K05",
    "gn:admin4_code":"10005100007.0",
    "gn:asciiname":"Zhongxinbu",
    "gn:country_code":"TW",
    "gn:dem":98,
    "gn:feature_class":"P",
    "gn:feature_code":"PPL",
    "gn:name":"Zhongxinbu",
    "gn:population":0,
    "gn:timezone":"Asia/Taipei",
    "iso:country":"TW",
    "name:und_x_variant":[
        "Jhongsinbu",
        "Chung-hsin-pu"
    ],
    "name:zho_x_preferred":[
        "\u4e2d\u5fc3\u57d4"
    ],
    "wof:name":"Zhongxinbu",
    "wof:placetype":"locality"
},
  "geometry": {"coordinates":[120.80517,24.50285],"type":"Point"}
}