{
  "type": "Feature",
  "properties": {
    "gn:admin1_code":"3.0",
    "gn:admin2_code":"TPQ",
    "gn:admin3_code":"F31",
    "gn:admin4_code":"65000220001.0",
    "gn:asciiname":"Demao",
    "gn:country_code":"TW",
    "gn:dem":30,
    "gn:feature_class":"P",
    "gn:feature_code":"PPL",
    "gn:name":"Demao",
    "gn:population":0,
    "gn:timezone":"Asia/Taipei",
    "iso:country":"TW",
    "name:und_x_variant":[
        "Te-mao"
    ],
    "name:zho_x_preferred":[
        "\u5fb7\u8302"
    ],
    "wof:name":"Demao",
    "wof:placetype":"locality"
},
  "geometry": {"coordinates":[121.52589,25.2847],"type":"Point"}
}