{
  "type": "Feature",
  "properties": {
    "gn:admin1_code":"4.0",
    "gn:admin2_code":"PIF",
    "gn:admin3_code":"T30",
    "gn:admin4_code":"10013300007.0",
    "gn:asciiname":"Xinpi",
    "gn:country_code":"TW",
    "gn:dem":58,
    "gn:feature_class":"P",
    "gn:feature_code":"PPL",
    "gn:name":"Xinpi",
    "gn:population":0,
    "gn:timezone":"Asia/Taipei",
    "iso:country":"TW",
    "name:hak_x_preferred":[
        "S\u00een-ph\u00ee-hi\u00f4ng"
    ],
    "name:jpn_x_preferred":[
        "\u65b0\u30d4\u90f7"
    ],
    "name:kor_x_preferred":[
        "\uc2e0\ud53c\ud5a5"
    ],
    "name:und_x_variant":[
        "\u65b0\u57e4",
        "Xinpi",
        "Sinpi"
    ],
    "name:vie_x_preferred":[
        "T\u00e2n B\u00ec"
    ],
    "name:zho_x_preferred":[
        "Hsin-p\u2019i"
    ],
    "name:zho_x_variant":[
        "\u65b0\u57e4\u9109"
    ],
    "wof:name":"Xinpi",
    "wof:placetype":"locality"
},
  "geometry": {"coordinates":[120.61444,22.44722],"type":"Point"}
}