{
  "type": "Feature",
  "properties": {
    "gn:admin1_code":"4.0",
    "gn:admin2_code":"PIF",
    "gn:admin3_code":"T30",
    "gn:admin4_code":"10013300007.0",
    "gn:asciiname":"Xinpi",
    "gn:country_code":"TW",
    "gn:dem":58,
    "gn:feature_class":"P",
    "gn:feature_code":"PPL",
    "gn:name":"Xinpi",
    "gn:population":0,
    "gn:timezone":"Asia/Taipei",
    "iso:country":"TW",
    "name:und_x_variant":[
        "\u65b0\u57e4",
        "Xinpi",
        "Sinpi",
        "Hsin-p\u2019i"
    ],
    "name:zho_x_preferred":[
        "Hsin-p\u2019i"
    ],
    "wof:name":"Xinpi",
    "wof:placetype":"locality"
},
  "geometry": {"coordinates":[120.61444,22.44722],"type":"Point"}
}