{
  "type": "Feature",
  "properties": {
    "gn:admin1_code":"2.0",
    "gn:admin2_code":"KHH",
    "gn:admin3_code":"E23",
    "gn:admin4_code":"64000230009.0",
    "gn:asciiname":"Qingqijia",
    "gn:country_code":"TW",
    "gn:dem":23,
    "gn:feature_class":"P",
    "gn:feature_code":"PPL",
    "gn:name":"Qingqijia",
    "gn:population":0,
    "gn:timezone":"Asia/Taipei",
    "iso:country":"TW",
    "name:und_x_variant":[
        "Cingcijia",
        "Qingqijia"
    ],
    "name:zho_x_preferred":[
        "Ch\u2019ing-ch\u2019i-ts\u2019un"
    ],
    "name:zho_x_variant":[
        "\u9752\u65d7\u7532",
        "Ch\u2019ing-ch\u2019i",
        "Ch\u2019ing-ch\u2019i-chia"
    ],
    "wof:name":"Qingqijia",
    "wof:placetype":"locality"
},
  "geometry": {"coordinates":[120.3175,22.89139],"type":"Point"}
}