{
  "type": "Feature",
  "properties": {
    "gn:admin1_code":"3.0",
    "gn:admin2_code":"TPQ",
    "gn:admin3_code":"F02",
    "gn:admin4_code":"65000170001.0",
    "gn:asciiname":"Fenliaoshuiwei",
    "gn:country_code":"TW",
    "gn:dem":215,
    "gn:feature_class":"P",
    "gn:feature_code":"PPL",
    "gn:name":"Fenliaoshuiwei",
    "gn:population":0,
    "gn:timezone":"Asia/Taipei",
    "iso:country":"TW",
    "name:und_x_variant":[
        "Fenliaoshueiwei",
        "Fen-liao-shui-wei"
    ],
    "name:zho_x_preferred":[
        "\u7c89\u5bee\u6c34\u5c3e"
    ],
    "wof:name":"Fenliaoshuiwei",
    "wof:placetype":"locality"
},
  "geometry": {"coordinates":[121.4057,25.09800000000001],"type":"Point"}
}