{
  "type": "Feature",
  "properties": {
    "iso:country":"TW",
    "qs:name":"\u6a4b\u982d\u9109",
    "qs:name_adm0":"\u81fa\u7063",
    "qs:name_adm1":"\u9ad8\u96c4\u5e02",
    "qs:photos":5280,
    "qs:photos_1k":1000,
    "qs:photos_9k":26,
    "qs:photos_9r":14,
    "qs:photos_all":5909,
    "qs:photos_sr":24,
    "qs:placetype":"County",
    "qs:pop_sr":"0",
    "wd:wordcount":114,
    "wof:name":"\u6a4b\u982d\u9109",
    "wof:placetype":"county"
},
  "geometry": {"coordinates":[120.313317,22.754456],"type":"Point"}
}