{
  "type": "Feature",
  "properties": {
    "iso:country":"TW",
    "name:eng_x_preferred":[
        "Gonghe"
    ],
    "name:eng_x_variant":[
        "Gonghe Village"
    ],
    "name:zho_tw_x_preferred":[
        "\u5171\u548c\u6751"
    ],
    "qs:name":"\u5171\u548c\u6751",
    "qs:name_adm0":"\u81fa\u7063",
    "qs:name_adm1":"\u65b0\u5317\u5e02",
    "qs:photos":18,
    "qs:photos_1k":4,
    "qs:photos_9k":1,
    "qs:photos_9r":1,
    "qs:photos_all":18,
    "qs:photos_sr":1,
    "qs:placetype":"Town",
    "qs:pop_sr":"0",
    "wof:name":"Gonghe",
    "wof:placetype":"locality"
},
  "geometry": {"coordinates":[121.858694,25.022589],"type":"Point"}
}