{
  "type": "Feature",
  "properties": {
    "gn:admin1_code":"4.0",
    "gn:admin2_code":"CYQ",
    "gn:admin3_code":"Q17",
    "gn:admin4_code":"10010160008.0",
    "gn:asciiname":"Kanjiao",
    "gn:country_code":"TW",
    "gn:dem":595,
    "gn:feature_class":"P",
    "gn:feature_code":"PPL",
    "gn:name":"Kanjiao",
    "gn:population":0,
    "gn:timezone":"Asia/Taipei",
    "iso:country":"TW",
    "name:und_x_variant":[
        "\u5d01\u8173",
        "Kanjiao"
    ],
    "name:zho_x_preferred":[
        "K\u2019an-chiao"
    ],
    "name:zho_x_variant":[
        "\u5d01\u8173"
    ],
    "wof:name":"Kanjiao",
    "wof:placetype":"locality"
},
  "geometry": {"coordinates":[120.62269999999999,23.47199],"type":"Point"}
}