{
  "type": "Feature",
  "properties": {
    "gn:admin1_code":"4.0",
    "gn:admin2_code":"CYQ",
    "gn:admin3_code":"Q03",
    "gn:admin4_code":"10010030014.0",
    "gn:asciiname":"Houdonggang",
    "gn:country_code":"TW",
    "gn:dem":6,
    "gn:feature_class":"P",
    "gn:feature_code":"PPL",
    "gn:name":"Houdonggang",
    "gn:population":0,
    "gn:timezone":"Asia/Taipei",
    "iso:country":"TW",
    "name:und_x_variant":[
        "Hou-tung-kang"
    ],
    "name:zho_x_preferred":[
        "\u5f8c\u6771\u6e2f"
    ],
    "wof:name":"Houdonggang",
    "wof:placetype":"locality"
},
  "geometry": {"coordinates":[120.18989999999999,23.3766],"type":"Point"}
}