{
  "type": "Feature",
  "properties": {
    "gn:admin1_code":"4.0",
    "gn:admin2_code":"TNN",
    "gn:admin3_code":"R27",
    "gn:admin4_code":"67000270006.0",
    "gn:asciiname":"Qigan",
    "gn:country_code":"TW",
    "gn:dem":14,
    "gn:feature_class":"P",
    "gn:feature_code":"PPL",
    "gn:name":"Qigan",
    "gn:population":0,
    "gn:timezone":"Asia/Taipei",
    "iso:country":"TW",
    "name:und_x_variant":[
        "Cigan"
    ],
    "name:zho_x_preferred":[
        "\u675e\u7aff"
    ],
    "name:zho_x_variant":[
        "Ch\u2019i-y\u00fc",
        "Ch\u2019i-kan"
    ],
    "wof:name":"Qigan",
    "wof:placetype":"locality"
},
  "geometry": {"coordinates":[120.26333,22.95028],"type":"Point"}
}