{
  "type": "Feature",
  "properties": {
    "gn:admin1_code":"4.0",
    "gn:admin2_code":"NAN",
    "gn:admin3_code":"M02",
    "gn:admin4_code":"10008020026.0",
    "gn:asciiname":"Neibu",
    "gn:country_code":"TW",
    "gn:dem":516,
    "gn:feature_class":"P",
    "gn:feature_code":"PPL",
    "gn:name":"Neibu",
    "gn:population":0,
    "gn:timezone":"Asia/Taipei",
    "iso:country":"TW",
    "name:und_x_variant":[
        "Nei-pu"
    ],
    "name:zho_x_preferred":[
        "\u5185\u57d4"
    ],
    "wof:name":"Neibu",
    "wof:placetype":"locality"
},
  "geometry": {"coordinates":[121.00081000000002,23.98539],"type":"Point"}
}