{
  "type": "Feature",
  "properties": {
    "gn:admin1_code":"02",
    "gn:admin2_code":"KHH",
    "gn:admin3_code":"E14",
    "gn:admin4_code":"64000140005.0",
    "gn:asciiname":"Sanlong",
    "gn:country_code":"TW",
    "gn:dem":13,
    "gn:feature_class":"P",
    "gn:feature_code":"PPL",
    "gn:name":"Sanlong",
    "gn:population":0,
    "gn:timezone":"Asia/Taipei",
    "iso:country":"TW",
    "name:und_x_variant":[
        "San-lung",
        "Sanlong"
    ],
    "name:zho_x_preferred":[
        "San-lung-ts\u2019un"
    ],
    "name:zho_x_variant":[
        "\u4e09\u9686"
    ],
    "wof:name":"Sanlong",
    "wof:placetype":"locality"
},
  "geometry": {"coordinates":[120.40233000000001,22.59653],"type":"Point"}
}