{
  "type": "Feature",
  "properties": {
    "gn:admin1_code":"4.0",
    "gn:admin2_code":"MIA",
    "gn:admin3_code":"K17",
    "gn:admin4_code":"10005170007.0",
    "gn:asciiname":"Qigulin",
    "gn:country_code":"TW",
    "gn:dem":328,
    "gn:feature_class":"P",
    "gn:feature_code":"PPL",
    "gn:name":"Qigulin",
    "gn:population":0,
    "gn:timezone":"Asia/Taipei",
    "iso:country":"TW",
    "name:und_x_variant":[
        "Cigulin",
        "Qigulin"
    ],
    "name:zho_x_preferred":[
        "\u4e03\u80a1\u6797"
    ],
    "name:zho_x_variant":[
        "Ch\u2019i-ku-lin"
    ],
    "wof:name":"Qigulin",
    "wof:placetype":"locality"
},
  "geometry": {"coordinates":[120.89839000000001,24.44695],"type":"Point"}
}