{
  "type": "Feature",
  "properties": {
    "gn:admin1_code":"04",
    "gn:admin2_code":"HSZ",
    "gn:admin3_code":"J09",
    "gn:admin4_code":"10004060016.0",
    "gn:asciiname":"Wanggaolou",
    "gn:country_code":"TW",
    "gn:dem":79,
    "gn:feature_class":"P",
    "gn:feature_code":"PPL",
    "gn:name":"Wanggaolou",
    "gn:population":0,
    "gn:timezone":"Asia/Taipei",
    "iso:country":"TW",
    "name:und_x_variant":[
        "Wang-kao-lou"
    ],
    "wof:name":"Wanggaolou",
    "wof:placetype":"locality"
},
  "geometry": {"coordinates":[120.98333,24.86667000000001],"type":"Point"}
}