{
  "type": "Feature",
  "properties": {
    "gn:admin1_code":"2.0",
    "gn:admin2_code":"KHH",
    "gn:admin3_code":"E32",
    "gn:admin4_code":"64000320004.0",
    "gn:asciiname":"Xiaxinkai",
    "gn:country_code":"TW",
    "gn:dem":378,
    "gn:feature_class":"P",
    "gn:feature_code":"PPL",
    "gn:name":"Xiaxinkai",
    "gn:population":0,
    "gn:timezone":"Asia/Taipei",
    "iso:country":"TW",
    "name:und_x_variant":[
        "Siasinkai"
    ],
    "name:zho_x_preferred":[
        "\u4e0b\u65b0\u958b"
    ],
    "name:zho_x_variant":[
        "Hsia-hsin-k\u2019ai"
    ],
    "wof:name":"Xiaxinkai",
    "wof:placetype":"locality"
},
  "geometry": {"coordinates":[120.68277999999999,23.06333],"type":"Point"}
}