{
  "type": "Feature",
  "properties": {
    "gn:admin1_code":"4.0",
    "gn:admin2_code":"TXG",
    "gn:admin3_code":"B10",
    "gn:admin4_code":"66000100017.0",
    "gn:asciiname":"Xiabanzhuang",
    "gn:country_code":"TW",
    "gn:dem":474,
    "gn:feature_class":"P",
    "gn:feature_code":"PPL",
    "gn:name":"Xiabanzhuang",
    "gn:population":0,
    "gn:timezone":"Asia/Taipei",
    "iso:country":"TW",
    "name:und_x_variant":[
        "Siabanjhuang",
        "Hsia-pan-chuang"
    ],
    "name:zho_x_preferred":[
        "\u4e0b\u534a\u5e84"
    ],
    "wof:name":"Xiabanzhuang",
    "wof:placetype":"locality"
},
  "geometry": {"coordinates":[120.84945,24.18834],"type":"Point"}
}