{
  "type": "Feature",
  "properties": {
    "gn:admin1_code":"4.0",
    "gn:admin2_code":"TNN",
    "gn:admin3_code":"R19",
    "gn:admin4_code":"67000190010.0",
    "gn:asciiname":"Xiwei",
    "gn:country_code":"TW",
    "gn:dem":14,
    "gn:feature_class":"P",
    "gn:feature_code":"PPL",
    "gn:name":"Xiwei",
    "gn:population":0,
    "gn:timezone":"Asia/Taipei",
    "iso:country":"TW",
    "name:und_x_variant":[
        "Siwei",
        "Hsi-wei"
    ],
    "name:zho_x_preferred":[
        "\u897f\u885e"
    ],
    "wof:name":"Xiwei",
    "wof:placetype":"locality"
},
  "geometry": {"coordinates":[120.26139000000001,23.13472],"type":"Point"}
}