{
  "type": "Feature",
  "properties": {
    "gn:admin1_code":"4.0",
    "gn:admin2_code":"NAN",
    "gn:admin3_code":"M09",
    "gn:admin4_code":"10008090009.0",
    "gn:asciiname":"Huopeikeng",
    "gn:country_code":"TW",
    "gn:dem":596,
    "gn:feature_class":"P",
    "gn:feature_code":"PPL",
    "gn:name":"Huopeikeng",
    "gn:population":0,
    "gn:timezone":"Asia/Taipei",
    "iso:country":"TW",
    "name:zho_x_preferred":[
        "Hua-p\u2019ei-k\u2019eng"
    ],
    "name:zho_x_variant":[
        "\u706b\u57f9\u5751",
        "Huo-p\u2019ei-k\u2019eng"
    ],
    "wof:name":"Huopeikeng",
    "wof:placetype":"locality"
},
  "geometry": {"coordinates":[120.89503000000001,23.91183],"type":"Point"}
}