{
  "type": "Feature",
  "properties": {
    "gn:admin1_code":"3.0",
    "gn:admin2_code":"TPQ",
    "gn:admin3_code":"F07",
    "gn:admin4_code":"65000060017.0",
    "gn:asciiname":"Chezilu",
    "gn:country_code":"TW",
    "gn:dem":30,
    "gn:feature_class":"P",
    "gn:feature_code":"PPL",
    "gn:name":"Chezilu",
    "gn:population":0,
    "gn:timezone":"Asia/Taipei",
    "iso:country":"TW",
    "name:und_x_variant":[
        "Chezihlu"
    ],
    "name:zho_x_preferred":[
        "\u8eca\u5b50\u8def"
    ],
    "name:zho_x_variant":[
        "Ch\u2019e-tzu-lu"
    ],
    "wof:name":"Chezilu",
    "wof:placetype":"locality"
},
  "geometry": {"coordinates":[121.50727999999999,24.95709],"type":"Point"}
}