{
  "type": "Feature",
  "properties": {
    "gn:admin1_code":"4.0",
    "gn:admin2_code":"TXG",
    "gn:admin3_code":"B27",
    "gn:admin4_code":"66000270035.0",
    "gn:asciiname":"Sanyao",
    "gn:country_code":"TW",
    "gn:dem":260,
    "gn:feature_class":"P",
    "gn:feature_code":"PPL",
    "gn:name":"Sanyao",
    "gn:population":0,
    "gn:timezone":"Asia/Taipei",
    "iso:country":"TW",
    "name:und_x_variant":[
        "San-yao"
    ],
    "name:zho_x_preferred":[
        "\u4e09\u78d8"
    ],
    "wof:name":"Sanyao",
    "wof:placetype":"locality"
},
  "geometry": {"coordinates":[120.75440999999999,24.15422],"type":"Point"}
}