{
  "type": "Feature",
  "properties": {
    "gn:admin1_code":"04",
    "gn:admin2_code":"NAN",
    "gn:admin3_code":"M02",
    "gn:admin4_code":"10008020029.0",
    "gn:asciiname":"Shouzhengong",
    "gn:country_code":"TW",
    "gn:dem":640,
    "gn:feature_class":"P",
    "gn:feature_code":"PPL",
    "gn:name":"Shouzhengong",
    "gn:population":0,
    "gn:timezone":"Asia/Taipei",
    "iso:country":"TW",
    "name:und_x_variant":[
        "Shou-chen-kung"
    ],
    "wof:name":"Shouzhengong",
    "wof:placetype":"locality"
},
  "geometry": {"coordinates":[120.93333,24.03333],"type":"Point"}
}