{
  "type": "Feature",
  "properties": {
    "iso:country":"TW",
    "qs:name":"\u5357\u5751\u6751",
    "qs:name_adm0":"\u81fa\u7063",
    "qs:name_adm1":"\u65b0\u7af9\u7e23",
    "qs:photos":24,
    "qs:photos_1k":5,
    "qs:photos_9k":1,
    "qs:photos_9r":1,
    "qs:photos_all":24,
    "qs:photos_sr":1,
    "qs:placetype":"Town",
    "qs:pop_sr":"0",
    "wof:name":"\u5357\u5751\u6751",
    "wof:placetype":"locality"
},
  "geometry": {"coordinates":[121.046762,24.661994],"type":"Point"}
}