{
  "type": "Feature",
  "properties": {
    "gn:admin1_code":"4.0",
    "gn:admin2_code":"HUA",
    "gn:admin3_code":"U06",
    "gn:admin4_code":"10015060015.0",
    "gn:asciiname":"Lingding",
    "gn:country_code":"TW",
    "gn:dem":31,
    "gn:feature_class":"P",
    "gn:feature_code":"PPL",
    "gn:name":"Lingding",
    "gn:population":0,
    "gn:timezone":"Asia/Taipei",
    "iso:country":"TW",
    "name:und_x_variant":[
        "Ling-ting",
        "Lingding",
        "\u5dba\u9802"
    ],
    "name:zho_x_preferred":[
        "\u5dba\u9802"
    ],
    "wof:name":"Lingding",
    "wof:placetype":"locality"
},
  "geometry": {"coordinates":[121.60693999999999,23.92667],"type":"Point"}
}