{
  "type": "Feature",
  "properties": {
    "gn:admin1_code":"03",
    "gn:admin2_code":"TPQ",
    "gn:admin3_code":"F07",
    "gn:admin4_code":"65000060027.0",
    "gn:asciiname":"Siqianshui",
    "gn:country_code":"TW",
    "gn:dem":433,
    "gn:feature_class":"P",
    "gn:feature_code":"PPL",
    "gn:name":"Siqianshui",
    "gn:population":0,
    "gn:timezone":"Asia/Taipei",
    "iso:country":"TW",
    "name:und_x_variant":[
        "Sihcianshuei",
        "Siqianshui"
    ],
    "name:zho_x_preferred":[
        "Ssu-k\u2019an-shui"
    ],
    "name:zho_x_variant":[
        "\u56db\u5d4c\u6c34",
        "Ssu-ch\u2019ien-shui"
    ],
    "wof:name":"Siqianshui",
    "wof:placetype":"locality"
},
  "geometry": {"coordinates":[121.57015,24.88586],"type":"Point"}
}