{
  "type": "Feature",
  "properties": {
    "gn:admin1_code":"4.0",
    "gn:admin2_code":"YUN",
    "gn:admin3_code":"P05",
    "gn:admin4_code":"10009050006.0",
    "gn:asciiname":"Xiawei",
    "gn:country_code":"TW",
    "gn:dem":21,
    "gn:feature_class":"P",
    "gn:feature_code":"PPL",
    "gn:name":"Xiawei",
    "gn:population":0,
    "gn:timezone":"Asia/Taipei",
    "iso:country":"TW",
    "name:und_x_variant":[
        "Hsia-chu-wei-tzu",
        "Chu-wei",
        "Xiawei",
        "Siawei",
        "Hsia-wei"
    ],
    "name:zho_x_preferred":[
        "\u4e0b\u570d"
    ],
    "wof:name":"Xiawei",
    "wof:placetype":"locality"
},
  "geometry": {"coordinates":[120.37766000000001,23.67151],"type":"Point"}
}