{
  "type": "Feature",
  "properties": {
    "gn:admin1_code":"4.0",
    "gn:admin2_code":"NAN",
    "gn:admin3_code":"M03",
    "gn:admin4_code":"10008030017.0",
    "gn:asciiname":"Xincuozi",
    "gn:country_code":"TW",
    "gn:dem":158,
    "gn:feature_class":"P",
    "gn:feature_code":"PPL",
    "gn:name":"Xincuozi",
    "gn:population":0,
    "gn:timezone":"Asia/Taipei",
    "iso:country":"TW",
    "name:und_x_variant":[
        "\u65b0\u539d\u4ed4",
        "Xincuozi",
        "Sincuozih",
        "Hsin-ts\u2019o-tzu"
    ],
    "name:zho_x_preferred":[
        "Hsin-ts\u2019o-tzu"
    ],
    "wof:name":"Xincuozi",
    "wof:placetype":"locality"
},
  "geometry": {"coordinates":[120.73003,23.99868],"type":"Point"}
}