{
  "type": "Feature",
  "properties": {
    "gn:admin1_code":"04",
    "gn:admin2_code":"HUA",
    "gn:admin3_code":"U03",
    "gn:admin4_code":"10015030006.0",
    "gn:asciiname":"Tonglin",
    "gn:country_code":"TW",
    "gn:dem":182,
    "gn:feature_class":"P",
    "gn:feature_code":"PPL",
    "gn:name":"Tonglin",
    "gn:population":0,
    "gn:timezone":"Asia/Taipei",
    "iso:country":"TW",
    "name:und_x_variant":[
        "\u6850\u6797",
        "Tonglin"
    ],
    "name:zho_x_preferred":[
        "T\u2019ung-lin"
    ],
    "name:zho_x_variant":[
        "\u6850\u6797"
    ],
    "wof:name":"Tonglin",
    "wof:placetype":"locality"
},
  "geometry": {"coordinates":[121.29456,23.30823],"type":"Point"}
}