{
  "type": "Feature",
  "properties": {
    "gn:admin1_code":"2.0",
    "gn:admin2_code":"KHH",
    "gn:admin3_code":"E30",
    "gn:admin4_code":"64000300006.0",
    "gn:asciiname":"Dalin",
    "gn:country_code":"TW",
    "gn:dem":95,
    "gn:feature_class":"P",
    "gn:feature_code":"PPL",
    "gn:name":"Dalin",
    "gn:population":0,
    "gn:timezone":"Asia/Taipei",
    "iso:country":"TW",
    "name:deu_x_preferred":[
        "Dalin"
    ],
    "name:fra_x_preferred":[
        "Dalin"
    ],
    "name:pol_x_preferred":[
        "Dalin"
    ],
    "name:und_x_variant":[
        "Ta-lin"
    ],
    "name:zho_x_preferred":[
        "\u5927\u6797"
    ],
    "wof:name":"Dalin",
    "wof:placetype":"locality"
},
  "geometry": {"coordinates":[120.51558,22.95977],"type":"Point"}
}