{
  "type": "Feature",
  "properties": {
    "gn:admin1_code":"4.0",
    "gn:admin2_code":"NAN",
    "gn:admin3_code":"M03",
    "gn:admin4_code":"10008030014.0",
    "gn:asciiname":"Beitou",
    "gn:country_code":"TW",
    "gn:dem":88,
    "gn:feature_class":"P",
    "gn:feature_code":"PPL",
    "gn:name":"Beitou",
    "gn:population":0,
    "gn:timezone":"Asia/Taipei",
    "iso:country":"TW",
    "name:und_x_variant":[
        "Hsin-chieh",
        "Beitou"
    ],
    "name:zho_x_preferred":[
        "Pei-t\u2019ou-li"
    ],
    "name:zho_x_variant":[
        "Pei-t\u2019ou-hsin-chieh",
        "\u5317\u6295",
        "Pei-t\u2019ou"
    ],
    "wof:name":"Beitou",
    "wof:placetype":"locality"
},
  "geometry": {"coordinates":[120.66267999999999,23.9838],"type":"Point"}
}