{
  "type": "Feature",
  "properties": {
    "gn:admin1_code":"04",
    "gn:admin2_code":"ILA",
    "gn:admin3_code":"G11",
    "gn:admin4_code":"10002110007.0",
    "gn:asciiname":"Taipingshan",
    "gn:country_code":"TW",
    "gn:dem":1895,
    "gn:feature_class":"P",
    "gn:feature_code":"PPL",
    "gn:name":"Taipingshan",
    "gn:population":0,
    "gn:timezone":"Asia/Taipei",
    "iso:country":"TW",
    "name:und_x_variant":[
        "Pa-pa",
        "Taipingshan"
    ],
    "name:zho_x_preferred":[
        "Ta-p\u2019ing-shan"
    ],
    "name:zho_x_variant":[
        "\u592a\u5e73\u5c71",
        "T\u2019ai-p\u2019ing",
        "T\u2019ai-p\u2019ing-shan"
    ],
    "wof:name":"Taipingshan",
    "wof:placetype":"locality"
},
  "geometry": {"coordinates":[121.53639,24.49333],"type":"Point"}
}