{
  "type": "Feature",
  "properties": {
    "gn:admin1_code":"4.0",
    "gn:admin2_code":"TXG",
    "gn:admin3_code":"B26",
    "gn:admin4_code":"66000260014.0",
    "gn:asciiname":"Chepingying",
    "gn:country_code":"TW",
    "gn:dem":90,
    "gn:feature_class":"P",
    "gn:feature_code":"PPL",
    "gn:name":"Chepingying",
    "gn:population":0,
    "gn:timezone":"Asia/Taipei",
    "iso:country":"TW",
    "name:und_x_variant":[
        "\u8eca\u5e73\u71df",
        "Chepingying"
    ],
    "name:zho_x_preferred":[
        "Ch\u2019e-p\u2019ing-ying"
    ],
    "wof:name":"Chepingying",
    "wof:placetype":"locality"
},
  "geometry": {"coordinates":[120.69920999999999,24.02615],"type":"Point"}
}