{
  "type": "Feature",
  "properties": {
    "gn:admin1_code":"04",
    "gn:admin2_code":"TXG",
    "gn:admin3_code":"B29",
    "gn:admin4_code":"66000290008.0",
    "gn:asciiname":"Miaobu",
    "gn:country_code":"TW",
    "gn:dem":1846,
    "gn:feature_class":"P",
    "gn:feature_code":"PPL",
    "gn:name":"Miaobu",
    "gn:population":0,
    "gn:timezone":"Asia/Taipei",
    "iso:country":"TW",
    "name:und_x_variant":[
        "Miao-pu"
    ],
    "name:zho_x_preferred":[
        "\u82d7\u5703"
    ],
    "wof:name":"Miaobu",
    "wof:placetype":"locality"
},
  "geometry": {"coordinates":[121.30333,24.325],"type":"Point"}
}