{
  "type": "Feature",
  "properties": {
    "gn:admin1_code":"4.0",
    "gn:admin2_code":"TNN",
    "gn:admin3_code":"R03",
    "gn:admin4_code":"67000030018.0",
    "gn:asciiname":"Fanziyuan",
    "gn:country_code":"TW",
    "gn:dem":43,
    "gn:feature_class":"P",
    "gn:feature_code":"PPL",
    "gn:name":"Fanziyuan",
    "gn:population":0,
    "gn:timezone":"Asia/Taipei",
    "iso:country":"TW",
    "name:und_x_variant":[
        "Fanzihyuan",
        "Fanziyuan"
    ],
    "name:zho_x_preferred":[
        "\u8543\u4ed4\u5712"
    ],
    "name:zho_x_variant":[
        "Fan-tzu-y\u00fcan"
    ],
    "wof:name":"Fanziyuan",
    "wof:placetype":"locality"
},
  "geometry": {"coordinates":[120.43667000000001,23.38056],"type":"Point"}
}