{
  "type": "Feature",
  "properties": {
    "gn:admin1_code":"4.0",
    "gn:admin2_code":"CHA",
    "gn:admin3_code":"N14",
    "gn:admin4_code":"10007090013.0",
    "gn:asciiname":"Zhumurukeng",
    "gn:country_code":"TW",
    "gn:dem":178,
    "gn:feature_class":"P",
    "gn:feature_code":"PPL",
    "gn:name":"Zhumurukeng",
    "gn:population":0,
    "gn:timezone":"Asia/Taipei",
    "iso:country":"TW",
    "name:und_x_variant":[
        "Jhumurukeng"
    ],
    "name:zho_x_preferred":[
        "\u8c6c\u6bcd\u4e73\u5751"
    ],
    "name:zho_x_variant":[
        "Chu-mu-ju-k\u2019eng"
    ],
    "wof:name":"Zhumurukeng",
    "wof:placetype":"locality"
},
  "geometry": {"coordinates":[120.62163,23.9871],"type":"Point"}
}