{
  "type": "Feature",
  "properties": {
    "gn:admin1_code":"4.0",
    "gn:admin2_code":"TPE",
    "gn:admin3_code":"A11",
    "gn:admin4_code":"63000080034.0",
    "gn:asciiname":"Xiangtoubu",
    "gn:country_code":"TW",
    "gn:dem":29,
    "gn:feature_class":"P",
    "gn:feature_code":"PPL",
    "gn:name":"Xiangtoubu",
    "gn:population":0,
    "gn:timezone":"Asia/Taipei",
    "iso:country":"TW",
    "name:und_x_variant":[
        "Siangtoubu",
        "Xiangtoubu"
    ],
    "name:zho_x_preferred":[
        "\u8c61\u982d\u57d4"
    ],
    "name:zho_x_variant":[
        "Hsiang-t\u2019ou-pu"
    ],
    "wof:name":"Xiangtoubu",
    "wof:placetype":"locality"
},
  "geometry": {"coordinates":[121.5913,24.99894],"type":"Point"}
}