{
  "type": "Feature",
  "properties": {
    "gn:admin1_code":"4.0",
    "gn:admin2_code":"TTT",
    "gn:admin3_code":"V09",
    "gn:admin4_code":"10014050004.0",
    "gn:asciiname":"Yongde",
    "gn:country_code":"TW",
    "gn:dem":238,
    "gn:feature_class":"P",
    "gn:feature_code":"PPL",
    "gn:name":"Yongde",
    "gn:population":0,
    "gn:timezone":"Asia/Taipei",
    "iso:country":"TW",
    "name:und_x_variant":[
        "Yung-te"
    ],
    "name:zho_x_preferred":[
        "\u6c38\u5fb7"
    ],
    "wof:name":"Yongde",
    "wof:placetype":"locality"
},
  "geometry": {"coordinates":[121.1285,22.9556],"type":"Point"}
}