{
  "type": "Feature",
  "properties": {
    "gn:admin1_code":"4.0",
    "gn:admin2_code":"NAN",
    "gn:admin3_code":"M10",
    "gn:admin4_code":"10008100011.0",
    "gn:asciiname":"Guoxingxiang",
    "gn:country_code":"TW",
    "gn:dem":374,
    "gn:feature_class":"P",
    "gn:feature_code":"PPL",
    "gn:name":"Guoxingxiang",
    "gn:population":0,
    "gn:timezone":"Asia/Taipei",
    "iso:country":"TW",
    "name:und_x_variant":[
        "Kuo-hsing-hsiang"
    ],
    "wof:name":"Guoxingxiang",
    "wof:placetype":"locality"
},
  "geometry": {"coordinates":[120.86667,23.95],"type":"Point"}
}