{
  "type": "Feature",
  "properties": {
    "gn:admin1_code":"4.0",
    "gn:admin2_code":"HUA",
    "gn:admin3_code":"U13",
    "gn:admin4_code":"10015130001.0",
    "gn:asciiname":"Jiaxing",
    "gn:country_code":"TW",
    "gn:dem":655,
    "gn:feature_class":"P",
    "gn:feature_code":"PPL",
    "gn:name":"Jiaxing",
    "gn:population":0,
    "gn:timezone":"Asia/Taipei",
    "iso:country":"TW",
    "name:ara_x_preferred":[
        "\u062c\u064a\u0627\u0634\u064a\u0646\u063a"
    ],
    "name:bul_x_preferred":[
        "\u0414\u0437\u044f\u0441\u0438\u043d"
    ],
    "name:cdo_x_preferred":[
        "G\u0103-h\u012dng"
    ],
    "name:ceb_x_preferred":[
        "Jiaxing"
    ],
    "name:ces_x_preferred":[
        "\u0164ia-sing"
    ],
    "name:dan_x_preferred":[
        "Jiaxing"
    ],
    "name:deu_x_preferred":[
        "Jiaxing"
    ],
    "name:est_x_preferred":[
        "Jiaxing"
    ],
    "name:eus_x_preferred":[
        "Jiaxing"
    ],
    "name:fas_x_preferred":[
        "\u062c\u06cc\u0634\u0627\u0646\u06af"
    ],
    "name:fin_x_preferred":[
        "Jiaxing"
    ],
    "name:fra_x_preferred":[
        "Jiaxing"
    ],
    "name:hak_x_preferred":[
        "K\u00e2-h\u00een-s\u1e73"
    ],
    "name:ind_x_preferred":[
        "Jiaxing"
    ],
    "name:ita_x_preferred":[
        "Jiaxing"
    ],
    "name:jpn_x_preferred":[
        "\u5609\u8208\u5e02"
    ],
    "name:kik_x_preferred":[
        "Jiaxing"
    ],
    "name:kor_x_preferred":[
        "\uc790\uc2f1\uc2dc"
    ],
    "name:lit_x_preferred":[
        "Dziasingas"
    ],
    "name:mlg_x_preferred":[
        "Jiaxing"
    ],
    "name:nld_x_preferred":[
        "Jiaxing"
    ],
    "name:nno_x_preferred":[
        "Jiaxing"
    ],
    "name:nor_x_preferred":[
        "Jiaxing"
    ],
    "name:pol_x_preferred":[
        "Jiaxing"
    ],
    "name:por_x_preferred":[
        "Jiaxing"
    ],
    "name:rus_x_preferred":[
        "\u0426\u0437\u044f\u0441\u0438\u043d"
    ],
    "name:spa_x_preferred":[
        "Jiaxing"
    ],
    "name:srp_x_preferred":[
        "\u0402\u0430\u0441\u0438\u043d\u0433"
    ],
    "name:swe_x_preferred":[
        "Jiaxing"
    ],
    "name:tgl_x_preferred":[
        "Jiaxing"
    ],
    "name:tur_x_preferred":[
        "Jiaxing"
    ],
    "name:ukr_x_preferred":[
        "\u0426\u0437\u044f\u0441\u0456\u043d"
    ],
    "name:und_x_variant":[
        "Chia-hsing"
    ],
    "name:urd_x_preferred":[
        "\u062c\u06cc\u0627\u0634\u0646\u06af"
    ],
    "name:vie_x_preferred":[
        "Gia H\u01b0ng"
    ],
    "name:war_x_preferred":[
        "Jiaxing"
    ],
    "name:zho_x_preferred":[
        "\u5609\u5174\u5e02"
    ],
    "wof:name":"Jiaxing",
    "wof:placetype":"locality"
},
  "geometry": {"coordinates":[121.31667,23.48333],"type":"Point"}
}