{
  "type": "Feature",
  "properties": {
    "gn:admin1_code":"4.0",
    "gn:admin2_code":"HUA",
    "gn:admin3_code":"U13",
    "gn:admin4_code":"10015130001.0",
    "gn:asciiname":"Jiaxing",
    "gn:country_code":"TW",
    "gn:dem":655,
    "gn:feature_class":"P",
    "gn:feature_code":"PPL",
    "gn:name":"Jiaxing",
    "gn:population":0,
    "gn:timezone":"Asia/Taipei",
    "iso:country":"TW",
    "name:und_x_variant":[
        "Chia-hsing"
    ],
    "wof:name":"Jiaxing",
    "wof:placetype":"locality"
},
  "geometry": {"coordinates":[121.31667,23.48333],"type":"Point"}
}