{
  "type": "Feature",
  "properties": {
    "gn:admin1_code":"01",
    "gn:admin2_code":"KIN",
    "gn:admin3_code":"W01",
    "gn:admin4_code":"9020030004.0",
    "gn:asciiname":"Dongcun",
    "gn:country_code":"TW",
    "gn:dem":24,
    "gn:feature_class":"P",
    "gn:feature_code":"PPL",
    "gn:name":"Dongcun",
    "gn:population":0,
    "gn:timezone":"Asia/Taipei",
    "iso:country":"TW",
    "name:und_x_variant":[
        "Tung-ts\u2019un"
    ],
    "name:zho_x_preferred":[
        "\u6771\u6751"
    ],
    "wof:name":"Dongcun",
    "wof:placetype":"locality"
},
  "geometry": {"coordinates":[118.44718,24.42828],"type":"Point"}
}