{
  "type": "Feature",
  "properties": {
    "gn:admin1_code":"4.0",
    "gn:admin2_code":"PEN",
    "gn:admin3_code":"X02",
    "gn:admin4_code":"10016020007.0",
    "gn:asciiname":"Hongluo",
    "gn:country_code":"TW",
    "gn:dem":10,
    "gn:feature_class":"P",
    "gn:feature_code":"PPL",
    "gn:name":"Hongluo",
    "gn:population":0,
    "gn:timezone":"Asia/Taipei",
    "iso:country":"TW",
    "name:und_x_variant":[
        "Hung-lo-chao",
        "Hongluo",
        "Hung-lo"
    ],
    "name:zho_x_preferred":[
        "Hung-lo-ts\u2019un"
    ],
    "name:zho_x_variant":[
        "\u7d05\u7f85"
    ],
    "wof:name":"Hongluo",
    "wof:placetype":"locality"
},
  "geometry": {"coordinates":[119.64286,23.58608],"type":"Point"}
}