{
  "type": "Feature",
  "properties": {
    "gn:admin1_code":"04",
    "gn:admin2_code":"CYQ",
    "gn:admin3_code":"Q06",
    "gn:admin4_code":"10010060013.0",
    "gn:asciiname":"Shanglun",
    "gn:country_code":"TW",
    "gn:dem":22,
    "gn:feature_class":"P",
    "gn:feature_code":"PPL",
    "gn:name":"Shanglun",
    "gn:population":0,
    "gn:timezone":"Asia/Taipei",
    "iso:country":"TW",
    "name:und_x_variant":[
        "Shan-lun",
        "Shanglun",
        "Shang-lun"
    ],
    "name:zho_x_preferred":[
        "\u4e0a\u5d19"
    ],
    "wof:name":"Shanglun",
    "wof:placetype":"locality"
},
  "geometry": {"coordinates":[120.4117,23.5888],"type":"Point"}
}