{
  "type": "Feature",
  "properties": {
    "gn:admin1_code":"4.0",
    "gn:admin2_code":"TAO",
    "gn:admin3_code":"H04",
    "gn:admin4_code":"68000040024.0",
    "gn:asciiname":"Hongpo",
    "gn:country_code":"TW",
    "gn:dem":165,
    "gn:feature_class":"P",
    "gn:feature_code":"PPL",
    "gn:name":"Hongpo",
    "gn:population":0,
    "gn:timezone":"Asia/Taipei",
    "iso:country":"TW",
    "name:zho_x_preferred":[
        "\u7d05\u5761"
    ],
    "name:zho_x_variant":[
        "Hung-p\u2019o"
    ],
    "wof:name":"Hongpo",
    "wof:placetype":"locality"
},
  "geometry": {"coordinates":[121.11611000000001,24.91472000000001],"type":"Point"}
}