{
  "type": "Feature",
  "properties": {
    "gn:admin1_code":"4.0",
    "gn:admin2_code":"TNN",
    "gn:admin3_code":"R13",
    "gn:admin4_code":"67000140011.0",
    "gn:asciiname":"Xibuliao",
    "gn:country_code":"TW",
    "gn:dem":11,
    "gn:feature_class":"P",
    "gn:feature_code":"PPL",
    "gn:name":"Xibuliao",
    "gn:population":0,
    "gn:timezone":"Asia/Taipei",
    "iso:country":"TW",
    "name:und_x_variant":[
        "Hsi-pu-liao",
        "Xibuliao",
        "Sibuliao",
        "\u6eaa\u57d4\u5bee"
    ],
    "name:zho_x_preferred":[
        "Ch\u2019i-pu-liao"
    ],
    "name:zho_x_variant":[
        "\u6eaa\u57d4\u5bee"
    ],
    "wof:name":"Xibuliao",
    "wof:placetype":"locality"
},
  "geometry": {"coordinates":[120.18556,23.08639],"type":"Point"}
}