{
  "type": "Feature",
  "properties": {
    "gn:admin1_code":"02",
    "gn:admin2_code":"KHH",
    "gn:admin3_code":"E22",
    "gn:admin4_code":"64000220002.0",
    "gn:asciiname":"Nei'an",
    "gn:country_code":"TW",
    "gn:dem":42,
    "gn:feature_class":"P",
    "gn:feature_code":"PPL",
    "gn:name":"Nei\u2019an",
    "gn:population":0,
    "gn:timezone":"Asia/Taipei",
    "iso:country":"TW",
    "name:und_x_variant":[
        "Nei-tung-kao-jui",
        "Nei-an"
    ],
    "name:zho_x_preferred":[
        "\u5185\u5b89"
    ],
    "name:zho_x_variant":[
        "Nei\u2019an"
    ],
    "wof:name":"Nei'an",
    "wof:placetype":"locality"
},
  "geometry": {"coordinates":[120.39556,22.85611],"type":"Point"}
}