{
  "type": "Feature",
  "properties": {
    "gn:admin1_code":"2.0",
    "gn:admin2_code":"KHH",
    "gn:admin3_code":"E35",
    "gn:admin4_code":"64000350018.0",
    "gn:asciiname":"Niuliao",
    "gn:country_code":"TW",
    "gn:dem":98,
    "gn:feature_class":"P",
    "gn:feature_code":"PPL",
    "gn:name":"Niuliao",
    "gn:population":0,
    "gn:timezone":"Asia/Taipei",
    "iso:country":"TW",
    "name:und_x_variant":[
        "Niouliao",
        "Niu-liao"
    ],
    "name:zho_x_preferred":[
        "\u725b\u5bee"
    ],
    "wof:name":"Niuliao",
    "wof:placetype":"locality"
},
  "geometry": {"coordinates":[120.44972,22.94389],"type":"Point"}
}