{
  "type": "Feature",
  "properties": {
    "gn:admin1_code":"04",
    "gn:admin2_code":"NAN",
    "gn:admin3_code":"M04",
    "gn:admin4_code":"10008040021.0",
    "gn:asciiname":"Baijiachun",
    "gn:country_code":"TW",
    "gn:dem":206,
    "gn:feature_class":"P",
    "gn:feature_code":"PPL",
    "gn:name":"Baijiachun",
    "gn:population":0,
    "gn:timezone":"Asia/Taipei",
    "iso:country":"TW",
    "name:zho_x_preferred":[
        "\u767e\u5bb6\u6625"
    ],
    "name:zho_x_variant":[
        "Pu-chih-ch\u2019un",
        "Pai-chia-ch\u2019un"
    ],
    "wof:name":"Baijiachun",
    "wof:placetype":"locality"
},
  "geometry": {"coordinates":[120.66388999999999,23.69278],"type":"Point"}
}