{
  "type": "Feature",
  "properties": {
    "gn:admin1_code":"4.0",
    "gn:admin2_code":"TAO",
    "gn:admin3_code":"H04",
    "gn:admin4_code":"68000040008.0",
    "gn:asciiname":"Yingpanjiao",
    "gn:country_code":"TW",
    "gn:dem":111,
    "gn:feature_class":"P",
    "gn:feature_code":"PPL",
    "gn:name":"Yingpanjiao",
    "gn:population":0,
    "gn:timezone":"Asia/Taipei",
    "iso:country":"TW",
    "name:zho_x_preferred":[
        "\u71df\u76e4\u811a"
    ],
    "name:zho_x_variant":[
        "Ying-p\u2019an-chiao"
    ],
    "wof:name":"Yingpanjiao",
    "wof:placetype":"locality"
},
  "geometry": {"coordinates":[121.12917,24.93722],"type":"Point"}
}