{
  "type": "Feature",
  "properties": {
    "gn:admin1_code":"4.0",
    "gn:admin2_code":"MIA",
    "gn:admin3_code":"K02",
    "gn:admin4_code":"10005020011.0",
    "gn:asciiname":"Nanyuanlikeng",
    "gn:country_code":"TW",
    "gn:dem":34,
    "gn:feature_class":"P",
    "gn:feature_code":"PPL",
    "gn:name":"Nanyuanlikeng",
    "gn:population":0,
    "gn:timezone":"Asia/Taipei",
    "iso:country":"TW",
    "name:zho_x_preferred":[
        "\u5357\u82d1\u88e1\u5751"
    ],
    "name:zho_x_variant":[
        "Nan-y\u00fcan-li-k\u2019eng"
    ],
    "wof:name":"Nanyuanlikeng",
    "wof:placetype":"locality"
},
  "geometry": {"coordinates":[120.66916999999999,24.44361],"type":"Point"}
}