{
  "type": "Feature",
  "properties": {
    "gn:admin1_code":"4.0",
    "gn:admin2_code":"MIA",
    "gn:admin3_code":"K14",
    "gn:admin4_code":"10005110009.0",
    "gn:asciiname":"Fengmei",
    "gn:country_code":"TW",
    "gn:dem":717,
    "gn:feature_class":"P",
    "gn:feature_code":"PPL",
    "gn:name":"Fengmei",
    "gn:population":0,
    "gn:timezone":"Asia/Taipei",
    "iso:country":"TW",
    "name:und_x_variant":[
        "Fongmei",
        "Feng-mei"
    ],
    "name:zho_x_preferred":[
        "Lu-ch\u2019ang"
    ],
    "name:zho_x_variant":[
        "Ch\u2019iu-pu-ssu-she",
        "\u98a8\u7f8e"
    ],
    "wof:name":"Fengmei",
    "wof:placetype":"locality"
},
  "geometry": {"coordinates":[121.02972,24.54694],"type":"Point"}
}