{
  "type": "Feature",
  "properties": {
    "gn:admin1_code":"4.0",
    "gn:admin2_code":"NAN",
    "gn:admin3_code":"M12",
    "gn:admin4_code":"10008120011.0",
    "gn:asciiname":"Wushuang",
    "gn:country_code":"TW",
    "gn:dem":2022,
    "gn:feature_class":"P",
    "gn:feature_code":"PPL",
    "gn:name":"Wushuang",
    "gn:population":0,
    "gn:timezone":"Asia/Taipei",
    "iso:country":"TW",
    "name:und_x_variant":[
        "Wu-shuang"
    ],
    "name:zho_x_preferred":[
        "\u7121\u96d9"
    ],
    "wof:name":"Wushuang",
    "wof:placetype":"locality"
},
  "geometry": {"coordinates":[121.01148000000001,23.54734],"type":"Point"}
}