{
  "type": "Feature",
  "properties": {
    "gn:admin1_code":"4.0",
    "gn:admin2_code":"NAN",
    "gn:admin3_code":"M13",
    "gn:admin4_code":"10008130012.0",
    "gn:asciiname":"Shisanwan",
    "gn:country_code":"TW",
    "gn:dem":1787,
    "gn:feature_class":"P",
    "gn:feature_code":"PPL",
    "gn:name":"Shisanwan",
    "gn:population":0,
    "gn:timezone":"Asia/Taipei",
    "iso:country":"TW",
    "name:und_x_variant":[
        "Shihsanwan",
        "Shih-san-wan"
    ],
    "name:zho_x_preferred":[
        "\u5341\u4e09\u7063"
    ],
    "wof:name":"Shisanwan",
    "wof:placetype":"locality"
},
  "geometry": {"coordinates":[121.21417,24.04222],"type":"Point"}
}