{
  "type": "Feature",
  "properties": {
    "gn:admin1_code":"4.0",
    "gn:admin2_code":"CHA",
    "gn:admin3_code":"N20",
    "gn:admin4_code":"10007180016.0",
    "gn:asciiname":"Fuxing",
    "gn:country_code":"TW",
    "gn:dem":69,
    "gn:feature_class":"P",
    "gn:feature_code":"PPL",
    "gn:name":"Fuxing",
    "gn:population":0,
    "gn:timezone":"Asia/Taipei",
    "iso:country":"TW",
    "name:und_x_variant":[
        "Fusing",
        "Fuxing",
        "Fu-hsing"
    ],
    "name:zho_x_preferred":[
        "\u5fa9\u8208"
    ],
    "wof:name":"Fuxing",
    "wof:placetype":"locality"
},
  "geometry": {"coordinates":[120.60469999999999,23.83033],"type":"Point"}
}