{
  "type": "Feature",
  "properties": {
    "gn:admin1_code":"04",
    "gn:admin2_code":"NAN",
    "gn:admin3_code":"M08",
    "gn:admin4_code":"10008080013.0",
    "gn:asciiname":"Yuanzicheng",
    "gn:country_code":"TW",
    "gn:dem":232,
    "gn:feature_class":"P",
    "gn:feature_code":"PPL",
    "gn:name":"Yuanzicheng",
    "gn:population":0,
    "gn:timezone":"Asia/Taipei",
    "iso:country":"TW",
    "name:und_x_variant":[
        "Yuanzihcheng"
    ],
    "name:zho_x_preferred":[
        "\u5713\u5b50\u57ce"
    ],
    "name:zho_x_variant":[
        "Y\u00fcan-tzu-ch\u2019eng"
    ],
    "wof:name":"Yuanzicheng",
    "wof:placetype":"locality"
},
  "geometry": {"coordinates":[120.78018,23.94136],"type":"Point"}
}