{
  "type": "Feature",
  "properties": {
    "gn:admin1_code":"4.0",
    "gn:admin2_code":"TXG",
    "gn:admin3_code":"B13",
    "gn:admin4_code":"66000130015.0",
    "gn:asciiname":"Nanshi",
    "gn:country_code":"TW",
    "gn:dem":30,
    "gn:feature_class":"P",
    "gn:feature_code":"PPL",
    "gn:name":"Nanshi",
    "gn:population":0,
    "gn:timezone":"Asia/Taipei",
    "iso:country":"TW",
    "name:und_x_variant":[
        "Nanshih",
        "Nan-shih"
    ],
    "name:zho_x_preferred":[
        "\u5357\u52e2"
    ],
    "wof:name":"Nanshi",
    "wof:placetype":"locality"
},
  "geometry": {"coordinates":[120.55710000000001,24.219],"type":"Point"}
}