{
  "type": "Feature",
  "properties": {
    "gn:admin1_code":"4.0",
    "gn:admin2_code":"PIF",
    "gn:admin3_code":"T24",
    "gn:admin4_code":"10013240004.0",
    "gn:asciiname":"Gangkou",
    "gn:country_code":"TW",
    "gn:dem":20,
    "gn:feature_class":"P",
    "gn:feature_code":"PPL",
    "gn:name":"Gangkou",
    "gn:population":0,
    "gn:timezone":"Asia/Taipei",
    "iso:country":"TW",
    "name:deu_x_preferred":[
        "Gangkou"
    ],
    "name:nor_x_preferred":[
        "Gangkou"
    ],
    "name:und_x_variant":[
        "Pa-kuei-chiao",
        "Gangkou"
    ],
    "name:zho_x_preferred":[
        "Chiang-k\u2019ou-lu"
    ],
    "name:zho_x_variant":[
        "\u6e2f\u53e3",
        "Kang-k\u2019ou-lu",
        "Kang-k\u2019ou"
    ],
    "wof:name":"Gangkou",
    "wof:placetype":"locality"
},
  "geometry": {"coordinates":[120.82556,21.99167000000001],"type":"Point"}
}