{
  "type": "Feature",
  "properties": {
    "gn:admin1_code":"4.0",
    "gn:admin2_code":"CYQ",
    "gn:admin3_code":"Q15",
    "gn:admin4_code":"10010140012.0",
    "gn:asciiname":"Dafangjiao",
    "gn:country_code":"TW",
    "gn:dem":239,
    "gn:feature_class":"P",
    "gn:feature_code":"PPL",
    "gn:name":"Dafangjiao",
    "gn:population":0,
    "gn:timezone":"Asia/Taipei",
    "iso:country":"TW",
    "name:und_x_variant":[
        "Ta-fang-chiao"
    ],
    "name:zho_x_preferred":[
        "\u5927\u678b\u8173"
    ],
    "wof:name":"Dafangjiao",
    "wof:placetype":"locality"
},
  "geometry": {"coordinates":[120.57535,23.46587],"type":"Point"}
}