{
  "type": "Feature",
  "properties": {
    "gn:admin1_code":"4.0",
    "gn:admin2_code":"TNN",
    "gn:admin3_code":"R30",
    "gn:admin4_code":"67000300004.0",
    "gn:asciiname":"Neigou",
    "gn:country_code":"TW",
    "gn:dem":81,
    "gn:feature_class":"P",
    "gn:feature_code":"PPL",
    "gn:name":"Neigou",
    "gn:population":0,
    "gn:timezone":"Asia/Taipei",
    "iso:country":"TW",
    "name:und_x_variant":[
        "Nei-kou"
    ],
    "name:zho_x_preferred":[
        "\u5185\u6e9d"
    ],
    "wof:name":"Neigou",
    "wof:placetype":"locality"
},
  "geometry": {"coordinates":[120.37860999999999,22.93333],"type":"Point"}
}