{
  "type": "Feature",
  "properties": {
    "gn:admin1_code":"3.0",
    "gn:admin2_code":"TPQ",
    "gn:admin3_code":"F02",
    "gn:admin4_code":"65000170008.0",
    "gn:asciiname":"Guolunzi",
    "gn:country_code":"TW",
    "gn:dem":250,
    "gn:feature_class":"P",
    "gn:feature_code":"PPL",
    "gn:name":"Guolunzi",
    "gn:population":0,
    "gn:timezone":"Asia/Taipei",
    "iso:country":"TW",
    "name:und_x_variant":[
        "Guolunzih",
        "Kuo-lun-tzu"
    ],
    "name:zho_x_preferred":[
        "\u904e\u5d19\u5b50"
    ],
    "wof:name":"Guolunzi",
    "wof:placetype":"locality"
},
  "geometry": {"coordinates":[121.35767,25.07465],"type":"Point"}
}