{
  "type": "Feature",
  "properties": {
    "gn:admin1_code":"4.0",
    "gn:admin2_code":"TNN",
    "gn:admin3_code":"R23",
    "gn:admin4_code":"67000230009.0",
    "gn:asciiname":"Guizikeng",
    "gn:country_code":"TW",
    "gn:dem":80,
    "gn:feature_class":"P",
    "gn:feature_code":"PPL",
    "gn:name":"Guizikeng",
    "gn:population":0,
    "gn:timezone":"Asia/Taipei",
    "iso:country":"TW",
    "name:und_x_variant":[
        "Gueizihkeng",
        "Guizikeng"
    ],
    "name:zho_x_preferred":[
        "\u9b3c\u5b50\u5751"
    ],
    "name:zho_x_variant":[
        "Kuei-tzu-k\u2019eng"
    ],
    "wof:name":"Guizikeng",
    "wof:placetype":"locality"
},
  "geometry": {"coordinates":[120.43940000000001,23.0904],"type":"Point"}
}