{
  "type": "Feature",
  "properties": {
    "gn:admin1_code":"4.0",
    "gn:admin2_code":"NAN",
    "gn:admin3_code":"M07",
    "gn:admin4_code":"10008070013.0",
    "gn:asciiname":"Ruitian",
    "gn:country_code":"TW",
    "gn:dem":222,
    "gn:feature_class":"P",
    "gn:feature_code":"PPL",
    "gn:name":"Ruitian",
    "gn:population":0,
    "gn:timezone":"Asia/Taipei",
    "iso:country":"TW",
    "name:und_x_variant":[
        "Rueitian",
        "Ruitian"
    ],
    "name:zho_x_preferred":[
        "\u745e\u7530"
    ],
    "name:zho_x_variant":[
        "Jui-t\u2019ien"
    ],
    "wof:name":"Ruitian",
    "wof:placetype":"locality"
},
  "geometry": {"coordinates":[120.7841,23.80474],"type":"Point"}
}