{
  "type": "Feature",
  "properties": {
    "gn:admin1_code":"4.0",
    "gn:admin2_code":"HSZ",
    "gn:admin3_code":"J09",
    "gn:admin4_code":"10004060004.0",
    "gn:asciiname":"Houhu",
    "gn:country_code":"TW",
    "gn:dem":27,
    "gn:feature_class":"P",
    "gn:feature_code":"PPL",
    "gn:name":"Houhu",
    "gn:population":0,
    "gn:timezone":"Asia/Taipei",
    "iso:country":"TW",
    "name:und_x_variant":[
        "Hou-hu"
    ],
    "name:zho_x_preferred":[
        "\u5f8c\u6e56"
    ],
    "name:zho_x_variant":[
        "Shih-jen-t\u2019ou"
    ],
    "wof:name":"Houhu",
    "wof:placetype":"locality"
},
  "geometry": {"coordinates":[120.9975,24.93306],"type":"Point"}
}