{
  "type": "Feature",
  "properties": {
    "gn:admin1_code":"4.0",
    "gn:admin2_code":"HUA",
    "gn:admin3_code":"U08",
    "gn:admin4_code":"10015080002.0",
    "gn:asciiname":"Xinfeng",
    "gn:country_code":"TW",
    "gn:dem":46,
    "gn:feature_class":"P",
    "gn:feature_code":"PPL",
    "gn:name":"Xinfeng",
    "gn:population":0,
    "gn:timezone":"Asia/Taipei",
    "iso:country":"TW",
    "name:ceb_x_preferred":[
        "Xinfeng"
    ],
    "name:deu_x_preferred":[
        "Xinfeng"
    ],
    "name:fra_x_preferred":[
        "Xinfeng"
    ],
    "name:kor_x_preferred":[
        "\uc2e0\ud391\ud604"
    ],
    "name:nor_x_preferred":[
        "Xinfeng"
    ],
    "name:swe_x_preferred":[
        "Xinfeng"
    ],
    "name:und_x_variant":[
        "Sinfong",
        "Xinfeng",
        "Hsin-feng"
    ],
    "name:zho_x_preferred":[
        "\u65b0\u8c50"
    ],
    "wof:name":"Xinfeng",
    "wof:placetype":"locality"
},
  "geometry": {"coordinates":[121.54528000000001,23.67222000000001],"type":"Point"}
}