{
  "type": "Feature",
  "properties": {
    "gn:admin1_code":"03",
    "gn:admin2_code":"TPQ",
    "gn:admin3_code":"F27",
    "gn:admin4_code":"65000100003.0",
    "gn:asciiname":"Shitoubu",
    "gn:country_code":"TW",
    "gn:dem":10,
    "gn:feature_class":"P",
    "gn:feature_code":"PPL",
    "gn:name":"Shitoubu",
    "gn:population":0,
    "gn:timezone":"Asia/Taipei",
    "iso:country":"TW",
    "name:und_x_variant":[
        "Shihtoubu",
        "Shitoubu"
    ],
    "name:zho_x_preferred":[
        "\u77f3\u982d\u57d4"
    ],
    "name:zho_x_variant":[
        "Shih-t\u2019ou-pu"
    ],
    "wof:name":"Shitoubu",
    "wof:placetype":"locality"
},
  "geometry": {"coordinates":[121.4473,25.23276],"type":"Point"}
}