{
  "type": "Feature",
  "properties": {
    "gn:admin1_code":"3.0",
    "gn:admin2_code":"TPQ",
    "gn:admin3_code":"F27",
    "gn:admin4_code":"65000100015.0",
    "gn:asciiname":"Zhangnaoliaoping",
    "gn:country_code":"TW",
    "gn:dem":161,
    "gn:feature_class":"P",
    "gn:feature_code":"PPL",
    "gn:name":"Zhangnaoliaoping",
    "gn:population":0,
    "gn:timezone":"Asia/Taipei",
    "iso:country":"TW",
    "name:und_x_variant":[
        "Jhangnaoliaoping",
        "Zhangnaoliaoping"
    ],
    "name:zho_x_preferred":[
        "\u6a1f\u8166\u5bee\u576a"
    ],
    "name:zho_x_variant":[
        "Chang-nao-liao-p\u2019ing"
    ],
    "wof:name":"Zhangnaoliaoping",
    "wof:placetype":"locality"
},
  "geometry": {"coordinates":[121.4725,25.16855],"type":"Point"}
}