{
  "type": "Feature",
  "properties": {
    "gn:admin1_code":"04",
    "gn:admin2_code":"TAO",
    "gn:admin3_code":"H05",
    "gn:admin4_code":"68000050025.0",
    "gn:asciiname":"Pankeng",
    "gn:country_code":"TW",
    "gn:dem":99,
    "gn:feature_class":"P",
    "gn:feature_code":"PPL",
    "gn:name":"Pankeng",
    "gn:population":0,
    "gn:timezone":"Asia/Taipei",
    "iso:country":"TW",
    "name:zho_x_preferred":[
        "\u76e4\u5751"
    ],
    "name:zho_x_variant":[
        "Ying-p\u2019an-k\u2019eng",
        "P\u2019an-k\u2019eng"
    ],
    "wof:name":"Pankeng",
    "wof:placetype":"locality"
},
  "geometry": {"coordinates":[121.30237,25.06249],"type":"Point"}
}