{
  "type": "Feature",
  "properties": {
    "gn:admin1_code":"04",
    "gn:admin2_code":"TNN",
    "gn:admin3_code":"R04",
    "gn:admin4_code":"67000040008.0",
    "gn:asciiname":"Wujunying",
    "gn:country_code":"TW",
    "gn:dem":20,
    "gn:feature_class":"P",
    "gn:feature_code":"PPL",
    "gn:name":"Wujunying",
    "gn:population":0,
    "gn:timezone":"Asia/Taipei",
    "iso:country":"TW",
    "name:und_x_variant":[
        "Wujyunying",
        "Wujunying"
    ],
    "name:zho_x_preferred":[
        "\u4e94\u8ecd\u71df"
    ],
    "name:zho_x_variant":[
        "Wu-ch\u00fcn-ying"
    ],
    "wof:name":"Wujunying",
    "wof:placetype":"locality"
},
  "geometry": {"coordinates":[120.35028,23.29667],"type":"Point"}
}