{
  "type": "Feature",
  "properties": {
    "gn:admin1_code":"02",
    "gn:admin2_code":"KHH",
    "gn:admin3_code":"E21",
    "gn:admin4_code":"64000210005.0",
    "gn:asciiname":"Wuguibu",
    "gn:country_code":"TW",
    "gn:dem":22,
    "gn:feature_class":"P",
    "gn:feature_code":"PPL",
    "gn:name":"Wuguibu",
    "gn:population":0,
    "gn:timezone":"Asia/Taipei",
    "iso:country":"TW",
    "name:und_x_variant":[
        "Wugueibu",
        "Wuguibu",
        "Wu-kuei-pu"
    ],
    "name:zho_x_preferred":[
        "\u70cf\u9b3c\u57d4"
    ],
    "wof:name":"Wuguibu",
    "wof:placetype":"locality"
},
  "geometry": {"coordinates":[120.34806,22.75833],"type":"Point"}
}