{
  "type": "Feature",
  "properties": {
    "gn:admin1_code":"4.0",
    "gn:admin2_code":"HUA",
    "gn:admin3_code":"U11",
    "gn:admin4_code":"10015110002.0",
    "gn:asciiname":"Xuejiachang",
    "gn:country_code":"TW",
    "gn:dem":805,
    "gn:feature_class":"P",
    "gn:feature_code":"PPL",
    "gn:name":"Xuejiachang",
    "gn:population":0,
    "gn:timezone":"Asia/Taipei",
    "iso:country":"TW",
    "name:und_x_variant":[
        "Syuejiachang"
    ],
    "name:zho_x_preferred":[
        "\u859b\u5bb6\u5834"
    ],
    "name:zho_x_variant":[
        "Hsieh-chia-ch\u2019ang",
        "Hs\u00fceh-chia-ch\u2019ang"
    ],
    "wof:name":"Xuejiachang",
    "wof:placetype":"locality"
},
  "geometry": {"coordinates":[121.46917000000001,24.19806],"type":"Point"}
}