{
  "type": "Feature",
  "properties": {
    "gn:admin1_code":"4.0",
    "gn:admin2_code":"MIA",
    "gn:admin3_code":"K13",
    "gn:admin4_code":"10005160007.0",
    "gn:asciiname":"Taoping",
    "gn:country_code":"TW",
    "gn:dem":33,
    "gn:feature_class":"P",
    "gn:feature_code":"PPL",
    "gn:name":"Taoping",
    "gn:population":0,
    "gn:timezone":"Asia/Taipei",
    "iso:country":"TW",
    "name:zho_x_preferred":[
        "\u6843\u576a"
    ],
    "name:zho_x_variant":[
        "T\u2019ao-p\u2019ing"
    ],
    "wof:name":"Taoping",
    "wof:placetype":"locality"
},
  "geometry": {"coordinates":[120.91473999999999,24.62239],"type":"Point"}
}