{
  "type": "Feature",
  "properties": {
    "gn:admin1_code":"4.0",
    "gn:admin2_code":"TAO",
    "gn:admin3_code":"H10",
    "gn:admin4_code":"68000100024.0",
    "gn:asciiname":"Jindonghu",
    "gn:country_code":"TW",
    "gn:dem":196,
    "gn:feature_class":"P",
    "gn:feature_code":"PPL",
    "gn:name":"Jindonghu",
    "gn:population":0,
    "gn:timezone":"Asia/Taipei",
    "iso:country":"TW",
    "name:und_x_variant":[
        "Ching-tung-hu",
        "Jindonghu",
        "Chin-tung-hu"
    ],
    "name:zho_x_preferred":[
        "\u91d1\u6771\u6e56"
    ],
    "wof:name":"Jindonghu",
    "wof:placetype":"locality"
},
  "geometry": {"coordinates":[121.23917,24.89583],"type":"Point"}
}