{
  "type": "Feature",
  "properties": {
    "gn:admin1_code":"4.0",
    "gn:admin2_code":"HUA",
    "gn:admin3_code":"U08",
    "gn:admin4_code":"10015080005.0",
    "gn:asciiname":"Sanfuqiao",
    "gn:country_code":"TW",
    "gn:dem":16,
    "gn:feature_class":"P",
    "gn:feature_code":"PPL",
    "gn:name":"Sanfuqiao",
    "gn:population":0,
    "gn:timezone":"Asia/Taipei",
    "iso:country":"TW",
    "name:und_x_variant":[
        "Sanfuqiao",
        "Sanfuciao"
    ],
    "name:zho_x_preferred":[
        "San-fu-ch\u2019iao"
    ],
    "name:zho_x_variant":[
        "\u4e09\u5bcc\u6a4b"
    ],
    "wof:name":"Sanfuqiao",
    "wof:placetype":"locality"
},
  "geometry": {"coordinates":[121.49550000000001,23.44348],"type":"Point"}
}