{
  "type": "Feature",
  "properties": {
    "gn:admin1_code":"03",
    "gn:admin2_code":"TPQ",
    "gn:admin3_code":"F23",
    "gn:admin4_code":"65000250012.0",
    "gn:asciiname":"Pingxi",
    "gn:country_code":"TW",
    "gn:dem":502,
    "gn:feature_class":"P",
    "gn:feature_code":"PPL",
    "gn:name":"Pingxi",
    "gn:population":0,
    "gn:timezone":"Asia/Taipei",
    "iso:country":"TW",
    "name:und_x_variant":[
        "Pingsi",
        "Pingxi"
    ],
    "name:zho_x_preferred":[
        "P\u2019ing-ch\u2019i"
    ],
    "name:zho_x_variant":[
        "\u576a\u6eaa",
        "P\u2019ing-hsi"
    ],
    "wof:name":"Pingxi",
    "wof:placetype":"locality"
},
  "geometry": {"coordinates":[121.83750000000001,24.91833],"type":"Point"}
}