{
  "type": "Feature",
  "properties": {
    "gn:admin1_code":"01",
    "gn:asciiname":"Siweicun",
    "gn:country_code":"TW",
    "gn:dem":-9999,
    "gn:feature_class":"P",
    "gn:feature_code":"PPL",
    "gn:name":"Siweicun",
    "gn:population":0,
    "gn:timezone":"Asia/Taipei",
    "iso:country":"TW",
    "name:und_x_variant":[
        "Ssu-wei-ts\u2019un"
    ],
    "wof:name":"Siweicun",
    "wof:placetype":"locality"
},
  "geometry": {"coordinates":[119.91667,26.16667],"type":"Point"}
}