{
  "type": "Feature",
  "properties": {
    "gn:admin1_code":"4.0",
    "gn:admin2_code":"NAN",
    "gn:admin3_code":"M02",
    "gn:admin4_code":"10008020014.0",
    "gn:asciiname":"Xinan",
    "gn:country_code":"TW",
    "gn:dem":451,
    "gn:feature_class":"P",
    "gn:feature_code":"PPL",
    "gn:name":"Xinan",
    "gn:population":0,
    "gn:timezone":"Asia/Taipei",
    "iso:country":"TW",
    "name:ceb_x_preferred":[
        "Xinan"
    ],
    "name:deu_x_preferred":[
        "Xinan"
    ],
    "name:swe_x_preferred":[
        "Xinan"
    ],
    "name:und_x_variant":[
        "Sinan",
        "Xinan",
        "Hsi-nan"
    ],
    "name:zho_x_preferred":[
        "Sheng-fan-k\u2019ung"
    ],
    "name:zho_x_variant":[
        "Ch\u2019i-nan",
        "Sheng-fan-k\u2019eng",
        "\u6eaa\u5357"
    ],
    "wof:name":"Xinan",
    "wof:placetype":"locality"
},
  "geometry": {"coordinates":[120.95603,23.95134],"type":"Point"}
}