{
  "type": "Feature",
  "properties": {
    "iso:country":"TW",
    "qs:name":"\u842c\u8c50\u6751",
    "qs:name_adm0":"\u81fa\u7063",
    "qs:name_adm1":"\u53f0\u4e2d\u5e02",
    "qs:photos":20,
    "qs:photos_1k":4,
    "qs:photos_9k":1,
    "qs:photos_9r":1,
    "qs:photos_all":20,
    "qs:photos_sr":1,
    "qs:placetype":"Town",
    "qs:pop_sr":"0",
    "wof:name":"\u842c\u8c50\u6751",
    "wof:placetype":"locality"
},
  "geometry": {"coordinates":[120.72305149999998,23.996635],"type":"Point"}
}