{
  "type": "Feature",
  "properties": {
    "gn:admin1_code":"2.0",
    "gn:admin2_code":"KHH",
    "gn:admin3_code":"E13",
    "gn:admin4_code":"64000130022.0",
    "gn:asciiname":"Qingshuiyan",
    "gn:country_code":"TW",
    "gn:dem":8,
    "gn:feature_class":"P",
    "gn:feature_code":"PPL",
    "gn:name":"Qingshuiyan",
    "gn:population":0,
    "gn:timezone":"Asia/Taipei",
    "iso:country":"TW",
    "name:und_x_variant":[
        "\u6e05\u6c34\u5dd6",
        "Cingshueiyan",
        "Qingshuiyan"
    ],
    "name:zho_x_preferred":[
        "Ch\u2019ing-shui-yen"
    ],
    "name:zho_x_variant":[
        "\u6e05\u6c34\u5dd6"
    ],
    "wof:name":"Qingshuiyan",
    "wof:placetype":"locality"
},
  "geometry": {"coordinates":[120.38934,22.52277],"type":"Point"}
}