{
  "type": "Feature",
  "properties": {
    "gn:admin1_code":"4.0",
    "gn:admin2_code":"TAO",
    "gn:admin3_code":"H06",
    "gn:admin4_code":"68000060011.0",
    "gn:asciiname":"Kanxia",
    "gn:country_code":"TW",
    "gn:dem":21,
    "gn:feature_class":"P",
    "gn:feature_code":"PPL",
    "gn:name":"Kanxia",
    "gn:population":0,
    "gn:timezone":"Asia/Taipei",
    "iso:country":"TW",
    "name:und_x_variant":[
        "Kansia",
        "Kanxia"
    ],
    "name:zho_x_preferred":[
        "\u5d01\u4e0b"
    ],
    "name:zho_x_variant":[
        "K\u2019an-hsia"
    ],
    "wof:name":"Kanxia",
    "wof:placetype":"locality"
},
  "geometry": {"coordinates":[121.26219,25.08563],"type":"Point"}
}