{
  "type": "Feature",
  "properties": {
    "gn:admin1_code":"04",
    "gn:admin2_code":"PIF",
    "gn:admin3_code":"T25",
    "gn:admin4_code":"10013250001.0",
    "gn:asciiname":"Citong",
    "gn:country_code":"TW",
    "gn:dem":4,
    "gn:feature_class":"P",
    "gn:feature_code":"PPL",
    "gn:name":"Citong",
    "gn:population":0,
    "gn:timezone":"Asia/Taipei",
    "iso:country":"TW",
    "name:und_x_variant":[
        "La-t\u2019ung-chiao",
        "Tz\u2019u-t\u2019ung-chiao",
        "\u83bf\u6850",
        "Tz\u2019u-t\u2019ung-ts\u2019un",
        "Cihtong",
        "Citong",
        "Tz\u2019u-t\u2019ung"
    ],
    "name:zho_x_preferred":[
        "Tz\u2019u-t\u2019ung"
    ],
    "wof:name":"Citong",
    "wof:placetype":"locality"
},
  "geometry": {"coordinates":[120.65416999999999,22.25111],"type":"Point"}
}