{
  "type": "Feature",
  "properties": {
    "gn:admin1_code":"04",
    "gn:admin2_code":"TXG",
    "gn:admin3_code":"B10",
    "gn:admin4_code":"66000100001.0",
    "gn:asciiname":"Dongshi",
    "gn:country_code":"TW",
    "gn:dem":369,
    "gn:feature_class":"P",
    "gn:feature_code":"PPL",
    "gn:name":"Dongshi",
    "gn:population":0,
    "gn:timezone":"Asia/Taipei",
    "iso:country":"TW",
    "name:und_x_variant":[
        "Tung-shih-chieh",
        "Tung-shih-chen",
        "Tung-shih",
        "\u6771\u52e2",
        "Dongshi",
        "Dongshih"
    ],
    "name:zho_x_preferred":[
        "\u6771\u52e2"
    ],
    "wof:name":"Dongshi",
    "wof:placetype":"locality"
},
  "geometry": {"coordinates":[120.82868000000001,24.25858],"type":"Point"}
}