{
  "type": "Feature",
  "properties": {
    "gn:admin1_code":"4.0",
    "gn:admin2_code":"HUA",
    "gn:admin3_code":"U13",
    "gn:admin4_code":"10015130003.0",
    "gn:asciiname":"Zhongping",
    "gn:country_code":"TW",
    "gn:dem":211,
    "gn:feature_class":"P",
    "gn:feature_code":"PPL",
    "gn:name":"Zhongping",
    "gn:population":0,
    "gn:timezone":"Asia/Taipei",
    "iso:country":"TW",
    "name:und_x_variant":[
        "\u4e2d\u5e73",
        "Zhongping",
        "Jhongping"
    ],
    "name:zho_x_preferred":[
        "Chung-p\u2019ing-she"
    ],
    "name:zho_x_variant":[
        "Chung-p\u2019ing",
        "\u4e2d\u5e73"
    ],
    "wof:name":"Zhongping",
    "wof:placetype":"locality"
},
  "geometry": {"coordinates":[121.29919,23.38948],"type":"Point"}
}