{
  "type": "Feature",
  "properties": {
    "gn:admin1_code":"4.0",
    "gn:admin2_code":"MIA",
    "gn:admin3_code":"K07",
    "gn:admin4_code":"10005140008.0",
    "gn:asciiname":"Buding",
    "gn:country_code":"TW",
    "gn:dem":36,
    "gn:feature_class":"P",
    "gn:feature_code":"PPL",
    "gn:name":"Buding",
    "gn:population":0,
    "gn:timezone":"Asia/Taipei",
    "iso:country":"TW",
    "name:und_x_variant":[
        "Pu-ting"
    ],
    "name:zho_x_preferred":[
        "\u57d4\u9802"
    ],
    "wof:name":"Buding",
    "wof:placetype":"locality"
},
  "geometry": {"coordinates":[120.75597,24.5654],"type":"Point"}
}