{
  "type": "Feature",
  "properties": {
    "iso:country":"TW",
    "qs:name":"\u842c\u91d1\u6751",
    "qs:name_adm0":"\u81fa\u7063",
    "qs:name_adm1":"\u5c4f\u6771\u7e23",
    "qs:photos":19,
    "qs:photos_1k":4,
    "qs:photos_9k":1,
    "qs:photos_9r":1,
    "qs:photos_all":19,
    "qs:photos_sr":1,
    "qs:placetype":"Town",
    "qs:pop_sr":"0",
    "wof:name":"\u842c\u91d1\u6751",
    "wof:placetype":"locality"
},
  "geometry": {"coordinates":[120.615936,22.58871],"type":"Point"}
}