{
  "type": "Feature",
  "properties": {
    "gn:admin1_code":"4.0",
    "gn:admin2_code":"CYQ",
    "gn:admin3_code":"Q03",
    "gn:admin4_code":"10010030009.0",
    "gn:asciiname":"Xinqinliao",
    "gn:country_code":"TW",
    "gn:dem":7,
    "gn:feature_class":"P",
    "gn:feature_code":"PPL",
    "gn:name":"Xinqinliao",
    "gn:population":0,
    "gn:timezone":"Asia/Taipei",
    "iso:country":"TW",
    "name:und_x_variant":[
        "Kuo-ling-liao",
        "Xinqinliao",
        "Sincinliao"
    ],
    "name:zho_x_preferred":[
        "Kuo-ts\u2019en-liao"
    ],
    "name:zho_x_variant":[
        "\u65b0\u82a9\u5bee",
        "Hsin-ch\u2019in",
        "Hsin-ts\u2019en-liao",
        "Hsin-ch\u2019in-liao"
    ],
    "wof:name":"Xinqinliao",
    "wof:placetype":"locality"
},
  "geometry": {"coordinates":[120.17143,23.34147],"type":"Point"}
}