{
  "type": "Feature",
  "properties": {
    "gn:admin1_code":"4.0",
    "gn:admin2_code":"YUN",
    "gn:admin3_code":"P12",
    "gn:admin4_code":"10009120005.0",
    "gn:asciiname":"Dongxing",
    "gn:country_code":"TW",
    "gn:dem":20,
    "gn:feature_class":"P",
    "gn:feature_code":"PPL",
    "gn:name":"Dongxing",
    "gn:population":0,
    "gn:timezone":"Asia/Taipei",
    "iso:country":"TW",
    "name:ceb_x_preferred":[
        "Dongxing"
    ],
    "name:deu_x_preferred":[
        "Dongxing"
    ],
    "name:fra_x_preferred":[
        "Dongxing"
    ],
    "name:mlg_x_preferred":[
        "Dongxing"
    ],
    "name:nor_x_preferred":[
        "Dongxing"
    ],
    "name:pnb_x_preferred":[
        "\u0688\u0648\u0646\u06af\u0634\u06cc\u0646\u06af"
    ],
    "name:rus_x_preferred":[
        "\u0414\u0443\u043d\u0441\u0438\u043d"
    ],
    "name:swe_x_preferred":[
        "Dongxing"
    ],
    "name:und_x_variant":[
        "Fu-hsing",
        "Dongxing",
        "Dongsing",
        "Tung-hsing"
    ],
    "name:vie_x_preferred":[
        "\u0110\u00f4ng H\u01b0ng"
    ],
    "name:zho_x_preferred":[
        "T\u2019ien-liao"
    ],
    "name:zho_x_variant":[
        "\u6771\u8208",
        "Fu-hsing-ts\u2019un"
    ],
    "wof:name":"Dongxing",
    "wof:placetype":"locality"
},
  "geometry": {"coordinates":[120.36638000000001,23.75874],"type":"Point"}
}