{
  "type": "Feature",
  "properties": {
    "gn:admin1_code":"4.0",
    "gn:admin2_code":"CYQ",
    "gn:admin3_code":"Q14",
    "gn:admin4_code":"10010130002.0",
    "gn:asciiname":"Banshanzi",
    "gn:country_code":"TW",
    "gn:dem":134,
    "gn:feature_class":"P",
    "gn:feature_code":"PPL",
    "gn:name":"Banshanzi",
    "gn:population":0,
    "gn:timezone":"Asia/Taipei",
    "iso:country":"TW",
    "name:und_x_variant":[
        "Banshanzih",
        "Banshanzi",
        "Pan-shan-tzu"
    ],
    "name:zho_x_preferred":[
        "\u534a\u5c71\u5b50"
    ],
    "wof:name":"Banshanzi",
    "wof:placetype":"locality"
},
  "geometry": {"coordinates":[120.54031999999999,23.4271],"type":"Point"}
}