{
  "type": "Feature",
  "properties": {
    "gn:admin1_code":"4.0",
    "gn:admin2_code":"TTT",
    "gn:admin3_code":"V13",
    "gn:admin4_code":"10014120003.0",
    "gn:asciiname":"Xiangyang",
    "gn:country_code":"TW",
    "gn:dem":2350,
    "gn:feature_class":"P",
    "gn:feature_code":"PPL",
    "gn:name":"Xiangyang",
    "gn:population":0,
    "gn:timezone":"Asia/Taipei",
    "iso:country":"TW",
    "name:und_x_variant":[
        "Siangyang",
        "Xiangyang",
        "Hsiang-yang"
    ],
    "name:zho_x_preferred":[
        "\u5411\u967d"
    ],
    "wof:name":"Xiangyang",
    "wof:placetype":"locality"
},
  "geometry": {"coordinates":[120.98505,23.24869],"type":"Point"}
}