{
  "type": "Feature",
  "properties": {
    "gn:admin1_code":"4.0",
    "gn:admin2_code":"ILA",
    "gn:admin3_code":"G06",
    "gn:admin4_code":"10002020018.0",
    "gn:asciiname":"Guangxing",
    "gn:country_code":"TW",
    "gn:dem":17,
    "gn:feature_class":"P",
    "gn:feature_code":"PPL",
    "gn:name":"Guangxing",
    "gn:population":0,
    "gn:timezone":"Asia/Taipei",
    "iso:country":"TW",
    "name:und_x_variant":[
        "Kuang-an",
        "Guangxing",
        "Guangsing",
        "Kuang-hsing"
    ],
    "name:zho_x_preferred":[
        "Kuang-an-ts\u2019un"
    ],
    "name:zho_x_variant":[
        "\u5ee3\u8208"
    ],
    "wof:name":"Guangxing",
    "wof:placetype":"locality"
},
  "geometry": {"coordinates":[121.75257999999999,24.6726],"type":"Point"}
}