{
  "type": "Feature",
  "properties": {
    "gn:admin1_code":"04",
    "gn:admin2_code":"TTT",
    "gn:admin3_code":"V05",
    "gn:admin4_code":"10014100004.0",
    "gn:asciiname":"Shangwu",
    "gn:country_code":"TW",
    "gn:dem":8,
    "gn:feature_class":"P",
    "gn:feature_code":"PPL",
    "gn:name":"Shangwu",
    "gn:population":0,
    "gn:timezone":"Asia/Taipei",
    "iso:country":"TW",
    "name:und_x_variant":[
        "Shang-wu"
    ],
    "name:zho_x_preferred":[
        "Chang-wu-ts\u2019un"
    ],
    "name:zho_x_variant":[
        "Shang-wu-ts\u2019un",
        "\u5c1a\u6b66"
    ],
    "wof:name":"Shangwu",
    "wof:placetype":"locality"
},
  "geometry": {"coordinates":[120.89082999999999,22.33972],"type":"Point"}
}