{
  "type": "Feature",
  "properties": {
    "gn:admin1_code":"04",
    "gn:admin2_code":"MIA",
    "gn:admin3_code":"K05",
    "gn:admin4_code":"10005100005.0",
    "gn:asciiname":"Niujiaokeng",
    "gn:country_code":"TW",
    "gn:dem":284,
    "gn:feature_class":"P",
    "gn:feature_code":"PPL",
    "gn:name":"Niujiaokeng",
    "gn:population":0,
    "gn:timezone":"Asia/Taipei",
    "iso:country":"TW",
    "name:und_x_variant":[
        "Nioujiaokeng"
    ],
    "name:zho_x_preferred":[
        "\u725b\u89d2\u5751"
    ],
    "name:zho_x_variant":[
        "Niu-chiao-k\u2019eng"
    ],
    "wof:name":"Niujiaokeng",
    "wof:placetype":"locality"
},
  "geometry": {"coordinates":[120.75833,24.46667],"type":"Point"}
}