{
  "type": "Feature",
  "properties": {
    "gn:admin1_code":"4.0",
    "gn:admin2_code":"CHA",
    "gn:admin3_code":"N02",
    "gn:admin4_code":"10007020026.0",
    "gn:asciiname":"Haibu",
    "gn:country_code":"TW",
    "gn:dem":7,
    "gn:feature_class":"P",
    "gn:feature_code":"PPL",
    "gn:name":"Haibu",
    "gn:population":0,
    "gn:timezone":"Asia/Taipei",
    "iso:country":"TW",
    "name:und_x_variant":[
        "Hai-pu"
    ],
    "name:zho_x_preferred":[
        "\u6d77\u57d4"
    ],
    "wof:name":"Haibu",
    "wof:placetype":"locality"
},
  "geometry": {"coordinates":[120.44444,24.08556],"type":"Point"}
}