{
  "type": "Feature",
  "properties": {
    "gn:admin1_code":"04",
    "gn:admin2_code":"TXG",
    "gn:admin3_code":"B11",
    "gn:admin4_code":"66000110024.0",
    "gn:asciiname":"Wulipai",
    "gn:country_code":"TW",
    "gn:dem":41,
    "gn:feature_class":"P",
    "gn:feature_code":"PPL",
    "gn:name":"Wulipai",
    "gn:population":0,
    "gn:timezone":"Asia/Taipei",
    "iso:country":"TW",
    "name:zho_x_preferred":[
        "\u4e94\u91cc\u724c"
    ],
    "name:zho_x_variant":[
        "Wu-li-p\u2019ai",
        "\u4e94\u91cc\u724c\u8857\u9053"
    ],
    "wof:name":"Wulipai",
    "wof:placetype":"locality"
},
  "geometry": {"coordinates":[120.64194000000001,24.40278],"type":"Point"}
}