{
  "type": "Feature",
  "properties": {
    "gn:admin1_code":"4.0",
    "gn:admin2_code":"TXG",
    "gn:admin3_code":"B26",
    "gn:admin4_code":"66000260019.0",
    "gn:asciiname":"Shulianhuajiao",
    "gn:country_code":"TW",
    "gn:dem":53,
    "gn:feature_class":"P",
    "gn:feature_code":"PPL",
    "gn:name":"Shulianhuajiao",
    "gn:population":0,
    "gn:timezone":"Asia/Taipei",
    "iso:country":"TW",
    "name:und_x_variant":[
        "\u6a39\u84ee\u82b1\u811a",
        "Shulianhuajiao",
        "Shu-lien-hua-chiao"
    ],
    "wof:name":"Shulianhuajiao",
    "wof:placetype":"locality"
},
  "geometry": {"coordinates":[120.6632,24.046],"type":"Point"}
}