{
  "type": "Feature",
  "properties": {
    "gn:admin1_code":"4.0",
    "gn:admin2_code":"HUA",
    "gn:admin3_code":"U08",
    "gn:admin4_code":"10015080003.0",
    "gn:asciiname":"Jiqi",
    "gn:country_code":"TW",
    "gn:dem":9,
    "gn:feature_class":"P",
    "gn:feature_code":"PPL",
    "gn:name":"Jiqi",
    "gn:population":0,
    "gn:timezone":"Asia/Taipei",
    "iso:country":"TW",
    "name:und_x_variant":[
        "Jici",
        "Jiqi"
    ],
    "name:zho_x_preferred":[
        "\u78ef\u5d0e"
    ],
    "name:zho_x_variant":[
        "Chi-ch\u2019i"
    ],
    "wof:name":"Jiqi",
    "wof:placetype":"locality"
},
  "geometry": {"coordinates":[121.5475,23.70833],"type":"Point"}
}