{
  "type": "Feature",
  "properties": {
    "gn:admin1_code":"04",
    "gn:admin2_code":"CHA",
    "gn:admin3_code":"N05",
    "gn:admin4_code":"10007100034.0",
    "gn:asciiname":"Baiguoshan",
    "gn:country_code":"TW",
    "gn:dem":36,
    "gn:feature_class":"P",
    "gn:feature_code":"PPL",
    "gn:name":"Baiguoshan",
    "gn:population":0,
    "gn:timezone":"Asia/Taipei",
    "iso:country":"TW",
    "name:und_x_variant":[
        "Pai-kuo-shan"
    ],
    "wof:name":"Baiguoshan",
    "wof:placetype":"locality"
},
  "geometry": {"coordinates":[120.59999999999999,23.96667],"type":"Point"}
}