{
  "type": "Feature",
  "properties": {
    "gn:admin1_code":"2.0",
    "gn:admin2_code":"KHH",
    "gn:admin3_code":"E37",
    "gn:admin4_code":"64000370001.0",
    "gn:asciiname":"Sishe",
    "gn:country_code":"TW",
    "gn:dem":801,
    "gn:feature_class":"P",
    "gn:feature_code":"PPL",
    "gn:name":"Sishe",
    "gn:population":0,
    "gn:timezone":"Asia/Taipei",
    "iso:country":"TW",
    "name:und_x_variant":[
        "Sihshe",
        "Ssu-she"
    ],
    "name:zho_x_preferred":[
        "\u56db\u793e"
    ],
    "wof:name":"Sishe",
    "wof:placetype":"locality"
},
  "geometry": {"coordinates":[120.76611,23.16778],"type":"Point"}
}