{
  "type": "Feature",
  "properties": {
    "iso:country":"TW",
    "qs:name":"\u529b\u91cc\u6751",
    "qs:name_adm0":"\u81fa\u7063",
    "qs:name_adm1":"\u5c4f\u6771\u7e23",
    "qs:photos":36,
    "qs:photos_1k":7,
    "qs:photos_9k":1,
    "qs:photos_9r":2,
    "qs:photos_all":36,
    "qs:photos_sr":2,
    "qs:placetype":"Town",
    "qs:pop_sr":"0",
    "wof:name":"\u529b\u91cc\u6751",
    "wof:placetype":"locality"
},
  "geometry": {"coordinates":[120.68719400000001,22.414726],"type":"Point"}
}