{
  "type": "Feature",
  "properties": {
    "gn:admin1_code":"4.0",
    "gn:admin2_code":"CHA",
    "gn:admin3_code":"N01",
    "gn:admin4_code":"10007010030.0",
    "gn:asciiname":"Zhuzijiao",
    "gn:country_code":"TW",
    "gn:dem":14,
    "gn:feature_class":"P",
    "gn:feature_code":"PPL",
    "gn:name":"Zhuzijiao",
    "gn:population":0,
    "gn:timezone":"Asia/Taipei",
    "iso:country":"TW",
    "name:und_x_variant":[
        "Jhuzihjiao",
        "Hsia-kan-tzu-chiao",
        "Chu-tzu-chiao"
    ],
    "name:zho_x_preferred":[
        "\u7af9\u5b50\u811a"
    ],
    "wof:name":"Zhuzijiao",
    "wof:placetype":"locality"
},
  "geometry": {"coordinates":[120.51833000000001,24.08278],"type":"Point"}
}