{
  "type": "Feature",
  "properties": {
    "gn:admin1_code":"04",
    "gn:admin2_code":"TXG",
    "gn:admin3_code":"B23",
    "gn:admin4_code":"66000230011.0",
    "gn:asciiname":"Dongyuancun",
    "gn:country_code":"TW",
    "gn:dem":31,
    "gn:feature_class":"P",
    "gn:feature_code":"PPL",
    "gn:name":"Dongyuancun",
    "gn:population":0,
    "gn:timezone":"Asia/Taipei",
    "iso:country":"TW",
    "name:und_x_variant":[
        "Tung-y\u00fcan-ts\u2019un"
    ],
    "wof:name":"Dongyuancun",
    "wof:placetype":"locality"
},
  "geometry": {"coordinates":[120.63333,24.08333],"type":"Point"}
}