{
  "type": "Feature",
  "properties": {
    "iso:country":"TW",
    "qs:name":"\u516c\u6b63\u91cc",
    "qs:name_adm0":"\u81fa\u7063",
    "qs:name_adm1":"\u53f0\u4e2d\u5e02",
    "qs:photos":651,
    "qs:photos_1k":132,
    "qs:photos_9k":3,
    "qs:photos_9r":5,
    "qs:photos_all":651,
    "qs:photos_sr":8,
    "qs:placetype":"Suburb",
    "qs:pop_sr":"0",
    "wd:wordcount":334,
    "wof:name":"\u516c\u6b63\u91cc",
    "wof:placetype":"neighbourhood"
},
  "geometry": {"coordinates":[120.65133299999999,24.147152],"type":"Point"}
}