{
  "type": "Feature",
  "properties": {
    "gn:admin1_code":"4.0",
    "gn:admin2_code":"TAO",
    "gn:admin3_code":"H07",
    "gn:admin4_code":"68000070016.0",
    "gn:asciiname":"Banling",
    "gn:country_code":"TW",
    "gn:dem":140,
    "gn:feature_class":"P",
    "gn:feature_code":"PPL",
    "gn:name":"Banling",
    "gn:population":0,
    "gn:timezone":"Asia/Taipei",
    "iso:country":"TW",
    "name:und_x_variant":[
        "Pan-ling"
    ],
    "name:zho_x_preferred":[
        "\u534a\u5dba"
    ],
    "wof:name":"Banling",
    "wof:placetype":"locality"
},
  "geometry": {"coordinates":[121.35406999999999,25.00196],"type":"Point"}
}