{
  "type": "Feature",
  "properties": {
    "gn:admin1_code":"4.0",
    "gn:admin2_code":"PEN",
    "gn:admin3_code":"X05",
    "gn:asciiname":"Dongpingwei",
    "gn:country_code":"TW",
    "gn:dem":4,
    "gn:feature_class":"P",
    "gn:feature_code":"PPL",
    "gn:name":"Dongpingwei",
    "gn:population":0,
    "gn:timezone":"Asia/Taipei",
    "iso:country":"TW",
    "name:zho_x_preferred":[
        "\u6771\u576a\u5c3e"
    ],
    "name:zho_x_variant":[
        "Tung-p\u2019ing-wei"
    ],
    "wof:name":"Dongpingwei",
    "wof:placetype":"locality"
},
  "geometry": {"coordinates":[119.61861,23.245],"type":"Point"}
}