{
  "type": "Feature",
  "properties": {
    "iso:country":"TW",
    "qs:name":"\u4f55\u660e\u91cc",
    "qs:name_adm0":"\u81fa\u7063",
    "qs:name_adm1":"\u53f0\u4e2d\u5e02",
    "qs:photos":69,
    "qs:photos_1k":14,
    "qs:photos_9k":1,
    "qs:photos_9r":2,
    "qs:photos_all":69,
    "qs:photos_sr":2,
    "qs:placetype":"Suburb",
    "qs:pop_sr":"0",
    "wof:name":"\u4f55\u660e\u91cc",
    "wof:placetype":"neighbourhood"
},
  "geometry": {"coordinates":[120.659645,24.160858],"type":"Point"}
}