{
  "type": "Feature",
  "properties": {
    "gn:admin1_code":"4.0",
    "gn:admin2_code":"CHA",
    "gn:admin3_code":"N05",
    "gn:admin4_code":"10007100029.0",
    "gn:asciiname":"Qilinkeng",
    "gn:country_code":"TW",
    "gn:dem":188,
    "gn:feature_class":"P",
    "gn:feature_code":"PPL",
    "gn:name":"Qilinkeng",
    "gn:population":0,
    "gn:timezone":"Asia/Taipei",
    "iso:country":"TW",
    "name:und_x_variant":[
        "Cilinkeng"
    ],
    "name:zho_x_preferred":[
        "\u9e92\u9e9f\u5751"
    ],
    "name:zho_x_variant":[
        "Ch\u2019i-lin-k\u2019eng"
    ],
    "wof:name":"Qilinkeng",
    "wof:placetype":"locality"
},
  "geometry": {"coordinates":[120.61771,23.95722],"type":"Point"}
}