{
  "type": "Feature",
  "properties": {
    "gn:admin1_code":"4.0",
    "gn:admin2_code":"CYQ",
    "gn:admin3_code":"Q17",
    "gn:admin4_code":"10010160010.0",
    "gn:asciiname":"Niushanxizi",
    "gn:country_code":"TW",
    "gn:dem":436,
    "gn:feature_class":"P",
    "gn:feature_code":"PPL",
    "gn:name":"Niushanxizi",
    "gn:population":0,
    "gn:timezone":"Asia/Taipei",
    "iso:country":"TW",
    "name:und_x_variant":[
        "Nioushansizih",
        "Niushanxizi",
        "Niu-shan-hsi-tzu"
    ],
    "name:zho_x_preferred":[
        "\u725b\u5c71\u6eaa\u4ed4"
    ],
    "wof:name":"Niushanxizi",
    "wof:placetype":"locality"
},
  "geometry": {"coordinates":[120.61987999999999,23.42994],"type":"Point"}
}