{
  "type": "Feature",
  "properties": {
    "gn:admin1_code":"4.0",
    "gn:admin2_code":"YUN",
    "gn:admin3_code":"P10",
    "gn:admin4_code":"10009100008.0",
    "gn:asciiname":"Wutuzi",
    "gn:country_code":"TW",
    "gn:dem":72,
    "gn:feature_class":"P",
    "gn:feature_code":"PPL",
    "gn:name":"Wutuzi",
    "gn:population":0,
    "gn:timezone":"Asia/Taipei",
    "iso:country":"TW",
    "name:und_x_variant":[
        "Wutuzih",
        "Wutuzi"
    ],
    "name:zho_x_preferred":[
        "\u70cf\u5857\u4ed4"
    ],
    "name:zho_x_variant":[
        "Wu-t\u2019u-tzu"
    ],
    "wof:name":"Wutuzi",
    "wof:placetype":"locality"
},
  "geometry": {"coordinates":[120.59686000000001,23.76763],"type":"Point"}
}