{
  "type": "Feature",
  "properties": {
    "iso:country":"TW",
    "qs:name":"\u96d9\u7389\u6751",
    "qs:name_adm0":"\u81fa\u7063",
    "qs:name_adm1":"\u65b0\u5317\u5e02",
    "qs:photos":627,
    "qs:photos_1k":127,
    "qs:photos_9k":3,
    "qs:photos_9r":5,
    "qs:photos_all":627,
    "qs:photos_sr":8,
    "qs:placetype":"Town",
    "qs:pop_sr":"0",
    "wof:name":"\u96d9\u7389\u6751",
    "wof:placetype":"locality"
},
  "geometry": {"coordinates":[121.928157,25.000605],"type":"Point"}
}