{
  "type": "Feature",
  "properties": {
    "gn:admin1_code":"4.0",
    "gn:admin2_code":"CYQ",
    "gn:admin3_code":"Q20",
    "gn:admin4_code":"10010180005.0",
    "gn:asciiname":"Neilaiji",
    "gn:country_code":"TW",
    "gn:dem":880,
    "gn:feature_class":"P",
    "gn:feature_code":"PPL",
    "gn:name":"Neilaiji",
    "gn:population":0,
    "gn:timezone":"Asia/Taipei",
    "iso:country":"TW",
    "name:und_x_variant":[
        "Lai-chi",
        "La-la-kou-she",
        "Neilaiji",
        "Lai-chi-she",
        "Nei-lai-chi"
    ],
    "name:zho_x_preferred":[
        "La-la-ch\u2019i-she"
    ],
    "name:zho_x_variant":[
        "La-la-ch\u2019i",
        "\u5167\u4f86\u5409"
    ],
    "wof:name":"Neilaiji",
    "wof:placetype":"locality"
},
  "geometry": {"coordinates":[120.74639000000001,23.52056],"type":"Point"}
}