{
  "type": "Feature",
  "properties": {
    "gn:admin1_code":"4.0",
    "gn:admin2_code":"CHA",
    "gn:admin3_code":"N19",
    "gn:admin4_code":"10007170008.0",
    "gn:asciiname":"Fangqiaotou",
    "gn:country_code":"TW",
    "gn:dem":38,
    "gn:feature_class":"P",
    "gn:feature_code":"PPL",
    "gn:name":"Fangqiaotou",
    "gn:population":0,
    "gn:timezone":"Asia/Taipei",
    "iso:country":"TW",
    "name:und_x_variant":[
        "Fangciaotou",
        "Fangqiaotou"
    ],
    "name:zho_x_preferred":[
        "\u678b\u6a4b\u982d"
    ],
    "name:zho_x_variant":[
        "Hsia-fang-ch\u2019iao-t\u2019ou",
        "Fang-ch\u2019iao-t\u2019ou"
    ],
    "wof:name":"Fangqiaotou",
    "wof:placetype":"locality"
},
  "geometry": {"coordinates":[120.5869,23.9217],"type":"Point"}
}