{
  "type": "Feature",
  "properties": {
    "gn:admin1_code":"4.0",
    "gn:admin2_code":"HUA",
    "gn:admin3_code":"U06",
    "gn:admin4_code":"10015060013.0",
    "gn:asciiname":"Bengkan",
    "gn:country_code":"TW",
    "gn:dem":31,
    "gn:feature_class":"P",
    "gn:feature_code":"PPL",
    "gn:name":"Bengkan",
    "gn:population":0,
    "gn:timezone":"Asia/Taipei",
    "iso:country":"TW",
    "name:zho_x_preferred":[
        "Peng-k\u2019an"
    ],
    "name:zho_x_variant":[
        "\u5d29\u5d01"
    ],
    "wof:name":"Bengkan",
    "wof:placetype":"locality"
},
  "geometry": {"coordinates":[121.57917,23.89139],"type":"Point"}
}