{
  "type": "Feature",
  "properties": {
    "gn:admin1_code":"4.0",
    "gn:admin2_code":"NAN",
    "gn:admin3_code":"M10",
    "gn:admin4_code":"10008100010.0",
    "gn:asciiname":"Zhuzilai",
    "gn:country_code":"TW",
    "gn:dem":365,
    "gn:feature_class":"P",
    "gn:feature_code":"PPL",
    "gn:name":"Zhuzilai",
    "gn:population":0,
    "gn:timezone":"Asia/Taipei",
    "iso:country":"TW",
    "name:und_x_variant":[
        "Jhuzihlai",
        "Zhuzilai",
        "Chu-tzu-lai"
    ],
    "name:zho_x_preferred":[
        "\u7af9\u5b50\u7c5f"
    ],
    "wof:name":"Zhuzilai",
    "wof:placetype":"locality"
},
  "geometry": {"coordinates":[120.90031999999999,23.98032000000001],"type":"Point"}
}