{
  "type": "Feature",
  "properties": {
    "gn:admin1_code":"03",
    "gn:admin2_code":"TPQ",
    "gn:admin3_code":"F21",
    "gn:admin4_code":"65000120032.0",
    "gn:asciiname":"Nanya",
    "gn:country_code":"TW",
    "gn:dem":37,
    "gn:feature_class":"P",
    "gn:feature_code":"PPL",
    "gn:name":"Nanya",
    "gn:population":0,
    "gn:timezone":"Asia/Taipei",
    "iso:country":"TW",
    "name:und_x_variant":[
        "Nan-ya-li",
        "Nanya",
        "Nan-ya"
    ],
    "name:zho_x_preferred":[
        "\u5357\u96c5"
    ],
    "wof:name":"Nanya",
    "wof:placetype":"locality"
},
  "geometry": {"coordinates":[121.87716,25.12086],"type":"Point"}
}