{
  "type": "Feature",
  "properties": {
    "gn:admin1_code":"04",
    "gn:admin2_code":"CHA",
    "gn:admin3_code":"N16",
    "gn:admin4_code":"10007140017.0",
    "gn:asciiname":"Shipi",
    "gn:country_code":"TW",
    "gn:dem":16,
    "gn:feature_class":"P",
    "gn:feature_code":"PPL",
    "gn:name":"Shipi",
    "gn:population":0,
    "gn:timezone":"Asia/Taipei",
    "iso:country":"TW",
    "name:und_x_variant":[
        "Shih-pei",
        "Shipi",
        "Shihpi"
    ],
    "name:zho_x_preferred":[
        "Shih-pei-ts\u2019un"
    ],
    "name:zho_x_variant":[
        "Shih-p\u2019i-ts\u2019un",
        "Shih-p\u2019i-chiao",
        "\u77f3\u57e4",
        "Shih-p\u2019i"
    ],
    "wof:name":"Shipi",
    "wof:placetype":"locality"
},
  "geometry": {"coordinates":[120.42064999999999,23.99017000000001],"type":"Point"}
}