{
  "type": "Feature",
  "properties": {
    "gn:admin1_code":"04",
    "gn:admin2_code":"NAN",
    "gn:admin3_code":"M13",
    "gn:admin4_code":"10008130008.0",
    "gn:asciiname":"Songlin",
    "gn:country_code":"TW",
    "gn:dem":839,
    "gn:feature_class":"P",
    "gn:feature_code":"PPL",
    "gn:name":"Songlin",
    "gn:population":0,
    "gn:timezone":"Asia/Taipei",
    "iso:country":"TW",
    "name:und_x_variant":[
        "Sung-lin"
    ],
    "name:zho_x_preferred":[
        "\u677e\u6797"
    ],
    "wof:name":"Songlin",
    "wof:placetype":"locality"
},
  "geometry": {"coordinates":[121.09778,23.96972],"type":"Point"}
}