{
  "type": "Feature",
  "properties": {
    "iso:country":"TW",
    "qs:name":"\u679c\u8cbf\u91cc",
    "qs:name_adm0":"\u81fa\u7063",
    "qs:name_adm1":"\u9ad8\u96c4\u5e02",
    "qs:photos":147,
    "qs:photos_1k":30,
    "qs:photos_9k":1,
    "qs:photos_9r":3,
    "qs:photos_all":147,
    "qs:photos_sr":3,
    "qs:placetype":"Suburb",
    "qs:pop_sr":"0",
    "wof:name":"\u679c\u8cbf\u91cc",
    "wof:placetype":"neighbourhood"
},
  "geometry": {"coordinates":[120.293228,22.672569],"type":"Point"}
}