{
  "type": "Feature",
  "properties": {
    "gn:admin1_code":"4.0",
    "gn:admin2_code":"TXG",
    "gn:admin3_code":"B10",
    "gn:admin4_code":"66000100008.0",
    "gn:asciiname":"Xiaozhongke",
    "gn:country_code":"TW",
    "gn:dem":364,
    "gn:feature_class":"P",
    "gn:feature_code":"PPL",
    "gn:name":"Xiaozhongke",
    "gn:population":0,
    "gn:timezone":"Asia/Taipei",
    "iso:country":"TW",
    "name:und_x_variant":[
        "Siaojhongke",
        "Xiaozhongke",
        "\u5c0f\u4e2d\u5d59"
    ],
    "name:zho_x_preferred":[
        "Hsiao-chung-k\u2019o"
    ],
    "name:zho_x_variant":[
        "\u5c0f\u4e2d\u5d59"
    ],
    "wof:name":"Xiaozhongke",
    "wof:placetype":"locality"
},
  "geometry": {"coordinates":[120.83743,24.25675],"type":"Point"}
}