{
  "type": "Feature",
  "properties": {
    "gn:admin1_code":"04",
    "gn:admin2_code":"KEE",
    "gn:admin3_code":"C03",
    "gn:admin4_code":"10017030009.0",
    "gn:asciiname":"Dongshikeng",
    "gn:country_code":"TW",
    "gn:dem":126,
    "gn:feature_class":"P",
    "gn:feature_code":"PPL",
    "gn:name":"Dongshikeng",
    "gn:population":0,
    "gn:timezone":"Asia/Taipei",
    "iso:country":"TW",
    "name:und_x_variant":[
        "Dongshihkeng",
        "Dongshikeng"
    ],
    "name:zho_x_preferred":[
        "\u6771\u52e2\u5751"
    ],
    "name:zho_x_variant":[
        "Tung-shih-k\u2019eng"
    ],
    "wof:name":"Dongshikeng",
    "wof:placetype":"locality"
},
  "geometry": {"coordinates":[121.75165,25.08095],"type":"Point"}
}