{
  "type": "Feature",
  "properties": {
    "gn:admin1_code":"04",
    "gn:admin2_code":"TXG",
    "gn:admin3_code":"B22",
    "gn:admin4_code":"66000220012.0",
    "gn:asciiname":"Songzijiao",
    "gn:country_code":"TW",
    "gn:dem":23,
    "gn:feature_class":"P",
    "gn:feature_code":"PPL",
    "gn:name":"Songzijiao",
    "gn:population":0,
    "gn:timezone":"Asia/Taipei",
    "iso:country":"TW",
    "name:und_x_variant":[
        "Songzihjiao",
        "Sung-tzu-chiao"
    ],
    "name:zho_x_preferred":[
        "\u677e\u4ed4\u811a"
    ],
    "wof:name":"Songzijiao",
    "wof:placetype":"locality"
},
  "geometry": {"coordinates":[120.60417,24.36194],"type":"Point"}
}