{
  "type": "Feature",
  "properties": {
    "gn:admin1_code":"4.0",
    "gn:admin2_code":"NAN",
    "gn:admin3_code":"M09",
    "gn:admin4_code":"10008090011.0",
    "gn:asciiname":"Dasheman",
    "gn:country_code":"TW",
    "gn:dem":693,
    "gn:feature_class":"P",
    "gn:feature_code":"PPL",
    "gn:name":"Dasheman",
    "gn:population":0,
    "gn:timezone":"Asia/Taipei",
    "iso:country":"TW",
    "name:und_x_variant":[
        "Ta-she-man"
    ],
    "name:zho_x_preferred":[
        "\u5927\u820c\u6eff"
    ],
    "wof:name":"Dasheman",
    "wof:placetype":"locality"
},
  "geometry": {"coordinates":[120.90096,23.8396],"type":"Point"}
}