{
  "type": "Feature",
  "properties": {
    "gn:admin1_code":"2.0",
    "gn:admin2_code":"KHH",
    "gn:admin3_code":"E34",
    "gn:admin4_code":"64000340007.0",
    "gn:asciiname":"Xinkaizhuang",
    "gn:country_code":"TW",
    "gn:dem":89,
    "gn:feature_class":"P",
    "gn:feature_code":"PPL",
    "gn:name":"Xinkaizhuang",
    "gn:population":0,
    "gn:timezone":"Asia/Taipei",
    "iso:country":"TW",
    "name:und_x_variant":[
        "Chu-wei",
        "Xinkaizhuang",
        "Sinkaijhuang"
    ],
    "name:zho_x_preferred":[
        "\u65b0\u958b\u838a"
    ],
    "name:zho_x_variant":[
        "Chu-y\u00fcan",
        "Hsin-k\u2019ai-chuang"
    ],
    "wof:name":"Xinkaizhuang",
    "wof:placetype":"locality"
},
  "geometry": {"coordinates":[120.53292999999999,22.94593],"type":"Point"}
}