{
  "type": "Feature",
  "properties": {
    "gn:admin1_code":"4.0",
    "gn:admin2_code":"TAO",
    "gn:admin3_code":"H02",
    "gn:admin4_code":"68000030013.0",
    "gn:asciiname":"Liziyuan",
    "gn:country_code":"TW",
    "gn:dem":102,
    "gn:feature_class":"P",
    "gn:feature_code":"PPL",
    "gn:name":"Liziyuan",
    "gn:population":0,
    "gn:timezone":"Asia/Taipei",
    "iso:country":"TW",
    "name:und_x_variant":[
        "Lizihyuan",
        "Liziyuan"
    ],
    "name:zho_x_preferred":[
        "\u6817\u5b50\u5712"
    ],
    "name:zho_x_variant":[
        "Li-tzu-y\u00fcan"
    ],
    "wof:name":"Liziyuan",
    "wof:placetype":"locality"
},
  "geometry": {"coordinates":[121.27957000000001,24.89187],"type":"Point"}
}