{
  "type": "Feature",
  "properties": {
    "gn:admin1_code":"4.0",
    "gn:admin2_code":"YUN",
    "gn:admin3_code":"P13",
    "gn:admin4_code":"10009130007.0",
    "gn:asciiname":"Sishi'erdong",
    "gn:country_code":"TW",
    "gn:dem":3,
    "gn:feature_class":"P",
    "gn:feature_code":"PPL",
    "gn:name":"Sishi\u2019erdong",
    "gn:population":0,
    "gn:timezone":"Asia/Taipei",
    "iso:country":"TW",
    "name:und_x_variant":[
        "Ssu-shih-erh-tung",
        "Sihshiherdong",
        "\u56db\u5341\u4e8c\u68df"
    ],
    "name:zho_x_preferred":[
        "Sishi\u2019erdong"
    ],
    "wof:name":"Sishi'erdong",
    "wof:placetype":"locality"
},
  "geometry": {"coordinates":[120.20694,23.7675],"type":"Point"}
}