{
  "type": "Feature",
  "properties": {
    "gn:admin1_code":"04",
    "gn:admin2_code":"ILA",
    "gn:admin3_code":"G05",
    "gn:admin4_code":"10002070009.0",
    "gn:asciiname":"Siyuanli",
    "gn:country_code":"TW",
    "gn:dem":10,
    "gn:feature_class":"P",
    "gn:feature_code":"PPL",
    "gn:name":"Siyuanli",
    "gn:population":0,
    "gn:timezone":"Asia/Taipei",
    "iso:country":"TW",
    "name:und_x_variant":[
        "Ssu-y\u00fcan-li"
    ],
    "wof:name":"Siyuanli",
    "wof:placetype":"locality"
},
  "geometry": {"coordinates":[121.71666999999999,24.75],"type":"Point"}
}