{
  "type": "Feature",
  "properties": {
    "gn:admin1_code":"4.0",
    "gn:admin2_code":"TXG",
    "gn:admin3_code":"B09",
    "gn:admin4_code":"66000090029.0",
    "gn:asciiname":"Fanziyuan",
    "gn:country_code":"TW",
    "gn:dem":332,
    "gn:feature_class":"P",
    "gn:feature_code":"PPL",
    "gn:name":"Fanziyuan",
    "gn:population":0,
    "gn:timezone":"Asia/Taipei",
    "iso:country":"TW",
    "name:und_x_variant":[
        "Fanzihyuan",
        "Fan-tzu-y\u00fcan"
    ],
    "name:zho_x_preferred":[
        "\u756a\u5b50\u5712"
    ],
    "name:zho_x_variant":[
        "Fan-tzu-y\u00fcan"
    ],
    "wof:name":"Fanziyuan",
    "wof:placetype":"locality"
},
  "geometry": {"coordinates":[120.75483,24.22466],"type":"Point"}
}