{
  "type": "Feature",
  "properties": {
    "iso:country":"TW",
    "qs:name":"\u57e4\u982d\u6751",
    "qs:name_adm0":"\u81fa\u7063",
    "qs:name_adm1":"\u65b0\u5317\u5e02",
    "qs:photos":64,
    "qs:photos_1k":13,
    "qs:photos_9k":1,
    "qs:photos_9r":2,
    "qs:photos_all":64,
    "qs:photos_sr":2,
    "qs:placetype":"Town",
    "qs:pop_sr":"0",
    "wof:name":"\u57e4\u982d\u6751",
    "wof:placetype":"locality"
},
  "geometry": {"coordinates":[121.42192799999999,25.133474],"type":"Point"}
}