{
  "type": "Feature",
  "properties": {
    "iso:country":"TW",
    "qs:name":"\u7530\u7f8e\u6751",
    "qs:name_adm0":"\u81fa\u7063",
    "qs:name_adm1":"\u82d7\u6817\u7e23",
    "qs:photos":156,
    "qs:photos_1k":32,
    "qs:photos_9k":1,
    "qs:photos_9r":4,
    "qs:photos_all":156,
    "qs:photos_sr":4,
    "qs:placetype":"Town",
    "qs:pop_sr":"0",
    "wof:name":"\u7530\u7f8e\u6751",
    "wof:placetype":"locality"
},
  "geometry": {"coordinates":[121.01174849999998,24.61094],"type":"Point"}
}