{
  "type": "Feature",
  "properties": {
    "gn:admin1_code":"4.0",
    "gn:admin2_code":"TAO",
    "gn:admin3_code":"H04",
    "gn:admin4_code":"68000040016.0",
    "gn:asciiname":"Meigang",
    "gn:country_code":"TW",
    "gn:dem":178,
    "gn:feature_class":"P",
    "gn:feature_code":"PPL",
    "gn:name":"Meigang",
    "gn:population":0,
    "gn:timezone":"Asia/Taipei",
    "iso:country":"TW",
    "name:und_x_variant":[
        "Mei-kang"
    ],
    "name:zho_x_preferred":[
        "\u6885\u5d17"
    ],
    "wof:name":"Meigang",
    "wof:placetype":"locality"
},
  "geometry": {"coordinates":[121.14722,24.92389],"type":"Point"}
}