{
  "type": "Feature",
  "properties": {
    "gn:admin1_code":"4.0",
    "gn:admin2_code":"HSZ",
    "gn:admin3_code":"J11",
    "gn:admin4_code":"10004100004.0",
    "gn:asciiname":"Xincheng",
    "gn:country_code":"TW",
    "gn:dem":31,
    "gn:feature_class":"P",
    "gn:feature_code":"PPL",
    "gn:name":"Xincheng",
    "gn:population":0,
    "gn:timezone":"Asia/Taipei",
    "iso:country":"TW",
    "name:ceb_x_preferred":[
        "Xincheng"
    ],
    "name:deu_x_preferred":[
        "Xincheng"
    ],
    "name:fra_x_preferred":[
        "Xincheng"
    ],
    "name:jpn_x_preferred":[
        "\u65b0\u57ce\u533a"
    ],
    "name:kor_x_preferred":[
        "\uc2e0\uccad\uad6c"
    ],
    "name:mlg_x_preferred":[
        "Xincheng"
    ],
    "name:nor_x_preferred":[
        "Xincheng"
    ],
    "name:rus_x_preferred":[
        "\u0421\u0438\u043d\u044c\u0447\u044d\u043d"
    ],
    "name:swe_x_preferred":[
        "Xincheng"
    ],
    "name:und_x_variant":[
        "Sincheng"
    ],
    "name:zho_x_preferred":[
        "\u65b0\u57ce"
    ],
    "name:zho_x_variant":[
        "Hsin-ch\u2019eng-li",
        "Hsin-ch\u2019eng",
        "\u65b0\u57ce\u533a"
    ],
    "wof:name":"Xincheng",
    "wof:placetype":"locality"
},
  "geometry": {"coordinates":[120.96389000000001,24.73066],"type":"Point"}
}