{
  "type": "Feature",
  "properties": {
    "gn:admin1_code":"4.0",
    "gn:admin2_code":"MIA",
    "gn:admin3_code":"K10",
    "gn:admin4_code":"10005050005.0",
    "gn:asciiname":"Xinglong",
    "gn:country_code":"TW",
    "gn:dem":36,
    "gn:feature_class":"P",
    "gn:feature_code":"PPL",
    "gn:name":"Xinglong",
    "gn:population":0,
    "gn:timezone":"Asia/Taipei",
    "iso:country":"TW",
    "name:und_x_variant":[
        "Hsiang-lung",
        "Singlong",
        "Xinglong",
        "Hsing-lung"
    ],
    "name:zho_x_preferred":[
        "\u8208\u9686"
    ],
    "wof:name":"Xinglong",
    "wof:placetype":"locality"
},
  "geometry": {"coordinates":[120.93194,24.69736],"type":"Point"}
}