{
  "type": "Feature",
  "properties": {
    "gn:admin1_code":"4.0",
    "gn:admin2_code":"HSQ",
    "gn:admin3_code":"O03",
    "gn:admin4_code":"10018030005.0",
    "gn:asciiname":"Dingziwei",
    "gn:country_code":"TW",
    "gn:dem":11,
    "gn:feature_class":"P",
    "gn:feature_code":"PPL",
    "gn:name":"Dingziwei",
    "gn:population":0,
    "gn:timezone":"Asia/Taipei",
    "iso:country":"TW",
    "name:und_x_variant":[
        "Dingzihwei",
        "Ting-tzu-wei"
    ],
    "name:zho_x_preferred":[
        "\u9802\u4ed4\u570d"
    ],
    "wof:name":"Dingziwei",
    "wof:placetype":"locality"
},
  "geometry": {"coordinates":[120.93111,24.79306],"type":"Point"}
}