{
  "type": "Feature",
  "properties": {
    "gn:admin1_code":"4.0",
    "gn:admin2_code":"NAN",
    "gn:admin3_code":"M02",
    "gn:admin4_code":"10008020017.0",
    "gn:asciiname":"Gongliyuan",
    "gn:country_code":"TW",
    "gn:dem":437,
    "gn:feature_class":"P",
    "gn:feature_code":"PPL",
    "gn:name":"Gongliyuan",
    "gn:population":0,
    "gn:timezone":"Asia/Taipei",
    "iso:country":"TW",
    "name:zho_x_preferred":[
        "\u5171\u52f5\u5712"
    ],
    "name:zho_x_variant":[
        "Kung-li-y\u00fcan"
    ],
    "wof:name":"Gongliyuan",
    "wof:placetype":"locality"
},
  "geometry": {"coordinates":[120.92128,23.975],"type":"Point"}
}