{
  "type": "Feature",
  "properties": {
    "iso:country":"TW",
    "qs:name":"\u767c\u7965\u6751",
    "qs:name_adm0":"\u81fa\u7063",
    "qs:name_adm1":"\u5357\u6295\u7e23",
    "qs:photos":274,
    "qs:photos_1k":56,
    "qs:photos_9k":1,
    "qs:photos_9r":4,
    "qs:photos_all":274,
    "qs:photos_sr":5,
    "qs:placetype":"Town",
    "qs:pop_sr":"0",
    "wof:name":"\u767c\u7965\u6751",
    "wof:placetype":"locality"
},
  "geometry": {"coordinates":[121.14454000000001,24.1421425],"type":"Point"}
}