{
  "type": "Feature",
  "properties": {
    "gn:admin1_code":"4.0",
    "gn:admin2_code":"NAN",
    "gn:admin3_code":"M05",
    "gn:admin4_code":"10008050007.0",
    "gn:asciiname":"Jiji",
    "gn:country_code":"TW",
    "gn:dem":240,
    "gn:feature_class":"P",
    "gn:feature_code":"PPL",
    "gn:name":"Jiji",
    "gn:population":0,
    "gn:timezone":"Asia/Taipei",
    "iso:country":"TW",
    "name:ceb_x_preferred":[
        "Jiji Zhen"
    ],
    "name:deu_x_preferred":[
        "Jiji"
    ],
    "name:hak_x_preferred":[
        "Si\u030dp-si\u030dp-ts\u1e73\u0301n"
    ],
    "name:jpn_x_preferred":[
        "\u96c6\u96c6\u93ae"
    ],
    "name:kor_x_preferred":[
        "\uc9c0\uc9c0\uc9c4"
    ],
    "name:pol_x_preferred":[
        "Jiji"
    ],
    "name:und_x_variant":[
        "Chi-chi"
    ],
    "name:vie_x_preferred":[
        "T\u1eadp T\u1eadp"
    ],
    "name:zho_x_preferred":[
        "\u96c6\u96c6"
    ],
    "name:zho_x_variant":[
        "\u96c6\u96c6\u93ae"
    ],
    "wof:name":"Jiji",
    "wof:placetype":"locality"
},
  "geometry": {"coordinates":[120.78815,23.82882],"type":"Point"}
}