{
  "type": "Feature",
  "properties": {
    "gn:admin1_code":"4.0",
    "gn:admin2_code":"NAN",
    "gn:admin3_code":"M05",
    "gn:admin4_code":"10008050007.0",
    "gn:asciiname":"Jiji",
    "gn:country_code":"TW",
    "gn:dem":240,
    "gn:feature_class":"P",
    "gn:feature_code":"PPL",
    "gn:name":"Jiji",
    "gn:population":0,
    "gn:timezone":"Asia/Taipei",
    "iso:country":"TW",
    "name:und_x_variant":[
        "Chi-chi"
    ],
    "name:zho_x_preferred":[
        "\u96c6\u96c6"
    ],
    "wof:name":"Jiji",
    "wof:placetype":"locality"
},
  "geometry": {"coordinates":[120.78815,23.82882],"type":"Point"}
}