{
  "type": "Feature",
  "properties": {
    "iso:country":"TW",
    "qs:name":"\u4e94\u798f\u6751",
    "qs:name_adm0":"\u81fa\u7063",
    "qs:name_adm1":"\u9ad8\u96c4\u5e02",
    "qs:photos":20,
    "qs:photos_1k":4,
    "qs:photos_9k":1,
    "qs:photos_9r":1,
    "qs:photos_all":20,
    "qs:photos_sr":1,
    "qs:placetype":"Town",
    "qs:pop_sr":"0",
    "wof:name":"\u4e94\u798f\u6751",
    "wof:placetype":"locality"
},
  "geometry": {"coordinates":[120.41559599999999,22.495048],"type":"Point"}
}