{
  "type": "Feature",
  "properties": {
    "gn:admin1_code":"04",
    "gn:admin2_code":"TNN",
    "gn:admin3_code":"R15",
    "gn:admin4_code":"67000160004.0",
    "gn:asciiname":"Ouwang",
    "gn:country_code":"TW",
    "gn:dem":9,
    "gn:feature_class":"P",
    "gn:feature_code":"PPL",
    "gn:name":"Ouwang",
    "gn:population":0,
    "gn:timezone":"Asia/Taipei",
    "iso:country":"TW",
    "name:und_x_variant":[
        "Ou-wang",
        "Ouwang",
        "\u6f1a\u6c6a"
    ],
    "name:zho_x_preferred":[
        "Ch\u2019ang-jung-ts\u2019un"
    ],
    "name:zho_x_variant":[
        "Chiang-ch\u00fcn",
        "Ch\u2019ang-jung",
        "\u6f1a\u6c6a"
    ],
    "wof:name":"Ouwang",
    "wof:placetype":"locality"
},
  "geometry": {"coordinates":[120.1575,23.20083],"type":"Point"}
}