{
  "type": "Feature",
  "properties": {
    "gn:admin1_code":"4.0",
    "gn:admin2_code":"HSZ",
    "gn:admin3_code":"J11",
    "gn:admin4_code":"10004100008.0",
    "gn:asciiname":"Fangzikeng",
    "gn:country_code":"TW",
    "gn:dem":75,
    "gn:feature_class":"P",
    "gn:feature_code":"PPL",
    "gn:name":"Fangzikeng",
    "gn:population":0,
    "gn:timezone":"Asia/Taipei",
    "iso:country":"TW",
    "name:und_x_variant":[
        "Fangzihkeng",
        "Fangzikeng"
    ],
    "name:zho_x_preferred":[
        "\u678b\u5b50\u5751"
    ],
    "name:zho_x_variant":[
        "Fang-tzu-k\u2019eng"
    ],
    "wof:name":"Fangzikeng",
    "wof:placetype":"locality"
},
  "geometry": {"coordinates":[121.02083,24.74222],"type":"Point"}
}