{
  "type": "Feature",
  "properties": {
    "iso:country":"TW",
    "qs:name":"\u795e\u8fb2\u91cc",
    "qs:name_adm0":"\u81fa\u7063",
    "qs:name_adm1":"\u5609\u7fa9\u5e02",
    "qs:photos":28,
    "qs:photos_1k":6,
    "qs:photos_9k":1,
    "qs:photos_9r":2,
    "qs:photos_all":28,
    "qs:photos_sr":2,
    "qs:placetype":"Suburb",
    "qs:pop_sr":"0",
    "wof:name":"\u795e\u8fb2\u91cc",
    "wof:placetype":"neighbourhood"
},
  "geometry": {"coordinates":[120.46064,23.4748425],"type":"Point"}
}