{
  "type": "Feature",
  "properties": {
    "gn:admin1_code":"04",
    "gn:admin2_code":"CHA",
    "gn:admin3_code":"N02",
    "gn:admin4_code":"10007020025.0",
    "gn:asciiname":"Dingshanliao",
    "gn:country_code":"TW",
    "gn:dem":7,
    "gn:feature_class":"P",
    "gn:feature_code":"PPL",
    "gn:name":"Dingshanliao",
    "gn:population":0,
    "gn:timezone":"Asia/Taipei",
    "iso:country":"TW",
    "name:und_x_variant":[
        "Ting-shan-liao"
    ],
    "name:zho_x_preferred":[
        "\u9802\u5c71\u5bee"
    ],
    "wof:name":"Dingshanliao",
    "wof:placetype":"locality"
},
  "geometry": {"coordinates":[120.45417,24.11917],"type":"Point"}
}