{
  "type": "Feature",
  "properties": {
    "gn:admin1_code":"04",
    "gn:admin2_code":"ILA",
    "gn:admin3_code":"G07",
    "gn:admin4_code":"10002090014.0",
    "gn:asciiname":"Piziwei",
    "gn:country_code":"TW",
    "gn:dem":11,
    "gn:feature_class":"P",
    "gn:feature_code":"PPL",
    "gn:name":"Piziwei",
    "gn:population":0,
    "gn:timezone":"Asia/Taipei",
    "iso:country":"TW",
    "name:und_x_variant":[
        "Lung-te-li",
        "Piziwei",
        "Pizihwei"
    ],
    "name:zho_x_preferred":[
        "\u57e4\u4ed4\u5c3e"
    ],
    "name:zho_x_variant":[
        "P\u2019i-tzu-wei"
    ],
    "wof:name":"Piziwei",
    "wof:placetype":"locality"
},
  "geometry": {"coordinates":[121.8283,24.6502],"type":"Point"}
}