{
  "type": "Feature",
  "properties": {
    "gn:admin1_code":"4.0",
    "gn:admin2_code":"HUA",
    "gn:admin3_code":"U11",
    "gn:admin4_code":"10015110002.0",
    "gn:asciiname":"Luoshao",
    "gn:country_code":"TW",
    "gn:dem":978,
    "gn:feature_class":"P",
    "gn:feature_code":"PPL",
    "gn:name":"Luoshao",
    "gn:population":0,
    "gn:timezone":"Asia/Taipei",
    "iso:country":"TW",
    "name:und_x_variant":[
        "Lo-shao"
    ],
    "name:zho_x_preferred":[
        "\u6d1b\u97f6"
    ],
    "wof:name":"Luoshao",
    "wof:placetype":"locality"
},
  "geometry": {"coordinates":[121.45111,24.20722],"type":"Point"}
}