{
  "type": "Feature",
  "properties": {
    "gn:admin1_code":"4.0",
    "gn:admin2_code":"NAN",
    "gn:admin3_code":"M06",
    "gn:admin4_code":"10008060013.0",
    "gn:asciiname":"Lankoudian",
    "gn:country_code":"TW",
    "gn:dem":259,
    "gn:feature_class":"P",
    "gn:feature_code":"PPL",
    "gn:name":"Lankoudian",
    "gn:population":0,
    "gn:timezone":"Asia/Taipei",
    "iso:country":"TW",
    "name:zho_x_preferred":[
        "\u7c43\u53e3\u5e97"
    ],
    "name:zho_x_variant":[
        "Lan-k\u2019ou-tien-tzu",
        "Lan-k\u2019ou-tien"
    ],
    "wof:name":"Lankoudian",
    "wof:placetype":"locality"
},
  "geometry": {"coordinates":[120.64643999999998,23.8655],"type":"Point"}
}