{
  "type": "Feature",
  "properties": {
    "gn:admin1_code":"4.0",
    "gn:admin2_code":"TNN",
    "gn:admin3_code":"R27",
    "gn:admin4_code":"67000270006.0",
    "gn:asciiname":"Xintian",
    "gn:country_code":"TW",
    "gn:dem":15,
    "gn:feature_class":"P",
    "gn:feature_code":"PPL",
    "gn:name":"Xintian",
    "gn:population":0,
    "gn:timezone":"Asia/Taipei",
    "iso:country":"TW",
    "name:und_x_variant":[
        "Sintian"
    ],
    "name:zho_x_preferred":[
        "\u65b0\u7530"
    ],
    "name:zho_x_variant":[
        "Hsin-t\u2019ien"
    ],
    "wof:name":"Xintian",
    "wof:placetype":"locality"
},
  "geometry": {"coordinates":[120.26389,22.95583],"type":"Point"}
}