{
  "type": "Feature",
  "properties": {
    "iso:country":"TW",
    "name:eng_x_preferred":[
        "Chikan"
    ],
    "name:eng_x_variant":[
        "Chikan Village"
    ],
    "name:zho_tw_x_preferred":[
        "\u8d64\u5d01\u91cc"
    ],
    "qs:name":"\u8d64\u5d01\u91cc",
    "qs:name_adm0":"\u81fa\u7063",
    "qs:name_adm1":"\u53f0\u5357\u5e02",
    "qs:photos":561,
    "qs:photos_1k":114,
    "qs:photos_9k":2,
    "qs:photos_9r":5,
    "qs:photos_all":561,
    "qs:photos_sr":8,
    "qs:placetype":"Suburb",
    "qs:pop_sr":"0",
    "wof:name":"Chikan",
    "wof:placetype":"neighbourhood"
},
  "geometry": {"coordinates":[120.206222,22.997745],"type":"Point"}
}