{
  "type": "Feature",
  "properties": {
    "gn:admin1_code":"04",
    "gn:admin2_code":"YUN",
    "gn:admin3_code":"P01",
    "gn:admin4_code":"10009010020.0",
    "gn:asciiname":"Shenzhenlun",
    "gn:country_code":"TW",
    "gn:dem":47,
    "gn:feature_class":"P",
    "gn:feature_code":"PPL",
    "gn:name":"Shenzhenlun",
    "gn:population":0,
    "gn:timezone":"Asia/Taipei",
    "iso:country":"TW",
    "name:und_x_variant":[
        "Shenjhenlun",
        "Shenzhenlun",
        "Shen-chen-liao",
        "Shen-chen-lun"
    ],
    "name:zho_x_preferred":[
        "Shen-ch\u2019\u00fcan-lun"
    ],
    "name:zho_x_variant":[
        "Shen-ch\u2019ou-lun",
        "\u6df1\u5733\u5d19",
        "Shen-ch\u00fcn-lun"
    ],
    "wof:name":"Shenzhenlun",
    "wof:placetype":"locality"
},
  "geometry": {"coordinates":[120.51944,23.6825],"type":"Point"}
}