{
  "type": "Feature",
  "properties": {
    "gn:admin1_code":"4.0",
    "gn:admin2_code":"YUN",
    "gn:admin3_code":"P13",
    "gn:admin4_code":"10009130011.0",
    "gn:asciiname":"Hunei",
    "gn:country_code":"TW",
    "gn:dem":12,
    "gn:feature_class":"P",
    "gn:feature_code":"PPL",
    "gn:name":"Hunei",
    "gn:population":0,
    "gn:timezone":"Asia/Taipei",
    "iso:country":"TW",
    "name:und_x_variant":[
        "Hu-nei"
    ],
    "name:zho_x_preferred":[
        "\u6e56\u5167"
    ],
    "wof:name":"Hunei",
    "wof:placetype":"locality"
},
  "geometry": {"coordinates":[120.27911,23.79444],"type":"Point"}
}