{
  "type": "Feature",
  "properties": {
    "gn:admin1_code":"04",
    "gn:admin2_code":"CYQ",
    "gn:admin3_code":"Q05",
    "gn:admin4_code":"10010050014.0",
    "gn:asciiname":"Yeziliao",
    "gn:country_code":"TW",
    "gn:dem":59,
    "gn:feature_class":"P",
    "gn:feature_code":"PPL",
    "gn:name":"Yeziliao",
    "gn:population":0,
    "gn:timezone":"Asia/Taipei",
    "iso:country":"TW",
    "name:und_x_variant":[
        "San-hsing",
        "Yeziliao",
        "Yezihliao",
        "Yeh-tzu-liao"
    ],
    "name:zho_x_preferred":[
        "San-hsing-ts\u2019un"
    ],
    "name:zho_x_variant":[
        "\u8449\u5b50\u5bee"
    ],
    "wof:name":"Yeziliao",
    "wof:placetype":"locality"
},
  "geometry": {"coordinates":[120.49848,23.56145],"type":"Point"}
}