{
  "type": "Feature",
  "properties": {
    "gn:admin1_code":"4.0",
    "gn:admin2_code":"TNN",
    "gn:admin3_code":"R02",
    "gn:admin4_code":"67000020012.0",
    "gn:asciiname":"Yichou",
    "gn:country_code":"TW",
    "gn:dem":10,
    "gn:feature_class":"P",
    "gn:feature_code":"PPL",
    "gn:name":"Yichou",
    "gn:population":0,
    "gn:timezone":"Asia/Taipei",
    "iso:country":"TW",
    "name:zho_x_preferred":[
        "\u7fa9\u7a20"
    ],
    "name:zho_x_variant":[
        "Niu-ch\u2019ou-tzu",
        "I-ch\u2019ou"
    ],
    "wof:name":"Yichou",
    "wof:placetype":"locality"
},
  "geometry": {"coordinates":[120.25591,23.32594],"type":"Point"}
}