{
  "type": "Feature",
  "properties": {
    "gn:admin1_code":"04",
    "gn:admin2_code":"MIA",
    "gn:admin3_code":"K07",
    "gn:admin4_code":"10005140006.0",
    "gn:asciiname":"Nankeng",
    "gn:country_code":"TW",
    "gn:dem":103,
    "gn:feature_class":"P",
    "gn:feature_code":"PPL",
    "gn:name":"Nankeng",
    "gn:population":0,
    "gn:timezone":"Asia/Taipei",
    "iso:country":"TW",
    "name:und_x_variant":[
        "Nan-hsing"
    ],
    "name:zho_x_preferred":[
        "\u5357\u5751"
    ],
    "name:zho_x_variant":[
        "Nan-k\u2019eng"
    ],
    "wof:name":"Nankeng",
    "wof:placetype":"locality"
},
  "geometry": {"coordinates":[120.77576000000001,24.53909],"type":"Point"}
}