{
  "type": "Feature",
  "properties": {
    "gn:admin1_code":"4.0",
    "gn:admin2_code":"TNN",
    "gn:admin3_code":"R19",
    "gn:admin4_code":"67000190012.0",
    "gn:asciiname":"Xiwei",
    "gn:country_code":"TW",
    "gn:dem":21,
    "gn:feature_class":"P",
    "gn:feature_code":"PPL",
    "gn:name":"Xiwei",
    "gn:population":0,
    "gn:timezone":"Asia/Taipei",
    "iso:country":"TW",
    "name:ceb_x_preferred":[
        "Xiwei"
    ],
    "name:swe_x_preferred":[
        "Xiwei"
    ],
    "name:und_x_variant":[
        "Hsi-mei-li",
        "Hsi-mei",
        "Xiwei",
        "Siwei",
        "Hsi-wei"
    ],
    "name:zho_x_preferred":[
        "Ch\u2019i-mei"
    ],
    "name:zho_x_variant":[
        "Ch\u2019i-mei-li",
        "Ch\u2019i-wei",
        "\u6eaa\u5c3e"
    ],
    "wof:name":"Xiwei",
    "wof:placetype":"locality"
},
  "geometry": {"coordinates":[120.28627,23.15221],"type":"Point"}
}