{
  "type": "Feature",
  "properties": {
    "gn:admin1_code":"4.0",
    "gn:admin2_code":"MIA",
    "gn:admin3_code":"K11",
    "gn:admin4_code":"10005150008.0",
    "gn:asciiname":"Tanwenhu",
    "gn:country_code":"TW",
    "gn:dem":19,
    "gn:feature_class":"P",
    "gn:feature_code":"PPL",
    "gn:name":"Tanwenhu",
    "gn:population":0,
    "gn:timezone":"Asia/Taipei",
    "iso:country":"TW",
    "name:und_x_variant":[
        "Tanwunhu"
    ],
    "name:zho_x_preferred":[
        "\u8ac7\u6587\u6e56"
    ],
    "name:zho_x_variant":[
        "T\u2019an-wen-hu"
    ],
    "wof:name":"Tanwenhu",
    "wof:placetype":"locality"
},
  "geometry": {"coordinates":[120.84829000000001,24.64963],"type":"Point"}
}