{
  "type": "Feature",
  "properties": {
    "gn:admin1_code":"4.0",
    "gn:admin2_code":"ILA",
    "gn:admin3_code":"G05",
    "gn:admin4_code":"10002070008.0",
    "gn:asciiname":"Xiacukeng",
    "gn:country_code":"TW",
    "gn:dem":77,
    "gn:feature_class":"P",
    "gn:feature_code":"PPL",
    "gn:name":"Xiacukeng",
    "gn:population":0,
    "gn:timezone":"Asia/Taipei",
    "iso:country":"TW",
    "name:und_x_variant":[
        "Siacukeng",
        "Xiacukeng"
    ],
    "name:zho_x_preferred":[
        "\u4e0b\u7c97\u5751"
    ],
    "name:zho_x_variant":[
        "Hsia-ts\u2019u-k\u2019eng"
    ],
    "wof:name":"Xiacukeng",
    "wof:placetype":"locality"
},
  "geometry": {"coordinates":[121.65734,24.71006],"type":"Point"}
}