{
  "type": "Feature",
  "properties": {
    "gn:admin1_code":"2.0",
    "gn:admin2_code":"KHH",
    "gn:admin3_code":"E37",
    "gn:admin4_code":"64000370001.0",
    "gn:asciiname":"Shengou",
    "gn:country_code":"TW",
    "gn:dem":735,
    "gn:feature_class":"P",
    "gn:feature_code":"PPL",
    "gn:name":"Shengou",
    "gn:population":0,
    "gn:timezone":"Asia/Taipei",
    "iso:country":"TW",
    "name:und_x_variant":[
        "Shen-kou"
    ],
    "name:zho_x_preferred":[
        "\u6df1\u6e9d"
    ],
    "wof:name":"Shengou",
    "wof:placetype":"locality"
},
  "geometry": {"coordinates":[120.755,23.15389],"type":"Point"}
}