{
  "type": "Feature",
  "properties": {
    "gn:admin1_code":"3.0",
    "gn:admin2_code":"TPQ",
    "gn:admin3_code":"F23",
    "gn:admin4_code":"65000250009.0",
    "gn:asciiname":"Zhikeng",
    "gn:country_code":"TW",
    "gn:dem":266,
    "gn:feature_class":"P",
    "gn:feature_code":"PPL",
    "gn:name":"Zhikeng",
    "gn:population":0,
    "gn:timezone":"Asia/Taipei",
    "iso:country":"TW",
    "name:und_x_variant":[
        "Jhihkeng",
        "Zhikeng"
    ],
    "name:zho_x_preferred":[
        "\u7d19\u5751"
    ],
    "name:zho_x_variant":[
        "Chih-k\u2019eng"
    ],
    "wof:name":"Zhikeng",
    "wof:placetype":"locality"
},
  "geometry": {"coordinates":[121.809,25.0279],"type":"Point"}
}