{
  "type": "Feature",
  "properties": {
    "gn:admin1_code":"4.0",
    "gn:admin2_code":"CHA",
    "gn:admin3_code":"N24",
    "gn:admin4_code":"10007240001.0",
    "gn:asciiname":"Xiatanqian",
    "gn:country_code":"TW",
    "gn:dem":14,
    "gn:feature_class":"P",
    "gn:feature_code":"PPL",
    "gn:name":"Xiatanqian",
    "gn:population":0,
    "gn:timezone":"Asia/Taipei",
    "iso:country":"TW",
    "name:und_x_variant":[
        "Siatancian",
        "Xiatanqian"
    ],
    "name:zho_x_preferred":[
        "\u4e0b\u6f6d\u5898"
    ],
    "name:zho_x_variant":[
        "Hsia-t\u2019an-ch\u2019ien"
    ],
    "wof:name":"Xiatanqian",
    "wof:placetype":"locality"
},
  "geometry": {"coordinates":[120.34648,23.83156],"type":"Point"}
}