{
  "type": "Feature",
  "properties": {
    "gn:admin1_code":"4.0",
    "gn:admin2_code":"MIA",
    "gn:admin3_code":"K03",
    "gn:admin4_code":"10005030005.0",
    "gn:asciiname":"Tuweiwo",
    "gn:country_code":"TW",
    "gn:dem":52,
    "gn:feature_class":"P",
    "gn:feature_code":"PPL",
    "gn:name":"Tuweiwo",
    "gn:population":0,
    "gn:timezone":"Asia/Taipei",
    "iso:country":"TW",
    "name:zho_x_preferred":[
        "\u571f\u5c3e\u7aa9"
    ],
    "name:zho_x_variant":[
        "T\u2019u-wei-wo"
    ],
    "wof:name":"Tuweiwo",
    "wof:placetype":"locality"
},
  "geometry": {"coordinates":[120.70332999999999,24.48028],"type":"Point"}
}