{
  "type": "Feature",
  "properties": {
    "iso:country":"TW",
    "qs:name":"\u677e\u7f85\u6751",
    "qs:name_adm0":"\u81fa\u7063",
    "qs:name_adm1":"\u5b9c\u862d\u7e23",
    "qs:photos":272,
    "qs:photos_1k":55,
    "qs:photos_9k":1,
    "qs:photos_9r":4,
    "qs:photos_all":272,
    "qs:photos_sr":5,
    "qs:placetype":"Town",
    "qs:pop_sr":"0",
    "wof:name":"\u677e\u7f85\u6751",
    "wof:placetype":"locality"
},
  "geometry": {"coordinates":[121.55718249999998,24.6783325],"type":"Point"}
}