{
  "type": "Feature",
  "properties": {
    "gn:country":"TW",
    "iso:country":"TW",
    "qs:name":"\u5bcc\u6e90\u6751",
    "qs:name_adm0":"\u81fa\u7063",
    "qs:name_adm1":"\u53f0\u6771\u7e23",
    "qs:photos":481,
    "qs:photos_1k":97,
    "qs:photos_9k":2,
    "qs:photos_9r":5,
    "qs:photos_all":481,
    "qs:photos_sr":7,
    "qs:placetype":"Town",
    "qs:pop_sr":"0",
    "wof:name":"\u5bcc\u6e90\u6751",
    "wof:placetype":"locality"
},
  "geometry": {"coordinates":[121.187192,22.821455],"type":"Point"}
}