{
  "type": "Feature",
  "properties": {
    "gn:admin1_code":"2.0",
    "gn:admin2_code":"KHH",
    "gn:admin3_code":"E19",
    "gn:admin4_code":"64000190014.0",
    "gn:asciiname":"Qianfengzi",
    "gn:country_code":"TW",
    "gn:dem":14,
    "gn:feature_class":"P",
    "gn:feature_code":"PPL",
    "gn:name":"Qianfengzi",
    "gn:population":0,
    "gn:timezone":"Asia/Taipei",
    "iso:country":"TW",
    "name:und_x_variant":[
        "Chia-feng-li",
        "Cianfongzih",
        "Qianfengzi"
    ],
    "name:zho_x_preferred":[
        "\u524d\u5cf0\u5b50"
    ],
    "name:zho_x_variant":[
        "Ch\u2019ien-feng-tzu"
    ],
    "wof:name":"Qianfengzi",
    "wof:placetype":"locality"
},
  "geometry": {"coordinates":[120.31139,22.83],"type":"Point"}
}