{
  "type": "Feature",
  "properties": {
    "gn:admin1_code":"3.0",
    "gn:admin2_code":"TPQ",
    "gn:admin3_code":"F14",
    "gn:admin4_code":"65000010124.0",
    "gn:asciiname":"Yupingzhuang",
    "gn:country_code":"TW",
    "gn:dem":19,
    "gn:feature_class":"P",
    "gn:feature_code":"PPL",
    "gn:name":"Yupingzhuang",
    "gn:population":0,
    "gn:timezone":"Asia/Taipei",
    "iso:country":"TW",
    "name:und_x_variant":[
        "Yupingjhuang"
    ],
    "name:zho_x_preferred":[
        "\u7389\u5e73\u838a"
    ],
    "name:zho_x_variant":[
        "Y\u00fc-p\u2019ing-chuang"
    ],
    "wof:name":"Yupingzhuang",
    "wof:placetype":"locality"
},
  "geometry": {"coordinates":[121.42906000000001,24.98294],"type":"Point"}
}