{
  "type": "Feature",
  "properties": {
    "gn:admin1_code":"4.0",
    "gn:admin2_code":"HSZ",
    "gn:admin3_code":"J14",
    "gn:admin4_code":"10004120007.0",
    "gn:asciiname":"Tianbu",
    "gn:country_code":"TW",
    "gn:dem":1020,
    "gn:feature_class":"P",
    "gn:feature_code":"PPL",
    "gn:name":"Tianbu",
    "gn:population":0,
    "gn:timezone":"Asia/Taipei",
    "iso:country":"TW",
    "name:zho_x_preferred":[
        "T\u2019a-pa-ho-she"
    ],
    "name:zho_x_variant":[
        "T\u2019a-pa-ho",
        "\u7530\u57d4",
        "Hsia-t\u2019ien-pu",
        "Feng-t\u2019ien",
        "T\u2019ien-pu"
    ],
    "wof:name":"Tianbu",
    "wof:placetype":"locality"
},
  "geometry": {"coordinates":[121.27500000000001,24.63917],"type":"Point"}
}