{
  "type": "Feature",
  "properties": {
    "gn:admin1_code":"4.0",
    "gn:admin2_code":"TXG",
    "gn:admin3_code":"B15",
    "gn:admin4_code":"66000150004.0",
    "gn:asciiname":"Quanzhoucuo",
    "gn:country_code":"TW",
    "gn:dem":243,
    "gn:feature_class":"P",
    "gn:feature_code":"PPL",
    "gn:name":"Quanzhoucuo",
    "gn:population":0,
    "gn:timezone":"Asia/Taipei",
    "iso:country":"TW",
    "name:und_x_variant":[
        "Cyuanjhoucuo",
        "Quanzhoucuo"
    ],
    "name:zho_x_preferred":[
        "\u6cc9\u5dde\u539d"
    ],
    "name:zho_x_variant":[
        "Ch\u2019\u00fcan-chou",
        "Ch\u2019\u00fcan-chou-ts\u2019o"
    ],
    "wof:name":"Quanzhoucuo",
    "wof:placetype":"locality"
},
  "geometry": {"coordinates":[120.72806,24.31333],"type":"Point"}
}