{
  "type": "Feature",
  "properties": {
    "gn:admin1_code":"4.0",
    "gn:admin2_code":"ILA",
    "gn:admin3_code":"G04",
    "gn:admin4_code":"10002060012.0",
    "gn:asciiname":"Shewei",
    "gn:country_code":"TW",
    "gn:dem":4,
    "gn:feature_class":"P",
    "gn:feature_code":"PPL",
    "gn:name":"Shewei",
    "gn:population":0,
    "gn:timezone":"Asia/Taipei",
    "iso:country":"TW",
    "name:und_x_variant":[
        "She-wei"
    ],
    "name:zho_x_preferred":[
        "\u793e\u5c3e"
    ],
    "name:zho_x_variant":[
        "To-lo-mei-y\u00fcan-she"
    ],
    "wof:name":"Shewei",
    "wof:placetype":"locality"
},
  "geometry": {"coordinates":[121.81471999999999,24.7875],"type":"Point"}
}