{
  "type": "Feature",
  "properties": {
    "gn:admin1_code":"2.0",
    "gn:admin2_code":"KHH",
    "gn:admin3_code":"E30",
    "gn:admin4_code":"64000300016.0",
    "gn:asciiname":"Dakeng",
    "gn:country_code":"TW",
    "gn:dem":76,
    "gn:feature_class":"P",
    "gn:feature_code":"PPL",
    "gn:name":"Dakeng",
    "gn:population":0,
    "gn:timezone":"Asia/Taipei",
    "iso:country":"TW",
    "name:ceb_x_preferred":[
        "Dakeng"
    ],
    "name:zho_x_preferred":[
        "\u5927\u5751"
    ],
    "name:zho_x_variant":[
        "Ta-k\u2019eng",
        "\u5927\u5751\u98a8\u666f\u5340"
    ],
    "wof:name":"Dakeng",
    "wof:placetype":"locality"
},
  "geometry": {"coordinates":[120.45193999999999,22.86389],"type":"Point"}
}