{
  "type": "Feature",
  "properties": {
    "gn:admin1_code":"04",
    "gn:admin2_code":"TAO",
    "gn:admin3_code":"H06",
    "gn:admin4_code":"68000060002.0",
    "gn:asciiname":"Tianliao",
    "gn:country_code":"TW",
    "gn:dem":22,
    "gn:feature_class":"P",
    "gn:feature_code":"PPL",
    "gn:name":"Tianliao",
    "gn:population":0,
    "gn:timezone":"Asia/Taipei",
    "iso:country":"TW",
    "name:zho_x_preferred":[
        "\u7530\u5bee"
    ],
    "name:zho_x_variant":[
        "Hsia-k\u2019an",
        "T\u2019ien-liao"
    ],
    "wof:name":"Tianliao",
    "wof:placetype":"locality"
},
  "geometry": {"coordinates":[121.18771,25.06137],"type":"Point"}
}