{
  "type": "Feature",
  "properties": {
    "gn:admin1_code":"04",
    "gn:admin2_code":"MIA",
    "gn:admin3_code":"K10",
    "gn:admin4_code":"10005050025.0",
    "gn:asciiname":"Nankeng",
    "gn:country_code":"TW",
    "gn:dem":22,
    "gn:feature_class":"P",
    "gn:feature_code":"PPL",
    "gn:name":"Nankeng",
    "gn:population":0,
    "gn:timezone":"Asia/Taipei",
    "iso:country":"TW",
    "name:zho_x_preferred":[
        "\u6e73\u5751"
    ],
    "name:zho_x_variant":[
        "Nan-k\u2019eng"
    ],
    "wof:name":"Nankeng",
    "wof:placetype":"locality"
},
  "geometry": {"coordinates":[120.88663,24.63853],"type":"Point"}
}