{
  "type": "Feature",
  "properties": {
    "gn:admin1_code":"4.0",
    "gn:admin2_code":"TNN",
    "gn:admin3_code":"R28",
    "gn:admin4_code":"67000280014.0",
    "gn:asciiname":"Dazhai",
    "gn:country_code":"TW",
    "gn:dem":23,
    "gn:feature_class":"P",
    "gn:feature_code":"PPL",
    "gn:name":"Dazhai",
    "gn:population":0,
    "gn:timezone":"Asia/Taipei",
    "iso:country":"TW",
    "name:fra_x_preferred":[
        "Dazhai"
    ],
    "name:jpn_x_preferred":[
        "\u5927\u5be8\u6751"
    ],
    "name:und_x_variant":[
        "Dajhai",
        "Ta-chai"
    ],
    "name:zho_x_preferred":[
        "\u5927\u5b85"
    ],
    "name:zho_x_variant":[
        "\u5927\u5be8\u6751"
    ],
    "wof:name":"Dazhai",
    "wof:placetype":"locality"
},
  "geometry": {"coordinates":[120.28917,22.98361],"type":"Point"}
}