{
  "type": "Feature",
  "properties": {
    "gn:admin1_code":"4.0",
    "gn:admin2_code":"YUN",
    "gn:admin3_code":"P12",
    "gn:admin4_code":"10009120003.0",
    "gn:asciiname":"Lunbei",
    "gn:country_code":"TW",
    "gn:dem":19,
    "gn:feature_class":"P",
    "gn:feature_code":"PPL",
    "gn:name":"Lunbei",
    "gn:population":0,
    "gn:timezone":"Asia/Taipei",
    "iso:country":"TW",
    "name:und_x_variant":[
        "Lun-pei"
    ],
    "name:zho_x_preferred":[
        "\u5d19\u80cc"
    ],
    "wof:name":"Lunbei",
    "wof:placetype":"locality"
},
  "geometry": {"coordinates":[120.3528,23.76033],"type":"Point"}
}