{
  "type": "Feature",
  "properties": {
    "gn:admin1_code":"4.0",
    "gn:admin2_code":"TAO",
    "gn:admin3_code":"H10",
    "gn:admin4_code":"68000100027.0",
    "gn:asciiname":"Bajiaotang",
    "gn:country_code":"TW",
    "gn:dem":161,
    "gn:feature_class":"P",
    "gn:feature_code":"PPL",
    "gn:name":"Bajiaotang",
    "gn:population":0,
    "gn:timezone":"Asia/Taipei",
    "iso:country":"TW",
    "name:zho_x_preferred":[
        "\u516b\u89d2\u5858"
    ],
    "name:zho_x_variant":[
        "Pa-chiao-t\u2019ang"
    ],
    "wof:name":"Bajiaotang",
    "wof:placetype":"locality"
},
  "geometry": {"coordinates":[121.19333,24.91444],"type":"Point"}
}