{
  "type": "Feature",
  "properties": {
    "gn:admin1_code":"4.0",
    "gn:admin2_code":"PIF",
    "gn:admin3_code":"T13",
    "gn:admin4_code":"10013130020.0",
    "gn:asciiname":"Xiadaxin",
    "gn:country_code":"TW",
    "gn:dem":54,
    "gn:feature_class":"P",
    "gn:feature_code":"PPL",
    "gn:name":"Xiadaxin",
    "gn:population":0,
    "gn:timezone":"Asia/Taipei",
    "iso:country":"TW",
    "name:und_x_variant":[
        "Siadasin",
        "Xiadaxin",
        "Hsia-ta-hsin"
    ],
    "name:zho_x_preferred":[
        "\u4e0b\u5927\u65b0"
    ],
    "wof:name":"Xiadaxin",
    "wof:placetype":"locality"
},
  "geometry": {"coordinates":[120.58114999999999,22.66638],"type":"Point"}
}