{
  "type": "Feature",
  "properties": {
    "gn:admin1_code":"04",
    "gn:admin2_code":"TAO",
    "gn:admin3_code":"H11",
    "gn:admin4_code":"68000110020.0",
    "gn:asciiname":"Shangkanglang",
    "gn:country_code":"TW",
    "gn:dem":32,
    "gn:feature_class":"P",
    "gn:feature_code":"PPL",
    "gn:name":"Shangkanglang",
    "gn:population":0,
    "gn:timezone":"Asia/Taipei",
    "iso:country":"TW",
    "name:zho_x_preferred":[
        "\u4e0a\u69fa\u6994"
    ],
    "name:zho_x_variant":[
        "Shang-k\u2019ang-lang"
    ],
    "wof:name":"Shangkanglang",
    "wof:placetype":"locality"
},
  "geometry": {"coordinates":[121.04833000000001,24.97472],"type":"Point"}
}