{
  "type": "Feature",
  "properties": {
    "gn:admin1_code":"04",
    "gn:admin2_code":"YUN",
    "gn:admin3_code":"P16",
    "gn:admin4_code":"10009160014.0",
    "gn:asciiname":"Wengang",
    "gn:country_code":"TW",
    "gn:dem":6,
    "gn:feature_class":"P",
    "gn:feature_code":"PPL",
    "gn:name":"Wengang",
    "gn:population":0,
    "gn:timezone":"Asia/Taipei",
    "iso:country":"TW",
    "name:und_x_variant":[
        "Wen-kang",
        "Wungang",
        "Wengang",
        "Wen-chiang"
    ],
    "name:zho_x_preferred":[
        "Wen-chiang-ts\u2019un"
    ],
    "name:zho_x_variant":[
        "\u868a\u6e2f"
    ],
    "wof:name":"Wengang",
    "wof:placetype":"locality"
},
  "geometry": {"coordinates":[120.22278,23.75528],"type":"Point"}
}