{
  "type": "Feature",
  "properties": {
    "gn:admin1_code":"4.0",
    "gn:admin2_code":"PIF",
    "gn:admin3_code":"T16",
    "gn:admin4_code":"10013160011.0",
    "gn:asciiname":"Xinkai",
    "gn:country_code":"TW",
    "gn:dem":40,
    "gn:feature_class":"P",
    "gn:feature_code":"PPL",
    "gn:name":"Xinkai",
    "gn:population":0,
    "gn:timezone":"Asia/Taipei",
    "iso:country":"TW",
    "name:pol_x_preferred":[
        "Xinkai"
    ],
    "name:rus_x_preferred":[
        "Xinkai"
    ],
    "name:und_x_variant":[
        "Hsin-k\u2019ai-ts\u2019un",
        "\u65b0\u958b",
        "Xinkai",
        "Sinkai",
        "Hsin-k\u2019ai"
    ],
    "name:zho_x_preferred":[
        "Hsin-k\u2019ai"
    ],
    "wof:name":"Xinkai",
    "wof:placetype":"locality"
},
  "geometry": {"coordinates":[120.61833,22.40806],"type":"Point"}
}