{
  "type": "Feature",
  "properties": {
    "gn:admin1_code":"02",
    "gn:admin2_code":"KHH",
    "gn:admin3_code":"E35",
    "gn:admin4_code":"64000350003.0",
    "gn:asciiname":"Baolin",
    "gn:country_code":"TW",
    "gn:dem":82,
    "gn:feature_class":"P",
    "gn:feature_code":"PPL",
    "gn:name":"Baolin",
    "gn:population":0,
    "gn:timezone":"Asia/Taipei",
    "iso:country":"TW",
    "name:und_x_variant":[
        "Pai-shu-lin",
        "Baolin",
        "Pao-lin"
    ],
    "name:zho_x_preferred":[
        "\u5bf3\u6797"
    ],
    "wof:name":"Baolin",
    "wof:placetype":"locality"
},
  "geometry": {"coordinates":[120.49833,22.96528],"type":"Point"}
}