{
  "type": "Feature",
  "properties": {
    "gn:admin1_code":"4.0",
    "gn:admin2_code":"CHA",
    "gn:admin3_code":"N15",
    "gn:admin4_code":"10007130012.0",
    "gn:asciiname":"Dalupan",
    "gn:country_code":"TW",
    "gn:dem":22,
    "gn:feature_class":"P",
    "gn:feature_code":"PPL",
    "gn:name":"Dalupan",
    "gn:population":0,
    "gn:timezone":"Asia/Taipei",
    "iso:country":"TW",
    "name:und_x_variant":[
        "\u5927\u8def\u7554",
        "Dalupan"
    ],
    "name:zho_x_preferred":[
        "Ta-lu-p\u2019an"
    ],
    "wof:name":"Dalupan",
    "wof:placetype":"locality"
},
  "geometry": {"coordinates":[120.56465,23.99455],"type":"Point"}
}