{
  "type": "Feature",
  "properties": {
    "gn:admin1_code":"02",
    "gn:admin2_code":"KHH",
    "gn:admin3_code":"E22",
    "gn:admin4_code":"64000220005.0",
    "gn:asciiname":"Shuiwatan",
    "gn:country_code":"TW",
    "gn:dem":87,
    "gn:feature_class":"P",
    "gn:feature_code":"PPL",
    "gn:name":"Shuiwatan",
    "gn:population":0,
    "gn:timezone":"Asia/Taipei",
    "iso:country":"TW",
    "name:und_x_variant":[
        "Shueiwatan"
    ],
    "name:zho_x_preferred":[
        "\u6c34\u86d9\u6f6d"
    ],
    "name:zho_x_variant":[
        "Shui-wa-t\u2019an"
    ],
    "wof:name":"Shuiwatan",
    "wof:placetype":"locality"
},
  "geometry": {"coordinates":[120.4075,22.83028],"type":"Point"}
}