{
  "type": "Feature",
  "properties": {
    "gn:admin1_code":"3.0",
    "gn:admin2_code":"TPQ",
    "gn:admin3_code":"F11",
    "gn:admin4_code":"65000290002.0",
    "gn:asciiname":"Zhongzhicun",
    "gn:country_code":"TW",
    "gn:dem":222,
    "gn:feature_class":"P",
    "gn:feature_code":"PPL",
    "gn:name":"Zhongzhicun",
    "gn:population":0,
    "gn:timezone":"Asia/Taipei",
    "iso:country":"TW",
    "name:und_x_variant":[
        "Jhongjhihcun",
        "Zhongzhicun"
    ],
    "name:zho_x_preferred":[
        "T\u2019ung-pi-she"
    ],
    "name:zho_x_variant":[
        "T\u2019ang-pi-ya",
        "T\u2019ang-pi-ya-she",
        "\u5fe0\u6cbb\u6751",
        "Chung-chih-ts\u2019un"
    ],
    "wof:name":"Zhongzhicun",
    "wof:placetype":"locality"
},
  "geometry": {"coordinates":[121.55379000000001,24.885],"type":"Point"}
}