{
  "type": "Feature",
  "properties": {
    "iso:country":"TW",
    "qs:name":"\u4e0a\u5fb7\u6751",
    "qs:name_adm0":"\u81fa\u7063",
    "qs:name_adm1":"\u65b0\u5317\u5e02",
    "qs:photos":5,
    "qs:photos_1k":1,
    "qs:photos_9k":1,
    "qs:photos_9r":1,
    "qs:photos_all":5,
    "qs:photos_sr":1,
    "qs:placetype":"Town",
    "qs:pop_sr":"0",
    "wof:name":"\u4e0a\u5fb7\u6751",
    "wof:placetype":"locality"
},
  "geometry": {"coordinates":[121.726799,24.964117],"type":"Point"}
}