{
  "type": "Feature",
  "properties": {
    "gn:admin1_code":"04",
    "gn:admin2_code":"NAN",
    "gn:admin3_code":"M10",
    "gn:admin4_code":"10008100004.0",
    "gn:asciiname":"Buwei",
    "gn:country_code":"TW",
    "gn:dem":329,
    "gn:feature_class":"P",
    "gn:feature_code":"PPL",
    "gn:name":"Buwei",
    "gn:population":0,
    "gn:timezone":"Asia/Taipei",
    "iso:country":"TW",
    "name:und_x_variant":[
        "Pu-wei"
    ],
    "name:zho_x_preferred":[
        "\u57d4\u5c3e"
    ],
    "wof:name":"Buwei",
    "wof:placetype":"locality"
},
  "geometry": {"coordinates":[120.88463,24.05714],"type":"Point"}
}