{
  "type": "Feature",
  "properties": {
    "gn:admin1_code":"04",
    "gn:admin2_code":"PIF",
    "gn:admin3_code":"T11",
    "gn:admin4_code":"10013110004.0",
    "gn:asciiname":"Shuiliu",
    "gn:country_code":"TW",
    "gn:dem":65,
    "gn:feature_class":"P",
    "gn:feature_code":"PPL",
    "gn:name":"Shuiliu",
    "gn:population":0,
    "gn:timezone":"Asia/Taipei",
    "iso:country":"TW",
    "name:und_x_variant":[
        "Shui-liu"
    ],
    "wof:name":"Shuiliu",
    "wof:placetype":"locality"
},
  "geometry": {"coordinates":[120.56667,22.83333],"type":"Point"}
}