{
  "type": "Feature",
  "properties": {
    "gn:admin1_code":"04",
    "gn:admin2_code":"NAN",
    "gn:admin3_code":"M10",
    "gn:admin4_code":"10008100010.0",
    "gn:asciiname":"Waipan'an",
    "gn:country_code":"TW",
    "gn:dem":338,
    "gn:feature_class":"P",
    "gn:feature_code":"PPL",
    "gn:name":"Waipan\u2019an",
    "gn:population":0,
    "gn:timezone":"Asia/Taipei",
    "iso:country":"TW",
    "name:zho_x_preferred":[
        "\u5916\u76e4\u5b89"
    ],
    "name:zho_x_variant":[
        "Waipan\u2019an",
        "Wai-p\u2019an-an"
    ],
    "wof:name":"Waipan'an",
    "wof:placetype":"locality"
},
  "geometry": {"coordinates":[120.89288999999999,23.9847],"type":"Point"}
}