{
  "type": "Feature",
  "properties": {
    "gn:admin1_code":"04",
    "gn:admin2_code":"ILA",
    "gn:admin3_code":"G11",
    "gn:admin4_code":"10002110009.0",
    "gn:asciiname":"Nanshan",
    "gn:country_code":"TW",
    "gn:dem":1148,
    "gn:feature_class":"P",
    "gn:feature_code":"PPL",
    "gn:name":"Nanshan",
    "gn:population":0,
    "gn:timezone":"Asia/Taipei",
    "iso:country":"TW",
    "name:cat_x_preferred":[
        "Nanshan"
    ],
    "name:ceb_x_preferred":[
        "Nanshan"
    ],
    "name:deu_x_preferred":[
        "Nanshan"
    ],
    "name:eus_x_preferred":[
        "Nanshan"
    ],
    "name:fra_x_preferred":[
        "Nanshan"
    ],
    "name:jpn_x_preferred":[
        "\u5357\u5c71\u533a"
    ],
    "name:kor_x_preferred":[
        "\ub09c\uc0b0\uad6c"
    ],
    "name:nld_x_preferred":[
        "Nanshan"
    ],
    "name:nor_x_preferred":[
        "Nanshan"
    ],
    "name:rus_x_preferred":[
        "\u041d\u0430\u043d\u044c\u0448\u0430\u043d\u044c"
    ],
    "name:swe_x_preferred":[
        "Nanshan"
    ],
    "name:und_x_variant":[
        "Nan-shan"
    ],
    "name:zho_x_preferred":[
        "P\u2019i-nan-she"
    ],
    "name:zho_x_variant":[
        "P\u2019i-ya-nan",
        "P\u2019i-ya-nan-she",
        "P\u2019i-tzu-nan",
        "P\u2019i-nan-ts\u2019un",
        "\u5357\u5c71",
        "P\u2019i-nan",
        "\u5357\u5c71\u533a"
    ],
    "wof:name":"Nanshan",
    "wof:placetype":"locality"
},
  "geometry": {"coordinates":[121.37972000000001,24.43833],"type":"Point"}
}