{
  "type": "Feature",
  "properties": {
    "gn:admin1_code":"04",
    "gn:admin2_code":"ILA",
    "gn:admin3_code":"G11",
    "gn:admin4_code":"10002110009.0",
    "gn:asciiname":"Nanshan",
    "gn:country_code":"TW",
    "gn:dem":1148,
    "gn:feature_class":"P",
    "gn:feature_code":"PPL",
    "gn:name":"Nanshan",
    "gn:population":0,
    "gn:timezone":"Asia/Taipei",
    "iso:country":"TW",
    "name:und_x_variant":[
        "Nan-shan"
    ],
    "name:zho_x_preferred":[
        "P\u2019i-nan-she"
    ],
    "name:zho_x_variant":[
        "P\u2019i-ya-nan",
        "P\u2019i-ya-nan-she",
        "P\u2019i-tzu-nan",
        "P\u2019i-nan-ts\u2019un",
        "\u5357\u5c71",
        "P\u2019i-nan"
    ],
    "wof:name":"Nanshan",
    "wof:placetype":"locality"
},
  "geometry": {"coordinates":[121.37972000000001,24.43833],"type":"Point"}
}