{
  "type": "Feature",
  "properties": {
    "gn:admin1_code":"3.0",
    "gn:admin2_code":"TPQ",
    "gn:admin3_code":"F09",
    "gn:admin4_code":"65000180007.0",
    "gn:asciiname":"Sifenli",
    "gn:country_code":"TW",
    "gn:dem":303,
    "gn:feature_class":"P",
    "gn:feature_code":"PPL",
    "gn:name":"Sifenli",
    "gn:population":0,
    "gn:timezone":"Asia/Taipei",
    "iso:country":"TW",
    "name:und_x_variant":[
        "Sihfenli",
        "Sifenli",
        "Ssu-fen-li"
    ],
    "name:zho_x_preferred":[
        "\u56db\u5206\u91cc"
    ],
    "wof:name":"Sifenli",
    "wof:placetype":"locality"
},
  "geometry": {"coordinates":[121.61547,25.01882],"type":"Point"}
}