{
  "type": "Feature",
  "properties": {
    "gn:admin1_code":"04",
    "gn:admin2_code":"PIF",
    "gn:admin3_code":"T05",
    "gn:admin4_code":"10013050026.0",
    "gn:asciiname":"Wanzinei",
    "gn:country_code":"TW",
    "gn:dem":12,
    "gn:feature_class":"P",
    "gn:feature_code":"PPL",
    "gn:name":"Wanzinei",
    "gn:population":0,
    "gn:timezone":"Asia/Taipei",
    "iso:country":"TW",
    "name:und_x_variant":[
        "Wan-tzu-nei",
        "Wanzinei",
        "Wanzihnei"
    ],
    "name:zho_x_preferred":[
        "\u7063\u5b50\u5185"
    ],
    "wof:name":"Wanzinei",
    "wof:placetype":"locality"
},
  "geometry": {"coordinates":[120.46460999999999,22.56697],"type":"Point"}
}